{
"type": "FeatureCollection",
"features": [
	{"geometry":{"coordinates":[81.075405,28.440155],"type":"Point"},"properties":{"man_made":"water_well","name":"Kadam","osm_id":"4409064478","tag":{"height":"30","leaf_cycle":"semi_evergreen","leaf_type":"leafless","natural":"tree"}},"type":"Feature"},
	{"geometry":{"coordinates":[81.073977,28.440835],"type":"Point"},"properties":{"name":"Pipal Tree","osm_id":"4409148061","tag":{"height":"6","leaf_cycle":"semi_evergreen","leaf_type":"leafless","natural":"tree"}},"type":"Feature"},
	{"geometry":{"coordinates":[81.07414,28.440881],"type":"Point"},"properties":{"osm_id":"4409156062","tag":{"natural":"tree"}},"type":"Feature"}
]
}
