{
"type": "FeatureCollection",
"features": [
	{"geometry":{"coordinates":[29.984389,64.75446],"type":"Point"},"properties":{"name":"Satalatva merkkipuu","osm_id":"8911296679","tag":{"natural":"tree","tourism":"attraction","website":"https://vienanreitti.fi/etusivu/nae-ja-koe/reitin-kohteet/satalatva/"}},"type":"Feature"}
]
}
