{
"type": "FeatureCollection",
"features": [
	{"geometry":{"coordinates":[-9.622187,51.900845],"type":"Point"},"properties":{"name":"Kenmare Waste Transfer Station","osm_id":"1573175996","tag":{"amenity":"recycling"}},"type":"Feature"}
]
}
