{
"type": "FeatureCollection",
"features": [
	{"geometry":{"coordinates":[17.347595,54.060471],"type":"Point"},"properties":{"name":"Lipa","osm_id":"2925170254","tag":{"natural":"tree"}},"type":"Feature"}
]
}
