{
"type": "FeatureCollection",
"features": [
	{"geometry":{"coordinates":[18.399962,52.615579],"type":"Point"},"properties":{"osm_id":"4706681571","tag":{"denotation":"natural_monument","natural":"tree","ref:CRFOP":"PL.ZIPOP.1393.PP.0407063.1015","ref:INSPIRE":"PL.ZIPOP.1393.PP.0407063.1015","website":"http://crfop.gdos.gov.pl/CRFOP/widok/viewfop.jsf?fop=PL.ZIPOP.1393.PP.0407063.1015"}},"type":"Feature"},
	{"geometry":{"coordinates":[18.379107,52.591852],"type":"Point"},"properties":{"osm_id":"4706681572","tag":{"denotation":"natural_monument","natural":"tree","ref:CRFOP":"PL.ZIPOP.1393.PP.0407063.1014","ref:INSPIRE":"PL.ZIPOP.1393.PP.0407063.1014","website":"http://crfop.gdos.gov.pl/CRFOP/widok/viewfop.jsf?fop=PL.ZIPOP.1393.PP.0407063.1014"}},"type":"Feature"}
]
}
