{
"type": "FeatureCollection",
"features": [
	{"geometry":{"coordinates":[135.799739,34.500279],"type":"Point"},"properties":{"name":"\u00e3\u0083\u00aa\u00e3\u0082\u00b5\u00e3\u0082\u00a4\u00e3\u0082\u00af\u00e3\u0083\u00ab\u00e3\u0082\u00a2\u00e3\u0082\u00a4","osm_id":"892728724","tag":{"amenity":"recycling","name:en":"Recycle Eye","recycling:batteries":"yes","recycling:scrap_metal":"yes"}},"type":"Feature"}
]
}
