{
"type": "FeatureCollection",
"features": [
	{"geometry":{"coordinates":[1.496584,45.830727],"type":"Point"},"properties":{"name":"Eco-point","osm_id":"9023454926","tag":{"amenity":"recycling","opening_hours":"24/7","operator":"SYDED de la Haute-Vienne","recycling:cans":"yes","recycling:glass_bottles":"yes","recycling:paper":"yes","recycling:plastic":"yes","recycling:plastic_bottles":"yes","recycling:plastic_packaging":"yes","recycling_type":"container"}},"type":"Feature"}
]
}
