{
"type": "FeatureCollection",
"features": [
	{"geometry":{"coordinates":[1.49898,45.612144],"type":"Point"},"properties":{"name":"Eco-point","osm_id":"2624824996","tag":{"amenity":"recycling","recycling_type":"container"}},"type":"Feature"}
]
}
