{
"type": "FeatureCollection",
"features": [
	{"geometry":{"coordinates":[1.527262,43.478947],"type":"Point"},"properties":{"osm_id":"935433301","tag":{"amenity":"recycling"}},"type":"Feature"},
	{"geometry":{"coordinates":[1.52213,43.457057],"type":"Point"},"properties":{"osm_id":"936769647","tag":{"amenity":"recycling"}},"type":"Feature"},
	{"geometry":{"coordinates":[1.506194,43.509389],"type":"Point"},"properties":{"osm_id":"2043479984","tag":{"addr:housenumber":"7"}},"type":"Feature"},
	{"geometry":{"coordinates":[1.512774,43.489428],"type":"Point"},"properties":{"osm_id":"2616079049","tag":{"amenity":"recycling","recycling:clothes":"no","recycling:glass":"yes","recycling:paper":"no"}},"type":"Feature"},
	{"geometry":{"coordinates":[1.513955,43.489656],"type":"Point"},"properties":{"osm_id":"3974560827","tag":{"amenity":"recycling","operator":"Sicoval","recycling:glass_bottles":"yes","recycling_type":"container"}},"type":"Feature"},
	{"geometry":{"coordinates":[1.53407,43.495502],"type":"Point"},"properties":{"osm_id":"4017932211","tag":{"amenity":"waste_basket"}},"type":"Feature"},
	{"geometry":{"coordinates":[1.534503,43.495646],"type":"Point"},"properties":{"osm_id":"4017932218","tag":{"amenity":"waste_basket"}},"type":"Feature"},
	{"geometry":{"coordinates":[1.534888,43.495749],"type":"Point"},"properties":{"osm_id":"4017932224","tag":{"amenity":"waste_basket"}},"type":"Feature"},
	{"geometry":{"coordinates":[1.534118,43.495817],"type":"Point"},"properties":{"osm_id":"4017932232","tag":{"amenity":"waste_basket"}},"type":"Feature"},
	{"geometry":{"coordinates":[1.534305,43.496087],"type":"Point"},"properties":{"osm_id":"4017932250","tag":{"amenity":"waste_basket"}},"type":"Feature"},
	{"geometry":{"coordinates":[1.570872,43.488708],"type":"Point"},"properties":{"osm_id":"5022997048","tag":{"amenity":"recycling","recycling:glass_bottles":"yes","recycling_type":"container"}},"type":"Feature"},
	{"geometry":{"coordinates":[1.553378,43.478065],"type":"Point"},"properties":{"osm_id":"5022998816","tag":{"amenity":"recycling","recycling:glass_bottles":"yes","recycling_type":"container"}},"type":"Feature"},
	{"geometry":{"coordinates":[1.501185,43.51508],"type":"Point"},"properties":{"osm_id":"5863925859","tag":{"amenity":"recycling","recycling:glass_bottles":"yes","recycling_type":"container"}},"type":"Feature"},
	{"geometry":{"coordinates":[1.511459,43.514516],"type":"Point"},"properties":{"osm_id":"5863925860","tag":{"amenity":"recycling","recycling:glass_bottles":"yes","recycling_type":"container"}},"type":"Feature"},
	{"geometry":{"coordinates":[1.50257,43.514415],"type":"Point"},"properties":{"osm_id":"7087828185","tag":{"amenity":"recycling","recycling:clothes":"yes","recycling:glass_bottles":"yes","recycling_type":"container"}},"type":"Feature"},
	{"geometry":{"coordinates":[1.504747,43.513019],"type":"Point"},"properties":{"osm_id":"7087828885","tag":{"amenity":"recycling","recycling:clothes":"yes","recycling:glass_bottles":"yes","recycling_type":"container"}},"type":"Feature"},
	{"geometry":{"coordinates":[1.563596,43.488674],"type":"Point"},"properties":{"osm_id":"7603119121","tag":{"amenity":"recycling","recycling:glass_bottles":"yes","recycling_type":"container"}},"type":"Feature"}
]
}
