{
"type": "FeatureCollection",
"features": [
	{"geometry":{"coordinates":[8.473868,49.90338],"type":"Point"},"properties":{"osm_id":"625269013","tag":{"amenity":"recycling","recycling:glass_bottles":"yes"}},"type":"Feature"},
	{"geometry":{"coordinates":[8.481423,49.899405],"type":"Point"},"properties":{"osm_id":"1296605604","tag":{"amenity":"waste_basket"}},"type":"Feature"},
	{"geometry":{"coordinates":[8.497546,49.934052],"type":"Point"},"properties":{"osm_id":"1668895805","tag":{"amenity":"recycling","recycling:glass_bottles":"yes","recycling_type":"container"}},"type":"Feature"},
	{"geometry":{"coordinates":[8.448644,49.902247],"type":"Point"},"properties":{"osm_id":"3594314135","tag":{"amenity":"recycling","recycling:clothes":"yes","recycling:glass_bottles":"yes","recycling_type":"container"}},"type":"Feature"},
	{"geometry":{"coordinates":[8.450277,49.941612],"type":"Point"},"properties":{"osm_id":"4102995730","tag":{"amenity":"waste_basket"}},"type":"Feature"},
	{"geometry":{"coordinates":[8.494534,49.931749],"type":"Point"},"properties":{"name":"Altglas","osm_id":"4582811790","tag":{"amenity":"recycling","name:de":"Altglas"}},"type":"Feature"},
	{"geometry":{"coordinates":[8.505727,49.937681],"type":"Point"},"properties":{"osm_id":"5015488852","tag":{"amenity":"waste_basket"}},"type":"Feature"},
	{"geometry":{"coordinates":[8.481625,49.921371],"type":"Point"},"properties":{"osm_id":"7850424858","tag":{"amenity":"waste_basket"}},"type":"Feature"}
]
}
