{
"type": "FeatureCollection",
"features": [
	{"geometry":{"coordinates":[8.493284,49.855275],"type":"Point"},"properties":{"osm_id":"57837237","tag":{"amenity":"recycling","recycling:cans":"no","recycling:clothes":"no","recycling:glass":"yes","recycling:paper":"no"}},"type":"Feature"},
	{"geometry":{"coordinates":[8.484247,49.873342],"type":"Point"},"properties":{"osm_id":"667564867","tag":{"amenity":"recycling","recycling:glass":"yes","recycling:glass_bottles":"yes","recycling_type":"container"}},"type":"Feature"},
	{"geometry":{"coordinates":[8.439537,49.856175],"type":"Point"},"properties":{"osm_id":"686818692","tag":{"amenity":"recycling","recycling:cans":"no","recycling:clothes":"no","recycling:glass":"yes","recycling:glass_bottles":"yes","recycling:paper":"no","recycling:plastic":"no","recycling_type":"container"}},"type":"Feature"},
	{"geometry":{"coordinates":[8.503147,49.852548],"type":"Point"},"properties":{"osm_id":"1097264083","tag":{"amenity":"recycling","recycling:glass_bottles":"yes"}},"type":"Feature"},
	{"geometry":{"coordinates":[8.438247,49.858167],"type":"Point"},"properties":{"osm_id":"1613001838","tag":{"amenity":"recycling","recycling_type":"container"}},"type":"Feature"},
	{"geometry":{"coordinates":[8.493191,49.877687],"type":"Point"},"properties":{"osm_id":"1668670637","tag":{"amenity":"recycling"}},"type":"Feature"},
	{"geometry":{"coordinates":[8.489638,49.88212],"type":"Point"},"properties":{"osm_id":"1668671158","tag":{"amenity":"recycling","recycling:clothes":"yes","recycling:glass":"yes","recycling:glass_bottles":"yes","recycling_type":"container"}},"type":"Feature"},
	{"geometry":{"coordinates":[8.458668,49.838783],"type":"Point"},"properties":{"osm_id":"2017404170","tag":{"amenity":"recycling","recycling:glass_bottles":"yes","recycling_type":"container"}},"type":"Feature"},
	{"geometry":{"coordinates":[8.485789,49.855984],"type":"Point"},"properties":{"osm_id":"2020421987","tag":{"amenity":"recycling","recycling:clothes":"yes","recycling:glass":"yes","recycling:glass_bottles":"yes","recycling_type":"container"}},"type":"Feature"},
	{"geometry":{"coordinates":[8.484215,49.877576],"type":"Point"},"properties":{"name":"Bauhof","osm_id":"2591376592","tag":{"amenity":"waste_disposal"}},"type":"Feature"},
	{"geometry":{"coordinates":[8.470042,49.839024],"type":"Point"},"properties":{"osm_id":"2651915468","tag":{"amenity":"recycling","recycling:glass_bottles":"yes","recycling_type":"container"}},"type":"Feature"},
	{"geometry":{"coordinates":[8.498693,49.846049],"type":"Point"},"properties":{"osm_id":"2817629254","tag":{"amenity":"waste_basket"}},"type":"Feature"},
	{"geometry":{"coordinates":[8.497875,49.856101],"type":"Point"},"properties":{"osm_id":"2987682167","tag":{"amenity":"recycling","recycling:cans":"no","recycling:clothes":"no","recycling:glass":"yes","recycling:paper":"no"}},"type":"Feature"},
	{"geometry":{"coordinates":[8.440377,49.854182],"type":"Point"},"properties":{"osm_id":"4185825108","tag":{"amenity":"waste_basket"}},"type":"Feature"},
	{"geometry":{"coordinates":[8.494436,49.853913],"type":"Point"},"properties":{"osm_id":"4755046882","tag":{"amenity":"waste_basket"}},"type":"Feature"},
	{"geometry":{"coordinates":[8.467018,49.85151],"type":"Point"},"properties":{"osm_id":"4771010641","tag":{"amenity":"waste_basket"}},"type":"Feature"},
	{"geometry":{"coordinates":[8.443787,49.854089],"type":"Point"},"properties":{"osm_id":"4776548222","tag":{"amenity":"recycling","recycling:cans":"no","recycling:clothes":"no","recycling:glass":"yes","recycling:glass_bottles":"yes","recycling:paper":"no","recycling:plastic":"no","recycling_type":"container"}},"type":"Feature"}
]
}
