{
"type": "FeatureCollection",
"features": [
	{"geometry":{"coordinates":[-1.220663,52.29026],"type":"Point"},"properties":{"osm_id":"522902116","tag":{"amenity":"recycling","recycling:cans":"yes","recycling:glass":"yes","recycling:paper":"yes"}},"type":"Feature"},
	{"geometry":{"coordinates":[-1.220688,52.29029],"type":"Point"},"properties":{"name":"Braunston North Rubbish Disposal","osm_id":"522902120","tag":{"access":"permissive","amenity":"waste_disposal","centralkey":"no","operator":"Canal and River Trust","waste":"trash","waterway":"waste_disposal"}},"type":"Feature"}
]
}
