{
"type": "FeatureCollection",
"features": [
	{"geometry":{"coordinates":[-7.520625,41.462486],"type":"Point"},"properties":{"name":"Castanheiro de Vales","osm_id":"4519477729","tag":{"natural":"tree"}},"type":"Feature"},
	{"geometry":{"coordinates":[-7.51075,41.477939],"type":"Point"},"properties":{"osm_id":"6538850312","tag":{"natural":"tree"}},"type":"Feature"},
	{"geometry":{"coordinates":[-7.510608,41.477907],"type":"Point"},"properties":{"osm_id":"6538850313","tag":{"natural":"tree"}},"type":"Feature"}
]
}
