{
"type": "FeatureCollection",
"features": [
	{"geometry":{"coordinates":[-116.717819,33.724861],"type":"Point"},"properties":{"name":"Green Waste","osm_id":"3764334249","tag":{"amenity":"recycling","recycling:cans":"no","recycling:clothes":"no","recycling:glass":"no","recycling:glass_bottles":"no","recycling:green_waste":"yes","recycling:paper":"no","recycling:plastic":"no"}},"type":"Feature"},
	{"geometry":{"coordinates":[-116.713126,33.748426],"type":"Point"},"properties":{"osm_id":"3797116609","tag":{"amenity":"recycling","operator":"Idyllwild Bible Church","recycling:cans":"yes","recycling:clothes":"no","recycling:glass":"no","recycling:glass_bottles":"no","recycling:paper":"no","recycling:plastic":"yes","recycling_type":"container"}},"type":"Feature"},
	{"geometry":{"coordinates":[-116.713463,33.748448],"type":"Point"},"properties":{"osm_id":"4689500349","tag":{"access":"private","amenity":"waste_disposal"}},"type":"Feature"}
]
}
