{
"type": "FeatureCollection",
"features": [
	{"geometry":{"coordinates":[-128.694056,54.058691],"type":"Point"},"properties":{"name":"KUTE","osm_id":"5199183523","tag":{"amenity":"recycling"}},"type":"Feature"},
	{"geometry":{"coordinates":[-128.694065,54.058682],"type":"Point"},"properties":{"name":"kitimat recycling depot","osm_id":"5199190821","tag":{"amenity":"recycling"}},"type":"Feature"}
]
}
