{
"type": "FeatureCollection",
"lastupdate": "2020-07-31T00:00:00Z",
"features": [
	{"geometry":{"coordinates":[-128.694055,54.05869],"type":"Point"},"properties":{"name":"KUTE","osm_id":"5199183523","tag":{"amenity":"recycling"}},"type":"Feature"},
	{"geometry":{"coordinates":[-128.694065,54.058681],"type":"Point"},"properties":{"name":"kitimat recycling depot","osm_id":"5199190821","tag":{"amenity":"recycling"}},"type":"Feature"}
]
}
