{
"type": "FeatureCollection",
"features": [
	{"geometry":{"coordinates":[8.755749,51.220337],"type":"Point"},"properties":{"osm_id":"1392812575","tag":{"amenity":"recycling","location":"overground","recycling:clothes":"yes","recycling:glass":"yes","recycling_type":"container"}},"type":"Feature"}
]
}
