{
"type": "FeatureCollection",
"lastupdate": "2020-08-02T00:00:00Z",
"features": [
	{"geometry":{"coordinates":[8.755748,51.220337],"type":"Point"},"properties":{"osm_id":"1392812575","tag":{"amenity":"recycling","location":"overground","recycling:clothes":"yes","recycling:glass":"yes","recycling_type":"container"}},"type":"Feature"}
]
}
