{
"type": "FeatureCollection",
"features": [
	{"geometry":{"coordinates":[8.785565,47.032499],"type":"Point"},"properties":{"osm_id":"560902605","tag":{"amenity":"waste_basket","bicycle":"yes","hiking":"yes","information":"guidepost","tourism":"information"}},"type":"Feature"},
	{"geometry":{"coordinates":[8.7866,47.036128],"type":"Point"},"properties":{"name":"Robidog","osm_id":"1277456123","tag":{"amenity":"waste_basket","vending":"excrement_bags"}},"type":"Feature"},
	{"geometry":{"coordinates":[8.78266,47.039064],"type":"Point"},"properties":{"osm_id":"6387576734","tag":{"amenity":"waste_basket","vending":"excrement_bags"}},"type":"Feature"}
]
}
