{
"type": "FeatureCollection",
"lastupdate": "2020-08-01T00:00:00Z",
"features": [
	{"geometry":{"coordinates":[8.785564,47.032498],"type":"Point"},"properties":{"osm_id":"560902605","tag":{"amenity":"waste_basket","bicycle":"yes","hiking":"yes","information":"guidepost","tourism":"information"}},"type":"Feature"},
	{"geometry":{"coordinates":[8.786599,47.036128],"type":"Point"},"properties":{"name":"Robidog","osm_id":"1277456123","tag":{"amenity":"waste_basket","vending":"excrement_bags"}},"type":"Feature"},
	{"geometry":{"coordinates":[8.78266,47.039063],"type":"Point"},"properties":{"osm_id":"6387576734","tag":{"amenity":"waste_basket","vending":"excrement_bags"}},"type":"Feature"}
]
}
