{
"type": "FeatureCollection",
"features": [
	{"geometry":{"coordinates":[-72.175812,19.392917],"type":"Point"},"properties":{"name":"nymes","osm_id":"1229710689","tag":{"name:botanical":"nymes","natural":"tree"}},"type":"Feature"}
]
}
