{
"type": "FeatureCollection",
"features": [
	{"geometry":{"coordinates":[11.196277,49.925061],"type":"Point"},"properties":{"name":"ND Vier Linden","osm_id":"2687390039","tag":{"denotation":"natural_monument","genus:de":"Linde","leaf_type":"broadleaved","natural":"tree"}},"type":"Feature"},
	{"geometry":{"coordinates":[11.238273,49.913344],"type":"Point"},"properties":{"osm_id":"5806716757","tag":{"natural":"tree"}},"type":"Feature"},
	{"geometry":{"coordinates":[11.238233,49.913302],"type":"Point"},"properties":{"osm_id":"5806716758","tag":{"natural":"tree"}},"type":"Feature"}
]
}
