{
"type": "FeatureCollection",
"features": [
	{"geometry":{"coordinates":[11.164408,43.391456],"type":"Point"},"properties":{"name":"Ciliegio","osm_id":"5643601068","tag":{"natural":"tree"}},"type":"Feature"},
	{"geometry":{"coordinates":[11.21065,43.405424],"type":"Point"},"properties":{"osm_id":"8932758358","tag":{"natural":"tree"}},"type":"Feature"},
	{"geometry":{"coordinates":[11.210655,43.405462],"type":"Point"},"properties":{"osm_id":"8932758359","tag":{"natural":"tree"}},"type":"Feature"},
	{"geometry":{"coordinates":[11.211177,43.405551],"type":"Point"},"properties":{"osm_id":"8932758370","tag":{"natural":"tree"}},"type":"Feature"},
	{"geometry":{"coordinates":[11.211099,43.405512],"type":"Point"},"properties":{"osm_id":"8932758371","tag":{"natural":"tree"}},"type":"Feature"},
	{"geometry":{"coordinates":[11.21103,43.405479],"type":"Point"},"properties":{"osm_id":"8932758372","tag":{"natural":"tree"}},"type":"Feature"},
	{"geometry":{"coordinates":[11.210965,43.405446],"type":"Point"},"properties":{"osm_id":"8932758373","tag":{"natural":"tree"}},"type":"Feature"},
	{"geometry":{"coordinates":[11.210892,43.405409],"type":"Point"},"properties":{"osm_id":"8932758374","tag":{"natural":"tree"}},"type":"Feature"},
	{"geometry":{"coordinates":[11.210816,43.405375],"type":"Point"},"properties":{"osm_id":"8932758375","tag":{"natural":"tree"}},"type":"Feature"},
	{"geometry":{"coordinates":[11.211117,43.405708],"type":"Point"},"properties":{"osm_id":"8932758376","tag":{"natural":"tree"}},"type":"Feature"},
	{"geometry":{"coordinates":[11.21104,43.40568],"type":"Point"},"properties":{"osm_id":"8932758377","tag":{"natural":"tree"}},"type":"Feature"},
	{"geometry":{"coordinates":[11.210944,43.405646],"type":"Point"},"properties":{"osm_id":"8932758378","tag":{"natural":"tree"}},"type":"Feature"},
	{"geometry":{"coordinates":[11.210856,43.405621],"type":"Point"},"properties":{"osm_id":"8932758379","tag":{"natural":"tree"}},"type":"Feature"},
	{"geometry":{"coordinates":[11.210784,43.405592],"type":"Point"},"properties":{"osm_id":"8932758380","tag":{"natural":"tree"}},"type":"Feature"},
	{"geometry":{"coordinates":[11.210712,43.405549],"type":"Point"},"properties":{"osm_id":"8932758381","tag":{"natural":"tree"}},"type":"Feature"},
	{"geometry":{"coordinates":[11.210666,43.405498],"type":"Point"},"properties":{"osm_id":"8932758382","tag":{"natural":"tree"}},"type":"Feature"},
	{"geometry":{"coordinates":[11.210705,43.406827],"type":"Point"},"properties":{"osm_id":"9075941216","tag":{"natural":"tree"}},"type":"Feature"},
	{"geometry":{"coordinates":[11.210675,43.406915],"type":"Point"},"properties":{"osm_id":"9075941217","tag":{"natural":"tree"}},"type":"Feature"}
]
}
