{
"type": "FeatureCollection",
"features": [
	{"geometry":{"coordinates":[11.164408,43.391456],"type":"Point"},"properties":{"name":"Ciliegio","osm_id":"5643601068","tag":{"natural":"tree"}},"type":"Feature"}
]
}
