{
"type": "FeatureCollection",
"features": [
	{"geometry":{"coordinates":[11.20653,47.100116],"type":"Point"},"properties":{"name":"Weiderost","osm_id":"9091845361","tag":{"amenity":"waste_basket"}},"type":"Feature"},
	{"geometry":{"coordinates":[11.209111,47.100499],"type":"Point"},"properties":{"name":"Weiderost","osm_id":"9091880092","tag":{"amenity":"waste_basket"}},"type":"Feature"},
	{"geometry":{"coordinates":[11.223673,47.109056],"type":"Point"},"properties":{"name":"Weiderost","osm_id":"9091956767","tag":{"amenity":"waste_basket"}},"type":"Feature"},
	{"geometry":{"coordinates":[11.241571,47.115849],"type":"Point"},"properties":{"name":"Weiderost","osm_id":"9091974143","tag":{"amenity":"waste_basket"}},"type":"Feature"},
	{"geometry":{"coordinates":[11.218775,47.107166],"type":"Point"},"properties":{"name":"Weiderost","osm_id":"9091981041","tag":{"amenity":"waste_basket"}},"type":"Feature"}
]
}
