{
"type": "FeatureCollection",
"lastupdate": "2020-08-01T00:00:00Z",
"features": [
	{"geometry":{"coordinates":[11.179447,43.643909],"type":"Point"},"properties":{"name":"Centro recupero di Canciulle","osm_id":"1208654669","tag":{"amenity":"recycling"}},"type":"Feature"}
]
}
