{
"type": "FeatureCollection",
"features": [
	{"geometry":{"coordinates":[11.179448,43.643909],"type":"Point"},"properties":{"name":"Centro recupero di Canciulle","osm_id":"1208654669","tag":{"amenity":"recycling"}},"type":"Feature"}
]
}
