{
"type": "FeatureCollection",
"features": [
	{"geometry":{"coordinates":[11.179447,43.643909],"type":"Point"},"properties":{"name":"Centro recupero di Canciulle","osm_id":"1208654669","tag":{"amenity":"recycling","recycling_type":"centre"}},"type":"Feature"}
]
}
