{
"type": "FeatureCollection",
"features": [
	{"geometry":{"coordinates":[-6.533991,53.33029],"type":"Point"},"properties":{"barrier":"fence","name":"Wheelie Bin Shed","osm_id":"8050297407","tag":{"amenity":"waste_disposal","fence_type":"wood"}},"type":"Feature"},
	{"geometry":{"coordinates":[-6.546389,53.325092],"type":"Point"},"properties":{"osm_id":"8409201746","tag":{"amenity":"waste_disposal","building":"shed"}},"type":"Feature"},
	{"geometry":{"coordinates":[-6.545874,53.325506],"type":"Point"},"properties":{"osm_id":"8409201757","tag":{"amenity":"waste_disposal","building":"shed"}},"type":"Feature"}
]
}
