{
"type": "FeatureCollection",
"features": [
	{"geometry":{"coordinates":[-88.513171,42.814188],"type":"Point"},"properties":{"name":"Mulberry tree","osm_id":"3626037722","tag":{"leaf_cycle":"deciduous","natural":"tree"}},"type":"Feature"}
]
}
