{
"type": "FeatureCollection",
"lastupdate": "2020-08-02T00:00:00Z",
"features": [
	{"geometry":{"coordinates":[18.8465,50.457782],"type":"Point"},"properties":{"name":"Olmet","osm_id":"5565919289","tag":{"addr:housenumber":"15","addr:street":"Towarowa","amenity":"recycling","fax":"+48 32 768 32 14","opening_hours":"Mo-Sa 07:00-17:00","phone":"+48 32 768 32 13","website":"http://olmet.pl"}},"type":"Feature"}
]
}
