{
"type": "FeatureCollection",
"lastupdate": "2020-08-02T00:00:00Z",
"features": [
	{"geometry":{"coordinates":[-103.255237,20.533213],"type":"Point"},"properties":{"name":"Fapsa El Salto","osm_id":"4278386799","tag":{"amenity":"recycling"}},"type":"Feature"}
]
}
