{
"type": "FeatureCollection",
"features": [
	{"geometry":{"coordinates":[-103.255238,20.533213],"type":"Point"},"properties":{"name":"Fapsa El Salto","osm_id":"4278386799","tag":{"amenity":"recycling"}},"type":"Feature"}
]
}
