{
"type": "FeatureCollection",
"lastupdate": "2020-08-06T00:00:00Z",
"features": [
	{"geometry":{"coordinates":[9.708111,59.121276],"type":"Point"},"properties":{"osm_id":"1463017469","tag":{"amenity":"recycling","description":"Telemarksporten","recycling:glass_bottles":"yes","recycling_type":"container","ref:sortere":"18317"}},"type":"Feature"},
	{"geometry":{"coordinates":[9.668122,59.109879],"type":"Point"},"properties":{"osm_id":"5555197441","tag":{"amenity":"recycling","description":"Stridsklevsenteret","recycling:glass_bottles":"yes","recycling_type":"container","ref:sortere":"18322"}},"type":"Feature"},
	{"geometry":{"coordinates":[9.685657,59.095875],"type":"Point"},"properties":{"osm_id":"5555197445","tag":{"amenity":"recycling","description":"Vi-To Senteret","recycling:glass_bottles":"yes","recycling_type":"container","ref:sortere":"18318"}},"type":"Feature"},
	{"geometry":{"coordinates":[9.687325,59.08724],"type":"Point"},"properties":{"osm_id":"5555197448","tag":{"amenity":"recycling","description":"L\u00f8vsj\u00f8toppen v/butikken","recycling:glass_bottles":"yes","recycling_type":"container","ref:sortere":"18312"}},"type":"Feature"},
	{"geometry":{"coordinates":[9.684014,59.106564],"type":"Point"},"properties":{"osm_id":"5555197449","tag":{"amenity":"recycling","description":"Hovet v/butikken","recycling:glass_bottles":"yes","recycling_type":"container","ref:sortere":"18310"}},"type":"Feature"},
	{"geometry":{"coordinates":[9.681858,59.117587],"type":"Point"},"properties":{"name":"Pasadalen gjenvinningsstasjon","osm_id":"5555203239","tag":{"amenity":"recycling","phone":"+47 48259337","recycling:batteries":"yes","recycling:clothes":"yes","recycling:electrical_items":"yes","recycling:garden_waste":"yes","recycling:glass_bottles":"yes","recycling:hazardous_waste":"yes","recycling:metal":"yes","recycling:paper":"yes","recycling:rubble":"yes","recycling:tyres":"yes","recycling:waste":"yes","recycling:wood":"yes","recycling_type":"centre","ref:sortere":"1329","website":"https://rig.no/gjenvinningstasjoner/pasadalen-porsgrunn"}},"type":"Feature"}
]
}
