{
"type": "FeatureCollection",
"features": [
	{"geometry":{"coordinates":[9.701022,50.490522],"type":"Point"},"properties":{"name":"Wertstoffhof","osm_id":"442018146","tag":{"amenity":"recycling"}},"type":"Feature"},
	{"geometry":{"coordinates":[9.677195,50.498565],"type":"Point"},"properties":{"osm_id":"705591622","tag":{"amenity":"recycling","recycling:clothes":"yes","recycling:glass":"yes"}},"type":"Feature"},
	{"geometry":{"coordinates":[9.708325,50.504581],"type":"Point"},"properties":{"osm_id":"2451000279","tag":{"amenity":"waste_basket"}},"type":"Feature"},
	{"geometry":{"coordinates":[9.705563,50.5051],"type":"Point"},"properties":{"osm_id":"2451000283","tag":{"amenity":"waste_basket"}},"type":"Feature"},
	{"geometry":{"coordinates":[9.7045,50.506104],"type":"Point"},"properties":{"osm_id":"2451000293","tag":{"amenity":"waste_basket"}},"type":"Feature"},
	{"geometry":{"coordinates":[9.710776,50.506363],"type":"Point"},"properties":{"osm_id":"2451000295","tag":{"amenity":"waste_basket"}},"type":"Feature"},
	{"geometry":{"coordinates":[9.721478,50.48061],"type":"Point"},"properties":{"osm_id":"3688321051","tag":{"amenity":"recycling","recycling_type":"container"}},"type":"Feature"}
]
}
