{
"type": "FeatureCollection",
"features": [
	{"geometry":{"coordinates":[9.701021,50.490522],"type":"Point"},"properties":{"name":"Wertstoffhof","osm_id":"442018146","tag":{"amenity":"recycling"}},"type":"Feature"},
	{"geometry":{"coordinates":[9.677195,50.498564],"type":"Point"},"properties":{"osm_id":"705591622","tag":{"amenity":"recycling","recycling:clothes":"yes","recycling:glass":"yes"}},"type":"Feature"},
	{"geometry":{"coordinates":[9.708324,50.504581],"type":"Point"},"properties":{"osm_id":"2451000279","tag":{"amenity":"waste_basket"}},"type":"Feature"},
	{"geometry":{"coordinates":[9.705563,50.505099],"type":"Point"},"properties":{"osm_id":"2451000283","tag":{"amenity":"waste_basket"}},"type":"Feature"},
	{"geometry":{"coordinates":[9.7045,50.506103],"type":"Point"},"properties":{"osm_id":"2451000293","tag":{"amenity":"waste_basket"}},"type":"Feature"},
	{"geometry":{"coordinates":[9.710776,50.506362],"type":"Point"},"properties":{"osm_id":"2451000295","tag":{"amenity":"waste_basket"}},"type":"Feature"},
	{"geometry":{"coordinates":[9.721478,50.48061],"type":"Point"},"properties":{"osm_id":"3688321051","tag":{"amenity":"recycling","recycling_type":"container"}},"type":"Feature"},
	{"geometry":{"coordinates":[9.71036,50.510809],"type":"Point"},"properties":{"osm_id":"8569634614","tag":{"amenity":"waste_basket","colour":"green","material":"plastic"}},"type":"Feature"},
	{"geometry":{"coordinates":[9.729398,50.499569],"type":"Point"},"properties":{"osm_id":"8569795780","tag":{"amenity":"waste_basket","colour":"blue","material":"metal"}},"type":"Feature"},
	{"geometry":{"coordinates":[9.699657,50.467841],"type":"Point"},"properties":{"osm_id":"8808790611","tag":{"amenity":"recycling","recycling:clothes":"yes","recycling:glass_bottles":"yes","recycling:shoes":"yes","recycling_type":"container"}},"type":"Feature"},
	{"geometry":{"coordinates":[9.700712,50.467796],"type":"Point"},"properties":{"osm_id":"8808821101","tag":{"amenity":"waste_basket"}},"type":"Feature"}
]
}
