{
"type": "FeatureCollection",
"features": [
	{"geometry":{"coordinates":[9.681819,46.78291],"type":"Point"},"properties":{"osm_id":"5196089637","tag":{"amenity":"waste_basket"}},"type":"Feature"},
	{"geometry":{"coordinates":[9.682041,46.782868],"type":"Point"},"properties":{"osm_id":"5196089638","tag":{"amenity":"waste_basket"}},"type":"Feature"},
	{"geometry":{"coordinates":[9.682225,46.782986],"type":"Point"},"properties":{"osm_id":"5196089640","tag":{"amenity":"waste_basket"}},"type":"Feature"},
	{"geometry":{"coordinates":[9.682031,46.782766],"type":"Point"},"properties":{"osm_id":"5196092943","tag":{"amenity":"waste_basket"}},"type":"Feature"},
	{"geometry":{"coordinates":[9.680747,46.782798],"type":"Point"},"properties":{"osm_id":"5196109779","tag":{"amenity":"waste_basket"}},"type":"Feature"},
	{"geometry":{"coordinates":[9.680618,46.782668],"type":"Point"},"properties":{"osm_id":"5196109781","tag":{"amenity":"waste_basket"}},"type":"Feature"},
	{"geometry":{"coordinates":[9.67978,46.783022],"type":"Point"},"properties":{"osm_id":"5196123972","tag":{"amenity":"waste_basket"}},"type":"Feature"},
	{"geometry":{"coordinates":[9.680074,46.782845],"type":"Point"},"properties":{"osm_id":"5196123973","tag":{"amenity":"waste_basket"}},"type":"Feature"},
	{"geometry":{"coordinates":[9.679901,46.78294],"type":"Point"},"properties":{"osm_id":"5196123974","tag":{"amenity":"waste_basket"}},"type":"Feature"},
	{"geometry":{"coordinates":[9.678784,46.783829],"type":"Point"},"properties":{"osm_id":"5413049782","tag":{"amenity":"recycling","recycling:glass":"yes","recycling_type":"container"}},"type":"Feature"},
	{"geometry":{"coordinates":[9.686206,46.782444],"type":"Point"},"properties":{"osm_id":"5413059536","tag":{"amenity":"recycling","recycling:glass":"yes","recycling_type":"container"}},"type":"Feature"},
	{"geometry":{"coordinates":[9.687521,46.782672],"type":"Point"},"properties":{"osm_id":"5413059592","tag":{"amenity":"recycling","recycling:glass":"yes","recycling_type":"container"}},"type":"Feature"},
	{"geometry":{"coordinates":[9.680262,46.780967],"type":"Point"},"properties":{"osm_id":"5414015677","tag":{"amenity":"recycling","recycling:glass":"yes","recycling_type":"container"}},"type":"Feature"},
	{"geometry":{"coordinates":[9.678605,46.780313],"type":"Point"},"properties":{"osm_id":"5414467836","tag":{"amenity":"recycling","recycling:glass":"yes","recycling_type":"container"}},"type":"Feature"},
	{"geometry":{"coordinates":[9.677793,46.779717],"type":"Point"},"properties":{"osm_id":"5414472672","tag":{"amenity":"recycling","recycling:glass":"yes","recycling_type":"container"}},"type":"Feature"},
	{"geometry":{"coordinates":[9.687635,46.782946],"type":"Point"},"properties":{"osm_id":"5418315237","tag":{"amenity":"recycling","recycling:clothes":"yes","recycling_type":"container"}},"type":"Feature"},
	{"geometry":{"coordinates":[9.682926,46.780939],"type":"Point"},"properties":{"osm_id":"6010748792","tag":{"amenity":"recycling","recycling:glass":"yes","recycling_type":"underfloor-container"}},"type":"Feature"},
	{"geometry":{"coordinates":[9.687591,46.782581],"type":"Point"},"properties":{"name":"Multisammelstelle","osm_id":"6010768325","tag":{"amenity":"recycling","operator":"Gemeinde Arosa","recycling_type":"centre"}},"type":"Feature"}
]
}
