{
"type": "FeatureCollection",
"features": [
	{"geometry":{"coordinates":[9.681818,46.78291],"type":"Point"},"properties":{"osm_id":"5196089637","tag":{"amenity":"waste_basket"}},"type":"Feature"},
	{"geometry":{"coordinates":[9.682224,46.782986],"type":"Point"},"properties":{"osm_id":"5196089640","tag":{"amenity":"waste_basket"}},"type":"Feature"},
	{"geometry":{"coordinates":[9.680747,46.782797],"type":"Point"},"properties":{"osm_id":"5196109779","tag":{"amenity":"waste_basket"}},"type":"Feature"},
	{"geometry":{"coordinates":[9.680617,46.782667],"type":"Point"},"properties":{"osm_id":"5196109781","tag":{"amenity":"waste_basket"}},"type":"Feature"},
	{"geometry":{"coordinates":[9.67978,46.783022],"type":"Point"},"properties":{"osm_id":"5196123972","tag":{"amenity":"waste_basket"}},"type":"Feature"},
	{"geometry":{"coordinates":[9.680073,46.782845],"type":"Point"},"properties":{"osm_id":"5196123973","tag":{"amenity":"waste_basket"}},"type":"Feature"},
	{"geometry":{"coordinates":[9.6799,46.782939],"type":"Point"},"properties":{"osm_id":"5196123974","tag":{"amenity":"waste_basket"}},"type":"Feature"},
	{"geometry":{"coordinates":[9.678784,46.783829],"type":"Point"},"properties":{"osm_id":"5413049782","tag":{"amenity":"recycling","recycling:glass":"yes","recycling_type":"container"}},"type":"Feature"},
	{"geometry":{"coordinates":[9.686206,46.782444],"type":"Point"},"properties":{"osm_id":"5413059536","tag":{"amenity":"recycling","recycling:glass":"yes","recycling_type":"container"}},"type":"Feature"},
	{"geometry":{"coordinates":[9.68752,46.782671],"type":"Point"},"properties":{"osm_id":"5413059592","tag":{"amenity":"recycling","recycling:glass":"yes","recycling_type":"container"}},"type":"Feature"},
	{"geometry":{"coordinates":[9.680232,46.780924],"type":"Point"},"properties":{"osm_id":"5414015677","tag":{"amenity":"recycling","recycling:glass":"yes","recycling_type":"container"}},"type":"Feature"},
	{"geometry":{"coordinates":[9.678604,46.780312],"type":"Point"},"properties":{"osm_id":"5414467836","tag":{"amenity":"recycling","recycling:glass":"yes","recycling_type":"container"}},"type":"Feature"},
	{"geometry":{"coordinates":[9.677792,46.779716],"type":"Point"},"properties":{"osm_id":"5414472672","tag":{"amenity":"recycling","recycling:glass":"yes","recycling_type":"container"}},"type":"Feature"},
	{"geometry":{"coordinates":[9.687635,46.782946],"type":"Point"},"properties":{"osm_id":"5418315237","tag":{"amenity":"recycling","recycling:clothes":"yes","recycling_type":"container"}},"type":"Feature"},
	{"geometry":{"coordinates":[9.682926,46.780939],"type":"Point"},"properties":{"osm_id":"6010748792","tag":{"amenity":"recycling","recycling:glass":"yes","recycling_type":"underfloor-container"}},"type":"Feature"},
	{"geometry":{"coordinates":[9.687591,46.782581],"type":"Point"},"properties":{"name":"Multisammelstelle","osm_id":"6010768325","tag":{"amenity":"recycling","operator":"Gemeinde Arosa","recycling_type":"centre"}},"type":"Feature"}
]
}
