{
"type": "FeatureCollection",
"features": [
	{"geometry":{"coordinates":[9.754611,45.18035],"type":"Point"},"properties":{"name":"Discarica","osm_id":"8575347175","tag":{"amenity":"recycling","recycling_type":"centre"}},"type":"Feature"}
]
}
