{
"type": "FeatureCollection",
"features": [
	{"geometry":{"coordinates":[-77.261326,37.342194],"type":"Point"},"properties":{"name":"The Great Willow Oak","osm_id":"3718923465","tag":{"denotation":"natural_monument","natural":"tree"}},"type":"Feature"}
]
}
