{
"type": "FeatureCollection",
"lastupdate": "2020-08-04T00:00:00Z",
"features": [
	{"geometry":{"coordinates":[153.430665,-28.072994],"type":"Point"},"properties":{"osm_id":"1373418299","tag":{"amenity":"waste_basket"}},"type":"Feature"},
	{"geometry":{"coordinates":[153.430683,-28.073129],"type":"Point"},"properties":{"osm_id":"1373418304","tag":{"amenity":"waste_basket"}},"type":"Feature"},
	{"geometry":{"coordinates":[153.42502,-28.07453],"type":"Point"},"properties":{"osm_id":"2196861471","tag":{"amenity":"waste_basket"}},"type":"Feature"},
	{"geometry":{"coordinates":[153.434239,-28.07595],"type":"Point"},"properties":{"osm_id":"6127201545","tag":{"amenity":"waste_basket"}},"type":"Feature"},
	{"geometry":{"coordinates":[153.418838,-28.108375],"type":"Point"},"properties":{"osm_id":"6189014378","tag":{"entrance":"yes"}},"type":"Feature"},
	{"geometry":{"coordinates":[153.41892,-28.108389],"type":"Point"},"properties":{"name":"Reedy Creek Recycle Market","osm_id":"6189015232","tag":{"amenity":"recycling","building":"yes","opening_hours":"We-Su 08:00-16:00; PH off","phone":"+61 7 5522 1955","recycling_type":"centre","website":"http://www.goldcoast.qld.gov.au/environment/reedy-creek-recycle-market-24249.html"}},"type":"Feature"}
]
}
