{
"type": "FeatureCollection",
"lastupdate": "2020-08-03T00:00:00Z",
"features": [
	{"geometry":{"coordinates":[-92.490573,44.743459],"type":"Point"},"properties":{"name":"Pierce County recycling center","osm_id":"3840256722","tag":{"addr:city":"Ellsworth","addr:housenumber":"707","addr:postcode":"54011","addr:state":"WI","addr:street":"N. Maple Street","amenity":"recycling","recycling:cans":"yes","recycling:glass":"yes","recycling:glass_bottles":"yes","recycling:paper":"yes","recycling:plastic":"yes","recycling_type":"centre"}},"type":"Feature"}
]
}
