{
"type": "FeatureCollection",
"lastupdate": "2020-08-05T00:00:00Z",
"features": [
	{"geometry":{"coordinates":[146.171994,-38.401496],"type":"Point"},"properties":{"name":"Mirboo North Tip","osm_id":"2083118364","tag":{"amenity":"recycling","recycling_type":"container"}},"type":"Feature"},
	{"geometry":{"coordinates":[146.171576,-38.401362],"type":"Point"},"properties":{"osm_id":"2083156054","tag":{"amenity":"waste_basket","designation":"Mirboo North Tip"}},"type":"Feature"}
]
}
