{
"type": "FeatureCollection",
"features": [
	{"geometry":{"coordinates":[146.171995,-38.401497],"type":"Point"},"properties":{"name":"Mirboo North Tip","osm_id":"2083118364","tag":{"amenity":"recycling","recycling_type":"container"}},"type":"Feature"},
	{"geometry":{"coordinates":[146.171576,-38.401362],"type":"Point"},"properties":{"osm_id":"2083156054","tag":{"amenity":"waste_basket","designation":"Mirboo North Tip"}},"type":"Feature"}
]
}
