{
"type": "FeatureCollection",
"features": [
	{"geometry":{"coordinates":[145.616686,-16.93585],"type":"Point"},"properties":{"name":"Clohesy Fig Tree","osm_id":"5068131232","tag":{"natural":"tree","tourism":"attraction"}},"type":"Feature"},
	{"geometry":{"coordinates":[145.615816,-16.936566],"type":"Point"},"properties":{"osm_id":"9007310964","tag":{"natural":"tree"}},"type":"Feature"}
]
}
