{
"type": "FeatureCollection",
"features": [
	{"geometry":{"coordinates":[8.02531,52.17846],"type":"Point"},"properties":{"name":"Koenigsbuche","osm_id":"534712536","tag":{"denotation":"natural_monument","natural":"tree","tourism":"attraction"}},"type":"Feature"},
	{"geometry":{"coordinates":[8.037515,52.167659],"type":"Point"},"properties":{"osm_id":"3711705129","tag":{"natural":"tree"}},"type":"Feature"},
	{"geometry":{"coordinates":[8.017077,52.171928],"type":"Point"},"properties":{"osm_id":"3711993765","tag":{"natural":"tree"}},"type":"Feature"},
	{"geometry":{"coordinates":[8.065935,52.205814],"type":"Point"},"properties":{"osm_id":"9110791946","tag":{"natural":"tree"}},"type":"Feature"},
	{"geometry":{"coordinates":[8.066111,52.205849],"type":"Point"},"properties":{"osm_id":"9110791947","tag":{"natural":"tree"}},"type":"Feature"},
	{"geometry":{"coordinates":[8.066257,52.205873],"type":"Point"},"properties":{"osm_id":"9110791948","tag":{"natural":"tree"}},"type":"Feature"}
]
}
