{
"type": "FeatureCollection",
"features": [
	{"geometry":{"coordinates":[8.012987,51.185241],"type":"Point"},"properties":{"osm_id":"1177321501","tag":{"genus":"Tilia","genus:de":"Linde","leaf_cycle":"deciduous","leaf_type":"broadleaved","name:botanical":"Tilia","natural":"tree"}},"type":"Feature"},
	{"geometry":{"coordinates":[8.028308,51.223427],"type":"Point"},"properties":{"name":"Linde","osm_id":"3469251803","tag":{"genus":"Tilia","leaf_type":"broadleaved","natural":"tree"}},"type":"Feature"}
]
}
