{
"type": "FeatureCollection",
"features": [
	{"geometry":{"coordinates":[8.012986,51.18524],"type":"Point"},"properties":{"osm_id":"1177321501","tag":{"genus":"Tilia","genus:de":"Linde","leaf_cycle":"deciduous","leaf_type":"broadleaved","natural":"tree"}},"type":"Feature"},
	{"geometry":{"coordinates":[8.028308,51.223426],"type":"Point"},"properties":{"name":"Linde","osm_id":"3469251803","tag":{"genus":"Tilia","leaf_type":"broadleaved","natural":"tree"}},"type":"Feature"},
	{"geometry":{"coordinates":[8.049155,51.192566],"type":"Point"},"properties":{"osm_id":"8321603791","tag":{"leaf_cycle":"deciduous","leaf_type":"broadleaved","natural":"tree"}},"type":"Feature"},
	{"geometry":{"coordinates":[8.084113,51.215183],"type":"Point"},"properties":{"osm_id":"8549920696","tag":{"denotation":"avenue","genus":"Betula","genus:de":"Birke","leaf_cycle":"deciduous","leaf_type":"broadleaved","natural":"tree"}},"type":"Feature"},
	{"geometry":{"coordinates":[8.08406,51.215146],"type":"Point"},"properties":{"osm_id":"8549920697","tag":{"denotation":"avenue","genus":"Betula","genus:de":"Birke","leaf_cycle":"deciduous","leaf_type":"broadleaved","natural":"tree"}},"type":"Feature"},
	{"geometry":{"coordinates":[8.083913,51.215051],"type":"Point"},"properties":{"osm_id":"8549920698","tag":{"denotation":"avenue","genus":"Betula","genus:de":"Birke","leaf_cycle":"deciduous","leaf_type":"broadleaved","natural":"tree"}},"type":"Feature"},
	{"geometry":{"coordinates":[8.083812,51.214986],"type":"Point"},"properties":{"osm_id":"8549920699","tag":{"denotation":"avenue","genus":"Betula","genus:de":"Birke","leaf_cycle":"deciduous","leaf_type":"broadleaved","natural":"tree"}},"type":"Feature"},
	{"geometry":{"coordinates":[8.083736,51.214939],"type":"Point"},"properties":{"osm_id":"8549920700","tag":{"denotation":"avenue","genus":"Betula","genus:de":"Birke","leaf_cycle":"deciduous","leaf_type":"broadleaved","natural":"tree"}},"type":"Feature"},
	{"geometry":{"coordinates":[8.083655,51.21489],"type":"Point"},"properties":{"osm_id":"8549920701","tag":{"denotation":"avenue","genus":"Betula","genus:de":"Birke","leaf_cycle":"deciduous","leaf_type":"broadleaved","natural":"tree"}},"type":"Feature"},
	{"geometry":{"coordinates":[8.083576,51.214842],"type":"Point"},"properties":{"osm_id":"8549920702","tag":{"denotation":"avenue","genus":"Betula","genus:de":"Birke","leaf_cycle":"deciduous","leaf_type":"broadleaved","natural":"tree"}},"type":"Feature"},
	{"geometry":{"coordinates":[8.083504,51.214798],"type":"Point"},"properties":{"osm_id":"8549920703","tag":{"denotation":"avenue","genus":"Betula","genus:de":"Birke","leaf_cycle":"deciduous","leaf_type":"broadleaved","natural":"tree"}},"type":"Feature"},
	{"geometry":{"coordinates":[8.083424,51.214749],"type":"Point"},"properties":{"osm_id":"8549920704","tag":{"denotation":"avenue","genus":"Betula","genus:de":"Birke","leaf_cycle":"deciduous","leaf_type":"broadleaved","natural":"tree"}},"type":"Feature"},
	{"geometry":{"coordinates":[8.083346,51.2147],"type":"Point"},"properties":{"osm_id":"8549920705","tag":{"denotation":"avenue","genus":"Betula","genus:de":"Birke","leaf_cycle":"deciduous","leaf_type":"broadleaved","natural":"tree"}},"type":"Feature"}
]
}
