{
"type": "FeatureCollection",
"features": [
	{"geometry":{"coordinates":[8.023042,48.416767],"type":"Point"},"properties":{"name":"Scheffeleiche","osm_id":"659909067","tag":{"natural":"tree"}},"type":"Feature"},
	{"geometry":{"coordinates":[8.072028,48.429344],"type":"Point"},"properties":{"osm_id":"1423269239","tag":{"natural":"tree"}},"type":"Feature"},
	{"geometry":{"coordinates":[8.011985,48.401508],"type":"Point"},"properties":{"osm_id":"3899398846","tag":{"natural":"tree"}},"type":"Feature"},
	{"geometry":{"coordinates":[8.012248,48.401521],"type":"Point"},"properties":{"osm_id":"3899398847","tag":{"natural":"tree"}},"type":"Feature"},
	{"geometry":{"coordinates":[8.012082,48.401559],"type":"Point"},"properties":{"osm_id":"3899398848","tag":{"natural":"tree"}},"type":"Feature"},
	{"geometry":{"coordinates":[8.01313,48.401637],"type":"Point"},"properties":{"osm_id":"3899398850","tag":{"natural":"tree"}},"type":"Feature"},
	{"geometry":{"coordinates":[8.013039,48.401677],"type":"Point"},"properties":{"osm_id":"3899398853","tag":{"natural":"tree"}},"type":"Feature"},
	{"geometry":{"coordinates":[8.015148,48.402006],"type":"Point"},"properties":{"osm_id":"3899399269","tag":{"natural":"tree"}},"type":"Feature"},
	{"geometry":{"coordinates":[8.015271,48.402017],"type":"Point"},"properties":{"osm_id":"3899399270","tag":{"natural":"tree"}},"type":"Feature"},
	{"geometry":{"coordinates":[8.0154,48.402047],"type":"Point"},"properties":{"osm_id":"3899399271","tag":{"natural":"tree"}},"type":"Feature"},
	{"geometry":{"coordinates":[8.015557,48.402084],"type":"Point"},"properties":{"osm_id":"3899399277","tag":{"natural":"tree"}},"type":"Feature"},
	{"geometry":{"coordinates":[8.015718,48.402117],"type":"Point"},"properties":{"osm_id":"3899399280","tag":{"natural":"tree"}},"type":"Feature"},
	{"geometry":{"coordinates":[8.015157,48.402144],"type":"Point"},"properties":{"osm_id":"3899399281","tag":{"natural":"tree"}},"type":"Feature"},
	{"geometry":{"coordinates":[8.015855,48.40215],"type":"Point"},"properties":{"osm_id":"3899399283","tag":{"natural":"tree"}},"type":"Feature"},
	{"geometry":{"coordinates":[8.016085,48.402199],"type":"Point"},"properties":{"osm_id":"3899399290","tag":{"natural":"tree"}},"type":"Feature"},
	{"geometry":{"coordinates":[8.016652,48.402264],"type":"Point"},"properties":{"osm_id":"3899399292","tag":{"natural":"tree"}},"type":"Feature"},
	{"geometry":{"coordinates":[8.016471,48.402268],"type":"Point"},"properties":{"osm_id":"3899399293","tag":{"natural":"tree"}},"type":"Feature"},
	{"geometry":{"coordinates":[8.021844,48.400084],"type":"Point"},"properties":{"osm_id":"5557119828","tag":{"natural":"tree"}},"type":"Feature"},
	{"geometry":{"coordinates":[8.021824,48.400217],"type":"Point"},"properties":{"osm_id":"5557119829","tag":{"natural":"tree"}},"type":"Feature"},
	{"geometry":{"coordinates":[8.02184,48.400341],"type":"Point"},"properties":{"osm_id":"5557119830","tag":{"natural":"tree"}},"type":"Feature"},
	{"geometry":{"coordinates":[8.012625,48.406079],"type":"Point"},"properties":{"osm_id":"5646278118","tag":{"natural":"tree"}},"type":"Feature"},
	{"geometry":{"coordinates":[8.019684,48.403874],"type":"Point"},"properties":{"osm_id":"5726079430","tag":{"natural":"tree"}},"type":"Feature"},
	{"geometry":{"coordinates":[8.003533,48.432578],"type":"Point"},"properties":{"osm_id":"5937498660","tag":{"natural":"tree"}},"type":"Feature"}
]
}
