{
"type": "FeatureCollection",
"features": [
	{"geometry":{"coordinates":[8.023042,48.416766],"type":"Point"},"properties":{"name":"Scheffeleiche","osm_id":"659909067","tag":{"natural":"tree"}},"type":"Feature"},
	{"geometry":{"coordinates":[8.072027,48.429344],"type":"Point"},"properties":{"osm_id":"1423269239","tag":{"natural":"tree"}},"type":"Feature"},
	{"geometry":{"coordinates":[8.011984,48.401507],"type":"Point"},"properties":{"osm_id":"3899398846","tag":{"natural":"tree"}},"type":"Feature"},
	{"geometry":{"coordinates":[8.012247,48.401521],"type":"Point"},"properties":{"osm_id":"3899398847","tag":{"natural":"tree"}},"type":"Feature"},
	{"geometry":{"coordinates":[8.012081,48.401559],"type":"Point"},"properties":{"osm_id":"3899398848","tag":{"natural":"tree"}},"type":"Feature"},
	{"geometry":{"coordinates":[8.01313,48.401637],"type":"Point"},"properties":{"osm_id":"3899398850","tag":{"natural":"tree"}},"type":"Feature"},
	{"geometry":{"coordinates":[8.013038,48.401676],"type":"Point"},"properties":{"osm_id":"3899398853","tag":{"natural":"tree"}},"type":"Feature"},
	{"geometry":{"coordinates":[8.015147,48.402005],"type":"Point"},"properties":{"osm_id":"3899399269","tag":{"natural":"tree"}},"type":"Feature"},
	{"geometry":{"coordinates":[8.01527,48.402017],"type":"Point"},"properties":{"osm_id":"3899399270","tag":{"natural":"tree"}},"type":"Feature"},
	{"geometry":{"coordinates":[8.0154,48.402047],"type":"Point"},"properties":{"osm_id":"3899399271","tag":{"natural":"tree"}},"type":"Feature"},
	{"geometry":{"coordinates":[8.015556,48.402083],"type":"Point"},"properties":{"osm_id":"3899399277","tag":{"natural":"tree"}},"type":"Feature"},
	{"geometry":{"coordinates":[8.015718,48.402117],"type":"Point"},"properties":{"osm_id":"3899399280","tag":{"natural":"tree"}},"type":"Feature"},
	{"geometry":{"coordinates":[8.015156,48.402144],"type":"Point"},"properties":{"osm_id":"3899399281","tag":{"natural":"tree"}},"type":"Feature"},
	{"geometry":{"coordinates":[8.015855,48.40215],"type":"Point"},"properties":{"osm_id":"3899399283","tag":{"natural":"tree"}},"type":"Feature"},
	{"geometry":{"coordinates":[8.016084,48.402198],"type":"Point"},"properties":{"osm_id":"3899399290","tag":{"natural":"tree"}},"type":"Feature"},
	{"geometry":{"coordinates":[8.016652,48.402264],"type":"Point"},"properties":{"osm_id":"3899399292","tag":{"natural":"tree"}},"type":"Feature"},
	{"geometry":{"coordinates":[8.016471,48.402267],"type":"Point"},"properties":{"osm_id":"3899399293","tag":{"natural":"tree"}},"type":"Feature"},
	{"geometry":{"coordinates":[8.021844,48.400084],"type":"Point"},"properties":{"osm_id":"5557119828","tag":{"natural":"tree"}},"type":"Feature"},
	{"geometry":{"coordinates":[8.021823,48.400216],"type":"Point"},"properties":{"osm_id":"5557119829","tag":{"natural":"tree"}},"type":"Feature"},
	{"geometry":{"coordinates":[8.02184,48.40034],"type":"Point"},"properties":{"osm_id":"5557119830","tag":{"natural":"tree"}},"type":"Feature"},
	{"geometry":{"coordinates":[8.012624,48.406078],"type":"Point"},"properties":{"osm_id":"5646278118","tag":{"natural":"tree"}},"type":"Feature"},
	{"geometry":{"coordinates":[8.019684,48.403874],"type":"Point"},"properties":{"osm_id":"5726079430","tag":{"natural":"tree"}},"type":"Feature"},
	{"geometry":{"coordinates":[8.003532,48.432577],"type":"Point"},"properties":{"osm_id":"5937498660","tag":{"natural":"tree"}},"type":"Feature"}
]
}
