{
"type": "FeatureCollection",
"features": [
	{"geometry":{"coordinates":[21.820903,50.774467],"type":"Point"},"properties":{"name":"Pomnik przyrody","osm_id":"4037117491","tag":{"denotation":"natural_monument","monument":"yes","natural":"tree","protected":"yes"}},"type":"Feature"}
]
}
