{
"type": "FeatureCollection",
"features": [
	{"geometry":{"coordinates":[21.831855,50.315788],"type":"Point"},"properties":{"name":"Pomnik przyrody","osm_id":"4029152491","tag":{"denotation":"natural_monument","monument":"yes","natural":"tree","protected":"yes"}},"type":"Feature"},
	{"geometry":{"coordinates":[21.831935,50.315851],"type":"Point"},"properties":{"name":"Pomnik przyrody","osm_id":"4029152492","tag":{"denotation":"natural_monument","monument":"yes","natural":"tree","protected":"yes"}},"type":"Feature"},
	{"geometry":{"coordinates":[21.83179,50.315919],"type":"Point"},"properties":{"name":"Pomnik przyrody","osm_id":"4029152493","tag":{"denotation":"natural_monument","monument":"yes","natural":"tree","protected":"yes"}},"type":"Feature"},
	{"geometry":{"coordinates":[21.831824,50.316001],"type":"Point"},"properties":{"name":"Pomnik przyrody","osm_id":"4029152494","tag":{"denotation":"natural_monument","monument":"yes","natural":"tree","protected":"yes"}},"type":"Feature"},
	{"geometry":{"coordinates":[21.831948,50.316019],"type":"Point"},"properties":{"name":"Pomnik przyrody","osm_id":"4029152495","tag":{"denotation":"natural_monument","monument":"yes","natural":"tree","protected":"yes"}},"type":"Feature"},
	{"geometry":{"coordinates":[21.831592,50.316117],"type":"Point"},"properties":{"name":"Pomnik przyrody","osm_id":"4029152496","tag":{"denotation":"natural_monument","monument":"yes","natural":"tree","protected":"yes"}},"type":"Feature"},
	{"geometry":{"coordinates":[21.8321,50.316155],"type":"Point"},"properties":{"name":"Pomnik przyrody","osm_id":"4029152497","tag":{"denotation":"natural_monument","monument":"yes","natural":"tree","protected":"yes"}},"type":"Feature"},
	{"geometry":{"coordinates":[21.831531,50.316164],"type":"Point"},"properties":{"name":"Pomnik przyrody","osm_id":"4029152498","tag":{"denotation":"natural_monument","monument":"yes","natural":"tree","protected":"yes"}},"type":"Feature"},
	{"geometry":{"coordinates":[21.831659,50.316218],"type":"Point"},"properties":{"name":"Pomnik przyrody","osm_id":"4029152499","tag":{"denotation":"natural_monument","monument":"yes","natural":"tree","protected":"yes"}},"type":"Feature"},
	{"geometry":{"coordinates":[21.832424,50.316473],"type":"Point"},"properties":{"name":"Pomnik przyrody","osm_id":"4029152500","tag":{"denotation":"natural_monument","monument":"yes","natural":"tree","protected":"yes"}},"type":"Feature"},
	{"geometry":{"coordinates":[21.832447,50.316597],"type":"Point"},"properties":{"name":"Pomnik przyrody","osm_id":"4029152501","tag":{"denotation":"natural_monument","monument":"yes","natural":"tree","protected":"yes"}},"type":"Feature"},
	{"geometry":{"coordinates":[21.831813,50.316664],"type":"Point"},"properties":{"name":"Pomnik przyrody","osm_id":"4029152502","tag":{"denotation":"natural_monument","monument":"yes","natural":"tree","protected":"yes"}},"type":"Feature"},
	{"geometry":{"coordinates":[21.83253,50.316945],"type":"Point"},"properties":{"name":"Pomnik przyrody","osm_id":"4029152503","tag":{"denotation":"natural_monument","monument":"yes","natural":"tree","protected":"yes"}},"type":"Feature"},
	{"geometry":{"coordinates":[21.832558,50.317001],"type":"Point"},"properties":{"name":"Pomnik przyrody","osm_id":"4029152504","tag":{"denotation":"natural_monument","monument":"yes","natural":"tree","protected":"yes"}},"type":"Feature"},
	{"geometry":{"coordinates":[21.831883,50.317289],"type":"Point"},"properties":{"name":"Pomnik przyrody","osm_id":"4029152505","tag":{"denotation":"natural_monument","monument":"yes","natural":"tree","protected":"yes"}},"type":"Feature"}
]
}
