{
"type": "FeatureCollection",
"features": [
	{"geometry":{"coordinates":[21.84187,49.817726],"type":"Point"},"properties":{"name":"Pomnik Przyrody","osm_id":"4001621966","tag":{"denotation":"natural_monument","monument":"yes","natural":"tree"}},"type":"Feature"},
	{"geometry":{"coordinates":[21.841924,49.818064],"type":"Point"},"properties":{"name":"Pomnik Przyrody","osm_id":"4001621967","tag":{"denotation":"natural_monument","monument":"yes","natural":"tree"}},"type":"Feature"}
]
}
