{
"type": "FeatureCollection",
"features": [
	{"geometry":{"coordinates":[-25.039713,17.172804],"type":"Point"},"properties":{"osm_id":"5712158695","tag":{"natural":"tree"}},"type":"Feature"},
	{"geometry":{"coordinates":[-25.015773,17.149225],"type":"Point"},"properties":{"osm_id":"5734522771","tag":{"natural":"tree"}},"type":"Feature"},
	{"geometry":{"coordinates":[-25.013903,17.149509],"type":"Point"},"properties":{"name":"palmeira","osm_id":"5734522803","tag":{"natural":"tree"}},"type":"Feature"},
	{"geometry":{"coordinates":[-25.013943,17.145864],"type":"Point"},"properties":{"name":"palmeira","osm_id":"5779891078","tag":{"natural":"tree"}},"type":"Feature"},
	{"geometry":{"coordinates":[-25.013968,17.145505],"type":"Point"},"properties":{"name":"palmeira","osm_id":"5779891079","tag":{"natural":"tree"}},"type":"Feature"},
	{"geometry":{"coordinates":[-25.01349,17.145465],"type":"Point"},"properties":{"name":"palmeira","osm_id":"5779891080","tag":{"natural":"tree"}},"type":"Feature"},
	{"geometry":{"coordinates":[-25.048583,17.15945],"type":"Point"},"properties":{"osm_id":"5796392615","tag":{"natural":"tree"}},"type":"Feature"},
	{"geometry":{"coordinates":[-25.048129,17.159978],"type":"Point"},"properties":{"osm_id":"5796392628","tag":{"natural":"tree"}},"type":"Feature"},
	{"geometry":{"coordinates":[-25.028318,17.144229],"type":"Point"},"properties":{"osm_id":"5804789310","tag":{"natural":"tree"}},"type":"Feature"},
	{"geometry":{"coordinates":[-25.028515,17.143995],"type":"Point"},"properties":{"osm_id":"5804789311","tag":{"natural":"tree"}},"type":"Feature"},
	{"geometry":{"coordinates":[-25.028539,17.144376],"type":"Point"},"properties":{"osm_id":"5804789312","tag":{"natural":"tree"}},"type":"Feature"},
	{"geometry":{"coordinates":[-25.02923,17.143293],"type":"Point"},"properties":{"osm_id":"5804797412","tag":{"natural":"tree"}},"type":"Feature"},
	{"geometry":{"coordinates":[-25.029316,17.143486],"type":"Point"},"properties":{"osm_id":"5804797413","tag":{"natural":"tree"}},"type":"Feature"},
	{"geometry":{"coordinates":[-25.02971,17.143743],"type":"Point"},"properties":{"osm_id":"5804797414","tag":{"natural":"tree"}},"type":"Feature"},
	{"geometry":{"coordinates":[-25.029441,17.143894],"type":"Point"},"properties":{"osm_id":"5804797415","tag":{"natural":"tree"}},"type":"Feature"},
	{"geometry":{"coordinates":[-25.029571,17.14405],"type":"Point"},"properties":{"osm_id":"5804797416","tag":{"natural":"tree"}},"type":"Feature"},
	{"geometry":{"coordinates":[-25.029662,17.144179],"type":"Point"},"properties":{"osm_id":"5804797417","tag":{"natural":"tree"}},"type":"Feature"},
	{"geometry":{"coordinates":[-25.029873,17.144376],"type":"Point"},"properties":{"osm_id":"5804797418","tag":{"natural":"tree"}},"type":"Feature"},
	{"geometry":{"coordinates":[-25.029873,17.144816],"type":"Point"},"properties":{"osm_id":"5804797419","tag":{"natural":"tree"}},"type":"Feature"},
	{"geometry":{"coordinates":[-25.029446,17.143045],"type":"Point"},"properties":{"osm_id":"5804797420","tag":{"natural":"tree"}},"type":"Feature"},
	{"geometry":{"coordinates":[-25.030022,17.142775],"type":"Point"},"properties":{"osm_id":"5804797421","tag":{"natural":"tree"}},"type":"Feature"},
	{"geometry":{"coordinates":[-25.030046,17.142568],"type":"Point"},"properties":{"osm_id":"5804797422","tag":{"natural":"tree"}},"type":"Feature"},
	{"geometry":{"coordinates":[-25.022316,17.146918],"type":"Point"},"properties":{"osm_id":"5804803910","tag":{"natural":"tree"}},"type":"Feature"},
	{"geometry":{"coordinates":[-25.018729,17.157018],"type":"Point"},"properties":{"osm_id":"5804829943","tag":{"natural":"tree"}},"type":"Feature"},
	{"geometry":{"coordinates":[-25.019152,17.157077],"type":"Point"},"properties":{"osm_id":"5804829944","tag":{"natural":"tree"}},"type":"Feature"},
	{"geometry":{"coordinates":[-25.018814,17.157297],"type":"Point"},"properties":{"osm_id":"5804830039","tag":{"natural":"tree"}},"type":"Feature"},
	{"geometry":{"coordinates":[-25.019591,17.156106],"type":"Point"},"properties":{"osm_id":"5804839914","tag":{"natural":"tree"}},"type":"Feature"},
	{"geometry":{"coordinates":[-25.019231,17.156111],"type":"Point"},"properties":{"osm_id":"5804839915","tag":{"natural":"tree"}},"type":"Feature"},
	{"geometry":{"coordinates":[-25.023705,17.143016],"type":"Point"},"properties":{"osm_id":"6211869143","tag":{"natural":"tree"}},"type":"Feature"},
	{"geometry":{"coordinates":[-25.023505,17.142767],"type":"Point"},"properties":{"osm_id":"6211869144","tag":{"natural":"tree"}},"type":"Feature"},
	{"geometry":{"coordinates":[-25.017481,17.16485],"type":"Point"},"properties":{"osm_id":"6249497670","tag":{"natural":"tree"}},"type":"Feature"},
	{"geometry":{"coordinates":[-25.021605,17.14391],"type":"Point"},"properties":{"osm_id":"8520969047","tag":{"natural":"tree"}},"type":"Feature"},
	{"geometry":{"coordinates":[-25.027269,17.161588],"type":"Point"},"properties":{"osm_id":"9149785711","tag":{"natural":"tree"}},"type":"Feature"}
]
}
