{
"type": "FeatureCollection",
"features": [
	{"geometry":{"coordinates":[-25.039713,17.172805],"type":"Point"},"properties":{"osm_id":"5712158695","tag":{"natural":"tree"}},"type":"Feature"},
	{"geometry":{"coordinates":[-25.015773,17.149226],"type":"Point"},"properties":{"osm_id":"5734522771","tag":{"natural":"tree"}},"type":"Feature"},
	{"geometry":{"coordinates":[-25.013903,17.14951],"type":"Point"},"properties":{"name":"palmeira","osm_id":"5734522803","tag":{"natural":"tree"}},"type":"Feature"},
	{"geometry":{"coordinates":[-25.013943,17.145865],"type":"Point"},"properties":{"name":"palmeira","osm_id":"5779891078","tag":{"natural":"tree"}},"type":"Feature"},
	{"geometry":{"coordinates":[-25.013969,17.145506],"type":"Point"},"properties":{"name":"palmeira","osm_id":"5779891079","tag":{"natural":"tree"}},"type":"Feature"},
	{"geometry":{"coordinates":[-25.01349,17.145465],"type":"Point"},"properties":{"name":"palmeira","osm_id":"5779891080","tag":{"natural":"tree"}},"type":"Feature"},
	{"geometry":{"coordinates":[-25.048584,17.15945],"type":"Point"},"properties":{"osm_id":"5796392615","tag":{"natural":"tree"}},"type":"Feature"},
	{"geometry":{"coordinates":[-25.048129,17.159978],"type":"Point"},"properties":{"osm_id":"5796392628","tag":{"natural":"tree"}},"type":"Feature"},
	{"geometry":{"coordinates":[-25.028318,17.144229],"type":"Point"},"properties":{"osm_id":"5804789310","tag":{"natural":"tree"}},"type":"Feature"},
	{"geometry":{"coordinates":[-25.028515,17.143996],"type":"Point"},"properties":{"osm_id":"5804789311","tag":{"natural":"tree"}},"type":"Feature"},
	{"geometry":{"coordinates":[-25.028539,17.144376],"type":"Point"},"properties":{"osm_id":"5804789312","tag":{"natural":"tree"}},"type":"Feature"},
	{"geometry":{"coordinates":[-25.02923,17.143294],"type":"Point"},"properties":{"osm_id":"5804797412","tag":{"natural":"tree"}},"type":"Feature"},
	{"geometry":{"coordinates":[-25.029317,17.143486],"type":"Point"},"properties":{"osm_id":"5804797413","tag":{"natural":"tree"}},"type":"Feature"},
	{"geometry":{"coordinates":[-25.029711,17.143743],"type":"Point"},"properties":{"osm_id":"5804797414","tag":{"natural":"tree"}},"type":"Feature"},
	{"geometry":{"coordinates":[-25.029442,17.143895],"type":"Point"},"properties":{"osm_id":"5804797415","tag":{"natural":"tree"}},"type":"Feature"},
	{"geometry":{"coordinates":[-25.029571,17.144051],"type":"Point"},"properties":{"osm_id":"5804797416","tag":{"natural":"tree"}},"type":"Feature"},
	{"geometry":{"coordinates":[-25.029663,17.144179],"type":"Point"},"properties":{"osm_id":"5804797417","tag":{"natural":"tree"}},"type":"Feature"},
	{"geometry":{"coordinates":[-25.029874,17.144376],"type":"Point"},"properties":{"osm_id":"5804797418","tag":{"natural":"tree"}},"type":"Feature"},
	{"geometry":{"coordinates":[-25.029874,17.144817],"type":"Point"},"properties":{"osm_id":"5804797419","tag":{"natural":"tree"}},"type":"Feature"},
	{"geometry":{"coordinates":[-25.029447,17.143046],"type":"Point"},"properties":{"osm_id":"5804797420","tag":{"natural":"tree"}},"type":"Feature"},
	{"geometry":{"coordinates":[-25.030023,17.142775],"type":"Point"},"properties":{"osm_id":"5804797421","tag":{"natural":"tree"}},"type":"Feature"},
	{"geometry":{"coordinates":[-25.030047,17.142569],"type":"Point"},"properties":{"osm_id":"5804797422","tag":{"natural":"tree"}},"type":"Feature"},
	{"geometry":{"coordinates":[-25.022317,17.146918],"type":"Point"},"properties":{"osm_id":"5804803910","tag":{"natural":"tree"}},"type":"Feature"},
	{"geometry":{"coordinates":[-25.018729,17.157018],"type":"Point"},"properties":{"osm_id":"5804829943","tag":{"natural":"tree"}},"type":"Feature"},
	{"geometry":{"coordinates":[-25.019153,17.157078],"type":"Point"},"properties":{"osm_id":"5804829944","tag":{"natural":"tree"}},"type":"Feature"},
	{"geometry":{"coordinates":[-25.018814,17.157298],"type":"Point"},"properties":{"osm_id":"5804830039","tag":{"natural":"tree"}},"type":"Feature"},
	{"geometry":{"coordinates":[-25.019591,17.156106],"type":"Point"},"properties":{"osm_id":"5804839914","tag":{"natural":"tree"}},"type":"Feature"},
	{"geometry":{"coordinates":[-25.019231,17.156111],"type":"Point"},"properties":{"osm_id":"5804839915","tag":{"natural":"tree"}},"type":"Feature"},
	{"geometry":{"coordinates":[-25.023706,17.143016],"type":"Point"},"properties":{"osm_id":"6211869143","tag":{"natural":"tree"}},"type":"Feature"},
	{"geometry":{"coordinates":[-25.023506,17.142767],"type":"Point"},"properties":{"osm_id":"6211869144","tag":{"natural":"tree"}},"type":"Feature"},
	{"geometry":{"coordinates":[-25.017481,17.16485],"type":"Point"},"properties":{"osm_id":"6249497670","tag":{"natural":"tree"}},"type":"Feature"}
]
}
