{
"type": "FeatureCollection",
"features": [
	{"geometry":{"coordinates":[-0.892352,52.232944],"type":"Point"},"properties":{"osm_id":"310605941","tag":{"amenity":"recycling","recycling:glass":"yes","recycling:plastic_bottles":"yes"}},"type":"Feature"},
	{"geometry":{"coordinates":[-0.900699,52.261122],"type":"Point"},"properties":{"osm_id":"1086957719","tag":{"amenity":"recycling"}},"type":"Feature"},
	{"geometry":{"coordinates":[-0.936086,52.238673],"type":"Point"},"properties":{"osm_id":"1092252996","tag":{"amenity":"recycling"}},"type":"Feature"},
	{"geometry":{"coordinates":[-0.89871,52.246424],"type":"Point"},"properties":{"name":"Recycling Banks","osm_id":"1512550160","tag":{"amenity":"recycling","recycling:cans":"yes","recycling:glass":"yes","recycling:plastic":"yes","recycling_type":"container"}},"type":"Feature"},
	{"geometry":{"coordinates":[-0.900104,52.246597],"type":"Point"},"properties":{"osm_id":"1512551084","tag":{"amenity":"recycling","recycling:clothes":"yes","recycling_type":"container"}},"type":"Feature"},
	{"geometry":{"coordinates":[-0.90472,52.242453],"type":"Point"},"properties":{"osm_id":"1512648473","tag":{"amenity":"waste_basket","designation":"Rubbish"}},"type":"Feature"},
	{"geometry":{"coordinates":[-0.90484,52.242879],"type":"Point"},"properties":{"osm_id":"1512648474","tag":{"amenity":"waste_basket","designation":"Rubbish"}},"type":"Feature"},
	{"geometry":{"coordinates":[-0.904295,52.24448],"type":"Point"},"properties":{"osm_id":"1512648475","tag":{"amenity":"waste_basket","designation":"Rubbish"}},"type":"Feature"},
	{"geometry":{"coordinates":[-0.904545,52.243884],"type":"Point"},"properties":{"osm_id":"1512648476","tag":{"amenity":"waste_basket","designation":"Rubbish"}},"type":"Feature"},
	{"geometry":{"coordinates":[-0.904254,52.244049],"type":"Point"},"properties":{"osm_id":"1512648486","tag":{"amenity":"waste_basket","designation":"dog waste"}},"type":"Feature"},
	{"geometry":{"coordinates":[-0.904848,52.242889],"type":"Point"},"properties":{"osm_id":"1512648487","tag":{"amenity":"waste_basket","designation":"Dog waste"}},"type":"Feature"},
	{"geometry":{"coordinates":[-0.899885,52.265338],"type":"Point"},"properties":{"osm_id":"5787111853","tag":{"amenity":"waste_basket"}},"type":"Feature"}
]
}
