{
"type": "FeatureCollection",
"features": [
	{"geometry":{"coordinates":[-0.950526,38.713177],"type":"Point"},"properties":{"name":"Camacho Recycling","osm_id":"1802740742","tag":{"amenity":"recycling"}},"type":"Feature"}
]
}
