{
"type": "FeatureCollection",
"lastupdate": "2020-08-05T00:00:00Z",
"features": [
	{"geometry":{"coordinates":[-0.950525,38.713177],"type":"Point"},"properties":{"name":"Camacho Recycling","osm_id":"1802740742","tag":{"amenity":"recycling"}},"type":"Feature"}
]
}
