{
"type": "FeatureCollection",
"features": [
	{"geometry":{"coordinates":[-3.085815,58.995109],"type":"Point"},"properties":{"name":"Cursiter Recycling Centre","osm_id":"9140169556","tag":{"addr:city":"Orkney","addr:housename":"OIC Cursiter CASite","addr:street":"Cursiter Quarry","amenity":"recycling","owner":"Orkney Islands Council","ownership":"municipal","recycling_type":"centre","wikidata":"Q106085844"}},"type":"Feature"}
]
}
