{
"type": "FeatureCollection",
"features": [
	{"geometry":{"coordinates":[-3.158227,55.646586],"type":"Point"},"properties":{"name":"Eshiels Recycling Centre","osm_id":"98859320","tag":{"amenity":"recycling"}},"type":"Feature"},
	{"geometry":{"coordinates":[-3.101373,55.633028],"type":"Point"},"properties":{"osm_id":"4189302497","tag":{"amenity":"waste_basket"}},"type":"Feature"},
	{"geometry":{"coordinates":[-3.122168,55.639438],"type":"Point"},"properties":{"osm_id":"4189302512","tag":{"amenity":"waste_basket"}},"type":"Feature"},
	{"geometry":{"coordinates":[-3.108722,55.640111],"type":"Point"},"properties":{"osm_id":"4189302521","tag":{"amenity":"waste_basket"}},"type":"Feature"},
	{"geometry":{"coordinates":[-3.102575,55.634927],"type":"Point"},"properties":{"osm_id":"4189302527","tag":{"amenity":"waste_basket"}},"type":"Feature"},
	{"geometry":{"coordinates":[-3.10052,55.631045],"type":"Point"},"properties":{"osm_id":"4189302530","tag":{"amenity":"waste_basket"}},"type":"Feature"},
	{"geometry":{"coordinates":[-3.10589,55.638458],"type":"Point"},"properties":{"osm_id":"4189302542","tag":{"amenity":"waste_basket"}},"type":"Feature"},
	{"geometry":{"coordinates":[-3.135066,55.652163],"type":"Point"},"properties":{"osm_id":"6982571993","tag":{"amenity":"waste_basket","survey:date":"2019-11-16"}},"type":"Feature"}
]
}
