{
"type": "FeatureCollection",
"features": [
	{"geometry":{"coordinates":[-3.128494,51.010719],"type":"Point"},"properties":{"name":"Waste Care","osm_id":"3874711467","tag":{"amenity":"recycling"}},"type":"Feature"},
	{"geometry":{"coordinates":[-3.086358,50.999612],"type":"Point"},"properties":{"osm_id":"4894098668","tag":{"amenity":"waste_basket","waste":"dog_excrement"}},"type":"Feature"},
	{"geometry":{"coordinates":[-3.099027,51.013374],"type":"Point"},"properties":{"osm_id":"4909436016","tag":{"amenity":"waste_basket","waste":"trash"}},"type":"Feature"},
	{"geometry":{"coordinates":[-3.119489,51.010153],"type":"Point"},"properties":{"osm_id":"5191155866","tag":{"amenity":"waste_basket","covered":"yes","waste":"trash"}},"type":"Feature"},
	{"geometry":{"coordinates":[-3.1192,51.011606],"type":"Point"},"properties":{"osm_id":"5191155882","tag":{"amenity":"waste_basket","waste":"trash"}},"type":"Feature"}
]
}
