{
"type": "FeatureCollection",
"features": [
	{"geometry":{"coordinates":[-9.026626,42.552958],"type":"Point"},"properties":{"osm_id":"8495128437","tag":{"amenity":"recycling","location":"overground","recycling_type":"container"}},"type":"Feature"}
]
}
