{
"type": "FeatureCollection",
"lastupdate": "2020-08-04T00:00:00Z",
"features": [
	{"geometry":{"coordinates":[-8.977672,7.235213],"type":"Point"},"properties":{"osm_id":"4882035271","tag":{"addr:city":"Ganta","amenity":"waste_basket","fee":"no","waste":"Domestic waste"}},"type":"Feature"},
	{"geometry":{"coordinates":[-8.984938,7.237046],"type":"Point"},"properties":{"osm_id":"6169149940","tag":{"addr:city":"Ganta","amenity":"waste_basket","category":"transitional_site","dump:official":"no","fee":"no","waste":"trash"}},"type":"Feature"},
	{"geometry":{"coordinates":[-8.986427,7.2341],"type":"Point"},"properties":{"name":"Save Environment Actors","osm_id":"6169149976","tag":{"addr:city":"Ganta","amenity":"waste_basket","category":"transitional_site","fee":"yes","operator":"Save Environment Actors","provider":"city_corporation","waste":"trash"}},"type":"Feature"},
	{"geometry":{"coordinates":[-8.985208,7.234246],"type":"Point"},"properties":{"osm_id":"6169150427","tag":{"addr:city":"Ganta","amenity":"waste_basket","dump:official":"no","fee":"no","waste":"trash"}},"type":"Feature"},
	{"geometry":{"coordinates":[-8.985233,7.234381],"type":"Point"},"properties":{"osm_id":"6169150484","tag":{"addr:city":"Ganta","amenity":"waste_basket","dump:official":"no","fee":"no","waste":"trash"}},"type":"Feature"},
	{"geometry":{"coordinates":[-8.984407,7.234814],"type":"Point"},"properties":{"osm_id":"6169150821","tag":{"addr:city":"Ganta","amenity":"waste_basket","dump:official":"no","fee":"no","waste":"trash"}},"type":"Feature"},
	{"geometry":{"coordinates":[-8.985321,7.235692],"type":"Point"},"properties":{"osm_id":"6169150826","tag":{"addr:city":"Ganta","amenity":"waste_basket","dump:official":"no","fee":"no","waste":"trash"}},"type":"Feature"},
	{"geometry":{"coordinates":[-8.985553,7.232081],"type":"Point"},"properties":{"name":"Save Environment Actors","osm_id":"6169150849","tag":{"addr:city":"Ganta","addr:street":"Ganta-Tapita Road","amenity":"waste_basket","category":"commercial_bin","dump:official":"yes","fee":"yes","operator":"Save Environment Actors","provider":"city_corporation","waste":"trash"}},"type":"Feature"},
	{"geometry":{"coordinates":[-8.984782,7.232755],"type":"Point"},"properties":{"osm_id":"6169150854","tag":{"addr:city":"Ganta","amenity":"waste_basket","dump:official":"yes","fee":"yes","operator":"Save Environment Actors","provider":"city_corporation","waste":"trash"}},"type":"Feature"},
	{"geometry":{"coordinates":[-8.986103,7.232278],"type":"Point"},"properties":{"osm_id":"6169151104","tag":{"addr:city":"Ganta","amenity":"waste_basket","category":"transitional_site","dump:official":"no","fee":"no","waste":"trash"}},"type":"Feature"},
	{"geometry":{"coordinates":[-8.984038,7.231887],"type":"Point"},"properties":{"name":"Save Environment Actors","osm_id":"6169151110","tag":{"addr:city":"Ganta","amenity":"waste_basket","category":"transitional_site","dump:official":"yes","fee":"yes","operator":"Save Environment Actors","provider":"city_corporation","waste":"trash"}},"type":"Feature"},
	{"geometry":{"coordinates":[-8.984821,7.232517],"type":"Point"},"properties":{"name":"Save Environment Actors","osm_id":"6169151166","tag":{"addr:city":"Ganta","amenity":"waste_basket","category":"transitional_site","dump:official":"yes","fee":"yes","operator":"Save Environment Actors","provider":"city_corporation","waste":"trash"}},"type":"Feature"},
	{"geometry":{"coordinates":[-8.984574,7.233934],"type":"Point"},"properties":{"name":"Save Environment Actors","osm_id":"6169151172","tag":{"addr:city":"Ganta","addr:street":"Guinea Road","amenity":"waste_basket","category":"transitional_site","dump:official":"yes","fee":"yes","operator":"Save Environment Actors","waste":"trash"}},"type":"Feature"},
	{"geometry":{"coordinates":[-8.985086,7.232728],"type":"Point"},"properties":{"name":"Save Environment Actors","osm_id":"6169151175","tag":{"addr:city":"Ganta","amenity":"waste_basket","category":"transitional_site","dump:official":"yes","fee":"yes","operator":"Save Environment Actors","provider":"city_corporation","waste":"trash"}},"type":"Feature"},
	{"geometry":{"coordinates":[-8.985311,7.233515],"type":"Point"},"properties":{"name":"Save Environment Actors","osm_id":"6169151748","tag":{"addr:city":"Ganta","amenity":"waste_basket","category":"commercial_bin","dump:official":"yes","fee":"yes","operator":"Save Environment Actors","provider":"city_corporation","waste":"trash"}},"type":"Feature"},
	{"geometry":{"coordinates":[-8.982488,7.227304],"type":"Point"},"properties":{"man_made":"yes","name":"Iron Recycling Center","osm_id":"6791033437","tag":{"addr:city":"Ganta","addr:street":"Ganta-Tapita Road","amenity":"recycling","opening_hours":"Mo-Sa 08:00-18:00","recycling:metal":"yes","recycling_type":"centre"}},"type":"Feature"}
]
}
