{
"type": "FeatureCollection",
"features": [
	{"geometry":{"coordinates":[8.426314,51.888446],"type":"Point"},"properties":{"osm_id":"261846741","tag":{"amenity":"recycling","recycling:clothes":"yes","recycling:glass":"yes","recycling:glass_bottles":"yes","recycling_type":"container"}},"type":"Feature"},
	{"geometry":{"coordinates":[8.396067,51.883958],"type":"Point"},"properties":{"osm_id":"262506143","tag":{"amenity":"recycling","opening_hours":"Mo-Sa 07:00-20:00","recycling:batteries":"yes","recycling:clothes":"yes","recycling:glass":"yes","recycling:paper":"no","recycling_type":"container"}},"type":"Feature"},
	{"geometry":{"coordinates":[8.431883,51.875247],"type":"Point"},"properties":{"osm_id":"262698556","tag":{"amenity":"recycling"}},"type":"Feature"},
	{"geometry":{"coordinates":[8.431374,51.859552],"type":"Point"},"properties":{"osm_id":"264561738","tag":{"amenity":"recycling","recycling:clothes":"yes","recycling:glass":"yes","recycling:glass_bottles":"yes","recycling_type":"container"}},"type":"Feature"},
	{"geometry":{"coordinates":[8.357642,51.888968],"type":"Point"},"properties":{"osm_id":"276517974","tag":{"amenity":"recycling","recycling:clothes":"yes","recycling:glass_bottles":"yes","recycling:paper":"yes","recycling:shoes":"yes","recycling_type":"container"}},"type":"Feature"},
	{"geometry":{"coordinates":[8.369558,51.888309],"type":"Point"},"properties":{"osm_id":"291218186","tag":{"amenity":"recycling","recycling_type":"container"}},"type":"Feature"},
	{"geometry":{"coordinates":[8.404974,51.880717],"type":"Point"},"properties":{"osm_id":"291836520","tag":{"amenity":"recycling","opening_hours":"Mo-Sa 07:00-20:00; PH off","recycling:batteries":"yes","recycling:clothes":"yes","recycling:glass":"yes","recycling_type":"container"}},"type":"Feature"},
	{"geometry":{"coordinates":[8.38289,51.884304],"type":"Point"},"properties":{"osm_id":"291842051","tag":{"amenity":"recycling","recycling_type":"container"}},"type":"Feature"},
	{"geometry":{"coordinates":[8.430587,51.886369],"type":"Point"},"properties":{"osm_id":"361082129","tag":{"amenity":"recycling","recycling:glass":"yes","recycling:paper":"yes"}},"type":"Feature"},
	{"geometry":{"coordinates":[8.384503,51.881367],"type":"Point"},"properties":{"osm_id":"429311833","tag":{"amenity":"recycling","opening_hours":"Mo-Sa 07:00-20:00; PH off","recycling:glass":"yes","recycling:paper":"yes","recycling_type":"container"}},"type":"Feature"},
	{"geometry":{"coordinates":[8.389918,51.87916],"type":"Point"},"properties":{"osm_id":"429324057","tag":{"amenity":"recycling","recycling:glass":"yes","recycling:paper":"yes","recycling_type":"container"}},"type":"Feature"},
	{"geometry":{"coordinates":[8.39459,51.887339],"type":"Point"},"properties":{"osm_id":"429330892","tag":{"amenity":"recycling","opening_hours":"Mo-Sa 07:00-20:00; PH off","recycling:batteries":"yes","recycling:glass":"yes","recycling:paper":"yes","recycling_type":"container"}},"type":"Feature"},
	{"geometry":{"coordinates":[8.389714,51.889448],"type":"Point"},"properties":{"osm_id":"429335453","tag":{"amenity":"recycling","location":"overground","recycling_type":"container"}},"type":"Feature"},
	{"geometry":{"coordinates":[8.3502,51.886788],"type":"Point"},"properties":{"osm_id":"508974907","tag":{"amenity":"recycling","recycling:clothes":"yes","recycling_type":"container"}},"type":"Feature"},
	{"geometry":{"coordinates":[8.354693,51.889639],"type":"Point"},"properties":{"osm_id":"508974922","tag":{"amenity":"recycling","recycling:glass":"no","recycling:paper":"yes","recycling_type":"container"}},"type":"Feature"},
	{"geometry":{"coordinates":[8.419751,51.883186],"type":"Point"},"properties":{"osm_id":"951550483","tag":{"amenity":"recycling","recycling:clothes":"yes","recycling_type":"container"}},"type":"Feature"},
	{"geometry":{"coordinates":[8.392492,51.87948],"type":"Point"},"properties":{"osm_id":"3714139890","tag":{"amenity":"recycling","recycling:clothes":"yes","recycling_type":"container"}},"type":"Feature"},
	{"geometry":{"coordinates":[8.36844,51.837778],"type":"Point"},"properties":{"osm_id":"4033124257","tag":{"amenity":"recycling","recycling:clothes":"yes","recycling:glass":"yes","recycling_type":"container"}},"type":"Feature"},
	{"geometry":{"coordinates":[8.422128,51.887894],"type":"Point"},"properties":{"osm_id":"5144775523","tag":{"amenity":"recycling","recycling_type":"container"}},"type":"Feature"},
	{"geometry":{"coordinates":[8.361976,51.88922],"type":"Point"},"properties":{"osm_id":"6307689092","tag":{"amenity":"recycling","recycling:glass":"yes","recycling:glass_bottles":"yes","recycling_type":"container"}},"type":"Feature"},
	{"geometry":{"coordinates":[8.434926,51.861235],"type":"Point"},"properties":{"osm_id":"6425378113","tag":{"amenity":"recycling","recycling:glass":"yes","recycling:glass_bottles":"yes","recycling_type":"container"}},"type":"Feature"}
]
}
