{
"type": "FeatureCollection",
"lastupdate": "2020-07-31T00:00:00Z",
"features": [
	{"geometry":{"coordinates":[8.426314,51.888445],"type":"Point"},"properties":{"osm_id":"261846741","tag":{"amenity":"recycling","recycling:clothes":"yes","recycling:glass":"yes","recycling:glass_bottles":"yes","recycling_type":"container"}},"type":"Feature"},
	{"geometry":{"coordinates":[8.396067,51.883958],"type":"Point"},"properties":{"osm_id":"262506143","tag":{"amenity":"recycling","opening_hours":"Mo-Sa 07:00-20:00","recycling:batteries":"yes","recycling:clothes":"yes","recycling:glass":"yes","recycling:paper":"no","recycling_type":"container"}},"type":"Feature"},
	{"geometry":{"coordinates":[8.431883,51.875247],"type":"Point"},"properties":{"osm_id":"262698556","tag":{"amenity":"recycling"}},"type":"Feature"},
	{"geometry":{"coordinates":[8.431374,51.859551],"type":"Point"},"properties":{"osm_id":"264561738","tag":{"amenity":"recycling","recycling:clothes":"yes","recycling:glass":"yes","recycling:glass_bottles":"yes","recycling_type":"container"}},"type":"Feature"},
	{"geometry":{"coordinates":[8.357641,51.888968],"type":"Point"},"properties":{"osm_id":"276517974","tag":{"amenity":"recycling","recycling:clothes":"yes","recycling:glass_bottles":"yes","recycling:paper":"yes","recycling:shoes":"yes","recycling_type":"container"}},"type":"Feature"},
	{"geometry":{"coordinates":[8.369557,51.888308],"type":"Point"},"properties":{"osm_id":"291218186","tag":{"amenity":"recycling","recycling_type":"container"}},"type":"Feature"},
	{"geometry":{"coordinates":[8.404973,51.880717],"type":"Point"},"properties":{"osm_id":"291836520","tag":{"amenity":"recycling","opening_hours":"Mo-Sa 07:00-20:00; PH off","recycling:batteries":"yes","recycling:clothes":"yes","recycling:glass":"yes","recycling_type":"container"}},"type":"Feature"},
	{"geometry":{"coordinates":[8.382889,51.884303],"type":"Point"},"properties":{"osm_id":"291842051","tag":{"amenity":"recycling","recycling_type":"container"}},"type":"Feature"},
	{"geometry":{"coordinates":[8.430586,51.886369],"type":"Point"},"properties":{"osm_id":"361082129","tag":{"amenity":"recycling","recycling:glass":"yes","recycling:paper":"yes"}},"type":"Feature"},
	{"geometry":{"coordinates":[8.384502,51.881366],"type":"Point"},"properties":{"osm_id":"429311833","tag":{"amenity":"recycling","opening_hours":"Mo-Sa 07:00-20:00; PH off","recycling:glass":"yes","recycling:paper":"yes","recycling_type":"container"}},"type":"Feature"},
	{"geometry":{"coordinates":[8.389917,51.879159],"type":"Point"},"properties":{"osm_id":"429324057","tag":{"amenity":"recycling","recycling:glass":"yes","recycling:paper":"yes","recycling_type":"container"}},"type":"Feature"},
	{"geometry":{"coordinates":[8.39459,51.887338],"type":"Point"},"properties":{"osm_id":"429330892","tag":{"amenity":"recycling","opening_hours":"Mo-Sa 07:00-20:00; PH off","recycling:batteries":"yes","recycling:glass":"yes","recycling:paper":"yes","recycling_type":"container"}},"type":"Feature"},
	{"geometry":{"coordinates":[8.389714,51.889447],"type":"Point"},"properties":{"osm_id":"429335453","tag":{"amenity":"recycling","location":"overground","recycling_type":"container"}},"type":"Feature"},
	{"geometry":{"coordinates":[8.350199,51.886788],"type":"Point"},"properties":{"osm_id":"508974907","tag":{"amenity":"recycling","recycling:clothes":"yes","recycling_type":"container"}},"type":"Feature"},
	{"geometry":{"coordinates":[8.354692,51.889638],"type":"Point"},"properties":{"osm_id":"508974922","tag":{"amenity":"recycling","recycling:glass":"no","recycling:paper":"yes","recycling_type":"container"}},"type":"Feature"},
	{"geometry":{"coordinates":[8.419751,51.883185],"type":"Point"},"properties":{"osm_id":"951550483","tag":{"amenity":"recycling","recycling:clothes":"yes","recycling_type":"container"}},"type":"Feature"},
	{"geometry":{"coordinates":[8.392491,51.87948],"type":"Point"},"properties":{"osm_id":"3714139890","tag":{"amenity":"recycling","recycling:clothes":"yes","recycling_type":"container"}},"type":"Feature"},
	{"geometry":{"coordinates":[8.368439,51.837778],"type":"Point"},"properties":{"osm_id":"4033124257","tag":{"amenity":"recycling","recycling:clothes":"yes","recycling:glass":"yes","recycling_type":"container"}},"type":"Feature"},
	{"geometry":{"coordinates":[8.422127,51.887894],"type":"Point"},"properties":{"osm_id":"5144775523","tag":{"amenity":"recycling","recycling_type":"container"}},"type":"Feature"},
	{"geometry":{"coordinates":[8.361975,51.88922],"type":"Point"},"properties":{"osm_id":"6307689092","tag":{"amenity":"recycling","recycling:glass":"yes","recycling:glass_bottles":"yes","recycling_type":"container"}},"type":"Feature"},
	{"geometry":{"coordinates":[8.434926,51.861235],"type":"Point"},"properties":{"osm_id":"6425378113","tag":{"amenity":"recycling","recycling:glass":"yes","recycling:glass_bottles":"yes","recycling_type":"container"}},"type":"Feature"}
]
}
