{
"type": "FeatureCollection",
"features": [
	{"geometry":{"coordinates":[8.351723,51.671861],"type":"Point"},"properties":{"osm_id":"1365291530","tag":{"amenity":"waste_basket"}},"type":"Feature"},
	{"geometry":{"coordinates":[8.358197,51.636687],"type":"Point"},"properties":{"osm_id":"2314682181","tag":{"amenity":"recycling","recycling:clothes":"yes","recycling_type":"container"}},"type":"Feature"},
	{"geometry":{"coordinates":[8.358019,51.636666],"type":"Point"},"properties":{"osm_id":"2314682182","tag":{"amenity":"recycling","recycling:electrical_appliances":"yes","recycling:glass_bottles":"yes","recycling_type":"container"}},"type":"Feature"},
	{"geometry":{"coordinates":[8.410751,51.670243],"type":"Point"},"properties":{"osm_id":"2338484189","tag":{"amenity":"recycling","recycling:books":"no","recycling:cans":"no","recycling:cardboard":"no","recycling:cartons":"no","recycling:clothes":"yes","recycling:electrical_appliances":"yes","recycling:glass":"yes","recycling:glass_bottles":"yes","recycling:green_waste":"no","recycling:magazines":"no","recycling:newspaper":"no","recycling:paper":"no","recycling:paper_packaging":"no","recycling:plastic":"no","recycling:plastic_bottles":"no","recycling:plastic_packaging":"no","recycling:scrap_metal":"no","recycling:small_appliances":"yes","recycling:waste":"no","recycling:wood":"no","recycling_type":"container"}},"type":"Feature"},
	{"geometry":{"coordinates":[8.360462,51.665107],"type":"Point"},"properties":{"osm_id":"3228044763","tag":{"amenity":"recycling","location":"overground","recycling_type":"container"}},"type":"Feature"},
	{"geometry":{"coordinates":[8.365008,51.65321],"type":"Point"},"properties":{"osm_id":"3674648825","tag":{"amenity":"recycling","recycling:clothes":"yes","recycling:glass_bottles":"yes","recycling:small_appliances":"yes","recycling_type":"container"}},"type":"Feature"},
	{"geometry":{"coordinates":[8.374552,51.632921],"type":"Point"},"properties":{"osm_id":"7644687950","tag":{"amenity":"waste_basket"}},"type":"Feature"},
	{"geometry":{"coordinates":[8.366646,51.632728],"type":"Point"},"properties":{"osm_id":"7644706341","tag":{"amenity":"waste_basket"}},"type":"Feature"}
]
}
