{
"type": "FeatureCollection",
"lastupdate": "2020-07-31T00:00:00Z",
"features": [
	{"geometry":{"coordinates":[8.424038,50.587903],"type":"Point"},"properties":{"osm_id":"268262839","tag":{"amenity":"recycling","location":"overground","recycling_type":"container"}},"type":"Feature"},
	{"geometry":{"coordinates":[8.395386,50.620474],"type":"Point"},"properties":{"osm_id":"3554932695","tag":{"amenity":"waste_basket"}},"type":"Feature"},
	{"geometry":{"coordinates":[8.381195,50.597805],"type":"Point"},"properties":{"osm_id":"5271403228","tag":{"amenity":"recycling"}},"type":"Feature"},
	{"geometry":{"coordinates":[8.372543,50.60683],"type":"Point"},"properties":{"osm_id":"5974699538","tag":{"amenity":"waste_basket"}},"type":"Feature"},
	{"geometry":{"coordinates":[8.397151,50.603953],"type":"Point"},"properties":{"osm_id":"5983392930","tag":{"amenity":"waste_basket"}},"type":"Feature"},
	{"geometry":{"coordinates":[8.363565,50.582943],"type":"Point"},"properties":{"osm_id":"6036552457","tag":{"amenity":"waste_basket"}},"type":"Feature"},
	{"geometry":{"coordinates":[8.367696,50.610794],"type":"Point"},"properties":{"osm_id":"6187853852","tag":{"amenity":"waste_basket"}},"type":"Feature"},
	{"geometry":{"coordinates":[8.382972,50.59972],"type":"Point"},"properties":{"osm_id":"6312661645","tag":{"amenity":"waste_basket"}},"type":"Feature"},
	{"geometry":{"coordinates":[8.374134,50.601558],"type":"Point"},"properties":{"osm_id":"6477939991","tag":{"amenity":"waste_basket"}},"type":"Feature"},
	{"geometry":{"coordinates":[8.370893,50.603835],"type":"Point"},"properties":{"osm_id":"6772702864","tag":{"amenity":"waste_basket"}},"type":"Feature"},
	{"geometry":{"coordinates":[8.364971,50.59412],"type":"Point"},"properties":{"osm_id":"6965482051","tag":{"amenity":"waste_basket"}},"type":"Feature"}
]
}
