{
"type": "FeatureCollection",
"features": [
	{"geometry":{"coordinates":[8.424038,50.587904],"type":"Point"},"properties":{"osm_id":"268262839","tag":{"amenity":"recycling","location":"overground","recycling_type":"container"}},"type":"Feature"},
	{"geometry":{"coordinates":[8.395386,50.620475],"type":"Point"},"properties":{"osm_id":"3554932695","tag":{"amenity":"waste_basket"}},"type":"Feature"},
	{"geometry":{"coordinates":[8.381195,50.597805],"type":"Point"},"properties":{"osm_id":"5271403228","tag":{"amenity":"recycling"}},"type":"Feature"},
	{"geometry":{"coordinates":[8.372544,50.606831],"type":"Point"},"properties":{"osm_id":"5974699538","tag":{"amenity":"waste_basket"}},"type":"Feature"},
	{"geometry":{"coordinates":[8.397151,50.603953],"type":"Point"},"properties":{"osm_id":"5983392930","tag":{"amenity":"waste_basket"}},"type":"Feature"},
	{"geometry":{"coordinates":[8.363566,50.582944],"type":"Point"},"properties":{"osm_id":"6036552457","tag":{"amenity":"waste_basket"}},"type":"Feature"},
	{"geometry":{"coordinates":[8.367696,50.610794],"type":"Point"},"properties":{"osm_id":"6187853852","tag":{"amenity":"waste_basket"}},"type":"Feature"},
	{"geometry":{"coordinates":[8.382973,50.599721],"type":"Point"},"properties":{"osm_id":"6312661645","tag":{"amenity":"waste_basket"}},"type":"Feature"},
	{"geometry":{"coordinates":[8.374135,50.601559],"type":"Point"},"properties":{"osm_id":"6477939991","tag":{"amenity":"waste_basket"}},"type":"Feature"},
	{"geometry":{"coordinates":[8.370893,50.603835],"type":"Point"},"properties":{"osm_id":"6772702864","tag":{"amenity":"waste_basket"}},"type":"Feature"},
	{"geometry":{"coordinates":[8.364971,50.594121],"type":"Point"},"properties":{"osm_id":"6965482051","tag":{"amenity":"waste_basket"}},"type":"Feature"}
]
}
