{
"type": "FeatureCollection",
"features": [
	{"geometry":{"coordinates":[8.394206,45.010217],"type":"Point"},"properties":{"osm_id":"2899437823","tag":{"amenity":"recycling","location":"overground","recycling_type":"container"}},"type":"Feature"},
	{"geometry":{"coordinates":[8.398892,45.010187],"type":"Point"},"properties":{"osm_id":"2899437833","tag":{"amenity":"recycling","location":"overground","recycling_type":"container"}},"type":"Feature"},
	{"geometry":{"coordinates":[8.43682,45.022295],"type":"Point"},"properties":{"osm_id":"4681254368","tag":{"amenity":"recycling","recycling_type":"container"}},"type":"Feature"},
	{"geometry":{"coordinates":[8.401123,45.010383],"type":"Point"},"properties":{"osm_id":"4701627056","tag":{"amenity":"recycling","recycling_type":"container"}},"type":"Feature"}
]
}
