{
"type": "FeatureCollection",
"features": [
	{"geometry":{"coordinates":[125.271362,6.101727],"type":"Point"},"properties":{"osm_id":"4213535698","tag":{"natural":"tree"}},"type":"Feature"},
	{"geometry":{"coordinates":[125.271311,6.101684],"type":"Point"},"properties":{"osm_id":"4213535699","tag":{"natural":"tree"}},"type":"Feature"},
	{"geometry":{"coordinates":[125.271253,6.101639],"type":"Point"},"properties":{"osm_id":"4213535700","tag":{"natural":"tree"}},"type":"Feature"},
	{"geometry":{"coordinates":[125.271196,6.101605],"type":"Point"},"properties":{"osm_id":"4213535701","tag":{"natural":"tree"}},"type":"Feature"},
	{"geometry":{"coordinates":[125.271243,6.101537],"type":"Point"},"properties":{"osm_id":"4213535702","tag":{"natural":"tree"}},"type":"Feature"},
	{"geometry":{"coordinates":[125.271329,6.101425],"type":"Point"},"properties":{"osm_id":"4213535703","tag":{"natural":"tree"}},"type":"Feature"},
	{"geometry":{"coordinates":[125.271373,6.101374],"type":"Point"},"properties":{"osm_id":"4213535704","tag":{"natural":"tree"}},"type":"Feature"},
	{"geometry":{"coordinates":[125.271289,6.101485],"type":"Point"},"properties":{"osm_id":"4213535705","tag":{"natural":"tree"}},"type":"Feature"},
	{"geometry":{"coordinates":[125.271411,6.101662],"type":"Point"},"properties":{"osm_id":"4213535706","tag":{"natural":"tree"}},"type":"Feature"},
	{"geometry":{"coordinates":[125.271539,6.101497],"type":"Point"},"properties":{"osm_id":"4213535707","tag":{"natural":"tree"}},"type":"Feature"},
	{"geometry":{"coordinates":[125.271479,6.101452],"type":"Point"},"properties":{"osm_id":"4213535708","tag":{"natural":"tree"}},"type":"Feature"},
	{"geometry":{"coordinates":[125.271419,6.10142],"type":"Point"},"properties":{"osm_id":"4213535709","tag":{"natural":"tree"}},"type":"Feature"},
	{"geometry":{"coordinates":[125.272125,6.100383],"type":"Point"},"properties":{"osm_id":"4213535710","tag":{"natural":"tree"}},"type":"Feature"},
	{"geometry":{"coordinates":[125.272173,6.100424],"type":"Point"},"properties":{"osm_id":"4213535711","tag":{"natural":"tree"}},"type":"Feature"},
	{"geometry":{"coordinates":[125.272221,6.100456],"type":"Point"},"properties":{"osm_id":"4213535712","tag":{"natural":"tree"}},"type":"Feature"},
	{"geometry":{"coordinates":[125.272281,6.100493],"type":"Point"},"properties":{"osm_id":"4213535713","tag":{"natural":"tree"}},"type":"Feature"},
	{"geometry":{"coordinates":[125.272243,6.100544],"type":"Point"},"properties":{"osm_id":"4213535714","tag":{"natural":"tree"}},"type":"Feature"},
	{"geometry":{"coordinates":[125.272203,6.100593],"type":"Point"},"properties":{"osm_id":"4213535715","tag":{"natural":"tree"}},"type":"Feature"},
	{"geometry":{"coordinates":[125.27216,6.100654],"type":"Point"},"properties":{"osm_id":"4213535716","tag":{"natural":"tree"}},"type":"Feature"},
	{"geometry":{"coordinates":[125.272129,6.100714],"type":"Point"},"properties":{"osm_id":"4213535717","tag":{"natural":"tree"}},"type":"Feature"},
	{"geometry":{"coordinates":[125.272087,6.100668],"type":"Point"},"properties":{"osm_id":"4213535718","tag":{"natural":"tree"}},"type":"Feature"},
	{"geometry":{"coordinates":[125.272029,6.100624],"type":"Point"},"properties":{"osm_id":"4213535719","tag":{"natural":"tree"}},"type":"Feature"},
	{"geometry":{"coordinates":[125.271973,6.100589],"type":"Point"},"properties":{"osm_id":"4213535720","tag":{"natural":"tree"}},"type":"Feature"},
	{"geometry":{"coordinates":[125.272016,6.100533],"type":"Point"},"properties":{"osm_id":"4213535721","tag":{"natural":"tree"}},"type":"Feature"},
	{"geometry":{"coordinates":[125.272089,6.100432],"type":"Point"},"properties":{"osm_id":"4213535722","tag":{"natural":"tree"}},"type":"Feature"},
	{"geometry":{"coordinates":[125.272045,6.100487],"type":"Point"},"properties":{"osm_id":"4213535723","tag":{"natural":"tree"}},"type":"Feature"},
	{"geometry":{"coordinates":[125.271383,6.099974],"type":"Point"},"properties":{"name":"Acacia Tree","osm_id":"4213538989","tag":{"denotation":"natural_monument","leaf_cycle":"evergreen","leaf_type":"needleleaved","natural":"tree"}},"type":"Feature"}
]
}
