{
"type": "FeatureCollection",
"lastupdate": "2020-08-02T00:00:00Z",
"features": [
	{"geometry":{"coordinates":[14.858448,61.186222],"type":"Point"},"properties":{"osm_id":"4010054622","tag":{"addr:city":"Skattungbyn","addr:country":"SE","addr:housenumber":"500","addr:postcode":"79495","addr:street":"Landsv\u00e4gen","amenity":"recycling","operator":"Nodava","recycling:cans":"yes","recycling:clothes":"yes","recycling:glass":"yes","recycling:glass_bottles":"yes","recycling:paper":"yes","recycling:plastic":"yes","recycling_type":"container"}},"type":"Feature"}
]
}
