{
"type": "FeatureCollection",
"features": [
	{"geometry":{"coordinates":[14.88486,51.063136],"type":"Point"},"properties":{"osm_id":"672868948","tag":{"amenity":"recycling","location":"overground","recycling:clothes":"yes","recycling:glass_bottles":"yes","recycling:shoes":"yes","recycling_type":"container"}},"type":"Feature"},
	{"geometry":{"coordinates":[14.869558,51.056184],"type":"Point"},"properties":{"osm_id":"697674537","tag":{"amenity":"recycling","recycling:clothes":"yes","recycling:glass_bottles":"yes","recycling_type":"container"}},"type":"Feature"},
	{"geometry":{"coordinates":[14.863908,51.016583],"type":"Point"},"properties":{"osm_id":"1191802325","tag":{"amenity":"waste_basket"}},"type":"Feature"},
	{"geometry":{"coordinates":[14.866011,51.0155],"type":"Point"},"properties":{"osm_id":"1191802391","tag":{"amenity":"waste_basket"}},"type":"Feature"}
]
}
