{
"type": "FeatureCollection",
"features": [
	{"geometry":{"coordinates":[14.939881,50.479621],"type":"Point"},"properties":{"osm_id":"3691747431","tag":{"amenity":"waste_basket"}},"type":"Feature"},
	{"geometry":{"coordinates":[14.92607,50.486155],"type":"Point"},"properties":{"osm_id":"3691747437","tag":{"amenity":"waste_basket"}},"type":"Feature"},
	{"geometry":{"coordinates":[14.908871,50.496863],"type":"Point"},"properties":{"osm_id":"3810418817","tag":{"amenity":"waste_basket"}},"type":"Feature"},
	{"geometry":{"coordinates":[14.925143,50.512224],"type":"Point"},"properties":{"osm_id":"3810418828","tag":{"amenity":"recycling","recycling:glass":"yes","recycling:plastic":"yes","recycling:plastic_bottles":"yes","recycling_type":"container"}},"type":"Feature"},
	{"geometry":{"coordinates":[14.940849,50.47518],"type":"Point"},"properties":{"osm_id":"3814197574","tag":{"amenity":"recycling","recycling:cardboard":"yes","recycling:glass":"yes","recycling:paper":"yes","recycling:plastic":"yes","recycling:plastic_bottles":"yes","recycling_type":"container"}},"type":"Feature"},
	{"geometry":{"coordinates":[14.925659,50.485779],"type":"Point"},"properties":{"osm_id":"3814197584","tag":{"amenity":"recycling","location":"underground","recycling:beverage_cartons":"yes","recycling:glass":"yes","recycling:paper":"yes","recycling:plastic":"yes","recycling_type":"container"}},"type":"Feature"},
	{"geometry":{"coordinates":[14.919587,50.469484],"type":"Point"},"properties":{"osm_id":"3820996456","tag":{"amenity":"recycling","recycling:glass":"yes","recycling:paper":"yes","recycling:plastic":"yes","recycling:plastic_bottles":"yes","recycling_type":"container"}},"type":"Feature"},
	{"geometry":{"coordinates":[14.928298,50.490132],"type":"Point"},"properties":{"osm_id":"3820996565","tag":{"amenity":"recycling","recycling:glass":"yes","recycling:paper":"yes","recycling:plastic":"yes","recycling_type":"container"}},"type":"Feature"},
	{"geometry":{"coordinates":[14.924874,50.490975],"type":"Point"},"properties":{"osm_id":"3820996566","tag":{"amenity":"recycling","recycling:glass":"yes","recycling:paper":"yes","recycling:plastic":"yes","recycling_type":"container"}},"type":"Feature"},
	{"geometry":{"coordinates":[14.909994,50.474236],"type":"Point"},"properties":{"osm_id":"3900264697","tag":{"amenity":"recycling","recycling:cardboard":"yes","recycling:glass":"yes","recycling:plastic":"yes","recycling:plastic_bottles":"yes","recycling_type":"container"}},"type":"Feature"},
	{"geometry":{"coordinates":[14.937589,50.481407],"type":"Point"},"properties":{"osm_id":"4026252414","tag":{"amenity":"recycling","location":"underground","recycling:glass":"yes","recycling:paper":"yes","recycling:plastic":"yes","recycling_type":"container"}},"type":"Feature"},
	{"geometry":{"coordinates":[14.938924,50.479325],"type":"Point"},"properties":{"osm_id":"4083332746","tag":{"amenity":"recycling","recycling:beverage_cartons":"yes","recycling:glass":"yes","recycling:paper":"yes","recycling:plastic":"yes","recycling:waste":"yes","recycling_type":"container"}},"type":"Feature"},
	{"geometry":{"coordinates":[14.934923,50.478601],"type":"Point"},"properties":{"osm_id":"6983264574","tag":{"amenity":"recycling","location":"underground","recycling:beverage_cartons":"yes","recycling:glass":"yes","recycling:paper":"yes","recycling:plastic":"yes","recycling_type":"container"}},"type":"Feature"},
	{"geometry":{"coordinates":[14.935659,50.479967],"type":"Point"},"properties":{"osm_id":"7146490670","tag":{"amenity":"recycling","recycling:clothes":"yes","recycling:electrical_appliances":"yes","recycling_type":"container"}},"type":"Feature"},
	{"geometry":{"coordinates":[14.935811,50.480553],"type":"Point"},"properties":{"osm_id":"7146492284","tag":{"amenity":"recycling","recycling:glass":"yes","recycling:paper":"yes","recycling:plastic":"yes","recycling_type":"container"}},"type":"Feature"}
]
}
