{
"type": "FeatureCollection",
"lastupdate": "2020-08-06T00:00:00Z",
"features": [
	{"geometry":{"coordinates":[14.933491,48.088273],"type":"Point"},"properties":{"name":"Altstoffsammelzentrum","osm_id":"1895041519","tag":{"amenity":"recycling","recycling_type":"centre"}},"type":"Feature"},
	{"geometry":{"coordinates":[14.856947,48.096353],"type":"Point"},"properties":{"osm_id":"2468960545","tag":{"amenity":"recycling"}},"type":"Feature"},
	{"geometry":{"coordinates":[14.864163,48.096476],"type":"Point"},"properties":{"osm_id":"2468960685","tag":{"amenity":"recycling"}},"type":"Feature"},
	{"geometry":{"coordinates":[14.859538,48.103176],"type":"Point"},"properties":{"osm_id":"2635118090","tag":{"amenity":"recycling","opening_hours":"Mo-Sa 08:00-19:00","recycling:beverage_cartons":"yes","recycling:cans":"yes","recycling:glass_bottles":"yes","recycling:plastic_bags":"yes","recycling:plastic_bottles":"yes","recycling_type":"container"}},"type":"Feature"},
	{"geometry":{"coordinates":[14.876755,48.106986],"type":"Point"},"properties":{"osm_id":"3027938435","tag":{"amenity":"recycling"}},"type":"Feature"},
	{"geometry":{"coordinates":[14.854259,48.106162],"type":"Point"},"properties":{"osm_id":"4318727768","tag":{"amenity":"recycling","recycling:beverage_cartons":"yes","recycling:cans":"yes","recycling:glass_bottles":"yes","recycling:plastic_bags":"yes","recycling:plastic_bottles":"yes","recycling_type":"container"}},"type":"Feature"},
	{"geometry":{"coordinates":[14.867513,48.063813],"type":"Point"},"properties":{"osm_id":"6109494158","tag":{"amenity":"recycling","recycling:cans":"yes","recycling:glass_bottles":"yes","recycling_type":"container"}},"type":"Feature"}
]
}
