{
"type": "FeatureCollection",
"lastupdate": "2020-08-02T00:00:00Z",
"features": [
	{"geometry":{"coordinates":[-122.292854,47.093186],"type":"Point"},"properties":{"name":"Land Recovery Recycling Center","osm_id":"3713825241","tag":{"amenity":"recycling","opening_hours":"Mo-Su,PH 08:00-17:45","recycling_type":"centre"}},"type":"Feature"},
	{"geometry":{"coordinates":[-122.293786,47.068354],"type":"Point"},"properties":{"name":"Gundie's Auto Recyclers","osm_id":"5078247532","tag":{"amenity":"recycling","name:en":"Gundie's Auto Recyclers"}},"type":"Feature"}
]
}
