{
"type": "FeatureCollection",
"lastupdate": "2020-08-06T00:00:00Z",
"features": [
	{"geometry":{"coordinates":[-122.260669,45.534713],"type":"Point"},"properties":{"osm_id":"4484624425","tag":{"amenity":"waste_basket"}},"type":"Feature"},
	{"geometry":{"coordinates":[-122.333211,45.578523],"type":"Point"},"properties":{"name":"Goodwill Donation Express","osm_id":"7306375867","tag":{"amenity":"recycling","recycling_type":"centre"}},"type":"Feature"}
]
}
