{
"type": "FeatureCollection",
"features": [
	{"geometry":{"coordinates":[-122.260669,45.534714],"type":"Point"},"properties":{"osm_id":"4484624425","tag":{"amenity":"waste_basket"}},"type":"Feature"},
	{"geometry":{"coordinates":[-122.333212,45.578523],"type":"Point"},"properties":{"name":"Goodwill Donation Express","osm_id":"7306375867","tag":{"amenity":"recycling","recycling_type":"centre"}},"type":"Feature"}
]
}
