{
"type": "FeatureCollection",
"lastupdate": "2020-08-02T00:00:00Z",
"features": [
	{"geometry":{"coordinates":[-122.29177,37.544197],"type":"Point"},"properties":{"osm_id":"262255312","tag":{"amenity":"recycling","recycling_type":"container"}},"type":"Feature"},
	{"geometry":{"coordinates":[-122.304856,37.554605],"type":"Point"},"properties":{"osm_id":"297814920","tag":{"amenity":"recycling","recycling_type":"centre"}},"type":"Feature"},
	{"geometry":{"coordinates":[-122.258588,37.517899],"type":"Point"},"properties":{"name":"Shoreway Recycling Center","osm_id":"2297721385","tag":{"addr:housenumber":"225","amenity":"recycling"}},"type":"Feature"},
	{"geometry":{"coordinates":[-122.337667,37.520731],"type":"Point"},"properties":{"osm_id":"3399360528","tag":{"amenity":"recycling","opening_hours":"Tu-Sa 10:00-16:00","recycling_type":"centre"}},"type":"Feature"},
	{"geometry":{"coordinates":[-122.322083,37.511271],"type":"Point"},"properties":{"osm_id":"4226150561","tag":{"amenity":"waste_basket"}},"type":"Feature"},
	{"geometry":{"coordinates":[-122.322394,37.511275],"type":"Point"},"properties":{"osm_id":"4226150562","tag":{"amenity":"waste_basket"}},"type":"Feature"},
	{"geometry":{"coordinates":[-122.297967,37.538139],"type":"Point"},"properties":{"osm_id":"5631616210","tag":{"amenity":"waste_basket"}},"type":"Feature"},
	{"geometry":{"coordinates":[-122.256216,37.541712],"type":"Point"},"properties":{"osm_id":"6796489047","tag":{"amenity":"waste_basket"}},"type":"Feature"},
	{"geometry":{"coordinates":[-122.260785,37.539979],"type":"Point"},"properties":{"osm_id":"6796489049","tag":{"amenity":"waste_basket"}},"type":"Feature"},
	{"geometry":{"coordinates":[-122.260368,37.540349],"type":"Point"},"properties":{"osm_id":"6796489052","tag":{"amenity":"waste_basket"}},"type":"Feature"},
	{"geometry":{"coordinates":[-122.260884,37.535894],"type":"Point"},"properties":{"osm_id":"6796489055","tag":{"amenity":"waste_basket"}},"type":"Feature"},
	{"geometry":{"coordinates":[-122.264667,37.534554],"type":"Point"},"properties":{"osm_id":"6796489056","tag":{"amenity":"waste_basket"}},"type":"Feature"},
	{"geometry":{"coordinates":[-122.264683,37.534554],"type":"Point"},"properties":{"osm_id":"6796489057","tag":{"amenity":"waste_basket"}},"type":"Feature"},
	{"geometry":{"coordinates":[-122.261386,37.533744],"type":"Point"},"properties":{"osm_id":"6796489058","tag":{"amenity":"waste_basket"}},"type":"Feature"},
	{"geometry":{"coordinates":[-122.267155,37.53559],"type":"Point"},"properties":{"osm_id":"6796489061","tag":{"amenity":"waste_basket"}},"type":"Feature"},
	{"geometry":{"coordinates":[-122.271426,37.544178],"type":"Point"},"properties":{"osm_id":"6796489074","tag":{"amenity":"waste_basket"}},"type":"Feature"}
]
}
