{
"type": "FeatureCollection",
"features": [
	{"geometry":{"coordinates":[11.094965,43.580526],"type":"Point"},"properties":{"osm_id":"1653817286","tag":{"name:botanical":"Quercus pubescens","natural":"tree","type":"roverella"}},"type":"Feature"}
]
}
