{
"type": "FeatureCollection",
"lastupdate": "2020-07-31T00:00:00Z",
"features": [
	{"geometry":{"coordinates":[2.751422,42.487142],"type":"Point"},"properties":{"name":"Composteur collectif","osm_id":"3479430444","tag":{"amenity":"recycling","recycling:green_waste":"yes","recycling_type":"container"}},"type":"Feature"}
]
}
