{
"type": "FeatureCollection",
"features": [
	{"geometry":{"coordinates":[2.751422,42.487142],"type":"Point"},"properties":{"name":"Composteur collectif","osm_id":"3479430444","tag":{"amenity":"recycling","recycling:green_waste":"yes","recycling_type":"container"}},"type":"Feature"},
	{"geometry":{"coordinates":[2.747036,42.485647],"type":"Point"},"properties":{"osm_id":"9007181524","tag":{"amenity":"recycling","recycling:cans":"yes","recycling:paper":"yes","recycling:plastic":"yes","recycling_type":"container"}},"type":"Feature"}
]
}
