{
"type": "FeatureCollection",
"features": [
	{"geometry":{"coordinates":[20.589113,38.165634],"type":"Point"},"properties":{"name":"Eiche","osm_id":"1025999055","tag":{"natural":"tree","tourism":"attraction"}},"type":"Feature"},
	{"geometry":{"coordinates":[20.585593,38.169637],"type":"Point"},"properties":{"osm_id":"4912357178","tag":{"natural":"tree"}},"type":"Feature"},
	{"geometry":{"coordinates":[20.589297,38.165962],"type":"Point"},"properties":{"osm_id":"4951329226","tag":{"natural":"tree"}},"type":"Feature"},
	{"geometry":{"coordinates":[20.588664,38.165498],"type":"Point"},"properties":{"osm_id":"4951329227","tag":{"natural":"tree"}},"type":"Feature"},
	{"geometry":{"coordinates":[20.58836,38.166558],"type":"Point"},"properties":{"osm_id":"4951340632","tag":{"natural":"tree"}},"type":"Feature"},
	{"geometry":{"coordinates":[20.588301,38.166056],"type":"Point"},"properties":{"osm_id":"4951340633","tag":{"natural":"tree"}},"type":"Feature"}
]
}
