{
"type": "FeatureCollection",
"lastupdate": "2020-08-03T00:00:00Z",
"features": [
	{"geometry":{"coordinates":[-8.324754,51.911479],"type":"Point"},"properties":{"name":"Glounthane","osm_id":"919665084","tag":{"amenity":"recycling"}},"type":"Feature"}
]
}
