{
"type": "FeatureCollection",
"features": [
	{"geometry":{"coordinates":[-8.324755,51.911479],"type":"Point"},"properties":{"name":"Glounthane","osm_id":"919665084","tag":{"amenity":"recycling"}},"type":"Feature"}
]
}
