{
"type": "FeatureCollection",
"lastupdate": "2020-08-02T00:00:00Z",
"features": [
	{"geometry":{"coordinates":[-8.289618,42.103052],"type":"Point"},"properties":{"osm_id":"2688825042","tag":{"amenity":"recycling","recycling_type":"container"}},"type":"Feature"},
	{"geometry":{"coordinates":[-8.28639,42.104846],"type":"Point"},"properties":{"osm_id":"2688825048","tag":{"amenity":"recycling","recycling_type":"container"}},"type":"Feature"},
	{"geometry":{"coordinates":[-8.263447,42.108696],"type":"Point"},"properties":{"name":"Ecoponto","osm_id":"3927328457","tag":{"amenity":"recycling"}},"type":"Feature"}
]
}
