{
"type": "FeatureCollection",
"features": [
	{"geometry":{"coordinates":[-8.337417,42.035133],"type":"Point"},"properties":{"osm_id":"1432303205","tag":{"amenity":"waste_disposal"}},"type":"Feature"},
	{"geometry":{"coordinates":[-8.302722,42.095482],"type":"Point"},"properties":{"osm_id":"2688825055","tag":{"amenity":"recycling","recycling_type":"container"}},"type":"Feature"},
	{"geometry":{"coordinates":[-8.320699,42.090571],"type":"Point"},"properties":{"name":"Ecoponto","osm_id":"2941769810","tag":{"amenity":"recycling","recycling_type":"container"}},"type":"Feature"},
	{"geometry":{"coordinates":[-8.296825,42.059199],"type":"Point"},"properties":{"osm_id":"6021827455","tag":{"amenity":"recycling"}},"type":"Feature"}
]
}
