{
"type": "FeatureCollection",
"features": [
	{"geometry":{"coordinates":[-8.337418,42.035134],"type":"Point"},"properties":{"osm_id":"1432303205","tag":{"amenity":"waste_disposal"}},"type":"Feature"},
	{"geometry":{"coordinates":[-8.302588,42.09625],"type":"Point"},"properties":{"osm_id":"2688825055","tag":{"amenity":"recycling","recycling_type":"container"}},"type":"Feature"},
	{"geometry":{"coordinates":[-8.320699,42.090571],"type":"Point"},"properties":{"name":"Ecoponto","osm_id":"2941769810","tag":{"amenity":"recycling","recycling_type":"container"}},"type":"Feature"},
	{"geometry":{"coordinates":[-8.296826,42.0592],"type":"Point"},"properties":{"osm_id":"6021827455","tag":{"amenity":"recycling"}},"type":"Feature"}
]
}
