{
"type": "FeatureCollection",
"lastupdate": "2020-07-31T00:00:00Z",
"features": [
	{"geometry":{"coordinates":[-8.302587,42.09625],"type":"Point"},"properties":{"osm_id":"2688825055","tag":{"amenity":"recycling","recycling_type":"container"}},"type":"Feature"},
	{"geometry":{"coordinates":[-8.320699,42.090571],"type":"Point"},"properties":{"name":"Ecoponto","osm_id":"2941769810","tag":{"amenity":"recycling","recycling_type":"container"}},"type":"Feature"},
	{"geometry":{"coordinates":[-8.296825,42.059199],"type":"Point"},"properties":{"osm_id":"6021827455","tag":{"amenity":"recycling"}},"type":"Feature"}
]
}
