{
"type": "FeatureCollection",
"lastupdate": "2020-08-04T00:00:00Z",
"features": [
	{"geometry":{"coordinates":[-8.314208,41.884039],"type":"Point"},"properties":{"osm_id":"2683452804","tag":{"amenity":"recycling"}},"type":"Feature"},
	{"geometry":{"coordinates":[-8.265531,41.872716],"type":"Point"},"properties":{"osm_id":"2683452808","tag":{"amenity":"recycling","location":"overground","recycling:cans":"yes","recycling:glass_bottles":"yes","recycling:paper":"yes","recycling:plastic":"no","recycling:plastic_bottles":"yes","recycling:plastic_packaging":"no","recycling_type":"container"}},"type":"Feature"}
]
}
