{
"type": "FeatureCollection",
"features": [
	{"geometry":{"coordinates":[-110.649242,50.002139],"type":"Point"},"properties":{"name":"City of Medicine Hat drop point","osm_id":"1119643667","tag":{"amenity":"recycling"}},"type":"Feature"}
]
}
