{
"type": "FeatureCollection",
"features": [
	{"geometry":{"coordinates":[-110.649243,50.00214],"type":"Point"},"properties":{"name":"City of Medicine Hat drop point","osm_id":"1119643667","tag":{"amenity":"recycling"}},"type":"Feature"}
]
}
