{
"type": "FeatureCollection",
"features": [
	{"geometry":{"coordinates":[138.656863,-34.708313],"type":"Point"},"properties":{"name":"Scout Recycling","osm_id":"1854158626","tag":{"amenity":"recycling","recycling:batteries":"yes","recycling:cans":"yes","recycling:paper":"yes","recycling:scrap_metal":"yes","recycling_type":"centre"}},"type":"Feature"}
]
}
