{
"type": "FeatureCollection",
"features": [
	{"geometry":{"coordinates":[-106.56117,35.263942],"type":"Point"},"properties":{"name":"Prosopis torreyana / Western Honey Mesquite","osm_id":"8439509922","tag":{"denotation":"single","height":"3","leaf_cycle":"deciduous","leaf_type":"broadleaved","natural":"tree"}},"type":"Feature"}
]
}
