{
"type": "FeatureCollection",
"lastupdate": "2020-07-31T00:00:00Z",
"features": [
	{"geometry":{"coordinates":[-71.263708,41.594328],"type":"Point"},"properties":{"name":"Portsmouth Compactor and Recycling Center","osm_id":"3131333398","tag":{"amenity":"recycling","recycling_type":"centre"}},"type":"Feature"}
]
}
