{
"type": "FeatureCollection",
"features": [
	{"geometry":{"coordinates":[-71.264024,41.59429],"type":"Point"},"properties":{"name":"Portsmouth Compactor and Recycling Center","osm_id":"3131333398","tag":{"amenity":"recycling","recycling_type":"centre"}},"type":"Feature"}
]
}
