{
"type": "FeatureCollection",
"features": [
	{"geometry":{"coordinates":[-41.918802,-22.51945],"type":"Point"},"properties":{"name":"EEE-6C","osm_id":"4121663608","tag":{"amenity":"recycling","operator":"ODEBRECHT"}},"type":"Feature"}
]
}
