{
"type": "FeatureCollection",
"features": [
	{"geometry":{"coordinates":[43.339267,42.552685],"type":"Point"},"properties":{"osm_id":"6776661619","tag":{"natural":"tree"}},"type":"Feature"},
	{"geometry":{"coordinates":[43.338124,42.551404],"type":"Point"},"properties":{"name":"Oak","osm_id":"6776671395","tag":{"natural":"tree"}},"type":"Feature"}
]
}
