{
"type": "FeatureCollection",
"features": [
	{"geometry":{"coordinates":[43.339096,42.552664],"type":"Point"},"properties":{"name":"Oak","osm_id":"6776661619","tag":{"natural":"tree"}},"type":"Feature"},
	{"geometry":{"coordinates":[43.338064,42.551455],"type":"Point"},"properties":{"name":"Oak","osm_id":"6776671395","tag":{"natural":"tree"}},"type":"Feature"}
]
}
