{
"type": "FeatureCollection",
"features": [
	{"geometry":{"coordinates":[24.32068,60.416682],"type":"Point"},"properties":{"name":"Tulevaisuuden kuusi","osm_id":"4894965655","tag":{"denotation":"landmark","leaf_cycle":"evergreen","leaf_type":"needleleaved","natural":"tree","start_date":"2017"}},"type":"Feature"},
	{"geometry":{"coordinates":[24.31521,60.416673],"type":"Point"},"properties":{"osm_id":"4936962079","tag":{"natural":"tree"}},"type":"Feature"},
	{"geometry":{"coordinates":[24.315497,60.416566],"type":"Point"},"properties":{"osm_id":"4936962080","tag":{"natural":"tree"}},"type":"Feature"},
	{"geometry":{"coordinates":[24.315744,60.416425],"type":"Point"},"properties":{"osm_id":"4936962081","tag":{"natural":"tree"}},"type":"Feature"},
	{"geometry":{"coordinates":[24.316677,60.418923],"type":"Point"},"properties":{"osm_id":"4937144880","tag":{"natural":"tree"}},"type":"Feature"}
]
}
