{
"type": "FeatureCollection",
"features": [
	{"geometry":{"coordinates":[24.275815,57.128655],"type":"Point"},"properties":{"osm_id":"2339408075","tag":{"natural":"tree"}},"type":"Feature"},
	{"geometry":{"coordinates":[24.275883,57.128751],"type":"Point"},"properties":{"osm_id":"2339408077","tag":{"natural":"tree"}},"type":"Feature"},
	{"geometry":{"coordinates":[24.27605,57.128853],"type":"Point"},"properties":{"osm_id":"2339408085","tag":{"natural":"tree"}},"type":"Feature"},
	{"geometry":{"coordinates":[24.276396,57.128904],"type":"Point"},"properties":{"osm_id":"2339408089","tag":{"natural":"tree"}},"type":"Feature"},
	{"geometry":{"coordinates":[24.338647,57.093106],"type":"Point"},"properties":{"osm_id":"6945750033","tag":{"natural":"tree"}},"type":"Feature"},
	{"geometry":{"coordinates":[24.324054,57.097469],"type":"Point"},"properties":{"osm_id":"7501175585","tag":{"genus":"Quercus","monument":"yes","natural":"tree"}},"type":"Feature"},
	{"geometry":{"coordinates":[24.278314,57.12802],"type":"Point"},"properties":{"osm_id":"7906510832","tag":{"natural":"tree"}},"type":"Feature"},
	{"geometry":{"coordinates":[24.278349,57.12806],"type":"Point"},"properties":{"osm_id":"7906510833","tag":{"natural":"tree"}},"type":"Feature"},
	{"geometry":{"coordinates":[24.278386,57.128089],"type":"Point"},"properties":{"osm_id":"7906510834","tag":{"natural":"tree"}},"type":"Feature"},
	{"geometry":{"coordinates":[24.278244,57.127979],"type":"Point"},"properties":{"osm_id":"7906510837","tag":{"natural":"tree"}},"type":"Feature"},
	{"geometry":{"coordinates":[24.278148,57.127728],"type":"Point"},"properties":{"osm_id":"7906510862","tag":{"natural":"tree"}},"type":"Feature"},
	{"geometry":{"coordinates":[24.278192,57.12777],"type":"Point"},"properties":{"osm_id":"7906510863","tag":{"natural":"tree"}},"type":"Feature"},
	{"geometry":{"coordinates":[24.310468,57.097311],"type":"Point"},"properties":{"osm_id":"8316096196","tag":{"natural":"tree"}},"type":"Feature"},
	{"geometry":{"coordinates":[24.272249,57.135411],"type":"Point"},"properties":{"osm_id":"8955174884","tag":{"leaf_type":"broadleaved","natural":"tree"}},"type":"Feature"},
	{"geometry":{"coordinates":[24.271723,57.135288],"type":"Point"},"properties":{"osm_id":"8955174885","tag":{"leaf_type":"broadleaved","natural":"tree"}},"type":"Feature"},
	{"geometry":{"coordinates":[24.271195,57.13587],"type":"Point"},"properties":{"osm_id":"8955174886","tag":{"leaf_type":"broadleaved","natural":"tree"}},"type":"Feature"},
	{"geometry":{"coordinates":[24.272778,57.135094],"type":"Point"},"properties":{"osm_id":"8955174887","tag":{"leaf_type":"broadleaved","natural":"tree"}},"type":"Feature"},
	{"geometry":{"coordinates":[24.272515,57.13526],"type":"Point"},"properties":{"osm_id":"8955174888","tag":{"leaf_type":"broadleaved","natural":"tree"}},"type":"Feature"},
	{"geometry":{"coordinates":[24.271827,57.135649],"type":"Point"},"properties":{"osm_id":"8955174890","tag":{"leaf_type":"broadleaved","natural":"tree"}},"type":"Feature"},
	{"geometry":{"coordinates":[24.271703,57.135711],"type":"Point"},"properties":{"osm_id":"8955174891","tag":{"leaf_type":"broadleaved","natural":"tree"}},"type":"Feature"},
	{"geometry":{"coordinates":[24.280885,57.13283],"type":"Point"},"properties":{"name":"Latvijas Simtgades ozols","osm_id":"8955235390","tag":{"denotation":"memorial","leaf_type":"broadleaved","natural":"tree"}},"type":"Feature"}
]
}
