{
"type": "FeatureCollection",
"features": [
	{"geometry":{"coordinates":[4.151114,51.138304],"type":"Point"},"properties":{"osm_id":"1627011509","tag":{"amenity":"recycling","recycling:glass":"yes"}},"type":"Feature"},
	{"geometry":{"coordinates":[4.197887,51.130666],"type":"Point"},"properties":{"osm_id":"1627586803","tag":{"amenity":"recycling","recycling_type":"container"}},"type":"Feature"},
	{"geometry":{"coordinates":[4.140978,51.162294],"type":"Point"},"properties":{"osm_id":"1628957046","tag":{"amenity":"recycling","recycling:glass":"yes"}},"type":"Feature"},
	{"geometry":{"coordinates":[4.132469,51.177403],"type":"Point"},"properties":{"osm_id":"1628957080","tag":{"amenity":"recycling","location":"overground","recycling:glass":"yes","recycling_type":"container"}},"type":"Feature"},
	{"geometry":{"coordinates":[4.150918,51.138301],"type":"Point"},"properties":{"osm_id":"6284608387","tag":{"amenity":"waste_basket"}},"type":"Feature"},
	{"geometry":{"coordinates":[4.132339,51.177123],"type":"Point"},"properties":{"osm_id":"8279843658","tag":{"amenity":"waste_basket"}},"type":"Feature"},
	{"geometry":{"coordinates":[4.144133,51.171759],"type":"Point"},"properties":{"osm_id":"9041847985","tag":{"amenity":"waste_basket"}},"type":"Feature"}
]
}
