{
"type": "FeatureCollection",
"features": [
	{"geometry":{"coordinates":[4.151114,51.138305],"type":"Point"},"properties":{"osm_id":"1627011509","tag":{"amenity":"recycling","recycling:glass":"yes"}},"type":"Feature"},
	{"geometry":{"coordinates":[4.197887,51.130667],"type":"Point"},"properties":{"osm_id":"1627586803","tag":{"amenity":"recycling","recycling_type":"container"}},"type":"Feature"},
	{"geometry":{"coordinates":[4.140979,51.162294],"type":"Point"},"properties":{"osm_id":"1628957046","tag":{"amenity":"recycling","recycling:glass":"yes"}},"type":"Feature"},
	{"geometry":{"coordinates":[4.13247,51.177403],"type":"Point"},"properties":{"osm_id":"1628957080","tag":{"amenity":"recycling","location":"overground","recycling:glass":"yes","recycling_type":"container"}},"type":"Feature"},
	{"geometry":{"coordinates":[4.150919,51.138302],"type":"Point"},"properties":{"osm_id":"6284608387","tag":{"amenity":"waste_basket"}},"type":"Feature"}
]
}
