{
"type": "FeatureCollection",
"features": [
	{"geometry":{"coordinates":[4.188796,50.665361],"type":"Point"},"properties":{"osm_id":"775671769","tag":{"amenity":"recycling","check_date:recycling":"2021-01-24","recycling:glass_bottles":"yes","recycling_type":"container"}},"type":"Feature"},
	{"geometry":{"coordinates":[4.167788,50.660428],"type":"Point"},"properties":{"osm_id":"775981891","tag":{"amenity":"recycling","recycling:glass_bottles":"yes","recycling_type":"container"}},"type":"Feature"},
	{"geometry":{"coordinates":[4.175256,50.652283],"type":"Point"},"properties":{"osm_id":"775981892","tag":{"amenity":"recycling","recycling:glass_bottles":"yes","recycling_type":"container"}},"type":"Feature"},
	{"geometry":{"coordinates":[4.21237,50.643562],"type":"Point"},"properties":{"osm_id":"775981903","tag":{"amenity":"recycling","recycling:glass_bottles":"yes","recycling_type":"container"}},"type":"Feature"},
	{"geometry":{"coordinates":[4.20464,50.641283],"type":"Point"},"properties":{"osm_id":"1788775186","tag":{"amenity":"recycling","location":"overground","recycling:glass_bottles":"yes","recycling_type":"container"}},"type":"Feature"},
	{"geometry":{"coordinates":[4.1421,50.664712],"type":"Point"},"properties":{"osm_id":"2183485764","tag":{"amenity":"recycling","recycling:glass_bottles":"yes","recycling_type":"container"}},"type":"Feature"},
	{"geometry":{"coordinates":[4.198561,50.672902],"type":"Point"},"properties":{"osm_id":"3727242643","tag":{"amenity":"recycling","recycling:glass_bottles":"yes","recycling_type":"container"}},"type":"Feature"},
	{"geometry":{"coordinates":[4.16733,50.639884],"type":"Point"},"properties":{"osm_id":"3876550554","tag":{"amenity":"recycling","recycling:cans":"no","recycling:glass":"no","recycling:glass_bottles":"yes","recycling:paper":"no","recycling:plastic":"no"}},"type":"Feature"},
	{"geometry":{"coordinates":[4.161743,50.655433],"type":"Point"},"properties":{"osm_id":"3961188130","tag":{"amenity":"recycling","recycling:glass_bottles":"yes","recycling_type":"container"}},"type":"Feature"},
	{"geometry":{"coordinates":[4.163237,50.669953],"type":"Point"},"properties":{"osm_id":"4266860027","tag":{"amenity":"waste_basket"}},"type":"Feature"},
	{"geometry":{"coordinates":[4.176787,50.651408],"type":"Point"},"properties":{"osm_id":"5844408362","tag":{"amenity":"waste_basket"}},"type":"Feature"},
	{"geometry":{"coordinates":[4.218451,50.657182],"type":"Point"},"properties":{"osm_id":"7124298368","tag":{"amenity":"waste_basket"}},"type":"Feature"},
	{"geometry":{"coordinates":[4.216509,50.653742],"type":"Point"},"properties":{"barrier":"gate","osm_id":"8625998360"},"type":"Feature"},
	{"geometry":{"coordinates":[4.216177,50.653902],"type":"Point"},"properties":{"barrier":"gate","osm_id":"8625998361"},"type":"Feature"}
]
}
