{
"type": "FeatureCollection",
"lastupdate": "2020-08-01T00:00:00Z",
"features": [
	{"geometry":{"coordinates":[4.140998,43.497747],"type":"Point"},"properties":{"osm_id":"2909150817","tag":{"amenity":"waste_basket"}},"type":"Feature"},
	{"geometry":{"coordinates":[4.142625,43.493239],"type":"Point"},"properties":{"osm_id":"2954123534","tag":{"amenity":"waste_basket"}},"type":"Feature"},
	{"geometry":{"coordinates":[4.145827,43.482114],"type":"Point"},"properties":{"osm_id":"3476064319","tag":{"amenity":"recycling","recycling:glass":"yes","recycling:paper":"yes","recycling_type":"container"}},"type":"Feature"},
	{"geometry":{"coordinates":[4.138935,43.510885],"type":"Point"},"properties":{"osm_id":"3733301569","tag":{"amenity":"waste_basket"}},"type":"Feature"},
	{"geometry":{"coordinates":[4.139669,43.516062],"type":"Point"},"properties":{"osm_id":"3733301585","tag":{"amenity":"recycling","description":"Container ent\u00e9rr\u00e9 dans le sol","location":"underground","recycling:magazines":"yes","recycling:newspaper":"yes","recycling_type":"container"}},"type":"Feature"},
	{"geometry":{"coordinates":[4.139658,43.516075],"type":"Point"},"properties":{"osm_id":"3733301586","tag":{"amenity":"recycling","description":"Container ent\u00e9rr\u00e9 dans le sol","location":"underground","recycling:cans":"yes","recycling:cardboard":"yes","recycling:plastic_bottles":"yes","recycling_type":"container"}},"type":"Feature"},
	{"geometry":{"coordinates":[4.139649,43.516086],"type":"Point"},"properties":{"osm_id":"3733301588","tag":{"amenity":"recycling","description":"Container ent\u00e9rr\u00e9 dans le sol","location":"underground","recycling:glass":"yes","recycling_type":"container"}},"type":"Feature"},
	{"geometry":{"coordinates":[4.145099,43.50869],"type":"Point"},"properties":{"osm_id":"3736279389","ref":"082","tag":{"amenity":"recycling","recycling:magazines":"yes","recycling:newspaper":"yes","recycling_type":"container"}},"type":"Feature"},
	{"geometry":{"coordinates":[4.149754,43.515355],"type":"Point"},"properties":{"osm_id":"3736279391","tag":{"amenity":"waste_basket"}},"type":"Feature"},
	{"geometry":{"coordinates":[4.14986,43.515506],"type":"Point"},"properties":{"osm_id":"3736279392","tag":{"amenity":"waste_basket"}},"type":"Feature"},
	{"geometry":{"coordinates":[4.144702,43.480183],"type":"Point"},"properties":{"osm_id":"4318737792","tag":{"amenity":"waste_basket"}},"type":"Feature"},
	{"geometry":{"coordinates":[4.14469,43.480185],"type":"Point"},"properties":{"osm_id":"4318737793","tag":{"amenity":"waste_basket"}},"type":"Feature"},
	{"geometry":{"coordinates":[4.144669,43.480191],"type":"Point"},"properties":{"osm_id":"4318737794","tag":{"amenity":"waste_basket"}},"type":"Feature"},
	{"geometry":{"coordinates":[4.14468,43.480187],"type":"Point"},"properties":{"osm_id":"4318755289","tag":{"amenity":"waste_basket"}},"type":"Feature"}
]
}
