{
"type": "FeatureCollection",
"features": [
	{"geometry":{"coordinates":[-0.812313,43.131441],"type":"Point"},"properties":{"name":"Trogne","osm_id":"8230776348","tag":{"leaf_cycle":"deciduous","leaf_type":"broadleaved","natural":"tree"}},"type":"Feature"}
]
}
