{
"type": "FeatureCollection",
"features": [
	{"geometry":{"coordinates":[10.803183,52.328175],"type":"Point"},"properties":{"osm_id":"362471815","tag":{"amenity":"recycling","location":"overground","recycling_type":"container"}},"type":"Feature"},
	{"geometry":{"coordinates":[10.739112,52.353452],"type":"Point"},"properties":{"osm_id":"634924174","tag":{"amenity":"recycling","recycling:clothes":"yes","recycling:glass":"yes","recycling_type":"container"}},"type":"Feature"},
	{"geometry":{"coordinates":[10.742412,52.359659],"type":"Point"},"properties":{"osm_id":"962622309","tag":{"amenity":"recycling","recycling:clothes":"yes","recycling:glass":"yes","recycling_type":"container"}},"type":"Feature"},
	{"geometry":{"coordinates":[10.752117,52.360424],"type":"Point"},"properties":{"osm_id":"1383160770","tag":{"amenity":"recycling","recycling_type":"container"}},"type":"Feature"},
	{"geometry":{"coordinates":[10.758174,52.360081],"type":"Point"},"properties":{"osm_id":"1833204590","tag":{"amenity":"recycling","recycling:glass":"yes","recycling_type":"container"}},"type":"Feature"},
	{"geometry":{"coordinates":[10.749229,52.363789],"type":"Point"},"properties":{"osm_id":"2381974526","tag":{"amenity":"recycling","recycling:clothes":"yes","recycling:shoes":"yes","recycling_type":"container"}},"type":"Feature"},
	{"geometry":{"coordinates":[10.783692,52.35059],"type":"Point"},"properties":{"osm_id":"2949055988","tag":{"amenity":"recycling","recycling:clothes":"yes","recycling:glass":"yes","recycling_type":"container"}},"type":"Feature"},
	{"geometry":{"coordinates":[10.769361,52.352094],"type":"Point"},"properties":{"osm_id":"4244391773","tag":{"amenity":"recycling","recycling:cans":"no","recycling:clothes":"yes","recycling:glass":"yes","recycling:paper":"yes","recycling_type":"container"}},"type":"Feature"}
]
}
