{
"type": "FeatureCollection",
"features": [
	{"geometry":{"coordinates":[10.803183,52.328175],"type":"Point"},"properties":{"osm_id":"362471815","tag":{"amenity":"recycling","location":"overground","recycling_type":"container"}},"type":"Feature"},
	{"geometry":{"coordinates":[10.739111,52.353452],"type":"Point"},"properties":{"osm_id":"634924174","tag":{"amenity":"recycling","recycling:clothes":"yes","recycling:glass":"yes","recycling_type":"container"}},"type":"Feature"},
	{"geometry":{"coordinates":[10.742412,52.359658],"type":"Point"},"properties":{"osm_id":"962622309","tag":{"amenity":"recycling","recycling:clothes":"yes","recycling:glass":"yes","recycling_type":"container"}},"type":"Feature"},
	{"geometry":{"coordinates":[10.752117,52.360424],"type":"Point"},"properties":{"osm_id":"1383160770","tag":{"amenity":"recycling","recycling:clothes":"yes","recycling:glass_bottles":"yes","recycling:paper":"yes","recycling:shoes":"yes","recycling_type":"container"}},"type":"Feature"},
	{"geometry":{"coordinates":[10.758173,52.360081],"type":"Point"},"properties":{"osm_id":"1833204590","tag":{"amenity":"recycling","recycling:clothes":"yes","recycling:glass_bottles":"yes","recycling:shoes":"yes","recycling_type":"container"}},"type":"Feature"},
	{"geometry":{"coordinates":[10.749229,52.363788],"type":"Point"},"properties":{"osm_id":"2381974526","tag":{"amenity":"recycling","recycling:clothes":"yes","recycling_type":"container"}},"type":"Feature"},
	{"geometry":{"coordinates":[10.783691,52.350589],"type":"Point"},"properties":{"osm_id":"2949055988","tag":{"amenity":"recycling","recycling:clothes":"yes","recycling:glass":"yes","recycling_type":"container"}},"type":"Feature"},
	{"geometry":{"coordinates":[10.76936,52.352093],"type":"Point"},"properties":{"osm_id":"4244391773","tag":{"amenity":"recycling","recycling:cans":"no","recycling:clothes":"yes","recycling:glass":"yes","recycling:paper":"yes","recycling_type":"container"}},"type":"Feature"},
	{"geometry":{"coordinates":[10.774073,52.351934],"type":"Point"},"properties":{"osm_id":"8000558967","tag":{"amenity":"recycling","recycling:clothes":"yes","recycling:shoes":"yes","recycling_type":"container"}},"type":"Feature"},
	{"geometry":{"coordinates":[10.766232,52.372268],"type":"Point"},"properties":{"osm_id":"9135800152","tag":{"amenity":"waste_basket"}},"type":"Feature"}
]
}
