{
"type": "FeatureCollection",
"features": [
	{"geometry":{"coordinates":[10.734171,48.175766],"type":"Point"},"properties":{"osm_id":"258842546","tag":{"amenity":"recycling","check_date":"2015-10-26","recycling:cans":"yes","recycling:clothes":"yes","recycling:glass_bottles":"yes","recycling:shoes":"yes","recycling_type":"container"}},"type":"Feature"},
	{"geometry":{"coordinates":[10.751777,48.175802],"type":"Point"},"properties":{"osm_id":"262955695","tag":{"amenity":"recycling","recycling:glass":"yes"}},"type":"Feature"},
	{"geometry":{"coordinates":[10.755629,48.17881],"type":"Point"},"properties":{"osm_id":"271171595","tag":{"amenity":"recycling","recycling:clothes":"yes","recycling:glass":"yes"}},"type":"Feature"},
	{"geometry":{"coordinates":[10.75053,48.172404],"type":"Point"},"properties":{"osm_id":"292122443","tag":{"amenity":"recycling","recycling:batteries":"no","recycling:clothes":"yes","recycling:glass":"yes"}},"type":"Feature"},
	{"geometry":{"coordinates":[10.74526,48.176247],"type":"Point"},"properties":{"osm_id":"956207326","tag":{"amenity":"recycling"}},"type":"Feature"},
	{"geometry":{"coordinates":[10.763787,48.173274],"type":"Point"},"properties":{"osm_id":"1072744320","tag":{"amenity":"recycling","recycling:cans":"yes","recycling:glass":"yes"}},"type":"Feature"},
	{"geometry":{"coordinates":[10.772924,48.194406],"type":"Point"},"properties":{"osm_id":"1185586516","tag":{"amenity":"recycling","recycling:garden_waste":"yes","recycling:green_waste":"yes"}},"type":"Feature"},
	{"geometry":{"coordinates":[10.769033,48.184128],"type":"Point"},"properties":{"osm_id":"1187065878","tag":{"amenity":"recycling","recycling:cans":"yes","recycling:glass_bottles":"yes"}},"type":"Feature"},
	{"geometry":{"coordinates":[10.766672,48.197181],"type":"Point"},"properties":{"osm_id":"1187684920","tag":{"amenity":"recycling","recycling:clothes":"yes","recycling_type":"container"}},"type":"Feature"},
	{"geometry":{"coordinates":[10.764716,48.207539],"type":"Point"},"properties":{"osm_id":"1187684925","tag":{"amenity":"recycling","recycling:cans":"yes","recycling:clothes":"yes","recycling:glass_bottles":"yes"}},"type":"Feature"},
	{"geometry":{"coordinates":[10.743814,48.170635],"type":"Point"},"properties":{"osm_id":"1187693494","tag":{"amenity":"recycling","recycling:cans":"yes","recycling:glass_bottles":"yes"}},"type":"Feature"},
	{"geometry":{"coordinates":[10.745163,48.176973],"type":"Point"},"properties":{"osm_id":"1187702257","tag":{"amenity":"recycling","recycling:cans":"yes","recycling:clothes":"yes","recycling:glass_bottles":"yes"}},"type":"Feature"},
	{"geometry":{"coordinates":[10.754265,48.171905],"type":"Point"},"properties":{"osm_id":"1187703898","tag":{"amenity":"recycling","recycling:cans":"yes","recycling:clothes":"yes","recycling:glass_bottles":"yes"}},"type":"Feature"},
	{"geometry":{"coordinates":[10.755812,48.190849],"type":"Point"},"properties":{"osm_id":"1187706627","tag":{"amenity":"recycling","recycling:cans":"yes","recycling:clothes":"yes","recycling:glass_bottles":"yes"}},"type":"Feature"},
	{"geometry":{"coordinates":[10.755106,48.18754],"type":"Point"},"properties":{"osm_id":"1187710730","tag":{"amenity":"recycling","recycling:cans":"yes","recycling:glass_bottles":"yes"}},"type":"Feature"},
	{"geometry":{"coordinates":[10.809146,48.166321],"type":"Point"},"properties":{"osm_id":"4213515367","tag":{"amenity":"waste_basket","waste":"dog_excrement"}},"type":"Feature"},
	{"geometry":{"coordinates":[10.80856,48.170666],"type":"Point"},"properties":{"osm_id":"4213515373","tag":{"amenity":"waste_basket","waste":"dog_excrement"}},"type":"Feature"},
	{"geometry":{"coordinates":[10.75509,48.178226],"type":"Point"},"properties":{"name":"Altglascontainer","osm_id":"6960179188","tag":{"amenity":"waste_disposal"}},"type":"Feature"},
	{"geometry":{"coordinates":[10.751447,48.175846],"type":"Point"},"properties":{"osm_id":"7288573115","tag":{"amenity":"waste_basket"}},"type":"Feature"},
	{"geometry":{"coordinates":[10.75579,48.195608],"type":"Point"},"properties":{"osm_id":"7339738703","tag":{"amenity":"recycling","recycling:glass":"yes","recycling_type":"container"}},"type":"Feature"}
]
}
