{
"type": "FeatureCollection",
"features": [
	{"geometry":{"coordinates":[10.734883,46.308466],"type":"Point"},"properties":{"osm_id":"415496892","tag":{"amenity":"recycling"}},"type":"Feature"},
	{"geometry":{"coordinates":[10.765251,46.315586],"type":"Point"},"properties":{"name":"Isola ecologica","osm_id":"2960411096","tag":{"amenity":"recycling","recycling:cans":"yes","recycling:clothes":"no","recycling:glass":"yes","recycling:paper":"yes","recycling_type":"container"}},"type":"Feature"},
	{"geometry":{"coordinates":[10.800253,46.313271],"type":"Point"},"properties":{"osm_id":"4317627236","tag":{"amenity":"waste_basket"}},"type":"Feature"},
	{"geometry":{"coordinates":[10.800512,46.313272],"type":"Point"},"properties":{"osm_id":"4317627239","tag":{"amenity":"waste_basket"}},"type":"Feature"},
	{"geometry":{"coordinates":[10.79213,46.313314],"type":"Point"},"properties":{"osm_id":"4747902235","tag":{"amenity":"waste_basket"}},"type":"Feature"},
	{"geometry":{"coordinates":[10.730892,46.309853],"type":"Point"},"properties":{"osm_id":"4749889103","tag":{"amenity":"waste_basket"}},"type":"Feature"},
	{"geometry":{"coordinates":[10.738204,46.306],"type":"Point"},"properties":{"osm_id":"4749889155","tag":{"amenity":"waste_basket"}},"type":"Feature"},
	{"geometry":{"coordinates":[10.731584,46.309399],"type":"Point"},"properties":{"osm_id":"4749889189","tag":{"amenity":"recycling","recycling:glass":"yes","recycling_type":"container"}},"type":"Feature"},
	{"geometry":{"coordinates":[10.739072,46.309913],"type":"Point"},"properties":{"osm_id":"4749889361","tag":{"amenity":"waste_basket"}},"type":"Feature"},
	{"geometry":{"coordinates":[10.75086,46.306426],"type":"Point"},"properties":{"osm_id":"4749889418","tag":{"amenity":"waste_basket"}},"type":"Feature"},
	{"geometry":{"coordinates":[10.758052,46.310263],"type":"Point"},"properties":{"osm_id":"4749889445","tag":{"amenity":"recycling","recycling:glass":"yes","recycling_type":"container"}},"type":"Feature"},
	{"geometry":{"coordinates":[10.759399,46.310095],"type":"Point"},"properties":{"osm_id":"4749889459","tag":{"amenity":"recycling","recycling:glass":"yes","recycling_type":"container"}},"type":"Feature"},
	{"geometry":{"coordinates":[10.759405,46.310077],"type":"Point"},"properties":{"osm_id":"4749889460","tag":{"amenity":"waste_basket"}},"type":"Feature"},
	{"geometry":{"coordinates":[10.763478,46.309931],"type":"Point"},"properties":{"osm_id":"4749889495","tag":{"amenity":"recycling","recycling:glass":"yes","recycling_type":"container"}},"type":"Feature"},
	{"geometry":{"coordinates":[10.763458,46.310073],"type":"Point"},"properties":{"osm_id":"4749889501","tag":{"amenity":"waste_basket"}},"type":"Feature"},
	{"geometry":{"coordinates":[10.765258,46.310117],"type":"Point"},"properties":{"osm_id":"4749889506","tag":{"amenity":"waste_basket"}},"type":"Feature"},
	{"geometry":{"coordinates":[10.765953,46.310171],"type":"Point"},"properties":{"osm_id":"4749889508","tag":{"amenity":"waste_basket"}},"type":"Feature"},
	{"geometry":{"coordinates":[10.765534,46.291295],"type":"Point"},"properties":{"osm_id":"4899313835","tag":{"amenity":"waste_basket"}},"type":"Feature"},
	{"geometry":{"coordinates":[10.768297,46.290787],"type":"Point"},"properties":{"osm_id":"4899313841","tag":{"amenity":"waste_basket"}},"type":"Feature"},
	{"geometry":{"coordinates":[10.768022,46.291909],"type":"Point"},"properties":{"osm_id":"4899313845","tag":{"amenity":"waste_basket"}},"type":"Feature"},
	{"geometry":{"coordinates":[10.764568,46.295178],"type":"Point"},"properties":{"osm_id":"4899313847","tag":{"amenity":"waste_basket"}},"type":"Feature"},
	{"geometry":{"coordinates":[10.796272,46.316102],"type":"Point"},"properties":{"osm_id":"6341429182","tag":{"amenity":"waste_disposal","waste":"trash"}},"type":"Feature"},
	{"geometry":{"coordinates":[10.796261,46.316072],"type":"Point"},"properties":{"osm_id":"6341429183","tag":{"amenity":"recycling","recycling:glass":"yes","recycling_type":"container"}},"type":"Feature"}
]
}
