{
"type": "FeatureCollection",
"lastupdate": "2020-08-05T00:00:00Z",
"features": [
	{"geometry":{"coordinates":[10.734882,46.308465],"type":"Point"},"properties":{"osm_id":"415496892","tag":{"amenity":"recycling"}},"type":"Feature"},
	{"geometry":{"coordinates":[10.765251,46.315586],"type":"Point"},"properties":{"name":"Isola ecologica","osm_id":"2960411096","tag":{"amenity":"recycling","recycling:cans":"yes","recycling:clothes":"no","recycling:glass":"yes","recycling:paper":"yes","recycling_type":"container"}},"type":"Feature"},
	{"geometry":{"coordinates":[10.800252,46.313271],"type":"Point"},"properties":{"osm_id":"4317627236","tag":{"amenity":"waste_basket"}},"type":"Feature"},
	{"geometry":{"coordinates":[10.800511,46.313271],"type":"Point"},"properties":{"osm_id":"4317627239","tag":{"amenity":"waste_basket"}},"type":"Feature"},
	{"geometry":{"coordinates":[10.79213,46.313314],"type":"Point"},"properties":{"osm_id":"4747902235","tag":{"amenity":"waste_basket"}},"type":"Feature"},
	{"geometry":{"coordinates":[10.730891,46.309853],"type":"Point"},"properties":{"osm_id":"4749889103","tag":{"amenity":"waste_basket"}},"type":"Feature"},
	{"geometry":{"coordinates":[10.738203,46.305999],"type":"Point"},"properties":{"osm_id":"4749889155","tag":{"amenity":"waste_basket"}},"type":"Feature"},
	{"geometry":{"coordinates":[10.731583,46.309399],"type":"Point"},"properties":{"osm_id":"4749889189","tag":{"amenity":"recycling","recycling:glass":"yes","recycling_type":"container"}},"type":"Feature"},
	{"geometry":{"coordinates":[10.739072,46.309913],"type":"Point"},"properties":{"osm_id":"4749889361","tag":{"amenity":"waste_basket"}},"type":"Feature"},
	{"geometry":{"coordinates":[10.75086,46.306425],"type":"Point"},"properties":{"osm_id":"4749889418","tag":{"amenity":"waste_basket"}},"type":"Feature"},
	{"geometry":{"coordinates":[10.758051,46.310262],"type":"Point"},"properties":{"osm_id":"4749889445","tag":{"amenity":"recycling","recycling:glass":"yes","recycling_type":"container"}},"type":"Feature"},
	{"geometry":{"coordinates":[10.759398,46.310094],"type":"Point"},"properties":{"osm_id":"4749889459","tag":{"amenity":"recycling","recycling:glass":"yes","recycling_type":"container"}},"type":"Feature"},
	{"geometry":{"coordinates":[10.759404,46.310076],"type":"Point"},"properties":{"osm_id":"4749889460","tag":{"amenity":"waste_basket"}},"type":"Feature"},
	{"geometry":{"coordinates":[10.763478,46.30993],"type":"Point"},"properties":{"osm_id":"4749889495","tag":{"amenity":"recycling","recycling:glass":"yes","recycling_type":"container"}},"type":"Feature"},
	{"geometry":{"coordinates":[10.763458,46.310072],"type":"Point"},"properties":{"osm_id":"4749889501","tag":{"amenity":"waste_basket"}},"type":"Feature"},
	{"geometry":{"coordinates":[10.765257,46.310116],"type":"Point"},"properties":{"osm_id":"4749889506","tag":{"amenity":"waste_basket"}},"type":"Feature"},
	{"geometry":{"coordinates":[10.765953,46.310171],"type":"Point"},"properties":{"osm_id":"4749889508","tag":{"amenity":"waste_basket"}},"type":"Feature"},
	{"geometry":{"coordinates":[10.765534,46.291295],"type":"Point"},"properties":{"osm_id":"4899313835","tag":{"amenity":"waste_basket"}},"type":"Feature"},
	{"geometry":{"coordinates":[10.768296,46.290787],"type":"Point"},"properties":{"osm_id":"4899313841","tag":{"amenity":"waste_basket"}},"type":"Feature"},
	{"geometry":{"coordinates":[10.768021,46.291909],"type":"Point"},"properties":{"osm_id":"4899313845","tag":{"amenity":"waste_basket"}},"type":"Feature"},
	{"geometry":{"coordinates":[10.764567,46.295177],"type":"Point"},"properties":{"osm_id":"4899313847","tag":{"amenity":"waste_basket"}},"type":"Feature"},
	{"geometry":{"coordinates":[10.79626,46.316072],"type":"Point"},"properties":{"osm_id":"6341429183","tag":{"amenity":"recycling","recycling:glass":"yes","recycling_type":"container"}},"type":"Feature"}
]
}
