{
"type": "FeatureCollection",
"features": [
	{"geometry":{"coordinates":[10.761775,42.928851],"type":"Point"},"properties":{"barrier":"gate","osm_id":"1947527438"},"type":"Feature"},
	{"geometry":{"coordinates":[10.762532,42.929859],"type":"Point"},"properties":{"barrier":"gate","osm_id":"2443607540","tag":{"entrance":"yes"}},"type":"Feature"},
	{"geometry":{"coordinates":[10.754431,42.923564],"type":"Point"},"properties":{"osm_id":"4336223485","tag":{"amenity":"waste_basket"}},"type":"Feature"},
	{"geometry":{"coordinates":[10.754447,42.923641],"type":"Point"},"properties":{"osm_id":"4336223487","tag":{"amenity":"waste_basket"}},"type":"Feature"},
	{"geometry":{"coordinates":[10.784042,42.933291],"type":"Point"},"properties":{"osm_id":"8326290378","tag":{"entrance":"main"}},"type":"Feature"},
	{"geometry":{"coordinates":[10.78878,42.934391],"type":"Point"},"properties":{"name":"Barbieri Ecologia","osm_id":"8327890620","tag":{"addr:city":"Follonica","addr:housenumber":"811","addr:postcode":"58022","addr:street":"Via dell'industria","amenity":"recycling","recycling_type":"centre","website":"https://barbieriecologia.it"}},"type":"Feature"},
	{"geometry":{"coordinates":[10.747043,42.92734],"type":"Point"},"properties":{"osm_id":"8605581823","tag":{"amenity":"recycling","recycling:batteries":"yes","recycling_type":"container"}},"type":"Feature"},
	{"geometry":{"coordinates":[10.746572,42.926593],"type":"Point"},"properties":{"osm_id":"8606028573","tag":{"amenity":"recycling","recycling:clothes":"yes","recycling_type":"container"}},"type":"Feature"},
	{"geometry":{"coordinates":[10.750866,42.926559],"type":"Point"},"properties":{"osm_id":"8606028574","tag":{"amenity":"recycling","recycling:batteries":"yes","recycling_type":"container"}},"type":"Feature"},
	{"geometry":{"coordinates":[10.747385,42.927456],"type":"Point"},"properties":{"osm_id":"8606028575","tag":{"amenity":"recycling","recycling:clothes":"yes","recycling_type":"container"}},"type":"Feature"},
	{"geometry":{"coordinates":[10.746527,42.927687],"type":"Point"},"properties":{"osm_id":"8606028576","tag":{"amenity":"waste_basket","waste":"drugs"}},"type":"Feature"},
	{"geometry":{"coordinates":[10.75015,42.92767],"type":"Point"},"properties":{"osm_id":"8608924243","tag":{"amenity":"recycling","recycling:clothes":"yes","recycling_type":"container","supervised":"yes"}},"type":"Feature"},
	{"geometry":{"coordinates":[10.775027,42.932739],"type":"Point"},"properties":{"osm_id":"8636875485","tag":{"amenity":"recycling","level":"0","recycling:cooking_oil":"yes","recycling_type":"container"}},"type":"Feature"},
	{"geometry":{"coordinates":[10.775018,42.932793],"type":"Point"},"properties":{"osm_id":"8636875486","tag":{"amenity":"recycling","level":"0","recycling:batteries":"yes","recycling_type":"container"}},"type":"Feature"},
	{"geometry":{"coordinates":[10.765744,42.928229],"type":"Point"},"properties":{"osm_id":"8645502881","tag":{"amenity":"recycling","recycling:sewage_oil":"yes","recycling_type":"container"}},"type":"Feature"},
	{"geometry":{"coordinates":[10.751453,42.926329],"type":"Point"},"properties":{"osm_id":"8660660364","tag":{"amenity":"recycling","recycling:clothes":"yes","recycling_type":"container"}},"type":"Feature"}
]
}
