{
"type": "FeatureCollection",
"features": [
	{"geometry":{"coordinates":[6.79704,52.38767],"type":"Point"},"properties":{"name":"Kroezeboom","osm_id":"597611085","tag":{"addr:street":"Lansinksweg","denotation":"natural_monument","description":"Monumentale eik de kroezeboom.","natural":"tree","wikipedia":"nl:Kroezeboom"}},"type":"Feature"},
	{"geometry":{"coordinates":[6.82287,52.380886],"type":"Point"},"properties":{"osm_id":"4756850623","tag":{"natural":"tree"}},"type":"Feature"}
]
}
