{
"type": "FeatureCollection",
"features": [
	{"geometry":{"coordinates":[6.797041,52.387671],"type":"Point"},"properties":{"name":"Kroezeboom","osm_id":"597611085","tag":{"addr:street":"Lansinksweg","description":"Monumentale eik de kroezeboom.","natural":"tree"}},"type":"Feature"},
	{"geometry":{"coordinates":[6.822871,52.380886],"type":"Point"},"properties":{"osm_id":"4756850623","tag":{"natural":"tree"}},"type":"Feature"}
]
}
