{
"type": "FeatureCollection",
"features": [
	{"geometry":{"coordinates":[6.776267,51.777101],"type":"Point"},"properties":{"osm_id":"305383117","tag":{"genus:de":"Eiche","leaf_type":"broadleaved","natural":"tree"}},"type":"Feature"},
	{"geometry":{"coordinates":[6.780776,51.776867],"type":"Point"},"properties":{"name":"Die Linde an der Staustufe","osm_id":"305775705","tag":{"natural":"tree","type":"lime"}},"type":"Feature"},
	{"geometry":{"coordinates":[6.774652,51.746051],"type":"Point"},"properties":{"osm_id":"371250942","tag":{"genus:de":"Eiche","leaf_type":"broadleaved","natural":"tree","type":"oak"}},"type":"Feature"},
	{"geometry":{"coordinates":[6.78699,51.750485],"type":"Point"},"properties":{"osm_id":"373530166","tag":{"amenity":"hunting_stand","natural":"tree","type":"Oak"}},"type":"Feature"},
	{"geometry":{"coordinates":[6.773576,51.754968],"type":"Point"},"properties":{"osm_id":"409615468","tag":{"hiking_trail_marker":"A4","natural":"tree"}},"type":"Feature"},
	{"geometry":{"coordinates":[6.784543,51.752844],"type":"Point"},"properties":{"osm_id":"410035125","tag":{"hiking_trail_marker":"XA34","natural":"tree"}},"type":"Feature"},
	{"geometry":{"coordinates":[6.785,51.752817],"type":"Point"},"properties":{"osm_id":"410035130","tag":{"hiking_trail_marker":"XA34","natural":"tree"}},"type":"Feature"},
	{"geometry":{"coordinates":[6.786034,51.75305],"type":"Point"},"properties":{"osm_id":"410035131","tag":{"hiking_trail_marker":"XA34","natural":"tree"}},"type":"Feature"},
	{"geometry":{"coordinates":[6.790879,51.751462],"type":"Point"},"properties":{"osm_id":"410114693","tag":{"hiking_trail_marker":"XA4","natural":"tree"}},"type":"Feature"},
	{"geometry":{"coordinates":[6.843287,51.728958],"type":"Point"},"properties":{"osm_id":"616056467","tag":{"natural":"tree","type":"oak"}},"type":"Feature"},
	{"geometry":{"coordinates":[6.810945,51.768455],"type":"Point"},"properties":{"osm_id":"1107011566","tag":{"natural":"tree"}},"type":"Feature"},
	{"geometry":{"coordinates":[6.855293,51.780967],"type":"Point"},"properties":{"osm_id":"1908183843","tag":{"natural":"tree"}},"type":"Feature"},
	{"geometry":{"coordinates":[6.855039,51.781052],"type":"Point"},"properties":{"osm_id":"1908183844","tag":{"natural":"tree"}},"type":"Feature"},
	{"geometry":{"coordinates":[6.854781,51.781135],"type":"Point"},"properties":{"osm_id":"1908183845","tag":{"natural":"tree"}},"type":"Feature"},
	{"geometry":{"coordinates":[6.854464,51.78125],"type":"Point"},"properties":{"osm_id":"1908183847","tag":{"natural":"tree"}},"type":"Feature"},
	{"geometry":{"coordinates":[6.854209,51.781331],"type":"Point"},"properties":{"osm_id":"1908183849","tag":{"natural":"tree"}},"type":"Feature"},
	{"geometry":{"coordinates":[6.853958,51.78142],"type":"Point"},"properties":{"osm_id":"1908183851","tag":{"natural":"tree"}},"type":"Feature"},
	{"geometry":{"coordinates":[6.853369,51.779857],"type":"Point"},"properties":{"osm_id":"2049364324","tag":{"natural":"tree"}},"type":"Feature"},
	{"geometry":{"coordinates":[6.85076,51.781116],"type":"Point"},"properties":{"osm_id":"2049364354","tag":{"natural":"tree"}},"type":"Feature"},
	{"geometry":{"coordinates":[6.850912,51.781144],"type":"Point"},"properties":{"osm_id":"2049364355","tag":{"natural":"tree"}},"type":"Feature"},
	{"geometry":{"coordinates":[6.851065,51.781179],"type":"Point"},"properties":{"osm_id":"2049364356","tag":{"natural":"tree"}},"type":"Feature"},
	{"geometry":{"coordinates":[6.851228,51.78121],"type":"Point"},"properties":{"osm_id":"2049364357","tag":{"natural":"tree"}},"type":"Feature"},
	{"geometry":{"coordinates":[6.851396,51.781234],"type":"Point"},"properties":{"osm_id":"2049364358","tag":{"natural":"tree"}},"type":"Feature"},
	{"geometry":{"coordinates":[6.851532,51.781268],"type":"Point"},"properties":{"osm_id":"2049364359","tag":{"natural":"tree"}},"type":"Feature"},
	{"geometry":{"coordinates":[6.851681,51.781293],"type":"Point"},"properties":{"osm_id":"2049364360","tag":{"natural":"tree"}},"type":"Feature"},
	{"geometry":{"coordinates":[6.851828,51.781317],"type":"Point"},"properties":{"osm_id":"2049364361","tag":{"natural":"tree"}},"type":"Feature"},
	{"geometry":{"coordinates":[6.851975,51.781348],"type":"Point"},"properties":{"osm_id":"2049364362","tag":{"natural":"tree"}},"type":"Feature"},
	{"geometry":{"coordinates":[6.85214,51.781384],"type":"Point"},"properties":{"osm_id":"2049364363","tag":{"natural":"tree"}},"type":"Feature"},
	{"geometry":{"coordinates":[6.852283,51.781404],"type":"Point"},"properties":{"osm_id":"2049364364","tag":{"natural":"tree"}},"type":"Feature"},
	{"geometry":{"coordinates":[6.852436,51.781431],"type":"Point"},"properties":{"osm_id":"2049364365","tag":{"natural":"tree"}},"type":"Feature"},
	{"geometry":{"coordinates":[6.827122,51.730439],"type":"Point"},"properties":{"osm_id":"2110358761","tag":{"natural":"tree"}},"type":"Feature"}
]
}
