{
"type": "FeatureCollection",
"features": [
	{"geometry":{"coordinates":[6.850583,49.68756],"type":"Point"},"properties":{"name":"gezeichneter Baum","osm_id":"3100346031","tag":{"natural":"tree","wikidata":"Q95471314","wikipedia":"de:Gezeichneter Baum"}},"type":"Feature"}
]
}
