{
"type": "FeatureCollection",
"features": [
	{"geometry":{"coordinates":[-78.178391,39.189658],"type":"Point"},"properties":{"name":"Eastern Cottonwood Tree","osm_id":"4633828733","tag":{"denotation":"single","description":"Nominated as a remarkable tree of Virginia.","leaf_cycle":"deciduous","leaf_type":"broadleaved","natural":"tree","website":"http://web2.cnre.vt.edu/4h/remarkabletree/detail.cfm?AutofieldforPrimaryKey=1155"}},"type":"Feature"}
]
}
