{
"type": "FeatureCollection",
"features": [
	{"geometry":{"coordinates":[-2.335153,53.51336],"type":"Point"},"properties":{"osm_id":"465239558","tag":{"addr:city":"Salford","addr:postcode":"M27 4BT","addr:street":"Swinton Hall Road","amenity":"recycling","opening_hours":"24/7","recycling:cardboard":"yes","recycling:clothes":"yes","recycling:glass":"yes","recycling:glass_bottles":"yes","recycling:paper":"yes","recycling:plastic_packaging":"yes","recycling:shoes":"yes","recycling_type":"container"}},"type":"Feature"},
	{"geometry":{"coordinates":[-2.313832,53.496566],"type":"Point"},"properties":{"osm_id":"4198780877","tag":{"amenity":"waste_basket"}},"type":"Feature"},
	{"geometry":{"coordinates":[-2.313461,53.49649],"type":"Point"},"properties":{"osm_id":"4198780878","tag":{"amenity":"waste_basket"}},"type":"Feature"},
	{"geometry":{"coordinates":[-2.314893,53.497641],"type":"Point"},"properties":{"osm_id":"4199033891","tag":{"amenity":"waste_basket"}},"type":"Feature"},
	{"geometry":{"coordinates":[-2.311646,53.496606],"type":"Point"},"properties":{"osm_id":"4199033995","tag":{"amenity":"waste_basket"}},"type":"Feature"},
	{"geometry":{"coordinates":[-2.310257,53.496711],"type":"Point"},"properties":{"osm_id":"4199034491","tag":{"amenity":"waste_basket"}},"type":"Feature"},
	{"geometry":{"coordinates":[-2.317007,53.498696],"type":"Point"},"properties":{"osm_id":"4199034590","tag":{"amenity":"waste_basket"}},"type":"Feature"},
	{"geometry":{"coordinates":[-2.315778,53.497812],"type":"Point"},"properties":{"osm_id":"4199034689","tag":{"amenity":"waste_basket"}},"type":"Feature"},
	{"geometry":{"coordinates":[-2.314652,53.497262],"type":"Point"},"properties":{"osm_id":"4199035189","tag":{"amenity":"waste_basket"}},"type":"Feature"},
	{"geometry":{"coordinates":[-2.314486,53.498168],"type":"Point"},"properties":{"osm_id":"4200087015","tag":{"amenity":"waste_basket"}},"type":"Feature"},
	{"geometry":{"coordinates":[-2.314959,53.498871],"type":"Point"},"properties":{"osm_id":"4200099513","tag":{"amenity":"waste_basket"}},"type":"Feature"},
	{"geometry":{"coordinates":[-2.315389,53.497467],"type":"Point"},"properties":{"osm_id":"4200099519","tag":{"amenity":"waste_basket"}},"type":"Feature"},
	{"geometry":{"coordinates":[-2.313849,53.497535],"type":"Point"},"properties":{"osm_id":"4200099524","tag":{"amenity":"waste_basket"}},"type":"Feature"},
	{"geometry":{"coordinates":[-2.312808,53.498321],"type":"Point"},"properties":{"osm_id":"4200099617","tag":{"amenity":"waste_basket"}},"type":"Feature"},
	{"geometry":{"coordinates":[-2.313435,53.498477],"type":"Point"},"properties":{"osm_id":"4200099620","tag":{"amenity":"waste_basket"}},"type":"Feature"},
	{"geometry":{"coordinates":[-2.312547,53.497539],"type":"Point"},"properties":{"osm_id":"4212103490","tag":{"amenity":"waste_basket"}},"type":"Feature"},
	{"geometry":{"coordinates":[-2.288113,53.53743],"type":"Point"},"properties":{"osm_id":"4726188023","tag":{"amenity":"waste_basket"}},"type":"Feature"},
	{"geometry":{"coordinates":[-2.367249,53.536834],"type":"Point"},"properties":{"osm_id":"5598821390","tag":{"amenity":"waste_basket"}},"type":"Feature"},
	{"geometry":{"coordinates":[-2.289281,53.490257],"type":"Point"},"properties":{"osm_id":"7603727869","tag":{"amenity":"recycling","recycling:clothes":"yes","recycling:shoes":"yes","recycling_type":"container"}},"type":"Feature"}
]
}
