{
"type": "FeatureCollection",
"lastupdate": "2020-08-03T00:00:00Z",
"features": [
	{"geometry":{"coordinates":[-2.335153,53.51336],"type":"Point"},"properties":{"osm_id":"465239558","tag":{"addr:city":"Salford","addr:postcode":"M27 4BT","addr:street":"Swinton Hall Road","amenity":"recycling","opening_hours":"24/7","recycling:cardboard":"yes","recycling:clothes":"yes","recycling:glass":"yes","recycling:glass_bottles":"yes","recycling:paper":"yes","recycling:plastic_packaging":"yes","recycling:shoes":"yes","recycling_type":"container"}},"type":"Feature"},
	{"geometry":{"coordinates":[-2.313831,53.496565],"type":"Point"},"properties":{"osm_id":"4198780877","tag":{"amenity":"waste_basket"}},"type":"Feature"},
	{"geometry":{"coordinates":[-2.313461,53.496489],"type":"Point"},"properties":{"osm_id":"4198780878","tag":{"amenity":"waste_basket"}},"type":"Feature"},
	{"geometry":{"coordinates":[-2.314893,53.49764],"type":"Point"},"properties":{"osm_id":"4199033891","tag":{"amenity":"waste_basket"}},"type":"Feature"},
	{"geometry":{"coordinates":[-2.311646,53.496606],"type":"Point"},"properties":{"osm_id":"4199033995","tag":{"amenity":"waste_basket"}},"type":"Feature"},
	{"geometry":{"coordinates":[-2.310257,53.49671],"type":"Point"},"properties":{"osm_id":"4199034491","tag":{"amenity":"waste_basket"}},"type":"Feature"},
	{"geometry":{"coordinates":[-2.317007,53.498695],"type":"Point"},"properties":{"osm_id":"4199034590","tag":{"amenity":"waste_basket"}},"type":"Feature"},
	{"geometry":{"coordinates":[-2.315777,53.497812],"type":"Point"},"properties":{"osm_id":"4199034689","tag":{"amenity":"waste_basket"}},"type":"Feature"},
	{"geometry":{"coordinates":[-2.314651,53.497261],"type":"Point"},"properties":{"osm_id":"4199035189","tag":{"amenity":"waste_basket"}},"type":"Feature"},
	{"geometry":{"coordinates":[-2.314486,53.498167],"type":"Point"},"properties":{"osm_id":"4200087015","tag":{"amenity":"waste_basket"}},"type":"Feature"},
	{"geometry":{"coordinates":[-2.314958,53.49887],"type":"Point"},"properties":{"osm_id":"4200099513","tag":{"amenity":"waste_basket"}},"type":"Feature"},
	{"geometry":{"coordinates":[-2.315389,53.497466],"type":"Point"},"properties":{"osm_id":"4200099519","tag":{"amenity":"waste_basket"}},"type":"Feature"},
	{"geometry":{"coordinates":[-2.313848,53.497534],"type":"Point"},"properties":{"osm_id":"4200099524","tag":{"amenity":"waste_basket"}},"type":"Feature"},
	{"geometry":{"coordinates":[-2.312807,53.498321],"type":"Point"},"properties":{"osm_id":"4200099617","tag":{"amenity":"waste_basket"}},"type":"Feature"},
	{"geometry":{"coordinates":[-2.313435,53.498477],"type":"Point"},"properties":{"osm_id":"4200099620","tag":{"amenity":"waste_basket"}},"type":"Feature"},
	{"geometry":{"coordinates":[-2.312547,53.497538],"type":"Point"},"properties":{"osm_id":"4212103490","tag":{"amenity":"waste_basket"}},"type":"Feature"},
	{"geometry":{"coordinates":[-2.288112,53.537429],"type":"Point"},"properties":{"osm_id":"4726188023","tag":{"amenity":"waste_basket"}},"type":"Feature"},
	{"geometry":{"coordinates":[-2.367249,53.536834],"type":"Point"},"properties":{"osm_id":"5598821390","tag":{"amenity":"waste_basket"}},"type":"Feature"},
	{"geometry":{"coordinates":[-2.289281,53.490257],"type":"Point"},"properties":{"osm_id":"7603727869","tag":{"amenity":"recycling","recycling:clothes":"yes","recycling:shoes":"yes","recycling_type":"container"}},"type":"Feature"}
]
}
