{
"type": "FeatureCollection",
"features": [
	{"geometry":{"coordinates":[-2.353523,47.345631],"type":"Point"},"properties":{"osm_id":"4885611249","tag":{"amenity":"recycling","location":"overground","recycling_type":"container"}},"type":"Feature"},
	{"geometry":{"coordinates":[-2.320839,47.347621],"type":"Point"},"properties":{"osm_id":"8602898636","tag":{"amenity":"waste_basket"}},"type":"Feature"}
]
}
