{
"type": "FeatureCollection",
"features": [
	{"geometry":{"coordinates":[-2.353523,47.345631],"type":"Point"},"properties":{"osm_id":"4885611249","tag":{"amenity":"recycling","location":"overground","recycling_type":"container"}},"type":"Feature"},
	{"geometry":{"coordinates":[-2.320839,47.347621],"type":"Point"},"properties":{"osm_id":"8602898636","tag":{"amenity":"waste_basket"}},"type":"Feature"},
	{"geometry":{"coordinates":[-2.350476,47.363306],"type":"Point"},"properties":{"osm_id":"8963314753","tag":{"amenity":"waste_basket","waste":"trash"}},"type":"Feature"},
	{"geometry":{"coordinates":[-2.350636,47.363244],"type":"Point"},"properties":{"osm_id":"8963314754","tag":{"amenity":"recycling","opening_hours":"24/7","recycling:glass":"yes","recycling:glass_bottles":"yes","recycling_type":"container","wheelchair":"yes"}},"type":"Feature"},
	{"geometry":{"coordinates":[-2.3505,47.363288],"type":"Point"},"properties":{"osm_id":"8963314755","tag":{"amenity":"recycling","opening_hours":"24/7","recycling:PET":"yes","recycling:cardboard":"yes","recycling:paper":"yes","recycling:plastic":"yes","recycling:plastic_bottles":"yes","recycling:plastic_packaging":"yes","recycling_type":"container","wheelchair":"yes"}},"type":"Feature"},
	{"geometry":{"coordinates":[-2.296138,47.389624],"type":"Point"},"properties":{"osm_id":"9054731415","tag":{"amenity":"recycling","recycling:glass_bottles":"yes","recycling_type":"container"}},"type":"Feature"},
	{"geometry":{"coordinates":[-2.296154,47.389613],"type":"Point"},"properties":{"osm_id":"9054734220","tag":{"amenity":"waste_disposal","waste":"household"}},"type":"Feature"},
	{"geometry":{"coordinates":[-2.29616,47.389606],"type":"Point"},"properties":{"osm_id":"9054734221","tag":{"amenity":"waste_disposal","waste":"household"}},"type":"Feature"},
	{"geometry":{"coordinates":[-2.296137,47.389608],"type":"Point"},"properties":{"osm_id":"9054734222","tag":{"amenity":"waste_disposal","waste":"recycling"}},"type":"Feature"},
	{"geometry":{"coordinates":[-2.29614,47.389602],"type":"Point"},"properties":{"osm_id":"9054734223","tag":{"amenity":"waste_disposal","waste":"recycling"}},"type":"Feature"}
]
}
