{
"type": "FeatureCollection",
"features": [
	{"geometry":{"coordinates":[-2.353307,42.432338],"type":"Point"},"properties":{"name":"Ecoparque","osm_id":"644924383","tag":{"amenity":"recycling"}},"type":"Feature"}
]
}
