{
"type": "FeatureCollection",
"features": [
	{"geometry":{"coordinates":[-2.54476,53.395935],"type":"Point"},"properties":{"osm_id":"626789855","tag":{"amenity":"recycling"}},"type":"Feature"},
	{"geometry":{"coordinates":[-2.515063,53.398662],"type":"Point"},"properties":{"highway":"bus_stop","osm_id":"1008806572","tag":{"amenity":"waste_basket","layby":"yes","shelter":"no"}},"type":"Feature"},
	{"geometry":{"coordinates":[-2.51482,53.418098],"type":"Point"},"properties":{"osm_id":"1341350999","tag":{"amenity":"recycling","location":"overground","recycling_type":"container"}},"type":"Feature"},
	{"geometry":{"coordinates":[-2.523797,53.425457],"type":"Point"},"properties":{"osm_id":"7277639875","tag":{"amenity":"waste_basket"}},"type":"Feature"},
	{"geometry":{"coordinates":[-2.52316,53.424954],"type":"Point"},"properties":{"osm_id":"7606784525","tag":{"amenity":"waste_basket","waste":"trash"}},"type":"Feature"},
	{"geometry":{"coordinates":[-2.523425,53.425263],"type":"Point"},"properties":{"osm_id":"7606807910","tag":{"amenity":"waste_basket","waste":"trash"}},"type":"Feature"}
]
}
