{
"type": "FeatureCollection",
"lastupdate": "2020-08-04T00:00:00Z",
"features": [
	{"geometry":{"coordinates":[-2.544759,53.395935],"type":"Point"},"properties":{"osm_id":"626789855","tag":{"amenity":"recycling"}},"type":"Feature"},
	{"geometry":{"coordinates":[-2.515062,53.398661],"type":"Point"},"properties":{"highway":"bus_stop","osm_id":"1008806572","tag":{"amenity":"waste_basket","layby":"yes","shelter":"no"}},"type":"Feature"},
	{"geometry":{"coordinates":[-2.514819,53.418097],"type":"Point"},"properties":{"osm_id":"1341350999","tag":{"amenity":"recycling","location":"overground","recycling_type":"container"}},"type":"Feature"},
	{"geometry":{"coordinates":[-2.523796,53.425456],"type":"Point"},"properties":{"osm_id":"7277639875","tag":{"amenity":"waste_basket"}},"type":"Feature"},
	{"geometry":{"coordinates":[-2.52316,53.424953],"type":"Point"},"properties":{"osm_id":"7606784525","tag":{"amenity":"waste_basket","waste":"trash"}},"type":"Feature"},
	{"geometry":{"coordinates":[-2.523424,53.425262],"type":"Point"},"properties":{"osm_id":"7606807910","tag":{"amenity":"waste_basket","waste":"trash"}},"type":"Feature"}
]
}
