{
"type": "FeatureCollection",
"features": [
	{"geometry":{"coordinates":[-54.992456,-27.477634],"type":"Point"},"properties":{"name":"Grapia Milenaria","osm_id":"2002896540","tag":{"denotation":"natural_monument","natural":"tree"}},"type":"Feature"}
]
}
