{
"type": "FeatureCollection",
"features": [
	{"geometry":{"coordinates":[-37.61967,-7.923135],"type":"Point"},"properties":{"osm_id":"5361107617","tag":{"natural":"tree"}},"type":"Feature"},
	{"geometry":{"coordinates":[-37.619175,-7.923422],"type":"Point"},"properties":{"osm_id":"5361107618","tag":{"natural":"tree"}},"type":"Feature"},
	{"geometry":{"coordinates":[-37.619161,-7.923543],"type":"Point"},"properties":{"osm_id":"5361107619","tag":{"natural":"tree"}},"type":"Feature"},
	{"geometry":{"coordinates":[-37.619225,-7.923672],"type":"Point"},"properties":{"osm_id":"5361107620","tag":{"natural":"tree"}},"type":"Feature"},
	{"geometry":{"coordinates":[-37.619202,-7.923806],"type":"Point"},"properties":{"osm_id":"5361112521","tag":{"natural":"tree"}},"type":"Feature"},
	{"geometry":{"coordinates":[-37.61943,-7.922989],"type":"Point"},"properties":{"osm_id":"5361112522","tag":{"natural":"tree"}},"type":"Feature"},
	{"geometry":{"coordinates":[-37.619075,-7.92294],"type":"Point"},"properties":{"osm_id":"5361112523","tag":{"natural":"tree"}},"type":"Feature"},
	{"geometry":{"coordinates":[-37.619756,-7.92331],"type":"Point"},"properties":{"osm_id":"5361112524","tag":{"natural":"tree"}},"type":"Feature"},
	{"geometry":{"coordinates":[-37.619651,-7.923214],"type":"Point"},"properties":{"osm_id":"5361112525","tag":{"natural":"tree"}},"type":"Feature"},
	{"geometry":{"coordinates":[-37.619114,-7.923145],"type":"Point"},"properties":{"osm_id":"5361112526","tag":{"natural":"tree"}},"type":"Feature"},
	{"geometry":{"coordinates":[-37.619175,-7.923277],"type":"Point"},"properties":{"osm_id":"5361112527","tag":{"natural":"tree"}},"type":"Feature"},
	{"geometry":{"coordinates":[-37.61925,-7.923159],"type":"Point"},"properties":{"osm_id":"5361112528","tag":{"natural":"tree"}},"type":"Feature"},
	{"geometry":{"coordinates":[-37.61923,-7.923209],"type":"Point"},"properties":{"osm_id":"5361112529","tag":{"natural":"tree"}},"type":"Feature"},
	{"geometry":{"coordinates":[-37.62,-7.923804],"type":"Point"},"properties":{"osm_id":"5361112530","tag":{"natural":"tree"}},"type":"Feature"},
	{"geometry":{"coordinates":[-37.619629,-7.923348],"type":"Point"},"properties":{"osm_id":"5361112531","tag":{"natural":"tree"}},"type":"Feature"},
	{"geometry":{"coordinates":[-37.61959,-7.923066],"type":"Point"},"properties":{"osm_id":"5361112532","tag":{"natural":"tree"}},"type":"Feature"},
	{"geometry":{"coordinates":[-37.619308,-7.922937],"type":"Point"},"properties":{"name":"Umbuzeiro","osm_id":"5361112533","tag":{"natural":"tree"}},"type":"Feature"},
	{"geometry":{"coordinates":[-37.619189,-7.922855],"type":"Point"},"properties":{"osm_id":"5361115507","tag":{"natural":"tree"}},"type":"Feature"},
	{"geometry":{"coordinates":[-37.619194,-7.92294],"type":"Point"},"properties":{"osm_id":"5361115508","tag":{"natural":"tree"}},"type":"Feature"},
	{"geometry":{"coordinates":[-37.62044,-7.923968],"type":"Point"},"properties":{"name":"Juazeiro","osm_id":"5361115509","tag":{"natural":"tree"}},"type":"Feature"}
]
}
