{
"type": "FeatureCollection",
"features": [
	{"geometry":{"coordinates":[7.852492,52.190986],"type":"Point"},"properties":{"osm_id":"428030832","tag":{"amenity":"recycling","location":"overground","recycling_type":"container"}},"type":"Feature"},
	{"geometry":{"coordinates":[7.828906,52.208547],"type":"Point"},"properties":{"osm_id":"1586663731","tag":{"amenity":"waste_basket"}},"type":"Feature"},
	{"geometry":{"coordinates":[7.895747,52.214264],"type":"Point"},"properties":{"osm_id":"2151686865","tag":{"amenity":"recycling","recycling_type":"container"}},"type":"Feature"},
	{"geometry":{"coordinates":[7.885168,52.213922],"type":"Point"},"properties":{"osm_id":"2151686866","tag":{"amenity":"recycling","recycling_type":"container"}},"type":"Feature"},
	{"geometry":{"coordinates":[7.844083,52.180048],"type":"Point"},"properties":{"osm_id":"2433877726","tag":{"amenity":"recycling","recycling:glass_bottles":"yes","recycling:paper":"yes","recycling_type":"container"}},"type":"Feature"},
	{"geometry":{"coordinates":[7.865126,52.183287],"type":"Point"},"properties":{"osm_id":"2433882794","tag":{"amenity":"recycling","recycling:clothes":"yes","recycling:glass_bottles":"yes","recycling_type":"container"}},"type":"Feature"},
	{"geometry":{"coordinates":[7.854515,52.188981],"type":"Point"},"properties":{"osm_id":"3431336486","tag":{"amenity":"recycling","recycling_type":"container"}},"type":"Feature"},
	{"geometry":{"coordinates":[7.902193,52.165256],"type":"Point"},"properties":{"osm_id":"4587329592","tag":{"amenity":"waste_basket"}},"type":"Feature"},
	{"geometry":{"coordinates":[7.851616,52.176375],"type":"Point"},"properties":{"name":"Glascontainer","osm_id":"4961594745","tag":{"amenity":"recycling","recycling:glass":"yes","recycling_type":"container"}},"type":"Feature"},
	{"geometry":{"coordinates":[7.869389,52.193499],"type":"Point"},"properties":{"osm_id":"7562961467","tag":{"amenity":"waste_basket","waste":"trash"}},"type":"Feature"},
	{"geometry":{"coordinates":[7.862358,52.190173],"type":"Point"},"properties":{"osm_id":"7563291265","tag":{"amenity":"recycling","recycling:clothes":"yes","recycling:glass_bottles":"yes","recycling_type":"container"}},"type":"Feature"},
	{"geometry":{"coordinates":[7.868341,52.182935],"type":"Point"},"properties":{"osm_id":"7563405749","tag":{"amenity":"recycling","recycling:clothes":"yes","recycling_type":"container"}},"type":"Feature"},
	{"geometry":{"coordinates":[7.85458,52.189041],"type":"Point"},"properties":{"name":"Glascontainer","osm_id":"7952119285","tag":{"amenity":"recycling","name:en":"Waste glass container","recycling_type":"container"}},"type":"Feature"}
]
}
