{
"type": "FeatureCollection",
"features": [
	{"geometry":{"coordinates":[7.852491,52.190986],"type":"Point"},"properties":{"osm_id":"428030832","tag":{"amenity":"recycling","location":"overground","recycling_type":"container"}},"type":"Feature"},
	{"geometry":{"coordinates":[7.828906,52.208547],"type":"Point"},"properties":{"osm_id":"1586663731","tag":{"amenity":"waste_basket"}},"type":"Feature"},
	{"geometry":{"coordinates":[7.895747,52.214264],"type":"Point"},"properties":{"osm_id":"2151686865","tag":{"amenity":"recycling","recycling_type":"container"}},"type":"Feature"},
	{"geometry":{"coordinates":[7.885168,52.213922],"type":"Point"},"properties":{"osm_id":"2151686866","tag":{"amenity":"recycling","recycling_type":"container"}},"type":"Feature"},
	{"geometry":{"coordinates":[7.844082,52.180048],"type":"Point"},"properties":{"osm_id":"2433877726","tag":{"amenity":"recycling","recycling:glass_bottles":"yes","recycling:paper":"yes","recycling_type":"container"}},"type":"Feature"},
	{"geometry":{"coordinates":[7.865125,52.183286],"type":"Point"},"properties":{"osm_id":"2433882794","tag":{"amenity":"recycling","recycling:clothes":"yes","recycling:glass_bottles":"yes","recycling_type":"container"}},"type":"Feature"},
	{"geometry":{"coordinates":[7.854514,52.188981],"type":"Point"},"properties":{"osm_id":"3431336486","tag":{"amenity":"recycling","recycling_type":"container"}},"type":"Feature"},
	{"geometry":{"coordinates":[7.902193,52.165255],"type":"Point"},"properties":{"osm_id":"4587329592","tag":{"amenity":"waste_basket"}},"type":"Feature"},
	{"geometry":{"coordinates":[7.851616,52.176374],"type":"Point"},"properties":{"name":"Glascontainer","osm_id":"4961594745","tag":{"amenity":"recycling","recycling:glass":"yes","recycling_type":"container"}},"type":"Feature"},
	{"geometry":{"coordinates":[7.869389,52.193498],"type":"Point"},"properties":{"osm_id":"7562961467","tag":{"amenity":"waste_basket","waste":"trash"}},"type":"Feature"},
	{"geometry":{"coordinates":[7.862357,52.190173],"type":"Point"},"properties":{"osm_id":"7563291265","tag":{"amenity":"recycling","recycling:clothes":"yes","recycling:glass_bottles":"yes","recycling_type":"container"}},"type":"Feature"},
	{"geometry":{"coordinates":[7.868341,52.182934],"type":"Point"},"properties":{"osm_id":"7563405749","tag":{"amenity":"recycling","recycling:clothes":"yes","recycling_type":"container"}},"type":"Feature"},
	{"geometry":{"coordinates":[7.85458,52.18904],"type":"Point"},"properties":{"name":"Glascontainer","osm_id":"7952119285","tag":{"amenity":"recycling","name:en":"Waste glass container","recycling_type":"container"}},"type":"Feature"},
	{"geometry":{"coordinates":[7.830009,52.171379],"type":"Point"},"properties":{"osm_id":"8209217169","tag":{"amenity":"recycling","recycling:glass_bottles":"yes","recycling_type":"container"}},"type":"Feature"},
	{"geometry":{"coordinates":[7.877832,52.175505],"type":"Point"},"properties":{"osm_id":"8676808927","tag":{"amenity":"recycling","recycling:clothes":"yes","recycling_type":"container"}},"type":"Feature"},
	{"geometry":{"coordinates":[7.881521,52.17549],"type":"Point"},"properties":{"osm_id":"8676808933","tag":{"amenity":"recycling","recycling:glass_bottles":"yes","recycling_type":"container"}},"type":"Feature"},
	{"geometry":{"coordinates":[7.86429,52.185942],"type":"Point"},"properties":{"osm_id":"8680917893","tag":{"amenity":"waste_basket","waste":"trash"}},"type":"Feature"},
	{"geometry":{"coordinates":[7.850558,52.194287],"type":"Point"},"properties":{"osm_id":"8680917897","tag":{"amenity":"waste_basket","waste":"trash"}},"type":"Feature"},
	{"geometry":{"coordinates":[7.891233,52.214289],"type":"Point"},"properties":{"osm_id":"9036331970","tag":{"amenity":"recycling","recycling_type":"container"}},"type":"Feature"}
]
}
