{
"type": "FeatureCollection",
"lastupdate": "2020-08-04T00:00:00Z",
"features": [
	{"geometry":{"coordinates":[7.852491,52.190986],"type":"Point"},"properties":{"osm_id":"428030832","tag":{"amenity":"recycling"}},"type":"Feature"},
	{"geometry":{"coordinates":[7.828906,52.208547],"type":"Point"},"properties":{"osm_id":"1586663731","tag":{"amenity":"waste_basket"}},"type":"Feature"},
	{"geometry":{"coordinates":[7.895747,52.214264],"type":"Point"},"properties":{"osm_id":"2151686865","tag":{"amenity":"recycling","recycling_type":"container"}},"type":"Feature"},
	{"geometry":{"coordinates":[7.885168,52.213922],"type":"Point"},"properties":{"osm_id":"2151686866","tag":{"amenity":"recycling","recycling_type":"container"}},"type":"Feature"},
	{"geometry":{"coordinates":[7.844082,52.180048],"type":"Point"},"properties":{"osm_id":"2433877726","tag":{"amenity":"recycling","recycling:glass_bottles":"yes","recycling:paper":"yes","recycling_type":"container"}},"type":"Feature"},
	{"geometry":{"coordinates":[7.865125,52.183286],"type":"Point"},"properties":{"osm_id":"2433882794","tag":{"amenity":"recycling","recycling:clothes":"yes","recycling:glass_bottles":"yes","recycling_type":"container"}},"type":"Feature"},
	{"geometry":{"coordinates":[7.854514,52.188981],"type":"Point"},"properties":{"osm_id":"3431336486","tag":{"amenity":"recycling","recycling_type":"container"}},"type":"Feature"},
	{"geometry":{"coordinates":[7.902193,52.165255],"type":"Point"},"properties":{"osm_id":"4587329592","tag":{"amenity":"waste_basket"}},"type":"Feature"},
	{"geometry":{"coordinates":[7.851616,52.176374],"type":"Point"},"properties":{"name":"Glascontainer","osm_id":"4961594745","tag":{"amenity":"recycling","recycling:glass":"yes","recycling_type":"container"}},"type":"Feature"},
	{"geometry":{"coordinates":[7.869389,52.193498],"type":"Point"},"properties":{"osm_id":"7562961467","tag":{"amenity":"waste_basket","waste":"trash"}},"type":"Feature"},
	{"geometry":{"coordinates":[7.862357,52.190173],"type":"Point"},"properties":{"osm_id":"7563291265","tag":{"amenity":"recycling","recycling:clothes":"yes","recycling:glass_bottles":"yes","recycling_type":"container"}},"type":"Feature"},
	{"geometry":{"coordinates":[7.868341,52.182934],"type":"Point"},"properties":{"osm_id":"7563405749","tag":{"amenity":"recycling","recycling:clothes":"yes","recycling_type":"container"}},"type":"Feature"}
]
}
