{
"type": "FeatureCollection",
"features": [
	{"geometry":{"coordinates":[7.843153,52.055379],"type":"Point"},"properties":{"osm_id":"3726070859","tag":{"amenity":"recycling","operator":"Kolpingsfamilie Ostbevern e. V.","recycling:clothes":"yes","recycling_type":"container","website":"www.kolping-ostbevern.de"}},"type":"Feature"}
]
}
