{
"type": "FeatureCollection",
"features": [
	{"geometry":{"coordinates":[7.90956,51.465614],"type":"Point"},"properties":{"osm_id":"301999592","tag":{"amenity":"recycling","recycling:glass":"yes"}},"type":"Feature"},
	{"geometry":{"coordinates":[7.906528,51.464321],"type":"Point"},"properties":{"osm_id":"302021367","tag":{"amenity":"recycling","recycling:glass":"yes"}},"type":"Feature"},
	{"geometry":{"coordinates":[7.895367,51.467672],"type":"Point"},"properties":{"osm_id":"302088988","tag":{"amenity":"recycling","recycling:glass":"yes"}},"type":"Feature"},
	{"geometry":{"coordinates":[7.863225,51.500186],"type":"Point"},"properties":{"name":"Bauhof der Gemeinde Wickede","osm_id":"395535961","tag":{"amenity":"recycling","opening_hours":"Mo-Fr 07:00-12:00, Mo-We 12:30-16:00, Th 12:30-15:30","recycling_type":"centre"}},"type":"Feature"},
	{"geometry":{"coordinates":[7.872602,51.498672],"type":"Point"},"properties":{"osm_id":"435760455","tag":{"amenity":"recycling"}},"type":"Feature"},
	{"geometry":{"coordinates":[7.859014,51.499897],"type":"Point"},"properties":{"osm_id":"436177986","tag":{"amenity":"recycling"}},"type":"Feature"},
	{"geometry":{"coordinates":[7.878044,51.502947],"type":"Point"},"properties":{"osm_id":"436179367","tag":{"amenity":"recycling"}},"type":"Feature"},
	{"geometry":{"coordinates":[7.867595,51.493837],"type":"Point"},"properties":{"osm_id":"700174975","tag":{"amenity":"recycling"}},"type":"Feature"},
	{"geometry":{"coordinates":[7.89927,51.455386],"type":"Point"},"properties":{"osm_id":"3812949980","tag":{"amenity":"waste_basket"}},"type":"Feature"},
	{"geometry":{"coordinates":[7.900357,51.483694],"type":"Point"},"properties":{"osm_id":"6573271312","tag":{"amenity":"waste_basket"}},"type":"Feature"},
	{"geometry":{"coordinates":[7.881654,51.45793],"type":"Point"},"properties":{"osm_id":"7552179232","tag":{"amenity":"waste_basket","waste":"trash"}},"type":"Feature"},
	{"geometry":{"coordinates":[7.894919,51.458688],"type":"Point"},"properties":{"osm_id":"7552179238","tag":{"amenity":"waste_basket","waste":"trash"}},"type":"Feature"},
	{"geometry":{"coordinates":[7.888063,51.457074],"type":"Point"},"properties":{"osm_id":"7552179243","tag":{"amenity":"waste_basket","waste":"trash"}},"type":"Feature"},
	{"geometry":{"coordinates":[7.899209,51.454861],"type":"Point"},"properties":{"osm_id":"7780668676","tag":{"amenity":"waste_basket"}},"type":"Feature"},
	{"geometry":{"coordinates":[7.881464,51.45569],"type":"Point"},"properties":{"osm_id":"7781054440","tag":{"amenity":"waste_basket"}},"type":"Feature"}
]
}
