{
"type": "FeatureCollection",
"lastupdate": "2020-08-05T00:00:00Z",
"features": [
	{"geometry":{"coordinates":[7.8913,47.306057],"type":"Point"},"properties":{"name":"Sammelstelle Gemeindehaus","osm_id":"1630433627","tag":{"amenity":"recycling"}},"type":"Feature"},
	{"geometry":{"coordinates":[7.910146,47.318595],"type":"Point"},"properties":{"name":"Altglassammelstelle","osm_id":"2082136153","tag":{"amenity":"recycling"}},"type":"Feature"},
	{"geometry":{"coordinates":[7.841616,47.33475],"type":"Point"},"properties":{"osm_id":"5417888787","tag":{"amenity":"recycling","opening_hours":"24/7","recycling:clothes":"yes","recycling:shoes":"yes","recycling_type":"container"}},"type":"Feature"},
	{"geometry":{"coordinates":[7.84128,47.334915],"type":"Point"},"properties":{"osm_id":"5417891747","tag":{"amenity":"recycling","location":"underground","opening_hours":"07:00-22:00; PH off","recycling:cans":"yes","recycling:glass":"yes","recycling_type":"container"}},"type":"Feature"},
	{"geometry":{"coordinates":[7.844969,47.330687],"type":"Point"},"properties":{"osm_id":"6137468225","tag":{"amenity":"recycling","recycling:clothes":"yes","recycling_type":"container"}},"type":"Feature"},
	{"geometry":{"coordinates":[7.900823,47.319309],"type":"Point"},"properties":{"osm_id":"6877992447","tag":{"amenity":"recycling","recycling:glass":"yes","recycling_type":"container"}},"type":"Feature"},
	{"geometry":{"coordinates":[7.877544,47.302365],"type":"Point"},"properties":{"osm_id":"7628312335","tag":{"amenity":"recycling","recycling:cans":"yes","recycling:clothes":"yes","recycling:glass_bottles":"yes","recycling_type":"container"}},"type":"Feature"}
]
}
