{
"type": "FeatureCollection",
"features": [
	{"geometry":{"coordinates":[13.690157,54.295512],"type":"Point"},"properties":{"osm_id":"849342502","tag":{"amenity":"recycling","recycling_type":"container"}},"type":"Feature"},
	{"geometry":{"coordinates":[13.707735,54.270186],"type":"Point"},"properties":{"osm_id":"1333823145","tag":{"amenity":"waste_basket"}},"type":"Feature"},
	{"geometry":{"coordinates":[13.706808,54.271087],"type":"Point"},"properties":{"osm_id":"1333823172","tag":{"amenity":"waste_basket"}},"type":"Feature"},
	{"geometry":{"coordinates":[13.705975,54.271962],"type":"Point"},"properties":{"osm_id":"1333823174","tag":{"amenity":"waste_basket"}},"type":"Feature"},
	{"geometry":{"coordinates":[13.710787,54.270829],"type":"Point"},"properties":{"osm_id":"1333854994","tag":{"amenity":"waste_basket"}},"type":"Feature"},
	{"geometry":{"coordinates":[13.709467,54.2698],"type":"Point"},"properties":{"osm_id":"1333855030","tag":{"amenity":"waste_basket"}},"type":"Feature"},
	{"geometry":{"coordinates":[13.710149,54.270334],"type":"Point"},"properties":{"osm_id":"1333855033","tag":{"amenity":"waste_basket"}},"type":"Feature"},
	{"geometry":{"coordinates":[13.693981,54.280919],"type":"Point"},"properties":{"osm_id":"1333888338","tag":{"amenity":"recycling","recycling:glass":"yes","recycling:paper":"no","recycling_type":"container"}},"type":"Feature"},
	{"geometry":{"coordinates":[13.707004,54.271864],"type":"Point"},"properties":{"osm_id":"1333959815","tag":{"amenity":"recycling","location":"overground","recycling:glass":"yes","recycling_type":"container"}},"type":"Feature"},
	{"geometry":{"coordinates":[13.694028,54.281273],"type":"Point"},"properties":{"osm_id":"2409898106","tag":{"amenity":"waste_basket"}},"type":"Feature"},
	{"geometry":{"coordinates":[13.707581,54.272484],"type":"Point"},"properties":{"osm_id":"6177173767","tag":{"amenity":"waste_basket","waste":"trash"}},"type":"Feature"},
	{"geometry":{"coordinates":[13.70681,54.273509],"type":"Point"},"properties":{"osm_id":"6177173768","tag":{"amenity":"waste_basket","waste":"trash"}},"type":"Feature"},
	{"geometry":{"coordinates":[13.694309,54.281098],"type":"Point"},"properties":{"osm_id":"6284918947","tag":{"amenity":"waste_basket","waste":"trash"}},"type":"Feature"},
	{"geometry":{"coordinates":[13.69376,54.281212],"type":"Point"},"properties":{"osm_id":"6284933103","tag":{"amenity":"waste_basket","waste":"trash"}},"type":"Feature"},
	{"geometry":{"coordinates":[13.664525,54.304502],"type":"Point"},"properties":{"osm_id":"7717136859","tag":{"amenity":"waste_basket"}},"type":"Feature"},
	{"geometry":{"coordinates":[13.693278,54.297125],"type":"Point"},"properties":{"osm_id":"7880506204","tag":{"amenity":"waste_basket"}},"type":"Feature"},
	{"geometry":{"coordinates":[13.683847,54.308766],"type":"Point"},"properties":{"osm_id":"7880531887","tag":{"amenity":"waste_basket"}},"type":"Feature"},
	{"geometry":{"coordinates":[13.681161,54.310976],"type":"Point"},"properties":{"osm_id":"7880532485","tag":{"amenity":"waste_disposal"}},"type":"Feature"}
]
}
