{
"type": "FeatureCollection",
"features": [
	{"geometry":{"coordinates":[13.630357,52.763446],"type":"Point"},"properties":{"osm_id":"2525412776","tag":{"amenity":"recycling","location":"overground","recycling:glass_bottles":"yes","recycling_type":"container"}},"type":"Feature"},
	{"geometry":{"coordinates":[13.644602,52.767444],"type":"Point"},"properties":{"osm_id":"3024294948","tag":{"amenity":"recycling","recycling:glass":"yes","recycling_type":"container"}},"type":"Feature"},
	{"geometry":{"coordinates":[13.694299,52.774741],"type":"Point"},"properties":{"osm_id":"8871269295","tag":{"amenity":"waste_basket","waste":"dog_excrement;trash"}},"type":"Feature"},
	{"geometry":{"coordinates":[13.694092,52.774556],"type":"Point"},"properties":{"osm_id":"8871269296","tag":{"amenity":"waste_basket","waste":"dog_excrement;trash"}},"type":"Feature"},
	{"geometry":{"coordinates":[13.693966,52.774655],"type":"Point"},"properties":{"osm_id":"8871269298","tag":{"amenity":"waste_basket","waste":"dog_excrement;trash"}},"type":"Feature"},
	{"geometry":{"coordinates":[13.694236,52.774936],"type":"Point"},"properties":{"osm_id":"8871269300","tag":{"amenity":"waste_basket","waste":"dog_excrement;trash"}},"type":"Feature"},
	{"geometry":{"coordinates":[13.694626,52.77503],"type":"Point"},"properties":{"osm_id":"8871335672","tag":{"amenity":"waste_basket","waste":"dog_excrement;trash"}},"type":"Feature"}
]
}
