{
"type": "FeatureCollection",
"features": [
	{"geometry":{"coordinates":[13.630357,52.763446],"type":"Point"},"properties":{"osm_id":"2525412776","tag":{"amenity":"recycling","location":"overground","recycling:clothes":"yes","recycling:glass":"yes","recycling:paper":"yes","recycling_type":"container"}},"type":"Feature"},
	{"geometry":{"coordinates":[13.644602,52.767444],"type":"Point"},"properties":{"osm_id":"3024294948","tag":{"amenity":"recycling","recycling:glass":"yes","recycling_type":"container"}},"type":"Feature"}
]
}
