{
"type": "FeatureCollection",
"features": [
	{"geometry":{"coordinates":[14.583598,56.762876],"type":"Point"},"properties":{"osm_id":"2921753009","tag":{"name:botanical":"Quercus","natural":"tree","type":"broad_leaved"}},"type":"Feature"}
]
}
