{
"type": "FeatureCollection",
"features": [
	{"geometry":{"coordinates":[14.583597,56.762875],"type":"Point"},"properties":{"osm_id":"2921753009","tag":{"name:botanical":"Quercus","natural":"tree","type":"broad_leaved"}},"type":"Feature"}
]
}
