{
"type": "FeatureCollection",
"features": [
	{"geometry":{"coordinates":[14.583597,56.762875],"type":"Point"},"properties":{"osm_id":"2921753009","tag":{"leaf_type":"broadleaved","name:botanical":"Quercus","natural":"tree"}},"type":"Feature"}
]
}
