{
"type": "FeatureCollection",
"features": [
	{"geometry":{"coordinates":[14.517363,37.903322],"type":"Point"},"properties":{"osm_id":"8093543224","tag":{"natural":"wood"}},"type":"Feature"},
	{"geometry":{"coordinates":[14.517363,37.903322],"type":"Point"},"properties":{"osm_id":"8093543224","tag":{"denomination":"Quercia Gigante","denotation":"natural_monument","diameter":"80 cm","height":"12","leaf_cycle":"deciduous","leaf_type":"broadleaved","natural":"tree"}},"type":"Feature"}
]
}
