{
"type": "FeatureCollection",
"lastupdate": "2020-08-03T00:00:00Z",
"features": [
	{"geometry":{"coordinates":[13.944381,56.834529],"type":"Point"},"properties":{"name":"ICA Maxi","osm_id":"593984043","tag":{"amenity":"recycling","opening_hours":"Mo-Su 08:00-22:00","payment:cash":"yes","recycling:batteries":"no","recycling:books":"no","recycling:cans":"yes","recycling:cardboard":"yes","recycling:cartons":"yes","recycling:clothes":"yes","recycling:electrical_appliances":"no","recycling:glass":"no","recycling:glass_bottles":"yes","recycling:green_waste":"no","recycling:magazines":"yes","recycling:newspaper":"yes","recycling:paper":"yes","recycling:paper_packaging":"yes","recycling:plastic":"yes","recycling:plastic_bottles":"no","recycling:plastic_packaging":"yes","recycling:scrap_metal":"yes","recycling:small_appliances":"no","recycling:waste":"no","recycling:wood":"no","recycling_type":"container","shop":"supermarket","wheelchair":"yes"}},"type":"Feature"},
	{"geometry":{"coordinates":[13.946478,56.84135],"type":"Point"},"properties":{"osm_id":"2501503397","tag":{"amenity":"recycling","recycling:batteries":"no","recycling:books":"no","recycling:cans":"yes","recycling:cardboard":"yes","recycling:cartons":"yes","recycling:electrical_appliances":"no","recycling:glass":"yes","recycling:glass_bottles":"yes","recycling:green_waste":"no","recycling:magazines":"yes","recycling:newspaper":"yes","recycling:paper":"yes","recycling:paper_packaging":"yes","recycling:plastic":"yes","recycling:plastic_bottles":"no","recycling:plastic_packaging":"yes","recycling:scrap_metal":"yes","recycling:small_appliances":"no","recycling:waste":"no","recycling:wood":"no","recycling_type":"container"}},"type":"Feature"},
	{"geometry":{"coordinates":[13.939978,56.837312],"type":"Point"},"properties":{"osm_id":"4745806052","tag":{"amenity":"waste_basket"}},"type":"Feature"},
	{"geometry":{"coordinates":[13.947823,56.82947],"type":"Point"},"properties":{"osm_id":"6647344085","tag":{"amenity":"waste_basket","colour":"black","material":"metal"}},"type":"Feature"},
	{"geometry":{"coordinates":[13.938881,56.844484],"type":"Point"},"properties":{"osm_id":"7596336636","tag":{"amenity":"waste_basket","waste":"dog_excrement"}},"type":"Feature"},
	{"geometry":{"coordinates":[13.938344,56.846146],"type":"Point"},"properties":{"osm_id":"7596336661","tag":{"amenity":"waste_basket","waste":"dog_excrement"}},"type":"Feature"},
	{"geometry":{"coordinates":[13.947287,56.83107],"type":"Point"},"properties":{"osm_id":"7603640631","tag":{"amenity":"waste_basket","waste":"trash"}},"type":"Feature"}
]
}
