{
"type": "FeatureCollection",
"lastupdate": "2020-08-04T00:00:00Z",
"features": [
	{"geometry":{"coordinates":[13.919418,51.22219],"type":"Point"},"properties":{"osm_id":"616926347","tag":{"amenity":"recycling"}},"type":"Feature"},
	{"geometry":{"coordinates":[13.906451,51.224713],"type":"Point"},"properties":{"osm_id":"1314260880","tag":{"amenity":"recycling"}},"type":"Feature"},
	{"geometry":{"coordinates":[13.895994,51.196222],"type":"Point"},"properties":{"osm_id":"2928020443","tag":{"amenity":"recycling","location":"overground","recycling_type":"container"}},"type":"Feature"},
	{"geometry":{"coordinates":[13.938949,51.2059],"type":"Point"},"properties":{"osm_id":"3781774659","tag":{"amenity":"recycling"}},"type":"Feature"},
	{"geometry":{"coordinates":[13.971717,51.191938],"type":"Point"},"properties":{"osm_id":"3781778387","tag":{"amenity":"recycling"}},"type":"Feature"},
	{"geometry":{"coordinates":[13.894633,51.197061],"type":"Point"},"properties":{"osm_id":"4876261224","tag":{"amenity":"waste_basket"}},"type":"Feature"}
]
}
