{
"type": "FeatureCollection",
"features": [
	{"geometry":{"coordinates":[13.919419,51.22219],"type":"Point"},"properties":{"osm_id":"616926347","tag":{"amenity":"recycling"}},"type":"Feature"},
	{"geometry":{"coordinates":[13.906451,51.224714],"type":"Point"},"properties":{"osm_id":"1314260880","tag":{"amenity":"recycling"}},"type":"Feature"},
	{"geometry":{"coordinates":[13.895994,51.196222],"type":"Point"},"properties":{"osm_id":"2928020443","tag":{"amenity":"recycling","location":"overground","recycling_type":"container"}},"type":"Feature"},
	{"geometry":{"coordinates":[13.938949,51.205901],"type":"Point"},"properties":{"osm_id":"3781774659","tag":{"amenity":"recycling"}},"type":"Feature"},
	{"geometry":{"coordinates":[13.971718,51.191939],"type":"Point"},"properties":{"osm_id":"3781778387","tag":{"amenity":"recycling"}},"type":"Feature"},
	{"geometry":{"coordinates":[13.894633,51.197062],"type":"Point"},"properties":{"osm_id":"4876261224","tag":{"amenity":"waste_basket"}},"type":"Feature"}
]
}
