{
"type": "FeatureCollection",
"lastupdate": "2020-08-01T00:00:00Z",
"features": [
	{"geometry":{"coordinates":[13.937065,48.669134],"type":"Point"},"properties":{"name":"Baurestmassendeponie","osm_id":"331584402","tag":{"amenity":"recycling"}},"type":"Feature"}
]
}
