{
"type": "FeatureCollection",
"features": [
	{"geometry":{"coordinates":[3.002618,49.577629],"type":"Point"},"properties":{"osm_id":"1934364547","tag":{"amenity":"recycling","recycling:clothes":"yes","recycling:glass":"yes","recycling_type":"container"}},"type":"Feature"},
	{"geometry":{"coordinates":[3.003886,49.585569],"type":"Point"},"properties":{"osm_id":"3419528317","tag":{"amenity":"recycling","recycling_type":"container"}},"type":"Feature"},
	{"geometry":{"coordinates":[2.988523,49.563317],"type":"Point"},"properties":{"osm_id":"4583242832","tag":{"amenity":"recycling","recycling:glass":"yes","recycling_type":"container"}},"type":"Feature"},
	{"geometry":{"coordinates":[2.996451,49.554472],"type":"Point"},"properties":{"osm_id":"4585976131","tag":{"amenity":"waste_basket"}},"type":"Feature"},
	{"geometry":{"coordinates":[3.001148,49.580425],"type":"Point"},"properties":{"osm_id":"4610518174","tag":{"amenity":"waste_basket"}},"type":"Feature"},
	{"geometry":{"coordinates":[3.001304,49.586179],"type":"Point"},"properties":{"osm_id":"4661075240","tag":{"amenity":"waste_basket"}},"type":"Feature"},
	{"geometry":{"coordinates":[2.999797,49.580597],"type":"Point"},"properties":{"osm_id":"4661075254","tag":{"amenity":"waste_basket"}},"type":"Feature"},
	{"geometry":{"coordinates":[3.019926,49.576948],"type":"Point"},"properties":{"name":"Recyclerie de Noyon","osm_id":"4795088420","tag":{"amenity":"recycling","recycling_type":"centre"}},"type":"Feature"},
	{"geometry":{"coordinates":[3.056706,49.580769],"type":"Point"},"properties":{"osm_id":"5333925442","tag":{"amenity":"recycling","recycling:clothes":"yes","recycling:shoes":"yes","recycling_type":"container"}},"type":"Feature"},
	{"geometry":{"coordinates":[3.056719,49.580742],"type":"Point"},"properties":{"osm_id":"5333925443","tag":{"amenity":"recycling","recycling:glass_bottles":"yes","recycling_type":"container"}},"type":"Feature"},
	{"geometry":{"coordinates":[3.050458,49.58621],"type":"Point"},"properties":{"osm_id":"5333925686","tag":{"amenity":"waste_basket"}},"type":"Feature"}
]
}
