{
"type": "FeatureCollection",
"features": [
	{"geometry":{"coordinates":[3.002617,49.577628],"type":"Point"},"properties":{"osm_id":"1934364547","tag":{"amenity":"recycling","recycling:clothes":"yes","recycling:glass_bottles":"yes","recycling_type":"container"}},"type":"Feature"},
	{"geometry":{"coordinates":[3.003885,49.585568],"type":"Point"},"properties":{"osm_id":"3419528317","tag":{"amenity":"recycling","recycling_type":"container"}},"type":"Feature"},
	{"geometry":{"coordinates":[2.988522,49.563317],"type":"Point"},"properties":{"osm_id":"4583242832","tag":{"amenity":"recycling","recycling:glass_bottles":"yes","recycling_type":"container"}},"type":"Feature"},
	{"geometry":{"coordinates":[2.996451,49.554472],"type":"Point"},"properties":{"osm_id":"4585976131","tag":{"amenity":"waste_basket"}},"type":"Feature"},
	{"geometry":{"coordinates":[3.001147,49.580425],"type":"Point"},"properties":{"osm_id":"4610518174","tag":{"amenity":"waste_basket"}},"type":"Feature"},
	{"geometry":{"coordinates":[3.001304,49.586179],"type":"Point"},"properties":{"osm_id":"4661075240","tag":{"amenity":"waste_basket"}},"type":"Feature"},
	{"geometry":{"coordinates":[2.999796,49.580596],"type":"Point"},"properties":{"osm_id":"4661075254","tag":{"amenity":"waste_basket"}},"type":"Feature"},
	{"geometry":{"coordinates":[3.056705,49.580768],"type":"Point"},"properties":{"osm_id":"5333925442","tag":{"amenity":"recycling","recycling:clothes":"yes","recycling:shoes":"yes","recycling_type":"container"}},"type":"Feature"},
	{"geometry":{"coordinates":[3.056719,49.580741],"type":"Point"},"properties":{"osm_id":"5333925443","tag":{"amenity":"recycling","recycling:glass_bottles":"yes","recycling_type":"container"}},"type":"Feature"},
	{"geometry":{"coordinates":[3.050458,49.58621],"type":"Point"},"properties":{"osm_id":"5333925686","tag":{"amenity":"waste_basket"}},"type":"Feature"},
	{"geometry":{"coordinates":[3.00278,49.576682],"type":"Point"},"properties":{"name":"Recyclerie de Noyon","osm_id":"8218941995","tag":{"addr:city":"Noyon","addr:housenumber":"1","addr:postcode":"60400","addr:street":"Rue Marceau","amenity":"recycling","recycling_type":"centre"}},"type":"Feature"}
]
}
