{
"type": "FeatureCollection",
"lastupdate": "2020-08-03T00:00:00Z",
"features": [
	{"geometry":{"coordinates":[3.060867,45.74026],"type":"Point"},"properties":{"osm_id":"1723898774","tag":{"amenity":"recycling"}},"type":"Feature"},
	{"geometry":{"coordinates":[3.061612,45.735799],"type":"Point"},"properties":{"osm_id":"1723898785","tag":{"amenity":"recycling","recycling:glass":"yes"}},"type":"Feature"},
	{"geometry":{"coordinates":[3.067036,45.731937],"type":"Point"},"properties":{"osm_id":"1734287324","tag":{"amenity":"recycling"}},"type":"Feature"},
	{"geometry":{"coordinates":[3.045575,45.724684],"type":"Point"},"properties":{"osm_id":"2619923020","tag":{"amenity":"recycling","recycling:glass":"yes"}},"type":"Feature"},
	{"geometry":{"coordinates":[3.075204,45.745141],"type":"Point"},"properties":{"osm_id":"2685026066","tag":{"amenity":"recycling","recycling:glass":"yes"}},"type":"Feature"},
	{"geometry":{"coordinates":[3.070066,45.749231],"type":"Point"},"properties":{"osm_id":"2685026102","tag":{"amenity":"recycling","recycling:glass":"yes","recycling_type":"container"}},"type":"Feature"},
	{"geometry":{"coordinates":[3.070085,45.749237],"type":"Point"},"properties":{"osm_id":"2685026103","tag":{"amenity":"recycling","operator":"Emma\u00fcs","recycling:clothes":"yes"}},"type":"Feature"},
	{"geometry":{"coordinates":[3.017615,45.719316],"type":"Point"},"properties":{"osm_id":"3014581872","tag":{"amenity":"recycling"}},"type":"Feature"},
	{"geometry":{"coordinates":[3.012797,45.745563],"type":"Point"},"properties":{"osm_id":"3028461319","tag":{"amenity":"recycling","recycling:glass":"yes"}},"type":"Feature"},
	{"geometry":{"coordinates":[3.067067,45.766328],"type":"Point"},"properties":{"osm_id":"3273764175","tag":{"amenity":"recycling","location":"overground","recycling:glass":"yes","recycling_type":"container"}},"type":"Feature"},
	{"geometry":{"coordinates":[3.062516,45.744431],"type":"Point"},"properties":{"osm_id":"3330934023","tag":{"amenity":"recycling","recycling:glass":"yes"}},"type":"Feature"},
	{"geometry":{"coordinates":[3.062592,45.753084],"type":"Point"},"properties":{"osm_id":"3330934085","tag":{"amenity":"recycling","recycling:glass":"yes"}},"type":"Feature"},
	{"geometry":{"coordinates":[3.049217,45.763313],"type":"Point"},"properties":{"osm_id":"3475420257","tag":{"amenity":"recycling","recycling:glass":"yes"}},"type":"Feature"},
	{"geometry":{"coordinates":[3.063559,45.746873],"type":"Point"},"properties":{"osm_id":"3475531142","tag":{"amenity":"recycling","recycling:glass":"yes"}},"type":"Feature"},
	{"geometry":{"coordinates":[3.048344,45.765073],"type":"Point"},"properties":{"osm_id":"4355024661","tag":{"amenity":"recycling","recycling:glass":"yes","recycling_type":"underground"}},"type":"Feature"},
	{"geometry":{"coordinates":[3.059195,45.748433],"type":"Point"},"properties":{"osm_id":"4709063900","tag":{"amenity":"recycling","recycling:glass":"yes","recycling_type":"container"}},"type":"Feature"},
	{"geometry":{"coordinates":[3.064472,45.738893],"type":"Point"},"properties":{"osm_id":"4709076171","tag":{"amenity":"waste_basket"}},"type":"Feature"},
	{"geometry":{"coordinates":[3.067987,45.713057],"type":"Point"},"properties":{"osm_id":"5020955841","tag":{"amenity":"recycling","recycling:clothes":"yes","recycling_type":"container"}},"type":"Feature"},
	{"geometry":{"coordinates":[3.068002,45.713048],"type":"Point"},"properties":{"osm_id":"5020955842","tag":{"amenity":"recycling","recycling:glass":"yes","recycling_type":"container"}},"type":"Feature"},
	{"geometry":{"coordinates":[3.075864,45.745085],"type":"Point"},"properties":{"osm_id":"5035628527","tag":{"amenity":"waste_basket"}},"type":"Feature"}
]
}
