{
"type": "FeatureCollection",
"lastupdate": "2020-08-04T00:00:00Z",
"features": [
	{"geometry":{"coordinates":[3.043686,44.664422],"type":"Point"},"properties":{"osm_id":"1392303392","tag":{"amenity":"recycling","recycling:glass_bottles":"yes","recycling:paper":"yes","recycling:plastic":"yes","recycling_type":"container"}},"type":"Feature"},
	{"geometry":{"coordinates":[3.032365,44.693934],"type":"Point"},"properties":{"osm_id":"2026049335","tag":{"amenity":"recycling"}},"type":"Feature"},
	{"geometry":{"coordinates":[2.998575,44.687129],"type":"Point"},"properties":{"osm_id":"3648951244","tag":{"amenity":"recycling","recycling:glass_bottles":"yes","recycling:paper":"yes","recycling:plastic":"yes","recycling_type":"container"}},"type":"Feature"},
	{"geometry":{"coordinates":[3.051515,44.661926],"type":"Point"},"properties":{"osm_id":"4485053493","tag":{"addr:street":"Rue de la Dev\u00e9zette","amenity":"recycling"}},"type":"Feature"},
	{"geometry":{"coordinates":[2.998678,44.690751],"type":"Point"},"properties":{"osm_id":"6690690584","tag":{"amenity":"recycling","recycling:green_waste":"yes","recycling_type":"centre"}},"type":"Feature"},
	{"geometry":{"coordinates":[3.005246,44.69632],"type":"Point"},"properties":{"osm_id":"7576011143","tag":{"amenity":"recycling","recycling:glass_bottles":"yes","recycling_type":"container"}},"type":"Feature"}
]
}
