{
"type": "FeatureCollection",
"features": [
	{"geometry":{"coordinates":[86.214537,26.841105],"type":"Point"},"properties":{"name":"Pipal chautari","osm_id":"2820387340","tag":{"natural":"tree"}},"type":"Feature"}
]
}
