{
"type": "FeatureCollection",
"features": [
	{"geometry":{"coordinates":[8.831662,48.836011],"type":"Point"},"properties":{"osm_id":"298923169","tag":{"amenity":"recycling","recycling:clothes":"yes","recycling_type":"container"}},"type":"Feature"},
	{"geometry":{"coordinates":[8.837438,48.837386],"type":"Point"},"properties":{"osm_id":"298923170","tag":{"amenity":"recycling","recycling:clothes":"yes","recycling_type":"container"}},"type":"Feature"},
	{"geometry":{"coordinates":[8.839978,48.829113],"type":"Point"},"properties":{"name":"Wertstoffhof","osm_id":"301449636","tag":{"amenity":"recycling","recycling_type":"centre"}},"type":"Feature"},
	{"geometry":{"coordinates":[8.790487,48.822149],"type":"Point"},"properties":{"osm_id":"472806178","tag":{"amenity":"recycling"}},"type":"Feature"},
	{"geometry":{"coordinates":[8.852471,48.859906],"type":"Point"},"properties":{"osm_id":"1491209772","tag":{"amenity":"recycling","recycling:glass_bottles":"yes","recycling_type":"container"}},"type":"Feature"},
	{"geometry":{"coordinates":[8.867848,48.810509],"type":"Point"},"properties":{"osm_id":"4784537178","tag":{"amenity":"waste_basket"}},"type":"Feature"},
	{"geometry":{"coordinates":[8.875883,48.807419],"type":"Point"},"properties":{"osm_id":"4793445286","tag":{"amenity":"waste_basket"}},"type":"Feature"},
	{"geometry":{"coordinates":[8.800832,48.823484],"type":"Point"},"properties":{"osm_id":"4808046158","tag":{"amenity":"waste_basket"}},"type":"Feature"},
	{"geometry":{"coordinates":[8.801726,48.823774],"type":"Point"},"properties":{"osm_id":"4808046160","tag":{"amenity":"waste_basket"}},"type":"Feature"},
	{"geometry":{"coordinates":[8.800583,48.823978],"type":"Point"},"properties":{"osm_id":"4808046161","tag":{"amenity":"waste_basket"}},"type":"Feature"},
	{"geometry":{"coordinates":[8.829694,48.836015],"type":"Point"},"properties":{"osm_id":"5851925045","tag":{"amenity":"recycling","recycling_type":"container"}},"type":"Feature"}
]
}
