{
"type": "FeatureCollection",
"features": [
	{"geometry":{"coordinates":[-79.002387,42.920724],"type":"Point"},"properties":{"osm_id":"819597012","tag":{"addr:city":"Fort Erie","addr:housenumber":"2327","addr:street":"Lambton Road"}},"type":"Feature"},
	{"geometry":{"coordinates":[-79.000819,42.920758],"type":"Point"},"properties":{"osm_id":"819682485","tag":{"addr:city":"Fort Erie","addr:housenumber":"2271","addr:street":"Lambton Road"}},"type":"Feature"}
]
}
