{
"type": "FeatureCollection",
"lastupdate": "2020-08-02T00:00:00Z",
"features": [
	{"geometry":{"coordinates":[-78.937422,33.740319],"type":"Point"},"properties":{"name":"Boggs Recycling","osm_id":"5757108774","tag":{"amenity":"recycling","recycling_type":"centre"}},"type":"Feature"}
]
}
