{
"type": "FeatureCollection",
"features": [
	{"geometry":{"coordinates":[-78.937422,33.740319],"type":"Point"},"properties":{"name":"Boggs Recycling","osm_id":"5757108774","tag":{"addr:city":"Myrtle Beach","addr:country":"US","addr:housenumber":"440","addr:postcode":"29579","addr:state":"SC","addr:street":"Ronald McNair Boulevard","amenity":"recycling","recycling_type":"centre"}},"type":"Feature"}
]
}
