{
"type": "FeatureCollection",
"features": [
	{"geometry":{"coordinates":[-78.996702,33.786795],"type":"Point"},"properties":{"highway":"turning_circle","osm_id":"113204275"},"type":"Feature"},
	{"geometry":{"coordinates":[-78.937423,33.74032],"type":"Point"},"properties":{"name":"Boggs Recycling","osm_id":"5757108774","tag":{"amenity":"recycling","recycling_type":"centre"}},"type":"Feature"}
]
}
