{
"type": "FeatureCollection",
"features": [
	{"geometry":{"coordinates":[13.247778,51.689983],"type":"Point"},"properties":{"osm_id":"623730318","tag":{"amenity":"recycling","recycling:glass":"yes"}},"type":"Feature"},
	{"geometry":{"coordinates":[13.222624,51.694477],"type":"Point"},"properties":{"osm_id":"4689447600","tag":{"amenity":"recycling","location":"overground","recycling:glass":"yes","recycling_type":"container"}},"type":"Feature"}
]
}
