{
"type": "FeatureCollection",
"features": [
	{"geometry":{"coordinates":[13.211312,51.582975],"type":"Point"},"properties":{"osm_id":"364983181","tag":{"amenity":"recycling","recycling:cans":"no","recycling:clothes":"yes","recycling:glass":"yes","recycling:paper":"yes"}},"type":"Feature"},
	{"geometry":{"coordinates":[13.228478,51.58587],"type":"Point"},"properties":{"osm_id":"364983192","tag":{"amenity":"recycling","recycling:clothes":"yes","recycling:glass":"yes","recycling:paper":"yes","recycling_type":"container"}},"type":"Feature"},
	{"geometry":{"coordinates":[13.252293,51.572844],"type":"Point"},"properties":{"osm_id":"371184239","tag":{"amenity":"recycling","location":"overground","recycling:clothes":"yes","recycling:glass":"yes","recycling_type":"container"}},"type":"Feature"},
	{"geometry":{"coordinates":[13.227302,51.581956],"type":"Point"},"properties":{"osm_id":"395269838","tag":{"amenity":"recycling","location":"overground","recycling:glass":"yes","recycling:paper":"yes","recycling_type":"container"}},"type":"Feature"},
	{"geometry":{"coordinates":[13.243807,51.578468],"type":"Point"},"properties":{"osm_id":"495208865","tag":{"amenity":"recycling","location":"overground","recycling:clothes":"yes","recycling:glass":"yes","recycling_type":"container"}},"type":"Feature"},
	{"geometry":{"coordinates":[13.257381,51.586315],"type":"Point"},"properties":{"osm_id":"549320560","tag":{"amenity":"recycling","recycling:glass":"yes"}},"type":"Feature"},
	{"geometry":{"coordinates":[13.242819,51.589441],"type":"Point"},"properties":{"osm_id":"607511740","tag":{"amenity":"recycling","recycling:glass":"yes"}},"type":"Feature"},
	{"geometry":{"coordinates":[13.24517,51.585118],"type":"Point"},"properties":{"osm_id":"607577548","tag":{"amenity":"recycling","recycling:glass":"yes"}},"type":"Feature"},
	{"geometry":{"coordinates":[13.228819,51.56795],"type":"Point"},"properties":{"osm_id":"1196966118","tag":{"amenity":"recycling","recycling:glass":"yes","recycling_type":"container"}},"type":"Feature"},
	{"geometry":{"coordinates":[13.213928,51.578492],"type":"Point"},"properties":{"osm_id":"1204698537","tag":{"amenity":"recycling","location":"overground","recycling:glass":"yes","recycling_type":"container"}},"type":"Feature"},
	{"geometry":{"coordinates":[13.249632,51.569235],"type":"Point"},"properties":{"osm_id":"1234008225","tag":{"amenity":"recycling","recycling:glass":"yes"}},"type":"Feature"}
]
}
