{
"type": "FeatureCollection",
"features": [
	{"geometry":{"coordinates":[13.239975,50.80255],"type":"Point"},"properties":{"osm_id":"858325818","tag":{"amenity":"recycling","location":"overground","recycling_type":"container"}},"type":"Feature"},
	{"geometry":{"coordinates":[13.219736,50.830256],"type":"Point"},"properties":{"osm_id":"1946163178","tag":{"amenity":"recycling","recycling:cans":"no","recycling:clothes":"yes","recycling:glass":"yes","recycling:scrap_metal":"yes"}},"type":"Feature"},
	{"geometry":{"coordinates":[13.257013,50.816259],"type":"Point"},"properties":{"osm_id":"2015436893","tag":{"amenity":"recycling","recycling:clothes":"yes","recycling:glass":"yes"}},"type":"Feature"},
	{"geometry":{"coordinates":[13.249147,50.805741],"type":"Point"},"properties":{"osm_id":"4209636543","tag":{"amenity":"recycling","recycling:clothes":"yes","recycling:glass":"yes","recycling_type":"container"}},"type":"Feature"},
	{"geometry":{"coordinates":[13.226539,50.798709],"type":"Point"},"properties":{"osm_id":"8571986253","tag":{"amenity":"recycling","recycling:clothes":"yes","recycling_type":"container"}},"type":"Feature"}
]
}
