{
"type": "FeatureCollection",
"features": [
	{"geometry":{"coordinates":[-1.001619,54.08837],"type":"Point"},"properties":{"osm_id":"3556591448","tag":{"natural":"tree"}},"type":"Feature"},
	{"geometry":{"coordinates":[-0.998108,54.088826],"type":"Point"},"properties":{"osm_id":"3556591454","tag":{"natural":"tree"}},"type":"Feature"},
	{"geometry":{"coordinates":[-0.998784,54.088925],"type":"Point"},"properties":{"osm_id":"3556591457","tag":{"natural":"tree"}},"type":"Feature"},
	{"geometry":{"coordinates":[-1.001729,54.08837],"type":"Point"},"properties":{"osm_id":"3556591469","tag":{"natural":"tree"}},"type":"Feature"},
	{"geometry":{"coordinates":[-1.001737,54.08832],"type":"Point"},"properties":{"osm_id":"3556591474","tag":{"natural":"tree"}},"type":"Feature"},
	{"geometry":{"coordinates":[-1.002244,54.088938],"type":"Point"},"properties":{"osm_id":"3556591475","tag":{"natural":"tree"}},"type":"Feature"},
	{"geometry":{"coordinates":[-1.001638,54.088905],"type":"Point"},"properties":{"osm_id":"3556591483","tag":{"natural":"tree"}},"type":"Feature"},
	{"geometry":{"coordinates":[-1.001995,54.088856],"type":"Point"},"properties":{"osm_id":"3556591486","tag":{"natural":"tree"}},"type":"Feature"},
	{"geometry":{"coordinates":[-1.001839,54.088842],"type":"Point"},"properties":{"osm_id":"3556592098","tag":{"natural":"tree"}},"type":"Feature"},
	{"geometry":{"coordinates":[-0.998269,54.088844],"type":"Point"},"properties":{"osm_id":"3556592106","tag":{"natural":"tree"}},"type":"Feature"},
	{"geometry":{"coordinates":[-1.001869,54.088773],"type":"Point"},"properties":{"osm_id":"3556592108","tag":{"natural":"tree"}},"type":"Feature"},
	{"geometry":{"coordinates":[-0.998658,54.088899],"type":"Point"},"properties":{"osm_id":"3556592113","tag":{"natural":"tree"}},"type":"Feature"},
	{"geometry":{"coordinates":[-1.001997,54.088452],"type":"Point"},"properties":{"osm_id":"3556592117","tag":{"natural":"tree"}},"type":"Feature"},
	{"geometry":{"coordinates":[-1.002008,54.088755],"type":"Point"},"properties":{"osm_id":"3556592128","tag":{"natural":"tree"}},"type":"Feature"},
	{"geometry":{"coordinates":[-1.001756,54.088969],"type":"Point"},"properties":{"osm_id":"3556592137","tag":{"natural":"tree"}},"type":"Feature"},
	{"geometry":{"coordinates":[-0.998932,54.088962],"type":"Point"},"properties":{"osm_id":"3556592141","tag":{"natural":"tree"}},"type":"Feature"},
	{"geometry":{"coordinates":[-1.001515,54.088353],"type":"Point"},"properties":{"osm_id":"3556592146","tag":{"natural":"tree"}},"type":"Feature"},
	{"geometry":{"coordinates":[-1.001536,54.08831],"type":"Point"},"properties":{"osm_id":"3556592155","tag":{"natural":"tree"}},"type":"Feature"},
	{"geometry":{"coordinates":[-1.001394,54.088831],"type":"Point"},"properties":{"osm_id":"3556592156","tag":{"natural":"tree"}},"type":"Feature"},
	{"geometry":{"coordinates":[-1.001627,54.088321],"type":"Point"},"properties":{"osm_id":"3556592159","tag":{"natural":"tree"}},"type":"Feature"},
	{"geometry":{"coordinates":[-1.006562,54.089081],"type":"Point"},"properties":{"osm_id":"3556599805","tag":{"natural":"tree"}},"type":"Feature"},
	{"geometry":{"coordinates":[-1.01141,54.085489],"type":"Point"},"properties":{"name":"Jubilee Oak Tree","osm_id":"4960268259","tag":{"natural":"tree"}},"type":"Feature"}
]
}
