{
"type": "FeatureCollection",
"features": [
	{"geometry":{"coordinates":[-1.00162,54.088371],"type":"Point"},"properties":{"osm_id":"3556591448","tag":{"natural":"tree"}},"type":"Feature"},
	{"geometry":{"coordinates":[-0.998109,54.088827],"type":"Point"},"properties":{"osm_id":"3556591454","tag":{"natural":"tree"}},"type":"Feature"},
	{"geometry":{"coordinates":[-0.998785,54.088926],"type":"Point"},"properties":{"osm_id":"3556591457","tag":{"natural":"tree"}},"type":"Feature"},
	{"geometry":{"coordinates":[-1.00173,54.088371],"type":"Point"},"properties":{"osm_id":"3556591469","tag":{"natural":"tree"}},"type":"Feature"},
	{"geometry":{"coordinates":[-1.001738,54.08832],"type":"Point"},"properties":{"osm_id":"3556591474","tag":{"natural":"tree"}},"type":"Feature"},
	{"geometry":{"coordinates":[-1.002245,54.088939],"type":"Point"},"properties":{"osm_id":"3556591475","tag":{"natural":"tree"}},"type":"Feature"},
	{"geometry":{"coordinates":[-1.001638,54.088905],"type":"Point"},"properties":{"osm_id":"3556591483","tag":{"natural":"tree"}},"type":"Feature"},
	{"geometry":{"coordinates":[-1.001995,54.088857],"type":"Point"},"properties":{"osm_id":"3556591486","tag":{"natural":"tree"}},"type":"Feature"},
	{"geometry":{"coordinates":[-1.00184,54.088843],"type":"Point"},"properties":{"osm_id":"3556592098","tag":{"natural":"tree"}},"type":"Feature"},
	{"geometry":{"coordinates":[-0.99827,54.088844],"type":"Point"},"properties":{"osm_id":"3556592106","tag":{"natural":"tree"}},"type":"Feature"},
	{"geometry":{"coordinates":[-1.001869,54.088773],"type":"Point"},"properties":{"osm_id":"3556592108","tag":{"natural":"tree"}},"type":"Feature"},
	{"geometry":{"coordinates":[-0.998659,54.088899],"type":"Point"},"properties":{"osm_id":"3556592113","tag":{"natural":"tree"}},"type":"Feature"},
	{"geometry":{"coordinates":[-1.001998,54.088452],"type":"Point"},"properties":{"osm_id":"3556592117","tag":{"natural":"tree"}},"type":"Feature"},
	{"geometry":{"coordinates":[-1.002009,54.088756],"type":"Point"},"properties":{"osm_id":"3556592128","tag":{"natural":"tree"}},"type":"Feature"},
	{"geometry":{"coordinates":[-1.001756,54.08897],"type":"Point"},"properties":{"osm_id":"3556592137","tag":{"natural":"tree"}},"type":"Feature"},
	{"geometry":{"coordinates":[-0.998932,54.088962],"type":"Point"},"properties":{"osm_id":"3556592141","tag":{"natural":"tree"}},"type":"Feature"},
	{"geometry":{"coordinates":[-1.001515,54.088353],"type":"Point"},"properties":{"osm_id":"3556592146","tag":{"natural":"tree"}},"type":"Feature"},
	{"geometry":{"coordinates":[-1.001537,54.088311],"type":"Point"},"properties":{"osm_id":"3556592155","tag":{"natural":"tree"}},"type":"Feature"},
	{"geometry":{"coordinates":[-1.001394,54.088832],"type":"Point"},"properties":{"osm_id":"3556592156","tag":{"natural":"tree"}},"type":"Feature"},
	{"geometry":{"coordinates":[-1.001628,54.088322],"type":"Point"},"properties":{"osm_id":"3556592159","tag":{"natural":"tree"}},"type":"Feature"},
	{"geometry":{"coordinates":[-1.006563,54.089082],"type":"Point"},"properties":{"osm_id":"3556599805","tag":{"natural":"tree"}},"type":"Feature"},
	{"geometry":{"coordinates":[-1.01141,54.08549],"type":"Point"},"properties":{"name":"Jubilee Oak Tree","osm_id":"4960268259","tag":{"natural":"tree"}},"type":"Feature"}
]
}
