{
"type": "FeatureCollection",
"features": [
	{"geometry":{"coordinates":[-75.853524,43.452847],"type":"Point"},"properties":{"is_in":"Oswego,New York,N.Y.,NY,USA","name":"Maple Hill","osm_id":"158481678","place":"hamlet","tag":{"gnis:Class":"Populated Place","gnis:County":"Oswego","gnis:County_num":"075","gnis:ST_alpha":"NY","gnis:ST_num":"36","gnis:id":"972758","import_uuid":"bb7269ee-502a-5391-8056-e3ce0e66489c"}},"type":"Feature"}
]
}
