{
"type": "FeatureCollection",
"lastupdate": "2020-07-31T00:00:00Z",
"features": [
	{"geometry":{"coordinates":[10.640451,59.756216],"type":"Point"},"properties":{"name":"Teigen gjenvinningsstasjon","osm_id":"5555203053","tag":{"amenity":"recycling","phone":"+47 90 80 40","recycling:asbestos":"yes","recycling:batteries":"yes","recycling:boats":"yes","recycling:clothes":"yes","recycling:electrical_items":"yes","recycling:garden_waste":"yes","recycling:glass":"yes","recycling:glass_bottles":"yes","recycling:hazardous_waste":"yes","recycling:marine_waste":"yes","recycling:metal":"yes","recycling:paper":"yes","recycling:plasterboard":"yes","recycling:plastic":"yes","recycling:plastic_packaging":"yes","recycling:polystyrene_foam":"yes","recycling:rubble":"yes","recycling:scrap_metal":"yes","recycling:second_hand":"yes","recycling:tyres":"yes","recycling:waste":"yes","recycling:wood":"yes","recycling_type":"centre","ref:sortere":"1467","website":"https://folloren.no/"}},"type":"Feature"},
	{"geometry":{"coordinates":[10.714241,59.736507],"type":"Point"},"properties":{"osm_id":"5555204659","tag":{"amenity":"recycling","description":"Knardahl Bussholdeplass returpunkt","recycling:glass_bottles":"yes","recycling_type":"container","ref:sortere":"15051"}},"type":"Feature"},
	{"geometry":{"coordinates":[10.709553,59.750554],"type":"Point"},"properties":{"osm_id":"5555204712","tag":{"amenity":"recycling","description":"Dalbanen sommer-returpunkt","recycling:glass_bottles":"yes","recycling_type":"container","ref:sortere":"15017"}},"type":"Feature"}
]
}
