{
"type": "FeatureCollection",
"features": [
	{"geometry":{"coordinates":[10.675243,49.971077],"type":"Point"},"properties":{"name":"Recyclinghof Eltmann","osm_id":"1234818111","tag":{"amenity":"recycling","recycling:batteries":"yes","recycling:cans":"yes","recycling:clothes":"yes","recycling:glass":"yes","recycling:paper":"yes","recycling:scrap_metal":"yes"}},"type":"Feature"},
	{"geometry":{"coordinates":[10.664198,49.973428],"type":"Point"},"properties":{"osm_id":"1725331651","tag":{"amenity":"waste_basket"}},"type":"Feature"},
	{"geometry":{"coordinates":[10.665332,49.973469],"type":"Point"},"properties":{"osm_id":"1725331657","tag":{"amenity":"waste_basket"}},"type":"Feature"},
	{"geometry":{"coordinates":[10.64364,49.995931],"type":"Point"},"properties":{"osm_id":"1733598275","tag":{"amenity":"recycling","recycling:cans":"yes","recycling:glass":"yes","recycling_type":"container"}},"type":"Feature"},
	{"geometry":{"coordinates":[10.665024,49.972892],"type":"Point"},"properties":{"osm_id":"1734107786","tag":{"amenity":"recycling","recycling:glass":"yes","recycling_type":"container"}},"type":"Feature"},
	{"geometry":{"coordinates":[10.659,49.972971],"type":"Point"},"properties":{"osm_id":"2891939607","tag":{"amenity":"waste_basket"}},"type":"Feature"},
	{"geometry":{"coordinates":[10.672652,49.982607],"type":"Point"},"properties":{"osm_id":"3161226960","tag":{"amenity":"waste_basket"}},"type":"Feature"},
	{"geometry":{"coordinates":[10.676657,49.984371],"type":"Point"},"properties":{"osm_id":"3161227679","tag":{"amenity":"waste_basket"}},"type":"Feature"},
	{"geometry":{"coordinates":[10.67976,49.986041],"type":"Point"},"properties":{"osm_id":"3161227686","tag":{"amenity":"waste_basket"}},"type":"Feature"},
	{"geometry":{"coordinates":[10.677228,49.98557],"type":"Point"},"properties":{"osm_id":"3323721258","tag":{"amenity":"recycling","recycling:cans":"yes","recycling:clothes":"yes","recycling:glass_bottles":"yes","recycling_type":"container"}},"type":"Feature"},
	{"geometry":{"coordinates":[10.672522,49.987728],"type":"Point"},"properties":{"osm_id":"3323728692","tag":{"amenity":"recycling","recycling:glass_bottles":"yes","recycling_type":"container"}},"type":"Feature"},
	{"geometry":{"coordinates":[10.661269,49.972661],"type":"Point"},"properties":{"osm_id":"6949007783","tag":{"amenity":"waste_disposal"}},"type":"Feature"},
	{"geometry":{"coordinates":[10.66109,49.972664],"type":"Point"},"properties":{"osm_id":"6949043128","tag":{"amenity":"recycling","recycling_type":"container"}},"type":"Feature"},
	{"geometry":{"coordinates":[10.662821,50.00582],"type":"Point"},"properties":{"osm_id":"8714982663","tag":{"amenity":"waste_basket","material":"wood","waste":"plastic"}},"type":"Feature"},
	{"geometry":{"coordinates":[10.662871,50.007021],"type":"Point"},"properties":{"osm_id":"8755509789","tag":{"amenity":"waste_basket"}},"type":"Feature"}
]
}
