{
"type": "FeatureCollection",
"features": [
	{"geometry":{"coordinates":[10.65499,49.620611],"type":"Point"},"properties":{"osm_id":"828418031","tag":{"amenity":"recycling"}},"type":"Feature"},
	{"geometry":{"coordinates":[10.704788,49.642723],"type":"Point"},"properties":{"osm_id":"841780313","tag":{"amenity":"recycling","location":"overground","recycling_type":"container"}},"type":"Feature"},
	{"geometry":{"coordinates":[10.718828,49.667413],"type":"Point"},"properties":{"osm_id":"1437156724","tag":{"amenity":"recycling","recycling:green_waste":"yes","recycling_type":"container"}},"type":"Feature"},
	{"geometry":{"coordinates":[10.654262,49.625126],"type":"Point"},"properties":{"osm_id":"3212404509","tag":{"amenity":"recycling"}},"type":"Feature"},
	{"geometry":{"coordinates":[10.695447,49.634306],"type":"Point"},"properties":{"name":"Wertstoffsammelstelle Gerhardshofen - Dachsbach","osm_id":"6295656520","tag":{"amenity":"recycling","opening_hours":"Fr 15:00-17:45; Sa 09:00-11:45","recycling_type":"centre"}},"type":"Feature"},
	{"geometry":{"coordinates":[10.721734,49.662076],"type":"Point"},"properties":{"osm_id":"6949309797","tag":{"amenity":"recycling","recycling:cans":"yes","recycling:glass":"yes","recycling:glass_bottles":"yes","recycling_type":"container","wheelchair":"yes"}},"type":"Feature"},
	{"geometry":{"coordinates":[10.694726,49.631456],"type":"Point"},"properties":{"osm_id":"8155255715","tag":{"amenity":"recycling","opening_hours:covid19":"open","recycling:green_waste":"yes","recycling_type":"container"}},"type":"Feature"}
]
}
