{
"type": "FeatureCollection",
"lastupdate": "2020-08-06T00:00:00Z",
"features": [
	{"geometry":{"coordinates":[10.68986,48.36645],"type":"Point"},"properties":{"is_in":"Agawang,Kutzenhausen,Augsburg,Schwaben,Bayern,Bundesrepublik Deutschland,Europe","name":"Wertstoffsammelstelle","osm_id":"297571517","tag":{"amenity":"recycling","opening_hours":"Sa 09:00-12:00","recycling:batteries":"no","recycling_type":"centre"}},"type":"Feature"},
	{"geometry":{"coordinates":[10.691279,48.394653],"type":"Point"},"properties":{"is_in":"Horgau,Augsburg,Schwaben,Bayern,Bundesrepublik Deutschland,Europe","osm_id":"307084661","tag":{"amenity":"recycling","recycling:batteries":"no","recycling:books":"no","recycling:cans":"yes","recycling:cardboard":"no","recycling:cartons":"no","recycling:clothes":"no","recycling:electrical_appliances":"no","recycling:glass":"no","recycling:glass_bottles":"yes","recycling:green_waste":"no","recycling:magazines":"no","recycling:newspaper":"no","recycling:paper":"no","recycling:plastic":"no","recycling_type":"container"}},"type":"Feature"},
	{"geometry":{"coordinates":[10.679974,48.391801],"type":"Point"},"properties":{"is_in":"Horgau,Augsburg,Schwaben,Bayern,Bundesrepublik Deutschland,Europe","name":"Wertstoffsammelstelle","osm_id":"307100943","tag":{"amenity":"recycling","recycling:batteries":"yes","recycling:cans":"yes","recycling:cartons":"yes","recycling:clothes":"yes","recycling:electrical_appliances":"yes","recycling:glass":"yes","recycling:glass_bottles":"yes","recycling:magazines":"yes","recycling:newspaper":"yes","recycling:paper_packaging":"yes","recycling:scrap_metal":"yes","recycling_type":"centre"}},"type":"Feature"},
	{"geometry":{"coordinates":[10.677842,48.396275],"type":"Point"},"properties":{"osm_id":"3577286416","tag":{"amenity":"waste_basket","waste":"dog_excrement"}},"type":"Feature"}
]
}
