{
"type": "FeatureCollection",
"lastupdate": "2020-08-06T00:00:00Z",
"features": [
	{"geometry":{"coordinates":[10.691133,48.34141],"type":"Point"},"properties":{"is_in":"Kutzenhausen,Augsburg,Schwaben,Bayern,Bundesrepublik Deutschland,Europe","osm_id":"302413223","tag":{"amenity":"recycling","recycling:glass":"yes"}},"type":"Feature"},
	{"geometry":{"coordinates":[10.651267,48.294241],"type":"Point"},"properties":{"name":"Wertstoffhof","osm_id":"336382650","tag":{"amenity":"recycling","recycling:batteries":"yes","recycling:cans":"yes","recycling:clothes":"yes","recycling:glass":"yes","recycling:paper":"yes","recycling:scrap_metal":"yes","recycling_type":"centre"}},"type":"Feature"},
	{"geometry":{"coordinates":[10.652823,48.287067],"type":"Point"},"properties":{"osm_id":"537982903","tag":{"amenity":"recycling","recycling:clothes":"yes"}},"type":"Feature"},
	{"geometry":{"coordinates":[10.661431,48.294249],"type":"Point"},"properties":{"osm_id":"1068815748","tag":{"amenity":"recycling","recycling:cans":"yes","recycling:clothes":"yes","recycling:glass":"yes","recycling:shoes":"yes"}},"type":"Feature"},
	{"geometry":{"coordinates":[10.70868,48.312626],"type":"Point"},"properties":{"osm_id":"4460860941","tag":{"amenity":"recycling","recycling:cans":"yes","recycling:glass_bottles":"yes","recycling_type":"container"}},"type":"Feature"}
]
}
