{
"type": "FeatureCollection",
"features": [
	{"geometry":{"coordinates":[120.63588,24.353244],"type":"Point"},"properties":{"osm_id":"3733087281","tag":{"natural":"tree"}},"type":"Feature"},
	{"geometry":{"coordinates":[120.61339,24.358309],"type":"Point"},"properties":{"name":"\u00e7\u0099\u00be\u00e5\u00b9\u00b4\u00e8\u008a\u0092\u00e6\u009e\u009c\u00e6\u00a8\u00b9","osm_id":"5636332068","tag":{"addr:city":"\u00e5\u008f\u00b0\u00e4\u00b8\u00ad\u00e5\u00b8\u0082","addr:district":"\u00e5\u00a4\u00a7\u00e7\u0094\u00b2","addr:floor":"1","addr:housenumber":"288","addr:postcode":"437","addr:street":"\u00e6\u00a9\u00ab\u00e5\u009c\u00b3\u00e8\u00a1\u0097","addr:unit":"1","natural":"tree"}},"type":"Feature"}
]
}
