{
"type": "FeatureCollection",
"features": [
	{"geometry":{"coordinates":[21.749488,50.682334],"type":"Point"},"properties":{"osm_id":"3597326598","tag":{"natural":"tree"}},"type":"Feature"},
	{"geometry":{"coordinates":[21.749297,50.682375],"type":"Point"},"properties":{"osm_id":"3597326601","tag":{"natural":"tree"}},"type":"Feature"},
	{"geometry":{"coordinates":[21.749377,50.682435],"type":"Point"},"properties":{"osm_id":"3597326612","tag":{"natural":"tree"}},"type":"Feature"},
	{"geometry":{"coordinates":[21.748759,50.682459],"type":"Point"},"properties":{"osm_id":"3597326624","tag":{"natural":"tree"}},"type":"Feature"},
	{"geometry":{"coordinates":[21.74943,50.68247],"type":"Point"},"properties":{"osm_id":"3597326630","tag":{"natural":"tree"}},"type":"Feature"},
	{"geometry":{"coordinates":[21.748492,50.682589],"type":"Point"},"properties":{"osm_id":"3597326670","tag":{"natural":"tree"}},"type":"Feature"},
	{"geometry":{"coordinates":[21.748571,50.682766],"type":"Point"},"properties":{"osm_id":"3597390319","tag":{"natural":"tree"}},"type":"Feature"},
	{"geometry":{"coordinates":[21.750036,50.68101],"type":"Point"},"properties":{"osm_id":"3599271413","tag":{"natural":"tree"}},"type":"Feature"},
	{"geometry":{"coordinates":[21.758622,50.696984],"type":"Point"},"properties":{"osm_id":"3599525475","tag":{"natural":"tree"}},"type":"Feature"},
	{"geometry":{"coordinates":[21.758581,50.697121],"type":"Point"},"properties":{"osm_id":"3599525483","tag":{"natural":"tree"}},"type":"Feature"},
	{"geometry":{"coordinates":[21.758517,50.697288],"type":"Point"},"properties":{"osm_id":"3599525490","tag":{"natural":"tree"}},"type":"Feature"},
	{"geometry":{"coordinates":[21.74568,50.681732],"type":"Point"},"properties":{"osm_id":"3600626804","tag":{"natural":"tree"}},"type":"Feature"},
	{"geometry":{"coordinates":[21.745931,50.6818],"type":"Point"},"properties":{"osm_id":"3600626823","tag":{"natural":"tree"}},"type":"Feature"},
	{"geometry":{"coordinates":[21.746271,50.681934],"type":"Point"},"properties":{"osm_id":"3600626864","tag":{"natural":"tree"}},"type":"Feature"},
	{"geometry":{"coordinates":[21.746197,50.682301],"type":"Point"},"properties":{"osm_id":"3600626931","tag":{"natural":"tree"}},"type":"Feature"},
	{"geometry":{"coordinates":[21.747165,50.682461],"type":"Point"},"properties":{"osm_id":"3601080215","tag":{"natural":"tree"}},"type":"Feature"},
	{"geometry":{"coordinates":[21.747108,50.682484],"type":"Point"},"properties":{"osm_id":"3601080216","tag":{"natural":"tree"}},"type":"Feature"},
	{"geometry":{"coordinates":[21.74707,50.682505],"type":"Point"},"properties":{"osm_id":"3601080217","tag":{"natural":"tree"}},"type":"Feature"},
	{"geometry":{"coordinates":[21.747103,50.682525],"type":"Point"},"properties":{"osm_id":"3601080219","tag":{"natural":"tree"}},"type":"Feature"},
	{"geometry":{"coordinates":[21.747019,50.682535],"type":"Point"},"properties":{"osm_id":"3601080221","tag":{"natural":"tree"}},"type":"Feature"},
	{"geometry":{"coordinates":[21.747051,50.682543],"type":"Point"},"properties":{"osm_id":"3601080224","tag":{"natural":"tree"}},"type":"Feature"},
	{"geometry":{"coordinates":[21.746983,50.682564],"type":"Point"},"properties":{"osm_id":"3601080228","tag":{"natural":"tree"}},"type":"Feature"},
	{"geometry":{"coordinates":[21.746951,50.682639],"type":"Point"},"properties":{"osm_id":"3601080233","tag":{"natural":"tree"}},"type":"Feature"},
	{"geometry":{"coordinates":[21.746735,50.682766],"type":"Point"},"properties":{"osm_id":"3601080238","tag":{"natural":"tree"}},"type":"Feature"},
	{"geometry":{"coordinates":[21.716961,50.696914],"type":"Point"},"properties":{"osm_id":"6158204673","tag":{"natural":"tree"}},"type":"Feature"},
	{"geometry":{"coordinates":[21.784665,50.686352],"type":"Point"},"properties":{"name":"Stara lipa","osm_id":"7563444371","tag":{"diameter":"200","leaf_cycle":"deciduous","leaf_type":"broadleaved","natural":"tree"}},"type":"Feature"}
]
}
