{
"type": "FeatureCollection",
"features": [
	{"geometry":{"coordinates":[21.749488,50.682333],"type":"Point"},"properties":{"osm_id":"3597326598","tag":{"natural":"tree"}},"type":"Feature"},
	{"geometry":{"coordinates":[21.749296,50.682374],"type":"Point"},"properties":{"osm_id":"3597326601","tag":{"natural":"tree"}},"type":"Feature"},
	{"geometry":{"coordinates":[21.749376,50.682434],"type":"Point"},"properties":{"osm_id":"3597326612","tag":{"natural":"tree"}},"type":"Feature"},
	{"geometry":{"coordinates":[21.748758,50.682458],"type":"Point"},"properties":{"osm_id":"3597326624","tag":{"natural":"tree"}},"type":"Feature"},
	{"geometry":{"coordinates":[21.74943,50.68247],"type":"Point"},"properties":{"osm_id":"3597326630","tag":{"natural":"tree"}},"type":"Feature"},
	{"geometry":{"coordinates":[21.748491,50.682589],"type":"Point"},"properties":{"osm_id":"3597326670","tag":{"natural":"tree"}},"type":"Feature"},
	{"geometry":{"coordinates":[21.74857,50.682765],"type":"Point"},"properties":{"osm_id":"3597390319","tag":{"natural":"tree"}},"type":"Feature"},
	{"geometry":{"coordinates":[21.750035,50.681009],"type":"Point"},"properties":{"osm_id":"3599271413","tag":{"natural":"tree"}},"type":"Feature"},
	{"geometry":{"coordinates":[21.758622,50.696983],"type":"Point"},"properties":{"osm_id":"3599525475","tag":{"natural":"tree"}},"type":"Feature"},
	{"geometry":{"coordinates":[21.75858,50.697121],"type":"Point"},"properties":{"osm_id":"3599525483","tag":{"natural":"tree"}},"type":"Feature"},
	{"geometry":{"coordinates":[21.758517,50.697288],"type":"Point"},"properties":{"osm_id":"3599525490","tag":{"natural":"tree"}},"type":"Feature"},
	{"geometry":{"coordinates":[21.74568,50.681732],"type":"Point"},"properties":{"osm_id":"3600626804","tag":{"natural":"tree"}},"type":"Feature"},
	{"geometry":{"coordinates":[21.74593,50.681799],"type":"Point"},"properties":{"osm_id":"3600626823","tag":{"natural":"tree"}},"type":"Feature"},
	{"geometry":{"coordinates":[21.746271,50.681933],"type":"Point"},"properties":{"osm_id":"3600626864","tag":{"natural":"tree"}},"type":"Feature"},
	{"geometry":{"coordinates":[21.746196,50.682301],"type":"Point"},"properties":{"osm_id":"3600626931","tag":{"natural":"tree"}},"type":"Feature"},
	{"geometry":{"coordinates":[21.747164,50.68246],"type":"Point"},"properties":{"osm_id":"3601080215","tag":{"natural":"tree"}},"type":"Feature"},
	{"geometry":{"coordinates":[21.747108,50.682484],"type":"Point"},"properties":{"osm_id":"3601080216","tag":{"natural":"tree"}},"type":"Feature"},
	{"geometry":{"coordinates":[21.74707,50.682504],"type":"Point"},"properties":{"osm_id":"3601080217","tag":{"natural":"tree"}},"type":"Feature"},
	{"geometry":{"coordinates":[21.747103,50.682524],"type":"Point"},"properties":{"osm_id":"3601080219","tag":{"natural":"tree"}},"type":"Feature"},
	{"geometry":{"coordinates":[21.747019,50.682534],"type":"Point"},"properties":{"osm_id":"3601080221","tag":{"natural":"tree"}},"type":"Feature"},
	{"geometry":{"coordinates":[21.747051,50.682542],"type":"Point"},"properties":{"osm_id":"3601080224","tag":{"natural":"tree"}},"type":"Feature"},
	{"geometry":{"coordinates":[21.746983,50.682563],"type":"Point"},"properties":{"osm_id":"3601080228","tag":{"natural":"tree"}},"type":"Feature"},
	{"geometry":{"coordinates":[21.74695,50.682638],"type":"Point"},"properties":{"osm_id":"3601080233","tag":{"natural":"tree"}},"type":"Feature"},
	{"geometry":{"coordinates":[21.746734,50.682766],"type":"Point"},"properties":{"osm_id":"3601080238","tag":{"natural":"tree"}},"type":"Feature"},
	{"geometry":{"coordinates":[21.71696,50.696913],"type":"Point"},"properties":{"osm_id":"6158204673","tag":{"natural":"tree"}},"type":"Feature"},
	{"geometry":{"coordinates":[21.784664,50.686351],"type":"Point"},"properties":{"name":"Stara lipa","osm_id":"7563444371","tag":{"diameter":"200","leaf_cycle":"deciduous","leaf_type":"broadleaved","natural":"tree"}},"type":"Feature"}
]
}
