{
"type": "FeatureCollection",
"features": [
	{"geometry":{"coordinates":[21.791163,50.481575],"type":"Point"},"properties":{"name":"Pomnik przyrody","osm_id":"4037297123","tag":{"denotation":"natural_monument","monument":"yes","natural":"tree","protected":"yes"}},"type":"Feature"},
	{"geometry":{"coordinates":[21.792168,50.481648],"type":"Point"},"properties":{"name":"Pomnik przyrody","osm_id":"4037297124","tag":{"denotation":"natural_monument","monument":"yes","natural":"tree","protected":"yes"}},"type":"Feature"},
	{"geometry":{"coordinates":[21.791414,50.48165],"type":"Point"},"properties":{"name":"Pomnik przyrody","osm_id":"4037297125","tag":{"denotation":"natural_monument","monument":"yes","natural":"tree","protected":"yes"}},"type":"Feature"},
	{"geometry":{"coordinates":[21.791497,50.481772],"type":"Point"},"properties":{"name":"Pomnik przyrody","osm_id":"4037297126","tag":{"denotation":"natural_monument","monument":"yes","natural":"tree","protected":"yes"}},"type":"Feature"},
	{"geometry":{"coordinates":[21.791021,50.481811],"type":"Point"},"properties":{"name":"Pomnik przyrody","osm_id":"4037297127","tag":{"denotation":"natural_monument","monument":"yes","natural":"tree","protected":"yes"}},"type":"Feature"},
	{"geometry":{"coordinates":[21.791538,50.481965],"type":"Point"},"properties":{"name":"Pomnik przyrody","osm_id":"4037297128","tag":{"denotation":"natural_monument","monument":"yes","natural":"tree","protected":"yes"}},"type":"Feature"},
	{"geometry":{"coordinates":[21.791808,50.481992],"type":"Point"},"properties":{"name":"Pomnik przyrody","osm_id":"4037297129","tag":{"denotation":"natural_monument","monument":"yes","natural":"tree","protected":"yes"}},"type":"Feature"},
	{"geometry":{"coordinates":[21.791657,50.482022],"type":"Point"},"properties":{"name":"Pomnik przyrody","osm_id":"4037297130","tag":{"denotation":"natural_monument","monument":"yes","natural":"tree","protected":"yes"}},"type":"Feature"},
	{"geometry":{"coordinates":[21.791755,50.482502],"type":"Point"},"properties":{"name":"Pomnik przyrody","osm_id":"4037297131","tag":{"denotation":"natural_monument","monument":"yes","natural":"tree","protected":"yes"}},"type":"Feature"}
]
}
