{
"type": "FeatureCollection",
"lastupdate": "2020-08-03T00:00:00Z",
"features": [
	{"geometry":{"coordinates":[11.73331,59.48575],"type":"Point"},"properties":{"name":"Grensen gjenvinningsstasjon, Marker","osm_id":"5555206057","tag":{"amenity":"recycling","recycling:batteries":"yes","recycling:boats":"yes","recycling:electrical_items":"yes","recycling:garden_waste":"yes","recycling:glass":"yes","recycling:glass_bottles":"yes","recycling:hazardous_waste":"yes","recycling:organic":"yes","recycling:paper":"yes","recycling:plastic_packaging":"yes","recycling:rubble":"yes","recycling:scrap_metal":"yes","recycling:tyres":"yes","recycling:waste":"yes","recycling:wood":"yes","recycling_type":"centre","ref:sortere":"1550;21329"}},"type":"Feature"}
]
}
