{
"type": "FeatureCollection",
"features": [
	{"geometry":{"coordinates":[11.704286,51.821879],"type":"Point"},"properties":{"osm_id":"686695430","tag":{"amenity":"recycling","recycling:cans":"no","recycling:glass":"yes","recycling:paper":"yes"}},"type":"Feature"},
	{"geometry":{"coordinates":[11.707301,51.821037],"type":"Point"},"properties":{"osm_id":"686695477","tag":{"amenity":"recycling","recycling:glass":"yes","recycling:paper":"yes"}},"type":"Feature"},
	{"geometry":{"coordinates":[11.727549,51.803745],"type":"Point"},"properties":{"osm_id":"2441881306","tag":{"amenity":"recycling","recycling:clothes":"yes","recycling_type":"container"}},"type":"Feature"},
	{"geometry":{"coordinates":[11.754306,51.82138],"type":"Point"},"properties":{"osm_id":"2451684573","tag":{"amenity":"recycling","recycling:clothes":"yes","recycling:glass_bottles":"yes","recycling_type":"container"}},"type":"Feature"},
	{"geometry":{"coordinates":[11.73736,51.804468],"type":"Point"},"properties":{"osm_id":"2527887677","tag":{"amenity":"recycling","recycling:cartons":"yes","recycling:clothes":"yes","recycling:glass_bottles":"yes"}},"type":"Feature"},
	{"geometry":{"coordinates":[11.738105,51.80079],"type":"Point"},"properties":{"osm_id":"2736149114","tag":{"amenity":"recycling","recycling:clothes":"yes"}},"type":"Feature"},
	{"geometry":{"coordinates":[11.743,51.794163],"type":"Point"},"properties":{"osm_id":"2808219758","tag":{"amenity":"waste_basket"}},"type":"Feature"},
	{"geometry":{"coordinates":[11.754633,51.824555],"type":"Point"},"properties":{"osm_id":"3509954530","tag":{"amenity":"recycling","recycling:clothes":"yes","recycling:glass":"yes","recycling:glass_bottles":"yes","recycling_type":"container"}},"type":"Feature"},
	{"geometry":{"coordinates":[11.740037,51.786328],"type":"Point"},"properties":{"osm_id":"3697653076","tag":{"amenity":"recycling","recycling:glass":"yes","recycling:glass_bottles":"yes","recycling_type":"container"}},"type":"Feature"},
	{"geometry":{"coordinates":[11.755497,51.782905],"type":"Point"},"properties":{"osm_id":"3901128031","tag":{"amenity":"recycling","recycling:clothes":"yes","recycling_type":"container"}},"type":"Feature"},
	{"geometry":{"coordinates":[11.731604,51.791646],"type":"Point"},"properties":{"osm_id":"4608394410","tag":{"amenity":"recycling","recycling:glass":"yes","recycling_type":"container"}},"type":"Feature"},
	{"geometry":{"coordinates":[11.743864,51.793045],"type":"Point"},"properties":{"osm_id":"4811167294","tag":{"amenity":"waste_basket"}},"type":"Feature"},
	{"geometry":{"coordinates":[11.734503,51.800233],"type":"Point"},"properties":{"osm_id":"4811204360","tag":{"amenity":"recycling","recycling:clothes":"yes","recycling:glass":"yes","recycling:glass_bottles":"yes","recycling_type":"container"}},"type":"Feature"},
	{"geometry":{"coordinates":[11.769298,51.795535],"type":"Point"},"properties":{"name":"PreZero Service Sachsen-Anhalt GmbH in Bernburg","osm_id":"8554430314","tag":{"addr:city":"Bernburg","addr:housenumber":"1","addr:postcode":"06406","addr:street":"Am Kirchfeld","amenity":"recycling","opening_hours":"Mo-Fr 07:00-17:00; Sa-Su off","phone":"+49 3471 36464 0","recycling:hardcore":"yes","recycling:metal":"yes","recycling:packaging":"yes","recycling:scrap_metal":"yes","recycling:tyres":"yes","recycling:wood":"yes","recycling_type":"centre","website":"https://prezero.com/bernburg/"}},"type":"Feature"}
]
}
