{
"type": "FeatureCollection",
"lastupdate": "2020-08-03T00:00:00Z",
"features": [
	{"geometry":{"coordinates":[11.720902,50.956748],"type":"Point"},"properties":{"osm_id":"846217608","tag":{"amenity":"recycling","recycling_type":"container"}},"type":"Feature"},
	{"geometry":{"coordinates":[11.727962,50.909561],"type":"Point"},"properties":{"name":"Altglascontainer","osm_id":"4325801896","tag":{"amenity":"recycling","recycling:glass":"yes"}},"type":"Feature"},
	{"geometry":{"coordinates":[11.689581,50.947631],"type":"Point"},"properties":{"osm_id":"4561266181","tag":{"amenity":"recycling","recycling:glass":"yes","recycling:glass_bottles":"yes","recycling_type":"container"}},"type":"Feature"}
]
}
