{
"type": "FeatureCollection",
"lastupdate": "2020-07-31T00:00:00Z",
"features": [
	{"geometry":{"coordinates":[11.769595,48.593358],"type":"Point"},"properties":{"name":"Wertstoffhof","osm_id":"296109778","tag":{"amenity":"recycling","recycling_type":"centre"}},"type":"Feature"},
	{"geometry":{"coordinates":[11.774833,48.623369],"type":"Point"},"properties":{"name":"Wertstoffhof Stadt Mainburg","osm_id":"1797002836","tag":{"amenity":"recycling","opening_hours":"Apr 01-Nov 30: Mo 16:00-19:00; We 16:00-19:00; Fr 15:00-19:00; Sa 09:00-13:00; Dec 01-Mar 31: We 17:00-19:00; Fr 17:00-19:00; Sa 09:00-12:00","recycling_type":"centre"}},"type":"Feature"}
]
}
