{
"type": "FeatureCollection",
"features": [
	{"geometry":{"coordinates":[11.775926,48.313886],"type":"Point"},"properties":{"osm_id":"874418786","tag":{"amenity":"recycling","opening_hours":"Mo-Sa 07:00-12:00,14:00-19:00; Su,PH off","recycling:cans":"yes","recycling:cardboard":"yes","recycling:clothes":"yes","recycling:glass_bottles":"yes","recycling:paper":"yes","recycling:shoes":"yes","recycling_type":"container","website":"https://www.landkreis-erding.de/abfallwirtschaft/rund-um-die-entsorgung/recyclinghoefe-containerplaetze/"}},"type":"Feature"},
	{"geometry":{"coordinates":[11.741072,48.332259],"type":"Point"},"properties":{"osm_id":"1434012957","tag":{"amenity":"waste_basket"}},"type":"Feature"},
	{"geometry":{"coordinates":[11.740585,48.332209],"type":"Point"},"properties":{"osm_id":"1434013017","tag":{"amenity":"waste_basket"}},"type":"Feature"},
	{"geometry":{"coordinates":[11.741181,48.331804],"type":"Point"},"properties":{"osm_id":"1434013059","tag":{"amenity":"waste_basket"}},"type":"Feature"},
	{"geometry":{"coordinates":[11.74623,48.317322],"type":"Point"},"properties":{"osm_id":"1879090783","tag":{"addr:city":"Hallbergmoos","addr:postcode":"85399","addr:street":"Freiherr-von-Hallberg-Platz","amenity":"recycling","operator":"Gemeinde Hallbergmoos","recycling:batteries":"no","recycling:books":"no","recycling:cans":"no","recycling:cardboard":"no","recycling:cartons":"no","recycling:clothes":"no","recycling:electrical_appliances":"no","recycling:glass_bottles":"yes","recycling:green_waste":"no","recycling:magazines":"no","recycling:newspaper":"no","recycling:paper":"no","recycling:paper_packaging":"no","recycling:plastic":"no","recycling:plastic_packaging":"no","recycling:scrap_metal":"no","recycling:small_appliances":"no","recycling:waste":"no","recycling:wood":"no","recycling_type":"container"}},"type":"Feature"},
	{"geometry":{"coordinates":[11.720206,48.308364],"type":"Point"},"properties":{"osm_id":"4258134027","tag":{"amenity":"waste_basket"}},"type":"Feature"},
	{"geometry":{"coordinates":[11.706022,48.298229],"type":"Point"},"properties":{"osm_id":"6866922276","tag":{"amenity":"recycling","material":"glass","operator":"Gemeinde","recycling:cans":"no","recycling:clothes":"no","recycling:glass":"yes","recycling:paper":"yes"}},"type":"Feature"}
]
}
