{
"type": "FeatureCollection",
"features": [
	{"geometry":{"coordinates":[11.71617,46.640845],"type":"Point"},"properties":{"osm_id":"2425650747","tag":{"amenity":"waste_basket"}},"type":"Feature"},
	{"geometry":{"coordinates":[11.762813,46.635125],"type":"Point"},"properties":{"osm_id":"4280664684","tag":{"amenity":"waste_basket"}},"type":"Feature"},
	{"geometry":{"coordinates":[11.763208,46.635121],"type":"Point"},"properties":{"osm_id":"4335637489","tag":{"amenity":"waste_basket"}},"type":"Feature"},
	{"geometry":{"coordinates":[11.762622,46.635084],"type":"Point"},"properties":{"osm_id":"8078471766","tag":{"amenity":"waste_basket"}},"type":"Feature"},
	{"geometry":{"coordinates":[11.739286,46.677214],"type":"Point"},"properties":{"osm_id":"8660540386","tag":{"amenity":"recycling","recycling:glass_bottles":"yes","recycling:paper":"yes","recycling_type":"container"}},"type":"Feature"},
	{"geometry":{"coordinates":[11.695241,46.66962],"type":"Point"},"properties":{"name":"Mini-Recyclinghof Afers","osm_id":"8660540388","tag":{"amenity":"recycling","name:de":"Mini-Recyclinghof Afers","opening_hours":"Sa 09:00-12:00","recycling_type":"centre","website":"https://www.asmb.it/de/umwelt/anfahrt-recyclinghoefe/"}},"type":"Feature"},
	{"geometry":{"coordinates":[11.69514,46.669585],"type":"Point"},"properties":{"osm_id":"8660540389","tag":{"amenity":"recycling","recycling:batteries":"yes","recycling:cans":"yes","recycling:glass_bottles":"yes","recycling:paper":"yes","recycling_type":"container"}},"type":"Feature"},
	{"geometry":{"coordinates":[11.693169,46.668277],"type":"Point"},"properties":{"osm_id":"8713040149","tag":{"amenity":"waste_basket"}},"type":"Feature"},
	{"geometry":{"coordinates":[11.690039,46.642598],"type":"Point"},"properties":{"osm_id":"8789692467","tag":{"amenity":"waste_basket"}},"type":"Feature"}
]
}
