{
"type": "FeatureCollection",
"features": [
	{"geometry":{"coordinates":[152.847854,-26.996694],"type":"Point"},"properties":{"name":"Mango Tree Trailhead","osm_id":"6189026193","tag":{"natural":"tree"}},"type":"Feature"}
]
}
