{
"type": "FeatureCollection",
"features": [
	{"geometry":{"coordinates":[152.847855,-26.996695],"type":"Point"},"properties":{"name":"Mango Tree Trailhead","osm_id":"6189026193","tag":{"natural":"tree"}},"type":"Feature"}
]
}
