{
"type": "FeatureCollection",
"features": [
	{"geometry":{"coordinates":[17.95148,53.70621],"type":"Point"},"properties":{"osm_id":"4706667071","tag":{"denotation":"natural_monument","natural":"tree","ref:CRFOP":"PL.ZIPOP.1393.PP.0416063.2102","ref:INSPIRE":"PL.ZIPOP.1393.PP.0416063.2102","website":"http://crfop.gdos.gov.pl/CRFOP/widok/viewfop.jsf?fop=PL.ZIPOP.1393.PP.0416063.2102"}},"type":"Feature"},
	{"geometry":{"coordinates":[18.01024,53.71691],"type":"Point"},"properties":{"osm_id":"4706667085","tag":{"denotation":"natural_monument","natural":"tree","ref:CRFOP":"PL.ZIPOP.1393.PP.0416063.2089","ref:INSPIRE":"PL.ZIPOP.1393.PP.0416063.2089","website":"http://crfop.gdos.gov.pl/CRFOP/widok/viewfop.jsf?fop=PL.ZIPOP.1393.PP.0416063.2089"}},"type":"Feature"},
	{"geometry":{"coordinates":[18.010629,53.71663],"type":"Point"},"properties":{"osm_id":"4706667086","tag":{"denotation":"natural_monument","natural":"tree","ref:CRFOP":"PL.ZIPOP.1393.PP.0416063.2088","ref:INSPIRE":"PL.ZIPOP.1393.PP.0416063.2088","website":"http://crfop.gdos.gov.pl/CRFOP/widok/viewfop.jsf?fop=PL.ZIPOP.1393.PP.0416063.2088"}},"type":"Feature"},
	{"geometry":{"coordinates":[18.010679,53.71676],"type":"Point"},"properties":{"osm_id":"4706667091","tag":{"denotation":"natural_monument","natural":"tree","ref:CRFOP":"PL.ZIPOP.1393.PP.0416063.2088","ref:INSPIRE":"PL.ZIPOP.1393.PP.0416063.2088","website":"http://crfop.gdos.gov.pl/CRFOP/widok/viewfop.jsf?fop=PL.ZIPOP.1393.PP.0416063.2088"}},"type":"Feature"},
	{"geometry":{"coordinates":[18.01093,53.71678],"type":"Point"},"properties":{"osm_id":"4706667092","tag":{"denotation":"natural_monument","natural":"tree","ref:CRFOP":"PL.ZIPOP.1393.PP.0416063.2088","ref:INSPIRE":"PL.ZIPOP.1393.PP.0416063.2088","website":"http://crfop.gdos.gov.pl/CRFOP/widok/viewfop.jsf?fop=PL.ZIPOP.1393.PP.0416063.2088"}},"type":"Feature"},
	{"geometry":{"coordinates":[17.93529,53.70601],"type":"Point"},"properties":{"osm_id":"4706667093","tag":{"denotation":"natural_monument","natural":"tree","ref:CRFOP":"PL.ZIPOP.1393.PP.0416063.2086","ref:INSPIRE":"PL.ZIPOP.1393.PP.0416063.2086","website":"http://crfop.gdos.gov.pl/CRFOP/widok/viewfop.jsf?fop=PL.ZIPOP.1393.PP.0416063.2086"}},"type":"Feature"}
]
}
