{
"type": "FeatureCollection",
"features": [
	{"geometry":{"coordinates":[17.984218,53.402965],"type":"Point"},"properties":{"osm_id":"4706667164","tag":{"denotation":"natural_monument","natural":"tree","ref:CRFOP":"PL.ZIPOP.1393.PP.0416042.1092","ref:INSPIRE":"PL.ZIPOP.1393.PP.0416042.1092","website":"http://crfop.gdos.gov.pl/CRFOP/widok/viewfop.jsf?fop=PL.ZIPOP.1393.PP.0416042.1092"}},"type":"Feature"},
	{"geometry":{"coordinates":[17.941859,53.41137],"type":"Point"},"properties":{"osm_id":"4706667165","tag":{"denotation":"natural_monument","natural":"tree","ref:CRFOP":"PL.ZIPOP.1393.PP.0416042.1090","ref:INSPIRE":"PL.ZIPOP.1393.PP.0416042.1090","website":"http://crfop.gdos.gov.pl/CRFOP/widok/viewfop.jsf?fop=PL.ZIPOP.1393.PP.0416042.1090"}},"type":"Feature"},
	{"geometry":{"coordinates":[17.948455,53.3913],"type":"Point"},"properties":{"osm_id":"4706692555","tag":{"denotation":"natural_monument","natural":"tree","ref:CRFOP":"PL.ZIPOP.1393.PP.0403043.984","ref:INSPIRE":"PL.ZIPOP.1393.PP.0403043.984","website":"http://crfop.gdos.gov.pl/CRFOP/widok/viewfop.jsf?fop=PL.ZIPOP.1393.PP.0403043.984"}},"type":"Feature"},
	{"geometry":{"coordinates":[17.948799,53.391382],"type":"Point"},"properties":{"osm_id":"4706692556","tag":{"denotation":"natural_monument","natural":"tree","ref:CRFOP":"PL.ZIPOP.1393.PP.0403043.984","ref:INSPIRE":"PL.ZIPOP.1393.PP.0403043.984","website":"http://crfop.gdos.gov.pl/CRFOP/widok/viewfop.jsf?fop=PL.ZIPOP.1393.PP.0403043.984"}},"type":"Feature"},
	{"geometry":{"coordinates":[17.948966,53.391398],"type":"Point"},"properties":{"osm_id":"4706692557","tag":{"denotation":"natural_monument","natural":"tree","ref:CRFOP":"PL.ZIPOP.1393.PP.0403043.984","ref:INSPIRE":"PL.ZIPOP.1393.PP.0403043.984","website":"http://crfop.gdos.gov.pl/CRFOP/widok/viewfop.jsf?fop=PL.ZIPOP.1393.PP.0403043.984"}},"type":"Feature"},
	{"geometry":{"coordinates":[17.948901,53.39145],"type":"Point"},"properties":{"osm_id":"4706692558","tag":{"denotation":"natural_monument","natural":"tree","ref:CRFOP":"PL.ZIPOP.1393.PP.0403043.984","ref:INSPIRE":"PL.ZIPOP.1393.PP.0403043.984","website":"http://crfop.gdos.gov.pl/CRFOP/widok/viewfop.jsf?fop=PL.ZIPOP.1393.PP.0403043.984"}},"type":"Feature"},
	{"geometry":{"coordinates":[17.94882,53.391658],"type":"Point"},"properties":{"osm_id":"4706692559","tag":{"denotation":"natural_monument","natural":"tree","ref:CRFOP":"PL.ZIPOP.1393.PP.0403043.984","ref:INSPIRE":"PL.ZIPOP.1393.PP.0403043.984","website":"http://crfop.gdos.gov.pl/CRFOP/widok/viewfop.jsf?fop=PL.ZIPOP.1393.PP.0403043.984"}},"type":"Feature"}
]
}
