{
"type": "FeatureCollection",
"features": [
	{"geometry":{"coordinates":[18.003437,53.022644],"type":"Point"},"properties":{"osm_id":"4706692536","tag":{"denotation":"natural_monument","natural":"tree","ref:CRFOP":"PL.ZIPOP.1393.PP.0403052.1253","ref:INSPIRE":"PL.ZIPOP.1393.PP.0403052.1253","website":"http://crfop.gdos.gov.pl/CRFOP/widok/viewfop.jsf?fop=PL.ZIPOP.1393.PP.0403052.1253"}},"type":"Feature"},
	{"geometry":{"coordinates":[18.004008,53.020387],"type":"Point"},"properties":{"osm_id":"4706692537","tag":{"denotation":"natural_monument","natural":"tree","ref:CRFOP":"PL.ZIPOP.1393.PP.0403052.1251","ref:INSPIRE":"PL.ZIPOP.1393.PP.0403052.1251","website":"http://crfop.gdos.gov.pl/CRFOP/widok/viewfop.jsf?fop=PL.ZIPOP.1393.PP.0403052.1251"}},"type":"Feature"},
	{"geometry":{"coordinates":[17.968463,53.040384],"type":"Point"},"properties":{"osm_id":"4706694897","tag":{"denotation":"natural_monument","natural":"tree","ref:CRFOP":"PL.ZIPOP.1393.PP.0403012.47","ref:INSPIRE":"PL.ZIPOP.1393.PP.0403012.47","start_date":"1985-04-10","website":"http://crfop.gdos.gov.pl/CRFOP/widok/viewfop.jsf?fop=PL.ZIPOP.1393.PP.0403012.47"}},"type":"Feature"},
	{"geometry":{"coordinates":[17.968429,53.040359],"type":"Point"},"properties":{"osm_id":"4706694898","tag":{"denotation":"natural_monument","natural":"tree","ref:CRFOP":"PL.ZIPOP.1393.PP.0403012.47","ref:INSPIRE":"PL.ZIPOP.1393.PP.0403012.47","start_date":"1985-04-10","website":"http://crfop.gdos.gov.pl/CRFOP/widok/viewfop.jsf?fop=PL.ZIPOP.1393.PP.0403012.47"}},"type":"Feature"},
	{"geometry":{"coordinates":[17.968532,53.040363],"type":"Point"},"properties":{"osm_id":"4706694899","tag":{"denotation":"natural_monument","natural":"tree","ref:CRFOP":"PL.ZIPOP.1393.PP.0403012.47","ref:INSPIRE":"PL.ZIPOP.1393.PP.0403012.47","start_date":"1985-04-10","website":"http://crfop.gdos.gov.pl/CRFOP/widok/viewfop.jsf?fop=PL.ZIPOP.1393.PP.0403012.47"}},"type":"Feature"}
]
}
