{
"type": "FeatureCollection",
"features": [
	{"geometry":{"coordinates":[17.984656,52.951869],"type":"Point"},"properties":{"osm_id":"4706665950","tag":{"denotation":"natural_monument","natural":"tree","ref:CRFOP":"PL.ZIPOP.1393.PP.0419043.1110","ref:INSPIRE":"PL.ZIPOP.1393.PP.0419043.1110","website":"http://crfop.gdos.gov.pl/CRFOP/widok/viewfop.jsf?fop=PL.ZIPOP.1393.PP.0419043.1110"}},"type":"Feature"},
	{"geometry":{"coordinates":[18.002593,52.935401],"type":"Point"},"properties":{"osm_id":"4706681681","tag":{"denotation":"natural_monument","natural":"tree","ref:CRFOP":"PL.ZIPOP.1393.PP.0407092.2279","ref:INSPIRE":"PL.ZIPOP.1393.PP.0407092.2279","website":"http://crfop.gdos.gov.pl/CRFOP/widok/viewfop.jsf?fop=PL.ZIPOP.1393.PP.0407092.2279"}},"type":"Feature"},
	{"geometry":{"coordinates":[17.986969,52.918985],"type":"Point"},"properties":{"osm_id":"4706681682","tag":{"denotation":"natural_monument","natural":"tree","ref:CRFOP":"PL.ZIPOP.1393.PP.0407092.2278","ref:INSPIRE":"PL.ZIPOP.1393.PP.0407092.2278","website":"http://crfop.gdos.gov.pl/CRFOP/widok/viewfop.jsf?fop=PL.ZIPOP.1393.PP.0407092.2278"}},"type":"Feature"},
	{"geometry":{"coordinates":[17.996365,52.92602],"type":"Point"},"properties":{"osm_id":"4706681683","tag":{"denotation":"natural_monument","natural":"tree","ref:CRFOP":"PL.ZIPOP.1393.PP.0407092.2277","ref:INSPIRE":"PL.ZIPOP.1393.PP.0407092.2277","website":"http://crfop.gdos.gov.pl/CRFOP/widok/viewfop.jsf?fop=PL.ZIPOP.1393.PP.0407092.2277"}},"type":"Feature"},
	{"geometry":{"coordinates":[18.004176,52.915164],"type":"Point"},"properties":{"osm_id":"4706681686","tag":{"denotation":"natural_monument","natural":"tree","ref:CRFOP":"PL.ZIPOP.1393.PP.0407092.2274","ref:INSPIRE":"PL.ZIPOP.1393.PP.0407092.2274","website":"http://crfop.gdos.gov.pl/CRFOP/widok/viewfop.jsf?fop=PL.ZIPOP.1393.PP.0407092.2274"}},"type":"Feature"}
]
}
