{
"type": "FeatureCollection",
"features": [
	{"geometry":{"coordinates":[17.988132,-29.991386],"type":"Point"},"properties":{"name":"Picnic Spot","osm_id":"4160509547","tag":{"natural":"tree"}},"type":"Feature"}
]
}
