{
"type": "FeatureCollection",
"features": [
	{"geometry":{"coordinates":[175.870303,-40.185512],"type":"Point"},"properties":{"name":"Rimu","osm_id":"4598761566","tag":{"leaf_cycle":"evergreen","leaf_type":"needleleaved","natural":"tree"}},"type":"Feature"}
]
}
