{
"type": "FeatureCollection",
"lastupdate": "2020-07-31T00:00:00Z",
"features": [
	{"geometry":{"coordinates":[-116.732907,32.465922],"type":"Point"},"properties":{"name":"BIODEGESTORES","osm_id":"2015684019","tag":{"amenity":"recycling","recycling_type":"centre"}},"type":"Feature"}
]
}
