{
"type": "FeatureCollection",
"features": [
	{"geometry":{"coordinates":[-116.732908,32.465923],"type":"Point"},"properties":{"name":"BIODEGESTORES","osm_id":"2015684019","tag":{"amenity":"recycling","recycling_type":"centre"}},"type":"Feature"}
]
}
