{
"type": "FeatureCollection",
"features": [
	{"geometry":{"coordinates":[14.627573,47.589385],"type":"Point"},"properties":{"name":"Chemische Toilette","osm_id":"7928076315","tag":{"amenity":"waste_disposal"}},"type":"Feature"},
	{"geometry":{"coordinates":[14.627568,47.589436],"type":"Point"},"properties":{"osm_id":"7928078581","tag":{"amenity":"recycling"}},"type":"Feature"}
]
}
