{
"type": "FeatureCollection",
"features": [
	{"geometry":{"coordinates":[-49.493819,-24.244839],"type":"Point"},"properties":{"name":"Arvore da Lenda","osm_id":"6039949612","tag":{"natural":"tree"}},"type":"Feature"}
]
}
