{
"type": "FeatureCollection",
"features": [
	{"geometry":{"coordinates":[-49.49382,-24.24484],"type":"Point"},"properties":{"name":"Arvore da Lenda","osm_id":"6039949612","tag":{"natural":"tree"}},"type":"Feature"}
]
}
