{
"type": "FeatureCollection",
"features": [
	{"geometry":{"coordinates":[1.82213,41.46655],"type":"Point"},"properties":{"name":"Alsina","osm_id":"8190628590","tag":{"denotation":"natural_monument","natural":"tree"}},"type":"Feature"}
]
}
