{
"type": "FeatureCollection",
"features": [
	{"geometry":{"coordinates":[-83.53163,36.671147],"type":"Point"},"properties":{"name":"Apple","osm_id":"7906216156","tag":{"natural":"tree"}},"type":"Feature"}
]
}
