{
"type": "FeatureCollection",
"lastupdate": "2020-08-03T00:00:00Z",
"features": [
	{"geometry":{"coordinates":[11.011944,61.573263],"type":"Point"},"properties":{"name":"Koppang gjenvinningsstasjon og brukthandel","osm_id":"5555204265","tag":{"amenity":"recycling","recycling:batteries":"yes","recycling:boats":"yes","recycling:electrical_items":"yes","recycling:garden_waste":"yes","recycling:glass_bottles":"yes","recycling:hazardous_waste":"yes","recycling:metal":"yes","recycling:paper":"yes","recycling:rubble":"yes","recycling:tyres":"yes","recycling:waste":"yes","recycling:wood":"yes","recycling_type":"centre","ref:sortere":"1222"}},"type":"Feature"},
	{"geometry":{"coordinates":[11.049773,61.569855],"type":"Point"},"properties":{"osm_id":"5555208840","tag":{"amenity":"recycling","description":"Koppang returpunkt","recycling:glass_bottles":"yes","recycling:paper":"yes","recycling:waste":"yes","recycling_type":"container","ref:sortere":"13554"}},"type":"Feature"},
	{"geometry":{"coordinates":[11.049646,61.570377],"type":"Point"},"properties":{"osm_id":"6195508620","tag":{"amenity":"recycling","description":"Amfi tekstilretur (Fretex-Fias)","recycling:clothes":"yes","recycling_type":"container","ref:sortere":"21961"}},"type":"Feature"}
]
}
