{
"type": "FeatureCollection",
"lastupdate": "2020-08-05T00:00:00Z",
"features": [
	{"geometry":{"coordinates":[11.031434,53.935627],"type":"Point"},"properties":{"highway":"bus_stop","name":"Klein Voigtshagen","osm_id":"1375330983","tag":{"amenity":"waste_basket","bench":"yes","bus":"yes","covered":"yes","public_transport":"platform","shelter":"yes"}},"type":"Feature"},
	{"geometry":{"coordinates":[11.010243,53.922467],"type":"Point"},"properties":{"osm_id":"2466411796","tag":{"amenity":"recycling","recycling:glass_bottles":"yes","recycling:paper":"yes","recycling_type":"container"}},"type":"Feature"},
	{"geometry":{"coordinates":[10.988411,53.932994],"type":"Point"},"properties":{"highway":"bus_stop","name":"Wilmstorf","osm_id":"2466445307","tag":{"amenity":"waste_basket","bench":"yes","bus":"yes","covered":"no","public_transport":"platform","shelter":"yes"}},"type":"Feature"}
]
}
