{
"type": "FeatureCollection",
"lastupdate": "2020-08-06T00:00:00Z",
"features": [
	{"geometry":{"coordinates":[10.98777,52.648537],"type":"Point"},"properties":{"name":"Kleider- und Glascontainer","osm_id":"353697985","tag":{"amenity":"recycling","recycling:clothes":"yes","recycling:glass":"yes","recycling_type":"container"}},"type":"Feature"}
]
}
