{
"type": "FeatureCollection",
"features": [
	{"geometry":{"coordinates":[11.035661,45.574304],"type":"Point"},"properties":{"osm_id":"6174852024","tag":{"amenity":"waste_basket","waste":"trash"}},"type":"Feature"},
	{"geometry":{"coordinates":[11.037475,45.574257],"type":"Point"},"properties":{"name":"Isola ecologica","osm_id":"6174852025","tag":{"amenity":"recycling","recycling_type":"centre"}},"type":"Feature"}
]
}
