{
"type": "FeatureCollection",
"features": [
	{"geometry":{"coordinates":[11.03566,45.574303],"type":"Point"},"properties":{"osm_id":"6174852024","tag":{"amenity":"waste_basket","waste":"trash"}},"type":"Feature"},
	{"geometry":{"coordinates":[11.037475,45.574256],"type":"Point"},"properties":{"name":"Isola ecologica","osm_id":"6174852025","tag":{"amenity":"recycling","recycling_type":"centre"}},"type":"Feature"},
	{"geometry":{"coordinates":[11.037548,45.574664],"type":"Point"},"properties":{"osm_id":"8895145242","tag":{"amenity":"waste_basket","waste":"trash"}},"type":"Feature"},
	{"geometry":{"coordinates":[11.046319,45.571895],"type":"Point"},"properties":{"osm_id":"9075987081","tag":{"amenity":"recycling","recycling:cans":"yes","recycling:cardboard":"yes","recycling:cartons":"yes","recycling:glass_bottles":"yes","recycling:green_waste":"yes","recycling:magazines":"yes","recycling:newspaper":"yes","recycling:paper":"yes","recycling:paper_packaging":"yes","recycling:plastic":"yes","recycling:plastic_bags":"yes","recycling:plastic_bottles":"yes","recycling:plastic_packaging":"yes","recycling:styrofoam":"yes","recycling:waste":"yes","recycling_type":"container"}},"type":"Feature"}
]
}
