{
"type": "FeatureCollection",
"lastupdate": "2020-08-01T00:00:00Z",
"features": [
	{"geometry":{"coordinates":[11.03566,45.574303],"type":"Point"},"properties":{"osm_id":"6174852024","tag":{"amenity":"waste_basket","waste":"trash"}},"type":"Feature"},
	{"geometry":{"coordinates":[11.037475,45.574256],"type":"Point"},"properties":{"name":"Isola ecologica","osm_id":"6174852025","tag":{"amenity":"recycling","recycling_type":"centre"}},"type":"Feature"}
]
}
