{
"type": "FeatureCollection",
"features": [
	{"geometry":{"coordinates":[11.419342,48.829575],"type":"Point"},"properties":{"name":"Wertstoffhof","osm_id":"266853706","tag":{"amenity":"recycling","recycling:batteries":"yes","recycling:clothes":"yes","recycling:glass":"yes","recycling_type":"centre"}},"type":"Feature"},
	{"geometry":{"coordinates":[11.402004,48.80866],"type":"Point"},"properties":{"osm_id":"369528117","tag":{"amenity":"recycling","recycling:glass_bottles":"yes","recycling_type":"container"}},"type":"Feature"},
	{"geometry":{"coordinates":[11.415111,48.822003],"type":"Point"},"properties":{"osm_id":"791145336","tag":{"amenity":"recycling","recycling:clothes":"yes","recycling:shoes":"yes"}},"type":"Feature"},
	{"geometry":{"coordinates":[11.368804,48.858117],"type":"Point"},"properties":{"osm_id":"2347893021","tag":{"amenity":"recycling","recycling:clothes":"yes","recycling:glass_bottles":"yes","recycling_type":"container"}},"type":"Feature"},
	{"geometry":{"coordinates":[11.358361,48.83483],"type":"Point"},"properties":{"osm_id":"3761260561","tag":{"amenity":"recycling","recycling:clothes":"yes","recycling:glass":"yes","recycling:glass_bottles":"yes","recycling_type":"container"}},"type":"Feature"},
	{"geometry":{"coordinates":[11.369844,48.839644],"type":"Point"},"properties":{"osm_id":"5665478702","tag":{"amenity":"recycling","recycling:clothes":"yes","recycling:glass_bottles":"yes","recycling_type":"container"}},"type":"Feature"}
]
}
