{
"type": "FeatureCollection",
"features": [
	{"geometry":{"coordinates":[11.366314,47.952422],"type":"Point"},"properties":{"osm_id":"882754066","tag":{"amenity":"recycling","recycling:glass":"yes","recycling_type":"container"}},"type":"Feature"},
	{"geometry":{"coordinates":[11.378404,47.961522],"type":"Point"},"properties":{"osm_id":"1367646646","tag":{"amenity":"recycling","location":"overground","recycling:glass_bottles":"yes","recycling_type":"container","wheelchair":"limited"}},"type":"Feature"},
	{"geometry":{"coordinates":[11.343738,47.944658],"type":"Point"},"properties":{"osm_id":"5190697097","tag":{"amenity":"waste_basket"}},"type":"Feature"},
	{"geometry":{"coordinates":[11.347372,47.963638],"type":"Point"},"properties":{"osm_id":"5190832473","tag":{"amenity":"waste_basket"}},"type":"Feature"},
	{"geometry":{"coordinates":[11.348641,47.9638],"type":"Point"},"properties":{"osm_id":"5632845721","tag":{"amenity":"waste_basket"}},"type":"Feature"}
]
}
