{
"type": "FeatureCollection",
"lastupdate": "2020-08-04T00:00:00Z",
"features": [
	{"geometry":{"coordinates":[11.365048,46.665234],"type":"Point"},"properties":{"osm_id":"760631865","tag":{"amenity":"recycling","description":"Astfeld \u00f6ffentlich"}},"type":"Feature"},
	{"geometry":{"coordinates":[11.363411,46.625666],"type":"Point"},"properties":{"name":"Recyclinghof","osm_id":"1956126708","tag":{"amenity":"recycling"}},"type":"Feature"}
]
}
