{
"type": "FeatureCollection",
"features": [
	{"geometry":{"coordinates":[-118.00757,33.686286],"type":"Point"},"properties":{"name":"rePLANET Recycling","osm_id":"1872338169","tag":{"amenity":"recycling","operator":"rePLANET Recycling","recycling:cans":"yes","recycling:glass":"yes","recycling:plastic_bottles":"yes","recycling_type":"centre"}},"type":"Feature"},
	{"geometry":{"coordinates":[-117.972888,33.652386],"type":"Point"},"properties":{"osm_id":"5323102414","tag":{"amenity":"waste_basket"}},"type":"Feature"},
	{"geometry":{"coordinates":[-117.972882,33.652378],"type":"Point"},"properties":{"osm_id":"5323102419","tag":{"amenity":"waste_basket"}},"type":"Feature"},
	{"geometry":{"coordinates":[-117.972133,33.652596],"type":"Point"},"properties":{"osm_id":"5323139334","tag":{"amenity":"waste_basket"}},"type":"Feature"},
	{"geometry":{"coordinates":[-117.972139,33.652595],"type":"Point"},"properties":{"osm_id":"5323139337","tag":{"amenity":"waste_basket"}},"type":"Feature"},
	{"geometry":{"coordinates":[-117.949916,33.651628],"type":"Point"},"properties":{"osm_id":"6047661404","tag":{"amenity":"waste_basket"}},"type":"Feature"}
]
}
