{
"type": "FeatureCollection",
"features": [
	{"geometry":{"coordinates":[-4.102848,42.291285],"type":"Point"},"properties":{"name":"Moral","osm_id":"3377191967","tag":{"natural":"tree"}},"type":"Feature"},
	{"geometry":{"coordinates":[-4.099984,42.282561],"type":"Point"},"properties":{"osm_id":"5191696158","tag":{"natural":"tree"}},"type":"Feature"},
	{"geometry":{"coordinates":[-4.100034,42.282516],"type":"Point"},"properties":{"osm_id":"5191696159","tag":{"natural":"tree"}},"type":"Feature"},
	{"geometry":{"coordinates":[-4.100298,42.282311],"type":"Point"},"properties":{"osm_id":"5191696173","tag":{"natural":"tree"}},"type":"Feature"},
	{"geometry":{"coordinates":[-4.100267,42.28229],"type":"Point"},"properties":{"osm_id":"5191696174","tag":{"natural":"tree"}},"type":"Feature"},
	{"geometry":{"coordinates":[-4.100233,42.282265],"type":"Point"},"properties":{"osm_id":"5191696175","tag":{"natural":"tree"}},"type":"Feature"},
	{"geometry":{"coordinates":[-4.100195,42.28224],"type":"Point"},"properties":{"osm_id":"5191696176","tag":{"natural":"tree"}},"type":"Feature"},
	{"geometry":{"coordinates":[-4.100159,42.282215],"type":"Point"},"properties":{"osm_id":"5191696177","tag":{"natural":"tree"}},"type":"Feature"}
]
}
