{
"type": "FeatureCollection",
"features": [
	{"geometry":{"coordinates":[-4.102847,42.291284],"type":"Point"},"properties":{"name":"Moral","osm_id":"3377191967","tag":{"natural":"tree"}},"type":"Feature"},
	{"geometry":{"coordinates":[-4.099984,42.28256],"type":"Point"},"properties":{"osm_id":"5191696158","tag":{"natural":"tree"}},"type":"Feature"},
	{"geometry":{"coordinates":[-4.100034,42.282516],"type":"Point"},"properties":{"osm_id":"5191696159","tag":{"natural":"tree"}},"type":"Feature"},
	{"geometry":{"coordinates":[-4.100297,42.282311],"type":"Point"},"properties":{"osm_id":"5191696173","tag":{"natural":"tree"}},"type":"Feature"},
	{"geometry":{"coordinates":[-4.100266,42.282289],"type":"Point"},"properties":{"osm_id":"5191696174","tag":{"natural":"tree"}},"type":"Feature"},
	{"geometry":{"coordinates":[-4.100232,42.282264],"type":"Point"},"properties":{"osm_id":"5191696175","tag":{"natural":"tree"}},"type":"Feature"},
	{"geometry":{"coordinates":[-4.100195,42.282239],"type":"Point"},"properties":{"osm_id":"5191696176","tag":{"natural":"tree"}},"type":"Feature"},
	{"geometry":{"coordinates":[-4.100159,42.282215],"type":"Point"},"properties":{"osm_id":"5191696177","tag":{"natural":"tree"}},"type":"Feature"}
]
}
