{
"type": "FeatureCollection",
"lastupdate": "2020-08-06T00:00:00Z",
"features": [
	{"geometry":{"coordinates":[4.294587,51.506194],"type":"Point"},"properties":{"osm_id":"648639150","tag":{"amenity":"recycling","recycling:cans":"no","recycling:clothes":"yes","recycling:glass":"yes","recycling:paper":"no","recycling:plastic":"yes","recycling:small_appliances":"yes","recycling_type":"container"}},"type":"Feature"},
	{"geometry":{"coordinates":[4.281617,51.479545],"type":"Point"},"properties":{"osm_id":"648887685","tag":{"amenity":"recycling","recycling:clothes":"yes","recycling:glass":"yes","recycling:plastic":"yes","recycling_type":"container"}},"type":"Feature"},
	{"geometry":{"coordinates":[4.293025,51.49634],"type":"Point"},"properties":{"osm_id":"648922483","tag":{"amenity":"recycling","recycling_type":"container"}},"type":"Feature"},
	{"geometry":{"coordinates":[4.29166,51.485848],"type":"Point"},"properties":{"osm_id":"656176555","tag":{"amenity":"recycling","recycling:clothes":"yes","recycling:glass":"yes","recycling:plastic":"yes","recycling_type":"container"}},"type":"Feature"},
	{"geometry":{"coordinates":[4.285329,51.493096],"type":"Point"},"properties":{"osm_id":"656176563","tag":{"amenity":"recycling","recycling:clothes":"yes","recycling:glass":"yes","recycling:plastic":"yes","recycling_type":"container"}},"type":"Feature"},
	{"geometry":{"coordinates":[4.291636,51.488593],"type":"Point"},"properties":{"osm_id":"717120706","tag":{"amenity":"recycling","recycling:clothes":"yes","recycling:glass":"yes","recycling:plastic":"yes","recycling_type":"container"}},"type":"Feature"},
	{"geometry":{"coordinates":[4.276503,51.502461],"type":"Point"},"properties":{"osm_id":"806988036","tag":{"amenity":"recycling","recycling:paper":"yes","recycling:scrap_metal":"yes","recycling_type":"container"}},"type":"Feature"},
	{"geometry":{"coordinates":[4.285824,51.497768],"type":"Point"},"properties":{"osm_id":"853537741","tag":{"amenity":"recycling","recycling:clothes":"yes","recycling:glass":"yes","recycling:plastic":"yes","recycling_type":"container"}},"type":"Feature"},
	{"geometry":{"coordinates":[4.28477,51.503467],"type":"Point"},"properties":{"osm_id":"1144466669","tag":{"amenity":"recycling","recycling:clothes":"yes","recycling:glass":"yes","recycling:plastic":"yes","recycling_type":"container"}},"type":"Feature"},
	{"geometry":{"coordinates":[4.276472,51.493003],"type":"Point"},"properties":{"osm_id":"3042093433","tag":{"amenity":"recycling","recycling:cans":"no","recycling:glass":"yes","recycling:paper":"no","recycling:plastic":"yes","recycling_type":"container"}},"type":"Feature"},
	{"geometry":{"coordinates":[4.228723,51.492965],"type":"Point"},"properties":{"osm_id":"4351793519","tag":{"amenity":"waste_basket","image":"https://d1cuyjsrcm0gby.cloudfront.net/Zkz-5gzOI_mRFTdM2dI4Cw/thumb-2048.jpg","mapillary":"https://www.mapillary.com/map/im/Zkz-5gzOI_mRFTdM2dI4Cw"}},"type":"Feature"},
	{"geometry":{"coordinates":[4.304119,51.49376],"type":"Point"},"properties":{"osm_id":"4595229274","tag":{"amenity":"recycling","recycling:clothes":"yes","recycling:glass":"yes","recycling:plastic":"yes","recycling_type":"container"}},"type":"Feature"},
	{"geometry":{"coordinates":[4.288967,51.498363],"type":"Point"},"properties":{"osm_id":"4941668242","tag":{"amenity":"waste_basket"}},"type":"Feature"},
	{"geometry":{"coordinates":[4.290127,51.497891],"type":"Point"},"properties":{"osm_id":"4941668250","tag":{"amenity":"waste_basket"}},"type":"Feature"},
	{"geometry":{"coordinates":[4.262286,51.480556],"type":"Point"},"properties":{"name":"Hondenpoep","osm_id":"6220657159","tag":{"amenity":"waste_basket","image":"https://d1cuyjsrcm0gby.cloudfront.net/oR9eyka9c1_OB-b-ia-D_Q/thumb-2048.jpg","mapillary":"https://www.mapillary.com/map/im/oR9eyka9c1_OB-b-ia-D_Q","waste":"dog_excrement"}},"type":"Feature"},
	{"geometry":{"coordinates":[4.22733,51.495208],"type":"Point"},"properties":{"osm_id":"6221996296","tag":{"amenity":"waste_basket","image":"https://d1cuyjsrcm0gby.cloudfront.net/IXHIydDxhdA9dobFHrNafA/thumb-2048.jpg","mapillary":"https://www.mapillary.com/map/im/IXHIydDxhdA9dobFHrNafA"}},"type":"Feature"},
	{"geometry":{"coordinates":[4.219531,51.479594],"type":"Point"},"properties":{"osm_id":"6488127290","tag":{"amenity":"waste_basket"}},"type":"Feature"}
]
}
