{
"type": "FeatureCollection",
"lastupdate": "2020-07-31T00:00:00Z",
"features": [
	{"geometry":{"coordinates":[4.242625,49.356986],"type":"Point"},"properties":{"osm_id":"6077559461","tag":{"addr:city":"Warmeriville","addr:postcode":"51110","amenity":"recycling","recycling_type":"centre"}},"type":"Feature"}
]
}
