{
"type": "FeatureCollection",
"features": [
	{"geometry":{"coordinates":[4.242625,49.356987],"type":"Point"},"properties":{"osm_id":"6077559461","tag":{"addr:city":"Warmeriville","addr:postcode":"51110","amenity":"recycling","recycling_type":"centre"}},"type":"Feature"}
]
}
