{
"type": "FeatureCollection",
"features": [
	{"geometry":{"coordinates":[4.241624,45.508757],"type":"Point"},"properties":{"name":"Chomat Arrosage","osm_id":"4077706921","tag":{"addr:city":"Saint-Just-Saint-Rambert","addr:country":"FR","addr:housenumber":"182","addr:postcode":"42170","addr:street":"route de bonson","amenity":"recycling","contact:facebook":"https://www.facebook.com/chomat.arrosage/photos_stream?tab=photos_stream","contact:phone":"+33 4 77 52 30 66","opening_hours":"Mo-Fr 08:00-12:00, 13:30-18:00; Sa 08:30-12:00","website":"www.chomat-arrosage.fr"}},"type":"Feature"},
	{"geometry":{"coordinates":[4.274111,45.509888],"type":"Point"},"properties":{"osm_id":"7319054427","tag":{"amenity":"recycling","recycling:glass":"yes","recycling_type":"centre"}},"type":"Feature"}
]
}
