{
"type": "FeatureCollection",
"features": [
	{"geometry":{"coordinates":[8.267172,25.381637],"type":"Point"},"properties":{"name":"Acacia","osm_id":"7640566087","tag":{"natural":"tree"}},"type":"Feature"},
	{"geometry":{"coordinates":[8.267721,25.382989],"type":"Point"},"properties":{"name":"Acacia","osm_id":"7640566088","tag":{"natural":"tree"}},"type":"Feature"},
	{"geometry":{"coordinates":[8.267468,25.383066],"type":"Point"},"properties":{"name":"Acacia","osm_id":"7640566089","tag":{"natural":"tree"}},"type":"Feature"},
	{"geometry":{"coordinates":[8.276564,25.402114],"type":"Point"},"properties":{"name":"Acacia","osm_id":"7640566116","tag":{"natural":"tree"}},"type":"Feature"},
	{"geometry":{"coordinates":[8.2647,25.375648],"type":"Point"},"properties":{"name":"Acacia","osm_id":"7642355286","tag":{"natural":"tree"}},"type":"Feature"},
	{"geometry":{"coordinates":[8.28734,25.38584],"type":"Point"},"properties":{"name":"Acacia","osm_id":"7773535223","tag":{"natural":"tree"}},"type":"Feature"}
]
}
