{
"type": "FeatureCollection",
"features": [
	{"geometry":{"coordinates":[8.267173,25.381638],"type":"Point"},"properties":{"name":"Acacia","osm_id":"7640566087","tag":{"natural":"tree"}},"type":"Feature"},
	{"geometry":{"coordinates":[8.267721,25.38299],"type":"Point"},"properties":{"name":"Acacia","osm_id":"7640566088","tag":{"natural":"tree"}},"type":"Feature"},
	{"geometry":{"coordinates":[8.267468,25.383066],"type":"Point"},"properties":{"name":"Acacia","osm_id":"7640566089","tag":{"natural":"tree"}},"type":"Feature"},
	{"geometry":{"coordinates":[8.276564,25.402114],"type":"Point"},"properties":{"name":"Acacia","osm_id":"7640566116","tag":{"natural":"tree"}},"type":"Feature"},
	{"geometry":{"coordinates":[8.264701,25.375649],"type":"Point"},"properties":{"name":"Acacia","osm_id":"7642355286","tag":{"natural":"tree"}},"type":"Feature"},
	{"geometry":{"coordinates":[8.287341,25.38584],"type":"Point"},"properties":{"name":"Acacia","osm_id":"7773535223","tag":{"natural":"tree"}},"type":"Feature"}
]
}
