{
"type": "FeatureCollection",
"lastupdate": "2020-08-01T00:00:00Z",
"features": [
	{"geometry":{"coordinates":[22.80299,63.653636],"type":"Point"},"properties":{"name":"Ab Ekorosk Oy","osm_id":"1200863655","tag":{"addr:city":"Jakobstad","addr:housenumber":"90","addr:postcode":"68600","addr:street":"Spituholmsv\u00e4gen","amenity":"recycling","email":"info@ekorosk.fi","fax":"(06) 781 4529","phone":"(06) 781 4500"}},"type":"Feature"}
]
}
