{
"type": "FeatureCollection",
"features": [
	{"geometry":{"coordinates":[-97.329176,37.65503],"type":"Point"},"properties":{"name":"Pro Kansas Miller Recycling Center","osm_id":"1930925361","tag":{"amenity":"recycling","recycling:batteries":"yes","recycling:cans":"yes","recycling:glass":"yes","recycling:paper":"yes","recycling_type":"centre"}},"type":"Feature"},
	{"geometry":{"coordinates":[-97.32769,37.686183],"type":"Point"},"properties":{"osm_id":"4017531328","tag":{"amenity":"waste_basket"}},"type":"Feature"},
	{"geometry":{"coordinates":[-97.338315,37.687759],"type":"Point"},"properties":{"osm_id":"4018767336","tag":{"amenity":"waste_basket"}},"type":"Feature"},
	{"geometry":{"coordinates":[-97.339741,37.686126],"type":"Point"},"properties":{"osm_id":"4018978925","tag":{"amenity":"waste_basket"}},"type":"Feature"},
	{"geometry":{"coordinates":[-97.334178,37.687819],"type":"Point"},"properties":{"osm_id":"4018979208","tag":{"amenity":"waste_basket"}},"type":"Feature"},
	{"geometry":{"coordinates":[-97.334491,37.688008],"type":"Point"},"properties":{"osm_id":"4018979227","tag":{"amenity":"waste_basket"}},"type":"Feature"},
	{"geometry":{"coordinates":[-97.347178,37.683913],"type":"Point"},"properties":{"osm_id":"4057418915","tag":{"amenity":"waste_basket"}},"type":"Feature"},
	{"geometry":{"coordinates":[-97.350765,37.684064],"type":"Point"},"properties":{"osm_id":"4057418949","tag":{"amenity":"waste_basket"}},"type":"Feature"},
	{"geometry":{"coordinates":[-97.34829,37.684067],"type":"Point"},"properties":{"osm_id":"4057418950","tag":{"amenity":"waste_basket"}},"type":"Feature"},
	{"geometry":{"coordinates":[-97.347952,37.68407],"type":"Point"},"properties":{"osm_id":"4057418951","tag":{"amenity":"waste_basket"}},"type":"Feature"},
	{"geometry":{"coordinates":[-97.351973,37.684071],"type":"Point"},"properties":{"osm_id":"4057418953","tag":{"amenity":"waste_basket"}},"type":"Feature"},
	{"geometry":{"coordinates":[-97.347211,37.6841],"type":"Point"},"properties":{"osm_id":"4057418957","tag":{"amenity":"waste_basket"}},"type":"Feature"},
	{"geometry":{"coordinates":[-97.345192,37.684852],"type":"Point"},"properties":{"osm_id":"4057419141","tag":{"amenity":"waste_basket"}},"type":"Feature"},
	{"geometry":{"coordinates":[-97.338557,37.715131],"type":"Point"},"properties":{"osm_id":"6340922721","tag":{"amenity":"waste_basket"}},"type":"Feature"},
	{"geometry":{"coordinates":[-97.338467,37.715129],"type":"Point"},"properties":{"osm_id":"6340922722","tag":{"amenity":"waste_basket"}},"type":"Feature"}
]
}
