{
"type": "FeatureCollection",
"lastupdate": "2020-08-05T00:00:00Z",
"features": [
	{"geometry":{"coordinates":[-97.329175,37.655029],"type":"Point"},"properties":{"name":"Pro Kansas Miller Recycling Center","osm_id":"1930925361","tag":{"amenity":"recycling","recycling:batteries":"yes","recycling:cans":"yes","recycling:glass":"yes","recycling:paper":"yes","recycling_type":"centre"}},"type":"Feature"},
	{"geometry":{"coordinates":[-97.327689,37.686183],"type":"Point"},"properties":{"osm_id":"4017531328","tag":{"amenity":"waste_basket"}},"type":"Feature"},
	{"geometry":{"coordinates":[-97.338314,37.687758],"type":"Point"},"properties":{"osm_id":"4018767336","tag":{"amenity":"waste_basket"}},"type":"Feature"},
	{"geometry":{"coordinates":[-97.33974,37.686126],"type":"Point"},"properties":{"osm_id":"4018978925","tag":{"amenity":"waste_basket"}},"type":"Feature"},
	{"geometry":{"coordinates":[-97.334178,37.687818],"type":"Point"},"properties":{"osm_id":"4018979208","tag":{"amenity":"waste_basket"}},"type":"Feature"},
	{"geometry":{"coordinates":[-97.33449,37.688007],"type":"Point"},"properties":{"osm_id":"4018979227","tag":{"amenity":"waste_basket"}},"type":"Feature"},
	{"geometry":{"coordinates":[-97.347178,37.683912],"type":"Point"},"properties":{"osm_id":"4057418915","tag":{"amenity":"waste_basket"}},"type":"Feature"},
	{"geometry":{"coordinates":[-97.350764,37.684064],"type":"Point"},"properties":{"osm_id":"4057418949","tag":{"amenity":"waste_basket"}},"type":"Feature"},
	{"geometry":{"coordinates":[-97.348289,37.684066],"type":"Point"},"properties":{"osm_id":"4057418950","tag":{"amenity":"waste_basket"}},"type":"Feature"},
	{"geometry":{"coordinates":[-97.347951,37.684069],"type":"Point"},"properties":{"osm_id":"4057418951","tag":{"amenity":"waste_basket"}},"type":"Feature"},
	{"geometry":{"coordinates":[-97.351972,37.68407],"type":"Point"},"properties":{"osm_id":"4057418953","tag":{"amenity":"waste_basket"}},"type":"Feature"},
	{"geometry":{"coordinates":[-97.347211,37.6841],"type":"Point"},"properties":{"osm_id":"4057418957","tag":{"amenity":"waste_basket"}},"type":"Feature"},
	{"geometry":{"coordinates":[-97.345191,37.684852],"type":"Point"},"properties":{"osm_id":"4057419141","tag":{"amenity":"waste_basket"}},"type":"Feature"},
	{"geometry":{"coordinates":[-97.338557,37.71513],"type":"Point"},"properties":{"osm_id":"6340922721","tag":{"amenity":"waste_basket"}},"type":"Feature"},
	{"geometry":{"coordinates":[-97.338467,37.715129],"type":"Point"},"properties":{"osm_id":"6340922722","tag":{"amenity":"waste_basket"}},"type":"Feature"}
]
}
