{
"type": "FeatureCollection",
"features": [
	{"geometry":{"coordinates":[174.082502,-35.265302],"type":"Point"},"properties":{"osm_id":"6641834355","tag":{"denotation":"natural_monument","description":"This tree is located at the Waitangi Treaty Grounds. Planted by AGNES WIFE OF JAMES BUSBY 1836.","diameter":"239.7 cm","leaf_cycle":"evergreen","natural":"tree","url":"https://register.notabletrees.org.nz/tree/view/734"}},"type":"Feature"},
	{"geometry":{"coordinates":[174.094087,-35.283645],"type":"Point"},"properties":{"osm_id":"7228035123","tag":{"natural":"tree"}},"type":"Feature"},
	{"geometry":{"coordinates":[174.094775,-35.284224],"type":"Point"},"properties":{"name":"1880 Elizabeth Colenso nee Fairburn Norfolk Pine","osm_id":"7228035129","tag":{"natural":"tree"}},"type":"Feature"}
]
}
