{
"type": "FeatureCollection",
"features": [
	{"geometry":{"coordinates":[80.540897,7.440069],"type":"Point"},"properties":{"name":"Keppitigala Rubber Estate","osm_id":"3854132661","tag":{"natural":"tree"}},"type":"Feature"}
]
}
