{
"type": "FeatureCollection",
"features": [
	{"geometry":{"coordinates":[21.572556,50.300939],"type":"Point"},"properties":{"osm_id":"5291885191","tag":{"natural":"tree"}},"type":"Feature"},
	{"geometry":{"coordinates":[21.572821,50.300838],"type":"Point"},"properties":{"osm_id":"5291885192","tag":{"natural":"tree"}},"type":"Feature"},
	{"geometry":{"coordinates":[21.572486,50.301154],"type":"Point"},"properties":{"osm_id":"5299285463","tag":{"leaf_type":"broadleaved","natural":"tree"}},"type":"Feature"},
	{"geometry":{"coordinates":[21.572132,50.300828],"type":"Point"},"properties":{"osm_id":"5299285464","tag":{"leaf_type":"broadleaved","natural":"tree"}},"type":"Feature"},
	{"geometry":{"coordinates":[21.572334,50.300962],"type":"Point"},"properties":{"osm_id":"5299285465","tag":{"leaf_type":"broadleaved","natural":"tree"}},"type":"Feature"},
	{"geometry":{"coordinates":[21.596833,50.316163],"type":"Point"},"properties":{"name":"Sosna Kasia","osm_id":"8176275039","tag":{"denotation":"natural_monument","diameter":"30cm","leaf_cycle":"evergreen","leaf_type":"needleleaved","name:en":"Katie pine","natural":"tree"}},"type":"Feature"}
]
}
