{
"type": "FeatureCollection",
"features": [
	{"geometry":{"coordinates":[21.5846,49.843165],"type":"Point"},"properties":{"name":"Pomnik przyrody","osm_id":"4005802301","tag":{"denotation":"natural_monument","monument":"yes","natural":"tree","protected":"yes"}},"type":"Feature"},
	{"geometry":{"coordinates":[21.583789,49.84372],"type":"Point"},"properties":{"name":"Pomnik przyrody","osm_id":"4005802302","tag":{"denotation":"natural_monument","monument":"yes","natural":"tree","protected":"yes"}},"type":"Feature"},
	{"geometry":{"coordinates":[21.580357,49.844396],"type":"Point"},"properties":{"name":"Pomnik przyrody","osm_id":"4005802303","tag":{"denotation":"natural_monument","monument":"yes","natural":"tree","protected":"yes"}},"type":"Feature"},
	{"geometry":{"coordinates":[21.56474,49.885773],"type":"Point"},"properties":{"name":"Stara Lipa","osm_id":"4044210635","tag":{"natural":"tree","start_date":"1500"}},"type":"Feature"}
]
}
