{
"type": "FeatureCollection",
"features": [
	{"geometry":{"coordinates":[-2.939059,52.873247],"type":"Point"},"properties":{"name":"Weston Arm Rubbish Disposal","osm_id":"1382924020","tag":{"access":"permissive","amenity":"waste_disposal","centralkey":"no","operator":"Canal and River Trust","waste":"trash","waterway":"waste_disposal"}},"type":"Feature"}
]
}
