{
"type": "FeatureCollection",
"lastupdate": "2020-08-06T00:00:00Z",
"features": [
	{"geometry":{"coordinates":[-2.979337,47.908449],"type":"Point"},"properties":{"osm_id":"3440691397","tag":{"amenity":"recycling","recycling:glass":"yes","recycling_type":"container"}},"type":"Feature"},
	{"geometry":{"coordinates":[-2.977554,47.906165],"type":"Point"},"properties":{"osm_id":"6691184965","tag":{"amenity":"waste_basket"}},"type":"Feature"},
	{"geometry":{"coordinates":[-2.976798,47.906068],"type":"Point"},"properties":{"osm_id":"6702742778","tag":{"amenity":"waste_basket"}},"type":"Feature"},
	{"geometry":{"coordinates":[-2.977358,47.905961],"type":"Point"},"properties":{"osm_id":"6702742779","tag":{"amenity":"waste_basket"}},"type":"Feature"},
	{"geometry":{"coordinates":[-2.976604,47.908066],"type":"Point"},"properties":{"osm_id":"6702787287","tag":{"amenity":"recycling","location":"underground","operator":"CCM","recycling:beverage_carton":"yes","recycling:cans":"yes","recycling:glass_bottles":"yes","recycling:magazines":"yes","recycling:paper":"yes","recycling:plastic_bottles":"yes","recycling:plastic_packaging":"yes","recycling_type":"container"}},"type":"Feature"},
	{"geometry":{"coordinates":[-2.980994,47.905957],"type":"Point"},"properties":{"osm_id":"6935851046","tag":{"amenity":"recycling","location":"underground","operator":"CCM","recycling:cans":"yes","recycling:glass_bottles":"yes","recycling:magazines":"yes","recycling:newspaper":"yes","recycling:paper":"yes","recycling:plastic_bottles":"yes","recycling:waste":"yes","recycling_type":"container"}},"type":"Feature"},
	{"geometry":{"coordinates":[-2.98259,47.908418],"type":"Point"},"properties":{"osm_id":"6935886114","tag":{"amenity":"recycling","location":"underground","operator":"CCM","recycling:beverage_carton":"yes","recycling:paper_packaging":"yes","recycling:plastic_bags":"yes","recycling:waste":"yes","recycling_type":"container"}},"type":"Feature"},
	{"geometry":{"coordinates":[-2.978788,47.905844],"type":"Point"},"properties":{"osm_id":"6935891526","tag":{"amenity":"recycling","location":"underground","recycling:beverage_carton":"yes","recycling:paper_packaging":"yes","recycling:plastic_bottles":"yes","recycling:waste":"yes","recycling_type":"container"}},"type":"Feature"},
	{"geometry":{"coordinates":[-2.980263,47.908008],"type":"Point"},"properties":{"osm_id":"7023801697","tag":{"amenity":"recycling","location":"underground","operator":"CCM","recycling:cans":"yes","recycling:glass_bottles":"yes","recycling:magazines":"yes","recycling:newspaper":"yes","recycling:paper":"yes","recycling:plastic_bottles":"yes","recycling:waste":"yes","recycling_type":"container"}},"type":"Feature"},
	{"geometry":{"coordinates":[-2.974293,47.90961],"type":"Point"},"properties":{"osm_id":"7183732988","tag":{"amenity":"recycling","location":"underground","operator":"CCM","recycling:beverage_carton":"yes","recycling:paper_packaging":"yes","recycling:plastic_bags":"yes","recycling:waste":"yes","recycling_type":"container"}},"type":"Feature"}
]
}
