{
"type": "FeatureCollection",
"lastupdate": "2020-08-01T00:00:00Z",
"features": [
	{"geometry":{"coordinates":[-2.934946,43.243178],"type":"Point"},"properties":{"name":"Garbigune Larraskitu","osm_id":"1048044143","tag":{"amenity":"recycling"}},"type":"Feature"},
	{"geometry":{"coordinates":[-2.987222,43.240866],"type":"Point"},"properties":{"osm_id":"2772386609","tag":{"amenity":"recycling","recycling:cans":"yes","recycling:paper":"yes"}},"type":"Feature"},
	{"geometry":{"coordinates":[-2.924468,43.258405],"type":"Point"},"properties":{"osm_id":"2813269285","tag":{"amenity":"waste_basket"}},"type":"Feature"},
	{"geometry":{"coordinates":[-2.915115,43.256303],"type":"Point"},"properties":{"osm_id":"3573290607","tag":{"amenity":"waste_basket"}},"type":"Feature"},
	{"geometry":{"coordinates":[-2.915301,43.256365],"type":"Point"},"properties":{"osm_id":"3573290615","tag":{"amenity":"waste_basket"}},"type":"Feature"},
	{"geometry":{"coordinates":[-2.915008,43.256377],"type":"Point"},"properties":{"osm_id":"3573290619","tag":{"amenity":"waste_basket"}},"type":"Feature"},
	{"geometry":{"coordinates":[-2.915732,43.256649],"type":"Point"},"properties":{"osm_id":"3573290642","tag":{"amenity":"waste_basket"}},"type":"Feature"},
	{"geometry":{"coordinates":[-2.915578,43.256708],"type":"Point"},"properties":{"osm_id":"3573290646","tag":{"amenity":"waste_basket"}},"type":"Feature"},
	{"geometry":{"coordinates":[-2.914451,43.253022],"type":"Point"},"properties":{"osm_id":"3744428856","tag":{"amenity":"waste_basket"}},"type":"Feature"},
	{"geometry":{"coordinates":[-2.913458,43.253158],"type":"Point"},"properties":{"osm_id":"3744428874","tag":{"amenity":"waste_basket"}},"type":"Feature"},
	{"geometry":{"coordinates":[-2.91459,43.253208],"type":"Point"},"properties":{"osm_id":"3744428879","tag":{"amenity":"waste_basket"}},"type":"Feature"},
	{"geometry":{"coordinates":[-2.914514,43.253273],"type":"Point"},"properties":{"osm_id":"3744428885","tag":{"amenity":"waste_basket"}},"type":"Feature"},
	{"geometry":{"coordinates":[-2.914736,43.253395],"type":"Point"},"properties":{"osm_id":"3744428897","tag":{"amenity":"waste_basket"}},"type":"Feature"},
	{"geometry":{"coordinates":[-2.914064,43.252304],"type":"Point"},"properties":{"osm_id":"3744497890","tag":{"amenity":"waste_basket"}},"type":"Feature"},
	{"geometry":{"coordinates":[-2.913869,43.252424],"type":"Point"},"properties":{"osm_id":"3744497919","tag":{"amenity":"waste_basket"}},"type":"Feature"},
	{"geometry":{"coordinates":[-2.914218,43.252499],"type":"Point"},"properties":{"osm_id":"3744502236","tag":{"amenity":"waste_basket"}},"type":"Feature"},
	{"geometry":{"coordinates":[-2.914018,43.252532],"type":"Point"},"properties":{"osm_id":"3744502244","tag":{"amenity":"waste_basket"}},"type":"Feature"},
	{"geometry":{"coordinates":[-2.987971,43.245516],"type":"Point"},"properties":{"osm_id":"3793820693","tag":{"amenity":"recycling","recycling:cans":"no","recycling:clothes":"yes","recycling:glass":"no","recycling:glass_bottles":"no","recycling:paper":"no","recycling:plastic":"no","recycling_type":"container"}},"type":"Feature"},
	{"geometry":{"coordinates":[-2.922709,43.259617],"type":"Point"},"properties":{"osm_id":"4701494366","tag":{"amenity":"recycling","recycling_type":"container"}},"type":"Feature"},
	{"geometry":{"coordinates":[-2.92308,43.258541],"type":"Point"},"properties":{"osm_id":"4701570962","tag":{"amenity":"waste_basket"}},"type":"Feature"},
	{"geometry":{"coordinates":[-2.926513,43.258576],"type":"Point"},"properties":{"osm_id":"4703598547","tag":{"amenity":"recycling","recycling_type":"container"}},"type":"Feature"},
	{"geometry":{"coordinates":[-2.935795,43.26079],"type":"Point"},"properties":{"osm_id":"4723777456","tag":{"amenity":"recycling","recycling_type":"container"}},"type":"Feature"},
	{"geometry":{"coordinates":[-2.930819,43.260932],"type":"Point"},"properties":{"osm_id":"4723870065","tag":{"amenity":"recycling","recycling:cans":"yes","recycling:glass_bottles":"yes","recycling:green_waste":"yes","recycling:paper":"yes","recycling:plastic":"no","recycling:plastic_packaging":"yes","recycling_type":"container"}},"type":"Feature"},
	{"geometry":{"coordinates":[-2.93206,43.257],"type":"Point"},"properties":{"osm_id":"4738272339","tag":{"amenity":"waste_basket"}},"type":"Feature"},
	{"geometry":{"coordinates":[-2.927207,43.257073],"type":"Point"},"properties":{"osm_id":"4739796159","tag":{"amenity":"waste_basket"}},"type":"Feature"},
	{"geometry":{"coordinates":[-2.926441,43.259606],"type":"Point"},"properties":{"osm_id":"4739821707","tag":{"amenity":"recycling","recycling_type":"container"}},"type":"Feature"},
	{"geometry":{"coordinates":[-2.905707,43.250853],"type":"Point"},"properties":{"osm_id":"6790214928","tag":{"amenity":"waste_basket","waste":"trash"}},"type":"Feature"},
	{"geometry":{"coordinates":[-2.905413,43.250964],"type":"Point"},"properties":{"osm_id":"6790214929","tag":{"amenity":"waste_basket","waste":"trash"}},"type":"Feature"}
]
}
