{
"type": "FeatureCollection",
"features": [
	{"geometry":{"coordinates":[17.218732,40.651379],"type":"Point"},"properties":{"name":"albero del capitano","osm_id":"4066728033","tag":{"natural":"tree"}},"type":"Feature"},
	{"geometry":{"coordinates":[17.207057,40.653406],"type":"Point"},"properties":{"name":"albero monumentale","osm_id":"4099675013","tag":{"natural":"tree"}},"type":"Feature"}
]
}
