{
"type": "FeatureCollection",
"features": [
	{"geometry":{"coordinates":[17.218732,40.651379],"type":"Point"},"properties":{"name":"Leccio secolare","osm_id":"4066728033","tag":{"natural":"tree"}},"type":"Feature"},
	{"geometry":{"coordinates":[17.20702,40.653516],"type":"Point"},"properties":{"name":"albero del Capitano","osm_id":"4099675013","tag":{"natural":"tree"}},"type":"Feature"}
]
}
