{
"type": "FeatureCollection",
"features": [
	{"geometry":{"coordinates":[17.218733,40.65138],"type":"Point"},"properties":{"name":"albero del capitano","osm_id":"4066728033","tag":{"natural":"tree"}},"type":"Feature"},
	{"geometry":{"coordinates":[17.207058,40.653407],"type":"Point"},"properties":{"name":"albero monumentale","osm_id":"4099675013","tag":{"natural":"tree"}},"type":"Feature"}
]
}
