{
"type": "FeatureCollection",
"features": [
	{"geometry":{"coordinates":[-71.294006,-32.450502],"type":"Point"},"properties":{"osm_id":"6293308086","tag":{"denotation":"park","natural":"tree","object:city":"La Chimba"}},"type":"Feature"},
	{"geometry":{"coordinates":[-71.293238,-32.450767],"type":"Point"},"properties":{"osm_id":"6293308087","tag":{"denotation":"park","natural":"tree","object:city":"La Ligua"}},"type":"Feature"},
	{"geometry":{"coordinates":[-71.293575,-32.450605],"type":"Point"},"properties":{"osm_id":"6293308088","tag":{"denotation":"park","natural":"tree","object:city":"La Chimba"}},"type":"Feature"},
	{"geometry":{"coordinates":[-71.293823,-32.450642],"type":"Point"},"properties":{"osm_id":"6293308089","tag":{"denotation":"park","natural":"tree","object:city":"La Chimba"}},"type":"Feature"},
	{"geometry":{"coordinates":[-71.293936,-32.450576],"type":"Point"},"properties":{"osm_id":"6293308090","tag":{"denotation":"park","natural":"tree","object:city":"La Chimba"}},"type":"Feature"},
	{"geometry":{"coordinates":[-71.293998,-32.450633],"type":"Point"},"properties":{"osm_id":"6293308091","tag":{"denotation":"park","natural":"tree","object:city":"La Chimba"}},"type":"Feature"},
	{"geometry":{"coordinates":[-71.294059,-32.450737],"type":"Point"},"properties":{"osm_id":"6293308092","tag":{"denotation":"park","natural":"tree","object:city":"La Chimba"}},"type":"Feature"},
	{"geometry":{"coordinates":[-71.293997,-32.450794],"type":"Point"},"properties":{"osm_id":"6293308093","tag":{"denotation":"park","natural":"tree","object:city":"La Chimba"}},"type":"Feature"},
	{"geometry":{"coordinates":[-71.293864,-32.450854],"type":"Point"},"properties":{"osm_id":"6293308094","tag":{"denotation":"park","natural":"tree","object:city":"La Chimba"}},"type":"Feature"},
	{"geometry":{"coordinates":[-71.29374,-32.451068],"type":"Point"},"properties":{"osm_id":"6293308095","tag":{"denotation":"park","natural":"tree","object:city":"La Chimba"}},"type":"Feature"},
	{"geometry":{"coordinates":[-71.293749,-32.451239],"type":"Point"},"properties":{"osm_id":"6293308096","tag":{"denotation":"park","natural":"tree","object:city":"La Chimba"}},"type":"Feature"},
	{"geometry":{"coordinates":[-71.293919,-32.450724],"type":"Point"},"properties":{"osm_id":"6293308097","tag":{"denotation":"park","natural":"tree","object:city":"La Chimba"}},"type":"Feature"},
	{"geometry":{"coordinates":[-71.29406,-32.450361],"type":"Point"},"properties":{"osm_id":"6293308098","tag":{"denotation":"park","natural":"tree","object:city":"La Chimba"}},"type":"Feature"},
	{"geometry":{"coordinates":[-71.293913,-32.450378],"type":"Point"},"properties":{"osm_id":"6293308099","tag":{"denotation":"park","natural":"tree","object:city":"La Chimba"}},"type":"Feature"},
	{"geometry":{"coordinates":[-71.293749,-32.450401],"type":"Point"},"properties":{"osm_id":"6293308100","tag":{"denotation":"park","natural":"tree","object:city":"La Chimba"}},"type":"Feature"},
	{"geometry":{"coordinates":[-71.293565,-32.450418],"type":"Point"},"properties":{"osm_id":"6293308101","tag":{"denotation":"park","natural":"tree","object:city":"La Chimba"}},"type":"Feature"},
	{"geometry":{"coordinates":[-71.293675,-32.45089],"type":"Point"},"properties":{"osm_id":"6293308102","tag":{"denotation":"park","natural":"tree","object:city":"La Chimba"}},"type":"Feature"},
	{"geometry":{"coordinates":[-71.293601,-32.45092],"type":"Point"},"properties":{"osm_id":"6293308103","tag":{"denotation":"park","natural":"tree","object:city":"La Chimba"}},"type":"Feature"},
	{"geometry":{"coordinates":[-71.293662,-32.450819],"type":"Point"},"properties":{"osm_id":"6293308104","tag":{"denotation":"park","natural":"tree","object:city":"La Chimba"}},"type":"Feature"}
]
}
