{
"type": "FeatureCollection",
"features": [
	{"geometry":{"coordinates":[-71.294005,-32.450501],"type":"Point"},"properties":{"osm_id":"6293308086","tag":{"denotation":"park","natural":"tree","object:city":"La Chimba"}},"type":"Feature"},
	{"geometry":{"coordinates":[-71.293237,-32.450767],"type":"Point"},"properties":{"osm_id":"6293308087","tag":{"denotation":"park","natural":"tree","object:city":"La Ligua"}},"type":"Feature"},
	{"geometry":{"coordinates":[-71.293574,-32.450605],"type":"Point"},"properties":{"osm_id":"6293308088","tag":{"denotation":"park","natural":"tree","object:city":"La Chimba"}},"type":"Feature"},
	{"geometry":{"coordinates":[-71.293823,-32.450641],"type":"Point"},"properties":{"osm_id":"6293308089","tag":{"denotation":"park","natural":"tree","object:city":"La Chimba"}},"type":"Feature"},
	{"geometry":{"coordinates":[-71.293936,-32.450576],"type":"Point"},"properties":{"osm_id":"6293308090","tag":{"denotation":"park","natural":"tree","object:city":"La Chimba"}},"type":"Feature"},
	{"geometry":{"coordinates":[-71.293998,-32.450632],"type":"Point"},"properties":{"osm_id":"6293308091","tag":{"denotation":"park","natural":"tree","object:city":"La Chimba"}},"type":"Feature"},
	{"geometry":{"coordinates":[-71.294058,-32.450737],"type":"Point"},"properties":{"osm_id":"6293308092","tag":{"denotation":"park","natural":"tree","object:city":"La Chimba"}},"type":"Feature"},
	{"geometry":{"coordinates":[-71.293996,-32.450793],"type":"Point"},"properties":{"osm_id":"6293308093","tag":{"denotation":"park","natural":"tree","object:city":"La Chimba"}},"type":"Feature"},
	{"geometry":{"coordinates":[-71.293863,-32.450853],"type":"Point"},"properties":{"osm_id":"6293308094","tag":{"denotation":"park","natural":"tree","object:city":"La Chimba"}},"type":"Feature"},
	{"geometry":{"coordinates":[-71.29374,-32.451068],"type":"Point"},"properties":{"osm_id":"6293308095","tag":{"denotation":"park","natural":"tree","object:city":"La Chimba"}},"type":"Feature"},
	{"geometry":{"coordinates":[-71.293749,-32.451238],"type":"Point"},"properties":{"osm_id":"6293308096","tag":{"denotation":"park","natural":"tree","object:city":"La Chimba"}},"type":"Feature"},
	{"geometry":{"coordinates":[-71.293919,-32.450723],"type":"Point"},"properties":{"osm_id":"6293308097","tag":{"denotation":"park","natural":"tree","object:city":"La Chimba"}},"type":"Feature"},
	{"geometry":{"coordinates":[-71.294059,-32.45036],"type":"Point"},"properties":{"osm_id":"6293308098","tag":{"denotation":"park","natural":"tree","object:city":"La Chimba"}},"type":"Feature"},
	{"geometry":{"coordinates":[-71.293912,-32.450377],"type":"Point"},"properties":{"osm_id":"6293308099","tag":{"denotation":"park","natural":"tree","object:city":"La Chimba"}},"type":"Feature"},
	{"geometry":{"coordinates":[-71.293749,-32.4504],"type":"Point"},"properties":{"osm_id":"6293308100","tag":{"denotation":"park","natural":"tree","object:city":"La Chimba"}},"type":"Feature"},
	{"geometry":{"coordinates":[-71.293565,-32.450417],"type":"Point"},"properties":{"osm_id":"6293308101","tag":{"denotation":"park","natural":"tree","object:city":"La Chimba"}},"type":"Feature"},
	{"geometry":{"coordinates":[-71.293675,-32.450889],"type":"Point"},"properties":{"osm_id":"6293308102","tag":{"denotation":"park","natural":"tree","object:city":"La Chimba"}},"type":"Feature"},
	{"geometry":{"coordinates":[-71.293601,-32.450919],"type":"Point"},"properties":{"osm_id":"6293308103","tag":{"denotation":"park","natural":"tree","object:city":"La Chimba"}},"type":"Feature"},
	{"geometry":{"coordinates":[-71.293661,-32.450818],"type":"Point"},"properties":{"osm_id":"6293308104","tag":{"denotation":"park","natural":"tree","object:city":"La Chimba"}},"type":"Feature"}
]
}
