{
"type": "FeatureCollection",
"features": [
	{"geometry":{"coordinates":[20.43591,46.60445],"type":"Point"},"properties":{"name":"Horthy-fa","osm_id":"8836795516","tag":{"historic":"yes","natural":"tree"}},"type":"Feature"}
]
}
