{
"type": "FeatureCollection",
"lastupdate": "2020-08-04T00:00:00Z",
"features": [
	{"geometry":{"coordinates":[21.08689,55.731265],"type":"Point"},"properties":{"osm_id":"1574595927","tag":{"amenity":"recycling","recycling:glass_bottles":"yes","recycling:paper":"yes","recycling:plastic":"yes","recycling_type":"container"}},"type":"Feature"},
	{"geometry":{"coordinates":[21.091419,55.765684],"type":"Point"},"properties":{"osm_id":"3701732020","tag":{"amenity":"recycling","recycling:cans":"yes","recycling:glass_bottles":"yes","recycling_type":"container"}},"type":"Feature"},
	{"geometry":{"coordinates":[21.093129,55.737274],"type":"Point"},"properties":{"name":"Maxima taromatas","osm_id":"4320503898","tag":{"amenity":"recycling","recycling:cans":"yes","recycling:glass_bottles":"yes","recycling:plastic_bottles":"yes"}},"type":"Feature"},
	{"geometry":{"coordinates":[21.083969,55.761807],"type":"Point"},"properties":{"osm_id":"4732460759","tag":{"amenity":"recycling","recycling_type":"container"}},"type":"Feature"}
]
}
