{
"type": "FeatureCollection",
"features": [
	{"geometry":{"coordinates":[138.711383,-35.02736],"type":"Point"},"properties":{"name":"Heathfield Resource Recovery Centre","osm_id":"3353764814","tag":{"addr:housenumber":"32","addr:postcode":"5153","addr:state":"SA","addr:street":"Scott Creet Road","addr:suburb":"Scott Creek","amenity":"recycling","opening_hours":"Mo-Fr 07:30-16:00, Sa-Su 09:00-16:00","operator":"Adelaide Hills Council","operator:type":"public","recycling_type":"centre","website":"https://www.ahrwma.com/heathfield-transfer-station"}},"type":"Feature"},
	{"geometry":{"coordinates":[138.710757,-34.989421],"type":"Point"},"properties":{"osm_id":"8953044260","tag":{"amenity":"waste_basket"}},"type":"Feature"},
	{"geometry":{"coordinates":[138.711478,-34.989832],"type":"Point"},"properties":{"osm_id":"8953044269","tag":{"amenity":"waste_basket"}},"type":"Feature"}
]
}
