{
"type": "FeatureCollection",
"lastupdate": "2020-08-03T00:00:00Z",
"features": [
	{"geometry":{"coordinates":[138.711383,-35.02736],"type":"Point"},"properties":{"name":"Heathfield Resource Recovery Centre","osm_id":"3353764814","tag":{"addr:housenumber":"32","addr:postcode":"5153","addr:state":"SA","addr:street":"Scott Creet Road","addr:suburb":"Scott Creek","amenity":"recycling","opening_hours":"Mo-Fr 07:30-16:00, Sa-Su 09:00-16:00","operator":"Adelaide Hills Council","operator:type":"public","recycling_type":"centre","website":"https://www.ahrwma.com/heathfield-transfer-station"}},"type":"Feature"}
]
}
