{
"type": "FeatureCollection",
"features": [
	{"geometry":{"coordinates":[152.96505,-27.539324],"type":"Point"},"properties":{"osm_id":"335329309","tag":{"amenity":"waste_basket","waste":"dog_waste"}},"type":"Feature"},
	{"geometry":{"coordinates":[152.948859,-27.533765],"type":"Point"},"properties":{"osm_id":"5740046803","tag":{"amenity":"waste_basket"}},"type":"Feature"},
	{"geometry":{"coordinates":[152.948655,-27.533551],"type":"Point"},"properties":{"osm_id":"5740046954","tag":{"amenity":"waste_basket"}},"type":"Feature"},
	{"geometry":{"coordinates":[152.948705,-27.533441],"type":"Point"},"properties":{"osm_id":"5740047053","tag":{"amenity":"waste_basket"}},"type":"Feature"},
	{"geometry":{"coordinates":[152.948765,-27.53324],"type":"Point"},"properties":{"osm_id":"5740047054","tag":{"amenity":"waste_basket"}},"type":"Feature"},
	{"geometry":{"coordinates":[152.962634,-27.542998],"type":"Point"},"properties":{"osm_id":"5935780245","tag":{"amenity":"waste_basket","waste":"trash"}},"type":"Feature"},
	{"geometry":{"coordinates":[152.96368,-27.54371],"type":"Point"},"properties":{"osm_id":"5935873525","tag":{"amenity":"waste_basket","waste":"trash"}},"type":"Feature"},
	{"geometry":{"coordinates":[152.963675,-27.54371],"type":"Point"},"properties":{"osm_id":"5935876524","tag":{"amenity":"recycling"}},"type":"Feature"},
	{"geometry":{"coordinates":[152.963684,-27.54371],"type":"Point"},"properties":{"osm_id":"5935876525","tag":{"amenity":"waste_basket","waste":"trash"}},"type":"Feature"},
	{"geometry":{"coordinates":[152.9633,-27.543503],"type":"Point"},"properties":{"osm_id":"5935876526","tag":{"amenity":"recycling"}},"type":"Feature"},
	{"geometry":{"coordinates":[152.963297,-27.543503],"type":"Point"},"properties":{"osm_id":"5935876528","tag":{"amenity":"waste_basket"}},"type":"Feature"},
	{"geometry":{"coordinates":[152.961762,-27.541749],"type":"Point"},"properties":{"osm_id":"5935929680","tag":{"amenity":"recycling"}},"type":"Feature"},
	{"geometry":{"coordinates":[152.961752,-27.541757],"type":"Point"},"properties":{"osm_id":"5935929681","tag":{"amenity":"waste_basket"}},"type":"Feature"},
	{"geometry":{"coordinates":[152.961749,-27.541763],"type":"Point"},"properties":{"osm_id":"5935929682","tag":{"amenity":"waste_basket"}},"type":"Feature"},
	{"geometry":{"coordinates":[152.97339,-27.531974],"type":"Point"},"properties":{"osm_id":"6392983002","tag":{"amenity":"waste_disposal"}},"type":"Feature"},
	{"geometry":{"coordinates":[152.974325,-27.532761],"type":"Point"},"properties":{"osm_id":"6392983008","tag":{"amenity":"waste_disposal"}},"type":"Feature"},
	{"geometry":{"coordinates":[152.974262,-27.529707],"type":"Point"},"properties":{"osm_id":"6397466811","tag":{"amenity":"waste_disposal"}},"type":"Feature"},
	{"geometry":{"coordinates":[152.972348,-27.531452],"type":"Point"},"properties":{"osm_id":"6397466812","tag":{"amenity":"waste_disposal"}},"type":"Feature"},
	{"geometry":{"coordinates":[152.977432,-27.532339],"type":"Point"},"properties":{"osm_id":"6397466813","tag":{"amenity":"waste_disposal"}},"type":"Feature"},
	{"geometry":{"coordinates":[152.973614,-27.532837],"type":"Point"},"properties":{"osm_id":"6397466814","tag":{"amenity":"waste_disposal"}},"type":"Feature"},
	{"geometry":{"coordinates":[152.973031,-27.529923],"type":"Point"},"properties":{"osm_id":"6397466816","tag":{"amenity":"waste_disposal"}},"type":"Feature"},
	{"geometry":{"coordinates":[152.973154,-27.532077],"type":"Point"},"properties":{"osm_id":"6397466817","tag":{"amenity":"waste_disposal"}},"type":"Feature"},
	{"geometry":{"coordinates":[152.957204,-27.541338],"type":"Point"},"properties":{"name":"TOMRA","osm_id":"7412956206","tag":{"addr:housenumber":"9","addr:state":"QLD","addr:street":"Counihan Road","addr:suburb":"Seventeen Mile Rocks","amenity":"recycling","opening_hours":"Mo-Su 07:00-18:00","recycling:beverage_cartons":"yes","recycling:cans":"yes","recycling:glass_bottles":"yes","recycling:plastic_bottles":"yes","recycling_type":"centre","website":"https://www.mytomra.com.au/seventeen-mile-rocks/"}},"type":"Feature"},
	{"geometry":{"coordinates":[152.951589,-27.565859],"type":"Point"},"properties":{"osm_id":"7792929285","tag":{"amenity":"waste_basket"}},"type":"Feature"}
]
}
