{
"type": "FeatureCollection",
"features": [
	{"geometry":{"coordinates":[152.965049,-27.539324],"type":"Point"},"properties":{"osm_id":"335329309","tag":{"amenity":"waste_basket","waste":"dog_waste"}},"type":"Feature"},
	{"geometry":{"coordinates":[152.948859,-27.533764],"type":"Point"},"properties":{"osm_id":"5740046803","tag":{"amenity":"waste_basket"}},"type":"Feature"},
	{"geometry":{"coordinates":[152.948655,-27.533551],"type":"Point"},"properties":{"osm_id":"5740046954","tag":{"amenity":"waste_basket"}},"type":"Feature"},
	{"geometry":{"coordinates":[152.948705,-27.533441],"type":"Point"},"properties":{"osm_id":"5740047053","tag":{"amenity":"waste_basket"}},"type":"Feature"},
	{"geometry":{"coordinates":[152.948765,-27.533239],"type":"Point"},"properties":{"osm_id":"5740047054","tag":{"amenity":"waste_basket"}},"type":"Feature"},
	{"geometry":{"coordinates":[152.962634,-27.542997],"type":"Point"},"properties":{"osm_id":"5935780245","tag":{"amenity":"waste_basket","waste":"trash"}},"type":"Feature"},
	{"geometry":{"coordinates":[152.963679,-27.54371],"type":"Point"},"properties":{"osm_id":"5935873525","tag":{"amenity":"waste_basket","waste":"trash"}},"type":"Feature"},
	{"geometry":{"coordinates":[152.963675,-27.54371],"type":"Point"},"properties":{"osm_id":"5935876524","tag":{"amenity":"recycling"}},"type":"Feature"},
	{"geometry":{"coordinates":[152.963683,-27.54371],"type":"Point"},"properties":{"osm_id":"5935876525","tag":{"amenity":"waste_basket","waste":"trash"}},"type":"Feature"},
	{"geometry":{"coordinates":[152.9633,-27.543503],"type":"Point"},"properties":{"osm_id":"5935876526","tag":{"amenity":"recycling"}},"type":"Feature"},
	{"geometry":{"coordinates":[152.963296,-27.543502],"type":"Point"},"properties":{"osm_id":"5935876528","tag":{"amenity":"waste_basket"}},"type":"Feature"},
	{"geometry":{"coordinates":[152.961762,-27.541749],"type":"Point"},"properties":{"osm_id":"5935929680","tag":{"amenity":"recycling"}},"type":"Feature"},
	{"geometry":{"coordinates":[152.961752,-27.541757],"type":"Point"},"properties":{"osm_id":"5935929681","tag":{"amenity":"waste_basket"}},"type":"Feature"},
	{"geometry":{"coordinates":[152.961748,-27.541762],"type":"Point"},"properties":{"osm_id":"5935929682","tag":{"amenity":"waste_basket"}},"type":"Feature"},
	{"geometry":{"coordinates":[152.973389,-27.531974],"type":"Point"},"properties":{"osm_id":"6392983002","tag":{"amenity":"waste_disposal"}},"type":"Feature"},
	{"geometry":{"coordinates":[152.974324,-27.53276],"type":"Point"},"properties":{"osm_id":"6392983008","tag":{"amenity":"waste_disposal"}},"type":"Feature"},
	{"geometry":{"coordinates":[152.974262,-27.529706],"type":"Point"},"properties":{"osm_id":"6397466811","tag":{"amenity":"waste_disposal"}},"type":"Feature"},
	{"geometry":{"coordinates":[152.972347,-27.531452],"type":"Point"},"properties":{"osm_id":"6397466812","tag":{"amenity":"waste_disposal"}},"type":"Feature"},
	{"geometry":{"coordinates":[152.977432,-27.532339],"type":"Point"},"properties":{"osm_id":"6397466813","tag":{"amenity":"waste_disposal"}},"type":"Feature"},
	{"geometry":{"coordinates":[152.973613,-27.532836],"type":"Point"},"properties":{"osm_id":"6397466814","tag":{"amenity":"waste_disposal"}},"type":"Feature"},
	{"geometry":{"coordinates":[152.97303,-27.529922],"type":"Point"},"properties":{"osm_id":"6397466816","tag":{"amenity":"waste_disposal"}},"type":"Feature"},
	{"geometry":{"coordinates":[152.973153,-27.532076],"type":"Point"},"properties":{"osm_id":"6397466817","tag":{"amenity":"waste_disposal"}},"type":"Feature"},
	{"geometry":{"coordinates":[152.957203,-27.541337],"type":"Point"},"properties":{"name":"TOMRA","osm_id":"7412956206","tag":{"addr:housenumber":"9","addr:state":"QLD","addr:street":"Counihan Road","addr:suburb":"Seventeen Mile Rocks","amenity":"recycling","opening_hours":"Mo-Su 07:00-18:00","recycling:beverage_cartons":"yes","recycling:cans":"yes","recycling:glass_bottles":"yes","recycling:plastic_bottles":"yes","recycling_type":"centre","website":"https://www.mytomra.com.au/seventeen-mile-rocks/"}},"type":"Feature"},
	{"geometry":{"coordinates":[152.951588,-27.565859],"type":"Point"},"properties":{"osm_id":"7792929285","tag":{"amenity":"waste_basket"}},"type":"Feature"},
	{"geometry":{"coordinates":[153.016605,-27.552732],"type":"Point"},"properties":{"osm_id":"9024061508","tag":{"amenity":"waste_basket"}},"type":"Feature"},
	{"geometry":{"coordinates":[153.016421,-27.552375],"type":"Point"},"properties":{"osm_id":"9024061513","tag":{"amenity":"waste_basket"}},"type":"Feature"}
]
}
