{
"type": "FeatureCollection",
"lastupdate": "2020-07-31T00:00:00Z",
"features": [
	{"geometry":{"coordinates":[-79.859715,-6.779084],"type":"Point"},"properties":{"name":"Naranjos","osm_id":"4715750689","tag":{"amenity":"recycling","name:es":"Naranjos"}},"type":"Feature"}
]
}
