{
"type": "FeatureCollection",
"features": [
	{"geometry":{"coordinates":[-2.760307,37.464327],"type":"Point"},"properties":{"name":"Encina de la Vega de Baza","osm_id":"3078600768","tag":{"denotation":"natural_monument","monument":"yes","natural":"tree"}},"type":"Feature"}
]
}
