{
"type": "FeatureCollection",
"features": [
	{"geometry":{"coordinates":[-4.449811,58.498246],"type":"Point"},"properties":{"osm_id":"4258149525","tag":{"amenity":"recycling"}},"type":"Feature"},
	{"geometry":{"coordinates":[-4.459869,58.496412],"type":"Point"},"properties":{"name":"Tongue Recycling Centre","osm_id":"9151220051","tag":{"amenity":"recycling","owner":"Highland Council","ownership":"municipal","recycling_type":"centre","wikidata":"Q106085781"}},"type":"Feature"}
]
}
