{
"type": "FeatureCollection",
"features": [
	{"geometry":{"coordinates":[-49.956569,-23.146935],"type":"Point"},"properties":{"name":"antiga triparia","osm_id":"6554128504","tag":{"leaf_cycle":"evergreen","leaf_type":"broadleaved","natural":"tree"}},"type":"Feature"}
]
}
