{
"type": "FeatureCollection",
"features": [
	{"geometry":{"coordinates":[-94.6969,38.372504],"type":"Point"},"properties":{"name":"Linn Valley Lakes POA Dumpster","osm_id":"4799418356","tag":{"amenity":"waste_disposal"}},"type":"Feature"},
	{"geometry":{"coordinates":[-94.745677,38.345961],"type":"Point"},"properties":{"osm_id":"7027105488","tag":{"amenity":"waste_disposal"}},"type":"Feature"}
]
}
