{
"type": "FeatureCollection",
"features": [
	{"geometry":{"coordinates":[-52.27371,4.898886],"type":"Point"},"properties":{"osm_id":"2680896179","tag":{"amenity":"recycling","operator":"CACL","recycling:glass_bottles":"yes","recycling_type":"container"}},"type":"Feature"},
	{"geometry":{"coordinates":[-52.279741,4.913753],"type":"Point"},"properties":{"osm_id":"2965195137","tag":{"amenity":"recycling","recycling:glass_bottles":"yes","recycling_type":"container"}},"type":"Feature"},
	{"geometry":{"coordinates":[-52.277257,4.911501],"type":"Point"},"properties":{"osm_id":"3098698823","tag":{"amenity":"recycling","operator":"CACL","recycling:glass_bottles":"yes","recycling_type":"container"}},"type":"Feature"},
	{"geometry":{"coordinates":[-52.283451,4.912495],"type":"Point"},"properties":{"name":"Association GuyaClic' - Atelier Recycl'Ordi","osm_id":"5548382443","tag":{"amenity":"recycling","building:levels":"0","email":"guyaclic@groupe-diverscite.fr","opening_hours":"Mo-Fr 08:00-16:00","recycling:computers":"yes","recycling_type":"centre","smoking":"no"}},"type":"Feature"},
	{"geometry":{"coordinates":[-52.260317,4.894884],"type":"Point"},"properties":{"osm_id":"5749362538","tag":{"amenity":"recycling","operator":"CACL","recycling:glass_bottles":"yes","recycling_type":"container"}},"type":"Feature"},
	{"geometry":{"coordinates":[-52.286258,4.909384],"type":"Point"},"properties":{"osm_id":"5823952234","tag":{"amenity":"recycling","operator":"CACL","recycling:glass_bottles":"yes","recycling_type":"container"}},"type":"Feature"},
	{"geometry":{"coordinates":[-52.270644,4.858507],"type":"Point"},"properties":{"osm_id":"5835260321","tag":{"amenity":"recycling","recycling:glass_bottles":"yes","recycling_type":"container","source:position":"GPS"}},"type":"Feature"},
	{"geometry":{"coordinates":[-52.280167,4.882559],"type":"Point"},"properties":{"osm_id":"5835260327","tag":{"amenity":"recycling","recycling:glass_bottles":"yes","recycling_type":"container","source:position":"GPS"}},"type":"Feature"},
	{"geometry":{"coordinates":[-52.278583,4.907949],"type":"Point"},"properties":{"osm_id":"5896692930","tag":{"amenity":"waste_basket","source:position":"GPS"}},"type":"Feature"},
	{"geometry":{"coordinates":[-52.272266,4.912431],"type":"Point"},"properties":{"osm_id":"6593751299","tag":{"amenity":"waste_basket"}},"type":"Feature"},
	{"geometry":{"coordinates":[-52.27235,4.912597],"type":"Point"},"properties":{"osm_id":"6593751300","tag":{"amenity":"waste_basket"}},"type":"Feature"},
	{"geometry":{"coordinates":[-52.272182,4.912518],"type":"Point"},"properties":{"osm_id":"6593751301","tag":{"amenity":"waste_basket"}},"type":"Feature"},
	{"geometry":{"coordinates":[-52.272116,4.912355],"type":"Point"},"properties":{"osm_id":"6593751302","tag":{"amenity":"waste_basket"}},"type":"Feature"},
	{"geometry":{"coordinates":[-52.279954,4.887449],"type":"Point"},"properties":{"osm_id":"7298056124","tag":{"amenity":"recycling","recycling:glass":"yes","recycling_type":"container"}},"type":"Feature"},
	{"geometry":{"coordinates":[-52.281857,4.887604],"type":"Point"},"properties":{"osm_id":"7298095992","tag":{"amenity":"waste_basket","shelter":"yes"}},"type":"Feature"}
]
}
