{
"type": "FeatureCollection",
"features": [
	{"geometry":{"coordinates":[-52.27371,4.898886],"type":"Point"},"properties":{"osm_id":"2680896179","tag":{"amenity":"recycling","operator":"CACL","recycling:glass_bottles":"yes","recycling_type":"container"}},"type":"Feature"},
	{"geometry":{"coordinates":[-52.279742,4.913754],"type":"Point"},"properties":{"osm_id":"2965195137","tag":{"amenity":"recycling","recycling:glass_bottles":"yes","recycling_type":"container"}},"type":"Feature"},
	{"geometry":{"coordinates":[-52.277258,4.911502],"type":"Point"},"properties":{"osm_id":"3098698823","tag":{"amenity":"recycling","operator":"CACL","recycling:glass_bottles":"yes","recycling_type":"container"}},"type":"Feature"},
	{"geometry":{"coordinates":[-52.283452,4.912495],"type":"Point"},"properties":{"name":"Association GuyaClic' - Atelier Recycl'Ordi","osm_id":"5548382443","tag":{"amenity":"recycling","building:levels":"0","email":"guyaclic@groupe-diverscite.fr","opening_hours":"Mo-Fr 08:00-16:00","recycling:computers":"yes","recycling_type":"centre","smoking":"no"}},"type":"Feature"},
	{"geometry":{"coordinates":[-52.260318,4.894885],"type":"Point"},"properties":{"osm_id":"5749362538","tag":{"amenity":"recycling","operator":"CACL","recycling:glass_bottles":"yes","recycling_type":"container"}},"type":"Feature"},
	{"geometry":{"coordinates":[-52.286259,4.909385],"type":"Point"},"properties":{"osm_id":"5823952234","tag":{"amenity":"recycling","operator":"CACL","recycling:glass_bottles":"yes","recycling_type":"container"}},"type":"Feature"},
	{"geometry":{"coordinates":[-52.270644,4.858507],"type":"Point"},"properties":{"osm_id":"5835260321","tag":{"amenity":"recycling","recycling:glass_bottles":"yes","recycling_type":"container","source:position":"GPS"}},"type":"Feature"},
	{"geometry":{"coordinates":[-52.280167,4.882559],"type":"Point"},"properties":{"osm_id":"5835260327","tag":{"amenity":"recycling","recycling:glass_bottles":"yes","recycling_type":"container","source:position":"GPS"}},"type":"Feature"},
	{"geometry":{"coordinates":[-52.278583,4.907949],"type":"Point"},"properties":{"osm_id":"5896692930","tag":{"amenity":"waste_basket","source:position":"GPS"}},"type":"Feature"},
	{"geometry":{"coordinates":[-52.272266,4.912431],"type":"Point"},"properties":{"osm_id":"6593751299","tag":{"amenity":"waste_basket"}},"type":"Feature"},
	{"geometry":{"coordinates":[-52.272351,4.912598],"type":"Point"},"properties":{"osm_id":"6593751300","tag":{"amenity":"waste_basket"}},"type":"Feature"},
	{"geometry":{"coordinates":[-52.272183,4.912519],"type":"Point"},"properties":{"osm_id":"6593751301","tag":{"amenity":"waste_basket"}},"type":"Feature"},
	{"geometry":{"coordinates":[-52.272116,4.912356],"type":"Point"},"properties":{"osm_id":"6593751302","tag":{"amenity":"waste_basket"}},"type":"Feature"},
	{"geometry":{"coordinates":[-52.279954,4.88745],"type":"Point"},"properties":{"osm_id":"7298056124","tag":{"amenity":"recycling","recycling:glass":"yes","recycling_type":"container"}},"type":"Feature"},
	{"geometry":{"coordinates":[-52.281871,4.887592],"type":"Point"},"properties":{"osm_id":"7298095992","tag":{"amenity":"waste_basket","shelter":"yes"}},"type":"Feature"}
]
}
