{
"type": "FeatureCollection",
"lastupdate": "2020-08-04T00:00:00Z",
"features": [
	{"geometry":{"coordinates":[5.250804,51.802056],"type":"Point"},"properties":{"osm_id":"1995349087","tag":{"amenity":"recycling","recycling:clothes":"yes","recycling:glass":"yes","recycling:magazines":"yes","recycling:newspaper":"yes","recycling:paper":"yes","recycling_type":"container"}},"type":"Feature"},
	{"geometry":{"coordinates":[5.252414,51.803001],"type":"Point"},"properties":{"osm_id":"1995349102","tag":{"amenity":"recycling","recycling:paper":"yes","recycling_type":"container"}},"type":"Feature"},
	{"geometry":{"coordinates":[5.267005,51.813034],"type":"Point"},"properties":{"barrier":"gate","osm_id":"2016777425"},"type":"Feature"},
	{"geometry":{"coordinates":[5.266736,51.813277],"type":"Point"},"properties":{"barrier":"gate","osm_id":"2016777426"},"type":"Feature"},
	{"geometry":{"coordinates":[5.237232,51.787982],"type":"Point"},"properties":{"osm_id":"3089094606","tag":{"amenity":"recycling","recycling:glass_bottles":"yes","recycling_type":"container"}},"type":"Feature"},
	{"geometry":{"coordinates":[5.263776,51.807512],"type":"Point"},"properties":{"osm_id":"4253477762","tag":{"amenity":"waste_basket"}},"type":"Feature"},
	{"geometry":{"coordinates":[5.253683,51.810094],"type":"Point"},"properties":{"osm_id":"5609607944","tag":{"amenity":"waste_basket","waste":"trash"}},"type":"Feature"},
	{"geometry":{"coordinates":[5.252486,51.803226],"type":"Point"},"properties":{"osm_id":"7140816339","tag":{"amenity":"waste_basket"}},"type":"Feature"},
	{"geometry":{"coordinates":[5.257899,51.803264],"type":"Point"},"properties":{"osm_id":"7140816368","tag":{"amenity":"waste_basket"}},"type":"Feature"},
	{"geometry":{"coordinates":[5.256353,51.801405],"type":"Point"},"properties":{"osm_id":"7140927980","tag":{"amenity":"waste_basket"}},"type":"Feature"},
	{"geometry":{"coordinates":[5.256109,51.800131],"type":"Point"},"properties":{"osm_id":"7140929604","tag":{"amenity":"waste_basket"}},"type":"Feature"},
	{"geometry":{"coordinates":[5.250966,51.799273],"type":"Point"},"properties":{"osm_id":"7284555142","tag":{"amenity":"waste_basket","waste":"dog"}},"type":"Feature"},
	{"geometry":{"coordinates":[5.25072,51.798949],"type":"Point"},"properties":{"osm_id":"7284555144","tag":{"amenity":"waste_basket"}},"type":"Feature"},
	{"geometry":{"coordinates":[5.250718,51.798134],"type":"Point"},"properties":{"osm_id":"7284555166","tag":{"amenity":"waste_basket"}},"type":"Feature"},
	{"geometry":{"coordinates":[5.251515,51.799853],"type":"Point"},"properties":{"osm_id":"7284555177","tag":{"amenity":"waste_basket"}},"type":"Feature"},
	{"geometry":{"coordinates":[5.251223,51.799364],"type":"Point"},"properties":{"osm_id":"7284569496","tag":{"amenity":"waste_basket","waste":"dog"}},"type":"Feature"},
	{"geometry":{"coordinates":[5.251225,51.799034],"type":"Point"},"properties":{"osm_id":"7284569499","tag":{"amenity":"waste_basket"}},"type":"Feature"},
	{"geometry":{"coordinates":[5.235612,51.801293],"type":"Point"},"properties":{"osm_id":"7595622146","tag":{"access":"private","amenity":"recycling","location":"underground","operator":"Avri","recycling:waste":"yes","recycling_type":"container"}},"type":"Feature"}
]
}
