{
"type": "FeatureCollection",
"features": [
	{"geometry":{"coordinates":[5.250804,51.802056],"type":"Point"},"properties":{"osm_id":"1995349087","tag":{"amenity":"recycling","recycling:clothes":"yes","recycling:glass":"yes","recycling:magazines":"yes","recycling:newspaper":"yes","recycling:paper":"yes","recycling_type":"container"}},"type":"Feature"},
	{"geometry":{"coordinates":[5.252414,51.803002],"type":"Point"},"properties":{"osm_id":"1995349102","tag":{"amenity":"recycling","recycling:paper":"yes","recycling_type":"container"}},"type":"Feature"},
	{"geometry":{"coordinates":[5.267006,51.813034],"type":"Point"},"properties":{"barrier":"gate","osm_id":"2016777425"},"type":"Feature"},
	{"geometry":{"coordinates":[5.266736,51.813278],"type":"Point"},"properties":{"barrier":"gate","osm_id":"2016777426"},"type":"Feature"},
	{"geometry":{"coordinates":[5.237233,51.787982],"type":"Point"},"properties":{"osm_id":"3089094606","tag":{"amenity":"recycling","recycling:glass_bottles":"yes","recycling_type":"container"}},"type":"Feature"},
	{"geometry":{"coordinates":[5.252454,51.802969],"type":"Point"},"properties":{"osm_id":"3137326718","tag":{"amenity":"waste_disposal"}},"type":"Feature"},
	{"geometry":{"coordinates":[5.263776,51.807512],"type":"Point"},"properties":{"osm_id":"4253477762","tag":{"amenity":"waste_basket"}},"type":"Feature"},
	{"geometry":{"coordinates":[5.253684,51.810095],"type":"Point"},"properties":{"osm_id":"5609607944","tag":{"amenity":"waste_basket","waste":"trash"}},"type":"Feature"},
	{"geometry":{"coordinates":[5.252487,51.803227],"type":"Point"},"properties":{"osm_id":"7140816339","tag":{"amenity":"waste_basket"}},"type":"Feature"},
	{"geometry":{"coordinates":[5.2579,51.803264],"type":"Point"},"properties":{"osm_id":"7140816368","tag":{"amenity":"waste_basket"}},"type":"Feature"},
	{"geometry":{"coordinates":[5.256354,51.801405],"type":"Point"},"properties":{"osm_id":"7140927980","tag":{"amenity":"waste_basket"}},"type":"Feature"},
	{"geometry":{"coordinates":[5.256109,51.800131],"type":"Point"},"properties":{"osm_id":"7140929604","tag":{"amenity":"waste_basket"}},"type":"Feature"},
	{"geometry":{"coordinates":[5.250967,51.799274],"type":"Point"},"properties":{"osm_id":"7284555142","tag":{"amenity":"waste_basket","waste":"dog"}},"type":"Feature"},
	{"geometry":{"coordinates":[5.25072,51.79895],"type":"Point"},"properties":{"osm_id":"7284555144","tag":{"amenity":"waste_basket"}},"type":"Feature"},
	{"geometry":{"coordinates":[5.250718,51.798134],"type":"Point"},"properties":{"osm_id":"7284555166","tag":{"amenity":"waste_basket"}},"type":"Feature"},
	{"geometry":{"coordinates":[5.251516,51.799854],"type":"Point"},"properties":{"osm_id":"7284555177","tag":{"amenity":"waste_basket"}},"type":"Feature"},
	{"geometry":{"coordinates":[5.251224,51.799365],"type":"Point"},"properties":{"osm_id":"7284569496","tag":{"amenity":"waste_basket","waste":"dog"}},"type":"Feature"},
	{"geometry":{"coordinates":[5.251226,51.799035],"type":"Point"},"properties":{"osm_id":"7284569499","tag":{"amenity":"waste_basket"}},"type":"Feature"},
	{"geometry":{"coordinates":[5.235612,51.801293],"type":"Point"},"properties":{"osm_id":"7595622146","tag":{"access":"private","amenity":"recycling","location":"underground","operator":"Avri","recycling:waste":"yes","recycling_type":"container"}},"type":"Feature"},
	{"geometry":{"coordinates":[5.210003,51.813663],"type":"Point"},"properties":{"osm_id":"7856881894","tag":{"amenity":"waste_basket"}},"type":"Feature"},
	{"geometry":{"coordinates":[5.211089,51.811788],"type":"Point"},"properties":{"osm_id":"7856881901","tag":{"amenity":"waste_basket"}},"type":"Feature"}
]
}
