{
"type": "FeatureCollection",
"lastupdate": "2020-08-05T00:00:00Z",
"features": [
	{"geometry":{"coordinates":[101.510821,6.381468],"type":"Point"},"properties":{"name":"\u00e0\u00b8\u00a3\u00e0\u00b8\u00b7\u00e0\u00b8\u00ad\u00e0\u00b9\u0080\u00e0\u00b8\u00aa\u00e0\u00b8\u00b2\u00e0\u00b8\u00b0\u00e0\u00b8\u00a3\u00e0\u00b8\u00b5\u00e0\u00b9\u0084\u00e0\u00b8\u008b\u00e0\u00b9\u0080\u00e0\u00b8\u0084\u00e0\u00b8\u00b4\u00e0\u00b8\u00a5","osm_id":"2927428973","tag":{"amenity":"recycling","name:en":"Rueso Recycle","name:th":"\u0e23\u0e37\u0e2d\u0e40\u0e2a\u0e32\u0e30 \u0e23\u0e35\u0e44\u0e0b\u0e40\u0e04\u0e34\u0e25"}},"type":"Feature"}
]
}
