{
"type": "FeatureCollection",
"features": [
	{"geometry":{"coordinates":[101.510821,6.381468],"type":"Point"},"properties":{"name":"\u00e0\u00b8\u00a3\u00e0\u00b8\u00b7\u00e0\u00b8\u00ad\u00e0\u00b9\u0080\u00e0\u00b8\u00aa\u00e0\u00b8\u00b2\u00e0\u00b8\u00b0\u00e0\u00b8\u00a3\u00e0\u00b8\u00b5\u00e0\u00b9\u0084\u00e0\u00b8\u008b\u00e0\u00b9\u0080\u00e0\u00b8\u0084\u00e0\u00b8\u00b4\u00e0\u00b8\u00a5","osm_id":"2927428973","tag":{"amenity":"recycling","name:en":"Rueso Recycle","name:th":"\u00e0\u00b8\u00a3\u00e0\u00b8\u00b7\u00e0\u00b8\u00ad\u00e0\u00b9\u0080\u00e0\u00b8\u00aa\u00e0\u00b8\u00b2\u00e0\u00b8\u00b0 \u00e0\u00b8\u00a3\u00e0\u00b8\u00b5\u00e0\u00b9\u0084\u00e0\u00b8\u008b\u00e0\u00b9\u0080\u00e0\u00b8\u0084\u00e0\u00b8\u00b4\u00e0\u00b8\u00a5"}},"type":"Feature"}
]
}
