{
"type": "FeatureCollection",
"lastupdate": "2020-08-02T00:00:00Z",
"features": [
	{"geometry":{"coordinates":[17.342618,62.415844],"type":"Point"},"properties":{"osm_id":"1379237421","tag":{"amenity":"recycling"}},"type":"Feature"},
	{"geometry":{"coordinates":[17.34054,62.428164],"type":"Point"},"properties":{"osm_id":"2063846507","tag":{"amenity":"waste_basket"}},"type":"Feature"},
	{"geometry":{"coordinates":[17.336739,62.426236],"type":"Point"},"properties":{"highway":"street_lamp","osm_id":"2063878739","tag":{"amenity":"waste_basket"}},"type":"Feature"},
	{"geometry":{"coordinates":[17.337339,62.419844],"type":"Point"},"properties":{"highway":"street_lamp","osm_id":"2065274407","tag":{"amenity":"waste_basket"}},"type":"Feature"},
	{"geometry":{"coordinates":[17.340336,62.419762],"type":"Point"},"properties":{"osm_id":"2065274427","tag":{"amenity":"waste_basket"}},"type":"Feature"},
	{"geometry":{"coordinates":[17.340496,62.421059],"type":"Point"},"properties":{"osm_id":"2065277733","tag":{"amenity":"waste_basket"}},"type":"Feature"},
	{"geometry":{"coordinates":[17.33642,62.420756],"type":"Point"},"properties":{"highway":"street_lamp","osm_id":"2065280739","tag":{"amenity":"waste_basket"}},"type":"Feature"},
	{"geometry":{"coordinates":[17.335808,62.423298],"type":"Point"},"properties":{"highway":"street_lamp","osm_id":"2065386226","tag":{"amenity":"waste_basket"}},"type":"Feature"},
	{"geometry":{"coordinates":[17.33203,62.414848],"type":"Point"},"properties":{"osm_id":"2076697849","tag":{"amenity":"waste_basket"}},"type":"Feature"},
	{"geometry":{"coordinates":[17.326799,62.417868],"type":"Point"},"properties":{"osm_id":"2076710340","tag":{"amenity":"waste_basket"}},"type":"Feature"},
	{"geometry":{"coordinates":[17.325,62.414838],"type":"Point"},"properties":{"osm_id":"2076784203","tag":{"amenity":"waste_basket"}},"type":"Feature"},
	{"geometry":{"coordinates":[17.325142,62.414971],"type":"Point"},"properties":{"osm_id":"2076784360","tag":{"amenity":"recycling"}},"type":"Feature"},
	{"geometry":{"coordinates":[17.347841,62.396617],"type":"Point"},"properties":{"highway":"platform","name":"Bruksgatan","osm_id":"2077798297","tag":{"amenity":"waste_basket","bench":"no","public_transport":"platform","shelter":"no"}},"type":"Feature"},
	{"geometry":{"coordinates":[17.31717,62.401065],"type":"Point"},"properties":{"highway":"street_lamp","osm_id":"2077966277","tag":{"amenity":"waste_basket"}},"type":"Feature"},
	{"geometry":{"coordinates":[17.376621,62.414065],"type":"Point"},"properties":{"osm_id":"2078048725","tag":{"amenity":"waste_basket"}},"type":"Feature"},
	{"geometry":{"coordinates":[17.332513,62.422382],"type":"Point"},"properties":{"osm_id":"2101252301","tag":{"amenity":"waste_basket"}},"type":"Feature"},
	{"geometry":{"coordinates":[17.339735,62.400947],"type":"Point"},"properties":{"osm_id":"2228430797","tag":{"amenity":"waste_basket"}},"type":"Feature"},
	{"geometry":{"coordinates":[17.338601,62.400994],"type":"Point"},"properties":{"osm_id":"2228432524","tag":{"amenity":"waste_basket"}},"type":"Feature"},
	{"geometry":{"coordinates":[17.338681,62.401161],"type":"Point"},"properties":{"osm_id":"2228469096","tag":{"amenity":"waste_basket"}},"type":"Feature"},
	{"geometry":{"coordinates":[17.340883,62.4009],"type":"Point"},"properties":{"osm_id":"2228479844","tag":{"amenity":"waste_basket"}},"type":"Feature"},
	{"geometry":{"coordinates":[17.339277,62.399703],"type":"Point"},"properties":{"osm_id":"2229032147","tag":{"amenity":"waste_basket"}},"type":"Feature"},
	{"geometry":{"coordinates":[17.366087,62.402136],"type":"Point"},"properties":{"highway":"street_lamp","osm_id":"2246143305","tag":{"amenity":"waste_basket"}},"type":"Feature"},
	{"geometry":{"coordinates":[17.358953,62.400953],"type":"Point"},"properties":{"osm_id":"2246311861","tag":{"amenity":"waste_basket"}},"type":"Feature"}
]
}
