{
"type": "FeatureCollection",
"features": [
	{"geometry":{"coordinates":[12.067619,50.784048],"type":"Point"},"properties":{"name":"Schwedeneiche","osm_id":"4419149375","tag":{"denotation":"natural_monument","natural":"tree"}},"type":"Feature"},
	{"geometry":{"coordinates":[12.121568,50.789743],"type":"Point"},"properties":{"osm_id":"5137048393","tag":{"natural":"tree"}},"type":"Feature"},
	{"geometry":{"coordinates":[12.120618,50.790375],"type":"Point"},"properties":{"osm_id":"5137048394","tag":{"natural":"tree"}},"type":"Feature"},
	{"geometry":{"coordinates":[12.081775,50.737073],"type":"Point"},"properties":{"osm_id":"7132701761","tag":{"leaf_cycle":"deciduous","leaf_type":"broadleaved","natural":"tree"}},"type":"Feature"}
]
}
