{
"type": "FeatureCollection",
"features": [
	{"geometry":{"coordinates":[12.067618,50.784048],"type":"Point"},"properties":{"name":"Schwedeneiche","osm_id":"4419149375","tag":{"denotation":"natural_monument","natural":"tree"}},"type":"Feature"},
	{"geometry":{"coordinates":[12.121568,50.789742],"type":"Point"},"properties":{"osm_id":"5137048393","tag":{"natural":"tree"}},"type":"Feature"},
	{"geometry":{"coordinates":[12.120617,50.790375],"type":"Point"},"properties":{"osm_id":"5137048394","tag":{"natural":"tree"}},"type":"Feature"},
	{"geometry":{"coordinates":[12.081775,50.737073],"type":"Point"},"properties":{"osm_id":"7132701761","tag":{"leaf_cycle":"deciduous","leaf_type":"broadleaved","natural":"tree"}},"type":"Feature"},
	{"geometry":{"coordinates":[12.079789,50.790352],"type":"Point"},"properties":{"osm_id":"8569740349","tag":{"natural":"tree"}},"type":"Feature"},
	{"geometry":{"coordinates":[12.081329,50.737453],"type":"Point"},"properties":{"osm_id":"9073357615","tag":{"natural":"tree"}},"type":"Feature"},
	{"geometry":{"coordinates":[12.081238,50.737399],"type":"Point"},"properties":{"osm_id":"9073357616","tag":{"natural":"tree"}},"type":"Feature"}
]
}
