{
"type": "FeatureCollection",
"features": [
	{"geometry":{"coordinates":[12.077156,49.946757],"type":"Point"},"properties":{"osm_id":"2485414339","tag":{"natural":"tree"}},"type":"Feature"},
	{"geometry":{"coordinates":[12.098795,49.896829],"type":"Point"},"properties":{"osm_id":"2485543354","tag":{"denomination":"catholic","description":"Bildbaum","historic":"wayside_shrine","leaf_type":"needleleaved","natural":"tree","religion":"christian"}},"type":"Feature"},
	{"geometry":{"coordinates":[12.091586,49.950275],"type":"Point"},"properties":{"osm_id":"3230139445","tag":{"natural":"tree"}},"type":"Feature"},
	{"geometry":{"coordinates":[12.091771,49.950418],"type":"Point"},"properties":{"osm_id":"3230139446","tag":{"natural":"tree"}},"type":"Feature"},
	{"geometry":{"coordinates":[12.091949,49.950553],"type":"Point"},"properties":{"osm_id":"3230139447","tag":{"natural":"tree"}},"type":"Feature"},
	{"geometry":{"coordinates":[12.092131,49.950696],"type":"Point"},"properties":{"osm_id":"3230139448","tag":{"natural":"tree"}},"type":"Feature"},
	{"geometry":{"coordinates":[12.086222,49.949377],"type":"Point"},"properties":{"osm_id":"8419951976","tag":{"denotation":"landmark","diameter_crown":"8","leaf_cycle":"deciduous","natural":"tree"}},"type":"Feature"},
	{"geometry":{"coordinates":[12.086402,49.949377],"type":"Point"},"properties":{"osm_id":"8419951977","tag":{"denotation":"landmark","diameter_crown":"8","leaf_cycle":"deciduous","natural":"tree"}},"type":"Feature"},
	{"geometry":{"coordinates":[12.083349,49.948593],"type":"Point"},"properties":{"osm_id":"8419960941","tag":{"denotation":"landmark","diameter_crown":"12","leaf_cycle":"deciduous","natural":"tree"}},"type":"Feature"},
	{"geometry":{"coordinates":[12.083493,49.948829],"type":"Point"},"properties":{"osm_id":"8419960942","tag":{"denotation":"landmark","diameter_crown":"12","leaf_cycle":"deciduous","natural":"tree"}},"type":"Feature"},
	{"geometry":{"coordinates":[12.115341,49.942251],"type":"Point"},"properties":{"osm_id":"8509467060","tag":{"diameter_crown":"8","natural":"tree"}},"type":"Feature"}
]
}
