{
"type": "FeatureCollection",
"features": [
	{"geometry":{"coordinates":[12.077156,49.946757],"type":"Point"},"properties":{"osm_id":"2485414339","tag":{"natural":"tree"}},"type":"Feature"},
	{"geometry":{"coordinates":[12.098795,49.896829],"type":"Point"},"properties":{"osm_id":"2485543354","tag":{"denomination":"catholic","description":"Bildbaum","historic":"wayside_shrine","leaf_type":"needleleaved","natural":"tree","religion":"christian"}},"type":"Feature"},
	{"geometry":{"coordinates":[12.091586,49.950275],"type":"Point"},"properties":{"osm_id":"3230139445","tag":{"natural":"tree"}},"type":"Feature"},
	{"geometry":{"coordinates":[12.091771,49.950418],"type":"Point"},"properties":{"osm_id":"3230139446","tag":{"natural":"tree"}},"type":"Feature"},
	{"geometry":{"coordinates":[12.091949,49.950553],"type":"Point"},"properties":{"osm_id":"3230139447","tag":{"natural":"tree"}},"type":"Feature"},
	{"geometry":{"coordinates":[12.092131,49.950696],"type":"Point"},"properties":{"osm_id":"3230139448","tag":{"natural":"tree"}},"type":"Feature"}
]
}
