{
"type": "FeatureCollection",
"features": [
	{"geometry":{"coordinates":[12.077156,49.946758],"type":"Point"},"properties":{"osm_id":"2485414339","tag":{"natural":"tree"}},"type":"Feature"},
	{"geometry":{"coordinates":[12.098795,49.896829],"type":"Point"},"properties":{"osm_id":"2485543354","tag":{"denomination":"catholic","description":"Bildbaum","historic":"wayside_shrine","leaf_type":"needleleaved","natural":"tree","religion":"christian"}},"type":"Feature"},
	{"geometry":{"coordinates":[12.091587,49.950275],"type":"Point"},"properties":{"osm_id":"3230139445","tag":{"natural":"tree"}},"type":"Feature"},
	{"geometry":{"coordinates":[12.091772,49.950418],"type":"Point"},"properties":{"osm_id":"3230139446","tag":{"natural":"tree"}},"type":"Feature"},
	{"geometry":{"coordinates":[12.09195,49.950553],"type":"Point"},"properties":{"osm_id":"3230139447","tag":{"natural":"tree"}},"type":"Feature"},
	{"geometry":{"coordinates":[12.092132,49.950697],"type":"Point"},"properties":{"osm_id":"3230139448","tag":{"natural":"tree"}},"type":"Feature"}
]
}
