{
"type": "FeatureCollection",
"features": [
	{"geometry":{"coordinates":[12.074397,48.894861],"type":"Point"},"properties":{"osm_id":"3697649159","tag":{"natural":"tree"}},"type":"Feature"},
	{"geometry":{"coordinates":[12.108502,48.882972],"type":"Point"},"properties":{"osm_id":"4485426082","tag":{"denotation":"natural_monument","leaf_cycle":"deciduous","leaf_type":"broadleaved","natural":"tree"}},"type":"Feature"},
	{"geometry":{"coordinates":[12.108646,48.882955],"type":"Point"},"properties":{"osm_id":"4485427057","tag":{"denotation":"natural_monument","leaf_cycle":"deciduous","leaf_type":"broadleaved","natural":"tree"}},"type":"Feature"},
	{"geometry":{"coordinates":[12.108561,48.882955],"type":"Point"},"properties":{"osm_id":"4485428221","tag":{"denotation":"natural_monument","leaf_cycle":"deciduous","leaf_type":"broadleaved","natural":"tree"}},"type":"Feature"},
	{"geometry":{"coordinates":[12.108781,48.883151],"type":"Point"},"properties":{"name":"Birne","osm_id":"4485441408","tag":{"denotation":"natural_monument","leaf_cycle":"deciduous","leaf_type":"broadleaved","natural":"tree"}},"type":"Feature"},
	{"geometry":{"coordinates":[12.108494,48.883064],"type":"Point"},"properties":{"osm_id":"4485441789","tag":{"denotation":"urban","leaf_cycle":"deciduous","leaf_type":"broadleaved","natural":"tree"}},"type":"Feature"},
	{"geometry":{"coordinates":[12.046806,48.890699],"type":"Point"},"properties":{"osm_id":"8625322104","tag":{"natural":"tree"}},"type":"Feature"},
	{"geometry":{"coordinates":[12.047033,48.890665],"type":"Point"},"properties":{"osm_id":"8625322105","tag":{"natural":"tree"}},"type":"Feature"},
	{"geometry":{"coordinates":[12.046836,48.890573],"type":"Point"},"properties":{"osm_id":"8625322106","tag":{"natural":"tree"}},"type":"Feature"},
	{"geometry":{"coordinates":[12.051222,48.890196],"type":"Point"},"properties":{"osm_id":"8625322107","tag":{"natural":"tree"}},"type":"Feature"},
	{"geometry":{"coordinates":[12.049,48.891926],"type":"Point"},"properties":{"osm_id":"8625348337","tag":{"natural":"tree"}},"type":"Feature"},
	{"geometry":{"coordinates":[12.121819,48.892268],"type":"Point"},"properties":{"osm_id":"8625424871","tag":{"natural":"tree"}},"type":"Feature"}
]
}
