{
"type": "FeatureCollection",
"features": [
	{"geometry":{"coordinates":[12.074397,48.894861],"type":"Point"},"properties":{"osm_id":"3697649159","tag":{"natural":"tree"}},"type":"Feature"},
	{"geometry":{"coordinates":[12.108502,48.882972],"type":"Point"},"properties":{"osm_id":"4485426082","tag":{"denotation":"natural_monument","leaf_cycle":"deciduous","leaf_type":"broadleaved","natural":"tree"}},"type":"Feature"},
	{"geometry":{"coordinates":[12.108646,48.882955],"type":"Point"},"properties":{"osm_id":"4485427057","tag":{"denotation":"natural_monument","leaf_cycle":"deciduous","leaf_type":"broadleaved","natural":"tree"}},"type":"Feature"},
	{"geometry":{"coordinates":[12.108561,48.882955],"type":"Point"},"properties":{"osm_id":"4485428221","tag":{"denotation":"natural_monument","leaf_cycle":"deciduous","leaf_type":"broadleaved","natural":"tree"}},"type":"Feature"},
	{"geometry":{"coordinates":[12.108781,48.883151],"type":"Point"},"properties":{"name":"Birne","osm_id":"4485441408","tag":{"denotation":"natural_monument","leaf_cycle":"deciduous","leaf_type":"broadleaved","natural":"tree"}},"type":"Feature"},
	{"geometry":{"coordinates":[12.108494,48.883064],"type":"Point"},"properties":{"osm_id":"4485441789","tag":{"denotation":"urban","leaf_cycle":"deciduous","leaf_type":"broadleaved","natural":"tree"}},"type":"Feature"}
]
}
