{
"type": "FeatureCollection",
"features": [
	{"geometry":{"coordinates":[-75.09018,39.844744],"type":"Point"},"properties":{"name":"Clement Oak","osm_id":"8527706492","tag":{"denotation":"landmark","leaf_cycle":"deciduous","leaf_type":"broadleaved","natural":"tree","wikidata":"Q30623019","wikipedia":"en:Clement Oak"}},"type":"Feature"}
]
}
