{
"type": "FeatureCollection",
"lastupdate": "2020-08-04T00:00:00Z",
"features": [
	{"geometry":{"coordinates":[-89.622859,39.759496],"type":"Point"},"properties":{"osm_id":"4061916325","tag":{"amenity":"waste_basket"}},"type":"Feature"},
	{"geometry":{"coordinates":[-89.621822,39.759757],"type":"Point"},"properties":{"osm_id":"4073555537","tag":{"amenity":"waste_basket"}},"type":"Feature"},
	{"geometry":{"coordinates":[-89.640039,39.714821],"type":"Point"},"properties":{"osm_id":"4789222294","tag":{"amenity":"waste_basket"}},"type":"Feature"},
	{"geometry":{"coordinates":[-89.64502,39.764932],"type":"Point"},"properties":{"name":"Lake Area Recycling Services","osm_id":"7191954058","tag":{"addr:city":"Springfield","addr:housenumber":"2742","addr:postcode":"62703","addr:state":"IL","addr:street":"South 6th Street","amenity":"recycling","phone":"+1-217-522-9271","recycling_type":"centre","website":"https://www.lakeareadisposal.com/"}},"type":"Feature"}
]
}
