{
"type": "FeatureCollection",
"features": [
	{"geometry":{"coordinates":[-89.622859,39.759496],"type":"Point"},"properties":{"osm_id":"4061916325","tag":{"amenity":"waste_basket"}},"type":"Feature"},
	{"geometry":{"coordinates":[-89.621822,39.759757],"type":"Point"},"properties":{"osm_id":"4073555537","tag":{"amenity":"waste_basket"}},"type":"Feature"},
	{"geometry":{"coordinates":[-89.64559,39.761435],"type":"Point"},"properties":{"osm_id":"4141059391","tag":{"amenity":"waste_disposal"}},"type":"Feature"},
	{"geometry":{"coordinates":[-89.634827,39.761239],"type":"Point"},"properties":{"osm_id":"4141059506","tag":{"amenity":"waste_disposal"}},"type":"Feature"},
	{"geometry":{"coordinates":[-89.634709,39.7582],"type":"Point"},"properties":{"osm_id":"4141059537","tag":{"amenity":"waste_disposal"}},"type":"Feature"},
	{"geometry":{"coordinates":[-89.63569,39.758115],"type":"Point"},"properties":{"osm_id":"4141059538","tag":{"amenity":"waste_disposal"}},"type":"Feature"},
	{"geometry":{"coordinates":[-89.635685,39.758003],"type":"Point"},"properties":{"osm_id":"4141059539","tag":{"amenity":"waste_disposal"}},"type":"Feature"},
	{"geometry":{"coordinates":[-89.647044,39.763027],"type":"Point"},"properties":{"osm_id":"4170399623","tag":{"amenity":"waste_disposal"}},"type":"Feature"},
	{"geometry":{"coordinates":[-89.644681,39.755811],"type":"Point"},"properties":{"osm_id":"4205799336","tag":{"amenity":"waste_disposal"}},"type":"Feature"},
	{"geometry":{"coordinates":[-89.628254,39.757371],"type":"Point"},"properties":{"osm_id":"4205799473","tag":{"amenity":"waste_disposal"}},"type":"Feature"},
	{"geometry":{"coordinates":[-89.640808,39.766478],"type":"Point"},"properties":{"osm_id":"4214325811","tag":{"amenity":"waste_disposal"}},"type":"Feature"},
	{"geometry":{"coordinates":[-89.616717,39.757582],"type":"Point"},"properties":{"osm_id":"4256718663","tag":{"amenity":"waste_disposal"}},"type":"Feature"},
	{"geometry":{"coordinates":[-89.644671,39.755246],"type":"Point"},"properties":{"osm_id":"4446513149","tag":{"amenity":"waste_disposal"}},"type":"Feature"},
	{"geometry":{"coordinates":[-89.628882,39.758706],"type":"Point"},"properties":{"osm_id":"4722256065","tag":{"amenity":"waste_disposal"}},"type":"Feature"},
	{"geometry":{"coordinates":[-89.640039,39.714821],"type":"Point"},"properties":{"osm_id":"4789222294","tag":{"amenity":"waste_basket"}},"type":"Feature"},
	{"geometry":{"coordinates":[-89.611783,39.768145],"type":"Point"},"properties":{"osm_id":"5526166721","tag":{"amenity":"waste_disposal"}},"type":"Feature"},
	{"geometry":{"coordinates":[-89.64502,39.764932],"type":"Point"},"properties":{"name":"Lake Area Recycling Services","osm_id":"7191954058","tag":{"addr:city":"Springfield","addr:housenumber":"2742","addr:postcode":"62703","addr:state":"IL","addr:street":"South 6th Street","amenity":"recycling","phone":"+1-217-522-9271","recycling_type":"centre","website":"https://www.lakeareadisposal.com/"}},"type":"Feature"},
	{"geometry":{"coordinates":[-89.619903,39.730484],"type":"Point"},"properties":{"osm_id":"8017691414","tag":{"amenity":"waste_basket"}},"type":"Feature"}
]
}
