{
"type": "FeatureCollection",
"features": [
	{"geometry":{"coordinates":[-89.62286,39.759497],"type":"Point"},"properties":{"osm_id":"4061916325","tag":{"amenity":"waste_basket"}},"type":"Feature"},
	{"geometry":{"coordinates":[-89.621823,39.759758],"type":"Point"},"properties":{"osm_id":"4073555537","tag":{"amenity":"waste_basket"}},"type":"Feature"},
	{"geometry":{"coordinates":[-89.645591,39.761436],"type":"Point"},"properties":{"osm_id":"4141059391","tag":{"amenity":"waste_disposal"}},"type":"Feature"},
	{"geometry":{"coordinates":[-89.634827,39.76124],"type":"Point"},"properties":{"osm_id":"4141059506","tag":{"amenity":"waste_disposal"}},"type":"Feature"},
	{"geometry":{"coordinates":[-89.634709,39.7582],"type":"Point"},"properties":{"osm_id":"4141059537","tag":{"amenity":"waste_disposal"}},"type":"Feature"},
	{"geometry":{"coordinates":[-89.635691,39.758115],"type":"Point"},"properties":{"osm_id":"4141059538","tag":{"amenity":"waste_disposal"}},"type":"Feature"},
	{"geometry":{"coordinates":[-89.635685,39.758004],"type":"Point"},"properties":{"osm_id":"4141059539","tag":{"amenity":"waste_disposal"}},"type":"Feature"},
	{"geometry":{"coordinates":[-89.647045,39.763027],"type":"Point"},"properties":{"osm_id":"4170399623","tag":{"amenity":"waste_disposal"}},"type":"Feature"},
	{"geometry":{"coordinates":[-89.644682,39.755812],"type":"Point"},"properties":{"osm_id":"4205799336","tag":{"amenity":"waste_disposal"}},"type":"Feature"},
	{"geometry":{"coordinates":[-89.628254,39.757371],"type":"Point"},"properties":{"osm_id":"4205799473","tag":{"amenity":"waste_disposal"}},"type":"Feature"},
	{"geometry":{"coordinates":[-89.640808,39.766479],"type":"Point"},"properties":{"osm_id":"4214325811","tag":{"amenity":"waste_disposal"}},"type":"Feature"},
	{"geometry":{"coordinates":[-89.616717,39.757582],"type":"Point"},"properties":{"osm_id":"4256718663","tag":{"amenity":"waste_disposal"}},"type":"Feature"},
	{"geometry":{"coordinates":[-89.644671,39.755246],"type":"Point"},"properties":{"osm_id":"4446513149","tag":{"amenity":"waste_disposal"}},"type":"Feature"},
	{"geometry":{"coordinates":[-89.628882,39.758707],"type":"Point"},"properties":{"osm_id":"4722256065","tag":{"amenity":"waste_disposal"}},"type":"Feature"},
	{"geometry":{"coordinates":[-89.640039,39.714822],"type":"Point"},"properties":{"osm_id":"4789222294","tag":{"amenity":"waste_basket"}},"type":"Feature"},
	{"geometry":{"coordinates":[-89.611784,39.768146],"type":"Point"},"properties":{"osm_id":"5526166721","tag":{"amenity":"waste_disposal"}},"type":"Feature"},
	{"geometry":{"coordinates":[-89.645021,39.764933],"type":"Point"},"properties":{"name":"Lake Area Recycling Services","osm_id":"7191954058","tag":{"addr:city":"Springfield","addr:housenumber":"2742","addr:postcode":"62703","addr:state":"IL","addr:street":"South 6th Street","amenity":"recycling","phone":"+1-217-522-9271","recycling_type":"centre","website":"https://www.lakeareadisposal.com/"}},"type":"Feature"}
]
}
