{
"type": "FeatureCollection",
"features": [
	{"geometry":{"coordinates":[-73.207332,44.449293],"type":"Point"},"properties":{"name":"Bottle & Can Redemption Center (shaws)","osm_id":"5469785066","tag":{"amenity":"recycling","operator":"Shaw's","recycling:cans":"yes","recycling:glass_bottles":"yes","recycling_type":"centre"}},"type":"Feature"},
	{"geometry":{"coordinates":[-73.184084,44.462356],"type":"Point"},"properties":{"name":"Bottle & Can Return Machines","osm_id":"5489573673","tag":{"amenity":"recycling","operator":"Hannaford","recycling_type":"centre"}},"type":"Feature"},
	{"geometry":{"coordinates":[-73.206352,44.451536],"type":"Point"},"properties":{"osm_id":"5511877843","tag":{"access":"private","amenity":"waste_disposal","waste":"trash"}},"type":"Feature"},
	{"geometry":{"coordinates":[-73.205242,44.448889],"type":"Point"},"properties":{"osm_id":"5511877880","tag":{"access":"private","amenity":"waste_disposal","waste":"trash"}},"type":"Feature"},
	{"geometry":{"coordinates":[-73.20613,44.449364],"type":"Point"},"properties":{"osm_id":"5511877881","tag":{"access":"private","amenity":"waste_disposal"}},"type":"Feature"},
	{"geometry":{"coordinates":[-73.205194,44.450595],"type":"Point"},"properties":{"osm_id":"5511878022","tag":{"access":"private","amenity":"waste_disposal","waste":"trash"}},"type":"Feature"},
	{"geometry":{"coordinates":[-73.204117,44.449231],"type":"Point"},"properties":{"osm_id":"5520714068","tag":{"access":"private","amenity":"waste_disposal","waste":"trash"}},"type":"Feature"},
	{"geometry":{"coordinates":[-73.204032,44.449726],"type":"Point"},"properties":{"osm_id":"5520714069","tag":{"access":"private","amenity":"waste_disposal","waste":"trash"}},"type":"Feature"},
	{"geometry":{"coordinates":[-73.206079,44.449778],"type":"Point"},"properties":{"osm_id":"5520714070","tag":{"access":"private","amenity":"waste_disposal","waste":"trash"}},"type":"Feature"},
	{"geometry":{"coordinates":[-73.209183,44.444675],"type":"Point"},"properties":{"osm_id":"5534878293","tag":{"access":"private","amenity":"waste_disposal"}},"type":"Feature"},
	{"geometry":{"coordinates":[-73.208972,44.441111],"type":"Point"},"properties":{"barrier":"gate","osm_id":"5534994073","tag":{"access":"private"}},"type":"Feature"},
	{"geometry":{"coordinates":[-73.210762,44.440496],"type":"Point"},"properties":{"barrier":"gate","osm_id":"5534994078","tag":{"access":"private"}},"type":"Feature"},
	{"geometry":{"coordinates":[-73.210736,44.440511],"type":"Point"},"properties":{"barrier":"gate","osm_id":"5534994079","tag":{"access":"private"}},"type":"Feature"}
]
}
