{
"type": "FeatureCollection",
"lastupdate": "2020-08-06T00:00:00Z",
"features": [
	{"geometry":{"coordinates":[-73.207332,44.449293],"type":"Point"},"properties":{"name":"Bottle & Can Redemption Center (shaws)","osm_id":"5469785066","tag":{"amenity":"recycling","operator":"Shaw's","recycling:cans":"yes","recycling:glass_bottles":"yes","recycling_type":"centre"}},"type":"Feature"},
	{"geometry":{"coordinates":[-73.184084,44.462356],"type":"Point"},"properties":{"name":"Bottle & Can Return Machines","osm_id":"5489573673","tag":{"amenity":"recycling","operator":"Hannaford","recycling_type":"centre"}},"type":"Feature"}
]
}
