{
"type": "FeatureCollection",
"features": [
	{"geometry":{"coordinates":[73.315795,28.049391],"type":"Point"},"properties":{"name":"Synthia Water Reserve","osm_id":"4634032570","tag":{"height":"100 ft","landuse":"reservoir","natural":"tree","reservoir_type":"water_storage"}},"type":"Feature"},
	{"geometry":{"coordinates":[73.318252,28.047201],"type":"Point"},"properties":{"osm_id":"4634032573","tag":{"natural":"tree"}},"type":"Feature"}
]
}
