{
"type": "FeatureCollection",
"features": [
	{"geometry":{"coordinates":[73.349432,16.718175],"type":"Point"},"properties":{"name":"Peeple","osm_id":"9141428879","tag":{"natural":"tree"}},"type":"Feature"}
]
}
