{
"type": "FeatureCollection",
"features": [
	{"geometry":{"coordinates":[102.565486,2.285622],"type":"Point"},"properties":{"name":"Pusat Pungutan Sampah","osm_id":"8575483819","tag":{"amenity":"waste_disposal"}},"type":"Feature"}
]
}
