{
"type": "FeatureCollection",
"features": [
	{"geometry":{"coordinates":[2.348577,41.707416],"type":"Point"},"properties":{"name":"Brosa.  Comensa vami cistat carretera","osm_id":"7871996985","tag":{"tourism":"information"}},"type":"Feature"}
]
}
