{
"type": "FeatureCollection",
"features": [
	{"geometry":{"coordinates":[2.348577,41.707416],"type":"Point"},"properties":{"name":"Brosa.  Comensa vami cistat carretera","osm_id":"7871996985","tag":{"tourism":"information"}},"type":"Feature"},
	{"geometry":{"coordinates":[2.348529,41.707461],"type":"Point"},"properties":{"osm_id":"7871996985","tag":{"amenity":"recycling","recycling:cans":"yes","recycling:cardboard":"yes","recycling:plastic_packaging":"yes","recycling_type":"container"}},"type":"Feature"}
]
}
