{
"type": "FeatureCollection",
"features": [
	{"geometry":{"coordinates":[2.297765,6.690682],"type":"Point"},"properties":{"name":"Centre La Joie Plus","osm_id":"5795825753","tag":{"amenity":"recycling","email":"michaelgbeto@gmail.com","office":"company","opening_hours":"Mo-Su 07:00-18:00","phone":"+22997101385"}},"type":"Feature"}
]
}
