{
"type": "FeatureCollection",
"features": [
	{"geometry":{"coordinates":[21.527573,61.570219],"type":"Point"},"properties":{"osm_id":"6678064018","tag":{"amenity":"recycling","colour":"green","recycling_type":"container"}},"type":"Feature"},
	{"geometry":{"coordinates":[21.524663,61.571108],"type":"Point"},"properties":{"osm_id":"6678064019","tag":{"amenity":"recycling","recycling_type":"container"}},"type":"Feature"},
	{"geometry":{"coordinates":[21.526264,61.569711],"type":"Point"},"properties":{"osm_id":"6678064020","tag":{"amenity":"recycling","recycling_type":"container"}},"type":"Feature"},
	{"geometry":{"coordinates":[21.522275,61.566259],"type":"Point"},"properties":{"name":"Trash can","osm_id":"8809092805","tag":{"amenity":"waste_basket"}},"type":"Feature"},
	{"geometry":{"coordinates":[21.521369,61.565524],"type":"Point"},"properties":{"osm_id":"8809843838","tag":{"access":"yes","amenity":"waste_disposal","colour":"black","waste":"mixed;recycling;plastic;organic"}},"type":"Feature"}
]
}
