{
"type": "FeatureCollection",
"features": [
	{"geometry":{"coordinates":[143.893367,-37.626196],"type":"Point"},"properties":{"name":"Tree of Knowledge","osm_id":"3215299017","tag":{"denotation":"landmark","natural":"tree"}},"type":"Feature"},
	{"geometry":{"coordinates":[143.892488,-37.626239],"type":"Point"},"properties":{"osm_id":"3237768632","tag":{"natural":"tree"}},"type":"Feature"},
	{"geometry":{"coordinates":[143.892163,-37.626338],"type":"Point"},"properties":{"osm_id":"3237786268","tag":{"natural":"tree"}},"type":"Feature"},
	{"geometry":{"coordinates":[143.892067,-37.626328],"type":"Point"},"properties":{"osm_id":"3237786269","tag":{"natural":"tree"}},"type":"Feature"}
]
}
