{
"type": "FeatureCollection",
"features": [
	{"geometry":{"coordinates":[-0.624917,42.313346],"type":"Point"},"properties":{"osm_id":"4362145149","tag":{"addr:city":"Loarre","amenity":"recycling","recycling:glass_bottles":"yes","recycling:organic":"yes","recycling:paper":"yes","recycling:plastic_bottles":"yes","recycling_type":"container"}},"type":"Feature"},
	{"geometry":{"coordinates":[-0.623634,42.315828],"type":"Point"},"properties":{"osm_id":"6205008079","tag":{"amenity":"waste_disposal"}},"type":"Feature"}
]
}
