{
"type": "FeatureCollection",
"lastupdate": "2020-08-05T00:00:00Z",
"features": [
	{"geometry":{"coordinates":[-77.156446,38.703578],"type":"Point"},"properties":{"osm_id":"1550886023","tag":{"amenity":"waste_basket"}},"type":"Feature"},
	{"geometry":{"coordinates":[-77.118716,38.721589],"type":"Point"},"properties":{"name":"Poop Station","osm_id":"3618372397","tag":{"amenity":"waste_basket"}},"type":"Feature"},
	{"geometry":{"coordinates":[-77.118187,38.722732],"type":"Point"},"properties":{"name":"Poop Station","osm_id":"3618389452","tag":{"amenity":"waste_basket"}},"type":"Feature"},
	{"geometry":{"coordinates":[-77.119475,38.722294],"type":"Point"},"properties":{"name":"Poop Station","osm_id":"3618391842","tag":{"amenity":"waste_basket"}},"type":"Feature"},
	{"geometry":{"coordinates":[-77.116298,38.723194],"type":"Point"},"properties":{"name":"Poop Station","osm_id":"3618394537","tag":{"amenity":"waste_basket"}},"type":"Feature"}
]
}
