{
"type": "FeatureCollection",
"features": [
	{"geometry":{"coordinates":[28.801864,-16.161072],"type":"Point"},"properties":{"name":"Massive Baobab","osm_id":"1250224042","tag":{"natural":"tree","type":"Baobab"}},"type":"Feature"}
]
}
