{
"type": "FeatureCollection",
"features": [
	{"geometry":{"coordinates":[-93.313022,16.351542],"type":"Point"},"properties":{"name":"La Pochota","osm_id":"5200497937","tag":{"natural":"tree"}},"type":"Feature"},
	{"geometry":{"coordinates":[-93.285977,16.335648],"type":"Point"},"properties":{"osm_id":"5443330943","tag":{"natural":"tree"}},"type":"Feature"},
	{"geometry":{"coordinates":[-93.28596,16.335739],"type":"Point"},"properties":{"osm_id":"5443330944","tag":{"natural":"tree"}},"type":"Feature"}
]
}
