{
"type": "FeatureCollection",
"features": [
	{"geometry":{"coordinates":[140.529006,35.885999],"type":"Point"},"properties":{"name":"\u00e5\u00be\u00a1\u00e7\u00a5\u009e\u00e6\u009c\u00a8","osm_id":"1955173056","tag":{"leaf_type":"needleleaved","name:en":"Divine tree","natural":"tree","tree:diameter":"7.4"}},"type":"Feature"},
	{"geometry":{"coordinates":[140.528769,35.885837],"type":"Point"},"properties":{"name":"\u00e5\u00a4\u00a7\u00e6\u00ad\u00a3\u00e5\u00a4\u00a9\u00e7\u009a\u0087\u00e5\u00be\u00a1\u00e6\u0089\u008b\u00e6\u00a4\u008d\u00e6\u009d\u00be","osm_id":"2019575520","tag":{"leaf_type":"needleleaved","name:en":"Pine tree planted by Emperor Taisho","natural":"tree","start_date":"1911-05-21"}},"type":"Feature"},
	{"geometry":{"coordinates":[140.528465,35.886185],"type":"Point"},"properties":{"name":"\u00e4\u00b8\u0089\u00e6\u009c\u00ac\u00e6\u009d\u0089","osm_id":"5363715280","tag":{"denotation":"natural_monument","leaf_cycle":"evergreen","leaf_type":"needleleaved","natural":"tree"}},"type":"Feature"}
]
}
