{
"type": "FeatureCollection",
"features": [
	{"geometry":{"coordinates":[13.658684,54.572922],"type":"Point"},"properties":{"name":"Mammutbaum","osm_id":"4985413180","tag":{"natural":"tree"}},"type":"Feature"}
]
}
