{
"type": "FeatureCollection",
"features": [
	{"geometry":{"coordinates":[13.650651,53.298301],"type":"Point"},"properties":{"name":"Kaisereiche (1888)","osm_id":"2789873708","tag":{"natural":"tree"}},"type":"Feature"}
]
}
