{
"type": "FeatureCollection",
"features": [
	{"geometry":{"coordinates":[13.654035,50.637382],"type":"Point"},"properties":{"name":"Krusnohorsky pamatny buk","osm_id":"4306457747","tag":{"natural":"tree"}},"type":"Feature"},
	{"geometry":{"coordinates":[13.666362,50.631334],"type":"Point"},"properties":{"osm_id":"4553767916","tag":{"natural":"tree"}},"type":"Feature"}
]
}
