{
"type": "FeatureCollection",
"features": [
	{"geometry":{"coordinates":[13.689553,47.834506],"type":"Point"},"properties":{"name":"Bergulme","osm_id":"3748629771","tag":{"denotation":"natural_monument","leaf_cycle":"deciduous","leaf_type":"broadleaved","natural":"tree"}},"type":"Feature"}
]
}
