{
"type": "FeatureCollection",
"features": [
	{"geometry":{"coordinates":[13.689553,47.834506],"type":"Point"},"properties":{"name":"Bergulme","osm_id":"3748629771","tag":{"denotation":"natural_monument","leaf_cycle":"deciduous","leaf_type":"broadleaved","natural":"tree"}},"type":"Feature"},
	{"geometry":{"coordinates":[13.675282,47.833093],"type":"Point"},"properties":{"osm_id":"8764080972","tag":{"denotation":"natural_monument","leaf_cycle":"evergreen","leaf_type":"needleleaved","natural":"tree"}},"type":"Feature"}
]
}
