{
"type": "FeatureCollection",
"features": [
	{"geometry":{"coordinates":[13.686391,47.134513],"type":"Point"},"properties":{"osm_id":"6200021015","tag":{"natural":"tree"}},"type":"Feature"},
	{"geometry":{"coordinates":[13.686434,47.134466],"type":"Point"},"properties":{"osm_id":"6200021016","tag":{"natural":"tree"}},"type":"Feature"},
	{"geometry":{"coordinates":[13.686607,47.1345],"type":"Point"},"properties":{"osm_id":"6200021017","tag":{"natural":"tree"}},"type":"Feature"},
	{"geometry":{"coordinates":[13.686619,47.134401],"type":"Point"},"properties":{"osm_id":"6200021018","tag":{"natural":"tree"}},"type":"Feature"},
	{"geometry":{"coordinates":[13.686285,47.134359],"type":"Point"},"properties":{"osm_id":"6200021019","tag":{"natural":"tree"}},"type":"Feature"},
	{"geometry":{"coordinates":[13.686168,47.134501],"type":"Point"},"properties":{"osm_id":"6200021020","tag":{"natural":"tree"}},"type":"Feature"},
	{"geometry":{"coordinates":[13.686257,47.134445],"type":"Point"},"properties":{"osm_id":"6200021021","tag":{"natural":"tree"}},"type":"Feature"},
	{"geometry":{"coordinates":[13.686187,47.134569],"type":"Point"},"properties":{"osm_id":"6200021022","tag":{"natural":"tree"}},"type":"Feature"},
	{"geometry":{"coordinates":[13.686294,47.134585],"type":"Point"},"properties":{"osm_id":"6200021023","tag":{"natural":"tree"}},"type":"Feature"},
	{"geometry":{"coordinates":[13.686384,47.134603],"type":"Point"},"properties":{"osm_id":"6200021024","tag":{"natural":"tree"}},"type":"Feature"},
	{"geometry":{"coordinates":[13.686494,47.134624],"type":"Point"},"properties":{"osm_id":"6200021025","tag":{"natural":"tree"}},"type":"Feature"},
	{"geometry":{"coordinates":[13.685967,47.134537],"type":"Point"},"properties":{"osm_id":"6200021026","tag":{"natural":"tree"}},"type":"Feature"},
	{"geometry":{"coordinates":[13.685894,47.134898],"type":"Point"},"properties":{"osm_id":"6200021027","tag":{"natural":"tree"}},"type":"Feature"},
	{"geometry":{"coordinates":[13.685773,47.134518],"type":"Point"},"properties":{"osm_id":"6200021028","tag":{"natural":"tree"}},"type":"Feature"},
	{"geometry":{"coordinates":[13.667459,47.142447],"type":"Point"},"properties":{"name":"Naturdenkmal Rotbuche","osm_id":"8914825627","tag":{"height":"1140","information":"yes","leaf_cycle":"deciduous","leaf_type":"broadleaved","natural":"tree"}},"type":"Feature"}
]
}
