{
"type": "FeatureCollection",
"features": [
	{"geometry":{"coordinates":[6.999331,47.252215],"type":"Point"},"properties":{"osm_id":"2823085612","tag":{"amenity":"waste_basket"}},"type":"Feature"},
	{"geometry":{"coordinates":[6.998922,47.25567],"type":"Point"},"properties":{"osm_id":"2823454304","tag":{"amenity":"recycling","location":"underground","recycling_type":"container"}},"type":"Feature"},
	{"geometry":{"coordinates":[6.991768,47.255372],"type":"Point"},"properties":{"osm_id":"2825962872","tag":{"amenity":"recycling"}},"type":"Feature"},
	{"geometry":{"coordinates":[6.993266,47.258601],"type":"Point"},"properties":{"osm_id":"2825965764","tag":{"amenity":"recycling"}},"type":"Feature"},
	{"geometry":{"coordinates":[6.998411,47.259485],"type":"Point"},"properties":{"osm_id":"2828444151","tag":{"amenity":"recycling"}},"type":"Feature"},
	{"geometry":{"coordinates":[6.950946,47.264377],"type":"Point"},"properties":{"osm_id":"4374221809","tag":{"amenity":"recycling","recycling:cans":"yes","recycling_type":"container"}},"type":"Feature"},
	{"geometry":{"coordinates":[6.952048,47.270067],"type":"Point"},"properties":{"osm_id":"6374143930","tag":{"amenity":"waste_basket"}},"type":"Feature"},
	{"geometry":{"coordinates":[6.950944,47.264405],"type":"Point"},"properties":{"osm_id":"6374147173","tag":{"amenity":"waste_basket"}},"type":"Feature"},
	{"geometry":{"coordinates":[6.949833,47.26234],"type":"Point"},"properties":{"osm_id":"6374380371","tag":{"amenity":"recycling","recycling:glass_bottles":"yes","recycling_type":"container"}},"type":"Feature"},
	{"geometry":{"coordinates":[6.99465,47.254484],"type":"Point"},"properties":{"osm_id":"7640630886","tag":{"amenity":"waste_basket"}},"type":"Feature"},
	{"geometry":{"coordinates":[6.952322,47.261429],"type":"Point"},"properties":{"osm_id":"7657350066","tag":{"amenity":"waste_basket","waste":"trash"}},"type":"Feature"},
	{"geometry":{"coordinates":[6.950948,47.264363],"type":"Point"},"properties":{"osm_id":"7658921428","tag":{"amenity":"recycling","recycling:glass_bottles":"yes","recycling_type":"container"}},"type":"Feature"},
	{"geometry":{"coordinates":[6.951137,47.264341],"type":"Point"},"properties":{"osm_id":"7658921429","tag":{"amenity":"recycling","recycling:waste":"yes","recycling_type":"container"}},"type":"Feature"},
	{"geometry":{"coordinates":[6.951146,47.264359],"type":"Point"},"properties":{"osm_id":"7658921430","tag":{"amenity":"recycling","recycling:waste":"yes","recycling_type":"container"}},"type":"Feature"},
	{"geometry":{"coordinates":[6.979192,47.259513],"type":"Point"},"properties":{"osm_id":"7770963662","tag":{"amenity":"waste_basket","waste":"trash"}},"type":"Feature"},
	{"geometry":{"coordinates":[6.989233,47.272847],"type":"Point"},"properties":{"osm_id":"7771369004","tag":{"amenity":"waste_basket","vending":"excrement_bags","waste":"dog_excrement"}},"type":"Feature"},
	{"geometry":{"coordinates":[6.998753,47.255747],"type":"Point"},"properties":{"osm_id":"7788629596","tag":{"amenity":"recycling","recycling:green_waste":"yes","recycling_type":"container"}},"type":"Feature"},
	{"geometry":{"coordinates":[6.998675,47.25571],"type":"Point"},"properties":{"osm_id":"7788629597","tag":{"amenity":"recycling","recycling:cans":"yes","recycling_type":"container"}},"type":"Feature"},
	{"geometry":{"coordinates":[6.998671,47.255754],"type":"Point"},"properties":{"osm_id":"7788629598","tag":{"amenity":"recycling","recycling:glass":"yes","recycling:glass_bottles":"yes","recycling_type":"container"}},"type":"Feature"},
	{"geometry":{"coordinates":[6.99864,47.255753],"type":"Point"},"properties":{"osm_id":"7788629599","tag":{"amenity":"recycling","recycling:glass":"yes","recycling:glass_bottles":"yes","recycling_type":"container"}},"type":"Feature"},
	{"geometry":{"coordinates":[6.998675,47.255681],"type":"Point"},"properties":{"osm_id":"7788629600","tag":{"amenity":"recycling","recycling:magazines":"yes","recycling:newspaper":"yes","recycling:paper":"yes","recycling_type":"container"}},"type":"Feature"},
	{"geometry":{"coordinates":[6.998837,47.255689],"type":"Point"},"properties":{"osm_id":"7788629601","tag":{"amenity":"recycling","recycling:cardboard":"yes","recycling_type":"container"}},"type":"Feature"},
	{"geometry":{"coordinates":[6.997566,47.255791],"type":"Point"},"properties":{"osm_id":"7788629639","tag":{"amenity":"waste_basket","waste":"trash"}},"type":"Feature"}
]
}
