{
"type": "FeatureCollection",
"lastupdate": "2020-07-31T00:00:00Z",
"features": [
	{"geometry":{"coordinates":[7.014054,45.18705],"type":"Point"},"properties":{"osm_id":"3048049736","tag":{"amenity":"waste_basket"}},"type":"Feature"},
	{"geometry":{"coordinates":[6.982308,45.205299],"type":"Point"},"properties":{"osm_id":"3635180955","tag":{"amenity":"recycling","location":"overground","recycling_type":"container"}},"type":"Feature"},
	{"geometry":{"coordinates":[7.022043,45.186481],"type":"Point"},"properties":{"osm_id":"4272910778","tag":{"amenity":"recycling","recycling:cans":"yes","recycling:glass":"yes","recycling:paper":"yes","recycling:plastic_bottles":"yes","recycling:waste":"yes"}},"type":"Feature"},
	{"geometry":{"coordinates":[6.984292,45.203643],"type":"Point"},"properties":{"osm_id":"4273520223","tag":{"amenity":"recycling","recycling:cans":"yes","recycling:glass":"yes","recycling:paper":"yes","recycling:plastic_bottles":"yes"}},"type":"Feature"},
	{"geometry":{"coordinates":[7.014026,45.187221],"type":"Point"},"properties":{"osm_id":"5811728642","tag":{"amenity":"waste_basket"}},"type":"Feature"},
	{"geometry":{"coordinates":[7.01407,45.190563],"type":"Point"},"properties":{"osm_id":"5846402096","tag":{"amenity":"waste_basket"}},"type":"Feature"},
	{"geometry":{"coordinates":[6.98132,45.204447],"type":"Point"},"properties":{"osm_id":"5940560259","tag":{"amenity":"recycling","location":"overground","recycling_type":"container"}},"type":"Feature"},
	{"geometry":{"coordinates":[7.02033,45.178445],"type":"Point"},"properties":{"osm_id":"7579890671","tag":{"amenity":"waste_basket"}},"type":"Feature"}
]
}
