{
"type": "FeatureCollection",
"features": [
	{"geometry":{"coordinates":[7.014054,45.18705],"type":"Point"},"properties":{"osm_id":"3048049736","tag":{"amenity":"waste_basket"}},"type":"Feature"},
	{"geometry":{"coordinates":[6.982309,45.205299],"type":"Point"},"properties":{"osm_id":"3635180955","tag":{"amenity":"recycling","location":"overground","recycling_type":"container"}},"type":"Feature"},
	{"geometry":{"coordinates":[6.982336,45.2053],"type":"Point"},"properties":{"osm_id":"3635180956","tag":{"amenity":"waste_disposal"}},"type":"Feature"},
	{"geometry":{"coordinates":[6.985085,45.186572],"type":"Point"},"properties":{"osm_id":"3642257779","tag":{"amenity":"waste_disposal"}},"type":"Feature"},
	{"geometry":{"coordinates":[7.022044,45.186481],"type":"Point"},"properties":{"osm_id":"4272910778","tag":{"amenity":"recycling","recycling:cans":"yes","recycling:glass":"yes","recycling:paper":"yes","recycling:plastic_bottles":"yes","recycling:waste":"yes"}},"type":"Feature"},
	{"geometry":{"coordinates":[7.022013,45.18649],"type":"Point"},"properties":{"osm_id":"4272910779","tag":{"amenity":"waste_disposal"}},"type":"Feature"},
	{"geometry":{"coordinates":[6.984292,45.203644],"type":"Point"},"properties":{"osm_id":"4273520223","tag":{"amenity":"recycling","recycling:cans":"yes","recycling:glass":"yes","recycling:paper":"yes","recycling:plastic_bottles":"yes"}},"type":"Feature"},
	{"geometry":{"coordinates":[6.984289,45.20363],"type":"Point"},"properties":{"osm_id":"4273520224","tag":{"amenity":"waste_disposal"}},"type":"Feature"},
	{"geometry":{"coordinates":[7.014026,45.187221],"type":"Point"},"properties":{"osm_id":"5811728642","tag":{"amenity":"waste_basket"}},"type":"Feature"},
	{"geometry":{"coordinates":[7.01407,45.190563],"type":"Point"},"properties":{"osm_id":"5846402096","tag":{"amenity":"waste_basket"}},"type":"Feature"},
	{"geometry":{"coordinates":[6.981321,45.204447],"type":"Point"},"properties":{"osm_id":"5940560259","tag":{"amenity":"recycling","location":"overground","recycling_type":"container"}},"type":"Feature"},
	{"geometry":{"coordinates":[6.981321,45.204437],"type":"Point"},"properties":{"osm_id":"5940560260","tag":{"amenity":"waste_disposal"}},"type":"Feature"},
	{"geometry":{"coordinates":[7.02033,45.178446],"type":"Point"},"properties":{"osm_id":"7579890671","tag":{"amenity":"waste_basket"}},"type":"Feature"}
]
}
