{
"type": "FeatureCollection",
"lastupdate": "2020-08-04T00:00:00Z",
"features": [
	{"geometry":{"coordinates":[7.018749,43.89015],"type":"Point"},"properties":{"name":"Aire de remblai (Terre / Cailloux )","osm_id":"743256822","tag":{"amenity":"recycling"}},"type":"Feature"}
]
}
