{
"type": "FeatureCollection",
"features": [
	{"geometry":{"coordinates":[7.018749,43.890151],"type":"Point"},"properties":{"name":"Aire de remblai (Terre / Cailloux )","osm_id":"743256822","tag":{"amenity":"recycling"}},"type":"Feature"}
]
}
