{
"type": "FeatureCollection",
"features": [
	{"geometry":{"coordinates":[-93.259644,36.684553],"type":"Point"},"properties":{"osm_id":"2682734378","tag":{"amenity":"waste_basket"}},"type":"Feature"},
	{"geometry":{"coordinates":[-93.260476,36.682978],"type":"Point"},"properties":{"osm_id":"2682734379","tag":{"amenity":"waste_basket"}},"type":"Feature"},
	{"geometry":{"coordinates":[-93.259111,36.685766],"type":"Point"},"properties":{"osm_id":"2682734382","tag":{"amenity":"recycling"}},"type":"Feature"},
	{"geometry":{"coordinates":[-93.258378,36.683236],"type":"Point"},"properties":{"osm_id":"2682734385","tag":{"amenity":"waste_basket"}},"type":"Feature"},
	{"geometry":{"coordinates":[-93.259116,36.685813],"type":"Point"},"properties":{"name":"Dumpster","osm_id":"2682734397","tag":{"amenity":"waste_basket"}},"type":"Feature"},
	{"geometry":{"coordinates":[-93.258614,36.684383],"type":"Point"},"properties":{"osm_id":"2682734399","tag":{"amenity":"waste_basket"}},"type":"Feature"}
]
}
