{
"type": "FeatureCollection",
"lastupdate": "2020-07-31T00:00:00Z",
"features": [
	{"geometry":{"coordinates":[-93.259644,36.684552],"type":"Point"},"properties":{"osm_id":"2682734378","tag":{"amenity":"waste_basket"}},"type":"Feature"},
	{"geometry":{"coordinates":[-93.260475,36.682978],"type":"Point"},"properties":{"osm_id":"2682734379","tag":{"amenity":"waste_basket"}},"type":"Feature"},
	{"geometry":{"coordinates":[-93.25911,36.685765],"type":"Point"},"properties":{"osm_id":"2682734382","tag":{"amenity":"recycling"}},"type":"Feature"},
	{"geometry":{"coordinates":[-93.258378,36.683236],"type":"Point"},"properties":{"osm_id":"2682734385","tag":{"amenity":"waste_basket"}},"type":"Feature"},
	{"geometry":{"coordinates":[-93.259116,36.685813],"type":"Point"},"properties":{"name":"Dumpster","osm_id":"2682734397","tag":{"amenity":"waste_basket"}},"type":"Feature"},
	{"geometry":{"coordinates":[-93.258614,36.684382],"type":"Point"},"properties":{"osm_id":"2682734399","tag":{"amenity":"waste_basket"}},"type":"Feature"}
]
}
