{
"type": "FeatureCollection",
"features": [
	{"geometry":{"coordinates":[18.738935,-17.170865],"type":"Point"},"properties":{"name":"R\u00e1\u00bb\u00abng Caila2","osm_id":"5854247594","tag":{"amenity":"recycling"}},"type":"Feature"}
]
}
