{
"type": "FeatureCollection",
"features": [
	{"geometry":{"coordinates":[-0.866808,51.478313],"type":"Point"},"properties":{"osm_id":"1111349908","tag":{"amenity":"recycling","recycling:cans":"no","recycling:clothes":"yes","recycling:glass":"yes"}},"type":"Feature"},
	{"geometry":{"coordinates":[-0.869516,51.500808],"type":"Point"},"properties":{"osm_id":"1278382579","tag":{"amenity":"recycling","location":"overground","recycling_type":"container"}},"type":"Feature"},
	{"geometry":{"coordinates":[-0.868743,51.476779],"type":"Point"},"properties":{"osm_id":"1311009579","tag":{"amenity":"recycling"}},"type":"Feature"},
	{"geometry":{"coordinates":[-0.845886,51.495145],"type":"Point"},"properties":{"osm_id":"1477544025","tag":{"amenity":"recycling","recycling:clothes":"yes","recycling:glass":"yes"}},"type":"Feature"},
	{"geometry":{"coordinates":[-0.869917,51.487375],"type":"Point"},"properties":{"osm_id":"1843335039","tag":{"amenity":"waste_basket"}},"type":"Feature"},
	{"geometry":{"coordinates":[-0.871999,51.499251],"type":"Point"},"properties":{"osm_id":"1843335103","tag":{"amenity":"waste_basket","check_date":"2021-04-18"}},"type":"Feature"},
	{"geometry":{"coordinates":[-0.878629,51.456546],"type":"Point"},"properties":{"osm_id":"1860575122","tag":{"amenity":"waste_basket"}},"type":"Feature"},
	{"geometry":{"coordinates":[-0.80705,51.485144],"type":"Point"},"properties":{"osm_id":"6780635720","tag":{"amenity":"waste_basket","waste":"trash"}},"type":"Feature"},
	{"geometry":{"coordinates":[-0.869257,51.505565],"type":"Point"},"properties":{"osm_id":"9064590119","tag":{"amenity":"waste_basket"}},"type":"Feature"}
]
}
