{
"type": "FeatureCollection",
"features": [
	{"geometry":{"coordinates":[-0.816352,51.199913],"type":"Point"},"properties":{"osm_id":"296972550","tag":{"amenity":"recycling","recycling:cans":"yes"}},"type":"Feature"},
	{"geometry":{"coordinates":[-0.802639,51.215938],"type":"Point"},"properties":{"name":"Recycling containers","osm_id":"297009244","tag":{"addr:city":"Farnham","addr:housename":"Upper Hart Car Park","addr:postcode":"GU9 7HA","addr:street":"The Hart","amenity":"recycling","recycling:cans":"yes","recycling:cardboard":"yes","recycling:cartons":"yes","recycling:foil":"yes","recycling:glass":"yes","recycling:paper":"yes","recycling:plastic_bottles":"yes","recycling:small_appliances":"yes","recycling_type":"container"}},"type":"Feature"},
	{"geometry":{"coordinates":[-0.798712,51.212527],"type":"Point"},"properties":{"osm_id":"297044525","tag":{"amenity":"recycling","recycling:cans":"yes","recycling:foil":"yes","recycling:paper":"yes","recycling:plastic_bottles":"y","recycling:shoes":"yes"}},"type":"Feature"},
	{"geometry":{"coordinates":[-0.794563,51.216104],"type":"Point"},"properties":{"osm_id":"297145485","tag":{"amenity":"recycling"}},"type":"Feature"},
	{"geometry":{"coordinates":[-0.795008,51.213727],"type":"Point"},"properties":{"osm_id":"1324435052","tag":{"amenity":"waste_basket"}},"type":"Feature"},
	{"geometry":{"coordinates":[-0.794766,51.213715],"type":"Point"},"properties":{"osm_id":"1324435142","tag":{"amenity":"waste_basket"}},"type":"Feature"},
	{"geometry":{"coordinates":[-0.796529,51.213216],"type":"Point"},"properties":{"osm_id":"1324435447","tag":{"amenity":"waste_basket","check_date":"2021-09-19"}},"type":"Feature"},
	{"geometry":{"coordinates":[-0.796041,51.213262],"type":"Point"},"properties":{"osm_id":"1324435546","tag":{"amenity":"waste_basket","check_date":"2021-09-19"}},"type":"Feature"},
	{"geometry":{"coordinates":[-0.797238,51.213137],"type":"Point"},"properties":{"osm_id":"1324435547","tag":{"amenity":"waste_basket"}},"type":"Feature"},
	{"geometry":{"coordinates":[-0.795624,51.217093],"type":"Point"},"properties":{"osm_id":"1324435680","tag":{"amenity":"waste_basket"}},"type":"Feature"},
	{"geometry":{"coordinates":[-0.80343,51.213119],"type":"Point"},"properties":{"osm_id":"1328032309","tag":{"amenity":"waste_basket"}},"type":"Feature"},
	{"geometry":{"coordinates":[-0.803068,51.213499],"type":"Point"},"properties":{"osm_id":"1328032358","tag":{"amenity":"waste_basket"}},"type":"Feature"},
	{"geometry":{"coordinates":[-0.801584,51.215363],"type":"Point"},"properties":{"osm_id":"7994999629","tag":{"amenity":"waste_basket"}},"type":"Feature"}
]
}
