{
"type": "FeatureCollection",
"lastupdate": "2020-07-31T00:00:00Z",
"features": [
	{"geometry":{"coordinates":[1.705623,41.900546],"type":"Point"},"properties":{"name":"Deixalleria de Cardona","osm_id":"7527715671","tag":{"amenity":"recycling"}},"type":"Feature"}
]
}
