{
"type": "FeatureCollection",
"features": [
	{"geometry":{"coordinates":[1.705623,41.900546],"type":"Point"},"properties":{"name":"Deixalleria de Cardona","osm_id":"7527715671","tag":{"amenity":"recycling","recycling_type":"centre"}},"type":"Feature"}
]
}
