{
"type": "FeatureCollection",
"features": [
	{"geometry":{"coordinates":[17.073435,47.934905],"type":"Point"},"properties":{"osm_id":"388197458","tag":{"amenity":"recycling","recycling:cans":"yes","recycling:glass":"yes","recycling_type":"container"}},"type":"Feature"},
	{"geometry":{"coordinates":[17.061532,47.942428],"type":"Point"},"properties":{"osm_id":"388514180","tag":{"addr:city":"Nickelsdorf","amenity":"recycling","recycling:paper":"yes","recycling_type":"container"}},"type":"Feature"},
	{"geometry":{"coordinates":[17.068834,47.939687],"type":"Point"},"properties":{"osm_id":"469249836","tag":{"amenity":"recycling","recycling:cans":"yes","recycling:glass":"yes","recycling:scrap_metal":"yes","recycling_type":"container"}},"type":"Feature"},
	{"geometry":{"coordinates":[17.06412,47.943754],"type":"Point"},"properties":{"osm_id":"3675362493","tag":{"amenity":"waste_basket"}},"type":"Feature"},
	{"geometry":{"coordinates":[17.053632,47.958536],"type":"Point"},"properties":{"osm_id":"3683327428","tag":{"amenity":"waste_basket"}},"type":"Feature"},
	{"geometry":{"coordinates":[17.090644,47.945364],"type":"Point"},"properties":{"osm_id":"4404301301","tag":{"amenity":"waste_basket"}},"type":"Feature"},
	{"geometry":{"coordinates":[17.086867,47.942415],"type":"Point"},"properties":{"osm_id":"4404357620","tag":{"amenity":"waste_basket"}},"type":"Feature"},
	{"geometry":{"coordinates":[17.086473,47.942602],"type":"Point"},"properties":{"osm_id":"4404357628","tag":{"amenity":"waste_basket"}},"type":"Feature"},
	{"geometry":{"coordinates":[17.086477,47.942803],"type":"Point"},"properties":{"osm_id":"4404357630","tag":{"amenity":"waste_basket"}},"type":"Feature"},
	{"geometry":{"coordinates":[17.072848,47.935809],"type":"Point"},"properties":{"osm_id":"4404446661","tag":{"amenity":"waste_basket"}},"type":"Feature"},
	{"geometry":{"coordinates":[17.079791,47.937131],"type":"Point"},"properties":{"osm_id":"4404446682","tag":{"amenity":"waste_basket"}},"type":"Feature"},
	{"geometry":{"coordinates":[17.080233,47.937206],"type":"Point"},"properties":{"osm_id":"4404446684","tag":{"amenity":"recycling","recycling:glass_bottles":"yes","recycling_type":"container"}},"type":"Feature"},
	{"geometry":{"coordinates":[17.080071,47.937217],"type":"Point"},"properties":{"osm_id":"4404446685","tag":{"amenity":"waste_basket"}},"type":"Feature"},
	{"geometry":{"coordinates":[17.080115,47.937249],"type":"Point"},"properties":{"osm_id":"4404446686","tag":{"amenity":"recycling","recycling:scrap_metal":"yes","recycling_type":"container"}},"type":"Feature"},
	{"geometry":{"coordinates":[17.062329,47.938986],"type":"Point"},"properties":{"osm_id":"4404446688","tag":{"amenity":"waste_basket"}},"type":"Feature"},
	{"geometry":{"coordinates":[17.063035,47.940634],"type":"Point"},"properties":{"osm_id":"4404446897","tag":{"amenity":"waste_basket"}},"type":"Feature"},
	{"geometry":{"coordinates":[17.062728,47.940954],"type":"Point"},"properties":{"osm_id":"4415297333","tag":{"amenity":"recycling","recycling:cans":"yes","recycling:glass_bottles":"yes","recycling:scrap_metal":"yes","recycling_type":"container"}},"type":"Feature"},
	{"geometry":{"coordinates":[17.07395,47.933111],"type":"Point"},"properties":{"osm_id":"4415297634","tag":{"amenity":"waste_basket"}},"type":"Feature"},
	{"geometry":{"coordinates":[17.070131,47.946173],"type":"Point"},"properties":{"osm_id":"5849373667","tag":{"amenity":"recycling","opening_hours":"24/7","operator":"Gemeinde Nickelsdorf","recycling:cans":"yes","recycling:glass":"yes","recycling:scrap_metal":"no","recycling_type":"container","wheelchair":"limited"}},"type":"Feature"}
]
}
