{
"type": "FeatureCollection",
"lastupdate": "2020-08-03T00:00:00Z",
"features": [
	{"geometry":{"coordinates":[17.073435,47.934905],"type":"Point"},"properties":{"osm_id":"388197458","tag":{"amenity":"recycling","recycling:cans":"yes","recycling:glass":"yes","recycling_type":"container"}},"type":"Feature"},
	{"geometry":{"coordinates":[17.061532,47.942428],"type":"Point"},"properties":{"osm_id":"388514180","tag":{"addr:city":"Nickelsdorf","amenity":"recycling","recycling:paper":"yes","recycling_type":"container"}},"type":"Feature"},
	{"geometry":{"coordinates":[17.068833,47.939686],"type":"Point"},"properties":{"osm_id":"469249836","tag":{"amenity":"recycling","recycling:cans":"yes","recycling:glass":"yes","recycling:scrap_metal":"yes","recycling_type":"container"}},"type":"Feature"},
	{"geometry":{"coordinates":[17.064119,47.943754],"type":"Point"},"properties":{"osm_id":"3675362493","tag":{"amenity":"waste_basket"}},"type":"Feature"},
	{"geometry":{"coordinates":[17.053631,47.958535],"type":"Point"},"properties":{"osm_id":"3683327428","tag":{"amenity":"waste_basket"}},"type":"Feature"},
	{"geometry":{"coordinates":[17.090644,47.945363],"type":"Point"},"properties":{"osm_id":"4404301301","tag":{"amenity":"waste_basket"}},"type":"Feature"},
	{"geometry":{"coordinates":[17.086867,47.942415],"type":"Point"},"properties":{"osm_id":"4404357620","tag":{"amenity":"waste_basket"}},"type":"Feature"},
	{"geometry":{"coordinates":[17.086472,47.942602],"type":"Point"},"properties":{"osm_id":"4404357628","tag":{"amenity":"waste_basket"}},"type":"Feature"},
	{"geometry":{"coordinates":[17.086476,47.942802],"type":"Point"},"properties":{"osm_id":"4404357630","tag":{"amenity":"waste_basket"}},"type":"Feature"},
	{"geometry":{"coordinates":[17.072847,47.935808],"type":"Point"},"properties":{"osm_id":"4404446661","tag":{"amenity":"waste_basket"}},"type":"Feature"},
	{"geometry":{"coordinates":[17.079791,47.937131],"type":"Point"},"properties":{"osm_id":"4404446682","tag":{"amenity":"waste_basket"}},"type":"Feature"},
	{"geometry":{"coordinates":[17.080233,47.937206],"type":"Point"},"properties":{"osm_id":"4404446684","tag":{"amenity":"recycling","recycling:glass_bottles":"yes","recycling_type":"container"}},"type":"Feature"},
	{"geometry":{"coordinates":[17.08007,47.937216],"type":"Point"},"properties":{"osm_id":"4404446685","tag":{"amenity":"waste_basket"}},"type":"Feature"},
	{"geometry":{"coordinates":[17.080115,47.937248],"type":"Point"},"properties":{"osm_id":"4404446686","tag":{"amenity":"recycling","recycling:scrap_metal":"yes","recycling_type":"container"}},"type":"Feature"},
	{"geometry":{"coordinates":[17.062328,47.938986],"type":"Point"},"properties":{"osm_id":"4404446688","tag":{"amenity":"waste_basket"}},"type":"Feature"},
	{"geometry":{"coordinates":[17.063034,47.940633],"type":"Point"},"properties":{"osm_id":"4404446897","tag":{"amenity":"waste_basket"}},"type":"Feature"},
	{"geometry":{"coordinates":[17.062728,47.940954],"type":"Point"},"properties":{"osm_id":"4415297333","tag":{"amenity":"recycling","recycling:cans":"yes","recycling:glass_bottles":"yes","recycling:scrap_metal":"yes","recycling_type":"container"}},"type":"Feature"},
	{"geometry":{"coordinates":[17.073949,47.93311],"type":"Point"},"properties":{"osm_id":"4415297634","tag":{"amenity":"waste_basket"}},"type":"Feature"},
	{"geometry":{"coordinates":[17.07013,47.946172],"type":"Point"},"properties":{"osm_id":"5849373667","tag":{"amenity":"recycling","opening_hours":"24/7","operator":"Gemeinde Nickelsdorf","recycling:cans":"yes","recycling:glass":"yes","recycling:scrap_metal":"no","recycling_type":"container","wheelchair":"limited"}},"type":"Feature"}
]
}
