{
"type": "FeatureCollection",
"lastupdate": "2020-08-05T00:00:00Z",
"features": [
	{"geometry":{"coordinates":[-83.527912,41.713593],"type":"Point"},"properties":{"name":"Toledo Topsoil and Mulch LLC","osm_id":"2518094462","tag":{"addr:housenumber":"5315","addr:street":"Stickney Avenue","amenity":"recycling","recycling:asphalt":"yes","recycling:green_waste":"yes","recycling:waste":"yes","recycling:wood":"yes"}},"type":"Feature"}
]
}
