{
"type": "FeatureCollection",
"features": [
	{"geometry":{"coordinates":[-85.483359,39.337116],"type":"Point"},"properties":{"name":"Greensburg Courthouse Tree","osm_id":"8899532402","tag":{"natural":"tree"}},"type":"Feature"},
	{"geometry":{"coordinates":[-85.483665,39.336812],"type":"Point"},"properties":{"osm_id":"8899661244","tag":{"natural":"tree"}},"type":"Feature"},
	{"geometry":{"coordinates":[-85.483914,39.336797],"type":"Point"},"properties":{"osm_id":"8899661245","tag":{"natural":"tree"}},"type":"Feature"},
	{"geometry":{"coordinates":[-85.483969,39.336905],"type":"Point"},"properties":{"osm_id":"8899661246","tag":{"natural":"tree"}},"type":"Feature"},
	{"geometry":{"coordinates":[-85.48388,39.336967],"type":"Point"},"properties":{"osm_id":"8899661247","tag":{"natural":"tree"}},"type":"Feature"},
	{"geometry":{"coordinates":[-85.483051,39.337512],"type":"Point"},"properties":{"osm_id":"8899661252","tag":{"natural":"tree"}},"type":"Feature"},
	{"geometry":{"coordinates":[-85.483085,39.337444],"type":"Point"},"properties":{"osm_id":"8899661253","tag":{"natural":"tree"}},"type":"Feature"},
	{"geometry":{"coordinates":[-85.483807,39.33744],"type":"Point"},"properties":{"osm_id":"8899661254","tag":{"natural":"tree"}},"type":"Feature"},
	{"geometry":{"coordinates":[-85.483918,39.337305],"type":"Point"},"properties":{"osm_id":"8899661255","tag":{"natural":"tree"}},"type":"Feature"},
	{"geometry":{"coordinates":[-85.483957,39.337208],"type":"Point"},"properties":{"osm_id":"8899661256","tag":{"natural":"tree"}},"type":"Feature"},
	{"geometry":{"coordinates":[-85.483873,39.337206],"type":"Point"},"properties":{"osm_id":"8899661257","tag":{"natural":"tree"}},"type":"Feature"},
	{"geometry":{"coordinates":[-85.483208,39.337037],"type":"Point"},"properties":{"osm_id":"8899661258","tag":{"natural":"tree"}},"type":"Feature"},
	{"geometry":{"coordinates":[-85.483109,39.337223],"type":"Point"},"properties":{"osm_id":"8899661259","tag":{"natural":"tree"}},"type":"Feature"},
	{"geometry":{"coordinates":[-85.483101,39.336804],"type":"Point"},"properties":{"osm_id":"8899661278","tag":{"natural":"tree"}},"type":"Feature"}
]
}
