{
"type": "FeatureCollection",
"features": [
	{"geometry":{"coordinates":[-16.476252,14.537391],"type":"Point"},"properties":{"osm_id":"5406074517","tag":{"addr:city":"Toukar","natural":"tree"}},"type":"Feature"},
	{"geometry":{"coordinates":[-16.476322,14.539117],"type":"Point"},"properties":{"osm_id":"5406075931","tag":{"addr:city":"Toukar","natural":"tree"}},"type":"Feature"},
	{"geometry":{"coordinates":[-16.475616,14.538567],"type":"Point"},"properties":{"osm_id":"5406075932","tag":{"addr:city":"Toukar","natural":"tree"}},"type":"Feature"},
	{"geometry":{"coordinates":[-16.477463,14.538116],"type":"Point"},"properties":{"osm_id":"5406075941","tag":{"addr:city":"Toukar","natural":"tree"}},"type":"Feature"},
	{"geometry":{"coordinates":[-16.477436,14.538411],"type":"Point"},"properties":{"osm_id":"5406075942","tag":{"addr:city":"Toukar","natural":"tree"}},"type":"Feature"},
	{"geometry":{"coordinates":[-16.477059,14.537872],"type":"Point"},"properties":{"osm_id":"5406075951","tag":{"addr:city":"Toukar","natural":"tree"}},"type":"Feature"},
	{"geometry":{"coordinates":[-16.476574,14.537952],"type":"Point"},"properties":{"osm_id":"5406075952","tag":{"addr:city":"Toukar","natural":"tree"}},"type":"Feature"},
	{"geometry":{"coordinates":[-16.477028,14.537115],"type":"Point"},"properties":{"osm_id":"5406075953","tag":{"addr:city":"Toukar","natural":"tree"}},"type":"Feature"},
	{"geometry":{"coordinates":[-16.477061,14.5368],"type":"Point"},"properties":{"osm_id":"5406075958","tag":{"addr:city":"Toukar","natural":"tree"}},"type":"Feature"},
	{"geometry":{"coordinates":[-16.476794,14.536773],"type":"Point"},"properties":{"osm_id":"5406075959","tag":{"addr:city":"Toukar","natural":"tree"}},"type":"Feature"}
]
}
