{
"type": "FeatureCollection",
"features": [
	{"geometry":{"coordinates":[139.28296,-28.401297],"type":"Point"},"properties":{"name":"Mckinlay's Tree Memorial","osm_id":"2385091398","tag":{"historic":"memorial","natural":"tree"}},"type":"Feature"},
	{"geometry":{"coordinates":[139.284014,-28.400959],"type":"Point"},"properties":{"name":"Mckinlay's Tree","osm_id":"2385091399","tag":{"natural":"tree"}},"type":"Feature"}
]
}
