{
"type": "FeatureCollection",
"features": [
	{"geometry":{"coordinates":[-76.583035,41.471906],"type":"Point"},"properties":{"osm_id":"1429423016","tag":{"amenity":"waste_basket"}},"type":"Feature"},
	{"geometry":{"coordinates":[-76.568992,41.469569],"type":"Point"},"properties":{"osm_id":"1837151787","tag":{"amenity":"waste_basket"}},"type":"Feature"},
	{"geometry":{"coordinates":[-76.577947,41.467574],"type":"Point"},"properties":{"name":"Recycling","osm_id":"4624015512","tag":{"amenity":"recycling","recycling_type":"container"}},"type":"Feature"}
]
}
