{
"type": "FeatureCollection",
"features": [
	{"geometry":{"coordinates":[5.737417,34.835564],"type":"Point"},"properties":{"name":"Sarwla","osm_id":"3451385269","tag":{"natural":"tree"}},"type":"Feature"}
]
}
