{
"type": "FeatureCollection",
"lastupdate": "2020-07-31T00:00:00Z",
"features": [
	{"geometry":{"coordinates":[18.456154,46.10206],"type":"Point"},"properties":{"osm_id":"3464280030","tag":{"addr:city":"Erzs\u00e9bet","addr:street":"Bor utca d\u00e9li v\u00e9ge","amenity":"recycling","source:date":"2011-09-08","url":"http://turistautak.hu/poi.php?id=97627"}},"type":"Feature"}
]
}
