{
"type": "FeatureCollection",
"lastupdate": "2020-08-05T00:00:00Z",
"features": [
	{"geometry":{"coordinates":[-8.23858,52.931593],"type":"Point"},"properties":{"osm_id":"6447392463","tag":{"amenity":"waste_basket"}},"type":"Feature"},
	{"geometry":{"coordinates":[-8.237569,52.931983],"type":"Point"},"properties":{"name":"Bottle bank","osm_id":"6447398657","tag":{"amenity":"recycling"}},"type":"Feature"},
	{"geometry":{"coordinates":[-8.238855,52.932294],"type":"Point"},"properties":{"osm_id":"6447401785","tag":{"amenity":"waste_basket"}},"type":"Feature"}
]
}
