{
"type": "FeatureCollection",
"features": [
	{"geometry":{"coordinates":[-8.215427,52.859583],"type":"Point"},"properties":{"name":"Nenagh Civic Amenity Site","osm_id":"323215277","tag":{"amenity":"recycling","opening_hours":"Tu-Fr 08:30-12:30,13:00-16:30; Sa 13:00-15:30","recycling:batteries":"yes","recycling:cans":"yes","recycling:christmas_trees":"yes","recycling:clothes":"no","recycling:electrical_appliances":"yes","recycling:glass":"yes","recycling:paper":"yes","recycling:small_appliances":"yes","recycling:tv_monitor":"yes","recycling_type":"centre","wheelchair":"yes"}},"type":"Feature"},
	{"geometry":{"coordinates":[-8.194412,52.862909],"type":"Point"},"properties":{"osm_id":"401355060","tag":{"amenity":"recycling","recycling:cans":"yes","recycling:glass":"yes"}},"type":"Feature"},
	{"geometry":{"coordinates":[-8.197118,52.871179],"type":"Point"},"properties":{"osm_id":"648605074","tag":{"amenity":"recycling","location":"overground","recycling:clothes":"yes","recycling:glass":"yes","recycling_type":"container"}},"type":"Feature"},
	{"geometry":{"coordinates":[-8.24393,52.891337],"type":"Point"},"properties":{"osm_id":"850148734","tag":{"amenity":"recycling","recycling:clothes":"yes"}},"type":"Feature"},
	{"geometry":{"coordinates":[-8.192546,52.864703],"type":"Point"},"properties":{"osm_id":"859437468","tag":{"amenity":"waste_basket","waste":"dog_excrement"}},"type":"Feature"},
	{"geometry":{"coordinates":[-8.192964,52.85751],"type":"Point"},"properties":{"osm_id":"1357918999","tag":{"amenity":"recycling","location":"overground","recycling:clothes":"yes","recycling_type":"container"}},"type":"Feature"},
	{"geometry":{"coordinates":[-8.210395,52.860882],"type":"Point"},"properties":{"osm_id":"1364839083","tag":{"amenity":"waste_basket"}},"type":"Feature"},
	{"geometry":{"coordinates":[-8.210707,52.86079],"type":"Point"},"properties":{"osm_id":"1364839084","tag":{"amenity":"waste_basket"}},"type":"Feature"},
	{"geometry":{"coordinates":[-8.210336,52.86129],"type":"Point"},"properties":{"osm_id":"1364839085","tag":{"amenity":"waste_basket"}},"type":"Feature"},
	{"geometry":{"coordinates":[-8.22327,52.866978],"type":"Point"},"properties":{"osm_id":"1503326698","tag":{"amenity":"waste_basket","waste":"dog_excrement"}},"type":"Feature"},
	{"geometry":{"coordinates":[-8.211578,52.868073],"type":"Point"},"properties":{"osm_id":"1503480273","tag":{"amenity":"waste_basket","waste":"dog_excrement"}},"type":"Feature"},
	{"geometry":{"coordinates":[-8.221985,52.870787],"type":"Point"},"properties":{"osm_id":"1518719776","tag":{"amenity":"waste_basket","waste":"dog_excrement"}},"type":"Feature"},
	{"geometry":{"coordinates":[-8.227347,52.874656],"type":"Point"},"properties":{"osm_id":"1518719779","tag":{"amenity":"waste_basket","waste":"dog_excrement"}},"type":"Feature"},
	{"geometry":{"coordinates":[-8.198501,52.862027],"type":"Point"},"properties":{"osm_id":"1837113366","tag":{"amenity":"waste_basket"}},"type":"Feature"},
	{"geometry":{"coordinates":[-8.196805,52.863141],"type":"Point"},"properties":{"osm_id":"1837113382","tag":{"amenity":"waste_basket"}},"type":"Feature"},
	{"geometry":{"coordinates":[-8.212377,52.861417],"type":"Point"},"properties":{"osm_id":"2336383840","tag":{"amenity":"waste_basket"}},"type":"Feature"},
	{"geometry":{"coordinates":[-8.198797,52.865144],"type":"Point"},"properties":{"osm_id":"2376638896","tag":{"amenity":"waste_basket"}},"type":"Feature"},
	{"geometry":{"coordinates":[-8.198384,52.865361],"type":"Point"},"properties":{"osm_id":"2376638900","tag":{"amenity":"waste_basket"}},"type":"Feature"},
	{"geometry":{"coordinates":[-8.230866,52.857351],"type":"Point"},"properties":{"osm_id":"6570180594","tag":{"amenity":"waste_basket","waste":"dog_excrement"}},"type":"Feature"},
	{"geometry":{"coordinates":[-8.196261,52.863318],"type":"Point"},"properties":{"osm_id":"6570180595","tag":{"amenity":"waste_basket","waste":"dog_excrement"}},"type":"Feature"}
]
}
