{
"type": "FeatureCollection",
"features": [
	{"geometry":{"coordinates":[-118.916011,36.777286],"type":"Point"},"properties":{"name":"Log Pile","osm_id":"5054608267","tag":{"natural":"tree"}},"type":"Feature"}
]
}
