{
"type": "FeatureCollection",
"features": [
	{"geometry":{"coordinates":[99.969233,9.77624],"type":"Point"},"properties":{"osm_id":"3329463750","tag":{"amenity":"waste_basket"}},"type":"Feature"},
	{"geometry":{"coordinates":[100.014246,9.735205],"type":"Point"},"properties":{"osm_id":"5279096757","tag":{"amenity":"waste_basket"}},"type":"Feature"},
	{"geometry":{"coordinates":[99.961436,9.766673],"type":"Point"},"properties":{"osm_id":"6531770585","tag":{"amenity":"waste_basket"}},"type":"Feature"},
	{"geometry":{"coordinates":[99.96525,9.759703],"type":"Point"},"properties":{"osm_id":"8465537917","tag":{"amenity":"recycling","name:en":"Plastic Recycling","recycling_type":"centre"}},"type":"Feature"}
]
}
