{
"type": "FeatureCollection",
"features": [
	{"geometry":{"coordinates":[83.817486,28.421361],"type":"Point"},"properties":{"name":"Waste Collection Center","osm_id":"6968249328","tag":{"addr:city":"Annapurna Rural Mun 11","addr:hamlet":"Chomrong","amenity":"waste_disposal","waste":"trash"}},"type":"Feature"},
	{"geometry":{"coordinates":[83.81771,28.423308],"type":"Point"},"properties":{"osm_id":"6968249339","tag":{"amenity":"waste_basket"}},"type":"Feature"}
]
}
