{
"type": "FeatureCollection",
"features": [
	{"geometry":{"coordinates":[-1.294499,53.676551],"type":"Point"},"properties":{"osm_id":"1591394398","tag":{"amenity":"waste_basket"}},"type":"Feature"},
	{"geometry":{"coordinates":[-1.302015,53.695644],"type":"Point"},"properties":{"osm_id":"7180445667","tag":{"amenity":"waste_basket","waste":"dog_excrement"}},"type":"Feature"},
	{"geometry":{"coordinates":[-1.307109,53.695417],"type":"Point"},"properties":{"osm_id":"7514404933","tag":{"amenity":"waste_basket","colour":"Black/Dark Grey","description":"On lampost 1","material":"plastic","operator":"Wakefield Council","waste":"trash;dog_excrement;recycling;mixed"}},"type":"Feature"},
	{"geometry":{"coordinates":[-1.316866,53.695401],"type":"Point"},"properties":{"osm_id":"7632225970","tag":{"amenity":"waste_basket","collection_times":"Thursday any time","material":"reinforced_concrete","operator":"Wakefield Council.","waste":"trash;dog_excrement;mixed;recycling"}},"type":"Feature"},
	{"geometry":{"coordinates":[-1.309799,53.69239],"type":"Point"},"properties":{"osm_id":"7804470535","tag":{"amenity":"waste_basket","waste":"trash;mixed;dog_excrement;recycling"}},"type":"Feature"},
	{"geometry":{"coordinates":[-1.313671,53.693535],"type":"Point"},"properties":{"osm_id":"7826597121","tag":{"addr:city":"Pontefract","addr:postcode":"WF8 4PQ","addr:street":"Stuart Road","amenity":"recycling","opening_hours":"24/7","opening_hours:covid19":"open","operator":"Shanks","operator:type":"public","recycling:clothes":"yes","recycling:glass":"yes","recycling:mixed":"yes","recycling:paper":"yes","recycling_type":"centre"}},"type":"Feature"},
	{"geometry":{"coordinates":[-1.307801,53.696652],"type":"Point"},"properties":{"osm_id":"7848376097","tag":{"amenity":"waste_basket","colour":"Blue","material":"concrete","operator":"Wakefield Council","waste":"trash;mixed;dog_excrement;recycling"}},"type":"Feature"},
	{"geometry":{"coordinates":[-1.31106,53.695541],"type":"Point"},"properties":{"osm_id":"7850578424","tag":{"amenity":"waste_basket","colour":"Black","material":"metal","operator":"Wakefield Council","waste":"trash;dog_excrement;mixed;recycling"}},"type":"Feature"},
	{"geometry":{"coordinates":[-1.306067,53.693699],"type":"Point"},"properties":{"osm_id":"7852121272","tag":{"amenity":"waste_basket","colour":"Black","material":"cast_iron","operator":"Wakefield Council","waste":"trash;dog_excrement;mixed;recycling"}},"type":"Feature"}
]
}
