{
"type": "FeatureCollection",
"features": [
	{"geometry":{"coordinates":[-1.2551,51.402689],"type":"Point"},"properties":{"osm_id":"389046456","tag":{"amenity":"recycling"}},"type":"Feature"},
	{"geometry":{"coordinates":[-1.274674,51.399578],"type":"Point"},"properties":{"osm_id":"719360428","tag":{"amenity":"waste_basket","waste":"trash"}},"type":"Feature"},
	{"geometry":{"coordinates":[-1.270556,51.40099],"type":"Point"},"properties":{"osm_id":"719479627","tag":{"amenity":"waste_basket","waste":"dog_excrement"}},"type":"Feature"},
	{"geometry":{"coordinates":[-1.273749,51.400483],"type":"Point"},"properties":{"osm_id":"719479636","tag":{"amenity":"recycling","recycling:paper":"yes"}},"type":"Feature"},
	{"geometry":{"coordinates":[-1.258753,51.400528],"type":"Point"},"properties":{"name":"Dog Bin","osm_id":"4697321846","tag":{"amenity":"waste_basket"}},"type":"Feature"},
	{"geometry":{"coordinates":[-1.25875,51.400718],"type":"Point"},"properties":{"osm_id":"4720920995","tag":{"amenity":"waste_basket"}},"type":"Feature"},
	{"geometry":{"coordinates":[-1.254329,51.403636],"type":"Point"},"properties":{"osm_id":"4901450491","tag":{"amenity":"waste_basket"}},"type":"Feature"},
	{"geometry":{"coordinates":[-1.249532,51.404375],"type":"Point"},"properties":{"osm_id":"5532753805","tag":{"amenity":"waste_basket"}},"type":"Feature"},
	{"geometry":{"coordinates":[-1.24952,51.404438],"type":"Point"},"properties":{"osm_id":"5532753806","tag":{"amenity":"waste_basket"}},"type":"Feature"},
	{"geometry":{"coordinates":[-1.274124,51.400274],"type":"Point"},"properties":{"osm_id":"5588840809","tag":{"amenity":"waste_basket","waste":"dog_excrement"}},"type":"Feature"},
	{"geometry":{"coordinates":[-1.27467,51.399588],"type":"Point"},"properties":{"osm_id":"5588840817","tag":{"amenity":"waste_basket","waste":"dog_excrement"}},"type":"Feature"},
	{"geometry":{"coordinates":[-1.273501,51.399959],"type":"Point"},"properties":{"osm_id":"5588841726","tag":{"amenity":"waste_basket","waste":"trash"}},"type":"Feature"},
	{"geometry":{"coordinates":[-1.273776,51.399873],"type":"Point"},"properties":{"osm_id":"5588841727","tag":{"amenity":"waste_basket","waste":"trash"}},"type":"Feature"}
]
}
