{
"type": "FeatureCollection",
"lastupdate": "2020-08-05T00:00:00Z",
"features": [
	{"geometry":{"coordinates":[-1.268191,44.019817],"type":"Point"},"properties":{"name":"Camping Lassalle","osm_id":"7440802358","tag":{"access":"customers","amenity":"recycling","operator":"SITCOM - C\u00f4te sud des Landes","operator:wikidata":"Q90819597","recycling:glass_bottles":"yes","recycling:plastic_bottles":"yes","recycling_type":"container","ref:FR:SITCOM":"PAV-374387"}},"type":"Feature"},
	{"geometry":{"coordinates":[-1.272547,43.992258],"type":"Point"},"properties":{"name":"Salle Des Fetes","osm_id":"7440802370","tag":{"amenity":"recycling","operator":"SITCOM - C\u00f4te sud des Landes","operator:wikidata":"Q90819597","recycling:batteries":"yes","recycling:cans":"yes","recycling:glass_bottles":"yes","recycling:paper":"yes","recycling:paper_packaging":"yes","recycling:plastic_bottles":"yes","recycling_type":"container","ref:FR:SITCOM":"PAV-374306"}},"type":"Feature"},
	{"geometry":{"coordinates":[-1.278243,44.024002],"type":"Point"},"properties":{"name":"Camping Les Vignes","osm_id":"7440803491","tag":{"access":"customers","amenity":"recycling","operator":"SITCOM - C\u00f4te sud des Landes","operator:wikidata":"Q90819597","recycling:batteries":"yes","recycling:cans":"yes","recycling:glass_bottles":"yes","recycling:paper":"yes","recycling:paper_packaging":"yes","recycling:plastic_bottles":"yes","recycling_type":"container","ref:FR:SITCOM":"PAV-374356"}},"type":"Feature"}
]
}
