{
"type": "FeatureCollection",
"features": [
	{"geometry":{"coordinates":[89.358966,24.840975],"type":"Point"},"properties":{"osm_id":"4363498421","tag":{"natural":"tree"}},"type":"Feature"},
	{"geometry":{"coordinates":[89.35896,24.840917],"type":"Point"},"properties":{"osm_id":"4363498731","tag":{"natural":"tree"}},"type":"Feature"},
	{"geometry":{"coordinates":[89.359129,24.840711],"type":"Point"},"properties":{"osm_id":"4363518699","tag":{"natural":"tree"}},"type":"Feature"},
	{"geometry":{"coordinates":[89.359564,24.841173],"type":"Point"},"properties":{"osm_id":"4364393561","tag":{"natural":"tree"}},"type":"Feature"},
	{"geometry":{"coordinates":[89.35954,24.841428],"type":"Point"},"properties":{"osm_id":"4364397166","tag":{"natural":"tree"}},"type":"Feature"},
	{"geometry":{"coordinates":[89.359522,24.841419],"type":"Point"},"properties":{"osm_id":"4364402194","tag":{"natural":"tree"}},"type":"Feature"},
	{"geometry":{"coordinates":[89.359553,24.841397],"type":"Point"},"properties":{"osm_id":"4364402195","tag":{"natural":"tree"}},"type":"Feature"},
	{"geometry":{"coordinates":[89.359539,24.841416],"type":"Point"},"properties":{"osm_id":"4364402196","tag":{"natural":"tree"}},"type":"Feature"},
	{"geometry":{"coordinates":[89.359538,24.841398],"type":"Point"},"properties":{"osm_id":"4364402197","tag":{"natural":"tree"}},"type":"Feature"},
	{"geometry":{"coordinates":[89.359531,24.841401],"type":"Point"},"properties":{"osm_id":"4364402198","tag":{"natural":"tree"}},"type":"Feature"},
	{"geometry":{"coordinates":[89.359518,24.84141],"type":"Point"},"properties":{"osm_id":"4364402199","tag":{"natural":"tree"}},"type":"Feature"},
	{"geometry":{"coordinates":[89.35952,24.841394],"type":"Point"},"properties":{"osm_id":"4364402200","tag":{"natural":"tree"}},"type":"Feature"},
	{"geometry":{"coordinates":[89.359363,24.820541],"type":"Point"},"properties":{"name":"Bot Gas","osm_id":"6517061421","tag":{"natural":"tree"}},"type":"Feature"}
]
}
