{
"type": "FeatureCollection",
"features": [
	{"geometry":{"coordinates":[89.359364,24.820541],"type":"Point"},"properties":{"name":"Bot Gas","osm_id":"6517061421","tag":{"natural":"tree"}},"type":"Feature"}
]
}
