{
"type": "FeatureCollection",
"lastupdate": "2020-08-04T00:00:00Z",
"features": [
	{"geometry":{"coordinates":[-106.063504,28.656799],"type":"Point"},"properties":{"name":"Papelera de Chihuahua","osm_id":"6617876750","tag":{"amenity":"recycling","recycling_type":"centre"}},"type":"Feature"}
]
}
