{
"type": "FeatureCollection",
"features": [
	{"geometry":{"coordinates":[-106.063504,28.6568],"type":"Point"},"properties":{"name":"Papelera de Chihuahua","osm_id":"6617876750","tag":{"amenity":"recycling","recycling_type":"centre"}},"type":"Feature"}
]
}
