{
"type": "FeatureCollection",
"features": [
	{"geometry":{"coordinates":[19.635472,41.859421],"type":"Point"},"properties":{"name":"CINARI I HANIT","osm_id":"3586919331","tag":{"natural":"tree"}},"type":"Feature"},
	{"geometry":{"coordinates":[19.652816,41.863688],"type":"Point"},"properties":{"name":"Rrapi i Dashurise","osm_id":"5528060931","tag":{"natural":"tree"}},"type":"Feature"}
]
}
