{
"type": "FeatureCollection",
"lastupdate": "2020-08-03T00:00:00Z",
"features": [
	{"geometry":{"coordinates":[77.662697,12.850232],"type":"Point"},"properties":{"name":"E-Waste Disposal Kiosk","osm_id":"3153843550","tag":{"amenity":"recycling","operator":"ELCIA","recycling:clothes":"no","recycling_type":"centre"}},"type":"Feature"}
]
}
