{
"type": "FeatureCollection",
"features": [
	{"geometry":{"coordinates":[16.051827,48.856916],"type":"Point"},"properties":{"osm_id":"869223137","tag":{"amenity":"recycling","recycling:glass":"yes","recycling:paper":"yes","recycling_type":"container"}},"type":"Feature"},
	{"geometry":{"coordinates":[16.048213,48.863069],"type":"Point"},"properties":{"osm_id":"1088585601","tag":{"amenity":"recycling","location":"overground","recycling:glass":"yes","recycling:paper":"yes","recycling_type":"container"}},"type":"Feature"},
	{"geometry":{"coordinates":[16.051438,48.861066],"type":"Point"},"properties":{"osm_id":"1147572791","tag":{"amenity":"recycling","location":"overground","recycling:glass":"yes","recycling:paper":"yes","recycling_type":"container"}},"type":"Feature"},
	{"geometry":{"coordinates":[16.058373,48.856054],"type":"Point"},"properties":{"osm_id":"1147672256","tag":{"amenity":"recycling","recycling:glass_bottles":"yes","recycling:paper":"yes","recycling:plastic_bottles":"yes","recycling_type":"container"}},"type":"Feature"},
	{"geometry":{"coordinates":[16.060952,48.854966],"type":"Point"},"properties":{"osm_id":"1147672448","tag":{"amenity":"recycling","location":"overground","recycling:glass_bottles":"yes","recycling:paper":"yes","recycling:plastic":"yes","recycling_type":"container"}},"type":"Feature"},
	{"geometry":{"coordinates":[16.044262,48.855358],"type":"Point"},"properties":{"osm_id":"1757057716","tag":{"amenity":"waste_basket"}},"type":"Feature"},
	{"geometry":{"coordinates":[16.048742,48.850813],"type":"Point"},"properties":{"osm_id":"3749294083","tag":{"amenity":"recycling","recycling:glass_bottles":"yes","recycling:paper":"yes","recycling:plastic":"yes","recycling:plastic_bottles":"yes","recycling:plastic_packaging":"yes","recycling_type":"container"}},"type":"Feature"},
	{"geometry":{"coordinates":[16.056224,48.853421],"type":"Point"},"properties":{"osm_id":"3752843274","tag":{"amenity":"recycling","recycling:clothes":"yes","recycling:electrical_appliances":"yes","recycling:glass_bottles":"yes","recycling:paper":"yes","recycling:plastic_bottles":"yes","recycling_type":"container"}},"type":"Feature"},
	{"geometry":{"coordinates":[16.043394,48.857411],"type":"Point"},"properties":{"osm_id":"4756492026","tag":{"amenity":"waste_basket"}},"type":"Feature"},
	{"geometry":{"coordinates":[16.059835,48.856715],"type":"Point"},"properties":{"osm_id":"5941233059","tag":{"amenity":"recycling","recycling:glass_bottles":"yes","recycling:paper":"yes","recycling:plastic":"yes","recycling:small_appliances":"yes","recycling_type":"container"}},"type":"Feature"},
	{"geometry":{"coordinates":[16.058512,48.853549],"type":"Point"},"properties":{"osm_id":"6050997170","tag":{"amenity":"recycling","recycling:glass":"yes","recycling:paper":"yes","recycling:plastic":"yes","recycling_type":"container"}},"type":"Feature"},
	{"geometry":{"coordinates":[16.059522,48.854014],"type":"Point"},"properties":{"osm_id":"6051003462","tag":{"amenity":"waste_basket"}},"type":"Feature"},
	{"geometry":{"coordinates":[16.059551,48.854254],"type":"Point"},"properties":{"osm_id":"6051003463","tag":{"amenity":"waste_basket"}},"type":"Feature"},
	{"geometry":{"coordinates":[16.060724,48.855043],"type":"Point"},"properties":{"osm_id":"6051003464","tag":{"amenity":"waste_basket"}},"type":"Feature"},
	{"geometry":{"coordinates":[16.060178,48.856035],"type":"Point"},"properties":{"osm_id":"6051003465","tag":{"amenity":"waste_basket"}},"type":"Feature"},
	{"geometry":{"coordinates":[16.061523,48.852875],"type":"Point"},"properties":{"osm_id":"6051003466","tag":{"amenity":"waste_basket"}},"type":"Feature"},
	{"geometry":{"coordinates":[16.058923,48.853601],"type":"Point"},"properties":{"osm_id":"6051003467","tag":{"amenity":"waste_basket"}},"type":"Feature"},
	{"geometry":{"coordinates":[16.040827,48.856223],"type":"Point"},"properties":{"osm_id":"8484453150","tag":{"amenity":"waste_basket"}},"type":"Feature"},
	{"geometry":{"coordinates":[16.045974,48.854217],"type":"Point"},"properties":{"osm_id":"8820983397","tag":{"amenity":"waste_basket","waste":"trash"}},"type":"Feature"},
	{"geometry":{"coordinates":[16.046063,48.853917],"type":"Point"},"properties":{"osm_id":"8820983398","tag":{"amenity":"waste_basket","waste":"trash"}},"type":"Feature"},
	{"geometry":{"coordinates":[16.051205,48.855277],"type":"Point"},"properties":{"osm_id":"8945163950","tag":{"amenity":"recycling","recycling:paper":"yes","recycling:plastic":"yes","recycling_type":"container"}},"type":"Feature"}
]
}
