{
"type": "FeatureCollection",
"features": [
	{"geometry":{"coordinates":[16.054383,47.48271],"type":"Point"},"properties":{"osm_id":"3913301469","tag":{"amenity":"recycling","location":"overground","recycling_type":"container"}},"type":"Feature"},
	{"geometry":{"coordinates":[16.03568,47.497974],"type":"Point"},"properties":{"osm_id":"5005314643","tag":{"amenity":"waste_disposal"}},"type":"Feature"},
	{"geometry":{"coordinates":[16.03346,47.475866],"type":"Point"},"properties":{"osm_id":"5171455733","tag":{"amenity":"waste_disposal"}},"type":"Feature"},
	{"geometry":{"coordinates":[16.058211,47.469237],"type":"Point"},"properties":{"osm_id":"5577295026","tag":{"amenity":"waste_basket"}},"type":"Feature"}
]
}
