{
"type": "FeatureCollection",
"lastupdate": "2020-08-04T00:00:00Z",
"features": [
	{"geometry":{"coordinates":[18.95025,46.687517],"type":"Point"},"properties":{"osm_id":"3452836272","tag":{"amenity":"recycling","location":"overground","recycling_type":"container","source:date":"2012-01-01","url":"http://turistautak.hu/poi.php?id=131414"}},"type":"Feature"},
	{"geometry":{"coordinates":[18.957633,46.691833],"type":"Point"},"properties":{"osm_id":"3452836277","tag":{"amenity":"recycling","source:date":"2012-01-01","url":"http://turistautak.hu/poi.php?id=131407"}},"type":"Feature"},
	{"geometry":{"coordinates":[18.965683,46.7341],"type":"Point"},"properties":{"osm_id":"3452836301","tag":{"amenity":"recycling","source:date":"2012-01-01","url":"http://turistautak.hu/poi.php?id=131405"}},"type":"Feature"}
]
}
