{
"type": "FeatureCollection",
"features": [
	{"geometry":{"coordinates":[-80.301673,32.511577],"type":"Point"},"properties":{"name":"Live Oak","osm_id":"4100715204","tag":{"natural":"tree"}},"type":"Feature"}
]
}
