{
"type": "FeatureCollection",
"lastupdate": "2020-08-06T00:00:00Z",
"features": [
	{"geometry":{"coordinates":[16.880327,49.15941],"type":"Point"},"properties":{"osm_id":"4839763741","tag":{"amenity":"recycling","recycling_type":"container"}},"type":"Feature"},
	{"geometry":{"coordinates":[16.881737,49.162203],"type":"Point"},"properties":{"osm_id":"4839763742","tag":{"amenity":"recycling","recycling_type":"container"}},"type":"Feature"},
	{"geometry":{"coordinates":[16.884197,49.207144],"type":"Point"},"properties":{"osm_id":"6532120505","tag":{"amenity":"recycling","material":"plastic","operator":"RESPONO a.s.","recycling:aluminium":"yes","recycling:cans":"yes","recycling:cartons":"yes","recycling:glass_bottles":"yes","recycling:green_waste":"yes","recycling:organic":"yes","recycling:paper":"yes","recycling:plastic":"yes","recycling_type":"container"}},"type":"Feature"},
	{"geometry":{"coordinates":[16.883177,49.207667],"type":"Point"},"properties":{"osm_id":"6603633831","tag":{"amenity":"recycling","recycling:cardboard":"yes","recycling:green_waste":"yes","recycling:paper":"yes","recycling:plastic":"yes","recycling:plastic_bottles":"yes","recycling_type":"container"}},"type":"Feature"},
	{"geometry":{"coordinates":[16.884012,49.208393],"type":"Point"},"properties":{"osm_id":"6629052661","tag":{"amenity":"recycling","location":"overground","recycling:cans":"yes","recycling:green_waste":"yes","recycling:paper":"yes","recycling:plastic":"yes","recycling_type":"container"}},"type":"Feature"},
	{"geometry":{"coordinates":[16.883725,49.208537],"type":"Point"},"properties":{"osm_id":"6629078263","tag":{"amenity":"recycling","location":"overground","recycling:cans":"yes","recycling:glass_bottles":"yes","recycling:green_waste":"yes","recycling:paper":"yes","recycling:plastic":"yes","recycling_type":"container"}},"type":"Feature"},
	{"geometry":{"coordinates":[16.882942,49.208406],"type":"Point"},"properties":{"osm_id":"6631905950","tag":{"amenity":"recycling","location":"overground","recycling_type":"container"}},"type":"Feature"},
	{"geometry":{"coordinates":[16.878077,49.202663],"type":"Point"},"properties":{"osm_id":"7551816915","tag":{"amenity":"recycling","recycling:aluminium":"yes","recycling:batteries":"yes","recycling:cans":"yes","recycling:cartons":"yes","recycling:electrical_appliances":"yes","recycling:glass_bottles":"yes","recycling:paper":"yes","recycling:plastic":"yes","recycling_type":"container"}},"type":"Feature"},
	{"geometry":{"coordinates":[16.88381,49.208357],"type":"Point"},"properties":{"osm_id":"7575417793","tag":{"amenity":"recycling","recycling:batteries":"yes","recycling:clothes":"yes","recycling:cooking_oil":"yes","recycling:shoes":"yes","recycling:small_electrical_appliances":"yes","recycling_type":"container"}},"type":"Feature"},
	{"geometry":{"coordinates":[16.884924,49.207476],"type":"Point"},"properties":{"osm_id":"7575491174","tag":{"amenity":"recycling","recycling_type":"container"}},"type":"Feature"},
	{"geometry":{"coordinates":[16.885422,49.207876],"type":"Point"},"properties":{"osm_id":"7575491175","tag":{"amenity":"recycling","recycling_type":"container"}},"type":"Feature"},
	{"geometry":{"coordinates":[16.884624,49.208172],"type":"Point"},"properties":{"osm_id":"7575491176","tag":{"amenity":"recycling","recycling:cans":"yes","recycling:green_waste":"yes","recycling:paper":"yes","recycling:plastic":"yes","recycling_type":"container"}},"type":"Feature"}
]
}
