{
"type": "FeatureCollection",
"features": [
	{"geometry":{"coordinates":[16.880328,49.15941],"type":"Point"},"properties":{"osm_id":"4839763741","tag":{"amenity":"recycling","recycling_type":"container"}},"type":"Feature"},
	{"geometry":{"coordinates":[16.881738,49.162204],"type":"Point"},"properties":{"osm_id":"4839763742","tag":{"amenity":"recycling","recycling_type":"container"}},"type":"Feature"},
	{"geometry":{"coordinates":[16.884198,49.207144],"type":"Point"},"properties":{"osm_id":"6532120505","tag":{"amenity":"recycling","material":"plastic","operator":"RESPONO a.s.","recycling:aluminium":"yes","recycling:cans":"yes","recycling:cartons":"yes","recycling:glass_bottles":"yes","recycling:green_waste":"yes","recycling:organic":"yes","recycling:paper":"yes","recycling:plastic":"yes","recycling_type":"container"}},"type":"Feature"},
	{"geometry":{"coordinates":[16.883178,49.207667],"type":"Point"},"properties":{"osm_id":"6603633831","tag":{"amenity":"recycling","recycling:cardboard":"yes","recycling:green_waste":"yes","recycling:paper":"yes","recycling:plastic":"yes","recycling:plastic_bottles":"yes","recycling_type":"container"}},"type":"Feature"},
	{"geometry":{"coordinates":[16.884012,49.208394],"type":"Point"},"properties":{"osm_id":"6629052661","tag":{"amenity":"recycling","location":"overground","recycling:cans":"yes","recycling:green_waste":"yes","recycling:paper":"yes","recycling:plastic":"yes","recycling_type":"container"}},"type":"Feature"},
	{"geometry":{"coordinates":[16.883726,49.208538],"type":"Point"},"properties":{"osm_id":"6629078263","tag":{"amenity":"recycling","location":"overground","recycling:cans":"yes","recycling:glass_bottles":"yes","recycling:green_waste":"yes","recycling:paper":"yes","recycling:plastic":"yes","recycling_type":"container"}},"type":"Feature"},
	{"geometry":{"coordinates":[16.882942,49.208407],"type":"Point"},"properties":{"osm_id":"6631905950","tag":{"amenity":"recycling","location":"overground","recycling_type":"container"}},"type":"Feature"},
	{"geometry":{"coordinates":[16.878077,49.202664],"type":"Point"},"properties":{"osm_id":"7551816915","tag":{"amenity":"recycling","recycling:aluminium":"yes","recycling:batteries":"yes","recycling:cans":"yes","recycling:cartons":"yes","recycling:electrical_appliances":"yes","recycling:glass_bottles":"yes","recycling:paper":"yes","recycling:plastic":"yes","recycling_type":"container"}},"type":"Feature"},
	{"geometry":{"coordinates":[16.88381,49.208358],"type":"Point"},"properties":{"osm_id":"7575417793","tag":{"amenity":"recycling","recycling:batteries":"yes","recycling:clothes":"yes","recycling:cooking_oil":"yes","recycling:shoes":"yes","recycling:small_electrical_appliances":"yes","recycling_type":"container"}},"type":"Feature"},
	{"geometry":{"coordinates":[16.884924,49.207476],"type":"Point"},"properties":{"osm_id":"7575491174","tag":{"amenity":"recycling","recycling_type":"container"}},"type":"Feature"},
	{"geometry":{"coordinates":[16.885423,49.207876],"type":"Point"},"properties":{"osm_id":"7575491175","tag":{"amenity":"recycling","recycling_type":"container"}},"type":"Feature"},
	{"geometry":{"coordinates":[16.884625,49.208172],"type":"Point"},"properties":{"osm_id":"7575491176","tag":{"amenity":"recycling","recycling:cans":"yes","recycling:green_waste":"yes","recycling:paper":"yes","recycling:plastic":"yes","recycling_type":"container"}},"type":"Feature"},
	{"geometry":{"coordinates":[16.884226,49.207149],"type":"Point"},"properties":{"osm_id":"7597717864","tag":{"access":"yes","amenity":"waste_disposal","operator":"RESPONO a.s."}},"type":"Feature"},
	{"geometry":{"coordinates":[16.884947,49.207472],"type":"Point"},"properties":{"osm_id":"7597717865","tag":{"access":"yes","amenity":"waste_disposal","operator":"RESPONO a.s."}},"type":"Feature"},
	{"geometry":{"coordinates":[16.885445,49.2079],"type":"Point"},"properties":{"osm_id":"7597717866","tag":{"access":"yes","amenity":"waste_disposal","operator":"RESPONO a.s."}},"type":"Feature"},
	{"geometry":{"coordinates":[16.884641,49.208166],"type":"Point"},"properties":{"osm_id":"7597717867","tag":{"access":"yes","amenity":"waste_disposal","operator":"RESPONO a.s."}},"type":"Feature"}
]
}
