{
"type": "FeatureCollection",
"lastupdate": "2020-08-04T00:00:00Z",
"features": [
	{"geometry":{"coordinates":[3.292534,50.642022],"type":"Point"},"properties":{"osm_id":"5429473229","tag":{"amenity":"recycling","recycling:glass":"yes","recycling_type":"container"}},"type":"Feature"},
	{"geometry":{"coordinates":[3.290375,50.642854],"type":"Point"},"properties":{"name":"Poubelle","osm_id":"6327494407","tag":{"amenity":"waste_basket"}},"type":"Feature"},
	{"geometry":{"coordinates":[3.290509,50.643221],"type":"Point"},"properties":{"name":"Poubelle","osm_id":"7048916775","tag":{"amenity":"waste_basket"}},"type":"Feature"},
	{"geometry":{"coordinates":[3.285872,50.647494],"type":"Point"},"properties":{"osm_id":"7549003736","tag":{"amenity":"recycling","recycling:clothes":"yes","recycling_type":"container"}},"type":"Feature"}
]
}
