{
"type": "FeatureCollection",
"features": [
	{"geometry":{"coordinates":[137.550828,36.181359],"type":"Point"},"properties":{"osm_id":"5650694590","tag":{"name:en":"Hirayu large Nezuko tree","natural":"tree","tourism":"attraction"}},"type":"Feature"}
]
}
