{
"type": "FeatureCollection",
"features": [
	{"geometry":{"coordinates":[19.181853,53.212047],"type":"Point"},"properties":{"osm_id":"4706691054","tag":{"denotation":"natural_monument","natural":"tree","ref:CRFOP":"PL.ZIPOP.1393.PP.0405032.611","ref:INSPIRE":"PL.ZIPOP.1393.PP.0405032.611","website":"http://crfop.gdos.gov.pl/CRFOP/widok/viewfop.jsf?fop=PL.ZIPOP.1393.PP.0405032.611"}},"type":"Feature"},
	{"geometry":{"coordinates":[19.231803,53.199452],"type":"Point"},"properties":{"osm_id":"4706691056","tag":{"denotation":"natural_monument","natural":"tree","ref:CRFOP":"PL.ZIPOP.1393.PP.0405032.609","ref:INSPIRE":"PL.ZIPOP.1393.PP.0405032.609","website":"http://crfop.gdos.gov.pl/CRFOP/widok/viewfop.jsf?fop=PL.ZIPOP.1393.PP.0405032.609"}},"type":"Feature"},
	{"geometry":{"coordinates":[19.196162,53.21153],"type":"Point"},"properties":{"osm_id":"5093986490","tag":{"natural":"tree"}},"type":"Feature"}
]
}
