{
"type": "FeatureCollection",
"features": [
	{"geometry":{"coordinates":[19.186878,52.84108],"type":"Point"},"properties":{"osm_id":"4706681674","tag":{"denotation":"natural_monument","natural":"tree","ref:CRFOP":"PL.ZIPOP.1393.PP.0408011.6002","ref:INSPIRE":"PL.ZIPOP.1393.PP.0408011.6002","website":"http://crfop.gdos.gov.pl/CRFOP/widok/viewfop.jsf?fop=PL.ZIPOP.1393.PP.0408011.6002"}},"type":"Feature"},
	{"geometry":{"coordinates":[19.183903,52.840522],"type":"Point"},"properties":{"osm_id":"4706681675","tag":{"denotation":"natural_monument","natural":"tree","ref:CRFOP":"PL.ZIPOP.1393.PP.0408011.6001","ref:INSPIRE":"PL.ZIPOP.1393.PP.0408011.6001","website":"http://crfop.gdos.gov.pl/CRFOP/widok/viewfop.jsf?fop=PL.ZIPOP.1393.PP.0408011.6001"}},"type":"Feature"},
	{"geometry":{"coordinates":[19.184908,52.840056],"type":"Point"},"properties":{"osm_id":"4706681676","tag":{"denotation":"natural_monument","natural":"tree","ref:CRFOP":"PL.ZIPOP.1393.PP.0408011.1039","ref:INSPIRE":"PL.ZIPOP.1393.PP.0408011.1039","website":"http://crfop.gdos.gov.pl/CRFOP/widok/viewfop.jsf?fop=PL.ZIPOP.1393.PP.0408011.1039"}},"type":"Feature"},
	{"geometry":{"coordinates":[19.178997,52.84228],"type":"Point"},"properties":{"osm_id":"4706681677","tag":{"denotation":"natural_monument","natural":"tree","ref:CRFOP":"PL.ZIPOP.1393.PP.0408011.1038","ref:INSPIRE":"PL.ZIPOP.1393.PP.0408011.1038","website":"http://crfop.gdos.gov.pl/CRFOP/widok/viewfop.jsf?fop=PL.ZIPOP.1393.PP.0408011.1038"}},"type":"Feature"},
	{"geometry":{"coordinates":[19.178738,52.842338],"type":"Point"},"properties":{"osm_id":"4706681678","tag":{"denotation":"natural_monument","natural":"tree","ref:CRFOP":"PL.ZIPOP.1393.PP.0408011.1038","ref:INSPIRE":"PL.ZIPOP.1393.PP.0408011.1038","website":"http://crfop.gdos.gov.pl/CRFOP/widok/viewfop.jsf?fop=PL.ZIPOP.1393.PP.0408011.1038"}},"type":"Feature"},
	{"geometry":{"coordinates":[19.16376,52.836283],"type":"Point"},"properties":{"osm_id":"5654787987","tag":{"leaf_cycle":"evergreen","leaf_type":"needleleaved","natural":"tree"}},"type":"Feature"},
	{"geometry":{"coordinates":[19.163837,52.836267],"type":"Point"},"properties":{"osm_id":"5654787988","tag":{"leaf_cycle":"evergreen","leaf_type":"needleleaved","natural":"tree"}},"type":"Feature"},
	{"geometry":{"coordinates":[19.163792,52.836467],"type":"Point"},"properties":{"osm_id":"5654787989","tag":{"denotation":"single","leaf_cycle":"deciduous","leaf_type":"broadleaved","natural":"tree"}},"type":"Feature"},
	{"geometry":{"coordinates":[19.178222,52.841756],"type":"Point"},"properties":{"osm_id":"6823918965","tag":{"natural":"tree"}},"type":"Feature"},
	{"geometry":{"coordinates":[19.178546,52.842159],"type":"Point"},"properties":{"osm_id":"6823918966","tag":{"natural":"tree"}},"type":"Feature"},
	{"geometry":{"coordinates":[19.178954,52.842046],"type":"Point"},"properties":{"osm_id":"6823918967","tag":{"natural":"tree"}},"type":"Feature"},
	{"geometry":{"coordinates":[19.178554,52.841647],"type":"Point"},"properties":{"osm_id":"6823918968","tag":{"natural":"tree"}},"type":"Feature"},
	{"geometry":{"coordinates":[19.178836,52.841835],"type":"Point"},"properties":{"osm_id":"6823918969","tag":{"natural":"tree"}},"type":"Feature"},
	{"geometry":{"coordinates":[19.178471,52.84205],"type":"Point"},"properties":{"osm_id":"6823918970","tag":{"natural":"tree"}},"type":"Feature"},
	{"geometry":{"coordinates":[19.178466,52.842149],"type":"Point"},"properties":{"osm_id":"6823918971","tag":{"natural":"tree"}},"type":"Feature"},
	{"geometry":{"coordinates":[19.178865,52.841313],"type":"Point"},"properties":{"osm_id":"6828613403","tag":{"natural":"tree"}},"type":"Feature"},
	{"geometry":{"coordinates":[19.178378,52.841007],"type":"Point"},"properties":{"osm_id":"6828613414","tag":{"natural":"tree"}},"type":"Feature"},
	{"geometry":{"coordinates":[19.178513,52.840976],"type":"Point"},"properties":{"osm_id":"6828613415","tag":{"natural":"tree"}},"type":"Feature"},
	{"geometry":{"coordinates":[19.17861,52.840949],"type":"Point"},"properties":{"osm_id":"6828613416","tag":{"natural":"tree"}},"type":"Feature"},
	{"geometry":{"coordinates":[19.178851,52.841197],"type":"Point"},"properties":{"osm_id":"6828613491","tag":{"natural":"tree"}},"type":"Feature"}
]
}
