{
"type": "FeatureCollection",
"features": [
	{"geometry":{"coordinates":[19.186878,52.84108],"type":"Point"},"properties":{"osm_id":"4706681674","tag":{"denotation":"natural_monument","natural":"tree","ref:CRFOP":"PL.ZIPOP.1393.PP.0408011.6002","ref:INSPIRE":"PL.ZIPOP.1393.PP.0408011.6002","website":"http://crfop.gdos.gov.pl/CRFOP/widok/viewfop.jsf?fop=PL.ZIPOP.1393.PP.0408011.6002"}},"type":"Feature"},
	{"geometry":{"coordinates":[19.183903,52.840521],"type":"Point"},"properties":{"osm_id":"4706681675","tag":{"denotation":"natural_monument","natural":"tree","ref:CRFOP":"PL.ZIPOP.1393.PP.0408011.6001","ref:INSPIRE":"PL.ZIPOP.1393.PP.0408011.6001","website":"http://crfop.gdos.gov.pl/CRFOP/widok/viewfop.jsf?fop=PL.ZIPOP.1393.PP.0408011.6001"}},"type":"Feature"},
	{"geometry":{"coordinates":[19.184908,52.840055],"type":"Point"},"properties":{"osm_id":"4706681676","tag":{"denotation":"natural_monument","natural":"tree","ref:CRFOP":"PL.ZIPOP.1393.PP.0408011.1039","ref:INSPIRE":"PL.ZIPOP.1393.PP.0408011.1039","website":"http://crfop.gdos.gov.pl/CRFOP/widok/viewfop.jsf?fop=PL.ZIPOP.1393.PP.0408011.1039"}},"type":"Feature"},
	{"geometry":{"coordinates":[19.178996,52.842279],"type":"Point"},"properties":{"osm_id":"4706681677","tag":{"denotation":"natural_monument","natural":"tree","ref:CRFOP":"PL.ZIPOP.1393.PP.0408011.1038","ref:INSPIRE":"PL.ZIPOP.1393.PP.0408011.1038","website":"http://crfop.gdos.gov.pl/CRFOP/widok/viewfop.jsf?fop=PL.ZIPOP.1393.PP.0408011.1038"}},"type":"Feature"},
	{"geometry":{"coordinates":[19.178737,52.842338],"type":"Point"},"properties":{"osm_id":"4706681678","tag":{"denotation":"natural_monument","natural":"tree","ref:CRFOP":"PL.ZIPOP.1393.PP.0408011.1038","ref:INSPIRE":"PL.ZIPOP.1393.PP.0408011.1038","website":"http://crfop.gdos.gov.pl/CRFOP/widok/viewfop.jsf?fop=PL.ZIPOP.1393.PP.0408011.1038"}},"type":"Feature"},
	{"geometry":{"coordinates":[19.163759,52.836283],"type":"Point"},"properties":{"osm_id":"5654787987","tag":{"leaf_cycle":"evergreen","leaf_type":"needleleaved","natural":"tree"}},"type":"Feature"},
	{"geometry":{"coordinates":[19.163837,52.836267],"type":"Point"},"properties":{"osm_id":"5654787988","tag":{"leaf_cycle":"evergreen","leaf_type":"needleleaved","natural":"tree"}},"type":"Feature"},
	{"geometry":{"coordinates":[19.163791,52.836467],"type":"Point"},"properties":{"osm_id":"5654787989","tag":{"denotation":"single","leaf_cycle":"deciduous","leaf_type":"broadleaved","natural":"tree"}},"type":"Feature"},
	{"geometry":{"coordinates":[19.178221,52.841755],"type":"Point"},"properties":{"osm_id":"6823918965","tag":{"natural":"tree"}},"type":"Feature"},
	{"geometry":{"coordinates":[19.178546,52.842158],"type":"Point"},"properties":{"osm_id":"6823918966","tag":{"natural":"tree"}},"type":"Feature"},
	{"geometry":{"coordinates":[19.178953,52.842045],"type":"Point"},"properties":{"osm_id":"6823918967","tag":{"natural":"tree"}},"type":"Feature"},
	{"geometry":{"coordinates":[19.178554,52.841647],"type":"Point"},"properties":{"osm_id":"6823918968","tag":{"natural":"tree"}},"type":"Feature"},
	{"geometry":{"coordinates":[19.178835,52.841834],"type":"Point"},"properties":{"osm_id":"6823918969","tag":{"natural":"tree"}},"type":"Feature"},
	{"geometry":{"coordinates":[19.178471,52.84205],"type":"Point"},"properties":{"osm_id":"6823918970","tag":{"natural":"tree"}},"type":"Feature"},
	{"geometry":{"coordinates":[19.178465,52.842149],"type":"Point"},"properties":{"osm_id":"6823918971","tag":{"natural":"tree"}},"type":"Feature"},
	{"geometry":{"coordinates":[19.178865,52.841313],"type":"Point"},"properties":{"osm_id":"6828613403","tag":{"natural":"tree"}},"type":"Feature"},
	{"geometry":{"coordinates":[19.178377,52.841006],"type":"Point"},"properties":{"osm_id":"6828613414","tag":{"natural":"tree"}},"type":"Feature"},
	{"geometry":{"coordinates":[19.178512,52.840976],"type":"Point"},"properties":{"osm_id":"6828613415","tag":{"natural":"tree"}},"type":"Feature"},
	{"geometry":{"coordinates":[19.178609,52.840949],"type":"Point"},"properties":{"osm_id":"6828613416","tag":{"natural":"tree"}},"type":"Feature"},
	{"geometry":{"coordinates":[19.17885,52.841197],"type":"Point"},"properties":{"osm_id":"6828613491","tag":{"natural":"tree"}},"type":"Feature"}
]
}
