{
"type": "FeatureCollection",
"features": [
	{"geometry":{"coordinates":[6.721644,50.245785],"type":"Point"},"properties":{"name":"Befreiungsbuche","osm_id":"949887529","tag":{"natural":"tree","tourism":"attraction"}},"type":"Feature"},
	{"geometry":{"coordinates":[6.681347,50.236811],"type":"Point"},"properties":{"osm_id":"2314891361","tag":{"natural":"tree"}},"type":"Feature"},
	{"geometry":{"coordinates":[6.681477,50.236958],"type":"Point"},"properties":{"osm_id":"2314891362","tag":{"natural":"tree"}},"type":"Feature"},
	{"geometry":{"coordinates":[6.702257,50.277914],"type":"Point"},"properties":{"osm_id":"3556968652","tag":{"natural":"tree"}},"type":"Feature"},
	{"geometry":{"coordinates":[6.767559,50.279221],"type":"Point"},"properties":{"osm_id":"7242307079","tag":{"natural":"tree"}},"type":"Feature"}
]
}
