{
"type": "FeatureCollection",
"features": [
	{"geometry":{"coordinates":[101.662321,3.244005],"type":"Point"},"properties":{"osm_id":"4442464766","tag":{"amenity":"recycling","recycling:cans":"yes","recycling:cardboard":"yes","recycling:glass":"yes","recycling:glass_bottles":"yes","recycling:paper":"yes","recycling:plastic_bottles":"yes","recycling:plastic_packaging":"yes","recycling_type":"container"}},"type":"Feature"},
	{"geometry":{"coordinates":[101.66868,3.210002],"type":"Point"},"properties":{"osm_id":"7320807763","tag":{"amenity":"waste_disposal","waste":"mixed"}},"type":"Feature"},
	{"geometry":{"coordinates":[101.667659,3.210483],"type":"Point"},"properties":{"name":"Bin 3","osm_id":"8377810685","tag":{"amenity":"recycling","operator":"Community Recycle for Charity (CRC)","recycling:cans":"yes","recycling:cardboard":"yes","recycling:glass_bottles":"yes","recycling:paper":"yes","recycling:plastic":"yes","recycling_type":"container","website":"http://crcbox.org/"}},"type":"Feature"},
	{"geometry":{"coordinates":[101.668498,3.210046],"type":"Point"},"properties":{"name":"Bin 4","osm_id":"8377810686","tag":{"amenity":"recycling","operator":"Community Recycle for Charity (CRC)","recycling:cans":"yes","recycling:cardboard":"yes","recycling:glass_bottles":"yes","recycling:paper":"yes","recycling:plastic":"yes","recycling_type":"container","website":"http://crcbox.org/"}},"type":"Feature"},
	{"geometry":{"coordinates":[101.66727,3.209331],"type":"Point"},"properties":{"name":"Bin 2","osm_id":"8377810687","tag":{"amenity":"recycling","operator":"Community Recycle for Charity (CRC)","recycling:cans":"yes","recycling:cardboard":"yes","recycling:glass_bottles":"yes","recycling:paper":"yes","recycling:plastic":"yes","recycling_type":"container","website":"http://crcbox.org/"}},"type":"Feature"},
	{"geometry":{"coordinates":[101.668632,3.208694],"type":"Point"},"properties":{"name":"Bin1","osm_id":"8377810688","tag":{"amenity":"recycling","operator":"Community Recycle for Charity (CRC)","recycling:cans":"yes","recycling:cardboard":"yes","recycling:glass_bottles":"yes","recycling:paper":"yes","recycling:plastic":"yes","recycling_type":"container","website":"http://crcbox.org/"}},"type":"Feature"}
]
}
