{
"type": "FeatureCollection",
"features": [
	{"geometry":{"coordinates":[29.61429,-1.319235],"type":"Point"},"properties":{"name":"Kabaya C O U","osm_id":"6759525831","tag":{"addr:county":"Bufumbira","addr:district":"Kisoro","addr:parish":"Bunagana","addr:subcounty":"Muramba","addr:village":"Gatwe","amenity":"waste_disposal","fee":"no","lit":"no","operator":"community","start_date":"2002-02-01","waste":"compost pit"}},"type":"Feature"},
	{"geometry":{"coordinates":[29.612598,-1.329495],"type":"Point"},"properties":{"name":"Ntamutindi","osm_id":"6759533447","tag":{"addr:county":"Bufumbira","addr:district":"Kisoro","addr:parish":"Muramba","addr:subcounty":"Muramba","addr:village":"Kanombe","amenity":"waste_disposal","fee":"no","lit":"no","operator":"community","start_date":"2016-01-01","waste":"compst pit"}},"type":"Feature"}
]
}
