{
"type": "FeatureCollection",
"lastupdate": "2020-08-04T00:00:00Z",
"features": [
	{"geometry":{"coordinates":[0.849204,49.859904],"type":"Point"},"properties":{"osm_id":"544477752","tag":{"amenity":"recycling","location":"overground","recycling:glass_bottles":"yes","recycling:paper":"yes","recycling:plastic_packaging":"yes","recycling_type":"container"}},"type":"Feature"},
	{"geometry":{"coordinates":[0.804172,49.874812],"type":"Point"},"properties":{"osm_id":"2415199774","tag":{"amenity":"recycling","recycling:glass":"yes","recycling:glass_bottles":"yes","recycling_type":"container"}},"type":"Feature"},
	{"geometry":{"coordinates":[0.87209,49.893169],"type":"Point"},"properties":{"osm_id":"5017983986","tag":{"amenity":"recycling","recycling:glass_bottles":"yes","recycling:paper":"yes","recycling:plastic_packaging":"yes","recycling_type":"container"}},"type":"Feature"},
	{"geometry":{"coordinates":[0.870613,49.887388],"type":"Point"},"properties":{"osm_id":"5017983988","tag":{"amenity":"recycling","recycling:glass_bottles":"yes","recycling:paper":"yes","recycling:plastic_packaging":"yes","recycling_type":"container"}},"type":"Feature"},
	{"geometry":{"coordinates":[0.798452,49.868685],"type":"Point"},"properties":{"osm_id":"7621864664","tag":{"amenity":"waste_basket","waste":"trash"}},"type":"Feature"},
	{"geometry":{"coordinates":[0.829902,49.887056],"type":"Point"},"properties":{"osm_id":"7622586554","tag":{"amenity":"recycling","recycling:cardboard":"yes","recycling:plastic_packaging":"yes","recycling_type":"container"}},"type":"Feature"},
	{"geometry":{"coordinates":[0.829858,49.887048],"type":"Point"},"properties":{"osm_id":"7622586555","tag":{"amenity":"recycling","recycling:glass_bottles":"yes","recycling_type":"container"}},"type":"Feature"},
	{"geometry":{"coordinates":[0.82955,49.882092],"type":"Point"},"properties":{"osm_id":"7626507459","tag":{"amenity":"waste_basket","waste":"trash"}},"type":"Feature"},
	{"geometry":{"coordinates":[0.829903,49.882909],"type":"Point"},"properties":{"osm_id":"7658841452","tag":{"amenity":"waste_basket","waste":"trash"}},"type":"Feature"}
]
}
