{
"type": "FeatureCollection",
"lastupdate": "2020-08-04T00:00:00Z",
"features": [
	{"geometry":{"coordinates":[17.826067,59.445502],"type":"Point"},"properties":{"osm_id":"29818231","tag":{"amenity":"recycling"}},"type":"Feature"},
	{"geometry":{"coordinates":[17.805872,59.45792],"type":"Point"},"properties":{"osm_id":"501802020","tag":{"amenity":"recycling","location":"overground","recycling_type":"container"}},"type":"Feature"},
	{"geometry":{"coordinates":[17.755391,59.484098],"type":"Point"},"properties":{"osm_id":"2798487313","tag":{"amenity":"recycling","recycling_type":"container"}},"type":"Feature"},
	{"geometry":{"coordinates":[17.809261,59.451673],"type":"Point"},"properties":{"osm_id":"4848891771","tag":{"amenity":"recycling","recycling_type":"container"}},"type":"Feature"}
]
}
