{
"type": "FeatureCollection",
"features": [
	{"geometry":{"coordinates":[17.826068,59.445502],"type":"Point"},"properties":{"osm_id":"29818231","tag":{"amenity":"recycling"}},"type":"Feature"},
	{"geometry":{"coordinates":[17.805872,59.457921],"type":"Point"},"properties":{"osm_id":"501802020","tag":{"amenity":"recycling","location":"overground","recycling_type":"container"}},"type":"Feature"},
	{"geometry":{"coordinates":[17.755392,59.484099],"type":"Point"},"properties":{"osm_id":"2798487313","tag":{"amenity":"recycling","recycling_type":"container"}},"type":"Feature"},
	{"geometry":{"coordinates":[17.809261,59.451673],"type":"Point"},"properties":{"osm_id":"4848891771","tag":{"amenity":"recycling","recycling_type":"container"}},"type":"Feature"}
]
}
