{
"type": "FeatureCollection",
"lastupdate": "2020-07-31T00:00:00Z",
"features": [
	{"geometry":{"coordinates":[17.762366,46.378144],"type":"Point"},"properties":{"name":"Balaton Rec","osm_id":"3463110681","tag":{"amenity":"recycling","recycling_type":"centre","source:date":"2015-01-12","url":"http://turistautak.hu/poi.php?id=124697"}},"type":"Feature"}
]
}
