{
"type": "FeatureCollection",
"features": [
	{"geometry":{"coordinates":[17.822237,43.312924],"type":"Point"},"properties":{"name":"Interkomerc","osm_id":"1693169531","tag":{"amenity":"recycling"}},"type":"Feature"}
]
}
