{
"type": "FeatureCollection",
"features": [
	{"geometry":{"coordinates":[-24.458753,14.945495],"type":"Point"},"properties":{"name":"Baobab","osm_id":"2049768634","tag":{"name:botanical":"Adansonia digitata","natural":"tree"}},"type":"Feature"},
	{"geometry":{"coordinates":[-24.445393,14.945922],"type":"Point"},"properties":{"name":"Baobab","osm_id":"2049768635","tag":{"name:botanical":"Adansonia digitata","natural":"tree"}},"type":"Feature"}
]
}
