{
"type": "FeatureCollection",
"features": [
	{"geometry":{"coordinates":[-9.153369,54.116608],"type":"Point"},"properties":{"osm_id":"3107239615","tag":{"amenity":"recycling","recycling:cans":"yes","recycling:clothes":"yes","recycling:glass":"yes","recycling_type":"container"}},"type":"Feature"},
	{"geometry":{"coordinates":[-9.17782,54.156802],"type":"Point"},"properties":{"name":"Rathroeen Recycling Centre","osm_id":"4436213865","tag":{"amenity":"recycling","opening_hours":"Mo-Sa","recycling:batteries":"yes","recycling:cardboard":"yes","recycling:clothes":"yes","recycling:glass":"yes","recycling:glass_bottles":"yes","recycling:paper":"yes","recycling:plastic":"yes","recycling:scrap_metal":"yes","recycling:tyres":"yes","recycling:white_goods":"yes","recycling_type":"centre"}},"type":"Feature"}
]
}
