{
"type": "FeatureCollection",
"features": [
	{"geometry":{"coordinates":[-10.094521,51.758031],"type":"Point"},"properties":{"osm_id":"8435257562","tag":{"amenity":"waste_disposal"}},"type":"Feature"},
	{"geometry":{"coordinates":[-10.0945,51.758039],"type":"Point"},"properties":{"osm_id":"8435257563","tag":{"amenity":"recycling","recycling_type":"container"}},"type":"Feature"},
	{"geometry":{"coordinates":[-10.099723,51.764967],"type":"Point"},"properties":{"name":"Bottle bank","osm_id":"8628351296","tag":{"amenity":"recycling","recycling_type":"container"}},"type":"Feature"}
]
}
