{
"type": "FeatureCollection",
"features": [
	{"geometry":{"coordinates":[13.293725,48.106345],"type":"Point"},"properties":{"osm_id":"4542764607","tag":{"natural":"tree"}},"type":"Feature"},
	{"geometry":{"coordinates":[13.286848,48.104],"type":"Point"},"properties":{"osm_id":"4542764972","tag":{"natural":"tree"}},"type":"Feature"},
	{"geometry":{"coordinates":[13.286602,48.103996],"type":"Point"},"properties":{"osm_id":"4542764973","tag":{"natural":"tree"}},"type":"Feature"},
	{"geometry":{"coordinates":[13.285815,48.104082],"type":"Point"},"properties":{"osm_id":"4542764974","tag":{"natural":"tree"}},"type":"Feature"},
	{"geometry":{"coordinates":[13.286416,48.104013],"type":"Point"},"properties":{"osm_id":"4542764975","tag":{"natural":"tree"}},"type":"Feature"},
	{"geometry":{"coordinates":[13.324673,48.072815],"type":"Point"},"properties":{"name":"Riesentanne","osm_id":"6061710564","tag":{"Age":"300","circumference":"5m","denotation":"natural_monument","height":"40","leaf_type":"needleleaved","natural":"tree"}},"type":"Feature"},
	{"geometry":{"coordinates":[13.313165,48.095502],"type":"Point"},"properties":{"osm_id":"6206514585","tag":{"natural":"tree"}},"type":"Feature"},
	{"geometry":{"coordinates":[13.312905,48.095675],"type":"Point"},"properties":{"osm_id":"6206514586","tag":{"natural":"tree"}},"type":"Feature"}
]
}
