{
"type": "FeatureCollection",
"features": [
	{"geometry":{"coordinates":[13.341222,47.873282],"type":"Point"},"properties":{"osm_id":"954795692","tag":{"natural":"tree"}},"type":"Feature"},
	{"geometry":{"coordinates":[13.318731,47.901758],"type":"Point"},"properties":{"osm_id":"3030421140","tag":{"genus":"Tilia","leaf_cycle":"deciduous","leaf_type":"broadleaved","natural":"tree"}},"type":"Feature"},
	{"geometry":{"coordinates":[13.283223,47.920361],"type":"Point"},"properties":{"osm_id":"3969121696","tag":{"natural":"tree"}},"type":"Feature"},
	{"geometry":{"coordinates":[13.282785,47.92038],"type":"Point"},"properties":{"osm_id":"3969121697","tag":{"natural":"tree"}},"type":"Feature"},
	{"geometry":{"coordinates":[13.283193,47.92045],"type":"Point"},"properties":{"osm_id":"3969121699","tag":{"natural":"tree"}},"type":"Feature"},
	{"geometry":{"coordinates":[13.279317,47.928744],"type":"Point"},"properties":{"osm_id":"3974382365","tag":{"natural":"tree"}},"type":"Feature"},
	{"geometry":{"coordinates":[13.341906,47.906271],"type":"Point"},"properties":{"osm_id":"4755276358","tag":{"natural":"tree"}},"type":"Feature"},
	{"geometry":{"coordinates":[13.341811,47.906338],"type":"Point"},"properties":{"osm_id":"4755276359","tag":{"natural":"tree"}},"type":"Feature"},
	{"geometry":{"coordinates":[13.341736,47.90634],"type":"Point"},"properties":{"osm_id":"4755276360","tag":{"natural":"tree"}},"type":"Feature"},
	{"geometry":{"coordinates":[13.341653,47.906337],"type":"Point"},"properties":{"osm_id":"4755276361","tag":{"natural":"tree"}},"type":"Feature"},
	{"geometry":{"coordinates":[13.34159,47.906297],"type":"Point"},"properties":{"osm_id":"4755276362","tag":{"natural":"tree"}},"type":"Feature"},
	{"geometry":{"coordinates":[13.341597,47.906222],"type":"Point"},"properties":{"osm_id":"4755276363","tag":{"natural":"tree"}},"type":"Feature"},
	{"geometry":{"coordinates":[13.321828,47.904503],"type":"Point"},"properties":{"name":"Naturdenkmal","osm_id":"4755276376","tag":{"denotation":"natural_monument","natural":"tree"}},"type":"Feature"},
	{"geometry":{"coordinates":[13.354795,47.904227],"type":"Point"},"properties":{"osm_id":"8919955137","tag":{"historic":"tree_shrine","leaf_type":"needleleaved","natural":"tree"}},"type":"Feature"},
	{"geometry":{"coordinates":[13.358194,47.894754],"type":"Point"},"properties":{"osm_id":"8919955179","tag":{"historic":"tree_shrine","leaf_type":"needleleaved","natural":"tree"}},"type":"Feature"}
]
}
