{
"type": "FeatureCollection",
"features": [
	{"geometry":{"coordinates":[13.341223,47.873282],"type":"Point"},"properties":{"osm_id":"954795692","tag":{"natural":"tree"}},"type":"Feature"},
	{"geometry":{"coordinates":[13.318732,47.901759],"type":"Point"},"properties":{"osm_id":"3030421140","tag":{"leaf_cycle":"deciduous","leaf_type":"broadleaved","name:botanical":"Tilia","natural":"tree"}},"type":"Feature"},
	{"geometry":{"coordinates":[13.283224,47.920361],"type":"Point"},"properties":{"osm_id":"3969121696","tag":{"natural":"tree"}},"type":"Feature"},
	{"geometry":{"coordinates":[13.282786,47.920381],"type":"Point"},"properties":{"osm_id":"3969121697","tag":{"natural":"tree"}},"type":"Feature"},
	{"geometry":{"coordinates":[13.283193,47.92045],"type":"Point"},"properties":{"osm_id":"3969121699","tag":{"natural":"tree"}},"type":"Feature"},
	{"geometry":{"coordinates":[13.279318,47.928744],"type":"Point"},"properties":{"osm_id":"3974382365","tag":{"natural":"tree"}},"type":"Feature"},
	{"geometry":{"coordinates":[13.341906,47.906272],"type":"Point"},"properties":{"osm_id":"4755276358","tag":{"natural":"tree"}},"type":"Feature"},
	{"geometry":{"coordinates":[13.341812,47.906338],"type":"Point"},"properties":{"osm_id":"4755276359","tag":{"natural":"tree"}},"type":"Feature"},
	{"geometry":{"coordinates":[13.341737,47.906341],"type":"Point"},"properties":{"osm_id":"4755276360","tag":{"natural":"tree"}},"type":"Feature"},
	{"geometry":{"coordinates":[13.341653,47.906338],"type":"Point"},"properties":{"osm_id":"4755276361","tag":{"natural":"tree"}},"type":"Feature"},
	{"geometry":{"coordinates":[13.34159,47.906298],"type":"Point"},"properties":{"osm_id":"4755276362","tag":{"natural":"tree"}},"type":"Feature"},
	{"geometry":{"coordinates":[13.341597,47.906223],"type":"Point"},"properties":{"osm_id":"4755276363","tag":{"natural":"tree"}},"type":"Feature"},
	{"geometry":{"coordinates":[13.321829,47.904503],"type":"Point"},"properties":{"name":"Naturdenkmal","osm_id":"4755276376","tag":{"denotation":"natural_monument","natural":"tree"}},"type":"Feature"}
]
}
