{
"type": "FeatureCollection",
"features": [
	{"geometry":{"coordinates":[-6.411851,54.353822],"type":"Point"},"properties":{"name":"Tandragee Amenity Centre","osm_id":"5263673021","tag":{"amenity":"recycling"}},"type":"Feature"}
]
}
