{
"type": "FeatureCollection",
"features": [
	{"geometry":{"coordinates":[-71.942067,42.926902],"type":"Point"},"properties":{"name":"Peterborough Recycling Center","osm_id":"4903013452","tag":{"amenity":"recycling","recycling_type":"centre"}},"type":"Feature"}
]
}
