{
"type": "FeatureCollection",
"features": [
	{"geometry":{"coordinates":[-82.709236,27.839325],"type":"Point"},"properties":{"osm_id":"2784384709","tag":{"amenity":"waste_basket"}},"type":"Feature"},
	{"geometry":{"coordinates":[-82.787273,27.880735],"type":"Point"},"properties":{"osm_id":"2846173085","tag":{"amenity":"waste_basket"}},"type":"Feature"},
	{"geometry":{"coordinates":[-82.774128,27.912615],"type":"Point"},"properties":{"name":"Trash Bin","osm_id":"4641422356","tag":{"amenity":"waste_basket"}},"type":"Feature"}
]
}
