{
"type": "FeatureCollection",
"lastupdate": "2020-08-01T00:00:00Z",
"features": [
	{"geometry":{"coordinates":[-82.709235,27.839325],"type":"Point"},"properties":{"osm_id":"2784384709","tag":{"amenity":"waste_basket"}},"type":"Feature"},
	{"geometry":{"coordinates":[-82.787273,27.880734],"type":"Point"},"properties":{"osm_id":"2846173085","tag":{"amenity":"waste_basket"}},"type":"Feature"},
	{"geometry":{"coordinates":[-82.774127,27.912614],"type":"Point"},"properties":{"name":"Trash Bin","osm_id":"4641422356","tag":{"amenity":"waste_basket"}},"type":"Feature"}
]
}
