{
"type": "FeatureCollection",
"lastupdate": "2020-08-05T00:00:00Z",
"features": [
	{"geometry":{"coordinates":[81.576064,28.12583],"type":"Point"},"properties":{"osm_id":"6009874488","tag":{"amenity":"recycling","name:en":"Kattupati Rice Mill","operator":"Bigyan Kattupati"}},"type":"Feature"}
]
}
