{
"type": "FeatureCollection",
"features": [
	{"geometry":{"coordinates":[81.576064,28.12583],"type":"Point"},"properties":{"osm_id":"6009874488","tag":{"amenity":"recycling","name:en":"Kattupati Rice Mill","operator":"Bigyan Kattupati"}},"type":"Feature"},
	{"geometry":{"coordinates":[81.58158,28.149149],"type":"Point"},"properties":{"name":"samir rice mill","osm_id":"9116642862","tag":{"addr:city":"khajura rm","addr:place":"ward no 8, sunaulo tole","amenity":"recycling","contact:phone":"9812451589","opening_hours":"daily","operator":"private","recycling_type":"centre"}},"type":"Feature"},
	{"geometry":{"coordinates":[81.583447,28.148279],"type":"Point"},"properties":{"name":"nisha rice mill","osm_id":"9116652918","tag":{"addr:city":"khajura rm","addr:place":"ward no 8, sunaulo tole","amenity":"recycling","contact:phone":"9819591220","opening_hours":"daily","operator":"private","recycling_type":"centre"}},"type":"Feature"}
]
}
