{
"type": "FeatureCollection",
"features": [
	{"geometry":{"coordinates":[81.576065,28.12583],"type":"Point"},"properties":{"osm_id":"6009874488","tag":{"amenity":"recycling","name:en":"Kattupati Rice Mill","operator":"Bigyan Kattupati"}},"type":"Feature"}
]
}
