{
"type": "FeatureCollection",
"features": [
	{"geometry":{"coordinates":[-75.37068,42.894042],"type":"Point"},"properties":{"is_in":"Oneida,New York,N.Y.,NY,USA","name":"Five Corners","osm_id":"158640825","place":"hamlet","tag":{"gnis:Class":"Populated Place","gnis:County":"Oneida","gnis:County_num":"065","gnis:ST_alpha":"NY","gnis:ST_num":"36","gnis:id":"950202","import_uuid":"bb7269ee-502a-5391-8056-e3ce0e66489c"}},"type":"Feature"}
]
}
