{
"type": "FeatureCollection",
"features": [
	{"geometry":{"coordinates":[-75.345451,40.067043],"type":"Point"},"properties":{"osm_id":"565306878","tag":{"amenity":"recycling"}},"type":"Feature"},
	{"geometry":{"coordinates":[-75.345726,40.067371],"type":"Point"},"properties":{"osm_id":"565306880","tag":{"amenity":"recycling"}},"type":"Feature"},
	{"geometry":{"coordinates":[-75.345683,40.067371],"type":"Point"},"properties":{"osm_id":"565306882","tag":{"amenity":"waste_basket"}},"type":"Feature"},
	{"geometry":{"coordinates":[-75.345494,40.067023],"type":"Point"},"properties":{"osm_id":"565306883","tag":{"amenity":"waste_basket"}},"type":"Feature"},
	{"geometry":{"coordinates":[-75.377536,40.051691],"type":"Point"},"properties":{"osm_id":"706661153","tag":{"amenity":"waste_basket"}},"type":"Feature"},
	{"geometry":{"coordinates":[-75.377439,40.050892],"type":"Point"},"properties":{"osm_id":"706668542","tag":{"amenity":"waste_basket"}},"type":"Feature"},
	{"geometry":{"coordinates":[-75.38335,40.066479],"type":"Point"},"properties":{"osm_id":"1181169335","tag":{"amenity":"waste_basket"}},"type":"Feature"},
	{"geometry":{"coordinates":[-75.38047,40.068207],"type":"Point"},"properties":{"osm_id":"1181169367","tag":{"amenity":"waste_basket"}},"type":"Feature"},
	{"geometry":{"coordinates":[-75.361252,40.079765],"type":"Point"},"properties":{"osm_id":"1200919403","tag":{"amenity":"waste_disposal"}},"type":"Feature"},
	{"geometry":{"coordinates":[-75.380435,40.06822],"type":"Point"},"properties":{"osm_id":"1201906094","tag":{"amenity":"recycling"}},"type":"Feature"},
	{"geometry":{"coordinates":[-75.383352,40.066461],"type":"Point"},"properties":{"osm_id":"1201906098","tag":{"amenity":"recycling"}},"type":"Feature"},
	{"geometry":{"coordinates":[-75.385622,40.075431],"type":"Point"},"properties":{"name":"Trash","osm_id":"3683065620","tag":{"amenity":"waste_basket"}},"type":"Feature"},
	{"geometry":{"coordinates":[-75.403646,40.083293],"type":"Point"},"properties":{"osm_id":"7220647041","tag":{"amenity":"waste_disposal"}},"type":"Feature"},
	{"geometry":{"coordinates":[-75.404649,40.083153],"type":"Point"},"properties":{"osm_id":"7220647054","tag":{"amenity":"waste_disposal"}},"type":"Feature"},
	{"geometry":{"coordinates":[-75.403805,40.082213],"type":"Point"},"properties":{"osm_id":"7220647059","tag":{"amenity":"waste_disposal"}},"type":"Feature"},
	{"geometry":{"coordinates":[-75.405774,40.082917],"type":"Point"},"properties":{"osm_id":"7220647066","tag":{"amenity":"waste_disposal"}},"type":"Feature"},
	{"geometry":{"coordinates":[-75.405586,40.082771],"type":"Point"},"properties":{"osm_id":"7227553784","tag":{"amenity":"waste_disposal"}},"type":"Feature"}
]
}
