{
"type": "FeatureCollection",
"features": [
	{"geometry":{"coordinates":[-75.345451,40.067042],"type":"Point"},"properties":{"osm_id":"565306878","tag":{"amenity":"recycling"}},"type":"Feature"},
	{"geometry":{"coordinates":[-75.345726,40.067371],"type":"Point"},"properties":{"osm_id":"565306880","tag":{"amenity":"recycling"}},"type":"Feature"},
	{"geometry":{"coordinates":[-75.345683,40.067371],"type":"Point"},"properties":{"osm_id":"565306882","tag":{"amenity":"waste_basket"}},"type":"Feature"},
	{"geometry":{"coordinates":[-75.345494,40.067023],"type":"Point"},"properties":{"osm_id":"565306883","tag":{"amenity":"waste_basket"}},"type":"Feature"},
	{"geometry":{"coordinates":[-75.377535,40.051691],"type":"Point"},"properties":{"osm_id":"706661153","tag":{"amenity":"waste_basket"}},"type":"Feature"},
	{"geometry":{"coordinates":[-75.377439,40.050892],"type":"Point"},"properties":{"osm_id":"706668542","tag":{"amenity":"waste_basket"}},"type":"Feature"},
	{"geometry":{"coordinates":[-75.38335,40.066478],"type":"Point"},"properties":{"osm_id":"1181169335","tag":{"amenity":"waste_basket"}},"type":"Feature"},
	{"geometry":{"coordinates":[-75.380469,40.068207],"type":"Point"},"properties":{"osm_id":"1181169367","tag":{"amenity":"waste_basket"}},"type":"Feature"},
	{"geometry":{"coordinates":[-75.361251,40.079764],"type":"Point"},"properties":{"osm_id":"1200919403","tag":{"amenity":"waste_disposal"}},"type":"Feature"},
	{"geometry":{"coordinates":[-75.380434,40.068219],"type":"Point"},"properties":{"osm_id":"1201906094","tag":{"amenity":"recycling"}},"type":"Feature"},
	{"geometry":{"coordinates":[-75.383351,40.06646],"type":"Point"},"properties":{"osm_id":"1201906098","tag":{"amenity":"recycling"}},"type":"Feature"},
	{"geometry":{"coordinates":[-75.385621,40.07543],"type":"Point"},"properties":{"name":"Trash","osm_id":"3683065620","tag":{"amenity":"waste_basket"}},"type":"Feature"},
	{"geometry":{"coordinates":[-75.403645,40.083293],"type":"Point"},"properties":{"osm_id":"7220647041","tag":{"amenity":"waste_disposal"}},"type":"Feature"},
	{"geometry":{"coordinates":[-75.404649,40.083153],"type":"Point"},"properties":{"osm_id":"7220647054","tag":{"amenity":"waste_disposal"}},"type":"Feature"},
	{"geometry":{"coordinates":[-75.403804,40.082212],"type":"Point"},"properties":{"osm_id":"7220647059","tag":{"amenity":"waste_disposal"}},"type":"Feature"},
	{"geometry":{"coordinates":[-75.405774,40.082917],"type":"Point"},"properties":{"osm_id":"7220647066","tag":{"amenity":"waste_disposal"}},"type":"Feature"},
	{"geometry":{"coordinates":[-75.405585,40.082771],"type":"Point"},"properties":{"osm_id":"7227553784","tag":{"amenity":"waste_disposal"}},"type":"Feature"}
]
}
