{
"type": "FeatureCollection",
"lastupdate": "2020-08-06T00:00:00Z",
"features": [
	{"geometry":{"coordinates":[-75.392186,39.82992],"type":"Point"},"properties":{"name":"International Non-Ferrous Metals","osm_id":"5680636960","tag":{"addr:city":"Chester","addr:housenumber":"2918","addr:postcode":"19013","addr:state":"PA","addr:street":"West 2nd Street","amenity":"recycling","recycling_type":"centre"}},"type":"Feature"},
	{"geometry":{"coordinates":[-75.372704,39.839517],"type":"Point"},"properties":{"name":"Boyle Disposal","osm_id":"5689230531","tag":{"addr:city":"Chester","addr:housenumber":"1117","addr:postcode":"19013","addr:state":"PA","addr:street":"West 2nd Street","amenity":"waste_basket"}},"type":"Feature"}
]
}
