{
"type": "FeatureCollection",
"features": [
	{"geometry":{"coordinates":[21.901938,50.602822],"type":"Point"},"properties":{"name":"Pomnik przyrody","osm_id":"4037116256","tag":{"denotation":"natural_monument","monument":"yes","natural":"tree","protected":"yes"}},"type":"Feature"},
	{"geometry":{"coordinates":[21.901646,50.603306],"type":"Point"},"properties":{"name":"Pomnik przyrody","osm_id":"4037116257","tag":{"denotation":"natural_monument","monument":"yes","natural":"tree","protected":"yes"}},"type":"Feature"},
	{"geometry":{"coordinates":[21.902136,50.603703],"type":"Point"},"properties":{"name":"Pomnik przyrody","osm_id":"4037116260","tag":{"denotation":"natural_monument","monument":"yes","natural":"tree","protected":"yes"}},"type":"Feature"},
	{"geometry":{"coordinates":[21.901651,50.603738],"type":"Point"},"properties":{"name":"Pomnik przyrody","osm_id":"4037116261","tag":{"denotation":"natural_monument","monument":"yes","natural":"tree","protected":"yes"}},"type":"Feature"},
	{"geometry":{"coordinates":[21.90206,50.603786],"type":"Point"},"properties":{"name":"Pomnik przyrody","osm_id":"4037116262","tag":{"denotation":"natural_monument","monument":"yes","natural":"tree","protected":"yes"}},"type":"Feature"},
	{"geometry":{"coordinates":[21.901676,50.603797],"type":"Point"},"properties":{"name":"Pomnik przyrody","osm_id":"4037116263","tag":{"denotation":"natural_monument","monument":"yes","natural":"tree","protected":"yes"}},"type":"Feature"},
	{"geometry":{"coordinates":[21.901311,50.604278],"type":"Point"},"properties":{"name":"Pomnik przyrody","osm_id":"4037116264","tag":{"denotation":"natural_monument","monument":"yes","natural":"tree","protected":"yes"}},"type":"Feature"},
	{"geometry":{"coordinates":[21.901053,50.604302],"type":"Point"},"properties":{"name":"Pomnik przyrody","osm_id":"4037116265","tag":{"denotation":"natural_monument","monument":"yes","natural":"tree","protected":"yes"}},"type":"Feature"},
	{"geometry":{"coordinates":[21.901062,50.604383],"type":"Point"},"properties":{"name":"Pomnik przyrody","osm_id":"4037116266","tag":{"denotation":"natural_monument","monument":"yes","natural":"tree","protected":"yes"}},"type":"Feature"},
	{"geometry":{"coordinates":[21.901004,50.604874],"type":"Point"},"properties":{"name":"Pomnik przyrody","osm_id":"4037116267","tag":{"denotation":"natural_monument","monument":"yes","natural":"tree","protected":"yes"}},"type":"Feature"}
]
}
