{
"type": "FeatureCollection",
"features": [
	{"geometry":{"coordinates":[21.935832,49.831844],"type":"Point"},"properties":{"name":"Pomnik Przyrody","osm_id":"4001621978","tag":{"denotation":"natural_monument","monument":"yes","natural":"tree"}},"type":"Feature"},
	{"geometry":{"coordinates":[21.934063,49.831962],"type":"Point"},"properties":{"name":"Pomnik Przyrody","osm_id":"4001621979","tag":{"denotation":"natural_monument","monument":"yes","natural":"tree"}},"type":"Feature"},
	{"geometry":{"coordinates":[21.935587,49.83207],"type":"Point"},"properties":{"name":"Pomnik Przyrody","osm_id":"4001621980","tag":{"denotation":"natural_monument","monument":"yes","natural":"tree"}},"type":"Feature"},
	{"geometry":{"coordinates":[21.932963,49.83273],"type":"Point"},"properties":{"name":"Pomnik Przyrody","osm_id":"4001621981","tag":{"denotation":"natural_monument","monument":"yes","natural":"tree"}},"type":"Feature"}
]
}
