{
"type": "FeatureCollection",
"lastupdate": "2020-08-05T00:00:00Z",
"features": [
	{"geometry":{"coordinates":[-6.840296,43.563029],"type":"Point"},"properties":{"name":"Reciclaje","osm_id":"812348529","tag":{"amenity":"recycling"}},"type":"Feature"},
	{"geometry":{"coordinates":[-6.809927,43.547356],"type":"Point"},"properties":{"osm_id":"3807995091","tag":{"amenity":"recycling","recycling_type":"container"}},"type":"Feature"}
]
}
