{
"type": "FeatureCollection",
"features": [
	{"geometry":{"coordinates":[20.117523,49.539848],"type":"Point"},"properties":{"name":"Jawor","osm_id":"7153523142","tag":{"denotation":"natural_monument","diameter":"180","leaf_cycle":"deciduous","leaf_type":"broadleaved","natural":"tree"}},"type":"Feature"},
	{"geometry":{"coordinates":[20.121858,49.505539],"type":"Point"},"properties":{"osm_id":"7216376602","tag":{"diameter":"45","leaf_cycle":"deciduous","leaf_type":"broadleaved","natural":"tree"}},"type":"Feature"}
]
}
