{
"type": "FeatureCollection",
"features": [
	{"geometry":{"coordinates":[6.754197,45.549858],"type":"Point"},"properties":{"osm_id":"2435532290","tag":{"amenity":"recycling","recycling:cans":"yes","recycling:glass":"yes","recycling:paper":"yes","recycling_type":"container"}},"type":"Feature"},
	{"geometry":{"coordinates":[6.754227,45.549859],"type":"Point"},"properties":{"osm_id":"2435532300","tag":{"amenity":"waste_disposal"}},"type":"Feature"},
	{"geometry":{"coordinates":[6.763231,45.54973],"type":"Point"},"properties":{"osm_id":"4780889411","tag":{"amenity":"recycling","recycling_type":"container"}},"type":"Feature"},
	{"geometry":{"coordinates":[6.76321,45.549718],"type":"Point"},"properties":{"osm_id":"4780889412","tag":{"amenity":"recycling","recycling_type":"container"}},"type":"Feature"},
	{"geometry":{"coordinates":[6.763195,45.549704],"type":"Point"},"properties":{"osm_id":"4780889413","tag":{"amenity":"recycling","recycling_type":"container"}},"type":"Feature"},
	{"geometry":{"coordinates":[6.763183,45.549687],"type":"Point"},"properties":{"osm_id":"4780889414","tag":{"amenity":"recycling","recycling_type":"container"}},"type":"Feature"},
	{"geometry":{"coordinates":[6.765032,45.547825],"type":"Point"},"properties":{"osm_id":"4781457345","tag":{"amenity":"recycling","recycling_type":"container"}},"type":"Feature"},
	{"geometry":{"coordinates":[6.757847,45.542773],"type":"Point"},"properties":{"osm_id":"5658379625","tag":{"amenity":"recycling","recycling_type":"container"}},"type":"Feature"},
	{"geometry":{"coordinates":[6.734159,45.559312],"type":"Point"},"properties":{"osm_id":"6219692938","tag":{"amenity":"recycling","location":"underground","recycling:glass_bottles":"yes","recycling:plastic_bottles":"yes","recycling:plastic_packaging":"yes","recycling_type":"container"}},"type":"Feature"},
	{"geometry":{"coordinates":[6.693068,45.575321],"type":"Point"},"properties":{"osm_id":"6783929085","tag":{"amenity":"recycling","recycling_type":"container"}},"type":"Feature"},
	{"geometry":{"coordinates":[6.742019,45.568806],"type":"Point"},"properties":{"osm_id":"7191998639","tag":{"amenity":"waste_basket"}},"type":"Feature"},
	{"geometry":{"coordinates":[6.76327,45.549745],"type":"Point"},"properties":{"osm_id":"7203039949","tag":{"amenity":"recycling","recycling_type":"container"}},"type":"Feature"},
	{"geometry":{"coordinates":[6.763251,45.549738],"type":"Point"},"properties":{"osm_id":"7203039950","tag":{"amenity":"recycling","recycling_type":"container"}},"type":"Feature"},
	{"geometry":{"coordinates":[6.73398,45.559971],"type":"Point"},"properties":{"osm_id":"7726942809","tag":{"amenity":"recycling","location":"underground","recycling:glass_bottles":"yes","recycling:plastic_bottles":"yes","recycling:plastic_packaging":"yes","recycling_type":"container"}},"type":"Feature"},
	{"geometry":{"coordinates":[6.732132,45.559734],"type":"Point"},"properties":{"osm_id":"7726942810","tag":{"amenity":"recycling","location":"underground","recycling:glass_bottles":"yes","recycling:plastic_bottles":"yes","recycling:plastic_packaging":"yes","recycling_type":"container"}},"type":"Feature"},
	{"geometry":{"coordinates":[6.739182,45.571028],"type":"Point"},"properties":{"osm_id":"7827821596","tag":{"amenity":"recycling","recycling_type":"container"}},"type":"Feature"}
]
}
