{
"type": "FeatureCollection",
"lastupdate": "2020-08-04T00:00:00Z",
"features": [
	{"geometry":{"coordinates":[6.720566,44.930062],"type":"Point"},"properties":{"osm_id":"3740940605","tag":{"amenity":"recycling","recycling_type":"container"}},"type":"Feature"},
	{"geometry":{"coordinates":[6.72592,44.931701],"type":"Point"},"properties":{"osm_id":"3741000001","tag":{"amenity":"recycling","recycling_type":"container"}},"type":"Feature"},
	{"geometry":{"coordinates":[6.731137,44.934752],"type":"Point"},"properties":{"osm_id":"5071493526","tag":{"amenity":"recycling","recycling_type":"container"}},"type":"Feature"},
	{"geometry":{"coordinates":[6.74892,44.937131],"type":"Point"},"properties":{"osm_id":"5302382933","tag":{"amenity":"recycling","recycling_type":"container"}},"type":"Feature"},
	{"geometry":{"coordinates":[6.746628,44.937679],"type":"Point"},"properties":{"osm_id":"5361793925","tag":{"amenity":"recycling","recycling:cans":"no","recycling:cardboard":"no","recycling:glass":"no","recycling:glass_bottles":"no","recycling:paper":"no","recycling:plastic":"no","recycling_type":"container"}},"type":"Feature"},
	{"geometry":{"coordinates":[6.748521,44.937569],"type":"Point"},"properties":{"osm_id":"5361793926","tag":{"amenity":"recycling","recycling:cans":"no","recycling:cardboard":"no","recycling:glass":"no","recycling:glass_bottles":"no","recycling:paper":"no","recycling:plastic":"no","recycling_type":"container"}},"type":"Feature"},
	{"geometry":{"coordinates":[6.748955,44.937878],"type":"Point"},"properties":{"osm_id":"5361793927","tag":{"amenity":"recycling","recycling:cans":"no","recycling:cardboard":"no","recycling:glass":"no","recycling:glass_bottles":"no","recycling:paper":"no","recycling:plastic":"no","recycling_type":"container"}},"type":"Feature"},
	{"geometry":{"coordinates":[6.682355,44.940017],"type":"Point"},"properties":{"name":"Recyclage","osm_id":"6432232885","tag":{"amenity":"recycling"}},"type":"Feature"},
	{"geometry":{"coordinates":[6.684614,44.927533],"type":"Point"},"properties":{"osm_id":"6579912005","tag":{"amenity":"recycling","recycling_type":"container"}},"type":"Feature"},
	{"geometry":{"coordinates":[6.730998,44.935522],"type":"Point"},"properties":{"osm_id":"6594175865","tag":{"amenity":"recycling","recycling_type":"container"}},"type":"Feature"},
	{"geometry":{"coordinates":[6.725521,44.931457],"type":"Point"},"properties":{"osm_id":"6966278203","tag":{"amenity":"waste_basket"}},"type":"Feature"},
	{"geometry":{"coordinates":[6.726,44.931496],"type":"Point"},"properties":{"osm_id":"6966278204","tag":{"amenity":"waste_basket"}},"type":"Feature"},
	{"geometry":{"coordinates":[6.728248,44.934313],"type":"Point"},"properties":{"osm_id":"7179302607","tag":{"amenity":"recycling","recycling:glass_bottles":"yes","recycling:paper":"yes","recycling:plastic":"yes","recycling_type":"container","survey:date":"2020-02-03"}},"type":"Feature"},
	{"geometry":{"coordinates":[6.721642,44.930267],"type":"Point"},"properties":{"osm_id":"7758120030","tag":{"amenity":"waste_basket"}},"type":"Feature"}
]
}
