{
"type": "FeatureCollection",
"features": [
	{"geometry":{"coordinates":[7.295277,50.630035],"type":"Point"},"properties":{"name":"Kreuzeiche","osm_id":"259072016","tag":{"natural":"tree"}},"type":"Feature"},
	{"geometry":{"coordinates":[7.303045,50.662575],"type":"Point"},"properties":{"osm_id":"3822497307","tag":{"natural":"tree"}},"type":"Feature"},
	{"geometry":{"coordinates":[7.302978,50.662713],"type":"Point"},"properties":{"osm_id":"3822497330","tag":{"natural":"tree"}},"type":"Feature"},
	{"geometry":{"coordinates":[7.371976,50.658413],"type":"Point"},"properties":{"osm_id":"3826673283","tag":{"natural":"tree"}},"type":"Feature"},
	{"geometry":{"coordinates":[7.370117,50.658874],"type":"Point"},"properties":{"osm_id":"3826673287","tag":{"natural":"tree"}},"type":"Feature"},
	{"geometry":{"coordinates":[7.370277,50.659226],"type":"Point"},"properties":{"osm_id":"3826673290","tag":{"natural":"tree"}},"type":"Feature"},
	{"geometry":{"coordinates":[7.371444,50.648758],"type":"Point"},"properties":{"osm_id":"3831361502","tag":{"natural":"tree"}},"type":"Feature"},
	{"geometry":{"coordinates":[7.307148,50.668515],"type":"Point"},"properties":{"osm_id":"5159481952","tag":{"leaf_type":"broadleaved","natural":"tree"}},"type":"Feature"},
	{"geometry":{"coordinates":[7.347682,50.63645],"type":"Point"},"properties":{"osm_id":"5358560885","tag":{"natural":"tree"}},"type":"Feature"},
	{"geometry":{"coordinates":[7.347725,50.636477],"type":"Point"},"properties":{"osm_id":"5360460084","tag":{"natural":"tree"}},"type":"Feature"},
	{"geometry":{"coordinates":[7.347757,50.636462],"type":"Point"},"properties":{"osm_id":"5360460085","tag":{"natural":"tree"}},"type":"Feature"},
	{"geometry":{"coordinates":[7.347724,50.636438],"type":"Point"},"properties":{"osm_id":"5360460086","tag":{"natural":"tree"}},"type":"Feature"},
	{"geometry":{"coordinates":[7.369929,50.675737],"type":"Point"},"properties":{"osm_id":"5846126970","tag":{"natural":"tree"}},"type":"Feature"},
	{"geometry":{"coordinates":[7.369893,50.676405],"type":"Point"},"properties":{"osm_id":"5846127387","tag":{"natural":"tree"}},"type":"Feature"},
	{"geometry":{"coordinates":[7.370108,50.676565],"type":"Point"},"properties":{"osm_id":"5846127388","tag":{"natural":"tree"}},"type":"Feature"},
	{"geometry":{"coordinates":[7.37932,50.661999],"type":"Point"},"properties":{"osm_id":"8913726521","tag":{"height":"5","natural":"tree"}},"type":"Feature"}
]
}
