{
"type": "FeatureCollection",
"features": [
	{"geometry":{"coordinates":[7.295278,50.630035],"type":"Point"},"properties":{"name":"Kreuzeiche","osm_id":"259072016","tag":{"natural":"tree"}},"type":"Feature"},
	{"geometry":{"coordinates":[7.303045,50.662576],"type":"Point"},"properties":{"osm_id":"3822497307","tag":{"natural":"tree"}},"type":"Feature"},
	{"geometry":{"coordinates":[7.302978,50.662714],"type":"Point"},"properties":{"osm_id":"3822497330","tag":{"natural":"tree"}},"type":"Feature"},
	{"geometry":{"coordinates":[7.371976,50.658413],"type":"Point"},"properties":{"osm_id":"3826673283","tag":{"natural":"tree"}},"type":"Feature"},
	{"geometry":{"coordinates":[7.370118,50.658875],"type":"Point"},"properties":{"osm_id":"3826673287","tag":{"natural":"tree"}},"type":"Feature"},
	{"geometry":{"coordinates":[7.370277,50.659227],"type":"Point"},"properties":{"osm_id":"3826673290","tag":{"natural":"tree"}},"type":"Feature"},
	{"geometry":{"coordinates":[7.371444,50.648758],"type":"Point"},"properties":{"osm_id":"3831361502","tag":{"natural":"tree"}},"type":"Feature"},
	{"geometry":{"coordinates":[7.307158,50.668496],"type":"Point"},"properties":{"osm_id":"5159481952","tag":{"natural":"tree"}},"type":"Feature"},
	{"geometry":{"coordinates":[7.347683,50.636451],"type":"Point"},"properties":{"osm_id":"5358560885","tag":{"natural":"tree"}},"type":"Feature"},
	{"geometry":{"coordinates":[7.347725,50.636478],"type":"Point"},"properties":{"osm_id":"5360460084","tag":{"natural":"tree"}},"type":"Feature"},
	{"geometry":{"coordinates":[7.347757,50.636462],"type":"Point"},"properties":{"osm_id":"5360460085","tag":{"natural":"tree"}},"type":"Feature"},
	{"geometry":{"coordinates":[7.347724,50.636438],"type":"Point"},"properties":{"osm_id":"5360460086","tag":{"natural":"tree"}},"type":"Feature"},
	{"geometry":{"coordinates":[7.369929,50.675737],"type":"Point"},"properties":{"osm_id":"5846126970","tag":{"natural":"tree"}},"type":"Feature"},
	{"geometry":{"coordinates":[7.369894,50.676405],"type":"Point"},"properties":{"osm_id":"5846127387","tag":{"natural":"tree"}},"type":"Feature"},
	{"geometry":{"coordinates":[7.370108,50.676566],"type":"Point"},"properties":{"osm_id":"5846127388","tag":{"natural":"tree"}},"type":"Feature"}
]
}
