{
"type": "FeatureCollection",
"features": [
	{"geometry":{"coordinates":[7.360108,45.368019],"type":"Point"},"properties":{"name":"Molliccio","osm_id":"3773052067","tag":{"leaf_cycle":"deciduous","leaf_type":"broadleaved","natural":"tree"}},"type":"Feature"}
]
}
