{
"type": "FeatureCollection",
"features": [
	{"geometry":{"coordinates":[-77.073601,39.136739],"type":"Point"},"properties":{"name":"Wooded Area","osm_id":"1107800832","tag":{"natural":"tree"}},"type":"Feature"},
	{"geometry":{"coordinates":[-77.075047,39.100934],"type":"Point"},"properties":{"osm_id":"6306884213","tag":{"denotation":"street","leaf_type":"broadleaved","natural":"tree"}},"type":"Feature"},
	{"geometry":{"coordinates":[-77.074775,39.100905],"type":"Point"},"properties":{"osm_id":"6306884230","tag":{"denotation":"street","leaf_cycle":"deciduous","leaf_type":"broadleaved","natural":"tree"}},"type":"Feature"},
	{"geometry":{"coordinates":[-77.074533,39.100881],"type":"Point"},"properties":{"osm_id":"6306884245","tag":{"denotation":"street","leaf_cycle":"deciduous","leaf_type":"broadleaved","natural":"tree"}},"type":"Feature"}
]
}
