{
"type": "FeatureCollection",
"features": [
	{"geometry":{"coordinates":[28.891387,41.057918],"type":"Point"},"properties":{"osm_id":"5102651521","tag":{"amenity":"waste_disposal"}},"type":"Feature"},
	{"geometry":{"coordinates":[28.893376,41.052364],"type":"Point"},"properties":{"osm_id":"5342202533","tag":{"amenity":"waste_disposal"}},"type":"Feature"},
	{"geometry":{"coordinates":[28.895847,41.048193],"type":"Point"},"properties":{"osm_id":"5601511013","tag":{"amenity":"waste_basket"}},"type":"Feature"},
	{"geometry":{"coordinates":[28.895674,41.048773],"type":"Point"},"properties":{"osm_id":"5601511014","tag":{"amenity":"waste_basket"}},"type":"Feature"},
	{"geometry":{"coordinates":[28.861328,41.095699],"type":"Point"},"properties":{"osm_id":"9054453160","tag":{"amenity":"waste_disposal"}},"type":"Feature"},
	{"geometry":{"coordinates":[28.86133,41.095673],"type":"Point"},"properties":{"osm_id":"9054453161","tag":{"amenity":"recycling","location":"overground","recycling:clothes":"yes","recycling_type":"container"}},"type":"Feature"}
]
}
