{
"type": "FeatureCollection",
"features": [
	{"geometry":{"coordinates":[124.889849,12.141484],"type":"Point"},"properties":{"name":"Temporary MRF (Material Recovery Facility)","osm_id":"5066134950","tag":{"amenity":"recycling","recycling_type":"centre"}},"type":"Feature"}
]
}
