{
"type": "FeatureCollection",
"lastupdate": "2020-08-01T00:00:00Z",
"features": [
	{"geometry":{"coordinates":[124.889849,12.141483],"type":"Point"},"properties":{"name":"Temporary MRF (Material Recovery Facility)","osm_id":"5066134950","tag":{"amenity":"recycling","recycling_type":"centre"}},"type":"Feature"}
]
}
