{
"type": "FeatureCollection",
"features": [
	{"geometry":{"coordinates":[-105.138204,40.626863],"type":"Point"},"properties":{"name":"Dumpster","osm_id":"832955980","tag":{"amenity":"recycling"}},"type":"Feature"}
]
}
