{
"type": "FeatureCollection",
"features": [
	{"geometry":{"coordinates":[18.689095,53.166947],"type":"Point"},"properties":{"osm_id":"4706668602","tag":{"denotation":"natural_monument","natural":"tree","ref:CRFOP":"PL.ZIPOP.1393.PP.0415022.428","ref:INSPIRE":"PL.ZIPOP.1393.PP.0415022.428","website":"http://crfop.gdos.gov.pl/CRFOP/widok/viewfop.jsf?fop=PL.ZIPOP.1393.PP.0415022.428"}},"type":"Feature"}
]
}
