{
"type": "FeatureCollection",
"lastupdate": "2020-08-05T00:00:00Z",
"features": [
	{"geometry":{"coordinates":[32.552049,0.373416],"type":"Point"},"properties":{"osm_id":"5466598374","tag":{"access":"yes","addr:city":"Kampala","addr:place":"Kazo","addr:suburb":"Kawempe","amenity":"recycling","fee":"no","legal":"no","operator":"private","recycling_type":"container","waste":"trash"}},"type":"Feature"}
]
}
