{
"type": "FeatureCollection",
"features": [
	{"geometry":{"coordinates":[13.109743,55.804725],"type":"Point"},"properties":{"osm_id":"2405723037","tag":{"amenity":"recycling"}},"type":"Feature"},
	{"geometry":{"coordinates":[13.135924,55.794876],"type":"Point"},"properties":{"osm_id":"2412820449","tag":{"amenity":"recycling"}},"type":"Feature"},
	{"geometry":{"coordinates":[13.106927,55.790693],"type":"Point"},"properties":{"osm_id":"2421475337","tag":{"amenity":"recycling"}},"type":"Feature"},
	{"geometry":{"coordinates":[13.108943,55.799173],"type":"Point"},"properties":{"osm_id":"3436606454","tag":{"amenity":"recycling","location":"overground","recycling_type":"container"}},"type":"Feature"},
	{"geometry":{"coordinates":[13.110589,55.7954],"type":"Point"},"properties":{"osm_id":"7596812948","tag":{"amenity":"waste_basket"}},"type":"Feature"},
	{"geometry":{"coordinates":[13.103969,55.791422],"type":"Point"},"properties":{"osm_id":"7596812959","tag":{"amenity":"waste_basket"}},"type":"Feature"},
	{"geometry":{"coordinates":[13.104725,55.789966],"type":"Point"},"properties":{"osm_id":"7596812980","tag":{"amenity":"waste_basket"}},"type":"Feature"},
	{"geometry":{"coordinates":[13.102778,55.777753],"type":"Point"},"properties":{"osm_id":"8633042447","tag":{"amenity":"recycling","recycling_type":"container"}},"type":"Feature"}
]
}
