{
"type": "FeatureCollection",
"features": [
	{"geometry":{"coordinates":[13.18111,52.080883],"type":"Point"},"properties":{"osm_id":"337550786","tag":{"amenity":"recycling","recycling:clothes":"yes","recycling:glass_bottles":"yes","recycling_type":"container"}},"type":"Feature"},
	{"geometry":{"coordinates":[13.162256,52.058703],"type":"Point"},"properties":{"osm_id":"356739509","tag":{"amenity":"recycling","recycling:glass":"yes"}},"type":"Feature"},
	{"geometry":{"coordinates":[13.166317,52.057901],"type":"Point"},"properties":{"osm_id":"356956489","tag":{"amenity":"recycling","location":"overground","recycling:clothes":"yes","recycling:glass":"no","recycling:glass_bottles":"yes","recycling_type":"container"}},"type":"Feature"},
	{"geometry":{"coordinates":[13.170867,52.095793],"type":"Point"},"properties":{"osm_id":"659819598","tag":{"amenity":"recycling","recycling:glass_bottles":"yes"}},"type":"Feature"},
	{"geometry":{"coordinates":[13.161579,52.091062],"type":"Point"},"properties":{"osm_id":"659819604","tag":{"amenity":"recycling","location":"underground","recycling:glass_bottles":"yes","recycling_type":"container"}},"type":"Feature"},
	{"geometry":{"coordinates":[13.170877,52.087011],"type":"Point"},"properties":{"osm_id":"659819609","tag":{"amenity":"recycling","recycling:glass_bottles":"yes"}},"type":"Feature"},
	{"geometry":{"coordinates":[13.174631,52.090984],"type":"Point"},"properties":{"osm_id":"661194945","tag":{"amenity":"recycling","recycling:glass_bottles":"yes"}},"type":"Feature"},
	{"geometry":{"coordinates":[13.154986,52.098657],"type":"Point"},"properties":{"osm_id":"681999708","tag":{"amenity":"recycling","recycling:clothes":"yes","recycling:glass":"yes","recycling_type":"container"}},"type":"Feature"},
	{"geometry":{"coordinates":[13.143557,52.096855],"type":"Point"},"properties":{"barrier":"gate","osm_id":"1012614794"},"type":"Feature"},
	{"geometry":{"coordinates":[13.177804,52.088252],"type":"Point"},"properties":{"osm_id":"1105787016","tag":{"amenity":"recycling","recycling:glass_bottles":"yes"}},"type":"Feature"},
	{"geometry":{"coordinates":[13.16691,52.082308],"type":"Point"},"properties":{"osm_id":"1168801537","tag":{"amenity":"recycling","location":"overground","recycling:glass_bottles":"yes","recycling_type":"container"}},"type":"Feature"},
	{"geometry":{"coordinates":[13.156069,52.099507],"type":"Point"},"properties":{"osm_id":"4069578235","tag":{"amenity":"recycling","recycling:clothes":"yes","recycling_type":"container"}},"type":"Feature"},
	{"geometry":{"coordinates":[13.123364,52.103258],"type":"Point"},"properties":{"osm_id":"5435668546","tag":{"amenity":"recycling","recycling:glass":"yes","recycling_type":"container"}},"type":"Feature"},
	{"geometry":{"coordinates":[13.12332,52.103186],"type":"Point"},"properties":{"osm_id":"5435668547","tag":{"amenity":"recycling","recycling:clothes":"yes","recycling_type":"container"}},"type":"Feature"},
	{"geometry":{"coordinates":[13.123264,52.103117],"type":"Point"},"properties":{"osm_id":"5435668548","tag":{"amenity":"recycling","recycling:glass":"yes","recycling_type":"container"}},"type":"Feature"},
	{"geometry":{"coordinates":[13.161549,52.091039],"type":"Point"},"properties":{"osm_id":"7468305550","tag":{"amenity":"recycling","location":"overground","recycling:clothes":"yes","recycling_type":"container"}},"type":"Feature"},
	{"geometry":{"coordinates":[13.166307,52.059619],"type":"Point"},"properties":{"osm_id":"7843014276","tag":{"amenity":"waste_basket","waste":"trash"}},"type":"Feature"},
	{"geometry":{"coordinates":[13.166592,52.059669],"type":"Point"},"properties":{"osm_id":"7843014277","tag":{"amenity":"waste_basket","waste":"trash"}},"type":"Feature"},
	{"geometry":{"coordinates":[13.16673,52.060109],"type":"Point"},"properties":{"osm_id":"7843014279","tag":{"amenity":"waste_basket","waste":"trash"}},"type":"Feature"},
	{"geometry":{"coordinates":[13.16654,52.059828],"type":"Point"},"properties":{"osm_id":"7843014280","tag":{"amenity":"waste_basket","waste":"trash"}},"type":"Feature"},
	{"geometry":{"coordinates":[13.166334,52.059828],"type":"Point"},"properties":{"osm_id":"7843014281","tag":{"amenity":"waste_basket","waste":"trash"}},"type":"Feature"}
]
}
