{
"type": "FeatureCollection",
"lastupdate": "2020-07-31T00:00:00Z",
"features": [
	{"geometry":{"coordinates":[13.124069,48.95889],"type":"Point"},"properties":{"osm_id":"597335277","tag":{"amenity":"recycling","recycling:paper":"yes","recycling_type":"container"}},"type":"Feature"},
	{"geometry":{"coordinates":[13.125296,48.958802],"type":"Point"},"properties":{"osm_id":"597335281","tag":{"amenity":"recycling","recycling:cans":"yes","recycling:glass":"yes"}},"type":"Feature"},
	{"geometry":{"coordinates":[13.130892,48.975204],"type":"Point"},"properties":{"osm_id":"694200519","tag":{"amenity":"recycling","recycling:cans":"yes","recycling:glass":"yes","recycling_type":"container"}},"type":"Feature"},
	{"geometry":{"coordinates":[13.134641,48.972539],"type":"Point"},"properties":{"osm_id":"694202574","tag":{"amenity":"recycling","recycling:cans":"yes","recycling:glass":"yes","recycling_type":"container"}},"type":"Feature"},
	{"geometry":{"coordinates":[13.137605,48.977962],"type":"Point"},"properties":{"osm_id":"694216283","tag":{"amenity":"recycling","recycling:cans":"yes","recycling:clothes":"no","recycling:glass":"yes","recycling_type":"container"}},"type":"Feature"},
	{"geometry":{"coordinates":[13.11542,48.97022],"type":"Point"},"properties":{"osm_id":"1695348917","tag":{"amenity":"recycling","location":"overground","recycling_type":"container"}},"type":"Feature"},
	{"geometry":{"coordinates":[13.123143,48.97402],"type":"Point"},"properties":{"osm_id":"1695350410","tag":{"amenity":"recycling"}},"type":"Feature"},
	{"geometry":{"coordinates":[13.118362,48.975609],"type":"Point"},"properties":{"osm_id":"1695350809","tag":{"amenity":"recycling"}},"type":"Feature"},
	{"geometry":{"coordinates":[13.159548,48.955939],"type":"Point"},"properties":{"osm_id":"2269060028","tag":{"amenity":"recycling"}},"type":"Feature"},
	{"geometry":{"coordinates":[13.132326,48.972413],"type":"Point"},"properties":{"osm_id":"4869991697","tag":{"amenity":"waste_basket"}},"type":"Feature"},
	{"geometry":{"coordinates":[13.132122,48.972406],"type":"Point"},"properties":{"osm_id":"4869994223","tag":{"amenity":"waste_basket"}},"type":"Feature"},
	{"geometry":{"coordinates":[13.112399,48.923627],"type":"Point"},"properties":{"osm_id":"5031712492","tag":{"amenity":"waste_basket"}},"type":"Feature"},
	{"geometry":{"coordinates":[13.136131,48.973846],"type":"Point"},"properties":{"osm_id":"6814309529","tag":{"amenity":"waste_basket"}},"type":"Feature"},
	{"geometry":{"coordinates":[13.153928,48.97901],"type":"Point"},"properties":{"osm_id":"6814320003","tag":{"amenity":"waste_basket"}},"type":"Feature"},
	{"geometry":{"coordinates":[13.124714,48.979598],"type":"Point"},"properties":{"osm_id":"6814431921","tag":{"amenity":"waste_basket"}},"type":"Feature"}
]
}
