{
"type": "FeatureCollection",
"features": [
	{"geometry":{"coordinates":[13.12407,48.95889],"type":"Point"},"properties":{"osm_id":"597335277","tag":{"amenity":"recycling","recycling:paper":"yes","recycling_type":"container"}},"type":"Feature"},
	{"geometry":{"coordinates":[13.125296,48.958803],"type":"Point"},"properties":{"osm_id":"597335281","tag":{"amenity":"recycling","recycling:cans":"yes","recycling:glass":"yes"}},"type":"Feature"},
	{"geometry":{"coordinates":[13.130893,48.975205],"type":"Point"},"properties":{"osm_id":"694200519","tag":{"amenity":"recycling","recycling:cans":"yes","recycling:glass":"yes","recycling_type":"container"}},"type":"Feature"},
	{"geometry":{"coordinates":[13.134641,48.972539],"type":"Point"},"properties":{"osm_id":"694202574","tag":{"amenity":"recycling","recycling:cans":"yes","recycling:glass":"yes","recycling_type":"container"}},"type":"Feature"},
	{"geometry":{"coordinates":[13.137606,48.977963],"type":"Point"},"properties":{"osm_id":"694216283","tag":{"amenity":"recycling","recycling:cans":"yes","recycling:clothes":"no","recycling:glass":"yes","recycling_type":"container"}},"type":"Feature"},
	{"geometry":{"coordinates":[13.115421,48.970221],"type":"Point"},"properties":{"osm_id":"1695348917","tag":{"amenity":"recycling","location":"overground","recycling:cans":"yes","recycling:clothes":"yes","recycling:glass_bottles":"yes","recycling:shoes":"yes","recycling_type":"container"}},"type":"Feature"},
	{"geometry":{"coordinates":[13.123143,48.974021],"type":"Point"},"properties":{"osm_id":"1695350410","tag":{"amenity":"recycling"}},"type":"Feature"},
	{"geometry":{"coordinates":[13.118362,48.975609],"type":"Point"},"properties":{"osm_id":"1695350809","tag":{"amenity":"recycling"}},"type":"Feature"},
	{"geometry":{"coordinates":[13.159548,48.95594],"type":"Point"},"properties":{"osm_id":"2269060028","tag":{"amenity":"recycling"}},"type":"Feature"},
	{"geometry":{"coordinates":[13.132327,48.972413],"type":"Point"},"properties":{"osm_id":"4869991697","tag":{"amenity":"waste_basket"}},"type":"Feature"},
	{"geometry":{"coordinates":[13.132123,48.972407],"type":"Point"},"properties":{"osm_id":"4869994223","tag":{"amenity":"waste_basket"}},"type":"Feature"},
	{"geometry":{"coordinates":[13.1124,48.923627],"type":"Point"},"properties":{"osm_id":"5031712492","tag":{"amenity":"waste_basket"}},"type":"Feature"},
	{"geometry":{"coordinates":[13.136131,48.973846],"type":"Point"},"properties":{"osm_id":"6814309529","tag":{"amenity":"waste_basket"}},"type":"Feature"},
	{"geometry":{"coordinates":[13.153929,48.97901],"type":"Point"},"properties":{"osm_id":"6814320003","tag":{"amenity":"waste_basket"}},"type":"Feature"},
	{"geometry":{"coordinates":[13.124715,48.979599],"type":"Point"},"properties":{"osm_id":"6814431921","tag":{"amenity":"waste_basket"}},"type":"Feature"}
]
}
