{
"type": "FeatureCollection",
"lastupdate": "2020-08-06T00:00:00Z",
"features": [
	{"geometry":{"coordinates":[13.168022,48.122169],"type":"Point"},"properties":{"osm_id":"713900625","tag":{"amenity":"recycling","recycling:glass_bottles":"yes","recycling:paper":"yes","recycling_type":"container"}},"type":"Feature"},
	{"geometry":{"coordinates":[13.152434,48.109893],"type":"Point"},"properties":{"osm_id":"893170733","tag":{"amenity":"recycling","recycling:glass_bottles":"yes","recycling_type":"container"}},"type":"Feature"},
	{"geometry":{"coordinates":[13.155228,48.109331],"type":"Point"},"properties":{"osm_id":"898701179","tag":{"amenity":"recycling","recycling:glass_bottles":"yes","recycling:scrap_metal":"yes","recycling_type":"container"}},"type":"Feature"},
	{"geometry":{"coordinates":[13.151946,48.108908],"type":"Point"},"properties":{"osm_id":"903729282","tag":{"amenity":"recycling","location":"overground","recycling:paper":"yes","recycling_type":"container"}},"type":"Feature"},
	{"geometry":{"coordinates":[13.152546,48.108695],"type":"Point"},"properties":{"osm_id":"1185893226","tag":{"amenity":"recycling","recycling:paper":"yes","recycling_type":"container"}},"type":"Feature"},
	{"geometry":{"coordinates":[13.120031,48.159103],"type":"Point"},"properties":{"osm_id":"6759737284","tag":{"amenity":"waste_basket","colour":"green","material":"metal"}},"type":"Feature"},
	{"geometry":{"coordinates":[13.120188,48.159629],"type":"Point"},"properties":{"osm_id":"6759766085","tag":{"amenity":"waste_basket","colour":"green","material":"metal"}},"type":"Feature"},
	{"geometry":{"coordinates":[13.133395,48.160817],"type":"Point"},"properties":{"osm_id":"6760124416","tag":{"amenity":"waste_basket","colour":"green","material":"metal"}},"type":"Feature"},
	{"geometry":{"coordinates":[13.118184,48.154299],"type":"Point"},"properties":{"osm_id":"6760505614","tag":{"amenity":"waste_basket","colour":"green","material":"metal"}},"type":"Feature"},
	{"geometry":{"coordinates":[13.118155,48.15459],"type":"Point"},"properties":{"osm_id":"6777919385","tag":{"amenity":"waste_basket","material":"metal"}},"type":"Feature"},
	{"geometry":{"coordinates":[13.118283,48.155831],"type":"Point"},"properties":{"osm_id":"6779217710","tag":{"amenity":"waste_basket","material":"metal"}},"type":"Feature"},
	{"geometry":{"coordinates":[13.118612,48.155228],"type":"Point"},"properties":{"osm_id":"6779395355","tag":{"amenity":"waste_basket","material":"metal"}},"type":"Feature"},
	{"geometry":{"coordinates":[13.118192,48.155185],"type":"Point"},"properties":{"osm_id":"6779395361","tag":{"amenity":"waste_basket","material":"metal"}},"type":"Feature"},
	{"geometry":{"coordinates":[13.118403,48.154709],"type":"Point"},"properties":{"osm_id":"6806457247","tag":{"amenity":"waste_basket","material":"metal"}},"type":"Feature"},
	{"geometry":{"coordinates":[13.118754,48.155911],"type":"Point"},"properties":{"osm_id":"6806457248","tag":{"amenity":"waste_basket","material":"metal"}},"type":"Feature"},
	{"geometry":{"coordinates":[13.118821,48.152275],"type":"Point"},"properties":{"osm_id":"6806457263","tag":{"amenity":"waste_basket","material":"metal"}},"type":"Feature"},
	{"geometry":{"coordinates":[13.124442,48.147862],"type":"Point"},"properties":{"osm_id":"6806457272","tag":{"amenity":"waste_basket","material":"metal"}},"type":"Feature"},
	{"geometry":{"coordinates":[13.120205,48.161514],"type":"Point"},"properties":{"osm_id":"6812430744","tag":{"amenity":"waste_basket","colour":"green","material":"metal"}},"type":"Feature"},
	{"geometry":{"coordinates":[13.120283,48.160222],"type":"Point"},"properties":{"osm_id":"6812430746","tag":{"amenity":"waste_basket","colour":"green","material":"metal"}},"type":"Feature"},
	{"geometry":{"coordinates":[13.117346,48.156394],"type":"Point"},"properties":{"osm_id":"7661792081","tag":{"amenity":"waste_basket","material":"metal","operator":"Marktgemeinde Helpfau-Uttendorf"}},"type":"Feature"}
]
}
