{
"type": "FeatureCollection",
"features": [
	{"geometry":{"coordinates":[-1.115202,51.740971],"type":"Point"},"properties":{"osm_id":"510134821","tag":{"amenity":"recycling","location":"overground","recycling:books":"yes","recycling:clothes":"yes","recycling:glass":"yes","recycling:music":"yes","recycling:shoes":"yes","recycling_type":"container"}},"type":"Feature"},
	{"geometry":{"coordinates":[-1.138504,51.747721],"type":"Point"},"properties":{"osm_id":"848848459","tag":{"amenity":"recycling"}},"type":"Feature"},
	{"geometry":{"coordinates":[-1.135296,51.74715],"type":"Point"},"properties":{"osm_id":"1694792573","tag":{"amenity":"waste_basket"}},"type":"Feature"},
	{"geometry":{"coordinates":[-1.095524,51.73833],"type":"Point"},"properties":{"osm_id":"7099589170","tag":{"amenity":"waste_basket"}},"type":"Feature"}
]
}
