{
"type": "FeatureCollection",
"lastupdate": "2020-08-03T00:00:00Z",
"features": [
	{"geometry":{"coordinates":[19.50355,47.459167],"type":"Point"},"properties":{"osm_id":"3446927996","tag":{"addr:street":":(","amenity":"recycling","source:date":"2011-12-29","url":"http://turistautak.hu/poi.php?id=52692"}},"type":"Feature"},
	{"geometry":{"coordinates":[19.496183,47.462017],"type":"Point"},"properties":{"osm_id":"3446928000","tag":{"addr:street":":(","amenity":"recycling","source:date":"2011-12-29","url":"http://turistautak.hu/poi.php?id=52693"}},"type":"Feature"}
]
}
