{
"type": "FeatureCollection",
"lastupdate": "2020-08-04T00:00:00Z",
"features": [
	{"geometry":{"coordinates":[-15.542837,27.769442],"type":"Point"},"properties":{"osm_id":"301955780","tag":{"amenity":"recycling","recycling:glass_bottles":"yes","recycling:paper":"yes","recycling:plastic":"yes","recycling_type":"container"}},"type":"Feature"},
	{"geometry":{"coordinates":[-15.546258,27.771577],"type":"Point"},"properties":{"osm_id":"2016402784","tag":{"amenity":"recycling","recycling:glass_bottles":"yes","recycling:paper":"yes","recycling:plastic":"yes","recycling_type":"container"}},"type":"Feature"},
	{"geometry":{"coordinates":[-15.536949,27.770582],"type":"Point"},"properties":{"osm_id":"2672238750","tag":{"amenity":"recycling","location":"overground","opening_hours":"24/7","recycling:PET":"yes","recycling:aluminium":"yes","recycling:cans":"yes","recycling:cardboard":"yes","recycling:glass":"no","recycling:glass_bottles":"yes","recycling:paper":"yes","recycling:plastic":"yes","recycling:plastic_bottles":"yes","recycling:plastic_packaging":"yes","recycling:scrap_metal":"yes","recycling_type":"container","wheelchair":"yes"}},"type":"Feature"},
	{"geometry":{"coordinates":[-15.539229,27.772726],"type":"Point"},"properties":{"osm_id":"2672238755","tag":{"amenity":"recycling","recycling:glass":"yes","recycling:paper":"yes","recycling:plastic":"yes","recycling_type":"container"}},"type":"Feature"},
	{"geometry":{"coordinates":[-15.548796,27.769547],"type":"Point"},"properties":{"osm_id":"3188617694","tag":{"amenity":"recycling","recycling:glass_bottles":"yes","recycling_type":"container"}},"type":"Feature"},
	{"geometry":{"coordinates":[-15.546376,27.772251],"type":"Point"},"properties":{"osm_id":"3206625874","tag":{"amenity":"waste_basket"}},"type":"Feature"},
	{"geometry":{"coordinates":[-15.546432,27.772461],"type":"Point"},"properties":{"osm_id":"3206625876","tag":{"amenity":"waste_basket"}},"type":"Feature"},
	{"geometry":{"coordinates":[-15.548014,27.76981],"type":"Point"},"properties":{"osm_id":"3643155486","tag":{"amenity":"waste_basket"}},"type":"Feature"},
	{"geometry":{"coordinates":[-15.546201,27.772521],"type":"Point"},"properties":{"osm_id":"3643155594","tag":{"amenity":"waste_basket"}},"type":"Feature"},
	{"geometry":{"coordinates":[-15.543887,27.77003],"type":"Point"},"properties":{"osm_id":"6121210627","tag":{"amenity":"recycling","recycling:glass":"yes","recycling:paper":"yes","recycling:plastic_packaging":"yes","recycling_type":"container"}},"type":"Feature"},
	{"geometry":{"coordinates":[-15.540373,27.772525],"type":"Point"},"properties":{"osm_id":"6152451213","tag":{"amenity":"recycling","building":"yes","location":"overground","recycling_type":"container"}},"type":"Feature"},
	{"geometry":{"coordinates":[-15.538061,27.771572],"type":"Point"},"properties":{"osm_id":"7298587997","tag":{"amenity":"waste_basket","waste":"trash"}},"type":"Feature"}
]
}
