{
"type": "FeatureCollection",
"features": [
	{"geometry":{"coordinates":[32.408554,34.755772],"type":"Point"},"properties":{"osm_id":"984872170","tag":{"natural":"tree"}},"type":"Feature"},
	{"geometry":{"coordinates":[32.422206,34.757644],"type":"Point"},"properties":{"name":"Green Area","osm_id":"3294265962","tag":{"natural":"tree"}},"type":"Feature"},
	{"geometry":{"coordinates":[32.406638,34.760469],"type":"Point"},"properties":{"osm_id":"5958886323","tag":{"natural":"tree"}},"type":"Feature"},
	{"geometry":{"coordinates":[32.406986,34.758481],"type":"Point"},"properties":{"osm_id":"5958886335","tag":{"natural":"tree"}},"type":"Feature"},
	{"geometry":{"coordinates":[32.406893,34.758497],"type":"Point"},"properties":{"osm_id":"5958886336","tag":{"natural":"tree"}},"type":"Feature"},
	{"geometry":{"coordinates":[32.406775,34.75853],"type":"Point"},"properties":{"osm_id":"5958886337","tag":{"natural":"tree"}},"type":"Feature"},
	{"geometry":{"coordinates":[32.406712,34.758546],"type":"Point"},"properties":{"osm_id":"5958886338","tag":{"natural":"tree"}},"type":"Feature"},
	{"geometry":{"coordinates":[32.40644,34.758617],"type":"Point"},"properties":{"osm_id":"5958886339","tag":{"natural":"tree"}},"type":"Feature"},
	{"geometry":{"coordinates":[32.406203,34.758687],"type":"Point"},"properties":{"osm_id":"5958886340","tag":{"natural":"tree"}},"type":"Feature"},
	{"geometry":{"coordinates":[32.406103,34.758708],"type":"Point"},"properties":{"osm_id":"5958886341","tag":{"natural":"tree"}},"type":"Feature"},
	{"geometry":{"coordinates":[32.41432,34.758021],"type":"Point"},"properties":{"osm_id":"5961006861","tag":{"natural":"tree"}},"type":"Feature"},
	{"geometry":{"coordinates":[32.414381,34.758044],"type":"Point"},"properties":{"osm_id":"5961006862","tag":{"natural":"tree"}},"type":"Feature"},
	{"geometry":{"coordinates":[32.413799,34.758085],"type":"Point"},"properties":{"osm_id":"5961006999","tag":{"natural":"tree"}},"type":"Feature"},
	{"geometry":{"coordinates":[32.413432,34.758017],"type":"Point"},"properties":{"osm_id":"5961007003","tag":{"natural":"tree"}},"type":"Feature"},
	{"geometry":{"coordinates":[32.393611,34.804343],"type":"Point"},"properties":{"osm_id":"7794077345","tag":{"natural":"tree"}},"type":"Feature"},
	{"geometry":{"coordinates":[32.393734,34.800312],"type":"Point"},"properties":{"osm_id":"7798638858","tag":{"natural":"tree"}},"type":"Feature"},
	{"geometry":{"coordinates":[32.39389,34.800553],"type":"Point"},"properties":{"osm_id":"7798638882","tag":{"natural":"tree"}},"type":"Feature"}
]
}
