{
"type": "FeatureCollection",
"features": [
	{"geometry":{"coordinates":[80.934564,29.259608],"type":"Point"},"properties":{"name":"Matha, Sivalaya","osm_id":"5034777765","tag":{"denotation":"natural_monument","leaf_cycle":"evergreen","leaf_type":"broadleaved","natural":"tree"}},"type":"Feature"}
]
}
