{
"type": "FeatureCollection",
"features": [
	{"geometry":{"coordinates":[8.205135,51.549376],"type":"Point"},"properties":{"name":"Friedenseiche mit Gedenkstein","osm_id":"2410879057","tag":{"denotation":"natural_monument","genus":"Quercus","genus:de":"Eiche","image":"http://www.flickr.com/photos/33766294@N03/9462436175/","inscription":"Friedenseiche - gepflanzt nach dem Kriege 1870/-71","leaf_cycle":"deciduous","leaf_type":"broadleaved","natural":"tree","natural_protection":"natural_monument","start_date":"1871"}},"type":"Feature"}
]
}
