{
"type": "FeatureCollection",
"features": [
	{"geometry":{"coordinates":[8.220137,48.659811],"type":"Point"},"properties":{"osm_id":"2640943692","tag":{"natural":"tree"}},"type":"Feature"},
	{"geometry":{"coordinates":[8.23181,48.671755],"type":"Point"},"properties":{"osm_id":"3166355225","tag":{"natural":"tree"}},"type":"Feature"},
	{"geometry":{"coordinates":[8.230949,48.675251],"type":"Point"},"properties":{"osm_id":"3166367982","tag":{"natural":"tree"}},"type":"Feature"},
	{"geometry":{"coordinates":[8.244693,48.633418],"type":"Point"},"properties":{"name":"Grosse Tanne","osm_id":"9007593216","tag":{"circumference":"5","height":"46","leaf_type":"needleleaved","natural":"tree"}},"type":"Feature"}
]
}
