{
"type": "FeatureCollection",
"features": [
	{"geometry":{"coordinates":[131.450987,31.918369],"type":"Point"},"properties":{"name":"OFF HOUSE","osm_id":"4748125725","tag":{"amenity":"recycling","name:ja":"OFF HOUSE"}},"type":"Feature"}
]
}
