{
"type": "FeatureCollection",
"lastupdate": "2020-08-01T00:00:00Z",
"features": [
	{"geometry":{"coordinates":[131.450986,31.918369],"type":"Point"},"properties":{"name":"OFF HOUSE","osm_id":"4748125725","tag":{"amenity":"recycling","name:ja":"OFF HOUSE"}},"type":"Feature"}
]
}
