{
"type": "FeatureCollection",
"features": [
	{"geometry":{"coordinates":[19.595101,49.453895],"type":"Point"},"properties":{"name":"ambona strzelnicza","osm_id":"2879703282","tag":{"natural":"tree","tourism":"viewpoint"}},"type":"Feature"}
]
}
