{
"type": "FeatureCollection",
"lastupdate": "2020-07-31T00:00:00Z",
"features": [
	{"geometry":{"coordinates":[-84.414971,42.279759],"type":"Point"},"properties":{"name":"Northwest Refuse","osm_id":"459410557","tag":{"amenity":"recycling"}},"type":"Feature"}
]
}
