{
"type": "FeatureCollection",
"lastupdate": "2020-08-04T00:00:00Z",
"features": [
	{"geometry":{"coordinates":[-84.38036,41.302759],"type":"Point"},"properties":{"name":"Werlor Waste Control & Recycling, Inc.","osm_id":"4082115438","tag":{"addr:city":"Defiance","addr:housenumber":"1420","addr:postcode":"43512","addr:state":"OH","addr:street":"Ralston Avenue","amenity":"recycling","recycling:cans":"yes","recycling:glass_bottles":"no","recycling_type":"centre"}},"type":"Feature"}
]
}
