{
"type": "FeatureCollection",
"features": [
	{"geometry":{"coordinates":[-82.943833,8.64736],"type":"Point"},"properties":{"name":"Punto Seguro","osm_id":"8097748724","tag":{"amenity":"recycling","description":"Farmacia Villa Neilly","indoor":"yes","operator":"Punto Seguro","recycling_type":"container"}},"type":"Feature"}
]
}
