{
"type": "FeatureCollection",
"features": [
	{"geometry":{"coordinates":[34.814995,-1.829031],"type":"Point"},"properties":{"osm_id":"4948179621","tag":{"name:en":"Alliance One Forest","name:sw":"Alliance One Forest","natural":"tree"}},"type":"Feature"}
]
}
