{
"type": "FeatureCollection",
"features": [
	{"geometry":{"coordinates":[34.85201,-7.601941],"type":"Point"},"properties":{"name":"Baobab with hole","osm_id":"1489195780","tag":{"natural":"tree"}},"type":"Feature"}
]
}
