{
"type": "FeatureCollection",
"features": [
	{"geometry":{"coordinates":[124.688133,9.220461],"type":"Point"},"properties":{"name":"Centennial Tree","osm_id":"2180140862","tag":{"natural":"tree"}},"type":"Feature"},
	{"geometry":{"coordinates":[124.634411,9.201781],"type":"Point"},"properties":{"name":"Centennial Tree","osm_id":"2181967123","tag":{"natural":"tree"}},"type":"Feature"}
]
}
