{
"type": "FeatureCollection",
"features": [
	{"geometry":{"coordinates":[124.688132,9.22046],"type":"Point"},"properties":{"name":"Centennial Tree","osm_id":"2180140862","tag":{"natural":"tree"}},"type":"Feature"},
	{"geometry":{"coordinates":[124.63441,9.201781],"type":"Point"},"properties":{"name":"Centennial Tree","osm_id":"2181967123","tag":{"natural":"tree"}},"type":"Feature"}
]
}
