{
"type": "FeatureCollection",
"features": [
	{"geometry":{"coordinates":[-58.994575,-27.434536],"type":"Point"},"properties":{"osm_id":"2311209915","tag":{"addr:city":"Resistencia","addr:country":"AR","addr:housenumber":"1500","addr:street":"La Rioja"}},"type":"Feature"},
	{"geometry":{"coordinates":[-58.98847,-27.404695],"type":"Point"},"properties":{"osm_id":"4927589704","tag":{"amenity":"waste_disposal"}},"type":"Feature"},
	{"geometry":{"coordinates":[-58.988583,-27.404601],"type":"Point"},"properties":{"osm_id":"4927589705","tag":{"amenity":"waste_disposal"}},"type":"Feature"},
	{"geometry":{"coordinates":[-58.988596,-27.404589],"type":"Point"},"properties":{"osm_id":"4927589707","tag":{"amenity":"waste_disposal"}},"type":"Feature"},
	{"geometry":{"coordinates":[-58.988045,-27.404599],"type":"Point"},"properties":{"osm_id":"4936200753","tag":{"amenity":"waste_disposal"}},"type":"Feature"},
	{"geometry":{"coordinates":[-58.988851,-27.404432],"type":"Point"},"properties":{"osm_id":"4936200768","tag":{"amenity":"waste_basket"}},"type":"Feature"},
	{"geometry":{"coordinates":[-58.988806,-27.40452],"type":"Point"},"properties":{"osm_id":"4936200769","tag":{"amenity":"waste_basket"}},"type":"Feature"}
]
}
