{
"type": "FeatureCollection",
"lastupdate": "2020-07-31T00:00:00Z",
"features": [
	{"geometry":{"coordinates":[-58.994575,-27.434536],"type":"Point"},"properties":{"osm_id":"2311209915","tag":{"addr:city":"Resistencia","addr:country":"AR","addr:housenumber":"1500","addr:street":"La Rioja"}},"type":"Feature"},
	{"geometry":{"coordinates":[-58.98885,-27.404431],"type":"Point"},"properties":{"osm_id":"4936200768","tag":{"amenity":"waste_basket"}},"type":"Feature"},
	{"geometry":{"coordinates":[-58.988805,-27.404519],"type":"Point"},"properties":{"osm_id":"4936200769","tag":{"amenity":"waste_basket"}},"type":"Feature"}
]
}
