{
"type": "FeatureCollection",
"features": [
	{"geometry":{"coordinates":[16.440667,52.307449],"type":"Point"},"properties":{"name":"Pomnik Przyrody","osm_id":"1407331060","tag":{"natural":"tree","type":"Buk"}},"type":"Feature"}
]
}
