{
"type": "FeatureCollection",
"features": [
	{"geometry":{"coordinates":[9.39537,53.5222],"type":"Point"},"properties":{"osm_id":"3150397843","tag":{"amenity":"recycling","recycling:clothes":"yes","recycling_type":"container"}},"type":"Feature"},
	{"geometry":{"coordinates":[9.387255,53.505528],"type":"Point"},"properties":{"name":"Werrtstoffhof Wedel","osm_id":"6299440228","tag":{"addr:city":"Fredenbeck","addr:housenumber":"50","addr:postcode":"21717","addr:street":"Mulsumer Weg","addr:suburb":"Wedel","amenity":"recycling","operator":"Landkreis Stade","operator:type":"public","recycling_type":"centre"}},"type":"Feature"}
]
}
