{
"type": "FeatureCollection",
"lastupdate": "2020-08-01T00:00:00Z",
"features": [
	{"geometry":{"coordinates":[9.387003,53.505704],"type":"Point"},"properties":{"name":"Wertstoffhof Wedel","osm_id":"1875078291","tag":{"amenity":"recycling","recycling_type":"centre"}},"type":"Feature"},
	{"geometry":{"coordinates":[9.39537,53.5222],"type":"Point"},"properties":{"osm_id":"3150397843","tag":{"amenity":"recycling","recycling:clothes":"yes","recycling_type":"container"}},"type":"Feature"}
]
}
