{
"type": "FeatureCollection",
"features": [
	{"geometry":{"coordinates":[9.387004,53.505705],"type":"Point"},"properties":{"name":"Wertstoffhof Wedel","osm_id":"1875078291","tag":{"amenity":"recycling","recycling_type":"centre"}},"type":"Feature"},
	{"geometry":{"coordinates":[9.395371,53.522201],"type":"Point"},"properties":{"osm_id":"3150397843","tag":{"amenity":"recycling","recycling:clothes":"yes","recycling_type":"container"}},"type":"Feature"}
]
}
