{
"type": "FeatureCollection",
"lastupdate": "2020-08-06T00:00:00Z",
"features": [
	{"geometry":{"coordinates":[9.338773,49.698659],"type":"Point"},"properties":{"osm_id":"199016643","tag":{"amenity":"recycling","recycling:glass_bottles":"yes","recycling_type":"container"}},"type":"Feature"},
	{"geometry":{"coordinates":[9.317758,49.671041],"type":"Point"},"properties":{"osm_id":"297312484","tag":{"amenity":"recycling","location":"overground","recycling:clothes":"yes","recycling:glass":"yes","recycling_type":"container"}},"type":"Feature"},
	{"geometry":{"coordinates":[9.3258,49.706107],"type":"Point"},"properties":{"osm_id":"7746296795","tag":{"amenity":"recycling","recycling:glass_bottles":"yes","recycling_type":"container"}},"type":"Feature"},
	{"geometry":{"coordinates":[9.32253,49.707542],"type":"Point"},"properties":{"osm_id":"7746296799","tag":{"amenity":"waste_basket","waste":"trash"}},"type":"Feature"},
	{"geometry":{"coordinates":[9.375988,49.673235],"type":"Point"},"properties":{"osm_id":"7746378041","tag":{"amenity":"recycling","recycling:glass_bottles":"yes","recycling_type":"container"}},"type":"Feature"},
	{"geometry":{"coordinates":[9.366106,49.676712],"type":"Point"},"properties":{"osm_id":"7746389985","tag":{"amenity":"waste_basket","waste":"trash"}},"type":"Feature"},
	{"geometry":{"coordinates":[9.35422,49.686048],"type":"Point"},"properties":{"osm_id":"7746389989","tag":{"amenity":"waste_basket","waste":"trash"}},"type":"Feature"}
]
}
