{
"type": "FeatureCollection",
"features": [
	{"geometry":{"coordinates":[9.338773,49.698659],"type":"Point"},"properties":{"osm_id":"199016643","tag":{"amenity":"recycling","recycling:clothes":"yes","recycling:glass_bottles":"yes","recycling:shoes":"yes","recycling_type":"container"}},"type":"Feature"},
	{"geometry":{"coordinates":[9.317758,49.671041],"type":"Point"},"properties":{"osm_id":"297312484","tag":{"amenity":"recycling","location":"overground","recycling:clothes":"yes","recycling:glass":"yes","recycling_type":"container"}},"type":"Feature"},
	{"geometry":{"coordinates":[9.3258,49.706107],"type":"Point"},"properties":{"osm_id":"7746296795","tag":{"amenity":"recycling","recycling:clothes":"yes","recycling:glass_bottles":"yes","recycling:shoes":"yes","recycling:small_electrical_appliances":"yes","recycling_type":"container"}},"type":"Feature"},
	{"geometry":{"coordinates":[9.32253,49.707542],"type":"Point"},"properties":{"osm_id":"7746296799","tag":{"amenity":"waste_basket","waste":"trash"}},"type":"Feature"},
	{"geometry":{"coordinates":[9.375988,49.673235],"type":"Point"},"properties":{"osm_id":"7746378041","tag":{"amenity":"recycling","recycling:clothes":"yes","recycling:glass_bottles":"yes","recycling_type":"container"}},"type":"Feature"},
	{"geometry":{"coordinates":[9.366106,49.676712],"type":"Point"},"properties":{"osm_id":"7746389985","tag":{"amenity":"waste_basket","waste":"trash"}},"type":"Feature"},
	{"geometry":{"coordinates":[9.35422,49.686048],"type":"Point"},"properties":{"osm_id":"7746389989","tag":{"amenity":"waste_basket","waste":"trash"}},"type":"Feature"},
	{"geometry":{"coordinates":[9.332901,49.702843],"type":"Point"},"properties":{"osm_id":"8499497828","tag":{"amenity":"recycling","recycling:clothes":"yes","recycling:glass_bottles":"yes","recycling_type":"container"}},"type":"Feature"},
	{"geometry":{"coordinates":[9.329577,49.702103],"type":"Point"},"properties":{"osm_id":"8500943593","tag":{"amenity":"waste_basket","waste":"trash"}},"type":"Feature"},
	{"geometry":{"coordinates":[9.328313,49.70524],"type":"Point"},"properties":{"osm_id":"8704942040","tag":{"amenity":"waste_basket","waste":"trash"}},"type":"Feature"},
	{"geometry":{"coordinates":[9.360299,49.718331],"type":"Point"},"properties":{"osm_id":"9022035688","tag":{"amenity":"waste_basket","waste":"trash"}},"type":"Feature"}
]
}
