{
"type": "FeatureCollection",
"features": [
	{"geometry":{"coordinates":[11.142446,59.750438],"type":"Point"},"properties":{"name":"Enebakk gjenvinningsstasjon","osm_id":"2252561678","tag":{"amenity":"recycling","phone":"+47 07623","recycling:batteries":"yes","recycling:clothes":"yes","recycling:electrical_items":"yes","recycling:garden_waste":"yes","recycling:glass_bottles":"yes","recycling:hazardous_waste":"yes","recycling:metal":"yes","recycling:paper":"yes","recycling:plasterboard":"yes","recycling:plastic":"yes","recycling:plastic_packaging":"yes","recycling:polystyrene_foam":"yes","recycling:rubble":"yes","recycling:scrap_metal":"yes","recycling:tyres":"yes","recycling:waste":"yes","recycling:wood":"yes","recycling_type":"centre","ref:sortere":"1111"}},"type":"Feature"},
	{"geometry":{"coordinates":[11.142467,59.750409],"type":"Point"},"properties":{"osm_id":"6195511379","tag":{"amenity":"recycling","description":"Lillestr\u00f8mveien 673, Enebakk gjenvinningsstasjon","recycling:clothes":"yes","recycling:glass_bottles":"yes","recycling_type":"container","ref:sortere":"19321"}},"type":"Feature"}
]
}
