{
"type": "FeatureCollection",
"features": [
	{"geometry":{"coordinates":[11.152433,50.310306],"type":"Point"},"properties":{"osm_id":"745364062","tag":{"amenity":"waste_basket"}},"type":"Feature"},
	{"geometry":{"coordinates":[11.1231,50.325434],"type":"Point"},"properties":{"osm_id":"897704259","tag":{"amenity":"recycling","location":"overground","recycling_type":"container"}},"type":"Feature"},
	{"geometry":{"coordinates":[11.135247,50.320553],"type":"Point"},"properties":{"osm_id":"1882330943","tag":{"amenity":"waste_basket"}},"type":"Feature"},
	{"geometry":{"coordinates":[11.135107,50.320618],"type":"Point"},"properties":{"osm_id":"1882330962","tag":{"amenity":"waste_basket"}},"type":"Feature"},
	{"geometry":{"coordinates":[11.145732,50.322461],"type":"Point"},"properties":{"osm_id":"1882331536","tag":{"amenity":"waste_basket"}},"type":"Feature"},
	{"geometry":{"coordinates":[11.140893,50.328245],"type":"Point"},"properties":{"osm_id":"1882331866","tag":{"amenity":"waste_basket"}},"type":"Feature"},
	{"geometry":{"coordinates":[11.149314,50.294536],"type":"Point"},"properties":{"osm_id":"1882476232","tag":{"amenity":"waste_basket"}},"type":"Feature"},
	{"geometry":{"coordinates":[11.134155,50.318686],"type":"Point"},"properties":{"osm_id":"2206440983","tag":{"amenity":"waste_basket"}},"type":"Feature"},
	{"geometry":{"coordinates":[11.128589,50.322166],"type":"Point"},"properties":{"osm_id":"2206441079","tag":{"amenity":"waste_basket"}},"type":"Feature"},
	{"geometry":{"coordinates":[11.127849,50.323064],"type":"Point"},"properties":{"osm_id":"2206441090","tag":{"amenity":"waste_basket"}},"type":"Feature"},
	{"geometry":{"coordinates":[11.129787,50.324261],"type":"Point"},"properties":{"osm_id":"2206441101","tag":{"amenity":"waste_basket"}},"type":"Feature"},
	{"geometry":{"coordinates":[11.130838,50.327263],"type":"Point"},"properties":{"osm_id":"2206441116","tag":{"amenity":"waste_basket"}},"type":"Feature"},
	{"geometry":{"coordinates":[11.130872,50.327894],"type":"Point"},"properties":{"osm_id":"2206441126","tag":{"amenity":"waste_basket"}},"type":"Feature"},
	{"geometry":{"coordinates":[11.131186,50.328727],"type":"Point"},"properties":{"osm_id":"2206441135","tag":{"amenity":"waste_basket"}},"type":"Feature"},
	{"geometry":{"coordinates":[11.151013,50.292621],"type":"Point"},"properties":{"highway":"street_lamp","osm_id":"2309816736","tag":{"amenity":"waste_basket"}},"type":"Feature"},
	{"geometry":{"coordinates":[11.150926,50.292806],"type":"Point"},"properties":{"highway":"street_lamp","osm_id":"2309816754","tag":{"amenity":"waste_basket"}},"type":"Feature"},
	{"geometry":{"coordinates":[11.151005,50.292957],"type":"Point"},"properties":{"highway":"street_lamp","osm_id":"2309816780","tag":{"amenity":"waste_basket"}},"type":"Feature"},
	{"geometry":{"coordinates":[11.15119,50.293017],"type":"Point"},"properties":{"highway":"street_lamp","osm_id":"2309816795","tag":{"amenity":"waste_basket"}},"type":"Feature"},
	{"geometry":{"coordinates":[11.151457,50.293042],"type":"Point"},"properties":{"highway":"street_lamp","osm_id":"2309816804","tag":{"amenity":"waste_basket"}},"type":"Feature"},
	{"geometry":{"coordinates":[11.151064,50.293177],"type":"Point"},"properties":{"osm_id":"2309816817","tag":{"amenity":"waste_basket"}},"type":"Feature"},
	{"geometry":{"coordinates":[11.150252,50.303301],"type":"Point"},"properties":{"osm_id":"2430372179","tag":{"amenity":"waste_basket"}},"type":"Feature"},
	{"geometry":{"coordinates":[11.151061,50.306081],"type":"Point"},"properties":{"osm_id":"2430372191","tag":{"amenity":"waste_basket"}},"type":"Feature"},
	{"geometry":{"coordinates":[11.119089,50.324298],"type":"Point"},"properties":{"osm_id":"3788286488","tag":{"amenity":"recycling","recycling:glass":"yes","recycling_type":"container"}},"type":"Feature"},
	{"geometry":{"coordinates":[11.078217,50.313821],"type":"Point"},"properties":{"osm_id":"4784935623","tag":{"amenity":"waste_basket"}},"type":"Feature"},
	{"geometry":{"coordinates":[11.099818,50.29472],"type":"Point"},"properties":{"osm_id":"5376341329","tag":{"amenity":"recycling","recycling:glass":"yes","recycling_type":"container"}},"type":"Feature"}
]
}
