{
"type": "FeatureCollection",
"features": [
	{"geometry":{"coordinates":[11.152432,50.310306],"type":"Point"},"properties":{"osm_id":"745364062","tag":{"amenity":"waste_basket"}},"type":"Feature"},
	{"geometry":{"coordinates":[11.123099,50.325433],"type":"Point"},"properties":{"osm_id":"897704259","tag":{"amenity":"recycling","location":"overground","recycling_type":"container"}},"type":"Feature"},
	{"geometry":{"coordinates":[11.135246,50.320553],"type":"Point"},"properties":{"osm_id":"1882330943","tag":{"amenity":"waste_basket"}},"type":"Feature"},
	{"geometry":{"coordinates":[11.135106,50.320617],"type":"Point"},"properties":{"osm_id":"1882330962","tag":{"amenity":"waste_basket"}},"type":"Feature"},
	{"geometry":{"coordinates":[11.145731,50.32246],"type":"Point"},"properties":{"osm_id":"1882331536","tag":{"amenity":"waste_basket"}},"type":"Feature"},
	{"geometry":{"coordinates":[11.140892,50.328245],"type":"Point"},"properties":{"osm_id":"1882331866","tag":{"amenity":"waste_basket"}},"type":"Feature"},
	{"geometry":{"coordinates":[11.149313,50.294535],"type":"Point"},"properties":{"osm_id":"1882476232","tag":{"amenity":"waste_basket"}},"type":"Feature"},
	{"geometry":{"coordinates":[11.134154,50.318686],"type":"Point"},"properties":{"osm_id":"2206440983","tag":{"amenity":"waste_basket"}},"type":"Feature"},
	{"geometry":{"coordinates":[11.128589,50.322166],"type":"Point"},"properties":{"osm_id":"2206441079","tag":{"amenity":"waste_basket"}},"type":"Feature"},
	{"geometry":{"coordinates":[11.127849,50.323064],"type":"Point"},"properties":{"osm_id":"2206441090","tag":{"amenity":"waste_basket"}},"type":"Feature"},
	{"geometry":{"coordinates":[11.129787,50.324261],"type":"Point"},"properties":{"osm_id":"2206441101","tag":{"amenity":"waste_basket"}},"type":"Feature"},
	{"geometry":{"coordinates":[11.130838,50.327263],"type":"Point"},"properties":{"osm_id":"2206441116","tag":{"amenity":"waste_basket"}},"type":"Feature"},
	{"geometry":{"coordinates":[11.130871,50.327894],"type":"Point"},"properties":{"osm_id":"2206441126","tag":{"amenity":"waste_basket"}},"type":"Feature"},
	{"geometry":{"coordinates":[11.131186,50.328726],"type":"Point"},"properties":{"osm_id":"2206441135","tag":{"amenity":"waste_basket"}},"type":"Feature"},
	{"geometry":{"coordinates":[11.151013,50.29262],"type":"Point"},"properties":{"highway":"street_lamp","osm_id":"2309816736","tag":{"amenity":"waste_basket"}},"type":"Feature"},
	{"geometry":{"coordinates":[11.150926,50.292806],"type":"Point"},"properties":{"highway":"street_lamp","osm_id":"2309816754","tag":{"amenity":"waste_basket"}},"type":"Feature"},
	{"geometry":{"coordinates":[11.151004,50.292956],"type":"Point"},"properties":{"highway":"street_lamp","osm_id":"2309816780","tag":{"amenity":"waste_basket"}},"type":"Feature"},
	{"geometry":{"coordinates":[11.15119,50.293017],"type":"Point"},"properties":{"highway":"street_lamp","osm_id":"2309816795","tag":{"amenity":"waste_basket"}},"type":"Feature"},
	{"geometry":{"coordinates":[11.151457,50.293042],"type":"Point"},"properties":{"highway":"street_lamp","osm_id":"2309816804","tag":{"amenity":"waste_basket"}},"type":"Feature"},
	{"geometry":{"coordinates":[11.151063,50.293176],"type":"Point"},"properties":{"osm_id":"2309816817","tag":{"amenity":"waste_basket"}},"type":"Feature"},
	{"geometry":{"coordinates":[11.150252,50.303301],"type":"Point"},"properties":{"osm_id":"2430372179","tag":{"amenity":"waste_basket"}},"type":"Feature"},
	{"geometry":{"coordinates":[11.15106,50.30608],"type":"Point"},"properties":{"osm_id":"2430372191","tag":{"amenity":"waste_basket"}},"type":"Feature"},
	{"geometry":{"coordinates":[11.119088,50.324298],"type":"Point"},"properties":{"osm_id":"3788286488","tag":{"amenity":"recycling","recycling:glass":"yes","recycling_type":"container"}},"type":"Feature"},
	{"geometry":{"coordinates":[11.078216,50.313821],"type":"Point"},"properties":{"osm_id":"4784935623","tag":{"amenity":"waste_basket"}},"type":"Feature"},
	{"geometry":{"coordinates":[11.099817,50.294719],"type":"Point"},"properties":{"osm_id":"5376341329","tag":{"amenity":"recycling","recycling:glass":"yes","recycling_type":"container"}},"type":"Feature"},
	{"geometry":{"coordinates":[11.148393,50.311772],"type":"Point"},"properties":{"osm_id":"8148993563","tag":{"amenity":"recycling","recycling:glass":"no","recycling:glass_bottles":"yes","recycling_type":"container"}},"type":"Feature"},
	{"geometry":{"coordinates":[11.14951,50.313754],"type":"Point"},"properties":{"osm_id":"8148993564","tag":{"amenity":"recycling","recycling:clothes":"yes","recycling_type":"container"}},"type":"Feature"}
]
}
