{
"type": "FeatureCollection",
"features": [
	{"geometry":{"coordinates":[11.151859,49.525956],"type":"Point"},"properties":{"osm_id":"321850872","tag":{"amenity":"recycling","location":"overground","recycling:clothes":"yes","recycling:glass":"yes","recycling_type":"container"}},"type":"Feature"},
	{"geometry":{"coordinates":[11.108497,49.505425],"type":"Point"},"properties":{"osm_id":"358538446","tag":{"amenity":"recycling","location":"overground","recycling_type":"container"}},"type":"Feature"},
	{"geometry":{"coordinates":[11.102546,49.504738],"type":"Point"},"properties":{"osm_id":"726557894","tag":{"amenity":"recycling","location":"overground","recycling_type":"container"}},"type":"Feature"},
	{"geometry":{"coordinates":[11.08789,49.503696],"type":"Point"},"properties":{"osm_id":"824407999","tag":{"amenity":"waste_basket"}},"type":"Feature"},
	{"geometry":{"coordinates":[11.144169,49.52413],"type":"Point"},"properties":{"osm_id":"1042430123","tag":{"amenity":"recycling","recycling:cans":"yes","recycling:glass":"yes","recycling_type":"container"}},"type":"Feature"},
	{"geometry":{"coordinates":[11.150791,49.529538],"type":"Point"},"properties":{"osm_id":"2290116476","tag":{"amenity":"waste_basket"}},"type":"Feature"},
	{"geometry":{"coordinates":[11.074678,49.529879],"type":"Point"},"properties":{"osm_id":"3658252047","tag":{"amenity":"waste_basket"}},"type":"Feature"},
	{"geometry":{"coordinates":[11.102234,49.507483],"type":"Point"},"properties":{"osm_id":"6744642120","tag":{"amenity":"recycling","recycling:clothes":"yes","recycling:shoes":"yes","recycling_type":"container"}},"type":"Feature"},
	{"geometry":{"coordinates":[11.127839,49.547192],"type":"Point"},"properties":{"osm_id":"7075708858","tag":{"amenity":"waste_basket","waste":"trash"}},"type":"Feature"}
]
}
