{
"type": "FeatureCollection",
"lastupdate": "2020-08-01T00:00:00Z",
"features": [
	{"geometry":{"coordinates":[11.151858,49.525955],"type":"Point"},"properties":{"osm_id":"321850872","tag":{"amenity":"recycling","location":"overground","recycling:clothes":"yes","recycling:glass":"yes","recycling_type":"container"}},"type":"Feature"},
	{"geometry":{"coordinates":[11.108497,49.505424],"type":"Point"},"properties":{"osm_id":"358538446","tag":{"amenity":"recycling","location":"overground","recycling_type":"container"}},"type":"Feature"},
	{"geometry":{"coordinates":[11.102545,49.504737],"type":"Point"},"properties":{"osm_id":"726557894","tag":{"amenity":"recycling","location":"overground","recycling_type":"container"}},"type":"Feature"},
	{"geometry":{"coordinates":[11.087889,49.503696],"type":"Point"},"properties":{"osm_id":"824407999","tag":{"amenity":"waste_basket"}},"type":"Feature"},
	{"geometry":{"coordinates":[11.144168,49.52413],"type":"Point"},"properties":{"osm_id":"1042430123","tag":{"amenity":"recycling","recycling:cans":"yes","recycling:glass":"yes","recycling_type":"container"}},"type":"Feature"},
	{"geometry":{"coordinates":[11.15079,49.529538],"type":"Point"},"properties":{"osm_id":"2290116476","tag":{"amenity":"waste_basket"}},"type":"Feature"},
	{"geometry":{"coordinates":[11.074677,49.529879],"type":"Point"},"properties":{"osm_id":"3658252047","tag":{"amenity":"waste_basket"}},"type":"Feature"},
	{"geometry":{"coordinates":[11.102234,49.507483],"type":"Point"},"properties":{"osm_id":"6744642120","tag":{"amenity":"recycling","recycling:clothes":"yes","recycling:shoes":"yes","recycling_type":"container"}},"type":"Feature"},
	{"geometry":{"coordinates":[11.127838,49.547192],"type":"Point"},"properties":{"osm_id":"7075708858","tag":{"amenity":"waste_basket","waste":"trash"}},"type":"Feature"}
]
}
