{
"type": "FeatureCollection",
"lastupdate": "2020-08-05T00:00:00Z",
"features": [
	{"geometry":{"coordinates":[5.6934,60.3794],"type":"Point"},"properties":{"osm_id":"5555200220","tag":{"amenity":"recycling","description":"Farlig avfall","recycling:batteries":"yes","recycling:hazardous_waste":"yes","recycling_type":"container","ref:sortere":"17002"}},"type":"Feature"},
	{"geometry":{"coordinates":[5.698451,60.3951],"type":"Point"},"properties":{"name":"Samnanger gjenvinningsstasjon","osm_id":"5555202789","tag":{"amenity":"recycling","recycling:batteries":"yes","recycling:boats":"yes","recycling:electrical_items":"yes","recycling:garden_waste":"yes","recycling:glass":"yes","recycling:glass_bottles":"yes","recycling:hazardous_waste":"yes","recycling:marine_waste":"yes","recycling:metal":"yes","recycling:paper":"yes","recycling:plastic_packaging":"yes","recycling:polystyrene_foam":"yes","recycling:rubble":"yes","recycling:scrap_metal":"yes","recycling:tyres":"yes","recycling:wood":"yes","recycling_type":"centre","ref:sortere":"4816"}},"type":"Feature"},
	{"geometry":{"coordinates":[5.6511,60.3977],"type":"Point"},"properties":{"osm_id":"6195514075","tag":{"access":"permissive","amenity":"recycling","description":"Hyttekontainer","recycling_type":"container","ref:sortere":"17024"}},"type":"Feature"},
	{"geometry":{"coordinates":[5.6525,60.3972],"type":"Point"},"properties":{"osm_id":"6195514728","tag":{"access":"permissive","amenity":"recycling","description":"Hyttekontainer","recycling_type":"container","ref:sortere":"16908"}},"type":"Feature"},
	{"geometry":{"coordinates":[5.6541,60.3781],"type":"Point"},"properties":{"osm_id":"6195518158","tag":{"access":"permissive","amenity":"recycling","description":"Hyttekontainer","recycling_type":"container","ref:sortere":"16414"}},"type":"Feature"},
	{"geometry":{"coordinates":[5.6618,60.3824],"type":"Point"},"properties":{"osm_id":"6195518159","tag":{"access":"permissive","amenity":"recycling","description":"Hyttekontainer","recycling_type":"container","ref:sortere":"16413"}},"type":"Feature"},
	{"geometry":{"coordinates":[5.6942,60.3794],"type":"Point"},"properties":{"osm_id":"6195518160","tag":{"access":"permissive","amenity":"recycling","description":"Hyttekontainer","recycling_type":"container","ref:sortere":"16412"}},"type":"Feature"},
	{"geometry":{"coordinates":[5.6403,60.4074],"type":"Point"},"properties":{"osm_id":"6195519469","tag":{"access":"permissive","amenity":"recycling","description":"Hyttekontainer","recycling_type":"container","ref:sortere":"16301"}},"type":"Feature"}
]
}
