{
"type": "FeatureCollection",
"lastupdate": "2020-08-02T00:00:00Z",
"features": [
	{"geometry":{"coordinates":[5.629851,52.385573],"type":"Point"},"properties":{"osm_id":"2209934385","tag":{"amenity":"recycling","recycling:glass":"yes","recycling:glass_bottles":"yes","recycling:waste":"yes","recycling_type":"container"}},"type":"Feature"},
	{"geometry":{"coordinates":[5.636106,52.38644],"type":"Point"},"properties":{"osm_id":"2267438904","tag":{"amenity":"recycling","recycling:cardboard":"yes","recycling:glass":"yes","recycling:glass_bottles":"yes","recycling:magazines":"yes","recycling:newspaper":"yes","recycling:paper":"yes","recycling:paper_packaging":"yes","recycling:waste":"yes","recycling_type":"container"}},"type":"Feature"},
	{"geometry":{"coordinates":[5.634835,52.387074],"type":"Point"},"properties":{"osm_id":"2267517016","tag":{"amenity":"recycling","recycling:glass":"yes","recycling:glass_bottles":"yes","recycling:paper":"yes","recycling:waste":"yes","recycling_type":"container"}},"type":"Feature"},
	{"geometry":{"coordinates":[5.706601,52.383064],"type":"Point"},"properties":{"name":"Milieupark","osm_id":"4786514031","tag":{"amenity":"recycling","recycling_type":"container"}},"type":"Feature"}
]
}
