{
"type": "FeatureCollection",
"features": [
	{"geometry":{"coordinates":[5.629851,52.385573],"type":"Point"},"properties":{"osm_id":"2209934385","tag":{"amenity":"recycling","recycling:glass":"yes","recycling:glass_bottles":"yes","recycling:waste":"yes","recycling_type":"container"}},"type":"Feature"},
	{"geometry":{"coordinates":[5.636181,52.386425],"type":"Point"},"properties":{"osm_id":"2245012356","tag":{"amenity":"waste_disposal","waste":"trash"}},"type":"Feature"},
	{"geometry":{"coordinates":[5.636106,52.386441],"type":"Point"},"properties":{"osm_id":"2267438904","tag":{"amenity":"recycling","recycling:cardboard":"yes","recycling:glass":"yes","recycling:glass_bottles":"yes","recycling:magazines":"yes","recycling:newspaper":"yes","recycling:paper":"yes","recycling:paper_packaging":"yes","recycling:waste":"yes","recycling_type":"container"}},"type":"Feature"},
	{"geometry":{"coordinates":[5.634835,52.387075],"type":"Point"},"properties":{"osm_id":"2267517016","tag":{"amenity":"recycling","recycling:glass":"yes","recycling:glass_bottles":"yes","recycling:paper":"yes","recycling:waste":"yes","recycling_type":"container"}},"type":"Feature"},
	{"geometry":{"coordinates":[5.706602,52.383065],"type":"Point"},"properties":{"name":"Milieupark","osm_id":"4786514031","tag":{"amenity":"recycling","recycling_type":"container"}},"type":"Feature"}
]
}
