{
"type": "FeatureCollection",
"features": [
	{"geometry":{"coordinates":[5.661498,51.30616],"type":"Point"},"properties":{"osm_id":"5658456926","tag":{"amenity":"waste_basket"}},"type":"Feature"},
	{"geometry":{"coordinates":[5.693373,51.329017],"type":"Point"},"properties":{"osm_id":"6075842541","tag":{"amenity":"waste_basket"}},"type":"Feature"},
	{"geometry":{"coordinates":[5.629363,51.30901],"type":"Point"},"properties":{"name":"Milieustraat Cranendonck","osm_id":"8025672011","tag":{"amenity":"recycling","recycling_type":"centre"}},"type":"Feature"},
	{"geometry":{"coordinates":[5.648308,51.328741],"type":"Point"},"properties":{"osm_id":"8201379301","tag":{"amenity":"waste_basket"}},"type":"Feature"},
	{"geometry":{"coordinates":[5.665189,51.341182],"type":"Point"},"properties":{"osm_id":"8201407839","tag":{"amenity":"waste_basket"}},"type":"Feature"},
	{"geometry":{"coordinates":[5.659929,51.342674],"type":"Point"},"properties":{"osm_id":"8201420559","tag":{"amenity":"waste_basket"}},"type":"Feature"},
	{"geometry":{"coordinates":[5.672499,51.331053],"type":"Point"},"properties":{"osm_id":"8662971341","tag":{"amenity":"waste_basket"}},"type":"Feature"},
	{"geometry":{"coordinates":[5.629128,51.297915],"type":"Point"},"properties":{"osm_id":"8757177418","tag":{"amenity":"waste_basket"}},"type":"Feature"}
]
}
