{
"type": "FeatureCollection",
"features": [
	{"geometry":{"coordinates":[5.629003,43.29698],"type":"Point"},"properties":{"osm_id":"1954744546","tag":{"amenity":"recycling","location":"underground","recycling:cans":"yes","recycling:glass":"yes","recycling:paper":"yes","recycling_type":"container"}},"type":"Feature"},
	{"geometry":{"coordinates":[5.685347,43.274595],"type":"Point"},"properties":{"osm_id":"5894576802","tag":{"amenity":"waste_disposal"}},"type":"Feature"},
	{"geometry":{"coordinates":[5.683272,43.271445],"type":"Point"},"properties":{"osm_id":"5996080962","tag":{"amenity":"recycling","recycling_type":"container"}},"type":"Feature"}
]
}
