{
"type": "FeatureCollection",
"features": [
	{"geometry":{"coordinates":[16.14847,49.65431],"type":"Point"},"properties":{"osm_id":"1188227937","tag":{"amenity":"recycling","recycling:glass":"yes","recycling:paper":"yes","recycling:plastic":"yes","recycling_type":"container"}},"type":"Feature"},
	{"geometry":{"coordinates":[16.146381,49.65593],"type":"Point"},"properties":{"osm_id":"1188228170","tag":{"amenity":"recycling","recycling:glass":"yes","recycling:paper":"yes","recycling:plastic":"yes","recycling:scrap_metal":"yes","recycling_type":"container"}},"type":"Feature"},
	{"geometry":{"coordinates":[16.116144,49.629759],"type":"Point"},"properties":{"osm_id":"2686983245","tag":{"amenity":"recycling","recycling:glass":"yes","recycling:paper":"yes","recycling:plastic":"yes","recycling_type":"container"}},"type":"Feature"},
	{"geometry":{"coordinates":[16.123788,49.646558],"type":"Point"},"properties":{"osm_id":"4901270972","tag":{"amenity":"recycling","recycling_type":"centre","website":"https://www.snezne.cz/sberny-dvur/ds-1044"}},"type":"Feature"},
	{"geometry":{"coordinates":[16.107715,49.624915],"type":"Point"},"properties":{"osm_id":"7099815460","tag":{"amenity":"recycling","recycling:glass":"yes","recycling:paper":"yes","recycling:plastic":"yes","recycling_type":"container"}},"type":"Feature"},
	{"geometry":{"coordinates":[16.150286,49.634849],"type":"Point"},"properties":{"osm_id":"7099835981","tag":{"amenity":"recycling","recycling:glass":"yes","recycling:plastic":"yes","recycling_type":"container"}},"type":"Feature"},
	{"geometry":{"coordinates":[16.112657,49.628843],"type":"Point"},"properties":{"osm_id":"7099836058","tag":{"amenity":"recycling","recycling:glass":"yes","recycling:paper":"yes","recycling:plastic":"yes","recycling_type":"container"}},"type":"Feature"},
	{"geometry":{"coordinates":[16.122171,49.62228],"type":"Point"},"properties":{"osm_id":"7099836072","tag":{"amenity":"recycling","recycling:glass":"yes","recycling:paper":"yes","recycling:plastic":"yes","recycling_type":"container"}},"type":"Feature"},
	{"geometry":{"coordinates":[16.137544,49.613567],"type":"Point"},"properties":{"osm_id":"7099836096","tag":{"amenity":"recycling","recycling:glass":"yes","recycling:paper":"yes","recycling:plastic":"yes","recycling_type":"container"}},"type":"Feature"},
	{"geometry":{"coordinates":[16.13486,49.636952],"type":"Point"},"properties":{"osm_id":"7099836222","tag":{"amenity":"recycling","recycling_type":"container"}},"type":"Feature"},
	{"geometry":{"coordinates":[16.130269,49.636828],"type":"Point"},"properties":{"osm_id":"7099836224","tag":{"amenity":"recycling","recycling:glass":"yes","recycling:paper":"yes","recycling:plastic":"yes","recycling_type":"container"}},"type":"Feature"},
	{"geometry":{"coordinates":[16.092778,49.656488],"type":"Point"},"properties":{"osm_id":"7656674437","tag":{"amenity":"recycling","recycling:glass":"yes","recycling:glass_bottles":"yes","recycling:plastic":"yes","recycling:plastic_bottles":"yes","recycling:plastic_packaging":"yes","recycling:waste":"yes","recycling_type":"container"}},"type":"Feature"},
	{"geometry":{"coordinates":[16.096654,49.641466],"type":"Point"},"properties":{"osm_id":"9004280069","tag":{"amenity":"recycling","recycling_type":"container"}},"type":"Feature"}
]
}
