{
"type": "FeatureCollection",
"features": [
	{"geometry":{"coordinates":[16.125307,48.333162],"type":"Point"},"properties":{"osm_id":"1147212422","tag":{"amenity":"recycling","recycling:beverage_cartons":"yes","recycling:cans":"yes","recycling:cartons":"yes","recycling:glass_bottles":"yes","recycling:paper":"yes","recycling_type":"container"}},"type":"Feature"},
	{"geometry":{"coordinates":[16.121112,48.295805],"type":"Point"},"properties":{"osm_id":"1381674161","tag":{"amenity":"recycling","recycling:glass_bottles":"yes","recycling_type":"container"}},"type":"Feature"},
	{"geometry":{"coordinates":[16.120672,48.33193],"type":"Point"},"properties":{"osm_id":"1406092035","tag":{"amenity":"recycling","recycling:beverage_cartons":"yes","recycling:cans":"yes","recycling:cartons":"yes","recycling:glass_bottles":"yes","recycling_type":"container"}},"type":"Feature"},
	{"geometry":{"coordinates":[16.118525,48.329951],"type":"Point"},"properties":{"osm_id":"1406092036","tag":{"amenity":"recycling","recycling:cans":"yes","recycling:glass_bottles":"yes","recycling_type":"container"}},"type":"Feature"},
	{"geometry":{"coordinates":[16.151934,48.304443],"type":"Point"},"properties":{"osm_id":"3017610977","tag":{"amenity":"recycling","recycling:glass_bottles":"yes","recycling_type":"container"}},"type":"Feature"},
	{"geometry":{"coordinates":[16.129438,48.29504],"type":"Point"},"properties":{"name":"Gemeindesammelzentrum","osm_id":"3212409698","tag":{"amenity":"recycling","recycling_type":"centre"}},"type":"Feature"},
	{"geometry":{"coordinates":[16.145825,48.30094],"type":"Point"},"properties":{"osm_id":"4575985570","tag":{"amenity":"waste_basket"}},"type":"Feature"},
	{"geometry":{"coordinates":[16.146221,48.29981],"type":"Point"},"properties":{"osm_id":"4575986203","tag":{"amenity":"waste_basket"}},"type":"Feature"},
	{"geometry":{"coordinates":[16.171617,48.307867],"type":"Point"},"properties":{"osm_id":"4810380548","tag":{"amenity":"waste_basket"}},"type":"Feature"},
	{"geometry":{"coordinates":[16.164429,48.305143],"type":"Point"},"properties":{"osm_id":"4810600487","tag":{"amenity":"waste_basket"}},"type":"Feature"},
	{"geometry":{"coordinates":[16.15985,48.336513],"type":"Point"},"properties":{"osm_id":"5792619279","tag":{"amenity":"waste_basket"}},"type":"Feature"},
	{"geometry":{"coordinates":[16.157676,48.304624],"type":"Point"},"properties":{"osm_id":"7844247338","tag":{"amenity":"recycling","recycling:beverage_cartons":"yes","recycling:cans":"yes","recycling:glass":"yes","recycling:glass_bottles":"yes","recycling_type":"container"}},"type":"Feature"}
]
}
