{
"type": "FeatureCollection",
"features": [
	{"geometry":{"coordinates":[16.125307,48.333162],"type":"Point"},"properties":{"osm_id":"1147212422","tag":{"amenity":"recycling","recycling:beverage_cartons":"yes","recycling:cans":"yes","recycling:cartons":"yes","recycling:glass_bottles":"yes","recycling:paper":"yes","recycling_type":"container"}},"type":"Feature"},
	{"geometry":{"coordinates":[16.121113,48.295806],"type":"Point"},"properties":{"osm_id":"1381674161","tag":{"amenity":"recycling","recycling:glass_bottles":"yes","recycling_type":"container"}},"type":"Feature"},
	{"geometry":{"coordinates":[16.120673,48.331931],"type":"Point"},"properties":{"osm_id":"1406092035","tag":{"amenity":"recycling","recycling:beverage_cartons":"yes","recycling:cans":"yes","recycling:cartons":"yes","recycling:glass_bottles":"yes","recycling_type":"container"}},"type":"Feature"},
	{"geometry":{"coordinates":[16.118525,48.329952],"type":"Point"},"properties":{"osm_id":"1406092036","tag":{"amenity":"recycling","recycling:cans":"yes","recycling:glass_bottles":"yes","recycling_type":"container"}},"type":"Feature"},
	{"geometry":{"coordinates":[16.151934,48.304443],"type":"Point"},"properties":{"osm_id":"3017610977","tag":{"amenity":"recycling","recycling:glass_bottles":"yes","recycling_type":"container"}},"type":"Feature"},
	{"geometry":{"coordinates":[16.129439,48.29504],"type":"Point"},"properties":{"name":"Gemeindesammelzentrum","osm_id":"3212409698","tag":{"amenity":"recycling","recycling_type":"centre"}},"type":"Feature"},
	{"geometry":{"coordinates":[16.145825,48.30094],"type":"Point"},"properties":{"osm_id":"4575985570","tag":{"amenity":"waste_basket"}},"type":"Feature"},
	{"geometry":{"coordinates":[16.146221,48.299811],"type":"Point"},"properties":{"osm_id":"4575986203","tag":{"amenity":"waste_basket"}},"type":"Feature"},
	{"geometry":{"coordinates":[16.171618,48.307867],"type":"Point"},"properties":{"osm_id":"4810380548","tag":{"amenity":"waste_basket"}},"type":"Feature"},
	{"geometry":{"coordinates":[16.16443,48.305144],"type":"Point"},"properties":{"osm_id":"4810600487","tag":{"amenity":"waste_basket"}},"type":"Feature"},
	{"geometry":{"coordinates":[16.159851,48.336514],"type":"Point"},"properties":{"osm_id":"5792619279","tag":{"amenity":"waste_basket"}},"type":"Feature"},
	{"geometry":{"coordinates":[16.157677,48.304625],"type":"Point"},"properties":{"osm_id":"7844247338","tag":{"amenity":"recycling","recycling:beverage_cartons":"yes","recycling:cans":"yes","recycling:glass":"yes","recycling:glass_bottles":"yes","recycling_type":"container"}},"type":"Feature"}
]
}
