{
"type": "FeatureCollection",
"features": [
	{"geometry":{"coordinates":[9.033857,51.180797],"type":"Point"},"properties":{"osm_id":"2829893991","tag":{"natural":"tree"}},"type":"Feature"},
	{"geometry":{"coordinates":[8.977601,51.205641],"type":"Point"},"properties":{"name":"Gerichtslinde","osm_id":"3050807274","tag":{"leaf_type":"broadleaved","natural":"tree"}},"type":"Feature"},
	{"geometry":{"coordinates":[9.039382,51.197633],"type":"Point"},"properties":{"osm_id":"4299596691","tag":{"genus":"Apfel","natural":"tree"}},"type":"Feature"},
	{"geometry":{"coordinates":[9.007646,51.182622],"type":"Point"},"properties":{"osm_id":"4465802554","tag":{"natural":"tree"}},"type":"Feature"},
	{"geometry":{"coordinates":[9.03527,51.200057],"type":"Point"},"properties":{"osm_id":"4938956039","tag":{"circumference":"3.15","denotation":"landmark","genus":"Fagus","genus:de":"Buche","leaf_cycle":"deciduous","leaf_type":"broadleaved","natural":"tree","source:circumference":"Messung 2017-06-26 in h=1,30m"}},"type":"Feature"},
	{"geometry":{"coordinates":[9.010019,51.181713],"type":"Point"},"properties":{"osm_id":"6549799054","tag":{"leaf_type":"broadleaved","natural":"tree"}},"type":"Feature"},
	{"geometry":{"coordinates":[9.009605,51.181662],"type":"Point"},"properties":{"osm_id":"6549799055","tag":{"leaf_type":"broadleaved","natural":"tree"}},"type":"Feature"}
]
}
