{
"type": "FeatureCollection",
"features": [
	{"geometry":{"coordinates":[9.03255,25.34744],"type":"Point"},"properties":{"name":"Acacia","osm_id":"8780581466","tag":{"natural":"tree"}},"type":"Feature"},
	{"geometry":{"coordinates":[9.032963,25.347047],"type":"Point"},"properties":{"name":"Acacia","osm_id":"8780581467","tag":{"natural":"tree"}},"type":"Feature"},
	{"geometry":{"coordinates":[9.033795,25.347295],"type":"Point"},"properties":{"name":"Acacia","osm_id":"8780581468","tag":{"natural":"tree"}},"type":"Feature"}
]
}
