{
"type": "FeatureCollection",
"features": [
	{"geometry":{"coordinates":[8.994474,24.953757],"type":"Point"},"properties":{"name":"Acacia","osm_id":"4831621842","tag":{"leaf_cycle":"semi_evergreen","leaf_type":"needleleaved","natural":"tree"}},"type":"Feature"},
	{"geometry":{"coordinates":[8.994901,24.953769],"type":"Point"},"properties":{"name":"Acacia","osm_id":"4831621843","tag":{"leaf_cycle":"semi_evergreen","leaf_type":"needleleaved","natural":"tree"}},"type":"Feature"}
]
}
