{
"type": "FeatureCollection",
"lastupdate": "2020-08-06T00:00:00Z",
"features": [
	{"geometry":{"coordinates":[24.563975,61.170754],"type":"Point"},"properties":{"name":"Rinki-Ekopiste","osm_id":"7079440149","tag":{"amenity":"recycling"}},"type":"Feature"}
]
}
