{
"type": "FeatureCollection",
"features": [
	{"geometry":{"coordinates":[-2.718396,54.629739],"type":"Point"},"properties":{"name":"The Rebel Tree","osm_id":"6432856522","tag":{"natural":"tree"}},"type":"Feature"}
]
}
