{
"type": "FeatureCollection",
"features": [
	{"geometry":{"coordinates":[-2.673007,37.668072],"type":"Point"},"properties":{"name":"Chopo de La Ventica","osm_id":"3078600755","tag":{"denotation":"natural_monument","monument":"yes","natural":"tree"}},"type":"Feature"}
]
}
