{
"type": "FeatureCollection",
"features": [
	{"geometry":{"coordinates":[-2.697803,37.618635],"type":"Point"},"properties":{"name":"Pino de la Casa Forestal San Marcos","osm_id":"3078600806","tag":{"denotation":"natural_monument","monument":"yes","natural":"tree"}},"type":"Feature"}
]
}
