{
"type": "FeatureCollection",
"features": [
	{"geometry":{"coordinates":[-78.479114,-0.292997],"type":"Point"},"properties":{"osm_id":"2724353261","tag":{"natural":"tree"}},"type":"Feature"},
	{"geometry":{"coordinates":[-78.479136,-0.293056],"type":"Point"},"properties":{"osm_id":"2724353262","tag":{"natural":"tree"}},"type":"Feature"},
	{"geometry":{"coordinates":[-78.445824,-0.314409],"type":"Point"},"properties":{"name":"La Palmera","osm_id":"4083541613","tag":{"natural":"tree"}},"type":"Feature"}
]
}
