{
"type": "FeatureCollection",
"features": [
	{"geometry":{"coordinates":[124.89627,12.028938],"type":"Point"},"properties":{"osm_id":"2726500941","tag":{"natural":"tree","type":"palm"}},"type":"Feature"},
	{"geometry":{"coordinates":[124.93629,12.018769],"type":"Point"},"properties":{"name":"Acacia","osm_id":"2726535822","tag":{"denotation":"landmark","natural":"tree","type":"conifer"}},"type":"Feature"}
]
}
