{
"type": "FeatureCollection",
"features": [
	{"geometry":{"coordinates":[124.896269,12.028937],"type":"Point"},"properties":{"osm_id":"2726500941","tag":{"natural":"tree","type":"palm"}},"type":"Feature"},
	{"geometry":{"coordinates":[124.93629,12.018768],"type":"Point"},"properties":{"name":"Acacia","osm_id":"2726535822","tag":{"denotation":"landmark","leaf_type":"needleleaved","natural":"tree"}},"type":"Feature"}
]
}
