{
"type": "FeatureCollection",
"lastupdate": "2020-08-04T00:00:00Z",
"features": [
	{"geometry":{"coordinates":[85.442195,27.729019],"type":"Point"},"properties":{"name":"Salambu Devi Baluwa Prasodhan Udyog Pvt Ltd","osm_id":"4803502725","tag":{"amenity":"recycling"}},"type":"Feature"}
]
}
