{
"type": "FeatureCollection",
"features": [
	{"geometry":{"coordinates":[85.442195,27.72902],"type":"Point"},"properties":{"name":"Salambu Devi Baluwa Prasodhan Udyog Pvt Ltd","osm_id":"4803502725","tag":{"amenity":"recycling"}},"type":"Feature"}
]
}
