{
"type": "FeatureCollection",
"features": [
	{"geometry":{"coordinates":[-79.764827,-6.487503],"type":"Point"},"properties":{"name":"Arbol Milenario","osm_id":"2441346051","tag":{"natural":"tree","type":"Algarrobo"}},"type":"Feature"}
]
}
