{
"type": "FeatureCollection",
"features": [
	{"geometry":{"coordinates":[-79.764828,-6.487504],"type":"Point"},"properties":{"name":"Arbol Milenario","osm_id":"2441346051","tag":{"natural":"tree","type":"Algarrobo"}},"type":"Feature"}
]
}
