{
"type": "FeatureCollection",
"features": [
	{"geometry":{"coordinates":[122.862561,9.332756],"type":"Point"},"properties":{"name":"Dalakit Tree","osm_id":"7285371112","tag":{"natural":"tree"}},"type":"Feature"}
]
}
