{
"type": "FeatureCollection",
"name": "points",
"crs": { "type": "name", "properties": { "name": "urn:ogc:def:crs:OGC:1.3:CRS84" } },
"features": [
{ "type": "Feature", "properties": { "osm_id": "18384027", "other_tags": "\"amenity\"=>\"recycling\"" }, "geometry": { "type": "Point", "coordinates": [ -0.7136656, 52.6794484 ] } },
{ "type": "Feature", "properties": { "osm_id": "18384411", "name": "Cottesmore Civic Amenity Site", "other_tags": "\"amenity\"=>\"recycling\"" }, "geometry": { "type": "Point", "coordinates": [ -0.6773455, 52.7050515 ] } },
{ "type": "Feature", "properties": { "osm_id": "1853423051", "other_tags": "\"amenity\"=>\"recycling\",\"recycling:cans\"=>\"yes\",\"recycling:glass\"=>\"yes\",\"recycling:paper\"=>\"yes\"" }, "geometry": { "type": "Point", "coordinates": [ -0.7014868, 52.6553618 ] } },
{ "type": "Feature", "properties": { "osm_id": "1853423058", "other_tags": "\"amenity\"=>\"waste_basket\"" }, "geometry": { "type": "Point", "coordinates": [ -0.7014756, 52.6553796 ] } },
{ "type": "Feature", "properties": { "osm_id": "2435781569", "other_tags": "\"amenity\"=>\"waste_basket\"" }, "geometry": { "type": "Point", "coordinates": [ -0.5461708, 52.6347232 ] } },
{ "type": "Feature", "properties": { "osm_id": "2436731865", "other_tags": "\"amenity\"=>\"waste_basket\"" }, "geometry": { "type": "Point", "coordinates": [ -0.5499362, 52.6300838 ] } },
{ "type": "Feature", "properties": { "osm_id": "2442952198", "other_tags": "\"amenity\"=>\"waste_basket\"" }, "geometry": { "type": "Point", "coordinates": [ -0.5525932, 52.6311655 ] } },
{ "type": "Feature", "properties": { "osm_id": "2442952202", "other_tags": "\"amenity\"=>\"recycling\"" }, "geometry": { "type": "Point", "coordinates": [ -0.5501513, 52.634658 ] } },
{ "type": "Feature", "properties": { "osm_id": "2442967884", "other_tags": "\"amenity\"=>\"waste_basket\"" }, "geometry": { "type": "Point", "coordinates": [ -0.5530775, 52.6309239 ] } },
{ "type": "Feature", "properties": { "osm_id": "6886358017", "other_tags": "\"amenity\"=>\"waste_basket\",\"waste\"=>\"dog_excrement\"" }, "geometry": { "type": "Point", "coordinates": [ -0.494064, 52.6607214 ] } },
{ "type": "Feature", "properties": { "osm_id": "7518562892", "other_tags": "\"amenity\"=>\"waste_basket\"" }, "geometry": { "type": "Point", "coordinates": [ -0.73052, 52.669 ] } },
{ "type": "Feature", "properties": { "osm_id": "8857885228", "other_tags": "\"amenity\"=>\"waste_basket\"" }, "geometry": { "type": "Point", "coordinates": [ -0.718791, 52.7143262 ] } },
{ "type": "Feature", "properties": { "osm_id": "9069710590", "other_tags": "\"amenity\"=>\"recycling\",\"operator\"=>\"Tesco\",\"recycling_type\"=>\"container\"" }, "geometry": { "type": "Point", "coordinates": [ -0.7318009, 52.6682099 ] } }
]
}
