{
"type": "FeatureCollection",
"name": "points",
"crs": { "type": "name", "properties": { "name": "urn:ogc:def:crs:OGC:1.3:CRS84" } },
"features": [
{ "type": "Feature", "properties": { "osm_id": "16146555", "name": "Potters Bar Household Waste Recycling Centre", "other_tags": "\"addr:postcode\"=>\"EN6 3JN\",\"addr:street\"=>\"Cranborne Road\",\"amenity\"=>\"recycling\",\"opening_hours\"=>\"Mo-Su 08:00-16:00\",\"recycling:aluminium\"=>\"yes\",\"recycling:batteries\"=>\"yes\",\"recycling:beverage_cartons\"=>\"yes\",\"recycling:books\"=>\"yes\",\"recycling:cans\"=>\"yes\",\"recycling:cardboard\"=>\"yes\",\"recycling:cartons\"=>\"yes\",\"recycling:chipboard\"=>\"yes\",\"recycling:clothes\"=>\"yes\",\"recycling:cooking_oil\"=>\"yes\",\"recycling:cork\"=>\"yes\",\"recycling:engine_oil\"=>\"yes\",\"recycling:flat_glass\"=>\"yes\",\"recycling:foil\"=>\"yes\",\"recycling:fridge_and_freezer\"=>\"yes\",\"recycling:garden_waste\"=>\"yes\",\"recycling:glass_bottles\"=>\"yes\",\"recycling:green_waste\"=>\"yes\",\"recycling:magazines\"=>\"yes\",\"recycling:newspaper\"=>\"yes\",\"recycling:paper\"=>\"yes\",\"recycling:paper_packaging\"=>\"yes\",\"recycling:plasterboard\"=>\"yes\",\"recycling:plastic\"=>\"yes\",\"recycling:plastic_bottles\"=>\"yes\",\"recycling:polyester\"=>\"yes\",\"recycling:scrap_metal\"=>\"yes\",\"recycling:sheet_metal\"=>\"yes\",\"recycling:shoes\"=>\"yes\",\"recycling:small_appliances\"=>\"yes\",\"recycling:tv_monitor\"=>\"yes\",\"recycling:tyres\"=>\"yes\",\"recycling:waste\"=>\"yes\",\"recycling:waste_oil\"=>\"yes\",\"recycling:white_goods\"=>\"yes\",\"recycling:wood\"=>\"yes\",\"website\"=>\"https:\/\/www.hertsmere.gov.uk\/environmentplanning\/recyclingandwaste\/recycling\/householdwastedisposalsites.jsp\"" }, "geometry": { "type": "Point", "coordinates": [ -0.2057809, 51.7070665 ] } },
{ "type": "Feature", "properties": { "osm_id": "428187416", "other_tags": "\"amenity\"=>\"recycling\"" }, "geometry": { "type": "Point", "coordinates": [ -0.2911628, 51.6488699 ] } },
{ "type": "Feature", "properties": { "osm_id": "526827285", "other_tags": "\"amenity\"=>\"recycling\",\"location\"=>\"overground\",\"recycling_type\"=>\"container\"" }, "geometry": { "type": "Point", "coordinates": [ -0.175531, 51.6960698 ] } },
{ "type": "Feature", "properties": { "osm_id": "1544600871", "name": "Duke of York Garden Centre", "other_tags": "\"amenity\"=>\"recycling\",\"recycling:clothes\"=>\"yes\",\"recycling:shoes\"=>\"yes\"" }, "geometry": { "type": "Point", "coordinates": [ -0.1877995, 51.6820571 ] } },
{ "type": "Feature", "properties": { "osm_id": "1715186572", "other_tags": "\"amenity\"=>\"recycling\",\"recycling_type\"=>\"container\"" }, "geometry": { "type": "Point", "coordinates": [ -0.3657527, 51.6440008 ] } },
{ "type": "Feature", "properties": { "osm_id": "2399645592", "other_tags": "\"amenity\"=>\"waste_basket\"" }, "geometry": { "type": "Point", "coordinates": [ -0.3551487, 51.6483223 ] } },
{ "type": "Feature", "properties": { "osm_id": "2906465589", "other_tags": "\"amenity\"=>\"waste_basket\"" }, "geometry": { "type": "Point", "coordinates": [ -0.2865617, 51.6516704 ] } },
{ "type": "Feature", "properties": { "osm_id": "2906465598", "other_tags": "\"amenity\"=>\"waste_basket\"" }, "geometry": { "type": "Point", "coordinates": [ -0.2849625, 51.6521436 ] } },
{ "type": "Feature", "properties": { "osm_id": "8833910365", "other_tags": "\"amenity\"=>\"waste_basket\",\"waste\"=>\"dog_excrement\"" }, "geometry": { "type": "Point", "coordinates": [ -0.2223597, 51.6865267 ] } },
{ "type": "Feature", "properties": { "osm_id": "8937059316", "other_tags": "\"amenity\"=>\"waste_basket\"" }, "geometry": { "type": "Point", "coordinates": [ -0.1738198, 51.6963385 ] } },
{ "type": "Feature", "properties": { "osm_id": "8937074527", "other_tags": "\"amenity\"=>\"waste_basket\"" }, "geometry": { "type": "Point", "coordinates": [ -0.1778563, 51.6918003 ] } },
{ "type": "Feature", "properties": { "osm_id": "8937142720", "other_tags": "\"amenity\"=>\"waste_basket\"" }, "geometry": { "type": "Point", "coordinates": [ -0.1755797, 51.6966744 ] } },
{ "type": "Feature", "properties": { "osm_id": "8939009438", "other_tags": "\"amenity\"=>\"waste_basket\"" }, "geometry": { "type": "Point", "coordinates": [ -0.1763274, 51.6955801 ] } },
{ "type": "Feature", "properties": { "osm_id": "8939009441", "other_tags": "\"amenity\"=>\"waste_basket\"" }, "geometry": { "type": "Point", "coordinates": [ -0.1762697, 51.6953701 ] } },
{ "type": "Feature", "properties": { "osm_id": "8939242662", "other_tags": "\"amenity\"=>\"waste_basket\"" }, "geometry": { "type": "Point", "coordinates": [ -0.1821535, 51.6929071 ] } }
]
}
