{
"type": "FeatureCollection",
"name": "points",
"crs": { "type": "name", "properties": { "name": "urn:ogc:def:crs:OGC:1.3:CRS84" } },
"features": [
{ "type": "Feature", "properties": { "osm_id": "274051194", "name": "Radcaster Recycling Centre", "other_tags": "\"amenity\"=>\"recycling\"" }, "geometry": { "type": "Point", "coordinates": [ -1.2687628, 53.883023 ] } },
{ "type": "Feature", "properties": { "osm_id": "473521107", "other_tags": "\"amenity\"=>\"recycling\"" }, "geometry": { "type": "Point", "coordinates": [ -1.0222709, 53.7264072 ] } },
{ "type": "Feature", "properties": { "osm_id": "573487878", "other_tags": "\"amenity\"=>\"recycling\"" }, "geometry": { "type": "Point", "coordinates": [ -1.067793, 53.7819544 ] } },
{ "type": "Feature", "properties": { "osm_id": "573487881", "other_tags": "\"amenity\"=>\"recycling\"" }, "geometry": { "type": "Point", "coordinates": [ -1.0676803, 53.7818467 ] } },
{ "type": "Feature", "properties": { "osm_id": "585425759", "other_tags": "\"amenity\"=>\"recycling\"" }, "geometry": { "type": "Point", "coordinates": [ -0.9582728, 53.8255775 ] } },
{ "type": "Feature", "properties": { "osm_id": "603974980", "other_tags": "\"amenity\"=>\"recycling\"" }, "geometry": { "type": "Point", "coordinates": [ -1.0705767, 53.7808484 ] } },
{ "type": "Feature", "properties": { "osm_id": "672947633", "other_tags": "\"amenity\"=>\"recycling\"" }, "geometry": { "type": "Point", "coordinates": [ -0.9501351, 53.8681256 ] } },
{ "type": "Feature", "properties": { "osm_id": "1377391163", "other_tags": "\"amenity\"=>\"recycling\",\"location\"=>\"overground\",\"recycling_type\"=>\"container\"" }, "geometry": { "type": "Point", "coordinates": [ -1.0659532, 53.8297948 ] } },
{ "type": "Feature", "properties": { "osm_id": "3932108391", "other_tags": "\"amenity\"=>\"waste_basket\"" }, "geometry": { "type": "Point", "coordinates": [ -1.2547844, 53.8876895 ] } },
{ "type": "Feature", "properties": { "osm_id": "3932145585", "other_tags": "\"amenity\"=>\"waste_basket\"" }, "geometry": { "type": "Point", "coordinates": [ -1.2582537, 53.8852237 ] } },
{ "type": "Feature", "properties": { "osm_id": "3932145612", "other_tags": "\"amenity\"=>\"waste_basket\"" }, "geometry": { "type": "Point", "coordinates": [ -1.2601678, 53.8887642 ] } },
{ "type": "Feature", "properties": { "osm_id": "3932157223", "other_tags": "\"amenity\"=>\"waste_basket\"" }, "geometry": { "type": "Point", "coordinates": [ -1.2605814, 53.8844259 ] } },
{ "type": "Feature", "properties": { "osm_id": "3932175414", "other_tags": "\"amenity\"=>\"waste_basket\"" }, "geometry": { "type": "Point", "coordinates": [ -1.2620108, 53.8835812 ] } },
{ "type": "Feature", "properties": { "osm_id": "3932199483", "other_tags": "\"amenity\"=>\"waste_basket\"" }, "geometry": { "type": "Point", "coordinates": [ -1.2618843, 53.8837954 ] } },
{ "type": "Feature", "properties": { "osm_id": "3932217249", "other_tags": "\"amenity\"=>\"recycling\"" }, "geometry": { "type": "Point", "coordinates": [ -1.2631628, 53.883924 ] } },
{ "type": "Feature", "properties": { "osm_id": "3932220451", "other_tags": "\"amenity\"=>\"waste_basket\"" }, "geometry": { "type": "Point", "coordinates": [ -1.2624499, 53.8849463 ] } },
{ "type": "Feature", "properties": { "osm_id": "3932220456", "other_tags": "\"amenity\"=>\"waste_basket\"" }, "geometry": { "type": "Point", "coordinates": [ -1.2621884, 53.8845526 ] } },
{ "type": "Feature", "properties": { "osm_id": "3932240762", "other_tags": "\"amenity\"=>\"waste_basket\"" }, "geometry": { "type": "Point", "coordinates": [ -1.2629342, 53.8841008 ] } },
{ "type": "Feature", "properties": { "osm_id": "3939241152", "other_tags": "\"amenity\"=>\"waste_basket\"" }, "geometry": { "type": "Point", "coordinates": [ -1.2644092, 53.885001 ] } },
{ "type": "Feature", "properties": { "osm_id": "3978314330", "other_tags": "\"amenity\"=>\"recycling\"" }, "geometry": { "type": "Point", "coordinates": [ -1.2344859, 53.7602365 ] } },
{ "type": "Feature", "properties": { "osm_id": "5082176726", "other_tags": "\"amenity\"=>\"recycling\",\"recycling_type\"=>\"container\"" }, "geometry": { "type": "Point", "coordinates": [ -1.069147, 53.7855151 ] } },
{ "type": "Feature", "properties": { "osm_id": "6557780310", "other_tags": "\"amenity\"=>\"recycling\"" }, "geometry": { "type": "Point", "coordinates": [ -1.0879656, 53.7721975 ] } },
{ "type": "Feature", "properties": { "osm_id": "7804886689", "other_tags": "\"amenity\"=>\"waste_basket\",\"waste\"=>\"dog_excrement\"" }, "geometry": { "type": "Point", "coordinates": [ -1.102328, 53.8146813 ] } }
]
}
