{
"type": "FeatureCollection",
"name": "points",
"crs": { "type": "name", "properties": { "name": "urn:ogc:def:crs:OGC:1.3:CRS84" } },
"features": [
{ "type": "Feature", "properties": { "osm_id": "6988303572", "other_tags": "\"amenity\"=>\"waste_basket\"" }, "geometry": { "type": "Point", "coordinates": [ -1.0789252, 52.602009 ] } },
{ "type": "Feature", "properties": { "osm_id": "6988303574", "other_tags": "\"amenity\"=>\"waste_basket\"" }, "geometry": { "type": "Point", "coordinates": [ -1.0787865, 52.6017871 ] } },
{ "type": "Feature", "properties": { "osm_id": "8810852116", "other_tags": "\"amenity\"=>\"waste_basket\"" }, "geometry": { "type": "Point", "coordinates": [ -1.1098331, 52.5828325 ] } },
{ "type": "Feature", "properties": { "osm_id": "8833038844", "other_tags": "\"amenity\"=>\"waste_basket\"" }, "geometry": { "type": "Point", "coordinates": [ -1.134042, 52.5825076 ] } },
{ "type": "Feature", "properties": { "osm_id": "8833038845", "other_tags": "\"amenity\"=>\"waste_basket\"" }, "geometry": { "type": "Point", "coordinates": [ -1.1338194, 52.5818948 ] } },
{ "type": "Feature", "properties": { "osm_id": "8856057750", "other_tags": "\"amenity\"=>\"recycling\",\"recycling:clothes\"=>\"yes\",\"recycling_type\"=>\"container\"" }, "geometry": { "type": "Point", "coordinates": [ -1.1321658, 52.5800825 ] } }
]
}
