{
"type": "FeatureCollection",
"name": "points",
"crs": { "type": "name", "properties": { "name": "urn:ogc:def:crs:OGC:1.3:CRS84" } },
"features": [
{ "type": "Feature", "properties": { "osm_id": "350559075", "other_tags": "\"amenity\"=>\"recycling\",\"recycling:glass\"=>\"yes\"" }, "geometry": { "type": "Point", "coordinates": [ -0.2798777, 50.8286636 ] } },
{ "type": "Feature", "properties": { "osm_id": "443982955", "other_tags": "\"amenity\"=>\"recycling\"" }, "geometry": { "type": "Point", "coordinates": [ -0.2751416, 50.8317495 ] } },
{ "type": "Feature", "properties": { "osm_id": "893189310", "other_tags": "\"amenity\"=>\"recycling\"" }, "geometry": { "type": "Point", "coordinates": [ -0.2757285, 50.833894 ] } },
{ "type": "Feature", "properties": { "osm_id": "1338001344", "other_tags": "\"amenity\"=>\"recycling\"" }, "geometry": { "type": "Point", "coordinates": [ -0.2486845, 50.8429412 ] } },
{ "type": "Feature", "properties": { "osm_id": "1338043882", "other_tags": "\"amenity\"=>\"recycling\",\"recycling_type\"=>\"centre\"" }, "geometry": { "type": "Point", "coordinates": [ -0.2596601, 50.8328085 ] } },
{ "type": "Feature", "properties": { "osm_id": "2463063135", "other_tags": "\"amenity\"=>\"waste_basket\"" }, "geometry": { "type": "Point", "coordinates": [ -0.2922159, 50.8253463 ] } },
{ "type": "Feature", "properties": { "osm_id": "2474201072", "other_tags": "\"amenity\"=>\"waste_basket\"" }, "geometry": { "type": "Point", "coordinates": [ -0.2370036, 50.8297817 ] } },
{ "type": "Feature", "properties": { "osm_id": "2474276955", "other_tags": "\"amenity\"=>\"waste_basket\"" }, "geometry": { "type": "Point", "coordinates": [ -0.2198504, 50.8354932 ] } },
{ "type": "Feature", "properties": { "osm_id": "5123926991", "other_tags": "\"amenity\"=>\"waste_basket\"" }, "geometry": { "type": "Point", "coordinates": [ -0.3312803, 50.8437127 ] } },
{ "type": "Feature", "properties": { "osm_id": "5123926993", "other_tags": "\"waste\"=>\"dog_excrement\",\"amenity\"=>\"waste_basket\"" }, "geometry": { "type": "Point", "coordinates": [ -0.3313507, 50.8435991 ] } },
{ "type": "Feature", "properties": { "osm_id": "5123926995", "other_tags": "\"amenity\"=>\"waste_basket\"" }, "geometry": { "type": "Point", "coordinates": [ -0.3314998, 50.8436366 ] } },
{ "type": "Feature", "properties": { "osm_id": "5588697532", "other_tags": "\"amenity\"=>\"waste_basket\"" }, "geometry": { "type": "Point", "coordinates": [ -0.2736249, 50.8422046 ] } },
{ "type": "Feature", "properties": { "osm_id": "5588697533", "other_tags": "\"waste\"=>\"dog_excrement\",\"amenity\"=>\"waste_basket\"" }, "geometry": { "type": "Point", "coordinates": [ -0.2733796, 50.8421114 ] } },
{ "type": "Feature", "properties": { "osm_id": "7841098700", "other_tags": "\"amenity\"=>\"waste_basket\"" }, "geometry": { "type": "Point", "coordinates": [ -0.233673, 50.840426 ] } },
{ "type": "Feature", "properties": { "osm_id": "7841098701", "other_tags": "\"amenity\"=>\"waste_basket\"" }, "geometry": { "type": "Point", "coordinates": [ -0.2326324, 50.8403241 ] } },
{ "type": "Feature", "properties": { "osm_id": "7841426750", "other_tags": "\"amenity\"=>\"waste_basket\",\"waste\"=>\"dog_excrement\"" }, "geometry": { "type": "Point", "coordinates": [ -0.2320133, 50.844803 ] } }
]
}
