{
"type": "FeatureCollection",
"name": "points",
"crs": { "type": "name", "properties": { "name": "urn:ogc:def:crs:OGC:1.3:CRS84" } },
"features": [
{ "type": "Feature", "properties": { "osm_id": "347810400", "other_tags": "\"amenity\"=>\"recycling\"" }, "geometry": { "type": "Point", "coordinates": [ -2.4058346, 51.9319423 ] } },
{ "type": "Feature", "properties": { "osm_id": "535960705", "other_tags": "\"amenity\"=>\"recycling\"" }, "geometry": { "type": "Point", "coordinates": [ -2.4811918, 51.8200429 ] } },
{ "type": "Feature", "properties": { "osm_id": "1491433003", "other_tags": "\"amenity\"=>\"recycling\"" }, "geometry": { "type": "Point", "coordinates": [ -2.4052564, 51.9316665 ] } },
{ "type": "Feature", "properties": { "osm_id": "2238580877", "other_tags": "\"amenity\"=>\"recycling\",\"recycling:cans\"=>\"yes\",\"recycling:clothes\"=>\"yes\",\"recycling:glass_bottles\"=>\"yes\",\"recycling:magazines\"=>\"yes\",\"recycling:newspaper\"=>\"yes\",\"recycling:paper\"=>\"yes\",\"recycling:paper_packaging\"=>\"yes\",\"recycling:waste\"=>\"no\",\"recycling_type\"=>\"container\"" }, "geometry": { "type": "Point", "coordinates": [ -2.6158885, 51.7922348 ] } },
{ "type": "Feature", "properties": { "osm_id": "2886413580", "other_tags": "\"amenity\"=>\"recycling\",\"location\"=>\"overground\",\"recycling_type\"=>\"container\"" }, "geometry": { "type": "Point", "coordinates": [ -2.531261, 51.728079 ] } },
{ "type": "Feature", "properties": { "osm_id": "2886415477", "other_tags": "\"amenity\"=>\"recycling\",\"recycling_type\"=>\"container\"" }, "geometry": { "type": "Point", "coordinates": [ -2.5362329, 51.7241238 ] } },
{ "type": "Feature", "properties": { "osm_id": "2886415478", "other_tags": "\"amenity\"=>\"recycling\",\"location\"=>\"overground\",\"recycling_type\"=>\"container\"" }, "geometry": { "type": "Point", "coordinates": [ -2.5344626, 51.7258185 ] } },
{ "type": "Feature", "properties": { "osm_id": "3630566776", "other_tags": "\"amenity\"=>\"waste_basket\"" }, "geometry": { "type": "Point", "coordinates": [ -2.5984465, 51.797013 ] } },
{ "type": "Feature", "properties": { "osm_id": "3632098516", "other_tags": "\"amenity\"=>\"waste_basket\"" }, "geometry": { "type": "Point", "coordinates": [ -2.5980299, 51.7929685 ] } },
{ "type": "Feature", "properties": { "osm_id": "3670936056", "other_tags": "\"amenity\"=>\"waste_basket\"" }, "geometry": { "type": "Point", "coordinates": [ -2.5276699, 51.7273043 ] } },
{ "type": "Feature", "properties": { "osm_id": "6415308208", "other_tags": "\"amenity\"=>\"waste_basket\"" }, "geometry": { "type": "Point", "coordinates": [ -2.6141466, 51.7902909 ] } },
{ "type": "Feature", "properties": { "osm_id": "7660299776", "other_tags": "\"amenity\"=>\"waste_basket\"" }, "geometry": { "type": "Point", "coordinates": [ -2.6410827, 51.7383856 ] } },
{ "type": "Feature", "properties": { "osm_id": "8693665259", "other_tags": "\"amenity\"=>\"recycling\",\"recycling:cans\"=>\"yes\",\"recycling:paper\"=>\"yes\",\"recycling:plastic\"=>\"yes\",\"recycling_type\"=>\"container\"" }, "geometry": { "type": "Point", "coordinates": [ -2.5607544, 51.8059895 ] } }
]
}
