{
"type": "FeatureCollection",
"name": "points",
"crs": { "type": "name", "properties": { "name": "urn:ogc:def:crs:OGC:1.3:CRS84" } },
"features": [
{ "type": "Feature", "properties": { "osm_id": "2624460985", "other_tags": "\"amenity\"=>\"waste_basket\"" }, "geometry": { "type": "Point", "coordinates": [ -1.3271243, 53.1032394 ] } },
{ "type": "Feature", "properties": { "osm_id": "2808036129", "other_tags": "\"amenity\"=>\"waste_basket\"" }, "geometry": { "type": "Point", "coordinates": [ -1.2669749, 53.212697 ] } },
{ "type": "Feature", "properties": { "osm_id": "2815464578", "other_tags": "\"amenity\"=>\"waste_basket\"" }, "geometry": { "type": "Point", "coordinates": [ -1.2120348, 53.2032939 ] } },
{ "type": "Feature", "properties": { "osm_id": "2815561769", "other_tags": "\"amenity\"=>\"waste_basket\"" }, "geometry": { "type": "Point", "coordinates": [ -1.212429, 53.2117307 ] } },
{ "type": "Feature", "properties": { "osm_id": "2815623309", "other_tags": "\"amenity\"=>\"recycling\"" }, "geometry": { "type": "Point", "coordinates": [ -1.227605, 53.2174101 ] } },
{ "type": "Feature", "properties": { "osm_id": "2826648552", "other_tags": "\"amenity\"=>\"waste_basket\"" }, "geometry": { "type": "Point", "coordinates": [ -1.2067225, 53.2389563 ] } },
{ "type": "Feature", "properties": { "osm_id": "2827514753", "other_tags": "\"amenity\"=>\"waste_basket\"" }, "geometry": { "type": "Point", "coordinates": [ -1.2223572, 53.2096997 ] } },
{ "type": "Feature", "properties": { "osm_id": "2827522362", "other_tags": "\"amenity\"=>\"waste_basket\"" }, "geometry": { "type": "Point", "coordinates": [ -1.2239317, 53.2095761 ] } },
{ "type": "Feature", "properties": { "osm_id": "2827567754", "other_tags": "\"amenity\"=>\"waste_basket\"" }, "geometry": { "type": "Point", "coordinates": [ -1.2289125, 53.2031083 ] } },
{ "type": "Feature", "properties": { "osm_id": "2828666394", "other_tags": "\"amenity\"=>\"waste_basket\"" }, "geometry": { "type": "Point", "coordinates": [ -1.2090353, 53.2271846 ] } },
{ "type": "Feature", "properties": { "osm_id": "2836455220", "other_tags": "\"amenity\"=>\"waste_basket\"" }, "geometry": { "type": "Point", "coordinates": [ -1.203863, 53.2319131 ] } },
{ "type": "Feature", "properties": { "osm_id": "2836455222", "other_tags": "\"amenity\"=>\"waste_basket\"" }, "geometry": { "type": "Point", "coordinates": [ -1.2037048, 53.2318265 ] } },
{ "type": "Feature", "properties": { "osm_id": "2836455224", "other_tags": "\"amenity\"=>\"waste_basket\"" }, "geometry": { "type": "Point", "coordinates": [ -1.2035358, 53.2317879 ] } },
{ "type": "Feature", "properties": { "osm_id": "5019770489", "other_tags": "\"amenity\"=>\"waste_basket\"" }, "geometry": { "type": "Point", "coordinates": [ -1.2931681, 53.2301974 ] } },
{ "type": "Feature", "properties": { "osm_id": "5277489052", "other_tags": "\"amenity\"=>\"recycling\",\"recycling_type\"=>\"container\"" }, "geometry": { "type": "Point", "coordinates": [ -1.3537833, 53.1198644 ] } },
{ "type": "Feature", "properties": { "osm_id": "6428512585", "other_tags": "\"amenity\"=>\"waste_basket\"" }, "geometry": { "type": "Point", "coordinates": [ -1.2947972, 53.2304356 ] } }
]
}
