{
"type": "FeatureCollection",
"name": "points",
"crs": { "type": "name", "properties": { "name": "urn:ogc:def:crs:OGC:1.3:CRS84" } },
"features": [
{ "type": "Feature", "properties": { "osm_id": "761704768", "other_tags": "\"amenity\"=>\"recycling\"" }, "geometry": { "type": "Point", "coordinates": [ -1.4843494, 52.5317378 ] } },
{ "type": "Feature", "properties": { "osm_id": "793580016", "other_tags": "\"access\"=>\"watermate key\",\"amenity\"=>\"recycling\",\"operator\"=>\"Canal and River Trust\"" }, "geometry": { "type": "Point", "coordinates": [ -1.4698987, 52.4573209 ] } },
{ "type": "Feature", "properties": { "osm_id": "800256406", "other_tags": "\"amenity\"=>\"recycling\",\"recycling:cans\"=>\"yes\",\"recycling:glass\"=>\"yes\",\"recycling:paper\"=>\"yes\"" }, "geometry": { "type": "Point", "coordinates": [ -1.4741415, 52.4796352 ] } },
{ "type": "Feature", "properties": { "osm_id": "800256510", "other_tags": "\"amenity\"=>\"recycling\",\"recycling:cans\"=>\"yes\",\"recycling:glass\"=>\"yes\",\"recycling:paper\"=>\"yes\",\"recycling:clothes\"=>\"yes\"" }, "geometry": { "type": "Point", "coordinates": [ -1.4705938, 52.4783884 ] } },
{ "type": "Feature", "properties": { "osm_id": "800307977", "other_tags": "\"amenity\"=>\"recycling\",\"recycling:cans\"=>\"yes\",\"recycling:glass\"=>\"yes\",\"recycling:paper\"=>\"yes\"" }, "geometry": { "type": "Point", "coordinates": [ -1.4725453, 52.4793314 ] } },
{ "type": "Feature", "properties": { "osm_id": "800588823", "other_tags": "\"amenity\"=>\"recycling\",\"recycling:cans\"=>\"yes\",\"recycling:glass\"=>\"yes\",\"recycling:paper\"=>\"yes\"" }, "geometry": { "type": "Point", "coordinates": [ -1.4727481, 52.4799037 ] } },
{ "type": "Feature", "properties": { "osm_id": "1808599053", "other_tags": "\"amenity\"=>\"recycling\"" }, "geometry": { "type": "Point", "coordinates": [ -1.4707745, 52.5148708 ] } },
{ "type": "Feature", "properties": { "osm_id": "5368909352", "other_tags": "\"amenity\"=>\"waste_basket\"" }, "geometry": { "type": "Point", "coordinates": [ -1.4514526, 52.5356402 ] } }
]
}
