{
"type": "FeatureCollection",
"name": "points",
"crs": { "type": "name", "properties": { "name": "urn:ogc:def:crs:OGC:1.3:CRS84" } },
"features": [
{ "type": "Feature", "properties": { "osm_id": "369861059", "other_tags": "\"amenity\"=>\"recycling\"" }, "geometry": { "type": "Point", "coordinates": [ -1.4768053, 53.3005113 ] } },
{ "type": "Feature", "properties": { "osm_id": "370007205", "other_tags": "\"amenity\"=>\"recycling\"" }, "geometry": { "type": "Point", "coordinates": [ -1.4544376, 53.3119291 ] } },
{ "type": "Feature", "properties": { "osm_id": "370156884", "other_tags": "\"amenity\"=>\"recycling\"" }, "geometry": { "type": "Point", "coordinates": [ -1.4643617, 53.3042665 ] } },
{ "type": "Feature", "properties": { "osm_id": "390524939", "other_tags": "\"amenity\"=>\"recycling\"" }, "geometry": { "type": "Point", "coordinates": [ -1.3578882, 53.3098339 ] } },
{ "type": "Feature", "properties": { "osm_id": "3811565477", "other_tags": "\"amenity\"=>\"recycling\"" }, "geometry": { "type": "Point", "coordinates": [ -1.4014197, 53.1201817 ] } },
{ "type": "Feature", "properties": { "osm_id": "7195457269", "other_tags": "\"amenity\"=>\"recycling\",\"recycling_type\"=>\"container\",\"recycling:bottles\"=>\"yes\"" }, "geometry": { "type": "Point", "coordinates": [ -1.4705551, 53.3036058 ] } }
]
}
