{
"type": "FeatureCollection",
"name": "points",
"crs": { "type": "name", "properties": { "name": "urn:ogc:def:crs:OGC:1.3:CRS84" } },
"features": [
{ "type": "Feature", "properties": { "osm_id": "624354922", "other_tags": "\"amenity\"=>\"recycling\"" }, "geometry": { "type": "Point", "coordinates": [ -0.6114294, 52.3260112 ] } },
{ "type": "Feature", "properties": { "osm_id": "1069391815", "name": "Rushden Household Waste Recycling Centre", "other_tags": "\"amenity\"=>\"recycling\",\"recycling_type\"=>\"centre\",\"website\"=>\"https:\/\/www.northamptonshire.gov.uk\/councilservices\/waste-and-recycling\/household-waste-recycling-centres\/Pages\/rushden-household-waste-recycling-centre.aspx\"" }, "geometry": { "type": "Point", "coordinates": [ -0.6225727, 52.2990775 ] } },
{ "type": "Feature", "properties": { "osm_id": "1352781852", "other_tags": "\"amenity\"=>\"waste_basket\"" }, "geometry": { "type": "Point", "coordinates": [ -0.4799246, 52.3241336 ] } },
{ "type": "Feature", "properties": { "osm_id": "1352781856", "other_tags": "\"amenity\"=>\"waste_basket\"" }, "geometry": { "type": "Point", "coordinates": [ -0.4800949, 52.3235286 ] } },
{ "type": "Feature", "properties": { "osm_id": "4223994941", "barrier": "gate" }, "geometry": { "type": "Point", "coordinates": [ -0.6515268, 52.518694 ] } },
{ "type": "Feature", "properties": { "osm_id": "5908449820", "other_tags": "\"amenity\"=>\"waste_basket\"" }, "geometry": { "type": "Point", "coordinates": [ -0.4667484, 52.4813302 ] } },
{ "type": "Feature", "properties": { "osm_id": "6386045936", "other_tags": "\"amenity\"=>\"waste_basket\"" }, "geometry": { "type": "Point", "coordinates": [ -0.5997701, 52.2892005 ] } }
]
}
