{
"type": "FeatureCollection",
"name": "points",
"crs": { "type": "name", "properties": { "name": "urn:ogc:def:crs:OGC:1.3:CRS84" } },
"features": [
{ "type": "Feature", "properties": { "osm_id": "626077187", "other_tags": "\"amenity\"=>\"recycling\"" }, "geometry": { "type": "Point", "coordinates": [ -6.2653942, 54.3467866 ] } },
{ "type": "Feature", "properties": { "osm_id": "703003586", "other_tags": "\"amenity\"=>\"recycling\"" }, "geometry": { "type": "Point", "coordinates": [ -6.1587334, 54.2365953 ] } },
{ "type": "Feature", "properties": { "osm_id": "845379356", "other_tags": "\"amenity\"=>\"recycling\"" }, "geometry": { "type": "Point", "coordinates": [ -6.1518475, 54.2462666 ] } },
{ "type": "Feature", "properties": { "osm_id": "851221760", "other_tags": "\"amenity\"=>\"recycling\"" }, "geometry": { "type": "Point", "coordinates": [ -6.2715295, 54.3517968 ] } },
{ "type": "Feature", "properties": { "osm_id": "1975260941", "name": "Fair green amenirty site", "other_tags": "\"amenity\"=>\"recycling\",\"recycling:batteries\"=>\"yes\",\"recycling:books\"=>\"yes\",\"recycling:cans\"=>\"yes\",\"recycling:cardboard\"=>\"yes\",\"recycling:cartons\"=>\"yes\",\"recycling:clothes\"=>\"yes\",\"recycling:electrical_appliances\"=>\"yes\",\"recycling:glass\"=>\"no\",\"recycling:glass_bottles\"=>\"yes\",\"recycling:green_waste\"=>\"yes\",\"recycling:magazines\"=>\"yes\",\"recycling:newspaper\"=>\"yes\",\"recycling:paper\"=>\"yes\",\"recycling:paper_packaging\"=>\"yes\",\"recycling:plastic\"=>\"yes\",\"recycling:plastic_bottles\"=>\"yes\",\"recycling:plastic_packaging\"=>\"yes\",\"recycling:scrap_metal\"=>\"yes\",\"recycling:small_appliances\"=>\"yes\",\"recycling:waste\"=>\"yes\",\"recycling:wood\"=>\"yes\",\"recycling_type\"=>\"centre\"" }, "geometry": { "type": "Point", "coordinates": [ -6.4480599, 54.4201549 ] } },
{ "type": "Feature", "properties": { "osm_id": "2219620433", "other_tags": "\"amenity\"=>\"recycling\"" }, "geometry": { "type": "Point", "coordinates": [ -6.1488298, 54.4188633 ] } },
{ "type": "Feature", "properties": { "osm_id": "2229439972", "other_tags": "\"amenity\"=>\"waste_basket\"" }, "geometry": { "type": "Point", "coordinates": [ -6.240529, 54.4029278 ] } },
{ "type": "Feature", "properties": { "osm_id": "4657643888", "other_tags": "\"amenity\"=>\"recycling\",\"recycling:glass\"=>\"yes\",\"recycling_type\"=>\"container\"" }, "geometry": { "type": "Point", "coordinates": [ -6.4363916, 54.428693 ] } },
{ "type": "Feature", "properties": { "osm_id": "4856142237", "other_tags": "\"amenity\"=>\"waste_basket\"" }, "geometry": { "type": "Point", "coordinates": [ -6.432548, 54.4166148 ] } },
{ "type": "Feature", "properties": { "osm_id": "4856142240", "other_tags": "\"amenity\"=>\"waste_basket\"" }, "geometry": { "type": "Point", "coordinates": [ -6.4350441, 54.4180279 ] } },
{ "type": "Feature", "properties": { "osm_id": "5263673021", "name": "Tandragee Amenity Centre", "other_tags": "\"amenity\"=>\"recycling\"" }, "geometry": { "type": "Point", "coordinates": [ -6.411851, 54.353822 ] } },
{ "type": "Feature", "properties": { "osm_id": "8075554643", "other_tags": "\"amenity\"=>\"waste_basket\",\"waste\"=>\"dog_excrement\"" }, "geometry": { "type": "Point", "coordinates": [ -6.4565045, 54.4189291 ] } }
]
}
