{
"type": "FeatureCollection",
"name": "points",
"crs": { "type": "name", "properties": { "name": "urn:ogc:def:crs:OGC:1.3:CRS84" } },
"features": [
{ "type": "Feature", "properties": { "osm_id": "3602714063", "name": "Recycling Centre", "other_tags": "\"amenity\"=>\"recycling\"" }, "geometry": { "type": "Point", "coordinates": [ -7.4861371, 54.8095028 ] } },
{ "type": "Feature", "properties": { "osm_id": "4998642352", "other_tags": "\"amenity\"=>\"recycling\",\"recycling_type\"=>\"centre\"" }, "geometry": { "type": "Point", "coordinates": [ -7.3154327, 54.8725587 ] } },
{ "type": "Feature", "properties": { "osm_id": "6805645041", "other_tags": "\"amenity\"=>\"waste_basket\"" }, "geometry": { "type": "Point", "coordinates": [ -7.5877062, 54.7065666 ] } },
{ "type": "Feature", "properties": { "osm_id": "7091738002", "other_tags": "\"amenity\"=>\"waste_basket\",\"material\"=>\"steel\",\"waste\"=>\"mixed\"" }, "geometry": { "type": "Point", "coordinates": [ -7.1544618, 54.9119082 ] } },
{ "type": "Feature", "properties": { "osm_id": "7289660755", "other_tags": "\"amenity\"=>\"waste_basket\"" }, "geometry": { "type": "Point", "coordinates": [ -7.2794918, 55.0050408 ] } }
]
}
