{
"type": "FeatureCollection",
"name": "points",
"crs": { "type": "name", "properties": { "name": "urn:ogc:def:crs:OGC:1.3:CRS84" } },
"features": [
{ "type": "Feature", "properties": { "osm_id": "283656856", "other_tags": "\"amenity\"=>\"recycling\"" }, "geometry": { "type": "Point", "coordinates": [ -2.8739985, 56.4679254 ] } },
{ "type": "Feature", "properties": { "osm_id": "283656890", "other_tags": "\"amenity\"=>\"recycling\"" }, "geometry": { "type": "Point", "coordinates": [ -2.8580769, 56.4747144 ] } },
{ "type": "Feature", "properties": { "osm_id": "830511628", "other_tags": "\"amenity\"=>\"recycling\",\"recycling_type\"=>\"container\",\"recycling:glass\"=>\"yes\"" }, "geometry": { "type": "Point", "coordinates": [ -2.95839, 56.4613784 ] } },
{ "type": "Feature", "properties": { "osm_id": "830511653", "other_tags": "\"amenity\"=>\"recycling\",\"recycling_type\"=>\"container\",\"recycling:glass\"=>\"yes\"" }, "geometry": { "type": "Point", "coordinates": [ -2.9551883, 56.4621987 ] } },
{ "type": "Feature", "properties": { "osm_id": "1015850662", "other_tags": "\"amenity\"=>\"recycling\"" }, "geometry": { "type": "Point", "coordinates": [ -3.0405494, 56.4540757 ] } },
{ "type": "Feature", "properties": { "osm_id": "1273268915", "other_tags": "\"amenity\"=>\"recycling\"" }, "geometry": { "type": "Point", "coordinates": [ -2.9489196, 56.4832812 ] } },
{ "type": "Feature", "properties": { "osm_id": "3693354116", "other_tags": "\"amenity\"=>\"recycling\",\"recycling_type\"=>\"container\",\"recycling:glass\"=>\"yes\"" }, "geometry": { "type": "Point", "coordinates": [ -2.9912082, 56.4600594 ] } },
{ "type": "Feature", "properties": { "osm_id": "4092694234", "other_tags": "\"amenity\"=>\"recycling\",\"recycling:cds\"=>\"no\",\"recycling:cans\"=>\"yes\",\"recycling_type\"=>\"container\",\"recycling:glass\"=>\"yes\",\"recycling:metal\"=>\"no\",\"recycling:paper\"=>\"yes\",\"recycling:clothes\"=>\"no\",\"recycling:organic\"=>\"no\",\"recycling:plastic\"=>\"yes\",\"recycling:batteries\"=>\"no\",\"recycling:cardboard\"=>\"yes\",\"recycling:computers\"=>\"no\",\"recycling:electrical_appliances\"=>\"no\"" }, "geometry": { "type": "Point", "coordinates": [ -2.9865909, 56.4526036 ] } },
{ "type": "Feature", "properties": { "osm_id": "4463712237", "other_tags": "\"amenity\"=>\"recycling\",\"opening_hours\"=>\"24\/7\",\"recycling_type\"=>\"container\",\"recycling:glass_bottles\"=>\"yes\"" }, "geometry": { "type": "Point", "coordinates": [ -2.9998212, 56.4654096 ] } },
{ "type": "Feature", "properties": { "osm_id": "4721039378", "other_tags": "\"amenity\"=>\"recycling\",\"opening_hours\"=>\"24\/7\",\"recycling_type\"=>\"container\",\"recycling:paper\"=>\"yes\",\"recycling:shoes\"=>\"yes\",\"recycling:clothes\"=>\"yes\",\"recycling:glass_bottles\"=>\"yes\",\"recycling:plastic_bottles\"=>\"yes\",\"recycling:plastic_packaging\"=>\"yes\"" }, "geometry": { "type": "Point", "coordinates": [ -2.9788348, 56.4536322 ] } },
{ "type": "Feature", "properties": { "osm_id": "4771344062", "other_tags": "\"amenity\"=>\"recycling\",\"opening_hours\"=>\"24\/7\",\"recycling_type\"=>\"container\",\"recycling:clothes\"=>\"yes\",\"recycling:glass_bottles\"=>\"yes\"" }, "geometry": { "type": "Point", "coordinates": [ -2.9301565, 56.4730468 ] } },
{ "type": "Feature", "properties": { "osm_id": "4967031064", "other_tags": "\"amenity\"=>\"recycling\",\"recycling_type\"=>\"container\",\"recycling:glass\"=>\"yes\"" }, "geometry": { "type": "Point", "coordinates": [ -2.9754863, 56.4683093 ] } },
{ "type": "Feature", "properties": { "osm_id": "4967031065", "other_tags": "\"amenity\"=>\"recycling\",\"recycling_type\"=>\"container\",\"recycling:glass\"=>\"yes\"" }, "geometry": { "type": "Point", "coordinates": [ -2.9801909, 56.4710132 ] } },
{ "type": "Feature", "properties": { "osm_id": "7982497152", "other_tags": "\"amenity\"=>\"recycling\",\"recycling:glass\"=>\"yes\",\"recycling_type\"=>\"container\"" }, "geometry": { "type": "Point", "coordinates": [ -2.9934733, 56.46212 ] } }
]
}
