{
"type": "FeatureCollection",
"name": "points",
"crs": { "type": "name", "properties": { "name": "urn:ogc:def:crs:OGC:1.3:CRS84" } },
"features": [
{ "type": "Feature", "properties": { "osm_id": "272781051", "other_tags": "\"amenity\"=>\"recycling\"" }, "geometry": { "type": "Point", "coordinates": [ -3.4465644, 51.4622443 ] } },
{ "type": "Feature", "properties": { "osm_id": "472088748", "name": "Tesco Public Recycling Facility", "other_tags": "\"amenity\"=>\"recycling\"" }, "geometry": { "type": "Point", "coordinates": [ -3.2902718, 51.4148701 ] } },
{ "type": "Feature", "properties": { "osm_id": "529452422", "other_tags": "\"amenity\"=>\"recycling\"" }, "geometry": { "type": "Point", "coordinates": [ -3.5067588, 51.4335048 ] } },
{ "type": "Feature", "properties": { "osm_id": "1165768694", "other_tags": "\"amenity\"=>\"recycling\"" }, "geometry": { "type": "Point", "coordinates": [ -3.2705891, 51.4015846 ] } },
{ "type": "Feature", "properties": { "osm_id": "3902347554", "other_tags": "\"waste\"=>\"trash\",\"amenity\"=>\"waste_basket\"" }, "geometry": { "type": "Point", "coordinates": [ -3.4849485, 51.406144 ] } },
{ "type": "Feature", "properties": { "osm_id": "5696836331", "other_tags": "\"amenity\"=>\"recycling\"" }, "geometry": { "type": "Point", "coordinates": [ -3.2781504, 51.3959274 ] } },
{ "type": "Feature", "properties": { "osm_id": "6023559561", "other_tags": "\"waste\"=>\"trash\",\"amenity\"=>\"waste_basket\"" }, "geometry": { "type": "Point", "coordinates": [ -3.4846011, 51.4085116 ] } },
{ "type": "Feature", "properties": { "osm_id": "6047245496", "other_tags": "\"waste\"=>\"dog_excrement\",\"amenity\"=>\"waste_basket\"" }, "geometry": { "type": "Point", "coordinates": [ -3.4788394, 51.4077696 ] } },
{ "type": "Feature", "properties": { "osm_id": "6164236511", "other_tags": "\"amenity\"=>\"waste_basket\"" }, "geometry": { "type": "Point", "coordinates": [ -3.4848597, 51.401121 ] } },
{ "type": "Feature", "properties": { "osm_id": "6501180165", "other_tags": "\"amenity\"=>\"recycling\",\"recycling_type\"=>\"container\",\"recycling:shoes\"=>\"yes\",\"recycling:clothes\"=>\"yes\"" }, "geometry": { "type": "Point", "coordinates": [ -3.4522685, 51.4616295 ] } },
{ "type": "Feature", "properties": { "osm_id": "7004100377", "other_tags": "\"waste\"=>\"trash\",\"amenity\"=>\"waste_basket\"" }, "geometry": { "type": "Point", "coordinates": [ -3.4793692, 51.4067819 ] } },
{ "type": "Feature", "properties": { "osm_id": "7004100378", "other_tags": "\"waste\"=>\"trash\",\"amenity\"=>\"waste_basket\"" }, "geometry": { "type": "Point", "coordinates": [ -3.479396, 51.4067016 ] } },
{ "type": "Feature", "properties": { "osm_id": "7004100379", "other_tags": "\"waste\"=>\"dog_excrement\",\"amenity\"=>\"waste_basket\"" }, "geometry": { "type": "Point", "coordinates": [ -3.4790937, 51.4062909 ] } },
{ "type": "Feature", "properties": { "osm_id": "7004100380", "other_tags": "\"waste\"=>\"trash\",\"amenity\"=>\"waste_basket\"" }, "geometry": { "type": "Point", "coordinates": [ -3.4765421, 51.4071366 ] } },
{ "type": "Feature", "properties": { "osm_id": "7004387166", "other_tags": "\"waste\"=>\"trash\",\"amenity\"=>\"waste_basket\"" }, "geometry": { "type": "Point", "coordinates": [ -3.4814738, 51.4082805 ] } },
{ "type": "Feature", "properties": { "osm_id": "7004387167", "other_tags": "\"amenity\"=>\"waste_basket\"" }, "geometry": { "type": "Point", "coordinates": [ -3.4810419, 51.4082246 ] } },
{ "type": "Feature", "properties": { "osm_id": "7004387168", "other_tags": "\"waste\"=>\"trash\",\"amenity\"=>\"waste_basket\"" }, "geometry": { "type": "Point", "coordinates": [ -3.4818316, 51.408309 ] } },
{ "type": "Feature", "properties": { "osm_id": "7004387169", "other_tags": "\"waste\"=>\"trash\",\"amenity\"=>\"waste_basket\"" }, "geometry": { "type": "Point", "coordinates": [ -3.4847981, 51.4068542 ] } },
{ "type": "Feature", "properties": { "osm_id": "7004387170", "other_tags": "\"waste\"=>\"trash\",\"amenity\"=>\"waste_basket\"" }, "geometry": { "type": "Point", "coordinates": [ -3.4853303, 51.4051564 ] } },
{ "type": "Feature", "properties": { "osm_id": "7004387171", "other_tags": "\"waste\"=>\"dog_excrement\",\"amenity\"=>\"waste_basket\"" }, "geometry": { "type": "Point", "coordinates": [ -3.4851146, 51.4020378 ] } },
{ "type": "Feature", "properties": { "osm_id": "7004387172", "other_tags": "\"amenity\"=>\"waste_basket\"" }, "geometry": { "type": "Point", "coordinates": [ -3.4851683, 51.4021316 ] } },
{ "type": "Feature", "properties": { "osm_id": "7004387173", "other_tags": "\"waste\"=>\"trash\",\"amenity\"=>\"waste_basket\"" }, "geometry": { "type": "Point", "coordinates": [ -3.4788704, 51.4023499 ] } }
]
}
