{
"type": "FeatureCollection",
"name": "points",
"crs": { "type": "name", "properties": { "name": "urn:ogc:def:crs:OGC:1.3:CRS84" } },
"features": [
{ "type": "Feature", "properties": { "osm_id": "346127641", "other_tags": "\"amenity\"=>\"recycling\"" }, "geometry": { "type": "Point", "coordinates": [ -3.8240826, 51.6302873 ] } },
{ "type": "Feature", "properties": { "osm_id": "1172839400", "other_tags": "\"amenity\"=>\"recycling\"" }, "geometry": { "type": "Point", "coordinates": [ -3.6521174, 51.650999 ] } },
{ "type": "Feature", "properties": { "osm_id": "1706238741", "other_tags": "\"amenity\"=>\"waste_basket\"" }, "geometry": { "type": "Point", "coordinates": [ -3.8484626, 51.6252765 ] } },
{ "type": "Feature", "properties": { "osm_id": "2326858662", "other_tags": "\"amenity\"=>\"waste_basket\"" }, "geometry": { "type": "Point", "coordinates": [ -3.6500909, 51.737595 ] } },
{ "type": "Feature", "properties": { "osm_id": "2326858663", "other_tags": "\"amenity\"=>\"waste_basket\"" }, "geometry": { "type": "Point", "coordinates": [ -3.6498899, 51.737809 ] } },
{ "type": "Feature", "properties": { "osm_id": "3535386287", "other_tags": "\"amenity\"=>\"recycling\"" }, "geometry": { "type": "Point", "coordinates": [ -3.8861115, 51.6230195 ] } }
]
}
