{
"type": "FeatureCollection",
"features": [
	{"geometry":{"coordinates":[-52.802501,-28.946275],"type":"Point"},"properties":{"name":"Cerejeira","osm_id":"5229127356","tag":{"leaf_cycle":"semi_deciduous","leaf_type":"needleleaved","natural":"tree"}},"type":"Feature"}
]
}
