{
"type": "FeatureCollection",
"features": [
	{"geometry":{"coordinates":[-105.074352,40.167032],"type":"Point"},"properties":{"osm_id":"5129570894","tag":{"amenity":"waste_basket"}},"type":"Feature"},
	{"geometry":{"coordinates":[-105.077958,40.167019],"type":"Point"},"properties":{"osm_id":"5129570895","tag":{"amenity":"waste_basket"}},"type":"Feature"},
	{"geometry":{"coordinates":[-105.079451,40.167366],"type":"Point"},"properties":{"osm_id":"5129570896","tag":{"amenity":"waste_basket"}},"type":"Feature"},
	{"geometry":{"coordinates":[-105.079501,40.167398],"type":"Point"},"properties":{"osm_id":"5129570897","tag":{"amenity":"waste_basket"}},"type":"Feature"},
	{"geometry":{"coordinates":[-105.080604,40.168564],"type":"Point"},"properties":{"osm_id":"5129570903","tag":{"amenity":"waste_basket"}},"type":"Feature"},
	{"geometry":{"coordinates":[-105.079332,40.170713],"type":"Point"},"properties":{"osm_id":"5129570904","tag":{"amenity":"waste_basket"}},"type":"Feature"},
	{"geometry":{"coordinates":[-105.081961,40.17387],"type":"Point"},"properties":{"osm_id":"5129570908","tag":{"amenity":"waste_basket"}},"type":"Feature"},
	{"geometry":{"coordinates":[-105.082908,40.174131],"type":"Point"},"properties":{"osm_id":"5129570909","tag":{"amenity":"waste_basket"}},"type":"Feature"},
	{"geometry":{"coordinates":[-105.074632,40.163534],"type":"Point"},"properties":{"osm_id":"5129571424","tag":{"amenity":"waste_basket"}},"type":"Feature"},
	{"geometry":{"coordinates":[-105.079512,40.167168],"type":"Point"},"properties":{"osm_id":"5129586935","tag":{"amenity":"waste_basket"}},"type":"Feature"},
	{"geometry":{"coordinates":[-105.045034,40.145154],"type":"Point"},"properties":{"osm_id":"6789515908","tag":{"amenity":"waste_basket"}},"type":"Feature"},
	{"geometry":{"coordinates":[-105.039588,40.147869],"type":"Point"},"properties":{"osm_id":"6789515922","tag":{"amenity":"waste_basket"}},"type":"Feature"},
	{"geometry":{"coordinates":[-105.076412,40.157868],"type":"Point"},"properties":{"name":"G & M Disposal","osm_id":"7499435461","tag":{"addr:city":"Longmont","addr:housenumber":"10100","addr:postcode":"80501","addr:state":"CO","addr:street":"North 119th Street","amenity":"recycling","recycling_type":"centre"}},"type":"Feature"}
]
}
