{
"type": "FeatureCollection",
"features": [
	{"geometry":{"coordinates":[-105.074352,40.167032],"type":"Point"},"properties":{"osm_id":"5129570894","tag":{"amenity":"waste_basket"}},"type":"Feature"},
	{"geometry":{"coordinates":[-105.077959,40.16702],"type":"Point"},"properties":{"osm_id":"5129570895","tag":{"amenity":"waste_basket"}},"type":"Feature"},
	{"geometry":{"coordinates":[-105.079452,40.167367],"type":"Point"},"properties":{"osm_id":"5129570896","tag":{"amenity":"waste_basket"}},"type":"Feature"},
	{"geometry":{"coordinates":[-105.079502,40.167398],"type":"Point"},"properties":{"osm_id":"5129570897","tag":{"amenity":"waste_basket"}},"type":"Feature"},
	{"geometry":{"coordinates":[-105.080605,40.168565],"type":"Point"},"properties":{"osm_id":"5129570903","tag":{"amenity":"waste_basket"}},"type":"Feature"},
	{"geometry":{"coordinates":[-105.079332,40.170713],"type":"Point"},"properties":{"osm_id":"5129570904","tag":{"amenity":"waste_basket"}},"type":"Feature"},
	{"geometry":{"coordinates":[-105.081962,40.17387],"type":"Point"},"properties":{"osm_id":"5129570908","tag":{"amenity":"waste_basket"}},"type":"Feature"},
	{"geometry":{"coordinates":[-105.082909,40.174132],"type":"Point"},"properties":{"osm_id":"5129570909","tag":{"amenity":"waste_basket"}},"type":"Feature"},
	{"geometry":{"coordinates":[-105.074633,40.163534],"type":"Point"},"properties":{"osm_id":"5129571424","tag":{"amenity":"waste_basket"}},"type":"Feature"},
	{"geometry":{"coordinates":[-105.079512,40.167169],"type":"Point"},"properties":{"osm_id":"5129586935","tag":{"amenity":"waste_basket"}},"type":"Feature"},
	{"geometry":{"coordinates":[-105.045035,40.145154],"type":"Point"},"properties":{"osm_id":"6789515908","tag":{"amenity":"waste_basket"}},"type":"Feature"},
	{"geometry":{"coordinates":[-105.039589,40.14787],"type":"Point"},"properties":{"osm_id":"6789515922","tag":{"amenity":"waste_basket"}},"type":"Feature"},
	{"geometry":{"coordinates":[-105.076413,40.157868],"type":"Point"},"properties":{"name":"G & M Disposal","osm_id":"7499435461","tag":{"addr:city":"Longmont","addr:housenumber":"10100","addr:postcode":"80501","addr:state":"CO","addr:street":"North 119th Street","amenity":"recycling","recycling_type":"centre"}},"type":"Feature"}
]
}
