{
"type": "FeatureCollection",
"features": [
	{"geometry":{"coordinates":[-89.343776,43.02761],"type":"Point"},"properties":{"name":"200 Year Oak","osm_id":"6290118218","tag":{"denotation":"landmark","leaf_cycle":"deciduous","natural":"tree"}},"type":"Feature"},
	{"geometry":{"coordinates":[-89.33243,43.030884],"type":"Point"},"properties":{"osm_id":"6596372251","tag":{"natural":"tree"}},"type":"Feature"},
	{"geometry":{"coordinates":[-89.332633,43.030643],"type":"Point"},"properties":{"osm_id":"6596372252","tag":{"natural":"tree"}},"type":"Feature"}
]
}
