{
"type": "FeatureCollection",
"features": [
	{"geometry":{"coordinates":[-1.248934,39.262389],"type":"Point"},"properties":{"name":"Olmo de Cantoblanco","osm_id":"7416941697","tag":{"denotation":"single","natural":"tree"}},"type":"Feature"}
]
}
