{
"type": "FeatureCollection",
"features": [
	{"geometry":{"coordinates":[-1.295988,38.955435],"type":"Point"},"properties":{"name":"Carrasca Gorda","osm_id":"7417269103","tag":{"denotation":"single","natural":"tree"}},"type":"Feature"}
]
}
