{
"type": "FeatureCollection",
"features": [
	{"geometry":{"coordinates":[177.718496,-38.561546],"type":"Point"},"properties":{"name":"Eastwoodhill Arboretum","osm_id":"5101665145","tag":{"addr:housenumber":"2392","addr:street":"2392 Wharekopae Rd, RD2 Ngatapa, Gisborne 4072","description":"National Arboretum of New Zealand","natural":"tree","opening_hours":"Mo-Su 09:00-16:00","phone":"+64 6 863 9003","website":"http://www.eastwoodhill.org.nz"}},"type":"Feature"}
]
}
