{
"type": "FeatureCollection",
"features": [
	{"geometry":{"coordinates":[-4.147821,55.761948],"type":"Point"},"properties":{"osm_id":"4712564600","tag":{"natural":"tree"}},"type":"Feature"},
	{"geometry":{"coordinates":[-4.147581,55.761948],"type":"Point"},"properties":{"osm_id":"4712564601","tag":{"natural":"tree"}},"type":"Feature"},
	{"geometry":{"coordinates":[-4.147165,55.761881],"type":"Point"},"properties":{"osm_id":"4712564602","tag":{"natural":"tree"}},"type":"Feature"},
	{"geometry":{"coordinates":[-4.147283,55.761981],"type":"Point"},"properties":{"osm_id":"4712564603","tag":{"natural":"tree"}},"type":"Feature"},
	{"geometry":{"coordinates":[-4.147379,55.761977],"type":"Point"},"properties":{"osm_id":"4712564604","tag":{"natural":"tree"}},"type":"Feature"},
	{"geometry":{"coordinates":[-4.147548,55.762061],"type":"Point"},"properties":{"osm_id":"4712564605","tag":{"natural":"tree"}},"type":"Feature"},
	{"geometry":{"coordinates":[-4.148307,55.761906],"type":"Point"},"properties":{"osm_id":"4712564606","tag":{"natural":"tree"}},"type":"Feature"},
	{"geometry":{"coordinates":[-4.148983,55.761716],"type":"Point"},"properties":{"osm_id":"4712564607","tag":{"natural":"tree"}},"type":"Feature"},
	{"geometry":{"coordinates":[-4.171593,55.758342],"type":"Point"},"properties":{"osm_id":"8072617850","tag":{"natural":"tree"}},"type":"Feature"},
	{"geometry":{"coordinates":[-4.137855,55.768714],"type":"Point"},"properties":{"name":"Four Oaks","osm_id":"8613723119","tag":{"leaf_type":"broadleaved","natural":"tree"}},"type":"Feature"},
	{"geometry":{"coordinates":[-4.207286,55.762898],"type":"Point"},"properties":{"osm_id":"8910609321","tag":{"natural":"tree"}},"type":"Feature"},
	{"geometry":{"coordinates":[-4.209854,55.756647],"type":"Point"},"properties":{"osm_id":"8936249663","tag":{"natural":"tree"}},"type":"Feature"},
	{"geometry":{"coordinates":[-4.209698,55.756991],"type":"Point"},"properties":{"osm_id":"8936249664","tag":{"natural":"tree"}},"type":"Feature"},
	{"geometry":{"coordinates":[-4.208645,55.756994],"type":"Point"},"properties":{"osm_id":"8936249665","tag":{"natural":"tree"}},"type":"Feature"},
	{"geometry":{"coordinates":[-4.209493,55.757374],"type":"Point"},"properties":{"osm_id":"8936249666","tag":{"natural":"tree"}},"type":"Feature"},
	{"geometry":{"coordinates":[-4.208161,55.757673],"type":"Point"},"properties":{"osm_id":"8936249667","tag":{"natural":"tree"}},"type":"Feature"},
	{"geometry":{"coordinates":[-4.186778,55.758959],"type":"Point"},"properties":{"osm_id":"9117226288","tag":{"natural":"tree"}},"type":"Feature"},
	{"geometry":{"coordinates":[-4.186715,55.759029],"type":"Point"},"properties":{"osm_id":"9117226289","tag":{"natural":"tree"}},"type":"Feature"},
	{"geometry":{"coordinates":[-4.186523,55.759156],"type":"Point"},"properties":{"osm_id":"9117226290","tag":{"natural":"tree"}},"type":"Feature"},
	{"geometry":{"coordinates":[-4.186465,55.759214],"type":"Point"},"properties":{"osm_id":"9117226291","tag":{"natural":"tree"}},"type":"Feature"},
	{"geometry":{"coordinates":[-4.186483,55.759186],"type":"Point"},"properties":{"osm_id":"9117226312","tag":{"natural":"tree"}},"type":"Feature"},
	{"geometry":{"coordinates":[-4.184777,55.75909],"type":"Point"},"properties":{"osm_id":"9117226327","tag":{"natural":"tree"}},"type":"Feature"},
	{"geometry":{"coordinates":[-4.185442,55.759244],"type":"Point"},"properties":{"osm_id":"9117226357","tag":{"natural":"tree"}},"type":"Feature"},
	{"geometry":{"coordinates":[-4.185378,55.759237],"type":"Point"},"properties":{"osm_id":"9117226358","tag":{"natural":"tree"}},"type":"Feature"},
	{"geometry":{"coordinates":[-4.185168,55.759316],"type":"Point"},"properties":{"osm_id":"9117226359","tag":{"natural":"tree"}},"type":"Feature"},
	{"geometry":{"coordinates":[-4.185186,55.759352],"type":"Point"},"properties":{"osm_id":"9117226360","tag":{"natural":"tree"}},"type":"Feature"},
	{"geometry":{"coordinates":[-4.185219,55.759378],"type":"Point"},"properties":{"osm_id":"9117226361","tag":{"natural":"tree"}},"type":"Feature"}
]
}
