{
"type": "FeatureCollection",
"features": [
	{"geometry":{"coordinates":[-4.147821,55.761948],"type":"Point"},"properties":{"osm_id":"4712564600","tag":{"natural":"tree"}},"type":"Feature"},
	{"geometry":{"coordinates":[-4.147581,55.761948],"type":"Point"},"properties":{"osm_id":"4712564601","tag":{"natural":"tree"}},"type":"Feature"},
	{"geometry":{"coordinates":[-4.147165,55.761881],"type":"Point"},"properties":{"osm_id":"4712564602","tag":{"natural":"tree"}},"type":"Feature"},
	{"geometry":{"coordinates":[-4.147283,55.761981],"type":"Point"},"properties":{"osm_id":"4712564603","tag":{"natural":"tree"}},"type":"Feature"},
	{"geometry":{"coordinates":[-4.147379,55.761977],"type":"Point"},"properties":{"osm_id":"4712564604","tag":{"natural":"tree"}},"type":"Feature"},
	{"geometry":{"coordinates":[-4.147548,55.762061],"type":"Point"},"properties":{"osm_id":"4712564605","tag":{"natural":"tree"}},"type":"Feature"},
	{"geometry":{"coordinates":[-4.148307,55.761906],"type":"Point"},"properties":{"osm_id":"4712564606","tag":{"natural":"tree"}},"type":"Feature"},
	{"geometry":{"coordinates":[-4.148983,55.761716],"type":"Point"},"properties":{"osm_id":"4712564607","tag":{"natural":"tree"}},"type":"Feature"},
	{"geometry":{"coordinates":[-4.171593,55.758342],"type":"Point"},"properties":{"osm_id":"8072617850","tag":{"natural":"tree"}},"type":"Feature"},
	{"geometry":{"coordinates":[-4.137855,55.768714],"type":"Point"},"properties":{"name":"Four Oaks","osm_id":"8613723119","tag":{"leaf_type":"broadleaved","natural":"tree"}},"type":"Feature"},
	{"geometry":{"coordinates":[-4.207286,55.762898],"type":"Point"},"properties":{"osm_id":"8910609321","tag":{"natural":"tree"}},"type":"Feature"},
	{"geometry":{"coordinates":[-4.209854,55.756647],"type":"Point"},"properties":{"osm_id":"8936249663","tag":{"natural":"tree"}},"type":"Feature"},
	{"geometry":{"coordinates":[-4.209698,55.756991],"type":"Point"},"properties":{"osm_id":"8936249664","tag":{"natural":"tree"}},"type":"Feature"},
	{"geometry":{"coordinates":[-4.208645,55.756994],"type":"Point"},"properties":{"osm_id":"8936249665","tag":{"natural":"tree"}},"type":"Feature"},
	{"geometry":{"coordinates":[-4.209493,55.757374],"type":"Point"},"properties":{"osm_id":"8936249666","tag":{"natural":"tree"}},"type":"Feature"},
	{"geometry":{"coordinates":[-4.208161,55.757673],"type":"Point"},"properties":{"osm_id":"8936249667","tag":{"natural":"tree"}},"type":"Feature"}
]
}
