{
"type": "FeatureCollection",
"lastupdate": "2020-08-06T00:00:00Z",
"features": [
	{"geometry":{"coordinates":[5.922996,52.964528],"type":"Point"},"properties":{"osm_id":"2477328111","tag":{"amenity":"recycling","recycling_type":"container"}},"type":"Feature"},
	{"geometry":{"coordinates":[5.889992,52.9758],"type":"Point"},"properties":{"name":"Afvalbrengstation Heerenveen Omrin","osm_id":"2926093634","tag":{"addr:city":"Heerenveen","addr:housenumber":"10","addr:postcode":"8447GM","addr:street":"De Ynfeart","amenity":"recycling","opening_hours":"Mo-Fr 09:00-16:30; Sa 10:00-16:00","recycling_type":"centre","source:date":"2014-06-21","website":"https://www.omrin.nl/bij-mij-thuis/services/op-de-kaart/milieustraten/heerenveen"}},"type":"Feature"},
	{"geometry":{"coordinates":[5.898201,52.961977],"type":"Point"},"properties":{"osm_id":"3696013255","tag":{"amenity":"waste_basket"}},"type":"Feature"},
	{"geometry":{"coordinates":[5.973844,52.96807],"type":"Point"},"properties":{"osm_id":"5046803223","tag":{"amenity":"recycling","recycling:glass":"yes","recycling:paper":"yes","recycling_type":"container"}},"type":"Feature"}
]
}
