{
"type": "FeatureCollection",
"features": [
	{"geometry":{"coordinates":[5.923107,45.266863],"type":"Point"},"properties":{"osm_id":"614857240","tag":{"amenity":"recycling","recycling:glass_bottles":"yes","recycling_type":"container"}},"type":"Feature"},
	{"geometry":{"coordinates":[5.909388,45.258318],"type":"Point"},"properties":{"osm_id":"648531069","tag":{"amenity":"recycling","location":"overground","recycling:glass":"yes","recycling_type":"container"}},"type":"Feature"},
	{"geometry":{"coordinates":[5.925787,45.252439],"type":"Point"},"properties":{"osm_id":"648531072","tag":{"amenity":"recycling","recycling:glass":"yes"}},"type":"Feature"},
	{"geometry":{"coordinates":[5.968844,45.269505],"type":"Point"},"properties":{"osm_id":"945749482","tag":{"amenity":"recycling","recycling:beverage_cartons":"yes","recycling:books":"yes","recycling:cans":"yes","recycling:cardboard":"yes","recycling:cartons":"yes","recycling:glass":"yes","recycling:glass_bottles":"yes","recycling:magazines":"yes","recycling:newspaper":"yes","recycling:paper":"yes","recycling:paper_packaging":"yes","recycling:plastic":"yes","recycling:plastic_bottles":"yes","recycling:plastic_packaging":"yes","recycling:waste":"yes"}},"type":"Feature"},
	{"geometry":{"coordinates":[5.975893,45.273409],"type":"Point"},"properties":{"osm_id":"945749655","tag":{"amenity":"recycling"}},"type":"Feature"},
	{"geometry":{"coordinates":[5.966802,45.272332],"type":"Point"},"properties":{"osm_id":"1725485393","tag":{"amenity":"recycling","recycling:beverage_cartons":"yes","recycling:cans":"yes","recycling:plastic":"yes","recycling:plastic_bottles":"yes","recycling:plastic_packaging":"yes","recycling:waste":"yes"}},"type":"Feature"},
	{"geometry":{"coordinates":[5.901721,45.272022],"type":"Point"},"properties":{"osm_id":"1737421783","tag":{"amenity":"recycling","recycling_type":"container"}},"type":"Feature"},
	{"geometry":{"coordinates":[5.901927,45.272599],"type":"Point"},"properties":{"osm_id":"1737421793","tag":{"amenity":"recycling","recycling_type":"container"}},"type":"Feature"},
	{"geometry":{"coordinates":[5.966773,45.272892],"type":"Point"},"properties":{"osm_id":"1753804321","tag":{"amenity":"recycling","recycling:beverage_cartons":"yes","recycling:books":"yes","recycling:cans":"yes","recycling:cardboard":"yes","recycling:cartons":"yes","recycling:clothes":"no","recycling:glass":"yes","recycling:glass_bottles":"yes","recycling:magazines":"yes","recycling:newspaper":"yes","recycling:paper":"yes","recycling:paper_packaging":"yes","recycling:plastic":"yes","recycling:plastic_bottles":"yes","recycling:plastic_packaging":"yes","recycling:waste":"yes","recycling_type":"container"}},"type":"Feature"},
	{"geometry":{"coordinates":[5.975075,45.266706],"type":"Point"},"properties":{"osm_id":"1753809538","tag":{"amenity":"recycling"}},"type":"Feature"},
	{"geometry":{"coordinates":[5.964976,45.269615],"type":"Point"},"properties":{"osm_id":"3043844726","tag":{"amenity":"recycling","recycling:aluminium":"yes","recycling:beverage_cartons":"yes","recycling:books":"yes","recycling:cans":"yes","recycling:cardboard":"yes","recycling:cartons":"yes","recycling:glass":"yes","recycling:glass_bottles":"yes","recycling:magazines":"yes","recycling:newspaper":"yes","recycling:paper":"yes","recycling:paper_packaging":"yes","recycling:plastic":"yes","recycling:plastic_bottles":"yes","recycling:plastic_packaging":"yes","recycling:waste":"yes","recycling_type":"container"}},"type":"Feature"},
	{"geometry":{"coordinates":[5.940791,45.23499],"type":"Point"},"properties":{"osm_id":"7108902313","tag":{"amenity":"recycling","recycling:cans":"yes","recycling:glass_bottles":"yes","recycling:paper":"yes","recycling:plastic_bottles":"yes","recycling:plastic_packaging":"yes","recycling_type":"container"}},"type":"Feature"},
	{"geometry":{"coordinates":[5.901259,45.262389],"type":"Point"},"properties":{"osm_id":"8360900592","tag":{"amenity":"waste_basket"}},"type":"Feature"},
	{"geometry":{"coordinates":[5.901524,45.262269],"type":"Point"},"properties":{"osm_id":"8360908028","tag":{"amenity":"recycling"}},"type":"Feature"},
	{"geometry":{"coordinates":[5.900034,45.251401],"type":"Point"},"properties":{"osm_id":"8837818016","tag":{"amenity":"recycling","location":"overground","recycling:cans":"yes","recycling:glass_bottles":"yes","recycling:paper":"yes","recycling:plastic":"yes","recycling_type":"container"}},"type":"Feature"},
	{"geometry":{"coordinates":[5.903313,45.261799],"type":"Point"},"properties":{"osm_id":"9063840806","tag":{"amenity":"waste_disposal","waste":"trash;recycling;plastic;glass"}},"type":"Feature"}
]
}
