{
"type": "FeatureCollection",
"features": [
	{"geometry":{"coordinates":[38.721236,14.126353],"type":"Point"},"properties":{"osm_id":"2684429633","tag":{"natural":"tree"}},"type":"Feature"},
	{"geometry":{"coordinates":[38.717144,14.129921],"type":"Point"},"properties":{"name":"Daero Ella","osm_id":"7769782889","tag":{"denotation":"religious","natural":"tree"}},"type":"Feature"}
]
}
