{
"type": "FeatureCollection",
"features": [
	{"geometry":{"coordinates":[-78.030005,41.959789],"type":"Point"},"properties":{"is_in":"Potter,Pennsylvania,Pa.,PA,USA","name":"Chrystal","osm_id":"158481352","place":"hamlet","tag":{"gnis:Class":"Populated Place","gnis:County":"Potter","gnis:County_num":"105","gnis:ST_alpha":"PA","gnis:ST_num":"42","gnis:id":"1203275","import_uuid":"bb7269ee-502a-5391-8056-e3ce0e66489c"}},"type":"Feature"}
]
}
