{
"type": "FeatureCollection",
"lastupdate": "2020-08-03T00:00:00Z",
"features": [
	{"geometry":{"coordinates":[140.128504,35.804797],"type":"Point"},"properties":{"name":"Wonder Rex (Recycle Shop)","osm_id":"5558703722","tag":{"amenity":"recycling","name:ja":"\uff37\uff4f\uff4e\uff44\uff45\uff52\uff32\uff25\uff38\u5343\u8449\u30cb\u30e5\u30fc\u30bf\u30a6\u30f3\u5e97"}},"type":"Feature"}
]
}
