{
"type": "FeatureCollection",
"features": [
	{"geometry":{"coordinates":[140.128504,35.804797],"type":"Point"},"properties":{"name":"Wonder Rex (Recycle Shop)","osm_id":"5558703722","tag":{"amenity":"recycling","name:ja":"\u00ef\u00bc\u00b7\u00ef\u00bd\u008f\u00ef\u00bd\u008e\u00ef\u00bd\u0084\u00ef\u00bd\u0085\u00ef\u00bd\u0092\u00ef\u00bc\u00b2\u00ef\u00bc\u00a5\u00ef\u00bc\u00b8\u00e5\u008d\u0083\u00e8\u0091\u0089\u00e3\u0083\u008b\u00e3\u0083\u00a5\u00e3\u0083\u00bc\u00e3\u0082\u00bf\u00e3\u0082\u00a6\u00e3\u0083\u00b3\u00e5\u00ba\u0097"}},"type":"Feature"}
]
}
