{
"type": "FeatureCollection",
"features": [
	{"geometry":{"coordinates":[23.105773,51.522362],"type":"Point"},"properties":{"name":"Tadeusz i Ludwika","osm_id":"2836760083","tag":{"addr:city":"Sosnowica","addr:postcode":"21-230","addr:street":"Aleja Kasztanowa","natural":"tree","tourism":"attraction"}},"type":"Feature"}
]
}
