{
"type": "FeatureCollection",
"features": [
	{"geometry":{"coordinates":[23.053871,51.119924],"type":"Point"},"properties":{"name":"Gniewomir","osm_id":"6604980338","tag":{"circumference":"3.6","natural":"tree"}},"type":"Feature"}
]
}
