{
"type": "FeatureCollection",
"features": [
	{"geometry":{"coordinates":[23.075792,50.29549],"type":"Point"},"properties":{"osm_id":"2287245792","tag":{"natural":"tree"}},"type":"Feature"},
	{"geometry":{"coordinates":[23.078081,50.289961],"type":"Point"},"properties":{"name":"Pomnik przyrody","osm_id":"4033898547","tag":{"denotation":"natural_monument","monument":"yes","natural":"tree","protected":"yes"}},"type":"Feature"}
]
}
