{
"type": "FeatureCollection",
"lastupdate": "2020-08-06T00:00:00Z",
"features": [
	{"geometry":{"coordinates":[-75.770262,40.806034],"type":"Point"},"properties":{"name":"Carbon County Recycling Center","osm_id":"5882273484","tag":{"addr:city":"Lehighton","addr:housenumber":"472","addr:postcode":"18235","addr:state":"PA","addr:street":"Seneca Road","amenity":"recycling","recycling_type":"centre"}},"type":"Feature"}
]
}
