{
"type": "FeatureCollection",
"features": [
	{"geometry":{"coordinates":[-82.391735,40.65395],"type":"Point"},"properties":{"name":"Site of the tree from the movie Shawshank Redemption, before felling.","osm_id":"5595636273","tag":{"natural":"tree","tourism":"attraction"}},"type":"Feature"}
]
}
