{
"type": "FeatureCollection",
"features": [
	{"geometry":{"coordinates":[-82.362888,34.777316],"type":"Point"},"properties":{"name":"Century Oak","osm_id":"4743910677","tag":{"leaf_type":"broadleaved","natural":"tree"}},"type":"Feature"},
	{"geometry":{"coordinates":[-82.362863,34.77741],"type":"Point"},"properties":{"name":"Century Oak","osm_id":"4743910678","tag":{"leaf_type":"broadleaved","natural":"tree"}},"type":"Feature"}
]
}
