{
"type": "FeatureCollection",
"features": [
	{"geometry":{"coordinates":[-78.267959,44.422538],"type":"Point"},"properties":{"osm_id":"913958274","tag":{"addr:city":"Township of Smith-Ennismore-Lakefield","addr:housenumber":"12","addr:street":"Charles Court"}},"type":"Feature"},
	{"geometry":{"coordinates":[-78.267428,44.422676],"type":"Point"},"properties":{"osm_id":"913960484","tag":{"addr:city":"Township of Smith-Ennismore-Lakefield","addr:housenumber":"2","addr:street":"Charles Court"}},"type":"Feature"}
]
}
