{
"type": "FeatureCollection",
"features": [
	{"geometry":{"coordinates":[-78.256947,39.198993],"type":"Point"},"properties":{"is_in":"Frederick,Virginia,Va.,VA,USA","name":"Zeiger","osm_id":"158415187","place":"hamlet","tag":{"gnis:Class":"Populated Place","gnis:County":"Frederick","gnis:County_num":"069","gnis:ST_alpha":"VA","gnis:ST_num":"51","gnis:id":"1987040","import_uuid":"bb7269ee-502a-5391-8056-e3ce0e66489c"}},"type":"Feature"}
]
}
