{
"type": "FeatureCollection",
"features": [
	{"geometry":{"coordinates":[-78.299967,35.548254],"type":"Point"},"properties":{"name":"Stericycle","osm_id":"8379904446","tag":{"amenity":"recycling","operator":"Stericycle","recycling:electrical_items":"yes","recycling_type":"container"}},"type":"Feature"}
]
}
