{
"type": "FeatureCollection",
"features": [
	{"geometry":{"coordinates":[-122.046757,47.106236],"type":"Point"},"properties":{"name":"Wilkeson Recycling Center","osm_id":"5127036022","tag":{"amenity":"recycling"}},"type":"Feature"},
	{"geometry":{"coordinates":[-122.049627,47.128477],"type":"Point"},"properties":{"osm_id":"6682398093","tag":{"amenity":"recycling","operator":"USAgain"}},"type":"Feature"}
]
}
