{
"type": "FeatureCollection",
"features": [
	{"geometry":{"coordinates":[18.135994,59.356807],"type":"Point"},"properties":{"osm_id":"1145986052","tag":{"natural":"tree"}},"type":"Feature"},
	{"geometry":{"coordinates":[18.121985,59.358806],"type":"Point"},"properties":{"osm_id":"1145986288","tag":{"natural":"tree"}},"type":"Feature"},
	{"geometry":{"coordinates":[18.122178,59.358703],"type":"Point"},"properties":{"osm_id":"1145986354","tag":{"natural":"tree"}},"type":"Feature"},
	{"geometry":{"coordinates":[18.121505,59.358854],"type":"Point"},"properties":{"osm_id":"1145986437","tag":{"natural":"tree"}},"type":"Feature"},
	{"geometry":{"coordinates":[18.122361,59.358733],"type":"Point"},"properties":{"osm_id":"1145986483","tag":{"natural":"tree"}},"type":"Feature"},
	{"geometry":{"coordinates":[18.121856,59.358728],"type":"Point"},"properties":{"osm_id":"1145986542","tag":{"natural":"tree"}},"type":"Feature"},
	{"geometry":{"coordinates":[18.121822,59.358904],"type":"Point"},"properties":{"osm_id":"1145986573","tag":{"natural":"tree"}},"type":"Feature"},
	{"geometry":{"coordinates":[18.122312,59.358848],"type":"Point"},"properties":{"osm_id":"1145986649","tag":{"natural":"tree"}},"type":"Feature"},
	{"geometry":{"coordinates":[18.121682,59.358664],"type":"Point"},"properties":{"osm_id":"1145986737","tag":{"natural":"tree"}},"type":"Feature"},
	{"geometry":{"coordinates":[18.122087,59.358767],"type":"Point"},"properties":{"osm_id":"1145986817","tag":{"natural":"tree"}},"type":"Feature"},
	{"geometry":{"coordinates":[18.155968,59.37101],"type":"Point"},"properties":{"osm_id":"2707257059","tag":{"natural":"tree"}},"type":"Feature"},
	{"geometry":{"coordinates":[18.169992,59.369658],"type":"Point"},"properties":{"osm_id":"4226875915","tag":{"natural":"tree"}},"type":"Feature"},
	{"geometry":{"coordinates":[18.192412,59.399098],"type":"Point"},"properties":{"name":"Stortallen","osm_id":"7883592938","tag":{"diameter":"121 cm","height":"30","natural":"tree"}},"type":"Feature"},
	{"geometry":{"coordinates":[18.193113,59.398829],"type":"Point"},"properties":{"name":"Stortallen","osm_id":"8495142820","tag":{"age":"350 years","circumference":"380 cm","denotation":"natural_monument","diameter_crown":"121 cm","height":"30 m","leaf_cycle":"semi_evergreen","leaf_type":"needleleaved","natural":"tree"}},"type":"Feature"}
]
}
