{
"type": "FeatureCollection",
"features": [
	{"geometry":{"coordinates":[18.135995,59.356808],"type":"Point"},"properties":{"osm_id":"1145986052","tag":{"natural":"tree"}},"type":"Feature"},
	{"geometry":{"coordinates":[18.121986,59.358806],"type":"Point"},"properties":{"osm_id":"1145986288","tag":{"natural":"tree"}},"type":"Feature"},
	{"geometry":{"coordinates":[18.122179,59.358704],"type":"Point"},"properties":{"osm_id":"1145986354","tag":{"natural":"tree"}},"type":"Feature"},
	{"geometry":{"coordinates":[18.121506,59.358854],"type":"Point"},"properties":{"osm_id":"1145986437","tag":{"natural":"tree"}},"type":"Feature"},
	{"geometry":{"coordinates":[18.122361,59.358734],"type":"Point"},"properties":{"osm_id":"1145986483","tag":{"natural":"tree"}},"type":"Feature"},
	{"geometry":{"coordinates":[18.121857,59.358728],"type":"Point"},"properties":{"osm_id":"1145986542","tag":{"natural":"tree"}},"type":"Feature"},
	{"geometry":{"coordinates":[18.121822,59.358905],"type":"Point"},"properties":{"osm_id":"1145986573","tag":{"natural":"tree"}},"type":"Feature"},
	{"geometry":{"coordinates":[18.122313,59.358849],"type":"Point"},"properties":{"osm_id":"1145986649","tag":{"natural":"tree"}},"type":"Feature"},
	{"geometry":{"coordinates":[18.121683,59.358664],"type":"Point"},"properties":{"osm_id":"1145986737","tag":{"natural":"tree"}},"type":"Feature"},
	{"geometry":{"coordinates":[18.122088,59.358768],"type":"Point"},"properties":{"osm_id":"1145986817","tag":{"natural":"tree"}},"type":"Feature"},
	{"geometry":{"coordinates":[18.155969,59.37101],"type":"Point"},"properties":{"osm_id":"2707257059","tag":{"natural":"tree"}},"type":"Feature"},
	{"geometry":{"coordinates":[18.169992,59.369658],"type":"Point"},"properties":{"osm_id":"4226875915","tag":{"natural":"tree"}},"type":"Feature"},
	{"geometry":{"coordinates":[18.192412,59.399099],"type":"Point"},"properties":{"name":"Stortallen","osm_id":"7883592938","tag":{"diameter":"121 cm","height":"30","natural":"tree"}},"type":"Feature"}
]
}
