{
"type": "FeatureCollection",
"features": [
	{"geometry":{"coordinates":[18.16836,53.64331],"type":"Point"},"properties":{"osm_id":"4706667122","tag":{"denotation":"natural_monument","natural":"tree","ref:CRFOP":"PL.ZIPOP.1393.PP.0416052.1938","ref:INSPIRE":"PL.ZIPOP.1393.PP.0416052.1938","website":"http://crfop.gdos.gov.pl/CRFOP/widok/viewfop.jsf?fop=PL.ZIPOP.1393.PP.0416052.1938"}},"type":"Feature"},
	{"geometry":{"coordinates":[18.16854,53.6434],"type":"Point"},"properties":{"osm_id":"4706667123","tag":{"denotation":"natural_monument","natural":"tree","ref:CRFOP":"PL.ZIPOP.1393.PP.0416052.1938","ref:INSPIRE":"PL.ZIPOP.1393.PP.0416052.1938","website":"http://crfop.gdos.gov.pl/CRFOP/widok/viewfop.jsf?fop=PL.ZIPOP.1393.PP.0416052.1938"}},"type":"Feature"},
	{"geometry":{"coordinates":[18.16901,53.64359],"type":"Point"},"properties":{"osm_id":"4706667124","tag":{"denotation":"natural_monument","natural":"tree","ref:CRFOP":"PL.ZIPOP.1393.PP.0416052.1938","ref:INSPIRE":"PL.ZIPOP.1393.PP.0416052.1938","website":"http://crfop.gdos.gov.pl/CRFOP/widok/viewfop.jsf?fop=PL.ZIPOP.1393.PP.0416052.1938"}},"type":"Feature"},
	{"geometry":{"coordinates":[18.16924,53.64367],"type":"Point"},"properties":{"osm_id":"4706667125","tag":{"denotation":"natural_monument","natural":"tree","ref:CRFOP":"PL.ZIPOP.1393.PP.0416052.1938","ref:INSPIRE":"PL.ZIPOP.1393.PP.0416052.1938","website":"http://crfop.gdos.gov.pl/CRFOP/widok/viewfop.jsf?fop=PL.ZIPOP.1393.PP.0416052.1938"}},"type":"Feature"},
	{"geometry":{"coordinates":[18.17034,53.64416],"type":"Point"},"properties":{"osm_id":"4706667126","tag":{"denotation":"natural_monument","natural":"tree","ref:CRFOP":"PL.ZIPOP.1393.PP.0416052.1938","ref:INSPIRE":"PL.ZIPOP.1393.PP.0416052.1938","website":"http://crfop.gdos.gov.pl/CRFOP/widok/viewfop.jsf?fop=PL.ZIPOP.1393.PP.0416052.1938"}},"type":"Feature"},
	{"geometry":{"coordinates":[18.17,53.64407],"type":"Point"},"properties":{"osm_id":"4706667127","tag":{"denotation":"natural_monument","natural":"tree","ref:CRFOP":"PL.ZIPOP.1393.PP.0416052.1938","ref:INSPIRE":"PL.ZIPOP.1393.PP.0416052.1938","website":"http://crfop.gdos.gov.pl/CRFOP/widok/viewfop.jsf?fop=PL.ZIPOP.1393.PP.0416052.1938"}},"type":"Feature"},
	{"geometry":{"coordinates":[18.16978,53.6439],"type":"Point"},"properties":{"osm_id":"4706667128","tag":{"denotation":"natural_monument","natural":"tree","ref:CRFOP":"PL.ZIPOP.1393.PP.0416052.1938","ref:INSPIRE":"PL.ZIPOP.1393.PP.0416052.1938","website":"http://crfop.gdos.gov.pl/CRFOP/widok/viewfop.jsf?fop=PL.ZIPOP.1393.PP.0416052.1938"}},"type":"Feature"},
	{"geometry":{"coordinates":[18.1711,53.596],"type":"Point"},"properties":{"osm_id":"4706668357","tag":{"denotation":"natural_monument","natural":"tree","ref:CRFOP":"PL.ZIPOP.1393.PP.0416012.285","ref:INSPIRE":"PL.ZIPOP.1393.PP.0416012.285","website":"http://crfop.gdos.gov.pl/CRFOP/widok/viewfop.jsf?fop=PL.ZIPOP.1393.PP.0416012.285"}},"type":"Feature"},
	{"geometry":{"coordinates":[18.156773,53.629243],"type":"Point"},"properties":{"osm_id":"4706668362","tag":{"denotation":"natural_monument","natural":"tree","ref:CRFOP":"PL.ZIPOP.1393.PP.0416012.280","ref:INSPIRE":"PL.ZIPOP.1393.PP.0416012.280","website":"http://crfop.gdos.gov.pl/CRFOP/widok/viewfop.jsf?fop=PL.ZIPOP.1393.PP.0416012.280"}},"type":"Feature"},
	{"geometry":{"coordinates":[18.15664,53.62905],"type":"Point"},"properties":{"osm_id":"4706668363","tag":{"denotation":"natural_monument","natural":"tree","ref:CRFOP":"PL.ZIPOP.1393.PP.0416012.279","ref:INSPIRE":"PL.ZIPOP.1393.PP.0416012.279","website":"http://crfop.gdos.gov.pl/CRFOP/widok/viewfop.jsf?fop=PL.ZIPOP.1393.PP.0416012.279"}},"type":"Feature"},
	{"geometry":{"coordinates":[18.156852,53.629323],"type":"Point"},"properties":{"osm_id":"4706668364","tag":{"denotation":"natural_monument","natural":"tree","ref:CRFOP":"PL.ZIPOP.1393.PP.0416012.278","ref:INSPIRE":"PL.ZIPOP.1393.PP.0416012.278","website":"http://crfop.gdos.gov.pl/CRFOP/widok/viewfop.jsf?fop=PL.ZIPOP.1393.PP.0416012.278"}},"type":"Feature"},
	{"geometry":{"coordinates":[18.156692,53.629146],"type":"Point"},"properties":{"osm_id":"4706668365","tag":{"denotation":"natural_monument","natural":"tree","ref:CRFOP":"PL.ZIPOP.1393.PP.0416012.277","ref:INSPIRE":"PL.ZIPOP.1393.PP.0416012.277","website":"http://crfop.gdos.gov.pl/CRFOP/widok/viewfop.jsf?fop=PL.ZIPOP.1393.PP.0416012.277"}},"type":"Feature"}
]
}
