{
"type": "FeatureCollection",
"features": [
	{"geometry":{"coordinates":[18.188183,52.517781],"type":"Point"},"properties":{"osm_id":"4706681596","tag":{"denotation":"natural_monument","natural":"tree","ref:CRFOP":"PL.ZIPOP.1393.PP.0409022.844","ref:INSPIRE":"PL.ZIPOP.1393.PP.0409022.844","website":"http://crfop.gdos.gov.pl/CRFOP/widok/viewfop.jsf?fop=PL.ZIPOP.1393.PP.0409022.844"}},"type":"Feature"},
	{"geometry":{"coordinates":[18.188627,52.518026],"type":"Point"},"properties":{"osm_id":"4706681597","tag":{"denotation":"natural_monument","natural":"tree","ref:CRFOP":"PL.ZIPOP.1393.PP.0409022.844","ref:INSPIRE":"PL.ZIPOP.1393.PP.0409022.844","website":"http://crfop.gdos.gov.pl/CRFOP/widok/viewfop.jsf?fop=PL.ZIPOP.1393.PP.0409022.844"}},"type":"Feature"},
	{"geometry":{"coordinates":[18.18914,52.518209],"type":"Point"},"properties":{"osm_id":"4706681598","tag":{"denotation":"natural_monument","natural":"tree","ref:CRFOP":"PL.ZIPOP.1393.PP.0409022.844","ref:INSPIRE":"PL.ZIPOP.1393.PP.0409022.844","website":"http://crfop.gdos.gov.pl/CRFOP/widok/viewfop.jsf?fop=PL.ZIPOP.1393.PP.0409022.844"}},"type":"Feature"}
]
}
