{
"type": "FeatureCollection",
"features": [
	{"geometry":{"coordinates":[-89.030156,13.566965],"type":"Point"},"properties":{"name":"Mango","osm_id":"5546588129","tag":{"denotation":"landmark","leaf_type":"broadleaved","natural":"tree"}},"type":"Feature"},
	{"geometry":{"coordinates":[-89.029723,13.566524],"type":"Point"},"properties":{"name":"Mango","osm_id":"5546588140","tag":{"denotation":"landmark","leaf_type":"broadleaved","natural":"tree"}},"type":"Feature"}
]
}
