{
"type": "FeatureCollection",
"features": [
	{"geometry":{"coordinates":[0.481799,40.537695],"type":"Point"},"properties":{"name":"Deixalleria Municipal d'Alcanar","osm_id":"827334192","tag":{"amenity":"recycling"}},"type":"Feature"},
	{"geometry":{"coordinates":[0.481852,40.540191],"type":"Point"},"properties":{"osm_id":"3096329506","tag":{"amenity":"recycling"}},"type":"Feature"},
	{"geometry":{"coordinates":[0.48101,40.541641],"type":"Point"},"properties":{"osm_id":"3096329513","tag":{"amenity":"recycling"}},"type":"Feature"},
	{"geometry":{"coordinates":[0.482122,40.541844],"type":"Point"},"properties":{"osm_id":"3096329514","tag":{"amenity":"recycling"}},"type":"Feature"},
	{"geometry":{"coordinates":[0.478558,40.542855],"type":"Point"},"properties":{"osm_id":"3096329515","tag":{"amenity":"recycling"}},"type":"Feature"},
	{"geometry":{"coordinates":[0.480909,40.543329],"type":"Point"},"properties":{"osm_id":"3096329516","tag":{"amenity":"recycling"}},"type":"Feature"},
	{"geometry":{"coordinates":[0.479588,40.544511],"type":"Point"},"properties":{"osm_id":"3096329517","tag":{"amenity":"recycling"}},"type":"Feature"},
	{"geometry":{"coordinates":[0.481338,40.544802],"type":"Point"},"properties":{"osm_id":"3096329518","tag":{"amenity":"recycling"}},"type":"Feature"},
	{"geometry":{"coordinates":[0.476987,40.539552],"type":"Point"},"properties":{"osm_id":"3096927091","tag":{"amenity":"recycling"}},"type":"Feature"},
	{"geometry":{"coordinates":[0.479479,40.540346],"type":"Point"},"properties":{"osm_id":"3096927093","tag":{"amenity":"recycling"}},"type":"Feature"},
	{"geometry":{"coordinates":[0.475428,40.540796],"type":"Point"},"properties":{"osm_id":"3096927097","tag":{"amenity":"recycling"}},"type":"Feature"},
	{"geometry":{"coordinates":[0.484976,40.542523],"type":"Point"},"properties":{"osm_id":"3096927110","tag":{"amenity":"recycling"}},"type":"Feature"},
	{"geometry":{"coordinates":[0.476767,40.542635],"type":"Point"},"properties":{"osm_id":"3096927112","tag":{"amenity":"recycling"}},"type":"Feature"},
	{"geometry":{"coordinates":[0.483841,40.54311],"type":"Point"},"properties":{"osm_id":"3096927116","tag":{"amenity":"recycling"}},"type":"Feature"},
	{"geometry":{"coordinates":[0.486503,40.543722],"type":"Point"},"properties":{"osm_id":"3096927117","tag":{"amenity":"recycling"}},"type":"Feature"},
	{"geometry":{"coordinates":[0.484036,40.54454],"type":"Point"},"properties":{"osm_id":"3096927123","tag":{"amenity":"recycling"}},"type":"Feature"},
	{"geometry":{"coordinates":[0.476775,40.544661],"type":"Point"},"properties":{"osm_id":"3096927124","tag":{"amenity":"recycling"}},"type":"Feature"},
	{"geometry":{"coordinates":[0.483714,40.546031],"type":"Point"},"properties":{"osm_id":"3096927152","tag":{"amenity":"recycling"}},"type":"Feature"},
	{"geometry":{"coordinates":[0.479314,40.546396],"type":"Point"},"properties":{"osm_id":"3096927154","tag":{"amenity":"recycling"}},"type":"Feature"},
	{"geometry":{"coordinates":[0.477323,40.54642],"type":"Point"},"properties":{"osm_id":"3096927156","tag":{"amenity":"recycling"}},"type":"Feature"}
]
}
