{
"type": "FeatureCollection",
"lastupdate": "2020-08-01T00:00:00Z",
"features": [
	{"geometry":{"coordinates":[0.481798,40.537695],"type":"Point"},"properties":{"name":"Deixalleria Municipal d'Alcanar","osm_id":"827334192","tag":{"amenity":"recycling"}},"type":"Feature"},
	{"geometry":{"coordinates":[0.481851,40.54019],"type":"Point"},"properties":{"osm_id":"3096329506","tag":{"amenity":"recycling"}},"type":"Feature"},
	{"geometry":{"coordinates":[0.481009,40.541641],"type":"Point"},"properties":{"osm_id":"3096329513","tag":{"amenity":"recycling"}},"type":"Feature"},
	{"geometry":{"coordinates":[0.482122,40.541844],"type":"Point"},"properties":{"osm_id":"3096329514","tag":{"amenity":"recycling"}},"type":"Feature"},
	{"geometry":{"coordinates":[0.478558,40.542854],"type":"Point"},"properties":{"osm_id":"3096329515","tag":{"amenity":"recycling"}},"type":"Feature"},
	{"geometry":{"coordinates":[0.480908,40.543328],"type":"Point"},"properties":{"osm_id":"3096329516","tag":{"amenity":"recycling"}},"type":"Feature"},
	{"geometry":{"coordinates":[0.479588,40.544511],"type":"Point"},"properties":{"osm_id":"3096329517","tag":{"amenity":"recycling"}},"type":"Feature"},
	{"geometry":{"coordinates":[0.481338,40.544801],"type":"Point"},"properties":{"osm_id":"3096329518","tag":{"amenity":"recycling"}},"type":"Feature"},
	{"geometry":{"coordinates":[0.476987,40.539551],"type":"Point"},"properties":{"osm_id":"3096927091","tag":{"amenity":"recycling"}},"type":"Feature"},
	{"geometry":{"coordinates":[0.479479,40.540346],"type":"Point"},"properties":{"osm_id":"3096927093","tag":{"amenity":"recycling"}},"type":"Feature"},
	{"geometry":{"coordinates":[0.475428,40.540795],"type":"Point"},"properties":{"osm_id":"3096927097","tag":{"amenity":"recycling"}},"type":"Feature"},
	{"geometry":{"coordinates":[0.484975,40.542523],"type":"Point"},"properties":{"osm_id":"3096927110","tag":{"amenity":"recycling"}},"type":"Feature"},
	{"geometry":{"coordinates":[0.476767,40.542634],"type":"Point"},"properties":{"osm_id":"3096927112","tag":{"amenity":"recycling"}},"type":"Feature"},
	{"geometry":{"coordinates":[0.483841,40.543109],"type":"Point"},"properties":{"osm_id":"3096927116","tag":{"amenity":"recycling"}},"type":"Feature"},
	{"geometry":{"coordinates":[0.486503,40.543721],"type":"Point"},"properties":{"osm_id":"3096927117","tag":{"amenity":"recycling"}},"type":"Feature"},
	{"geometry":{"coordinates":[0.484035,40.54454],"type":"Point"},"properties":{"osm_id":"3096927123","tag":{"amenity":"recycling"}},"type":"Feature"},
	{"geometry":{"coordinates":[0.476775,40.54466],"type":"Point"},"properties":{"osm_id":"3096927124","tag":{"amenity":"recycling"}},"type":"Feature"},
	{"geometry":{"coordinates":[0.483714,40.546031],"type":"Point"},"properties":{"osm_id":"3096927152","tag":{"amenity":"recycling"}},"type":"Feature"},
	{"geometry":{"coordinates":[0.479314,40.546395],"type":"Point"},"properties":{"osm_id":"3096927154","tag":{"amenity":"recycling"}},"type":"Feature"},
	{"geometry":{"coordinates":[0.477322,40.54642],"type":"Point"},"properties":{"osm_id":"3096927156","tag":{"amenity":"recycling"}},"type":"Feature"}
]
}
