{
"type": "FeatureCollection",
"lastupdate": "2020-08-01T00:00:00Z",
"features": [
	{"geometry":{"coordinates":[4.527215,45.945484],"type":"Point"},"properties":{"osm_id":"536129594","tag":{"amenity":"recycling","recycling:clothes":"yes","recycling:glass":"yes"}},"type":"Feature"},
	{"geometry":{"coordinates":[4.565042,45.945191],"type":"Point"},"properties":{"osm_id":"1674338941","tag":{"amenity":"recycling","recycling:batteries":"no","recycling:books":"no","recycling:cans":"yes","recycling:cardboard":"no","recycling:cartons":"yes","recycling:clothes":"no","recycling:electrical_appliances":"no","recycling:glass":"yes","recycling:glass_bottles":"yes","recycling:green_waste":"no","recycling:magazines":"yes","recycling:newspaper":"yes","recycling:paper":"yes","recycling:paper_packaging":"no","recycling:plastic":"yes","recycling:plastic_bottles":"yes","recycling:plastic_packaging":"yes","recycling:scrap_metal":"yes","recycling:small_appliances":"no","recycling:waste":"no","recycling:wood":"no","recycling_type":"container"}},"type":"Feature"},
	{"geometry":{"coordinates":[4.527911,45.918411],"type":"Point"},"properties":{"osm_id":"1827923803","tag":{"amenity":"recycling","recycling:glass_bottles":"yes","recycling_type":"container"}},"type":"Feature"},
	{"geometry":{"coordinates":[4.556884,45.925874],"type":"Point"},"properties":{"name":"Centre de tri des Plaines","osm_id":"6695141120","tag":{"addr:city":"Val d'Oingt - Saint Laurent d'Oingt","addr:postcode":"69620","addr:street":"Les Plaines","amenity":"recycling","recycling_type":"centre","ref:FR:SINOE":"43113","start_date":"2005-03-01"}},"type":"Feature"},
	{"geometry":{"coordinates":[4.569061,45.907125],"type":"Point"},"properties":{"osm_id":"7636713930","tag":{"amenity":"recycling","capacity":"1","recycling:glass_bottles":"yes","recycling_type":"container"}},"type":"Feature"}
]
}
