{
"type": "FeatureCollection",
"features": [
	{"geometry":{"coordinates":[30.1344,8.310174],"type":"Point"},"properties":{"name":"The Ler Tree","osm_id":"3029731832","tag":{"natural":"tree"}},"type":"Feature"}
]
}
