{
"type": "FeatureCollection",
"features": [
	{"geometry":{"coordinates":[-50.730057,-23.085503],"type":"Point"},"properties":{"name":"Centro de reciclagem Osnir de Oliveira da Cruz","osm_id":"9187329555","tag":{"addr:city":"Leopolis","addr:postcode":"86330000","addr:street":"PR-160","addr:suburb":"Bairro Rural Agua da Rita","amenity":"recycling","recycling_type":"centre"}},"type":"Feature"}
]
}
