{
"type": "FeatureCollection",
"features": [
	{"geometry":{"coordinates":[-110.849877,52.844618],"type":"Point"},"properties":{"osm_id":"980018014","tag":{"amenity":"recycling"}},"type":"Feature"},
	{"geometry":{"coordinates":[-110.866431,52.834651],"type":"Point"},"properties":{"name":"Bottles Recycling","osm_id":"3686194903","tag":{"amenity":"recycling"}},"type":"Feature"}
]
}
