{
"type": "FeatureCollection",
"lastupdate": "2020-08-03T00:00:00Z",
"features": [
	{"geometry":{"coordinates":[-110.849877,52.844618],"type":"Point"},"properties":{"osm_id":"980018014","tag":{"amenity":"recycling"}},"type":"Feature"},
	{"geometry":{"coordinates":[-110.86643,52.83465],"type":"Point"},"properties":{"name":"Bottles Recycling","osm_id":"3686194903","tag":{"amenity":"recycling"}},"type":"Feature"}
]
}
