{
"type": "FeatureCollection",
"lastupdate": "2020-08-06T00:00:00Z",
"features": [
	{"geometry":{"coordinates":[-95.884264,35.944201],"type":"Point"},"properties":{"name":"Metropolitan Environmental Trust","osm_id":"4943144710","tag":{"addr:city":"Bixby","addr:country":"US","addr:housenumber":"211","addr:postcode":"74008","addr:state":"OK","addr:street":"North Cabaniss Avenue","amenity":"recycling","opening_hours":"Mo-Fr 09:30-13:30; Sa 09:30-15:30; Su 10:30-14:30","recycling:batteries":"yes","recycling:cans":"yes","recycling:glass_bottles":"yes","recycling:paper":"yes","recycling:plastic_bottles":"yes","recycling_type":"centre","website":"http://metrecycle.com/bixby/"}},"type":"Feature"}
]
}
