{
"type": "FeatureCollection",
"lastupdate": "2020-08-06T00:00:00Z",
"features": [
	{"geometry":{"coordinates":[23.211511,69.953437],"type":"Point"},"properties":{"osm_id":"3365706450","tag":{"amenity":"waste_basket"}},"type":"Feature"},
	{"geometry":{"coordinates":[23.214489,69.953534],"type":"Point"},"properties":{"osm_id":"5555192582","tag":{"amenity":"recycling","description":"Gakori v/Extra","recycling:glass_bottles":"yes","recycling_type":"container","ref:sortere":"632"}},"type":"Feature"},
	{"geometry":{"coordinates":[23.216144,69.943888],"type":"Point"},"properties":{"name":"Gakori","osm_id":"6665770348","tag":{"amenity":"waste_basket","waste":"trash"}},"type":"Feature"},
	{"geometry":{"coordinates":[23.258801,69.9305],"type":"Point"},"properties":{"osm_id":"6859988360","tag":{"amenity":"waste_basket","waste":"trash"}},"type":"Feature"}
]
}
