{
"type": "FeatureCollection",
"lastupdate": "2020-08-02T00:00:00Z",
"features": [
	{"geometry":{"coordinates":[23.250921,69.882421],"type":"Point"},"properties":{"osm_id":"6195508585","tag":{"amenity":"recycling","description":"Mottak for marint avfall - Alta","operator":"Masternes Gjenvinning AS","phone":"+47 97009360","recycling:marine_waste":"yes","recycling_type":"container","ref:sortere":"110","website":"https://masternes.no/"}},"type":"Feature"}
]
}
