{
"type": "FeatureCollection",
"features": [
	{"geometry":{"coordinates":[5.23484,51.287563],"type":"Point"},"properties":{"osm_id":"4813336841","tag":{"denomination":"roman_catholic","historic":"wayside_shrine","image":"https://commons.wikimedia.org/wiki/File:OLV_kapelletje_aan_Steenovens,_Postel.jpg","leaf_cycle":"deciduous","leaf_type":"broadleaved","natural":"tree","religion":"christian"}},"type":"Feature"},
	{"geometry":{"coordinates":[5.189522,51.288249],"type":"Point"},"properties":{"osm_id":"4815351328","tag":{"leaf_cycle":"deciduous","leaf_type":"broadleaved","natural":"tree"}},"type":"Feature"},
	{"geometry":{"coordinates":[5.189926,51.287674],"type":"Point"},"properties":{"osm_id":"4815351365","tag":{"leaf_cycle":"deciduous","leaf_type":"broadleaved","natural":"tree"}},"type":"Feature"},
	{"geometry":{"coordinates":[5.189371,51.288812],"type":"Point"},"properties":{"osm_id":"6708199579","tag":{"natural":"tree"}},"type":"Feature"},
	{"geometry":{"coordinates":[5.189251,51.28888],"type":"Point"},"properties":{"osm_id":"6708199580","tag":{"natural":"tree"}},"type":"Feature"}
]
}
