{
"type": "FeatureCollection",
"features": [
	{"geometry":{"coordinates":[5.192044,50.52355],"type":"Point"},"properties":{"osm_id":"2700648831","tag":{"natural":"tree"}},"type":"Feature"},
	{"geometry":{"coordinates":[5.238784,50.547542],"type":"Point"},"properties":{"osm_id":"2977864338","tag":{"natural":"tree","type":"broad_leaved"}},"type":"Feature"},
	{"geometry":{"coordinates":[5.225864,50.56281],"type":"Point"},"properties":{"osm_id":"2985960333","tag":{"natural":"tree","type":"broad_leaved"}},"type":"Feature"},
	{"geometry":{"coordinates":[5.22581,50.56278],"type":"Point"},"properties":{"osm_id":"2985960334","tag":{"natural":"tree","type":"broad_leaved"}},"type":"Feature"},
	{"geometry":{"coordinates":[5.215814,50.563638],"type":"Point"},"properties":{"osm_id":"2986657995","tag":{"natural":"tree","type":"broad_leaved"}},"type":"Feature"},
	{"geometry":{"coordinates":[5.224249,50.543535],"type":"Point"},"properties":{"name":"Le vieux tilleul","osm_id":"3020876357","tag":{"natural":"tree","type":"Lime_tree"}},"type":"Feature"},
	{"geometry":{"coordinates":[5.214523,50.537472],"type":"Point"},"properties":{"osm_id":"3026795601","tag":{"natural":"tree","type":"broad_leaved"}},"type":"Feature"},
	{"geometry":{"coordinates":[5.214518,50.537375],"type":"Point"},"properties":{"osm_id":"3026795602","tag":{"natural":"tree","type":"broad_leaved"}},"type":"Feature"},
	{"geometry":{"coordinates":[5.240381,50.518562],"type":"Point"},"properties":{"osm_id":"3099119295","tag":{"natural":"tree"}},"type":"Feature"},
	{"geometry":{"coordinates":[5.230744,50.56554],"type":"Point"},"properties":{"osm_id":"3202435929","tag":{"natural":"tree","type":"broad_leaved"}},"type":"Feature"},
	{"geometry":{"coordinates":[5.208209,50.545467],"type":"Point"},"properties":{"osm_id":"3937950746","tag":{"natural":"tree"}},"type":"Feature"},
	{"geometry":{"coordinates":[5.208137,50.545482],"type":"Point"},"properties":{"osm_id":"3937950752","tag":{"natural":"tree"}},"type":"Feature"},
	{"geometry":{"coordinates":[5.208288,50.545441],"type":"Point"},"properties":{"osm_id":"3937950754","tag":{"natural":"tree"}},"type":"Feature"}
]
}
