{
"type": "FeatureCollection",
"features": [
	{"geometry":{"coordinates":[5.192045,50.523551],"type":"Point"},"properties":{"osm_id":"2700648831","tag":{"natural":"tree"}},"type":"Feature"},
	{"geometry":{"coordinates":[5.238785,50.547543],"type":"Point"},"properties":{"osm_id":"2977864338","tag":{"natural":"tree","type":"broad_leaved"}},"type":"Feature"},
	{"geometry":{"coordinates":[5.225865,50.562811],"type":"Point"},"properties":{"osm_id":"2985960333","tag":{"natural":"tree","type":"broad_leaved"}},"type":"Feature"},
	{"geometry":{"coordinates":[5.22581,50.562781],"type":"Point"},"properties":{"osm_id":"2985960334","tag":{"natural":"tree","type":"broad_leaved"}},"type":"Feature"},
	{"geometry":{"coordinates":[5.215815,50.563639],"type":"Point"},"properties":{"osm_id":"2986657995","tag":{"natural":"tree","type":"broad_leaved"}},"type":"Feature"},
	{"geometry":{"coordinates":[5.22425,50.543535],"type":"Point"},"properties":{"name":"Le vieux tilleul","osm_id":"3020876357","tag":{"natural":"tree","type":"Lime_tree"}},"type":"Feature"},
	{"geometry":{"coordinates":[5.214524,50.537473],"type":"Point"},"properties":{"osm_id":"3026795601","tag":{"natural":"tree","type":"broad_leaved"}},"type":"Feature"},
	{"geometry":{"coordinates":[5.214518,50.537376],"type":"Point"},"properties":{"osm_id":"3026795602","tag":{"natural":"tree","type":"broad_leaved"}},"type":"Feature"},
	{"geometry":{"coordinates":[5.240382,50.518563],"type":"Point"},"properties":{"osm_id":"3099119295","tag":{"natural":"tree"}},"type":"Feature"},
	{"geometry":{"coordinates":[5.230744,50.565541],"type":"Point"},"properties":{"osm_id":"3202435929","tag":{"natural":"tree","type":"broad_leaved"}},"type":"Feature"},
	{"geometry":{"coordinates":[5.20821,50.545467],"type":"Point"},"properties":{"osm_id":"3937950746","tag":{"natural":"tree"}},"type":"Feature"},
	{"geometry":{"coordinates":[5.208137,50.545482],"type":"Point"},"properties":{"osm_id":"3937950752","tag":{"natural":"tree"}},"type":"Feature"},
	{"geometry":{"coordinates":[5.208288,50.545441],"type":"Point"},"properties":{"osm_id":"3937950754","tag":{"natural":"tree"}},"type":"Feature"}
]
}
