{
"type": "FeatureCollection",
"features": [
	{"geometry":{"coordinates":[14.956712,48.151446],"type":"Point"},"properties":{"name":"Bildbaum Steinberg","osm_id":"1888989545","tag":{"denomination":"roman_catholic","historic":"wayside_shrine","natural":"tree","religion":"christian"}},"type":"Feature"},
	{"geometry":{"coordinates":[14.948535,48.153853],"type":"Point"},"properties":{"osm_id":"1891735612","tag":{"natural":"tree","type":"broad_leaved"}},"type":"Feature"},
	{"geometry":{"coordinates":[14.977317,48.122936],"type":"Point"},"properties":{"osm_id":"5339466939","tag":{"natural":"tree"}},"type":"Feature"},
	{"geometry":{"coordinates":[14.977641,48.122946],"type":"Point"},"properties":{"osm_id":"5339466940","tag":{"natural":"tree"}},"type":"Feature"},
	{"geometry":{"coordinates":[14.977964,48.122943],"type":"Point"},"properties":{"osm_id":"5339466941","tag":{"natural":"tree"}},"type":"Feature"},
	{"geometry":{"coordinates":[14.976995,48.122903],"type":"Point"},"properties":{"osm_id":"5339466942","tag":{"natural":"tree"}},"type":"Feature"},
	{"geometry":{"coordinates":[14.963592,48.115226],"type":"Point"},"properties":{"osm_id":"7743505496","tag":{"natural":"tree"}},"type":"Feature"},
	{"geometry":{"coordinates":[14.963663,48.115233],"type":"Point"},"properties":{"osm_id":"7743505497","tag":{"natural":"tree"}},"type":"Feature"},
	{"geometry":{"coordinates":[14.963657,48.115296],"type":"Point"},"properties":{"osm_id":"7743505498","tag":{"natural":"tree"}},"type":"Feature"}
]
}
