{
"type": "FeatureCollection",
"features": [
	{"geometry":{"coordinates":[14.956713,48.151446],"type":"Point"},"properties":{"name":"Bildbaum Steinberg","osm_id":"1888989545","tag":{"denomination":"roman_catholic","historic":"wayside_shrine","natural":"tree","religion":"christian"}},"type":"Feature"},
	{"geometry":{"coordinates":[14.948535,48.153854],"type":"Point"},"properties":{"osm_id":"1891735612","tag":{"natural":"tree","type":"broad_leaved"}},"type":"Feature"},
	{"geometry":{"coordinates":[14.977318,48.122936],"type":"Point"},"properties":{"osm_id":"5339466939","tag":{"natural":"tree"}},"type":"Feature"},
	{"geometry":{"coordinates":[14.977642,48.122947],"type":"Point"},"properties":{"osm_id":"5339466940","tag":{"natural":"tree"}},"type":"Feature"},
	{"geometry":{"coordinates":[14.977964,48.122944],"type":"Point"},"properties":{"osm_id":"5339466941","tag":{"natural":"tree"}},"type":"Feature"},
	{"geometry":{"coordinates":[14.976996,48.122904],"type":"Point"},"properties":{"osm_id":"5339466942","tag":{"natural":"tree"}},"type":"Feature"},
	{"geometry":{"coordinates":[14.963592,48.115226],"type":"Point"},"properties":{"osm_id":"7743505496","tag":{"natural":"tree"}},"type":"Feature"},
	{"geometry":{"coordinates":[14.963663,48.115233],"type":"Point"},"properties":{"osm_id":"7743505497","tag":{"natural":"tree"}},"type":"Feature"},
	{"geometry":{"coordinates":[14.963658,48.115297],"type":"Point"},"properties":{"osm_id":"7743505498","tag":{"natural":"tree"}},"type":"Feature"}
]
}
