{
"type": "FeatureCollection",
"features": [
	{"geometry":{"coordinates":[14.987744,-17.511884],"type":"Point"},"properties":{"name":"Ombalantu Baobab","osm_id":"2023080833","tag":{"diameter":"20 m","height":"28","natural":"tree","type":"baobab","wikidata":"Q186346","wikipedia":"en:Ombalantu baobab tree"}},"type":"Feature"},
	{"geometry":{"coordinates":[14.979084,-17.498072],"type":"Point"},"properties":{"osm_id":"2023080888","tag":{"natural":"tree"}},"type":"Feature"}
]
}
