{
"type": "FeatureCollection",
"lastupdate": "2020-08-04T00:00:00Z",
"features": [
	{"geometry":{"coordinates":[6.6338,43.929921],"type":"Point"},"properties":{"name":"L'Iscle de Vergons","osm_id":"7203843878","tag":{"amenity":"recycling","contact:website":"http://www.ccapv.fr/environnement-et-developpement-durable/environnement/97-environnement-et-developpement-durable/gestion-des-dechets/les-bons-gestes-du-tri/76-les-bons-gestes-du-tri","operator":"Communaut\u00e9\u00a0de\u00a0Communes\u00a0Alpes\u00a0Provence\u00a0Verdon,\u00a0Sources\u00a0de\u00a0Lumi\u00e8res","recycling:glass_bottles":"yes","recycling:paper":"yes","recycling:plastic":"yes","recycling:waste":"yes","recycling_type":"container"}},"type":"Feature"},
	{"geometry":{"coordinates":[6.672494,43.960974],"type":"Point"},"properties":{"name":"Lotissement Les Auches Bas","osm_id":"7203844614","tag":{"amenity":"recycling","contact:website":"http://www.ccapv.fr/environnement-et-developpement-durable/environnement/97-environnement-et-developpement-durable/gestion-des-dechets/les-bons-gestes-du-tri/76-les-bons-gestes-du-tri","operator":"Communaut\u00e9\u00a0de\u00a0Communes\u00a0Alpes\u00a0Provence\u00a0Verdon,\u00a0Sources\u00a0de\u00a0Lumi\u00e8res","recycling:glass_bottles":"yes","recycling:paper":"yes","recycling:plastic":"yes","recycling:waste":"yes","recycling_type":"container"}},"type":"Feature"},
	{"geometry":{"coordinates":[6.665507,43.928764],"type":"Point"},"properties":{"name":"Route d'Ubraye","osm_id":"7203844720","tag":{"amenity":"recycling","contact:website":"http://www.ccapv.fr/environnement-et-developpement-durable/environnement/97-environnement-et-developpement-durable/gestion-des-dechets/les-bons-gestes-du-tri/76-les-bons-gestes-du-tri","operator":"Communaut\u00e9\u00a0de\u00a0Communes\u00a0Alpes\u00a0Provence\u00a0Verdon,\u00a0Sources\u00a0de\u00a0Lumi\u00e8res","recycling:glass_bottles":"yes","recycling:paper":"yes","recycling:plastic":"yes","recycling:waste":"yes","recycling_type":"container"}},"type":"Feature"},
	{"geometry":{"coordinates":[6.663669,43.931615],"type":"Point"},"properties":{"name":"Rouaine","osm_id":"7203844750","tag":{"amenity":"recycling","contact:website":"http://www.ccapv.fr/environnement-et-developpement-durable/environnement/97-environnement-et-developpement-durable/gestion-des-dechets/les-bons-gestes-du-tri/76-les-bons-gestes-du-tri","operator":"Communaut\u00e9\u00a0de\u00a0Communes\u00a0Alpes\u00a0Provence\u00a0Verdon,\u00a0Sources\u00a0de\u00a0Lumi\u00e8res","recycling:glass_bottles":"yes","recycling:paper":"yes","recycling:plastic":"yes","recycling:waste":"yes","recycling_type":"container"}},"type":"Feature"}
]
}
