{
"type": "FeatureCollection",
"features": [
	{"geometry":{"coordinates":[11.844423,53.697686],"type":"Point"},"properties":{"osm_id":"4087828583","tag":{"natural":"tree"}},"type":"Feature"},
	{"geometry":{"coordinates":[11.835459,53.716041],"type":"Point"},"properties":{"osm_id":"5081476205","tag":{"natural":"tree"}},"type":"Feature"},
	{"geometry":{"coordinates":[11.836163,53.715591],"type":"Point"},"properties":{"osm_id":"5081476208","tag":{"natural":"tree"}},"type":"Feature"},
	{"geometry":{"coordinates":[11.83461,53.716414],"type":"Point"},"properties":{"osm_id":"5081476209","tag":{"natural":"tree"}},"type":"Feature"},
	{"geometry":{"coordinates":[11.812829,53.711292],"type":"Point"},"properties":{"name":"Neumeister Linde","osm_id":"7978186540","tag":{"natural":"tree"}},"type":"Feature"}
]
}
