{
"type": "FeatureCollection",
"features": [
	{"geometry":{"coordinates":[11.862616,50.069327],"type":"Point"},"properties":{"name":"Vogelbeerbaum","osm_id":"3424464444","tag":{"natural":"tree"}},"type":"Feature"},
	{"geometry":{"coordinates":[11.847305,50.095483],"type":"Point"},"properties":{"osm_id":"4689370927","tag":{"natural":"tree"}},"type":"Feature"},
	{"geometry":{"coordinates":[11.847519,50.095468],"type":"Point"},"properties":{"osm_id":"4689370928","tag":{"natural":"tree"}},"type":"Feature"},
	{"geometry":{"coordinates":[11.847726,50.09544],"type":"Point"},"properties":{"osm_id":"4689370956","tag":{"natural":"tree"}},"type":"Feature"},
	{"geometry":{"coordinates":[11.846846,50.095516],"type":"Point"},"properties":{"osm_id":"4689370966","tag":{"natural":"tree"}},"type":"Feature"},
	{"geometry":{"coordinates":[11.848176,50.09539],"type":"Point"},"properties":{"osm_id":"4689370978","tag":{"natural":"tree"}},"type":"Feature"},
	{"geometry":{"coordinates":[11.847948,50.095418],"type":"Point"},"properties":{"osm_id":"4689371104","tag":{"natural":"tree"}},"type":"Feature"},
	{"geometry":{"coordinates":[11.847079,50.095492],"type":"Point"},"properties":{"osm_id":"4689371112","tag":{"natural":"tree"}},"type":"Feature"}
]
}
