{
"type": "FeatureCollection",
"features": [
	{"geometry":{"coordinates":[11.790889,48.797377],"type":"Point"},"properties":{"osm_id":"2943488544","tag":{"genus:de":"Kastanie","leaf_type":"broadleaved","natural":"tree"}},"type":"Feature"},
	{"geometry":{"coordinates":[11.850453,48.753862],"type":"Point"},"properties":{"osm_id":"2961555990","tag":{"natural":"tree"}},"type":"Feature"},
	{"geometry":{"coordinates":[11.850473,48.754063],"type":"Point"},"properties":{"osm_id":"2961556014","tag":{"natural":"tree"}},"type":"Feature"},
	{"geometry":{"coordinates":[11.850369,48.754265],"type":"Point"},"properties":{"osm_id":"2961556140","tag":{"natural":"tree"}},"type":"Feature"},
	{"geometry":{"coordinates":[11.78599,48.767883],"type":"Point"},"properties":{"name":"Mosereiche","osm_id":"7935048530","tag":{"genus":"quercus","natural":"tree"}},"type":"Feature"}
]
}
