{
"type": "FeatureCollection",
"features": [
	{"geometry":{"coordinates":[11.790888,48.797376],"type":"Point"},"properties":{"osm_id":"2943488544","tag":{"genus:de":"Kastanie","leaf_type":"broadleaved","natural":"tree"}},"type":"Feature"},
	{"geometry":{"coordinates":[11.850453,48.753862],"type":"Point"},"properties":{"osm_id":"2961555990","tag":{"natural":"tree"}},"type":"Feature"},
	{"geometry":{"coordinates":[11.850472,48.754062],"type":"Point"},"properties":{"osm_id":"2961556014","tag":{"natural":"tree"}},"type":"Feature"},
	{"geometry":{"coordinates":[11.850368,48.754264],"type":"Point"},"properties":{"osm_id":"2961556140","tag":{"natural":"tree"}},"type":"Feature"},
	{"geometry":{"coordinates":[11.785989,48.767882],"type":"Point"},"properties":{"name":"Mosereiche","osm_id":"7935048530","tag":{"genus":"quercus","natural":"tree"}},"type":"Feature"}
]
}
