{
"type": "FeatureCollection",
"features": [
	{"geometry":{"coordinates":[11.847878,48.54188],"type":"Point"},"properties":{"name":"Lindenbaum","osm_id":"1364619000","tag":{"genus":"Tilia","genus:de":"Linde","height":"15","natural":"tree"}},"type":"Feature"},
	{"geometry":{"coordinates":[11.843428,48.533565],"type":"Point"},"properties":{"osm_id":"5834983427","tag":{"natural":"tree"}},"type":"Feature"}
]
}
