{
"type": "FeatureCollection",
"features": [
	{"geometry":{"coordinates":[11.817091,43.78987],"type":"Point"},"properties":{"name":"Castagno Miraglia","osm_id":"3084205142","tag":{"denotation":"natural_monument","genus":"Castanea sativa","leaf_cycle":"deciduous","leaf_type":"broadleaved","natural":"tree","wikidata":"Q3662058","wikipedia":"it:Castagno Miraglia"}},"type":"Feature"}
]
}
