{
"type": "FeatureCollection",
"features": [
	{"geometry":{"coordinates":[141.351737,43.063436],"type":"Point"},"properties":{"osm_id":"6098246486","tag":{"amenity":"waste_basket"}},"type":"Feature"},
	{"geometry":{"coordinates":[141.39551,43.023651],"type":"Point"},"properties":{"name":"\u00e3\u0081\u0098\u00e3\u0082\u0085\u00e3\u0082\u0093\u00e3\u0081\u008b\u00e3\u0082\u0093\u00e3\u0082\u00b3\u00e3\u0083\u00b3\u00e3\u0083\u0093\u00e3\u0083\u008b24 \u00e8\u00a5\u00bf\u00e5\u00b2\u00a1\u00e5\u00ba\u0097","osm_id":"7527835666","tag":{"amenity":"recycling","name:en":"Jyunkan-Convenience-24 Nishioka shop","name:ja":"\u00e3\u0081\u0098\u00e3\u0082\u0085\u00e3\u0082\u0093\u00e3\u0081\u008b\u00e3\u0082\u0093\u00e3\u0082\u00b3\u00e3\u0083\u00b3\u00e3\u0083\u0093\u00e3\u0083\u008b24 \u00e8\u00a5\u00bf\u00e5\u00b2\u00a1\u00e5\u00ba\u0097","operator":"\u00e6\u00a0\u00aa\u00e5\u00bc\u008f\u00e4\u00bc\u009a\u00e7\u00a4\u00be \u00e3\u0083\u009e\u00e3\u0083\u0086\u00e3\u0083\u0083\u00e3\u0082\u00af","recycling_type":"container"}},"type":"Feature"}
]
}
