{
"type": "FeatureCollection",
"lastupdate": "2020-08-03T00:00:00Z",
"features": [
	{"geometry":{"coordinates":[141.351737,43.063435],"type":"Point"},"properties":{"osm_id":"6098246486","tag":{"amenity":"waste_basket"}},"type":"Feature"},
	{"geometry":{"coordinates":[141.39551,43.02365],"type":"Point"},"properties":{"name":"\u00e3\u0081\u0098\u00e3\u0082\u0085\u00e3\u0082\u0093\u00e3\u0081\u008b\u00e3\u0082\u0093\u00e3\u0082\u00b3\u00e3\u0083\u00b3\u00e3\u0083\u0093\u00e3\u0083\u008b24 \u00e8\u00a5\u00bf\u00e5\u00b2\u00a1\u00e5\u00ba\u0097","osm_id":"7527835666","tag":{"amenity":"recycling","name:en":"Jyunkan-Convenience-24 Nishioka shop","name:ja":"\u3058\u3085\u3093\u304b\u3093\u30b3\u30f3\u30d3\u30cb24 \u897f\u5ca1\u5e97","operator":"\u682a\u5f0f\u4f1a\u793e \u30de\u30c6\u30c3\u30af","recycling_type":"container"}},"type":"Feature"}
]
}
