{
"type": "FeatureCollection",
"features": [
	{"geometry":{"coordinates":[-3.308885,43.049997],"type":"Point"},"properties":{"name":"Tejo Centenario","osm_id":"4536720856","tag":{"natural":"tree"}},"type":"Feature"},
	{"geometry":{"coordinates":[-3.333398,43.053192],"type":"Point"},"properties":{"name":"Tejo","osm_id":"4536720858","tag":{"natural":"tree"}},"type":"Feature"}
]
}
