{
"type": "FeatureCollection",
"features": [
	{"geometry":{"coordinates":[-3.308886,43.049998],"type":"Point"},"properties":{"name":"Tejo Centenario","osm_id":"4536720856","tag":{"natural":"tree"}},"type":"Feature"},
	{"geometry":{"coordinates":[-3.333399,43.053192],"type":"Point"},"properties":{"name":"Tejo","osm_id":"4536720858","tag":{"natural":"tree"}},"type":"Feature"}
]
}
