{
"type": "FeatureCollection",
"features": [
	{"geometry":{"coordinates":[-3.309663,42.388153],"type":"Point"},"properties":{"name":"Nogal","osm_id":"3106194853","tag":{"denotation":"landmark","leaf_type":"broadleaved","natural":"tree"}},"type":"Feature"},
	{"geometry":{"coordinates":[-3.310963,42.387495],"type":"Point"},"properties":{"osm_id":"3155526710","tag":{"natural":"tree"}},"type":"Feature"},
	{"geometry":{"coordinates":[-3.3098,42.38762],"type":"Point"},"properties":{"osm_id":"3155526711","tag":{"natural":"tree"}},"type":"Feature"},
	{"geometry":{"coordinates":[-3.307434,42.392646],"type":"Point"},"properties":{"osm_id":"4326321121","tag":{"natural":"tree"}},"type":"Feature"},
	{"geometry":{"coordinates":[-3.308063,42.392259],"type":"Point"},"properties":{"osm_id":"4326321122","tag":{"natural":"tree"}},"type":"Feature"},
	{"geometry":{"coordinates":[-3.308846,42.388153],"type":"Point"},"properties":{"osm_id":"4683367917","tag":{"natural":"tree"}},"type":"Feature"},
	{"geometry":{"coordinates":[-3.309839,42.385661],"type":"Point"},"properties":{"name":"Manzano","osm_id":"4697101209","tag":{"leaf_type":"broadleaved","natural":"tree"}},"type":"Feature"},
	{"geometry":{"coordinates":[-3.308837,42.385685],"type":"Point"},"properties":{"osm_id":"4701564400","tag":{"natural":"tree"}},"type":"Feature"},
	{"geometry":{"coordinates":[-3.309435,42.388441],"type":"Point"},"properties":{"osm_id":"4723833653","tag":{"natural":"tree"}},"type":"Feature"},
	{"geometry":{"coordinates":[-3.309405,42.38848],"type":"Point"},"properties":{"osm_id":"4723833654","tag":{"natural":"tree"}},"type":"Feature"},
	{"geometry":{"coordinates":[-3.309374,42.388527],"type":"Point"},"properties":{"osm_id":"4723833655","tag":{"natural":"tree"}},"type":"Feature"},
	{"geometry":{"coordinates":[-3.309308,42.388605],"type":"Point"},"properties":{"osm_id":"4723833656","tag":{"natural":"tree"}},"type":"Feature"}
]
}
