{
"type": "FeatureCollection",
"features": [
	{"geometry":{"coordinates":[-3.302867,40.927872],"type":"Point"},"properties":{"name":"Olivo centenario","osm_id":"6550963082","tag":{"natural":"tree"}},"type":"Feature"}
]
}
