{
"type": "FeatureCollection",
"features": [
	{"geometry":{"coordinates":[-3.302867,40.927872],"type":"Point"},"properties":{"name":"Olivo centenario","osm_id":"6550963082","tag":{"natural":"tree"}},"type":"Feature"},
	{"geometry":{"coordinates":[-3.301609,40.925514],"type":"Point"},"properties":{"osm_id":"8400040291","tag":{"natural":"tree"}},"type":"Feature"},
	{"geometry":{"coordinates":[-3.29913,40.925451],"type":"Point"},"properties":{"osm_id":"8400040292","tag":{"natural":"tree"}},"type":"Feature"},
	{"geometry":{"coordinates":[-3.301924,40.924942],"type":"Point"},"properties":{"osm_id":"8400040293","tag":{"natural":"tree"}},"type":"Feature"},
	{"geometry":{"coordinates":[-3.301873,40.92482],"type":"Point"},"properties":{"osm_id":"8400040294","tag":{"natural":"tree"}},"type":"Feature"},
	{"geometry":{"coordinates":[-3.306169,40.926867],"type":"Point"},"properties":{"osm_id":"8400040295","tag":{"natural":"tree"}},"type":"Feature"}
]
}
