{
"type": "FeatureCollection",
"features": [
	{"geometry":{"coordinates":[9.956744,59.017695],"type":"Point"},"properties":{"osm_id":"1392851825","tag":{"natural":"tree"}},"type":"Feature"},
	{"geometry":{"coordinates":[9.979647,59.028668],"type":"Point"},"properties":{"name":"Ullebergeika","osm_id":"1764496227","tag":{"natural":"tree"}},"type":"Feature"},
	{"geometry":{"coordinates":[10.000022,59.039491],"type":"Point"},"properties":{"osm_id":"5708642419","tag":{"natural":"tree"}},"type":"Feature"},
	{"geometry":{"coordinates":[9.999664,59.039541],"type":"Point"},"properties":{"osm_id":"5708642420","tag":{"natural":"tree"}},"type":"Feature"}
]
}
