{
"type": "FeatureCollection",
"features": [
	{"geometry":{"coordinates":[9.942329,51.115587],"type":"Point"},"properties":{"name":"Lauseeiche","osm_id":"442440495","tag":{"amenity":"bench","backrest":"yes","natural":"tree"}},"type":"Feature"},
	{"geometry":{"coordinates":[9.984017,51.115982],"type":"Point"},"properties":{"osm_id":"3476263009","tag":{"natural":"tree"}},"type":"Feature"},
	{"geometry":{"coordinates":[9.983899,51.115959],"type":"Point"},"properties":{"osm_id":"3476263018","tag":{"natural":"tree"}},"type":"Feature"},
	{"geometry":{"coordinates":[9.984859,51.11607],"type":"Point"},"properties":{"osm_id":"3476263027","tag":{"natural":"tree"}},"type":"Feature"},
	{"geometry":{"coordinates":[9.983459,51.115861],"type":"Point"},"properties":{"osm_id":"3476263029","tag":{"natural":"tree"}},"type":"Feature"},
	{"geometry":{"coordinates":[9.984752,51.116046],"type":"Point"},"properties":{"osm_id":"3476263064","tag":{"natural":"tree"}},"type":"Feature"},
	{"geometry":{"coordinates":[9.983625,51.115895],"type":"Point"},"properties":{"osm_id":"3476263073","tag":{"natural":"tree"}},"type":"Feature"},
	{"geometry":{"coordinates":[10.004873,51.118409],"type":"Point"},"properties":{"osm_id":"7104104091","tag":{"leaf_type":"broadleaved","natural":"tree"}},"type":"Feature"}
]
}
