{
"type": "FeatureCollection",
"features": [
	{"geometry":{"coordinates":[-85.173284,35.189802],"type":"Point"},"properties":{"name":"Middle Valley Recycling","osm_id":"945904448","tag":{"amenity":"recycling"}},"type":"Feature"},
	{"geometry":{"coordinates":[-85.176309,35.18572],"type":"Point"},"properties":{"name":"Middle Valley Recycling Center","osm_id":"6602972809","tag":{"amenity":"recycling","recycling_type":"centre"}},"type":"Feature"}
]
}
