{
"type": "FeatureCollection",
"features": [
	{"geometry":{"coordinates":[13.514311,55.877111],"type":"Point"},"properties":{"name":"Thousand Year Old Oak","osm_id":"2950993743","tag":{"denotation":"natural_monument","natural":"tree"}},"type":"Feature"}
]
}
