{
"type": "FeatureCollection",
"features": [
	{"geometry":{"coordinates":[1.896456,41.309986],"type":"Point"},"properties":{"name":"Roure del fondo de les Burigues","osm_id":"1670794583","tag":{"natural":"tree","type":"Roure"}},"type":"Feature"}
]
}
