{
"type": "FeatureCollection",
"features": [
	{"geometry":{"coordinates":[33.420361,37.018658],"type":"Point"},"properties":{"name":"mmk metalurji","osm_id":"4828051221","tag":{"amenity":"recycling","name:en":"steel","name:tr":"mmk metalurji"}},"type":"Feature"}
]
}
