{
"type": "FeatureCollection",
"lastupdate": "2020-08-01T00:00:00Z",
"features": [
	{"geometry":{"coordinates":[33.42036,37.018658],"type":"Point"},"properties":{"name":"mmk metalurji","osm_id":"4828051221","tag":{"amenity":"recycling","name:en":"steel","name:tr":"mmk metalurji"}},"type":"Feature"}
]
}
