{
"type": "FeatureCollection",
"features": [
	{"geometry":{"coordinates":[-116.181414,33.699526],"type":"Point"},"properties":{"name":"Valley Scrap","osm_id":"3784921633","tag":{"amenity":"recycling"}},"type":"Feature"}
]
}
