{
"type": "FeatureCollection",
"lastupdate": "2020-07-31T00:00:00Z",
"features": [
	{"geometry":{"coordinates":[-116.181414,33.699525],"type":"Point"},"properties":{"name":"Valley Scrap","osm_id":"3784921633","tag":{"amenity":"recycling"}},"type":"Feature"}
]
}
