{
"type": "FeatureCollection",
"features": [
	{"geometry":{"coordinates":[0.654663,52.224954],"type":"Point"},"properties":{"name":"The Tea Party Oak","osm_id":"1486358416","tag":{"natural":"tree"}},"type":"Feature"},
	{"geometry":{"coordinates":[0.68696,52.266459],"type":"Point"},"properties":{"osm_id":"6374677789","tag":{"natural":"tree"}},"type":"Feature"},
	{"geometry":{"coordinates":[0.686128,52.266935],"type":"Point"},"properties":{"osm_id":"6374677792","tag":{"natural":"tree"}},"type":"Feature"},
	{"geometry":{"coordinates":[0.686622,52.266643],"type":"Point"},"properties":{"osm_id":"6374677794","tag":{"natural":"tree"}},"type":"Feature"},
	{"geometry":{"coordinates":[0.686391,52.266787],"type":"Point"},"properties":{"osm_id":"6374677795","tag":{"natural":"tree"}},"type":"Feature"},
	{"geometry":{"coordinates":[0.687056,52.266397],"type":"Point"},"properties":{"osm_id":"6374677796","tag":{"natural":"tree"}},"type":"Feature"},
	{"geometry":{"coordinates":[0.686515,52.266715],"type":"Point"},"properties":{"osm_id":"6374677797","tag":{"natural":"tree"}},"type":"Feature"},
	{"geometry":{"coordinates":[0.686257,52.266863],"type":"Point"},"properties":{"osm_id":"6374677798","tag":{"natural":"tree"}},"type":"Feature"},
	{"geometry":{"coordinates":[0.687352,52.266226],"type":"Point"},"properties":{"osm_id":"6374677799","tag":{"natural":"tree"}},"type":"Feature"},
	{"geometry":{"coordinates":[0.687717,52.266019],"type":"Point"},"properties":{"osm_id":"6374677800","tag":{"natural":"tree"}},"type":"Feature"},
	{"geometry":{"coordinates":[0.687609,52.266072],"type":"Point"},"properties":{"osm_id":"6374677801","tag":{"natural":"tree"}},"type":"Feature"},
	{"geometry":{"coordinates":[0.68585,52.267083],"type":"Point"},"properties":{"osm_id":"6374677866","tag":{"natural":"tree"}},"type":"Feature"},
	{"geometry":{"coordinates":[0.685973,52.267017],"type":"Point"},"properties":{"osm_id":"6374677867","tag":{"natural":"tree"}},"type":"Feature"}
]
}
