{
"type": "FeatureCollection",
"features": [
	{"geometry":{"coordinates":[0.654663,52.224955],"type":"Point"},"properties":{"name":"The Tea Party Oak","osm_id":"1486358416","tag":{"natural":"tree"}},"type":"Feature"},
	{"geometry":{"coordinates":[0.68696,52.266459],"type":"Point"},"properties":{"osm_id":"6374677789","tag":{"natural":"tree"}},"type":"Feature"},
	{"geometry":{"coordinates":[0.686129,52.266936],"type":"Point"},"properties":{"osm_id":"6374677792","tag":{"natural":"tree"}},"type":"Feature"},
	{"geometry":{"coordinates":[0.686622,52.266643],"type":"Point"},"properties":{"osm_id":"6374677794","tag":{"natural":"tree"}},"type":"Feature"},
	{"geometry":{"coordinates":[0.686392,52.266788],"type":"Point"},"properties":{"osm_id":"6374677795","tag":{"natural":"tree"}},"type":"Feature"},
	{"geometry":{"coordinates":[0.687057,52.266397],"type":"Point"},"properties":{"osm_id":"6374677796","tag":{"natural":"tree"}},"type":"Feature"},
	{"geometry":{"coordinates":[0.686515,52.266716],"type":"Point"},"properties":{"osm_id":"6374677797","tag":{"natural":"tree"}},"type":"Feature"},
	{"geometry":{"coordinates":[0.686258,52.266863],"type":"Point"},"properties":{"osm_id":"6374677798","tag":{"natural":"tree"}},"type":"Feature"},
	{"geometry":{"coordinates":[0.687352,52.266227],"type":"Point"},"properties":{"osm_id":"6374677799","tag":{"natural":"tree"}},"type":"Feature"},
	{"geometry":{"coordinates":[0.687717,52.26602],"type":"Point"},"properties":{"osm_id":"6374677800","tag":{"natural":"tree"}},"type":"Feature"},
	{"geometry":{"coordinates":[0.68761,52.266072],"type":"Point"},"properties":{"osm_id":"6374677801","tag":{"natural":"tree"}},"type":"Feature"},
	{"geometry":{"coordinates":[0.68585,52.267083],"type":"Point"},"properties":{"osm_id":"6374677866","tag":{"natural":"tree"}},"type":"Feature"},
	{"geometry":{"coordinates":[0.685973,52.267018],"type":"Point"},"properties":{"osm_id":"6374677867","tag":{"natural":"tree"}},"type":"Feature"}
]
}
