{
"type": "FeatureCollection",
"features": [
	{"geometry":{"coordinates":[-2.592939,37.861398],"type":"Point"},"properties":{"name":"Chopo del Cortijo de Maza I","osm_id":"3078600756","tag":{"denotation":"natural_monument","monument":"yes","natural":"tree"}},"type":"Feature"},
	{"geometry":{"coordinates":[-2.593094,37.861302],"type":"Point"},"properties":{"name":"Chopo del Cortijo de Maza II","osm_id":"3078600757","tag":{"denotation":"natural_monument","monument":"yes","natural":"tree"}},"type":"Feature"}
]
}
