{
"type": "FeatureCollection",
"lastupdate": "2020-08-03T00:00:00Z",
"features": [
	{"geometry":{"coordinates":[-74.122253,4.724997],"type":"Point"},"properties":{"osm_id":"3420579396","tag":{"amenity":"waste_basket"}},"type":"Feature"},
	{"geometry":{"coordinates":[-74.122691,4.724671],"type":"Point"},"properties":{"osm_id":"3420579397","tag":{"amenity":"waste_basket"}},"type":"Feature"},
	{"geometry":{"coordinates":[-74.123709,4.707729],"type":"Point"},"properties":{"osm_id":"3420847896","tag":{"amenity":"waste_basket"}},"type":"Feature"},
	{"geometry":{"coordinates":[-74.100094,4.706967],"type":"Point"},"properties":{"name":"cas@com","osm_id":"3420887220","tag":{"amenity":"waste_basket"}},"type":"Feature"},
	{"geometry":{"coordinates":[-74.100289,4.70433],"type":"Point"},"properties":{"name":"Dafores","osm_id":"3420887302","tag":{"amenity":"waste_basket"}},"type":"Feature"},
	{"geometry":{"coordinates":[-74.127041,4.672871],"type":"Point"},"properties":{"osm_id":"4109881023","tag":{"amenity":"waste_basket"}},"type":"Feature"},
	{"geometry":{"coordinates":[-74.126521,4.672211],"type":"Point"},"properties":{"osm_id":"4109881024","tag":{"amenity":"waste_basket"}},"type":"Feature"},
	{"geometry":{"coordinates":[-74.114247,4.729673],"type":"Point"},"properties":{"osm_id":"4110743390","tag":{"amenity":"waste_basket"}},"type":"Feature"},
	{"geometry":{"coordinates":[-74.114545,4.729703],"type":"Point"},"properties":{"osm_id":"4110743391","tag":{"amenity":"waste_basket"}},"type":"Feature"},
	{"geometry":{"coordinates":[-74.114443,4.730136],"type":"Point"},"properties":{"osm_id":"4110743400","tag":{"amenity":"waste_basket"}},"type":"Feature"},
	{"geometry":{"coordinates":[-74.110778,4.669703],"type":"Point"},"properties":{"osm_id":"4114686224","tag":{"amenity":"waste_basket"}},"type":"Feature"},
	{"geometry":{"coordinates":[-74.110886,4.669617],"type":"Point"},"properties":{"osm_id":"4114686225","tag":{"amenity":"waste_basket"}},"type":"Feature"},
	{"geometry":{"coordinates":[-74.109917,4.670831],"type":"Point"},"properties":{"osm_id":"4114686267","tag":{"amenity":"waste_basket"}},"type":"Feature"},
	{"geometry":{"coordinates":[-74.110125,4.671409],"type":"Point"},"properties":{"osm_id":"4114686268","tag":{"amenity":"waste_basket"}},"type":"Feature"},
	{"geometry":{"coordinates":[-74.112685,4.658291],"type":"Point"},"properties":{"name":"Mimos y papiros","osm_id":"4115263648","tag":{"amenity":"waste_basket"}},"type":"Feature"},
	{"geometry":{"coordinates":[-74.125907,4.711143],"type":"Point"},"properties":{"osm_id":"4895713323","tag":{"amenity":"waste_basket"}},"type":"Feature"},
	{"geometry":{"coordinates":[-74.148231,4.689062],"type":"Point"},"properties":{"osm_id":"5252641321","tag":{"amenity":"recycling"}},"type":"Feature"}
]
}
