{
"type": "FeatureCollection",
"features": [
	{"geometry":{"coordinates":[-74.122254,4.724998],"type":"Point"},"properties":{"osm_id":"3420579396","tag":{"amenity":"waste_basket"}},"type":"Feature"},
	{"geometry":{"coordinates":[-74.122691,4.724672],"type":"Point"},"properties":{"osm_id":"3420579397","tag":{"amenity":"waste_basket"}},"type":"Feature"},
	{"geometry":{"coordinates":[-74.123709,4.70773],"type":"Point"},"properties":{"osm_id":"3420847896","tag":{"amenity":"waste_basket"}},"type":"Feature"},
	{"geometry":{"coordinates":[-74.100094,4.706968],"type":"Point"},"properties":{"name":"cas@com","osm_id":"3420887220","tag":{"amenity":"waste_basket"}},"type":"Feature"},
	{"geometry":{"coordinates":[-74.10029,4.704331],"type":"Point"},"properties":{"name":"Dafores","osm_id":"3420887302","tag":{"amenity":"waste_basket"}},"type":"Feature"},
	{"geometry":{"coordinates":[-74.127042,4.672872],"type":"Point"},"properties":{"osm_id":"4109881023","tag":{"amenity":"waste_basket"}},"type":"Feature"},
	{"geometry":{"coordinates":[-74.126521,4.672211],"type":"Point"},"properties":{"osm_id":"4109881024","tag":{"amenity":"waste_basket"}},"type":"Feature"},
	{"geometry":{"coordinates":[-74.114247,4.729674],"type":"Point"},"properties":{"osm_id":"4110743390","tag":{"amenity":"waste_basket"}},"type":"Feature"},
	{"geometry":{"coordinates":[-74.114545,4.729703],"type":"Point"},"properties":{"osm_id":"4110743391","tag":{"amenity":"waste_basket"}},"type":"Feature"},
	{"geometry":{"coordinates":[-74.114443,4.730136],"type":"Point"},"properties":{"osm_id":"4110743400","tag":{"amenity":"waste_basket"}},"type":"Feature"},
	{"geometry":{"coordinates":[-74.110778,4.669704],"type":"Point"},"properties":{"osm_id":"4114686224","tag":{"amenity":"waste_basket"}},"type":"Feature"},
	{"geometry":{"coordinates":[-74.110887,4.669617],"type":"Point"},"properties":{"osm_id":"4114686225","tag":{"amenity":"waste_basket"}},"type":"Feature"},
	{"geometry":{"coordinates":[-74.109917,4.670831],"type":"Point"},"properties":{"osm_id":"4114686267","tag":{"amenity":"waste_basket"}},"type":"Feature"},
	{"geometry":{"coordinates":[-74.110126,4.67141],"type":"Point"},"properties":{"osm_id":"4114686268","tag":{"amenity":"waste_basket"}},"type":"Feature"},
	{"geometry":{"coordinates":[-74.112685,4.658292],"type":"Point"},"properties":{"name":"Mimos y papiros","osm_id":"4115263648","tag":{"amenity":"waste_basket"}},"type":"Feature"},
	{"geometry":{"coordinates":[-74.125908,4.711144],"type":"Point"},"properties":{"osm_id":"4895713323","tag":{"amenity":"waste_basket"}},"type":"Feature"},
	{"geometry":{"coordinates":[-74.148232,4.689062],"type":"Point"},"properties":{"osm_id":"5252641321","tag":{"amenity":"recycling"}},"type":"Feature"}
]
}
