{
"type": "FeatureCollection",
"lastupdate": "2020-08-06T00:00:00Z",
"features": [
	{"geometry":{"coordinates":[-42.224555,-14.475856],"type":"Point"},"properties":{"name":"Cooperativa de catadores","osm_id":"1643077684","tag":{"amenity":"recycling","recycling_type":"centre"}},"type":"Feature"}
]
}
