{
"type": "FeatureCollection",
"features": [
	{"geometry":{"coordinates":[-42.224556,-14.475856],"type":"Point"},"properties":{"name":"Cooperativa de catadores","osm_id":"1643077684","tag":{"amenity":"recycling","recycling_type":"centre"}},"type":"Feature"}
]
}
