{
"type": "FeatureCollection",
"features": [
	{"geometry":{"coordinates":[-42.224518,-14.475796],"type":"Point"},"properties":{"name":"Cooperativa de catadores","osm_id":"1643077684","tag":{"amenity":"recycling","recycling_type":"centre"}},"type":"Feature"}
]
}
