{
"type": "FeatureCollection",
"features": [
	{"geometry":{"coordinates":[-100.188278,25.472898],"type":"Point"},"properties":{"osm_id":"2491362894","tag":{"height":"3","name:botanical":"Fresno","natural":"tree"}},"type":"Feature"}
]
}
