{
"type": "FeatureCollection",
"features": [
	{"geometry":{"coordinates":[-89.897892,16.928621],"type":"Point"},"properties":{"osm_id":"2791271436","tag":{"natural":"tree"}},"type":"Feature"},
	{"geometry":{"coordinates":[-89.902201,16.926033],"type":"Point"},"properties":{"name":"ficus","osm_id":"2791271439","tag":{"natural":"tree"}},"type":"Feature"},
	{"geometry":{"coordinates":[-89.891639,16.93045],"type":"Point"},"properties":{"osm_id":"3068006308","tag":{"natural":"tree"}},"type":"Feature"},
	{"geometry":{"coordinates":[-89.891902,16.930299],"type":"Point"},"properties":{"osm_id":"3068007415","tag":{"natural":"tree"}},"type":"Feature"},
	{"geometry":{"coordinates":[-89.905041,16.920418],"type":"Point"},"properties":{"osm_id":"3068007416","tag":{"natural":"tree"}},"type":"Feature"},
	{"geometry":{"coordinates":[-89.891838,16.930504],"type":"Point"},"properties":{"osm_id":"3068007417","tag":{"natural":"tree"}},"type":"Feature"},
	{"geometry":{"coordinates":[-89.891668,16.928362],"type":"Point"},"properties":{"osm_id":"3071725059","tag":{"natural":"tree"}},"type":"Feature"},
	{"geometry":{"coordinates":[-89.892247,16.928411],"type":"Point"},"properties":{"osm_id":"3071725060","tag":{"natural":"tree"}},"type":"Feature"},
	{"geometry":{"coordinates":[-89.891066,16.926668],"type":"Point"},"properties":{"osm_id":"3071725061","tag":{"natural":"tree"}},"type":"Feature"},
	{"geometry":{"coordinates":[-89.891242,16.928264],"type":"Point"},"properties":{"osm_id":"3071725062","tag":{"natural":"tree"}},"type":"Feature"},
	{"geometry":{"coordinates":[-89.885411,16.919117],"type":"Point"},"properties":{"osm_id":"3071725063","tag":{"natural":"tree"}},"type":"Feature"},
	{"geometry":{"coordinates":[-89.885057,16.919184],"type":"Point"},"properties":{"osm_id":"3071725064","tag":{"natural":"tree"}},"type":"Feature"},
	{"geometry":{"coordinates":[-89.892414,16.928416],"type":"Point"},"properties":{"osm_id":"3071725065","tag":{"natural":"tree"}},"type":"Feature"},
	{"geometry":{"coordinates":[-89.89216,16.922028],"type":"Point"},"properties":{"osm_id":"3071725066","tag":{"natural":"tree"}},"type":"Feature"},
	{"geometry":{"coordinates":[-89.901584,16.925691],"type":"Point"},"properties":{"osm_id":"3100523920","tag":{"natural":"tree"}},"type":"Feature"},
	{"geometry":{"coordinates":[-89.88566,16.918732],"type":"Point"},"properties":{"osm_id":"3100523927","tag":{"natural":"tree"}},"type":"Feature"},
	{"geometry":{"coordinates":[-89.905095,16.920053],"type":"Point"},"properties":{"osm_id":"3100526930","tag":{"natural":"tree"}},"type":"Feature"}
]
}
