{
"type": "FeatureCollection",
"features": [
	{"geometry":{"coordinates":[-122.472024,49.318433],"type":"Point"},"properties":{"name":"Sani-station","osm_id":"5166695524","tag":{"amenity":"waste_disposal","waste":"sewage"}},"type":"Feature"},
	{"geometry":{"coordinates":[-122.454769,49.324736],"type":"Point"},"properties":{"osm_id":"8822681725","tag":{"amenity":"waste_basket"}},"type":"Feature"},
	{"geometry":{"coordinates":[-122.491342,49.289674],"type":"Point"},"properties":{"osm_id":"9018930871","tag":{"amenity":"waste_basket","material":"metal"}},"type":"Feature"},
	{"geometry":{"coordinates":[-122.48973,49.292246],"type":"Point"},"properties":{"osm_id":"9018932019","tag":{"amenity":"waste_basket","material":"metal"}},"type":"Feature"}
]
}
