{
"type": "FeatureCollection",
"features": [
	{"geometry":{"coordinates":[-122.472025,49.318433],"type":"Point"},"properties":{"name":"Sani-station","osm_id":"5166695524","tag":{"amenity":"waste_disposal","waste":"sewage"}},"type":"Feature"}
]
}
