{
"type": "FeatureCollection",
"features": [
	{"geometry":{"coordinates":[-122.472024,49.318433],"type":"Point"},"properties":{"name":"Sani-station","osm_id":"5166695524","tag":{"amenity":"waste_disposal","waste":"sewage"}},"type":"Feature"},
	{"geometry":{"coordinates":[-122.454769,49.324736],"type":"Point"},"properties":{"osm_id":"8822681725","tag":{"amenity":"waste_basket"}},"type":"Feature"}
]
}
