{
"type": "FeatureCollection",
"features": [
	{"geometry":{"coordinates":[-55.124034,-29.549806],"type":"Point"},"properties":{"name":"centro","osm_id":"8975923342","tag":{"landuse":"recreation_ground","leisure":"park"}},"type":"Feature"},
	{"geometry":{"coordinates":[-55.124594,-29.549988],"type":"Point"},"properties":{"osm_id":"8975923342","tag":{"natural":"tree"}},"type":"Feature"}
]
}
