{
"type": "FeatureCollection",
"features": [
	{"geometry":{"coordinates":[10.388884,60.240369],"type":"Point"},"properties":{"osm_id":"5555193814","tag":{"amenity":"recycling","description":"Coop Mega, Jevnaker","recycling:glass_bottles":"yes","recycling_type":"container","ref:sortere":"240"}},"type":"Feature"},
	{"geometry":{"coordinates":[10.441171,60.260895],"type":"Point"},"properties":{"name":"Restavfall","osm_id":"6558459162","tag":{"amenity":"waste_disposal","image":"https://images.mapillary.com/oF1-IjnUc0d9WT-Si7HGMw/thumb-2048.jpg","mapillary":"https://www.mapillary.com/map/im/oF1-IjnUc0d9WT-Si7HGMw"}},"type":"Feature"}
]
}
