{
"type": "FeatureCollection",
"lastupdate": "2020-08-05T00:00:00Z",
"features": [
	{"geometry":{"coordinates":[10.437743,59.938689],"type":"Point"},"properties":{"name":"Isi gjenvinningsstasjon","osm_id":"5555204280","tag":{"amenity":"recycling","phone":"+47 67174330","recycling:asbestos":"yes","recycling:batteries":"yes","recycling:boats":"yes","recycling:clothes":"yes","recycling:drugs":"yes","recycling:electrical_items":"yes","recycling:garden_waste":"yes","recycling:glass":"yes","recycling:glass_bottles":"yes","recycling:hazardous_waste":"yes","recycling:marine_waste":"yes","recycling:metal":"yes","recycling:paper":"yes","recycling:plasterboard":"yes","recycling:plastic":"yes","recycling:polystyrene_foam":"yes","recycling:rubble":"yes","recycling:scrap_metal":"yes","recycling:second_hand":"yes","recycling:tyres":"yes","recycling:waste":"yes","recycling:wood":"yes","recycling_type":"centre","ref:sortere":"1187"}},"type":"Feature"}
]
}
