{
"type": "FeatureCollection",
"features": [
	{"geometry":{"coordinates":[10.407494,50.7825],"type":"Point"},"properties":{"osm_id":"1535073817","tag":{"amenity":"recycling"}},"type":"Feature"},
	{"geometry":{"coordinates":[10.3749,50.737611],"type":"Point"},"properties":{"osm_id":"2472552213","tag":{"amenity":"recycling","location":"overground","recycling_type":"container"}},"type":"Feature"},
	{"geometry":{"coordinates":[10.384103,50.767456],"type":"Point"},"properties":{"osm_id":"6596338137","tag":{"amenity":"recycling","recycling_type":"container"}},"type":"Feature"}
]
}
