{
"type": "FeatureCollection",
"features": [
	{"geometry":{"coordinates":[10.407494,50.7825],"type":"Point"},"properties":{"osm_id":"1535073817","tag":{"amenity":"recycling"}},"type":"Feature"},
	{"geometry":{"coordinates":[10.374899,50.73761],"type":"Point"},"properties":{"osm_id":"2472552213","tag":{"amenity":"recycling","location":"overground","recycling:cardboard":"yes","recycling:cartons":"yes","recycling:clothes":"yes","recycling:glass":"yes","recycling:glass_bottles":"yes","recycling:magazines":"yes","recycling:newspaper":"yes","recycling:paper":"yes","recycling:paper_packaging":"yes","recycling_type":"container"}},"type":"Feature"},
	{"geometry":{"coordinates":[10.384102,50.767456],"type":"Point"},"properties":{"osm_id":"6596338137","tag":{"amenity":"recycling","recycling_type":"container"}},"type":"Feature"}
]
}
