{
"type": "FeatureCollection",
"features": [
	{"geometry":{"coordinates":[10.429883,46.958036],"type":"Point"},"properties":{"name":"Recyclinghof Runggal","osm_id":"8094035686","tag":{"amenity":"recycling","recycling_type":"centre"}},"type":"Feature"}
]
}
