{
"type": "FeatureCollection",
"features": [
	{"geometry":{"coordinates":[10.429883,46.958036],"type":"Point"},"properties":{"name":"Recyclinghof Runggal","osm_id":"8094035686","tag":{"amenity":"recycling","recycling_type":"centre"}},"type":"Feature"},
	{"geometry":{"coordinates":[10.392363,46.959676],"type":"Point"},"properties":{"osm_id":"8977413614","tag":{"amenity":"recycling","recycling:aluminium":"yes","recycling:cans":"yes","recycling:glass":"yes","recycling:glass_bottles":"yes","recycling_type":"container"}},"type":"Feature"},
	{"geometry":{"coordinates":[10.397413,46.96037],"type":"Point"},"properties":{"osm_id":"8977413615","tag":{"amenity":"recycling","recycling:aluminium":"yes","recycling:cans":"yes","recycling:glass":"yes","recycling:glass_bottles":"yes","recycling_type":"container"}},"type":"Feature"}
]
}
