{
"type": "FeatureCollection",
"features": [
	{"geometry":{"coordinates":[12.227415,61.285897],"type":"Point"},"properties":{"osm_id":"1177503278","tag":{"amenity":"waste_basket"}},"type":"Feature"},
	{"geometry":{"coordinates":[12.230745,61.28208],"type":"Point"},"properties":{"osm_id":"1177504729","tag":{"amenity":"waste_basket"}},"type":"Feature"},
	{"geometry":{"coordinates":[12.265455,61.301226],"type":"Point"},"properties":{"name":"Trysil gjenvinningsstasjonen","osm_id":"5555203272","tag":{"amenity":"recycling","phone":"+47 62 45 34","recycling:batteries":"yes","recycling:electrical_items":"yes","recycling:garden_waste":"yes","recycling:glass":"yes","recycling:glass_bottles":"yes","recycling:hazardous_waste":"yes","recycling:paper":"yes","recycling:rubble":"yes","recycling:scrap_metal":"yes","recycling:tyres":"yes","recycling:waste":"yes","recycling:wood":"yes","recycling_type":"centre","ref:sortere":"1298"}},"type":"Feature"}
]
}
