{
"type": "FeatureCollection",
"lastupdate": "2020-08-01T00:00:00Z",
"features": [
	{"geometry":{"coordinates":[12.256661,48.472572],"type":"Point"},"properties":{"osm_id":"924560202","tag":{"amenity":"recycling","recycling:glass_bottles":"yes","recycling_type":"container"}},"type":"Feature"},
	{"geometry":{"coordinates":[12.274611,48.488592],"type":"Point"},"properties":{"name":"Bauschuttannahmestelle Feuerberg","osm_id":"2181214528","tag":{"amenity":"recycling","recycling:batteries":"no","recycling:books":"no","recycling:cans":"no","recycling:cardboard":"no","recycling:cartons":"no","recycling:clothes":"no","recycling:electrical_appliances":"no","recycling:glass":"no","recycling:glass_bottles":"no","recycling:green_waste":"no","recycling:magazines":"no","recycling:newspaper":"no","recycling:paper":"no","recycling:paper_packaging":"no","recycling:plastic":"no","recycling:plastic_bottles":"no","recycling:plastic_packaging":"no","recycling:scrap_metal":"no","recycling:small_appliances":"no","recycling:waste":"no","recycling:wood":"no","recycling_type":"centre"}},"type":"Feature"},
	{"geometry":{"coordinates":[12.248376,48.473973],"type":"Point"},"properties":{"osm_id":"4249501401","tag":{"amenity":"waste_basket"}},"type":"Feature"}
]
}
