{
"type": "FeatureCollection",
"features": [
	{"geometry":{"coordinates":[12.296869,45.198104],"type":"Point"},"properties":{"osm_id":"1065711259","tag":{"amenity":"waste_basket"}},"type":"Feature"},
	{"geometry":{"coordinates":[12.296288,45.199403],"type":"Point"},"properties":{"osm_id":"1065711413","tag":{"amenity":"waste_basket"}},"type":"Feature"},
	{"geometry":{"coordinates":[12.273013,45.206857],"type":"Point"},"properties":{"name":"Ecocentro Chioggia","osm_id":"1547397448","tag":{"amenity":"recycling","recycling:clothes":"yes","recycling:glass":"yes","recycling:paper":"yes"}},"type":"Feature"},
	{"geometry":{"coordinates":[12.303163,45.190333],"type":"Point"},"properties":{"osm_id":"3767116767","tag":{"amenity":"recycling","recycling_type":"container"}},"type":"Feature"},
	{"geometry":{"coordinates":[12.303233,45.190367],"type":"Point"},"properties":{"osm_id":"3767116768","tag":{"amenity":"recycling","recycling_type":"container"}},"type":"Feature"},
	{"geometry":{"coordinates":[12.300581,45.201667],"type":"Point"},"properties":{"osm_id":"5918619560","tag":{"amenity":"waste_basket"}},"type":"Feature"},
	{"geometry":{"coordinates":[12.300657,45.202281],"type":"Point"},"properties":{"osm_id":"5918819318","tag":{"amenity":"waste_basket"}},"type":"Feature"},
	{"geometry":{"coordinates":[12.285258,45.206071],"type":"Point"},"properties":{"osm_id":"5920583781","tag":{"amenity":"waste_basket"}},"type":"Feature"},
	{"geometry":{"coordinates":[12.277037,45.198889],"type":"Point"},"properties":{"osm_id":"6957939125","tag":{"amenity":"recycling","recycling_type":"container"}},"type":"Feature"}
]
}
