{
"type": "FeatureCollection",
"features": [
	{"geometry":{"coordinates":[4.397504,50.701727],"type":"Point"},"properties":{"osm_id":"462199939","tag":{"amenity":"recycling","recycling:glass_bottles":"yes"}},"type":"Feature"},
	{"geometry":{"coordinates":[4.40034,50.701235],"type":"Point"},"properties":{"osm_id":"471203829","tag":{"amenity":"recycling","recycling:glass_bottles":"yes","recycling_type":"container"}},"type":"Feature"},
	{"geometry":{"coordinates":[4.413806,50.69497],"type":"Point"},"properties":{"osm_id":"472661370","tag":{"amenity":"recycling","recycling:glass_bottles":"yes","recycling_type":"container"}},"type":"Feature"},
	{"geometry":{"coordinates":[4.402477,50.69645],"type":"Point"},"properties":{"osm_id":"475359739","tag":{"amenity":"recycling","recycling:glass_bottles":"yes"}},"type":"Feature"},
	{"geometry":{"coordinates":[4.416676,50.709878],"type":"Point"},"properties":{"osm_id":"1100670631","tag":{"amenity":"recycling"}},"type":"Feature"},
	{"geometry":{"coordinates":[4.413044,50.701773],"type":"Point"},"properties":{"osm_id":"3966885689","tag":{"amenity":"recycling","recycling:clothes":"yes","recycling:glass_bottles":"yes","recycling_type":"container"}},"type":"Feature"},
	{"geometry":{"coordinates":[4.441118,50.721341],"type":"Point"},"properties":{"osm_id":"4351585020","tag":{"amenity":"waste_basket"}},"type":"Feature"},
	{"geometry":{"coordinates":[4.476349,50.690198],"type":"Point"},"properties":{"osm_id":"4621832323","tag":{"amenity":"recycling","recycling_type":"container"}},"type":"Feature"},
	{"geometry":{"coordinates":[4.466813,50.736381],"type":"Point"},"properties":{"osm_id":"6188010549","tag":{"amenity":"waste_basket"}},"type":"Feature"},
	{"geometry":{"coordinates":[4.460654,50.736031],"type":"Point"},"properties":{"osm_id":"7141271720","tag":{"amenity":"waste_basket"}},"type":"Feature"},
	{"geometry":{"coordinates":[4.397434,50.70155],"type":"Point"},"properties":{"osm_id":"7518719440","tag":{"amenity":"recycling","operator":"Les Petits Riens-Spullen Hulp","recycling:clothes":"yes","recycling:shoes":"yes","recycling_type":"container","website":"https://petitsriens.be"}},"type":"Feature"}
]
}
