{
"type": "FeatureCollection",
"features": [
	{"geometry":{"coordinates":[4.397504,50.701726],"type":"Point"},"properties":{"osm_id":"462199939","tag":{"amenity":"recycling","recycling:glass_bottles":"yes"}},"type":"Feature"},
	{"geometry":{"coordinates":[4.400339,50.701235],"type":"Point"},"properties":{"osm_id":"471203829","tag":{"amenity":"recycling","recycling:glass_bottles":"yes","recycling_type":"container"}},"type":"Feature"},
	{"geometry":{"coordinates":[4.413805,50.694969],"type":"Point"},"properties":{"osm_id":"472661370","tag":{"amenity":"recycling","recycling:glass_bottles":"yes","recycling_type":"container"}},"type":"Feature"},
	{"geometry":{"coordinates":[4.402476,50.69645],"type":"Point"},"properties":{"osm_id":"475359739","tag":{"amenity":"recycling","recycling:glass_bottles":"yes"}},"type":"Feature"},
	{"geometry":{"coordinates":[4.416675,50.709878],"type":"Point"},"properties":{"osm_id":"1100670631","tag":{"amenity":"recycling"}},"type":"Feature"},
	{"geometry":{"coordinates":[4.413043,50.701772],"type":"Point"},"properties":{"osm_id":"3966885689","tag":{"amenity":"recycling","recycling:clothes":"yes","recycling:glass_bottles":"yes","recycling_type":"container"}},"type":"Feature"},
	{"geometry":{"coordinates":[4.441118,50.721341],"type":"Point"},"properties":{"osm_id":"4351585020","tag":{"amenity":"waste_basket"}},"type":"Feature"},
	{"geometry":{"coordinates":[4.476349,50.690197],"type":"Point"},"properties":{"osm_id":"4621832323","tag":{"amenity":"recycling","recycling_type":"container"}},"type":"Feature"},
	{"geometry":{"coordinates":[4.466812,50.73638],"type":"Point"},"properties":{"osm_id":"6188010549","tag":{"amenity":"waste_basket"}},"type":"Feature"},
	{"geometry":{"coordinates":[4.460654,50.73603],"type":"Point"},"properties":{"osm_id":"7141271720","tag":{"amenity":"waste_basket"}},"type":"Feature"},
	{"geometry":{"coordinates":[4.397434,50.70155],"type":"Point"},"properties":{"osm_id":"7518719440","tag":{"amenity":"recycling","operator":"Les Petits Riens-Spullen Hulp","recycling:clothes":"yes","recycling:shoes":"yes","recycling_type":"container","website":"https://petitsriens.be"}},"type":"Feature"},
	{"geometry":{"coordinates":[4.469527,50.736044],"type":"Point"},"properties":{"osm_id":"8222829687","tag":{"amenity":"waste_basket"}},"type":"Feature"},
	{"geometry":{"coordinates":[4.469488,50.736073],"type":"Point"},"properties":{"osm_id":"8222829687","tag":{"amenity":"waste_basket"}},"type":"Feature"},
	{"geometry":{"coordinates":[4.469229,50.736358],"type":"Point"},"properties":{"osm_id":"8222829688","tag":{"amenity":"waste_basket"}},"type":"Feature"},
	{"geometry":{"coordinates":[4.469252,50.736333],"type":"Point"},"properties":{"osm_id":"8222829688","tag":{"amenity":"waste_basket"}},"type":"Feature"},
	{"geometry":{"coordinates":[4.467587,50.735634],"type":"Point"},"properties":{"osm_id":"8222829690","tag":{"amenity":"waste_basket"}},"type":"Feature"},
	{"geometry":{"coordinates":[4.467018,50.734697],"type":"Point"},"properties":{"osm_id":"8222829691","tag":{"amenity":"waste_basket"}},"type":"Feature"},
	{"geometry":{"coordinates":[4.465822,50.735351],"type":"Point"},"properties":{"osm_id":"8222829692","tag":{"amenity":"waste_basket"}},"type":"Feature"},
	{"geometry":{"coordinates":[4.457748,50.73286],"type":"Point"},"properties":{"osm_id":"8222829693","tag":{"amenity":"waste_basket"}},"type":"Feature"},
	{"geometry":{"coordinates":[4.457875,50.73264],"type":"Point"},"properties":{"osm_id":"8222829694","tag":{"amenity":"waste_basket"}},"type":"Feature"},
	{"geometry":{"coordinates":[4.4583,50.732645],"type":"Point"},"properties":{"osm_id":"8222829695","tag":{"amenity":"waste_basket"}},"type":"Feature"},
	{"geometry":{"coordinates":[4.466887,50.736032],"type":"Point"},"properties":{"osm_id":"8222829700","tag":{"amenity":"waste_basket"}},"type":"Feature"},
	{"geometry":{"coordinates":[4.466888,50.736024],"type":"Point"},"properties":{"osm_id":"8222829700","tag":{"amenity":"waste_basket"}},"type":"Feature"},
	{"geometry":{"coordinates":[4.45772,50.732128],"type":"Point"},"properties":{"osm_id":"8222829701","tag":{"amenity":"waste_basket"}},"type":"Feature"},
	{"geometry":{"coordinates":[4.457749,50.732059],"type":"Point"},"properties":{"osm_id":"8222829702","tag":{"amenity":"waste_basket"}},"type":"Feature"},
	{"geometry":{"coordinates":[4.457653,50.732196],"type":"Point"},"properties":{"osm_id":"8222829703","tag":{"amenity":"waste_basket"}},"type":"Feature"},
	{"geometry":{"coordinates":[4.45756,50.732041],"type":"Point"},"properties":{"osm_id":"8222829704","tag":{"amenity":"waste_basket"}},"type":"Feature"},
	{"geometry":{"coordinates":[4.468139,50.735685],"type":"Point"},"properties":{"osm_id":"8222980200","tag":{"amenity":"waste_basket"}},"type":"Feature"}
]
}
