{
"type": "FeatureCollection",
"lastupdate": "2020-08-06T00:00:00Z",
"features": [
	{"geometry":{"coordinates":[4.397504,50.701726],"type":"Point"},"properties":{"osm_id":"462199939","tag":{"amenity":"recycling","recycling:glass_bottles":"yes"}},"type":"Feature"},
	{"geometry":{"coordinates":[4.400339,50.701235],"type":"Point"},"properties":{"osm_id":"471203829","tag":{"amenity":"recycling","recycling:glass_bottles":"yes","recycling_type":"container"}},"type":"Feature"},
	{"geometry":{"coordinates":[4.413805,50.694969],"type":"Point"},"properties":{"osm_id":"472661370","tag":{"amenity":"recycling","recycling:glass_bottles":"yes","recycling_type":"container"}},"type":"Feature"},
	{"geometry":{"coordinates":[4.402476,50.69645],"type":"Point"},"properties":{"osm_id":"475359739","tag":{"amenity":"recycling","recycling:glass_bottles":"yes"}},"type":"Feature"},
	{"geometry":{"coordinates":[4.416675,50.709878],"type":"Point"},"properties":{"osm_id":"1100670631","tag":{"amenity":"recycling"}},"type":"Feature"},
	{"geometry":{"coordinates":[4.413043,50.701772],"type":"Point"},"properties":{"osm_id":"3966885689","tag":{"amenity":"recycling","recycling:clothes":"yes","recycling:glass_bottles":"yes","recycling_type":"container"}},"type":"Feature"},
	{"geometry":{"coordinates":[4.441118,50.721341],"type":"Point"},"properties":{"osm_id":"4351585020","tag":{"amenity":"waste_basket"}},"type":"Feature"},
	{"geometry":{"coordinates":[4.476349,50.690197],"type":"Point"},"properties":{"osm_id":"4621832323","tag":{"amenity":"recycling","recycling_type":"container"}},"type":"Feature"},
	{"geometry":{"coordinates":[4.466812,50.73638],"type":"Point"},"properties":{"osm_id":"6188010549","tag":{"amenity":"waste_basket"}},"type":"Feature"},
	{"geometry":{"coordinates":[4.460654,50.73603],"type":"Point"},"properties":{"osm_id":"7141271720","tag":{"amenity":"waste_basket"}},"type":"Feature"},
	{"geometry":{"coordinates":[4.397434,50.70155],"type":"Point"},"properties":{"osm_id":"7518719440","tag":{"amenity":"recycling","operator":"Les Petits Riens-Spullen Hulp","recycling:clothes":"yes","recycling:shoes":"yes","recycling_type":"container","website":"https://petitsriens.be"}},"type":"Feature"}
]
}
