{
"type": "FeatureCollection",
"lastupdate": "2020-08-05T00:00:00Z",
"features": [
	{"geometry":{"coordinates":[4.421829,44.014205],"type":"Point"},"properties":{"osm_id":"1683093065","tag":{"amenity":"waste_basket"}},"type":"Feature"},
	{"geometry":{"coordinates":[4.426417,44.012069],"type":"Point"},"properties":{"osm_id":"2390026845","tag":{"amenity":"waste_basket"}},"type":"Feature"},
	{"geometry":{"coordinates":[4.418636,44.011864],"type":"Point"},"properties":{"name":"poubelle","osm_id":"2841597300","tag":{"amenity":"waste_basket","name:en":"rubbish bin"}},"type":"Feature"},
	{"geometry":{"coordinates":[4.420023,44.019341],"type":"Point"},"properties":{"osm_id":"3757627636","tag":{"amenity":"recycling","operator":"SICTOMU","recycling:cans":"yes","recycling:clothes":"no","recycling:glass":"yes","recycling:glass_bottles":"yes","recycling:paper":"yes","recycling:plastic":"yes","recycling_type":"container"}},"type":"Feature"},
	{"geometry":{"coordinates":[4.415944,44.01145],"type":"Point"},"properties":{"osm_id":"4303845076","tag":{"amenity":"recycling"}},"type":"Feature"},
	{"geometry":{"coordinates":[4.423051,44.011819],"type":"Point"},"properties":{"osm_id":"4442158602","tag":{"amenity":"recycling","recycling:glass_bottles":"yes","recycling_type":"container"}},"type":"Feature"}
]
}
