{
"type": "FeatureCollection",
"features": [
	{"geometry":{"coordinates":[0.985364,47.416486],"type":"Point"},"properties":{"osm_id":"594785619","tag":{"amenity":"recycling","recycling:glass":"yes"}},"type":"Feature"},
	{"geometry":{"coordinates":[0.987024,47.417286],"type":"Point"},"properties":{"osm_id":"594785633","tag":{"amenity":"recycling","recycling:glass":"yes"}},"type":"Feature"},
	{"geometry":{"coordinates":[1.011981,47.403378],"type":"Point"},"properties":{"osm_id":"2199920622","tag":{"amenity":"waste_basket"}},"type":"Feature"},
	{"geometry":{"coordinates":[1.007271,47.404581],"type":"Point"},"properties":{"osm_id":"2199920637","tag":{"amenity":"waste_basket"}},"type":"Feature"},
	{"geometry":{"coordinates":[0.986588,47.410144],"type":"Point"},"properties":{"osm_id":"2199947691","tag":{"amenity":"waste_basket","check_date":"2021-06-26"}},"type":"Feature"},
	{"geometry":{"coordinates":[0.986107,47.410209],"type":"Point"},"properties":{"osm_id":"2199947692","tag":{"amenity":"waste_basket"}},"type":"Feature"},
	{"geometry":{"coordinates":[0.994216,47.408667],"type":"Point"},"properties":{"osm_id":"2293834690","tag":{"amenity":"recycling","location":"overground","recycling:glass":"yes","recycling:paper":"yes","recycling_type":"container"}},"type":"Feature"},
	{"geometry":{"coordinates":[0.985666,47.413016],"type":"Point"},"properties":{"osm_id":"3035683244","tag":{"amenity":"waste_basket"}},"type":"Feature"},
	{"geometry":{"coordinates":[0.9863,47.413069],"type":"Point"},"properties":{"osm_id":"3035683245","tag":{"amenity":"waste_basket"}},"type":"Feature"},
	{"geometry":{"coordinates":[1.051017,47.434447],"type":"Point"},"properties":{"osm_id":"3059201266","tag":{"amenity":"recycling","recycling:glass":"yes","recycling_type":"container"}},"type":"Feature"},
	{"geometry":{"coordinates":[0.981926,47.404192],"type":"Point"},"properties":{"osm_id":"3060630227","tag":{"amenity":"recycling","recycling:cans":"yes","recycling:glass":"yes","recycling:paper":"yes"}},"type":"Feature"},
	{"geometry":{"coordinates":[0.98245,47.402975],"type":"Point"},"properties":{"osm_id":"3060632729","tag":{"amenity":"recycling","recycling:cans":"yes","recycling:glass":"yes","recycling:paper":"yes"}},"type":"Feature"},
	{"geometry":{"coordinates":[1.009517,47.413461],"type":"Point"},"properties":{"osm_id":"3079863801","tag":{"amenity":"recycling","recycling:cans":"yes","recycling:clothes":"yes","recycling:glass_bottles":"yes","recycling:paper":"yes"}},"type":"Feature"},
	{"geometry":{"coordinates":[0.975855,47.399691],"type":"Point"},"properties":{"osm_id":"5321956318","tag":{"amenity":"recycling","capacity":"2","location":"overground","recycling:glass_bottles":"yes","recycling_type":"container"}},"type":"Feature"},
	{"geometry":{"coordinates":[0.980923,47.41217],"type":"Point"},"properties":{"osm_id":"8380603153","tag":{"amenity":"waste_basket"}},"type":"Feature"},
	{"geometry":{"coordinates":[0.981892,47.415225],"type":"Point"},"properties":{"osm_id":"9090799918","tag":{"amenity":"waste_basket","survey:date":"2021-09-13"}},"type":"Feature"},
	{"geometry":{"coordinates":[0.98147,47.415194],"type":"Point"},"properties":{"osm_id":"9090804318","tag":{"amenity":"waste_basket","survey:date":"2021-09-13"}},"type":"Feature"},
	{"geometry":{"coordinates":[0.982019,47.415658],"type":"Point"},"properties":{"osm_id":"9090804319","tag":{"amenity":"waste_basket","survey:date":"2021-09-13"}},"type":"Feature"}
]
}
