{
"type": "FeatureCollection",
"lastupdate": "2020-08-02T00:00:00Z",
"features": [
	{"geometry":{"coordinates":[15.501957,60.528608],"type":"Point"},"properties":{"osm_id":"420117400","tag":{"amenity":"recycling","recycling:batteries":"yes","recycling:cardboard":"yes","recycling:electrical_appliances":"yes","recycling:engine_oil":"yes","recycling:glass":"yes","recycling:glass_bottles":"yes","recycling:green_waste":"yes","recycling:mobile_phones":"yes","recycling:paper":"yes","recycling:plastic":"yes","recycling:scrap_metal":"yes","recycling:small_appliances":"yes","recycling:tyres":"yes","recycling:white_goods":"yes","recycling:wood":"yes","recycling_type":"centre"}},"type":"Feature"},
	{"geometry":{"coordinates":[15.502724,60.528317],"type":"Point"},"properties":{"osm_id":"1368393031","tag":{"amenity":"recycling","recycling:batteries":"yes","recycling:glass":"yes","recycling:glass_bottles":"yes","recycling:paper":"yes","recycling:plastic":"yes","recycling_type":"container"}},"type":"Feature"},
	{"geometry":{"coordinates":[15.533409,60.503325],"type":"Point"},"properties":{"name":"Hundlatrin","osm_id":"1676537469","tag":{"amenity":"waste_basket"}},"type":"Feature"},
	{"geometry":{"coordinates":[15.543982,60.50572],"type":"Point"},"properties":{"name":"Hundlatrin","osm_id":"1676539348","tag":{"amenity":"waste_basket"}},"type":"Feature"},
	{"geometry":{"coordinates":[15.542114,60.508488],"type":"Point"},"properties":{"osm_id":"2242444502","tag":{"amenity":"recycling","recycling_type":"container"}},"type":"Feature"},
	{"geometry":{"coordinates":[15.537927,60.505154],"type":"Point"},"properties":{"name":"Hundlatrin","osm_id":"2247066144","ref":"169","tag":{"amenity":"waste_basket"}},"type":"Feature"},
	{"geometry":{"coordinates":[15.55221,60.50761],"type":"Point"},"properties":{"osm_id":"6703895998","tag":{"amenity":"waste_basket"}},"type":"Feature"}
]
}
