{
"type": "FeatureCollection",
"lastupdate": "2020-08-02T00:00:00Z",
"features": [
	{"geometry":{"coordinates":[15.483464,48.84389],"type":"Point"},"properties":{"name":"Recyclingcontainer","osm_id":"3217979794","tag":{"amenity":"recycling","recycling:cans":"yes","recycling:clothes":"no","recycling:glass":"yes","recycling:paper":"no"}},"type":"Feature"}
]
}
