{
"type": "FeatureCollection",
"features": [
	{"geometry":{"coordinates":[15.506132,46.961429],"type":"Point"},"properties":{"osm_id":"568364275","tag":{"amenity":"recycling","recycling:batteries":"yes","recycling:cans":"yes","recycling:chemicals":"yes","recycling:electrical_appliances":"yes","recycling:glass_bottles":"yes","recycling:oil":"yes","recycling:organic":"yes","recycling:paper":"yes","recycling:plastic_packaging":"yes","recycling:wood":"yes","recycling_type":"centre"}},"type":"Feature"},
	{"geometry":{"coordinates":[15.482606,46.964302],"type":"Point"},"properties":{"osm_id":"834760590","tag":{"amenity":"recycling","recycling:cans":"yes","recycling:glass":"yes","recycling_type":"container"}},"type":"Feature"},
	{"geometry":{"coordinates":[15.487997,46.94509],"type":"Point"},"properties":{"osm_id":"1911563572","tag":{"amenity":"waste_basket"}},"type":"Feature"},
	{"geometry":{"coordinates":[15.482125,46.963829],"type":"Point"},"properties":{"osm_id":"1911563722","tag":{"amenity":"waste_basket"}},"type":"Feature"},
	{"geometry":{"coordinates":[15.510995,46.932236],"type":"Point"},"properties":{"osm_id":"7157684430","tag":{"access":"yes","amenity":"recycling","recycling:glass_bottles":"yes","recycling_type":"container","waste":"glass"}},"type":"Feature"},
	{"geometry":{"coordinates":[15.484449,46.965313],"type":"Point"},"properties":{"osm_id":"7439596145","tag":{"amenity":"waste_basket"}},"type":"Feature"},
	{"geometry":{"coordinates":[15.487692,46.967663],"type":"Point"},"properties":{"osm_id":"7439596165","tag":{"amenity":"waste_basket"}},"type":"Feature"},
	{"geometry":{"coordinates":[15.488311,46.967527],"type":"Point"},"properties":{"osm_id":"7439596166","tag":{"amenity":"waste_basket"}},"type":"Feature"},
	{"geometry":{"coordinates":[15.549999,46.938187],"type":"Point"},"properties":{"osm_id":"7575215908","tag":{"access":"yes","amenity":"recycling","recycling:glass_bottles":"yes","recycling:scrap_metal":"yes","recycling_type":"container","waste":"glass;scrap_metal"}},"type":"Feature"},
	{"geometry":{"coordinates":[15.538429,46.947649],"type":"Point"},"properties":{"osm_id":"7589940566","tag":{"access":"yes","amenity":"recycling","recycling:glass_bottles":"yes","recycling:scrap_metal":"yes","recycling_type":"container","waste":"glass;scrap_metal"}},"type":"Feature"},
	{"geometry":{"coordinates":[15.532164,46.920819],"type":"Point"},"properties":{"osm_id":"7592014909","tag":{"amenity":"recycling","recycling:glass":"yes","recycling_type":"container"}},"type":"Feature"},
	{"geometry":{"coordinates":[15.532139,46.93602],"type":"Point"},"properties":{"name":"ASZ St. Ulrich","osm_id":"7592892096","tag":{"amenity":"recycling","recycling_type":"centre"}},"type":"Feature"},
	{"geometry":{"coordinates":[15.515593,46.942001],"type":"Point"},"properties":{"osm_id":"7602941928","tag":{"amenity":"recycling","recycling:glass_bottles":"yes","recycling:plastic_packaging":"yes","recycling:scrap_metal":"yes","recycling_type":"container"}},"type":"Feature"},
	{"geometry":{"coordinates":[15.510978,46.938681],"type":"Point"},"properties":{"osm_id":"7668966305","tag":{"amenity":"waste_basket","colour":"green","material":"plastic","waste":"trash"}},"type":"Feature"}
]
}
