{
"type": "FeatureCollection",
"features": [
	{"geometry":{"coordinates":[15.506131,46.961428],"type":"Point"},"properties":{"osm_id":"568364275","tag":{"amenity":"recycling","recycling:batteries":"yes","recycling:cans":"yes","recycling:chemicals":"yes","recycling:electrical_appliances":"yes","recycling:glass_bottles":"yes","recycling:oil":"yes","recycling:organic":"yes","recycling:paper":"yes","recycling:plastic_packaging":"yes","recycling:wood":"yes","recycling_type":"centre"}},"type":"Feature"},
	{"geometry":{"coordinates":[15.482605,46.964301],"type":"Point"},"properties":{"osm_id":"834760590","tag":{"amenity":"recycling","recycling:cans":"yes","recycling:glass":"yes","recycling_type":"container"}},"type":"Feature"},
	{"geometry":{"coordinates":[15.487997,46.945089],"type":"Point"},"properties":{"osm_id":"1911563572","tag":{"amenity":"waste_basket"}},"type":"Feature"},
	{"geometry":{"coordinates":[15.482125,46.963828],"type":"Point"},"properties":{"osm_id":"1911563722","tag":{"amenity":"waste_basket"}},"type":"Feature"},
	{"geometry":{"coordinates":[15.510995,46.932235],"type":"Point"},"properties":{"osm_id":"7157684430","tag":{"access":"yes","amenity":"recycling","recycling:glass_bottles":"yes","recycling_type":"container","waste":"glass"}},"type":"Feature"},
	{"geometry":{"coordinates":[15.484449,46.965312],"type":"Point"},"properties":{"osm_id":"7439596145","tag":{"amenity":"waste_basket"}},"type":"Feature"},
	{"geometry":{"coordinates":[15.487691,46.967662],"type":"Point"},"properties":{"osm_id":"7439596165","tag":{"amenity":"waste_basket"}},"type":"Feature"},
	{"geometry":{"coordinates":[15.488311,46.967527],"type":"Point"},"properties":{"osm_id":"7439596166","tag":{"amenity":"waste_basket"}},"type":"Feature"},
	{"geometry":{"coordinates":[15.549999,46.938186],"type":"Point"},"properties":{"osm_id":"7575215908","tag":{"access":"yes","amenity":"recycling","recycling:glass_bottles":"yes","recycling:scrap_metal":"yes","recycling_type":"container","waste":"glass;scrap_metal"}},"type":"Feature"},
	{"geometry":{"coordinates":[15.538428,46.947649],"type":"Point"},"properties":{"osm_id":"7589940566","tag":{"access":"yes","amenity":"recycling","recycling:glass_bottles":"yes","recycling:scrap_metal":"yes","recycling_type":"container","waste":"glass;scrap_metal"}},"type":"Feature"},
	{"geometry":{"coordinates":[15.532164,46.920818],"type":"Point"},"properties":{"osm_id":"7592014909","tag":{"amenity":"recycling","recycling:glass":"yes","recycling_type":"container"}},"type":"Feature"},
	{"geometry":{"coordinates":[15.532138,46.93602],"type":"Point"},"properties":{"name":"ASZ St. Ulrich","osm_id":"7592892096","tag":{"amenity":"recycling","recycling_type":"centre"}},"type":"Feature"},
	{"geometry":{"coordinates":[15.515592,46.942001],"type":"Point"},"properties":{"osm_id":"7602941928","tag":{"amenity":"recycling","recycling:glass_bottles":"yes","recycling:plastic_packaging":"yes","recycling:scrap_metal":"yes","recycling_type":"container"}},"type":"Feature"},
	{"geometry":{"coordinates":[15.510977,46.93868],"type":"Point"},"properties":{"osm_id":"7668966305","tag":{"amenity":"waste_basket","colour":"green","material":"plastic","waste":"trash"}},"type":"Feature"}
]
}
