{
"type": "FeatureCollection",
"features": [
	{"geometry":{"coordinates":[-5.793426,43.616393],"type":"Point"},"properties":{"osm_id":"2384344204","tag":{"amenity":"recycling","recycling_type":"container"}},"type":"Feature"},
	{"geometry":{"coordinates":[-5.764381,43.590525],"type":"Point"},"properties":{"osm_id":"2399321926","tag":{"amenity":"recycling","recycling_type":"container"}},"type":"Feature"},
	{"geometry":{"coordinates":[-5.766843,43.589215],"type":"Point"},"properties":{"osm_id":"2399321927","tag":{"amenity":"recycling","recycling:cans":"yes","recycling:clothes":"no","recycling:glass_bottles":"yes","recycling:paper":"yes","recycling_type":"container"}},"type":"Feature"},
	{"geometry":{"coordinates":[-5.770848,43.586267],"type":"Point"},"properties":{"osm_id":"2399321928","tag":{"amenity":"recycling","recycling_type":"container"}},"type":"Feature"},
	{"geometry":{"coordinates":[-5.767951,43.591125],"type":"Point"},"properties":{"osm_id":"2684511296","tag":{"amenity":"recycling","location":"underground","operator":"Cogersa","recycling:batteries":"yes","recycling:beverage_cartons":"yes","recycling:cans":"yes","recycling:cartons":"yes","recycling:clothes":"no","recycling:glass_bottles":"yes","recycling:magazines":"yes","recycling:newspaper":"yes","recycling:organic":"yes","recycling:paper":"yes","recycling:paper_packaging":"yes","recycling:plastic":"yes","recycling:plastic_bottles":"yes","recycling:plastic_packaging":"yes","recycling_type":"container"}},"type":"Feature"},
	{"geometry":{"coordinates":[-5.768176,43.591026],"type":"Point"},"properties":{"osm_id":"2684511297","tag":{"amenity":"recycling","location":"overground","recycling:cans":"no","recycling:clothes":"yes","recycling:glass":"no","recycling:glass_bottles":"no","recycling:paper":"no","recycling:plastic":"no","recycling_type":"container"}},"type":"Feature"},
	{"geometry":{"coordinates":[-5.759666,43.584964],"type":"Point"},"properties":{"osm_id":"5648004324","tag":{"amenity":"waste_basket"}},"type":"Feature"},
	{"geometry":{"coordinates":[-5.788796,43.61918],"type":"Point"},"properties":{"osm_id":"5901624392","tag":{"amenity":"recycling","recycling_type":"container"}},"type":"Feature"},
	{"geometry":{"coordinates":[-5.788112,43.621987],"type":"Point"},"properties":{"osm_id":"7776617454","tag":{"amenity":"recycling","recycling_type":"container"}},"type":"Feature"},
	{"geometry":{"coordinates":[-5.766869,43.586501],"type":"Point"},"properties":{"osm_id":"7799492108","tag":{"amenity":"recycling","recycling_type":"container"}},"type":"Feature"},
	{"geometry":{"coordinates":[-5.76341,43.58969],"type":"Point"},"properties":{"osm_id":"8951406509","tag":{"amenity":"waste_basket"}},"type":"Feature"},
	{"geometry":{"coordinates":[-5.789714,43.616086],"type":"Point"},"properties":{"osm_id":"9046778215","tag":{"amenity":"recycling"}},"type":"Feature"},
	{"geometry":{"coordinates":[-5.793666,43.616661],"type":"Point"},"properties":{"osm_id":"9123214679","tag":{"amenity":"recycling"}},"type":"Feature"}
]
}
