{
"type": "FeatureCollection",
"features": [
	{"geometry":{"coordinates":[-76.345611,-13.135815],"type":"Point"},"properties":{"osm_id":"4158505781","tag":{"natural":"tree"}},"type":"Feature"},
	{"geometry":{"coordinates":[-76.345714,-13.135835],"type":"Point"},"properties":{"osm_id":"4158505783","tag":{"natural":"tree"}},"type":"Feature"},
	{"geometry":{"coordinates":[-76.345545,-13.13586],"type":"Point"},"properties":{"osm_id":"4158505784","tag":{"natural":"tree"}},"type":"Feature"},
	{"geometry":{"coordinates":[-76.345662,-13.135866],"type":"Point"},"properties":{"osm_id":"4158505785","tag":{"natural":"tree"}},"type":"Feature"},
	{"geometry":{"coordinates":[-76.345617,-13.135873],"type":"Point"},"properties":{"osm_id":"4158505788","tag":{"natural":"tree"}},"type":"Feature"},
	{"geometry":{"coordinates":[-76.345903,-13.135881],"type":"Point"},"properties":{"osm_id":"4158506490","tag":{"natural":"tree"}},"type":"Feature"},
	{"geometry":{"coordinates":[-76.346645,-13.135943],"type":"Point"},"properties":{"osm_id":"4158506504","tag":{"natural":"tree"}},"type":"Feature"},
	{"geometry":{"coordinates":[-76.346158,-13.135973],"type":"Point"},"properties":{"osm_id":"4158506515","tag":{"natural":"tree"}},"type":"Feature"},
	{"geometry":{"coordinates":[-76.346669,-13.136092],"type":"Point"},"properties":{"name":"Herbay Alto","osm_id":"4167979911","place":"village","tag":{"natural":"tree"}},"type":"Feature"}
]
}
