{
"type": "FeatureCollection",
"features": [
	{"geometry":{"coordinates":[-76.34561,-13.135815],"type":"Point"},"properties":{"osm_id":"4158505781","tag":{"natural":"tree"}},"type":"Feature"},
	{"geometry":{"coordinates":[-76.345714,-13.135834],"type":"Point"},"properties":{"osm_id":"4158505783","tag":{"natural":"tree"}},"type":"Feature"},
	{"geometry":{"coordinates":[-76.345545,-13.135859],"type":"Point"},"properties":{"osm_id":"4158505784","tag":{"natural":"tree"}},"type":"Feature"},
	{"geometry":{"coordinates":[-76.345661,-13.135866],"type":"Point"},"properties":{"osm_id":"4158505785","tag":{"natural":"tree"}},"type":"Feature"},
	{"geometry":{"coordinates":[-76.345617,-13.135872],"type":"Point"},"properties":{"osm_id":"4158505788","tag":{"natural":"tree"}},"type":"Feature"},
	{"geometry":{"coordinates":[-76.345903,-13.13588],"type":"Point"},"properties":{"osm_id":"4158506490","tag":{"natural":"tree"}},"type":"Feature"},
	{"geometry":{"coordinates":[-76.346644,-13.135942],"type":"Point"},"properties":{"osm_id":"4158506504","tag":{"natural":"tree"}},"type":"Feature"},
	{"geometry":{"coordinates":[-76.346157,-13.135973],"type":"Point"},"properties":{"osm_id":"4158506515","tag":{"natural":"tree"}},"type":"Feature"},
	{"geometry":{"coordinates":[-76.346669,-13.136091],"type":"Point"},"properties":{"name":"Herbay Alto","osm_id":"4167979911","place":"village","tag":{"natural":"tree"}},"type":"Feature"}
]
}
