{
"type": "FeatureCollection",
"features": [
	{"geometry":{"coordinates":[-76.34561,-13.135815],"type":"Point"},"properties":{"osm_id":"4158505781","tag":{"natural":"tree"}},"type":"Feature"},
	{"geometry":{"coordinates":[-76.345714,-13.135834],"type":"Point"},"properties":{"osm_id":"4158505783","tag":{"natural":"tree"}},"type":"Feature"},
	{"geometry":{"coordinates":[-76.345545,-13.135859],"type":"Point"},"properties":{"osm_id":"4158505784","tag":{"natural":"tree"}},"type":"Feature"},
	{"geometry":{"coordinates":[-76.345661,-13.135866],"type":"Point"},"properties":{"osm_id":"4158505785","tag":{"natural":"tree"}},"type":"Feature"},
	{"geometry":{"coordinates":[-76.345617,-13.135872],"type":"Point"},"properties":{"osm_id":"4158505788","tag":{"natural":"tree"}},"type":"Feature"},
	{"geometry":{"coordinates":[-76.345903,-13.13588],"type":"Point"},"properties":{"osm_id":"4158506490","tag":{"natural":"tree"}},"type":"Feature"},
	{"geometry":{"coordinates":[-76.346644,-13.135942],"type":"Point"},"properties":{"osm_id":"4158506504","tag":{"natural":"tree"}},"type":"Feature"},
	{"geometry":{"coordinates":[-76.346157,-13.135973],"type":"Point"},"properties":{"osm_id":"4158506515","tag":{"natural":"tree"}},"type":"Feature"},
	{"geometry":{"coordinates":[-76.346669,-13.136091],"type":"Point"},"properties":{"name":"Herbay Alto","osm_id":"4167979911","place":"village","tag":{"natural":"tree"}},"type":"Feature"},
	{"geometry":{"coordinates":[-76.29562,-13.085221],"type":"Point"},"properties":{"osm_id":"9112734760","tag":{"natural":"tree"}},"type":"Feature"},
	{"geometry":{"coordinates":[-76.29565,-13.085274],"type":"Point"},"properties":{"osm_id":"9112734761","tag":{"natural":"tree"}},"type":"Feature"},
	{"geometry":{"coordinates":[-76.295674,-13.085316],"type":"Point"},"properties":{"osm_id":"9112734762","tag":{"natural":"tree"}},"type":"Feature"},
	{"geometry":{"coordinates":[-76.295703,-13.085351],"type":"Point"},"properties":{"osm_id":"9112734763","tag":{"natural":"tree"}},"type":"Feature"},
	{"geometry":{"coordinates":[-76.295494,-13.085148],"type":"Point"},"properties":{"osm_id":"9112734764","tag":{"natural":"tree"}},"type":"Feature"},
	{"geometry":{"coordinates":[-76.295414,-13.085199],"type":"Point"},"properties":{"osm_id":"9112734765","tag":{"natural":"tree"}},"type":"Feature"},
	{"geometry":{"coordinates":[-76.295289,-13.085278],"type":"Point"},"properties":{"osm_id":"9112734766","tag":{"natural":"tree"}},"type":"Feature"},
	{"geometry":{"coordinates":[-76.296133,-13.084526],"type":"Point"},"properties":{"osm_id":"9112734780","tag":{"natural":"tree"}},"type":"Feature"},
	{"geometry":{"coordinates":[-76.296086,-13.084556],"type":"Point"},"properties":{"osm_id":"9112734781","tag":{"natural":"tree"}},"type":"Feature"},
	{"geometry":{"coordinates":[-76.296038,-13.08458],"type":"Point"},"properties":{"osm_id":"9112734782","tag":{"natural":"tree"}},"type":"Feature"},
	{"geometry":{"coordinates":[-76.295993,-13.084609],"type":"Point"},"properties":{"osm_id":"9112734783","tag":{"natural":"tree"}},"type":"Feature"},
	{"geometry":{"coordinates":[-76.295951,-13.084641],"type":"Point"},"properties":{"osm_id":"9112734784","tag":{"natural":"tree"}},"type":"Feature"},
	{"geometry":{"coordinates":[-76.295898,-13.084669],"type":"Point"},"properties":{"osm_id":"9112734785","tag":{"natural":"tree"}},"type":"Feature"}
]
}
