{
"type": "FeatureCollection",
"features": [
	{"geometry":{"coordinates":[12.139643,48.335067],"type":"Point"},"properties":{"osm_id":"283697051","tag":{"amenity":"recycling","opening_hours":"Mo-Sa 07:00-12:00,14:00-19:00; Su,PH off","recycling:cans":"yes","recycling:cardboard":"yes","recycling:clothes":"yes","recycling:glass_bottles":"yes","recycling:paper":"yes","recycling:shoes":"yes","recycling_type":"container","website":"https://www.landkreis-erding.de/abfallwirtschaft/rund-um-die-entsorgung/recyclinghoefe-containerplaetze/"}},"type":"Feature"},
	{"geometry":{"coordinates":[12.17355,48.302565],"type":"Point"},"properties":{"osm_id":"8379262804","tag":{"amenity":"waste_basket"}},"type":"Feature"},
	{"geometry":{"coordinates":[12.145502,48.31732],"type":"Point"},"properties":{"osm_id":"8479179081","tag":{"amenity":"recycling","recycling:glass_bottles":"yes","recycling_type":"container"}},"type":"Feature"},
	{"geometry":{"coordinates":[12.152112,48.305037],"type":"Point"},"properties":{"osm_id":"8777558097","tag":{"amenity":"recycling","opening_hours":"Mo-Sa 07:00-12:00,14:00-19:00; Su,PH off","recycling:cans":"yes","recycling:cardboard":"yes","recycling:clothes":"yes","recycling:glass_bottles":"yes","recycling:paper":"yes","recycling:shoes":"yes","recycling_type":"container","website":"https://www.landkreis-erding.de/abfallwirtschaft/rund-um-die-entsorgung/recyclinghoefe-containerplaetze/"}},"type":"Feature"}
]
}
