{
"type": "FeatureCollection",
"lastupdate": "2020-08-05T00:00:00Z",
"features": [
	{"geometry":{"coordinates":[12.147185,48.024032],"type":"Point"},"properties":{"name":"Wertstoffhof","osm_id":"277358634","tag":{"amenity":"recycling","recycling:batteries":"yes","recycling:cans":"yes","recycling:clothes":"yes","recycling:glass":"yes"}},"type":"Feature"},
	{"geometry":{"coordinates":[12.177217,48.026407],"type":"Point"},"properties":{"osm_id":"910634148","tag":{"amenity":"recycling","recycling:clothes":"yes","recycling:glass":"yes","recycling:paper":"yes"}},"type":"Feature"},
	{"geometry":{"coordinates":[12.13848,47.992289],"type":"Point"},"properties":{"name":"Wertstoffhof Rott","osm_id":"1763116066","tag":{"amenity":"recycling","recycling_type":"centre"}},"type":"Feature"},
	{"geometry":{"coordinates":[12.146646,48.019603],"type":"Point"},"properties":{"osm_id":"6800379058","tag":{"amenity":"waste_basket","waste":"trash"}},"type":"Feature"}
]
}
