{
"type": "FeatureCollection",
"lastupdate": "2020-07-31T00:00:00Z",
"features": [
	{"geometry":{"coordinates":[12.19825,44.402002],"type":"Point"},"properties":{"osm_id":"675910419","tag":{"amenity":"recycling","location":"overground","recycling:cans":"yes","recycling:glass":"yes","recycling:paper":"yes","recycling_type":"container"}},"type":"Feature"},
	{"geometry":{"coordinates":[12.205911,44.401777],"type":"Point"},"properties":{"osm_id":"675910664","tag":{"amenity":"recycling","location":"overground","recycling:cans":"yes","recycling:glass":"yes","recycling:paper":"yes","recycling_type":"container"}},"type":"Feature"},
	{"geometry":{"coordinates":[12.20269,44.401755],"type":"Point"},"properties":{"osm_id":"675911961","tag":{"amenity":"recycling","location":"overground","recycling:cans":"yes","recycling:glass":"yes","recycling:paper":"yes","recycling_type":"container"}},"type":"Feature"},
	{"geometry":{"coordinates":[12.196421,44.401656],"type":"Point"},"properties":{"osm_id":"1494342445","tag":{"amenity":"recycling","location":"overground","recycling_type":"container"}},"type":"Feature"},
	{"geometry":{"coordinates":[12.180912,44.395414],"type":"Point"},"properties":{"osm_id":"2469812511","tag":{"amenity":"recycling","location":"overground","recycling_type":"container"}},"type":"Feature"},
	{"geometry":{"coordinates":[12.192652,44.401085],"type":"Point"},"properties":{"osm_id":"2603811519","tag":{"amenity":"recycling","location":"overground","recycling_type":"container"}},"type":"Feature"},
	{"geometry":{"coordinates":[12.18151,44.4013],"type":"Point"},"properties":{"osm_id":"3326169655","tag":{"amenity":"recycling","location":"overground","recycling_type":"container"}},"type":"Feature"},
	{"geometry":{"coordinates":[12.188922,44.399119],"type":"Point"},"properties":{"osm_id":"3969461447","tag":{"amenity":"recycling","location":"overground","recycling_type":"container"}},"type":"Feature"},
	{"geometry":{"coordinates":[12.189772,44.400773],"type":"Point"},"properties":{"osm_id":"3969468565","tag":{"amenity":"recycling","location":"overground","recycling_type":"container"}},"type":"Feature"},
	{"geometry":{"coordinates":[12.203399,44.377995],"type":"Point"},"properties":{"osm_id":"4146477649","tag":{"amenity":"recycling"}},"type":"Feature"},
	{"geometry":{"coordinates":[12.204228,44.379102],"type":"Point"},"properties":{"osm_id":"4146477650","tag":{"amenity":"recycling"}},"type":"Feature"},
	{"geometry":{"coordinates":[12.185176,44.401564],"type":"Point"},"properties":{"osm_id":"4587332169","tag":{"amenity":"recycling","recycling_type":"container"}},"type":"Feature"},
	{"geometry":{"coordinates":[12.190663,44.398177],"type":"Point"},"properties":{"osm_id":"4983888040","tag":{"amenity":"recycling","recycling_type":"container"}},"type":"Feature"}
]
}
