{
"type": "FeatureCollection",
"features": [
	{"geometry":{"coordinates":[12.198251,44.402003],"type":"Point"},"properties":{"osm_id":"675910419","tag":{"amenity":"recycling","location":"overground","recycling:cans":"yes","recycling:glass":"yes","recycling:paper":"yes","recycling_type":"container"}},"type":"Feature"},
	{"geometry":{"coordinates":[12.205912,44.401778],"type":"Point"},"properties":{"osm_id":"675910664","tag":{"amenity":"recycling","location":"overground","recycling:cans":"yes","recycling:glass":"yes","recycling:paper":"yes","recycling_type":"container"}},"type":"Feature"},
	{"geometry":{"coordinates":[12.20269,44.401756],"type":"Point"},"properties":{"osm_id":"675911961","tag":{"amenity":"recycling","location":"overground","recycling:cans":"yes","recycling:glass":"yes","recycling:paper":"yes","recycling_type":"container"}},"type":"Feature"},
	{"geometry":{"coordinates":[12.196422,44.401657],"type":"Point"},"properties":{"osm_id":"1494342445","tag":{"amenity":"recycling","location":"overground","recycling_type":"container"}},"type":"Feature"},
	{"geometry":{"coordinates":[12.180913,44.395414],"type":"Point"},"properties":{"osm_id":"2469812511","tag":{"amenity":"recycling","location":"overground","recycling_type":"container"}},"type":"Feature"},
	{"geometry":{"coordinates":[12.192652,44.401085],"type":"Point"},"properties":{"osm_id":"2603811519","tag":{"amenity":"recycling","location":"overground","recycling_type":"container"}},"type":"Feature"},
	{"geometry":{"coordinates":[12.181511,44.4013],"type":"Point"},"properties":{"osm_id":"3326169655","tag":{"amenity":"recycling","location":"overground","recycling_type":"container"}},"type":"Feature"},
	{"geometry":{"coordinates":[12.188923,44.39912],"type":"Point"},"properties":{"osm_id":"3969461447","tag":{"amenity":"recycling","location":"overground","recycling_type":"container"}},"type":"Feature"},
	{"geometry":{"coordinates":[12.189773,44.400773],"type":"Point"},"properties":{"osm_id":"3969468565","tag":{"amenity":"recycling","location":"overground","recycling_type":"container"}},"type":"Feature"},
	{"geometry":{"coordinates":[12.2034,44.377996],"type":"Point"},"properties":{"osm_id":"4146477649","tag":{"amenity":"recycling"}},"type":"Feature"},
	{"geometry":{"coordinates":[12.204229,44.379102],"type":"Point"},"properties":{"osm_id":"4146477650","tag":{"amenity":"recycling"}},"type":"Feature"},
	{"geometry":{"coordinates":[12.185176,44.401564],"type":"Point"},"properties":{"osm_id":"4587332169","tag":{"amenity":"recycling","recycling_type":"container"}},"type":"Feature"},
	{"geometry":{"coordinates":[12.190664,44.398178],"type":"Point"},"properties":{"osm_id":"4983888040","tag":{"amenity":"recycling","recycling_type":"container"}},"type":"Feature"},
	{"geometry":{"coordinates":[12.17754,44.396245],"type":"Point"},"properties":{"osm_id":"6355038537","tag":{"amenity":"waste_disposal"}},"type":"Feature"}
]
}
