{
"type": "FeatureCollection",
"features": [
	{"geometry":{"coordinates":[-7.567114,41.617561],"type":"Point"},"properties":{"name":"Ecoponto","osm_id":"4326643342","tag":{"amenity":"recycling"}},"type":"Feature"}
]
}
