{
"type": "FeatureCollection",
"lastupdate": "2020-08-01T00:00:00Z",
"features": [
	{"geometry":{"coordinates":[-7.567114,41.61756],"type":"Point"},"properties":{"name":"Ecoponto","osm_id":"4326643342","tag":{"amenity":"recycling"}},"type":"Feature"}
]
}
