{
"type": "FeatureCollection",
"lastupdate": "2020-08-01T00:00:00Z",
"features": [
	{"geometry":{"coordinates":[-111.558126,33.409635],"type":"Point"},"properties":{"osm_id":"2620357193","tag":{"amenity":"waste_basket"}},"type":"Feature"},
	{"geometry":{"coordinates":[-111.546372,33.388773],"type":"Point"},"properties":{"osm_id":"3204267556","tag":{"amenity":"waste_basket"}},"type":"Feature"},
	{"geometry":{"coordinates":[-111.550284,33.413416],"type":"Point"},"properties":{"osm_id":"3661315368","tag":{"amenity":"waste_basket"}},"type":"Feature"},
	{"geometry":{"coordinates":[-111.550193,33.414272],"type":"Point"},"properties":{"osm_id":"3661315374","tag":{"amenity":"waste_basket"}},"type":"Feature"},
	{"geometry":{"coordinates":[-111.579948,33.381775],"type":"Point"},"properties":{"name":"C Johnson Recycling","osm_id":"3662217834","tag":{"addr:city":"Apache Junction","addr:housenumber":"3625","addr:postcode":"85120","addr:state":"AZ","addr:street":"South Meridian Drive","amenity":"recycling","facebook":"https://www.facebook.com/CJohnsonRecycling","opening_hours":"Mo-Fr 08:00-16:00; Sa 08:00-13:00","phone":"+1 480 982 1238","recycling:aluminium":"yes","recycling:batteries":"yes","recycling:cans":"yes","recycling:electrical_appliances":"yes","recycling:scrap_metal":"yes","recycling_type":"centre","website":"http://cjohnsonrecycling.com/"}},"type":"Feature"},
	{"geometry":{"coordinates":[-111.593198,33.401863],"type":"Point"},"properties":{"osm_id":"4182574984","tag":{"amenity":"waste_basket"}},"type":"Feature"},
	{"geometry":{"coordinates":[-111.548646,33.417584],"type":"Point"},"properties":{"osm_id":"5444112688","tag":{"amenity":"waste_basket"}},"type":"Feature"},
	{"geometry":{"coordinates":[-111.548753,33.417499],"type":"Point"},"properties":{"osm_id":"5444112689","tag":{"amenity":"waste_basket"}},"type":"Feature"},
	{"geometry":{"coordinates":[-111.548004,33.4176],"type":"Point"},"properties":{"osm_id":"5444112690","tag":{"amenity":"waste_basket"}},"type":"Feature"},
	{"geometry":{"coordinates":[-111.548814,33.416729],"type":"Point"},"properties":{"osm_id":"5444112691","tag":{"amenity":"waste_basket"}},"type":"Feature"},
	{"geometry":{"coordinates":[-111.548832,33.416617],"type":"Point"},"properties":{"osm_id":"5444112692","tag":{"amenity":"waste_basket"}},"type":"Feature"},
	{"geometry":{"coordinates":[-111.548756,33.416625],"type":"Point"},"properties":{"osm_id":"5444112693","tag":{"amenity":"waste_basket"}},"type":"Feature"},
	{"geometry":{"coordinates":[-111.544418,33.422781],"type":"Point"},"properties":{"osm_id":"6011055600","tag":{"amenity":"waste_basket","waste":"drugs"}},"type":"Feature"},
	{"geometry":{"coordinates":[-111.550478,33.412065],"type":"Point"},"properties":{"osm_id":"6350797611","tag":{"amenity":"waste_basket"}},"type":"Feature"},
	{"geometry":{"coordinates":[-111.549965,33.422736],"type":"Point"},"properties":{"osm_id":"6357165514","tag":{"amenity":"waste_basket"}},"type":"Feature"},
	{"geometry":{"coordinates":[-111.548509,33.422654],"type":"Point"},"properties":{"osm_id":"6357165515","tag":{"amenity":"waste_basket"}},"type":"Feature"},
	{"geometry":{"coordinates":[-111.547307,33.412122],"type":"Point"},"properties":{"osm_id":"6463540300","tag":{"amenity":"recycling","recycling:clothes":"yes","recycling_type":"container"}},"type":"Feature"},
	{"geometry":{"coordinates":[-111.547317,33.412137],"type":"Point"},"properties":{"osm_id":"6463540301","tag":{"amenity":"recycling","recycling:clothes":"yes","recycling_type":"container"}},"type":"Feature"},
	{"geometry":{"coordinates":[-111.557596,33.415689],"type":"Point"},"properties":{"osm_id":"6496131751","tag":{"amenity":"waste_basket"}},"type":"Feature"},
	{"geometry":{"coordinates":[-111.557625,33.416104],"type":"Point"},"properties":{"osm_id":"6496131753","tag":{"amenity":"waste_basket"}},"type":"Feature"}
]
}
