{
"type": "FeatureCollection",
"features": [
	{"geometry":{"coordinates":[12.948299,53.188107],"type":"Point"},"properties":{"osm_id":"391525211","tag":{"amenity":"recycling","location":"overground","recycling:glass":"yes","recycling_type":"container"}},"type":"Feature"},
	{"geometry":{"coordinates":[12.968468,53.222659],"type":"Point"},"properties":{"osm_id":"6580381592","tag":{"amenity":"recycling","operator":"Kanuhof Wustrow","recycling_type":"container"}},"type":"Feature"}
]
}
