{
"type": "FeatureCollection",
"features": [
	{"geometry":{"coordinates":[12.929967,50.728544],"type":"Point"},"properties":{"osm_id":"2440543073","tag":{"amenity":"waste_basket","check_date":"2020-12-27"}},"type":"Feature"},
	{"geometry":{"coordinates":[12.929802,50.728816],"type":"Point"},"properties":{"osm_id":"2440543076","tag":{"amenity":"waste_basket","check_date":"2020-12-27"}},"type":"Feature"},
	{"geometry":{"coordinates":[13.004751,50.736048],"type":"Point"},"properties":{"osm_id":"2700434579","tag":{"amenity":"recycling","location":"overground","recycling:glass":"yes","recycling_type":"container"}},"type":"Feature"},
	{"geometry":{"coordinates":[12.961961,50.734882],"type":"Point"},"properties":{"osm_id":"3441707925","tag":{"amenity":"recycling","recycling:clothes":"yes","recycling_type":"container"}},"type":"Feature"},
	{"geometry":{"coordinates":[12.928419,50.719568],"type":"Point"},"properties":{"osm_id":"5181871961","tag":{"amenity":"waste_basket","check_date":"2021-10-24"}},"type":"Feature"},
	{"geometry":{"coordinates":[12.934468,50.734661],"type":"Point"},"properties":{"osm_id":"5683163218","tag":{"amenity":"waste_disposal"}},"type":"Feature"},
	{"geometry":{"coordinates":[12.921484,50.735207],"type":"Point"},"properties":{"osm_id":"6612925920","tag":{"amenity":"waste_basket"}},"type":"Feature"},
	{"geometry":{"coordinates":[12.921356,50.735326],"type":"Point"},"properties":{"osm_id":"6612925921","tag":{"amenity":"waste_basket"}},"type":"Feature"},
	{"geometry":{"coordinates":[12.920151,50.734375],"type":"Point"},"properties":{"osm_id":"7042148215","tag":{"amenity":"waste_basket"}},"type":"Feature"},
	{"geometry":{"coordinates":[12.950714,50.713123],"type":"Point"},"properties":{"osm_id":"8026386812","tag":{"amenity":"waste_basket","material":"metal"}},"type":"Feature"},
	{"geometry":{"coordinates":[12.92071,50.734503],"type":"Point"},"properties":{"osm_id":"8274683930","tag":{"amenity":"waste_basket"}},"type":"Feature"}
]
}
