{
"type": "FeatureCollection",
"lastupdate": "2020-08-04T00:00:00Z",
"features": [
	{"geometry":{"coordinates":[-52.36964,-24.024634],"type":"Point"},"properties":{"name":"Frizzo Reciclados","osm_id":"3013693198","tag":{"amenity":"recycling","recycling:cans":"no","recycling:clothes":"no","recycling:paper":"yes"}},"type":"Feature"}
]
}
