{
"type": "FeatureCollection",
"features": [
	{"geometry":{"coordinates":[-52.36964,-24.024634],"type":"Point"},"properties":{"name":"Frizzo Reciclados","osm_id":"3013693198","tag":{"amenity":"recycling","recycling:cans":"no","recycling:clothes":"no","recycling:paper":"yes"}},"type":"Feature"},
	{"geometry":{"coordinates":[-52.354785,-24.018453],"type":"Point"},"properties":{"osm_id":"5688678769","tag":{"amenity":"waste_disposal"}},"type":"Feature"}
]
}
