{
"type": "FeatureCollection",
"features": [
	{"geometry":{"coordinates":[44.475376,48.690613],"type":"Point"},"properties":{"osm_id":"917929305","tag":{"amenity":"waste_disposal","shop":"kiosk"}},"type":"Feature"},
	{"geometry":{"coordinates":[44.473506,48.689311],"type":"Point"},"properties":{"osm_id":"917929306","tag":{"amenity":"waste_disposal"}},"type":"Feature"},
	{"geometry":{"coordinates":[44.472895,48.688892],"type":"Point"},"properties":{"osm_id":"1430872607","tag":{"amenity":"recycling"}},"type":"Feature"},
	{"geometry":{"coordinates":[44.488034,48.689315],"type":"Point"},"properties":{"osm_id":"6829569279","tag":{"amenity":"waste_disposal"}},"type":"Feature"}
]
}
