{
"type": "FeatureCollection",
"features": [
	{"geometry":{"coordinates":[1.377608,41.53898],"type":"Point"},"properties":{"name":"Deixalleria de Santa Coloma de Queralt","osm_id":"2181492837","tag":{"amenity":"waste_disposal"}},"type":"Feature"},
	{"geometry":{"coordinates":[1.385821,41.533639],"type":"Point"},"properties":{"osm_id":"7717720418","tag":{"amenity":"recycling","recycling_type":"container"}},"type":"Feature"}
]
}
