{
"type": "FeatureCollection",
"features": [
	{"geometry":{"coordinates":[-82.409944,29.638772],"type":"Point"},"properties":{"osm_id":"3835165314","tag":{"amenity":"waste_basket"}},"type":"Feature"},
	{"geometry":{"coordinates":[-82.371478,29.654815],"type":"Point"},"properties":{"osm_id":"4026996526","tag":{"amenity":"waste_basket"}},"type":"Feature"},
	{"geometry":{"coordinates":[-82.353635,29.648401],"type":"Point"},"properties":{"osm_id":"4027014581","tag":{"amenity":"waste_basket"}},"type":"Feature"},
	{"geometry":{"coordinates":[-82.353642,29.648402],"type":"Point"},"properties":{"osm_id":"4027014582","tag":{"amenity":"recycling","opening_hours":"24/7","recycling:batteries":"no","recycling:cans":"yes","recycling:cardboard":"no","recycling:clothes":"no","recycling:electrical_appliances":"no","recycling:glass":"yes","recycling:glass_bottles":"yes","recycling:green_waste":"no","recycling:paper":"no","recycling:plastic":"yes","recycling:plastic_bottles":"yes","recycling:plastic_packaging":"no","recycling:scrap_metal":"no","recycling:shoes":"no","recycling:small_appliances":"no","recycling:waste":"no","recycling_type":"container"}},"type":"Feature"},
	{"geometry":{"coordinates":[-82.429709,29.683795],"type":"Point"},"properties":{"name":"ARC of Alachua County","osm_id":"4190056063","tag":{"amenity":"recycling","description":"Paper recycling for residents on wednesday. Hard disk recycling and business paper recycling for a fee","operator":"Gone4Ever","recycling:electrical_appliances":"yes","recycling:paper":"yes","recycling_type":"centre","wheelchair":"yes"}},"type":"Feature"},
	{"geometry":{"coordinates":[-82.357792,29.645808],"type":"Point"},"properties":{"osm_id":"4272412770","tag":{"amenity":"waste_basket"}},"type":"Feature"},
	{"geometry":{"coordinates":[-82.358686,29.614008],"type":"Point"},"properties":{"osm_id":"4921470540","tag":{"amenity":"waste_disposal"}},"type":"Feature"},
	{"geometry":{"coordinates":[-82.358628,29.618385],"type":"Point"},"properties":{"osm_id":"4921470541","tag":{"amenity":"waste_disposal"}},"type":"Feature"},
	{"geometry":{"coordinates":[-82.375131,29.623006],"type":"Point"},"properties":{"osm_id":"7064477688","tag":{"amenity":"waste_disposal"}},"type":"Feature"},
	{"geometry":{"coordinates":[-82.3751,29.623006],"type":"Point"},"properties":{"osm_id":"7064477689","tag":{"amenity":"waste_disposal"}},"type":"Feature"},
	{"geometry":{"coordinates":[-82.375069,29.623007],"type":"Point"},"properties":{"osm_id":"7064477690","tag":{"amenity":"waste_disposal"}},"type":"Feature"},
	{"geometry":{"coordinates":[-82.380744,29.62094],"type":"Point"},"properties":{"osm_id":"7064477700","tag":{"amenity":"waste_disposal"}},"type":"Feature"},
	{"geometry":{"coordinates":[-82.381242,29.62074],"type":"Point"},"properties":{"osm_id":"7064477702","tag":{"amenity":"waste_disposal"}},"type":"Feature"},
	{"geometry":{"coordinates":[-82.381206,29.620744],"type":"Point"},"properties":{"osm_id":"7064477703","tag":{"amenity":"waste_disposal"}},"type":"Feature"},
	{"geometry":{"coordinates":[-82.380126,29.621365],"type":"Point"},"properties":{"osm_id":"7064477713","tag":{"amenity":"waste_disposal"}},"type":"Feature"},
	{"geometry":{"coordinates":[-82.380091,29.621354],"type":"Point"},"properties":{"osm_id":"7064477714","tag":{"amenity":"waste_disposal"}},"type":"Feature"},
	{"geometry":{"coordinates":[-82.384629,29.625656],"type":"Point"},"properties":{"osm_id":"7064575322","tag":{"amenity":"waste_disposal"}},"type":"Feature"},
	{"geometry":{"coordinates":[-82.382148,29.624639],"type":"Point"},"properties":{"osm_id":"7064575328","tag":{"amenity":"waste_disposal"}},"type":"Feature"},
	{"geometry":{"coordinates":[-82.382112,29.624651],"type":"Point"},"properties":{"osm_id":"7064575329","tag":{"amenity":"waste_disposal"}},"type":"Feature"},
	{"geometry":{"coordinates":[-82.375917,29.651148],"type":"Point"},"properties":{"osm_id":"7070946984","tag":{"amenity":"waste_disposal"}},"type":"Feature"},
	{"geometry":{"coordinates":[-82.373276,29.625354],"type":"Point"},"properties":{"osm_id":"7120518689","tag":{"amenity":"waste_disposal"}},"type":"Feature"},
	{"geometry":{"coordinates":[-82.360555,29.646678],"type":"Point"},"properties":{"osm_id":"7120569015","tag":{"amenity":"waste_disposal"}},"type":"Feature"},
	{"geometry":{"coordinates":[-82.360523,29.646683],"type":"Point"},"properties":{"osm_id":"7120569016","tag":{"amenity":"waste_disposal"}},"type":"Feature"}
]
}
