{
"type": "FeatureCollection",
"features": [
	{"geometry":{"coordinates":[-82.409944,29.638772],"type":"Point"},"properties":{"osm_id":"3835165314","tag":{"amenity":"waste_basket"}},"type":"Feature"},
	{"geometry":{"coordinates":[-82.371478,29.654815],"type":"Point"},"properties":{"osm_id":"4026996526","tag":{"amenity":"waste_basket"}},"type":"Feature"},
	{"geometry":{"coordinates":[-82.353635,29.648401],"type":"Point"},"properties":{"osm_id":"4027014581","tag":{"amenity":"waste_basket"}},"type":"Feature"},
	{"geometry":{"coordinates":[-82.353642,29.648402],"type":"Point"},"properties":{"osm_id":"4027014582","tag":{"amenity":"recycling","opening_hours":"24/7","recycling:batteries":"no","recycling:cans":"yes","recycling:cardboard":"no","recycling:clothes":"no","recycling:electrical_appliances":"no","recycling:glass":"yes","recycling:glass_bottles":"yes","recycling:green_waste":"no","recycling:paper":"no","recycling:plastic":"yes","recycling:plastic_bottles":"yes","recycling:plastic_packaging":"no","recycling:scrap_metal":"no","recycling:shoes":"no","recycling:small_appliances":"no","recycling:waste":"no","recycling_type":"container"}},"type":"Feature"},
	{"geometry":{"coordinates":[-82.429709,29.683795],"type":"Point"},"properties":{"name":"ARC of Alachua County","osm_id":"4190056063","tag":{"amenity":"recycling","description":"Paper recycling for residents on wednesday. Hard disk recycling and business paper recycling for a fee","operator":"Gone4Ever","recycling:electrical_appliances":"yes","recycling:paper":"yes","recycling_type":"centre","wheelchair":"yes"}},"type":"Feature"},
	{"geometry":{"coordinates":[-82.357792,29.645808],"type":"Point"},"properties":{"osm_id":"4272412770","tag":{"amenity":"waste_basket"}},"type":"Feature"}
]
}
