{
"type": "FeatureCollection",
"lastupdate": "2020-08-01T00:00:00Z",
"features": [
	{"geometry":{"coordinates":[-8.506139,42.67573],"type":"Point"},"properties":{"name":"Punto limpio","osm_id":"1857131215","tag":{"amenity":"recycling","recycling_type":"centre"}},"type":"Feature"}
]
}
