{
"type": "FeatureCollection",
"features": [
	{"geometry":{"coordinates":[-8.50614,42.67573],"type":"Point"},"properties":{"name":"Punto limpio","osm_id":"1857131215","tag":{"amenity":"recycling","recycling_type":"centre"}},"type":"Feature"}
]
}
