{
"type": "FeatureCollection",
"features": [
	{"geometry":{"coordinates":[6.611752,50.561046],"type":"Point"},"properties":{"osm_id":"812289864","tag":{"natural":"tree"}},"type":"Feature"},
	{"geometry":{"coordinates":[6.636967,50.530335],"type":"Point"},"properties":{"osm_id":"6034592264","tag":{"leaf_cycle":"deciduous","leaf_type":"broadleaved","natural":"tree"}},"type":"Feature"},
	{"geometry":{"coordinates":[6.6455,50.539517],"type":"Point"},"properties":{"osm_id":"6034594061","tag":{"natural":"tree"}},"type":"Feature"},
	{"geometry":{"coordinates":[6.66232,50.561107],"type":"Point"},"properties":{"osm_id":"7328642656","tag":{"denotation":"landmark","leaf_cycle":"deciduous","leaf_type":"broadleaved","natural":"tree"}},"type":"Feature"},
	{"geometry":{"coordinates":[6.6477,50.542282],"type":"Point"},"properties":{"name":"Kastanie","osm_id":"7335795240","tag":{"denotation":"landmark","leaf_cycle":"deciduous","leaf_type":"broadleaved","natural":"tree"}},"type":"Feature"},
	{"geometry":{"coordinates":[6.649065,50.553389],"type":"Point"},"properties":{"name":"Birke","osm_id":"7335817245","tag":{"denotation":"landmark","leaf_cycle":"deciduous","leaf_type":"broadleaved","natural":"tree"}},"type":"Feature"},
	{"geometry":{"coordinates":[6.64908,50.553405],"type":"Point"},"properties":{"name":"Birke","osm_id":"7335817246","tag":{"denotation":"landmark","leaf_cycle":"deciduous","leaf_type":"broadleaved","natural":"tree"}},"type":"Feature"}
]
}
