{
"type": "FeatureCollection",
"features": [
	{"geometry":{"coordinates":[6.625289,45.630012],"type":"Point"},"properties":{"name":"Col du coin","osm_id":"7858566600","tag":{"information":"guidepost","tourism":"information"}},"type":"Feature"}
]
}
