{
"type": "FeatureCollection",
"lastupdate": "2020-08-01T00:00:00Z",
"features": [
	{"geometry":{"coordinates":[-45.910517,-23.120069],"type":"Point"},"properties":{"name":"Unifer Metais","osm_id":"3175146525","tag":{"addr:housenumber":"Km 100","addr:street":"Rodovia Monteiro Lobato","amenity":"recycling"}},"type":"Feature"}
]
}
