{
"type": "FeatureCollection",
"features": [
	{"geometry":{"coordinates":[-45.910517,-23.12007],"type":"Point"},"properties":{"name":"Unifer Metais","osm_id":"3175146525","tag":{"addr:housenumber":"Km 100","addr:street":"Rodovia Monteiro Lobato","amenity":"recycling"}},"type":"Feature"}
]
}
