{
"type": "FeatureCollection",
"features": [
	{"geometry":{"coordinates":[42.142529,9.307656],"type":"Point"},"properties":{"name":"Thume Kumbi","osm_id":"1173920958","tag":{"natural":"tree","tourism":"attraction"}},"type":"Feature"},
	{"geometry":{"coordinates":[42.142359,9.30909],"type":"Point"},"properties":{"name":"Birds Palma","osm_id":"2320642878","tag":{"natural":"tree"}},"type":"Feature"},
	{"geometry":{"coordinates":[42.13508,9.308272],"type":"Point"},"properties":{"osm_id":"2320643437","tag":{"natural":"tree"}},"type":"Feature"}
]
}
