{
"type": "FeatureCollection",
"lastupdate": "2020-08-01T00:00:00Z",
"features": [
	{"geometry":{"coordinates":[13.996261,57.917401],"type":"Point"},"properties":{"name":"Sibbabo Avfallsstation","osm_id":"1815090039","tag":{"amenity":"recycling"}},"type":"Feature"}
]
}
