{
"type": "FeatureCollection",
"lastupdate": "2020-08-01T00:00:00Z",
"features": [
	{"geometry":{"coordinates":[14.049224,46.155527],"type":"Point"},"properties":{"osm_id":"761573217","tag":{"amenity":"recycling"}},"type":"Feature"},
	{"geometry":{"coordinates":[14.047266,46.173962],"type":"Point"},"properties":{"name":"Brdo","osm_id":"762537954","tag":{"amenity":"recycling"}},"type":"Feature"},
	{"geometry":{"coordinates":[14.050245,46.155166],"type":"Point"},"properties":{"osm_id":"4985243490","tag":{"amenity":"waste_basket"}},"type":"Feature"}
]
}
