{
"type": "FeatureCollection",
"features": [
	{"geometry":{"coordinates":[14.049224,46.155527],"type":"Point"},"properties":{"osm_id":"761573217","tag":{"amenity":"recycling"}},"type":"Feature"},
	{"geometry":{"coordinates":[14.047266,46.173962],"type":"Point"},"properties":{"name":"Brdo","osm_id":"762537954","tag":{"amenity":"recycling"}},"type":"Feature"},
	{"geometry":{"coordinates":[14.050245,46.155166],"type":"Point"},"properties":{"osm_id":"4985243490","tag":{"amenity":"waste_basket"}},"type":"Feature"},
	{"geometry":{"coordinates":[13.98766,46.135402],"type":"Point"},"properties":{"osm_id":"5022733698","tag":{"amenity":"waste_disposal"}},"type":"Feature"}
]
}
