{
"type": "FeatureCollection",
"features": [
	{"geometry":{"coordinates":[7.759865,52.883847],"type":"Point"},"properties":{"name":"Wertstoffhof Vrees","osm_id":"8822210081","tag":{"amenity":"recycling","opening_hours":"Sa 10:00-16:00","operator":"Abfallwirtschaftsbetrieb Landkreis Emsland","recycling:cardboard":"yes","recycling:glass_bottles":"yes","recycling:green_waste":"yes","recycling:magazines":"yes","recycling:newspaper":"yes","recycling:paper":"yes","recycling:paper_packaging":"yes","recycling:scrap_metal":"yes","recycling_type":"centre"}},"type":"Feature"}
]
}
