{
"type": "FeatureCollection",
"lastupdate": "2020-08-01T00:00:00Z",
"features": [
	{"geometry":{"coordinates":[7.808812,50.661912],"type":"Point"},"properties":{"osm_id":"836416745","tag":{"addr:city":"Hachenburg","addr:housenumber":"10","addr:postcode":"57627","addr:street":"Floriansweg","amenity":"recycling","operator":"Bellersheim Abfall Wirtschaft","recycling:batteries":"yes","recycling:cans":"yes","recycling:clothes":"yes","recycling:glass":"yes","recycling:paper":"yes","recycling:scrap_metal":"yes","recycling_type":"centre"}},"type":"Feature"},
	{"geometry":{"coordinates":[7.736582,50.657244],"type":"Point"},"properties":{"osm_id":"859433642","tag":{"amenity":"recycling","recycling:clothes":"yes","recycling:glass":"yes"}},"type":"Feature"},
	{"geometry":{"coordinates":[7.735404,50.67018],"type":"Point"},"properties":{"osm_id":"968517093","tag":{"amenity":"recycling","recycling:cans":"no","recycling:glass":"yes"}},"type":"Feature"},
	{"geometry":{"coordinates":[7.778637,50.677132],"type":"Point"},"properties":{"osm_id":"1036067770","tag":{"amenity":"recycling","recycling_type":"container"}},"type":"Feature"},
	{"geometry":{"coordinates":[7.76554,50.634229],"type":"Point"},"properties":{"osm_id":"4289493563","tag":{"amenity":"waste_basket"}},"type":"Feature"},
	{"geometry":{"coordinates":[7.760918,50.663103],"type":"Point"},"properties":{"osm_id":"6635914444","tag":{"amenity":"recycling","recycling:glass":"yes","recycling_type":"container"}},"type":"Feature"},
	{"geometry":{"coordinates":[7.755038,50.656684],"type":"Point"},"properties":{"osm_id":"6635914491","tag":{"amenity":"recycling","recycling:glass":"yes","recycling_type":"container"}},"type":"Feature"},
	{"geometry":{"coordinates":[7.749685,50.652504],"type":"Point"},"properties":{"osm_id":"6635914492","tag":{"amenity":"recycling","recycling:glass":"yes","recycling_type":"container"}},"type":"Feature"}
]
}
