{
"type": "FeatureCollection",
"features": [
	{"geometry":{"coordinates":[7.740311,50.051315],"type":"Point"},"properties":{"osm_id":"310429468","tag":{"amenity":"recycling","recycling:glass":"yes","recycling_type":"container"}},"type":"Feature"},
	{"geometry":{"coordinates":[7.770528,50.056571],"type":"Point"},"properties":{"osm_id":"310429470","tag":{"amenity":"recycling","location":"overground","recycling:clothes":"yes","recycling:glass":"yes","recycling_type":"container"}},"type":"Feature"},
	{"geometry":{"coordinates":[7.764938,50.05758],"type":"Point"},"properties":{"osm_id":"317231533","tag":{"amenity":"recycling","recycling:glass":"yes","recycling_type":"container"}},"type":"Feature"},
	{"geometry":{"coordinates":[7.767011,50.04836],"type":"Point"},"properties":{"osm_id":"317255223","tag":{"amenity":"recycling","recycling:glass":"yes"}},"type":"Feature"},
	{"geometry":{"coordinates":[7.777624,50.029717],"type":"Point"},"properties":{"osm_id":"317795504","tag":{"amenity":"recycling","recycling:glass":"yes"}},"type":"Feature"},
	{"geometry":{"coordinates":[7.808143,50.041758],"type":"Point"},"properties":{"osm_id":"634598322","tag":{"amenity":"recycling","recycling:glass_bottles":"yes","recycling_type":"container"}},"type":"Feature"},
	{"geometry":{"coordinates":[7.806566,50.049906],"type":"Point"},"properties":{"osm_id":"1023179107","tag":{"amenity":"recycling","recycling:clothes":"yes","recycling:glass_bottles":"yes","recycling_type":"container"}},"type":"Feature"},
	{"geometry":{"coordinates":[7.822115,50.051207],"type":"Point"},"properties":{"osm_id":"1023179207","tag":{"amenity":"recycling","recycling:glass_bottles":"yes","recycling_type":"container"}},"type":"Feature"},
	{"geometry":{"coordinates":[7.803365,50.042987],"type":"Point"},"properties":{"osm_id":"1113299269","tag":{"amenity":"recycling","recycling:glass_bottles":"yes","recycling_type":"container"}},"type":"Feature"},
	{"geometry":{"coordinates":[7.803581,50.04421],"type":"Point"},"properties":{"osm_id":"1165664116","tag":{"amenity":"waste_basket"}},"type":"Feature"},
	{"geometry":{"coordinates":[7.820273,50.056913],"type":"Point"},"properties":{"osm_id":"1176864919","tag":{"amenity":"waste_basket"}},"type":"Feature"},
	{"geometry":{"coordinates":[7.785575,50.051355],"type":"Point"},"properties":{"osm_id":"1401202457","tag":{"amenity":"recycling","recycling:glass_bottles":"yes","recycling_type":"container"}},"type":"Feature"},
	{"geometry":{"coordinates":[7.821968,50.051186],"type":"Point"},"properties":{"barrier":"gate","osm_id":"1482614818"},"type":"Feature"},
	{"geometry":{"coordinates":[7.821405,50.051219],"type":"Point"},"properties":{"barrier":"gate","osm_id":"1482614826"},"type":"Feature"},
	{"geometry":{"coordinates":[7.807606,50.043437],"type":"Point"},"properties":{"osm_id":"1562532006","tag":{"amenity":"waste_basket","vending":"excrement_bags"}},"type":"Feature"},
	{"geometry":{"coordinates":[7.821305,50.051242],"type":"Point"},"properties":{"osm_id":"1584401915","tag":{"amenity":"recycling","recycling:clothes":"yes","recycling_type":"container"}},"type":"Feature"},
	{"geometry":{"coordinates":[7.785625,50.052293],"type":"Point"},"properties":{"osm_id":"1603829149","tag":{"amenity":"recycling","recycling:glass_bottles":"yes","recycling_type":"container"}},"type":"Feature"},
	{"geometry":{"coordinates":[7.775804,50.031303],"type":"Point"},"properties":{"osm_id":"1874385786","tag":{"amenity":"waste_basket"}},"type":"Feature"},
	{"geometry":{"coordinates":[7.787258,50.054734],"type":"Point"},"properties":{"osm_id":"1949883477","tag":{"amenity":"recycling","recycling:green_waste":"yes","recycling_type":"container"}},"type":"Feature"},
	{"geometry":{"coordinates":[7.806347,50.047364],"type":"Point"},"properties":{"osm_id":"2087027433","tag":{"amenity":"waste_basket","vending":"excrement_bags"}},"type":"Feature"},
	{"geometry":{"coordinates":[7.766583,50.058985],"type":"Point"},"properties":{"osm_id":"2383363270","tag":{"amenity":"waste_basket"}},"type":"Feature"},
	{"geometry":{"coordinates":[7.810218,50.040723],"type":"Point"},"properties":{"osm_id":"2956910139","tag":{"amenity":"waste_basket"}},"type":"Feature"},
	{"geometry":{"coordinates":[7.808828,50.051816],"type":"Point"},"properties":{"osm_id":"2960882196","tag":{"amenity":"waste_basket"}},"type":"Feature"},
	{"geometry":{"coordinates":[7.809814,50.052652],"type":"Point"},"properties":{"osm_id":"2960882197","tag":{"amenity":"waste_basket"}},"type":"Feature"},
	{"geometry":{"coordinates":[7.818305,50.038806],"type":"Point"},"properties":{"osm_id":"4998073017","tag":{"amenity":"waste_basket"}},"type":"Feature"},
	{"geometry":{"coordinates":[7.769526,50.055954],"type":"Point"},"properties":{"osm_id":"6807609287","tag":{"amenity":"waste_basket"}},"type":"Feature"}
]
}
