{
"type": "FeatureCollection",
"features": [
	{"geometry":{"coordinates":[2.891539,50.848114],"type":"Point"},"properties":{"osm_id":"1325330257","tag":{"amenity":"waste_basket"}},"type":"Feature"},
	{"geometry":{"coordinates":[2.891777,50.84978],"type":"Point"},"properties":{"osm_id":"1325330280","tag":{"amenity":"waste_basket"}},"type":"Feature"},
	{"geometry":{"coordinates":[2.891393,50.848717],"type":"Point"},"properties":{"osm_id":"1379036836","tag":{"amenity":"waste_basket"}},"type":"Feature"},
	{"geometry":{"coordinates":[2.885032,50.852762],"type":"Point"},"properties":{"osm_id":"1838964994","tag":{"amenity":"waste_basket"}},"type":"Feature"},
	{"geometry":{"coordinates":[2.885162,50.852971],"type":"Point"},"properties":{"osm_id":"1838964999","tag":{"amenity":"waste_basket"}},"type":"Feature"},
	{"geometry":{"coordinates":[2.825535,50.856486],"type":"Point"},"properties":{"osm_id":"2329839676","tag":{"amenity":"waste_basket"}},"type":"Feature"},
	{"geometry":{"coordinates":[2.876768,50.848206],"type":"Point"},"properties":{"osm_id":"3962033730","tag":{"amenity":"waste_basket"}},"type":"Feature"},
	{"geometry":{"coordinates":[2.87684,50.848227],"type":"Point"},"properties":{"osm_id":"3962033731","tag":{"amenity":"waste_basket"}},"type":"Feature"},
	{"geometry":{"coordinates":[2.876913,50.848248],"type":"Point"},"properties":{"osm_id":"3962033732","tag":{"amenity":"waste_basket"}},"type":"Feature"},
	{"geometry":{"coordinates":[2.876984,50.848268],"type":"Point"},"properties":{"osm_id":"3962033733","tag":{"amenity":"waste_basket"}},"type":"Feature"},
	{"geometry":{"coordinates":[2.877055,50.848289],"type":"Point"},"properties":{"osm_id":"3962033734","tag":{"amenity":"waste_basket"}},"type":"Feature"},
	{"geometry":{"coordinates":[2.877125,50.848309],"type":"Point"},"properties":{"osm_id":"3962033735","tag":{"amenity":"waste_basket"}},"type":"Feature"},
	{"geometry":{"coordinates":[2.82225,50.855511],"type":"Point"},"properties":{"osm_id":"4735016128","tag":{"amenity":"waste_basket"}},"type":"Feature"},
	{"geometry":{"coordinates":[2.816456,50.854604],"type":"Point"},"properties":{"osm_id":"4735149279","tag":{"amenity":"waste_basket"}},"type":"Feature"},
	{"geometry":{"coordinates":[2.862105,50.849423],"type":"Point"},"properties":{"osm_id":"6863087173","tag":{"amenity":"recycling","operator":"Vlaams Internationaal Centrum","recycling:clothes":"yes","recycling:curtains":"yes","recycling:shoes":"yes","recycling_type":"container"}},"type":"Feature"},
	{"geometry":{"coordinates":[2.862078,50.849423],"type":"Point"},"properties":{"osm_id":"6863099338","tag":{"amenity":"recycling","operator":"Vlaams Internationaal Centrum","recycling:clothes":"yes","recycling:curtains":"yes","recycling:shoes":"yes","recycling_type":"container"}},"type":"Feature"},
	{"geometry":{"coordinates":[2.883294,50.857793],"type":"Point"},"properties":{"osm_id":"6863261402","tag":{"amenity":"recycling","operator":"Vlaams Internationaal Centrum","recycling:clothes":"yes","recycling:curtains":"yes","recycling:shoes":"yes","recycling_type":"container"}},"type":"Feature"},
	{"geometry":{"coordinates":[2.870173,50.854571],"type":"Point"},"properties":{"osm_id":"7830282239","tag":{"amenity":"recycling","recycling:glass":"yes","recycling_type":"container"}},"type":"Feature"},
	{"geometry":{"coordinates":[2.884246,50.853244],"type":"Point"},"properties":{"osm_id":"8199431483","tag":{"amenity":"recycling","opening_hours":"Mo-Su 08:00-20:00","opening_hours:covid19":"same","operator":"IVVO","recycling:glass":"yes","recycling_type":"container"}},"type":"Feature"},
	{"geometry":{"coordinates":[2.85655,50.89562],"type":"Point"},"properties":{"osm_id":"8206889241","tag":{"amenity":"waste_basket"}},"type":"Feature"},
	{"geometry":{"coordinates":[2.876032,50.888824],"type":"Point"},"properties":{"name":"Groenpark Ieper","osm_id":"8220763169","tag":{"addr:housenumber":"8","addr:street":"Bargiestraat","amenity":"recycling","recycling:green_waste":"yes","recycling_type":"centre","website":"https://www.ivvo.be/groenpark-ieper"}},"type":"Feature"}
]
}
