{
"type": "FeatureCollection",
"features": [
	{"geometry":{"coordinates":[-3.071576,39.360664],"type":"Point"},"properties":{"name":"Carrasca Gorda","osm_id":"2507991932","tag":{"natural":"tree","type":"Encina"}},"type":"Feature"},
	{"geometry":{"coordinates":[-3.024413,39.311834],"type":"Point"},"properties":{"name":"Pino Hermano Vicentillo","osm_id":"7810418334","tag":{"leaf_cycle":"evergreen","natural":"tree"}},"type":"Feature"}
]
}
