{
"type": "FeatureCollection",
"features": [
	{"geometry":{"coordinates":[-3.071576,39.360664],"type":"Point"},"properties":{"name":"Carrasca Gorda","osm_id":"2507991932","tag":{"natural":"tree","type":"Encina"}},"type":"Feature"},
	{"geometry":{"coordinates":[-3.024413,39.311834],"type":"Point"},"properties":{"name":"Pino Hermano Vicentillo","osm_id":"7810418334","tag":{"leaf_cycle":"evergreen","natural":"tree"}},"type":"Feature"},
	{"geometry":{"coordinates":[-3.044688,39.331791],"type":"Point"},"properties":{"osm_id":"8960830838","tag":{"natural":"tree"}},"type":"Feature"},
	{"geometry":{"coordinates":[-3.044623,39.331604],"type":"Point"},"properties":{"osm_id":"8960830839","tag":{"natural":"tree"}},"type":"Feature"},
	{"geometry":{"coordinates":[-3.045246,39.331276],"type":"Point"},"properties":{"osm_id":"8960830840","tag":{"natural":"tree"}},"type":"Feature"},
	{"geometry":{"coordinates":[-3.043668,39.329841],"type":"Point"},"properties":{"osm_id":"8960830841","tag":{"natural":"tree"}},"type":"Feature"},
	{"geometry":{"coordinates":[-3.042767,39.328036],"type":"Point"},"properties":{"osm_id":"8960830842","tag":{"natural":"tree"}},"type":"Feature"},
	{"geometry":{"coordinates":[-3.043068,39.327073],"type":"Point"},"properties":{"osm_id":"8960830843","tag":{"natural":"tree"}},"type":"Feature"},
	{"geometry":{"coordinates":[-3.043432,39.326446],"type":"Point"},"properties":{"osm_id":"8960830844","tag":{"natural":"tree"}},"type":"Feature"},
	{"geometry":{"coordinates":[-3.04369,39.325832],"type":"Point"},"properties":{"osm_id":"8960830845","tag":{"natural":"tree"}},"type":"Feature"},
	{"geometry":{"coordinates":[-3.041442,39.324963],"type":"Point"},"properties":{"osm_id":"8960865971","tag":{"natural":"tree"}},"type":"Feature"},
	{"geometry":{"coordinates":[-3.041198,39.325396],"type":"Point"},"properties":{"osm_id":"8960865972","tag":{"natural":"tree"}},"type":"Feature"},
	{"geometry":{"coordinates":[-3.045216,39.328355],"type":"Point"},"properties":{"osm_id":"8960866018","tag":{"natural":"tree"}},"type":"Feature"},
	{"geometry":{"coordinates":[-3.05469,39.336718],"type":"Point"},"properties":{"osm_id":"8960866870","tag":{"natural":"tree"}},"type":"Feature"},
	{"geometry":{"coordinates":[-3.068648,39.334198],"type":"Point"},"properties":{"osm_id":"8960867109","tag":{"natural":"tree"}},"type":"Feature"},
	{"geometry":{"coordinates":[-3.041701,39.312082],"type":"Point"},"properties":{"osm_id":"8963904379","tag":{"natural":"tree"}},"type":"Feature"},
	{"geometry":{"coordinates":[-3.030534,39.324245],"type":"Point"},"properties":{"osm_id":"8968906813","tag":{"natural":"tree"}},"type":"Feature"},
	{"geometry":{"coordinates":[-3.030694,39.324221],"type":"Point"},"properties":{"osm_id":"8968906814","tag":{"natural":"tree"}},"type":"Feature"},
	{"geometry":{"coordinates":[-3.03753,39.332368],"type":"Point"},"properties":{"osm_id":"8969006813","tag":{"natural":"tree"}},"type":"Feature"},
	{"geometry":{"coordinates":[-3.037696,39.33238],"type":"Point"},"properties":{"osm_id":"8969006814","tag":{"natural":"tree"}},"type":"Feature"},
	{"geometry":{"coordinates":[-3.039168,39.332539],"type":"Point"},"properties":{"osm_id":"8969006815","tag":{"natural":"tree"}},"type":"Feature"},
	{"geometry":{"coordinates":[-3.034289,39.32246],"type":"Point"},"properties":{"osm_id":"9050224161","tag":{"natural":"tree"}},"type":"Feature"},
	{"geometry":{"coordinates":[-3.029155,39.352636],"type":"Point"},"properties":{"osm_id":"9051722671","tag":{"natural":"tree"}},"type":"Feature"},
	{"geometry":{"coordinates":[-3.029247,39.352643],"type":"Point"},"properties":{"osm_id":"9051722672","tag":{"natural":"tree"}},"type":"Feature"}
]
}
