{
"type": "FeatureCollection",
"features": [
	{"geometry":{"coordinates":[103.198077,1.936596],"type":"Point"},"properties":{"name":"FELDA ayer hitam","osm_id":"6424688503","tag":{"natural":"tree"}},"type":"Feature"}
]
}
