{
"type": "FeatureCollection",
"features": [
	{"geometry":{"coordinates":[11.950684,51.923857],"type":"Point"},"properties":{"name":"Luther-Eiche","osm_id":"3297291713","tag":{"denotation":"natural_monument","image":"https://commons.wikimedia.org/wiki/File:Breitenhagen,Luther-Eiche.jpg","natural":"tree"}},"type":"Feature"}
]
}
