{
"type": "FeatureCollection",
"features": [
	{"geometry":{"coordinates":[11.901035,51.111596],"type":"Point"},"properties":{"osm_id":"1829847301","tag":{"genus:de":"Eiche","leaf_cycle":"deciduous","leaf_type":"broadleaved","natural":"tree"}},"type":"Feature"},
	{"geometry":{"coordinates":[11.899598,51.112982],"type":"Point"},"properties":{"name":"Eiche","osm_id":"1833921762","tag":{"natural":"tree"}},"type":"Feature"},
	{"geometry":{"coordinates":[11.913105,51.079662],"type":"Point"},"properties":{"osm_id":"6221445937","tag":{"genus:de":"Kirsche","natural":"tree"}},"type":"Feature"}
]
}
