{
"type": "FeatureCollection",
"features": [
	{"geometry":{"coordinates":[-8.433647,41.90984],"type":"Point"},"properties":{"name":"figuier","osm_id":"6649561206","tag":{"leaf_cycle":"deciduous","leaf_type":"broadleaved","name:fr":"figuier","natural":"tree"}},"type":"Feature"},
	{"geometry":{"coordinates":[-8.436285,41.918452],"type":"Point"},"properties":{"name":"figuier","osm_id":"6649562073","tag":{"leaf_cycle":"deciduous","leaf_type":"broadleaved","name:fr":"figuier","natural":"tree"}},"type":"Feature"},
	{"geometry":{"coordinates":[-8.435182,41.91598],"type":"Point"},"properties":{"name":"oranger","osm_id":"6650874575","tag":{"diameter":"40cm","leaf_cycle":"evergreen","leaf_type":"broadleaved","natural":"tree"}},"type":"Feature"},
	{"geometry":{"coordinates":[-8.435248,41.916107],"type":"Point"},"properties":{"osm_id":"6650874577","tag":{"natural":"tree"}},"type":"Feature"},
	{"geometry":{"coordinates":[-8.435252,41.91615],"type":"Point"},"properties":{"osm_id":"6650874578","tag":{"natural":"tree"}},"type":"Feature"},
	{"geometry":{"coordinates":[-8.435181,41.91628],"type":"Point"},"properties":{"name":"amandier","osm_id":"6650874579","tag":{"diameter":"5cm","natural":"tree"}},"type":"Feature"},
	{"geometry":{"coordinates":[-8.43507,41.916338],"type":"Point"},"properties":{"osm_id":"6650874581","tag":{"description":"chataignier","natural":"tree"}},"type":"Feature"},
	{"geometry":{"coordinates":[-8.435277,41.91608],"type":"Point"},"properties":{"osm_id":"6650874582","tag":{"natural":"tree"}},"type":"Feature"},
	{"geometry":{"coordinates":[-8.435302,41.916116],"type":"Point"},"properties":{"osm_id":"6650874583","tag":{"natural":"tree"}},"type":"Feature"},
	{"geometry":{"coordinates":[-8.434902,41.916316],"type":"Point"},"properties":{"name":"noyer","osm_id":"6650896682","tag":{"natural":"tree"}},"type":"Feature"},
	{"geometry":{"coordinates":[-8.434718,41.916167],"type":"Point"},"properties":{"osm_id":"6650896683","tag":{"natural":"tree"}},"type":"Feature"},
	{"geometry":{"coordinates":[-8.434819,41.916215],"type":"Point"},"properties":{"name":"olivier","osm_id":"6650896684","tag":{"natural":"tree"}},"type":"Feature"},
	{"geometry":{"coordinates":[-8.434887,41.916362],"type":"Point"},"properties":{"osm_id":"6650908385","tag":{"natural":"tree"}},"type":"Feature"},
	{"geometry":{"coordinates":[-8.414625,41.902936],"type":"Point"},"properties":{"name":"pin","osm_id":"6651065292","tag":{"diameter":"40cm","leaf_cycle":"evergreen","leaf_type":"needleleaved","natural":"tree"}},"type":"Feature"},
	{"geometry":{"coordinates":[-8.414127,41.902342],"type":"Point"},"properties":{"name":"chene","osm_id":"6651065293","tag":{"diameter":"20cm","leaf_cycle":"deciduous","leaf_type":"broadleaved","natural":"tree"}},"type":"Feature"},
	{"geometry":{"coordinates":[-8.415483,41.902544],"type":"Point"},"properties":{"name":"eucalyptus","osm_id":"6651065294","tag":{"diameter":"1m","leaf_cycle":"evergreen","leaf_type":"broadleaved","natural":"tree"}},"type":"Feature"},
	{"geometry":{"coordinates":[-8.415526,41.902472],"type":"Point"},"properties":{"name":"eucalyptus","osm_id":"6651065295","tag":{"diameter":"50","leaf_cycle":"evergreen","leaf_type":"broadleaved","natural":"tree"}},"type":"Feature"},
	{"geometry":{"coordinates":[-8.435252,41.91603],"type":"Point"},"properties":{"name":"oranger","osm_id":"6654729484","tag":{"diameter":"40cm","leaf_cycle":"evergreen","leaf_type":"broadleaved","natural":"tree"}},"type":"Feature"},
	{"geometry":{"coordinates":[-8.435,41.916293],"type":"Point"},"properties":{"name":"citronier","osm_id":"6654751185","tag":{"diameter":"5cm","leaf_cycle":"evergreen","leaf_type":"broadleaved","natural":"tree"}},"type":"Feature"}
]
}
