{
"type": "FeatureCollection",
"features": [
	{"geometry":{"coordinates":[-104.642239,50.498758],"type":"Point"},"properties":{"name":"Regina Blue Bin","osm_id":"847527597","tag":{"amenity":"recycling","recycling_type":"container"}},"type":"Feature"},
	{"geometry":{"coordinates":[-104.677424,50.495109],"type":"Point"},"properties":{"name":"Regina Blue Bin","osm_id":"1090470297","tag":{"amenity":"recycling","recycling_type":"container"}},"type":"Feature"},
	{"geometry":{"coordinates":[-104.658051,50.488409],"type":"Point"},"properties":{"osm_id":"2327781478","tag":{"amenity":"waste_basket"}},"type":"Feature"},
	{"geometry":{"coordinates":[-104.659623,50.487444],"type":"Point"},"properties":{"osm_id":"2327781492","tag":{"amenity":"waste_basket"}},"type":"Feature"},
	{"geometry":{"coordinates":[-104.662544,50.486446],"type":"Point"},"properties":{"osm_id":"2327781494","tag":{"amenity":"waste_basket"}},"type":"Feature"},
	{"geometry":{"coordinates":[-104.658963,50.487931],"type":"Point"},"properties":{"osm_id":"2327781498","tag":{"amenity":"waste_basket"}},"type":"Feature"},
	{"geometry":{"coordinates":[-104.661382,50.487108],"type":"Point"},"properties":{"osm_id":"2327781499","tag":{"amenity":"waste_basket"}},"type":"Feature"},
	{"geometry":{"coordinates":[-104.649672,50.487975],"type":"Point"},"properties":{"osm_id":"2327781500","tag":{"amenity":"waste_basket"}},"type":"Feature"},
	{"geometry":{"coordinates":[-104.669906,50.491332],"type":"Point"},"properties":{"osm_id":"6625189857","tag":{"amenity":"waste_basket"}},"type":"Feature"},
	{"geometry":{"coordinates":[-104.670357,50.48997],"type":"Point"},"properties":{"osm_id":"6625189858","tag":{"amenity":"waste_basket"}},"type":"Feature"},
	{"geometry":{"coordinates":[-104.669694,50.457621],"type":"Point"},"properties":{"osm_id":"6625199669","tag":{"amenity":"waste_basket"}},"type":"Feature"},
	{"geometry":{"coordinates":[-104.669857,50.459505],"type":"Point"},"properties":{"osm_id":"6625205694","tag":{"amenity":"waste_basket"}},"type":"Feature"},
	{"geometry":{"coordinates":[-104.665048,50.45841],"type":"Point"},"properties":{"osm_id":"6625205763","tag":{"amenity":"waste_basket"}},"type":"Feature"},
	{"geometry":{"coordinates":[-104.651248,50.474992],"type":"Point"},"properties":{"osm_id":"6625216840","tag":{"amenity":"waste_basket"}},"type":"Feature"},
	{"geometry":{"coordinates":[-104.652779,50.475363],"type":"Point"},"properties":{"osm_id":"6625216848","tag":{"amenity":"waste_basket"}},"type":"Feature"},
	{"geometry":{"coordinates":[-104.659147,50.473836],"type":"Point"},"properties":{"osm_id":"6625216868","tag":{"amenity":"waste_basket"}},"type":"Feature"},
	{"geometry":{"coordinates":[-104.663661,50.4752],"type":"Point"},"properties":{"osm_id":"6625216873","tag":{"amenity":"waste_basket"}},"type":"Feature"},
	{"geometry":{"coordinates":[-104.664428,50.475183],"type":"Point"},"properties":{"osm_id":"6625216874","tag":{"amenity":"waste_basket"}},"type":"Feature"},
	{"geometry":{"coordinates":[-104.673053,50.476469],"type":"Point"},"properties":{"osm_id":"6625218396","tag":{"amenity":"waste_basket"}},"type":"Feature"},
	{"geometry":{"coordinates":[-104.667898,50.459218],"type":"Point"},"properties":{"osm_id":"7015035069","tag":{"amenity":"waste_basket"}},"type":"Feature"},
	{"geometry":{"coordinates":[-104.672284,50.460406],"type":"Point"},"properties":{"osm_id":"7015035072","tag":{"amenity":"waste_basket"}},"type":"Feature"},
	{"geometry":{"coordinates":[-104.675835,50.46058],"type":"Point"},"properties":{"osm_id":"7015088786","tag":{"amenity":"waste_basket"}},"type":"Feature"},
	{"geometry":{"coordinates":[-104.674709,50.458871],"type":"Point"},"properties":{"osm_id":"7015088795","tag":{"amenity":"waste_basket"}},"type":"Feature"},
	{"geometry":{"coordinates":[-104.676022,50.457941],"type":"Point"},"properties":{"osm_id":"7015088869","tag":{"amenity":"waste_basket"}},"type":"Feature"},
	{"geometry":{"coordinates":[-104.673647,50.458019],"type":"Point"},"properties":{"osm_id":"7015088873","tag":{"amenity":"waste_basket"}},"type":"Feature"}
]
}
