{
"type": "FeatureCollection",
"lastupdate": "2020-08-05T00:00:00Z",
"features": [
	{"geometry":{"coordinates":[-104.642239,50.498757],"type":"Point"},"properties":{"name":"Regina Blue Bin","osm_id":"847527597","tag":{"amenity":"recycling","recycling_type":"container"}},"type":"Feature"},
	{"geometry":{"coordinates":[-104.677424,50.495108],"type":"Point"},"properties":{"name":"Regina Blue Bin","osm_id":"1090470297","tag":{"amenity":"recycling","recycling_type":"container"}},"type":"Feature"},
	{"geometry":{"coordinates":[-104.658051,50.488408],"type":"Point"},"properties":{"osm_id":"2327781478","tag":{"amenity":"waste_basket"}},"type":"Feature"},
	{"geometry":{"coordinates":[-104.659622,50.487444],"type":"Point"},"properties":{"osm_id":"2327781492","tag":{"amenity":"waste_basket"}},"type":"Feature"},
	{"geometry":{"coordinates":[-104.662543,50.486445],"type":"Point"},"properties":{"osm_id":"2327781494","tag":{"amenity":"waste_basket"}},"type":"Feature"},
	{"geometry":{"coordinates":[-104.658962,50.48793],"type":"Point"},"properties":{"osm_id":"2327781498","tag":{"amenity":"waste_basket"}},"type":"Feature"},
	{"geometry":{"coordinates":[-104.661382,50.487108],"type":"Point"},"properties":{"osm_id":"2327781499","tag":{"amenity":"waste_basket"}},"type":"Feature"},
	{"geometry":{"coordinates":[-104.649671,50.487975],"type":"Point"},"properties":{"osm_id":"2327781500","tag":{"amenity":"waste_basket"}},"type":"Feature"},
	{"geometry":{"coordinates":[-104.669906,50.491332],"type":"Point"},"properties":{"osm_id":"6625189857","tag":{"amenity":"waste_basket"}},"type":"Feature"},
	{"geometry":{"coordinates":[-104.670357,50.48997],"type":"Point"},"properties":{"osm_id":"6625189858","tag":{"amenity":"waste_basket"}},"type":"Feature"},
	{"geometry":{"coordinates":[-104.669693,50.457621],"type":"Point"},"properties":{"osm_id":"6625199669","tag":{"amenity":"waste_basket"}},"type":"Feature"},
	{"geometry":{"coordinates":[-104.669856,50.459505],"type":"Point"},"properties":{"osm_id":"6625205694","tag":{"amenity":"waste_basket"}},"type":"Feature"},
	{"geometry":{"coordinates":[-104.665047,50.45841],"type":"Point"},"properties":{"osm_id":"6625205763","tag":{"amenity":"waste_basket"}},"type":"Feature"},
	{"geometry":{"coordinates":[-104.651247,50.474992],"type":"Point"},"properties":{"osm_id":"6625216840","tag":{"amenity":"waste_basket"}},"type":"Feature"},
	{"geometry":{"coordinates":[-104.652779,50.475362],"type":"Point"},"properties":{"osm_id":"6625216848","tag":{"amenity":"waste_basket"}},"type":"Feature"},
	{"geometry":{"coordinates":[-104.659146,50.473836],"type":"Point"},"properties":{"osm_id":"6625216868","tag":{"amenity":"waste_basket"}},"type":"Feature"},
	{"geometry":{"coordinates":[-104.66366,50.4752],"type":"Point"},"properties":{"osm_id":"6625216873","tag":{"amenity":"waste_basket"}},"type":"Feature"},
	{"geometry":{"coordinates":[-104.664427,50.475183],"type":"Point"},"properties":{"osm_id":"6625216874","tag":{"amenity":"waste_basket"}},"type":"Feature"},
	{"geometry":{"coordinates":[-104.673052,50.476469],"type":"Point"},"properties":{"osm_id":"6625218396","tag":{"amenity":"waste_basket"}},"type":"Feature"},
	{"geometry":{"coordinates":[-104.667897,50.459217],"type":"Point"},"properties":{"osm_id":"7015035069","tag":{"amenity":"waste_basket"}},"type":"Feature"},
	{"geometry":{"coordinates":[-104.672284,50.460405],"type":"Point"},"properties":{"osm_id":"7015035072","tag":{"amenity":"waste_basket"}},"type":"Feature"},
	{"geometry":{"coordinates":[-104.675834,50.460579],"type":"Point"},"properties":{"osm_id":"7015088786","tag":{"amenity":"waste_basket"}},"type":"Feature"},
	{"geometry":{"coordinates":[-104.674709,50.45887],"type":"Point"},"properties":{"osm_id":"7015088795","tag":{"amenity":"waste_basket"}},"type":"Feature"},
	{"geometry":{"coordinates":[-104.676022,50.457941],"type":"Point"},"properties":{"osm_id":"7015088869","tag":{"amenity":"waste_basket"}},"type":"Feature"},
	{"geometry":{"coordinates":[-104.673647,50.458018],"type":"Point"},"properties":{"osm_id":"7015088873","tag":{"amenity":"waste_basket"}},"type":"Feature"}
]
}
