{
"type": "FeatureCollection",
"lastupdate": "2020-08-04T00:00:00Z",
"features": [
	{"geometry":{"coordinates":[8.219133,60.542853],"type":"Point"},"properties":{"osm_id":"5555202993","tag":{"amenity":"recycling","description":"Bard\u00f8lsg\u00e5rd","recycling:glass_bottles":"yes","recycling:paper":"yes","recycling:waste":"yes","recycling_type":"container","ref:sortere":"16133"}},"type":"Feature"},
	{"geometry":{"coordinates":[8.193192,60.532832],"type":"Point"},"properties":{"osm_id":"5555203030","tag":{"amenity":"recycling","description":"R\u00f8nsg\u00e5rd","recycling:glass_bottles":"yes","recycling:paper":"yes","recycling:waste":"yes","recycling_type":"container","ref:sortere":"16114"}},"type":"Feature"},
	{"geometry":{"coordinates":[8.193375,60.520965],"type":"Point"},"properties":{"osm_id":"5555203031","tag":{"amenity":"recycling","description":"R\u00f8de Kors (Vestlia)","recycling:waste":"yes","recycling_type":"container","ref:sortere":"16113"}},"type":"Feature"},
	{"geometry":{"coordinates":[8.215982,60.525008],"type":"Point"},"properties":{"osm_id":"5555203033","tag":{"amenity":"recycling","description":"Gamle Skurdalsvegen","recycling:glass_bottles":"yes","recycling:paper":"yes","recycling:waste":"yes","recycling_type":"container","ref:sortere":"16112"}},"type":"Feature"},
	{"geometry":{"coordinates":[8.236268,60.505403],"type":"Point"},"properties":{"osm_id":"5555203035","tag":{"amenity":"recycling","description":"Kikut","recycling:glass_bottles":"yes","recycling:paper":"yes","recycling:waste":"yes","recycling_type":"container","ref:sortere":"16111"}},"type":"Feature"},
	{"geometry":{"coordinates":[8.248664,60.538494],"type":"Point"},"properties":{"name":"Lauvrud avfallsmottak, Geilo","osm_id":"5555204256","tag":{"amenity":"recycling","phone":"+47 32086110","recycling:asbestos":"yes","recycling:batteries":"yes","recycling:electrical_items":"yes","recycling:garden_waste":"yes","recycling:glass":"yes","recycling:glass_bottles":"yes","recycling:hazardous_waste":"yes","recycling:paper":"yes","recycling:plasterboard":"yes","recycling:plastic_packaging":"yes","recycling:polystyrene_foam":"yes","recycling:rubble":"yes","recycling:scrap_metal":"yes","recycling:second_hand":"yes","recycling:tyres":"yes","recycling:waste":"yes","recycling:wood":"yes","recycling_type":"centre","ref:sortere":"1231","website":"https://www.hallingdalrenovasjon.no/"}},"type":"Feature"},
	{"geometry":{"coordinates":[8.216363,60.526397],"type":"Point"},"properties":{"osm_id":"6195520908","tag":{"amenity":"recycling","description":"Kommunelager Vestlia","recycling:glass_bottles":"yes","recycling:paper":"yes","recycling:waste":"yes","recycling_type":"container","ref:sortere":"16112"}},"type":"Feature"}
]
}
