{
"type": "FeatureCollection",
"features": [
	{"geometry":{"coordinates":[100.393669,5.433498],"type":"Point"},"properties":{"osm_id":"4434338804","tag":{"amenity":"waste_disposal"}},"type":"Feature"},
	{"geometry":{"coordinates":[100.393367,5.432042],"type":"Point"},"properties":{"osm_id":"5940788246","tag":{"amenity":"waste_disposal"}},"type":"Feature"},
	{"geometry":{"coordinates":[100.39875,5.428378],"type":"Point"},"properties":{"osm_id":"5940818309","tag":{"amenity":"waste_disposal"}},"type":"Feature"},
	{"geometry":{"coordinates":[100.458095,5.363421],"type":"Point"},"properties":{"osm_id":"5951108839","tag":{"amenity":"waste_basket"}},"type":"Feature"},
	{"geometry":{"coordinates":[100.380516,5.429095],"type":"Point"},"properties":{"name":"\u00e6\u0085\u0088\u00e6\u00b5\u008e\u00e5\u008c\u0097\u00e6\u00b5\u00b7\u00e7\u008e\u00af\u00e4\u00bf\u009d\u00e6\u0095\u0099\u00e8\u0082\u00b2\u00e7\u00ab\u0099","osm_id":"6186186148","tag":{"amenity":"recycling","name:en":"Tzu Chi Butterworth Recycling and Education Center","recycling_type":"centre"}},"type":"Feature"},
	{"geometry":{"coordinates":[100.397792,5.428173],"type":"Point"},"properties":{"osm_id":"6416312678","tag":{"amenity":"waste_disposal"}},"type":"Feature"}
]
}
