{
"type": "FeatureCollection",
"features": [
	{"geometry":{"coordinates":[7.445941,44.52194],"type":"Point"},"properties":{"name":"Castagno","osm_id":"3745691458","tag":{"leaf_type":"broadleaved","natural":"tree"}},"type":"Feature"},
	{"geometry":{"coordinates":[7.469718,44.518884],"type":"Point"},"properties":{"osm_id":"4485462222","tag":{"natural":"tree"}},"type":"Feature"},
	{"geometry":{"coordinates":[7.469511,44.518874],"type":"Point"},"properties":{"osm_id":"4485462223","tag":{"natural":"tree"}},"type":"Feature"},
	{"geometry":{"coordinates":[7.469223,44.518863],"type":"Point"},"properties":{"osm_id":"4485462224","tag":{"natural":"tree"}},"type":"Feature"},
	{"geometry":{"coordinates":[7.469015,44.518848],"type":"Point"},"properties":{"osm_id":"4485462225","tag":{"natural":"tree"}},"type":"Feature"},
	{"geometry":{"coordinates":[7.468851,44.518842],"type":"Point"},"properties":{"osm_id":"4485462226","tag":{"natural":"tree"}},"type":"Feature"},
	{"geometry":{"coordinates":[7.468633,44.518829],"type":"Point"},"properties":{"osm_id":"4485462227","tag":{"natural":"tree"}},"type":"Feature"}
]
}
