{
"type": "FeatureCollection",
"features": [
	{"geometry":{"coordinates":[7.401329,43.802992],"type":"Point"},"properties":{"osm_id":"715712620","tag":{"genus":"Platanus","genus:fr":"Platane","natural":"tree"}},"type":"Feature"},
	{"geometry":{"coordinates":[7.443588,43.786703],"type":"Point"},"properties":{"name":"Orme de 1713","osm_id":"1658019663","tag":{"denotation":"natural_monument","genus":"Ulmus","leaf_cycle":"deciduous","leaf_type":"broadleaved","natural":"tree","start_date":"1713","tourism":"attraction"}},"type":"Feature"}
]
}
