{
"type": "FeatureCollection",
"features": [
	{"geometry":{"coordinates":[7.401329,43.802992],"type":"Point"},"properties":{"osm_id":"715712620","tag":{"genus":"Platanus","genus:fr":"Platane","natural":"tree"}},"type":"Feature"},
	{"geometry":{"coordinates":[7.443588,43.786703],"type":"Point"},"properties":{"name":"Orme de 1713","osm_id":"1658019663","tag":{"denotation":"natural_monument","genus":"Ulmus","leaf_cycle":"deciduous","leaf_type":"broadleaved","natural":"tree","start_date":"1713","tourism":"attraction","wikimedia_commons":"File:Gorbio (l'orme1).jpg"}},"type":"Feature"},
	{"geometry":{"coordinates":[7.425094,43.771231],"type":"Point"},"properties":{"osm_id":"8419621483","tag":{"natural":"tree"}},"type":"Feature"},
	{"geometry":{"coordinates":[7.424798,43.771288],"type":"Point"},"properties":{"osm_id":"8419621484","tag":{"natural":"tree"}},"type":"Feature"},
	{"geometry":{"coordinates":[7.424977,43.771153],"type":"Point"},"properties":{"osm_id":"8419621487","tag":{"natural":"tree"}},"type":"Feature"}
]
}
