{
"type": "FeatureCollection",
"features": [
	{"geometry":{"coordinates":[116.154042,-31.939893],"type":"Point"},"properties":{"barrier":"log","name":"Fallen Tree","osm_id":"1116955258","tag":{"height":"2","natural":"tree"}},"type":"Feature"}
]
}
