{
"type": "FeatureCollection",
"features": [
	{"geometry":{"coordinates":[151.482876,-33.394192],"type":"Point"},"properties":{"osm_id":"4947845724","tag":{"amenity":"waste_basket"}},"type":"Feature"},
	{"geometry":{"coordinates":[151.48294,-33.394038],"type":"Point"},"properties":{"osm_id":"4947845725","tag":{"amenity":"waste_basket"}},"type":"Feature"},
	{"geometry":{"coordinates":[151.475841,-33.364332],"type":"Point"},"properties":{"osm_id":"5042212519","tag":{"amenity":"waste_basket"}},"type":"Feature"},
	{"geometry":{"coordinates":[151.475358,-33.364589],"type":"Point"},"properties":{"osm_id":"5042213748","tag":{"amenity":"waste_basket"}},"type":"Feature"},
	{"geometry":{"coordinates":[151.47874,-33.361305],"type":"Point"},"properties":{"osm_id":"5042213815","tag":{"amenity":"waste_basket"}},"type":"Feature"},
	{"geometry":{"coordinates":[151.479553,-33.360689],"type":"Point"},"properties":{"osm_id":"5042213851","tag":{"amenity":"waste_basket"}},"type":"Feature"},
	{"geometry":{"coordinates":[151.493383,-33.366109],"type":"Point"},"properties":{"osm_id":"5198058790","tag":{"amenity":"waste_basket"}},"type":"Feature"},
	{"geometry":{"coordinates":[151.46118,-33.365854],"type":"Point"},"properties":{"name":"Return and Earn","osm_id":"6507553716","tag":{"amenity":"recycling"}},"type":"Feature"},
	{"geometry":{"coordinates":[151.445851,-33.427326],"type":"Point"},"properties":{"osm_id":"6796384794","tag":{"amenity":"waste_basket"}},"type":"Feature"},
	{"geometry":{"coordinates":[151.446758,-33.428592],"type":"Point"},"properties":{"osm_id":"6796384796","tag":{"amenity":"waste_basket"}},"type":"Feature"},
	{"geometry":{"coordinates":[151.446535,-33.428272],"type":"Point"},"properties":{"osm_id":"6796384797","tag":{"amenity":"waste_basket"}},"type":"Feature"},
	{"geometry":{"coordinates":[151.475931,-33.365509],"type":"Point"},"properties":{"osm_id":"7121827538","tag":{"amenity":"waste_basket","waste":"trash"}},"type":"Feature"},
	{"geometry":{"coordinates":[151.475665,-33.365372],"type":"Point"},"properties":{"osm_id":"7121827540","tag":{"amenity":"waste_basket","waste":"trash"}},"type":"Feature"},
	{"geometry":{"coordinates":[151.47296,-33.374875],"type":"Point"},"properties":{"osm_id":"7134853495","tag":{"amenity":"waste_basket","colour":"white","waste":"trash"}},"type":"Feature"},
	{"geometry":{"coordinates":[151.473038,-33.373594],"type":"Point"},"properties":{"osm_id":"7134853623","tag":{"amenity":"waste_basket","level":"0","material":"white","waste":"trash"}},"type":"Feature"}
]
}
