{
"type": "FeatureCollection",
"features": [
	{"geometry":{"coordinates":[21.693178,49.992339],"type":"Point"},"properties":{"name":"Pomnik przyrody","osm_id":"4005802327","tag":{"denotation":"natural_monument","monument":"yes","natural":"tree","protected":"yes"}},"type":"Feature"}
]
}
