{
"type": "FeatureCollection",
"features": [
	{"geometry":{"coordinates":[12.507001,50.912041],"type":"Point"},"properties":{"osm_id":"1944252337","tag":{"amenity":"recycling","recycling:glass":"yes","recycling_type":"container"}},"type":"Feature"},
	{"geometry":{"coordinates":[12.550241,50.925688],"type":"Point"},"properties":{"osm_id":"2089048384","tag":{"amenity":"recycling","location":"overground","recycling:glass":"yes","recycling_type":"container"}},"type":"Feature"},
	{"geometry":{"coordinates":[12.553061,50.930841],"type":"Point"},"properties":{"osm_id":"2089199061","tag":{"amenity":"recycling","recycling:glass":"yes"}},"type":"Feature"},
	{"geometry":{"coordinates":[12.549344,50.956312],"type":"Point"},"properties":{"osm_id":"2091341505","tag":{"amenity":"recycling","recycling:clothes":"yes","recycling_type":"container"}},"type":"Feature"},
	{"geometry":{"coordinates":[12.540171,50.907602],"type":"Point"},"properties":{"osm_id":"3450597943","tag":{"amenity":"recycling","recycling:cans":"no","recycling:glass":"yes","recycling:paper":"no"}},"type":"Feature"},
	{"geometry":{"coordinates":[12.565581,50.952665],"type":"Point"},"properties":{"osm_id":"7430845985","tag":{"amenity":"recycling","recycling_type":"container","survey:date":"2020-04-21"}},"type":"Feature"}
]
}
