{
"type": "FeatureCollection",
"lastupdate": "2020-08-03T00:00:00Z",
"features": [
	{"geometry":{"coordinates":[12.52608,49.33773],"type":"Point"},"properties":{"name":"Wertstoffhof","osm_id":"821878570","tag":{"amenity":"recycling"}},"type":"Feature"},
	{"geometry":{"coordinates":[12.501831,49.349923],"type":"Point"},"properties":{"osm_id":"6876058940","tag":{"amenity":"waste_basket","waste":"trash"}},"type":"Feature"},
	{"geometry":{"coordinates":[12.501554,49.349841],"type":"Point"},"properties":{"osm_id":"6876058943","tag":{"amenity":"waste_basket","waste":"dog_excrement"}},"type":"Feature"},
	{"geometry":{"coordinates":[12.501717,49.349375],"type":"Point"},"properties":{"osm_id":"6876058944","tag":{"amenity":"waste_basket","waste":"trash"}},"type":"Feature"},
	{"geometry":{"coordinates":[12.505072,49.33653],"type":"Point"},"properties":{"osm_id":"7229864734","tag":{"amenity":"waste_basket","waste":"trash"}},"type":"Feature"}
]
}
