{
"type": "FeatureCollection",
"lastupdate": "2020-08-02T00:00:00Z",
"features": [
	{"geometry":{"coordinates":[12.511822,48.637725],"type":"Point"},"properties":{"name":"Kompostierplatz Dingolfing","osm_id":"1109546296","tag":{"amenity":"recycling","recycling:batteries":"no"}},"type":"Feature"},
	{"geometry":{"coordinates":[12.509966,48.636784],"type":"Point"},"properties":{"barrier":"gate","osm_id":"1120474699","tag":{"bicycle":"yes","foot":"yes","motorcar":"yes","motorcycle":"yes"}},"type":"Feature"},
	{"geometry":{"coordinates":[12.509756,48.637284],"type":"Point"},"properties":{"barrier":"gate","osm_id":"1120474756","tag":{"bicycle":"yes","foot":"yes","motorcar":"yes","motorcycle":"yes"}},"type":"Feature"},
	{"geometry":{"coordinates":[12.494527,48.641922],"type":"Point"},"properties":{"osm_id":"2180227258","tag":{"amenity":"recycling","recycling:clothes":"yes","recycling:shoes":"yes","recycling_type":"container"}},"type":"Feature"},
	{"geometry":{"coordinates":[12.498037,48.642484],"type":"Point"},"properties":{"osm_id":"2439267156","tag":{"amenity":"waste_basket"}},"type":"Feature"},
	{"geometry":{"coordinates":[12.492435,48.666827],"type":"Point"},"properties":{"barrier":"gate","osm_id":"2887923859","tag":{"bicycle":"no","foot":"no"}},"type":"Feature"},
	{"geometry":{"coordinates":[12.498657,48.645069],"type":"Point"},"properties":{"osm_id":"3724220125","tag":{"amenity":"waste_basket"}},"type":"Feature"},
	{"geometry":{"coordinates":[12.532155,48.645352],"type":"Point"},"properties":{"name":"Wertstoffhof Gottfrieding","osm_id":"5761771795","tag":{"amenity":"recycling","recycling:batteries":"yes","recycling:cans":"yes","recycling:clothes":"yes","recycling:glass_bottles":"yes","recycling:paper":"yes","recycling:plastic":"yes","recycling:plastic_bottles":"yes","recycling:scrap_metal":"yes","recycling:shoes":"yes","recycling_type":"centre"}},"type":"Feature"}
]
}
