{
"type": "FeatureCollection",
"features": [
	{"geometry":{"coordinates":[12.563218,47.467456],"type":"Point"},"properties":{"name":"Recyclinghof der Gemeinde Fieberbrunn","osm_id":"2324613065","tag":{"addr:city":"Fieberbrunn","addr:country":"AT","addr:housenumber":"1","addr:postcode":"6391","addr:street":"Dandlerau","amenity":"recycling","collection_times":"Mo 14:00-17:00; Th 13:00-19:00; Fr 09:00-12:00","contact:email":"umwelt@fieberbrunn.tirol.gv.at","layer":"1","operator":"Gemeinde Fieberbrunn","phone":"+43535452005","recycling:batteries":"yes","recycling:cans":"yes","recycling:clothes":"yes","recycling:glass":"yes","recycling:paper":"yes","recycling:scrap_metal":"yes","recycling_type":"centre","website":"http://www.fieberbrunn.tirol.gv.at/system/web/gemeindebetrieb.aspx?menuonr=218504141&detailonr=116166"}},"type":"Feature"},
	{"geometry":{"coordinates":[12.561535,47.50018],"type":"Point"},"properties":{"name":"Recyclinghof St. Jakob in Haus","osm_id":"7306955560","tag":{"addr:city":"St. Jakob in Haus","addr:country":"AT","addr:housename":"Bau- u. Recyclinghof","addr:housenumber":"2","addr:postcode":"6392","addr:street":"Sportplatzweg","amenity":"recycling","opening_hours":"We 14:00-19:00","recycling_type":"centre"}},"type":"Feature"},
	{"geometry":{"coordinates":[12.561535,47.50018],"type":"Point"},"properties":{"name":"Recyclinghof St. Jakob in Haus","osm_id":"7307023075","tag":{"addr:city":"St. Jakob in Haus","addr:country":"AT","addr:housename":"Bau- u. Recyclinghof","addr:housenumber":"2","addr:postcode":"6392","addr:street":"Sportplatzweg","amenity":"recycling","opening_hours":"We 14:00-19:00","recycling_type":"centre"}},"type":"Feature"}
]
}
