{
"type": "FeatureCollection",
"features": [
	{"geometry":{"coordinates":[-102.248072,21.874994],"type":"Point"},"properties":{"name":"Carol","osm_id":"4405086289","tag":{"amenity":"waste_basket","name:es":"Carol"}},"type":"Feature"},
	{"geometry":{"coordinates":[-102.283165,21.903001],"type":"Point"},"properties":{"name":"Centro de acopio la Estrella","osm_id":"6489562134","tag":{"amenity":"recycling","recycling_type":"centre"}},"type":"Feature"},
	{"geometry":{"coordinates":[-102.266414,21.926931],"type":"Point"},"properties":{"name":"Centro de Acopio Siglo XXI","osm_id":"6489562265","tag":{"amenity":"recycling","recycling_type":"centre"}},"type":"Feature"},
	{"geometry":{"coordinates":[-102.287414,21.900814],"type":"Point"},"properties":{"osm_id":"7235529285","tag":{"amenity":"waste_disposal"}},"type":"Feature"},
	{"geometry":{"coordinates":[-102.2773,21.912162],"type":"Point"},"properties":{"osm_id":"7273316785","tag":{"amenity":"waste_disposal"}},"type":"Feature"}
]
}
