{
"type": "FeatureCollection",
"features": [
	{"geometry":{"coordinates":[135.820944,35.12402],"type":"Point"},"properties":{"name":"\u00e5\u008d\u0083\u00e5\u00b9\u00b4\u00e3\u0081\u00ae\u00e5\u00a7\u00ab\u00e5\u00b0\u008f\u00e6\u009d\u00be","osm_id":"3698398599","tag":{"natural":"tree"}},"type":"Feature"},
	{"geometry":{"coordinates":[135.820938,35.123978],"type":"Point"},"properties":{"name":"\u00e6\u00b1\u0080\u00e3\u0081\u00ae\u00e6\u00a1\u009c","osm_id":"3698398611","tag":{"natural":"tree"}},"type":"Feature"},
	{"geometry":{"coordinates":[135.833625,35.119011],"type":"Point"},"properties":{"osm_id":"6130899852","tag":{"natural":"tree"}},"type":"Feature"},
	{"geometry":{"coordinates":[135.83358,35.119011],"type":"Point"},"properties":{"osm_id":"6130899853","tag":{"natural":"tree"}},"type":"Feature"},
	{"geometry":{"coordinates":[135.8335,35.118934],"type":"Point"},"properties":{"osm_id":"6130899855","tag":{"natural":"tree"}},"type":"Feature"},
	{"geometry":{"coordinates":[135.833513,35.118952],"type":"Point"},"properties":{"osm_id":"6130899856","tag":{"natural":"tree"}},"type":"Feature"},
	{"geometry":{"coordinates":[135.833941,35.121217],"type":"Point"},"properties":{"name":"Fuji Pine","osm_id":"6514741435","tag":{"denotation":"garden","leaf_cycle":"evergreen","leaf_type":"leafless","name:ja":"\u00e5\u00af\u008c\u00e5\u00a3\u00ab\u00e3\u0081\u00ae\u00e6\u009d\u00be","natural":"tree"}},"type":"Feature"}
]
}
