{
"type": "FeatureCollection",
"features": [
	{"geometry":{"coordinates":[30.989136,2.416805],"type":"Point"},"properties":{"osm_id":"6646199028","tag":{"natural":"tree"}},"type":"Feature"},
	{"geometry":{"coordinates":[30.986274,2.44369],"type":"Point"},"properties":{"name":"Euclaputors tree","osm_id":"9147491805","tag":{"addr:district":"Zombo","addr:parish":"Zingili","addr:street":"landmark","addr:subcounty":"Paidha_Town_Council","comment":"It's in the middle of village","gps":"2.44369 30.9862744 1439.2427647340019 4.283","natural":"tree","village":"Arindima"}},"type":"Feature"},
	{"geometry":{"coordinates":[30.991051,2.417903],"type":"Point"},"properties":{"name":"Big tree","osm_id":"9147491812","tag":{"addr:district":"Zombo","addr:parish":"Omua","addr:street":"landmark","addr:subcounty":"Paidha_Town_Council","comment":"Meeting point of the people","gps":"2.4179033 30.9910517 1498.6 2.128","natural":"tree","village":"Abongo"}},"type":"Feature"}
]
}
