{
"type": "FeatureCollection",
"features": [
	{"geometry":{"coordinates":[-85.935371,37.832969],"type":"Point"},"properties":{"name":"Recycling Trailer","osm_id":"2583050629","tag":{"amenity":"recycling"}},"type":"Feature"}
]
}
