{
"type": "FeatureCollection",
"lastupdate": "2020-08-04T00:00:00Z",
"features": [
	{"geometry":{"coordinates":[-85.93537,37.832968],"type":"Point"},"properties":{"name":"Recycling Trailer","osm_id":"2583050629","tag":{"amenity":"recycling"}},"type":"Feature"}
]
}
