{
"type": "FeatureCollection",
"features": [
	{"geometry":{"coordinates":[-85.93537,37.832968],"type":"Point"},"properties":{"name":"Recycling Trailer","osm_id":"2583050629","tag":{"amenity":"recycling"}},"type":"Feature"},
	{"geometry":{"coordinates":[-85.927362,37.811091],"type":"Point"},"properties":{"osm_id":"8314018057","tag":{"amenity":"waste_disposal"}},"type":"Feature"}
]
}
