{
"type": "FeatureCollection",
"features": [
	{"geometry":{"coordinates":[76.590914,9.233548],"type":"Point"},"properties":{"name":"the peepul treee","osm_id":"4611679540","tag":{"denotation":"landmark","leaf_cycle":"evergreen","leaf_type":"broadleaved","natural":"tree"}},"type":"Feature"},
	{"geometry":{"coordinates":[76.590382,9.233487],"type":"Point"},"properties":{"osm_id":"7471027087","tag":{"natural":"tree"}},"type":"Feature"},
	{"geometry":{"coordinates":[76.590187,9.232018],"type":"Point"},"properties":{"osm_id":"7471558530","tag":{"natural":"tree"}},"type":"Feature"},
	{"geometry":{"coordinates":[76.584395,9.238373],"type":"Point"},"properties":{"osm_id":"7473167691","tag":{"natural":"tree"}},"type":"Feature"},
	{"geometry":{"coordinates":[76.555652,9.237529],"type":"Point"},"properties":{"osm_id":"8250723238","tag":{"natural":"tree"}},"type":"Feature"}
]
}
