{
"type": "FeatureCollection",
"features": [
	{"geometry":{"coordinates":[120.803274,23.505036],"type":"Point"},"properties":{"name":"\u00e6\u00b0\u00b4\u00e5\u00b1\u00b1\u00e7\u00a5\u009e\u00e6\u009c\u00a8","osm_id":"4188727496","tag":{"alt_name:en":"Shuishan Giant Tree","name:en":"Giant Tree of Shuishan Mt","name:zh":"\u00e6\u00b0\u00b4\u00e5\u00b1\u00b1\u00e7\u00a5\u009e\u00e6\u009c\u00a8","natural":"tree","tourism":"attraction"}},"type":"Feature"},
	{"geometry":{"coordinates":[120.807952,23.517193],"type":"Point"},"properties":{"name":"\u00e9\u0098\u00bf\u00e9\u0087\u008c\u00e5\u00b1\u00b1\u00e7\u00a5\u009e\u00e6\u009c\u00a8","osm_id":"4414801217","tag":{"name:en":"Big Tree","name:zh":"\u00e9\u0098\u00bf\u00e9\u0087\u008c\u00e5\u00b1\u00b1\u00e7\u00a5\u009e\u00e6\u009c\u00a8","natural":"tree","tourism":"attraction"}},"type":"Feature"},
	{"geometry":{"coordinates":[120.810576,23.515988],"type":"Point"},"properties":{"name":"\u00e6\u00ab\u00bb\u00e7\u008e\u008b","osm_id":"7685957909","tag":{"natural":"tree"}},"type":"Feature"}
]
}
