{
"type": "FeatureCollection",
"lastupdate": "2020-08-03T00:00:00Z",
"features": [
	{"geometry":{"coordinates":[-66.488717,45.833863],"type":"Point"},"properties":{"name":"Oromocto Recycling Drop Off","osm_id":"4279960890","tag":{"amenity":"recycling"}},"type":"Feature"},
	{"geometry":{"coordinates":[-66.519821,45.832827],"type":"Point"},"properties":{"name":"Oromocto Recycling Depot","osm_id":"4279974989","tag":{"amenity":"recycling"}},"type":"Feature"}
]
}
