{
"type": "FeatureCollection",
"features": [
	{"geometry":{"coordinates":[-66.488718,45.833864],"type":"Point"},"properties":{"name":"Oromocto Recycling Drop Off","osm_id":"4279960890","tag":{"amenity":"recycling"}},"type":"Feature"},
	{"geometry":{"coordinates":[-66.519822,45.832828],"type":"Point"},"properties":{"name":"Oromocto Recycling Depot","osm_id":"4279974989","tag":{"amenity":"recycling"}},"type":"Feature"}
]
}
