{
"type": "FeatureCollection",
"features": [
	{"geometry":{"coordinates":[9.716753,44.703334],"type":"Point"},"properties":{"osm_id":"2523424230","tag":{"natural":"tree"}},"type":"Feature"},
	{"geometry":{"coordinates":[9.720909,44.709721],"type":"Point"},"properties":{"name":"Ginepri","osm_id":"2524227538","tag":{"leaf_type":"needleleaved","natural":"tree"}},"type":"Feature"}
]
}
