{
"type": "FeatureCollection",
"features": [
	{"geometry":{"coordinates":[-4.117188,57.592636],"type":"Point"},"properties":{"osm_id":"2420247231","tag":{"amenity":"recycling","recycling:cans":"yes","recycling:clothes":"yes","recycling:glass":"yes","recycling:paper":"yes"}},"type":"Feature"},
	{"geometry":{"coordinates":[-4.112705,57.591823],"type":"Point"},"properties":{"osm_id":"2930080979","tag":{"amenity":"recycling","location":"overground","recycling:cans":"yes","recycling:paper":"yes","recycling_type":"container"}},"type":"Feature"}
]
}
