{
"type": "FeatureCollection",
"features": [
	{"geometry":{"coordinates":[-4.115087,50.373815],"type":"Point"},"properties":{"osm_id":"365198475","tag":{"amenity":"recycling"}},"type":"Feature"},
	{"geometry":{"coordinates":[-4.123226,50.36802],"type":"Point"},"properties":{"osm_id":"365372525","tag":{"amenity":"recycling","location":"overground","recycling_type":"container"}},"type":"Feature"},
	{"geometry":{"coordinates":[-4.101828,50.372082],"type":"Point"},"properties":{"name":"Chelson Meadow","osm_id":"4170572580","tag":{"amenity":"recycling","operator":"Plymouth City Council","recycling:batteries":"yes","recycling:cans":"yes","recycling:cardboard":"yes","recycling:clothes":"yes","recycling:electrical_appliances":"yes","recycling:glass":"yes","recycling:glass_bottles":"yes","recycling:green_waste":"yes","recycling:paper":"yes","recycling:plastic":"yes","recycling:plastic_bottles":"yes","recycling:plastic_packaging":"yes","recycling:scrap_metal":"yes","recycling:shoes":"yes","recycling:small_appliances":"yes","recycling:waste":"yes","recycling_type":"centre"}},"type":"Feature"},
	{"geometry":{"coordinates":[-4.05139,50.360241],"type":"Point"},"properties":{"osm_id":"6721919131","tag":{"amenity":"waste_basket"}},"type":"Feature"},
	{"geometry":{"coordinates":[-4.0497,50.360878],"type":"Point"},"properties":{"osm_id":"6721919144","tag":{"amenity":"waste_basket"}},"type":"Feature"},
	{"geometry":{"coordinates":[-4.045267,50.361471],"type":"Point"},"properties":{"osm_id":"6721919209","tag":{"amenity":"waste_basket"}},"type":"Feature"},
	{"geometry":{"coordinates":[-4.046882,50.361545],"type":"Point"},"properties":{"osm_id":"6721919210","tag":{"amenity":"waste_basket"}},"type":"Feature"},
	{"geometry":{"coordinates":[-4.046462,50.362121],"type":"Point"},"properties":{"osm_id":"6742114206","tag":{"amenity":"waste_basket"}},"type":"Feature"},
	{"geometry":{"coordinates":[-4.085746,50.36618],"type":"Point"},"properties":{"osm_id":"6925465724","tag":{"amenity":"waste_basket","waste":"trash;dog_excrement"}},"type":"Feature"}
]
}
