{
"type": "FeatureCollection",
"features": [
	{"geometry":{"coordinates":[-4.115087,50.373814],"type":"Point"},"properties":{"osm_id":"365198475","tag":{"amenity":"recycling"}},"type":"Feature"},
	{"geometry":{"coordinates":[-4.123225,50.368019],"type":"Point"},"properties":{"osm_id":"365372525","tag":{"amenity":"recycling","location":"overground","recycling_type":"container"}},"type":"Feature"},
	{"geometry":{"coordinates":[-4.101828,50.372081],"type":"Point"},"properties":{"name":"Chelson Meadow","osm_id":"4170572580","tag":{"amenity":"recycling","building":"no","operator":"Plymouth City Council","owner":"Plymouth City Council","ownership":"municipal","recycling:batteries":"yes","recycling:cans":"yes","recycling:cardboard":"yes","recycling:clothes":"yes","recycling:electrical_appliances":"yes","recycling:glass":"yes","recycling:glass_bottles":"yes","recycling:green_waste":"yes","recycling:paper":"yes","recycling:plastic":"yes","recycling:plastic_bottles":"yes","recycling:plastic_packaging":"yes","recycling:scrap_metal":"yes","recycling:shoes":"yes","recycling:small_appliances":"yes","recycling:waste":"yes","recycling_type":"centre","wikidata":"Q106093895"}},"type":"Feature"},
	{"geometry":{"coordinates":[-4.051389,50.360241],"type":"Point"},"properties":{"osm_id":"6721919131","tag":{"amenity":"waste_basket"}},"type":"Feature"},
	{"geometry":{"coordinates":[-4.049699,50.360878],"type":"Point"},"properties":{"osm_id":"6721919144","tag":{"amenity":"waste_basket"}},"type":"Feature"},
	{"geometry":{"coordinates":[-4.045189,50.361475],"type":"Point"},"properties":{"osm_id":"6721919209","tag":{"amenity":"waste_basket"}},"type":"Feature"},
	{"geometry":{"coordinates":[-4.046882,50.361544],"type":"Point"},"properties":{"osm_id":"6721919210","tag":{"amenity":"waste_basket"}},"type":"Feature"},
	{"geometry":{"coordinates":[-4.046462,50.36212],"type":"Point"},"properties":{"osm_id":"6742114206","tag":{"amenity":"waste_basket"}},"type":"Feature"},
	{"geometry":{"coordinates":[-4.085745,50.366179],"type":"Point"},"properties":{"osm_id":"6925465724","tag":{"amenity":"waste_basket","waste":"trash;dog_excrement"}},"type":"Feature"},
	{"geometry":{"coordinates":[-4.099038,50.393376],"type":"Point"},"properties":{"osm_id":"8857988477","tag":{"amenity":"waste_basket","waste":"trash;dog_excrement"}},"type":"Feature"},
	{"geometry":{"coordinates":[-4.127067,50.391996],"type":"Point"},"properties":{"osm_id":"9010501631","tag":{"amenity":"waste_basket"}},"type":"Feature"},
	{"geometry":{"coordinates":[-4.130283,50.392309],"type":"Point"},"properties":{"osm_id":"9010501636","tag":{"amenity":"waste_basket","waste":"trash;dog_excrement"}},"type":"Feature"},
	{"geometry":{"coordinates":[-4.128512,50.396245],"type":"Point"},"properties":{"osm_id":"9010501657","tag":{"amenity":"waste_basket"}},"type":"Feature"},
	{"geometry":{"coordinates":[-4.049236,50.383537],"type":"Point"},"properties":{"osm_id":"9036500345","tag":{"amenity":"waste_basket"}},"type":"Feature"},
	{"geometry":{"coordinates":[-4.048963,50.383795],"type":"Point"},"properties":{"osm_id":"9036500346","tag":{"amenity":"waste_basket"}},"type":"Feature"},
	{"geometry":{"coordinates":[-4.048192,50.384334],"type":"Point"},"properties":{"osm_id":"9036500362","tag":{"amenity":"waste_basket"}},"type":"Feature"}
]
}
