{
"type": "FeatureCollection",
"features": [
	{"geometry":{"coordinates":[32.019898,3.391668],"type":"Point"},"properties":{"name":"Waste disposal","osm_id":"5772350808","tag":{"addr:block":"Pagirnya 2 market","addr:district":"Adjumani","addr:settlement":"Pagrinya","amenity":"waste_disposal","fee":"yes","lit":"no","operator":"LWF","operator:type":"ngo","source:version":"Sanitation;v3.0.2","start_date":"2016-06-01","waste":"Food waste, shop waste etc"}},"type":"Feature"},
	{"geometry":{"coordinates":[32.001898,3.370215],"type":"Point"},"properties":{"name":"Waste disposal pit","osm_id":"5772350825","tag":{"addr:block":"Block A","addr:district":"Adjumani","addr:settlement":"Pagrinya","amenity":"waste_disposal","fee":"no","lit":"no","operator":"LWF","operator:type":"ngo","source:version":"Sanitation;v3.0.2","start_date":"2017-04-01"}},"type":"Feature"}
]
}
