{
"type": "FeatureCollection",
"features": [
	{"geometry":{"coordinates":[-3.608061,57.319454],"type":"Point"},"properties":{"name":"Grantown Recycling Centre","osm_id":"9151220045","tag":{"amenity":"recycling","owner":"Highland Council","ownership":"municipal","recycling_type":"centre","wikidata":"Q106085777"}},"type":"Feature"}
]
}
