{
"type": "FeatureCollection",
"lastupdate": "2020-08-03T00:00:00Z",
"features": [
	{"geometry":{"coordinates":[0.954849,52.044679],"type":"Point"},"properties":{"name":"Magdalen Road car park","osm_id":"2159583727","tag":{"amenity":"recycling","recycling:cans":"yes","recycling:cartons":"yes","recycling:clothes":"yes","recycling:glass_bottles":"yes","recycling:magazines":"yes","recycling:newspaper":"yes","recycling:paper":"yes","recycling:small_appliances":"no","recycling:waste":"no","recycling:wood":"no","recycling_type":"centre"}},"type":"Feature"},
	{"geometry":{"coordinates":[0.954142,52.043774],"type":"Point"},"properties":{"osm_id":"7061452747","tag":{"amenity":"waste_basket"}},"type":"Feature"},
	{"geometry":{"coordinates":[0.955663,52.041151],"type":"Point"},"properties":{"osm_id":"7061764084","tag":{"amenity":"waste_basket"}},"type":"Feature"}
]
}
