{
"type": "FeatureCollection",
"features": [
	{"geometry":{"coordinates":[5.428785,48.659474],"type":"Point"},"properties":{"name":"Arbre mort","osm_id":"2455144270","tag":{"natural":"tree"}},"type":"Feature"}
]
}
