{
"type": "FeatureCollection",
"features": [
	{"geometry":{"coordinates":[152.789248,-26.944133],"type":"Point"},"properties":{"name":"Woodford Tip","osm_id":"3008680481","tag":{"amenity":"recycling"}},"type":"Feature"}
]
}
