{
"type": "FeatureCollection",
"features": [
	{"geometry":{"coordinates":[-72.070222,19.343012],"type":"Point"},"properties":{"name":"manguier","osm_id":"1229710767","tag":{"name:botanical":"manguier","natural":"tree"}},"type":"Feature"},
	{"geometry":{"coordinates":[-72.05887,19.366651],"type":"Point"},"properties":{"osm_id":"2635371933","tag":{"natural":"tree"}},"type":"Feature"},
	{"geometry":{"coordinates":[-72.020869,19.337377],"type":"Point"},"properties":{"osm_id":"2644242973","tag":{"natural":"tree"}},"type":"Feature"},
	{"geometry":{"coordinates":[-72.059035,19.366409],"type":"Point"},"properties":{"osm_id":"2657930093","tag":{"natural":"tree"}},"type":"Feature"}
]
}
