{
"type": "FeatureCollection",
"features": [
	{"geometry":{"coordinates":[-72.070222,19.343011],"type":"Point"},"properties":{"name":"manguier","osm_id":"1229710767","tag":{"name:botanical":"manguier","natural":"tree"}},"type":"Feature"},
	{"geometry":{"coordinates":[-72.05887,19.36665],"type":"Point"},"properties":{"osm_id":"2635371933","tag":{"natural":"tree"}},"type":"Feature"},
	{"geometry":{"coordinates":[-72.020869,19.337376],"type":"Point"},"properties":{"osm_id":"2644242973","tag":{"natural":"tree"}},"type":"Feature"},
	{"geometry":{"coordinates":[-72.059034,19.366408],"type":"Point"},"properties":{"osm_id":"2657930093","tag":{"natural":"tree"}},"type":"Feature"}
]
}
