{
"type": "FeatureCollection",
"features": [
	{"geometry":{"coordinates":[37.615291,-1.784605],"type":"Point"},"properties":{"name":"Makueni Dumping Site","osm_id":"5588163885","tag":{"amenity":"waste_disposal","image":"https://kc.humanitarianresponse.info/attachment/original?media_file=mapkibera/attachments/1524493225325.jpg","opening_hours":"24/7","type":"Dumpling site","village":"Malivani","wb_pb:id":"21643551","wheelchair":"limited"}},"type":"Feature"}
]
}
