{
"type": "FeatureCollection",
"features": [
	{"geometry":{"coordinates":[-95.970296,19.043181],"type":"Point"},"properties":{"name":"PALMAS","osm_id":"2876634196","tag":{"height":"5","natural":"tree","type":"palm"}},"type":"Feature"},
	{"geometry":{"coordinates":[-95.970329,19.043425],"type":"Point"},"properties":{"name":"PALMAS","osm_id":"2876634197","tag":{"height":"5","natural":"tree","type":"palm"}},"type":"Feature"},
	{"geometry":{"coordinates":[-95.970341,19.043545],"type":"Point"},"properties":{"name":"PALMAS","osm_id":"2876634198","tag":{"height":"5","natural":"tree","type":"palm"}},"type":"Feature"},
	{"geometry":{"coordinates":[-95.970395,19.044066],"type":"Point"},"properties":{"name":"PALMAS","osm_id":"2876634199","tag":{"height":"5","natural":"tree","type":"palm"}},"type":"Feature"},
	{"geometry":{"coordinates":[-95.97041,19.044203],"type":"Point"},"properties":{"name":"PALMAS","osm_id":"2876634200","tag":{"height":"5","natural":"tree","type":"palm"}},"type":"Feature"},
	{"geometry":{"coordinates":[-95.970418,19.044287],"type":"Point"},"properties":{"name":"PALMAS","osm_id":"2876637301","tag":{"height":"5","natural":"tree","type":"palm"}},"type":"Feature"},
	{"geometry":{"coordinates":[-95.970441,19.044501],"type":"Point"},"properties":{"name":"PALMAS","osm_id":"2876637302","tag":{"height":"5","natural":"tree","type":"palm"}},"type":"Feature"},
	{"geometry":{"coordinates":[-95.97047,19.044785],"type":"Point"},"properties":{"name":"PALMAS","osm_id":"2876637303","tag":{"height":"5","natural":"tree","type":"palm"}},"type":"Feature"}
]
}
