{
"type": "FeatureCollection",
"features": [
	{"geometry":{"coordinates":[-49.14881,-14.311944],"type":"Point"},"properties":{"name":"Reciplam","osm_id":"4610770393","tag":{"amenity":"recycling","name:pt":"Reciplam"}},"type":"Feature"}
]
}
