{
"type": "FeatureCollection",
"lastupdate": "2020-08-04T00:00:00Z",
"features": [
	{"geometry":{"coordinates":[-49.148809,-14.311943],"type":"Point"},"properties":{"name":"Reciplam","osm_id":"4610770393","tag":{"amenity":"recycling","name:pt":"Reciplam"}},"type":"Feature"}
]
}
