{
"type": "FeatureCollection",
"features": [
	{"geometry":{"coordinates":[18.0862,53.75255],"type":"Point"},"properties":{"osm_id":"4706667156","tag":{"denotation":"natural_monument","natural":"tree","ref:CRFOP":"PL.ZIPOP.1393.PP.0416052.1920","ref:INSPIRE":"PL.ZIPOP.1393.PP.0416052.1920","website":"http://crfop.gdos.gov.pl/CRFOP/widok/viewfop.jsf?fop=PL.ZIPOP.1393.PP.0416052.1920"}},"type":"Feature"}
]
}
