{
"type": "FeatureCollection",
"features": [
	{"geometry":{"coordinates":[18.102702,53.279944],"type":"Point"},"properties":{"osm_id":"4706693062","tag":{"denotation":"natural_monument","natural":"tree","ref:CRFOP":"PL.ZIPOP.1393.PP.0403032.533","ref:INSPIRE":"PL.ZIPOP.1393.PP.0403032.533","website":"http://crfop.gdos.gov.pl/CRFOP/widok/viewfop.jsf?fop=PL.ZIPOP.1393.PP.0403032.533"}},"type":"Feature"},
	{"geometry":{"coordinates":[18.102472,53.279946],"type":"Point"},"properties":{"osm_id":"4706693063","tag":{"denotation":"natural_monument","natural":"tree","ref:CRFOP":"PL.ZIPOP.1393.PP.0403032.533","ref:INSPIRE":"PL.ZIPOP.1393.PP.0403032.533","website":"http://crfop.gdos.gov.pl/CRFOP/widok/viewfop.jsf?fop=PL.ZIPOP.1393.PP.0403032.533"}},"type":"Feature"},
	{"geometry":{"coordinates":[18.060406,53.292912],"type":"Point"},"properties":{"osm_id":"4706693071","tag":{"denotation":"natural_monument","natural":"tree","ref:CRFOP":"PL.ZIPOP.1393.PP.0403032.530","ref:INSPIRE":"PL.ZIPOP.1393.PP.0403032.530","website":"http://crfop.gdos.gov.pl/CRFOP/widok/viewfop.jsf?fop=PL.ZIPOP.1393.PP.0403032.530"}},"type":"Feature"},
	{"geometry":{"coordinates":[18.099427,53.308048],"type":"Point"},"properties":{"osm_id":"4706693706","tag":{"denotation":"natural_monument","natural":"tree","ref:CRFOP":"PL.ZIPOP.1393.PP.0403032.522","ref:INSPIRE":"PL.ZIPOP.1393.PP.0403032.522","start_date":"1991-08-14","website":"http://crfop.gdos.gov.pl/CRFOP/widok/viewfop.jsf?fop=PL.ZIPOP.1393.PP.0403032.522"}},"type":"Feature"},
	{"geometry":{"coordinates":[18.103972,53.319821],"type":"Point"},"properties":{"name":"Bastian","osm_id":"4706694239","tag":{"denotation":"natural_monument","natural":"tree","ref:CRFOP":"PL.ZIPOP.1393.PP.0403032.503","ref:INSPIRE":"PL.ZIPOP.1393.PP.0403032.503","start_date":"2005-01-01","website":"http://crfop.gdos.gov.pl/CRFOP/widok/viewfop.jsf?fop=PL.ZIPOP.1393.PP.0403032.503"}},"type":"Feature"}
]
}
