{
"type": "FeatureCollection",
"features": [
	{"geometry":{"coordinates":[18.038633,52.999382],"type":"Point"},"properties":{"osm_id":"4706692543","tag":{"denotation":"natural_monument","natural":"tree","ref:CRFOP":"PL.ZIPOP.1393.PP.0403052.1246","ref:INSPIRE":"PL.ZIPOP.1393.PP.0403052.1246","website":"http://crfop.gdos.gov.pl/CRFOP/widok/viewfop.jsf?fop=PL.ZIPOP.1393.PP.0403052.1246"}},"type":"Feature"},
	{"geometry":{"coordinates":[18.038687,52.998721],"type":"Point"},"properties":{"osm_id":"4706692544","tag":{"denotation":"natural_monument","natural":"tree","ref:CRFOP":"PL.ZIPOP.1393.PP.0403052.1246","ref:INSPIRE":"PL.ZIPOP.1393.PP.0403052.1246","website":"http://crfop.gdos.gov.pl/CRFOP/widok/viewfop.jsf?fop=PL.ZIPOP.1393.PP.0403052.1246"}},"type":"Feature"}
]
}
