{
"type": "FeatureCollection",
"features": [
	{"geometry":{"coordinates":[18.10544,52.879288],"type":"Point"},"properties":{"osm_id":"4706681736","tag":{"denotation":"natural_monument","natural":"tree","ref:CRFOP":"PL.ZIPOP.1393.PP.0407092.2266","ref:INSPIRE":"PL.ZIPOP.1393.PP.0407092.2266","website":"http://crfop.gdos.gov.pl/CRFOP/widok/viewfop.jsf?fop=PL.ZIPOP.1393.PP.0407092.2266"}},"type":"Feature"},
	{"geometry":{"coordinates":[18.104727,52.880054],"type":"Point"},"properties":{"osm_id":"4706681737","tag":{"denotation":"natural_monument","natural":"tree","ref:CRFOP":"PL.ZIPOP.1393.PP.0407092.2266","ref:INSPIRE":"PL.ZIPOP.1393.PP.0407092.2266","website":"http://crfop.gdos.gov.pl/CRFOP/widok/viewfop.jsf?fop=PL.ZIPOP.1393.PP.0407092.2266"}},"type":"Feature"},
	{"geometry":{"coordinates":[18.104864,52.880126],"type":"Point"},"properties":{"osm_id":"4706681738","tag":{"denotation":"natural_monument","natural":"tree","ref:CRFOP":"PL.ZIPOP.1393.PP.0407092.2266","ref:INSPIRE":"PL.ZIPOP.1393.PP.0407092.2266","website":"http://crfop.gdos.gov.pl/CRFOP/widok/viewfop.jsf?fop=PL.ZIPOP.1393.PP.0407092.2266"}},"type":"Feature"},
	{"geometry":{"coordinates":[18.105006,52.880203],"type":"Point"},"properties":{"osm_id":"4706681739","tag":{"denotation":"natural_monument","natural":"tree","ref:CRFOP":"PL.ZIPOP.1393.PP.0407092.2266","ref:INSPIRE":"PL.ZIPOP.1393.PP.0407092.2266","website":"http://crfop.gdos.gov.pl/CRFOP/widok/viewfop.jsf?fop=PL.ZIPOP.1393.PP.0407092.2266"}},"type":"Feature"},
	{"geometry":{"coordinates":[18.105135,52.880276],"type":"Point"},"properties":{"osm_id":"4706681740","tag":{"denotation":"natural_monument","natural":"tree","ref:CRFOP":"PL.ZIPOP.1393.PP.0407092.2266","ref:INSPIRE":"PL.ZIPOP.1393.PP.0407092.2266","website":"http://crfop.gdos.gov.pl/CRFOP/widok/viewfop.jsf?fop=PL.ZIPOP.1393.PP.0407092.2266"}},"type":"Feature"}
]
}
