{
"type": "FeatureCollection",
"features": [
	{"geometry":{"coordinates":[10.453243,51.86996],"type":"Point"},"properties":{"name":"Dicker Forstmeister","osm_id":"891534950","tag":{"alt_name":"Bergahorn","denotation":"natural_monument","leaf_cycle":"deciduous","monument":"yes","natural":"tree","old_name":"Grenzahorn"}},"type":"Feature"}
]
}
