{
"type": "FeatureCollection",
"features": [
	{"geometry":{"coordinates":[10.439708,50.762544],"type":"Point"},"properties":{"osm_id":"1764575740","tag":{"genus:de":"Birke","leaf_cycle":"deciduous","leaf_type":"broadleaved","name:botanical":"Betula","natural":"tree"}},"type":"Feature"},
	{"geometry":{"coordinates":[10.439759,50.762559],"type":"Point"},"properties":{"osm_id":"1764575742","tag":{"genus:de":"Birke","leaf_cycle":"deciduous","leaf_type":"broadleaved","name:botanical":"Betula","natural":"tree"}},"type":"Feature"},
	{"geometry":{"coordinates":[10.406038,50.785948],"type":"Point"},"properties":{"osm_id":"4685267499","tag":{"leaf_cycle":"deciduous","leaf_type":"broadleaved","natural":"tree"}},"type":"Feature"},
	{"geometry":{"coordinates":[10.406567,50.785995],"type":"Point"},"properties":{"osm_id":"4685267500","tag":{"leaf_cycle":"deciduous","leaf_type":"broadleaved","natural":"tree"}},"type":"Feature"},
	{"geometry":{"coordinates":[10.383961,50.767562],"type":"Point"},"properties":{"osm_id":"6596338136","tag":{"leaf_cycle":"deciduous","leaf_type":"broadleaved","natural":"tree"}},"type":"Feature"},
	{"geometry":{"coordinates":[10.38462,50.767275],"type":"Point"},"properties":{"osm_id":"6596338140","tag":{"leaf_cycle":"deciduous","leaf_type":"broadleaved","natural":"tree"}},"type":"Feature"}
]
}
