{
"type": "FeatureCollection",
"features": [
	{"geometry":{"coordinates":[10.453824,44.564409],"type":"Point"},"properties":{"name":"Cerro secolare","osm_id":"6262067088","tag":{"leaf_type":"broadleaved","natural":"tree"}},"type":"Feature"}
]
}
