{
"type": "FeatureCollection",
"features": [
	{"geometry":{"coordinates":[10.429855,24.127807],"type":"Point"},"properties":{"name":"Acacia","osm_id":"9020064059","tag":{"natural":"tree"}},"type":"Feature"},
	{"geometry":{"coordinates":[10.429654,24.127221],"type":"Point"},"properties":{"name":"Acacia","osm_id":"9020064060","tag":{"natural":"tree"}},"type":"Feature"}
]
}
