{
"type": "FeatureCollection",
"features": [
	{"geometry":{"coordinates":[7.021078,49.778001],"type":"Point"},"properties":{"name":"Alte Eiche in Etgert","osm_id":"1610577502","tag":{"monument":"yes","natural":"tree","type":"Eiche"}},"type":"Feature"},
	{"geometry":{"coordinates":[6.984043,49.726143],"type":"Point"},"properties":{"osm_id":"4799490405","tag":{"leaf_type":"broadleaved","natural":"tree"}},"type":"Feature"},
	{"geometry":{"coordinates":[6.983603,49.72603],"type":"Point"},"properties":{"osm_id":"4799490406","tag":{"leaf_type":"broadleaved","natural":"tree"}},"type":"Feature"},
	{"geometry":{"coordinates":[7.020354,49.76528],"type":"Point"},"properties":{"osm_id":"6815725551","tag":{"natural":"tree"}},"type":"Feature"}
]
}
