{
"type": "FeatureCollection",
"features": [
	{"geometry":{"coordinates":[7.012108,49.511637],"type":"Point"},"properties":{"name":"Napoleon-Eiche","osm_id":"3927604282","tag":{"leaf_cycle":"deciduous","leaf_type":"broadleaved","natural":"tree"}},"type":"Feature"},
	{"geometry":{"coordinates":[6.977203,49.537828],"type":"Point"},"properties":{"osm_id":"5104172299","tag":{"natural":"tree"}},"type":"Feature"},
	{"geometry":{"coordinates":[6.972426,49.533136],"type":"Point"},"properties":{"osm_id":"5109541159","tag":{"natural":"tree"}},"type":"Feature"},
	{"geometry":{"coordinates":[6.972179,49.533406],"type":"Point"},"properties":{"osm_id":"5109541160","tag":{"natural":"tree"}},"type":"Feature"},
	{"geometry":{"coordinates":[6.972107,49.533517],"type":"Point"},"properties":{"osm_id":"5109541161","tag":{"natural":"tree"}},"type":"Feature"},
	{"geometry":{"coordinates":[6.971959,49.533744],"type":"Point"},"properties":{"osm_id":"5109541162","tag":{"natural":"tree"}},"type":"Feature"},
	{"geometry":{"coordinates":[6.971884,49.533885],"type":"Point"},"properties":{"osm_id":"5109541163","tag":{"natural":"tree"}},"type":"Feature"}
]
}
