{
"type": "FeatureCollection",
"features": [
	{"geometry":{"coordinates":[-3.509481,56.496432],"type":"Point"},"properties":{"name":"Bankfoot recycling centre","osm_id":"9148482158","tag":{"amenity":"recycling","owner":"Perth & Kinross Council","ownership":"municipal","recycling_type":"centre","wikidata":"Q106085855"}},"type":"Feature"}
]
}
