{
"type": "FeatureCollection",
"features": [
	{"geometry":{"coordinates":[-87.782797,41.569176],"type":"Point"},"properties":{"osm_id":"4444769214","tag":{"denotation":"urban","description":"Peach Tree","leaf_cycle":"deciduous","leaf_type":"broadleaved","natural":"tree"}},"type":"Feature"},
	{"geometry":{"coordinates":[-87.782797,41.569176],"type":"Point"},"properties":{"name":"Peach Tree","osm_id":"4444769215","tag":{"denotation":"urban","leaf_cycle":"deciduous","leaf_type":"broadleaved","natural":"tree"}},"type":"Feature"},
	{"geometry":{"coordinates":[-87.782578,41.56921],"type":"Point"},"properties":{"osm_id":"4444769220","tag":{"denotation":"urban","genus":"quercus","leaf_cycle":"deciduous","leaf_type":"broadleaved","natural":"tree"}},"type":"Feature"}
]
}
