{
"type": "FeatureCollection",
"features": [
	{"geometry":{"coordinates":[3.128574,51.084047],"type":"Point"},"properties":{"name":"Glascontainer","osm_id":"897508999","tag":{"amenity":"recycling"}},"type":"Feature"},
	{"geometry":{"coordinates":[3.097033,51.085513],"type":"Point"},"properties":{"osm_id":"3880783916","tag":{"amenity":"recycling","operator":"Wereld Missie Hulp","recycling:clothes":"yes","recycling_type":"container"}},"type":"Feature"},
	{"geometry":{"coordinates":[3.097021,51.085525],"type":"Point"},"properties":{"osm_id":"3880783917","tag":{"amenity":"recycling","operator":"Wereld Missie Hulp","recycling:clothes":"yes","recycling_type":"container"}},"type":"Feature"},
	{"geometry":{"coordinates":[3.097008,51.085711],"type":"Point"},"properties":{"osm_id":"3880783943","tag":{"amenity":"waste_basket"}},"type":"Feature"},
	{"geometry":{"coordinates":[3.097838,51.086096],"type":"Point"},"properties":{"osm_id":"3880785870","tag":{"amenity":"recycling","recycling:glass_bottles":"yes","recycling_type":"container"}},"type":"Feature"},
	{"geometry":{"coordinates":[3.099492,51.085939],"type":"Point"},"properties":{"osm_id":"3880883694","tag":{"amenity":"recycling","operator":"Vlaams Inzamel Centrum Textiel","recycling:clothes":"yes","recycling_type":"container"}},"type":"Feature"},
	{"geometry":{"coordinates":[3.095921,51.086385],"type":"Point"},"properties":{"osm_id":"3880883717","tag":{"amenity":"waste_basket"}},"type":"Feature"},
	{"geometry":{"coordinates":[3.095766,51.086449],"type":"Point"},"properties":{"osm_id":"3880883722","tag":{"amenity":"waste_basket"}},"type":"Feature"},
	{"geometry":{"coordinates":[3.107612,51.069429],"type":"Point"},"properties":{"osm_id":"4450927256","tag":{"amenity":"recycling","recycling:glass":"yes","recycling_type":"container"}},"type":"Feature"},
	{"geometry":{"coordinates":[3.148363,51.111004],"type":"Point"},"properties":{"osm_id":"6831063927","tag":{"amenity":"recycling","recycling:glass_bottles":"yes","recycling_type":"container"}},"type":"Feature"},
	{"geometry":{"coordinates":[3.155178,51.109813],"type":"Point"},"properties":{"osm_id":"7367337288","tag":{"amenity":"recycling","recycling:glass_bottles":"yes","recycling_type":"container"}},"type":"Feature"},
	{"geometry":{"coordinates":[3.160632,51.105305],"type":"Point"},"properties":{"osm_id":"7367337289","tag":{"amenity":"recycling","recycling:glass_bottles":"yes","recycling_type":"container"}},"type":"Feature"},
	{"geometry":{"coordinates":[3.158518,51.102612],"type":"Point"},"properties":{"osm_id":"7367337290","tag":{"amenity":"recycling","recycling:glass_bottles":"yes","recycling_type":"container"}},"type":"Feature"},
	{"geometry":{"coordinates":[3.157761,51.099985],"type":"Point"},"properties":{"osm_id":"7367337291","tag":{"amenity":"recycling","recycling:glass_bottles":"yes","recycling_type":"container"}},"type":"Feature"},
	{"geometry":{"coordinates":[3.105071,51.098878],"type":"Point"},"properties":{"osm_id":"7367337293","tag":{"amenity":"recycling","recycling:glass_bottles":"yes","recycling_type":"container"}},"type":"Feature"},
	{"geometry":{"coordinates":[3.090057,51.113587],"type":"Point"},"properties":{"osm_id":"7367337294","tag":{"amenity":"recycling","recycling:glass_bottles":"yes","recycling_type":"container"}},"type":"Feature"},
	{"geometry":{"coordinates":[3.085854,51.115734],"type":"Point"},"properties":{"osm_id":"7367337295","tag":{"amenity":"recycling","recycling:glass_bottles":"yes","recycling_type":"container"}},"type":"Feature"}
]
}
