{
"type": "FeatureCollection",
"features": [
	{"geometry":{"coordinates":[3.128574,51.084048],"type":"Point"},"properties":{"name":"Glascontainer","osm_id":"897508999","tag":{"amenity":"recycling"}},"type":"Feature"},
	{"geometry":{"coordinates":[3.097033,51.085513],"type":"Point"},"properties":{"osm_id":"3880783916","tag":{"amenity":"recycling","operator":"Wereld Missie Hulp","recycling:clothes":"yes","recycling_type":"container"}},"type":"Feature"},
	{"geometry":{"coordinates":[3.097022,51.085525],"type":"Point"},"properties":{"osm_id":"3880783917","tag":{"amenity":"recycling","operator":"Wereld Missie Hulp","recycling:clothes":"yes","recycling_type":"container"}},"type":"Feature"},
	{"geometry":{"coordinates":[3.097008,51.085711],"type":"Point"},"properties":{"osm_id":"3880783943","tag":{"amenity":"waste_basket"}},"type":"Feature"},
	{"geometry":{"coordinates":[3.097839,51.086097],"type":"Point"},"properties":{"osm_id":"3880785870","tag":{"amenity":"recycling","recycling:glass_bottles":"yes","recycling_type":"container"}},"type":"Feature"},
	{"geometry":{"coordinates":[3.099492,51.085939],"type":"Point"},"properties":{"osm_id":"3880883694","tag":{"amenity":"recycling","operator":"Vlaams Inzamel Centrum Textiel","recycling:clothes":"yes","recycling_type":"container"}},"type":"Feature"},
	{"geometry":{"coordinates":[3.095922,51.086385],"type":"Point"},"properties":{"osm_id":"3880883717","tag":{"amenity":"waste_basket"}},"type":"Feature"},
	{"geometry":{"coordinates":[3.095767,51.086449],"type":"Point"},"properties":{"osm_id":"3880883722","tag":{"amenity":"waste_basket"}},"type":"Feature"},
	{"geometry":{"coordinates":[3.107612,51.06943],"type":"Point"},"properties":{"osm_id":"4450927256","tag":{"amenity":"recycling","recycling:glass":"yes","recycling_type":"container"}},"type":"Feature"},
	{"geometry":{"coordinates":[3.148364,51.111004],"type":"Point"},"properties":{"osm_id":"6831063927","tag":{"amenity":"recycling","recycling:glass_bottles":"yes","recycling_type":"container"}},"type":"Feature"},
	{"geometry":{"coordinates":[3.155179,51.109814],"type":"Point"},"properties":{"osm_id":"7367337288","tag":{"amenity":"recycling","recycling:glass_bottles":"yes","recycling_type":"container"}},"type":"Feature"},
	{"geometry":{"coordinates":[3.160632,51.105305],"type":"Point"},"properties":{"osm_id":"7367337289","tag":{"amenity":"recycling","recycling:glass_bottles":"yes","recycling_type":"container"}},"type":"Feature"},
	{"geometry":{"coordinates":[3.158518,51.102612],"type":"Point"},"properties":{"osm_id":"7367337290","tag":{"amenity":"recycling","recycling:glass_bottles":"yes","recycling_type":"container"}},"type":"Feature"},
	{"geometry":{"coordinates":[3.157761,51.099985],"type":"Point"},"properties":{"osm_id":"7367337291","tag":{"amenity":"recycling","recycling:glass_bottles":"yes","recycling_type":"container"}},"type":"Feature"},
	{"geometry":{"coordinates":[3.105072,51.098878],"type":"Point"},"properties":{"osm_id":"7367337293","tag":{"amenity":"recycling","recycling:glass_bottles":"yes","recycling_type":"container"}},"type":"Feature"},
	{"geometry":{"coordinates":[3.090058,51.113588],"type":"Point"},"properties":{"osm_id":"7367337294","tag":{"amenity":"recycling","recycling:glass_bottles":"yes","recycling_type":"container"}},"type":"Feature"},
	{"geometry":{"coordinates":[3.085855,51.115735],"type":"Point"},"properties":{"osm_id":"7367337295","tag":{"amenity":"recycling","recycling:glass_bottles":"yes","recycling_type":"container"}},"type":"Feature"}
]
}
