{
"type": "FeatureCollection",
"features": [
	{"geometry":{"coordinates":[3.088799,45.660217],"type":"Point"},"properties":{"osm_id":"2302489514","tag":{"amenity":"recycling"}},"type":"Feature"},
	{"geometry":{"coordinates":[3.088754,45.660181],"type":"Point"},"properties":{"osm_id":"2320551064","tag":{"amenity":"waste_basket"}},"type":"Feature"},
	{"geometry":{"coordinates":[3.125358,45.669875],"type":"Point"},"properties":{"osm_id":"3302349622","tag":{"addr:city":"Tallende","addr:postcode":"63450","addr:street":"Rue Pierre Bohat-Combas","amenity":"recycling","recycling:glass":"yes"}},"type":"Feature"},
	{"geometry":{"coordinates":[3.108761,45.669341],"type":"Point"},"properties":{"osm_id":"3306828157","tag":{"amenity":"waste_basket"}},"type":"Feature"},
	{"geometry":{"coordinates":[3.109535,45.667665],"type":"Point"},"properties":{"osm_id":"3756321442","tag":{"amenity":"recycling","recycling:glass":"yes","recycling_type":"underground"}},"type":"Feature"},
	{"geometry":{"coordinates":[3.126809,45.672506],"type":"Point"},"properties":{"osm_id":"4199893895","tag":{"amenity":"recycling","recycling_type":"container"}},"type":"Feature"}
]
}
