{
"type": "FeatureCollection",
"features": [
	{"geometry":{"coordinates":[5.60792,44.937988],"type":"Point"},"properties":{"osm_id":"4966989735","tag":{"amenity":"recycling","recycling:cardboard":"yes","recycling:glass":"no","recycling:glass_bottles":"yes","recycling:paper":"yes","recycling:plastic_packaging":"yes","recycling_type":"container"}},"type":"Feature"},
	{"geometry":{"coordinates":[5.606314,44.944499],"type":"Point"},"properties":{"osm_id":"5054782669","tag":{"amenity":"recycling","recycling:cans":"yes","recycling:cardboard":"yes","recycling:glass":"no","recycling:glass_bottles":"yes","recycling:paper":"yes","recycling:plastic_bottles":"yes","recycling:plastic_packaging":"yes","recycling:waste":"yes","recycling_type":"container"}},"type":"Feature"},
	{"geometry":{"coordinates":[5.608377,44.937898],"type":"Point"},"properties":{"osm_id":"5179150215","tag":{"amenity":"waste_basket"}},"type":"Feature"},
	{"geometry":{"coordinates":[5.589761,44.955046],"type":"Point"},"properties":{"osm_id":"5600455928","tag":{"amenity":"waste_disposal","waste":"organic"}},"type":"Feature"},
	{"geometry":{"coordinates":[5.623328,44.931016],"type":"Point"},"properties":{"osm_id":"6573356015","tag":{"amenity":"recycling","location":"underground","recycling_type":"container"}},"type":"Feature"},
	{"geometry":{"coordinates":[5.623341,44.931032],"type":"Point"},"properties":{"osm_id":"6573356016","tag":{"amenity":"recycling","location":"underground","recycling_type":"container"}},"type":"Feature"},
	{"geometry":{"coordinates":[5.623368,44.931021],"type":"Point"},"properties":{"osm_id":"6573356017","tag":{"amenity":"recycling"}},"type":"Feature"},
	{"geometry":{"coordinates":[5.623357,44.931008],"type":"Point"},"properties":{"osm_id":"6573356018","tag":{"amenity":"waste_disposal"}},"type":"Feature"},
	{"geometry":{"coordinates":[5.621326,44.912648],"type":"Point"},"properties":{"osm_id":"8931153356","tag":{"amenity":"waste_disposal"}},"type":"Feature"}
]
}
