{
"type": "FeatureCollection",
"features": [
	{"geometry":{"coordinates":[5.582507,43.345353],"type":"Point"},"properties":{"osm_id":"1569393181","tag":{"amenity":"recycling","recycling:cans":"yes","recycling:clothes":"no","recycling:glass":"yes","recycling:paper":"yes"}},"type":"Feature"},
	{"geometry":{"coordinates":[5.602348,43.349118],"type":"Point"},"properties":{"osm_id":"1569459929","tag":{"amenity":"recycling"}},"type":"Feature"},
	{"geometry":{"coordinates":[5.583857,43.379441],"type":"Point"},"properties":{"osm_id":"2199306721","tag":{"amenity":"recycling","recycling:cans":"yes","recycling:glass":"yes","recycling:paper":"yes","recycling_type":"container"}},"type":"Feature"},
	{"geometry":{"coordinates":[5.599851,43.380047],"type":"Point"},"properties":{"osm_id":"2199306740","tag":{"amenity":"recycling","recycling:cans":"yes","recycling:glass":"yes","recycling:paper":"yes","recycling_type":"container"}},"type":"Feature"},
	{"geometry":{"coordinates":[5.594976,43.332085],"type":"Point"},"properties":{"osm_id":"2201168508","tag":{"amenity":"recycling","recycling:cans":"yes","recycling:clothes":"no","recycling:glass":"yes","recycling:paper":"yes"}},"type":"Feature"},
	{"geometry":{"coordinates":[5.585018,43.33633],"type":"Point"},"properties":{"osm_id":"2202024589","tag":{"amenity":"recycling","recycling:cans":"yes","recycling:glass":"yes","recycling:paper":"yes"}},"type":"Feature"},
	{"geometry":{"coordinates":[5.601272,43.33977],"type":"Point"},"properties":{"osm_id":"2202024616","tag":{"amenity":"recycling","recycling:cans":"yes","recycling:clothes":"yes","recycling:glass":"yes","recycling:paper":"yes","recycling_type":"container"}},"type":"Feature"},
	{"geometry":{"coordinates":[5.575995,43.384929],"type":"Point"},"properties":{"osm_id":"2906571993","tag":{"amenity":"recycling","recycling:glass":"yes","recycling:paper":"yes"}},"type":"Feature"},
	{"geometry":{"coordinates":[5.559266,43.385625],"type":"Point"},"properties":{"osm_id":"2909860988","tag":{"amenity":"recycling","recycling:cans":"yes","recycling:clothes":"no","recycling:glass":"no","recycling:paper":"yes"}},"type":"Feature"},
	{"geometry":{"coordinates":[5.596825,43.326614],"type":"Point"},"properties":{"name":"Aqua Service 13","osm_id":"3745713425","tag":{"amenity":"recycling","contact:phone":"+33 4 42 04 49 29","opening_hours":"Tu-Sa 09:00-12:00, 14:00-18:00","website":"https://www.aquaservice13.com/"}},"type":"Feature"}
]
}
