{
"type": "FeatureCollection",
"features": [
	{"geometry":{"coordinates":[11.632285,51.091743],"type":"Point"},"properties":{"name":"Grenzlicht","osm_id":"718670905","tag":{"natural":"tree"}},"type":"Feature"},
	{"geometry":{"coordinates":[11.672526,51.104775],"type":"Point"},"properties":{"osm_id":"1616676037","tag":{"natural":"tree"}},"type":"Feature"},
	{"geometry":{"coordinates":[11.648513,51.108716],"type":"Point"},"properties":{"osm_id":"2205703326","tag":{"image":"http://i.imgur.com/yDn4qVml.jpg","natural":"tree"}},"type":"Feature"},
	{"geometry":{"coordinates":[11.655588,51.106458],"type":"Point"},"properties":{"osm_id":"5873510873","tag":{"denotation":"avenue","leaf_cycle":"semi_deciduous","leaf_type":"broadleaved","natural":"tree"}},"type":"Feature"},
	{"geometry":{"coordinates":[11.655453,51.106438],"type":"Point"},"properties":{"osm_id":"5873510874","tag":{"denotation":"avenue","leaf_cycle":"semi_deciduous","leaf_type":"broadleaved","natural":"tree"}},"type":"Feature"},
	{"geometry":{"coordinates":[11.655378,51.106425],"type":"Point"},"properties":{"osm_id":"5873510875","tag":{"denotation":"avenue","leaf_cycle":"semi_deciduous","leaf_type":"broadleaved","natural":"tree"}},"type":"Feature"},
	{"geometry":{"coordinates":[11.655318,51.106404],"type":"Point"},"properties":{"osm_id":"5873510876","tag":{"denotation":"avenue","leaf_cycle":"semi_deciduous","leaf_type":"broadleaved","natural":"tree"}},"type":"Feature"}
]
}
