{
"type": "FeatureCollection",
"features": [
	{"geometry":{"coordinates":[11.620994,50.472082],"type":"Point"},"properties":{"osm_id":"2320447901","tag":{"height":"25","natural":"tree","type":"Eiche"}},"type":"Feature"},
	{"geometry":{"coordinates":[11.622443,50.4721],"type":"Point"},"properties":{"osm_id":"2320447907","tag":{"natural":"tree"}},"type":"Feature"},
	{"geometry":{"coordinates":[11.62186,50.471662],"type":"Point"},"properties":{"name":"Linde","osm_id":"2324603497","tag":{"height":"15","natural":"tree"}},"type":"Feature"},
	{"geometry":{"coordinates":[11.6656,50.485272],"type":"Point"},"properties":{"osm_id":"2404120293","tag":{"natural":"tree"}},"type":"Feature"}
]
}
