{
"type": "FeatureCollection",
"features": [
	{"geometry":{"coordinates":[11.689055,46.775114],"type":"Point"},"properties":{"osm_id":"1924186213","tag":{"natural":"tree"}},"type":"Feature"},
	{"geometry":{"coordinates":[11.686434,46.772028],"type":"Point"},"properties":{"osm_id":"1925843219","tag":{"natural":"tree"}},"type":"Feature"},
	{"geometry":{"coordinates":[11.686524,46.772122],"type":"Point"},"properties":{"osm_id":"1925843220","tag":{"natural":"tree"}},"type":"Feature"},
	{"geometry":{"coordinates":[11.686632,46.772215],"type":"Point"},"properties":{"osm_id":"1925843221","tag":{"natural":"tree"}},"type":"Feature"},
	{"geometry":{"coordinates":[11.686621,46.77229],"type":"Point"},"properties":{"osm_id":"1925843222","tag":{"natural":"tree"}},"type":"Feature"},
	{"geometry":{"coordinates":[11.686708,46.772451],"type":"Point"},"properties":{"osm_id":"1925843224","tag":{"natural":"tree"}},"type":"Feature"},
	{"geometry":{"coordinates":[11.686602,46.772453],"type":"Point"},"properties":{"osm_id":"1925843225","tag":{"natural":"tree"}},"type":"Feature"},
	{"geometry":{"coordinates":[11.686725,46.772567],"type":"Point"},"properties":{"osm_id":"1925843226","tag":{"natural":"tree"}},"type":"Feature"},
	{"geometry":{"coordinates":[11.686607,46.772629],"type":"Point"},"properties":{"osm_id":"1925843227","tag":{"natural":"tree"}},"type":"Feature"},
	{"geometry":{"coordinates":[11.686747,46.772697],"type":"Point"},"properties":{"osm_id":"1925843228","tag":{"natural":"tree"}},"type":"Feature"},
	{"geometry":{"coordinates":[11.686683,46.772797],"type":"Point"},"properties":{"osm_id":"1925843230","tag":{"natural":"tree"}},"type":"Feature"},
	{"geometry":{"coordinates":[11.641579,46.776205],"type":"Point"},"properties":{"name":"Naturdenkmal Dorflinde","osm_id":"2518740216","tag":{"denotation":"natural_monument","height":"22","name:botanical":"Tilia cordata","natural":"tree","protected":"yes"}},"type":"Feature"},
	{"geometry":{"coordinates":[11.634293,46.746875],"type":"Point"},"properties":{"osm_id":"3049064946","tag":{"natural":"tree"}},"type":"Feature"},
	{"geometry":{"coordinates":[11.646472,46.772464],"type":"Point"},"properties":{"osm_id":"4354447346","tag":{"leaf_cycle":"deciduous","leaf_type":"broadleaved","natural":"tree"}},"type":"Feature"},
	{"geometry":{"coordinates":[11.646365,46.772509],"type":"Point"},"properties":{"osm_id":"4354447349","tag":{"leaf_cycle":"deciduous","leaf_type":"broadleaved","natural":"tree"}},"type":"Feature"},
	{"geometry":{"coordinates":[11.646203,46.772556],"type":"Point"},"properties":{"osm_id":"4354447350","tag":{"leaf_cycle":"deciduous","leaf_type":"broadleaved","natural":"tree"}},"type":"Feature"},
	{"geometry":{"coordinates":[11.634255,46.746902],"type":"Point"},"properties":{"osm_id":"5280031355","tag":{"leaf_cycle":"deciduous","leaf_type":"broadleaved","natural":"tree"}},"type":"Feature"},
	{"geometry":{"coordinates":[11.63644,46.760866],"type":"Point"},"properties":{"osm_id":"5280710053","tag":{"leaf_cycle":"deciduous","leaf_type":"broadleaved","natural":"tree"}},"type":"Feature"},
	{"geometry":{"coordinates":[11.655904,46.769592],"type":"Point"},"properties":{"osm_id":"5283768155","tag":{"leaf_cycle":"deciduous","leaf_type":"broadleaved","natural":"tree"}},"type":"Feature"},
	{"geometry":{"coordinates":[11.659188,46.749381],"type":"Point"},"properties":{"osm_id":"6050930767","tag":{"natural":"tree"}},"type":"Feature"}
]
}
