{
"type": "FeatureCollection",
"features": [
	{"geometry":{"coordinates":[11.689056,46.775115],"type":"Point"},"properties":{"osm_id":"1924186213","tag":{"natural":"tree"}},"type":"Feature"},
	{"geometry":{"coordinates":[11.686435,46.772029],"type":"Point"},"properties":{"osm_id":"1925843219","tag":{"natural":"tree"}},"type":"Feature"},
	{"geometry":{"coordinates":[11.686524,46.772122],"type":"Point"},"properties":{"osm_id":"1925843220","tag":{"natural":"tree"}},"type":"Feature"},
	{"geometry":{"coordinates":[11.686633,46.772216],"type":"Point"},"properties":{"osm_id":"1925843221","tag":{"natural":"tree"}},"type":"Feature"},
	{"geometry":{"coordinates":[11.686622,46.772291],"type":"Point"},"properties":{"osm_id":"1925843222","tag":{"natural":"tree"}},"type":"Feature"},
	{"geometry":{"coordinates":[11.686708,46.772451],"type":"Point"},"properties":{"osm_id":"1925843224","tag":{"natural":"tree"}},"type":"Feature"},
	{"geometry":{"coordinates":[11.686602,46.772453],"type":"Point"},"properties":{"osm_id":"1925843225","tag":{"natural":"tree"}},"type":"Feature"},
	{"geometry":{"coordinates":[11.686725,46.772568],"type":"Point"},"properties":{"osm_id":"1925843226","tag":{"natural":"tree"}},"type":"Feature"},
	{"geometry":{"coordinates":[11.686608,46.772629],"type":"Point"},"properties":{"osm_id":"1925843227","tag":{"natural":"tree"}},"type":"Feature"},
	{"geometry":{"coordinates":[11.686747,46.772698],"type":"Point"},"properties":{"osm_id":"1925843228","tag":{"natural":"tree"}},"type":"Feature"},
	{"geometry":{"coordinates":[11.686683,46.772797],"type":"Point"},"properties":{"osm_id":"1925843230","tag":{"natural":"tree"}},"type":"Feature"},
	{"geometry":{"coordinates":[11.64158,46.776206],"type":"Point"},"properties":{"name":"Naturdenkmal Dorflinde","osm_id":"2518740216","tag":{"denotation":"natural_monument","height":"22","name:botanical":"Tilia cordata","natural":"tree","protected":"yes"}},"type":"Feature"},
	{"geometry":{"coordinates":[11.634294,46.746876],"type":"Point"},"properties":{"osm_id":"3049064946","tag":{"natural":"tree"}},"type":"Feature"},
	{"geometry":{"coordinates":[11.646473,46.772464],"type":"Point"},"properties":{"osm_id":"4354447346","tag":{"leaf_cycle":"deciduous","leaf_type":"broadleaved","natural":"tree"}},"type":"Feature"},
	{"geometry":{"coordinates":[11.646365,46.77251],"type":"Point"},"properties":{"osm_id":"4354447349","tag":{"leaf_cycle":"deciduous","leaf_type":"broadleaved","natural":"tree"}},"type":"Feature"},
	{"geometry":{"coordinates":[11.646204,46.772557],"type":"Point"},"properties":{"osm_id":"4354447350","tag":{"leaf_cycle":"deciduous","leaf_type":"broadleaved","natural":"tree"}},"type":"Feature"},
	{"geometry":{"coordinates":[11.634256,46.746902],"type":"Point"},"properties":{"osm_id":"5280031355","tag":{"leaf_cycle":"deciduous","leaf_type":"broadleaved","natural":"tree"}},"type":"Feature"},
	{"geometry":{"coordinates":[11.636441,46.760866],"type":"Point"},"properties":{"osm_id":"5280710053","tag":{"leaf_cycle":"deciduous","leaf_type":"broadleaved","natural":"tree"}},"type":"Feature"},
	{"geometry":{"coordinates":[11.655904,46.769593],"type":"Point"},"properties":{"osm_id":"5283768155","tag":{"leaf_cycle":"deciduous","leaf_type":"broadleaved","natural":"tree"}},"type":"Feature"},
	{"geometry":{"coordinates":[11.659188,46.749382],"type":"Point"},"properties":{"osm_id":"6050930767","tag":{"natural":"tree"}},"type":"Feature"}
]
}
