{
"type": "FeatureCollection",
"features": [
	{"geometry":{"coordinates":[3.764703,51.143539],"type":"Point"},"properties":{"osm_id":"381145435","tag":{"amenity":"recycling","recycling:glass":"yes"}},"type":"Feature"},
	{"geometry":{"coordinates":[3.693835,51.153256],"type":"Point"},"properties":{"osm_id":"381382520","tag":{"amenity":"recycling","recycling:glass":"yes"}},"type":"Feature"},
	{"geometry":{"coordinates":[3.75767,51.140171],"type":"Point"},"properties":{"osm_id":"2289940351","tag":{"amenity":"waste_basket"}},"type":"Feature"},
	{"geometry":{"coordinates":[3.740524,51.141126],"type":"Point"},"properties":{"name":"Recyclagepark Evergem","osm_id":"3233312851","tag":{"addr:housenumber":"32","addr:street":"Jacques Paryslaan","amenity":"recycling"}},"type":"Feature"},
	{"geometry":{"coordinates":[3.753145,51.178805],"type":"Point"},"properties":{"osm_id":"4230714315","tag":{"amenity":"waste_basket"}},"type":"Feature"}
]
}
