{
"type": "FeatureCollection",
"features": [
	{"geometry":{"coordinates":[3.764703,51.143539],"type":"Point"},"properties":{"osm_id":"381145435","tag":{"amenity":"recycling","recycling:glass":"yes"}},"type":"Feature"},
	{"geometry":{"coordinates":[3.693873,51.153371],"type":"Point"},"properties":{"osm_id":"381382520","tag":{"amenity":"recycling","mapillary":"nzSgiWWWBuZZqV4L7b3GXm","opening_hours":"24/7","recycling:glass":"yes","recycling:glass_bottles":"yes","recycling_type":"container"}},"type":"Feature"},
	{"geometry":{"coordinates":[3.757669,51.140171],"type":"Point"},"properties":{"osm_id":"2289940351","tag":{"amenity":"waste_basket"}},"type":"Feature"},
	{"geometry":{"coordinates":[3.740523,51.141126],"type":"Point"},"properties":{"name":"Recyclagepark Evergem","osm_id":"3233312851","tag":{"addr:housenumber":"32","addr:street":"Jacques Paryslaan","amenity":"recycling","opening_hours":"Mo-We 13:00-17:00; Th, Fr 11:00-17:00; Sa 10:00-16:00","phone":"+3292536214","website":"evergem.be/recyclagepark"}},"type":"Feature"},
	{"geometry":{"coordinates":[3.753144,51.178804],"type":"Point"},"properties":{"osm_id":"4230714315","tag":{"amenity":"waste_basket"}},"type":"Feature"},
	{"geometry":{"coordinates":[3.734233,51.155326],"type":"Point"},"properties":{"osm_id":"8500040872","tag":{"amenity":"recycling","mapillary":"bs8JOQzzLn9RWnrxIKdCog","recycling:glass_bottles":"yes","recycling_type":"container"}},"type":"Feature"},
	{"geometry":{"coordinates":[3.734198,51.155343],"type":"Point"},"properties":{"osm_id":"8500048227","tag":{"amenity":"recycling","mapillary":"bs8JOQzzLn9RWnrxIKdCog","recycling:clothes":"yes","recycling_type":"container"}},"type":"Feature"}
]
}
