{
"type": "FeatureCollection",
"lastupdate": "2020-08-06T00:00:00Z",
"features": [
	{"geometry":{"coordinates":[3.764703,51.143539],"type":"Point"},"properties":{"osm_id":"381145435","tag":{"amenity":"recycling","recycling:glass":"yes"}},"type":"Feature"},
	{"geometry":{"coordinates":[3.693834,51.153255],"type":"Point"},"properties":{"osm_id":"381382520","tag":{"amenity":"recycling","recycling:glass":"yes"}},"type":"Feature"},
	{"geometry":{"coordinates":[3.757669,51.140171],"type":"Point"},"properties":{"osm_id":"2289940351","tag":{"amenity":"waste_basket"}},"type":"Feature"},
	{"geometry":{"coordinates":[3.740523,51.141126],"type":"Point"},"properties":{"name":"Recyclagepark Evergem","osm_id":"3233312851","tag":{"addr:housenumber":"32","addr:street":"Jacques Paryslaan","amenity":"recycling"}},"type":"Feature"},
	{"geometry":{"coordinates":[3.753144,51.178804],"type":"Point"},"properties":{"osm_id":"4230714315","tag":{"amenity":"waste_basket"}},"type":"Feature"}
]
}
