{
"type": "FeatureCollection",
"features": [
	{"geometry":{"coordinates":[16.749372,53.187674],"type":"Point"},"properties":{"name":"Pomnik przyrody","osm_id":"4855526250","tag":{"natural":"tree"}},"type":"Feature"}
]
}
