{
"type": "FeatureCollection",
"features": [
	{"geometry":{"coordinates":[16.776232,46.622555],"type":"Point"},"properties":{"name":"Jellegfa","osm_id":"3446767108","tag":{"natural":"tree","source:date":"2013-09-04","url":"http://turistautak.hu/poi.php?id=26550"}},"type":"Feature"}
]
}
