{
"type": "FeatureCollection",
"lastupdate": "2020-08-05T00:00:00Z",
"features": [
	{"geometry":{"coordinates":[4.653526,52.055095],"type":"Point"},"properties":{"osm_id":"539467191","tag":{"amenity":"recycling","location":"underground","recycling:clothes":"yes","recycling:glass_bottles":"yes","recycling:paper":"yes","recycling:shoes":"yes","recycling_type":"container"}},"type":"Feature"},
	{"geometry":{"coordinates":[4.657469,52.074021],"type":"Point"},"properties":{"osm_id":"1370111871","tag":{"amenity":"recycling","recycling_type":"container"}},"type":"Feature"},
	{"geometry":{"coordinates":[4.643913,52.06711],"type":"Point"},"properties":{"osm_id":"1503057584","tag":{"amenity":"recycling","recycling_type":"container"}},"type":"Feature"},
	{"geometry":{"coordinates":[4.625332,52.075398],"type":"Point"},"properties":{"osm_id":"4597061477","tag":{"amenity":"waste_basket"}},"type":"Feature"},
	{"geometry":{"coordinates":[4.656388,52.076349],"type":"Point"},"properties":{"osm_id":"4620625083","tag":{"amenity":"waste_basket"}},"type":"Feature"},
	{"geometry":{"coordinates":[4.655984,52.076304],"type":"Point"},"properties":{"osm_id":"4620625084","tag":{"amenity":"waste_basket"}},"type":"Feature"},
	{"geometry":{"coordinates":[4.64758,52.078549],"type":"Point"},"properties":{"osm_id":"4936176845","tag":{"amenity":"recycling","recycling_type":"container"}},"type":"Feature"},
	{"geometry":{"coordinates":[4.646165,52.054713],"type":"Point"},"properties":{"osm_id":"7008862445","tag":{"amenity":"recycling","recycling:clothes":"yes","recycling:shoes":"yes","recycling_type":"container"}},"type":"Feature"},
	{"geometry":{"coordinates":[4.646512,52.05518],"type":"Point"},"properties":{"osm_id":"7008862446","tag":{"amenity":"recycling","location":"underground","recycling:glass_bottles":"yes","recycling:paper":"yes","recycling_type":"container"}},"type":"Feature"},
	{"geometry":{"coordinates":[4.646047,52.056803],"type":"Point"},"properties":{"osm_id":"7540693470","tag":{"amenity":"waste_basket","waste":"trash"}},"type":"Feature"},
	{"geometry":{"coordinates":[4.652043,52.058278],"type":"Point"},"properties":{"osm_id":"7544457047","tag":{"amenity":"waste_basket","waste":"trash"}},"type":"Feature"},
	{"geometry":{"coordinates":[4.651535,52.057914],"type":"Point"},"properties":{"osm_id":"7544457048","tag":{"amenity":"waste_basket","waste":"trash;dog_excrement"}},"type":"Feature"}
]
}
