{
"type": "FeatureCollection",
"lastupdate": "2020-08-05T00:00:00Z",
"features": [
	{"geometry":{"coordinates":[4.641338,45.683682],"type":"Point"},"properties":{"osm_id":"2292355092","tag":{"amenity":"recycling","location":"overground","recycling:glass_bottles":"yes","recycling_type":"container"}},"type":"Feature"},
	{"geometry":{"coordinates":[4.648596,45.66635],"type":"Point"},"properties":{"osm_id":"3284221480","tag":{"amenity":"recycling","recycling:glass_bottles":"yes","recycling:paper":"yes","recycling_type":"container"}},"type":"Feature"},
	{"geometry":{"coordinates":[4.630765,45.66035],"type":"Point"},"properties":{"osm_id":"4031093186","tag":{"amenity":"recycling","recycling:glass":"yes"}},"type":"Feature"}
]
}
