{
"type": "FeatureCollection",
"features": [
	{"geometry":{"coordinates":[4.587096,44.108756],"type":"Point"},"properties":{"osm_id":"2152154795","tag":{"amenity":"recycling","recycling:paper":"yes","recycling_type":"container"}},"type":"Feature"},
	{"geometry":{"coordinates":[4.587046,44.108762],"type":"Point"},"properties":{"osm_id":"2152154802","tag":{"amenity":"recycling","recycling:glass":"yes","recycling_type":"container"}},"type":"Feature"},
	{"geometry":{"coordinates":[4.595103,44.08783],"type":"Point"},"properties":{"osm_id":"2262739379","tag":{"amenity":"recycling","recycling_type":"container"}},"type":"Feature"},
	{"geometry":{"coordinates":[4.610011,44.142502],"type":"Point"},"properties":{"osm_id":"7022175165","tag":{"amenity":"recycling","recycling:glass":"yes","recycling:glass_bottles":"yes","recycling:paper":"yes","recycling_type":"container"}},"type":"Feature"},
	{"geometry":{"coordinates":[4.614779,44.121722],"type":"Point"},"properties":{"osm_id":"9143910070","tag":{"amenity":"recycling","colour":"green","location":"overground","material":"plastic","recycling:glass_bottles":"yes","recycling_type":"container"}},"type":"Feature"},
	{"geometry":{"coordinates":[4.614784,44.121693],"type":"Point"},"properties":{"osm_id":"9143910071","tag":{"amenity":"recycling","location":"overground","material":"plastic","recycling:glass_bottles":"yes","recycling_type":"container"}},"type":"Feature"}
]
}
