{
"type": "FeatureCollection",
"features": [
	{"geometry":{"coordinates":[27.639757,38.224069],"type":"Point"},"properties":{"name":"Tarihi Kara Selvi","osm_id":"4921347313","tag":{"natural":"tree"}},"type":"Feature"}
]
}
