{
"type": "FeatureCollection",
"lastupdate": "2020-08-02T00:00:00Z",
"features": [
	{"geometry":{"coordinates":[-76.094268,43.072659],"type":"Point"},"properties":{"name":"Metalico Aluminum Recovery, Inc.","osm_id":"2047990392","tag":{"addr:city":"DeWitt","addr:country":"US","addr:housenumber":"6223","addr:postcode":"13206","addr:state":"NY","addr:street":"Thompson Road","amenity":"recycling","operator":"Metalico, Inc.","phone":"315 463 9500","recycling:aluminium":"yes","recycling:scrap_metal":"yes","recycling_type":"centre","website":"http://www.metalico.com/Aluminum/contact.html"}},"type":"Feature"},
	{"geometry":{"coordinates":[-76.101309,43.068992],"type":"Point"},"properties":{"osm_id":"3692614083","tag":{"amenity":"waste_basket"}},"type":"Feature"},
	{"geometry":{"coordinates":[-76.097699,43.069821],"type":"Point"},"properties":{"osm_id":"4249297710","tag":{"amenity":"waste_basket"}},"type":"Feature"}
]
}
