{
"type": "FeatureCollection",
"lastupdate": "2020-08-06T00:00:00Z",
"features": [
	{"geometry":{"coordinates":[-76.033527,40.11017],"type":"Point"},"properties":{"name":"Eagle Disposal","osm_id":"6982830037","tag":{"amenity":"recycling","recycling_type":"centre"}},"type":"Feature"}
]
}
