{
"type": "FeatureCollection",
"features": [
	{"geometry":{"coordinates":[23.660211,35.389363],"type":"Point"},"properties":{"name":"2,000-year-old Plane Tree","osm_id":"304621484","tag":{"monument":"yes","natural":"tree","tourism":"attraction"}},"type":"Feature"},
	{"geometry":{"coordinates":[23.657088,35.414249],"type":"Point"},"properties":{"name":"Plateau tree","osm_id":"1405380469","tag":{"natural":"tree"}},"type":"Feature"},
	{"geometry":{"coordinates":[23.696556,35.436273],"type":"Point"},"properties":{"name":"Spring Plantane","osm_id":"1410261097","tag":{"natural":"tree"}},"type":"Feature"},
	{"geometry":{"coordinates":[23.696579,35.436235],"type":"Point"},"properties":{"osm_id":"1411895035","tag":{"natural":"tree"}},"type":"Feature"},
	{"geometry":{"coordinates":[23.700311,35.410708],"type":"Point"},"properties":{"osm_id":"4408200286","tag":{"natural":"tree"}},"type":"Feature"},
	{"geometry":{"coordinates":[23.700193,35.410772],"type":"Point"},"properties":{"osm_id":"4408201989","tag":{"natural":"tree"}},"type":"Feature"},
	{"geometry":{"coordinates":[23.700212,35.4108],"type":"Point"},"properties":{"osm_id":"4408201990","tag":{"natural":"tree"}},"type":"Feature"}
]
}
