{
"type": "FeatureCollection",
"lastupdate": "2020-08-04T00:00:00Z",
"features": [
	{"geometry":{"coordinates":[-105.856865,37.46026],"type":"Point"},"properties":{"name":"Rickey Recycling Center","osm_id":"7098533009","tag":{"addr:city":"Alamosa","addr:housenumber":"1130","addr:postcode":"81101","addr:state":"CO","addr:street":"Old Airport Road","amenity":"recycling","operator":"City of Alamosa","operator:type":"public","recycling_type":"centre"}},"type":"Feature"}
]
}
