{
"type": "FeatureCollection",
"lastupdate": "2020-08-06T00:00:00Z",
"features": [
	{"geometry":{"coordinates":[15.87721,51.09785],"type":"Point"},"properties":{"name":"Skup makulatury","osm_id":"4375676749","tag":{"amenity":"recycling","recycling_type":"centre"}},"type":"Feature"}
]
}
