{
"type": "FeatureCollection",
"lastupdate": "2020-08-03T00:00:00Z",
"features": [
	{"geometry":{"coordinates":[14.273731,46.615238],"type":"Point"},"properties":{"osm_id":"1075035697","tag":{"amenity":"recycling","location":"overground","recycling:clothes":"yes","recycling:glass":"yes","recycling_type":"container"}},"type":"Feature"},
	{"geometry":{"coordinates":[14.28106,46.611618],"type":"Point"},"properties":{"osm_id":"1601020703","tag":{"amenity":"recycling","recycling:glass":"yes","recycling_type":"container"}},"type":"Feature"},
	{"geometry":{"coordinates":[14.271118,46.617779],"type":"Point"},"properties":{"osm_id":"1713289495","tag":{"amenity":"recycling","recycling:batteries":"no","recycling:clothes":"yes","recycling:glass":"yes","recycling_type":"container"}},"type":"Feature"},
	{"geometry":{"coordinates":[14.257833,46.617564],"type":"Point"},"properties":{"osm_id":"1832224241","tag":{"amenity":"recycling"}},"type":"Feature"},
	{"geometry":{"coordinates":[14.257363,46.618982],"type":"Point"},"properties":{"osm_id":"1832224339","tag":{"amenity":"waste_basket"}},"type":"Feature"},
	{"geometry":{"coordinates":[14.26488,46.614261],"type":"Point"},"properties":{"osm_id":"2973387987","tag":{"amenity":"waste_basket"}},"type":"Feature"},
	{"geometry":{"coordinates":[14.264571,46.614546],"type":"Point"},"properties":{"osm_id":"2973387988","tag":{"amenity":"waste_basket"}},"type":"Feature"},
	{"geometry":{"coordinates":[14.264656,46.614985],"type":"Point"},"properties":{"osm_id":"2973387989","tag":{"amenity":"waste_basket"}},"type":"Feature"},
	{"geometry":{"coordinates":[14.291462,46.613584],"type":"Point"},"properties":{"osm_id":"3676512480","tag":{"access":"private","entrance":"service"}},"type":"Feature"},
	{"geometry":{"coordinates":[14.268653,46.591666],"type":"Point"},"properties":{"osm_id":"3697767381","tag":{"amenity":"recycling","recycling:glass":"yes","recycling_type":"container"}},"type":"Feature"},
	{"geometry":{"coordinates":[14.260457,46.590282],"type":"Point"},"properties":{"osm_id":"3699806263","tag":{"amenity":"recycling","recycling:clothes":"yes","recycling_type":"container"}},"type":"Feature"},
	{"geometry":{"coordinates":[14.299227,46.606903],"type":"Point"},"properties":{"osm_id":"3894358585","tag":{"amenity":"waste_basket"}},"type":"Feature"},
	{"geometry":{"coordinates":[14.291985,46.612894],"type":"Point"},"properties":{"osm_id":"4414491609","tag":{"access":"private","amenity":"recycling","indoor":"yes","recycling:cartons":"yes","recycling:paper":"yes","recycling:plastic":"yes","recycling:plastic_bottles":"yes","recycling:waste":"yes","recycling_type":"container"}},"type":"Feature"},
	{"geometry":{"coordinates":[14.289192,46.613217],"type":"Point"},"properties":{"osm_id":"4488433089","tag":{"amenity":"recycling","recycling:glass":"yes","recycling_type":"container"}},"type":"Feature"},
	{"geometry":{"coordinates":[14.311691,46.614911],"type":"Point"},"properties":{"osm_id":"4796329137","tag":{"amenity":"recycling","recycling:glass":"yes","recycling:glass_bottles":"yes","recycling_type":"container"}},"type":"Feature"},
	{"geometry":{"coordinates":[14.264101,46.618623],"type":"Point"},"properties":{"osm_id":"5818836739","tag":{"amenity":"waste_basket"}},"type":"Feature"},
	{"geometry":{"coordinates":[14.288259,46.613645],"type":"Point"},"properties":{"osm_id":"6033828782","tag":{"amenity":"waste_basket"}},"type":"Feature"},
	{"geometry":{"coordinates":[14.264904,46.61412],"type":"Point"},"properties":{"osm_id":"6276448152","tag":{"amenity":"waste_basket"}},"type":"Feature"},
	{"geometry":{"coordinates":[14.265546,46.614268],"type":"Point"},"properties":{"osm_id":"6276448153","tag":{"amenity":"waste_basket"}},"type":"Feature"},
	{"geometry":{"coordinates":[14.252674,46.613091],"type":"Point"},"properties":{"osm_id":"7393367028","tag":{"amenity":"waste_basket"}},"type":"Feature"},
	{"geometry":{"coordinates":[14.251579,46.614717],"type":"Point"},"properties":{"osm_id":"7393367029","tag":{"amenity":"waste_basket"}},"type":"Feature"}
]
}
