{
"type": "FeatureCollection",
"features": [
	{"geometry":{"coordinates":[14.303138,42.296391],"type":"Point"},"properties":{"osm_id":"6293396600","tag":{"amenity":"recycling","recycling:plastic_bottles":"yes","recycling_type":"centre"}},"type":"Feature"},
	{"geometry":{"coordinates":[14.304628,42.29538],"type":"Point"},"properties":{"osm_id":"6293396623","tag":{"amenity":"recycling","recycling_type":"centre"}},"type":"Feature"},
	{"geometry":{"coordinates":[14.315029,42.341449],"type":"Point"},"properties":{"osm_id":"8324708007","tag":{"amenity":"waste_basket","colour":"#FFEBCD","material":"stone"}},"type":"Feature"},
	{"geometry":{"coordinates":[14.315486,42.341236],"type":"Point"},"properties":{"osm_id":"8360223301","tag":{"amenity":"waste_basket","colour":"green","direction":"0","hazard":"children","material":"metal","maxweight:hgv":"7.5","traffic_sign":"yes"}},"type":"Feature"},
	{"geometry":{"coordinates":[14.317787,42.339709],"type":"Point"},"properties":{"osm_id":"8363877548","tag":{"amenity":"waste_basket","waste":"dog_excrement"}},"type":"Feature"},
	{"geometry":{"coordinates":[14.31776,42.339649],"type":"Point"},"properties":{"osm_id":"8363877550","tag":{"amenity":"waste_basket","material":"metal","waste":"mixed"}},"type":"Feature"},
	{"geometry":{"coordinates":[14.31759,42.339979],"type":"Point"},"properties":{"osm_id":"8364269139","tag":{"amenity":"waste_basket"}},"type":"Feature"},
	{"geometry":{"coordinates":[14.317778,42.339839],"type":"Point"},"properties":{"osm_id":"8364356969","tag":{"amenity":"waste_basket","colour":"grey","material":"metal","waste":"mixed"}},"type":"Feature"},
	{"geometry":{"coordinates":[14.316683,42.340328],"type":"Point"},"properties":{"name":"Raccolta Abiti Usati","osm_id":"8364757132","tag":{"amenity":"recycling","colour":"green","operator":"Pat Service","phone:mobile":"+39 349 056 5217","recycling:bags":"yes","recycling:clothes":"yes","recycling:shoes":"yes","recycling:toys":"yes","recycling_type":"container"}},"type":"Feature"},
	{"geometry":{"coordinates":[14.317021,42.339882],"type":"Point"},"properties":{"highway":"street_lamp","osm_id":"8365243222","tag":{"amenity":"waste_basket","colour":"green","direction":"270","height":"7","lamp_mount":"bent_mast","lamp_type":"electric","material":"metal","waste":"mixed"}},"type":"Feature"},
	{"geometry":{"coordinates":[14.315786,42.341857],"type":"Point"},"properties":{"name":"Humana","osm_id":"8378882462","tag":{"amenity":"recycling","brand":"Humana","colour":"yellow","description":"People To People Italia project","operator":"Humana","recycling:clothes":"yes","recycling:shoes":"yes","recycling_type":"container"}},"type":"Feature"},
	{"geometry":{"coordinates":[14.315566,42.341252],"type":"Point"},"properties":{"osm_id":"8386707230","tag":{"amenity":"waste_basket","waste":"dog_excrement"}},"type":"Feature"},
	{"geometry":{"coordinates":[14.318706,42.33959],"type":"Point"},"properties":{"osm_id":"8390132942","tag":{"amenity":"recycling","colour":"red","recycling:medicines":"yes","recycling_type":"container"}},"type":"Feature"},
	{"geometry":{"coordinates":[14.316963,42.340439],"type":"Point"},"properties":{"osm_id":"8393436133","tag":{"amenity":"waste_basket","colour":"#DCDCDC","material":"metal","waste":"mixed"}},"type":"Feature"},
	{"geometry":{"coordinates":[14.317153,42.340389],"type":"Point"},"properties":{"osm_id":"8393612589","tag":{"amenity":"waste_basket","colour":"green","material":"metal","waste":"mixed"}},"type":"Feature"},
	{"geometry":{"coordinates":[14.32332,42.345883],"type":"Point"},"properties":{"osm_id":"8586688474","tag":{"amenity":"waste_basket","colour":"darkgrey","material":"metal","waste":"mixed"}},"type":"Feature"},
	{"geometry":{"coordinates":[14.32132,42.339275],"type":"Point"},"properties":{"osm_id":"8704541263","tag":{"amenity":"waste_basket","material":"metal","waste":"dog_excrement"}},"type":"Feature"},
	{"geometry":{"coordinates":[14.305862,42.300946],"type":"Point"},"properties":{"osm_id":"8887437455","tag":{"amenity":"waste_basket","colour":"brown","material":"wood","waste":"mixed"}},"type":"Feature"}
]
}
