{
"type": "FeatureCollection",
"features": [
	{"geometry":{"coordinates":[13.25329,50.809714],"type":"Point"},"properties":{"osm_id":"2015406306","tag":{"diameter_crown":"16","height":"19","monument":"yes","name:botanical":"Tilia Cordata","natural":"tree","start_date":"1845"}},"type":"Feature"},
	{"geometry":{"coordinates":[13.215555,50.828785],"type":"Point"},"properties":{"name":"Melanchton-Linde","osm_id":"2850284965","tag":{"genus":"Tilia","genus:de":"Linde","natural":"tree","start_date":"1817"}},"type":"Feature"},
	{"geometry":{"coordinates":[13.260505,50.816931],"type":"Point"},"properties":{"osm_id":"3216486236","tag":{"monument":"yes","natural":"tree"}},"type":"Feature"},
	{"geometry":{"coordinates":[13.232724,50.802039],"type":"Point"},"properties":{"osm_id":"3744503246","tag":{"denotation":"natural_monument","genus":"Tilia","genus:de":"Linde","natural":"tree"}},"type":"Feature"},
	{"geometry":{"coordinates":[13.228376,50.800136],"type":"Point"},"properties":{"osm_id":"4179013734","tag":{"denotation":"natural_monument","monument:natural":"yes","natural":"tree"}},"type":"Feature"}
]
}
