{
"type": "FeatureCollection",
"features": [
	{"geometry":{"coordinates":[7.144594,51.302156],"type":"Point"},"properties":{"osm_id":"1623614908","tag":{"natural":"tree"}},"type":"Feature"},
	{"geometry":{"coordinates":[7.145683,51.30454],"type":"Point"},"properties":{"osm_id":"1623614912","tag":{"natural":"tree"}},"type":"Feature"},
	{"geometry":{"coordinates":[7.143714,51.300817],"type":"Point"},"properties":{"osm_id":"1623614915","tag":{"natural":"tree"}},"type":"Feature"},
	{"geometry":{"coordinates":[7.142813,51.301002],"type":"Point"},"properties":{"osm_id":"1623614917","tag":{"natural":"tree"}},"type":"Feature"},
	{"geometry":{"coordinates":[7.154346,51.302732],"type":"Point"},"properties":{"osm_id":"2450527265","tag":{"natural":"tree"}},"type":"Feature"},
	{"geometry":{"coordinates":[7.154672,51.3012],"type":"Point"},"properties":{"osm_id":"2450527269","tag":{"natural":"tree"}},"type":"Feature"},
	{"geometry":{"coordinates":[7.144119,51.304514],"type":"Point"},"properties":{"osm_id":"2450537999","tag":{"natural":"tree"}},"type":"Feature"},
	{"geometry":{"coordinates":[7.173337,51.311397],"type":"Point"},"properties":{"osm_id":"2497053130","tag":{"natural":"tree"}},"type":"Feature"},
	{"geometry":{"coordinates":[7.125417,51.324322],"type":"Point"},"properties":{"osm_id":"2842056377","tag":{"natural":"tree"}},"type":"Feature"},
	{"geometry":{"coordinates":[7.161479,51.295838],"type":"Point"},"properties":{"osm_id":"4095672908","tag":{"natural":"tree"}},"type":"Feature"},
	{"geometry":{"coordinates":[7.179312,51.335298],"type":"Point"},"properties":{"name":"Sommerlinde","osm_id":"7624699489","tag":{"denotation":"natural_monument","diameter":"307 cm","leaf_cycle":"deciduous","leaf_type":"broadleaved","natural":"tree"}},"type":"Feature"},
	{"geometry":{"coordinates":[7.186753,51.328736],"type":"Point"},"properties":{"name":"Stieleiche","osm_id":"7903978438","tag":{"denotation":"natural_monument","leaf_cycle":"deciduous","leaf_type":"broadleaved","natural":"tree"}},"type":"Feature"}
]
}
