{
"type": "FeatureCollection",
"features": [
	{"geometry":{"coordinates":[7.129446,49.728165],"type":"Point"},"properties":{"osm_id":"3279098280","tag":{"natural":"tree"}},"type":"Feature"},
	{"geometry":{"coordinates":[7.20178,49.77723],"type":"Point"},"properties":{"name":"Eiche","osm_id":"7869344310","tag":{"denotation":"landmark","leaf_cycle":"deciduous","leaf_type":"broadleaved","natural":"tree"}},"type":"Feature"}
]
}
