{
"type": "FeatureCollection",
"lastupdate": "2020-08-01T00:00:00Z",
"features": [
	{"geometry":{"coordinates":[85.367316,27.723724],"type":"Point"},"properties":{"name":"Waste sorting plant","osm_id":"3479686277","tag":{"amenity":"recycling","recycling_type":"centre"}},"type":"Feature"},
	{"geometry":{"coordinates":[85.348683,27.737587],"type":"Point"},"properties":{"osm_id":"4787741735","tag":{"amenity":"recycling","name:en":"DR Interprises"}},"type":"Feature"},
	{"geometry":{"coordinates":[85.364792,27.725835],"type":"Point"},"properties":{"osm_id":"5694656439","tag":{"amenity":"waste_basket"}},"type":"Feature"},
	{"geometry":{"coordinates":[85.345771,27.727032],"type":"Point"},"properties":{"osm_id":"7682014471","tag":{"amenity":"waste_basket"}},"type":"Feature"}
]
}
