{
"type": "FeatureCollection",
"features": [
	{"geometry":{"coordinates":[-4.586395,56.005974],"type":"Point"},"properties":{"osm_id":"5800826361","tag":{"amenity":"waste_basket"}},"type":"Feature"},
	{"geometry":{"coordinates":[-4.584129,56.004433],"type":"Point"},"properties":{"osm_id":"5800826366","tag":{"amenity":"waste_basket"}},"type":"Feature"},
	{"geometry":{"coordinates":[-4.58577,56.005694],"type":"Point"},"properties":{"osm_id":"5800826368","tag":{"amenity":"waste_basket"}},"type":"Feature"},
	{"geometry":{"coordinates":[-4.587635,56.007243],"type":"Point"},"properties":{"osm_id":"5800826377","tag":{"amenity":"waste_basket"}},"type":"Feature"},
	{"geometry":{"coordinates":[-4.584594,56.00481],"type":"Point"},"properties":{"osm_id":"5800826379","tag":{"amenity":"waste_basket"}},"type":"Feature"},
	{"geometry":{"coordinates":[-4.587332,56.006901],"type":"Point"},"properties":{"osm_id":"5800826380","tag":{"amenity":"waste_basket"}},"type":"Feature"},
	{"geometry":{"coordinates":[-4.58725,56.006578],"type":"Point"},"properties":{"osm_id":"5800970258","tag":{"amenity":"waste_basket"}},"type":"Feature"},
	{"geometry":{"coordinates":[-4.583984,56.004479],"type":"Point"},"properties":{"osm_id":"5800970268","tag":{"amenity":"waste_basket"}},"type":"Feature"},
	{"geometry":{"coordinates":[-4.588778,56.00699],"type":"Point"},"properties":{"osm_id":"5800970269","tag":{"amenity":"waste_basket"}},"type":"Feature"},
	{"geometry":{"coordinates":[-4.585965,56.005526],"type":"Point"},"properties":{"osm_id":"5800970276","tag":{"amenity":"waste_basket"}},"type":"Feature"},
	{"geometry":{"coordinates":[-4.584024,56.002741],"type":"Point"},"properties":{"osm_id":"5800984849","tag":{"amenity":"waste_basket"}},"type":"Feature"},
	{"geometry":{"coordinates":[-4.583757,56.002812],"type":"Point"},"properties":{"osm_id":"5800984851","tag":{"amenity":"recycling","recycling:bottles":"yes","recycling_type":"container"}},"type":"Feature"},
	{"geometry":{"coordinates":[-4.582525,56.003294],"type":"Point"},"properties":{"osm_id":"5801065082","tag":{"amenity":"waste_basket"}},"type":"Feature"},
	{"geometry":{"coordinates":[-4.578868,56.004129],"type":"Point"},"properties":{"osm_id":"5902391334","tag":{"amenity":"recycling","location":"overground","recycling:bottles":"yes","recycling_type":"container"}},"type":"Feature"}
]
}
