{
"type": "FeatureCollection",
"features": [
	{"geometry":{"coordinates":[22.053452,50.758841],"type":"Point"},"properties":{"name":"Pomnik przyrody","osm_id":"4037117341","tag":{"denotation":"natural_monument","monument":"yes","natural":"tree","protected":"yes"}},"type":"Feature"},
	{"geometry":{"coordinates":[22.052304,50.760183],"type":"Point"},"properties":{"name":"Pomnik przyrody","osm_id":"4037117344","tag":{"denotation":"natural_monument","monument":"yes","natural":"tree","protected":"yes"}},"type":"Feature"}
]
}
