{
"type": "FeatureCollection",
"features": [
	{"geometry":{"coordinates":[21.982918,50.436565],"type":"Point"},"properties":{"name":"Pomnik przyrody","osm_id":"1842142351","tag":{"addr:city":"Stany","historic":"heritage","natural":"tree"}},"type":"Feature"},
	{"geometry":{"coordinates":[21.981427,50.435886],"type":"Point"},"properties":{"name":"Pomnik przyrody","osm_id":"4037115735","tag":{"denotation":"natural_monument","monument":"yes","natural":"tree","protected":"yes"}},"type":"Feature"},
	{"geometry":{"coordinates":[21.982946,50.436663],"type":"Point"},"properties":{"name":"Pomnik przyrody","osm_id":"4037115744","tag":{"denotation":"natural_monument","monument":"yes","natural":"tree","protected":"yes"}},"type":"Feature"},
	{"geometry":{"coordinates":[21.982658,50.436965],"type":"Point"},"properties":{"name":"Pomnik przyrody","osm_id":"4037115747","tag":{"denotation":"natural_monument","monument":"yes","natural":"tree","protected":"yes"}},"type":"Feature"},
	{"geometry":{"coordinates":[21.982657,50.437045],"type":"Point"},"properties":{"name":"Pomnik przyrody","osm_id":"4037115749","tag":{"denotation":"natural_monument","monument":"yes","natural":"tree","protected":"yes"}},"type":"Feature"},
	{"geometry":{"coordinates":[21.98157,50.439065],"type":"Point"},"properties":{"name":"Pomnik przyrody","osm_id":"4037115752","tag":{"denotation":"natural_monument","monument":"yes","natural":"tree","protected":"yes"}},"type":"Feature"}
]
}
