{
"type": "FeatureCollection",
"features": [
	{"geometry":{"coordinates":[9.573086,54.449512],"type":"Point"},"properties":{"osm_id":"755873353","tag":{"amenity":"recycling","recycling:glass":"yes"}},"type":"Feature"},
	{"geometry":{"coordinates":[9.522137,54.419404],"type":"Point"},"properties":{"name":"ASF-Recyclinghof Kropp","osm_id":"6145861750","tag":{"addr:city":"Kropp","addr:country":"DE","addr:housenumber":"27","addr:postcode":"24848","addr:street":"Industriestra\u00dfe","amenity":"recycling","opening_hours":"Nov-Feb: Mo,We-Fr 09:00-16:00; Sa 09:00-13:00; Su,Tu,PH off; Mar-Oct: Mo,We-Fr 09:00-17:00; Sa 08:00-13:00; Su,Tu,PH off","recycling_type":"centre"}},"type":"Feature"}
]
}
