{
"type": "FeatureCollection",
"features": [
	{"geometry":{"coordinates":[9.508703,50.623174],"type":"Point"},"properties":{"name":"Glas u. Altkleidercontainer","osm_id":"588933849","tag":{"amenity":"recycling","name:de":"Glas u. Altkleidercontainer","recycling:glass":"yes"}},"type":"Feature"},
	{"geometry":{"coordinates":[9.502581,50.620465],"type":"Point"},"properties":{"name":"Recyclinghof","osm_id":"886302665","tag":{"amenity":"recycling"}},"type":"Feature"},
	{"geometry":{"coordinates":[9.508684,50.623188],"type":"Point"},"properties":{"osm_id":"1578634358","tag":{"amenity":"recycling","recycling:clothes":"yes"}},"type":"Feature"},
	{"geometry":{"coordinates":[9.508648,50.595893],"type":"Point"},"properties":{"osm_id":"1591459820","tag":{"amenity":"recycling","recycling:clothes":"yes"}},"type":"Feature"},
	{"geometry":{"coordinates":[9.508614,50.595918],"type":"Point"},"properties":{"osm_id":"1591459826","tag":{"amenity":"recycling","recycling:glass_bottles":"yes"}},"type":"Feature"},
	{"geometry":{"coordinates":[9.537703,50.590823],"type":"Point"},"properties":{"osm_id":"1642116655","tag":{"amenity":"recycling","recycling:glass_bottles":"yes","recycling_type":"container"}},"type":"Feature"},
	{"geometry":{"coordinates":[9.537762,50.590822],"type":"Point"},"properties":{"osm_id":"1642116658","tag":{"amenity":"recycling","recycling:clothes":"yes","recycling_type":"container"}},"type":"Feature"},
	{"geometry":{"coordinates":[9.520184,50.610735],"type":"Point"},"properties":{"osm_id":"1643357222","tag":{"amenity":"recycling"}},"type":"Feature"},
	{"geometry":{"coordinates":[9.5414,50.589685],"type":"Point"},"properties":{"osm_id":"1647455833","tag":{"amenity":"waste_basket"}},"type":"Feature"},
	{"geometry":{"coordinates":[9.541426,50.594098],"type":"Point"},"properties":{"osm_id":"1647830155","tag":{"amenity":"waste_basket"}},"type":"Feature"},
	{"geometry":{"coordinates":[9.523479,50.578466],"type":"Point"},"properties":{"osm_id":"1669832450","tag":{"amenity":"recycling","recycling:clothes":"yes","recycling_type":"container"}},"type":"Feature"},
	{"geometry":{"coordinates":[9.523518,50.578466],"type":"Point"},"properties":{"osm_id":"1669832456","tag":{"amenity":"recycling","recycling:glass_bottles":"yes","recycling_type":"container"}},"type":"Feature"},
	{"geometry":{"coordinates":[9.563032,50.573047],"type":"Point"},"properties":{"osm_id":"1820749967","tag":{"amenity":"recycling","opening_hours":"Mo-Sa 07:00-20:00","recycling:glass_bottles":"yes","recycling_type":"container"}},"type":"Feature"},
	{"geometry":{"coordinates":[9.532264,50.592903],"type":"Point"},"properties":{"osm_id":"3586423951","tag":{"amenity":"recycling","recycling:clothes":"yes","recycling_type":"container"}},"type":"Feature"},
	{"geometry":{"coordinates":[9.513766,50.621059],"type":"Point"},"properties":{"name":"Altkleidercontainer","osm_id":"4568846689","tag":{"amenity":"recycling","name:de":"Altkleidercontainer"}},"type":"Feature"},
	{"geometry":{"coordinates":[9.543939,50.581413],"type":"Point"},"properties":{"osm_id":"4947503621","tag":{"amenity":"recycling"}},"type":"Feature"},
	{"geometry":{"coordinates":[9.5785,50.570297],"type":"Point"},"properties":{"osm_id":"6729076110","tag":{"amenity":"recycling","opening_hours":"Mo-Sa 07:00-20:00","recycling:glass_bottles":"yes","recycling_type":"container","wheelchair":"yes"}},"type":"Feature"},
	{"geometry":{"coordinates":[9.578687,50.571623],"type":"Point"},"properties":{"osm_id":"6729102689","tag":{"amenity":"recycling","opening_hours":"24/7","recycling:clothes":"yes","recycling_type":"container","wheelchair":"yes"}},"type":"Feature"},
	{"geometry":{"coordinates":[9.572992,50.572798],"type":"Point"},"properties":{"osm_id":"8541875063","tag":{"amenity":"waste_basket","waste":"dog_excrement"}},"type":"Feature"},
	{"geometry":{"coordinates":[9.578272,50.571687],"type":"Point"},"properties":{"osm_id":"8642787486","tag":{"amenity":"waste_basket","waste":"dog_excrement"}},"type":"Feature"},
	{"geometry":{"coordinates":[9.563047,50.573066],"type":"Point"},"properties":{"osm_id":"8664350743","tag":{"amenity":"recycling","opening_hours":"24/7","operator":"Malteser Hilfsdienst e.V.","recycling:clothes":"yes","recycling_type":"container"}},"type":"Feature"},
	{"geometry":{"coordinates":[9.577253,50.581566],"type":"Point"},"properties":{"osm_id":"9008474797","tag":{"amenity":"waste_basket","waste":"trash"}},"type":"Feature"}
]
}
