{
"type": "FeatureCollection",
"features": [
	{"geometry":{"coordinates":[9.508703,50.623175],"type":"Point"},"properties":{"name":"Glas u. Altkleidercontainer","osm_id":"588933849","tag":{"amenity":"recycling","name:de":"Glas u. Altkleidercontainer","recycling:glass":"yes"}},"type":"Feature"},
	{"geometry":{"coordinates":[9.502581,50.620465],"type":"Point"},"properties":{"name":"Recyclinghof","osm_id":"886302665","tag":{"amenity":"recycling"}},"type":"Feature"},
	{"geometry":{"coordinates":[9.508684,50.623189],"type":"Point"},"properties":{"osm_id":"1578634358","tag":{"amenity":"recycling","recycling:clothes":"yes"}},"type":"Feature"},
	{"geometry":{"coordinates":[9.508649,50.595894],"type":"Point"},"properties":{"osm_id":"1591459820","tag":{"amenity":"recycling","recycling:clothes":"yes"}},"type":"Feature"},
	{"geometry":{"coordinates":[9.508614,50.595919],"type":"Point"},"properties":{"osm_id":"1591459826","tag":{"amenity":"recycling","recycling:glass_bottles":"yes"}},"type":"Feature"},
	{"geometry":{"coordinates":[9.537704,50.590824],"type":"Point"},"properties":{"osm_id":"1642116655","tag":{"amenity":"recycling","recycling:glass_bottles":"yes","recycling_type":"container"}},"type":"Feature"},
	{"geometry":{"coordinates":[9.537762,50.590822],"type":"Point"},"properties":{"osm_id":"1642116658","tag":{"amenity":"recycling","recycling:clothes":"yes","recycling_type":"container"}},"type":"Feature"},
	{"geometry":{"coordinates":[9.520185,50.610736],"type":"Point"},"properties":{"osm_id":"1643357222","tag":{"amenity":"recycling"}},"type":"Feature"},
	{"geometry":{"coordinates":[9.541401,50.589685],"type":"Point"},"properties":{"osm_id":"1647455833","tag":{"amenity":"waste_basket"}},"type":"Feature"},
	{"geometry":{"coordinates":[9.541427,50.594098],"type":"Point"},"properties":{"osm_id":"1647830155","tag":{"amenity":"waste_basket"}},"type":"Feature"},
	{"geometry":{"coordinates":[9.52348,50.578467],"type":"Point"},"properties":{"osm_id":"1669832450","tag":{"amenity":"recycling","recycling:clothes":"yes","recycling_type":"container"}},"type":"Feature"},
	{"geometry":{"coordinates":[9.523518,50.578467],"type":"Point"},"properties":{"osm_id":"1669832456","tag":{"amenity":"recycling","recycling:glass_bottles":"yes","recycling_type":"container"}},"type":"Feature"},
	{"geometry":{"coordinates":[9.56305,50.573065],"type":"Point"},"properties":{"osm_id":"1820749967","tag":{"amenity":"recycling","recycling:glass_bottles":"yes","recycling_type":"container"}},"type":"Feature"},
	{"geometry":{"coordinates":[9.532265,50.592904],"type":"Point"},"properties":{"osm_id":"3586423951","tag":{"amenity":"recycling","recycling:clothes":"yes","recycling_type":"container"}},"type":"Feature"},
	{"geometry":{"coordinates":[9.513766,50.62106],"type":"Point"},"properties":{"name":"Altkleidercontainer","osm_id":"4568846689","tag":{"amenity":"recycling","name:de":"Altkleidercontainer"}},"type":"Feature"},
	{"geometry":{"coordinates":[9.54394,50.581414],"type":"Point"},"properties":{"osm_id":"4947503621","tag":{"amenity":"recycling"}},"type":"Feature"},
	{"geometry":{"coordinates":[9.578284,50.570863],"type":"Point"},"properties":{"name":"Glas-Container","osm_id":"6729076110","tag":{"amenity":"recycling","recycling:glass":"yes","recycling_type":"container"}},"type":"Feature"},
	{"geometry":{"coordinates":[9.578687,50.571624],"type":"Point"},"properties":{"osm_id":"6729102689","tag":{"amenity":"recycling","recycling:clothes":"yes","recycling_type":"container"}},"type":"Feature"}
]
}
