{
"type": "FeatureCollection",
"features": [
	{"geometry":{"coordinates":[9.514223,45.629795],"type":"Point"},"properties":{"name":"Piazzola Ecologica Comunale","osm_id":"664002235","tag":{"amenity":"recycling","recycling_type":"centre"}},"type":"Feature"},
	{"geometry":{"coordinates":[9.533634,45.587826],"type":"Point"},"properties":{"osm_id":"7036971069","tag":{"amenity":"waste_basket"}},"type":"Feature"},
	{"geometry":{"coordinates":[9.533527,45.588005],"type":"Point"},"properties":{"osm_id":"7036971070","tag":{"amenity":"waste_basket"}},"type":"Feature"}
]
}
