{
"type": "FeatureCollection",
"lastupdate": "2020-07-31T00:00:00Z",
"features": [
	{"geometry":{"coordinates":[13.488203,46.129921],"type":"Point"},"properties":{"osm_id":"2124926130","tag":{"amenity":"recycling","recycling:batteries":"no","recycling:cans":"yes","recycling:glass":"yes","recycling:paper":"yes","recycling_type":"container"}},"type":"Feature"},
	{"geometry":{"coordinates":[13.492184,46.117414],"type":"Point"},"properties":{"osm_id":"2590830166","tag":{"amenity":"recycling","location":"overground","recycling_type":"container"}},"type":"Feature"},
	{"geometry":{"coordinates":[13.486828,46.11468],"type":"Point"},"properties":{"name":"Ecopiazzola","osm_id":"4709024973","tag":{"amenity":"recycling","recycling_type":"centre"}},"type":"Feature"},
	{"geometry":{"coordinates":[13.486789,46.129343],"type":"Point"},"properties":{"osm_id":"6832249386","tag":{"amenity":"recycling","location":"overground","operator":"Caritas Diocesana","recycling":"clothes","recycling_type":"container"}},"type":"Feature"},
	{"geometry":{"coordinates":[13.484125,46.129661],"type":"Point"},"properties":{"osm_id":"6924949020","tag":{"amenity":"waste_basket","waste":"trash"}},"type":"Feature"},
	{"geometry":{"coordinates":[13.48724,46.127091],"type":"Point"},"properties":{"osm_id":"6924992130","tag":{"amenity":"waste_basket","waste":"trash"}},"type":"Feature"},
	{"geometry":{"coordinates":[13.487467,46.127066],"type":"Point"},"properties":{"osm_id":"6924992131","tag":{"amenity":"waste_basket","waste":"trash"}},"type":"Feature"},
	{"geometry":{"coordinates":[13.486962,46.127133],"type":"Point"},"properties":{"osm_id":"6924992132","tag":{"amenity":"waste_basket","waste":"trash"}},"type":"Feature"},
	{"geometry":{"coordinates":[13.486646,46.122606],"type":"Point"},"properties":{"osm_id":"6925009945","tag":{"amenity":"waste_basket","waste":"trash"}},"type":"Feature"},
	{"geometry":{"coordinates":[13.48671,46.12284],"type":"Point"},"properties":{"osm_id":"6925009946","tag":{"amenity":"waste_basket","waste":"trash"}},"type":"Feature"},
	{"geometry":{"coordinates":[13.486043,46.128968],"type":"Point"},"properties":{"osm_id":"7043486142","tag":{"amenity":"waste_basket","waste":"trash"}},"type":"Feature"},
	{"geometry":{"coordinates":[13.48672,46.129976],"type":"Point"},"properties":{"osm_id":"7043486143","tag":{"amenity":"waste_basket","waste":"trash"}},"type":"Feature"},
	{"geometry":{"coordinates":[13.486755,46.130188],"type":"Point"},"properties":{"osm_id":"7043486144","tag":{"amenity":"waste_basket","waste":"trash"}},"type":"Feature"},
	{"geometry":{"coordinates":[13.477449,46.111864],"type":"Point"},"properties":{"osm_id":"7052565102","tag":{"amenity":"recycling","recycling:batteries":"no","recycling:clothes":"no","recycling:glass_bottles":"yes","recycling:green_waste":"no","recycling:organic":"yes","recycling:paper":"no","recycling:plastic":"no","recycling:scrap_metal":"no","recycling_type":"container"}},"type":"Feature"},
	{"geometry":{"coordinates":[13.494898,46.089532],"type":"Point"},"properties":{"osm_id":"7686928666","ref":"SP31","tag":{"amenity":"waste_basket"}},"type":"Feature"}
]
}
