{
"type": "FeatureCollection",
"lastupdate": "2020-08-05T00:00:00Z",
"features": [
	{"geometry":{"coordinates":[-85.276229,38.197862],"type":"Point"},"properties":{"name":"Midwest Metals","osm_id":"5832382457","tag":{"addr:city":"Shelbyville","addr:housenumber":"40","addr:postcode":"40065","addr:state":"ky","addr:street":"Windhurst Way","amenity":"recycling","building":"yes","phone":"(502) 633-4211","recycling_type":"centre","website":"mwmcorp.com"}},"type":"Feature"},
	{"geometry":{"coordinates":[-85.279251,38.199625],"type":"Point"},"properties":{"name":"Shelby County Recycling Center","osm_id":"5832382458","tag":{"addr:city":"Shelbyville","addr:housenumber":"170","addr:postcode":"40065","addr:state":"KY","addr:street":"Windhurst Way","amenity":"recycling","phone":"(502) 633-2699","recycling_type":"centre"}},"type":"Feature"}
]
}
