{
"type": "FeatureCollection",
"features": [
	{"geometry":{"coordinates":[9.564246,48.208363],"type":"Point"},"properties":{"name":"Friedenslinde","osm_id":"2578074591","tag":{"description":"Naturdenkmal","natural":"tree"}},"type":"Feature"},
	{"geometry":{"coordinates":[9.523593,48.166729],"type":"Point"},"properties":{"osm_id":"3425090122","tag":{"natural":"tree"}},"type":"Feature"},
	{"geometry":{"coordinates":[9.526275,48.172958],"type":"Point"},"properties":{"osm_id":"3426611168","tag":{"natural":"tree"}},"type":"Feature"},
	{"geometry":{"coordinates":[9.532131,48.174621],"type":"Point"},"properties":{"osm_id":"3428365234","tag":{"natural":"tree"}},"type":"Feature"},
	{"geometry":{"coordinates":[9.505732,48.199724],"type":"Point"},"properties":{"name":"Friedenslinde","osm_id":"3975318054","tag":{"natural":"tree"}},"type":"Feature"},
	{"geometry":{"coordinates":[9.522276,48.202744],"type":"Point"},"properties":{"osm_id":"5628797654","tag":{"leaf_cycle":"deciduous","leaf_type":"broadleaved","natural":"tree"}},"type":"Feature"},
	{"geometry":{"coordinates":[9.522029,48.202721],"type":"Point"},"properties":{"osm_id":"5628797655","tag":{"leaf_cycle":"deciduous","leaf_type":"broadleaved","natural":"tree"}},"type":"Feature"},
	{"geometry":{"coordinates":[9.535377,48.176039],"type":"Point"},"properties":{"osm_id":"5630217486","tag":{"natural":"tree"}},"type":"Feature"},
	{"geometry":{"coordinates":[9.532758,48.177698],"type":"Point"},"properties":{"osm_id":"5630217487","tag":{"natural":"tree"}},"type":"Feature"},
	{"geometry":{"coordinates":[9.567643,48.187899],"type":"Point"},"properties":{"osm_id":"5630271430","tag":{"leaf_cycle":"deciduous","leaf_type":"broadleaved","natural":"tree"}},"type":"Feature"},
	{"geometry":{"coordinates":[9.572742,48.166849],"type":"Point"},"properties":{"osm_id":"5630668024","tag":{"leaf_cycle":"deciduous","leaf_type":"broadleaved","natural":"tree"}},"type":"Feature"},
	{"geometry":{"coordinates":[9.572656,48.166157],"type":"Point"},"properties":{"osm_id":"5630668025","tag":{"leaf_cycle":"deciduous","leaf_type":"broadleaved","natural":"tree"}},"type":"Feature"},
	{"geometry":{"coordinates":[9.519807,48.170372],"type":"Point"},"properties":{"osm_id":"5700529053","tag":{"natural":"tree"}},"type":"Feature"},
	{"geometry":{"coordinates":[9.519652,48.170413],"type":"Point"},"properties":{"osm_id":"5700529054","tag":{"natural":"tree"}},"type":"Feature"},
	{"geometry":{"coordinates":[9.521089,48.167536],"type":"Point"},"properties":{"osm_id":"6858587943","tag":{"natural":"tree"}},"type":"Feature"},
	{"geometry":{"coordinates":[9.496403,48.174936],"type":"Point"},"properties":{"osm_id":"7084275487","tag":{"leaf_cycle":"deciduous","leaf_type":"broadleaved","natural":"tree"}},"type":"Feature"},
	{"geometry":{"coordinates":[9.511158,48.221543],"type":"Point"},"properties":{"osm_id":"7787071561","tag":{"leaf_cycle":"deciduous","leaf_type":"broadleaved","natural":"tree"}},"type":"Feature"}
]
}
