{
"type": "FeatureCollection",
"features": [
	{"geometry":{"coordinates":[-3.910796,55.771641],"type":"Point"},"properties":{"osm_id":"3621915033","tag":{"amenity":"waste_basket"}},"type":"Feature"},
	{"geometry":{"coordinates":[-3.910982,55.768852],"type":"Point"},"properties":{"osm_id":"3630090958","tag":{"amenity":"waste_basket"}},"type":"Feature"},
	{"geometry":{"coordinates":[-3.89765,55.763855],"type":"Point"},"properties":{"osm_id":"3630091836","tag":{"amenity":"waste_basket"}},"type":"Feature"},
	{"geometry":{"coordinates":[-3.911454,55.768651],"type":"Point"},"properties":{"osm_id":"3630108122","tag":{"amenity":"waste_basket"}},"type":"Feature"},
	{"geometry":{"coordinates":[-3.921192,55.76624],"type":"Point"},"properties":{"osm_id":"3637312625","tag":{"amenity":"waste_basket"}},"type":"Feature"},
	{"geometry":{"coordinates":[-3.884505,55.750638],"type":"Point"},"properties":{"osm_id":"5752664397","tag":{"amenity":"recycling","recycling_type":"container"}},"type":"Feature"},
	{"geometry":{"coordinates":[-3.943713,55.770584],"type":"Point"},"properties":{"name":"Netherton Waste disposal and recycling centre","osm_id":"9148157285","tag":{"amenity":"recycling","owner":"North Lanarkshire Council","ownership":"municipal","recycling_type":"centre","wikidata":"Q106085836"}},"type":"Feature"}
]
}
