{
"type": "FeatureCollection",
"lastupdate": "2020-08-03T00:00:00Z",
"features": [
	{"geometry":{"coordinates":[-3.912942,48.066037],"type":"Point"},"properties":{"name":"Point Tri","osm_id":"1423421010","tag":{"amenity":"recycling","recycling:batteries":"no","recycling:books":"yes","recycling:cans":"yes","recycling:cartons":"yes","recycling:clothes":"no","recycling:electrical_appliances":"no","recycling:glass":"no","recycling:glass_bottles":"yes","recycling:green_waste":"yes","recycling:magazines":"yes","recycling:newspaper":"yes","recycling:paper":"yes","recycling:paper_packaging":"yes","recycling:plastic":"no","recycling:plastic_bottles":"yes","recycling:plastic_packaging":"no","recycling:scrap_metal":"no","recycling:small_appliances":"no","recycling:waste":"no","recycling:wood":"no","recycling_type":"container"}},"type":"Feature"},
	{"geometry":{"coordinates":[-3.888961,48.088348],"type":"Point"},"properties":{"osm_id":"1481651650","tag":{"amenity":"recycling"}},"type":"Feature"}
]
}
