{
"type": "FeatureCollection",
"features": [
	{"geometry":{"coordinates":[-3.913827,40.146368],"type":"Point"},"properties":{"name":"Planta Lola","osm_id":"7852607030","tag":{"addr:city":"El Viso de San Juan","addr:housenumber":"22","addr:street":"Avenida de la Industria","amenity":"recycling","opening_hours":"Mo-Fr 09:00-14:00","opening_hours:covid19":"same","recycling:asbestos":"yes","recycling_type":"centre","website":"https://plantalola.com/"}},"type":"Feature"}
]
}
