{
"type": "FeatureCollection",
"features": [
	{"geometry":{"coordinates":[0.258758,46.649301],"type":"Point"},"properties":{"osm_id":"1069277759","tag":{"amenity":"recycling","location":"overground","recycling:glass_bottles":"yes","recycling_type":"container"}},"type":"Feature"},
	{"geometry":{"coordinates":[0.247396,46.641194],"type":"Point"},"properties":{"osm_id":"1069282483","tag":{"amenity":"recycling"}},"type":"Feature"},
	{"geometry":{"coordinates":[0.21578,46.625049],"type":"Point"},"properties":{"osm_id":"4460391776","tag":{"amenity":"waste_basket"}},"type":"Feature"}
]
}
