{
"type": "FeatureCollection",
"features": [
	{"geometry":{"coordinates":[-108.480338,49.402244],"type":"Point"},"properties":{"name":"Rock Pile","osm_id":"3889591658","tag":{"natural":"tree"}},"type":"Feature"}
]
}
