{
"type": "FeatureCollection",
"lastupdate": "2020-08-06T00:00:00Z",
"features": [
	{"geometry":{"coordinates":[23.375657,50.848102],"type":"Point"},"properties":{"name":"Kosz","osm_id":"6407481906","tag":{"amenity":"waste_basket","waste":"trash"}},"type":"Feature"}
]
}
