{
"type": "FeatureCollection",
"lastupdate": "2020-08-05T00:00:00Z",
"features": [
	{"geometry":{"coordinates":[12.626736,53.480106],"type":"Point"},"properties":{"osm_id":"897442001","tag":{"amenity":"recycling","location":"overground","recycling_type":"container"}},"type":"Feature"},
	{"geometry":{"coordinates":[12.62733,53.479579],"type":"Point"},"properties":{"osm_id":"2429897383","tag":{"amenity":"waste_basket"}},"type":"Feature"},
	{"geometry":{"coordinates":[12.611008,53.455597],"type":"Point"},"properties":{"osm_id":"5730772897","tag":{"amenity":"waste_basket"}},"type":"Feature"},
	{"geometry":{"coordinates":[12.609976,53.455],"type":"Point"},"properties":{"osm_id":"5730774845","tag":{"amenity":"waste_basket"}},"type":"Feature"},
	{"geometry":{"coordinates":[12.610708,53.46057],"type":"Point"},"properties":{"osm_id":"5731860740","tag":{"amenity":"recycling","recycling:clothes":"yes","recycling:glass":"yes","recycling:glass_bottles":"yes","recycling:paper":"yes","recycling_type":"container"}},"type":"Feature"},
	{"geometry":{"coordinates":[12.610699,53.455434],"type":"Point"},"properties":{"osm_id":"7623340686","tag":{"amenity":"waste_basket"}},"type":"Feature"}
]
}
