{
"type": "FeatureCollection",
"lastupdate": "2020-08-01T00:00:00Z",
"features": [
	{"geometry":{"coordinates":[12.570774,48.03933],"type":"Point"},"properties":{"name":"Wertstoffhof","osm_id":"469821393","tag":{"amenity":"recycling","recycling:batteries":"yes","recycling:cans":"yes","recycling:clothes":"yes","recycling:glass":"yes","recycling:paper":"yes","recycling:scrap_metal":"yes","recycling_type":"centre"}},"type":"Feature"},
	{"geometry":{"coordinates":[12.637365,48.006215],"type":"Point"},"properties":{"barrier":"gate","osm_id":"5569752700"},"type":"Feature"},
	{"geometry":{"coordinates":[12.637203,48.006467],"type":"Point"},"properties":{"barrier":"gate","osm_id":"5569752704"},"type":"Feature"}
]
}
