{
"type": "FeatureCollection",
"lastupdate": "2020-08-03T00:00:00Z",
"features": [
	{"geometry":{"coordinates":[12.633137,47.871312],"type":"Point"},"properties":{"osm_id":"360671631","tag":{"amenity":"recycling","recycling:batteries":"no","recycling:cans":"no","recycling:clothes":"no","recycling:glass":"yes","recycling:paper":"no","recycling:scrap_metal":"no","recycling_type":"container"}},"type":"Feature"},
	{"geometry":{"coordinates":[12.647858,47.865177],"type":"Point"},"properties":{"osm_id":"386901773","tag":{"amenity":"recycling","recycling:cans":"yes","recycling:paper":"yes","recycling:scrap_metal":"yes","recycling_type":"container"}},"type":"Feature"},
	{"geometry":{"coordinates":[12.633178,47.862753],"type":"Point"},"properties":{"osm_id":"684560573","tag":{"amenity":"recycling","recycling:cans":"yes","recycling:clothes":"yes","recycling:glass":"no","recycling:glass_bottles":"yes","recycling:paper":"yes","recycling_type":"container"}},"type":"Feature"},
	{"geometry":{"coordinates":[12.60437,47.838103],"type":"Point"},"properties":{"name":"Wertstoffhof","osm_id":"1093824285","tag":{"amenity":"recycling","opening_hours":"Mo + Fr 14:00-17:00; Sa 09:00-13:00","recycling_type":"centre"}},"type":"Feature"},
	{"geometry":{"coordinates":[12.646697,47.821812],"type":"Point"},"properties":{"osm_id":"4653257884","tag":{"amenity":"recycling","operator":"Altstoffverwertung DEMI","recycling:clothes":"yes","recycling:shoes":"yes","recycling_type":"container"}},"type":"Feature"},
	{"geometry":{"coordinates":[12.647736,47.866647],"type":"Point"},"properties":{"osm_id":"6727468754","tag":{"amenity":"waste_basket","waste":"trash"}},"type":"Feature"},
	{"geometry":{"coordinates":[12.650135,47.828336],"type":"Point"},"properties":{"osm_id":"7619585070","tag":{"amenity":"recycling","recycling:clothes":"yes","recycling_type":"container"}},"type":"Feature"}
]
}
