{
"type": "FeatureCollection",
"lastupdate": "2020-07-31T00:00:00Z",
"features": [
	{"geometry":{"coordinates":[12.614781,43.071066],"type":"Point"},"properties":{"osm_id":"5276798090","tag":{"amenity":"waste_basket"}},"type":"Feature"},
	{"geometry":{"coordinates":[12.582802,43.070261],"type":"Point"},"properties":{"name":"Isola ecologica","osm_id":"7211031099"},"type":"Feature"}
]
}
