{
"type": "FeatureCollection",
"features": [
	{"geometry":{"coordinates":[12.614781,43.071066],"type":"Point"},"properties":{"osm_id":"5276798090","tag":{"amenity":"waste_basket"}},"type":"Feature"},
	{"geometry":{"coordinates":[12.582802,43.070261],"type":"Point"},"properties":{"name":"Isola ecologica","osm_id":"7211031099"},"type":"Feature"},
	{"geometry":{"coordinates":[12.600536,43.07673],"type":"Point"},"properties":{"osm_id":"8796381072","tag":{"amenity":"waste_basket"}},"type":"Feature"},
	{"geometry":{"coordinates":[12.600147,43.074819],"type":"Point"},"properties":{"osm_id":"8796381073","tag":{"amenity":"waste_basket"}},"type":"Feature"},
	{"geometry":{"coordinates":[12.598491,43.074286],"type":"Point"},"properties":{"osm_id":"8796381076","tag":{"amenity":"waste_basket"}},"type":"Feature"},
	{"geometry":{"coordinates":[12.597795,43.074258],"type":"Point"},"properties":{"osm_id":"8796381079","tag":{"amenity":"waste_basket"}},"type":"Feature"},
	{"geometry":{"coordinates":[12.59524,43.073092],"type":"Point"},"properties":{"osm_id":"8796381081","tag":{"amenity":"waste_basket"}},"type":"Feature"},
	{"geometry":{"coordinates":[12.591246,43.072142],"type":"Point"},"properties":{"osm_id":"8796381084","tag":{"amenity":"waste_basket"}},"type":"Feature"},
	{"geometry":{"coordinates":[12.589275,43.071001],"type":"Point"},"properties":{"osm_id":"8796381086","tag":{"amenity":"waste_basket"}},"type":"Feature"}
]
}
