{
"type": "FeatureCollection",
"features": [
	{"geometry":{"coordinates":[12.614782,43.071067],"type":"Point"},"properties":{"osm_id":"5276798090","tag":{"amenity":"waste_basket"}},"type":"Feature"},
	{"geometry":{"coordinates":[12.582802,43.070261],"type":"Point"},"properties":{"name":"Isola ecologica","osm_id":"7211031099"},"type":"Feature"}
]
}
