{
"type": "FeatureCollection",
"features": [
	{"geometry":{"coordinates":[5.293432,52.395544],"type":"Point"},"properties":{"osm_id":"469952065","tag":{"amenity":"recycling","recycling:glass_bottles":"yes","recycling:paper":"yes","recycling_type":"container"}},"type":"Feature"},
	{"geometry":{"coordinates":[5.294296,52.395322],"type":"Point"},"properties":{"osm_id":"469952067","tag":{"amenity":"recycling","operator":"Leger des Heils","recycling:clothes":"yes","recycling:shoes":"yes","recycling_type":"container"}},"type":"Feature"},
	{"geometry":{"coordinates":[5.292884,52.397975],"type":"Point"},"properties":{"osm_id":"470284261","tag":{"amenity":"waste_basket"}},"type":"Feature"},
	{"geometry":{"coordinates":[5.294564,52.398435],"type":"Point"},"properties":{"osm_id":"470284299","tag":{"amenity":"waste_basket"}},"type":"Feature"},
	{"geometry":{"coordinates":[5.298782,52.400475],"type":"Point"},"properties":{"osm_id":"470284467","tag":{"amenity":"waste_basket"}},"type":"Feature"},
	{"geometry":{"coordinates":[5.302621,52.40223],"type":"Point"},"properties":{"osm_id":"470284499","tag":{"amenity":"waste_basket"}},"type":"Feature"},
	{"geometry":{"coordinates":[5.303132,52.40244],"type":"Point"},"properties":{"osm_id":"470284504","tag":{"amenity":"waste_basket"}},"type":"Feature"},
	{"geometry":{"coordinates":[5.303187,52.402466],"type":"Point"},"properties":{"osm_id":"470284506","tag":{"amenity":"waste_basket"}},"type":"Feature"},
	{"geometry":{"coordinates":[5.303709,52.402687],"type":"Point"},"properties":{"osm_id":"470284508","tag":{"amenity":"waste_basket"}},"type":"Feature"},
	{"geometry":{"coordinates":[5.311601,52.402808],"type":"Point"},"properties":{"name":"Glas, Papier","osm_id":"597326053","tag":{"amenity":"recycling","recycling_type":"container"}},"type":"Feature"},
	{"geometry":{"coordinates":[5.305283,52.403303],"type":"Point"},"properties":{"osm_id":"946796000","tag":{"amenity":"waste_basket"}},"type":"Feature"},
	{"geometry":{"coordinates":[5.305516,52.403406],"type":"Point"},"properties":{"osm_id":"946796015","tag":{"amenity":"waste_basket"}},"type":"Feature"},
	{"geometry":{"coordinates":[5.305674,52.393196],"type":"Point"},"properties":{"osm_id":"1559416120","tag":{"amenity":"recycling","recycling_type":"container"}},"type":"Feature"},
	{"geometry":{"coordinates":[5.281127,52.394171],"type":"Point"},"properties":{"osm_id":"7801471193","tag":{"amenity":"waste_disposal"}},"type":"Feature"},
	{"geometry":{"coordinates":[5.282819,52.39569],"type":"Point"},"properties":{"osm_id":"7801471194","tag":{"amenity":"waste_disposal"}},"type":"Feature"}
]
}
