{
"type": "FeatureCollection",
"lastupdate": "2020-08-06T00:00:00Z",
"features": [
	{"geometry":{"coordinates":[5.293431,52.395543],"type":"Point"},"properties":{"osm_id":"469952065","tag":{"amenity":"recycling","recycling:glass_bottles":"yes","recycling:paper":"yes","recycling_type":"container"}},"type":"Feature"},
	{"geometry":{"coordinates":[5.294295,52.395322],"type":"Point"},"properties":{"osm_id":"469952067","tag":{"amenity":"recycling","operator":"Leger des Heils","recycling:clothes":"yes","recycling:shoes":"yes","recycling_type":"container"}},"type":"Feature"},
	{"geometry":{"coordinates":[5.292884,52.397975],"type":"Point"},"properties":{"osm_id":"470284261","tag":{"amenity":"waste_basket"}},"type":"Feature"},
	{"geometry":{"coordinates":[5.294564,52.398435],"type":"Point"},"properties":{"osm_id":"470284299","tag":{"amenity":"waste_basket"}},"type":"Feature"},
	{"geometry":{"coordinates":[5.298782,52.400475],"type":"Point"},"properties":{"osm_id":"470284467","tag":{"amenity":"waste_basket"}},"type":"Feature"},
	{"geometry":{"coordinates":[5.30262,52.40223],"type":"Point"},"properties":{"osm_id":"470284499","tag":{"amenity":"waste_basket"}},"type":"Feature"},
	{"geometry":{"coordinates":[5.303131,52.402439],"type":"Point"},"properties":{"osm_id":"470284504","tag":{"amenity":"waste_basket"}},"type":"Feature"},
	{"geometry":{"coordinates":[5.303186,52.402465],"type":"Point"},"properties":{"osm_id":"470284506","tag":{"amenity":"waste_basket"}},"type":"Feature"},
	{"geometry":{"coordinates":[5.303708,52.402686],"type":"Point"},"properties":{"osm_id":"470284508","tag":{"amenity":"waste_basket"}},"type":"Feature"},
	{"geometry":{"coordinates":[5.3116,52.402807],"type":"Point"},"properties":{"name":"Glas, Papier","osm_id":"597326053","tag":{"amenity":"recycling","recycling_type":"container"}},"type":"Feature"},
	{"geometry":{"coordinates":[5.305283,52.403303],"type":"Point"},"properties":{"osm_id":"946796000","tag":{"amenity":"waste_basket"}},"type":"Feature"},
	{"geometry":{"coordinates":[5.305516,52.403405],"type":"Point"},"properties":{"osm_id":"946796015","tag":{"amenity":"waste_basket"}},"type":"Feature"},
	{"geometry":{"coordinates":[5.305673,52.393196],"type":"Point"},"properties":{"osm_id":"1559416120","tag":{"amenity":"recycling","recycling_type":"container"}},"type":"Feature"}
]
}
