{
"type": "FeatureCollection",
"features": [
	{"geometry":{"coordinates":[5.323163,50.427813],"type":"Point"},"properties":{"osm_id":"4608644289","tag":{"amenity":"recycling","recycling:glass_bottles":"yes","recycling_type":"container"}},"type":"Feature"},
	{"geometry":{"coordinates":[5.316546,50.427627],"type":"Point"},"properties":{"name":"Intradel","osm_id":"5112992973","tag":{"amenity":"recycling"}},"type":"Feature"},
	{"geometry":{"coordinates":[5.302712,50.443671],"type":"Point"},"properties":{"osm_id":"7910096667","tag":{"amenity":"recycling","recycling:clothes":"yes","recycling:glass_bottles":"yes","recycling_type":"container"}},"type":"Feature"}
]
}
