{
"type": "FeatureCollection",
"lastupdate": "2020-08-05T00:00:00Z",
"features": [
	{"geometry":{"coordinates":[5.323162,50.427812],"type":"Point"},"properties":{"osm_id":"4608644289","tag":{"amenity":"recycling","recycling:glass_bottles":"yes","recycling_type":"container"}},"type":"Feature"},
	{"geometry":{"coordinates":[5.316545,50.427626],"type":"Point"},"properties":{"name":"Intradel","osm_id":"5112992973","tag":{"amenity":"recycling"}},"type":"Feature"}
]
}
