{
"type": "FeatureCollection",
"features": [
	{"geometry":{"coordinates":[-72.326764,18.231544],"type":"Point"},"properties":{"name":"cocotier","osm_id":"1167057667","tag":{"height":"5m","natural":"tree"}},"type":"Feature"},
	{"geometry":{"coordinates":[-72.326834,18.231615],"type":"Point"},"properties":{"name":"cocotier","osm_id":"1167062017","tag":{"height":"5m","natural":"tree"}},"type":"Feature"},
	{"geometry":{"coordinates":[-72.326748,18.231689],"type":"Point"},"properties":{"name":"guime","osm_id":"1167062496","tag":{"height":"3m","natural":"tree"}},"type":"Feature"},
	{"geometry":{"coordinates":[-72.326706,18.231692],"type":"Point"},"properties":{"name":"guime","osm_id":"1167063419","tag":{"height":"3m","natural":"tree"}},"type":"Feature"},
	{"geometry":{"coordinates":[-72.326678,18.231672],"type":"Point"},"properties":{"name":"manguier","osm_id":"1167071761","tag":{"name:botanical":"3m","natural":"tree"}},"type":"Feature"},
	{"geometry":{"coordinates":[-72.326824,18.231602],"type":"Point"},"properties":{"name":"cocotier","osm_id":"1167075079","tag":{"height":"5m","natural":"tree"}},"type":"Feature"},
	{"geometry":{"coordinates":[-72.326794,18.231673],"type":"Point"},"properties":{"name":"guime","osm_id":"1167076678","tag":{"height":"3m","natural":"tree"}},"type":"Feature"},
	{"geometry":{"coordinates":[-72.326797,18.231584],"type":"Point"},"properties":{"name":"cocotier","osm_id":"1167082432","tag":{"height":"5m","natural":"tree"}},"type":"Feature"},
	{"geometry":{"coordinates":[-72.290606,18.270987],"type":"Point"},"properties":{"name":"cocotier","osm_id":"1170978868","tag":{"natural":"tree"}},"type":"Feature"},
	{"geometry":{"coordinates":[-72.290553,18.270935],"type":"Point"},"properties":{"name":"palmier","osm_id":"1170979714","tag":{"natural":"tree"}},"type":"Feature"},
	{"geometry":{"coordinates":[-72.290602,18.270985],"type":"Point"},"properties":{"name":"palmier","osm_id":"1170980554","tag":{"natural":"tree"}},"type":"Feature"},
	{"geometry":{"coordinates":[-72.286169,18.265282],"type":"Point"},"properties":{"osm_id":"1170981237","tag":{"natural":"tree"}},"type":"Feature"},
	{"geometry":{"coordinates":[-72.290549,18.270936],"type":"Point"},"properties":{"name":"palmier","osm_id":"1170982032","tag":{"natural":"tree"}},"type":"Feature"},
	{"geometry":{"coordinates":[-72.290472,18.270977],"type":"Point"},"properties":{"name":"cocotier","osm_id":"1170982531","tag":{"natural":"tree"}},"type":"Feature"},
	{"geometry":{"coordinates":[-72.290378,18.270859],"type":"Point"},"properties":{"name":"manguier","osm_id":"1170983222","tag":{"natural":"tree"}},"type":"Feature"},
	{"geometry":{"coordinates":[-72.29038,18.270876],"type":"Point"},"properties":{"name":"manguier","osm_id":"1170986137","tag":{"natural":"tree"}},"type":"Feature"},
	{"geometry":{"coordinates":[-72.290488,18.271011],"type":"Point"},"properties":{"name":"bambou","osm_id":"1170986663","tag":{"natural":"tree"}},"type":"Feature"}
]
}
