{
"type": "FeatureCollection",
"features": [
	{"geometry":{"coordinates":[112.691376,-7.579589],"type":"Point"},"properties":{"name":"BUNDERAN APOLLO","osm_id":"3045288884","tag":{"natural":"tree"}},"type":"Feature"}
]
}
