{
"type": "FeatureCollection",
"features": [
	{"geometry":{"coordinates":[-1.453337,51.148529],"type":"Point"},"properties":{"name":"Chilbolton Recycling","osm_id":"442112714","tag":{"amenity":"recycling","odbl":"clean","recycling:glass_bottles":"yes"}},"type":"Feature"}
]
}
