{
"type": "FeatureCollection",
"lastupdate": "2020-07-31T00:00:00Z",
"features": [
	{"geometry":{"coordinates":[-60.007965,-3.078338],"type":"Point"},"properties":{"name":"Posto de Coleta","osm_id":"4771981124","tag":{"amenity":"recycling"}},"type":"Feature"},
	{"geometry":{"coordinates":[-59.997036,-3.105413],"type":"Point"},"properties":{"osm_id":"4887992145","tag":{"addr:street":"Rua Rio Madeira","amenity":"recycling"}},"type":"Feature"},
	{"geometry":{"coordinates":[-60.009151,-3.115571],"type":"Point"},"properties":{"osm_id":"5258866350","tag":{"amenity":"waste_basket"}},"type":"Feature"}
]
}
