{
"type": "FeatureCollection",
"features": [
	{"geometry":{"coordinates":[121.452192,14.136319],"type":"Point"},"properties":{"osm_id":"1129416777","tag":{"natural":"tree"}},"type":"Feature"},
	{"geometry":{"coordinates":[121.452248,14.136322],"type":"Point"},"properties":{"osm_id":"1129417017","tag":{"natural":"tree"}},"type":"Feature"},
	{"geometry":{"coordinates":[121.452238,14.136156],"type":"Point"},"properties":{"osm_id":"1129417290","tag":{"natural":"tree"}},"type":"Feature"},
	{"geometry":{"coordinates":[121.45214,14.136383],"type":"Point"},"properties":{"osm_id":"1129417358","tag":{"natural":"tree"}},"type":"Feature"},
	{"geometry":{"coordinates":[121.452327,14.136156],"type":"Point"},"properties":{"osm_id":"1129417524","tag":{"natural":"tree"}},"type":"Feature"},
	{"geometry":{"coordinates":[121.396713,14.112053],"type":"Point"},"properties":{"name":"Treehouse","osm_id":"2839787533","tag":{"natural":"tree"}},"type":"Feature"},
	{"geometry":{"coordinates":[121.396762,14.112332],"type":"Point"},"properties":{"osm_id":"5532705928","tag":{"natural":"tree"}},"type":"Feature"}
]
}
