{
"type": "FeatureCollection",
"lastupdate": "2020-07-31T00:00:00Z",
"features": [
	{"geometry":{"coordinates":[6.919668,52.128986],"type":"Point"},"properties":{"osm_id":"662296692","tag":{"amenity":"recycling","recycling:clothes":"yes","recycling:glass":"yes","recycling:glass_bottles":"yes","recycling_type":"container"}},"type":"Feature"},
	{"geometry":{"coordinates":[6.921819,52.128081],"type":"Point"},"properties":{"name":"Paul & Sohn GmbH","osm_id":"2689484194","tag":{"amenity":"recycling","recycling_type":"centre"}},"type":"Feature"},
	{"geometry":{"coordinates":[6.857315,52.158435],"type":"Point"},"properties":{"osm_id":"3453103366","tag":{"amenity":"waste_basket"}},"type":"Feature"}
]
}
