{
"type": "FeatureCollection",
"features": [
	{"geometry":{"coordinates":[6.911522,48.123337],"type":"Point"},"properties":{"osm_id":"1651769300","tag":{"amenity":"recycling","location":"overground","recycling:cardboard":"yes","recycling:glass_bottles":"yes","recycling:paper":"yes","recycling:plastic_bottles":"yes","recycling:waste":"yes","recycling_type":"container"}},"type":"Feature"}
]
}
