{
"type": "FeatureCollection",
"lastupdate": "2020-08-02T00:00:00Z",
"features": [
	{"geometry":{"coordinates":[6.911521,48.123336],"type":"Point"},"properties":{"osm_id":"1651769300","tag":{"amenity":"recycling","location":"overground","recycling:cardboard":"yes","recycling:glass":"yes","recycling:paper":"yes","recycling:plastic_bottles":"yes","recycling:waste":"yes","recycling_type":"container"}},"type":"Feature"}
]
}
