{
"type": "FeatureCollection",
"features": [
	{"geometry":{"coordinates":[-8.646326,52.642371],"type":"Point"},"properties":{"osm_id":"280886343","tag":{"amenity":"recycling","location":"overground","recycling_type":"container"}},"type":"Feature"}
]
}
