{
"type": "FeatureCollection",
"lastupdate": "2020-07-31T00:00:00Z",
"features": [
	{"geometry":{"coordinates":[-8.646326,52.642371],"type":"Point"},"properties":{"osm_id":"280886343","tag":{"amenity":"recycling","location":"overground","recycling_type":"container"}},"type":"Feature"},
	{"geometry":{"coordinates":[-8.680949,52.640288],"type":"Point"},"properties":{"name":"Mungret Recycling Centre","osm_id":"7082500078","tag":{"amenity":"recycling","contact:mobile":"+353 87 748 9130","contact:phone":"+353 61 305720","opening_hours":"Tu-Fr 10:00-17:00; PH off","recycling:batteries":"yes","recycling:cans":"yes","recycling:clothes":"yes","recycling:glass":"yes","recycling:paper":"yes","recycling:scrap_metal":"yes","recycling_type":"centre"}},"type":"Feature"}
]
}
