{
"type": "FeatureCollection",
"lastupdate": "2020-08-01T00:00:00Z",
"features": [
	{"geometry":{"coordinates":[-8.645861,42.028403],"type":"Point"},"properties":{"osm_id":"2554094922","tag":{"amenity":"waste_basket"}},"type":"Feature"},
	{"geometry":{"coordinates":[-8.645156,42.028473],"type":"Point"},"properties":{"osm_id":"2554094923","tag":{"amenity":"waste_basket"}},"type":"Feature"},
	{"geometry":{"coordinates":[-8.646033,42.027658],"type":"Point"},"properties":{"osm_id":"2554094924","tag":{"amenity":"waste_basket"}},"type":"Feature"},
	{"geometry":{"coordinates":[-8.646105,42.027498],"type":"Point"},"properties":{"osm_id":"2554094925","tag":{"amenity":"recycling","recycling_type":"container"}},"type":"Feature"},
	{"geometry":{"coordinates":[-8.645823,42.02868],"type":"Point"},"properties":{"osm_id":"2554094926","tag":{"amenity":"recycling","recycling:cooking_oil":"yes","recycling_type":"container"}},"type":"Feature"},
	{"geometry":{"coordinates":[-8.64603,42.027656],"type":"Point"},"properties":{"osm_id":"2554094927","tag":{"amenity":"waste_basket"}},"type":"Feature"},
	{"geometry":{"coordinates":[-8.64533,42.029317],"type":"Point"},"properties":{"osm_id":"2554094928","tag":{"amenity":"waste_basket"}},"type":"Feature"},
	{"geometry":{"coordinates":[-8.645231,42.028241],"type":"Point"},"properties":{"osm_id":"2554094929","tag":{"amenity":"waste_basket"}},"type":"Feature"},
	{"geometry":{"coordinates":[-8.645679,42.027974],"type":"Point"},"properties":{"osm_id":"2554094930","tag":{"amenity":"waste_basket"}},"type":"Feature"},
	{"geometry":{"coordinates":[-8.645357,42.027919],"type":"Point"},"properties":{"osm_id":"2554094931","tag":{"amenity":"waste_basket"}},"type":"Feature"},
	{"geometry":{"coordinates":[-8.645507,42.027771],"type":"Point"},"properties":{"osm_id":"2554094932","tag":{"amenity":"waste_basket"}},"type":"Feature"},
	{"geometry":{"coordinates":[-8.700612,41.97026],"type":"Point"},"properties":{"osm_id":"2691468830","tag":{"amenity":"recycling"}},"type":"Feature"},
	{"geometry":{"coordinates":[-8.64255,42.023768],"type":"Point"},"properties":{"osm_id":"2691469485","tag":{"amenity":"recycling"}},"type":"Feature"},
	{"geometry":{"coordinates":[-8.643061,42.024788],"type":"Point"},"properties":{"osm_id":"2691469500","tag":{"amenity":"recycling","recycling_type":"container"}},"type":"Feature"},
	{"geometry":{"coordinates":[-8.658511,41.984853],"type":"Point"},"properties":{"osm_id":"2759604971","tag":{"amenity":"recycling"}},"type":"Feature"},
	{"geometry":{"coordinates":[-8.643598,42.023603],"type":"Point"},"properties":{"osm_id":"2759605019","tag":{"amenity":"recycling","recycling_type":"container"}},"type":"Feature"},
	{"geometry":{"coordinates":[-8.689517,41.970712],"type":"Point"},"properties":{"name":"Ecoponto","osm_id":"3469238454","tag":{"amenity":"recycling"}},"type":"Feature"},
	{"geometry":{"coordinates":[-8.640773,42.022364],"type":"Point"},"properties":{"osm_id":"3587860311","tag":{"amenity":"recycling","recycling_type":"container"}},"type":"Feature"},
	{"geometry":{"coordinates":[-8.645057,42.025936],"type":"Point"},"properties":{"name":"Ecoponto","osm_id":"3722675267","tag":{"amenity":"recycling","recycling_type":"container"}},"type":"Feature"},
	{"geometry":{"coordinates":[-8.684169,41.984986],"type":"Point"},"properties":{"name":"Ecoponto","osm_id":"3734668227","tag":{"amenity":"recycling"}},"type":"Feature"},
	{"geometry":{"coordinates":[-8.677935,41.985653],"type":"Point"},"properties":{"name":"Ecoponto","osm_id":"3734669754","tag":{"amenity":"recycling","recycling_type":"container"}},"type":"Feature"}
]
}
