{
"type": "FeatureCollection",
"features": [
	{"geometry":{"coordinates":[-8.645862,42.028403],"type":"Point"},"properties":{"osm_id":"2554094922","tag":{"amenity":"waste_basket"}},"type":"Feature"},
	{"geometry":{"coordinates":[-8.645156,42.028473],"type":"Point"},"properties":{"osm_id":"2554094923","tag":{"amenity":"waste_basket"}},"type":"Feature"},
	{"geometry":{"coordinates":[-8.646033,42.027658],"type":"Point"},"properties":{"osm_id":"2554094924","tag":{"amenity":"waste_basket"}},"type":"Feature"},
	{"geometry":{"coordinates":[-8.646106,42.027499],"type":"Point"},"properties":{"osm_id":"2554094925","tag":{"amenity":"recycling","recycling_type":"container"}},"type":"Feature"},
	{"geometry":{"coordinates":[-8.645824,42.028681],"type":"Point"},"properties":{"osm_id":"2554094926","tag":{"amenity":"recycling","recycling:cooking_oil":"yes","recycling_type":"container"}},"type":"Feature"},
	{"geometry":{"coordinates":[-8.646031,42.027656],"type":"Point"},"properties":{"osm_id":"2554094927","tag":{"amenity":"waste_basket"}},"type":"Feature"},
	{"geometry":{"coordinates":[-8.645331,42.029318],"type":"Point"},"properties":{"osm_id":"2554094928","tag":{"amenity":"waste_basket"}},"type":"Feature"},
	{"geometry":{"coordinates":[-8.645231,42.028242],"type":"Point"},"properties":{"osm_id":"2554094929","tag":{"amenity":"waste_basket"}},"type":"Feature"},
	{"geometry":{"coordinates":[-8.645679,42.027975],"type":"Point"},"properties":{"osm_id":"2554094930","tag":{"amenity":"waste_basket"}},"type":"Feature"},
	{"geometry":{"coordinates":[-8.645358,42.027919],"type":"Point"},"properties":{"osm_id":"2554094931","tag":{"amenity":"waste_basket"}},"type":"Feature"},
	{"geometry":{"coordinates":[-8.645508,42.027772],"type":"Point"},"properties":{"osm_id":"2554094932","tag":{"amenity":"waste_basket"}},"type":"Feature"},
	{"geometry":{"coordinates":[-8.645561,42.02925],"type":"Point"},"properties":{"osm_id":"2554094934","tag":{"amenity":"waste_disposal"}},"type":"Feature"},
	{"geometry":{"coordinates":[-8.700612,41.970261],"type":"Point"},"properties":{"osm_id":"2691468830","tag":{"amenity":"recycling"}},"type":"Feature"},
	{"geometry":{"coordinates":[-8.64255,42.023769],"type":"Point"},"properties":{"osm_id":"2691469485","tag":{"amenity":"recycling"}},"type":"Feature"},
	{"geometry":{"coordinates":[-8.643062,42.024788],"type":"Point"},"properties":{"osm_id":"2691469500","tag":{"amenity":"recycling","recycling_type":"container"}},"type":"Feature"},
	{"geometry":{"coordinates":[-8.658512,41.984853],"type":"Point"},"properties":{"osm_id":"2759604971","tag":{"amenity":"recycling"}},"type":"Feature"},
	{"geometry":{"coordinates":[-8.658573,41.984889],"type":"Point"},"properties":{"osm_id":"2759604993","tag":{"amenity":"waste_disposal"}},"type":"Feature"},
	{"geometry":{"coordinates":[-8.643599,42.023603],"type":"Point"},"properties":{"osm_id":"2759605019","tag":{"amenity":"recycling","recycling_type":"container"}},"type":"Feature"},
	{"geometry":{"coordinates":[-8.689518,41.970712],"type":"Point"},"properties":{"name":"Ecoponto","osm_id":"3469238454","tag":{"amenity":"recycling"}},"type":"Feature"},
	{"geometry":{"coordinates":[-8.640773,42.022365],"type":"Point"},"properties":{"osm_id":"3587860311","tag":{"amenity":"recycling","recycling_type":"container"}},"type":"Feature"},
	{"geometry":{"coordinates":[-8.645058,42.025936],"type":"Point"},"properties":{"name":"Ecoponto","osm_id":"3722675267","tag":{"amenity":"recycling","recycling_type":"container"}},"type":"Feature"},
	{"geometry":{"coordinates":[-8.68417,41.984987],"type":"Point"},"properties":{"name":"Ecoponto","osm_id":"3734668227","tag":{"amenity":"recycling"}},"type":"Feature"},
	{"geometry":{"coordinates":[-8.677936,41.985653],"type":"Point"},"properties":{"name":"Ecoponto","osm_id":"3734669754","tag":{"amenity":"recycling","recycling_type":"container"}},"type":"Feature"},
	{"geometry":{"coordinates":[-8.645108,42.029986],"type":"Point"},"properties":{"osm_id":"4580476987","tag":{"amenity":"waste_disposal"}},"type":"Feature"},
	{"geometry":{"coordinates":[-8.645817,42.0287],"type":"Point"},"properties":{"osm_id":"4580477141","tag":{"amenity":"waste_disposal"}},"type":"Feature"}
]
}
