{
"type": "FeatureCollection",
"lastupdate": "2020-08-03T00:00:00Z",
"features": [
	{"geometry":{"coordinates":[-8.619239,41.549041],"type":"Point"},"properties":{"osm_id":"1235342536","tag":{"amenity":"recycling","recycling:cans":"yes","recycling:clothes":"yes","recycling:glass":"yes","recycling:paper":"yes"}},"type":"Feature"},
	{"geometry":{"coordinates":[-8.621201,41.548018],"type":"Point"},"properties":{"osm_id":"1235342584","tag":{"amenity":"recycling","recycling:cans":"yes","recycling:glass":"yes","recycling:paper":"yes"}},"type":"Feature"},
	{"geometry":{"coordinates":[-8.622096,41.532579],"type":"Point"},"properties":{"name":"Masof","osm_id":"1263587613","tag":{"amenity":"recycling"}},"type":"Feature"},
	{"geometry":{"coordinates":[-8.624123,41.530322],"type":"Point"},"properties":{"osm_id":"1480198824","tag":{"amenity":"recycling"}},"type":"Feature"},
	{"geometry":{"coordinates":[-8.627958,41.528873],"type":"Point"},"properties":{"osm_id":"1480198830","tag":{"amenity":"recycling"}},"type":"Feature"},
	{"geometry":{"coordinates":[-8.622803,41.529756],"type":"Point"},"properties":{"osm_id":"2235612177","tag":{"amenity":"recycling","recycling:batteries":"yes","recycling:cans":"yes","recycling:glass":"yes","recycling:paper":"yes","recycling_type":"container"}},"type":"Feature"},
	{"geometry":{"coordinates":[-8.633167,41.53093],"type":"Point"},"properties":{"osm_id":"2239100902","tag":{"amenity":"recycling","recycling:cans":"yes","recycling:glass":"yes","recycling:paper":"yes","recycling_type":"container"}},"type":"Feature"},
	{"geometry":{"coordinates":[-8.63028,41.570073],"type":"Point"},"properties":{"osm_id":"2965890342","tag":{"amenity":"recycling"}},"type":"Feature"},
	{"geometry":{"coordinates":[-8.695564,41.572719],"type":"Point"},"properties":{"name":"Ecoponto","osm_id":"3510593782","tag":{"amenity":"recycling","recycling_type":"container"}},"type":"Feature"}
]
}
