{
"type": "FeatureCollection",
"features": [
	{"geometry":{"coordinates":[-89.019325,37.732264],"type":"Point"},"properties":{"name":"CIMCO Recycling","osm_id":"2660493546","tag":{"amenity":"recycling","website":"https://www.cimcoresources.com/"}},"type":"Feature"}
]
}
