{
"type": "FeatureCollection",
"lastupdate": "2020-08-02T00:00:00Z",
"features": [
	{"geometry":{"coordinates":[-89.019324,37.732264],"type":"Point"},"properties":{"name":"CIMCO Recycling","osm_id":"2660493546","tag":{"amenity":"recycling","website":"https://www.cimcoresources.com/"}},"type":"Feature"}
]
}
