{
"type": "FeatureCollection",
"features": [
	{"geometry":{"coordinates":[-5.202669,50.304594],"type":"Point"},"properties":{"name":"Drovers way entrance old fir tree","osm_id":"3443660684","tag":{"natural":"tree"}},"type":"Feature"},
	{"geometry":{"coordinates":[-5.200465,50.304289],"type":"Point"},"properties":{"name":"Park old fir tree","osm_id":"3443660685","tag":{"natural":"tree"}},"type":"Feature"}
]
}
