{
"type": "FeatureCollection",
"features": [
	{"geometry":{"coordinates":[-5.20267,50.304595],"type":"Point"},"properties":{"name":"Drovers way entrance old fir tree","osm_id":"3443660684","tag":{"natural":"tree"}},"type":"Feature"},
	{"geometry":{"coordinates":[-5.200497,50.304139],"type":"Point"},"properties":{"name":"Park old fir tree","osm_id":"3443660685","tag":{"natural":"tree"}},"type":"Feature"}
]
}
