{
"type": "FeatureCollection",
"features": [
	{"geometry":{"coordinates":[-0.268588,38.683219],"type":"Point"},"properties":{"name":"Anoguer","osm_id":"4994511155","tag":{"natural":"tree"}},"type":"Feature"}
]
}
