{
"type": "FeatureCollection",
"lastupdate": "2020-08-01T00:00:00Z",
"features": [
	{"geometry":{"coordinates":[12.476566,65.644286],"type":"Point"},"properties":{"osm_id":"6195508590","tag":{"amenity":"recycling","description":"Perpetuum Mobile","operator":"Perpetuum AS","phone":"+47 40002929","recycling:marine_waste":"yes","recycling_type":"container","ref:sortere":"40","website":"https://perpetuum.no/"}},"type":"Feature"}
]
}
