{
"type": "FeatureCollection",
"features": [
	{"geometry":{"coordinates":[-84.469841,10.088939],"type":"Point"},"properties":{"name":"Punto Seguro","osm_id":"8097727856","tag":{"amenity":"recycling","description":"Farmagap","indoor":"yes","operator":"Punto Seguro","recycling_type":"container"}},"type":"Feature"},
	{"geometry":{"coordinates":[-84.470239,10.088392],"type":"Point"},"properties":{"name":"Punto Seguro","osm_id":"8097727864","tag":{"amenity":"recycling","description":"Farmacia Ecofarma Mercado","indoor":"yes","operator":"Punto Seguro","recycling_type":"container"}},"type":"Feature"},
	{"geometry":{"coordinates":[-84.473565,10.084668],"type":"Point"},"properties":{"name":"Punto Seguro","osm_id":"8097727865","tag":{"amenity":"recycling","description":"Farmacia Ecofarma Toscana","indoor":"yes","operator":"Punto Seguro","recycling_type":"container"}},"type":"Feature"}
]
}
