{
"type": "FeatureCollection",
"features": [
	{"geometry":{"coordinates":[-84.469841,10.088939],"type":"Point"},"properties":{"name":"Punto Seguro","osm_id":"8097727856","tag":{"amenity":"recycling","description":"Farmagap","email":"info@punto-seguro.com","indoor":"yes","operator":"Punto Seguro","phone":"+50683252970","recycling_type":"container","website":"https://www.punto-seguro.com"}},"type":"Feature"},
	{"geometry":{"coordinates":[-84.470239,10.088392],"type":"Point"},"properties":{"name":"Punto Seguro","osm_id":"8097727864","tag":{"amenity":"recycling","description":"Farmacia Ecofarma Mercado","email":"info@punto-seguro.com","indoor":"yes","operator":"Punto Seguro","phone":"+50683252970","recycling_type":"container","website":"https://www.punto-seguro.com"}},"type":"Feature"},
	{"geometry":{"coordinates":[-84.473565,10.084668],"type":"Point"},"properties":{"name":"Punto Seguro","osm_id":"8097727865","tag":{"amenity":"recycling","description":"Farmacia Ecofarma Toscana","email":"info@punto-seguro.com","indoor":"yes","operator":"Punto Seguro","phone":"+50683252970","recycling_type":"container","website":"https://www.punto-seguro.com"}},"type":"Feature"}
]
}
