{
"type": "FeatureCollection",
"features": [
	{"geometry":{"coordinates":[31.694342,3.519697],"type":"Point"},"properties":{"name":"Dust Bin","osm_id":"5772353175","tag":{"addr:block":"IBAKWE MARKET","addr:district":"Moyo","addr:settlement":"Palorinya","addr:zone":"Zone_BC","amenity":"waste_basket","fee":"yes","lit":"no","operator:type":"community","source:version":"Sanitation;v3.0.2","start_date":"2018-02-01","waste":"Disposal Basket"}},"type":"Feature"}
]
}
