{
"type": "FeatureCollection",
"features": [
	{"geometry":{"coordinates":[-4.36539,56.230673],"type":"Point"},"properties":{"name":"Bicycle Tree","osm_id":"5968531044","tag":{"natural":"tree","tourism":"attraction","wikidata":"Q55605400","wikipedia":"en:Bicycle Tree (Trossachs)"}},"type":"Feature"}
]
}
