{
"type": "FeatureCollection",
"lastupdate": "2020-08-03T00:00:00Z",
"features": [
	{"geometry":{"coordinates":[-7.669422,41.449765],"type":"Point"},"properties":{"name":"Ecoponto","osm_id":"2791195320","tag":{"amenity":"recycling"}},"type":"Feature"}
]
}
