{
"type": "FeatureCollection",
"features": [
	{"geometry":{"coordinates":[-17.974958,28.756851],"type":"Point"},"properties":{"osm_id":"2578570938","tag":{"genus":"Dracaena drago","natural":"tree"}},"type":"Feature"},
	{"geometry":{"coordinates":[-17.979858,28.765732],"type":"Point"},"properties":{"name":"Pino de La Virgen","osm_id":"3847675277","tag":{"natural":"tree"}},"type":"Feature"}
]
}
