{
"type": "FeatureCollection",
"features": [
	{"geometry":{"coordinates":[-103.728568,19.255863],"type":"Point"},"properties":{"name":"OFITEC","osm_id":"4896324963","tag":{"addr:city":"Colima","addr:housenumber":"352","addr:postcode":"28035","addr:street":"De los Maestros","amenity":"waste_basket"}},"type":"Feature"}
]
}
