{
"type": "FeatureCollection",
"features": [
	{"geometry":{"coordinates":[-1.50962,55.12896],"type":"Point"},"properties":{"name":"King St recycling","osm_id":"641747623","tag":{"amenity":"recycling"}},"type":"Feature"},
	{"geometry":{"coordinates":[-1.560776,55.169893],"type":"Point"},"properties":{"osm_id":"996342992","tag":{"amenity":"recycling","recycling:cans":"no","recycling:clothes":"yes","recycling:glass":"no"}},"type":"Feature"},
	{"geometry":{"coordinates":[-1.560595,55.170082],"type":"Point"},"properties":{"osm_id":"996343099","tag":{"amenity":"recycling","recycling:cans":"yes","recycling:glass":"yes"}},"type":"Feature"},
	{"geometry":{"coordinates":[-1.510972,55.128802],"type":"Point"},"properties":{"osm_id":"4324882986","tag":{"amenity":"waste_basket"}},"type":"Feature"},
	{"geometry":{"coordinates":[-1.546843,55.130059],"type":"Point"},"properties":{"osm_id":"4325049786","tag":{"amenity":"waste_basket"}},"type":"Feature"},
	{"geometry":{"coordinates":[-1.570024,55.139369],"type":"Point"},"properties":{"osm_id":"4330780590","tag":{"amenity":"waste_basket"}},"type":"Feature"},
	{"geometry":{"coordinates":[-1.568554,55.140574],"type":"Point"},"properties":{"osm_id":"4332097347","tag":{"amenity":"waste_basket"}},"type":"Feature"},
	{"geometry":{"coordinates":[-1.568276,55.1409],"type":"Point"},"properties":{"osm_id":"4332097363","tag":{"amenity":"waste_basket"}},"type":"Feature"},
	{"geometry":{"coordinates":[-1.569288,55.141596],"type":"Point"},"properties":{"osm_id":"4332107821","tag":{"amenity":"waste_basket"}},"type":"Feature"}
]
}
