{
"type": "FeatureCollection",
"features": [
	{"geometry":{"coordinates":[-1.561761,53.138558],"type":"Point"},"properties":{"name":"Sainsbury's Recycling point","osm_id":"937575104","tag":{"amenity":"recycling"}},"type":"Feature"},
	{"geometry":{"coordinates":[-1.563179,53.143423],"type":"Point"},"properties":{"osm_id":"4203431782","tag":{"amenity":"recycling"}},"type":"Feature"},
	{"geometry":{"coordinates":[-1.555668,53.138],"type":"Point"},"properties":{"osm_id":"5517877611","tag":{"amenity":"waste_basket"}},"type":"Feature"},
	{"geometry":{"coordinates":[-1.556301,53.133507],"type":"Point"},"properties":{"osm_id":"8638266218","tag":{"amenity":"waste_basket"}},"type":"Feature"},
	{"geometry":{"coordinates":[-1.556375,53.134378],"type":"Point"},"properties":{"osm_id":"8638266219","tag":{"amenity":"waste_basket"}},"type":"Feature"},
	{"geometry":{"coordinates":[-1.556307,53.13375],"type":"Point"},"properties":{"osm_id":"8638274317","tag":{"amenity":"waste_basket"}},"type":"Feature"},
	{"geometry":{"coordinates":[-1.551825,53.134819],"type":"Point"},"properties":{"osm_id":"8638274319","tag":{"amenity":"waste_basket"}},"type":"Feature"},
	{"geometry":{"coordinates":[-1.555544,53.134945],"type":"Point"},"properties":{"osm_id":"8638274419","tag":{"amenity":"waste_basket"}},"type":"Feature"},
	{"geometry":{"coordinates":[-1.553424,53.134824],"type":"Point"},"properties":{"osm_id":"8638274420","tag":{"amenity":"waste_basket"}},"type":"Feature"},
	{"geometry":{"coordinates":[-1.551636,53.135007],"type":"Point"},"properties":{"osm_id":"8638274423","tag":{"amenity":"waste_basket"}},"type":"Feature"},
	{"geometry":{"coordinates":[-1.554123,53.134882],"type":"Point"},"properties":{"osm_id":"8638274617","tag":{"amenity":"waste_basket"}},"type":"Feature"},
	{"geometry":{"coordinates":[-1.546028,53.144137],"type":"Point"},"properties":{"osm_id":"8868110800","tag":{"amenity":"waste_basket","waste":"dog_excrement"}},"type":"Feature"}
]
}
