{
"type": "FeatureCollection",
"features": [
	{"geometry":{"coordinates":[-1.561762,53.138558],"type":"Point"},"properties":{"name":"Sainsbury's Recycling point","osm_id":"937575104","tag":{"amenity":"recycling"}},"type":"Feature"},
	{"geometry":{"coordinates":[-1.56318,53.143423],"type":"Point"},"properties":{"osm_id":"4203431782","tag":{"amenity":"recycling"}},"type":"Feature"},
	{"geometry":{"coordinates":[-1.555668,53.138001],"type":"Point"},"properties":{"osm_id":"5517877611","tag":{"amenity":"waste_basket"}},"type":"Feature"}
]
}
