{
"type": "FeatureCollection",
"features": [
	{"geometry":{"coordinates":[-1.58196,47.012642],"type":"Point"},"properties":{"osm_id":"3776139979","tag":{"amenity":"recycling","recycling:glass":"yes","recycling:glass_bottles":"yes","recycling:paper":"yes","recycling_type":"container"}},"type":"Feature"},
	{"geometry":{"coordinates":[-1.561974,47.037533],"type":"Point"},"properties":{"osm_id":"4946221236","tag":{"amenity":"recycling","recycling:glass_bottles":"yes","recycling:paper":"yes","recycling_type":"container"}},"type":"Feature"},
	{"geometry":{"coordinates":[-1.569308,47.014132],"type":"Point"},"properties":{"osm_id":"5003384082","tag":{"amenity":"recycling","recycling_type":"container"}},"type":"Feature"},
	{"geometry":{"coordinates":[-1.523477,46.994025],"type":"Point"},"properties":{"osm_id":"5276002822","tag":{"amenity":"recycling","location":"underground","recycling:glass_bottles":"yes","recycling:paper":"yes","recycling_type":"container"}},"type":"Feature"}
]
}
