{
"type": "FeatureCollection",
"lastupdate": "2020-08-02T00:00:00Z",
"features": [
	{"geometry":{"coordinates":[-1.581959,47.012641],"type":"Point"},"properties":{"osm_id":"3776139979","tag":{"amenity":"recycling","recycling:glass":"yes","recycling:glass_bottles":"yes","recycling:paper":"yes","recycling_type":"container"}},"type":"Feature"},
	{"geometry":{"coordinates":[-1.561973,47.037532],"type":"Point"},"properties":{"osm_id":"4946221236","tag":{"amenity":"recycling","recycling:glass_bottles":"yes","recycling:paper":"yes","recycling_type":"container"}},"type":"Feature"},
	{"geometry":{"coordinates":[-1.569307,47.014131],"type":"Point"},"properties":{"osm_id":"5003384082","tag":{"amenity":"recycling","recycling_type":"container"}},"type":"Feature"},
	{"geometry":{"coordinates":[-1.523476,46.994024],"type":"Point"},"properties":{"osm_id":"5276002822","tag":{"amenity":"recycling","location":"underground","recycling:glass_bottles":"yes","recycling:paper":"yes","recycling_type":"container"}},"type":"Feature"}
]
}
