{
"type": "FeatureCollection",
"lastupdate": "2020-08-01T00:00:00Z",
"features": [
	{"geometry":{"coordinates":[6.068709,59.177387],"type":"Point"},"properties":{"osm_id":"1880666461","tag":{"amenity":"recycling","description":"Fister, campingplass","recycling:glass_bottles":"yes","recycling:paper":"yes","recycling:plastic_packaging":"yes","recycling_type":"container","ref:sortere":"310"}},"type":"Feature"},
	{"geometry":{"coordinates":[6.123219,59.204576],"type":"Point"},"properties":{"osm_id":"2075247886","tag":{"amenity":"waste_basket"}},"type":"Feature"},
	{"geometry":{"coordinates":[6.123147,59.204603],"type":"Point"},"properties":{"osm_id":"2075247901","tag":{"amenity":"waste_basket"}},"type":"Feature"},
	{"geometry":{"coordinates":[6.101317,59.217815],"type":"Point"},"properties":{"name":"Vikaneset gjenvinningsstasjon","osm_id":"5555203019","tag":{"amenity":"recycling","recycling:asbestos":"yes","recycling:batteries":"yes","recycling:boats":"yes","recycling:electrical_items":"yes","recycling:garden_waste":"yes","recycling:glass":"yes","recycling:glass_bottles":"yes","recycling:hazardous_waste":"yes","recycling:marine_waste":"yes","recycling:metal":"yes","recycling:paper":"yes","recycling:plasterboard":"yes","recycling:plastic":"yes","recycling:plastic_packaging":"yes","recycling:polystyrene_foam":"yes","recycling:rubble":"yes","recycling:scrap_metal":"yes","recycling:second_hand":"yes","recycling:tyres":"yes","recycling:waste":"yes","recycling:wood":"yes","recycling_type":"centre","ref:sortere":"1501"}},"type":"Feature"}
]
}
