{
"type": "FeatureCollection",
"features": [
	{"geometry":{"coordinates":[6.137945,52.78538],"type":"Point"},"properties":{"osm_id":"599680389","tag":{"amenity":"recycling","recycling_type":"container"}},"type":"Feature"},
	{"geometry":{"coordinates":[6.120351,52.793704],"type":"Point"},"properties":{"osm_id":"2186381904","tag":{"amenity":"recycling","recycling_type":"underfloor-container"}},"type":"Feature"},
	{"geometry":{"coordinates":[6.148107,52.788386],"type":"Point"},"properties":{"osm_id":"2219305914","tag":{"amenity":"recycling","designation":"central container","recycling_type":"container"}},"type":"Feature"},
	{"geometry":{"coordinates":[6.145141,52.791205],"type":"Point"},"properties":{"osm_id":"2219305915","tag":{"amenity":"recycling","designation":"central contrainer","recycling_type":"container"}},"type":"Feature"},
	{"geometry":{"coordinates":[6.14388,52.790982],"type":"Point"},"properties":{"osm_id":"2219305916","tag":{"amenity":"recycling","designation":"central container","recycling_type":"container"}},"type":"Feature"},
	{"geometry":{"coordinates":[6.143789,52.790953],"type":"Point"},"properties":{"osm_id":"2219305918","tag":{"amenity":"recycling","designation":"central container","recycling:waste":"yes","recycling_type":"container"}},"type":"Feature"},
	{"geometry":{"coordinates":[6.146419,52.787905],"type":"Point"},"properties":{"name":"centrale vuilcontainer","osm_id":"2497800796","tag":{"amenity":"recycling","recycling_type":"container"}},"type":"Feature"},
	{"geometry":{"coordinates":[6.133304,52.792745],"type":"Point"},"properties":{"name":"Koterhoek","osm_id":"2508459376","tag":{"amenity":"recycling","recycling_type":"container"}},"type":"Feature"},
	{"geometry":{"coordinates":[6.11761,52.790746],"type":"Point"},"properties":{"osm_id":"5410426413","tag":{"amenity":"waste_basket"}},"type":"Feature"},
	{"geometry":{"coordinates":[6.117095,52.790986],"type":"Point"},"properties":{"osm_id":"5410428144","tag":{"amenity":"waste_basket"}},"type":"Feature"},
	{"geometry":{"coordinates":[6.117004,52.790689],"type":"Point"},"properties":{"osm_id":"5410428146","tag":{"amenity":"waste_basket"}},"type":"Feature"},
	{"geometry":{"coordinates":[6.117768,52.79059],"type":"Point"},"properties":{"osm_id":"5410428161","tag":{"amenity":"waste_basket"}},"type":"Feature"},
	{"geometry":{"coordinates":[6.11805,52.790676],"type":"Point"},"properties":{"osm_id":"5410428162","tag":{"amenity":"waste_basket"}},"type":"Feature"},
	{"geometry":{"coordinates":[6.096221,52.800412],"type":"Point"},"properties":{"osm_id":"6137864398","tag":{"amenity":"waste_basket"}},"type":"Feature"},
	{"geometry":{"coordinates":[6.085641,52.762312],"type":"Point"},"properties":{"osm_id":"7174289952","tag":{"amenity":"waste_basket","waste":"trash"}},"type":"Feature"}
]
}
