{
"type": "FeatureCollection",
"features": [
	{"geometry":{"coordinates":[6.085079,44.034906],"type":"Point"},"properties":{"osm_id":"3176895961","tag":{"amenity":"waste_basket"}},"type":"Feature"},
	{"geometry":{"coordinates":[6.138635,44.049061],"type":"Point"},"properties":{"osm_id":"4371007961","tag":{"amenity":"recycling","recycling_type":"container"}},"type":"Feature"},
	{"geometry":{"coordinates":[6.144269,44.050936],"type":"Point"},"properties":{"osm_id":"4371046911","tag":{"amenity":"waste_basket"}},"type":"Feature"},
	{"geometry":{"coordinates":[6.146711,44.051451],"type":"Point"},"properties":{"osm_id":"4371046926","tag":{"amenity":"waste_disposal"}},"type":"Feature"},
	{"geometry":{"coordinates":[6.146775,44.051468],"type":"Point"},"properties":{"osm_id":"4371046927","tag":{"amenity":"recycling"}},"type":"Feature"},
	{"geometry":{"coordinates":[6.148835,44.054699],"type":"Point"},"properties":{"osm_id":"4371046945","tag":{"amenity":"waste_disposal"}},"type":"Feature"},
	{"geometry":{"coordinates":[6.148843,44.054723],"type":"Point"},"properties":{"osm_id":"4371046946","tag":{"amenity":"recycling"}},"type":"Feature"},
	{"geometry":{"coordinates":[6.141941,44.050637],"type":"Point"},"properties":{"osm_id":"4371053351","tag":{"amenity":"recycling","recycling_type":"container"}},"type":"Feature"},
	{"geometry":{"coordinates":[6.142392,44.052026],"type":"Point"},"properties":{"osm_id":"4371053362","tag":{"amenity":"recycling","recycling_type":"container"}},"type":"Feature"},
	{"geometry":{"coordinates":[6.141395,44.049989],"type":"Point"},"properties":{"osm_id":"4372070093","tag":{"amenity":"waste_disposal"}},"type":"Feature"},
	{"geometry":{"coordinates":[6.141434,44.048743],"type":"Point"},"properties":{"osm_id":"4372105283","tag":{"amenity":"waste_basket"}},"type":"Feature"},
	{"geometry":{"coordinates":[6.141762,44.048847],"type":"Point"},"properties":{"osm_id":"4372105286","tag":{"amenity":"waste_basket"}},"type":"Feature"},
	{"geometry":{"coordinates":[6.132718,44.045722],"type":"Point"},"properties":{"name":"PAV","osm_id":"4428637684","tag":{"amenity":"recycling","location":"underground","recycling_type":"container"}},"type":"Feature"},
	{"geometry":{"coordinates":[6.125925,44.042569],"type":"Point"},"properties":{"osm_id":"4828737300","tag":{"amenity":"recycling","recycling_type":"container"}},"type":"Feature"},
	{"geometry":{"coordinates":[6.102939,44.058977],"type":"Point"},"properties":{"osm_id":"5214037533","tag":{"amenity":"recycling","recycling:glass":"yes","recycling:paper":"yes","recycling:plastic_bottles":"yes","recycling_type":"container"}},"type":"Feature"},
	{"geometry":{"coordinates":[6.125405,44.04177],"type":"Point"},"properties":{"osm_id":"5587503528","tag":{"amenity":"recycling","recycling_type":"container"}},"type":"Feature"},
	{"geometry":{"coordinates":[6.105364,44.035554],"type":"Point"},"properties":{"osm_id":"5588607009","tag":{"amenity":"recycling","recycling_type":"container"}},"type":"Feature"},
	{"geometry":{"coordinates":[6.115308,44.049818],"type":"Point"},"properties":{"osm_id":"5707667278","tag":{"amenity":"waste_disposal"}},"type":"Feature"},
	{"geometry":{"coordinates":[6.116674,44.034888],"type":"Point"},"properties":{"osm_id":"7925023880","tag":{"amenity":"waste_basket","waste":"trash"}},"type":"Feature"},
	{"geometry":{"coordinates":[6.118845,44.034748],"type":"Point"},"properties":{"osm_id":"7925045285","tag":{"amenity":"recycling","recycling:beverage_cartons":"yes","recycling:books":"no","recycling:cans":"yes","recycling:cardboard":"yes","recycling:magazines":"yes","recycling:newspaper":"yes","recycling:paper":"yes","recycling:paper_packaging":"yes","recycling:plastic":"yes","recycling:plastic_bottles":"yes","recycling:plastic_packaging":"yes","recycling_type":"container"}},"type":"Feature"}
]
}
