{
"type": "FeatureCollection",
"lastupdate": "2020-07-31T00:00:00Z",
"features": [
	{"geometry":{"coordinates":[6.085078,44.034906],"type":"Point"},"properties":{"osm_id":"3176895961","tag":{"amenity":"waste_basket"}},"type":"Feature"},
	{"geometry":{"coordinates":[6.138634,44.04906],"type":"Point"},"properties":{"osm_id":"4371007961","tag":{"amenity":"recycling","recycling_type":"container"}},"type":"Feature"},
	{"geometry":{"coordinates":[6.144268,44.050936],"type":"Point"},"properties":{"osm_id":"4371046911","tag":{"amenity":"waste_basket"}},"type":"Feature"},
	{"geometry":{"coordinates":[6.146775,44.051467],"type":"Point"},"properties":{"osm_id":"4371046927","tag":{"amenity":"recycling"}},"type":"Feature"},
	{"geometry":{"coordinates":[6.148842,44.054722],"type":"Point"},"properties":{"osm_id":"4371046946","tag":{"amenity":"recycling"}},"type":"Feature"},
	{"geometry":{"coordinates":[6.141941,44.050636],"type":"Point"},"properties":{"osm_id":"4371053351","tag":{"amenity":"recycling","recycling_type":"container"}},"type":"Feature"},
	{"geometry":{"coordinates":[6.142391,44.052025],"type":"Point"},"properties":{"osm_id":"4371053362","tag":{"amenity":"recycling","recycling_type":"container"}},"type":"Feature"},
	{"geometry":{"coordinates":[6.141434,44.048743],"type":"Point"},"properties":{"osm_id":"4372105283","tag":{"amenity":"waste_basket"}},"type":"Feature"},
	{"geometry":{"coordinates":[6.141761,44.048847],"type":"Point"},"properties":{"osm_id":"4372105286","tag":{"amenity":"waste_basket"}},"type":"Feature"},
	{"geometry":{"coordinates":[6.132718,44.045721],"type":"Point"},"properties":{"name":"PAV","osm_id":"4428637684","tag":{"amenity":"recycling","location":"underground","recycling_type":"container"}},"type":"Feature"},
	{"geometry":{"coordinates":[6.125924,44.042568],"type":"Point"},"properties":{"osm_id":"4828737300","tag":{"amenity":"recycling","recycling_type":"container"}},"type":"Feature"},
	{"geometry":{"coordinates":[6.102939,44.058977],"type":"Point"},"properties":{"osm_id":"5214037533","tag":{"amenity":"recycling","recycling:glass":"yes","recycling:paper":"yes","recycling:plastic_bottles":"yes","recycling_type":"container"}},"type":"Feature"},
	{"geometry":{"coordinates":[6.125404,44.04177],"type":"Point"},"properties":{"osm_id":"5587503528","tag":{"amenity":"recycling","recycling_type":"container"}},"type":"Feature"},
	{"geometry":{"coordinates":[6.105363,44.035553],"type":"Point"},"properties":{"osm_id":"5588607009","tag":{"amenity":"recycling","recycling_type":"container"}},"type":"Feature"}
]
}
