{
"type": "FeatureCollection",
"features": [
	{"geometry":{"coordinates":[11.530679,51.356899],"type":"Point"},"properties":{"osm_id":"2178522485","tag":{"natural":"tree"}},"type":"Feature"},
	{"geometry":{"coordinates":[11.53067,51.356969],"type":"Point"},"properties":{"osm_id":"2178522486","tag":{"natural":"tree"}},"type":"Feature"},
	{"geometry":{"coordinates":[11.530534,51.356995],"type":"Point"},"properties":{"osm_id":"2178522487","tag":{"natural":"tree"}},"type":"Feature"},
	{"geometry":{"coordinates":[11.530735,51.357044],"type":"Point"},"properties":{"osm_id":"2178522488","tag":{"natural":"tree"}},"type":"Feature"},
	{"geometry":{"coordinates":[11.530218,51.357047],"type":"Point"},"properties":{"osm_id":"2178522489","tag":{"natural":"tree"}},"type":"Feature"},
	{"geometry":{"coordinates":[11.530564,51.357057],"type":"Point"},"properties":{"osm_id":"2178522490","tag":{"natural":"tree"}},"type":"Feature"},
	{"geometry":{"coordinates":[11.53037,51.357085],"type":"Point"},"properties":{"osm_id":"2178522491","tag":{"natural":"tree"}},"type":"Feature"},
	{"geometry":{"coordinates":[11.530232,51.35713],"type":"Point"},"properties":{"osm_id":"2178522492","tag":{"natural":"tree"}},"type":"Feature"},
	{"geometry":{"coordinates":[11.530487,51.357134],"type":"Point"},"properties":{"osm_id":"2178522493","tag":{"natural":"tree"}},"type":"Feature"},
	{"geometry":{"coordinates":[11.530577,51.357189],"type":"Point"},"properties":{"osm_id":"2178522495","tag":{"natural":"tree"}},"type":"Feature"},
	{"geometry":{"coordinates":[11.530374,51.357199],"type":"Point"},"properties":{"osm_id":"2178522496","tag":{"natural":"tree"}},"type":"Feature"},
	{"geometry":{"coordinates":[11.595409,51.37783],"type":"Point"},"properties":{"name":"Friedenseiche 1871","osm_id":"3705506225","tag":{"image":"http://i.imgur.com/AtjNz0gl.jpg","natural":"tree"}},"type":"Feature"},
	{"geometry":{"coordinates":[11.589348,51.397512],"type":"Point"},"properties":{"osm_id":"4535084060","tag":{"leaf_cycle":"deciduous","leaf_type":"broadleaved","natural":"tree"}},"type":"Feature"},
	{"geometry":{"coordinates":[11.598017,51.398247],"type":"Point"},"properties":{"osm_id":"4535084064","tag":{"leaf_cycle":"deciduous","leaf_type":"broadleaved","natural":"tree"}},"type":"Feature"},
	{"geometry":{"coordinates":[11.53256,51.376232],"type":"Point"},"properties":{"osm_id":"5498485094","tag":{"height":"14","leaf_cycle":"deciduous","leaf_type":"broadleaved","natural":"tree"}},"type":"Feature"},
	{"geometry":{"coordinates":[11.596191,51.376154],"type":"Point"},"properties":{"name":"Naturdenkmal Maulbeerbaum","osm_id":"7018121554","tag":{"denotation":"natural_monument","heritage":"yes","image":"https://commons.wikimedia.org/wiki/File:Querfurt,_Naturdenkmal,_Maulbeerbaum.jpg","natural":"tree"}},"type":"Feature"},
	{"geometry":{"coordinates":[11.541489,51.398225],"type":"Point"},"properties":{"osm_id":"8319014878","tag":{"denotation":"urban","leaf_cycle":"deciduous","leaf_type":"broadleaved","natural":"tree"}},"type":"Feature"}
]
}
