{
"type": "FeatureCollection",
"lastupdate": "2020-08-03T00:00:00Z",
"features": [
	{"geometry":{"coordinates":[-117.009478,46.733569],"type":"Point"},"properties":{"osm_id":"129918191","tag":{"amenity":"recycling"}},"type":"Feature"},
	{"geometry":{"coordinates":[-117.003399,46.736572],"type":"Point"},"properties":{"name":"Moscow Recycling Center","osm_id":"1887826577","tag":{"amenity":"recycling","recycling_type":"centre"}},"type":"Feature"}
]
}
