{
"type": "FeatureCollection",
"features": [
	{"geometry":{"coordinates":[-117.058739,33.362877],"type":"Point"},"properties":{"name":"Pala Transfer Station","osm_id":"2616785106","tag":{"amenity":"recycling","operator":"Pala Band of Mission Indians"}},"type":"Feature"}
]
}
