{
"type": "FeatureCollection",
"features": [
	{"geometry":{"coordinates":[152.886402,-27.123823],"type":"Point"},"properties":{"name":"Upper Caboolture Waste Transfer","osm_id":"8856913817","tag":{"amenity":"recycling","operator":"Moreton Bay Regional Council","phone":"+61 7 3205 0555","recycling_type":"centre","website":"https://moretonbay.qld.gov.au/"}},"type":"Feature"}
]
}
