{
"type": "FeatureCollection",
"features": [
	{"geometry":{"coordinates":[-81.26084,40.68574],"type":"Point"},"properties":{"name":"7881 Apple Tree","osm_id":"7952056967","tag":{"denotation":"garden","diameter":"20 in","height":"40","leaf_cycle":"deciduous","leaf_type":"broadleaved","natural":"tree"}},"type":"Feature"}
]
}
