{
"type": "FeatureCollection",
"features": [
	{"geometry":{"coordinates":[-81.573458,39.80785],"type":"Point"},"properties":{"is_in":"Noble,Ohio,Ohio,OH,USA","name":"Coal Ridge","osm_id":"154322999","place":"hamlet","tag":{"gnis:Class":"Populated Place","gnis:County":"Noble","gnis:County_num":"121","gnis:ST_alpha":"OH","gnis:ST_num":"39","gnis:id":"1060979","import_uuid":"bb7269ee-502a-5391-8056-e3ce0e66489c"}},"type":"Feature"}
]
}
