{
"type": "FeatureCollection",
"features": [
	{"geometry":{"coordinates":[-81.649602,36.288775],"type":"Point"},"properties":{"name":"Green Valley Convenience Center","osm_id":"2177342225","tag":{"amenity":"recycling","recycling:cans":"yes","recycling:glass":"yes","recycling:paper":"yes","recycling_type":"container"}},"type":"Feature"}
]
}
