{
"type": "FeatureCollection",
"lastupdate": "2020-08-02T00:00:00Z",
"features": [
	{"geometry":{"coordinates":[-76.47229,40.795234],"type":"Point"},"properties":{"name":"Kulpmont Recycling Drop-Off Center","osm_id":"5766338476","tag":{"addr:city":"Kulpmont","addr:housenumber":"860","addr:postcode":"17834","addr:state":"PA","addr:street":"Spruce Street","amenity":"recycling","recycling_type":"centre"}},"type":"Feature"}
]
}
