{
"type": "FeatureCollection",
"features": [
	{"geometry":{"coordinates":[-79.923571,40.656382],"type":"Point"},"properties":{"name":"Penn Oak (1598)","osm_id":"6333810517","tag":{"natural":"tree"}},"type":"Feature"}
]
}
