{
"type": "FeatureCollection",
"features": [
	{"geometry":{"coordinates":[7.53972,49.969955],"type":"Point"},"properties":{"osm_id":"1616709834","tag":{"natural":"tree"}},"type":"Feature"},
	{"geometry":{"coordinates":[7.539899,49.969973],"type":"Point"},"properties":{"osm_id":"1616709837","tag":{"natural":"tree"}},"type":"Feature"},
	{"geometry":{"coordinates":[7.539779,49.970055],"type":"Point"},"properties":{"osm_id":"1616709840","tag":{"natural":"tree"}},"type":"Feature"},
	{"geometry":{"coordinates":[7.542597,49.989624],"type":"Point"},"properties":{"osm_id":"4361332655","tag":{"natural":"tree"}},"type":"Feature"},
	{"geometry":{"coordinates":[7.542574,49.989709],"type":"Point"},"properties":{"osm_id":"4361332656","tag":{"natural":"tree"}},"type":"Feature"},
	{"geometry":{"coordinates":[7.552383,49.973132],"type":"Point"},"properties":{"name":"Riesenmammutbaum","osm_id":"4508972837","tag":{"genus":"Sequoiadendron","height":"12","leaf_cycle":"evergreen","leaf_type":"needleleaved","natural":"tree"}},"type":"Feature"},
	{"geometry":{"coordinates":[7.552391,49.973224],"type":"Point"},"properties":{"name":"Riesenmammutbaum","osm_id":"4508972838","tag":{"genus":"Sequoiadendron","height":"18","leaf_cycle":"evergreen","leaf_type":"needleleaved","natural":"tree"}},"type":"Feature"},
	{"geometry":{"coordinates":[7.519732,49.954088],"type":"Point"},"properties":{"name":"Naturdenkmal, Eiche","osm_id":"4687212710","tag":{"circumference":"4.80","denotation":"natural_monument","genus:de":"Eiche","leaf_type":"broadleaved","natural":"tree"}},"type":"Feature"},
	{"geometry":{"coordinates":[7.533113,49.957378],"type":"Point"},"properties":{"name":"Naturdenkmal, Eiche","osm_id":"4687221128","tag":{"circumference":"2.96","denotation":"natural_monument","genus:de":"Eiche","leaf_type":"broadleaved","natural":"tree"}},"type":"Feature"},
	{"geometry":{"coordinates":[7.534598,49.95508],"type":"Point"},"properties":{"name":"Naturdenkmal, Maulbeerbaum","osm_id":"4687299200","tag":{"denotation":"natural_monument","genus:de":"Maulbeerbaum","natural":"tree"}},"type":"Feature"},
	{"geometry":{"coordinates":[7.490669,49.9527],"type":"Point"},"properties":{"osm_id":"5876576765","tag":{"natural":"tree"}},"type":"Feature"},
	{"geometry":{"coordinates":[7.526756,49.9939],"type":"Point"},"properties":{"osm_id":"7476321811","tag":{"natural":"tree"}},"type":"Feature"}
]
}
