{
"type": "FeatureCollection",
"features": [
	{"geometry":{"coordinates":[7.546637,49.791436],"type":"Point"},"properties":{"osm_id":"2605947088","tag":{"natural":"tree"}},"type":"Feature"},
	{"geometry":{"coordinates":[7.555408,49.831483],"type":"Point"},"properties":{"osm_id":"3709803968","tag":{"natural":"tree"}},"type":"Feature"},
	{"geometry":{"coordinates":[7.502025,49.790316],"type":"Point"},"properties":{"name":"Alte Eiche","osm_id":"4831551274","tag":{"natural":"tree"}},"type":"Feature"},
	{"geometry":{"coordinates":[7.49988,49.80593],"type":"Point"},"properties":{"osm_id":"6432495826","tag":{"natural":"tree"}},"type":"Feature"},
	{"geometry":{"coordinates":[7.502165,49.805833],"type":"Point"},"properties":{"osm_id":"6432495827","tag":{"natural":"tree"}},"type":"Feature"},
	{"geometry":{"coordinates":[7.502026,49.805868],"type":"Point"},"properties":{"osm_id":"6432495828","tag":{"natural":"tree"}},"type":"Feature"},
	{"geometry":{"coordinates":[7.501553,49.805871],"type":"Point"},"properties":{"osm_id":"6432495829","tag":{"natural":"tree"}},"type":"Feature"},
	{"geometry":{"coordinates":[7.507658,49.803756],"type":"Point"},"properties":{"osm_id":"6432495877","tag":{"natural":"tree"}},"type":"Feature"},
	{"geometry":{"coordinates":[7.510812,49.804539],"type":"Point"},"properties":{"osm_id":"6432495878","tag":{"natural":"tree"}},"type":"Feature"},
	{"geometry":{"coordinates":[7.51034,49.804674],"type":"Point"},"properties":{"osm_id":"6432495879","tag":{"natural":"tree"}},"type":"Feature"},
	{"geometry":{"coordinates":[7.514069,49.821704],"type":"Point"},"properties":{"osm_id":"6433151304","tag":{"natural":"tree"}},"type":"Feature"},
	{"geometry":{"coordinates":[7.541996,49.835878],"type":"Point"},"properties":{"osm_id":"6441006210","tag":{"natural":"tree"}},"type":"Feature"}
]
}
