{
"type": "FeatureCollection",
"features": [
	{"geometry":{"coordinates":[-100.805477,20.448842],"type":"Point"},"properties":{"name":"ecofrigo .: Centro de Acopio y reciclado de  refrigeradores y aires acondicionados :.","osm_id":"1225668452","tag":{"amenity":"recycling","recycling:electrical_appliances":"yes","recycling_type":"centre"}},"type":"Feature"},
	{"geometry":{"coordinates":[-100.805648,20.44849],"type":"Point"},"properties":{"name":"Super Capturador SuperDrecksKescht","osm_id":"1642172075","tag":{"amenity":"recycling","recycling:batteries":"yes","recycling:cans":"yes","recycling:waste":"yes","recycling_type":"centre"}},"type":"Feature"}
]
}
