{
"type": "FeatureCollection",
"lastupdate": "2020-08-05T00:00:00Z",
"features": [
	{"geometry":{"coordinates":[-9.554318,7.039001],"type":"Point"},"properties":{"osm_id":"5039102025","tag":{"addr:city":"Gbarnga","addr:street":"Gbarnga - Monrovia Highway","amenity":"waste_basket","fee":"no","waste":"trash"}},"type":"Feature"},
	{"geometry":{"coordinates":[-9.552663,7.046755],"type":"Point"},"properties":{"osm_id":"5039102075","tag":{"addr:city":"Gbarnga","addr:street":"Gbarnga - Monrovia high way","amenity":"waste_basket","toilets:disposal":"bucket"}},"type":"Feature"},
	{"geometry":{"coordinates":[-9.555262,7.04163],"type":"Point"},"properties":{"osm_id":"5039102078","tag":{"addr:city":"Gbarnga","addr:street":"Gbarnga - Monrovia high way","amenity":"waste_basket","fee":"no","toilets:disposal":"bucket"}},"type":"Feature"},
	{"geometry":{"coordinates":[-9.554312,7.041461],"type":"Point"},"properties":{"osm_id":"5039102082","tag":{"addr:city":"Gbarnga","addr:street":"Gbarnga - Monrovia high way","amenity":"waste_basket","toilets:disposal":"bucket"}},"type":"Feature"}
]
}
