{
"type": "FeatureCollection",
"features": [
	{"geometry":{"coordinates":[-8.5609,51.933176],"type":"Point"},"properties":{"name":"Charity Clothes Bank","osm_id":"4837907911","tag":{"amenity":"recycling","recycling:clothes":"yes","recycling_type":"container"}},"type":"Feature"},
	{"geometry":{"coordinates":[-8.555417,51.929138],"type":"Point"},"properties":{"osm_id":"7489621085","tag":{"amenity":"recycling","description":"5 glass containers (clear, green, brown), cans and clothes.","recycling:cans":"yes","recycling:clothes":"yes","recycling:glass":"yes","recycling:glass_bottles":"yes","recycling_type":"container"}},"type":"Feature"},
	{"geometry":{"coordinates":[-8.545982,51.935227],"type":"Point"},"properties":{"osm_id":"8317083340","tag":{"amenity":"waste_disposal"}},"type":"Feature"},
	{"geometry":{"coordinates":[-8.545988,51.93526],"type":"Point"},"properties":{"osm_id":"8317083341","tag":{"amenity":"waste_disposal"}},"type":"Feature"},
	{"geometry":{"coordinates":[-8.54597,51.935192],"type":"Point"},"properties":{"osm_id":"8317083342","tag":{"amenity":"waste_disposal"}},"type":"Feature"}
]
}
