{
"type": "FeatureCollection",
"features": [
	{"geometry":{"coordinates":[-8.560901,51.933177],"type":"Point"},"properties":{"name":"Charity Clothes Bank","osm_id":"4837907911","tag":{"amenity":"recycling","recycling:clothes":"yes","recycling_type":"container"}},"type":"Feature"},
	{"geometry":{"coordinates":[-8.555417,51.929139],"type":"Point"},"properties":{"osm_id":"7489621085","tag":{"amenity":"recycling","description":"5 glass containers (clear, green, brown), cans and clothes.","recycling:cans":"yes","recycling:clothes":"yes","recycling:glass":"yes","recycling:glass_bottles":"yes","recycling_type":"container"}},"type":"Feature"}
]
}
