{
"type": "FeatureCollection",
"features": [
	{"geometry":{"coordinates":[-8.594024,42.047367],"type":"Point"},"properties":{"name":"Ecoponto","osm_id":"3204625936","tag":{"amenity":"recycling"}},"type":"Feature"},
	{"geometry":{"coordinates":[-8.579543,42.04489],"type":"Point"},"properties":{"name":"Ecoponto","osm_id":"3228089439","tag":{"amenity":"recycling"}},"type":"Feature"},
	{"geometry":{"coordinates":[-8.55751,42.084688],"type":"Point"},"properties":{"osm_id":"5899118686","tag":{"amenity":"recycling"}},"type":"Feature"}
]
}
