{
"type": "FeatureCollection",
"lastupdate": "2020-08-05T00:00:00Z",
"features": [
	{"geometry":{"coordinates":[-8.594023,42.047367],"type":"Point"},"properties":{"name":"Ecoponto","osm_id":"3204625936","tag":{"amenity":"recycling"}},"type":"Feature"},
	{"geometry":{"coordinates":[-8.579542,42.04489],"type":"Point"},"properties":{"name":"Ecoponto","osm_id":"3228089439","tag":{"amenity":"recycling"}},"type":"Feature"},
	{"geometry":{"coordinates":[-8.557509,42.084687],"type":"Point"},"properties":{"osm_id":"5899118686","tag":{"amenity":"recycling"}},"type":"Feature"}
]
}
