{
"type": "FeatureCollection",
"lastupdate": "2020-08-03T00:00:00Z",
"features": [
	{"geometry":{"coordinates":[-8.547555,41.46441],"type":"Point"},"properties":{"osm_id":"2178164351","tag":{"amenity":"recycling"}},"type":"Feature"},
	{"geometry":{"coordinates":[-8.530675,41.479846],"type":"Point"},"properties":{"osm_id":"2756734303","tag":{"amenity":"recycling","recycling_type":"container"}},"type":"Feature"},
	{"geometry":{"coordinates":[-8.567398,41.488817],"type":"Point"},"properties":{"name":"Ecoponto","osm_id":"3459082699","tag":{"amenity":"recycling","image":"https://storage12.openstreetcam.org/files/photo/2019/8/19/lth/1946009_2_113ba_8.jpg","recycling_type":"container","survey:date":"2019-08-19"}},"type":"Feature"},
	{"geometry":{"coordinates":[-8.568852,41.474216],"type":"Point"},"properties":{"name":"Ecoponto","osm_id":"3473060400","tag":{"amenity":"recycling"}},"type":"Feature"},
	{"geometry":{"coordinates":[-8.58828,41.443729],"type":"Point"},"properties":{"name":"Ecoponto","osm_id":"4107342303","tag":{"amenity":"recycling"}},"type":"Feature"},
	{"geometry":{"coordinates":[-8.556915,41.501991],"type":"Point"},"properties":{"name":"Ecoponto","osm_id":"4248171535","tag":{"amenity":"recycling"}},"type":"Feature"},
	{"geometry":{"coordinates":[-8.532626,41.493816],"type":"Point"},"properties":{"name":"Ecoponto","osm_id":"4248190089","tag":{"amenity":"recycling"}},"type":"Feature"},
	{"geometry":{"coordinates":[-8.533469,41.484761],"type":"Point"},"properties":{"name":"Ecoponto","osm_id":"4248191586","tag":{"amenity":"recycling"}},"type":"Feature"},
	{"geometry":{"coordinates":[-8.529121,41.481785],"type":"Point"},"properties":{"name":"Ecoponto","osm_id":"4248192829","tag":{"amenity":"recycling"}},"type":"Feature"}
]
}
