{
"type": "FeatureCollection",
"lastupdate": "2020-08-03T00:00:00Z",
"features": [
	{"geometry":{"coordinates":[-0.078436,51.281184],"type":"Point"},"properties":{"osm_id":"251147222","tag":{"amenity":"recycling"}},"type":"Feature"},
	{"geometry":{"coordinates":[-0.007609,51.256677],"type":"Point"},"properties":{"osm_id":"1326937581","tag":{"amenity":"waste_basket"}},"type":"Feature"},
	{"geometry":{"coordinates":[-0.004868,51.257505],"type":"Point"},"properties":{"osm_id":"1326937623","tag":{"amenity":"waste_basket"}},"type":"Feature"},
	{"geometry":{"coordinates":[-0.004658,51.256299],"type":"Point"},"properties":{"osm_id":"1340017076","tag":{"amenity":"recycling","phone":"+44 1883 732990","recycling:cans":"yes","recycling:cardboard":"yes","recycling:cartons":"yes","recycling:clothes":"yes","recycling:glass":"yes","recycling:paper":"yes","recycling:plastic_bottles":"yes","website":"https://www.tandridge.gov.uk/Recycling-and-rubbish/Recycling/Recycling-banks"}},"type":"Feature"},
	{"geometry":{"coordinates":[-0.004382,51.258442],"type":"Point"},"properties":{"osm_id":"4907917725","tag":{"amenity":"waste_basket"}},"type":"Feature"},
	{"geometry":{"coordinates":[-0.004374,51.258382],"type":"Point"},"properties":{"osm_id":"4907917726","tag":{"amenity":"waste_basket"}},"type":"Feature"},
	{"geometry":{"coordinates":[-0.004426,51.258436],"type":"Point"},"properties":{"osm_id":"4907917727","tag":{"amenity":"waste_basket"}},"type":"Feature"}
]
}
