{
"type": "FeatureCollection",
"features": [
	{"geometry":{"coordinates":[-0.078436,51.281184],"type":"Point"},"properties":{"osm_id":"251147222","tag":{"amenity":"recycling"}},"type":"Feature"},
	{"geometry":{"coordinates":[-0.007609,51.256677],"type":"Point"},"properties":{"osm_id":"1326937581","tag":{"amenity":"waste_basket","check_date":"2021-01-29"}},"type":"Feature"},
	{"geometry":{"coordinates":[-0.004868,51.257505],"type":"Point"},"properties":{"osm_id":"1326937623","tag":{"amenity":"waste_basket","check_date":"2021-01-30"}},"type":"Feature"},
	{"geometry":{"coordinates":[-0.004658,51.256299],"type":"Point"},"properties":{"osm_id":"1340017076","tag":{"amenity":"recycling","phone":"+44 1883 732990","recycling:cans":"yes","recycling:cardboard":"yes","recycling:cartons":"yes","recycling:clothes":"yes","recycling:glass":"yes","recycling:paper":"yes","recycling:plastic_bottles":"yes","website":"https://www.tandridge.gov.uk/Recycling-and-rubbish/Recycling/Recycling-banks"}},"type":"Feature"},
	{"geometry":{"coordinates":[-0.004382,51.258442],"type":"Point"},"properties":{"osm_id":"4907917725","tag":{"amenity":"waste_basket"}},"type":"Feature"},
	{"geometry":{"coordinates":[-0.004374,51.258382],"type":"Point"},"properties":{"osm_id":"4907917726","tag":{"amenity":"waste_basket"}},"type":"Feature"},
	{"geometry":{"coordinates":[-0.004426,51.258436],"type":"Point"},"properties":{"osm_id":"4907917727","tag":{"amenity":"waste_basket"}},"type":"Feature"},
	{"geometry":{"coordinates":[-0.078734,51.263278],"type":"Point"},"properties":{"osm_id":"8960997364","tag":{"amenity":"waste_basket","waste":"dog_excrement"}},"type":"Feature"},
	{"geometry":{"coordinates":[-0.077683,51.263258],"type":"Point"},"properties":{"osm_id":"8960997365","tag":{"amenity":"waste_basket"}},"type":"Feature"},
	{"geometry":{"coordinates":[-0.075193,51.282104],"type":"Point"},"properties":{"osm_id":"8960997378","tag":{"amenity":"waste_basket"}},"type":"Feature"},
	{"geometry":{"coordinates":[-0.010474,51.255285],"type":"Point"},"properties":{"osm_id":"9130321097","tag":{"amenity":"waste_basket","waste":"dog_excrement"}},"type":"Feature"},
	{"geometry":{"coordinates":[-0.010319,51.255219],"type":"Point"},"properties":{"osm_id":"9130321098","tag":{"amenity":"waste_basket","waste":"trash"}},"type":"Feature"}
]
}
