{
"type": "FeatureCollection",
"features": [
	{"geometry":{"coordinates":[-0.057715,45.603548],"type":"Point"},"properties":{"osm_id":"7197531603","tag":{"amenity":"recycling","location":"underground","operator":"Calitom","recycling_type":"container"}},"type":"Feature"},
	{"geometry":{"coordinates":[-0.000361,45.638528],"type":"Point"},"properties":{"osm_id":"7685418599","tag":{"amenity":"waste_basket"}},"type":"Feature"},
	{"geometry":{"coordinates":[-0.052913,45.599857],"type":"Point"},"properties":{"osm_id":"7702438043","tag":{"amenity":"waste_basket"}},"type":"Feature"},
	{"geometry":{"coordinates":[-0.05027,45.596241],"type":"Point"},"properties":{"osm_id":"7760797373","tag":{"amenity":"waste_basket"}},"type":"Feature"},
	{"geometry":{"coordinates":[-0.05394,45.598504],"type":"Point"},"properties":{"osm_id":"7765296274","tag":{"amenity":"waste_basket"}},"type":"Feature"},
	{"geometry":{"coordinates":[-0.054736,45.600044],"type":"Point"},"properties":{"osm_id":"7768096676","tag":{"amenity":"waste_basket"}},"type":"Feature"},
	{"geometry":{"coordinates":[-0.055739,45.60234],"type":"Point"},"properties":{"osm_id":"7816359912","tag":{"amenity":"waste_basket"}},"type":"Feature"},
	{"geometry":{"coordinates":[-0.052304,45.601646],"type":"Point"},"properties":{"osm_id":"7817729955","tag":{"amenity":"waste_basket"}},"type":"Feature"},
	{"geometry":{"coordinates":[-0.044579,45.598486],"type":"Point"},"properties":{"osm_id":"7817812708","tag":{"amenity":"waste_basket"}},"type":"Feature"},
	{"geometry":{"coordinates":[-0.056178,45.607362],"type":"Point"},"properties":{"osm_id":"7818040381","tag":{"amenity":"waste_basket"}},"type":"Feature"},
	{"geometry":{"coordinates":[-0.057561,45.603715],"type":"Point"},"properties":{"osm_id":"7824324176","tag":{"amenity":"recycling","brand":"Le Relais","charity":"yes","recycling:clothes":"yes","recycling:shoes":"yes","recycling_type":"container","website":"https://www.lerelais.org/"}},"type":"Feature"},
	{"geometry":{"coordinates":[-0.048129,45.588317],"type":"Point"},"properties":{"osm_id":"7824350397","tag":{"amenity":"recycling","brand":"Le Relais","charity":"yes","recycling:clothes":"yes","recycling:shoes":"yes","recycling_type":"container","website":"https://www.lerelais.org/"}},"type":"Feature"},
	{"geometry":{"coordinates":[-0.04812,45.588304],"type":"Point"},"properties":{"osm_id":"7824350398","tag":{"amenity":"recycling","brand":"Le Relais","charity":"yes","recycling:clothes":"yes","recycling:shoes":"yes","recycling_type":"container","website":"https://www.lerelais.org/"}},"type":"Feature"}
]
}
