{
"type": "FeatureCollection",
"lastupdate": "2020-07-31T00:00:00Z",
"features": [
	{"geometry":{"coordinates":[-0.057715,45.603548],"type":"Point"},"properties":{"osm_id":"7197531603","tag":{"amenity":"recycling","location":"underground","operator":"Calitom","recycling_type":"container"}},"type":"Feature"},
	{"geometry":{"coordinates":[-0.000361,45.638528],"type":"Point"},"properties":{"osm_id":"7685418599","tag":{"amenity":"waste_basket"}},"type":"Feature"},
	{"geometry":{"coordinates":[-0.052913,45.599857],"type":"Point"},"properties":{"osm_id":"7702438043","tag":{"amenity":"waste_basket"}},"type":"Feature"},
	{"geometry":{"coordinates":[-0.05027,45.596241],"type":"Point"},"properties":{"osm_id":"7760797373","tag":{"amenity":"waste_basket"}},"type":"Feature"},
	{"geometry":{"coordinates":[-0.05394,45.598504],"type":"Point"},"properties":{"osm_id":"7765296274","tag":{"amenity":"waste_basket"}},"type":"Feature"},
	{"geometry":{"coordinates":[-0.054736,45.600044],"type":"Point"},"properties":{"osm_id":"7768096676","tag":{"amenity":"waste_basket"}},"type":"Feature"}
]
}
