{
"type": "FeatureCollection",
"features": [
	{"geometry":{"coordinates":[-0.222496,53.979228],"type":"Point"},"properties":{"name":"Clothing Recycling","osm_id":"1780104988","tag":{"amenity":"recycling","recycling_type":"container"}},"type":"Feature"}
]
}
