{
"type": "FeatureCollection",
"features": [
	{"geometry":{"coordinates":[9.935727,54.208713],"type":"Point"},"properties":{"name":"Schredderplatz","osm_id":"2159508945","tag":{"amenity":"recycling","recycling:green_waste":"yes"}},"type":"Feature"},
	{"geometry":{"coordinates":[9.932323,54.18853],"type":"Point"},"properties":{"osm_id":"2293371015","tag":{"amenity":"recycling","recycling:glass_bottles":"yes","recycling:paper":"no","recycling_type":"container"}},"type":"Feature"},
	{"geometry":{"coordinates":[9.931965,54.188849],"type":"Point"},"properties":{"osm_id":"2293371021","tag":{"amenity":"recycling","recycling:glass_bottles":"yes","recycling:paper":"no","recycling_type":"container"}},"type":"Feature"}
]
}
