{
"type": "FeatureCollection",
"lastupdate": "2020-08-01T00:00:00Z",
"features": [
	{"geometry":{"coordinates":[9.935727,54.208713],"type":"Point"},"properties":{"name":"Schredderplatz","osm_id":"2159508945","tag":{"amenity":"recycling","recycling:green_waste":"yes"}},"type":"Feature"},
	{"geometry":{"coordinates":[9.932322,54.188529],"type":"Point"},"properties":{"osm_id":"2293371015","tag":{"amenity":"recycling","recycling:glass_bottles":"yes","recycling:paper":"no","recycling_type":"container"}},"type":"Feature"},
	{"geometry":{"coordinates":[9.931964,54.188848],"type":"Point"},"properties":{"osm_id":"2293371021","tag":{"amenity":"recycling","recycling:glass_bottles":"yes","recycling:paper":"no","recycling_type":"container"}},"type":"Feature"}
]
}
