{
"type": "FeatureCollection",
"features": [
	{"geometry":{"coordinates":[175.871488,-38.213738],"type":"Point"},"properties":{"name":"Recycling Centre","osm_id":"5297050863","tag":{"amenity":"recycling"}},"type":"Feature"}
]
}
