{
"type": "FeatureCollection",
"lastupdate": "2020-07-31T00:00:00Z",
"features": [
	{"geometry":{"coordinates":[175.871487,-38.213737],"type":"Point"},"properties":{"name":"Recycling Centre","osm_id":"5297050863","tag":{"amenity":"recycling"}},"type":"Feature"}
]
}
