{
"type": "FeatureCollection",
"features": [
	{"geometry":{"coordinates":[-6.203606,54.60529],"type":"Point"},"properties":{"osm_id":"1589798835","tag":{"amenity":"waste_basket"}},"type":"Feature"},
	{"geometry":{"coordinates":[-6.212434,54.620346],"type":"Point"},"properties":{"name":"Crumlin Recycling","osm_id":"4115044291","tag":{"amenity":"recycling"}},"type":"Feature"}
]
}
