{
"type": "FeatureCollection",
"features": [
	{"geometry":{"coordinates":[-6.22119,53.467992],"type":"Point"},"properties":{"osm_id":"334615369","tag":{"amenity":"recycling","recycling:glass":"yes"}},"type":"Feature"},
	{"geometry":{"coordinates":[-6.202955,53.460743],"type":"Point"},"properties":{"osm_id":"334615373","tag":{"amenity":"recycling","recycling:batteries":"yes","recycling:cans":"yes","recycling:clothes":"yes","recycling:glass":"yes","recycling:paper":"yes","recycling:scrap_metal":"no"}},"type":"Feature"},
	{"geometry":{"coordinates":[-6.22082,53.448939],"type":"Point"},"properties":{"osm_id":"388505449","tag":{"amenity":"recycling","recycling:glass":"yes"}},"type":"Feature"},
	{"geometry":{"coordinates":[-6.212837,53.46632],"type":"Point"},"properties":{"osm_id":"388508639","tag":{"amenity":"recycling","recycling:cans":"yes","recycling_type":"container"}},"type":"Feature"},
	{"geometry":{"coordinates":[-6.166529,53.439756],"type":"Point"},"properties":{"osm_id":"388561351","tag":{"amenity":"recycling","recycling:cans":"yes","recycling:glass":"yes"}},"type":"Feature"},
	{"geometry":{"coordinates":[-6.21354,53.461712],"type":"Point"},"properties":{"osm_id":"1142109671","tag":{"amenity":"waste_basket"}},"type":"Feature"},
	{"geometry":{"coordinates":[-6.22191,53.462866],"type":"Point"},"properties":{"osm_id":"5410332485","tag":{"amenity":"recycling","location":"overground","recycling:glass":"yes","recycling_type":"container"}},"type":"Feature"},
	{"geometry":{"coordinates":[-6.211788,53.454068],"type":"Point"},"properties":{"osm_id":"5564545736","tag":{"amenity":"waste_basket"}},"type":"Feature"},
	{"geometry":{"coordinates":[-6.23872,53.45325],"type":"Point"},"properties":{"osm_id":"5641967454","tag":{"amenity":"waste_basket"}},"type":"Feature"},
	{"geometry":{"coordinates":[-6.173076,53.445456],"type":"Point"},"properties":{"osm_id":"5686741940","tag":{"amenity":"waste_basket"}},"type":"Feature"},
	{"geometry":{"coordinates":[-6.176207,53.440592],"type":"Point"},"properties":{"osm_id":"5686762323","tag":{"amenity":"waste_basket"}},"type":"Feature"},
	{"geometry":{"coordinates":[-6.163073,53.449362],"type":"Point"},"properties":{"osm_id":"5686841718","tag":{"amenity":"waste_basket"}},"type":"Feature"},
	{"geometry":{"coordinates":[-6.155091,53.450589],"type":"Point"},"properties":{"osm_id":"5686878419","tag":{"amenity":"waste_basket"}},"type":"Feature"},
	{"geometry":{"coordinates":[-6.181494,53.448768],"type":"Point"},"properties":{"osm_id":"5686927453","tag":{"amenity":"waste_basket"}},"type":"Feature"},
	{"geometry":{"coordinates":[-6.183563,53.452761],"type":"Point"},"properties":{"osm_id":"5686927454","tag":{"amenity":"waste_basket"}},"type":"Feature"},
	{"geometry":{"coordinates":[-6.183355,53.452658],"type":"Point"},"properties":{"osm_id":"5686927455","tag":{"amenity":"waste_basket"}},"type":"Feature"},
	{"geometry":{"coordinates":[-6.206397,53.450958],"type":"Point"},"properties":{"osm_id":"5755563471","tag":{"amenity":"waste_basket"}},"type":"Feature"},
	{"geometry":{"coordinates":[-6.204913,53.450464],"type":"Point"},"properties":{"osm_id":"5755563472","tag":{"amenity":"waste_basket"}},"type":"Feature"},
	{"geometry":{"coordinates":[-6.204506,53.448671],"type":"Point"},"properties":{"osm_id":"5755642235","tag":{"amenity":"waste_basket"}},"type":"Feature"},
	{"geometry":{"coordinates":[-6.204365,53.448526],"type":"Point"},"properties":{"osm_id":"5755642236","tag":{"amenity":"waste_basket"}},"type":"Feature"},
	{"geometry":{"coordinates":[-6.223708,53.450625],"type":"Point"},"properties":{"osm_id":"5755688147","tag":{"amenity":"waste_basket"}},"type":"Feature"},
	{"geometry":{"coordinates":[-6.227652,53.468464],"type":"Point"},"properties":{"osm_id":"5755688148","tag":{"amenity":"waste_basket"}},"type":"Feature"},
	{"geometry":{"coordinates":[-6.222559,53.463016],"type":"Point"},"properties":{"name":"Recycling centre","osm_id":"6257763535","tag":{"amenity":"recycling","recycling:glass":"yes","recycling:plastic":"yes","recycling_type":"centre"}},"type":"Feature"},
	{"geometry":{"coordinates":[-6.15702,53.449962],"type":"Point"},"properties":{"osm_id":"7166942386","tag":{"amenity":"waste_basket"}},"type":"Feature"}
]
}
