{
"type": "FeatureCollection",
"lastupdate": "2020-08-03T00:00:00Z",
"features": [
	{"geometry":{"coordinates":[8.063949,51.391989],"type":"Point"},"properties":{"osm_id":"1679638666","tag":{"amenity":"recycling","location":"overground","recycling_type":"container"}},"type":"Feature"},
	{"geometry":{"coordinates":[8.011379,51.388907],"type":"Point"},"properties":{"osm_id":"1834663473","tag":{"amenity":"waste_basket"}},"type":"Feature"},
	{"geometry":{"coordinates":[8.069555,51.377678],"type":"Point"},"properties":{"osm_id":"2014760442","tag":{"amenity":"recycling","recycling:clothes":"yes","recycling:glass_bottles":"yes"}},"type":"Feature"},
	{"geometry":{"coordinates":[8.072569,51.385637],"type":"Point"},"properties":{"osm_id":"2014761645","tag":{"amenity":"recycling","location":"overground","recycling:glass_bottles":"yes","recycling_type":"container"}},"type":"Feature"},
	{"geometry":{"coordinates":[8.079083,51.39122],"type":"Point"},"properties":{"osm_id":"2479837994","tag":{"amenity":"recycling","location":"overground","recycling:glass_bottles":"yes","recycling_type":"container"}},"type":"Feature"},
	{"geometry":{"coordinates":[8.064571,51.393792],"type":"Point"},"properties":{"osm_id":"2639675935","tag":{"amenity":"waste_basket"}},"type":"Feature"},
	{"geometry":{"coordinates":[8.041309,51.370846],"type":"Point"},"properties":{"osm_id":"3481698085","tag":{"amenity":"waste_basket"}},"type":"Feature"},
	{"geometry":{"coordinates":[8.019513,51.382188],"type":"Point"},"properties":{"osm_id":"3919403673","tag":{"amenity":"recycling","recycling:glass":"yes","recycling_type":"container"}},"type":"Feature"},
	{"geometry":{"coordinates":[8.055299,51.395488],"type":"Point"},"properties":{"osm_id":"4188093968","tag":{"amenity":"recycling","recycling:clothes":"yes","recycling:glass_bottles":"yes","recycling_type":"container"}},"type":"Feature"},
	{"geometry":{"coordinates":[8.047397,51.390847],"type":"Point"},"properties":{"osm_id":"7315092439","tag":{"amenity":"waste_basket"}},"type":"Feature"},
	{"geometry":{"coordinates":[8.085737,51.392425],"type":"Point"},"properties":{"name":"Glasrecyclingcontainer","osm_id":"7635753485","tag":{"amenity":"recycling"}},"type":"Feature"},
	{"geometry":{"coordinates":[8.081641,51.392478],"type":"Point"},"properties":{"osm_id":"7730979420","tag":{"amenity":"waste_basket","ashtray":"no","material":"metal","support":"pole"}},"type":"Feature"}
]
}
