{
"type": "FeatureCollection",
"features": [
	{"geometry":{"coordinates":[-71.465335,42.425475],"type":"Point"},"properties":{"osm_id":"4225901190","tag":{"natural":"tree"}},"type":"Feature"},
	{"geometry":{"coordinates":[-71.464899,42.425505],"type":"Point"},"properties":{"name":"oak","osm_id":"4225901866","tag":{"natural":"tree"}},"type":"Feature"},
	{"geometry":{"coordinates":[-71.50165,42.436856],"type":"Point"},"properties":{"osm_id":"7228073671","tag":{"natural":"tree"}},"type":"Feature"},
	{"geometry":{"coordinates":[-71.501776,42.436771],"type":"Point"},"properties":{"osm_id":"7228073672","tag":{"natural":"tree"}},"type":"Feature"},
	{"geometry":{"coordinates":[-71.501727,42.43672],"type":"Point"},"properties":{"osm_id":"7228073673","tag":{"natural":"tree"}},"type":"Feature"},
	{"geometry":{"coordinates":[-71.501501,42.436758],"type":"Point"},"properties":{"osm_id":"7228073674","tag":{"natural":"tree"}},"type":"Feature"},
	{"geometry":{"coordinates":[-71.501675,42.436671],"type":"Point"},"properties":{"osm_id":"7228073675","tag":{"natural":"tree"}},"type":"Feature"},
	{"geometry":{"coordinates":[-71.501617,42.436626],"type":"Point"},"properties":{"osm_id":"7228073676","tag":{"natural":"tree"}},"type":"Feature"},
	{"geometry":{"coordinates":[-71.501477,42.436702],"type":"Point"},"properties":{"osm_id":"7228073677","tag":{"natural":"tree"}},"type":"Feature"},
	{"geometry":{"coordinates":[-71.501454,42.436649],"type":"Point"},"properties":{"osm_id":"7228073678","tag":{"natural":"tree"}},"type":"Feature"},
	{"geometry":{"coordinates":[-71.50152,42.436612],"type":"Point"},"properties":{"osm_id":"7228073679","tag":{"natural":"tree"}},"type":"Feature"},
	{"geometry":{"coordinates":[-71.501826,42.436927],"type":"Point"},"properties":{"osm_id":"7228208914","tag":{"natural":"tree"}},"type":"Feature"},
	{"geometry":{"coordinates":[-71.501744,42.437079],"type":"Point"},"properties":{"osm_id":"7228208915","tag":{"natural":"tree"}},"type":"Feature"},
	{"geometry":{"coordinates":[-71.501762,42.437073],"type":"Point"},"properties":{"osm_id":"7228208916","tag":{"natural":"tree"}},"type":"Feature"},
	{"geometry":{"coordinates":[-71.501472,42.436546],"type":"Point"},"properties":{"osm_id":"7228208917","tag":{"natural":"tree"}},"type":"Feature"},
	{"geometry":{"coordinates":[-71.501901,42.436926],"type":"Point"},"properties":{"osm_id":"7228249153","tag":{"natural":"tree"}},"type":"Feature"},
	{"geometry":{"coordinates":[-71.502076,42.436931],"type":"Point"},"properties":{"osm_id":"7228249154","tag":{"natural":"tree"}},"type":"Feature"},
	{"geometry":{"coordinates":[-71.501961,42.436797],"type":"Point"},"properties":{"osm_id":"7228249155","tag":{"natural":"tree"}},"type":"Feature"},
	{"geometry":{"coordinates":[-71.501882,42.436832],"type":"Point"},"properties":{"osm_id":"7228249156","tag":{"natural":"tree"}},"type":"Feature"},
	{"geometry":{"coordinates":[-71.501807,42.436988],"type":"Point"},"properties":{"osm_id":"7228268970","tag":{"natural":"tree"}},"type":"Feature"},
	{"geometry":{"coordinates":[-71.501815,42.437055],"type":"Point"},"properties":{"osm_id":"7228268971","tag":{"natural":"tree"}},"type":"Feature"},
	{"geometry":{"coordinates":[-71.501819,42.437038],"type":"Point"},"properties":{"osm_id":"7228268972","tag":{"natural":"tree"}},"type":"Feature"},
	{"geometry":{"coordinates":[-71.501849,42.437001],"type":"Point"},"properties":{"osm_id":"7228268973","tag":{"natural":"tree"}},"type":"Feature"},
	{"geometry":{"coordinates":[-71.501852,42.436982],"type":"Point"},"properties":{"osm_id":"7228268974","tag":{"natural":"tree"}},"type":"Feature"},
	{"geometry":{"coordinates":[-71.501884,42.437038],"type":"Point"},"properties":{"osm_id":"7228268975","tag":{"natural":"tree"}},"type":"Feature"},
	{"geometry":{"coordinates":[-71.501747,42.437024],"type":"Point"},"properties":{"osm_id":"7228268976","tag":{"natural":"tree"}},"type":"Feature"},
	{"geometry":{"coordinates":[-71.501577,42.436841],"type":"Point"},"properties":{"osm_id":"7228541897","tag":{"natural":"tree"}},"type":"Feature"},
	{"geometry":{"coordinates":[-71.510743,42.437457],"type":"Point"},"properties":{"osm_id":"7229145698","tag":{"natural":"tree"}},"type":"Feature"},
	{"geometry":{"coordinates":[-71.487314,42.431543],"type":"Point"},"properties":{"osm_id":"7237379567","tag":{"natural":"tree"}},"type":"Feature"}
]
}
