{
"type": "FeatureCollection",
"features": [
	{"geometry":{"coordinates":[22.532059,56.802429],"type":"Point"},"properties":{"name":"Upuru ozols","osm_id":"8518897824","tag":{"natural":"tree"}},"type":"Feature"}
]
}
