{
"type": "FeatureCollection",
"lastupdate": "2020-07-31T00:00:00Z",
"features": [
	{"geometry":{"coordinates":[24.385136,44.438484],"type":"Point"},"properties":{"name":"MA3 COLECT","osm_id":"6124092670","tag":{"amenity":"recycling","recycling_type":"centre"}},"type":"Feature"}
]
}
