{
"type": "FeatureCollection",
"lastupdate": "2020-08-06T00:00:00Z",
"features": [
	{"geometry":{"coordinates":[-40.340626,-20.433388],"type":"Point"},"properties":{"name":"Reciclagem Riviera","osm_id":"4048950154","tag":{"amenity":"recycling","recycling:cans":"yes","recycling:cardboard":"yes","recycling:electrical_appliances":"yes","recycling:glass":"yes","recycling:glass_bottles":"yes","recycling:paper":"yes","recycling:plastic":"yes","recycling:plastic_bottles":"yes","recycling:plastic_packaging":"yes","recycling:scrap_metal":"yes","recycling_type":"centre"}},"type":"Feature"},
	{"geometry":{"coordinates":[-40.338084,-20.430509],"type":"Point"},"properties":{"osm_id":"4049147655","tag":{"amenity":"waste_basket"}},"type":"Feature"},
	{"geometry":{"coordinates":[-40.338173,-20.430667],"type":"Point"},"properties":{"osm_id":"4049147656","tag":{"amenity":"waste_basket"}},"type":"Feature"},
	{"geometry":{"coordinates":[-40.338327,-20.430708],"type":"Point"},"properties":{"osm_id":"4049147657","tag":{"amenity":"waste_basket"}},"type":"Feature"},
	{"geometry":{"coordinates":[-40.33843,-20.430202],"type":"Point"},"properties":{"osm_id":"4049147658","tag":{"amenity":"waste_basket"}},"type":"Feature"},
	{"geometry":{"coordinates":[-40.33157,-20.448762],"type":"Point"},"properties":{"osm_id":"7192191262","tag":{"amenity":"waste_basket"}},"type":"Feature"}
]
}
