{
"type": "FeatureCollection",
"lastupdate": "2020-08-06T00:00:00Z",
"features": [
	{"geometry":{"coordinates":[-81.127166,34.956268],"type":"Point"},"properties":{"name":"York County Trash Collection and Recycling Center","osm_id":"2297156491","tag":{"amenity":"waste_basket"}},"type":"Feature"}
]
}
