{
"type": "FeatureCollection",
"features": [
	{"geometry":{"coordinates":[-81.127167,34.956269],"type":"Point"},"properties":{"name":"York County Trash Collection and Recycling Center","osm_id":"2297156491","tag":{"amenity":"waste_basket"}},"type":"Feature"}
]
}
