{
"type": "FeatureCollection",
"lastupdate": "2020-08-06T00:00:00Z",
"features": [
	{"geometry":{"coordinates":[16.584281,52.609295],"type":"Point"},"properties":{"barrier":"gate","osm_id":"3792018454"},"type":"Feature"},
	{"geometry":{"coordinates":[16.567974,52.622639],"type":"Point"},"properties":{"osm_id":"4271203230","tag":{"amenity":"waste_basket"}},"type":"Feature"},
	{"geometry":{"coordinates":[16.535265,52.61419],"type":"Point"},"properties":{"osm_id":"4430796289","tag":{"amenity":"recycling"}},"type":"Feature"},
	{"geometry":{"coordinates":[16.580027,52.604537],"type":"Point"},"properties":{"osm_id":"4430900608","tag":{"amenity":"recycling"}},"type":"Feature"},
	{"geometry":{"coordinates":[16.554062,52.627416],"type":"Point"},"properties":{"name":"Skup makulatury i palet","osm_id":"4431165997","tag":{"addr:city":"Szamotu\u0142y","addr:city:simc":"0971531","addr:postcode":"64-500","addr:street":"Powsta\u0144c\u00f3w Wielkopolskich","amenity":"recycling","recycling_type":"centre"}},"type":"Feature"},
	{"geometry":{"coordinates":[16.597429,52.601405],"type":"Point"},"properties":{"osm_id":"4431357086","tag":{"amenity":"recycling","recycling:glass":"yes","recycling:paper":"yes","recycling:plastic":"yes"}},"type":"Feature"},
	{"geometry":{"coordinates":[16.594408,52.617471],"type":"Point"},"properties":{"osm_id":"4431555479","tag":{"amenity":"recycling","recycling:glass":"yes","recycling:paper":"yes","recycling:plastic":"yes"}},"type":"Feature"},
	{"geometry":{"coordinates":[16.528063,52.608867],"type":"Point"},"properties":{"osm_id":"4432432671","tag":{"amenity":"recycling","recycling:glass":"yes","recycling:plastic":"yes"}},"type":"Feature"},
	{"geometry":{"coordinates":[16.571631,52.61221],"type":"Point"},"properties":{"osm_id":"4434779338","tag":{"amenity":"recycling"}},"type":"Feature"},
	{"geometry":{"coordinates":[16.576886,52.617568],"type":"Point"},"properties":{"osm_id":"4435748401","tag":{"addr:city":"Szamotu\u0142y","addr:city:simc":"0971531","addr:housenumber":"3","addr:postcode":"64-500","addr:street":"Szczuczy\u0144ska","amenity":"recycling"}},"type":"Feature"},
	{"geometry":{"coordinates":[16.571218,52.611064],"type":"Point"},"properties":{"osm_id":"4436266675","tag":{"amenity":"recycling"}},"type":"Feature"},
	{"geometry":{"coordinates":[16.590211,52.606118],"type":"Point"},"properties":{"osm_id":"4436509608","tag":{"amenity":"recycling"}},"type":"Feature"},
	{"geometry":{"coordinates":[16.584437,52.609468],"type":"Point"},"properties":{"osm_id":"4436509644","tag":{"amenity":"recycling"}},"type":"Feature"},
	{"geometry":{"coordinates":[16.585073,52.614379],"type":"Point"},"properties":{"osm_id":"4437789482","tag":{"amenity":"recycling"}},"type":"Feature"},
	{"geometry":{"coordinates":[16.582873,52.618876],"type":"Point"},"properties":{"osm_id":"4437789533","tag":{"amenity":"recycling"}},"type":"Feature"},
	{"geometry":{"coordinates":[16.584112,52.62092],"type":"Point"},"properties":{"osm_id":"4437823244","tag":{"amenity":"recycling"}},"type":"Feature"},
	{"geometry":{"coordinates":[16.574309,52.613042],"type":"Point"},"properties":{"osm_id":"4477011856","tag":{"amenity":"recycling"}},"type":"Feature"},
	{"geometry":{"coordinates":[16.572939,52.613679],"type":"Point"},"properties":{"osm_id":"4477011880","tag":{"amenity":"recycling"}},"type":"Feature"},
	{"geometry":{"coordinates":[16.599135,52.632648],"type":"Point"},"properties":{"osm_id":"4484177926","tag":{"amenity":"recycling"}},"type":"Feature"},
	{"geometry":{"coordinates":[16.585899,52.607795],"type":"Point"},"properties":{"osm_id":"4484686873","tag":{"amenity":"recycling"}},"type":"Feature"},
	{"geometry":{"coordinates":[16.585716,52.603537],"type":"Point"},"properties":{"osm_id":"6502104546","tag":{"amenity":"waste_basket","waste":"trash"}},"type":"Feature"},
	{"geometry":{"coordinates":[16.585281,52.603695],"type":"Point"},"properties":{"osm_id":"6502104557","tag":{"amenity":"waste_basket","waste":"trash"}},"type":"Feature"},
	{"geometry":{"coordinates":[16.585858,52.603585],"type":"Point"},"properties":{"osm_id":"6502104560","tag":{"amenity":"waste_basket","waste":"trash"}},"type":"Feature"}
]
}
