{
"type": "FeatureCollection",
"features": [
	{"geometry":{"coordinates":[-88.164587,42.119929],"type":"Point"},"properties":{"name":"Pear Tree","osm_id":"2953650411","tag":{"natural":"tree"}},"type":"Feature"},
	{"geometry":{"coordinates":[-88.168295,42.116355],"type":"Point"},"properties":{"name":"Pear Tree","osm_id":"2953650735","tag":{"natural":"tree"}},"type":"Feature"},
	{"geometry":{"coordinates":[-88.168115,42.116168],"type":"Point"},"properties":{"name":"Pear Tree","osm_id":"2953650736","tag":{"natural":"tree"}},"type":"Feature"}
]
}
