{
"type": "FeatureCollection",
"features": [
	{"geometry":{"coordinates":[4.145147,49.370768],"type":"Point"},"properties":{"name":"La Pouplie","osm_id":"6077421883","tag":{"leaf_cycle":"deciduous","leaf_type":"broadleaved","natural":"tree"}},"type":"Feature"}
]
}
