{
"type": "FeatureCollection",
"features": [
	{"geometry":{"coordinates":[6.332527,24.95738],"type":"Point"},"properties":{"name":"Tamarisk","osm_id":"7832105008","tag":{"natural":"tree"}},"type":"Feature"},
	{"geometry":{"coordinates":[6.331958,24.957535],"type":"Point"},"properties":{"name":"Tamarisk","osm_id":"7832105009","tag":{"natural":"tree"}},"type":"Feature"},
	{"geometry":{"coordinates":[6.331151,24.957472],"type":"Point"},"properties":{"name":"Tamarisk","osm_id":"7832105010","tag":{"natural":"tree"}},"type":"Feature"},
	{"geometry":{"coordinates":[6.330816,24.957392],"type":"Point"},"properties":{"name":"Tamarisk","osm_id":"7832105011","tag":{"natural":"tree"}},"type":"Feature"},
	{"geometry":{"coordinates":[6.330556,24.957798],"type":"Point"},"properties":{"name":"Tamarisk","osm_id":"7832105012","tag":{"natural":"tree"}},"type":"Feature"}
]
}
