{
"type": "FeatureCollection",
"features": [
	{"geometry":{"coordinates":[6.332528,24.95738],"type":"Point"},"properties":{"name":"Tamarisk","osm_id":"7832105008","tag":{"natural":"tree"}},"type":"Feature"},
	{"geometry":{"coordinates":[6.331959,24.957536],"type":"Point"},"properties":{"name":"Tamarisk","osm_id":"7832105009","tag":{"natural":"tree"}},"type":"Feature"},
	{"geometry":{"coordinates":[6.331152,24.957473],"type":"Point"},"properties":{"name":"Tamarisk","osm_id":"7832105010","tag":{"natural":"tree"}},"type":"Feature"},
	{"geometry":{"coordinates":[6.330816,24.957392],"type":"Point"},"properties":{"name":"Tamarisk","osm_id":"7832105011","tag":{"natural":"tree"}},"type":"Feature"},
	{"geometry":{"coordinates":[6.330556,24.957799],"type":"Point"},"properties":{"name":"Tamarisk","osm_id":"7832105012","tag":{"natural":"tree"}},"type":"Feature"}
]
}
