{
"type": "FeatureCollection",
"lastupdate": "2020-08-04T00:00:00Z",
"features": [
	{"geometry":{"coordinates":[39.236212,-6.841702],"type":"Point"},"properties":{"osm_id":"3743657694","tag":{"addr:city":"Dar es salaam","addr:district":"Ilala","addr:municipality":"Ilala","amenity":"recycling","recycling:scrap_metal":"yes"}},"type":"Feature"},
	{"geometry":{"coordinates":[39.260758,-6.850542],"type":"Point"},"properties":{"name":"Ally Alluminium","osm_id":"3840523518","tag":{"addr:city":"Dar es salaam","addr:district":"Temeke","addr:municipality":"Temeke","amenity":"recycling","recycling:glass":"yes","recycling_type":"centre"}},"type":"Feature"}
]
}
