{
"type": "FeatureCollection",
"features": [
	{"geometry":{"coordinates":[8.787082,44.759997],"type":"Point"},"properties":{"osm_id":"4070000223","tag":{"description":"magnolia","natural":"tree"}},"type":"Feature"},
	{"geometry":{"coordinates":[8.786183,44.762077],"type":"Point"},"properties":{"osm_id":"4079924283","tag":{"natural":"tree"}},"type":"Feature"},
	{"geometry":{"coordinates":[8.786217,44.762113],"type":"Point"},"properties":{"osm_id":"4079924284","tag":{"natural":"tree"}},"type":"Feature"},
	{"geometry":{"coordinates":[8.786246,44.762154],"type":"Point"},"properties":{"osm_id":"4079924285","tag":{"natural":"tree"}},"type":"Feature"},
	{"geometry":{"coordinates":[8.786273,44.762188],"type":"Point"},"properties":{"osm_id":"4079924286","tag":{"natural":"tree"}},"type":"Feature"},
	{"geometry":{"coordinates":[8.786301,44.762227],"type":"Point"},"properties":{"osm_id":"4079924287","tag":{"natural":"tree"}},"type":"Feature"},
	{"geometry":{"coordinates":[8.786329,44.762265],"type":"Point"},"properties":{"osm_id":"4079924288","tag":{"natural":"tree"}},"type":"Feature"},
	{"geometry":{"coordinates":[8.786576,44.762261],"type":"Point"},"properties":{"osm_id":"4079926108","tag":{"natural":"tree"}},"type":"Feature"},
	{"geometry":{"coordinates":[8.787126,44.762047],"type":"Point"},"properties":{"osm_id":"4079927666","tag":{"natural":"tree"}},"type":"Feature"},
	{"geometry":{"coordinates":[8.787082,44.762048],"type":"Point"},"properties":{"osm_id":"4079927667","tag":{"natural":"tree"}},"type":"Feature"},
	{"geometry":{"coordinates":[8.787032,44.762033],"type":"Point"},"properties":{"osm_id":"4079927668","tag":{"natural":"tree"}},"type":"Feature"},
	{"geometry":{"coordinates":[8.787026,44.762001],"type":"Point"},"properties":{"osm_id":"4079927669","tag":{"natural":"tree"}},"type":"Feature"},
	{"geometry":{"coordinates":[8.787052,44.76196],"type":"Point"},"properties":{"osm_id":"4079927670","tag":{"natural":"tree"}},"type":"Feature"},
	{"geometry":{"coordinates":[8.786817,44.761936],"type":"Point"},"properties":{"osm_id":"4079936010","tag":{"natural":"tree"}},"type":"Feature"},
	{"geometry":{"coordinates":[8.786824,44.761908],"type":"Point"},"properties":{"osm_id":"4079936011","tag":{"natural":"tree"}},"type":"Feature"},
	{"geometry":{"coordinates":[8.786643,44.761968],"type":"Point"},"properties":{"osm_id":"4079936012","tag":{"natural":"tree"}},"type":"Feature"},
	{"geometry":{"coordinates":[8.786683,44.761946],"type":"Point"},"properties":{"osm_id":"4079936013","tag":{"natural":"tree"}},"type":"Feature"},
	{"geometry":{"coordinates":[8.786728,44.761922],"type":"Point"},"properties":{"osm_id":"4079936014","tag":{"natural":"tree"}},"type":"Feature"},
	{"geometry":{"coordinates":[8.78642,44.761972],"type":"Point"},"properties":{"osm_id":"4079936015","tag":{"natural":"tree"}},"type":"Feature"},
	{"geometry":{"coordinates":[8.786453,44.761997],"type":"Point"},"properties":{"osm_id":"4079936016","tag":{"natural":"tree"}},"type":"Feature"},
	{"geometry":{"coordinates":[8.786482,44.762029],"type":"Point"},"properties":{"osm_id":"4079936017","tag":{"natural":"tree"}},"type":"Feature"},
	{"geometry":{"coordinates":[8.786504,44.762048],"type":"Point"},"properties":{"osm_id":"4079936018","tag":{"natural":"tree"}},"type":"Feature"},
	{"geometry":{"coordinates":[8.786539,44.762028],"type":"Point"},"properties":{"osm_id":"4079936019","tag":{"natural":"tree"}},"type":"Feature"},
	{"geometry":{"coordinates":[8.786572,44.762009],"type":"Point"},"properties":{"osm_id":"4079936020","tag":{"natural":"tree"}},"type":"Feature"},
	{"geometry":{"coordinates":[8.779046,44.729857],"type":"Point"},"properties":{"name":"Quercus crenata","osm_id":"5611243717","tag":{"denotation":"natural_monument","description":"Albero monumentale del Piemonte","leaf_cycle":"evergreen","leaf_type":"broadleaved","name:it":"Cerro-sughera","natural":"tree"}},"type":"Feature"}
]
}
