{
"type": "FeatureCollection",
"features": [
	{"geometry":{"coordinates":[8.731753,24.909371],"type":"Point"},"properties":{"osm_id":"5649463867","tag":{"natural":"tree"}},"type":"Feature"},
	{"geometry":{"coordinates":[8.771949,24.89725],"type":"Point"},"properties":{"name":"Acacia","osm_id":"7762255683","tag":{"natural":"tree"}},"type":"Feature"}
]
}
