{
"type": "FeatureCollection",
"lastupdate": "2020-08-03T00:00:00Z",
"features": [
	{"geometry":{"coordinates":[23.588097,60.834613],"type":"Point"},"properties":{"osm_id":"655246124","tag":{"amenity":"recycling","recycling:batteries":"yes","recycling:clothes":"yes","recycling:glass":"yes","recycling:paper":"yes","recycling:scrap_metal":"yes"}},"type":"Feature"},
	{"geometry":{"coordinates":[23.630497,60.817573],"type":"Point"},"properties":{"osm_id":"1142490527","tag":{"amenity":"recycling","location":"overground","recycling_type":"container"}},"type":"Feature"},
	{"geometry":{"coordinates":[23.637429,60.814168],"type":"Point"},"properties":{"osm_id":"6545048439","tag":{"amenity":"recycling","recycling:cartons":"yes","recycling:glass":"yes","recycling:scrap_metal":"yes","recycling_type":"container"}},"type":"Feature"},
	{"geometry":{"coordinates":[23.613167,60.814637],"type":"Point"},"properties":{"osm_id":"6652952274","tag":{"amenity":"recycling","recycling:clothes":"yes","recycling:glass":"yes","recycling:metal":"yes","recycling:paper":"yes","recycling_type":"container"}},"type":"Feature"},
	{"geometry":{"coordinates":[23.616747,60.810076],"type":"Point"},"properties":{"osm_id":"6778265858","tag":{"amenity":"recycling","recycling:clothes":"yes","recycling:paper":"yes","recycling_type":"container"}},"type":"Feature"}
]
}
