{
"type": "FeatureCollection",
"lastupdate": "2020-08-04T00:00:00Z",
"features": [
	{"geometry":{"coordinates":[23.560631,46.079336],"type":"Point"},"properties":{"name":"RoRec - Centru de colectare DEEE","osm_id":"2634807379","tag":{"addr:city":"Alba Iulia","addr:housenumber":"17","addr:postcode":"510066","addr:street":"Strada Tulnicului","amenity":"recycling","description":"Colectare gratuita de deseuri electrice de la populatie si de la firme, in vederea casarii.","phone":"+40 751 302 130","recycling:cans":"no","recycling:clothes":"no","recycling:electrical_items":"yes","recycling:glass":"no","recycling:paper":"no","recycling_type":"centre","website":"http://www.rorec.ro"}},"type":"Feature"},
	{"geometry":{"coordinates":[23.571295,46.084914],"type":"Point"},"properties":{"osm_id":"2679595232","tag":{"amenity":"recycling","recycling_type":"container"}},"type":"Feature"}
]
}
