{
"type": "FeatureCollection",
"features": [
	{"geometry":{"coordinates":[15.140533,60.558328],"type":"Point"},"properties":{"osm_id":"2674760594","tag":{"amenity":"recycling","recycling:batteries":"yes","recycling:cans":"yes","recycling:clothes":"yes","recycling:glass_bottles":"yes","recycling:paper":"yes","recycling:plastic":"no","recycling:plastic_packaging":"yes","recycling_type":"container"}},"type":"Feature"},
	{"geometry":{"coordinates":[15.130338,60.561036],"type":"Point"},"properties":{"osm_id":"7856124649","tag":{"amenity":"recycling","location":"overground","recycling_type":"container"}},"type":"Feature"}
]
}
