{
"type": "FeatureCollection",
"features": [
	{"geometry":{"coordinates":[15.194965,60.126701],"type":"Point"},"properties":{"osm_id":"473141835","tag":{"amenity":"recycling","recycling_type":"container"}},"type":"Feature"},
	{"geometry":{"coordinates":[15.198189,60.137544],"type":"Point"},"properties":{"osm_id":"492880485","tag":{"amenity":"recycling","recycling:batteries":"yes","recycling:glass_bottles":"yes","recycling:paper":"yes","recycling:scrap_metal":"yes","recycling_type":"container"}},"type":"Feature"},
	{"geometry":{"coordinates":[15.192418,60.151697],"type":"Point"},"properties":{"osm_id":"846720891","tag":{"amenity":"recycling","recycling_type":"container"}},"type":"Feature"},
	{"geometry":{"coordinates":[15.178688,60.148904],"type":"Point"},"properties":{"osm_id":"1272424784","tag":{"amenity":"waste_basket"}},"type":"Feature"},
	{"geometry":{"coordinates":[15.178718,60.148947],"type":"Point"},"properties":{"name":"Hundlatrin","osm_id":"1272424789","tag":{"amenity":"waste_basket"}},"type":"Feature"},
	{"geometry":{"coordinates":[15.178986,60.150115],"type":"Point"},"properties":{"osm_id":"1272424795","tag":{"amenity":"waste_basket"}},"type":"Feature"},
	{"geometry":{"coordinates":[15.155356,60.13626],"type":"Point"},"properties":{"osm_id":"1316530519","tag":{"amenity":"recycling","recycling_type":"container"}},"type":"Feature"},
	{"geometry":{"coordinates":[15.181421,60.140661],"type":"Point"},"properties":{"osm_id":"6142286302","tag":{"amenity":"recycling","recycling:batteries":"yes","recycling:cans":"yes","recycling:cardboard":"yes","recycling:glass_bottles":"yes","recycling:magazines":"yes","recycling:newspaper":"yes","recycling:paper":"yes","recycling:paper_packaging":"yes","recycling:plastic":"yes","recycling:plastic_bottles":"yes","recycling:plastic_packaging":"yes","recycling_type":"container"}},"type":"Feature"}
]
}
