{
"type": "FeatureCollection",
"features": [
	{"geometry":{"coordinates":[15.151734,50.727478],"type":"Point"},"properties":{"osm_id":"4226425668","tag":{"amenity":"waste_basket"}},"type":"Feature"},
	{"geometry":{"coordinates":[15.162658,50.736274],"type":"Point"},"properties":{"osm_id":"4712383483","tag":{"amenity":"recycling","recycling_type":"container"}},"type":"Feature"},
	{"geometry":{"coordinates":[15.195192,50.697702],"type":"Point"},"properties":{"osm_id":"4911443895","tag":{"amenity":"recycling","recycling_type":"container"}},"type":"Feature"},
	{"geometry":{"coordinates":[15.166069,50.720925],"type":"Point"},"properties":{"osm_id":"4912015865","tag":{"amenity":"recycling","recycling_type":"container"}},"type":"Feature"},
	{"geometry":{"coordinates":[15.175654,50.723548],"type":"Point"},"properties":{"osm_id":"4912510021","tag":{"amenity":"recycling","recycling_type":"container"}},"type":"Feature"},
	{"geometry":{"coordinates":[15.174148,50.72437],"type":"Point"},"properties":{"osm_id":"4912876284","tag":{"amenity":"recycling","recycling_type":"container"}},"type":"Feature"},
	{"geometry":{"coordinates":[15.162262,50.723138],"type":"Point"},"properties":{"osm_id":"4914423179","tag":{"amenity":"recycling","recycling_type":"container"}},"type":"Feature"},
	{"geometry":{"coordinates":[15.169379,50.72343],"type":"Point"},"properties":{"osm_id":"4914458636","tag":{"amenity":"recycling","recycling_type":"container"}},"type":"Feature"},
	{"geometry":{"coordinates":[15.16162,50.723472],"type":"Point"},"properties":{"osm_id":"4914465260","tag":{"amenity":"recycling","recycling_type":"container"}},"type":"Feature"},
	{"geometry":{"coordinates":[15.178281,50.72383],"type":"Point"},"properties":{"osm_id":"4914493050","tag":{"amenity":"recycling","recycling_type":"container"}},"type":"Feature"},
	{"geometry":{"coordinates":[15.181742,50.729509],"type":"Point"},"properties":{"osm_id":"4915661045","tag":{"amenity":"recycling","recycling:beverage_cartons":"yes","recycling:glass":"yes","recycling:paper":"yes","recycling:plastic":"yes","recycling_type":"container"}},"type":"Feature"},
	{"geometry":{"coordinates":[15.12637,50.705393],"type":"Point"},"properties":{"osm_id":"5542788217","tag":{"amenity":"recycling","recycling_type":"container"}},"type":"Feature"},
	{"geometry":{"coordinates":[15.17437,50.723199],"type":"Point"},"properties":{"osm_id":"7238967232","tag":{"amenity":"recycling","recycling:glass":"yes","recycling:paper":"yes","recycling:plastic":"yes","recycling_type":"container"}},"type":"Feature"},
	{"geometry":{"coordinates":[15.158248,50.727468],"type":"Point"},"properties":{"osm_id":"7402359523","tag":{"amenity":"recycling","recycling:glass":"yes","recycling:paper":"yes","recycling:plastic":"yes","recycling_type":"container"}},"type":"Feature"},
	{"geometry":{"coordinates":[15.185201,50.681753],"type":"Point"},"properties":{"osm_id":"8284027500","tag":{"amenity":"recycling","recycling:glass":"yes","recycling:paper":"yes","recycling:plastic":"yes","recycling_type":"container"}},"type":"Feature"},
	{"geometry":{"coordinates":[15.185711,50.702966],"type":"Point"},"properties":{"osm_id":"8443548819","tag":{"amenity":"recycling","location":"underground","recycling:glass":"yes","recycling:paper":"yes","recycling:plastic":"yes","recycling_type":"container"}},"type":"Feature"},
	{"geometry":{"coordinates":[15.185664,50.707754],"type":"Point"},"properties":{"osm_id":"8443548842","tag":{"amenity":"recycling","recycling:clothes":"yes","recycling:glass":"yes","recycling:paper":"yes","recycling:plastic":"yes","recycling_type":"container"}},"type":"Feature"},
	{"geometry":{"coordinates":[15.134604,50.707398],"type":"Point"},"properties":{"osm_id":"8443548855","tag":{"amenity":"recycling","recycling:glass":"yes","recycling:plastic":"yes","recycling_type":"container"}},"type":"Feature"},
	{"geometry":{"coordinates":[15.186123,50.726067],"type":"Point"},"properties":{"osm_id":"9017517800","tag":{"amenity":"recycling","recycling_type":"container"}},"type":"Feature"}
]
}
