{
"type": "FeatureCollection",
"features": [
	{"geometry":{"coordinates":[15.169574,48.609765],"type":"Point"},"properties":{"name":"Altstoffsammelzentrum","osm_id":"457150026","tag":{"amenity":"recycling","recycling_type":"centre"}},"type":"Feature"},
	{"geometry":{"coordinates":[15.199235,48.617411],"type":"Point"},"properties":{"osm_id":"2419966770","tag":{"amenity":"waste_basket"}},"type":"Feature"},
	{"geometry":{"coordinates":[15.198968,48.617501],"type":"Point"},"properties":{"osm_id":"2419966774","tag":{"amenity":"waste_basket"}},"type":"Feature"},
	{"geometry":{"coordinates":[15.200159,48.617258],"type":"Point"},"properties":{"osm_id":"2419966815","tag":{"amenity":"waste_basket"}},"type":"Feature"},
	{"geometry":{"coordinates":[15.199948,48.617158],"type":"Point"},"properties":{"osm_id":"2419966820","tag":{"amenity":"waste_basket"}},"type":"Feature"},
	{"geometry":{"coordinates":[15.199566,48.61726],"type":"Point"},"properties":{"osm_id":"2419966825","tag":{"amenity":"waste_basket"}},"type":"Feature"},
	{"geometry":{"coordinates":[15.200274,48.617125],"type":"Point"},"properties":{"osm_id":"2419966827","tag":{"amenity":"waste_basket"}},"type":"Feature"},
	{"geometry":{"coordinates":[15.169328,48.607836],"type":"Point"},"properties":{"osm_id":"2429951242","tag":{"amenity":"waste_basket"}},"type":"Feature"},
	{"geometry":{"coordinates":[15.180513,48.613995],"type":"Point"},"properties":{"osm_id":"2429957210","tag":{"amenity":"recycling","recycling:cans":"yes","recycling:glass_bottles":"yes"}},"type":"Feature"},
	{"geometry":{"coordinates":[15.167209,48.604633],"type":"Point"},"properties":{"osm_id":"5654076019","tag":{"amenity":"waste_basket"}},"type":"Feature"}
]
}
