{
"type": "FeatureCollection",
"lastupdate": "2020-08-02T00:00:00Z",
"features": [
	{"geometry":{"coordinates":[15.169573,48.609764],"type":"Point"},"properties":{"name":"Altstoffsammelzentrum","osm_id":"457150026","tag":{"amenity":"recycling","recycling_type":"centre"}},"type":"Feature"},
	{"geometry":{"coordinates":[15.199234,48.617411],"type":"Point"},"properties":{"osm_id":"2419966770","tag":{"amenity":"waste_basket"}},"type":"Feature"},
	{"geometry":{"coordinates":[15.198967,48.617501],"type":"Point"},"properties":{"osm_id":"2419966774","tag":{"amenity":"waste_basket"}},"type":"Feature"},
	{"geometry":{"coordinates":[15.200158,48.617258],"type":"Point"},"properties":{"osm_id":"2419966815","tag":{"amenity":"waste_basket"}},"type":"Feature"},
	{"geometry":{"coordinates":[15.199948,48.617157],"type":"Point"},"properties":{"osm_id":"2419966820","tag":{"amenity":"waste_basket"}},"type":"Feature"},
	{"geometry":{"coordinates":[15.199565,48.61726],"type":"Point"},"properties":{"osm_id":"2419966825","tag":{"amenity":"waste_basket"}},"type":"Feature"},
	{"geometry":{"coordinates":[15.200274,48.617125],"type":"Point"},"properties":{"osm_id":"2419966827","tag":{"amenity":"waste_basket"}},"type":"Feature"},
	{"geometry":{"coordinates":[15.169327,48.607836],"type":"Point"},"properties":{"osm_id":"2429951242","tag":{"amenity":"waste_basket"}},"type":"Feature"},
	{"geometry":{"coordinates":[15.180512,48.613995],"type":"Point"},"properties":{"osm_id":"2429957210","tag":{"amenity":"recycling","recycling:cans":"yes","recycling:glass_bottles":"yes"}},"type":"Feature"},
	{"geometry":{"coordinates":[15.167208,48.604632],"type":"Point"},"properties":{"osm_id":"5654076019","tag":{"amenity":"waste_basket"}},"type":"Feature"}
]
}
