{
"type": "FeatureCollection",
"features": [
	{"geometry":{"coordinates":[15.199363,45.804151],"type":"Point"},"properties":{"name":"Komunala Novo mesto","osm_id":"4763862228","tag":{"amenity":"recycling","recycling_type":"centre"}},"type":"Feature"},
	{"geometry":{"coordinates":[15.16735,45.803435],"type":"Point"},"properties":{"osm_id":"7810913283","tag":{"amenity":"waste_basket"}},"type":"Feature"}
]
}
