{
"type": "FeatureCollection",
"lastupdate": "2020-08-06T00:00:00Z",
"features": [
	{"geometry":{"coordinates":[15.199363,45.804151],"type":"Point"},"properties":{"name":"Komunala Novo mesto","osm_id":"4763862228","tag":{"amenity":"recycling","recycling_type":"centre"}},"type":"Feature"}
]
}
