{
"type": "FeatureCollection",
"features": [
	{"geometry":{"coordinates":[-95.984175,36.172007],"type":"Point"},"properties":{"osm_id":"2138422385","tag":{"amenity":"waste_basket"}},"type":"Feature"},
	{"geometry":{"coordinates":[-95.98939,36.153075],"type":"Point"},"properties":{"osm_id":"3144650180","tag":{"amenity":"waste_basket"}},"type":"Feature"},
	{"geometry":{"coordinates":[-95.989767,36.15282],"type":"Point"},"properties":{"osm_id":"3144650875","tag":{"amenity":"waste_basket"}},"type":"Feature"},
	{"geometry":{"coordinates":[-95.98989,36.153581],"type":"Point"},"properties":{"osm_id":"4380650369","tag":{"amenity":"waste_basket"}},"type":"Feature"},
	{"geometry":{"coordinates":[-95.984094,36.110118],"type":"Point"},"properties":{"name":"Crossing the Prairie","osm_id":"4680259792","tag":{"amenity":"waste_basket"}},"type":"Feature"}
]
}
