{
"type": "FeatureCollection",
"lastupdate": "2020-08-04T00:00:00Z",
"features": [
	{"geometry":{"coordinates":[-95.984174,36.172006],"type":"Point"},"properties":{"osm_id":"2138422385","tag":{"amenity":"waste_basket"}},"type":"Feature"},
	{"geometry":{"coordinates":[-95.989389,36.153074],"type":"Point"},"properties":{"osm_id":"3144650180","tag":{"amenity":"waste_basket"}},"type":"Feature"},
	{"geometry":{"coordinates":[-95.989767,36.152819],"type":"Point"},"properties":{"osm_id":"3144650875","tag":{"amenity":"waste_basket"}},"type":"Feature"},
	{"geometry":{"coordinates":[-95.98989,36.15358],"type":"Point"},"properties":{"osm_id":"4380650369","tag":{"amenity":"waste_basket"}},"type":"Feature"},
	{"geometry":{"coordinates":[-95.984094,36.110117],"type":"Point"},"properties":{"name":"Crossing the Prairie","osm_id":"4680259792","tag":{"amenity":"waste_basket"}},"type":"Feature"}
]
}
