{
"type": "FeatureCollection",
"features": [
	{"geometry":{"coordinates":[10.974337,48.587104],"type":"Point"},"properties":{"name":"Marienbuche","osm_id":"967822269","tag":{"genus":"Fagus","genus:de":"Buche","leaf_cycle":"deciduous","leaf_type":"broadleaved","natural":"tree"}},"type":"Feature"},
	{"geometry":{"coordinates":[10.964488,48.617193],"type":"Point"},"properties":{"osm_id":"3256479177","tag":{"natural":"tree"}},"type":"Feature"},
	{"geometry":{"coordinates":[10.975089,48.61735],"type":"Point"},"properties":{"osm_id":"3256479183","tag":{"natural":"tree"}},"type":"Feature"},
	{"geometry":{"coordinates":[10.965371,48.617612],"type":"Point"},"properties":{"osm_id":"3256479192","tag":{"natural":"tree"}},"type":"Feature"},
	{"geometry":{"coordinates":[10.973978,48.617743],"type":"Point"},"properties":{"osm_id":"3256479198","tag":{"natural":"tree"}},"type":"Feature"},
	{"geometry":{"coordinates":[10.966407,48.617853],"type":"Point"},"properties":{"osm_id":"3256479210","tag":{"natural":"tree"}},"type":"Feature"},
	{"geometry":{"coordinates":[10.967433,48.617953],"type":"Point"},"properties":{"osm_id":"3256479216","tag":{"natural":"tree"}},"type":"Feature"},
	{"geometry":{"coordinates":[10.973163,48.617972],"type":"Point"},"properties":{"osm_id":"3256479219","tag":{"natural":"tree"}},"type":"Feature"},
	{"geometry":{"coordinates":[10.969491,48.618026],"type":"Point"},"properties":{"osm_id":"3256479229","tag":{"natural":"tree"}},"type":"Feature"},
	{"geometry":{"coordinates":[10.970438,48.618056],"type":"Point"},"properties":{"osm_id":"3256479232","tag":{"natural":"tree"}},"type":"Feature"},
	{"geometry":{"coordinates":[10.970676,48.618064],"type":"Point"},"properties":{"osm_id":"3256479235","tag":{"natural":"tree"}},"type":"Feature"},
	{"geometry":{"coordinates":[10.971202,48.618071],"type":"Point"},"properties":{"osm_id":"3256479237","tag":{"natural":"tree"}},"type":"Feature"},
	{"geometry":{"coordinates":[10.970967,48.618078],"type":"Point"},"properties":{"osm_id":"3256479239","tag":{"natural":"tree"}},"type":"Feature"},
	{"geometry":{"coordinates":[10.971461,48.618078],"type":"Point"},"properties":{"osm_id":"3256479240","tag":{"natural":"tree"}},"type":"Feature"},
	{"geometry":{"coordinates":[10.971691,48.618087],"type":"Point"},"properties":{"osm_id":"3256479241","tag":{"natural":"tree"}},"type":"Feature"},
	{"geometry":{"coordinates":[10.971914,48.618092],"type":"Point"},"properties":{"osm_id":"3256479243","tag":{"natural":"tree"}},"type":"Feature"}
]
}
