{
"type": "FeatureCollection",
"features": [
	{"geometry":{"coordinates":[10.974338,48.587104],"type":"Point"},"properties":{"name":"Marienbuche","osm_id":"967822269","tag":{"genus":"Fagus","genus:de":"Buche","leaf_cycle":"deciduous","leaf_type":"broadleaved","natural":"tree"}},"type":"Feature"},
	{"geometry":{"coordinates":[10.964489,48.617194],"type":"Point"},"properties":{"osm_id":"3256479177","tag":{"natural":"tree"}},"type":"Feature"},
	{"geometry":{"coordinates":[10.97509,48.61735],"type":"Point"},"properties":{"osm_id":"3256479183","tag":{"natural":"tree"}},"type":"Feature"},
	{"geometry":{"coordinates":[10.965372,48.617612],"type":"Point"},"properties":{"osm_id":"3256479192","tag":{"natural":"tree"}},"type":"Feature"},
	{"geometry":{"coordinates":[10.973979,48.617743],"type":"Point"},"properties":{"osm_id":"3256479198","tag":{"natural":"tree"}},"type":"Feature"},
	{"geometry":{"coordinates":[10.966408,48.617854],"type":"Point"},"properties":{"osm_id":"3256479210","tag":{"natural":"tree"}},"type":"Feature"},
	{"geometry":{"coordinates":[10.967434,48.617954],"type":"Point"},"properties":{"osm_id":"3256479216","tag":{"natural":"tree"}},"type":"Feature"},
	{"geometry":{"coordinates":[10.973163,48.617972],"type":"Point"},"properties":{"osm_id":"3256479219","tag":{"natural":"tree"}},"type":"Feature"},
	{"geometry":{"coordinates":[10.969492,48.618027],"type":"Point"},"properties":{"osm_id":"3256479229","tag":{"natural":"tree"}},"type":"Feature"},
	{"geometry":{"coordinates":[10.970439,48.618057],"type":"Point"},"properties":{"osm_id":"3256479232","tag":{"natural":"tree"}},"type":"Feature"},
	{"geometry":{"coordinates":[10.970676,48.618065],"type":"Point"},"properties":{"osm_id":"3256479235","tag":{"natural":"tree"}},"type":"Feature"},
	{"geometry":{"coordinates":[10.971203,48.618072],"type":"Point"},"properties":{"osm_id":"3256479237","tag":{"natural":"tree"}},"type":"Feature"},
	{"geometry":{"coordinates":[10.970967,48.618078],"type":"Point"},"properties":{"osm_id":"3256479239","tag":{"natural":"tree"}},"type":"Feature"},
	{"geometry":{"coordinates":[10.971461,48.618078],"type":"Point"},"properties":{"osm_id":"3256479240","tag":{"natural":"tree"}},"type":"Feature"},
	{"geometry":{"coordinates":[10.971691,48.618088],"type":"Point"},"properties":{"osm_id":"3256479241","tag":{"natural":"tree"}},"type":"Feature"},
	{"geometry":{"coordinates":[10.971914,48.618092],"type":"Point"},"properties":{"osm_id":"3256479243","tag":{"natural":"tree"}},"type":"Feature"}
]
}
