{
"type": "FeatureCollection",
"features": [
	{"geometry":{"coordinates":[-25.310419,16.961254],"type":"Point"},"properties":{"osm_id":"5840236347","tag":{"natural":"tree"}},"type":"Feature"},
	{"geometry":{"coordinates":[-25.310363,16.960578],"type":"Point"},"properties":{"osm_id":"5840236348","tag":{"natural":"tree"}},"type":"Feature"},
	{"geometry":{"coordinates":[-25.31106,16.95696],"type":"Point"},"properties":{"osm_id":"5840372234","tag":{"natural":"tree"}},"type":"Feature"},
	{"geometry":{"coordinates":[-25.310413,16.955915],"type":"Point"},"properties":{"osm_id":"5840372235","tag":{"natural":"tree"}},"type":"Feature"},
	{"geometry":{"coordinates":[-25.309308,16.954194],"type":"Point"},"properties":{"osm_id":"5849461391","tag":{"natural":"tree"}},"type":"Feature"},
	{"geometry":{"coordinates":[-25.310336,16.956132],"type":"Point"},"properties":{"osm_id":"5849465397","tag":{"natural":"tree"}},"type":"Feature"},
	{"geometry":{"coordinates":[-25.310782,16.956838],"type":"Point"},"properties":{"osm_id":"5849465398","tag":{"natural":"tree"}},"type":"Feature"},
	{"geometry":{"coordinates":[-25.310527,16.956464],"type":"Point"},"properties":{"osm_id":"5849465399","tag":{"natural":"tree"}},"type":"Feature"},
	{"geometry":{"coordinates":[-25.310049,16.95583],"type":"Point"},"properties":{"name":"palmeira","osm_id":"5849465400","tag":{"natural":"tree"}},"type":"Feature"},
	{"geometry":{"coordinates":[-25.310401,16.957629],"type":"Point"},"properties":{"name":"palmeira","osm_id":"6791309774","tag":{"natural":"tree"}},"type":"Feature"},
	{"geometry":{"coordinates":[-25.310432,16.957536],"type":"Point"},"properties":{"name":"palmeira","osm_id":"6791309775","tag":{"natural":"tree"}},"type":"Feature"},
	{"geometry":{"coordinates":[-25.310432,16.957437],"type":"Point"},"properties":{"name":"palmeira","osm_id":"6791309776","tag":{"natural":"tree"}},"type":"Feature"},
	{"geometry":{"coordinates":[-25.310458,16.957357],"type":"Point"},"properties":{"name":"palmeira","osm_id":"6791309777","tag":{"natural":"tree"}},"type":"Feature"},
	{"geometry":{"coordinates":[-25.310209,16.957905],"type":"Point"},"properties":{"osm_id":"7917538353","tag":{"natural":"tree"}},"type":"Feature"},
	{"geometry":{"coordinates":[-25.310331,16.957825],"type":"Point"},"properties":{"osm_id":"7917538354","tag":{"natural":"tree"}},"type":"Feature"},
	{"geometry":{"coordinates":[-25.309714,16.957527],"type":"Point"},"properties":{"osm_id":"7917538355","tag":{"natural":"tree"}},"type":"Feature"},
	{"geometry":{"coordinates":[-25.310128,16.957441],"type":"Point"},"properties":{"osm_id":"7917538356","tag":{"natural":"tree"}},"type":"Feature"},
	{"geometry":{"coordinates":[-25.309441,16.957398],"type":"Point"},"properties":{"osm_id":"7917538357","tag":{"natural":"tree"}},"type":"Feature"},
	{"geometry":{"coordinates":[-25.309562,16.95784],"type":"Point"},"properties":{"osm_id":"7917538358","tag":{"natural":"tree"}},"type":"Feature"},
	{"geometry":{"coordinates":[-25.309959,16.957175],"type":"Point"},"properties":{"osm_id":"7917538359","tag":{"natural":"tree"}},"type":"Feature"},
	{"geometry":{"coordinates":[-25.302002,16.963303],"type":"Point"},"properties":{"osm_id":"7917595419","tag":{"natural":"tree"}},"type":"Feature"},
	{"geometry":{"coordinates":[-25.301926,16.9621],"type":"Point"},"properties":{"osm_id":"7917618912","tag":{"natural":"tree"}},"type":"Feature"}
]
}
