{
"type": "FeatureCollection",
"lastupdate": "2020-08-05T00:00:00Z",
"features": [
	{"geometry":{"coordinates":[10.343578,60.225453],"type":"Point"},"properties":{"name":"Trollmyra gjenvinningsstasjon","osm_id":"5555203043","tag":{"amenity":"recycling","recycling:asbestos":"yes","recycling:batteries":"yes","recycling:boats":"yes","recycling:clothes":"yes","recycling:electrical_items":"yes","recycling:garden_waste":"yes","recycling:glass":"yes","recycling:glass_bottles":"yes","recycling:hazardous_waste":"yes","recycling:metal":"yes","recycling:organic":"yes","recycling:paper":"yes","recycling:plasterboard":"yes","recycling:plastic_packaging":"yes","recycling:rubble":"yes","recycling:scrap_metal":"yes","recycling:second_hand":"yes","recycling:tyres":"yes","recycling:waste":"yes","recycling:wood":"yes","recycling_type":"centre","ref:sortere":"1476"}},"type":"Feature"},
	{"geometry":{"coordinates":[10.344528,60.226939],"type":"Point"},"properties":{"osm_id":"6195520918","tag":{"amenity":"recycling","description":"Trollmyra gjenvinningsstasjon","recycling:clothes":"yes","recycling:garden_waste":"yes","recycling:glass_bottles":"yes","recycling_type":"container","ref:sortere":"14900"}},"type":"Feature"},
	{"geometry":{"coordinates":[10.362655,60.227284],"type":"Point"},"properties":{"name":"Fretex","osm_id":"6573242853","tag":{"amenity":"recycling","image":"https://images.mapillary.com/2jgozSw4NP-kuP0G_D5IVA/thumb-2048.jpg","mapillary":"https://www.mapillary.com/map/im/2jgozSw4NP-kuP0G_D5IVA","recycling:clothes":"yes","recycling:shoes":"yes","recycling_type":"container"}},"type":"Feature"},
	{"geometry":{"coordinates":[10.337682,60.200285],"type":"Point"},"properties":{"osm_id":"6576517020","tag":{"amenity":"waste_basket","image":"https://images.mapillary.com/_BmirP0f3bE5qDZiWaSAdw/thumb-2048.jpg","mapillary":"https://www.mapillary.com/map/im/_BmirP0f3bE5qDZiWaSAdw"}},"type":"Feature"}
]
}
