{
"type": "FeatureCollection",
"lastupdate": "2020-08-01T00:00:00Z",
"features": [
	{"geometry":{"coordinates":[10.306666,48.366356],"type":"Point"},"properties":{"osm_id":"283933172","tag":{"amenity":"recycling","recycling:clothes":"yes","recycling:glass":"yes","recycling:shoes":"yes"}},"type":"Feature"},
	{"geometry":{"coordinates":[10.352876,48.364859],"type":"Point"},"properties":{"osm_id":"809896174","tag":{"amenity":"recycling","recycling:cans":"yes","recycling:glass":"yes","recycling:paper":"yes","recycling:scrap_metal":"yes"}},"type":"Feature"},
	{"geometry":{"coordinates":[10.31154,48.368778],"type":"Point"},"properties":{"osm_id":"1640210278","tag":{"amenity":"recycling","recycling:clothes":"yes","recycling:glass":"yes"}},"type":"Feature"},
	{"geometry":{"coordinates":[10.315842,48.369071],"type":"Point"},"properties":{"osm_id":"1640210280","tag":{"amenity":"recycling","location":"overground","operator":"Aktion Hoffnung","recycling:clothes":"yes","recycling_type":"container"}},"type":"Feature"},
	{"geometry":{"coordinates":[10.312764,48.372633],"type":"Point"},"properties":{"osm_id":"1640304217","tag":{"amenity":"recycling","recycling:clothes":"yes"}},"type":"Feature"},
	{"geometry":{"coordinates":[10.309279,48.37773],"type":"Point"},"properties":{"osm_id":"1640304253","tag":{"amenity":"recycling","recycling:clothes":"yes","recycling:glass":"yes"}},"type":"Feature"},
	{"geometry":{"coordinates":[10.304894,48.369809],"type":"Point"},"properties":{"osm_id":"1640442803","tag":{"amenity":"recycling","location":"overground","recycling:glass":"yes","recycling_type":"container"}},"type":"Feature"},
	{"geometry":{"coordinates":[10.306414,48.371344],"type":"Point"},"properties":{"osm_id":"1640442847","tag":{"amenity":"recycling","recycling:clothes":"yes"}},"type":"Feature"},
	{"geometry":{"coordinates":[10.300429,48.369859],"type":"Point"},"properties":{"osm_id":"1640466907","tag":{"amenity":"recycling","recycling:clothes":"yes"}},"type":"Feature"},
	{"geometry":{"coordinates":[10.303099,48.389405],"type":"Point"},"properties":{"osm_id":"1641723435","tag":{"amenity":"recycling","recycling:cans":"yes","recycling:clothes":"yes","recycling:glass":"yes","recycling_type":"container"}},"type":"Feature"},
	{"geometry":{"coordinates":[10.309425,48.389351],"type":"Point"},"properties":{"osm_id":"4959711363","tag":{"amenity":"recycling","recycling:glass":"yes","recycling_type":"container"}},"type":"Feature"},
	{"geometry":{"coordinates":[10.309426,48.389319],"type":"Point"},"properties":{"osm_id":"4959711364","tag":{"amenity":"recycling","operator":"Aktion Hoffnung","recycling:clothes":"yes","recycling:shoes":"yes","recycling_type":"container"}},"type":"Feature"},
	{"geometry":{"coordinates":[10.297514,48.347493],"type":"Point"},"properties":{"osm_id":"7493950686","tag":{"amenity":"recycling","recycling:cans":"yes","recycling:glass_bottles":"yes","recycling_type":"container"}},"type":"Feature"}
]
}
