{
"type": "FeatureCollection",
"lastupdate": "2020-08-06T00:00:00Z",
"features": [
	{"geometry":{"coordinates":[10.337418,43.864953],"type":"Point"},"properties":{"name":"Ersu Ambiente, Isola Ecologica","osm_id":"1542884641","tag":{"amenity":"recycling","recycling_type":"container"}},"type":"Feature"},
	{"geometry":{"coordinates":[10.297536,43.866126],"type":"Point"},"properties":{"osm_id":"1974803469","tag":{"amenity":"recycling"}},"type":"Feature"},
	{"geometry":{"coordinates":[10.36041,43.849474],"type":"Point"},"properties":{"osm_id":"2162373348","tag":{"amenity":"recycling","recycling:glass":"yes","recycling:plastic":"yes","recycling_type":"container"}},"type":"Feature"}
]
}
