{
"type": "FeatureCollection",
"features": [
	{"geometry":{"coordinates":[10.337418,43.864953],"type":"Point"},"properties":{"name":"Ersu Ambiente, Isola Ecologica","osm_id":"1542884641","tag":{"amenity":"recycling","recycling_type":"container"}},"type":"Feature"},
	{"geometry":{"coordinates":[10.36041,43.849474],"type":"Point"},"properties":{"osm_id":"2162373348","tag":{"amenity":"recycling","recycling:glass":"yes","recycling:plastic":"yes","recycling_type":"container"}},"type":"Feature"}
]
}
