{
"type": "FeatureCollection",
"features": [
	{"geometry":{"coordinates":[-3.930827,51.021102],"type":"Point"},"properties":{"name":"Lerwell Beach Tree","osm_id":"4928769493","tag":{"natural":"tree"}},"type":"Feature"}
]
}
