{
"type": "FeatureCollection",
"features": [
	{"geometry":{"coordinates":[-3.95001,42.832877],"type":"Point"},"properties":{"name":"Roble Albar","osm_id":"3339870915","tag":{"genus":"Quercus","natural":"tree"}},"type":"Feature"}
]
}
