{
"type": "FeatureCollection",
"lastupdate": "2020-08-05T00:00:00Z",
"features": [
	{"geometry":{"coordinates":[132.78848,34.446128],"type":"Point"},"properties":{"osm_id":"2786958346","tag":{"amenity":"waste_basket","waste":"trash"}},"type":"Feature"},
	{"geometry":{"coordinates":[132.788245,34.44619],"type":"Point"},"properties":{"osm_id":"2786958368","tag":{"amenity":"recycling","recycling:cans":"yes","recycling:plastic_bottles":"yes"}},"type":"Feature"},
	{"geometry":{"coordinates":[132.788266,34.446185],"type":"Point"},"properties":{"osm_id":"2786958372","tag":{"amenity":"recycling","recycling:cans":"yes","recycling:plastic_bottles":"yes"}},"type":"Feature"},
	{"geometry":{"coordinates":[132.788219,34.446386],"type":"Point"},"properties":{"osm_id":"2786958381","tag":{"amenity":"recycling","recycling:cans":"yes","recycling:plastic_bottles":"yes"}},"type":"Feature"},
	{"geometry":{"coordinates":[132.788139,34.446367],"type":"Point"},"properties":{"osm_id":"2786958385","tag":{"amenity":"recycling","recycling:paper":"yes"}},"type":"Feature"},
	{"geometry":{"coordinates":[132.788131,34.446369],"type":"Point"},"properties":{"osm_id":"2786958389","tag":{"amenity":"recycling","recycling:cans":"yes","recycling:plastic_bottles":"yes"}},"type":"Feature"},
	{"geometry":{"coordinates":[132.788124,34.446371],"type":"Point"},"properties":{"osm_id":"2786958393","tag":{"amenity":"recycling","recycling:cans":"yes","recycling:plastic_bottles":"yes"}},"type":"Feature"},
	{"geometry":{"coordinates":[132.788116,34.446373],"type":"Point"},"properties":{"osm_id":"2786958397","tag":{"amenity":"waste_basket","waste":"trash"}},"type":"Feature"},
	{"geometry":{"coordinates":[132.78791,34.446424],"type":"Point"},"properties":{"osm_id":"2786958414","tag":{"amenity":"recycling","recycling:cans":"yes","recycling:plastic_bottles":"yes"}},"type":"Feature"},
	{"geometry":{"coordinates":[132.788474,34.44613],"type":"Point"},"properties":{"osm_id":"2790412221","tag":{"amenity":"recycling","recycling:paper":"yes"}},"type":"Feature"},
	{"geometry":{"coordinates":[132.788487,34.446127],"type":"Point"},"properties":{"osm_id":"2790412225","tag":{"amenity":"recycling","recycling:cans":"yes","recycling:plastic_bottles":"yes"}},"type":"Feature"},
	{"geometry":{"coordinates":[132.788765,34.446056],"type":"Point"},"properties":{"name":"\u00e5\u0096\u00ab\u00e7\u0085\u0099\u00e3\u0082\u00b3\u00e3\u0083\u00bc\u00e3\u0083\u008a\u00e3\u0083\u00bc","osm_id":"2790412243","tag":{"amenity":"waste_basket","name:en":"Smoking Area","name:ja":"\u55ab\u7159\u30b3\u30fc\u30ca\u30fc","smoking":"yes","waste":"cigarettes"}},"type":"Feature"}
]
}
