{
"type": "FeatureCollection",
"features": [
	{"geometry":{"coordinates":[-1.580262,43.312299],"type":"Point"},"properties":{"osm_id":"3014055040","tag":{"natural":"tree"}},"type":"Feature"},
	{"geometry":{"coordinates":[-1.580365,43.312303],"type":"Point"},"properties":{"osm_id":"3014055041","tag":{"natural":"tree"}},"type":"Feature"},
	{"geometry":{"coordinates":[-1.58036,43.312346],"type":"Point"},"properties":{"osm_id":"3014055042","tag":{"natural":"tree"}},"type":"Feature"},
	{"geometry":{"coordinates":[-1.580254,43.312354],"type":"Point"},"properties":{"osm_id":"3014055043","tag":{"natural":"tree"}},"type":"Feature"},
	{"geometry":{"coordinates":[-1.580355,43.31239],"type":"Point"},"properties":{"osm_id":"3014055044","tag":{"natural":"tree"}},"type":"Feature"},
	{"geometry":{"coordinates":[-1.580247,43.312405],"type":"Point"},"properties":{"osm_id":"3014055045","tag":{"natural":"tree"}},"type":"Feature"},
	{"geometry":{"coordinates":[-1.58035,43.312432],"type":"Point"},"properties":{"osm_id":"3014055046","tag":{"natural":"tree"}},"type":"Feature"},
	{"geometry":{"coordinates":[-1.580242,43.312445],"type":"Point"},"properties":{"osm_id":"3014055047","tag":{"natural":"tree"}},"type":"Feature"},
	{"geometry":{"coordinates":[-1.580344,43.312479],"type":"Point"},"properties":{"osm_id":"3014055048","tag":{"natural":"tree"}},"type":"Feature"},
	{"geometry":{"coordinates":[-1.580234,43.3125],"type":"Point"},"properties":{"osm_id":"3014055049","tag":{"natural":"tree"}},"type":"Feature"},
	{"geometry":{"coordinates":[-1.580339,43.31252],"type":"Point"},"properties":{"osm_id":"3014055050","tag":{"natural":"tree"}},"type":"Feature"},
	{"geometry":{"coordinates":[-1.580227,43.312555],"type":"Point"},"properties":{"osm_id":"3014055051","tag":{"natural":"tree"}},"type":"Feature"},
	{"geometry":{"coordinates":[-1.580334,43.312559],"type":"Point"},"properties":{"osm_id":"3014055052","tag":{"natural":"tree"}},"type":"Feature"},
	{"geometry":{"coordinates":[-1.517113,43.272709],"type":"Point"},"properties":{"name":"Urdazubiko aritza","osm_id":"4886215312","tag":{"denotation":"natural_monument","image":"File:Urdazubiko_aritza.jpg","name:es":"Roble de Urdax","name:eu":"Urdazubiko aritza","natural":"tree","tourism":"attraction"}},"type":"Feature"},
	{"geometry":{"coordinates":[-1.582026,43.312333],"type":"Point"},"properties":{"osm_id":"5906565564","tag":{"natural":"tree"}},"type":"Feature"},
	{"geometry":{"coordinates":[-1.578005,43.313571],"type":"Point"},"properties":{"osm_id":"5906566293","tag":{"natural":"tree"}},"type":"Feature"},
	{"geometry":{"coordinates":[-1.578004,43.313503],"type":"Point"},"properties":{"osm_id":"5906566294","tag":{"natural":"tree"}},"type":"Feature"},
	{"geometry":{"coordinates":[-1.578003,43.313445],"type":"Point"},"properties":{"osm_id":"5906566295","tag":{"natural":"tree"}},"type":"Feature"},
	{"geometry":{"coordinates":[-1.578219,43.313431],"type":"Point"},"properties":{"osm_id":"5906566296","tag":{"natural":"tree"}},"type":"Feature"},
	{"geometry":{"coordinates":[-1.578217,43.313494],"type":"Point"},"properties":{"osm_id":"5906566297","tag":{"natural":"tree"}},"type":"Feature"},
	{"geometry":{"coordinates":[-1.578217,43.313558],"type":"Point"},"properties":{"osm_id":"5906566298","tag":{"natural":"tree"}},"type":"Feature"},
	{"geometry":{"coordinates":[-1.578219,43.31364],"type":"Point"},"properties":{"osm_id":"5906566299","tag":{"natural":"tree"}},"type":"Feature"},
	{"geometry":{"coordinates":[-1.578213,43.313698],"type":"Point"},"properties":{"osm_id":"5906566300","tag":{"natural":"tree"}},"type":"Feature"},
	{"geometry":{"coordinates":[-1.503507,43.266145],"type":"Point"},"properties":{"osm_id":"7632548292","tag":{"natural":"tree"}},"type":"Feature"},
	{"geometry":{"coordinates":[-1.503498,43.266115],"type":"Point"},"properties":{"osm_id":"7632548293","tag":{"natural":"tree"}},"type":"Feature"},
	{"geometry":{"coordinates":[-1.50353,43.266188],"type":"Point"},"properties":{"osm_id":"7632548294","tag":{"natural":"tree"}},"type":"Feature"},
	{"geometry":{"coordinates":[-1.503549,43.266232],"type":"Point"},"properties":{"osm_id":"7632548295","tag":{"natural":"tree"}},"type":"Feature"},
	{"geometry":{"coordinates":[-1.539251,43.26789],"type":"Point"},"properties":{"osm_id":"7897285486","tag":{"natural":"tree"}},"type":"Feature"},
	{"geometry":{"coordinates":[-1.539399,43.267945],"type":"Point"},"properties":{"osm_id":"7897285487","tag":{"natural":"tree"}},"type":"Feature"},
	{"geometry":{"coordinates":[-1.5391,43.267865],"type":"Point"},"properties":{"osm_id":"7897285488","tag":{"natural":"tree"}},"type":"Feature"},
	{"geometry":{"coordinates":[-1.541944,43.269582],"type":"Point"},"properties":{"osm_id":"7897285538","tag":{"natural":"tree"}},"type":"Feature"},
	{"geometry":{"coordinates":[-1.542113,43.269735],"type":"Point"},"properties":{"osm_id":"7897285549","tag":{"natural":"tree"}},"type":"Feature"}
]
}
