{
"type": "FeatureCollection",
"features": [
	{"geometry":{"coordinates":[-1.563588,40.327301],"type":"Point"},"properties":{"name":"Pino Gordo","osm_id":"7800666183","tag":{"denotation":"natural_monument","height":"30","leaf_cycle":"evergreen","leaf_type":"needleleaved","natural":"tree"}},"type":"Feature"}
]
}
