{
"type": "FeatureCollection",
"features": [
	{"geometry":{"coordinates":[-7.510452,56.950277],"type":"Point"},"properties":{"osm_id":"8742339279","tag":{"amenity":"waste_basket"}},"type":"Feature"},
	{"geometry":{"coordinates":[-7.471302,56.95658],"type":"Point"},"properties":{"name":"Garrygall Recycling Centre","osm_id":"9156294698","tag":{"amenity":"recycling","owner":"Comhairle nan Eilean Siar","ownership":"municipal","recycling_type":"centre","wikidata":"Q106085721"}},"type":"Feature"}
]
}
