{
"type": "FeatureCollection",
"lastupdate": "2020-08-05T00:00:00Z",
"features": [
	{"geometry":{"coordinates":[137.459287,36.848831],"type":"Point"},"properties":{"name":"Natsunodobokukogyo Mokuzai Recycling \u00e5\u00a4\u008f\u00e9\u0087\u008e\u00e5\u009c\u009f\u00e6\u009c\u00a8\u00e5\u00b7\u00a5\u00e6\u00a5\u00ad\u00ef\u00bc\u0088\u00e6\u00a0\u00aa\u00ef\u00bc\u0089 \u00e6\u009c\u00a8\u00e6\u009d\u0090\u00e3\u0083\u00aa\u00e3\u0082\u00b5\u00e3\u0082\u00a4\u00e3\u0082\u00af\u00e3\u0083\u00ab\u00e3\u0082\u00bb\u00e3\u0083\u00b3\u00e3\u0082\u00bf\u00e3\u0083\u00bc","osm_id":"7100250223","tag":{"amenity":"recycling","recycling_type":"centre"}},"type":"Feature"}
]
}
