{
"type": "FeatureCollection",
"lastupdate": "2020-08-04T00:00:00Z",
"features": [
	{"geometry":{"coordinates":[24.830327,58.992337],"type":"Point"},"properties":{"name":"Jaama vanavara taaskasutus","osm_id":"4885173421","tag":{"amenity":"recycling","phone":"+37258017007"}},"type":"Feature"}
]
}
