{
"type": "FeatureCollection",
"features": [
	{"geometry":{"coordinates":[24.830327,58.992337],"type":"Point"},"properties":{"name":"Jaama vanavara taaskasutus","osm_id":"4885173421","tag":{"amenity":"recycling","phone":"+37258017007"}},"type":"Feature"},
	{"geometry":{"coordinates":[24.828918,58.992231],"type":"Point"},"properties":{"osm_id":"8873204908","tag":{"amenity":"recycling","recycling:beverage_cartons":"yes","recycling:cans":"yes","recycling:cardboard":"yes","recycling:cartons":"yes","recycling:glass_bottles":"yes","recycling:paper":"yes","recycling:paper_packaging":"yes","recycling:plastic":"yes","recycling:plastic_bottles":"yes","recycling:plastic_packaging":"yes","recycling_type":"container"}},"type":"Feature"}
]
}
