{
"type": "FeatureCollection",
"features": [
	{"geometry":{"coordinates":[15.137389,50.786624],"type":"Point"},"properties":{"osm_id":"4721684122","tag":{"leaf_cycle":"evergreen","leaf_type":"needleleaved","natural":"tree"}},"type":"Feature"},
	{"geometry":{"coordinates":[15.144092,50.787741],"type":"Point"},"properties":{"osm_id":"4721684318","tag":{"leaf_cycle":"evergreen","leaf_type":"needleleaved","natural":"tree"}},"type":"Feature"},
	{"geometry":{"coordinates":[15.144588,50.787799],"type":"Point"},"properties":{"osm_id":"4721684319","tag":{"leaf_cycle":"evergreen","leaf_type":"needleleaved","natural":"tree"}},"type":"Feature"},
	{"geometry":{"coordinates":[15.140093,50.785763],"type":"Point"},"properties":{"osm_id":"4721715672","tag":{"leaf_cycle":"evergreen","leaf_type":"needleleaved","natural":"tree"}},"type":"Feature"},
	{"geometry":{"coordinates":[15.140067,50.785723],"type":"Point"},"properties":{"osm_id":"4721715673","tag":{"leaf_cycle":"evergreen","leaf_type":"needleleaved","natural":"tree"}},"type":"Feature"},
	{"geometry":{"coordinates":[15.140189,50.785764],"type":"Point"},"properties":{"osm_id":"4721715674","tag":{"leaf_cycle":"evergreen","leaf_type":"needleleaved","natural":"tree"}},"type":"Feature"},
	{"geometry":{"coordinates":[15.140155,50.785811],"type":"Point"},"properties":{"osm_id":"4721715675","tag":{"leaf_cycle":"evergreen","leaf_type":"needleleaved","natural":"tree"}},"type":"Feature"},
	{"geometry":{"coordinates":[15.140797,50.785935],"type":"Point"},"properties":{"osm_id":"4721715676","tag":{"leaf_cycle":"evergreen","leaf_type":"needleleaved","natural":"tree"}},"type":"Feature"},
	{"geometry":{"coordinates":[15.140644,50.785832],"type":"Point"},"properties":{"osm_id":"4721715677","tag":{"leaf_cycle":"evergreen","leaf_type":"needleleaved","natural":"tree"}},"type":"Feature"},
	{"geometry":{"coordinates":[15.136717,50.786806],"type":"Point"},"properties":{"osm_id":"4721715678","tag":{"leaf_cycle":"evergreen","leaf_type":"needleleaved","natural":"tree"}},"type":"Feature"},
	{"geometry":{"coordinates":[15.136715,50.786877],"type":"Point"},"properties":{"osm_id":"4721715679","tag":{"leaf_cycle":"evergreen","leaf_type":"needleleaved","natural":"tree"}},"type":"Feature"},
	{"geometry":{"coordinates":[15.13678,50.786914],"type":"Point"},"properties":{"osm_id":"4721715680","tag":{"leaf_cycle":"evergreen","leaf_type":"needleleaved","natural":"tree"}},"type":"Feature"},
	{"geometry":{"coordinates":[15.200198,50.759612],"type":"Point"},"properties":{"osm_id":"4807741511","tag":{"historic":"wayside_shrine","natural":"tree","religion":"christian"}},"type":"Feature"},
	{"geometry":{"coordinates":[15.198311,50.784532],"type":"Point"},"properties":{"name":"Buk","osm_id":"7448029015","tag":{"natural":"tree"}},"type":"Feature"},
	{"geometry":{"coordinates":[15.19999,50.7839],"type":"Point"},"properties":{"name":"Buk","osm_id":"7505784094","tag":{"natural":"tree"}},"type":"Feature"},
	{"geometry":{"coordinates":[15.156101,50.74379],"type":"Point"},"properties":{"osm_id":"7506029641","tag":{"natural":"tree"}},"type":"Feature"},
	{"geometry":{"coordinates":[15.155957,50.743816],"type":"Point"},"properties":{"osm_id":"7506029642","tag":{"natural":"tree"}},"type":"Feature"},
	{"geometry":{"coordinates":[15.155865,50.74409],"type":"Point"},"properties":{"osm_id":"7506029643","tag":{"natural":"tree"}},"type":"Feature"},
	{"geometry":{"coordinates":[15.155855,50.74422],"type":"Point"},"properties":{"osm_id":"7506029644","tag":{"natural":"tree"}},"type":"Feature"},
	{"geometry":{"coordinates":[15.155823,50.744215],"type":"Point"},"properties":{"osm_id":"7506029645","tag":{"natural":"tree"}},"type":"Feature"}
]
}
