{
"type": "FeatureCollection",
"features": [
	{"geometry":{"coordinates":[15.137388,50.786624],"type":"Point"},"properties":{"osm_id":"4721684122","tag":{"leaf_cycle":"evergreen","leaf_type":"needleleaved","natural":"tree"}},"type":"Feature"},
	{"geometry":{"coordinates":[15.144091,50.78774],"type":"Point"},"properties":{"osm_id":"4721684318","tag":{"leaf_cycle":"evergreen","leaf_type":"needleleaved","natural":"tree"}},"type":"Feature"},
	{"geometry":{"coordinates":[15.144588,50.787798],"type":"Point"},"properties":{"osm_id":"4721684319","tag":{"leaf_cycle":"evergreen","leaf_type":"needleleaved","natural":"tree"}},"type":"Feature"},
	{"geometry":{"coordinates":[15.140092,50.785762],"type":"Point"},"properties":{"osm_id":"4721715672","tag":{"leaf_cycle":"evergreen","leaf_type":"needleleaved","natural":"tree"}},"type":"Feature"},
	{"geometry":{"coordinates":[15.140067,50.785722],"type":"Point"},"properties":{"osm_id":"4721715673","tag":{"leaf_cycle":"evergreen","leaf_type":"needleleaved","natural":"tree"}},"type":"Feature"},
	{"geometry":{"coordinates":[15.140188,50.785764],"type":"Point"},"properties":{"osm_id":"4721715674","tag":{"leaf_cycle":"evergreen","leaf_type":"needleleaved","natural":"tree"}},"type":"Feature"},
	{"geometry":{"coordinates":[15.140154,50.785811],"type":"Point"},"properties":{"osm_id":"4721715675","tag":{"leaf_cycle":"evergreen","leaf_type":"needleleaved","natural":"tree"}},"type":"Feature"},
	{"geometry":{"coordinates":[15.140796,50.785935],"type":"Point"},"properties":{"osm_id":"4721715676","tag":{"leaf_cycle":"evergreen","leaf_type":"needleleaved","natural":"tree"}},"type":"Feature"},
	{"geometry":{"coordinates":[15.140643,50.785831],"type":"Point"},"properties":{"osm_id":"4721715677","tag":{"leaf_cycle":"evergreen","leaf_type":"needleleaved","natural":"tree"}},"type":"Feature"},
	{"geometry":{"coordinates":[15.136716,50.786806],"type":"Point"},"properties":{"osm_id":"4721715678","tag":{"leaf_cycle":"evergreen","leaf_type":"needleleaved","natural":"tree"}},"type":"Feature"},
	{"geometry":{"coordinates":[15.136714,50.786877],"type":"Point"},"properties":{"osm_id":"4721715679","tag":{"leaf_cycle":"evergreen","leaf_type":"needleleaved","natural":"tree"}},"type":"Feature"},
	{"geometry":{"coordinates":[15.13678,50.786913],"type":"Point"},"properties":{"osm_id":"4721715680","tag":{"leaf_cycle":"evergreen","leaf_type":"needleleaved","natural":"tree"}},"type":"Feature"},
	{"geometry":{"coordinates":[15.200197,50.759612],"type":"Point"},"properties":{"osm_id":"4807741511","tag":{"historic":"wayside_shrine","natural":"tree","religion":"christian"}},"type":"Feature"},
	{"geometry":{"coordinates":[15.19831,50.784532],"type":"Point"},"properties":{"name":"Buk","osm_id":"7448029015","tag":{"natural":"tree"}},"type":"Feature"},
	{"geometry":{"coordinates":[15.19999,50.783899],"type":"Point"},"properties":{"name":"Buk","osm_id":"7505784094","tag":{"natural":"tree"}},"type":"Feature"},
	{"geometry":{"coordinates":[15.156101,50.743789],"type":"Point"},"properties":{"osm_id":"7506029641","tag":{"natural":"tree"}},"type":"Feature"},
	{"geometry":{"coordinates":[15.155957,50.743815],"type":"Point"},"properties":{"osm_id":"7506029642","tag":{"natural":"tree"}},"type":"Feature"},
	{"geometry":{"coordinates":[15.155864,50.744089],"type":"Point"},"properties":{"osm_id":"7506029643","tag":{"natural":"tree"}},"type":"Feature"},
	{"geometry":{"coordinates":[15.155854,50.74422],"type":"Point"},"properties":{"osm_id":"7506029644","tag":{"natural":"tree"}},"type":"Feature"},
	{"geometry":{"coordinates":[15.155823,50.744214],"type":"Point"},"properties":{"osm_id":"7506029645","tag":{"natural":"tree"}},"type":"Feature"}
]
}
