{
"type": "FeatureCollection",
"features": [
	{"geometry":{"coordinates":[-5.541724,50.111937],"type":"Point"},"properties":{"osm_id":"682351845","tag":{"amenity":"recycling","location":"overground","recycling_type":"container"}},"type":"Feature"},
	{"geometry":{"coordinates":[-5.542426,50.111615],"type":"Point"},"properties":{"osm_id":"682369534","tag":{"amenity":"recycling","location":"overground","recycling_type":"container"}},"type":"Feature"},
	{"geometry":{"coordinates":[-5.568833,50.065654],"type":"Point"},"properties":{"osm_id":"683892865","tag":{"amenity":"recycling"}},"type":"Feature"},
	{"geometry":{"coordinates":[-5.623084,50.074504],"type":"Point"},"properties":{"osm_id":"683907490","tag":{"amenity":"recycling"}},"type":"Feature"},
	{"geometry":{"coordinates":[-5.617022,50.075765],"type":"Point"},"properties":{"osm_id":"2181419700","tag":{"access":"private","amenity":"recycling","recycling:glass":"yes","recycling_type":"container"}},"type":"Feature"},
	{"geometry":{"coordinates":[-5.54968,50.103287],"type":"Point"},"properties":{"osm_id":"2399838190","tag":{"amenity":"waste_basket"}},"type":"Feature"},
	{"geometry":{"coordinates":[-5.617113,50.075745],"type":"Point"},"properties":{"osm_id":"4428375798","tag":{"access":"private","amenity":"waste_disposal"}},"type":"Feature"},
	{"geometry":{"coordinates":[-5.538241,50.119391],"type":"Point"},"properties":{"osm_id":"6875225912","tag":{"amenity":"waste_basket"}},"type":"Feature"},
	{"geometry":{"coordinates":[-5.608988,50.107918],"type":"Point"},"properties":{"osm_id":"7729003036","tag":{"amenity":"waste_basket"}},"type":"Feature"},
	{"geometry":{"coordinates":[-5.609293,50.107833],"type":"Point"},"properties":{"osm_id":"7729024468","tag":{"amenity":"waste_basket"}},"type":"Feature"}
]
}
