{
"type": "FeatureCollection",
"features": [
	{"geometry":{"coordinates":[10.624424,52.671508],"type":"Point"},"properties":{"name":"Freundschaftseiche","osm_id":"2665187510","tag":{"leaf_type":"broadleaved","natural":"tree","start_date":"1990"}},"type":"Feature"},
	{"geometry":{"coordinates":[10.594593,52.681929],"type":"Point"},"properties":{"osm_id":"2893805273","tag":{"leaf_cycle":"deciduous","leaf_type":"broadleaved","natural":"tree"}},"type":"Feature"},
	{"geometry":{"coordinates":[10.590059,52.683663],"type":"Point"},"properties":{"osm_id":"2894023872","tag":{"leaf_cycle":"deciduous","leaf_type":"broadleaved","natural":"tree"}},"type":"Feature"},
	{"geometry":{"coordinates":[10.59003,52.683769],"type":"Point"},"properties":{"osm_id":"2894023873","tag":{"leaf_cycle":"deciduous","leaf_type":"broadleaved","natural":"tree"}},"type":"Feature"},
	{"geometry":{"coordinates":[10.586761,52.68411],"type":"Point"},"properties":{"osm_id":"2894023887","tag":{"leaf_cycle":"deciduous","leaf_type":"broadleaved","natural":"tree"}},"type":"Feature"},
	{"geometry":{"coordinates":[10.586821,52.684224],"type":"Point"},"properties":{"osm_id":"2894023891","tag":{"leaf_cycle":"deciduous","leaf_type":"broadleaved","natural":"tree"}},"type":"Feature"},
	{"geometry":{"coordinates":[10.547385,52.683185],"type":"Point"},"properties":{"osm_id":"3467824838","tag":{"natural":"tree"}},"type":"Feature"},
	{"geometry":{"coordinates":[10.62858,52.654627],"type":"Point"},"properties":{"osm_id":"5411932159","tag":{"natural":"tree"}},"type":"Feature"}
]
}
