{
"type": "FeatureCollection",
"features": [
	{"geometry":{"coordinates":[10.616198,50.50644],"type":"Point"},"properties":{"osm_id":"1666285529","tag":{"natural":"tree"}},"type":"Feature"},
	{"geometry":{"coordinates":[10.616408,50.506681],"type":"Point"},"properties":{"osm_id":"1666285547","tag":{"natural":"tree"}},"type":"Feature"},
	{"geometry":{"coordinates":[10.617004,50.50663],"type":"Point"},"properties":{"osm_id":"1666285550","tag":{"natural":"tree"}},"type":"Feature"},
	{"geometry":{"coordinates":[10.616676,50.506755],"type":"Point"},"properties":{"osm_id":"1666285553","tag":{"natural":"tree"}},"type":"Feature"},
	{"geometry":{"coordinates":[10.616426,50.506701],"type":"Point"},"properties":{"osm_id":"1666285562","tag":{"natural":"tree"}},"type":"Feature"},
	{"geometry":{"coordinates":[10.616144,50.506708],"type":"Point"},"properties":{"osm_id":"1666285563","tag":{"natural":"tree"}},"type":"Feature"},
	{"geometry":{"coordinates":[10.616822,50.506801],"type":"Point"},"properties":{"osm_id":"1666285571","tag":{"natural":"tree"}},"type":"Feature"},
	{"geometry":{"coordinates":[10.616155,50.50725],"type":"Point"},"properties":{"osm_id":"1670019928","tag":{"natural":"tree"}},"type":"Feature"},
	{"geometry":{"coordinates":[10.616544,50.507215],"type":"Point"},"properties":{"osm_id":"1670019948","tag":{"natural":"tree"}},"type":"Feature"},
	{"geometry":{"coordinates":[10.616219,50.507375],"type":"Point"},"properties":{"osm_id":"1670019956","tag":{"natural":"tree"}},"type":"Feature"},
	{"geometry":{"coordinates":[10.616243,50.507494],"type":"Point"},"properties":{"osm_id":"1670019967","tag":{"natural":"tree"}},"type":"Feature"},
	{"geometry":{"coordinates":[10.614707,50.493272],"type":"Point"},"properties":{"name":"Dicke Eiche","osm_id":"1991900000","tag":{"denotation":"natural_monument","natural":"tree"}},"type":"Feature"},
	{"geometry":{"coordinates":[10.557359,50.475642],"type":"Point"},"properties":{"osm_id":"2241768946","tag":{"natural":"tree"}},"type":"Feature"},
	{"geometry":{"coordinates":[10.557388,50.475855],"type":"Point"},"properties":{"osm_id":"2241768947","tag":{"natural":"tree"}},"type":"Feature"},
	{"geometry":{"coordinates":[10.5574,50.476006],"type":"Point"},"properties":{"osm_id":"2241768948","tag":{"natural":"tree"}},"type":"Feature"},
	{"geometry":{"coordinates":[10.557376,50.476121],"type":"Point"},"properties":{"osm_id":"2241768949","tag":{"natural":"tree"}},"type":"Feature"},
	{"geometry":{"coordinates":[10.5573,50.476493],"type":"Point"},"properties":{"osm_id":"2241768950","tag":{"natural":"tree"}},"type":"Feature"},
	{"geometry":{"coordinates":[10.557283,50.476686],"type":"Point"},"properties":{"osm_id":"2241768951","tag":{"natural":"tree"}},"type":"Feature"},
	{"geometry":{"coordinates":[10.557266,50.476798],"type":"Point"},"properties":{"osm_id":"2241768952","tag":{"natural":"tree"}},"type":"Feature"},
	{"geometry":{"coordinates":[10.557239,50.47689],"type":"Point"},"properties":{"osm_id":"2241768953","tag":{"natural":"tree"}},"type":"Feature"},
	{"geometry":{"coordinates":[10.557244,50.477072],"type":"Point"},"properties":{"osm_id":"2241768954","tag":{"natural":"tree"}},"type":"Feature"}
]
}
