{
"type": "FeatureCollection",
"features": [
	{"geometry":{"coordinates":[10.616198,50.50644],"type":"Point"},"properties":{"osm_id":"1666285529","tag":{"natural":"tree"}},"type":"Feature"},
	{"geometry":{"coordinates":[10.616408,50.506682],"type":"Point"},"properties":{"osm_id":"1666285547","tag":{"natural":"tree"}},"type":"Feature"},
	{"geometry":{"coordinates":[10.617004,50.50663],"type":"Point"},"properties":{"osm_id":"1666285550","tag":{"natural":"tree"}},"type":"Feature"},
	{"geometry":{"coordinates":[10.616677,50.506755],"type":"Point"},"properties":{"osm_id":"1666285553","tag":{"natural":"tree"}},"type":"Feature"},
	{"geometry":{"coordinates":[10.616427,50.506701],"type":"Point"},"properties":{"osm_id":"1666285562","tag":{"natural":"tree"}},"type":"Feature"},
	{"geometry":{"coordinates":[10.616144,50.506708],"type":"Point"},"properties":{"osm_id":"1666285563","tag":{"natural":"tree"}},"type":"Feature"},
	{"geometry":{"coordinates":[10.616822,50.506801],"type":"Point"},"properties":{"osm_id":"1666285571","tag":{"natural":"tree"}},"type":"Feature"},
	{"geometry":{"coordinates":[10.616155,50.507251],"type":"Point"},"properties":{"osm_id":"1670019928","tag":{"natural":"tree"}},"type":"Feature"},
	{"geometry":{"coordinates":[10.616544,50.507216],"type":"Point"},"properties":{"osm_id":"1670019948","tag":{"natural":"tree"}},"type":"Feature"},
	{"geometry":{"coordinates":[10.61622,50.507375],"type":"Point"},"properties":{"osm_id":"1670019956","tag":{"natural":"tree"}},"type":"Feature"},
	{"geometry":{"coordinates":[10.616244,50.507495],"type":"Point"},"properties":{"osm_id":"1670019967","tag":{"natural":"tree"}},"type":"Feature"},
	{"geometry":{"coordinates":[10.614708,50.493272],"type":"Point"},"properties":{"name":"Dicke Eiche","osm_id":"1991900000","tag":{"denotation":"natural_monument","natural":"tree"}},"type":"Feature"},
	{"geometry":{"coordinates":[10.557359,50.475642],"type":"Point"},"properties":{"osm_id":"2241768946","tag":{"natural":"tree"}},"type":"Feature"},
	{"geometry":{"coordinates":[10.557389,50.475856],"type":"Point"},"properties":{"osm_id":"2241768947","tag":{"natural":"tree"}},"type":"Feature"},
	{"geometry":{"coordinates":[10.557401,50.476007],"type":"Point"},"properties":{"osm_id":"2241768948","tag":{"natural":"tree"}},"type":"Feature"},
	{"geometry":{"coordinates":[10.557376,50.476122],"type":"Point"},"properties":{"osm_id":"2241768949","tag":{"natural":"tree"}},"type":"Feature"},
	{"geometry":{"coordinates":[10.557301,50.476494],"type":"Point"},"properties":{"osm_id":"2241768950","tag":{"natural":"tree"}},"type":"Feature"},
	{"geometry":{"coordinates":[10.557283,50.476687],"type":"Point"},"properties":{"osm_id":"2241768951","tag":{"natural":"tree"}},"type":"Feature"},
	{"geometry":{"coordinates":[10.557266,50.476799],"type":"Point"},"properties":{"osm_id":"2241768952","tag":{"natural":"tree"}},"type":"Feature"},
	{"geometry":{"coordinates":[10.557239,50.476891],"type":"Point"},"properties":{"osm_id":"2241768953","tag":{"natural":"tree"}},"type":"Feature"},
	{"geometry":{"coordinates":[10.557244,50.477073],"type":"Point"},"properties":{"osm_id":"2241768954","tag":{"natural":"tree"}},"type":"Feature"}
]
}
