{
"type": "FeatureCollection",
"features": [
	{"geometry":{"coordinates":[10.580658,48.13993],"type":"Point"},"properties":{"osm_id":"3470655601","tag":{"natural":"tree"}},"type":"Feature"},
	{"geometry":{"coordinates":[10.580677,48.140089],"type":"Point"},"properties":{"osm_id":"3470655602","tag":{"natural":"tree"}},"type":"Feature"},
	{"geometry":{"coordinates":[10.58069,48.140233],"type":"Point"},"properties":{"osm_id":"3470655603","tag":{"natural":"tree"}},"type":"Feature"},
	{"geometry":{"coordinates":[10.580589,48.140634],"type":"Point"},"properties":{"osm_id":"3470655610","tag":{"natural":"tree"}},"type":"Feature"},
	{"geometry":{"coordinates":[10.581103,48.140788],"type":"Point"},"properties":{"osm_id":"3470655611","tag":{"natural":"tree"}},"type":"Feature"},
	{"geometry":{"coordinates":[10.580251,48.140861],"type":"Point"},"properties":{"osm_id":"3470655614","tag":{"natural":"tree"}},"type":"Feature"},
	{"geometry":{"coordinates":[10.58038,48.140884],"type":"Point"},"properties":{"osm_id":"3470655615","tag":{"natural":"tree"}},"type":"Feature"},
	{"geometry":{"coordinates":[10.580663,48.141026],"type":"Point"},"properties":{"osm_id":"3470655617","tag":{"natural":"tree"}},"type":"Feature"},
	{"geometry":{"coordinates":[10.582145,48.142202],"type":"Point"},"properties":{"osm_id":"3470655637","tag":{"natural":"tree"}},"type":"Feature"},
	{"geometry":{"coordinates":[10.583162,48.143136],"type":"Point"},"properties":{"osm_id":"3470655657","tag":{"natural":"tree"}},"type":"Feature"},
	{"geometry":{"coordinates":[10.581743,48.137512],"type":"Point"},"properties":{"name":"Kastanie","osm_id":"4705111146","tag":{"denotation":"single","leaf_cycle":"deciduous","leaf_type":"broadleaved","natural":"tree"}},"type":"Feature"},
	{"geometry":{"coordinates":[10.584019,48.139049],"type":"Point"},"properties":{"name":"Linde","osm_id":"4705111147","tag":{"leaf_cycle":"deciduous","leaf_type":"broadleaved","natural":"tree"}},"type":"Feature"},
	{"geometry":{"coordinates":[10.589964,48.155438],"type":"Point"},"properties":{"osm_id":"4988507198","tag":{"natural":"tree"}},"type":"Feature"}
]
}
