{
"type": "FeatureCollection",
"features": [
	{"geometry":{"coordinates":[10.62925,43.136544],"type":"Point"},"properties":{"name":"Il Castagnone","osm_id":"3265030528","tag":{"natural":"tree"}},"type":"Feature"},
	{"geometry":{"coordinates":[10.550523,43.180262],"type":"Point"},"properties":{"osm_id":"4925197674","tag":{"natural":"tree"}},"type":"Feature"},
	{"geometry":{"coordinates":[10.605412,43.159989],"type":"Point"},"properties":{"osm_id":"6932825703","tag":{"natural":"tree"}},"type":"Feature"},
	{"geometry":{"coordinates":[10.60549,43.159996],"type":"Point"},"properties":{"osm_id":"6932825704","tag":{"natural":"tree"}},"type":"Feature"}
]
}
