{
"type": "FeatureCollection",
"features": [
	{"geometry":{"coordinates":[10.629249,43.136543],"type":"Point"},"properties":{"name":"Il Castagnone","osm_id":"3265030528","tag":{"natural":"tree"}},"type":"Feature"},
	{"geometry":{"coordinates":[10.550522,43.180261],"type":"Point"},"properties":{"osm_id":"4925197674","tag":{"natural":"tree"}},"type":"Feature"},
	{"geometry":{"coordinates":[10.605412,43.159988],"type":"Point"},"properties":{"osm_id":"6932825703","tag":{"natural":"tree"}},"type":"Feature"},
	{"geometry":{"coordinates":[10.60549,43.159995],"type":"Point"},"properties":{"osm_id":"6932825704","tag":{"natural":"tree"}},"type":"Feature"}
]
}
