{
"type": "FeatureCollection",
"features": [
	{"geometry":{"coordinates":[12.320293,52.325306],"type":"Point"},"properties":{"name":"Friedenseiche","osm_id":"1421492669","tag":{"genus:de":"Eiche","leaf_cycle":"deciduous","leaf_type":"broadleaved","natural":"tree"}},"type":"Feature"},
	{"geometry":{"coordinates":[12.354256,52.362156],"type":"Point"},"properties":{"osm_id":"7475466485","tag":{"denotation":"avenue","leaf_cycle":"deciduous","leaf_type":"broadleaved","natural":"tree"}},"type":"Feature"},
	{"geometry":{"coordinates":[12.354624,52.362282],"type":"Point"},"properties":{"osm_id":"7475466486","tag":{"denotation":"avenue","leaf_cycle":"deciduous","leaf_type":"broadleaved","natural":"tree"}},"type":"Feature"},
	{"geometry":{"coordinates":[12.354537,52.36225],"type":"Point"},"properties":{"osm_id":"7475466487","tag":{"denotation":"avenue","leaf_cycle":"deciduous","leaf_type":"broadleaved","natural":"tree"}},"type":"Feature"},
	{"geometry":{"coordinates":[12.354439,52.362218],"type":"Point"},"properties":{"osm_id":"7475466488","tag":{"denotation":"avenue","leaf_cycle":"deciduous","leaf_type":"broadleaved","natural":"tree"}},"type":"Feature"}
]
}
