{
"type": "FeatureCollection",
"features": [
	{"geometry":{"coordinates":[12.35038,43.201774],"type":"Point"},"properties":{"name":"Tiglio degli antenati","osm_id":"5275837898","tag":{"denotation":"natural_monument","genus":"Tilia cordata Mill.","leaf_cycle":"deciduous","leaf_type":"broadleaved","natural":"tree"}},"type":"Feature"}
]
}
