{
"type": "FeatureCollection",
"lastupdate": "2020-08-06T00:00:00Z",
"features": [
	{"geometry":{"coordinates":[15.212134,59.280822],"type":"Point"},"properties":{"osm_id":"1673481831","tag":{"amenity":"recycling","recycling:batteries":"no","recycling:books":"yes","recycling:cans":"yes","recycling:cardboard":"yes","recycling:cartons":"yes","recycling:clothes":"yes","recycling:electrical_appliances":"no","recycling:glass":"yes","recycling:glass_bottles":"yes","recycling:green_waste":"no","recycling:magazines":"yes","recycling:newspaper":"yes","recycling:paper":"yes","recycling:paper_packaging":"yes","recycling:plastic":"yes","recycling:plastic_bottles":"yes","recycling:plastic_packaging":"yes","recycling:scrap_metal":"yes","recycling:small_appliances":"no","recycling:waste":"no","recycling:wood":"no","recycling_type":"container"}},"type":"Feature"},
	{"geometry":{"coordinates":[15.225786,59.273447],"type":"Point"},"properties":{"osm_id":"3677158337","tag":{"amenity":"waste_basket"}},"type":"Feature"},
	{"geometry":{"coordinates":[15.208558,59.27187],"type":"Point"},"properties":{"osm_id":"4524639246","tag":{"amenity":"waste_basket"}},"type":"Feature"},
	{"geometry":{"coordinates":[15.210459,59.270304],"type":"Point"},"properties":{"osm_id":"4524639249","tag":{"amenity":"waste_basket"}},"type":"Feature"},
	{"geometry":{"coordinates":[15.20999,59.26998],"type":"Point"},"properties":{"osm_id":"4524639251","tag":{"amenity":"waste_basket"}},"type":"Feature"},
	{"geometry":{"coordinates":[15.208158,59.280214],"type":"Point"},"properties":{"osm_id":"4524639262","tag":{"amenity":"waste_basket"}},"type":"Feature"},
	{"geometry":{"coordinates":[15.226348,59.266793],"type":"Point"},"properties":{"osm_id":"4526949575","tag":{"amenity":"waste_basket"}},"type":"Feature"},
	{"geometry":{"coordinates":[15.212173,59.27865],"type":"Point"},"properties":{"osm_id":"5113428423","tag":{"amenity":"waste_basket"}},"type":"Feature"},
	{"geometry":{"coordinates":[15.236318,59.304749],"type":"Point"},"properties":{"osm_id":"5268124620","tag":{"amenity":"recycling","recycling_type":"container"}},"type":"Feature"},
	{"geometry":{"coordinates":[15.210796,59.266584],"type":"Point"},"properties":{"osm_id":"5311937291","tag":{"amenity":"recycling","location":"overground","recycling:glass":"yes","recycling_type":"container"}},"type":"Feature"},
	{"geometry":{"coordinates":[15.261589,59.294729],"type":"Point"},"properties":{"osm_id":"6805759622","tag":{"amenity":"waste_basket"}},"type":"Feature"}
]
}
