{
"type": "FeatureCollection",
"lastupdate": "2020-08-02T00:00:00Z",
"features": [
	{"geometry":{"coordinates":[15.236247,46.854681],"type":"Point"},"properties":{"osm_id":"3710799326","tag":{"amenity":"recycling","recycling_type":"container"}},"type":"Feature"},
	{"geometry":{"coordinates":[15.21519,46.814954],"type":"Point"},"properties":{"name":"Carla Kleidercontainern","osm_id":"3849832860","tag":{"addr:city":"Deutschlandsberg","addr:country":"AT","addr:housenumber":"11","addr:postcode":"8530","addr:street":"Hauptplatz","amenity":"recycling","operator":"Caritas Graz-Seckau","recycling:clothes":"yes","recycling_type":"container"}},"type":"Feature"},
	{"geometry":{"coordinates":[15.217917,46.837934],"type":"Point"},"properties":{"osm_id":"5208834104","tag":{"amenity":"recycling","recycling_type":"container"}},"type":"Feature"},
	{"geometry":{"coordinates":[15.207843,46.840674],"type":"Point"},"properties":{"osm_id":"5208834298","tag":{"amenity":"recycling","recycling_type":"container"}},"type":"Feature"}
]
}
