{
"type": "FeatureCollection",
"lastupdate": "2020-07-31T00:00:00Z",
"features": [
	{"geometry":{"coordinates":[15.261437,46.714578],"type":"Point"},"properties":{"osm_id":"4296895479","tag":{"amenity":"recycling","recycling:cans":"yes","recycling:cans:count":"3","recycling:glass_bottles":"yes","recycling:glass_bottles:count":"3","recycling_type":"container"}},"type":"Feature"},
	{"geometry":{"coordinates":[15.2379,46.738383],"type":"Point"},"properties":{"osm_id":"7353671738","tag":{"amenity":"recycling","opening_hours":"24/7","recycling:clothes":"yes","recycling:cooking_oil":"yes","recycling:glass":"yes","recycling:metal_packaging":"yes","recycling_type":"container"}},"type":"Feature"},
	{"geometry":{"coordinates":[15.279337,46.72102],"type":"Point"},"properties":{"name":"Bauhhof Wies","osm_id":"7353671739","tag":{"amenity":"recycling","operator":"Marktgemeinde Wies","operator:type":"public","recycling_type":"centre"}},"type":"Feature"}
]
}
