{
"type": "FeatureCollection",
"features": [
	{"geometry":{"coordinates":[-44.988757,-21.248572],"type":"Point"},"properties":{"osm_id":"4059010649","tag":{"natural":"tree"}},"type":"Feature"},
	{"geometry":{"coordinates":[-44.98862,-21.248684],"type":"Point"},"properties":{"osm_id":"4366922381","tag":{"natural":"tree"}},"type":"Feature"},
	{"geometry":{"coordinates":[-44.988478,-21.248312],"type":"Point"},"properties":{"osm_id":"4366922383","tag":{"natural":"tree"}},"type":"Feature"},
	{"geometry":{"coordinates":[-44.999752,-21.241008],"type":"Point"},"properties":{"osm_id":"4458120636","tag":{"natural":"tree"}},"type":"Feature"},
	{"geometry":{"coordinates":[-44.985473,-21.246213],"type":"Point"},"properties":{"name":"Murraya paniculata","osm_id":"5003816395","tag":{"leaf_cycle":"evergreen","leaf_type":"broadleaved","natural":"tree"}},"type":"Feature"},
	{"geometry":{"coordinates":[-44.988032,-21.242114],"type":"Point"},"properties":{"name":"Poincianella pluviosa","osm_id":"5003816396","tag":{"natural":"tree"}},"type":"Feature"}
]
}
