{
"type": "FeatureCollection",
"features": [
	{"geometry":{"coordinates":[-44.988758,-21.248572],"type":"Point"},"properties":{"osm_id":"4059010649","tag":{"natural":"tree"}},"type":"Feature"},
	{"geometry":{"coordinates":[-44.988621,-21.248685],"type":"Point"},"properties":{"osm_id":"4366922381","tag":{"natural":"tree"}},"type":"Feature"},
	{"geometry":{"coordinates":[-44.988478,-21.248312],"type":"Point"},"properties":{"osm_id":"4366922383","tag":{"natural":"tree"}},"type":"Feature"},
	{"geometry":{"coordinates":[-44.999753,-21.241009],"type":"Point"},"properties":{"osm_id":"4458120636","tag":{"natural":"tree"}},"type":"Feature"},
	{"geometry":{"coordinates":[-44.985474,-21.246213],"type":"Point"},"properties":{"name":"Murraya paniculata","osm_id":"5003816395","tag":{"leaf_cycle":"evergreen","leaf_type":"broadleaved","natural":"tree"}},"type":"Feature"},
	{"geometry":{"coordinates":[-44.988033,-21.242115],"type":"Point"},"properties":{"name":"Poincianella pluviosa","osm_id":"5003816396","tag":{"natural":"tree"}},"type":"Feature"}
]
}
