{
"type": "FeatureCollection",
"lastupdate": "2020-08-04T00:00:00Z",
"features": [
	{"geometry":{"coordinates":[10.030564,57.450801],"type":"Point"},"properties":{"name":"AVV Genbrugscenter","osm_id":"4700027464","tag":{"amenity":"recycling","fvst:navnelbnr":"545940","recycling_type":"centre","website":"https://www.avv.dk/"}},"type":"Feature"}
]
}
