{
"type": "FeatureCollection",
"lastupdate": "2020-08-03T00:00:00Z",
"features": [
	{"geometry":{"coordinates":[10.045585,55.37422],"type":"Point"},"properties":{"highway":"bus_stop","name":"Aarupskolen (V) (Assens Kommune)","osm_id":"1708557857","ref":"2361","tag":{"amenity":"waste_basket","bench":"yes","bus":"yes","departures_board":"timetable","local_ref":"Zone 81","naptan:Bearing":"W","network":"FynBus","network:wikidata":"Q12313224","public_transport":"platform","route_ref":"130;131;132;820;813","shelter":"yes","shelter_type":"public_transport"}},"type":"Feature"},
	{"geometry":{"coordinates":[10.045771,55.374212],"type":"Point"},"properties":{"highway":"bus_stop","name":"Aarupskolen (Assens Kommune)","osm_id":"1708557862","ref":"2362","tag":{"amenity":"waste_basket","bench":"yes","bus":"yes","departures_board":"timetable","local_ref":"Zone 81","naptan:Bearing":"E","network":"FynBus","network:wikidata":"Q12313224","public_transport":"platform","route_ref":"130;131;132;820;813","shelter":"yes","shelter_type":"public_transport"}},"type":"Feature"},
	{"geometry":{"coordinates":[10.047065,55.378433],"type":"Point"},"properties":{"osm_id":"4788690669","tag":{"amenity":"waste_basket"}},"type":"Feature"},
	{"geometry":{"coordinates":[10.046418,55.375143],"type":"Point"},"properties":{"osm_id":"6993558921","tag":{"amenity":"waste_basket"}},"type":"Feature"},
	{"geometry":{"coordinates":[10.047154,55.375076],"type":"Point"},"properties":{"osm_id":"6993558922","tag":{"amenity":"waste_basket"}},"type":"Feature"}
]
}
