{
"type": "FeatureCollection",
"features": [
	{"geometry":{"coordinates":[10.045585,55.374221],"type":"Point"},"properties":{"highway":"bus_stop","name":"Aarupskolen (V) (Assens Kommune)","osm_id":"1708557857","ref":"2361","tag":{"amenity":"waste_basket","bench":"yes","bus":"yes","departures_board":"timetable","local_ref":"2081","naptan:Bearing":"W","network":"FynBus","network:wikidata":"Q12313224","public_transport":"platform","route_ref":"130;131;132;820;813","shelter":"yes","shelter_type":"public_transport"}},"type":"Feature"},
	{"geometry":{"coordinates":[10.045772,55.374212],"type":"Point"},"properties":{"highway":"bus_stop","name":"Aarupskolen (Assens Kommune)","osm_id":"1708557862","ref":"2362","tag":{"amenity":"waste_basket","bench":"yes","bus":"yes","departures_board":"timetable","local_ref":"2081","naptan:Bearing":"E","network":"FynBus","network:wikidata":"Q12313224","public_transport":"platform","route_ref":"130;131;132;820;813","shelter":"yes","shelter_type":"public_transport"}},"type":"Feature"},
	{"geometry":{"coordinates":[10.047066,55.378434],"type":"Point"},"properties":{"osm_id":"4788690669","tag":{"amenity":"waste_basket"}},"type":"Feature"},
	{"geometry":{"coordinates":[10.046419,55.375143],"type":"Point"},"properties":{"osm_id":"6993558921","tag":{"amenity":"waste_basket"}},"type":"Feature"},
	{"geometry":{"coordinates":[10.047155,55.375076],"type":"Point"},"properties":{"osm_id":"6993558922","tag":{"amenity":"waste_basket"}},"type":"Feature"}
]
}
