{
"type": "FeatureCollection",
"lastupdate": "2020-08-03T00:00:00Z",
"features": [
	{"geometry":{"coordinates":[10.070182,54.410374],"type":"Point"},"properties":{"osm_id":"372646739","tag":{"amenity":"recycling","location":"overground","recycling:clothes":"yes","recycling:glass":"yes","recycling_type":"container"}},"type":"Feature"},
	{"geometry":{"coordinates":[10.037477,54.384799],"type":"Point"},"properties":{"osm_id":"472471509","tag":{"amenity":"recycling","location":"overground","recycling:clothes":"yes","recycling:glass":"yes","recycling_type":"container"}},"type":"Feature"},
	{"geometry":{"coordinates":[10.054658,54.394946],"type":"Point"},"properties":{"osm_id":"790566620","tag":{"amenity":"recycling"}},"type":"Feature"},
	{"geometry":{"coordinates":[10.101635,54.370303],"type":"Point"},"properties":{"osm_id":"1804983872","tag":{"amenity":"waste_basket"}},"type":"Feature"},
	{"geometry":{"coordinates":[10.029656,54.3701],"type":"Point"},"properties":{"osm_id":"1975062543","tag":{"amenity":"waste_basket"}},"type":"Feature"},
	{"geometry":{"coordinates":[10.046224,54.379731],"type":"Point"},"properties":{"osm_id":"4036982691","tag":{"amenity":"waste_basket"}},"type":"Feature"},
	{"geometry":{"coordinates":[10.057655,54.383027],"type":"Point"},"properties":{"osm_id":"4036982694","tag":{"amenity":"waste_basket"}},"type":"Feature"},
	{"geometry":{"coordinates":[10.028841,54.370438],"type":"Point"},"properties":{"osm_id":"7342862828","tag":{"amenity":"waste_basket"}},"type":"Feature"},
	{"geometry":{"coordinates":[10.036104,54.388773],"type":"Point"},"properties":{"osm_id":"7600517789","tag":{"amenity":"waste_basket"}},"type":"Feature"}
]
}
