{
"type": "FeatureCollection",
"features": [
	{"geometry":{"coordinates":[10.070182,54.410374],"type":"Point"},"properties":{"osm_id":"372646739","tag":{"amenity":"recycling","location":"overground","recycling:clothes":"yes","recycling:glass":"yes","recycling_type":"container"}},"type":"Feature"},
	{"geometry":{"coordinates":[10.037478,54.3848],"type":"Point"},"properties":{"osm_id":"472471509","tag":{"amenity":"recycling","location":"overground","recycling:clothes":"yes","recycling:glass":"yes","recycling_type":"container"}},"type":"Feature"},
	{"geometry":{"coordinates":[10.054659,54.394947],"type":"Point"},"properties":{"osm_id":"790566620","tag":{"amenity":"recycling"}},"type":"Feature"},
	{"geometry":{"coordinates":[10.101635,54.370304],"type":"Point"},"properties":{"osm_id":"1804983872","tag":{"amenity":"waste_basket"}},"type":"Feature"},
	{"geometry":{"coordinates":[10.029656,54.370101],"type":"Point"},"properties":{"osm_id":"1975062543","tag":{"amenity":"waste_basket"}},"type":"Feature"},
	{"geometry":{"coordinates":[10.046224,54.379732],"type":"Point"},"properties":{"osm_id":"4036982691","tag":{"amenity":"waste_basket"}},"type":"Feature"},
	{"geometry":{"coordinates":[10.057655,54.383028],"type":"Point"},"properties":{"osm_id":"4036982694","tag":{"amenity":"waste_basket"}},"type":"Feature"},
	{"geometry":{"coordinates":[10.028841,54.370439],"type":"Point"},"properties":{"osm_id":"7342862828","tag":{"amenity":"waste_basket"}},"type":"Feature"},
	{"geometry":{"coordinates":[10.036105,54.388774],"type":"Point"},"properties":{"osm_id":"7600517789","tag":{"amenity":"waste_basket"}},"type":"Feature"}
]
}
