{
"type": "FeatureCollection",
"features": [
	{"geometry":{"coordinates":[10.030816,53.840388],"type":"Point"},"properties":{"osm_id":"441168893","tag":{"amenity":"recycling","recycling:clothes":"yes","recycling:glass_bottles":"yes","recycling:paper":"yes","recycling_type":"container"}},"type":"Feature"},
	{"geometry":{"coordinates":[10.070853,53.834979],"type":"Point"},"properties":{"osm_id":"813405752","tag":{"amenity":"recycling","recycling:clothes":"yes","recycling:glass_bottles":"yes","recycling_type":"container"}},"type":"Feature"},
	{"geometry":{"coordinates":[10.08099,53.81877],"type":"Point"},"properties":{"osm_id":"945337383","tag":{"amenity":"recycling","location":"overground","recycling:clothes":"yes","recycling_type":"container"}},"type":"Feature"},
	{"geometry":{"coordinates":[10.06457,53.806461],"type":"Point"},"properties":{"osm_id":"1754128565","tag":{"amenity":"waste_basket"}},"type":"Feature"},
	{"geometry":{"coordinates":[10.036742,53.803107],"type":"Point"},"properties":{"osm_id":"2090212215","tag":{"amenity":"waste_basket"}},"type":"Feature"},
	{"geometry":{"coordinates":[10.021241,53.81046],"type":"Point"},"properties":{"osm_id":"2655765576","tag":{"amenity":"waste_basket"}},"type":"Feature"},
	{"geometry":{"coordinates":[10.054948,53.813943],"type":"Point"},"properties":{"osm_id":"2661572250","tag":{"amenity":"waste_basket"}},"type":"Feature"},
	{"geometry":{"coordinates":[10.042942,53.844363],"type":"Point"},"properties":{"osm_id":"6247601608","tag":{"amenity":"waste_basket"}},"type":"Feature"},
	{"geometry":{"coordinates":[10.103723,53.831671],"type":"Point"},"properties":{"osm_id":"6465725779","tag":{"amenity":"waste_basket"}},"type":"Feature"},
	{"geometry":{"coordinates":[10.098967,53.835814],"type":"Point"},"properties":{"osm_id":"6465725780","tag":{"amenity":"waste_basket"}},"type":"Feature"},
	{"geometry":{"coordinates":[10.099308,53.839577],"type":"Point"},"properties":{"osm_id":"6465725784","tag":{"amenity":"waste_basket"}},"type":"Feature"},
	{"geometry":{"coordinates":[10.094166,53.848879],"type":"Point"},"properties":{"osm_id":"6465726419","tag":{"amenity":"waste_basket"}},"type":"Feature"},
	{"geometry":{"coordinates":[10.105627,53.80676],"type":"Point"},"properties":{"osm_id":"6983680631","tag":{"amenity":"waste_basket"}},"type":"Feature"},
	{"geometry":{"coordinates":[10.106222,53.807701],"type":"Point"},"properties":{"osm_id":"6983680632","tag":{"amenity":"waste_basket"}},"type":"Feature"}
]
}
