{
"type": "FeatureCollection",
"features": [
	{"geometry":{"coordinates":[10.080572,52.820932],"type":"Point"},"properties":{"osm_id":"30830730","tag":{"amenity":"recycling","recycling_type":"container"}},"type":"Feature"},
	{"geometry":{"coordinates":[10.102106,52.831535],"type":"Point"},"properties":{"osm_id":"31218987","tag":{"amenity":"recycling","recycling:glass":"yes","recycling_type":"container"}},"type":"Feature"},
	{"geometry":{"coordinates":[10.098782,52.834545],"type":"Point"},"properties":{"osm_id":"297696512","tag":{"amenity":"recycling","recycling:glass":"yes","recycling_type":"container"}},"type":"Feature"},
	{"geometry":{"coordinates":[10.091403,52.846778],"type":"Point"},"properties":{"osm_id":"877806940","tag":{"amenity":"recycling","location":"overground","recycling_type":"container"}},"type":"Feature"},
	{"geometry":{"coordinates":[10.079839,52.82127],"type":"Point"},"properties":{"osm_id":"6049698268","tag":{"amenity":"recycling","recycling:glass":"yes","recycling_type":"container"}},"type":"Feature"},
	{"geometry":{"coordinates":[10.093897,52.831296],"type":"Point"},"properties":{"osm_id":"6502376861","tag":{"amenity":"waste_basket"}},"type":"Feature"},
	{"geometry":{"coordinates":[10.095135,52.829212],"type":"Point"},"properties":{"osm_id":"6527777489","tag":{"amenity":"waste_basket"}},"type":"Feature"},
	{"geometry":{"coordinates":[10.102338,52.831531],"type":"Point"},"properties":{"osm_id":"6538308293","tag":{"amenity":"recycling","recycling:clothes":"yes","recycling_type":"container"}},"type":"Feature"},
	{"geometry":{"coordinates":[10.09394,52.827084],"type":"Point"},"properties":{"osm_id":"6538373086","tag":{"amenity":"waste_basket"}},"type":"Feature"},
	{"geometry":{"coordinates":[10.094809,52.827498],"type":"Point"},"properties":{"osm_id":"6546836534","tag":{"amenity":"waste_basket"}},"type":"Feature"},
	{"geometry":{"coordinates":[10.100032,52.829162],"type":"Point"},"properties":{"osm_id":"7206897537","tag":{"amenity":"waste_basket","operator":"Netto"}},"type":"Feature"},
	{"geometry":{"coordinates":[10.100251,52.828856],"type":"Point"},"properties":{"osm_id":"7419480522","tag":{"amenity":"recycling","recycling:clothes":"yes"}},"type":"Feature"},
	{"geometry":{"coordinates":[10.100998,52.828983],"type":"Point"},"properties":{"osm_id":"7419480721","tag":{"amenity":"waste_basket"}},"type":"Feature"},
	{"geometry":{"coordinates":[10.091385,52.83239],"type":"Point"},"properties":{"osm_id":"7428752106","tag":{"amenity":"waste_basket"}},"type":"Feature"},
	{"geometry":{"coordinates":[10.087769,52.831695],"type":"Point"},"properties":{"osm_id":"7449748848","tag":{"amenity":"waste_basket"}},"type":"Feature"},
	{"geometry":{"coordinates":[10.087535,52.831873],"type":"Point"},"properties":{"osm_id":"7449748854","tag":{"amenity":"waste_basket"}},"type":"Feature"},
	{"geometry":{"coordinates":[10.087145,52.831939],"type":"Point"},"properties":{"osm_id":"7449748856","tag":{"amenity":"waste_basket"}},"type":"Feature"},
	{"geometry":{"coordinates":[10.086971,52.831701],"type":"Point"},"properties":{"osm_id":"7449748863","tag":{"amenity":"waste_basket"}},"type":"Feature"},
	{"geometry":{"coordinates":[10.076281,52.841858],"type":"Point"},"properties":{"osm_id":"7449791380","tag":{"amenity":"waste_basket"}},"type":"Feature"},
	{"geometry":{"coordinates":[10.078132,52.828999],"type":"Point"},"properties":{"osm_id":"7481827567","tag":{"amenity":"waste_basket"}},"type":"Feature"},
	{"geometry":{"coordinates":[10.093918,52.831748],"type":"Point"},"properties":{"osm_id":"7501510522","tag":{"amenity":"waste_basket"}},"type":"Feature"},
	{"geometry":{"coordinates":[10.08188,52.824368],"type":"Point"},"properties":{"osm_id":"7554135525","tag":{"amenity":"recycling","recycling:clothes":"yes"}},"type":"Feature"},
	{"geometry":{"coordinates":[10.104656,52.827992],"type":"Point"},"properties":{"osm_id":"7556554581","tag":{"amenity":"waste_basket"}},"type":"Feature"},
	{"geometry":{"coordinates":[10.094466,52.831048],"type":"Point"},"properties":{"osm_id":"7556555997","tag":{"amenity":"waste_basket"}},"type":"Feature"},
	{"geometry":{"coordinates":[10.09448,52.831161],"type":"Point"},"properties":{"osm_id":"7556585000","tag":{"amenity":"waste_basket"}},"type":"Feature"},
	{"geometry":{"coordinates":[10.056538,52.813803],"type":"Point"},"properties":{"osm_id":"7696358978","tag":{"amenity":"recycling","recycling:glass_bottles":"yes","recycling_type":"container"}},"type":"Feature"},
	{"geometry":{"coordinates":[10.105493,52.839252],"type":"Point"},"properties":{"osm_id":"7832313935","tag":{"amenity":"waste_basket"}},"type":"Feature"}
]
}
