{
"type": "FeatureCollection",
"features": [
	{"geometry":{"coordinates":[10.083602,49.943489],"type":"Point"},"properties":{"osm_id":"267663665","tag":{"amenity":"recycling","recycling:glass":"yes","recycling_type":"container"}},"type":"Feature"},
	{"geometry":{"coordinates":[10.077313,49.946303],"type":"Point"},"properties":{"osm_id":"5020864428","tag":{"amenity":"recycling","recycling_type":"container"}},"type":"Feature"},
	{"geometry":{"coordinates":[10.020757,49.944237],"type":"Point"},"properties":{"osm_id":"7100289141","tag":{"amenity":"waste_basket","waste":"trash"}},"type":"Feature"},
	{"geometry":{"coordinates":[10.073718,49.898162],"type":"Point"},"properties":{"name":"Altkleidercontainer BRK","osm_id":"9060161054","tag":{"amenity":"recycling","clothes":"yes"}},"type":"Feature"}
]
}
