{
"type": "FeatureCollection",
"features": [
	{"geometry":{"coordinates":[10.107265,48.730814],"type":"Point"},"properties":{"osm_id":"616711346","tag":{"amenity":"recycling"}},"type":"Feature"},
	{"geometry":{"coordinates":[10.070682,48.725985],"type":"Point"},"properties":{"osm_id":"739657224","tag":{"amenity":"recycling"}},"type":"Feature"},
	{"geometry":{"coordinates":[10.106007,48.735547],"type":"Point"},"properties":{"osm_id":"3099111147","tag":{"amenity":"recycling","recycling_type":"container"}},"type":"Feature"},
	{"geometry":{"coordinates":[10.106114,48.736106],"type":"Point"},"properties":{"osm_id":"3111814843","tag":{"amenity":"waste_basket"}},"type":"Feature"},
	{"geometry":{"coordinates":[10.07355,48.693342],"type":"Point"},"properties":{"osm_id":"3506187892","tag":{"amenity":"waste_basket"}},"type":"Feature"},
	{"geometry":{"coordinates":[10.082669,48.725706],"type":"Point"},"properties":{"osm_id":"3519201163","tag":{"amenity":"recycling","location":"overground","recycling:cans":"yes","recycling:clothes":"yes","recycling:glass_bottles":"yes","recycling_type":"container"}},"type":"Feature"},
	{"geometry":{"coordinates":[10.064253,48.693492],"type":"Point"},"properties":{"osm_id":"5062082642","tag":{"amenity":"recycling","operator":"M\u00fcllbewusstsein Landkreis Heidenheim","recycling:cans":"yes","recycling:clothes":"yes","recycling:glass":"no","recycling:glass_bottles":"yes","recycling:shoes":"yes","recycling_type":"container"}},"type":"Feature"},
	{"geometry":{"coordinates":[10.059838,48.694953],"type":"Point"},"properties":{"osm_id":"5062445742","tag":{"amenity":"recycling","operator":"Landkreis Heidenheim","recycling:cans":"yes","recycling:clothes":"yes","recycling:glass":"no","recycling:glass_bottles":"yes","recycling:shoes":"yes","recycling_type":"container"}},"type":"Feature"},
	{"geometry":{"coordinates":[10.053841,48.692104],"type":"Point"},"properties":{"osm_id":"5089938043","tag":{"amenity":"recycling","operator":"Landkreis Heidenheim","recycling:batteries":"no","recycling:cans":"yes","recycling:clothes":"yes","recycling:glass":"yes","recycling:glass_bottles":"yes","recycling:shoes":"yes","recycling_type":"container"}},"type":"Feature"},
	{"geometry":{"coordinates":[10.066783,48.69158],"type":"Point"},"properties":{"osm_id":"5111245321","tag":{"amenity":"recycling","recycling:cans":"no","recycling:glass_bottles":"yes","recycling_type":"container"}},"type":"Feature"}
]
}
