{
"type": "FeatureCollection",
"features": [
	{"geometry":{"coordinates":[10.086878,48.47459],"type":"Point"},"properties":{"osm_id":"273511913","tag":{"amenity":"recycling","recycling:glass":"yes","recycling_type":"container"}},"type":"Feature"},
	{"geometry":{"coordinates":[10.06075,48.483792],"type":"Point"},"properties":{"osm_id":"276804350","tag":{"amenity":"recycling","location":"overground","recycling:clothes":"yes","recycling:glass":"no","recycling:glass_bottles":"yes","recycling:paper":"yes","recycling_type":"container"}},"type":"Feature"},
	{"geometry":{"coordinates":[10.021604,48.49561],"type":"Point"},"properties":{"osm_id":"276964305","tag":{"amenity":"recycling","recycling:glass":"yes"}},"type":"Feature"},
	{"geometry":{"coordinates":[10.020735,48.505204],"type":"Point"},"properties":{"osm_id":"292755499","tag":{"amenity":"recycling","recycling:glass_bottles":"yes","recycling_type":"container"}},"type":"Feature"},
	{"geometry":{"coordinates":[10.106387,48.495369],"type":"Point"},"properties":{"osm_id":"836629325","tag":{"amenity":"recycling","recycling_type":"container"}},"type":"Feature"},
	{"geometry":{"coordinates":[10.069181,48.494396],"type":"Point"},"properties":{"osm_id":"1420248899","tag":{"amenity":"recycling","recycling_type":"centre"}},"type":"Feature"},
	{"geometry":{"coordinates":[10.021729,48.496005],"type":"Point"},"properties":{"osm_id":"4505923338","tag":{"amenity":"waste_basket"}},"type":"Feature"},
	{"geometry":{"coordinates":[10.02716,48.49528],"type":"Point"},"properties":{"osm_id":"4518732604","tag":{"amenity":"recycling","recycling:clothes":"yes","recycling:shoes":"yes","recycling_type":"container"}},"type":"Feature"},
	{"geometry":{"coordinates":[10.023739,48.484356],"type":"Point"},"properties":{"osm_id":"7572626424","tag":{"amenity":"waste_basket"}},"type":"Feature"}
]
}
