{
"type": "FeatureCollection",
"lastupdate": "2020-08-03T00:00:00Z",
"features": [
	{"geometry":{"coordinates":[10.032287,46.980424],"type":"Point"},"properties":{"name":"Bauhof Gaschurn","osm_id":"6835550695","tag":{"amenity":"recycling","operator":"Gemeinde Gaschurn","operator:type":"public","recycling_type":"centre"}},"type":"Feature"}
]
}
