{
"type": "FeatureCollection",
"features": [
	{"geometry":{"coordinates":[10.032287,46.980425],"type":"Point"},"properties":{"name":"Bauhof Gaschurn","osm_id":"6835550695","tag":{"amenity":"recycling","operator":"Gemeinde Gaschurn","operator:type":"public","recycling_type":"centre"}},"type":"Feature"}
]
}
