{
"type": "FeatureCollection",
"features": [
	{"geometry":{"coordinates":[115.213096,-8.566414],"type":"Point"},"properties":{"name":"Tetra Pcks","osm_id":"2481896257","tag":{"amenity":"recycling","recycling_type":"container"}},"type":"Feature"}
]
}
