{
"type": "FeatureCollection",
"lastupdate": "2020-08-04T00:00:00Z",
"features": [
	{"geometry":{"coordinates":[3.979486,51.836665],"type":"Point"},"properties":{"osm_id":"2707425349","tag":{"amenity":"waste_basket"}},"type":"Feature"},
	{"geometry":{"coordinates":[3.98238,51.836848],"type":"Point"},"properties":{"osm_id":"2707425363","tag":{"amenity":"waste_basket"}},"type":"Feature"},
	{"geometry":{"coordinates":[3.98385,51.841366],"type":"Point"},"properties":{"name":"Doe Mee, Verlos de Zee","osm_id":"3672459435","tag":{"amenity":"waste_basket","website":"http://www.verlosdezee.nl/"}},"type":"Feature"},
	{"geometry":{"coordinates":[3.969105,51.837242],"type":"Point"},"properties":{"osm_id":"3672507379","tag":{"amenity":"waste_basket"}},"type":"Feature"}
]
}
