{
"type": "FeatureCollection",
"features": [
	{"geometry":{"coordinates":[3.979486,51.836666],"type":"Point"},"properties":{"osm_id":"2707425349","tag":{"amenity":"waste_basket"}},"type":"Feature"},
	{"geometry":{"coordinates":[3.982381,51.836849],"type":"Point"},"properties":{"osm_id":"2707425363","tag":{"amenity":"waste_basket"}},"type":"Feature"},
	{"geometry":{"coordinates":[3.983851,51.841367],"type":"Point"},"properties":{"name":"Doe Mee, Verlos de Zee","osm_id":"3672459435","tag":{"amenity":"waste_basket","website":"http://www.verlosdezee.nl/"}},"type":"Feature"},
	{"geometry":{"coordinates":[3.969106,51.837243],"type":"Point"},"properties":{"osm_id":"3672507379","tag":{"amenity":"waste_basket"}},"type":"Feature"}
]
}
