{
"type": "FeatureCollection",
"lastupdate": "2020-08-01T00:00:00Z",
"features": [
	{"geometry":{"coordinates":[4.020864,43.61383],"type":"Point"},"properties":{"osm_id":"3750180648","tag":{"amenity":"recycling","location":"underground","recycling_type":"container"}},"type":"Feature"},
	{"geometry":{"coordinates":[4.010836,43.617133],"type":"Point"},"properties":{"osm_id":"3750270554","tag":{"amenity":"recycling","location":"underground","recycling_type":"container"}},"type":"Feature"},
	{"geometry":{"coordinates":[4.014592,43.617842],"type":"Point"},"properties":{"osm_id":"3750283462","tag":{"amenity":"recycling","recycling_type":"container"}},"type":"Feature"},
	{"geometry":{"coordinates":[4.007103,43.615842],"type":"Point"},"properties":{"osm_id":"3750344006","tag":{"amenity":"waste_basket"}},"type":"Feature"},
	{"geometry":{"coordinates":[4.0112,43.621485],"type":"Point"},"properties":{"osm_id":"3750386032","tag":{"amenity":"recycling","location":"overground","recycling_type":"container"}},"type":"Feature"},
	{"geometry":{"coordinates":[4.011992,43.614207],"type":"Point"},"properties":{"osm_id":"3758830013","tag":{"amenity":"recycling","location":"underground","recycling_type":"container"}},"type":"Feature"},
	{"geometry":{"coordinates":[4.009918,43.61334],"type":"Point"},"properties":{"osm_id":"3758830014","tag":{"amenity":"recycling","location":"underground","recycling_type":"container"}},"type":"Feature"},
	{"geometry":{"coordinates":[4.006874,43.612771],"type":"Point"},"properties":{"osm_id":"3758830015","tag":{"amenity":"recycling","location":"underground","recycling_type":"container"}},"type":"Feature"},
	{"geometry":{"coordinates":[3.993797,43.617224],"type":"Point"},"properties":{"osm_id":"3758830018","tag":{"amenity":"waste_basket"}},"type":"Feature"},
	{"geometry":{"coordinates":[3.957732,43.592502],"type":"Point"},"properties":{"osm_id":"3760419252","tag":{"amenity":"recycling","recycling_type":"container"}},"type":"Feature"},
	{"geometry":{"coordinates":[4.007668,43.614085],"type":"Point"},"properties":{"osm_id":"3814118523","tag":{"amenity":"waste_basket"}},"type":"Feature"},
	{"geometry":{"coordinates":[4.007249,43.614145],"type":"Point"},"properties":{"osm_id":"3833361775","tag":{"amenity":"recycling","recycling_type":"container"}},"type":"Feature"},
	{"geometry":{"coordinates":[4.022546,43.612464],"type":"Point"},"properties":{"osm_id":"3887941922","tag":{"amenity":"waste_basket"}},"type":"Feature"},
	{"geometry":{"coordinates":[4.016749,43.619269],"type":"Point"},"properties":{"osm_id":"3898622213","tag":{"amenity":"recycling","recycling_type":"container"}},"type":"Feature"},
	{"geometry":{"coordinates":[4.009046,43.619033],"type":"Point"},"properties":{"osm_id":"3898622221","tag":{"amenity":"waste_basket"}},"type":"Feature"},
	{"geometry":{"coordinates":[4.020563,43.614233],"type":"Point"},"properties":{"osm_id":"3899396532","tag":{"amenity":"recycling","location":"underground","recycling_type":"container"}},"type":"Feature"},
	{"geometry":{"coordinates":[4.005721,43.62239],"type":"Point"},"properties":{"osm_id":"3902818069","tag":{"amenity":"recycling","recycling:glass":"yes","recycling:glass_bottles":"yes","recycling_type":"container"}},"type":"Feature"},
	{"geometry":{"coordinates":[3.957541,43.642163],"type":"Point"},"properties":{"osm_id":"4001381025","tag":{"amenity":"recycling","recycling:glass":"yes","recycling:glass_bottles":"yes","recycling_type":"container"}},"type":"Feature"},
	{"geometry":{"coordinates":[3.999279,43.616443],"type":"Point"},"properties":{"osm_id":"4469655838","tag":{"amenity":"waste_basket"}},"type":"Feature"},
	{"geometry":{"coordinates":[3.999187,43.616301],"type":"Point"},"properties":{"osm_id":"4469655839","tag":{"amenity":"waste_basket"}},"type":"Feature"},
	{"geometry":{"coordinates":[4.008106,43.613538],"type":"Point"},"properties":{"osm_id":"5770057193","tag":{"amenity":"recycling","recycling_type":"container"}},"type":"Feature"}
]
}
