{
"type": "FeatureCollection",
"features": [
	{"geometry":{"coordinates":[4.020865,43.61383],"type":"Point"},"properties":{"osm_id":"3750180648","tag":{"amenity":"recycling","location":"underground","recycling_type":"container"}},"type":"Feature"},
	{"geometry":{"coordinates":[4.010837,43.617134],"type":"Point"},"properties":{"osm_id":"3750270554","tag":{"amenity":"recycling","location":"underground","recycling_type":"container"}},"type":"Feature"},
	{"geometry":{"coordinates":[4.014592,43.617843],"type":"Point"},"properties":{"osm_id":"3750283462","tag":{"amenity":"recycling","recycling_type":"container"}},"type":"Feature"},
	{"geometry":{"coordinates":[4.007104,43.615842],"type":"Point"},"properties":{"osm_id":"3750344006","tag":{"amenity":"waste_basket"}},"type":"Feature"},
	{"geometry":{"coordinates":[4.011201,43.621485],"type":"Point"},"properties":{"osm_id":"3750386032","tag":{"amenity":"recycling","location":"overground","recycling_type":"container"}},"type":"Feature"},
	{"geometry":{"coordinates":[4.011992,43.614208],"type":"Point"},"properties":{"osm_id":"3758830013","tag":{"amenity":"recycling","location":"underground","recycling_type":"container"}},"type":"Feature"},
	{"geometry":{"coordinates":[4.009918,43.613341],"type":"Point"},"properties":{"osm_id":"3758830014","tag":{"amenity":"recycling","location":"underground","recycling_type":"container"}},"type":"Feature"},
	{"geometry":{"coordinates":[4.006875,43.612772],"type":"Point"},"properties":{"osm_id":"3758830015","tag":{"amenity":"recycling","location":"underground","recycling_type":"container"}},"type":"Feature"},
	{"geometry":{"coordinates":[3.993798,43.617224],"type":"Point"},"properties":{"osm_id":"3758830018","tag":{"amenity":"waste_basket"}},"type":"Feature"},
	{"geometry":{"coordinates":[3.957732,43.592502],"type":"Point"},"properties":{"osm_id":"3760419252","tag":{"amenity":"recycling","recycling_type":"container"}},"type":"Feature"},
	{"geometry":{"coordinates":[4.007669,43.614086],"type":"Point"},"properties":{"osm_id":"3814118523","tag":{"amenity":"waste_basket"}},"type":"Feature"},
	{"geometry":{"coordinates":[4.00725,43.614146],"type":"Point"},"properties":{"osm_id":"3833361775","tag":{"amenity":"recycling","recycling_type":"container"}},"type":"Feature"},
	{"geometry":{"coordinates":[4.022546,43.612465],"type":"Point"},"properties":{"osm_id":"3887941922","tag":{"amenity":"waste_basket"}},"type":"Feature"},
	{"geometry":{"coordinates":[4.01675,43.619269],"type":"Point"},"properties":{"osm_id":"3898622213","tag":{"amenity":"recycling","recycling_type":"container"}},"type":"Feature"},
	{"geometry":{"coordinates":[4.009047,43.619033],"type":"Point"},"properties":{"osm_id":"3898622221","tag":{"amenity":"waste_basket"}},"type":"Feature"},
	{"geometry":{"coordinates":[4.020564,43.614234],"type":"Point"},"properties":{"osm_id":"3899396532","tag":{"amenity":"recycling","location":"underground","recycling_type":"container"}},"type":"Feature"},
	{"geometry":{"coordinates":[4.005722,43.622391],"type":"Point"},"properties":{"osm_id":"3902818069","tag":{"amenity":"recycling","recycling:glass":"yes","recycling:glass_bottles":"yes","recycling_type":"container"}},"type":"Feature"},
	{"geometry":{"coordinates":[3.957541,43.642164],"type":"Point"},"properties":{"osm_id":"4001381025","tag":{"amenity":"recycling","recycling:glass":"yes","recycling:glass_bottles":"yes","recycling_type":"container"}},"type":"Feature"},
	{"geometry":{"coordinates":[3.999279,43.616443],"type":"Point"},"properties":{"osm_id":"4469655838","tag":{"amenity":"waste_basket"}},"type":"Feature"},
	{"geometry":{"coordinates":[3.999188,43.616302],"type":"Point"},"properties":{"osm_id":"4469655839","tag":{"amenity":"waste_basket"}},"type":"Feature"},
	{"geometry":{"coordinates":[4.008106,43.613538],"type":"Point"},"properties":{"osm_id":"5770057193","tag":{"amenity":"recycling","recycling_type":"container"}},"type":"Feature"},
	{"geometry":{"coordinates":[4.042231,43.642761],"type":"Point"},"properties":{"osm_id":"7810140412","tag":{"amenity":"recycling","recycling:glass":"yes","recycling:glass_bottles":"yes","recycling_type":"container"}},"type":"Feature"}
]
}
