{
"type": "FeatureCollection",
"features": [
	{"geometry":{"coordinates":[175.109923,-37.072604],"type":"Point"},"properties":{"name":"Kauri Grove","osm_id":"2132763865","tag":{"natural":"tree"}},"type":"Feature"}
]
}
