{
"type": "FeatureCollection",
"features": [
	{"geometry":{"coordinates":[10.69602,50.282543],"type":"Point"},"properties":{"name":"7 Eichen","osm_id":"676821726","tag":{"denotation":"natural_monument","natural":"tree"}},"type":"Feature"},
	{"geometry":{"coordinates":[10.684178,50.267945],"type":"Point"},"properties":{"name":"Teufelseiche","osm_id":"2087349223","tag":{"natural":"tree"}},"type":"Feature"}
]
}
