{
"type": "FeatureCollection",
"features": [
	{"geometry":{"coordinates":[-0.317786,42.499717],"type":"Point"},"properties":{"osm_id":"3804793954","tag":{"amenity":"recycling","recycling:cans":"yes","recycling:glass_bottles":"yes","recycling:paper":"yes","recycling:plastic":"yes","recycling_type":"container"}},"type":"Feature"},
	{"geometry":{"coordinates":[-0.338498,42.525387],"type":"Point"},"properties":{"osm_id":"4084090147","tag":{"addr:city":"Latas","addr:postcode":"22613","amenity":"recycling","recycling:cans":"yes","recycling:glass_bottles":"yes","recycling:paper":"yes","recycling:plastic":"yes","recycling_type":"container"}},"type":"Feature"},
	{"geometry":{"coordinates":[-0.343593,42.549647],"type":"Point"},"properties":{"osm_id":"4431692518","tag":{"amenity":"recycling","recycling:glass_bottles":"yes","recycling:organic_waste":"yes","recycling:paper":"yes","recycling:plastic_bottles":"yes","recycling_type":"container"}},"type":"Feature"},
	{"geometry":{"coordinates":[-0.33765,42.528847],"type":"Point"},"properties":{"osm_id":"4463476709","tag":{"amenity":"waste_basket"}},"type":"Feature"},
	{"geometry":{"coordinates":[-0.338036,42.52804],"type":"Point"},"properties":{"osm_id":"4463577292","tag":{"amenity":"waste_basket"}},"type":"Feature"},
	{"geometry":{"coordinates":[-0.337862,42.527148],"type":"Point"},"properties":{"osm_id":"4464109150","tag":{"amenity":"waste_basket"}},"type":"Feature"},
	{"geometry":{"coordinates":[-0.335356,42.525597],"type":"Point"},"properties":{"osm_id":"4464682269","tag":{"amenity":"waste_basket"}},"type":"Feature"},
	{"geometry":{"coordinates":[-0.316855,42.551279],"type":"Point"},"properties":{"osm_id":"6604809014","tag":{"amenity":"recycling","material":"plastic","recycling:organic_waste":"yes","recycling:plastic_bottles":"yes","recycling:plastic_packaging":"yes","recycling_type":"container"}},"type":"Feature"}
]
}
