{
"type": "FeatureCollection",
"features": [
	{"geometry":{"coordinates":[-0.308161,5.669866],"type":"Point"},"properties":{"name":"Ga Odumase","osm_id":"8577168407","tag":{"addr:district":"Ga West","amenity":"recycling","description":"Production of plastic flakes","email":"narteytettehe@gmail.com","opening_hours":"Mo-Sa 09:00-17:00; Su 13:30-17:00","operator":"Ernest Nartey-Tetteh","operator:type":"private","phone":"+233 26 262 6916","recycling:plastic":"yes","recycling_type":"centre"}},"type":"Feature"},
	{"geometry":{"coordinates":[-0.286056,5.702183],"type":"Point"},"properties":{"name":"Ezov Environmental Services","osm_id":"8577168409","tag":{"addr:district":"Ga North","amenity":"recycling","description":"Grinding of plastic waste","email":"ezovernviron@gmail.com","opening_hours":"Mo-Sa 08:00-17:00","operator":"Ezov Environmental Services","operator:type":"private","phone":"+233 55 036 4378; +233 24 265 2303","recycling:plastic":"yes","recycling:plastic_bottles":"yes","recycling_type":"centre"}},"type":"Feature"}
]
}
