{
"type": "FeatureCollection",
"lastupdate": "2020-08-04T00:00:00Z",
"features": [
	{"geometry":{"coordinates":[-4.937548,56.255761],"type":"Point"},"properties":{"name":"Cairndow Inn","osm_id":"6390503885","tag":{"amenity":"recycling","recycling:glass_bottles":"yes"}},"type":"Feature"}
]
}
