{
"type": "FeatureCollection",
"features": [
	{"geometry":{"coordinates":[-4.937548,56.255762],"type":"Point"},"properties":{"name":"Cairndow Inn","osm_id":"6390503885","tag":{"amenity":"recycling","recycling:glass_bottles":"yes"}},"type":"Feature"}
]
}
