{
"type": "FeatureCollection",
"features": [
	{"geometry":{"coordinates":[-117.701599,33.539626],"type":"Point"},"properties":{"osm_id":"7855372892","tag":{"addr:city":"Laguna Niguel","addr:housenumber":"24522","addr:postcode":"92677","addr:street":"Kings Road","building":"yes","height":"7.35"}},"type":"Feature"}
]
}
