{
"type": "FeatureCollection",
"features": [
	{"geometry":{"coordinates":[-122.878255,44.545684],"type":"Point"},"properties":{"name":"Recycling depot","osm_id":"2474782323","tag":{"amenity":"recycling"}},"type":"Feature"},
	{"geometry":{"coordinates":[-122.900345,44.53827],"type":"Point"},"properties":{"osm_id":"6907750527","tag":{"amenity":"waste_basket","material":"metal"}},"type":"Feature"}
]
}
