{
"type": "FeatureCollection",
"features": [
	{"geometry":{"coordinates":[2.10554,42.911039],"type":"Point"},"properties":{"name":"Chene Vieux","osm_id":"8400255964","tag":{"natural":"tree"}},"type":"Feature"},
	{"geometry":{"coordinates":[2.105957,42.91047],"type":"Point"},"properties":{"name":"Sapin Harpe","osm_id":"8400255965","tag":{"leaf_type":"needleleaved","natural":"tree"}},"type":"Feature"}
]
}
