{
"type": "FeatureCollection",
"lastupdate": "2020-08-03T00:00:00Z",
"features": [
	{"geometry":{"coordinates":[2.43713,41.53284],"type":"Point"},"properties":{"osm_id":"1686818749","tag":{"amenity":"waste_basket"}},"type":"Feature"},
	{"geometry":{"coordinates":[2.432059,41.530107],"type":"Point"},"properties":{"barrier":"gate","osm_id":"2164321506"},"type":"Feature"},
	{"geometry":{"coordinates":[2.448015,41.536938],"type":"Point"},"properties":{"name":"taca d'oli","osm_id":"2276093948","tag":{"amenity":"recycling","recycling_type":"centre"}},"type":"Feature"},
	{"geometry":{"coordinates":[2.39437,41.545644],"type":"Point"},"properties":{"osm_id":"3657636124","tag":{"amenity":"waste_basket"}},"type":"Feature"},
	{"geometry":{"coordinates":[2.434829,41.540255],"type":"Point"},"properties":{"osm_id":"4147219943","tag":{"amenity":"recycling"}},"type":"Feature"},
	{"geometry":{"coordinates":[2.426415,41.552721],"type":"Point"},"properties":{"osm_id":"4883141317","tag":{"amenity":"recycling"}},"type":"Feature"},
	{"geometry":{"coordinates":[2.433591,41.525466],"type":"Point"},"properties":{"osm_id":"5293467321","tag":{"amenity":"waste_basket"}},"type":"Feature"},
	{"geometry":{"coordinates":[2.447667,41.553651],"type":"Point"},"properties":{"osm_id":"6373891830","tag":{"amenity":"recycling","recycling_type":"container"}},"type":"Feature"},
	{"geometry":{"coordinates":[2.44893,41.536182],"type":"Point"},"properties":{"osm_id":"7177788121","tag":{"amenity":"recycling","recycling:cans":"yes","recycling:cardboard":"yes","recycling:glass_bottles":"yes","recycling:paper":"yes","recycling:plastic":"yes","recycling:plastic_bottles":"yes","recycling:plastic_packaging":"yes","recycling:waste":"yes","recycling_type":"container"}},"type":"Feature"},
	{"geometry":{"coordinates":[2.449898,41.536317],"type":"Point"},"properties":{"osm_id":"7177788127","tag":{"amenity":"recycling","recycling:cans":"yes","recycling:cardboard":"yes","recycling:glass_bottles":"yes","recycling:paper":"yes","recycling:plastic":"yes","recycling:plastic_bottles":"yes","recycling:plastic_packaging":"yes","recycling:waste":"yes","recycling_type":"container"}},"type":"Feature"},
	{"geometry":{"coordinates":[2.455457,41.539889],"type":"Point"},"properties":{"osm_id":"7177788134","tag":{"amenity":"recycling","recycling:cans":"yes","recycling:cardboard":"yes","recycling:glass_bottles":"yes","recycling:paper":"yes","recycling:plastic":"yes","recycling:plastic_bottles":"yes","recycling:plastic_packaging":"yes","recycling:waste":"yes","recycling_type":"container"}},"type":"Feature"},
	{"geometry":{"coordinates":[2.451432,41.537336],"type":"Point"},"properties":{"osm_id":"7177788135","tag":{"amenity":"recycling","recycling:cans":"yes","recycling:cardboard":"yes","recycling:glass_bottles":"yes","recycling:paper":"yes","recycling:plastic":"yes","recycling:plastic_bottles":"yes","recycling:plastic_packaging":"yes","recycling:waste":"yes","recycling_type":"container"}},"type":"Feature"},
	{"geometry":{"coordinates":[2.456239,41.541164],"type":"Point"},"properties":{"osm_id":"7177838294","tag":{"amenity":"recycling","recycling:cans":"yes","recycling:cardboard":"yes","recycling:glass_bottles":"yes","recycling:paper":"yes","recycling:plastic":"yes","recycling:plastic_bottles":"yes","recycling:plastic_packaging":"yes","recycling:waste":"yes","recycling_type":"container"}},"type":"Feature"},
	{"geometry":{"coordinates":[2.453167,41.53911],"type":"Point"},"properties":{"osm_id":"7188664988","tag":{"amenity":"recycling","recycling:cans":"yes","recycling:cardboard":"yes","recycling:glass_bottles":"yes","recycling:paper":"yes","recycling:plastic":"yes","recycling:plastic_bottles":"yes","recycling:plastic_packaging":"yes","recycling:waste":"yes","recycling_type":"container"}},"type":"Feature"},
	{"geometry":{"coordinates":[2.454772,41.54032],"type":"Point"},"properties":{"osm_id":"7188664989","tag":{"amenity":"recycling","recycling:cans":"yes","recycling:cardboard":"yes","recycling:glass_bottles":"yes","recycling:paper":"yes","recycling:plastic":"yes","recycling:plastic_bottles":"yes","recycling:plastic_packaging":"yes","recycling:waste":"yes","recycling_type":"container"}},"type":"Feature"},
	{"geometry":{"coordinates":[2.391536,41.516487],"type":"Point"},"properties":{"barrier":"gate","osm_id":"7402507652"},"type":"Feature"}
]
}
