{
"type": "FeatureCollection",
"features": [
	{"geometry":{"coordinates":[-70.950994,-29.978204],"type":"Point"},"properties":{"name":"pimiento","osm_id":"4944960623","tag":{"natural":"tree"}},"type":"Feature"},
	{"geometry":{"coordinates":[-70.950967,-29.978221],"type":"Point"},"properties":{"osm_id":"4944960624","tag":{"natural":"tree"}},"type":"Feature"},
	{"geometry":{"coordinates":[-70.950921,-29.978249],"type":"Point"},"properties":{"osm_id":"4944960625","tag":{"natural":"tree"}},"type":"Feature"},
	{"geometry":{"coordinates":[-70.950816,-29.978291],"type":"Point"},"properties":{"osm_id":"4944960626","tag":{"natural":"tree"}},"type":"Feature"},
	{"geometry":{"coordinates":[-70.95077,-29.978313],"type":"Point"},"properties":{"osm_id":"4944960627","tag":{"natural":"tree"}},"type":"Feature"},
	{"geometry":{"coordinates":[-70.950738,-29.978334],"type":"Point"},"properties":{"osm_id":"4944960628","tag":{"natural":"tree"}},"type":"Feature"},
	{"geometry":{"coordinates":[-70.9507,-29.97835],"type":"Point"},"properties":{"osm_id":"4944960629","tag":{"natural":"tree"}},"type":"Feature"},
	{"geometry":{"coordinates":[-70.950553,-29.978425],"type":"Point"},"properties":{"osm_id":"4944960631","tag":{"natural":"tree"}},"type":"Feature"},
	{"geometry":{"coordinates":[-70.950497,-29.978456],"type":"Point"},"properties":{"osm_id":"4944960632","tag":{"natural":"tree"}},"type":"Feature"},
	{"geometry":{"coordinates":[-70.950863,-29.978272],"type":"Point"},"properties":{"osm_id":"4944960633","tag":{"natural":"tree"}},"type":"Feature"}
]
}
