{
"type": "FeatureCollection",
"features": [
	{"geometry":{"coordinates":[-70.950994,-29.978203],"type":"Point"},"properties":{"name":"pimiento","osm_id":"4944960623","tag":{"natural":"tree"}},"type":"Feature"},
	{"geometry":{"coordinates":[-70.950966,-29.978221],"type":"Point"},"properties":{"osm_id":"4944960624","tag":{"natural":"tree"}},"type":"Feature"},
	{"geometry":{"coordinates":[-70.950921,-29.978249],"type":"Point"},"properties":{"osm_id":"4944960625","tag":{"natural":"tree"}},"type":"Feature"},
	{"geometry":{"coordinates":[-70.950815,-29.97829],"type":"Point"},"properties":{"osm_id":"4944960626","tag":{"natural":"tree"}},"type":"Feature"},
	{"geometry":{"coordinates":[-70.950769,-29.978313],"type":"Point"},"properties":{"osm_id":"4944960627","tag":{"natural":"tree"}},"type":"Feature"},
	{"geometry":{"coordinates":[-70.950738,-29.978334],"type":"Point"},"properties":{"osm_id":"4944960628","tag":{"natural":"tree"}},"type":"Feature"},
	{"geometry":{"coordinates":[-70.9507,-29.978349],"type":"Point"},"properties":{"osm_id":"4944960629","tag":{"natural":"tree"}},"type":"Feature"},
	{"geometry":{"coordinates":[-70.950552,-29.978425],"type":"Point"},"properties":{"osm_id":"4944960631","tag":{"natural":"tree"}},"type":"Feature"},
	{"geometry":{"coordinates":[-70.950497,-29.978456],"type":"Point"},"properties":{"osm_id":"4944960632","tag":{"natural":"tree"}},"type":"Feature"},
	{"geometry":{"coordinates":[-70.950863,-29.978271],"type":"Point"},"properties":{"osm_id":"4944960633","tag":{"natural":"tree"}},"type":"Feature"}
]
}
