{
"type": "FeatureCollection",
"features": [
	{"geometry":{"coordinates":[107.135237,12.387786],"type":"Point"},"properties":{"name":"Twin Trees","osm_id":"4675087533","tag":{"natural":"tree"}},"type":"Feature"}
]
}
