{
"type": "FeatureCollection",
"features": [
	{"geometry":{"coordinates":[77.39564,12.909617],"type":"Point"},"properties":{"name":"Big Banyan Tree","osm_id":"760176073","tag":{"natural":"tree","wikidata":"Q5287736"}},"type":"Feature"},
	{"geometry":{"coordinates":[77.416767,12.922331],"type":"Point"},"properties":{"osm_id":"1140351501","tag":{"natural":"tree"}},"type":"Feature"}
]
}
