{
"type": "FeatureCollection",
"features": [
	{"geometry":{"coordinates":[12.440099,50.527685],"type":"Point"},"properties":{"osm_id":"3124376474","tag":{"leaf_cycle":"deciduous","leaf_type":"broadleaved","natural":"tree"}},"type":"Feature"},
	{"geometry":{"coordinates":[12.41084,50.537228],"type":"Point"},"properties":{"osm_id":"4004661698","tag":{"natural":"tree"}},"type":"Feature"},
	{"geometry":{"coordinates":[12.410956,50.537361],"type":"Point"},"properties":{"osm_id":"4004661699","tag":{"natural":"tree"}},"type":"Feature"},
	{"geometry":{"coordinates":[12.411499,50.537913],"type":"Point"},"properties":{"osm_id":"4004661705","tag":{"natural":"tree"}},"type":"Feature"},
	{"geometry":{"coordinates":[12.414954,50.541381],"type":"Point"},"properties":{"osm_id":"4004661780","tag":{"natural":"tree"}},"type":"Feature"},
	{"geometry":{"coordinates":[12.401346,50.542674],"type":"Point"},"properties":{"osm_id":"4004661808","tag":{"natural":"tree"}},"type":"Feature"},
	{"geometry":{"coordinates":[12.403155,50.544284],"type":"Point"},"properties":{"osm_id":"4004661876","tag":{"natural":"tree"}},"type":"Feature"},
	{"geometry":{"coordinates":[12.465396,50.565559],"type":"Point"},"properties":{"name":"Schweden Fichte","osm_id":"4357996469","tag":{"natural":"tree"}},"type":"Feature"},
	{"geometry":{"coordinates":[12.462452,50.516919],"type":"Point"},"properties":{"name":"Holzbachfichte","osm_id":"7251949773","tag":{"denotation":"natural_monument","diameter":"140 cm","leaf_cycle":"evergreen","leaf_type":"needleleaved","natural":"tree"}},"type":"Feature"},
	{"geometry":{"coordinates":[12.42173,50.563729],"type":"Point"},"properties":{"osm_id":"8821175686","tag":{"natural":"tree"}},"type":"Feature"}
]
}
