{
"type": "FeatureCollection",
"features": [
	{"geometry":{"coordinates":[12.399613,42.950143],"type":"Point"},"properties":{"osm_id":"2900598704","tag":{"natural":"tree"}},"type":"Feature"},
	{"geometry":{"coordinates":[12.402917,42.951438],"type":"Point"},"properties":{"osm_id":"2900617609","tag":{"natural":"tree"}},"type":"Feature"},
	{"geometry":{"coordinates":[12.412043,42.981897],"type":"Point"},"properties":{"osm_id":"5175021058","tag":{"natural":"tree"}},"type":"Feature"},
	{"geometry":{"coordinates":[12.412078,42.981958],"type":"Point"},"properties":{"osm_id":"5175021059","tag":{"natural":"tree"}},"type":"Feature"},
	{"geometry":{"coordinates":[12.412013,42.981852],"type":"Point"},"properties":{"osm_id":"5175021060","tag":{"natural":"tree"}},"type":"Feature"},
	{"geometry":{"coordinates":[12.411971,42.981788],"type":"Point"},"properties":{"osm_id":"5175021061","tag":{"natural":"tree"}},"type":"Feature"},
	{"geometry":{"coordinates":[12.41193,42.981719],"type":"Point"},"properties":{"osm_id":"5175021062","tag":{"natural":"tree"}},"type":"Feature"},
	{"geometry":{"coordinates":[12.402654,42.964573],"type":"Point"},"properties":{"name":"Roverelle della Madonna dei Bagni","osm_id":"5204023386","tag":{"denotation":"natural_monument","genus":"Quercus pubescens Willd.","leaf_cycle":"deciduous","leaf_type":"broadleaved","natural":"tree"}},"type":"Feature"}
]
}
