{
"type": "FeatureCollection",
"features": [
	{"geometry":{"coordinates":[12.399612,42.950142],"type":"Point"},"properties":{"osm_id":"2900598704","tag":{"natural":"tree"}},"type":"Feature"},
	{"geometry":{"coordinates":[12.402917,42.951437],"type":"Point"},"properties":{"osm_id":"2900617609","tag":{"natural":"tree"}},"type":"Feature"},
	{"geometry":{"coordinates":[12.412042,42.981897],"type":"Point"},"properties":{"osm_id":"5175021058","tag":{"natural":"tree"}},"type":"Feature"},
	{"geometry":{"coordinates":[12.412077,42.981958],"type":"Point"},"properties":{"osm_id":"5175021059","tag":{"natural":"tree"}},"type":"Feature"},
	{"geometry":{"coordinates":[12.412013,42.981852],"type":"Point"},"properties":{"osm_id":"5175021060","tag":{"natural":"tree"}},"type":"Feature"},
	{"geometry":{"coordinates":[12.41197,42.981787],"type":"Point"},"properties":{"osm_id":"5175021061","tag":{"natural":"tree"}},"type":"Feature"},
	{"geometry":{"coordinates":[12.41193,42.981718],"type":"Point"},"properties":{"osm_id":"5175021062","tag":{"natural":"tree"}},"type":"Feature"},
	{"geometry":{"coordinates":[12.402653,42.964573],"type":"Point"},"properties":{"name":"Roverelle della Madonna dei Bagni","osm_id":"5204023386","tag":{"denotation":"natural_monument","genus":"Quercus pubescens Willd.","leaf_cycle":"deciduous","leaf_type":"broadleaved","natural":"tree"}},"type":"Feature"}
]
}
