{
"type": "FeatureCollection",
"lastupdate": "2020-08-05T00:00:00Z",
"features": [
	{"geometry":{"coordinates":[-89.372019,41.95425],"type":"Point"},"properties":{"name":"Dumpster","osm_id":"3295870152","tag":{"amenity":"waste_basket"}},"type":"Feature"},
	{"geometry":{"coordinates":[-89.370234,41.953398],"type":"Point"},"properties":{"name":"Dumpster","osm_id":"3296011790","tag":{"amenity":"waste_basket"}},"type":"Feature"}
]
}
