{
"type": "FeatureCollection",
"features": [
	{"geometry":{"coordinates":[121.120923,13.945081],"type":"Point"},"properties":{"name":"FAB Disposal Area","osm_id":"8927233618","tag":{"amenity":"recycling","recycling_type":"centre"}},"type":"Feature"}
]
}
