{
"type": "FeatureCollection",
"features": [
	{"geometry":{"coordinates":[123.584101,10.269706],"type":"Point"},"properties":{"name":"Acacia","osm_id":"4358211415","tag":{"natural":"tree"}},"type":"Feature"}
]
}
