{
"type": "FeatureCollection",
"features": [
	{"geometry":{"coordinates":[123.5841,10.269705],"type":"Point"},"properties":{"name":"Acacia","osm_id":"4358211415","tag":{"natural":"tree"}},"type":"Feature"}
]
}
