{
"type": "FeatureCollection",
"features": [
	{"geometry":{"coordinates":[1.884308,42.465109],"type":"Point"},"properties":{"osm_id":"3009901101","tag":{"amenity":"waste_basket"}},"type":"Feature"},
	{"geometry":{"coordinates":[1.886247,42.465407],"type":"Point"},"properties":{"osm_id":"3009902359","tag":{"amenity":"recycling","recycling:PET":"yes","recycling:aluminium":"yes","recycling:cans":"yes","recycling:cardboard":"yes","recycling:glass_bottles":"yes","recycling:paper":"yes","recycling:plastic":"yes","recycling:plastic_bottles":"yes","recycling:plastic_packaging":"yes","recycling_type":"container"}},"type":"Feature"},
	{"geometry":{"coordinates":[1.881757,42.465441],"type":"Point"},"properties":{"osm_id":"3009902362","tag":{"amenity":"waste_basket"}},"type":"Feature"},
	{"geometry":{"coordinates":[1.880041,42.466469],"type":"Point"},"properties":{"osm_id":"3009902403","tag":{"amenity":"waste_basket"}},"type":"Feature"},
	{"geometry":{"coordinates":[1.879301,42.468186],"type":"Point"},"properties":{"osm_id":"3009902424","tag":{"amenity":"waste_basket"}},"type":"Feature"},
	{"geometry":{"coordinates":[1.879246,42.468393],"type":"Point"},"properties":{"osm_id":"3009902434","tag":{"amenity":"waste_basket"}},"type":"Feature"},
	{"geometry":{"coordinates":[1.924189,42.432061],"type":"Point"},"properties":{"osm_id":"3233143396","tag":{"amenity":"waste_basket"}},"type":"Feature"},
	{"geometry":{"coordinates":[1.924701,42.431462],"type":"Point"},"properties":{"osm_id":"3233174061","tag":{"amenity":"recycling","recycling:cans":"yes","recycling:glass_bottles":"yes","recycling:paper":"yes","recycling_type":"container"}},"type":"Feature"},
	{"geometry":{"coordinates":[1.925202,42.43975],"type":"Point"},"properties":{"osm_id":"4370377638","tag":{"amenity":"recycling"}},"type":"Feature"},
	{"geometry":{"coordinates":[1.928615,42.432344],"type":"Point"},"properties":{"name":"mini deixalleria","osm_id":"5727918922","tag":{"amenity":"recycling","recycling:batteries":"yes","recycling_type":"container"}},"type":"Feature"},
	{"geometry":{"coordinates":[1.888628,42.465983],"type":"Point"},"properties":{"osm_id":"6761485832","tag":{"amenity":"recycling","recycling:PET":"yes","recycling:aluminium":"yes","recycling:cans":"yes","recycling:cardboard":"yes","recycling:glass_bottles":"yes","recycling:paper":"yes","recycling:plastic":"yes","recycling:plastic_bottles":"yes","recycling:plastic_packaging":"yes","recycling_type":"container"}},"type":"Feature"}
]
}
