{
"type": "FeatureCollection",
"lastupdate": "2020-07-31T00:00:00Z",
"features": [
	{"geometry":{"coordinates":[1.884307,42.465108],"type":"Point"},"properties":{"osm_id":"3009901101","tag":{"amenity":"waste_basket"}},"type":"Feature"},
	{"geometry":{"coordinates":[1.886246,42.465407],"type":"Point"},"properties":{"osm_id":"3009902359","tag":{"amenity":"recycling","recycling:PET":"yes","recycling:aluminium":"yes","recycling:cans":"yes","recycling:cardboard":"yes","recycling:glass_bottles":"yes","recycling:paper":"yes","recycling:plastic":"yes","recycling:plastic_bottles":"yes","recycling:plastic_packaging":"yes","recycling_type":"container"}},"type":"Feature"},
	{"geometry":{"coordinates":[1.881756,42.46544],"type":"Point"},"properties":{"osm_id":"3009902362","tag":{"amenity":"waste_basket"}},"type":"Feature"},
	{"geometry":{"coordinates":[1.88004,42.466469],"type":"Point"},"properties":{"osm_id":"3009902403","tag":{"amenity":"waste_basket"}},"type":"Feature"},
	{"geometry":{"coordinates":[1.8793,42.468186],"type":"Point"},"properties":{"osm_id":"3009902424","tag":{"amenity":"waste_basket"}},"type":"Feature"},
	{"geometry":{"coordinates":[1.879245,42.468392],"type":"Point"},"properties":{"osm_id":"3009902434","tag":{"amenity":"waste_basket"}},"type":"Feature"},
	{"geometry":{"coordinates":[1.924189,42.432061],"type":"Point"},"properties":{"osm_id":"3233143396","tag":{"amenity":"waste_basket"}},"type":"Feature"},
	{"geometry":{"coordinates":[1.924701,42.431462],"type":"Point"},"properties":{"osm_id":"3233174061","tag":{"amenity":"recycling","recycling:cans":"yes","recycling:glass_bottles":"yes","recycling:paper":"yes","recycling_type":"container"}},"type":"Feature"},
	{"geometry":{"coordinates":[1.925201,42.43975],"type":"Point"},"properties":{"osm_id":"4370377638","tag":{"amenity":"recycling"}},"type":"Feature"},
	{"geometry":{"coordinates":[1.928614,42.432343],"type":"Point"},"properties":{"name":"mini deixalleria","osm_id":"5727918922","tag":{"amenity":"recycling","recycling:batteries":"yes","recycling_type":"container"}},"type":"Feature"},
	{"geometry":{"coordinates":[1.888627,42.465983],"type":"Point"},"properties":{"osm_id":"6761485832","tag":{"amenity":"recycling","recycling:PET":"yes","recycling:aluminium":"yes","recycling:cans":"yes","recycling:cardboard":"yes","recycling:glass_bottles":"yes","recycling:paper":"yes","recycling:plastic":"yes","recycling:plastic_bottles":"yes","recycling:plastic_packaging":"yes","recycling_type":"container"}},"type":"Feature"}
]
}
