{
"type": "FeatureCollection",
"features": [
	{"geometry":{"coordinates":[6.567282,49.81806],"type":"Point"},"properties":{"name":"Antoniushof","osm_id":"2510466745","tag":{"amenity":"recycling","recycling:green_waste":"yes","recycling_type":"centre"}},"type":"Feature"},
	{"geometry":{"coordinates":[6.582478,49.833766],"type":"Point"},"properties":{"osm_id":"5242768645","tag":{"amenity":"recycling","opening_hours":"Mo-Sa 07:00-20:00; Su,PH off","operator":"Zweckverband Abfallwirtschaft Region Trier","recycling:glass_bottles":"yes","recycling_type":"container"}},"type":"Feature"},
	{"geometry":{"coordinates":[6.504306,49.790526],"type":"Point"},"properties":{"osm_id":"6046340016","tag":{"amenity":"waste_basket"}},"type":"Feature"},
	{"geometry":{"coordinates":[6.504293,49.790191],"type":"Point"},"properties":{"osm_id":"6046340017","tag":{"amenity":"waste_basket"}},"type":"Feature"},
	{"geometry":{"coordinates":[6.504451,49.789597],"type":"Point"},"properties":{"osm_id":"6046340018","tag":{"amenity":"waste_basket"}},"type":"Feature"},
	{"geometry":{"coordinates":[6.513454,49.805596],"type":"Point"},"properties":{"osm_id":"7147293410","tag":{"amenity":"recycling","opening_hours":"Mo-Sa 07:00-20:00; Su,PH off","operator":"Zweckverband Abfallwirtschaft Region Trier","recycling:glass_bottles":"yes","recycling_type":"container"}},"type":"Feature"}
]
}
