{
"type": "FeatureCollection",
"features": [
	{"geometry":{"coordinates":[9.469044,41.037531],"type":"Point"},"properties":{"name":"Wild-Birne","osm_id":"6573361933","tag":{"genus":"Pyrus","leaf_cycle":"deciduous","leaf_type":"broadleaved","natural":"tree"}},"type":"Feature"}
]
}
