{
"type": "FeatureCollection",
"features": [
	{"geometry":{"coordinates":[10.994354,50.835271],"type":"Point"},"properties":{"name":"Kaiserlinde","osm_id":"343696888","tag":{"genus":"Tilia","genus:de":"Linde","leaf_cycle":"deciduous","leaf_type":"broadleaved","natural":"tree"}},"type":"Feature"},
	{"geometry":{"coordinates":[11.034725,50.836253],"type":"Point"},"properties":{"osm_id":"3421011093","tag":{"leaf_cycle":"deciduous","leaf_type":"broadleaved","natural":"tree"}},"type":"Feature"},
	{"geometry":{"coordinates":[11.057721,50.825736],"type":"Point"},"properties":{"osm_id":"4905715974","tag":{"leaf_cycle":"deciduous","leaf_type":"broadleaved","natural":"tree"}},"type":"Feature"},
	{"geometry":{"coordinates":[11.056628,50.826121],"type":"Point"},"properties":{"osm_id":"4905715975","tag":{"leaf_cycle":"deciduous","leaf_type":"broadleaved","natural":"tree"}},"type":"Feature"},
	{"geometry":{"coordinates":[11.069657,50.831719],"type":"Point"},"properties":{"osm_id":"6036759613","tag":{"natural":"tree"}},"type":"Feature"},
	{"geometry":{"coordinates":[11.069773,50.831651],"type":"Point"},"properties":{"osm_id":"6036759614","tag":{"natural":"tree"}},"type":"Feature"},
	{"geometry":{"coordinates":[11.052588,50.833921],"type":"Point"},"properties":{"osm_id":"7065872276","tag":{"natural":"tree"}},"type":"Feature"},
	{"geometry":{"coordinates":[11.052687,50.833998],"type":"Point"},"properties":{"osm_id":"7065872277","tag":{"natural":"tree"}},"type":"Feature"},
	{"geometry":{"coordinates":[11.05285,50.833497],"type":"Point"},"properties":{"osm_id":"7065872278","tag":{"natural":"tree"}},"type":"Feature"},
	{"geometry":{"coordinates":[11.056258,50.832854],"type":"Point"},"properties":{"osm_id":"7065880102","tag":{"natural":"tree"}},"type":"Feature"},
	{"geometry":{"coordinates":[11.042389,50.847247],"type":"Point"},"properties":{"osm_id":"7069126023","tag":{"natural":"tree"}},"type":"Feature"},
	{"geometry":{"coordinates":[11.040003,50.837878],"type":"Point"},"properties":{"osm_id":"7074530584","tag":{"natural":"tree"}},"type":"Feature"},
	{"geometry":{"coordinates":[11.039724,50.837841],"type":"Point"},"properties":{"osm_id":"7074554785","tag":{"natural":"tree"}},"type":"Feature"},
	{"geometry":{"coordinates":[11.039921,50.839631],"type":"Point"},"properties":{"osm_id":"7074554786","tag":{"natural":"tree"}},"type":"Feature"},
	{"geometry":{"coordinates":[11.039875,50.838962],"type":"Point"},"properties":{"osm_id":"7074554787","tag":{"natural":"tree"}},"type":"Feature"},
	{"geometry":{"coordinates":[11.039948,50.839236],"type":"Point"},"properties":{"osm_id":"7074554788","tag":{"natural":"tree"}},"type":"Feature"},
	{"geometry":{"coordinates":[11.040374,50.838652],"type":"Point"},"properties":{"osm_id":"7074554789","tag":{"natural":"tree"}},"type":"Feature"}
]
}
