{
"type": "FeatureCollection",
"features": [
	{"geometry":{"coordinates":[10.994355,50.835272],"type":"Point"},"properties":{"name":"Kaiserlinde","osm_id":"343696888","tag":{"genus":"Tilia","genus:de":"Linde","leaf_cycle":"deciduous","leaf_type":"broadleaved","natural":"tree"}},"type":"Feature"},
	{"geometry":{"coordinates":[11.034726,50.836254],"type":"Point"},"properties":{"osm_id":"3421011093","tag":{"leaf_cycle":"deciduous","leaf_type":"broadleaved","natural":"tree"}},"type":"Feature"},
	{"geometry":{"coordinates":[11.057722,50.825737],"type":"Point"},"properties":{"osm_id":"4905715974","tag":{"leaf_cycle":"deciduous","leaf_type":"broadleaved","natural":"tree"}},"type":"Feature"},
	{"geometry":{"coordinates":[11.056629,50.826122],"type":"Point"},"properties":{"osm_id":"4905715975","tag":{"leaf_cycle":"deciduous","leaf_type":"broadleaved","natural":"tree"}},"type":"Feature"},
	{"geometry":{"coordinates":[11.069658,50.83172],"type":"Point"},"properties":{"osm_id":"6036759613","tag":{"natural":"tree"}},"type":"Feature"},
	{"geometry":{"coordinates":[11.069773,50.831651],"type":"Point"},"properties":{"osm_id":"6036759614","tag":{"natural":"tree"}},"type":"Feature"},
	{"geometry":{"coordinates":[11.052588,50.833921],"type":"Point"},"properties":{"osm_id":"7065872276","tag":{"natural":"tree"}},"type":"Feature"},
	{"geometry":{"coordinates":[11.052687,50.833998],"type":"Point"},"properties":{"osm_id":"7065872277","tag":{"natural":"tree"}},"type":"Feature"},
	{"geometry":{"coordinates":[11.052851,50.833498],"type":"Point"},"properties":{"osm_id":"7065872278","tag":{"natural":"tree"}},"type":"Feature"},
	{"geometry":{"coordinates":[11.056259,50.832854],"type":"Point"},"properties":{"osm_id":"7065880102","tag":{"natural":"tree"}},"type":"Feature"},
	{"geometry":{"coordinates":[11.04239,50.847247],"type":"Point"},"properties":{"osm_id":"7069126023","tag":{"natural":"tree"}},"type":"Feature"},
	{"geometry":{"coordinates":[11.040003,50.837878],"type":"Point"},"properties":{"osm_id":"7074530584","tag":{"natural":"tree"}},"type":"Feature"},
	{"geometry":{"coordinates":[11.039724,50.837842],"type":"Point"},"properties":{"osm_id":"7074554785","tag":{"natural":"tree"}},"type":"Feature"},
	{"geometry":{"coordinates":[11.039921,50.839631],"type":"Point"},"properties":{"osm_id":"7074554786","tag":{"natural":"tree"}},"type":"Feature"},
	{"geometry":{"coordinates":[11.039876,50.838962],"type":"Point"},"properties":{"osm_id":"7074554787","tag":{"natural":"tree"}},"type":"Feature"},
	{"geometry":{"coordinates":[11.039948,50.839237],"type":"Point"},"properties":{"osm_id":"7074554788","tag":{"natural":"tree"}},"type":"Feature"},
	{"geometry":{"coordinates":[11.040375,50.838652],"type":"Point"},"properties":{"osm_id":"7074554789","tag":{"natural":"tree"}},"type":"Feature"}
]
}
