{
"type": "FeatureCollection",
"features": [
	{"geometry":{"coordinates":[11.035757,50.12203],"type":"Point"},"properties":{"name":"Dorflinde","osm_id":"2426911787","tag":{"denotation":"natural_monument","genus":"Tilia","genus:de":"Linde","leaf_cycle":"deciduous","leaf_type":"broadleaved","natural":"tree","wikidata":"Q41294570"}},"type":"Feature"},
	{"geometry":{"coordinates":[11.062565,50.14519],"type":"Point"},"properties":{"osm_id":"2461206638","tag":{"natural":"tree"}},"type":"Feature"},
	{"geometry":{"coordinates":[11.060028,50.145956],"type":"Point"},"properties":{"osm_id":"3377289422","tag":{"natural":"tree"}},"type":"Feature"},
	{"geometry":{"coordinates":[11.059999,50.145977],"type":"Point"},"properties":{"osm_id":"3377289423","tag":{"natural":"tree"}},"type":"Feature"},
	{"geometry":{"coordinates":[11.059974,50.145995],"type":"Point"},"properties":{"osm_id":"3377289424","tag":{"natural":"tree"}},"type":"Feature"},
	{"geometry":{"coordinates":[11.059953,50.14601],"type":"Point"},"properties":{"osm_id":"3377289425","tag":{"natural":"tree"}},"type":"Feature"},
	{"geometry":{"coordinates":[11.059933,50.146026],"type":"Point"},"properties":{"osm_id":"3377289426","tag":{"natural":"tree"}},"type":"Feature"},
	{"geometry":{"coordinates":[11.059929,50.145904],"type":"Point"},"properties":{"osm_id":"3377289427","tag":{"natural":"tree"}},"type":"Feature"},
	{"geometry":{"coordinates":[11.05991,50.145922],"type":"Point"},"properties":{"osm_id":"3377289428","tag":{"natural":"tree"}},"type":"Feature"},
	{"geometry":{"coordinates":[11.059884,50.145942],"type":"Point"},"properties":{"osm_id":"3377289429","tag":{"natural":"tree"}},"type":"Feature"},
	{"geometry":{"coordinates":[11.059863,50.14596],"type":"Point"},"properties":{"osm_id":"3377289430","tag":{"natural":"tree"}},"type":"Feature"},
	{"geometry":{"coordinates":[11.059843,50.145976],"type":"Point"},"properties":{"osm_id":"3377289431","tag":{"natural":"tree"}},"type":"Feature"},
	{"geometry":{"coordinates":[11.060316,50.145778],"type":"Point"},"properties":{"osm_id":"3377289432","tag":{"natural":"tree"}},"type":"Feature"},
	{"geometry":{"coordinates":[11.058898,50.145751],"type":"Point"},"properties":{"osm_id":"3723399132","tag":{"natural":"tree"}},"type":"Feature"},
	{"geometry":{"coordinates":[11.058938,50.145772],"type":"Point"},"properties":{"osm_id":"3723399134","tag":{"natural":"tree"}},"type":"Feature"},
	{"geometry":{"coordinates":[11.058977,50.145792],"type":"Point"},"properties":{"osm_id":"3723399135","tag":{"natural":"tree"}},"type":"Feature"},
	{"geometry":{"coordinates":[11.059017,50.145814],"type":"Point"},"properties":{"osm_id":"3723399136","tag":{"natural":"tree"}},"type":"Feature"},
	{"geometry":{"coordinates":[11.05906,50.145836],"type":"Point"},"properties":{"osm_id":"3723399140","tag":{"natural":"tree"}},"type":"Feature"},
	{"geometry":{"coordinates":[11.056779,50.145946],"type":"Point"},"properties":{"osm_id":"5180700936","tag":{"natural":"tree"}},"type":"Feature"},
	{"geometry":{"coordinates":[10.999916,50.134011],"type":"Point"},"properties":{"osm_id":"8242236329","tag":{"natural":"tree"}},"type":"Feature"},
	{"geometry":{"coordinates":[10.997524,50.131372],"type":"Point"},"properties":{"name":"Stiehleiche","osm_id":"8485483376","tag":{"natural":"tree"}},"type":"Feature"},
	{"geometry":{"coordinates":[11.061,50.138081],"type":"Point"},"properties":{"osm_id":"8598943469","tag":{"genus":"Sequoiadendron","genus:de":"Mammutbaum","natural":"tree"}},"type":"Feature"},
	{"geometry":{"coordinates":[11.069666,50.149639],"type":"Point"},"properties":{"name":"Naturdenkmal Rosskastanie","osm_id":"9014350117","tag":{"circumference":"270","denotation":"natural_monument","height":"17","leaf_type":"broadleaved","natural":"tree"}},"type":"Feature"},
	{"geometry":{"coordinates":[11.071006,50.148177],"type":"Point"},"properties":{"name":"Naturdenkmal Feld-Ahorn","osm_id":"9014373983","tag":{"circumference":"270","denotation":"natural_monument","height":"21","leaf_type":"broadleaved","natural":"tree"}},"type":"Feature"},
	{"geometry":{"coordinates":[11.056658,50.156396],"type":"Point"},"properties":{"name":"Naturdenkmal Winter-Linde","osm_id":"9014373990","tag":{"circumference":"302","denotation":"natural_monument","height":"16","leaf_type":"broadleaved","natural":"tree"}},"type":"Feature"},
	{"geometry":{"coordinates":[11.055317,50.157025],"type":"Point"},"properties":{"name":"Naturdenkmal Sommer-Linde","osm_id":"9014373991","tag":{"denotation":"natural_monument","height":"24","leaf_type":"broadleaved","natural":"tree"}},"type":"Feature"}
]
}
