{
"type": "FeatureCollection",
"features": [
	{"geometry":{"coordinates":[11.042952,44.075283],"type":"Point"},"properties":{"name":"Castagno","osm_id":"5214307797","ref":"57","tag":{"access":"unknown","circumference":"6.1","denotation":"natural_monument","height":"19","monument":"yes","name:it":"Castagno","natural":"tree","operator":"Matteoni Giordano","phone":"+39057323878","start_date":"1590","survey:date":"2004-10-28"}},"type":"Feature"},
	{"geometry":{"coordinates":[11.042161,44.074405],"type":"Point"},"properties":{"name":"Castagno","osm_id":"5214307798","ref":"38","tag":{"access":"unknown","circumference":"4.55","denotation":"natural_monument","height":"7","monument":"yes","name:it":"Castagno","natural":"tree","operator":"Matteoni Giordano","phone":"+39057323878","start_date":"1590","survey:date":"2004-10-28"}},"type":"Feature"},
	{"geometry":{"coordinates":[11.042076,44.074848],"type":"Point"},"properties":{"name":"Castagno","osm_id":"5214307799","ref":"37","tag":{"access":"unknown","circumference":"5.55","denotation":"natural_monument","height":"15","monument":"yes","name:it":"Castagno","natural":"tree","operator":"Matteoni Giordano","phone":"+39057323878","start_date":"1590","survey:date":"2004-10-28"}},"type":"Feature"},
	{"geometry":{"coordinates":[11.04067,44.07463],"type":"Point"},"properties":{"name":"Castagno","osm_id":"5214307800","ref":"41","tag":{"access":"unknown","circumference":"5.67","denotation":"natural_monument","height":"15","monument":"yes","name:it":"Castagno","natural":"tree","operator":"Matteoni Giordano","phone":"+39057323878","start_date":"1590","survey:date":"2004-10-28"}},"type":"Feature"}
]
}
