{
"type": "FeatureCollection",
"features": [
	{"geometry":{"coordinates":[-72.213666,7.64475],"type":"Point"},"properties":{"name":"San Josecito","osm_id":"2535933771","tag":{"amenity":"recycling"}},"type":"Feature"}
]
}
