{
"type": "FeatureCollection",
"lastupdate": "2020-08-02T00:00:00Z",
"features": [
	{"geometry":{"coordinates":[-72.213665,7.64475],"type":"Point"},"properties":{"name":"San Josecito","osm_id":"2535933771","tag":{"amenity":"recycling"}},"type":"Feature"}
]
}
