{
"type": "FeatureCollection",
"features": [
	{"geometry":{"coordinates":[14.17469,50.919243],"type":"Point"},"properties":{"osm_id":"846350073","tag":{"amenity":"recycling","recycling:clothes":"yes","recycling:glass":"yes","recycling_type":"container"}},"type":"Feature"},
	{"geometry":{"coordinates":[14.178556,50.911704],"type":"Point"},"properties":{"osm_id":"851498502","tag":{"amenity":"recycling","recycling:glass":"yes","recycling_type":"container"}},"type":"Feature"},
	{"geometry":{"coordinates":[14.179262,50.935423],"type":"Point"},"properties":{"osm_id":"1149966177","tag":{"amenity":"recycling"}},"type":"Feature"},
	{"geometry":{"coordinates":[14.236336,50.944184],"type":"Point"},"properties":{"osm_id":"1149966194","tag":{"amenity":"recycling"}},"type":"Feature"},
	{"geometry":{"coordinates":[14.179837,50.91983],"type":"Point"},"properties":{"osm_id":"1481689793","tag":{"amenity":"waste_basket"}},"type":"Feature"},
	{"geometry":{"coordinates":[14.174278,50.918346],"type":"Point"},"properties":{"osm_id":"1481724160","tag":{"amenity":"waste_basket"}},"type":"Feature"},
	{"geometry":{"coordinates":[14.159475,50.91546],"type":"Point"},"properties":{"osm_id":"2531769946","tag":{"amenity":"waste_basket"}},"type":"Feature"},
	{"geometry":{"coordinates":[14.159184,50.915492],"type":"Point"},"properties":{"osm_id":"2531769947","tag":{"amenity":"waste_basket"}},"type":"Feature"},
	{"geometry":{"coordinates":[14.158257,50.91573],"type":"Point"},"properties":{"osm_id":"2531769950","tag":{"amenity":"waste_basket"}},"type":"Feature"},
	{"geometry":{"coordinates":[14.157609,50.915825],"type":"Point"},"properties":{"osm_id":"2531769954","tag":{"amenity":"waste_basket"}},"type":"Feature"},
	{"geometry":{"coordinates":[14.156195,50.916063],"type":"Point"},"properties":{"osm_id":"2531769959","tag":{"amenity":"waste_basket"}},"type":"Feature"},
	{"geometry":{"coordinates":[14.154459,50.916378],"type":"Point"},"properties":{"osm_id":"2531769963","tag":{"amenity":"waste_basket"}},"type":"Feature"},
	{"geometry":{"coordinates":[14.154139,50.916465],"type":"Point"},"properties":{"osm_id":"2531769966","tag":{"amenity":"waste_basket"}},"type":"Feature"},
	{"geometry":{"coordinates":[14.153228,50.916691],"type":"Point"},"properties":{"osm_id":"2531769971","tag":{"amenity":"waste_basket"}},"type":"Feature"},
	{"geometry":{"coordinates":[14.207515,50.935145],"type":"Point"},"properties":{"osm_id":"2915547719","tag":{"amenity":"recycling","location":"overground","recycling:paper":"yes","recycling_type":"container"}},"type":"Feature"},
	{"geometry":{"coordinates":[14.167026,50.912528],"type":"Point"},"properties":{"osm_id":"3545657516","tag":{"amenity":"waste_basket"}},"type":"Feature"},
	{"geometry":{"coordinates":[14.160099,50.912909],"type":"Point"},"properties":{"osm_id":"3547500850","tag":{"amenity":"waste_basket"}},"type":"Feature"},
	{"geometry":{"coordinates":[14.160224,50.913178],"type":"Point"},"properties":{"osm_id":"3547500858","tag":{"amenity":"waste_basket"}},"type":"Feature"},
	{"geometry":{"coordinates":[14.160097,50.91322],"type":"Point"},"properties":{"osm_id":"3547500862","tag":{"amenity":"waste_basket"}},"type":"Feature"},
	{"geometry":{"coordinates":[14.163653,50.903961],"type":"Point"},"properties":{"osm_id":"3686144262","tag":{"amenity":"waste_basket"}},"type":"Feature"},
	{"geometry":{"coordinates":[14.174937,50.919698],"type":"Point"},"properties":{"osm_id":"4083395481","tag":{"amenity":"waste_basket"}},"type":"Feature"},
	{"geometry":{"coordinates":[14.175333,50.920171],"type":"Point"},"properties":{"osm_id":"4083397198","tag":{"amenity":"waste_basket"}},"type":"Feature"},
	{"geometry":{"coordinates":[14.166664,50.90755],"type":"Point"},"properties":{"osm_id":"4888427286","tag":{"amenity":"waste_basket"}},"type":"Feature"},
	{"geometry":{"coordinates":[14.169326,50.942934],"type":"Point"},"properties":{"osm_id":"6830138113","tag":{"amenity":"recycling","recycling:glass":"yes","recycling_type":"container"}},"type":"Feature"},
	{"geometry":{"coordinates":[14.154716,50.918707],"type":"Point"},"properties":{"osm_id":"7593491823","tag":{"amenity":"waste_basket"}},"type":"Feature"},
	{"geometry":{"coordinates":[14.167674,50.91125],"type":"Point"},"properties":{"osm_id":"7637225314","tag":{"amenity":"recycling"}},"type":"Feature"},
	{"geometry":{"coordinates":[14.173233,50.917494],"type":"Point"},"properties":{"osm_id":"7783252419","tag":{"amenity":"waste_basket"}},"type":"Feature"},
	{"geometry":{"coordinates":[14.174225,50.918492],"type":"Point"},"properties":{"osm_id":"9145949617","tag":{"amenity":"waste_basket"}},"type":"Feature"},
	{"geometry":{"coordinates":[14.166733,50.917277],"type":"Point"},"properties":{"osm_id":"9147949059","tag":{"amenity":"waste_basket"}},"type":"Feature"}
]
}
