{
"type": "FeatureCollection",
"features": [
	{"geometry":{"coordinates":[-79.381863,21.911124],"type":"Point"},"properties":{"osm_id":"3967724814","tag":{"natural":"tree"}},"type":"Feature"},
	{"geometry":{"coordinates":[-79.381915,21.91074],"type":"Point"},"properties":{"osm_id":"3967724815","tag":{"natural":"tree"}},"type":"Feature"},
	{"geometry":{"coordinates":[-79.381329,21.911045],"type":"Point"},"properties":{"osm_id":"3967724816","tag":{"natural":"tree"}},"type":"Feature"},
	{"geometry":{"coordinates":[-79.380353,21.91119],"type":"Point"},"properties":{"osm_id":"3967724817","tag":{"natural":"tree"}},"type":"Feature"},
	{"geometry":{"coordinates":[-79.380495,21.911075],"type":"Point"},"properties":{"osm_id":"3967724818","tag":{"natural":"tree"}},"type":"Feature"},
	{"geometry":{"coordinates":[-79.380302,21.911595],"type":"Point"},"properties":{"osm_id":"3967724819","tag":{"natural":"tree"}},"type":"Feature"},
	{"geometry":{"coordinates":[-79.382009,21.889954],"type":"Point"},"properties":{"osm_id":"3969233836","tag":{"natural":"tree"}},"type":"Feature"},
	{"geometry":{"coordinates":[-79.443101,21.927517],"type":"Point"},"properties":{"name":"Palma real","osm_id":"4532917485","tag":{"natural":"tree"}},"type":"Feature"}
]
}
