{
"type": "FeatureCollection",
"features": [
	{"geometry":{"coordinates":[1.582074,41.523967],"type":"Point"},"properties":{"name":"Om de 5 Ulls","osm_id":"8438445885","tag":{"natural":"tree"}},"type":"Feature"}
]
}
