{
"type": "FeatureCollection",
"features": [
	{"geometry":{"coordinates":[4.650112,45.055778],"type":"Point"},"properties":{"osm_id":"6058252016","tag":{"natural":"tree"}},"type":"Feature"},
	{"geometry":{"coordinates":[4.650173,45.05582],"type":"Point"},"properties":{"osm_id":"6058252017","tag":{"natural":"tree"}},"type":"Feature"},
	{"geometry":{"coordinates":[4.65024,45.055858],"type":"Point"},"properties":{"osm_id":"6058252018","tag":{"natural":"tree"}},"type":"Feature"},
	{"geometry":{"coordinates":[4.654301,45.056283],"type":"Point"},"properties":{"osm_id":"6058252051","tag":{"natural":"tree"}},"type":"Feature"},
	{"geometry":{"coordinates":[4.654283,45.056372],"type":"Point"},"properties":{"osm_id":"6058252052","tag":{"natural":"tree"}},"type":"Feature"},
	{"geometry":{"coordinates":[4.654274,45.056466],"type":"Point"},"properties":{"osm_id":"6058252053","tag":{"natural":"tree"}},"type":"Feature"},
	{"geometry":{"coordinates":[4.652125,45.036577],"type":"Point"},"properties":{"name":"Platane","osm_id":"6060355137","tag":{"natural":"tree"}},"type":"Feature"},
	{"geometry":{"coordinates":[4.652235,45.036527],"type":"Point"},"properties":{"name":"Platane","osm_id":"6060355138","tag":{"natural":"tree"}},"type":"Feature"},
	{"geometry":{"coordinates":[4.652341,45.036484],"type":"Point"},"properties":{"name":"Platane","osm_id":"6060355139","tag":{"natural":"tree"}},"type":"Feature"},
	{"geometry":{"coordinates":[4.652473,45.036486],"type":"Point"},"properties":{"name":"Platane","osm_id":"6060355140","tag":{"natural":"tree"}},"type":"Feature"}
]
}
