{
"type": "FeatureCollection",
"features": [
	{"geometry":{"coordinates":[4.650111,45.055778],"type":"Point"},"properties":{"osm_id":"6058252016","tag":{"natural":"tree"}},"type":"Feature"},
	{"geometry":{"coordinates":[4.650172,45.05582],"type":"Point"},"properties":{"osm_id":"6058252017","tag":{"natural":"tree"}},"type":"Feature"},
	{"geometry":{"coordinates":[4.650239,45.055857],"type":"Point"},"properties":{"osm_id":"6058252018","tag":{"natural":"tree"}},"type":"Feature"},
	{"geometry":{"coordinates":[4.654301,45.056282],"type":"Point"},"properties":{"osm_id":"6058252051","tag":{"natural":"tree"}},"type":"Feature"},
	{"geometry":{"coordinates":[4.654283,45.056371],"type":"Point"},"properties":{"osm_id":"6058252052","tag":{"natural":"tree"}},"type":"Feature"},
	{"geometry":{"coordinates":[4.654274,45.056466],"type":"Point"},"properties":{"osm_id":"6058252053","tag":{"natural":"tree"}},"type":"Feature"},
	{"geometry":{"coordinates":[4.652124,45.036577],"type":"Point"},"properties":{"name":"Platane","osm_id":"6060355137","tag":{"natural":"tree"}},"type":"Feature"},
	{"geometry":{"coordinates":[4.652234,45.036527],"type":"Point"},"properties":{"name":"Platane","osm_id":"6060355138","tag":{"natural":"tree"}},"type":"Feature"},
	{"geometry":{"coordinates":[4.65234,45.036483],"type":"Point"},"properties":{"name":"Platane","osm_id":"6060355139","tag":{"natural":"tree"}},"type":"Feature"},
	{"geometry":{"coordinates":[4.652473,45.036485],"type":"Point"},"properties":{"name":"Platane","osm_id":"6060355140","tag":{"natural":"tree"}},"type":"Feature"}
]
}
