{
"type": "FeatureCollection",
"features": [
	{"geometry":{"coordinates":[18.356111,53.481589],"type":"Point"},"properties":{"osm_id":"4706672391","tag":{"denotation":"natural_monument","natural":"tree","ref:CRFOP":"PL.ZIPOP.1393.PP.0414032.554","ref:INSPIRE":"PL.ZIPOP.1393.PP.0414032.554","website":"http://crfop.gdos.gov.pl/CRFOP/widok/viewfop.jsf?fop=PL.ZIPOP.1393.PP.0414032.554"}},"type":"Feature"},
	{"geometry":{"coordinates":[18.356139,53.481505],"type":"Point"},"properties":{"osm_id":"4706672392","tag":{"denotation":"natural_monument","natural":"tree","ref:CRFOP":"PL.ZIPOP.1393.PP.0414032.554","ref:INSPIRE":"PL.ZIPOP.1393.PP.0414032.554","website":"http://crfop.gdos.gov.pl/CRFOP/widok/viewfop.jsf?fop=PL.ZIPOP.1393.PP.0414032.554"}},"type":"Feature"},
	{"geometry":{"coordinates":[18.354994,53.481965],"type":"Point"},"properties":{"osm_id":"4706672393","tag":{"denotation":"natural_monument","natural":"tree","ref:CRFOP":"PL.ZIPOP.1393.PP.0414032.554","ref:INSPIRE":"PL.ZIPOP.1393.PP.0414032.554","website":"http://crfop.gdos.gov.pl/CRFOP/widok/viewfop.jsf?fop=PL.ZIPOP.1393.PP.0414032.554"}},"type":"Feature"},
	{"geometry":{"coordinates":[18.355448,53.481964],"type":"Point"},"properties":{"osm_id":"4706672394","tag":{"denotation":"natural_monument","natural":"tree","ref:CRFOP":"PL.ZIPOP.1393.PP.0414032.554","ref:INSPIRE":"PL.ZIPOP.1393.PP.0414032.554","website":"http://crfop.gdos.gov.pl/CRFOP/widok/viewfop.jsf?fop=PL.ZIPOP.1393.PP.0414032.554"}},"type":"Feature"},
	{"geometry":{"coordinates":[18.355691,53.481972],"type":"Point"},"properties":{"osm_id":"4706672395","tag":{"denotation":"natural_monument","natural":"tree","ref:CRFOP":"PL.ZIPOP.1393.PP.0414032.554","ref:INSPIRE":"PL.ZIPOP.1393.PP.0414032.554","website":"http://crfop.gdos.gov.pl/CRFOP/widok/viewfop.jsf?fop=PL.ZIPOP.1393.PP.0414032.554"}},"type":"Feature"},
	{"geometry":{"coordinates":[18.355579,53.48205],"type":"Point"},"properties":{"osm_id":"4706672396","tag":{"denotation":"natural_monument","natural":"tree","ref:CRFOP":"PL.ZIPOP.1393.PP.0414032.554","ref:INSPIRE":"PL.ZIPOP.1393.PP.0414032.554","website":"http://crfop.gdos.gov.pl/CRFOP/widok/viewfop.jsf?fop=PL.ZIPOP.1393.PP.0414032.554"}},"type":"Feature"},
	{"geometry":{"coordinates":[18.338272,53.46673],"type":"Point"},"properties":{"osm_id":"4706672397","tag":{"denotation":"natural_monument","natural":"tree","ref:CRFOP":"PL.ZIPOP.1393.PP.0414032.553","ref:INSPIRE":"PL.ZIPOP.1393.PP.0414032.553","website":"http://crfop.gdos.gov.pl/CRFOP/widok/viewfop.jsf?fop=PL.ZIPOP.1393.PP.0414032.553"}},"type":"Feature"},
	{"geometry":{"coordinates":[18.338165,53.466625],"type":"Point"},"properties":{"osm_id":"4706672398","tag":{"denotation":"natural_monument","natural":"tree","ref:CRFOP":"PL.ZIPOP.1393.PP.0414032.553","ref:INSPIRE":"PL.ZIPOP.1393.PP.0414032.553","website":"http://crfop.gdos.gov.pl/CRFOP/widok/viewfop.jsf?fop=PL.ZIPOP.1393.PP.0414032.553"}},"type":"Feature"},
	{"geometry":{"coordinates":[18.337973,53.466855],"type":"Point"},"properties":{"osm_id":"4706672399","tag":{"denotation":"natural_monument","natural":"tree","ref:CRFOP":"PL.ZIPOP.1393.PP.0414032.553","ref:INSPIRE":"PL.ZIPOP.1393.PP.0414032.553","website":"http://crfop.gdos.gov.pl/CRFOP/widok/viewfop.jsf?fop=PL.ZIPOP.1393.PP.0414032.553"}},"type":"Feature"},
	{"geometry":{"coordinates":[18.337739,53.466754],"type":"Point"},"properties":{"osm_id":"4706672400","tag":{"denotation":"natural_monument","natural":"tree","ref:CRFOP":"PL.ZIPOP.1393.PP.0414032.553","ref:INSPIRE":"PL.ZIPOP.1393.PP.0414032.553","website":"http://crfop.gdos.gov.pl/CRFOP/widok/viewfop.jsf?fop=PL.ZIPOP.1393.PP.0414032.553"}},"type":"Feature"}
]
}
