{
"type": "FeatureCollection",
"features": [
	{"geometry":{"coordinates":[11.270495,50.903773],"type":"Point"},"properties":{"osm_id":"916547193","tag":{"amenity":"waste_basket"}},"type":"Feature"},
	{"geometry":{"coordinates":[11.332221,50.921024],"type":"Point"},"properties":{"osm_id":"1717965011","tag":{"amenity":"waste_basket"}},"type":"Feature"},
	{"geometry":{"coordinates":[11.331997,50.921191],"type":"Point"},"properties":{"osm_id":"1717965034","tag":{"amenity":"recycling","location":"overground","recycling:glass":"yes","recycling_type":"container"}},"type":"Feature"},
	{"geometry":{"coordinates":[11.330003,50.936353],"type":"Point"},"properties":{"osm_id":"1718015538","tag":{"amenity":"waste_basket"}},"type":"Feature"},
	{"geometry":{"coordinates":[11.330744,50.93474],"type":"Point"},"properties":{"osm_id":"2419929956","tag":{"amenity":"recycling","recycling_type":"container"}},"type":"Feature"},
	{"geometry":{"coordinates":[11.333564,50.915862],"type":"Point"},"properties":{"osm_id":"5076969154","tag":{"amenity":"waste_basket"}},"type":"Feature"},
	{"geometry":{"coordinates":[11.301917,50.950646],"type":"Point"},"properties":{"osm_id":"5159699011","tag":{"amenity":"recycling","recycling_type":"container"}},"type":"Feature"},
	{"geometry":{"coordinates":[11.300232,50.951084],"type":"Point"},"properties":{"osm_id":"5159699013","tag":{"amenity":"waste_basket"}},"type":"Feature"},
	{"geometry":{"coordinates":[11.293897,50.933859],"type":"Point"},"properties":{"osm_id":"5375736027","tag":{"amenity":"waste_disposal"}},"type":"Feature"},
	{"geometry":{"coordinates":[11.281124,50.940572],"type":"Point"},"properties":{"osm_id":"5908254399","tag":{"amenity":"recycling","operator":"Remondis","recycling:glass_bottles":"yes","recycling_type":"container"}},"type":"Feature"},
	{"geometry":{"coordinates":[11.281175,50.940569],"type":"Point"},"properties":{"osm_id":"5908254400","tag":{"amenity":"recycling","recycling:clothes":"yes","recycling_type":"container"}},"type":"Feature"},
	{"geometry":{"coordinates":[11.331491,50.921604],"type":"Point"},"properties":{"osm_id":"6523976683","tag":{"amenity":"recycling","recycling:clothes":"yes","recycling:glass_bottles":"yes","recycling_type":"container"}},"type":"Feature"}
]
}
