{
"type": "FeatureCollection",
"features": [
	{"geometry":{"coordinates":[11.335006,49.320447],"type":"Point"},"properties":{"osm_id":"292228052","tag":{"amenity":"recycling","recycling_type":"container"}},"type":"Feature"},
	{"geometry":{"coordinates":[11.306895,49.320396],"type":"Point"},"properties":{"osm_id":"292956546","tag":{"amenity":"recycling","location":"overground","recycling_type":"container"}},"type":"Feature"},
	{"geometry":{"coordinates":[11.310062,49.32503],"type":"Point"},"properties":{"osm_id":"292969766","tag":{"amenity":"recycling","recycling:cans":"yes","recycling:glass":"yes"}},"type":"Feature"},
	{"geometry":{"coordinates":[11.278563,49.29729],"type":"Point"},"properties":{"osm_id":"293266125","tag":{"amenity":"recycling","recycling:clothes":"yes","recycling:glass":"yes"}},"type":"Feature"},
	{"geometry":{"coordinates":[11.280058,49.294524],"type":"Point"},"properties":{"osm_id":"293266168","tag":{"amenity":"recycling","recycling:clothes":"yes","recycling:glass":"yes"}},"type":"Feature"},
	{"geometry":{"coordinates":[11.29326,49.298069],"type":"Point"},"properties":{"osm_id":"453501463","tag":{"amenity":"recycling","recycling:clothes":"yes","recycling:glass":"yes","recycling_type":"container"}},"type":"Feature"},
	{"geometry":{"coordinates":[11.337429,49.323469],"type":"Point"},"properties":{"osm_id":"6985379680","tag":{"amenity":"waste_basket"}},"type":"Feature"},
	{"geometry":{"coordinates":[11.282082,49.298059],"type":"Point"},"properties":{"osm_id":"8827108580","tag":{"amenity":"waste_basket","waste":"trash"}},"type":"Feature"},
	{"geometry":{"coordinates":[11.284482,49.297618],"type":"Point"},"properties":{"osm_id":"8890606488","tag":{"amenity":"waste_basket","waste":"trash"}},"type":"Feature"}
]
}
