{
"type": "FeatureCollection",
"features": [
	{"geometry":{"coordinates":[-1.037945,52.91064],"type":"Point"},"properties":{"name":"Cotgrave Precinct Recycling Site","osm_id":"3659545260","tag":{"amenity":"recycling","operator":"Rushcliffe Borough Council","recycling:clothes":"yes","recycling:glass_bottles":"yes","recycling:shoes":"yes","recycling_type":"container"}},"type":"Feature"},
	{"geometry":{"coordinates":[-1.038911,52.946032],"type":"Point"},"properties":{"osm_id":"3702059692","tag":{"amenity":"recycling","operator":"Rushcliffe Borough Council","recycling:clothes":"yes","recycling:glass_bottles":"yes","recycling:shoes":"yes","recycling_type":"container"}},"type":"Feature"},
	{"geometry":{"coordinates":[-1.040567,52.913141],"type":"Point"},"properties":{"osm_id":"6358721435","tag":{"amenity":"waste_basket"}},"type":"Feature"},
	{"geometry":{"coordinates":[-0.993063,52.913489],"type":"Point"},"properties":{"osm_id":"6577539129","tag":{"amenity":"waste_basket"}},"type":"Feature"},
	{"geometry":{"coordinates":[-1.044367,52.945437],"type":"Point"},"properties":{"osm_id":"7857252739","tag":{"direction":"ESE","generator:method":"photovoltaic","generator:output:electricity":"yes","generator:solar:modules":"14","generator:source":"solar","generator:type":"solar_photovoltaic_panel","location":"roof","power":"generator"}},"type":"Feature"}
]
}
