{
"type": "FeatureCollection",
"lastupdate": "2020-08-05T00:00:00Z",
"features": [
	{"geometry":{"coordinates":[-1.037945,52.910639],"type":"Point"},"properties":{"name":"Cotgrave Precinct Recycling Site","osm_id":"3659545260","tag":{"amenity":"recycling","operator":"Rushcliffe Borough Council","recycling:clothes":"yes","recycling:glass_bottles":"yes","recycling:shoes":"yes","recycling_type":"container"}},"type":"Feature"},
	{"geometry":{"coordinates":[-1.038911,52.946031],"type":"Point"},"properties":{"osm_id":"3702059692","tag":{"amenity":"recycling","operator":"Rushcliffe Borough Council","recycling:clothes":"yes","recycling:glass_bottles":"yes","recycling:shoes":"yes","recycling_type":"container"}},"type":"Feature"},
	{"geometry":{"coordinates":[-1.040566,52.913141],"type":"Point"},"properties":{"osm_id":"6358721435","tag":{"amenity":"waste_basket"}},"type":"Feature"},
	{"geometry":{"coordinates":[-0.993062,52.913488],"type":"Point"},"properties":{"osm_id":"6577539129","tag":{"amenity":"waste_basket"}},"type":"Feature"}
]
}
