{
"type": "FeatureCollection",
"features": [
	{"geometry":{"coordinates":[-0.979854,45.958529],"type":"Point"},"properties":{"osm_id":"7236633486","tag":{"amenity":"recycling","location":"overground","recycling:glass_bottles":"yes","recycling_type":"container"}},"type":"Feature"},
	{"geometry":{"coordinates":[-1.036543,45.99214],"type":"Point"},"properties":{"osm_id":"7236645090","tag":{"amenity":"recycling","location":"overground","recycling:glass_bottles":"yes","recycling_type":"container"}},"type":"Feature"},
	{"geometry":{"coordinates":[-1.045055,45.961191],"type":"Point"},"properties":{"osm_id":"7778733585","tag":{"amenity":"waste_basket"}},"type":"Feature"}
]
}
