{
"type": "FeatureCollection",
"lastupdate": "2020-08-03T00:00:00Z",
"features": [
	{"geometry":{"coordinates":[-1.034703,43.036896],"type":"Point"},"properties":{"osm_id":"6602105959","tag":{"amenity":"recycling"}},"type":"Feature"},
	{"geometry":{"coordinates":[-1.027994,43.037818],"type":"Point"},"properties":{"osm_id":"6602174899","tag":{"amenity":"recycling","location":"overground","recycling_type":"container"}},"type":"Feature"}
]
}
