{
"type": "FeatureCollection",
"features": [
	{"geometry":{"coordinates":[5.859936,50.612092],"type":"Point"},"properties":{"osm_id":"736970503","tag":{"amenity":"waste_basket"}},"type":"Feature"},
	{"geometry":{"coordinates":[5.860526,50.612292],"type":"Point"},"properties":{"osm_id":"736970595","tag":{"amenity":"recycling","recycling:glass":"yes","recycling_type":"container"}},"type":"Feature"},
	{"geometry":{"coordinates":[5.881106,50.613465],"type":"Point"},"properties":{"osm_id":"765627075","tag":{"amenity":"waste_basket"}},"type":"Feature"},
	{"geometry":{"coordinates":[5.813699,50.584984],"type":"Point"},"properties":{"osm_id":"765990228","tag":{"amenity":"recycling","recycling:glass":"yes"}},"type":"Feature"},
	{"geometry":{"coordinates":[5.882104,50.614842],"type":"Point"},"properties":{"osm_id":"766068572","tag":{"amenity":"recycling","recycling:glass":"yes"}},"type":"Feature"},
	{"geometry":{"coordinates":[5.888054,50.594632],"type":"Point"},"properties":{"osm_id":"766114840","tag":{"amenity":"waste_basket"}},"type":"Feature"},
	{"geometry":{"coordinates":[5.88397,50.586057],"type":"Point"},"properties":{"osm_id":"766141466","tag":{"amenity":"waste_basket"}},"type":"Feature"},
	{"geometry":{"coordinates":[5.833438,50.609096],"type":"Point"},"properties":{"osm_id":"1355588383","tag":{"amenity":"recycling","recycling:clothes":"yes","recycling:glass":"yes"}},"type":"Feature"},
	{"geometry":{"coordinates":[5.846194,50.588116],"type":"Point"},"properties":{"name":"Parc container","osm_id":"1551797867","tag":{"amenity":"recycling","description":"Recyparc de Verviers","recycling:batteries":"yes","recycling:books":"no","recycling:cans":"yes","recycling:cardboard":"yes","recycling:cartons":"yes","recycling:clothes":"no","recycling:electrical_appliances":"yes","recycling:glass":"yes","recycling:glass_bottles":"yes","recycling:green_waste":"yes","recycling:magazines":"yes","recycling:newspaper":"yes","recycling:paper_packaging":"yes","recycling:plastic":"yes","recycling:plastic_bottles":"no","recycling:plastic_packaging":"no","recycling:small_appliances":"yes","recycling:waste":"no","recycling:wood":"yes","recycling_type":"container"}},"type":"Feature"},
	{"geometry":{"coordinates":[5.845571,50.579796],"type":"Point"},"properties":{"osm_id":"4691672389","tag":{"amenity":"waste_disposal","operator":"Sos Plastiques"}},"type":"Feature"},
	{"geometry":{"coordinates":[5.86885,50.603929],"type":"Point"},"properties":{"osm_id":"5787518321","tag":{"amenity":"waste_basket"}},"type":"Feature"},
	{"geometry":{"coordinates":[5.869176,50.603917],"type":"Point"},"properties":{"osm_id":"5787518322","tag":{"amenity":"waste_basket"}},"type":"Feature"},
	{"geometry":{"coordinates":[5.833187,50.614033],"type":"Point"},"properties":{"osm_id":"5801146589","tag":{"amenity":"recycling","recycling_type":"container"}},"type":"Feature"},
	{"geometry":{"coordinates":[5.83267,50.61302],"type":"Point"},"properties":{"osm_id":"5806021490","tag":{"amenity":"waste_basket"}},"type":"Feature"},
	{"geometry":{"coordinates":[5.832157,50.612965],"type":"Point"},"properties":{"osm_id":"5806021499","tag":{"amenity":"waste_basket"}},"type":"Feature"},
	{"geometry":{"coordinates":[5.831783,50.613232],"type":"Point"},"properties":{"osm_id":"5806021501","tag":{"amenity":"waste_basket"}},"type":"Feature"},
	{"geometry":{"coordinates":[5.831558,50.613222],"type":"Point"},"properties":{"osm_id":"5806021502","tag":{"amenity":"waste_basket"}},"type":"Feature"},
	{"geometry":{"coordinates":[5.83289,50.613904],"type":"Point"},"properties":{"osm_id":"5806021505","tag":{"amenity":"waste_basket"}},"type":"Feature"},
	{"geometry":{"coordinates":[5.834215,50.614303],"type":"Point"},"properties":{"osm_id":"6535301523","tag":{"amenity":"waste_basket","material":"plastic"}},"type":"Feature"},
	{"geometry":{"coordinates":[5.856185,50.588535],"type":"Point"},"properties":{"osm_id":"6541685601","tag":{"amenity":"waste_basket"}},"type":"Feature"},
	{"geometry":{"coordinates":[5.856175,50.588524],"type":"Point"},"properties":{"osm_id":"6541685602","tag":{"amenity":"waste_basket"}},"type":"Feature"}
]
}
