{
"type": "FeatureCollection",
"features": [
	{"geometry":{"coordinates":[5.859936,50.612092],"type":"Point"},"properties":{"osm_id":"736970503","tag":{"amenity":"waste_basket"}},"type":"Feature"},
	{"geometry":{"coordinates":[5.860525,50.612291],"type":"Point"},"properties":{"osm_id":"736970595","tag":{"amenity":"recycling","recycling:glass":"yes","recycling_type":"container"}},"type":"Feature"},
	{"geometry":{"coordinates":[5.881105,50.613464],"type":"Point"},"properties":{"osm_id":"765627075","tag":{"amenity":"waste_basket"}},"type":"Feature"},
	{"geometry":{"coordinates":[5.813699,50.584983],"type":"Point"},"properties":{"osm_id":"765990228","tag":{"amenity":"recycling","recycling:glass":"yes"}},"type":"Feature"},
	{"geometry":{"coordinates":[5.882103,50.614841],"type":"Point"},"properties":{"osm_id":"766068572","tag":{"amenity":"recycling","recycling:glass":"yes"}},"type":"Feature"},
	{"geometry":{"coordinates":[5.888054,50.594631],"type":"Point"},"properties":{"osm_id":"766114840","tag":{"amenity":"waste_basket"}},"type":"Feature"},
	{"geometry":{"coordinates":[5.883969,50.586057],"type":"Point"},"properties":{"osm_id":"766141466","tag":{"amenity":"waste_basket"}},"type":"Feature"},
	{"geometry":{"coordinates":[5.833437,50.609096],"type":"Point"},"properties":{"osm_id":"1355588383","tag":{"amenity":"recycling","recycling:clothes":"yes","recycling:glass":"yes"}},"type":"Feature"},
	{"geometry":{"coordinates":[5.846167,50.587965],"type":"Point"},"properties":{"name":"Recyparc de Verviers","osm_id":"1551797867","tag":{"amenity":"recycling","recycling:batteries":"yes","recycling:books":"no","recycling:cans":"yes","recycling:cardboard":"yes","recycling:cartons":"yes","recycling:clothes":"no","recycling:electrical_appliances":"yes","recycling:glass":"yes","recycling:glass_bottles":"yes","recycling:green_waste":"yes","recycling:magazines":"yes","recycling:newspaper":"yes","recycling:paper_packaging":"yes","recycling:plastic":"yes","recycling:plastic_bottles":"no","recycling:plastic_packaging":"no","recycling:small_appliances":"yes","recycling:waste":"no","recycling:wood":"yes","recycling_type":"centre"}},"type":"Feature"},
	{"geometry":{"coordinates":[5.84557,50.579795],"type":"Point"},"properties":{"osm_id":"4691672389","tag":{"amenity":"waste_disposal","operator":"Sos Plastiques"}},"type":"Feature"},
	{"geometry":{"coordinates":[5.868849,50.603929],"type":"Point"},"properties":{"osm_id":"5787518321","tag":{"amenity":"waste_basket"}},"type":"Feature"},
	{"geometry":{"coordinates":[5.869176,50.603916],"type":"Point"},"properties":{"osm_id":"5787518322","tag":{"amenity":"waste_basket"}},"type":"Feature"},
	{"geometry":{"coordinates":[5.833186,50.614033],"type":"Point"},"properties":{"osm_id":"5801146589","tag":{"amenity":"recycling","recycling_type":"container"}},"type":"Feature"},
	{"geometry":{"coordinates":[5.83267,50.61302],"type":"Point"},"properties":{"osm_id":"5806021490","tag":{"amenity":"waste_basket"}},"type":"Feature"},
	{"geometry":{"coordinates":[5.832157,50.612965],"type":"Point"},"properties":{"osm_id":"5806021499","tag":{"amenity":"waste_basket"}},"type":"Feature"},
	{"geometry":{"coordinates":[5.831782,50.613231],"type":"Point"},"properties":{"osm_id":"5806021501","tag":{"amenity":"waste_basket"}},"type":"Feature"},
	{"geometry":{"coordinates":[5.831558,50.613221],"type":"Point"},"properties":{"osm_id":"5806021502","tag":{"amenity":"waste_basket"}},"type":"Feature"},
	{"geometry":{"coordinates":[5.83289,50.613904],"type":"Point"},"properties":{"osm_id":"5806021505","tag":{"amenity":"waste_basket"}},"type":"Feature"},
	{"geometry":{"coordinates":[5.834215,50.614302],"type":"Point"},"properties":{"osm_id":"6535301523","tag":{"amenity":"waste_basket","material":"plastic"}},"type":"Feature"},
	{"geometry":{"coordinates":[5.856184,50.588534],"type":"Point"},"properties":{"osm_id":"6541685601","tag":{"amenity":"waste_basket"}},"type":"Feature"},
	{"geometry":{"coordinates":[5.856175,50.588524],"type":"Point"},"properties":{"osm_id":"6541685602","tag":{"amenity":"waste_basket"}},"type":"Feature"},
	{"geometry":{"coordinates":[5.856005,50.588778],"type":"Point"},"properties":{"osm_id":"9053622519","tag":{"amenity":"waste_basket","colour":"grey","material":"steel","waste":"trash"}},"type":"Feature"},
	{"geometry":{"coordinates":[5.856106,50.588952],"type":"Point"},"properties":{"osm_id":"9053622524","tag":{"amenity":"waste_basket","colour":"grey","material":"steel","waste":"trash"}},"type":"Feature"}
]
}
