{
"type": "FeatureCollection",
"features": [
	{"geometry":{"coordinates":[5.842964,47.20745],"type":"Point"},"properties":{"osm_id":"1352585168","tag":{"amenity":"recycling","location":"overground","recycling_type":"container"}},"type":"Feature"},
	{"geometry":{"coordinates":[5.876311,47.195354],"type":"Point"},"properties":{"osm_id":"6367743636","tag":{"amenity":"recycling","recycling_type":"container"}},"type":"Feature"},
	{"geometry":{"coordinates":[5.828149,47.186283],"type":"Point"},"properties":{"osm_id":"6563173403","tag":{"amenity":"recycling","recycling_type":"container"}},"type":"Feature"},
	{"geometry":{"coordinates":[5.820548,47.185264],"type":"Point"},"properties":{"osm_id":"6802056846","tag":{"amenity":"waste_basket"}},"type":"Feature"},
	{"geometry":{"coordinates":[5.810667,47.182863],"type":"Point"},"properties":{"osm_id":"6802078990","tag":{"amenity":"recycling","recycling_type":"container"}},"type":"Feature"},
	{"geometry":{"coordinates":[5.832315,47.182566],"type":"Point"},"properties":{"osm_id":"8412072289","tag":{"amenity":"recycling","recycling:glass_bottles":"yes","recycling_type":"container"}},"type":"Feature"},
	{"geometry":{"coordinates":[5.832288,47.182561],"type":"Point"},"properties":{"osm_id":"8412072290","tag":{"amenity":"recycling","recycling:glass_bottles":"yes","recycling_type":"container"}},"type":"Feature"},
	{"geometry":{"coordinates":[5.832261,47.182556],"type":"Point"},"properties":{"osm_id":"8412072291","tag":{"amenity":"recycling","recycling:glass_bottles":"yes","recycling_type":"container"}},"type":"Feature"},
	{"geometry":{"coordinates":[5.832234,47.182551],"type":"Point"},"properties":{"osm_id":"8412072292","tag":{"amenity":"recycling","recycling:glass_bottles":"yes","recycling_type":"container"}},"type":"Feature"},
	{"geometry":{"coordinates":[5.831356,47.182306],"type":"Point"},"properties":{"barrier":"gate","osm_id":"8412072294"},"type":"Feature"},
	{"geometry":{"coordinates":[5.832211,47.182406],"type":"Point"},"properties":{"barrier":"gate","osm_id":"8412072300"},"type":"Feature"},
	{"geometry":{"coordinates":[5.832069,47.182427],"type":"Point"},"properties":{"barrier":"gate","osm_id":"8412072301"},"type":"Feature"}
]
}
