{
"type": "FeatureCollection",
"features": [
	{"geometry":{"coordinates":[5.879083,45.280303],"type":"Point"},"properties":{"osm_id":"829907025","tag":{"amenity":"recycling","recycling:glass":"yes"}},"type":"Feature"},
	{"geometry":{"coordinates":[5.852164,45.292183],"type":"Point"},"properties":{"osm_id":"841825756","tag":{"amenity":"recycling","location":"overground","recycling_type":"container"}},"type":"Feature"},
	{"geometry":{"coordinates":[5.887426,45.310706],"type":"Point"},"properties":{"osm_id":"841827994","tag":{"amenity":"recycling","location":"overground","recycling:glass":"yes","recycling:paper":"yes","recycling_type":"container"}},"type":"Feature"},
	{"geometry":{"coordinates":[5.879055,45.303291],"type":"Point"},"properties":{"osm_id":"1448485802","tag":{"amenity":"recycling","location":"overground","recycling:glass":"yes","recycling:paper":"yes","recycling_type":"container"}},"type":"Feature"},
	{"geometry":{"coordinates":[5.878085,45.27811],"type":"Point"},"properties":{"osm_id":"2066612621","tag":{"amenity":"recycling","recycling_type":"container"}},"type":"Feature"},
	{"geometry":{"coordinates":[5.872692,45.30123],"type":"Point"},"properties":{"osm_id":"2452658073","tag":{"amenity":"recycling","location":"overground","recycling:glass":"yes","recycling:paper":"yes","recycling_type":"container"}},"type":"Feature"},
	{"geometry":{"coordinates":[5.887087,45.312732],"type":"Point"},"properties":{"osm_id":"3759895859","tag":{"amenity":"recycling","location":"overground","recycling:clothes":"yes","recycling:glass":"yes","recycling:glass_bottles":"yes","recycling:paper":"yes","recycling_type":"container"}},"type":"Feature"},
	{"geometry":{"coordinates":[5.859457,45.291791],"type":"Point"},"properties":{"osm_id":"5852126416","tag":{"amenity":"recycling","recycling:cans":"yes","recycling:glass_bottles":"yes","recycling:paper":"yes","recycling:plastic_bottles":"yes","recycling:plastic_packaging":"yes","recycling_type":"container"}},"type":"Feature"},
	{"geometry":{"coordinates":[5.883445,45.278306],"type":"Point"},"properties":{"osm_id":"6379281591","tag":{"amenity":"recycling","recycling:cartons":"yes","recycling:glass_bottles":"yes","recycling:papers":"yes","recycling_type":"container"}},"type":"Feature"},
	{"geometry":{"coordinates":[5.883468,45.278343],"type":"Point"},"properties":{"osm_id":"6379281592","tag":{"amenity":"recycling","operator":"gresy","recycling:clothes":"yes","recycling_type":"container"}},"type":"Feature"},
	{"geometry":{"coordinates":[5.884886,45.277103],"type":"Point"},"properties":{"osm_id":"6379281597","tag":{"amenity":"waste_basket"}},"type":"Feature"},
	{"geometry":{"coordinates":[5.886151,45.282826],"type":"Point"},"properties":{"osm_id":"6964189413","tag":{"amenity":"waste_disposal","waste":"recycling;household"}},"type":"Feature"}
]
}
