{
"type": "FeatureCollection",
"features": [
	{"geometry":{"coordinates":[10.741298,44.151376],"type":"Point"},"properties":{"name":"Faggio","osm_id":"5190555595","ref":"102","tag":{"access":"yes","circumference":"4.5","denotation":"natural_monument","height":"18","monument":"yes","name:it":"Faggio","natural":"tree","start_date":"1810","survey:date":"2005-06-03"}},"type":"Feature"},
	{"geometry":{"coordinates":[10.725697,44.200997],"type":"Point"},"properties":{"name":"Il Vecchione Ferito","osm_id":"9064804132","tag":{"denotation":"natural_monument","natural":"tree"}},"type":"Feature"}
]
}
