{
"type": "FeatureCollection",
"features": [
	{"geometry":{"coordinates":[-77.836312,39.633428],"type":"Point"},"properties":{"name":"Aluminum","osm_id":"2800836722","tag":{"amenity":"recycling"}},"type":"Feature"},
	{"geometry":{"coordinates":[-77.835808,39.633813],"type":"Point"},"properties":{"name":"Cardboard","osm_id":"2800836723","tag":{"amenity":"recycling"}},"type":"Feature"},
	{"geometry":{"coordinates":[-77.836005,39.634837],"type":"Point"},"properties":{"name":"Aluminum","osm_id":"2800836725","tag":{"amenity":"recycling"}},"type":"Feature"},
	{"geometry":{"coordinates":[-77.836875,39.633679],"type":"Point"},"properties":{"name":"Aluminum","osm_id":"2800836726","tag":{"amenity":"recycling"}},"type":"Feature"}
]
}
