{
"type": "FeatureCollection",
"features": [
	{"geometry":{"coordinates":[-77.836859,39.63372],"type":"Point"},"properties":{"name":"Dump Station","osm_id":"2798580940","tag":{"amenity":"waste_disposal"}},"type":"Feature"},
	{"geometry":{"coordinates":[-77.836156,39.634294],"type":"Point"},"properties":{"name":"Trash","osm_id":"2798580943","tag":{"amenity":"waste_disposal"}},"type":"Feature"},
	{"geometry":{"coordinates":[-77.836312,39.633429],"type":"Point"},"properties":{"name":"Aluminum","osm_id":"2800836722","tag":{"amenity":"recycling"}},"type":"Feature"},
	{"geometry":{"coordinates":[-77.835809,39.633814],"type":"Point"},"properties":{"name":"Cardboard","osm_id":"2800836723","tag":{"amenity":"recycling"}},"type":"Feature"},
	{"geometry":{"coordinates":[-77.836005,39.634837],"type":"Point"},"properties":{"name":"Aluminum","osm_id":"2800836725","tag":{"amenity":"recycling"}},"type":"Feature"},
	{"geometry":{"coordinates":[-77.836876,39.633679],"type":"Point"},"properties":{"name":"Aluminum","osm_id":"2800836726","tag":{"amenity":"recycling"}},"type":"Feature"}
]
}
