{
"type": "FeatureCollection",
"lastupdate": "2020-08-01T00:00:00Z",
"features": [
	{"geometry":{"coordinates":[4.862968,51.657989],"type":"Point"},"properties":{"osm_id":"2559948989","tag":{"amenity":"recycling","recycling:glass":"yes","recycling_type":"container"}},"type":"Feature"},
	{"geometry":{"coordinates":[4.863996,51.659699],"type":"Point"},"properties":{"osm_id":"2559949014","tag":{"amenity":"recycling","recycling:glass":"yes","recycling_type":"container"}},"type":"Feature"},
	{"geometry":{"coordinates":[4.847844,51.648184],"type":"Point"},"properties":{"name":"Milieustraat Oosterhout","osm_id":"4934097789","tag":{"amenity":"recycling","recycling_type":"centre"}},"type":"Feature"},
	{"geometry":{"coordinates":[4.921396,51.623626],"type":"Point"},"properties":{"osm_id":"6795832375","tag":{"amenity":"waste_basket","inscription":"Hondenpoep"}},"type":"Feature"},
	{"geometry":{"coordinates":[4.91948,51.623513],"type":"Point"},"properties":{"osm_id":"6795835109","tag":{"amenity":"waste_basket"}},"type":"Feature"},
	{"geometry":{"coordinates":[4.917151,51.622787],"type":"Point"},"properties":{"osm_id":"6795835110","tag":{"amenity":"waste_basket"}},"type":"Feature"},
	{"geometry":{"coordinates":[4.916485,51.622929],"type":"Point"},"properties":{"osm_id":"6795844763","tag":{"amenity":"waste_basket"}},"type":"Feature"},
	{"geometry":{"coordinates":[4.918278,51.623398],"type":"Point"},"properties":{"osm_id":"6795845675","tag":{"amenity":"waste_basket"}},"type":"Feature"},
	{"geometry":{"coordinates":[4.906013,51.624809],"type":"Point"},"properties":{"osm_id":"6795847430","tag":{"amenity":"waste_basket"}},"type":"Feature"},
	{"geometry":{"coordinates":[4.920314,51.623629],"type":"Point"},"properties":{"osm_id":"6795853315","tag":{"amenity":"waste_basket"}},"type":"Feature"},
	{"geometry":{"coordinates":[4.921855,51.624118],"type":"Point"},"properties":{"osm_id":"6795853485","tag":{"amenity":"waste_basket"}},"type":"Feature"},
	{"geometry":{"coordinates":[4.906022,51.624834],"type":"Point"},"properties":{"osm_id":"7055509134","tag":{"amenity":"waste_basket"}},"type":"Feature"}
]
}
