{
"type": "FeatureCollection",
"lastupdate": "2020-08-03T00:00:00Z",
"features": [
	{"geometry":{"coordinates":[4.920775,50.032413],"type":"Point"},"properties":{"osm_id":"5780239229","tag":{"amenity":"recycling","collection_times":"24/7","location":"underground","recycling:glass":"no","recycling:glass_bottles":"yes","recycling_type":"container"}},"type":"Feature"},
	{"geometry":{"coordinates":[4.920824,50.032406],"type":"Point"},"properties":{"osm_id":"5780239230","tag":{"amenity":"recycling","brand":"Terre","recycling:clothes":"yes","recycling_type":"container"}},"type":"Feature"},
	{"geometry":{"coordinates":[4.921127,50.032381],"type":"Point"},"properties":{"osm_id":"5780239232","tag":{"amenity":"waste_basket"}},"type":"Feature"},
	{"geometry":{"coordinates":[4.91892,50.031642],"type":"Point"},"properties":{"osm_id":"5780868676","tag":{"amenity":"waste_basket"}},"type":"Feature"},
	{"geometry":{"coordinates":[4.920803,50.032378],"type":"Point"},"properties":{"osm_id":"5784393854","tag":{"amenity":"waste_basket"}},"type":"Feature"},
	{"geometry":{"coordinates":[4.92109,50.033029],"type":"Point"},"properties":{"osm_id":"5784480575","tag":{"amenity":"waste_basket"}},"type":"Feature"},
	{"geometry":{"coordinates":[4.920542,50.032597],"type":"Point"},"properties":{"osm_id":"5784504001","tag":{"amenity":"recycling","brand":"Curitas","collection_times":"24/7","recycling:clothes":"yes","recycling_type":"container"}},"type":"Feature"}
]
}
