{
"type": "FeatureCollection",
"features": [
	{"geometry":{"coordinates":[-80.207035,39.01889],"type":"Point"},"properties":{"name":"Historic Location of the Pringle Tree","osm_id":"3428668235","tag":{"natural":"tree"}},"type":"Feature"},
	{"geometry":{"coordinates":[-80.233778,39.004046],"type":"Point"},"properties":{"osm_id":"5967422814","tag":{"natural":"tree"}},"type":"Feature"},
	{"geometry":{"coordinates":[-80.233778,39.004089],"type":"Point"},"properties":{"osm_id":"5967422815","tag":{"natural":"tree"}},"type":"Feature"},
	{"geometry":{"coordinates":[-80.233775,39.004137],"type":"Point"},"properties":{"osm_id":"5967422816","tag":{"natural":"tree"}},"type":"Feature"}
]
}
