{
"type": "FeatureCollection",
"features": [
	{"geometry":{"coordinates":[146.499186,-37.12863],"type":"Point"},"properties":{"name":"Hug Tree","osm_id":"340737042","tag":{"natural":"tree"}},"type":"Feature"}
]
}
