{
"type": "FeatureCollection",
"lastupdate": "2020-08-04T00:00:00Z",
"features": [
	{"geometry":{"coordinates":[10.924037,62.374918],"type":"Point"},"properties":{"name":"Eid omlastingstasjon og Torpet behandlingsanlegg","osm_id":"5555202933","tag":{"amenity":"recycling","recycling:asbestos":"yes","recycling:hazardous_waste":"yes","recycling:plasterboard":"yes","recycling:rubble":"yes","recycling:scrap_metal":"yes","recycling:waste":"yes","recycling:wood":"yes","recycling_type":"centre","ref:sortere":"1575"}},"type":"Feature"},
	{"geometry":{"coordinates":[10.93796,62.36677],"type":"Point"},"properties":{"osm_id":"5555208615","tag":{"access":"permissive","amenity":"recycling","description":"Eid hyttepunkt","recycling:glass_bottles":"yes","recycling:paper":"yes","recycling:waste":"yes","recycling_type":"container","ref:sortere":"13571"}},"type":"Feature"}
]
}
