{
"type": "FeatureCollection",
"features": [
	{"geometry":{"coordinates":[10.95362,49.33777],"type":"Point"},"properties":{"osm_id":"760994783","tag":{"amenity":"recycling","recycling:glass":"yes","recycling:scrap_metal":"yes","recycling_type":"container"}},"type":"Feature"},
	{"geometry":{"coordinates":[10.949392,49.369312],"type":"Point"},"properties":{"osm_id":"763153015","tag":{"amenity":"recycling","recycling:cans":"yes","recycling:clothes":"yes","recycling:glass":"yes"}},"type":"Feature"},
	{"geometry":{"coordinates":[10.92386,49.341276],"type":"Point"},"properties":{"osm_id":"773130542","tag":{"amenity":"recycling","recycling:cans":"yes","recycling:glass":"yes","recycling:scrap_metal":"yes"}},"type":"Feature"},
	{"geometry":{"coordinates":[10.906954,49.361458],"type":"Point"},"properties":{"osm_id":"915274810","tag":{"amenity":"recycling","recycling:cans":"yes","recycling:glass":"yes","recycling:scrap_metal":"yes"}},"type":"Feature"},
	{"geometry":{"coordinates":[10.93605,49.380645],"type":"Point"},"properties":{"osm_id":"915274815","tag":{"amenity":"recycling","recycling:cans":"yes","recycling:clothes":"yes","recycling:glass":"yes","recycling:scrap_metal":"yes"}},"type":"Feature"},
	{"geometry":{"coordinates":[10.911815,49.380302],"type":"Point"},"properties":{"osm_id":"950585091","tag":{"amenity":"recycling","location":"overground","recycling:cans":"yes","recycling:clothes":"yes","recycling:glass":"yes","recycling:scrap_metal":"yes","recycling_type":"container"}},"type":"Feature"},
	{"geometry":{"coordinates":[10.92865,49.379648],"type":"Point"},"properties":{"osm_id":"954585507","tag":{"amenity":"recycling","recycling:cans":"yes","recycling:clothes":"yes","recycling:glass":"yes","recycling:scrap_metal":"yes","recycling_type":"container"}},"type":"Feature"}
]
}
