{
"type": "FeatureCollection",
"features": [
	{"geometry":{"coordinates":[10.938802,48.458438],"type":"Point"},"properties":{"osm_id":"970969915","tag":{"amenity":"recycling","operator":"REMONDIS","recycling:glass":"yes"}},"type":"Feature"},
	{"geometry":{"coordinates":[10.966271,48.516441],"type":"Point"},"properties":{"osm_id":"3242840315","tag":{"amenity":"waste_basket"}},"type":"Feature"},
	{"geometry":{"coordinates":[10.91517,48.489084],"type":"Point"},"properties":{"name":"Wertstoffhof Rehling","osm_id":"3360608686","tag":{"amenity":"recycling","recycling_type":"centre","website":"http://www.gemeinde-rehling.de/index.php?option=com_content&view=article&id=13%3Awertstoffsammelstelle&catid=3%3Aeinrichtungen-der-gemeinde&Itemid=31"}},"type":"Feature"}
]
}
