{
"type": "FeatureCollection",
"lastupdate": "2020-08-05T00:00:00Z",
"features": [
	{"geometry":{"coordinates":[10.954438,43.728081],"type":"Point"},"properties":{"osm_id":"5276978749","tag":{"amenity":"waste_basket"}},"type":"Feature"},
	{"geometry":{"coordinates":[10.943647,43.727077],"type":"Point"},"properties":{"osm_id":"6146010292","tag":{"amenity":"recycling","recycling_type":"container"}},"type":"Feature"},
	{"geometry":{"coordinates":[10.947779,43.717833],"type":"Point"},"properties":{"osm_id":"6369862408","tag":{"amenity":"waste_basket"}},"type":"Feature"},
	{"geometry":{"coordinates":[10.947814,43.716833],"type":"Point"},"properties":{"osm_id":"6375678714","tag":{"amenity":"waste_basket"}},"type":"Feature"},
	{"geometry":{"coordinates":[10.902644,43.713262],"type":"Point"},"properties":{"name":"Centro di Raccolta","osm_id":"6410155098","tag":{"amenity":"recycling","operator":"Alia","recycling_type":"centre"}},"type":"Feature"},
	{"geometry":{"coordinates":[10.947942,43.718025],"type":"Point"},"properties":{"osm_id":"7513649024","tag":{"amenity":"waste_basket","operator":"Alia Servizi Ambientali"}},"type":"Feature"}
]
}
