{
"type": "FeatureCollection",
"features": [
	{"geometry":{"coordinates":[-4.652251,12.292654],"type":"Point"},"properties":{"name":"NERE","osm_id":"5232673997","tag":{"natural":"tree"}},"type":"Feature"},
	{"geometry":{"coordinates":[-4.650451,12.291563],"type":"Point"},"properties":{"osm_id":"5232676430","tag":{"natural":"tree"}},"type":"Feature"}
]
}
