{
"type": "FeatureCollection",
"features": [
	{"geometry":{"coordinates":[64.328271,39.987308],"type":"Point"},"properties":{"name":"Juda xafli joy. Tagida yotish mumkin emas","osm_id":"6496486056","tag":{"denotation":"landmark","leaf_type":"broadleaved","natural":"tree"}},"type":"Feature"}
]
}
