{
"type": "FeatureCollection",
"features": [
	{"geometry":{"coordinates":[-6.912766,38.285647],"type":"Point"},"properties":{"name":"Punto Limpio","osm_id":"8309464219","tag":{"amenity":"recycling","recycling_type":"centre"}},"type":"Feature"}
]
}
