{
"type": "FeatureCollection",
"features": [
	{"geometry":{"coordinates":[30.409391,39.891705],"type":"Point"},"properties":{"osm_id":"4527022931","tag":{"natural":"tree"}},"type":"Feature"},
	{"geometry":{"coordinates":[30.409872,39.89146],"type":"Point"},"properties":{"osm_id":"4527022932","tag":{"natural":"tree"}},"type":"Feature"},
	{"geometry":{"coordinates":[30.409133,39.891897],"type":"Point"},"properties":{"osm_id":"4527022933","tag":{"natural":"tree"}},"type":"Feature"},
	{"geometry":{"coordinates":[30.364538,39.901676],"type":"Point"},"properties":{"name":"1000 year old tree","osm_id":"4528728691","tag":{"natural":"tree"}},"type":"Feature"},
	{"geometry":{"coordinates":[30.366727,39.90126],"type":"Point"},"properties":{"osm_id":"4528732413","tag":{"natural":"tree"}},"type":"Feature"},
	{"geometry":{"coordinates":[30.397953,39.888424],"type":"Point"},"properties":{"osm_id":"4528962323","tag":{"natural":"tree"}},"type":"Feature"},
	{"geometry":{"coordinates":[30.410005,39.895246],"type":"Point"},"properties":{"osm_id":"4528965764","tag":{"natural":"tree"}},"type":"Feature"},
	{"geometry":{"coordinates":[30.40795,39.896654],"type":"Point"},"properties":{"osm_id":"4528965765","tag":{"natural":"tree"}},"type":"Feature"},
	{"geometry":{"coordinates":[30.407901,39.896786],"type":"Point"},"properties":{"osm_id":"4528965766","tag":{"natural":"tree"}},"type":"Feature"},
	{"geometry":{"coordinates":[30.40854,39.896523],"type":"Point"},"properties":{"osm_id":"4528965767","tag":{"natural":"tree"}},"type":"Feature"},
	{"geometry":{"coordinates":[30.408068,39.895909],"type":"Point"},"properties":{"osm_id":"4528965768","tag":{"natural":"tree"}},"type":"Feature"},
	{"geometry":{"coordinates":[30.403918,39.896053],"type":"Point"},"properties":{"osm_id":"4528965769","tag":{"natural":"tree"}},"type":"Feature"}
]
}
