{
"type": "FeatureCollection",
"features": [
	{"geometry":{"coordinates":[30.409391,39.891705],"type":"Point"},"properties":{"osm_id":"4527022931","tag":{"natural":"tree"}},"type":"Feature"},
	{"geometry":{"coordinates":[30.409871,39.891459],"type":"Point"},"properties":{"osm_id":"4527022932","tag":{"natural":"tree"}},"type":"Feature"},
	{"geometry":{"coordinates":[30.409132,39.891896],"type":"Point"},"properties":{"osm_id":"4527022933","tag":{"natural":"tree"}},"type":"Feature"},
	{"geometry":{"coordinates":[30.364538,39.901675],"type":"Point"},"properties":{"name":"1000 year old tree","osm_id":"4528728691","tag":{"natural":"tree"}},"type":"Feature"},
	{"geometry":{"coordinates":[30.366726,39.901259],"type":"Point"},"properties":{"osm_id":"4528732413","tag":{"natural":"tree"}},"type":"Feature"},
	{"geometry":{"coordinates":[30.397953,39.888424],"type":"Point"},"properties":{"osm_id":"4528962323","tag":{"natural":"tree"}},"type":"Feature"},
	{"geometry":{"coordinates":[30.410005,39.895245],"type":"Point"},"properties":{"osm_id":"4528965764","tag":{"natural":"tree"}},"type":"Feature"},
	{"geometry":{"coordinates":[30.407949,39.896654],"type":"Point"},"properties":{"osm_id":"4528965765","tag":{"natural":"tree"}},"type":"Feature"},
	{"geometry":{"coordinates":[30.407901,39.896786],"type":"Point"},"properties":{"osm_id":"4528965766","tag":{"natural":"tree"}},"type":"Feature"},
	{"geometry":{"coordinates":[30.408539,39.896522],"type":"Point"},"properties":{"osm_id":"4528965767","tag":{"natural":"tree"}},"type":"Feature"},
	{"geometry":{"coordinates":[30.408067,39.895909],"type":"Point"},"properties":{"osm_id":"4528965768","tag":{"natural":"tree"}},"type":"Feature"},
	{"geometry":{"coordinates":[30.403918,39.896053],"type":"Point"},"properties":{"osm_id":"4528965769","tag":{"natural":"tree"}},"type":"Feature"}
]
}
