{
"type": "FeatureCollection",
"features": [
	{"geometry":{"coordinates":[-83.599141,35.680095],"type":"Point"},"properties":{"name":"large tree","osm_id":"5071940670","tag":{"natural":"tree"}},"type":"Feature"}
]
}
