{
"type": "FeatureCollection",
"lastupdate": "2020-08-06T00:00:00Z",
"features": [
	{"geometry":{"coordinates":[-84.754391,42.246112],"type":"Point"},"properties":{"name":"Albion Area Recycling Site","osm_id":"1821709494","tag":{"amenity":"recycling","recycling:cans":"yes","recycling:cardboard":"yes","recycling:glass":"yes","recycling:glass_bottles":"yes","recycling:magazines":"yes","recycling:newspaper":"yes","recycling:paper":"yes","recycling:plastic":"yes","recycling:plastic_bottles":"yes","recycling_type":"container"}},"type":"Feature"}
]
}
