{
"type": "FeatureCollection",
"features": [
	{"geometry":{"coordinates":[15.81472,50.376795],"type":"Point"},"properties":{"osm_id":"2656454589","tag":{"leaf_type":"broadleaved","name:botanical":"Tilia","natural":"tree"}},"type":"Feature"},
	{"geometry":{"coordinates":[15.81477,50.376863],"type":"Point"},"properties":{"osm_id":"2656454591","tag":{"leaf_type":"broadleaved","name:botanical":"Tilia","natural":"tree"}},"type":"Feature"}
]
}
