{
"type": "FeatureCollection",
"features": [
	{"geometry":{"coordinates":[-74.991796,6.188918],"type":"Point"},"properties":{"osm_id":"4395589653","tag":{"natural":"tree"}},"type":"Feature"},
	{"geometry":{"coordinates":[-74.992171,6.188731],"type":"Point"},"properties":{"osm_id":"4395589655","tag":{"natural":"tree"}},"type":"Feature"},
	{"geometry":{"coordinates":[-74.991903,6.188726],"type":"Point"},"properties":{"osm_id":"4395589657","tag":{"natural":"tree"}},"type":"Feature"},
	{"geometry":{"coordinates":[-74.989899,6.188555],"type":"Point"},"properties":{"osm_id":"4395589658","tag":{"natural":"tree"}},"type":"Feature"},
	{"geometry":{"coordinates":[-74.99201,6.189027],"type":"Point"},"properties":{"osm_id":"4395589660","tag":{"natural":"tree"}},"type":"Feature"},
	{"geometry":{"coordinates":[-74.992348,6.188723],"type":"Point"},"properties":{"osm_id":"4395589661","tag":{"natural":"tree"}},"type":"Feature"},
	{"geometry":{"coordinates":[-74.991622,6.188536],"type":"Point"},"properties":{"osm_id":"4395589662","tag":{"natural":"tree"}},"type":"Feature"},
	{"geometry":{"coordinates":[-74.991892,6.188398],"type":"Point"},"properties":{"osm_id":"4395589663","tag":{"natural":"tree"}},"type":"Feature"},
	{"geometry":{"coordinates":[-74.991769,6.188475],"type":"Point"},"properties":{"osm_id":"4395589664","tag":{"natural":"tree"}},"type":"Feature"},
	{"geometry":{"coordinates":[-74.990233,6.188437],"type":"Point"},"properties":{"name":"Eucalipto","osm_id":"4395589665","tag":{"natural":"tree"}},"type":"Feature"},
	{"geometry":{"coordinates":[-74.991742,6.188773],"type":"Point"},"properties":{"osm_id":"4395589666","tag":{"natural":"tree"}},"type":"Feature"},
	{"geometry":{"coordinates":[-74.992346,6.188918],"type":"Point"},"properties":{"name":"Mango","osm_id":"4395589667","tag":{"natural":"tree"}},"type":"Feature"},
	{"geometry":{"coordinates":[-74.992026,6.188344],"type":"Point"},"properties":{"osm_id":"4395589668","tag":{"natural":"tree"}},"type":"Feature"},
	{"geometry":{"coordinates":[-74.992158,6.188597],"type":"Point"},"properties":{"osm_id":"4395589669","tag":{"natural":"tree"}},"type":"Feature"},
	{"geometry":{"coordinates":[-74.992209,6.188405],"type":"Point"},"properties":{"osm_id":"4395589670","tag":{"natural":"tree"}},"type":"Feature"},
	{"geometry":{"coordinates":[-74.992035,6.188485],"type":"Point"},"properties":{"osm_id":"4395589671","tag":{"natural":"tree"}},"type":"Feature"},
	{"geometry":{"coordinates":[-74.99186,6.188659],"type":"Point"},"properties":{"osm_id":"4395589672","tag":{"natural":"tree"}},"type":"Feature"},
	{"geometry":{"coordinates":[-74.992145,6.188251],"type":"Point"},"properties":{"osm_id":"4395589675","tag":{"natural":"tree"}},"type":"Feature"}
]
}
