{
"type": "FeatureCollection",
"features": [
	{"geometry":{"coordinates":[-74.991796,6.188918],"type":"Point"},"properties":{"osm_id":"4395589653","tag":{"natural":"tree"}},"type":"Feature"},
	{"geometry":{"coordinates":[-74.992172,6.188731],"type":"Point"},"properties":{"osm_id":"4395589655","tag":{"natural":"tree"}},"type":"Feature"},
	{"geometry":{"coordinates":[-74.991904,6.188726],"type":"Point"},"properties":{"osm_id":"4395589657","tag":{"natural":"tree"}},"type":"Feature"},
	{"geometry":{"coordinates":[-74.9899,6.188555],"type":"Point"},"properties":{"osm_id":"4395589658","tag":{"natural":"tree"}},"type":"Feature"},
	{"geometry":{"coordinates":[-74.992011,6.189027],"type":"Point"},"properties":{"osm_id":"4395589660","tag":{"natural":"tree"}},"type":"Feature"},
	{"geometry":{"coordinates":[-74.992349,6.188723],"type":"Point"},"properties":{"osm_id":"4395589661","tag":{"natural":"tree"}},"type":"Feature"},
	{"geometry":{"coordinates":[-74.991623,6.188537],"type":"Point"},"properties":{"osm_id":"4395589662","tag":{"natural":"tree"}},"type":"Feature"},
	{"geometry":{"coordinates":[-74.991893,6.188398],"type":"Point"},"properties":{"osm_id":"4395589663","tag":{"natural":"tree"}},"type":"Feature"},
	{"geometry":{"coordinates":[-74.991769,6.188475],"type":"Point"},"properties":{"osm_id":"4395589664","tag":{"natural":"tree"}},"type":"Feature"},
	{"geometry":{"coordinates":[-74.990233,6.188438],"type":"Point"},"properties":{"name":"Eucalipto","osm_id":"4395589665","tag":{"natural":"tree"}},"type":"Feature"},
	{"geometry":{"coordinates":[-74.991743,6.188774],"type":"Point"},"properties":{"osm_id":"4395589666","tag":{"natural":"tree"}},"type":"Feature"},
	{"geometry":{"coordinates":[-74.992346,6.188918],"type":"Point"},"properties":{"name":"Mango","osm_id":"4395589667","tag":{"natural":"tree"}},"type":"Feature"},
	{"geometry":{"coordinates":[-74.992027,6.188345],"type":"Point"},"properties":{"osm_id":"4395589668","tag":{"natural":"tree"}},"type":"Feature"},
	{"geometry":{"coordinates":[-74.992158,6.188598],"type":"Point"},"properties":{"osm_id":"4395589669","tag":{"natural":"tree"}},"type":"Feature"},
	{"geometry":{"coordinates":[-74.992209,6.188406],"type":"Point"},"properties":{"osm_id":"4395589670","tag":{"natural":"tree"}},"type":"Feature"},
	{"geometry":{"coordinates":[-74.992035,6.188486],"type":"Point"},"properties":{"osm_id":"4395589671","tag":{"natural":"tree"}},"type":"Feature"},
	{"geometry":{"coordinates":[-74.991861,6.188659],"type":"Point"},"properties":{"osm_id":"4395589672","tag":{"natural":"tree"}},"type":"Feature"},
	{"geometry":{"coordinates":[-74.992145,6.188252],"type":"Point"},"properties":{"osm_id":"4395589675","tag":{"natural":"tree"}},"type":"Feature"}
]
}
