{
"type": "FeatureCollection",
"features": [
	{"geometry":{"coordinates":[11.782486,48.814504],"type":"Point"},"properties":{"osm_id":"268595717","tag":{"amenity":"recycling","recycling:clothes":"yes","recycling:glass":"yes","recycling:shoes":"yes"}},"type":"Feature"},
	{"geometry":{"coordinates":[11.853893,48.821161],"type":"Point"},"properties":{"osm_id":"612037390","tag":{"amenity":"recycling","recycling:glass":"yes","recycling_type":"container"}},"type":"Feature"},
	{"geometry":{"coordinates":[11.845564,48.812064],"type":"Point"},"properties":{"osm_id":"612037780","tag":{"amenity":"recycling","location":"overground","recycling:glass":"yes","recycling_type":"container"}},"type":"Feature"},
	{"geometry":{"coordinates":[11.861057,48.810821],"type":"Point"},"properties":{"osm_id":"612075881","tag":{"amenity":"recycling","recycling:glass":"yes","recycling_type":"container"}},"type":"Feature"},
	{"geometry":{"coordinates":[11.810533,48.838761],"type":"Point"},"properties":{"osm_id":"616208917","tag":{"amenity":"recycling","recycling:glass":"yes","recycling_type":"container"}},"type":"Feature"},
	{"geometry":{"coordinates":[11.854306,48.816835],"type":"Point"},"properties":{"osm_id":"1349656260","tag":{"amenity":"recycling","location":"overground","recycling_type":"container"}},"type":"Feature"},
	{"geometry":{"coordinates":[11.851288,48.826411],"type":"Point"},"properties":{"osm_id":"7905477096","tag":{"amenity":"waste_basket","material":"steel","waste":"trash"}},"type":"Feature"},
	{"geometry":{"coordinates":[11.789343,48.817786],"type":"Point"},"properties":{"osm_id":"9177991989","tag":{"amenity":"waste_basket"}},"type":"Feature"}
]
}
