{
"type": "FeatureCollection",
"features": [
	{"geometry":{"coordinates":[96.148957,16.797241],"type":"Point"},"properties":{"name":"Bodhi Tree","osm_id":"4419423175","tag":{"natural":"tree"}},"type":"Feature"},
	{"geometry":{"coordinates":[96.149402,16.797384],"type":"Point"},"properties":{"name":"Bodhi Tree","osm_id":"4419423180","tag":{"natural":"tree"}},"type":"Feature"},
	{"geometry":{"coordinates":[96.149504,16.7974],"type":"Point"},"properties":{"name":"Bodhi Tree","osm_id":"4419423186","tag":{"natural":"tree"}},"type":"Feature"},
	{"geometry":{"coordinates":[96.150109,16.799523],"type":"Point"},"properties":{"name":"Bodhi Tree","osm_id":"4419552355","tag":{"natural":"tree"}},"type":"Feature"},
	{"geometry":{"coordinates":[96.150717,16.79775],"type":"Point"},"properties":{"name":"Bodhi Tree","osm_id":"4419569934","tag":{"natural":"tree"}},"type":"Feature"},
	{"geometry":{"coordinates":[96.148501,16.799578],"type":"Point"},"properties":{"name":"Bodhi Tree","osm_id":"4419569935","tag":{"natural":"tree"}},"type":"Feature"}
]
}
