{
"type": "FeatureCollection",
"features": [
	{"geometry":{"coordinates":[96.148956,16.79724],"type":"Point"},"properties":{"name":"Bodhi Tree","osm_id":"4419423175","tag":{"natural":"tree"}},"type":"Feature"},
	{"geometry":{"coordinates":[96.149402,16.797384],"type":"Point"},"properties":{"name":"Bodhi Tree","osm_id":"4419423180","tag":{"natural":"tree"}},"type":"Feature"},
	{"geometry":{"coordinates":[96.149504,16.797399],"type":"Point"},"properties":{"name":"Bodhi Tree","osm_id":"4419423186","tag":{"natural":"tree"}},"type":"Feature"},
	{"geometry":{"coordinates":[96.150108,16.799522],"type":"Point"},"properties":{"name":"Bodhi Tree","osm_id":"4419552355","tag":{"natural":"tree"}},"type":"Feature"},
	{"geometry":{"coordinates":[96.150716,16.79775],"type":"Point"},"properties":{"name":"Bodhi Tree","osm_id":"4419569934","tag":{"natural":"tree"}},"type":"Feature"},
	{"geometry":{"coordinates":[96.148501,16.799578],"type":"Point"},"properties":{"name":"Bodhi Tree","osm_id":"4419569935","tag":{"natural":"tree"}},"type":"Feature"}
]
}
