{
"type": "FeatureCollection",
"features": [
	{"geometry":{"coordinates":[34.306466,28.664523],"type":"Point"},"properties":{"name":"Nachlet Gorra","osm_id":"2697774131","tag":{"natural":"tree"}},"type":"Feature"}
]
}
