{
"type": "FeatureCollection",
"lastupdate": "2020-07-31T00:00:00Z",
"features": [
	{"geometry":{"coordinates":[-117.545587,34.090569],"type":"Point"},"properties":{"name":"Campbell Recycling","osm_id":"1291088181","tag":{"amenity":"recycling","opening_hours":"Mo-Sa 8:30-16:30","recycling:aluminium":"yes","recycling:batteries":"yes","recycling:cans":"yes","recycling:cardboard":"yes","recycling:glass_bottles":"yes","recycling:scrap_metal":"yes","recycling:sheet_metal":"yes","recycling:small_appliances":"yes","recycling:white_goods":"yes"}},"type":"Feature"},
	{"geometry":{"coordinates":[-117.591673,34.134276],"type":"Point"},"properties":{"osm_id":"4640515935","tag":{"amenity":"recycling","recycling_type":"container"}},"type":"Feature"}
]
}
