{
"type": "FeatureCollection",
"lastupdate": "2020-08-04T00:00:00Z",
"features": [
	{"geometry":{"coordinates":[6.854227,49.48916],"type":"Point"},"properties":{"osm_id":"800988385","tag":{"amenity":"recycling","recycling:glass":"yes","recycling_type":"container"}},"type":"Feature"},
	{"geometry":{"coordinates":[6.781161,49.454191],"type":"Point"},"properties":{"osm_id":"1286629957","tag":{"amenity":"recycling"}},"type":"Feature"},
	{"geometry":{"coordinates":[6.841076,49.44744],"type":"Point"},"properties":{"osm_id":"2613481723","tag":{"amenity":"recycling","recycling:glass":"yes","recycling:paper":"yes","recycling_type":"container"}},"type":"Feature"},
	{"geometry":{"coordinates":[6.851806,49.465804],"type":"Point"},"properties":{"osm_id":"2668978512","tag":{"amenity":"recycling"}},"type":"Feature"},
	{"geometry":{"coordinates":[6.832337,49.46582],"type":"Point"},"properties":{"osm_id":"2752395053","tag":{"amenity":"recycling","recycling:clothes":"yes","recycling:glass":"yes","recycling:paper":"yes"}},"type":"Feature"},
	{"geometry":{"coordinates":[6.85099,49.444298],"type":"Point"},"properties":{"osm_id":"3922233106","tag":{"amenity":"recycling","recycling:cardboard":"yes","recycling:glass":"yes","recycling:paper":"yes","recycling_type":"container","wheelchair":"yes"}},"type":"Feature"},
	{"geometry":{"coordinates":[6.837302,49.49236],"type":"Point"},"properties":{"osm_id":"4974552211","tag":{"amenity":"recycling","location":"overground","recycling:clothes":"yes","recycling:glass":"yes","recycling:paper":"yes","recycling_type":"container"}},"type":"Feature"},
	{"geometry":{"coordinates":[6.84385,49.453113],"type":"Point"},"properties":{"osm_id":"5434211822","tag":{"amenity":"recycling","recycling_type":"container"}},"type":"Feature"},
	{"geometry":{"coordinates":[6.842372,49.451716],"type":"Point"},"properties":{"osm_id":"5434211825","tag":{"amenity":"waste_basket"}},"type":"Feature"},
	{"geometry":{"coordinates":[6.839307,49.487229],"type":"Point"},"properties":{"osm_id":"5881821109","tag":{"amenity":"waste_basket"}},"type":"Feature"},
	{"geometry":{"coordinates":[6.854152,49.487601],"type":"Point"},"properties":{"osm_id":"7644535616","tag":{"amenity":"waste_basket"}},"type":"Feature"}
]
}
