{
"type": "FeatureCollection",
"features": [
	{"geometry":{"coordinates":[6.852924,45.91409],"type":"Point"},"properties":{"osm_id":"246136978","tag":{"amenity":"recycling","recycling:glass_bottles":"yes"}},"type":"Feature"},
	{"geometry":{"coordinates":[6.852866,45.912339],"type":"Point"},"properties":{"osm_id":"251792166","tag":{"amenity":"recycling"}},"type":"Feature"},
	{"geometry":{"coordinates":[6.797104,45.890649],"type":"Point"},"properties":{"osm_id":"1032261428","tag":{"amenity":"waste_basket"}},"type":"Feature"},
	{"geometry":{"coordinates":[6.800379,45.892734],"type":"Point"},"properties":{"osm_id":"1032261442","tag":{"amenity":"recycling","recycling:cartons":"yes","recycling:glass":"yes","recycling:paper":"yes","recycling:plastic":"yes","recycling:waste":"yes","recycling_type":"container"}},"type":"Feature"},
	{"geometry":{"coordinates":[6.802525,45.894588],"type":"Point"},"properties":{"osm_id":"1038831383","tag":{"amenity":"waste_basket"}},"type":"Feature"},
	{"geometry":{"coordinates":[6.78174,45.895285],"type":"Point"},"properties":{"osm_id":"1044222693","tag":{"amenity":"waste_basket"}},"type":"Feature"},
	{"geometry":{"coordinates":[6.843261,45.904771],"type":"Point"},"properties":{"name":"Litter bin + recycling","osm_id":"1385680137","tag":{"amenity":"recycling"}},"type":"Feature"},
	{"geometry":{"coordinates":[6.840747,45.905183],"type":"Point"},"properties":{"osm_id":"1399138920","tag":{"amenity":"recycling","recycling_type":"centre"}},"type":"Feature"},
	{"geometry":{"coordinates":[6.84062,45.900058],"type":"Point"},"properties":{"osm_id":"1399146895","tag":{"amenity":"recycling"}},"type":"Feature"},
	{"geometry":{"coordinates":[6.836182,45.902518],"type":"Point"},"properties":{"osm_id":"1875111659","tag":{"amenity":"recycling","recycling:cans":"yes","recycling:glass":"yes","recycling:paper":"yes","recycling:scrap_metal":"yes","recycling_type":"container"}},"type":"Feature"},
	{"geometry":{"coordinates":[6.768893,45.931265],"type":"Point"},"properties":{"osm_id":"1882526114","tag":{"amenity":"recycling","recycling:cans":"yes","recycling:cardboard":"yes","recycling:glass":"yes","recycling:paper":"yes","recycling:plastic":"yes","recycling_type":"container"}},"type":"Feature"},
	{"geometry":{"coordinates":[6.850496,45.915895],"type":"Point"},"properties":{"osm_id":"2192961294","tag":{"amenity":"waste_basket"}},"type":"Feature"},
	{"geometry":{"coordinates":[6.849918,45.915924],"type":"Point"},"properties":{"osm_id":"2192969680","tag":{"amenity":"waste_basket"}},"type":"Feature"},
	{"geometry":{"coordinates":[6.848447,45.914926],"type":"Point"},"properties":{"osm_id":"4919754162","tag":{"amenity":"waste_basket"}},"type":"Feature"},
	{"geometry":{"coordinates":[6.773145,45.902548],"type":"Point"},"properties":{"osm_id":"5673183954","tag":{"amenity":"waste_basket","waste":"trash"}},"type":"Feature"},
	{"geometry":{"coordinates":[6.772951,45.902953],"type":"Point"},"properties":{"osm_id":"5673183955","tag":{"amenity":"waste_basket","waste":"trash"}},"type":"Feature"},
	{"geometry":{"coordinates":[6.850226,45.916009],"type":"Point"},"properties":{"osm_id":"5830185345","tag":{"amenity":"waste_disposal"}},"type":"Feature"},
	{"geometry":{"coordinates":[6.850191,45.916005],"type":"Point"},"properties":{"osm_id":"5830185346","tag":{"amenity":"waste_disposal"}},"type":"Feature"},
	{"geometry":{"coordinates":[6.850308,45.916024],"type":"Point"},"properties":{"osm_id":"5830185347","tag":{"amenity":"waste_disposal"}},"type":"Feature"},
	{"geometry":{"coordinates":[6.850268,45.916016],"type":"Point"},"properties":{"osm_id":"5830185348","tag":{"amenity":"waste_disposal"}},"type":"Feature"},
	{"geometry":{"coordinates":[6.829362,45.898385],"type":"Point"},"properties":{"osm_id":"7222862606","tag":{"amenity":"recycling","recycling:cans":"yes","recycling:glass":"yes","recycling:paper":"yes","recycling:scrap_metal":"yes","recycling_type":"container"}},"type":"Feature"},
	{"geometry":{"coordinates":[6.835391,45.90459],"type":"Point"},"properties":{"osm_id":"7222862607","tag":{"amenity":"recycling","recycling:cans":"yes","recycling:glass":"yes","recycling:paper":"yes","recycling:scrap_metal":"yes","recycling_type":"container"}},"type":"Feature"},
	{"geometry":{"coordinates":[6.798865,45.891724],"type":"Point"},"properties":{"osm_id":"7514583269","tag":{"amenity":"waste_disposal","waste":"recycling;plastic"}},"type":"Feature"},
	{"geometry":{"coordinates":[6.800225,45.892619],"type":"Point"},"properties":{"osm_id":"7514583270","tag":{"amenity":"waste_disposal","waste":"organic;excrements;glass"}},"type":"Feature"},
	{"geometry":{"coordinates":[6.779965,45.89736],"type":"Point"},"properties":{"osm_id":"7650079373","tag":{"amenity":"recycling"}},"type":"Feature"},
	{"geometry":{"coordinates":[6.853267,45.913266],"type":"Point"},"properties":{"osm_id":"7816898286","tag":{"amenity":"recycling","survey:date":"2020-08-16"}},"type":"Feature"}
]
}
