{
"type": "FeatureCollection",
"lastupdate": "2020-08-05T00:00:00Z",
"features": [
	{"geometry":{"coordinates":[6.852924,45.914089],"type":"Point"},"properties":{"osm_id":"246136978","tag":{"amenity":"recycling","recycling:glass_bottles":"yes"}},"type":"Feature"},
	{"geometry":{"coordinates":[6.852865,45.912338],"type":"Point"},"properties":{"osm_id":"251792166","tag":{"amenity":"recycling"}},"type":"Feature"},
	{"geometry":{"coordinates":[6.797103,45.890648],"type":"Point"},"properties":{"osm_id":"1032261428","tag":{"amenity":"waste_basket"}},"type":"Feature"},
	{"geometry":{"coordinates":[6.800378,45.892733],"type":"Point"},"properties":{"osm_id":"1032261442","tag":{"amenity":"recycling","recycling:cartons":"yes","recycling:glass":"yes","recycling:paper":"yes","recycling:plastic":"yes","recycling:waste":"yes","recycling_type":"container"}},"type":"Feature"},
	{"geometry":{"coordinates":[6.802525,45.894587],"type":"Point"},"properties":{"osm_id":"1038831383","tag":{"amenity":"waste_basket"}},"type":"Feature"},
	{"geometry":{"coordinates":[6.781739,45.895284],"type":"Point"},"properties":{"osm_id":"1044222693","tag":{"amenity":"waste_basket"}},"type":"Feature"},
	{"geometry":{"coordinates":[6.843261,45.90477],"type":"Point"},"properties":{"name":"Litter bin + recycling","osm_id":"1385680137","tag":{"amenity":"recycling"}},"type":"Feature"},
	{"geometry":{"coordinates":[6.840746,45.905182],"type":"Point"},"properties":{"osm_id":"1399138920","tag":{"amenity":"recycling","recycling_type":"centre"}},"type":"Feature"},
	{"geometry":{"coordinates":[6.84062,45.900058],"type":"Point"},"properties":{"osm_id":"1399146895","tag":{"amenity":"recycling"}},"type":"Feature"},
	{"geometry":{"coordinates":[6.836181,45.902517],"type":"Point"},"properties":{"osm_id":"1875111659","tag":{"amenity":"recycling","recycling:cans":"yes","recycling:glass":"yes","recycling:paper":"yes","recycling:scrap_metal":"yes","recycling_type":"container"}},"type":"Feature"},
	{"geometry":{"coordinates":[6.768893,45.931265],"type":"Point"},"properties":{"osm_id":"1882526114","tag":{"amenity":"recycling","recycling:cans":"yes","recycling:cardboard":"yes","recycling:glass":"yes","recycling:paper":"yes","recycling:plastic":"yes","recycling_type":"container"}},"type":"Feature"},
	{"geometry":{"coordinates":[6.850495,45.915894],"type":"Point"},"properties":{"osm_id":"2192961294","tag":{"amenity":"waste_basket"}},"type":"Feature"},
	{"geometry":{"coordinates":[6.849917,45.915923],"type":"Point"},"properties":{"osm_id":"2192969680","tag":{"amenity":"waste_basket"}},"type":"Feature"},
	{"geometry":{"coordinates":[6.848446,45.914926],"type":"Point"},"properties":{"osm_id":"4919754162","tag":{"amenity":"waste_basket"}},"type":"Feature"},
	{"geometry":{"coordinates":[6.773144,45.902547],"type":"Point"},"properties":{"osm_id":"5673183954","tag":{"amenity":"waste_basket","waste":"trash"}},"type":"Feature"},
	{"geometry":{"coordinates":[6.77295,45.902953],"type":"Point"},"properties":{"osm_id":"5673183955","tag":{"amenity":"waste_basket","waste":"trash"}},"type":"Feature"},
	{"geometry":{"coordinates":[6.829361,45.898385],"type":"Point"},"properties":{"osm_id":"7222862606","tag":{"amenity":"recycling","recycling:cans":"yes","recycling:glass":"yes","recycling:paper":"yes","recycling:scrap_metal":"yes","recycling_type":"container"}},"type":"Feature"},
	{"geometry":{"coordinates":[6.835391,45.904589],"type":"Point"},"properties":{"osm_id":"7222862607","tag":{"amenity":"recycling","recycling:cans":"yes","recycling:glass":"yes","recycling:paper":"yes","recycling:scrap_metal":"yes","recycling_type":"container"}},"type":"Feature"},
	{"geometry":{"coordinates":[6.779964,45.897359],"type":"Point"},"properties":{"osm_id":"7650079373","tag":{"amenity":"recycling"}},"type":"Feature"}
]
}
