{
"type": "FeatureCollection",
"features": [
	{"geometry":{"coordinates":[6.780734,44.66256],"type":"Point"},"properties":{"osm_id":"2332710292","tag":{"amenity":"recycling"}},"type":"Feature"},
	{"geometry":{"coordinates":[6.774915,44.67044],"type":"Point"},"properties":{"osm_id":"4011732654","tag":{"amenity":"recycling","recycling:glass":"yes","recycling:paper":"yes","recycling:plastic_packaging":"yes","recycling:waste":"yes","recycling_type":"container"}},"type":"Feature"},
	{"geometry":{"coordinates":[6.778199,44.668628],"type":"Point"},"properties":{"osm_id":"4901061139","tag":{"amenity":"recycling","recycling_type":"container"}},"type":"Feature"},
	{"geometry":{"coordinates":[6.77806,44.666801],"type":"Point"},"properties":{"osm_id":"4903169599","tag":{"amenity":"recycling"}},"type":"Feature"},
	{"geometry":{"coordinates":[6.776161,44.667166],"type":"Point"},"properties":{"osm_id":"4907412862","tag":{"amenity":"recycling"}},"type":"Feature"},
	{"geometry":{"coordinates":[6.778193,44.668611],"type":"Point"},"properties":{"osm_id":"4907424412","tag":{"amenity":"recycling"}},"type":"Feature"},
	{"geometry":{"coordinates":[6.775478,44.671706],"type":"Point"},"properties":{"osm_id":"4907425263","tag":{"amenity":"recycling","location":"overground","recycling_type":"container"}},"type":"Feature"},
	{"geometry":{"coordinates":[6.772735,44.673347],"type":"Point"},"properties":{"osm_id":"4907433261","tag":{"amenity":"recycling"}},"type":"Feature"},
	{"geometry":{"coordinates":[6.776544,44.666036],"type":"Point"},"properties":{"osm_id":"5912478387","tag":{"amenity":"recycling","recycling_type":"container"}},"type":"Feature"},
	{"geometry":{"coordinates":[6.777096,44.668747],"type":"Point"},"properties":{"osm_id":"5912478388","tag":{"amenity":"recycling","recycling_type":"container"}},"type":"Feature"},
	{"geometry":{"coordinates":[6.776956,44.667732],"type":"Point"},"properties":{"osm_id":"7922118542","tag":{"amenity":"waste_basket"}},"type":"Feature"},
	{"geometry":{"coordinates":[6.780723,44.662515],"type":"Point"},"properties":{"osm_id":"7938650103","tag":{"amenity":"recycling","recycling_type":"container"}},"type":"Feature"}
]
}
