{
"type": "FeatureCollection",
"lastupdate": "2020-08-04T00:00:00Z",
"features": [
	{"geometry":{"coordinates":[6.780734,44.662559],"type":"Point"},"properties":{"osm_id":"2332710292","tag":{"amenity":"recycling"}},"type":"Feature"},
	{"geometry":{"coordinates":[6.774914,44.670439],"type":"Point"},"properties":{"osm_id":"4011732654","tag":{"amenity":"recycling","recycling:glass":"yes","recycling:paper":"yes","recycling:plastic_packaging":"yes","recycling:waste":"yes","recycling_type":"container"}},"type":"Feature"},
	{"geometry":{"coordinates":[6.778199,44.668628],"type":"Point"},"properties":{"osm_id":"4901061139","tag":{"amenity":"recycling","recycling_type":"container"}},"type":"Feature"},
	{"geometry":{"coordinates":[6.77806,44.666801],"type":"Point"},"properties":{"osm_id":"4903169599","tag":{"amenity":"recycling"}},"type":"Feature"},
	{"geometry":{"coordinates":[6.776161,44.667165],"type":"Point"},"properties":{"osm_id":"4907412862","tag":{"amenity":"recycling"}},"type":"Feature"},
	{"geometry":{"coordinates":[6.778193,44.66861],"type":"Point"},"properties":{"osm_id":"4907424412","tag":{"amenity":"recycling"}},"type":"Feature"},
	{"geometry":{"coordinates":[6.775478,44.671706],"type":"Point"},"properties":{"osm_id":"4907425263","tag":{"amenity":"recycling","location":"overground","recycling_type":"container"}},"type":"Feature"},
	{"geometry":{"coordinates":[6.772735,44.673346],"type":"Point"},"properties":{"osm_id":"4907433261","tag":{"amenity":"recycling"}},"type":"Feature"},
	{"geometry":{"coordinates":[6.776544,44.666035],"type":"Point"},"properties":{"osm_id":"5912478387","tag":{"amenity":"recycling","recycling_type":"container"}},"type":"Feature"},
	{"geometry":{"coordinates":[6.777096,44.668746],"type":"Point"},"properties":{"osm_id":"5912478388","tag":{"amenity":"recycling","recycling_type":"container"}},"type":"Feature"}
]
}
