{
"type": "FeatureCollection",
"features": [
	{"geometry":{"coordinates":[6.847758,43.699312],"type":"Point"},"properties":{"osm_id":"1688960058","tag":{"amenity":"waste_basket"}},"type":"Feature"},
	{"geometry":{"coordinates":[6.851104,43.697441],"type":"Point"},"properties":{"osm_id":"2435474385","tag":{"amenity":"recycling","location":"overground","recycling_type":"container"}},"type":"Feature"},
	{"geometry":{"coordinates":[6.843408,43.690634],"type":"Point"},"properties":{"osm_id":"3037449278","tag":{"amenity":"waste_disposal"}},"type":"Feature"},
	{"geometry":{"coordinates":[6.844188,43.691681],"type":"Point"},"properties":{"osm_id":"3037449280","tag":{"amenity":"waste_disposal"}},"type":"Feature"},
	{"geometry":{"coordinates":[6.84695,43.693494],"type":"Point"},"properties":{"osm_id":"3037449294","tag":{"amenity":"waste_disposal"}},"type":"Feature"},
	{"geometry":{"coordinates":[6.850898,43.699249],"type":"Point"},"properties":{"osm_id":"3037840882","tag":{"amenity":"recycling","location":"overground","recycling_type":"container"}},"type":"Feature"},
	{"geometry":{"coordinates":[6.85046,43.700073],"type":"Point"},"properties":{"osm_id":"3037841234","tag":{"amenity":"waste_disposal"}},"type":"Feature"},
	{"geometry":{"coordinates":[6.848675,43.700408],"type":"Point"},"properties":{"osm_id":"3037841258","tag":{"amenity":"recycling","location":"overground","recycling_type":"container"}},"type":"Feature"},
	{"geometry":{"coordinates":[6.848597,43.700428],"type":"Point"},"properties":{"osm_id":"3037841259","tag":{"amenity":"waste_disposal"}},"type":"Feature"},
	{"geometry":{"coordinates":[6.847679,43.699311],"type":"Point"},"properties":{"osm_id":"3038128199","tag":{"amenity":"recycling","recycling:clothes":"yes","recycling_type":"container"}},"type":"Feature"},
	{"geometry":{"coordinates":[6.846864,43.698427],"type":"Point"},"properties":{"osm_id":"3044755455","tag":{"amenity":"recycling","recycling:clothes":"yes","recycling_type":"container"}},"type":"Feature"},
	{"geometry":{"coordinates":[6.80303,43.647202],"type":"Point"},"properties":{"osm_id":"4124694587","tag":{"amenity":"recycling","recycling:cans":"yes","recycling:cardboard":"yes","recycling:glass":"yes","recycling:glass_bottles":"yes","recycling:paper":"yes","recycling:plastic":"yes","recycling:plastic_bottles":"yes","recycling:plastic_packaging":"yes","recycling:waste":"yes","recycling_type":"container"}},"type":"Feature"},
	{"geometry":{"coordinates":[6.854209,43.693179],"type":"Point"},"properties":{"osm_id":"4372141997","tag":{"amenity":"waste_disposal"}},"type":"Feature"},
	{"geometry":{"coordinates":[6.851043,43.697466],"type":"Point"},"properties":{"osm_id":"4372142037","tag":{"amenity":"waste_disposal"}},"type":"Feature"},
	{"geometry":{"coordinates":[6.847927,43.693227],"type":"Point"},"properties":{"osm_id":"5586195540","tag":{"amenity":"waste_disposal"}},"type":"Feature"},
	{"geometry":{"coordinates":[6.85174,43.644657],"type":"Point"},"properties":{"osm_id":"7041954751","tag":{"amenity":"waste_disposal"}},"type":"Feature"},
	{"geometry":{"coordinates":[6.85472,43.645025],"type":"Point"},"properties":{"osm_id":"7119075965","tag":{"amenity":"waste_disposal"}},"type":"Feature"}
]
}
