{
"type": "FeatureCollection",
"features": [
	{"geometry":{"coordinates":[6.847758,43.699313],"type":"Point"},"properties":{"osm_id":"1688960058","tag":{"amenity":"waste_basket"}},"type":"Feature"},
	{"geometry":{"coordinates":[6.851105,43.697441],"type":"Point"},"properties":{"osm_id":"2435474385","tag":{"amenity":"recycling","location":"overground","recycling_type":"container"}},"type":"Feature"},
	{"geometry":{"coordinates":[6.843408,43.690634],"type":"Point"},"properties":{"osm_id":"3037449278","tag":{"amenity":"waste_disposal"}},"type":"Feature"},
	{"geometry":{"coordinates":[6.844188,43.691682],"type":"Point"},"properties":{"osm_id":"3037449280","tag":{"amenity":"waste_disposal"}},"type":"Feature"},
	{"geometry":{"coordinates":[6.84695,43.693494],"type":"Point"},"properties":{"osm_id":"3037449294","tag":{"amenity":"waste_disposal"}},"type":"Feature"},
	{"geometry":{"coordinates":[6.850898,43.69925],"type":"Point"},"properties":{"osm_id":"3037840882","tag":{"amenity":"recycling","location":"overground","recycling_type":"container"}},"type":"Feature"},
	{"geometry":{"coordinates":[6.850461,43.700074],"type":"Point"},"properties":{"osm_id":"3037841234","tag":{"amenity":"waste_disposal"}},"type":"Feature"},
	{"geometry":{"coordinates":[6.848675,43.700408],"type":"Point"},"properties":{"osm_id":"3037841258","tag":{"amenity":"recycling","location":"overground","recycling_type":"container"}},"type":"Feature"},
	{"geometry":{"coordinates":[6.848598,43.700429],"type":"Point"},"properties":{"osm_id":"3037841259","tag":{"amenity":"waste_disposal"}},"type":"Feature"},
	{"geometry":{"coordinates":[6.84768,43.699311],"type":"Point"},"properties":{"osm_id":"3038128199","tag":{"amenity":"recycling","recycling:clothes":"yes","recycling_type":"container"}},"type":"Feature"},
	{"geometry":{"coordinates":[6.846864,43.698428],"type":"Point"},"properties":{"osm_id":"3044755455","tag":{"amenity":"recycling","recycling:clothes":"yes","recycling_type":"container"}},"type":"Feature"},
	{"geometry":{"coordinates":[6.803031,43.647203],"type":"Point"},"properties":{"osm_id":"4124694587","tag":{"amenity":"recycling","recycling:cans":"yes","recycling:cardboard":"yes","recycling:glass":"yes","recycling:glass_bottles":"yes","recycling:paper":"yes","recycling:plastic":"yes","recycling:plastic_bottles":"yes","recycling:plastic_packaging":"yes","recycling:waste":"yes","recycling_type":"container"}},"type":"Feature"},
	{"geometry":{"coordinates":[6.854209,43.69318],"type":"Point"},"properties":{"osm_id":"4372141997","tag":{"amenity":"waste_disposal"}},"type":"Feature"},
	{"geometry":{"coordinates":[6.851044,43.697466],"type":"Point"},"properties":{"osm_id":"4372142037","tag":{"amenity":"waste_disposal"}},"type":"Feature"},
	{"geometry":{"coordinates":[6.847928,43.693228],"type":"Point"},"properties":{"osm_id":"5586195540","tag":{"amenity":"waste_disposal"}},"type":"Feature"},
	{"geometry":{"coordinates":[6.85174,43.644658],"type":"Point"},"properties":{"osm_id":"7041954751","tag":{"amenity":"waste_disposal"}},"type":"Feature"},
	{"geometry":{"coordinates":[6.854721,43.645025],"type":"Point"},"properties":{"osm_id":"7119075965","tag":{"amenity":"waste_disposal"}},"type":"Feature"}
]
}
