{
"type": "FeatureCollection",
"features": [
	{"geometry":{"coordinates":[-87.029978,12.366911],"type":"Point"},"properties":{"name":"La Casa Verde","osm_id":"7155546085","tag":{"amenity":"recycling"}},"type":"Feature"}
]
}
