{
"type": "FeatureCollection",
"features": [
	{"geometry":{"coordinates":[173.369391,-34.86977],"type":"Point"},"properties":{"name":"Transfer Station","osm_id":"622253337","tag":{"amenity":"recycling"}},"type":"Feature"}
]
}
