{
"type": "FeatureCollection",
"features": [
	{"geometry":{"coordinates":[173.368842,-34.868099],"type":"Point"},"properties":{"name":"Transfer Station","osm_id":"622253337","tag":{"amenity":"recycling"}},"type":"Feature"}
]
}
