{
"type": "FeatureCollection",
"features": [
	{"geometry":{"coordinates":[-85.146181,31.898495],"type":"Point"},"properties":{"name":"The Tree That Owns Itself","osm_id":"6441105265","tag":{"monument":"yes","natural":"tree","wikipedia":"en:Tree That Owns Itself (Alabama)"}},"type":"Feature"},
	{"geometry":{"coordinates":[-85.158792,31.887592],"type":"Point"},"properties":{"osm_id":"9111573016","tag":{"natural":"tree"}},"type":"Feature"},
	{"geometry":{"coordinates":[-85.160983,31.886641],"type":"Point"},"properties":{"osm_id":"9111584671","tag":{"natural":"tree"}},"type":"Feature"},
	{"geometry":{"coordinates":[-85.160581,31.886554],"type":"Point"},"properties":{"osm_id":"9111584672","tag":{"natural":"tree"}},"type":"Feature"},
	{"geometry":{"coordinates":[-85.160013,31.886095],"type":"Point"},"properties":{"osm_id":"9111584673","tag":{"natural":"tree"}},"type":"Feature"},
	{"geometry":{"coordinates":[-85.159601,31.887083],"type":"Point"},"properties":{"osm_id":"9111584929","tag":{"natural":"tree"}},"type":"Feature"},
	{"geometry":{"coordinates":[-85.159939,31.887358],"type":"Point"},"properties":{"osm_id":"9111584930","tag":{"natural":"tree"}},"type":"Feature"},
	{"geometry":{"coordinates":[-85.159725,31.886438],"type":"Point"},"properties":{"osm_id":"9111584933","tag":{"natural":"tree"}},"type":"Feature"},
	{"geometry":{"coordinates":[-85.160318,31.886477],"type":"Point"},"properties":{"osm_id":"9111584934","tag":{"natural":"tree"}},"type":"Feature"},
	{"geometry":{"coordinates":[-85.158848,31.887552],"type":"Point"},"properties":{"osm_id":"9111591117","tag":{"natural":"tree"}},"type":"Feature"},
	{"geometry":{"coordinates":[-85.158768,31.887537],"type":"Point"},"properties":{"osm_id":"9111591118","tag":{"natural":"tree"}},"type":"Feature"},
	{"geometry":{"coordinates":[-85.158669,31.887617],"type":"Point"},"properties":{"osm_id":"9111591119","tag":{"natural":"tree"}},"type":"Feature"},
	{"geometry":{"coordinates":[-85.158323,31.887773],"type":"Point"},"properties":{"osm_id":"9111591120","tag":{"natural":"tree"}},"type":"Feature"},
	{"geometry":{"coordinates":[-85.15868,31.8879],"type":"Point"},"properties":{"osm_id":"9111591121","tag":{"natural":"tree"}},"type":"Feature"},
	{"geometry":{"coordinates":[-85.158208,31.887889],"type":"Point"},"properties":{"osm_id":"9111591122","tag":{"natural":"tree"}},"type":"Feature"},
	{"geometry":{"coordinates":[-85.159408,31.887388],"type":"Point"},"properties":{"osm_id":"9111790577","tag":{"natural":"tree"}},"type":"Feature"}
]
}
