{
"type": "FeatureCollection",
"features": [
	{"geometry":{"coordinates":[-85.146182,31.898495],"type":"Point"},"properties":{"name":"The Tree That Owns Itself","osm_id":"6441105265","tag":{"monument":"yes","natural":"tree","wikipedia":"en:Tree That Owns Itself (Alabama)"}},"type":"Feature"}
]
}
