{
"type": "FeatureCollection",
"features": [
	{"geometry":{"coordinates":[-85.150896,10.338378],"type":"Point"},"properties":{"name":"Guaiacum sanctum","osm_id":"6020901802","tag":{"designation":"Zygophyllaceae","natural":"tree"}},"type":"Feature"}
]
}
