{
"type": "FeatureCollection",
"features": [
	{"geometry":{"coordinates":[34.450147,28.769251],"type":"Point"},"properties":{"name":"ratha","osm_id":"2687318001","tag":{"natural":"tree"}},"type":"Feature"},
	{"geometry":{"coordinates":[34.451846,28.769791],"type":"Point"},"properties":{"osm_id":"3077196671","tag":{"description":"ratha","natural":"tree"}},"type":"Feature"},
	{"geometry":{"coordinates":[34.44744,28.770664],"type":"Point"},"properties":{"osm_id":"3077199682","tag":{"description":"ratha","natural":"tree"}},"type":"Feature"}
]
}
