{
"type": "FeatureCollection",
"features": [
	{"geometry":{"coordinates":[110.461185,-7.029528],"type":"Point"},"properties":{"osm_id":"5631687468","tag":{"amenity":"waste_disposal","waste":"trash"}},"type":"Feature"},
	{"geometry":{"coordinates":[110.461612,-7.06426],"type":"Point"},"properties":{"name":"TPS BKJ","osm_id":"9129136893","tag":{"amenity":"recycling","description":"Tempat Pembuangan Sampah","operator":"Dinas Kebersihan Kota Semarang","recycling:green_waste":"yes","recycling_type":"container"}},"type":"Feature"}
]
}
