{
"type": "FeatureCollection",
"features": [
	{"geometry":{"coordinates":[-72.361118,41.406203],"type":"Point"},"properties":{"name":"6' tulip tree","osm_id":"6693622508","tag":{"natural":"tree","website":"https://photos.app.goo.gl/ANHzVTfST8mBjLhv9"}},"type":"Feature"}
]
}
