{
"type": "FeatureCollection",
"features": [
	{"geometry":{"coordinates":[14.600395,50.971903],"type":"Point"},"properties":{"name":"Friedenseiche 1871","osm_id":"278918576","tag":{"natural":"tree"}},"type":"Feature"},
	{"geometry":{"coordinates":[14.663174,50.980512],"type":"Point"},"properties":{"osm_id":"1872519226","tag":{"natural":"tree"}},"type":"Feature"},
	{"geometry":{"coordinates":[14.595777,50.990359],"type":"Point"},"properties":{"osm_id":"2297671556","tag":{"natural":"tree"}},"type":"Feature"},
	{"geometry":{"coordinates":[14.670448,50.958805],"type":"Point"},"properties":{"osm_id":"4118389322","tag":{"genus:de":"Eiche","leaf_cycle":"deciduous","leaf_type":"broadleaved","natural":"tree"}},"type":"Feature"},
	{"geometry":{"coordinates":[14.677336,50.981496],"type":"Point"},"properties":{"osm_id":"4544503304","tag":{"natural":"tree"}},"type":"Feature"},
	{"geometry":{"coordinates":[14.675117,50.982137],"type":"Point"},"properties":{"osm_id":"4544503305","tag":{"natural":"tree"}},"type":"Feature"},
	{"geometry":{"coordinates":[14.619069,50.983161],"type":"Point"},"properties":{"osm_id":"4829257029","tag":{"leaf_cycle":"deciduous","leaf_type":"broadleaved","natural":"tree"}},"type":"Feature"},
	{"geometry":{"coordinates":[14.619112,50.983186],"type":"Point"},"properties":{"osm_id":"4829257030","tag":{"leaf_cycle":"deciduous","leaf_type":"broadleaved","natural":"tree"}},"type":"Feature"},
	{"geometry":{"coordinates":[14.61918,50.983147],"type":"Point"},"properties":{"osm_id":"4829257031","tag":{"leaf_cycle":"deciduous","leaf_type":"broadleaved","natural":"tree"}},"type":"Feature"},
	{"geometry":{"coordinates":[14.619138,50.983117],"type":"Point"},"properties":{"osm_id":"4829257032","tag":{"leaf_cycle":"deciduous","leaf_type":"broadleaved","natural":"tree"}},"type":"Feature"},
	{"geometry":{"coordinates":[14.624363,50.980972],"type":"Point"},"properties":{"osm_id":"4829297336","tag":{"leaf_cycle":"deciduous","leaf_type":"broadleaved","natural":"tree"}},"type":"Feature"},
	{"geometry":{"coordinates":[14.618227,51.002565],"type":"Point"},"properties":{"osm_id":"5459111202","tag":{"leaf_cycle":"deciduous","leaf_type":"broadleaved","natural":"tree"}},"type":"Feature"},
	{"geometry":{"coordinates":[14.618264,51.002735],"type":"Point"},"properties":{"osm_id":"5459111203","tag":{"leaf_cycle":"deciduous","leaf_type":"broadleaved","natural":"tree"}},"type":"Feature"},
	{"geometry":{"coordinates":[14.618018,51.002936],"type":"Point"},"properties":{"osm_id":"5459111204","tag":{"leaf_cycle":"deciduous","leaf_type":"broadleaved","natural":"tree"}},"type":"Feature"},
	{"geometry":{"coordinates":[14.61692,51.003218],"type":"Point"},"properties":{"osm_id":"5459111214","tag":{"leaf_cycle":"deciduous","leaf_type":"broadleaved","natural":"tree"}},"type":"Feature"},
	{"geometry":{"coordinates":[14.617116,51.003204],"type":"Point"},"properties":{"osm_id":"5459111215","tag":{"leaf_cycle":"deciduous","leaf_type":"broadleaved","natural":"tree"}},"type":"Feature"},
	{"geometry":{"coordinates":[14.618951,51.002728],"type":"Point"},"properties":{"osm_id":"5459111216","tag":{"leaf_cycle":"deciduous","leaf_type":"broadleaved","natural":"tree"}},"type":"Feature"},
	{"geometry":{"coordinates":[14.619219,51.002655],"type":"Point"},"properties":{"osm_id":"5459111217","tag":{"leaf_cycle":"deciduous","leaf_type":"broadleaved","natural":"tree"}},"type":"Feature"},
	{"geometry":{"coordinates":[14.618595,51.00262],"type":"Point"},"properties":{"osm_id":"5459111218","tag":{"leaf_cycle":"deciduous","leaf_type":"broadleaved","natural":"tree"}},"type":"Feature"},
	{"geometry":{"coordinates":[14.619135,51.002389],"type":"Point"},"properties":{"osm_id":"5459111523","tag":{"leaf_type":"broadleaved","natural":"tree"}},"type":"Feature"},
	{"geometry":{"coordinates":[14.616376,51.003106],"type":"Point"},"properties":{"osm_id":"5459111538","tag":{"leaf_type":"broadleaved","natural":"tree"}},"type":"Feature"},
	{"geometry":{"coordinates":[14.616448,51.003102],"type":"Point"},"properties":{"osm_id":"5459111539","tag":{"leaf_cycle":"deciduous","leaf_type":"broadleaved","natural":"tree"}},"type":"Feature"},
	{"geometry":{"coordinates":[14.61653,51.003093],"type":"Point"},"properties":{"osm_id":"5459111540","tag":{"leaf_cycle":"deciduous","leaf_type":"broadleaved","natural":"tree"}},"type":"Feature"},
	{"geometry":{"coordinates":[14.618149,51.002219],"type":"Point"},"properties":{"osm_id":"5459111543","tag":{"leaf_cycle":"deciduous","leaf_type":"broadleaved","natural":"tree"}},"type":"Feature"},
	{"geometry":{"coordinates":[14.618128,51.002136],"type":"Point"},"properties":{"osm_id":"5459111544","tag":{"leaf_cycle":"deciduous","leaf_type":"broadleaved","natural":"tree"}},"type":"Feature"},
	{"geometry":{"coordinates":[14.641896,50.982168],"type":"Point"},"properties":{"osm_id":"7728553788","tag":{"leaf_type":"broadleaved","natural":"tree"}},"type":"Feature"}
]
}
