{
"type": "FeatureCollection",
"features": [
	{"geometry":{"coordinates":[14.240519,45.807841],"type":"Point"},"properties":{"name":"Meliwova jelka","osm_id":"5135763196","tag":{"denotation":"natural_monument","leaf_type":"needleleaved","natural":"tree"}},"type":"Feature"},
	{"geometry":{"coordinates":[14.265278,45.82768],"type":"Point"},"properties":{"osm_id":"5161559362","tag":{"natural":"tree"}},"type":"Feature"}
]
}
