{
"type": "FeatureCollection",
"features": [
	{"geometry":{"coordinates":[-74.843856,40.605346],"type":"Point"},"properties":{"name":"Dumpster","osm_id":"7924330110","tag":{"access":"permissive","amenity":"waste_disposal","waste":"trash"}},"type":"Feature"}
]
}
