{
"type": "FeatureCollection",
"lastupdate": "2020-08-05T00:00:00Z",
"features": [
	{"geometry":{"coordinates":[-97.474828,25.854033],"type":"Point"},"properties":{"name":"Compra de metales","osm_id":"4537330292","tag":{"amenity":"recycling","name:es":"Compra de metales"}},"type":"Feature"},
	{"geometry":{"coordinates":[-97.47909,25.837659],"type":"Point"},"properties":{"name":"Compra y venta metales","osm_id":"4537330390","tag":{"amenity":"recycling","name:es":"Compra y venta metales"}},"type":"Feature"},
	{"geometry":{"coordinates":[-97.527667,25.878623],"type":"Point"},"properties":{"name":"ERCA","osm_id":"4836286163","tag":{"amenity":"recycling","recycling_type":"centre"}},"type":"Feature"}
]
}
