{
"type": "FeatureCollection",
"features": [
	{"geometry":{"coordinates":[18.468907,52.575199],"type":"Point"},"properties":{"osm_id":"4706675795","tag":{"denotation":"natural_monument","natural":"tree","ref:CRFOP":"PL.ZIPOP.1393.PP.0411053.6079","ref:INSPIRE":"PL.ZIPOP.1393.PP.0411053.6079","website":"http://crfop.gdos.gov.pl/CRFOP/widok/viewfop.jsf?fop=PL.ZIPOP.1393.PP.0411053.6079"}},"type":"Feature"},
	{"geometry":{"coordinates":[18.470155,52.576402],"type":"Point"},"properties":{"osm_id":"4706675796","tag":{"denotation":"natural_monument","natural":"tree","ref:CRFOP":"PL.ZIPOP.1393.PP.0411053.6078","ref:INSPIRE":"PL.ZIPOP.1393.PP.0411053.6078","website":"http://crfop.gdos.gov.pl/CRFOP/widok/viewfop.jsf?fop=PL.ZIPOP.1393.PP.0411053.6078"}},"type":"Feature"},
	{"geometry":{"coordinates":[18.470049,52.577159],"type":"Point"},"properties":{"osm_id":"4706675797","tag":{"denotation":"natural_monument","natural":"tree","ref:CRFOP":"PL.ZIPOP.1393.PP.0411053.6077","ref:INSPIRE":"PL.ZIPOP.1393.PP.0411053.6077","website":"http://crfop.gdos.gov.pl/CRFOP/widok/viewfop.jsf?fop=PL.ZIPOP.1393.PP.0411053.6077"}},"type":"Feature"},
	{"geometry":{"coordinates":[18.49814,52.553071],"type":"Point"},"properties":{"osm_id":"4706675800","tag":{"denotation":"natural_monument","natural":"tree","ref:CRFOP":"PL.ZIPOP.1393.PP.0411053.6072","ref:INSPIRE":"PL.ZIPOP.1393.PP.0411053.6072","website":"http://crfop.gdos.gov.pl/CRFOP/widok/viewfop.jsf?fop=PL.ZIPOP.1393.PP.0411053.6072"}},"type":"Feature"},
	{"geometry":{"coordinates":[18.497993,52.55329],"type":"Point"},"properties":{"osm_id":"4706675801","tag":{"denotation":"natural_monument","natural":"tree","ref:CRFOP":"PL.ZIPOP.1393.PP.0411053.6071","ref:INSPIRE":"PL.ZIPOP.1393.PP.0411053.6071","website":"http://crfop.gdos.gov.pl/CRFOP/widok/viewfop.jsf?fop=PL.ZIPOP.1393.PP.0411053.6071"}},"type":"Feature"}
]
}
