{
"type": "FeatureCollection",
"features": [
	{"geometry":{"coordinates":[18.507309,46.034489],"type":"Point"},"properties":{"name":"jellegfa (vadgesztenye)","osm_id":"6328479611","tag":{"leaf_cycle":"deciduous","leaf_type":"broadleaved","natural":"tree"}},"type":"Feature"}
]
}
