{
"type": "FeatureCollection",
"features": [
	{"geometry":{"coordinates":[-1.61941,54.79279],"type":"Point"},"properties":{"name":"Sycamore","osm_id":"393339124","tag":{"natural":"tree"}},"type":"Feature"},
	{"geometry":{"coordinates":[-1.638154,54.775734],"type":"Point"},"properties":{"osm_id":"2821105076","tag":{"natural":"tree"}},"type":"Feature"},
	{"geometry":{"coordinates":[-1.638605,54.775876],"type":"Point"},"properties":{"osm_id":"2821105077","tag":{"natural":"tree"}},"type":"Feature"},
	{"geometry":{"coordinates":[-1.6389,54.775979],"type":"Point"},"properties":{"osm_id":"2821105078","tag":{"natural":"tree"}},"type":"Feature"},
	{"geometry":{"coordinates":[-1.639212,54.776082],"type":"Point"},"properties":{"osm_id":"2821105079","tag":{"natural":"tree"}},"type":"Feature"},
	{"geometry":{"coordinates":[-1.63948,54.776156],"type":"Point"},"properties":{"osm_id":"2821105080","tag":{"natural":"tree"}},"type":"Feature"},
	{"geometry":{"coordinates":[-1.639744,54.776244],"type":"Point"},"properties":{"osm_id":"2821105081","tag":{"natural":"tree"}},"type":"Feature"},
	{"geometry":{"coordinates":[-1.636357,54.77547],"type":"Point"},"properties":{"osm_id":"2821105082","tag":{"natural":"tree"}},"type":"Feature"},
	{"geometry":{"coordinates":[-1.633176,54.775524],"type":"Point"},"properties":{"osm_id":"2821105083","tag":{"natural":"tree"}},"type":"Feature"},
	{"geometry":{"coordinates":[-1.634712,54.776015],"type":"Point"},"properties":{"osm_id":"2821105084","tag":{"natural":"tree"}},"type":"Feature"},
	{"geometry":{"coordinates":[-1.635855,54.776345],"type":"Point"},"properties":{"osm_id":"2821105085","tag":{"natural":"tree"}},"type":"Feature"},
	{"geometry":{"coordinates":[-1.582489,54.804823],"type":"Point"},"properties":{"osm_id":"4191633683","tag":{"natural":"tree"}},"type":"Feature"},
	{"geometry":{"coordinates":[-1.582411,54.804905],"type":"Point"},"properties":{"osm_id":"4191633691","tag":{"natural":"tree"}},"type":"Feature"},
	{"geometry":{"coordinates":[-1.582422,54.805038],"type":"Point"},"properties":{"osm_id":"4191633704","tag":{"natural":"tree"}},"type":"Feature"},
	{"geometry":{"coordinates":[-1.594441,54.81993],"type":"Point"},"properties":{"osm_id":"4236326652","tag":{"natural":"tree"}},"type":"Feature"},
	{"geometry":{"coordinates":[-1.593828,54.819889],"type":"Point"},"properties":{"osm_id":"4236326653","tag":{"natural":"tree"}},"type":"Feature"},
	{"geometry":{"coordinates":[-1.637392,54.797257],"type":"Point"},"properties":{"osm_id":"4242907199","tag":{"natural":"tree"}},"type":"Feature"},
	{"geometry":{"coordinates":[-1.637287,54.797401],"type":"Point"},"properties":{"osm_id":"4242907209","tag":{"natural":"tree"}},"type":"Feature"},
	{"geometry":{"coordinates":[-1.588935,54.780645],"type":"Point"},"properties":{"osm_id":"4937581191","tag":{"natural":"tree"}},"type":"Feature"},
	{"geometry":{"coordinates":[-1.582508,54.796353],"type":"Point"},"properties":{"osm_id":"7343653125","tag":{"natural":"tree"}},"type":"Feature"},
	{"geometry":{"coordinates":[-1.582664,54.79627],"type":"Point"},"properties":{"osm_id":"7343653126","tag":{"natural":"tree"}},"type":"Feature"},
	{"geometry":{"coordinates":[-1.582593,54.7962],"type":"Point"},"properties":{"osm_id":"7343653127","tag":{"natural":"tree"}},"type":"Feature"},
	{"geometry":{"coordinates":[-1.58484,54.794758],"type":"Point"},"properties":{"osm_id":"7343653302","tag":{"natural":"tree"}},"type":"Feature"},
	{"geometry":{"coordinates":[-1.58422,54.794663],"type":"Point"},"properties":{"osm_id":"7343653303","tag":{"natural":"tree"}},"type":"Feature"},
	{"geometry":{"coordinates":[-1.584492,54.794639],"type":"Point"},"properties":{"osm_id":"7343653304","tag":{"natural":"tree"}},"type":"Feature"},
	{"geometry":{"coordinates":[-1.584115,54.794904],"type":"Point"},"properties":{"osm_id":"7343653305","tag":{"natural":"tree"}},"type":"Feature"}
]
}
