{
"type": "FeatureCollection",
"features": [
	{"geometry":{"coordinates":[-1.61941,54.792789],"type":"Point"},"properties":{"name":"Sycamore","osm_id":"393339124","tag":{"natural":"tree"}},"type":"Feature"},
	{"geometry":{"coordinates":[-1.638153,54.775734],"type":"Point"},"properties":{"osm_id":"2821105076","tag":{"natural":"tree"}},"type":"Feature"},
	{"geometry":{"coordinates":[-1.638604,54.775875],"type":"Point"},"properties":{"osm_id":"2821105077","tag":{"natural":"tree"}},"type":"Feature"},
	{"geometry":{"coordinates":[-1.6389,54.775978],"type":"Point"},"properties":{"osm_id":"2821105078","tag":{"natural":"tree"}},"type":"Feature"},
	{"geometry":{"coordinates":[-1.639211,54.776082],"type":"Point"},"properties":{"osm_id":"2821105079","tag":{"natural":"tree"}},"type":"Feature"},
	{"geometry":{"coordinates":[-1.639479,54.776156],"type":"Point"},"properties":{"osm_id":"2821105080","tag":{"natural":"tree"}},"type":"Feature"},
	{"geometry":{"coordinates":[-1.639744,54.776243],"type":"Point"},"properties":{"osm_id":"2821105081","tag":{"natural":"tree"}},"type":"Feature"},
	{"geometry":{"coordinates":[-1.636357,54.775469],"type":"Point"},"properties":{"osm_id":"2821105082","tag":{"natural":"tree"}},"type":"Feature"},
	{"geometry":{"coordinates":[-1.633175,54.775523],"type":"Point"},"properties":{"osm_id":"2821105083","tag":{"natural":"tree"}},"type":"Feature"},
	{"geometry":{"coordinates":[-1.634711,54.776014],"type":"Point"},"properties":{"osm_id":"2821105084","tag":{"natural":"tree"}},"type":"Feature"},
	{"geometry":{"coordinates":[-1.635855,54.776344],"type":"Point"},"properties":{"osm_id":"2821105085","tag":{"natural":"tree"}},"type":"Feature"},
	{"geometry":{"coordinates":[-1.582488,54.804823],"type":"Point"},"properties":{"osm_id":"4191633683","tag":{"natural":"tree"}},"type":"Feature"},
	{"geometry":{"coordinates":[-1.58241,54.804905],"type":"Point"},"properties":{"osm_id":"4191633691","tag":{"natural":"tree"}},"type":"Feature"},
	{"geometry":{"coordinates":[-1.582421,54.805038],"type":"Point"},"properties":{"osm_id":"4191633704","tag":{"natural":"tree"}},"type":"Feature"},
	{"geometry":{"coordinates":[-1.594441,54.819929],"type":"Point"},"properties":{"osm_id":"4236326652","tag":{"natural":"tree"}},"type":"Feature"},
	{"geometry":{"coordinates":[-1.593827,54.819888],"type":"Point"},"properties":{"osm_id":"4236326653","tag":{"natural":"tree"}},"type":"Feature"},
	{"geometry":{"coordinates":[-1.637392,54.797257],"type":"Point"},"properties":{"osm_id":"4242907199","tag":{"natural":"tree"}},"type":"Feature"},
	{"geometry":{"coordinates":[-1.637287,54.797401],"type":"Point"},"properties":{"osm_id":"4242907209","tag":{"natural":"tree"}},"type":"Feature"},
	{"geometry":{"coordinates":[-1.588935,54.780644],"type":"Point"},"properties":{"osm_id":"4937581191","tag":{"natural":"tree"}},"type":"Feature"},
	{"geometry":{"coordinates":[-1.582508,54.796353],"type":"Point"},"properties":{"osm_id":"7343653125","tag":{"natural":"tree"}},"type":"Feature"},
	{"geometry":{"coordinates":[-1.582664,54.79627],"type":"Point"},"properties":{"osm_id":"7343653126","tag":{"natural":"tree"}},"type":"Feature"},
	{"geometry":{"coordinates":[-1.582592,54.796199],"type":"Point"},"properties":{"osm_id":"7343653127","tag":{"natural":"tree"}},"type":"Feature"},
	{"geometry":{"coordinates":[-1.584839,54.794757],"type":"Point"},"properties":{"osm_id":"7343653302","tag":{"natural":"tree"}},"type":"Feature"},
	{"geometry":{"coordinates":[-1.584219,54.794662],"type":"Point"},"properties":{"osm_id":"7343653303","tag":{"natural":"tree"}},"type":"Feature"},
	{"geometry":{"coordinates":[-1.584491,54.794638],"type":"Point"},"properties":{"osm_id":"7343653304","tag":{"natural":"tree"}},"type":"Feature"},
	{"geometry":{"coordinates":[-1.584115,54.794904],"type":"Point"},"properties":{"osm_id":"7343653305","tag":{"natural":"tree"}},"type":"Feature"}
]
}
