{
"type": "FeatureCollection",
"lastupdate": "2020-08-04T00:00:00Z",
"features": [
	{"geometry":{"coordinates":[80.595424,7.268256],"type":"Point"},"properties":{"name":"Recycle bins","osm_id":"5922321886","tag":{"amenity":"waste_basket"}},"type":"Feature"}
]
}
