{
"type": "FeatureCollection",
"features": [
	{"geometry":{"coordinates":[80.595425,7.268256],"type":"Point"},"properties":{"name":"Recycle bins","osm_id":"5922321886","tag":{"amenity":"waste_basket"}},"type":"Feature"}
]
}
