{
"type": "FeatureCollection",
"lastupdate": "2020-08-03T00:00:00Z",
"features": [
	{"geometry":{"coordinates":[-84.332029,33.798541],"type":"Point"},"properties":{"name":"Emory Recycles","osm_id":"490648379","tag":{"amenity":"recycling"}},"type":"Feature"},
	{"geometry":{"coordinates":[-84.329461,33.815863],"type":"Point"},"properties":{"osm_id":"2053641400","tag":{"access":"private","amenity":"recycling"}},"type":"Feature"}
]
}
