{
"type": "FeatureCollection",
"features": [
	{"geometry":{"coordinates":[9.873154,49.470737],"type":"Point"},"properties":{"osm_id":"289652773","tag":{"amenity":"recycling","recycling:clothes":"yes","recycling:glass_bottles":"yes","recycling_type":"container"}},"type":"Feature"},
	{"geometry":{"coordinates":[9.905266,49.479376],"type":"Point"},"properties":{"name":"Recyclinghof","osm_id":"290359581","tag":{"amenity":"recycling","recycling_type":"centre"}},"type":"Feature"},
	{"geometry":{"coordinates":[9.900534,49.477241],"type":"Point"},"properties":{"osm_id":"313959503","tag":{"amenity":"recycling","recycling:glass_bottles":"yes","recycling_type":"container"}},"type":"Feature"},
	{"geometry":{"coordinates":[9.902847,49.480707],"type":"Point"},"properties":{"osm_id":"316242869","tag":{"amenity":"recycling","recycling:clothes":"yes","recycling_type":"container"}},"type":"Feature"},
	{"geometry":{"coordinates":[9.925247,49.453757],"type":"Point"},"properties":{"osm_id":"339169335","tag":{"amenity":"recycling","recycling:clothes":"yes","recycling:glass_bottles":"yes","recycling_type":"container"}},"type":"Feature"},
	{"geometry":{"coordinates":[9.904039,49.479081],"type":"Point"},"properties":{"osm_id":"340397260","tag":{"amenity":"recycling","recycling:clothes":"yes","recycling_type":"container"}},"type":"Feature"},
	{"geometry":{"coordinates":[9.855689,49.44196],"type":"Point"},"properties":{"osm_id":"356872867","tag":{"amenity":"recycling","recycling_type":"container"}},"type":"Feature"},
	{"geometry":{"coordinates":[9.908865,49.452001],"type":"Point"},"properties":{"osm_id":"2134080938","tag":{"amenity":"recycling","recycling:glass_bottles":"yes","recycling_type":"container"}},"type":"Feature"}
]
}
