{
"type": "FeatureCollection",
"features": [
	{"geometry":{"coordinates":[9.873155,49.470737],"type":"Point"},"properties":{"osm_id":"289652773","tag":{"amenity":"recycling","recycling:clothes":"yes","recycling:glass":"yes"}},"type":"Feature"},
	{"geometry":{"coordinates":[9.905267,49.479376],"type":"Point"},"properties":{"name":"Recyclinghof","osm_id":"290359581","tag":{"amenity":"recycling"}},"type":"Feature"},
	{"geometry":{"coordinates":[9.900535,49.477241],"type":"Point"},"properties":{"osm_id":"313959503","tag":{"amenity":"recycling","recycling:glass":"yes"}},"type":"Feature"},
	{"geometry":{"coordinates":[9.902848,49.480708],"type":"Point"},"properties":{"osm_id":"316242869","tag":{"amenity":"recycling","recycling:clothes":"yes"}},"type":"Feature"},
	{"geometry":{"coordinates":[9.925248,49.453757],"type":"Point"},"properties":{"osm_id":"339169335","tag":{"amenity":"recycling","recycling:clothes":"yes","recycling:glass":"yes"}},"type":"Feature"},
	{"geometry":{"coordinates":[9.90404,49.479082],"type":"Point"},"properties":{"osm_id":"340397260","tag":{"amenity":"recycling","recycling:clothes":"yes"}},"type":"Feature"},
	{"geometry":{"coordinates":[9.855589,49.442088],"type":"Point"},"properties":{"osm_id":"356872867","tag":{"amenity":"recycling"}},"type":"Feature"},
	{"geometry":{"coordinates":[9.908865,49.452002],"type":"Point"},"properties":{"osm_id":"2134080938","tag":{"amenity":"recycling","recycling:glass_bottles":"yes","recycling_type":"container"}},"type":"Feature"}
]
}
