{
"type": "FeatureCollection",
"lastupdate": "2020-08-06T00:00:00Z",
"features": [
	{"geometry":{"coordinates":[9.914344,49.400098],"type":"Point"},"properties":{"name":"Recyclinghof","osm_id":"361550899","tag":{"amenity":"recycling","recycling:batteries":"yes","recycling:books":"yes","recycling:cartons":"yes","recycling:clothes":"yes","recycling:electrical_appliances":"yes","recycling:glass":"yes","recycling:glass_bottles":"yes","recycling:green_waste":"yes","recycling:magazines":"yes","recycling:metal":"yes","recycling:newspaper":"yes","recycling:paper":"yes","recycling:paper_packaging":"yes","recycling:plastic":"yes","recycling:plastic_bottles":"yes","recycling:plastic_packaging":"yes","recycling:scrap_metal":"yes","recycling_type":"centre"}},"type":"Feature"},
	{"geometry":{"coordinates":[9.920848,49.424185],"type":"Point"},"properties":{"osm_id":"413589630","tag":{"amenity":"recycling","recycling:clothes":"yes"}},"type":"Feature"},
	{"geometry":{"coordinates":[9.920067,49.42273],"type":"Point"},"properties":{"osm_id":"413589714","tag":{"amenity":"recycling","recycling:clothes":"yes","recycling:glass":"yes"}},"type":"Feature"}
]
}
