{
"type": "FeatureCollection",
"lastupdate": "2020-08-01T00:00:00Z",
"features": [
	{"geometry":{"coordinates":[9.862583,49.253584],"type":"Point"},"properties":{"name":"langenburg2","osm_id":"1598877950","tag":{"amenity":"recycling"}},"type":"Feature"},
	{"geometry":{"coordinates":[9.919496,49.256024],"type":"Point"},"properties":{"osm_id":"1599191658","tag":{"amenity":"recycling","recycling:cans":"no","recycling:glass":"yes","recycling:glass_bottles":"yes","recycling:paper":"no","recycling:plastic":"no","recycling_type":"container"}},"type":"Feature"},
	{"geometry":{"coordinates":[9.852095,49.253178],"type":"Point"},"properties":{"osm_id":"1856871663","tag":{"amenity":"recycling","recycling:glass":"yes","recycling:glass_bottles":"yes","recycling_type":"container"}},"type":"Feature"}
]
}
