{
"type": "FeatureCollection",
"features": [
	{"geometry":{"coordinates":[9.92169,47.082575],"type":"Point"},"properties":{"osm_id":"984000703","tag":{"amenity":"recycling","recycling:batteries":"yes","recycling:cans":"yes","recycling:clothes":"yes","recycling:glass":"yes","recycling:paper":"yes","recycling:scrap_metal":"yes","recycling_type":"centre"}},"type":"Feature"},
	{"geometry":{"coordinates":[9.901035,47.079837],"type":"Point"},"properties":{"osm_id":"1424532457","tag":{"amenity":"waste_basket"}},"type":"Feature"},
	{"geometry":{"coordinates":[9.925735,47.068977],"type":"Point"},"properties":{"osm_id":"3562074436","tag":{"amenity":"waste_basket"}},"type":"Feature"},
	{"geometry":{"coordinates":[9.930297,47.069181],"type":"Point"},"properties":{"osm_id":"3562074439","tag":{"amenity":"waste_basket"}},"type":"Feature"},
	{"geometry":{"coordinates":[9.92237,47.071295],"type":"Point"},"properties":{"osm_id":"3562074440","tag":{"amenity":"waste_basket"}},"type":"Feature"},
	{"geometry":{"coordinates":[9.92063,47.07206],"type":"Point"},"properties":{"osm_id":"3562074442","tag":{"amenity":"waste_basket"}},"type":"Feature"},
	{"geometry":{"coordinates":[9.920059,47.072494],"type":"Point"},"properties":{"osm_id":"3562074443","tag":{"amenity":"waste_basket"}},"type":"Feature"},
	{"geometry":{"coordinates":[9.918567,47.073017],"type":"Point"},"properties":{"osm_id":"3562074446","tag":{"amenity":"waste_basket"}},"type":"Feature"},
	{"geometry":{"coordinates":[9.917096,47.073762],"type":"Point"},"properties":{"osm_id":"3562074451","tag":{"amenity":"waste_basket"}},"type":"Feature"},
	{"geometry":{"coordinates":[9.917756,47.07444],"type":"Point"},"properties":{"osm_id":"3562074455","tag":{"amenity":"waste_basket"}},"type":"Feature"},
	{"geometry":{"coordinates":[9.918362,47.075616],"type":"Point"},"properties":{"osm_id":"3562074458","tag":{"amenity":"waste_basket"}},"type":"Feature"},
	{"geometry":{"coordinates":[9.919333,47.076614],"type":"Point"},"properties":{"osm_id":"3562074460","tag":{"amenity":"waste_basket"}},"type":"Feature"},
	{"geometry":{"coordinates":[9.91995,47.077394],"type":"Point"},"properties":{"osm_id":"3562074462","tag":{"amenity":"waste_basket"}},"type":"Feature"},
	{"geometry":{"coordinates":[9.909343,47.074895],"type":"Point"},"properties":{"osm_id":"5601841623","tag":{"amenity":"waste_basket"}},"type":"Feature"},
	{"geometry":{"coordinates":[9.907832,47.075906],"type":"Point"},"properties":{"osm_id":"5601844721","tag":{"amenity":"waste_basket"}},"type":"Feature"},
	{"geometry":{"coordinates":[9.892433,47.072985],"type":"Point"},"properties":{"osm_id":"5902608546","tag":{"addr:city":"Tschagguns","addr:country":"AT","addr:housenumber":"2","addr:postcode":"6774","addr:street":"Feschasweg","amenity":"recycling","at_bev:addr_date":"2018-04-02","recycling_type":"centre"}},"type":"Feature"},
	{"geometry":{"coordinates":[9.852058,47.097021],"type":"Point"},"properties":{"osm_id":"7567116603","tag":{"amenity":"recycling","recycling_type":"centre"}},"type":"Feature"}
]
}
