{
"type": "FeatureCollection",
"lastupdate": "2020-07-31T00:00:00Z",
"features": [
	{"geometry":{"coordinates":[-87.986712,43.213202],"type":"Point"},"properties":{"name":"Waste Oil Collection","osm_id":"6783518197","tag":{"amenity":"waste_basket","operator":"City of Mequon"}},"type":"Feature"}
]
}
