{
"type": "FeatureCollection",
"features": [
	{"geometry":{"coordinates":[-87.992163,43.00785],"type":"Point"},"properties":{"osm_id":"676315956","tag":{"amenity":"recycling","recycling_type":"centre"}},"type":"Feature"},
	{"geometry":{"coordinates":[-87.980496,43.043945],"type":"Point"},"properties":{"name":"Cimco Recycling","osm_id":"9006958813","tag":{"amenity":"recycling","recycling_type":"centre"}},"type":"Feature"},
	{"geometry":{"coordinates":[-87.99437,43.040801],"type":"Point"},"properties":{"osm_id":"9007305749","tag":{"amenity":"waste_basket"}},"type":"Feature"},
	{"geometry":{"coordinates":[-88.037655,43.04266],"type":"Point"},"properties":{"osm_id":"9127313866","tag":{"amenity":"waste_basket","colour":"grey","covered":"yes","indoor":"no","material":"metal"}},"type":"Feature"}
]
}
