{
"type": "FeatureCollection",
"features": [
	{"geometry":{"coordinates":[12.125137,48.345131],"type":"Point"},"properties":{"osm_id":"2238462323","tag":{"amenity":"recycling","recycling:clothes":"yes","recycling_type":"container"}},"type":"Feature"},
	{"geometry":{"coordinates":[12.126169,48.345263],"type":"Point"},"properties":{"osm_id":"2238462324","tag":{"amenity":"recycling","opening_hours":"Mo-Sa 07:00-12:00,14:00-19:00; Su,PH off","recycling:cans":"yes","recycling:cardboard":"yes","recycling:glass_bottles":"yes","recycling:paper":"yes","recycling_type":"container","website":"https://www.landkreis-erding.de/abfallwirtschaft/rund-um-die-entsorgung/recyclinghoefe-containerplaetze/"}},"type":"Feature"},
	{"geometry":{"coordinates":[12.055836,48.362122],"type":"Point"},"properties":{"osm_id":"6919032861","tag":{"amenity":"waste_basket"}},"type":"Feature"},
	{"geometry":{"coordinates":[12.056396,48.362173],"type":"Point"},"properties":{"osm_id":"8521215656","tag":{"amenity":"waste_basket"}},"type":"Feature"},
	{"geometry":{"coordinates":[12.097586,48.377712],"type":"Point"},"properties":{"osm_id":"8777299482","tag":{"amenity":"recycling","opening_hours":"Mo-Sa 07:00-12:00,14:00-19:00; Su,PH off","recycling:cans":"yes","recycling:cardboard":"yes","recycling:glass_bottles":"yes","recycling:paper":"yes","recycling_type":"container","website":"https://www.landkreis-erding.de/abfallwirtschaft/rund-um-die-entsorgung/recyclinghoefe-containerplaetze/"}},"type":"Feature"},
	{"geometry":{"coordinates":[12.116265,48.350209],"type":"Point"},"properties":{"osm_id":"8777323017","tag":{"amenity":"recycling","opening_hours":"Mo-Sa 07:00-12:00,14:00-19:00; Su,PH off","recycling:cans":"yes","recycling:cardboard":"yes","recycling:clothes":"yes","recycling:glass_bottles":"yes","recycling:paper":"yes","recycling:shoes":"yes","recycling_type":"container","website":"https://www.landkreis-erding.de/abfallwirtschaft/rund-um-die-entsorgung/recyclinghoefe-containerplaetze/"}},"type":"Feature"},
	{"geometry":{"coordinates":[12.068048,48.346266],"type":"Point"},"properties":{"barrier":"gate","osm_id":"8777477217"},"type":"Feature"}
]
}
