{
"type": "FeatureCollection",
"features": [
	{"geometry":{"coordinates":[-87.040757,41.460862],"type":"Point"},"properties":{"osm_id":"3043825783","tag":{"natural":"tree"}},"type":"Feature"},
	{"geometry":{"coordinates":[-87.040799,41.460862],"type":"Point"},"properties":{"osm_id":"3043825784","tag":{"natural":"tree"}},"type":"Feature"},
	{"geometry":{"coordinates":[-87.040356,41.460885],"type":"Point"},"properties":{"osm_id":"3043825786","tag":{"natural":"tree"}},"type":"Feature"},
	{"geometry":{"coordinates":[-87.040731,41.460886],"type":"Point"},"properties":{"osm_id":"3043825787","tag":{"natural":"tree"}},"type":"Feature"},
	{"geometry":{"coordinates":[-87.039266,41.460931],"type":"Point"},"properties":{"osm_id":"3043825788","tag":{"natural":"tree"}},"type":"Feature"},
	{"geometry":{"coordinates":[-87.040165,41.461138],"type":"Point"},"properties":{"osm_id":"3043825808","tag":{"natural":"tree"}},"type":"Feature"},
	{"geometry":{"coordinates":[-87.040229,41.461148],"type":"Point"},"properties":{"osm_id":"3043825811","tag":{"natural":"tree"}},"type":"Feature"},
	{"geometry":{"coordinates":[-87.039577,41.461202],"type":"Point"},"properties":{"osm_id":"3043825813","tag":{"natural":"tree"}},"type":"Feature"},
	{"geometry":{"coordinates":[-87.040231,41.461206],"type":"Point"},"properties":{"osm_id":"3043825814","tag":{"natural":"tree"}},"type":"Feature"},
	{"geometry":{"coordinates":[-87.039473,41.461224],"type":"Point"},"properties":{"osm_id":"3043825816","tag":{"natural":"tree"}},"type":"Feature"},
	{"geometry":{"coordinates":[-87.040285,41.461224],"type":"Point"},"properties":{"osm_id":"3043825817","tag":{"natural":"tree"}},"type":"Feature"},
	{"geometry":{"coordinates":[-87.039525,41.461236],"type":"Point"},"properties":{"osm_id":"3043825819","tag":{"natural":"tree"}},"type":"Feature"},
	{"geometry":{"coordinates":[-87.03937,41.461252],"type":"Point"},"properties":{"osm_id":"3043825821","tag":{"natural":"tree"}},"type":"Feature"},
	{"geometry":{"coordinates":[-87.039434,41.461262],"type":"Point"},"properties":{"osm_id":"3043825823","tag":{"natural":"tree"}},"type":"Feature"},
	{"geometry":{"coordinates":[-87.039268,41.461263],"type":"Point"},"properties":{"osm_id":"3043825824","tag":{"natural":"tree"}},"type":"Feature"},
	{"geometry":{"coordinates":[-87.040273,41.461271],"type":"Point"},"properties":{"osm_id":"3043825826","tag":{"natural":"tree"}},"type":"Feature"},
	{"geometry":{"coordinates":[-87.03907,41.461282],"type":"Point"},"properties":{"osm_id":"3043825827","tag":{"natural":"tree"}},"type":"Feature"},
	{"geometry":{"coordinates":[-87.039319,41.461283],"type":"Point"},"properties":{"osm_id":"3043825828","tag":{"natural":"tree"}},"type":"Feature"},
	{"geometry":{"coordinates":[-87.039192,41.461287],"type":"Point"},"properties":{"osm_id":"3043825829","tag":{"natural":"tree"}},"type":"Feature"},
	{"geometry":{"coordinates":[-87.03913,41.461304],"type":"Point"},"properties":{"osm_id":"3043829233","tag":{"natural":"tree"}},"type":"Feature"},
	{"geometry":{"coordinates":[-87.040287,41.461324],"type":"Point"},"properties":{"osm_id":"3043829236","tag":{"natural":"tree"}},"type":"Feature"},
	{"geometry":{"coordinates":[-87.040339,41.461346],"type":"Point"},"properties":{"osm_id":"3043829237","tag":{"natural":"tree"}},"type":"Feature"},
	{"geometry":{"coordinates":[-87.040338,41.461393],"type":"Point"},"properties":{"osm_id":"3043829243","tag":{"natural":"tree"}},"type":"Feature"},
	{"geometry":{"coordinates":[-87.040567,41.461606],"type":"Point"},"properties":{"osm_id":"3043829274","tag":{"natural":"tree"}},"type":"Feature"},
	{"geometry":{"coordinates":[-87.040505,41.46161],"type":"Point"},"properties":{"osm_id":"3043829275","tag":{"natural":"tree"}},"type":"Feature"},
	{"geometry":{"coordinates":[-87.04058,41.461627],"type":"Point"},"properties":{"osm_id":"3043829276","tag":{"natural":"tree"}},"type":"Feature"},
	{"geometry":{"coordinates":[-87.040535,41.461637],"type":"Point"},"properties":{"osm_id":"3043829277","tag":{"natural":"tree"}},"type":"Feature"},
	{"geometry":{"coordinates":[-87.040597,41.461641],"type":"Point"},"properties":{"osm_id":"3043829279","tag":{"natural":"tree"}},"type":"Feature"},
	{"geometry":{"coordinates":[-87.041635,41.462504],"type":"Point"},"properties":{"name":"Merlin","osm_id":"6148209194","tag":{"denotation":"garden","leaf_cycle":"deciduous","leaf_type":"broadleaved","natural":"tree"}},"type":"Feature"}
]
}
