{
"type": "FeatureCollection",
"features": [
	{"geometry":{"coordinates":[24.698145,59.448477],"type":"Point"},"properties":{"osm_id":"2408410669","tag":{"amenity":"recycling"}},"type":"Feature"},
	{"geometry":{"coordinates":[24.716479,59.451527],"type":"Point"},"properties":{"osm_id":"4492280202","tag":{"amenity":"recycling"}},"type":"Feature"},
	{"geometry":{"coordinates":[24.717938,59.450959],"type":"Point"},"properties":{"name":"Taarapunkt","osm_id":"4515793840","tag":{"amenity":"recycling","recycling:cans":"yes","recycling:glass_bottles":"yes","recycling:plastic_bottles":"yes","recycling_type":"centre"}},"type":"Feature"},
	{"geometry":{"coordinates":[24.702418,59.446624],"type":"Point"},"properties":{"osm_id":"4556067986","tag":{"amenity":"recycling","recycling:cans":"yes","recycling:cardboard":"yes","recycling:glass":"yes","recycling:glass_bottles":"yes","recycling:paper":"yes","recycling:plastic":"yes","recycling:plastic_bottles":"yes","recycling:plastic_packaging":"yes","recycling_type":"container"}},"type":"Feature"},
	{"geometry":{"coordinates":[24.698445,59.447489],"type":"Point"},"properties":{"osm_id":"7131814215","tag":{"amenity":"recycling","recycling:cans":"yes","recycling:glass":"yes","recycling:glass_bottles":"yes","recycling:plastic":"yes","recycling:plastic_bottles":"yes","recycling_type":"container"}},"type":"Feature"},
	{"geometry":{"coordinates":[24.735608,59.447206],"type":"Point"},"properties":{"osm_id":"7231368255","tag":{"amenity":"recycling","opening_hours":"24/7","recycling:glass":"yes","recycling:glass_bottles":"yes","recycling_type":"container"}},"type":"Feature"},
	{"geometry":{"coordinates":[24.733252,59.44586],"type":"Point"},"properties":{"osm_id":"7231368256","tag":{"amenity":"recycling","opening_hours":"24/7","recycling:glass":"yes","recycling:glass_bottles":"yes","recycling_type":"container"}},"type":"Feature"},
	{"geometry":{"coordinates":[24.735125,59.447664],"type":"Point"},"properties":{"osm_id":"7237531848","tag":{"amenity":"waste_disposal"}},"type":"Feature"},
	{"geometry":{"coordinates":[24.735553,59.450282],"type":"Point"},"properties":{"osm_id":"7565999585","tag":{"amenity":"waste_basket"}},"type":"Feature"},
	{"geometry":{"coordinates":[24.73916,59.452832],"type":"Point"},"properties":{"osm_id":"7899403574","tag":{"amenity":"waste_disposal"}},"type":"Feature"},
	{"geometry":{"coordinates":[24.721807,59.472967],"type":"Point"},"properties":{"osm_id":"7952296829","tag":{"amenity":"recycling","recycling:cans":"yes","recycling:cardboard":"yes","recycling:cartons":"yes","recycling:glass":"yes","recycling:glass_bottles":"yes","recycling:newspaper":"yes","recycling:paper":"yes","recycling:paper_packaging":"yes","recycling:plastic":"yes","recycling:plastic_bottles":"yes","recycling:plastic_packaging":"yes","recycling_type":"container"}},"type":"Feature"},
	{"geometry":{"coordinates":[24.706636,59.448528],"type":"Point"},"properties":{"osm_id":"8004206484","tag":{"amenity":"waste_disposal"}},"type":"Feature"}
]
}
