{
"type": "FeatureCollection",
"lastupdate": "2020-08-03T00:00:00Z",
"features": [
	{"geometry":{"coordinates":[24.782581,58.58688],"type":"Point"},"properties":{"name":"Vanade rehvide kogumispunkt","osm_id":"1849565238","tag":{"amenity":"recycling","recycling_type":"centre"}},"type":"Feature"}
]
}
