{
"type": "FeatureCollection",
"features": [
	{"geometry":{"coordinates":[24.784144,58.586448],"type":"Point"},"properties":{"osm_id":"1838446911","tag":{"amenity":"waste_disposal"}},"type":"Feature"},
	{"geometry":{"coordinates":[24.782009,58.58551],"type":"Point"},"properties":{"osm_id":"1838821665","tag":{"amenity":"waste_disposal"}},"type":"Feature"},
	{"geometry":{"coordinates":[24.781986,58.586373],"type":"Point"},"properties":{"osm_id":"1838821754","tag":{"amenity":"waste_disposal"}},"type":"Feature"},
	{"geometry":{"coordinates":[24.782098,58.58689],"type":"Point"},"properties":{"osm_id":"1838821770","tag":{"amenity":"waste_disposal"}},"type":"Feature"},
	{"geometry":{"coordinates":[24.784714,58.587036],"type":"Point"},"properties":{"osm_id":"1838821777","tag":{"amenity":"waste_disposal"}},"type":"Feature"},
	{"geometry":{"coordinates":[24.783407,58.588139],"type":"Point"},"properties":{"osm_id":"1838830841","tag":{"amenity":"waste_disposal"}},"type":"Feature"},
	{"geometry":{"coordinates":[24.782581,58.58688],"type":"Point"},"properties":{"name":"Vanade rehvide kogumispunkt","osm_id":"1849565238","tag":{"amenity":"recycling","recycling_type":"centre"}},"type":"Feature"}
]
}
