{
"type": "FeatureCollection",
"features": [
	{"geometry":{"coordinates":[-59.608906,-26.805313],"type":"Point"},"properties":{"name":"Quebracho Colorado (Schinopsis balansae)","osm_id":"4195906807","tag":{"natural":"tree"}},"type":"Feature"},
	{"geometry":{"coordinates":[-59.625336,-26.802236],"type":"Point"},"properties":{"osm_id":"4956808676","tag":{"natural":"tree"}},"type":"Feature"}
]
}
