{
"type": "FeatureCollection",
"lastupdate": "2020-08-03T00:00:00Z",
"features": [
	{"geometry":{"coordinates":[19.367252,69.23498],"type":"Point"},"properties":{"name":"Metallmottak Balsfjord","osm_id":"5555201502","tag":{"amenity":"recycling","recycling:boats":"yes","recycling:cars":"yes","recycling:metal":"yes","recycling:scrap_metal":"yes","recycling_type":"centre","ref:sortere":"5360","website":"http://senja-avfall.no"}},"type":"Feature"}
]
}
