{
"type": "FeatureCollection",
"features": [
	{"geometry":{"coordinates":[6.235261,51.797741],"type":"Point"},"properties":{"name":"Friedenslinde","osm_id":"605012000","place":"locality","tag":{"amenity":"bench","natural":"tree"}},"type":"Feature"},
	{"geometry":{"coordinates":[6.156912,51.795668],"type":"Point"},"properties":{"osm_id":"3959259657","tag":{"leaf_type":"broadleaved","natural":"tree"}},"type":"Feature"},
	{"geometry":{"coordinates":[6.157303,51.795885],"type":"Point"},"properties":{"osm_id":"3959259667","tag":{"leaf_type":"broadleaved","natural":"tree"}},"type":"Feature"},
	{"geometry":{"coordinates":[6.157807,51.795954],"type":"Point"},"properties":{"osm_id":"3959259669","tag":{"leaf_type":"broadleaved","natural":"tree"}},"type":"Feature"},
	{"geometry":{"coordinates":[6.157464,51.796142],"type":"Point"},"properties":{"osm_id":"3959259671","tag":{"leaf_type":"broadleaved","natural":"tree"}},"type":"Feature"},
	{"geometry":{"coordinates":[6.240155,51.818472],"type":"Point"},"properties":{"osm_id":"7829217168","tag":{"natural":"tree"}},"type":"Feature"}
]
}
