{
"type": "FeatureCollection",
"features": [
	{"geometry":{"coordinates":[6.235261,51.797741],"type":"Point"},"properties":{"name":"Friedenslinde","osm_id":"605012000","place":"locality","tag":{"amenity":"bench","natural":"tree"}},"type":"Feature"},
	{"geometry":{"coordinates":[6.156912,51.795668],"type":"Point"},"properties":{"osm_id":"3959259657","tag":{"leaf_type":"broadleaved","natural":"tree"}},"type":"Feature"},
	{"geometry":{"coordinates":[6.157303,51.795885],"type":"Point"},"properties":{"osm_id":"3959259667","tag":{"leaf_type":"broadleaved","natural":"tree"}},"type":"Feature"},
	{"geometry":{"coordinates":[6.157807,51.795954],"type":"Point"},"properties":{"osm_id":"3959259669","tag":{"leaf_type":"broadleaved","natural":"tree"}},"type":"Feature"},
	{"geometry":{"coordinates":[6.157464,51.796142],"type":"Point"},"properties":{"osm_id":"3959259671","tag":{"leaf_type":"broadleaved","natural":"tree"}},"type":"Feature"},
	{"geometry":{"coordinates":[6.240155,51.818472],"type":"Point"},"properties":{"osm_id":"7829217168","tag":{"natural":"tree"}},"type":"Feature"},
	{"geometry":{"coordinates":[6.160882,51.803728],"type":"Point"},"properties":{"osm_id":"9051866874","tag":{"natural":"tree"}},"type":"Feature"},
	{"geometry":{"coordinates":[6.161003,51.803722],"type":"Point"},"properties":{"osm_id":"9051866875","tag":{"natural":"tree"}},"type":"Feature"},
	{"geometry":{"coordinates":[6.161026,51.803871],"type":"Point"},"properties":{"osm_id":"9051866876","tag":{"natural":"tree"}},"type":"Feature"},
	{"geometry":{"coordinates":[6.160905,51.803886],"type":"Point"},"properties":{"osm_id":"9051866877","tag":{"natural":"tree"}},"type":"Feature"},
	{"geometry":{"coordinates":[6.160647,51.803548],"type":"Point"},"properties":{"osm_id":"9051874338","tag":{"natural":"tree"}},"type":"Feature"},
	{"geometry":{"coordinates":[6.160641,51.803473],"type":"Point"},"properties":{"osm_id":"9051874339","tag":{"natural":"tree"}},"type":"Feature"}
]
}
