{
"type": "FeatureCollection",
"features": [
	{"geometry":{"coordinates":[6.235261,51.797741],"type":"Point"},"properties":{"name":"Friedenslinde","osm_id":"605012000","place":"locality","tag":{"amenity":"bench","natural":"tree"}},"type":"Feature"},
	{"geometry":{"coordinates":[6.156912,51.795669],"type":"Point"},"properties":{"osm_id":"3959259657","tag":{"leaf_type":"broadleaved","natural":"tree"}},"type":"Feature"},
	{"geometry":{"coordinates":[6.157304,51.795885],"type":"Point"},"properties":{"osm_id":"3959259667","tag":{"leaf_type":"broadleaved","natural":"tree"}},"type":"Feature"},
	{"geometry":{"coordinates":[6.157808,51.795955],"type":"Point"},"properties":{"osm_id":"3959259669","tag":{"leaf_type":"broadleaved","natural":"tree"}},"type":"Feature"},
	{"geometry":{"coordinates":[6.157465,51.796143],"type":"Point"},"properties":{"osm_id":"3959259671","tag":{"leaf_type":"broadleaved","natural":"tree"}},"type":"Feature"},
	{"geometry":{"coordinates":[6.240155,51.818472],"type":"Point"},"properties":{"osm_id":"7829217168","tag":{"natural":"tree"}},"type":"Feature"}
]
}
