{
"type": "FeatureCollection",
"lastupdate": "2020-08-02T00:00:00Z",
"features": [
	{"geometry":{"coordinates":[6.019625,51.952147],"type":"Point"},"properties":{"name":"Afvalaanbiedstation Duiven","osm_id":"1824781521","tag":{"amenity":"recycling","recycling_type":"container"}},"type":"Feature"},
	{"geometry":{"coordinates":[5.984634,51.949098],"type":"Point"},"properties":{"osm_id":"2909096194","tag":{"amenity":"waste_basket"}},"type":"Feature"},
	{"geometry":{"coordinates":[5.989653,51.949298],"type":"Point"},"properties":{"osm_id":"2909096200","tag":{"amenity":"waste_basket"}},"type":"Feature"},
	{"geometry":{"coordinates":[5.976735,51.954209],"type":"Point"},"properties":{"osm_id":"2914691757","tag":{"amenity":"waste_basket"}},"type":"Feature"},
	{"geometry":{"coordinates":[5.977397,51.961012],"type":"Point"},"properties":{"osm_id":"2916225779","tag":{"amenity":"waste_basket"}},"type":"Feature"},
	{"geometry":{"coordinates":[5.984845,51.947581],"type":"Point"},"properties":{"osm_id":"2916230845","tag":{"amenity":"waste_basket"}},"type":"Feature"},
	{"geometry":{"coordinates":[5.985005,51.947904],"type":"Point"},"properties":{"osm_id":"2916230846","tag":{"amenity":"waste_basket"}},"type":"Feature"},
	{"geometry":{"coordinates":[5.978135,51.956613],"type":"Point"},"properties":{"osm_id":"3149317108","tag":{"amenity":"waste_basket"}},"type":"Feature"},
	{"geometry":{"coordinates":[5.978777,51.954701],"type":"Point"},"properties":{"osm_id":"3286082114","tag":{"amenity":"waste_basket"}},"type":"Feature"},
	{"geometry":{"coordinates":[5.996412,51.966853],"type":"Point"},"properties":{"osm_id":"3430839544","tag":{"amenity":"recycling","recycling:clothes":"yes","recycling_type":"container"}},"type":"Feature"},
	{"geometry":{"coordinates":[5.991191,51.987978],"type":"Point"},"properties":{"osm_id":"3605223208","tag":{"amenity":"waste_basket"}},"type":"Feature"},
	{"geometry":{"coordinates":[5.981734,51.945063],"type":"Point"},"properties":{"osm_id":"3928851706","tag":{"amenity":"waste_basket"}},"type":"Feature"},
	{"geometry":{"coordinates":[5.979964,51.987632],"type":"Point"},"properties":{"osm_id":"4536478290","tag":{"amenity":"waste_basket"}},"type":"Feature"},
	{"geometry":{"coordinates":[5.980686,51.994974],"type":"Point"},"properties":{"osm_id":"4536519492","tag":{"amenity":"waste_basket"}},"type":"Feature"},
	{"geometry":{"coordinates":[5.981083,51.995159],"type":"Point"},"properties":{"osm_id":"5588963586","tag":{"amenity":"waste_basket"}},"type":"Feature"},
	{"geometry":{"coordinates":[6.021222,51.948018],"type":"Point"},"properties":{"osm_id":"6483572871","tag":{"amenity":"recycling","recycling:glass":"yes","recycling_type":"container"}},"type":"Feature"},
	{"geometry":{"coordinates":[6.024292,51.948187],"type":"Point"},"properties":{"osm_id":"6483572872","tag":{"amenity":"recycling","recycling:glass":"yes","recycling_type":"container"}},"type":"Feature"}
]
}
