{
"type": "FeatureCollection",
"features": [
	{"geometry":{"coordinates":[5.993591,44.18658],"type":"Point"},"properties":{"name":"PAV mairie","osm_id":"1979938375","tag":{"amenity":"recycling","recycling:glass":"yes","recycling:paper":"yes","recycling:scrap_metal":"yes"}},"type":"Feature"},
	{"geometry":{"coordinates":[5.984887,44.157669],"type":"Point"},"properties":{"osm_id":"6928681666","tag":{"amenity":"recycling","opening_hours":"24/7","recycling:PET":"yes","recycling:cans":"yes","recycling:plastic_bottles":"yes","recycling:plastic_packaging":"yes","recycling_type":"container"}},"type":"Feature"},
	{"geometry":{"coordinates":[5.976979,44.179123],"type":"Point"},"properties":{"name":"PAV collette","osm_id":"8403663745","tag":{"amenity":"recycling","operator":"CCSB","recycling_type":"container"}},"type":"Feature"},
	{"geometry":{"coordinates":[5.984968,44.157677],"type":"Point"},"properties":{"osm_id":"8453425889","tag":{"amenity":"recycling","opening_hours":"24/7","recycling:glass_bottles":"yes","recycling_type":"container"}},"type":"Feature"},
	{"geometry":{"coordinates":[5.984928,44.157673],"type":"Point"},"properties":{"osm_id":"8453426191","tag":{"amenity":"recycling","opening_hours":"24/7","recycling:clothes":"yes","recycling_type":"container"}},"type":"Feature"}
]
}
