{
"type": "FeatureCollection",
"features": [
	{"geometry":{"coordinates":[15.112332,41.507315],"type":"Point"},"properties":{"name":"Quercia di San Luca","osm_id":"563897741","tag":{"genus":"Quercus","genus:en":"Oak","historic":"yes","leaf_cycle":"deciduous","leaf_type":"broadleaved","natural":"tree"}},"type":"Feature"}
]
}
