{
"type": "FeatureCollection",
"features": [
	{"geometry":{"coordinates":[-83.464042,42.484473],"type":"Point"},"properties":{"name":"Novi D.P.W.","osm_id":"538774795","tag":{"amenity":"recycling"}},"type":"Feature"},
	{"geometry":{"coordinates":[-83.475436,42.482207],"type":"Point"},"properties":{"osm_id":"4516227287","tag":{"amenity":"waste_basket"}},"type":"Feature"}
]
}
