{
"type": "FeatureCollection",
"features": [
	{"geometry":{"coordinates":[-47.097955,-23.436786],"type":"Point"},"properties":{"osm_id":"3600466478","tag":{"natural":"tree"}},"type":"Feature"},
	{"geometry":{"coordinates":[-47.099033,-23.437057],"type":"Point"},"properties":{"osm_id":"3600466479","tag":{"natural":"tree"}},"type":"Feature"},
	{"geometry":{"coordinates":[-47.099876,-23.437298],"type":"Point"},"properties":{"osm_id":"3600466480","tag":{"natural":"tree"}},"type":"Feature"},
	{"geometry":{"coordinates":[-47.105833,-23.424066],"type":"Point"},"properties":{"name":"Coqueiro","osm_id":"3726499565","tag":{"natural":"tree"}},"type":"Feature"}
]
}
