{
"type": "FeatureCollection",
"lastupdate": "2020-07-31T00:00:00Z",
"features": [
	{"geometry":{"coordinates":[35.443072,38.733547],"type":"Point"},"properties":{"osm_id":"2306645979","tag":{"addr:street":"Mustafa Kemal Pa\u015fa Bulvar\u0131","amenity":"waste_basket"}},"type":"Feature"}
]
}
