{
"type": "FeatureCollection",
"features": [
	{"geometry":{"coordinates":[35.501892,33.877952],"type":"Point"},"properties":{"osm_id":"359935684","tag":{"amenity":"recycling"}},"type":"Feature"},
	{"geometry":{"coordinates":[35.492775,33.899737],"type":"Point"},"properties":{"osm_id":"7830564585","tag":{"amenity":"recycling","recycling:clothes":"yes","recycling_type":"container"}},"type":"Feature"},
	{"geometry":{"coordinates":[35.483854,33.896397],"type":"Point"},"properties":{"osm_id":"7948176687","tag":{"amenity":"recycling","name:en":"Recycling glass and plastic","recycling_type":"container"}},"type":"Feature"},
	{"geometry":{"coordinates":[35.481515,33.898597],"type":"Point"},"properties":{"osm_id":"7948176985","tag":{"amenity":"recycling","name:en":"Organic Waste Recycling","recycling_type":"container"}},"type":"Feature"}
]
}
