{
"type": "FeatureCollection",
"features": [
	{"geometry":{"coordinates":[7.445067,46.45715],"type":"Point"},"properties":{"osm_id":"323135750","tag":{"amenity":"recycling","location":"overground","recycling_type":"container"}},"type":"Feature"},
	{"geometry":{"coordinates":[7.442464,46.456181],"type":"Point"},"properties":{"osm_id":"449557788","tag":{"amenity":"recycling","recycling:pet":"yes"}},"type":"Feature"},
	{"geometry":{"coordinates":[7.42117,46.494186],"type":"Point"},"properties":{"osm_id":"555012367","tag":{"amenity":"recycling"}},"type":"Feature"},
	{"geometry":{"coordinates":[7.444189,46.457991],"type":"Point"},"properties":{"osm_id":"7127800607","tag":{"amenity":"recycling","recycling:clothes":"yes","recycling_type":"container"}},"type":"Feature"},
	{"geometry":{"coordinates":[7.442981,46.45568],"type":"Point"},"properties":{"name":"Glassammelstelle","osm_id":"7197046048","tag":{"amenity":"recycling"}},"type":"Feature"},
	{"geometry":{"coordinates":[7.444235,46.454397],"type":"Point"},"properties":{"name":"Robidog","osm_id":"7985344864","tag":{"amenity":"waste_disposal"}},"type":"Feature"}
]
}
