{
"type": "FeatureCollection",
"features": [
	{"geometry":{"coordinates":[12.739849,42.577003],"type":"Point"},"properties":{"name":"Roverella di Arrone","osm_id":"6020555616","tag":{"addr:city":"Arrone","denotation":"natural_monument","genus":"Quercus pubescens Willd.","leaf_cycle":"deciduous","leaf_type":"broadleaved","natural":"tree"}},"type":"Feature"}
]
}
