{
"type": "FeatureCollection",
"features": [
	{"geometry":{"coordinates":[79.900565,7.139656],"type":"Point"},"properties":{"name":"Raddolugama Bodiya","osm_id":"4242403431","tag":{"amenity":"place_of_worship","natural":"tree","religion":"buddhist"}},"type":"Feature"},
	{"geometry":{"coordinates":[79.911532,7.127805],"type":"Point"},"properties":{"name":"Bo Tree","osm_id":"4255617993","tag":{"natural":"tree"}},"type":"Feature"}
]
}
