{
"type": "FeatureCollection",
"features": [
	{"geometry":{"coordinates":[-4.741482,51.800894],"type":"Point"},"properties":{"osm_id":"2571604206","tag":{"natural":"tree","type":"Ash"}},"type":"Feature"},
	{"geometry":{"coordinates":[-4.743317,51.798049],"type":"Point"},"properties":{"osm_id":"2573282982","tag":{"natural":"tree","type":"broad_leaved"}},"type":"Feature"},
	{"geometry":{"coordinates":[-4.743315,51.798099],"type":"Point"},"properties":{"osm_id":"2573282985","tag":{"natural":"tree","type":"broad_leaved"}},"type":"Feature"},
	{"geometry":{"coordinates":[-4.745458,51.796706],"type":"Point"},"properties":{"osm_id":"2579383016","tag":{"leaf_type":"broadleaved","natural":"tree"}},"type":"Feature"},
	{"geometry":{"coordinates":[-4.743243,51.797113],"type":"Point"},"properties":{"osm_id":"3043413259","tag":{"natural":"tree"}},"type":"Feature"},
	{"geometry":{"coordinates":[-4.743237,51.797156],"type":"Point"},"properties":{"osm_id":"3043413260","tag":{"natural":"tree"}},"type":"Feature"},
	{"geometry":{"coordinates":[-4.743221,51.797193],"type":"Point"},"properties":{"osm_id":"3043413261","tag":{"natural":"tree"}},"type":"Feature"},
	{"geometry":{"coordinates":[-4.74427,51.796432],"type":"Point"},"properties":{"osm_id":"4922274623","tag":{"genus":"Horse Chestnut","leaf_cycle":"deciduous","leaf_type":"broadleaved","natural":"tree"}},"type":"Feature"},
	{"geometry":{"coordinates":[-4.737457,51.801302],"type":"Point"},"properties":{"name":"Apple","osm_id":"6050674480","tag":{"denotation":"urban","leaf_cycle":"deciduous","leaf_type":"broadleaved","natural":"tree"}},"type":"Feature"}
]
}
