{
"type": "FeatureCollection",
"features": [
	{"geometry":{"coordinates":[-4.741482,51.800893],"type":"Point"},"properties":{"osm_id":"2571604206","tag":{"natural":"tree","type":"Ash"}},"type":"Feature"},
	{"geometry":{"coordinates":[-4.743316,51.798049],"type":"Point"},"properties":{"osm_id":"2573282982","tag":{"leaf_type":"broadleaved","natural":"tree"}},"type":"Feature"},
	{"geometry":{"coordinates":[-4.743315,51.798099],"type":"Point"},"properties":{"osm_id":"2573282985","tag":{"leaf_type":"broadleaved","natural":"tree"}},"type":"Feature"},
	{"geometry":{"coordinates":[-4.745458,51.796705],"type":"Point"},"properties":{"osm_id":"2579383016","tag":{"leaf_type":"broadleaved","natural":"tree"}},"type":"Feature"},
	{"geometry":{"coordinates":[-4.743242,51.797113],"type":"Point"},"properties":{"osm_id":"3043413259","tag":{"natural":"tree"}},"type":"Feature"},
	{"geometry":{"coordinates":[-4.743236,51.797155],"type":"Point"},"properties":{"osm_id":"3043413260","tag":{"natural":"tree"}},"type":"Feature"},
	{"geometry":{"coordinates":[-4.743221,51.797193],"type":"Point"},"properties":{"osm_id":"3043413261","tag":{"natural":"tree"}},"type":"Feature"},
	{"geometry":{"coordinates":[-4.744269,51.796432],"type":"Point"},"properties":{"osm_id":"4922274623","tag":{"genus":"Horse Chestnut","leaf_cycle":"deciduous","leaf_type":"broadleaved","natural":"tree"}},"type":"Feature"},
	{"geometry":{"coordinates":[-4.737457,51.801301],"type":"Point"},"properties":{"name":"Apple","osm_id":"6050674480","tag":{"denotation":"urban","leaf_cycle":"deciduous","leaf_type":"broadleaved","natural":"tree"}},"type":"Feature"},
	{"geometry":{"coordinates":[-4.738999,51.799787],"type":"Point"},"properties":{"osm_id":"8380567357","tag":{"natural":"tree"}},"type":"Feature"}
]
}
