{
"type": "FeatureCollection",
"features": [
	{"geometry":{"coordinates":[-86.864675,33.103416],"type":"Point"},"properties":{"osm_id":"459784533","tag":{"height":"30","name:botanical":"Ginkgo biloba","natural":"tree","type":"Ginkgo biloba"}},"type":"Feature"}
]
}
