{
"type": "FeatureCollection",
"features": [
	{"geometry":{"coordinates":[-46.75986,-23.663739],"type":"Point"},"properties":{"osm_id":"5506996805","tag":{"amenity":"waste_disposal"}},"type":"Feature"},
	{"geometry":{"coordinates":[-46.761335,-23.665003],"type":"Point"},"properties":{"name":"\"Congo\"","osm_id":"5507123251","tag":{"amenity":"waste_disposal"}},"type":"Feature"},
	{"geometry":{"coordinates":[-46.785143,-23.659779],"type":"Point"},"properties":{"name":"Waste","osm_id":"5507123280","tag":{"amenity":"waste_disposal"}},"type":"Feature"},
	{"geometry":{"coordinates":[-46.779071,-23.655344],"type":"Point"},"properties":{"osm_id":"5509143234","tag":{"amenity":"waste_basket"}},"type":"Feature"},
	{"geometry":{"coordinates":[-46.786388,-23.658555],"type":"Point"},"properties":{"osm_id":"5512243525","tag":{"amenity":"waste_disposal"}},"type":"Feature"}
]
}
