{
"type": "FeatureCollection",
"features": [
	{"geometry":{"coordinates":[124.851998,8.275982],"type":"Point"},"properties":{"name":"Tree of Life","osm_id":"6806947948","tag":{"leaf_type":"broadleaved","natural":"tree"}},"type":"Feature"}
]
}
