{
"type": "FeatureCollection",
"features": [
	{"geometry":{"coordinates":[8.107409,48.671069],"type":"Point"},"properties":{"osm_id":"392718072","tag":{"height":"5","natural":"tree"}},"type":"Feature"},
	{"geometry":{"coordinates":[8.107539,48.67107],"type":"Point"},"properties":{"osm_id":"392718073","tag":{"height":"5","natural":"tree"}},"type":"Feature"},
	{"geometry":{"coordinates":[8.114479,48.68288],"type":"Point"},"properties":{"osm_id":"561529380","tag":{"natural":"tree"}},"type":"Feature"},
	{"geometry":{"coordinates":[8.158983,48.671789],"type":"Point"},"properties":{"name":"Friedenseiche (1871)","osm_id":"984546458","tag":{"genus":"Quercus","genus:de":"Eiche","genus:wikidata":"Q12004","leaf_cycle":"deciduous","leaf_type":"broadleaved","natural":"tree"}},"type":"Feature"},
	{"geometry":{"coordinates":[8.137675,48.649811],"type":"Point"},"properties":{"osm_id":"1997042000","tag":{"natural":"tree"}},"type":"Feature"},
	{"geometry":{"coordinates":[8.091437,48.655992],"type":"Point"},"properties":{"osm_id":"2968612122","tag":{"natural":"tree"}},"type":"Feature"},
	{"geometry":{"coordinates":[8.106309,48.670586],"type":"Point"},"properties":{"osm_id":"3014371545","tag":{"natural":"tree"}},"type":"Feature"},
	{"geometry":{"coordinates":[8.133493,48.685788],"type":"Point"},"properties":{"osm_id":"3254970788","tag":{"leaf_type":"broadleaved","natural":"tree"}},"type":"Feature"},
	{"geometry":{"coordinates":[8.134284,48.686104],"type":"Point"},"properties":{"osm_id":"3277255121","tag":{"leaf_type":"broadleaved","natural":"tree"}},"type":"Feature"},
	{"geometry":{"coordinates":[8.137331,48.685477],"type":"Point"},"properties":{"osm_id":"3277256482","tag":{"leaf_type":"broadleaved","natural":"tree"}},"type":"Feature"},
	{"geometry":{"coordinates":[8.13203,48.685415],"type":"Point"},"properties":{"osm_id":"3277259151","tag":{"leaf_type":"broadleaved","natural":"tree"}},"type":"Feature"},
	{"geometry":{"coordinates":[8.117531,48.688419],"type":"Point"},"properties":{"osm_id":"3388136609","tag":{"natural":"tree"}},"type":"Feature"},
	{"geometry":{"coordinates":[8.117767,48.688544],"type":"Point"},"properties":{"osm_id":"3388136610","tag":{"natural":"tree"}},"type":"Feature"},
	{"geometry":{"coordinates":[8.119793,48.672407],"type":"Point"},"properties":{"name":"Gespaltene Linde","osm_id":"5240925523","tag":{"genus":"Tilia","genus:de":"Linde","genus:wikidata":"Q127849","leaf_cycle":"deciduous","leaf_type":"broadleaved","natural":"tree"}},"type":"Feature"}
]
}
