{
"type": "FeatureCollection",
"features": [
	{"geometry":{"coordinates":[8.107409,48.671069],"type":"Point"},"properties":{"osm_id":"392718072","tag":{"height":"5","natural":"tree"}},"type":"Feature"},
	{"geometry":{"coordinates":[8.107539,48.671071],"type":"Point"},"properties":{"osm_id":"392718073","tag":{"height":"5","natural":"tree"}},"type":"Feature"},
	{"geometry":{"coordinates":[8.11448,48.682881],"type":"Point"},"properties":{"osm_id":"561529380","tag":{"natural":"tree"}},"type":"Feature"},
	{"geometry":{"coordinates":[8.158983,48.671789],"type":"Point"},"properties":{"name":"Friedenseiche (1871)","osm_id":"984546458","tag":{"natural":"tree"}},"type":"Feature"},
	{"geometry":{"coordinates":[8.137676,48.649812],"type":"Point"},"properties":{"osm_id":"1997042000","tag":{"natural":"tree"}},"type":"Feature"},
	{"geometry":{"coordinates":[8.091437,48.655993],"type":"Point"},"properties":{"osm_id":"2968612122","tag":{"natural":"tree"}},"type":"Feature"},
	{"geometry":{"coordinates":[8.106309,48.670587],"type":"Point"},"properties":{"osm_id":"3014371545","tag":{"natural":"tree"}},"type":"Feature"},
	{"geometry":{"coordinates":[8.133493,48.685789],"type":"Point"},"properties":{"osm_id":"3254970788","tag":{"leaf_type":"broadleaved","natural":"tree"}},"type":"Feature"},
	{"geometry":{"coordinates":[8.134285,48.686104],"type":"Point"},"properties":{"osm_id":"3277255121","tag":{"leaf_type":"broadleaved","natural":"tree"}},"type":"Feature"},
	{"geometry":{"coordinates":[8.137332,48.685477],"type":"Point"},"properties":{"osm_id":"3277256482","tag":{"leaf_type":"broadleaved","natural":"tree"}},"type":"Feature"},
	{"geometry":{"coordinates":[8.132031,48.685416],"type":"Point"},"properties":{"osm_id":"3277259151","tag":{"leaf_type":"broadleaved","natural":"tree"}},"type":"Feature"},
	{"geometry":{"coordinates":[8.117531,48.68842],"type":"Point"},"properties":{"osm_id":"3388136609","tag":{"natural":"tree"}},"type":"Feature"},
	{"geometry":{"coordinates":[8.117767,48.688544],"type":"Point"},"properties":{"osm_id":"3388136610","tag":{"natural":"tree"}},"type":"Feature"},
	{"geometry":{"coordinates":[8.119794,48.672408],"type":"Point"},"properties":{"name":"Gespaltene Linde","osm_id":"5240925523","tag":{"natural":"tree"}},"type":"Feature"}
]
}
