{
"type": "FeatureCollection",
"lastupdate": "2020-08-03T00:00:00Z",
"features": [
	{"geometry":{"coordinates":[14.711844,63.157088],"type":"Point"},"properties":{"osm_id":"504664549","tag":{"amenity":"recycling","opening_hours":"24/7","recycling:clothes":"yes","recycling:glass":"yes","recycling:newspaper":"yes","recycling:paper_packaging":"yes","recycling:plastic_packaging":"yes","recycling_type":"container"}},"type":"Feature"},
	{"geometry":{"coordinates":[14.68169,63.155649],"type":"Point"},"properties":{"osm_id":"510820407","tag":{"amenity":"recycling","recycling:cans":"yes","recycling:glass":"yes","recycling:paper":"yes","recycling:scrap_metal":"yes","recycling_type":"container"}},"type":"Feature"},
	{"geometry":{"coordinates":[14.681645,63.166753],"type":"Point"},"properties":{"osm_id":"531968296","tag":{"amenity":"recycling","recycling_type":"container"}},"type":"Feature"},
	{"geometry":{"coordinates":[14.751791,63.158622],"type":"Point"},"properties":{"name":"Torvalla Vattentornet","osm_id":"1393644537","tag":{"amenity":"recycling","recycling:glass":"yes","recycling:newspaper":"yes","recycling:paper":"yes","recycling:plastic":"yes","recycling:scrap_metal":"yes","recycling_type":"container"}},"type":"Feature"},
	{"geometry":{"coordinates":[14.683301,63.169119],"type":"Point"},"properties":{"osm_id":"6863971259","tag":{"amenity":"waste_basket"}},"type":"Feature"}
]
}
