{
"type": "FeatureCollection",
"features": [
	{"geometry":{"coordinates":[14.734344,36.923578],"type":"Point"},"properties":{"name":"Ecostazione di Ibla","osm_id":"4441388579","tag":{"amenity":"recycling"}},"type":"Feature"},
	{"geometry":{"coordinates":[14.724308,36.923254],"type":"Point"},"properties":{"osm_id":"5162640442","tag":{"amenity":"recycling","recycling:glass_bottles":"yes","recycling:paper":"yes","recycling:plastic_bottles":"yes","recycling:plastic_packaging":"yes","recycling_type":"container"}},"type":"Feature"}
]
}
