{
"type": "FeatureCollection",
"features": [
	{"geometry":{"coordinates":[-7.784666,52.956194],"type":"Point"},"properties":{"name":"Roscrea Recycling Centre","osm_id":"428635358","tag":{"amenity":"recycling","recycling:batteries":"yes","recycling:cans":"yes","recycling:paper":"yes"}},"type":"Feature"}
]
}
