{
"type": "FeatureCollection",
"lastupdate": "2020-08-06T00:00:00Z",
"features": [
	{"geometry":{"coordinates":[-7.817254,41.038267],"type":"Point"},"properties":{"name":"Contentores do Lixo","osm_id":"2059102032","tag":{"amenity":"recycling","recycling_type":"container"}},"type":"Feature"},
	{"geometry":{"coordinates":[-7.813293,41.038933],"type":"Point"},"properties":{"osm_id":"5460740412","tag":{"amenity":"waste_basket"}},"type":"Feature"}
]
}
