{
"type": "FeatureCollection",
"features": [
	{"geometry":{"coordinates":[-7.817254,41.038267],"type":"Point"},"properties":{"name":"Contentores do Lixo","osm_id":"2059102032","tag":{"amenity":"recycling","recycling_type":"container"}},"type":"Feature"},
	{"geometry":{"coordinates":[-7.742189,40.983298],"type":"Point"},"properties":{"name":"Trash","osm_id":"4234066851","tag":{"amenity":"waste_disposal"}},"type":"Feature"},
	{"geometry":{"coordinates":[-7.814316,41.039206],"type":"Point"},"properties":{"osm_id":"5460740410","tag":{"amenity":"waste_disposal"}},"type":"Feature"},
	{"geometry":{"coordinates":[-7.813293,41.038934],"type":"Point"},"properties":{"osm_id":"5460740412","tag":{"amenity":"waste_basket"}},"type":"Feature"}
]
}
