{
"type": "FeatureCollection",
"features": [
	{"geometry":{"coordinates":[87.548668,26.455479],"type":"Point"},"properties":{"name":"Peepal Tree","osm_id":"4173614490","tag":{"natural":"tree"}},"type":"Feature"}
]
}
