{
"type": "FeatureCollection",
"features": [
	{"geometry":{"coordinates":[87.548667,26.455478],"type":"Point"},"properties":{"name":"Peepal Tree","osm_id":"4173614490","tag":{"natural":"tree"}},"type":"Feature"}
]
}
