{
"type": "FeatureCollection",
"features": [
	{"geometry":{"coordinates":[17.859392,59.620533],"type":"Point"},"properties":{"name":"Apple tree","osm_id":"5839700609","tag":{"natural":"tree"}},"type":"Feature"}
]
}
