{
"type": "FeatureCollection",
"features": [
	{"geometry":{"coordinates":[17.899924,53.238782],"type":"Point"},"properties":{"osm_id":"4706692571","tag":{"denotation":"natural_monument","natural":"tree","ref:CRFOP":"PL.ZIPOP.1393.PP.0403043.978","ref:INSPIRE":"PL.ZIPOP.1393.PP.0403043.978","website":"http://crfop.gdos.gov.pl/CRFOP/widok/viewfop.jsf?fop=PL.ZIPOP.1393.PP.0403043.978"}},"type":"Feature"},
	{"geometry":{"coordinates":[17.844822,53.260716],"type":"Point"},"properties":{"osm_id":"4706692572","tag":{"denotation":"natural_monument","natural":"tree","ref:CRFOP":"PL.ZIPOP.1393.PP.0403043.977","ref:INSPIRE":"PL.ZIPOP.1393.PP.0403043.977","website":"http://crfop.gdos.gov.pl/CRFOP/widok/viewfop.jsf?fop=PL.ZIPOP.1393.PP.0403043.977"}},"type":"Feature"},
	{"geometry":{"coordinates":[17.919499,53.251643],"type":"Point"},"properties":{"osm_id":"4706693031","tag":{"denotation":"natural_monument","natural":"tree","ref:CRFOP":"PL.ZIPOP.1393.PP.0403043.962","ref:INSPIRE":"PL.ZIPOP.1393.PP.0403043.962","website":"http://crfop.gdos.gov.pl/CRFOP/widok/viewfop.jsf?fop=PL.ZIPOP.1393.PP.0403043.962"}},"type":"Feature"},
	{"geometry":{"coordinates":[17.919359,53.251551],"type":"Point"},"properties":{"osm_id":"4706693032","tag":{"denotation":"natural_monument","natural":"tree","ref:CRFOP":"PL.ZIPOP.1393.PP.0403043.962","ref:INSPIRE":"PL.ZIPOP.1393.PP.0403043.962","website":"http://crfop.gdos.gov.pl/CRFOP/widok/viewfop.jsf?fop=PL.ZIPOP.1393.PP.0403043.962"}},"type":"Feature"},
	{"geometry":{"coordinates":[17.919792,53.251103],"type":"Point"},"properties":{"osm_id":"4706693033","tag":{"denotation":"natural_monument","natural":"tree","ref:CRFOP":"PL.ZIPOP.1393.PP.0403043.962","ref:INSPIRE":"PL.ZIPOP.1393.PP.0403043.962","website":"http://crfop.gdos.gov.pl/CRFOP/widok/viewfop.jsf?fop=PL.ZIPOP.1393.PP.0403043.962"}},"type":"Feature"},
	{"geometry":{"coordinates":[17.920185,53.251482],"type":"Point"},"properties":{"osm_id":"4706693053","tag":{"denotation":"natural_monument","natural":"tree","ref:CRFOP":"PL.ZIPOP.1393.PP.0403043.952","ref:INSPIRE":"PL.ZIPOP.1393.PP.0403043.952","website":"http://crfop.gdos.gov.pl/CRFOP/widok/viewfop.jsf?fop=PL.ZIPOP.1393.PP.0403043.952"}},"type":"Feature"},
	{"geometry":{"coordinates":[17.912987,53.22775],"type":"Point"},"properties":{"osm_id":"6343015954","tag":{"natural":"tree"}},"type":"Feature"},
	{"geometry":{"coordinates":[17.913056,53.227735],"type":"Point"},"properties":{"osm_id":"6343015955","tag":{"natural":"tree"}},"type":"Feature"},
	{"geometry":{"coordinates":[17.913128,53.227719],"type":"Point"},"properties":{"osm_id":"6343015956","tag":{"natural":"tree"}},"type":"Feature"},
	{"geometry":{"coordinates":[17.913199,53.227704],"type":"Point"},"properties":{"osm_id":"6343015957","tag":{"natural":"tree"}},"type":"Feature"},
	{"geometry":{"coordinates":[17.913272,53.227688],"type":"Point"},"properties":{"osm_id":"6343015958","tag":{"natural":"tree"}},"type":"Feature"},
	{"geometry":{"coordinates":[17.913337,53.227673],"type":"Point"},"properties":{"osm_id":"6343015959","tag":{"natural":"tree"}},"type":"Feature"},
	{"geometry":{"coordinates":[17.92374,53.243783],"type":"Point"},"properties":{"osm_id":"6412446744","tag":{"natural":"tree"}},"type":"Feature"}
]
}
