{
"type": "FeatureCollection",
"features": [
	{"geometry":{"coordinates":[39.4729,-6.450812],"type":"Point"},"properties":{"name":"schooltree","osm_id":"767435337","tag":{"name:botanical":"Adansonia","natural":"tree","type":"Baobab / Monkey Bread Tree"}},"type":"Feature"},
	{"geometry":{"coordinates":[39.546324,-6.432553],"type":"Point"},"properties":{"osm_id":"5028650298","tag":{"natural":"tree"}},"type":"Feature"},
	{"geometry":{"coordinates":[39.54582,-6.432661],"type":"Point"},"properties":{"osm_id":"5028650307","tag":{"natural":"tree"}},"type":"Feature"},
	{"geometry":{"coordinates":[39.546004,-6.432412],"type":"Point"},"properties":{"osm_id":"5028652626","tag":{"natural":"tree"}},"type":"Feature"},
	{"geometry":{"coordinates":[39.547028,-6.431896],"type":"Point"},"properties":{"osm_id":"5028652633","tag":{"natural":"tree"}},"type":"Feature"}
]
}
