{
"type": "FeatureCollection",
"features": [
	{"geometry":{"coordinates":[39.4729,-6.450811],"type":"Point"},"properties":{"name":"schooltree","osm_id":"767435337","tag":{"name:botanical":"Adansonia","natural":"tree","type":"Baobab / Monkey Bread Tree"}},"type":"Feature"},
	{"geometry":{"coordinates":[39.546324,-6.432552],"type":"Point"},"properties":{"osm_id":"5028650298","tag":{"natural":"tree"}},"type":"Feature"},
	{"geometry":{"coordinates":[39.54582,-6.43266],"type":"Point"},"properties":{"osm_id":"5028650307","tag":{"natural":"tree"}},"type":"Feature"},
	{"geometry":{"coordinates":[39.546004,-6.432412],"type":"Point"},"properties":{"osm_id":"5028652626","tag":{"natural":"tree"}},"type":"Feature"},
	{"geometry":{"coordinates":[39.547027,-6.431895],"type":"Point"},"properties":{"osm_id":"5028652633","tag":{"natural":"tree"}},"type":"Feature"},
	{"geometry":{"coordinates":[39.464412,-6.43193],"type":"Point"},"properties":{"osm_id":"8261200246","tag":{"natural":"tree"}},"type":"Feature"}
]
}
