{
"type": "FeatureCollection",
"lastupdate": "2020-08-03T00:00:00Z",
"features": [
	{"geometry":{"coordinates":[13.380378,48.90631],"type":"Point"},"properties":{"osm_id":"474824043","tag":{"amenity":"recycling","recycling:cans":"yes","recycling:clothes":"yes","recycling:glass":"yes"}},"type":"Feature"},
	{"geometry":{"coordinates":[13.359879,48.92064],"type":"Point"},"properties":{"osm_id":"1360196972","tag":{"amenity":"recycling","recycling:glass_bottles":"yes","recycling_type":"container"}},"type":"Feature"},
	{"geometry":{"coordinates":[13.393933,48.87837],"type":"Point"},"properties":{"name":"Recyclingzentrum Grafenau","osm_id":"2734803931","tag":{"amenity":"recycling","recycling:batteries":"yes","recycling:cans":"yes","recycling:clothes":"yes","recycling:glass":"yes","recycling:paper":"yes","recycling:scrap_metal":"yes","recycling_type":"centre"}},"type":"Feature"},
	{"geometry":{"coordinates":[13.430704,48.884433],"type":"Point"},"properties":{"osm_id":"3270432375","tag":{"amenity":"recycling","recycling_type":"centre"}},"type":"Feature"},
	{"geometry":{"coordinates":[13.396315,48.898447],"type":"Point"},"properties":{"name":"Hundeklo","osm_id":"4161975105","tag":{"amenity":"waste_basket"}},"type":"Feature"},
	{"geometry":{"coordinates":[13.381353,48.906498],"type":"Point"},"properties":{"name":"Glascontainer","osm_id":"4743722238","tag":{"amenity":"recycling","recycling:glass":"yes","recycling_type":"container"}},"type":"Feature"}
]
}
