{
"type": "FeatureCollection",
"features": [
	{"geometry":{"coordinates":[11.890394,50.098677],"type":"Point"},"properties":{"name":"Wertstoffhof","osm_id":"311878855","tag":{"amenity":"recycling"}},"type":"Feature"},
	{"geometry":{"coordinates":[11.875566,50.108138],"type":"Point"},"properties":{"osm_id":"312460487","tag":{"amenity":"recycling"}},"type":"Feature"},
	{"geometry":{"coordinates":[11.929035,50.102254],"type":"Point"},"properties":{"osm_id":"1658838691","tag":{"amenity":"recycling"}},"type":"Feature"}
]
}
