{
"type": "FeatureCollection",
"lastupdate": "2020-08-03T00:00:00Z",
"features": [
	{"geometry":{"coordinates":[11.890393,50.098677],"type":"Point"},"properties":{"name":"Wertstoffhof","osm_id":"311878855","tag":{"amenity":"recycling"}},"type":"Feature"},
	{"geometry":{"coordinates":[11.875565,50.108137],"type":"Point"},"properties":{"osm_id":"312460487","tag":{"amenity":"recycling"}},"type":"Feature"},
	{"geometry":{"coordinates":[11.929034,50.102253],"type":"Point"},"properties":{"osm_id":"1658838691","tag":{"amenity":"recycling"}},"type":"Feature"}
]
}
