{
"type": "FeatureCollection",
"features": [
	{"geometry":{"coordinates":[0.084711,49.369045],"type":"Point"},"properties":{"osm_id":"600576399","tag":{"amenity":"recycling","recycling:cans":"yes","recycling:glass_bottles":"yes","recycling:paper":"yes","recycling_type":"container"}},"type":"Feature"},
	{"geometry":{"coordinates":[0.072073,49.344042],"type":"Point"},"properties":{"osm_id":"1769468784","tag":{"amenity":"recycling","recycling_type":"container"}},"type":"Feature"},
	{"geometry":{"coordinates":[0.007088,49.327632],"type":"Point"},"properties":{"osm_id":"1865984548","tag":{"amenity":"recycling","recycling_type":"container"}},"type":"Feature"},
	{"geometry":{"coordinates":[0.009486,49.327786],"type":"Point"},"properties":{"osm_id":"1865984553","tag":{"amenity":"recycling","location":"overground","recycling_type":"container"}},"type":"Feature"},
	{"geometry":{"coordinates":[0.084307,49.359929],"type":"Point"},"properties":{"osm_id":"4767131888","tag":{"amenity":"waste_basket","level":"0"}},"type":"Feature"},
	{"geometry":{"coordinates":[0.084254,49.360062],"type":"Point"},"properties":{"osm_id":"4767131908","tag":{"amenity":"waste_basket","level":"0"}},"type":"Feature"},
	{"geometry":{"coordinates":[0.084096,49.359866],"type":"Point"},"properties":{"osm_id":"4767131910","tag":{"amenity":"waste_basket","level":"0"}},"type":"Feature"},
	{"geometry":{"coordinates":[0.050545,49.34868],"type":"Point"},"properties":{"osm_id":"5229555377","tag":{"amenity":"recycling","recycling:glass_bottles":"yes","recycling_type":"container"}},"type":"Feature"},
	{"geometry":{"coordinates":[0.087884,49.337373],"type":"Point"},"properties":{"osm_id":"7687066536","tag":{"amenity":"waste_basket"}},"type":"Feature"},
	{"geometry":{"coordinates":[0.076549,49.359624],"type":"Point"},"properties":{"osm_id":"8524885923","tag":{"amenity":"waste_basket","colour":"green","material":"metal"}},"type":"Feature"},
	{"geometry":{"coordinates":[0.07595,49.361145],"type":"Point"},"properties":{"osm_id":"8524929365","tag":{"amenity":"waste_basket","colour":"white"}},"type":"Feature"},
	{"geometry":{"coordinates":[0.00842,49.329582],"type":"Point"},"properties":{"osm_id":"8974303236","tag":{"amenity":"waste_basket","waste":"trash"}},"type":"Feature"}
]
}
