{
"type": "FeatureCollection",
"features": [
	{"geometry":{"coordinates":[-55.532179,-27.254343],"type":"Point"},"properties":{"osm_id":"1714272874","tag":{"natural":"tree"}},"type":"Feature"},
	{"geometry":{"coordinates":[-55.531052,-27.254837],"type":"Point"},"properties":{"osm_id":"1714272876","tag":{"natural":"tree"}},"type":"Feature"},
	{"geometry":{"coordinates":[-55.532149,-27.254031],"type":"Point"},"properties":{"osm_id":"1714272886","tag":{"natural":"tree"}},"type":"Feature"},
	{"geometry":{"coordinates":[-55.532031,-27.253838],"type":"Point"},"properties":{"osm_id":"1714272900","tag":{"natural":"tree"}},"type":"Feature"},
	{"geometry":{"coordinates":[-55.532476,-27.2545],"type":"Point"},"properties":{"name":"Higuera brava","osm_id":"3286888124","tag":{"natural":"tree","tourism":"attraction"}},"type":"Feature"},
	{"geometry":{"coordinates":[-55.53123,-27.255211],"type":"Point"},"properties":{"osm_id":"3286893029","tag":{"natural":"tree"}},"type":"Feature"},
	{"geometry":{"coordinates":[-55.531403,-27.255345],"type":"Point"},"properties":{"osm_id":"3286893030","tag":{"natural":"tree"}},"type":"Feature"},
	{"geometry":{"coordinates":[-55.531514,-27.255412],"type":"Point"},"properties":{"osm_id":"3286893031","tag":{"natural":"tree"}},"type":"Feature"},
	{"geometry":{"coordinates":[-55.530532,-27.255278],"type":"Point"},"properties":{"osm_id":"3286893032","tag":{"natural":"tree"}},"type":"Feature"},
	{"geometry":{"coordinates":[-55.531022,-27.255775],"type":"Point"},"properties":{"osm_id":"6067450304","tag":{"natural":"tree"}},"type":"Feature"},
	{"geometry":{"coordinates":[-55.530828,-27.255769],"type":"Point"},"properties":{"osm_id":"6067450305","tag":{"natural":"tree"}},"type":"Feature"},
	{"geometry":{"coordinates":[-55.530742,-27.254588],"type":"Point"},"properties":{"osm_id":"6067450306","tag":{"natural":"tree"}},"type":"Feature"},
	{"geometry":{"coordinates":[-55.530744,-27.254666],"type":"Point"},"properties":{"osm_id":"6067450307","tag":{"natural":"tree"}},"type":"Feature"},
	{"geometry":{"coordinates":[-55.530615,-27.254952],"type":"Point"},"properties":{"osm_id":"6067450308","tag":{"natural":"tree"}},"type":"Feature"},
	{"geometry":{"coordinates":[-55.531,-27.254497],"type":"Point"},"properties":{"osm_id":"6067450309","tag":{"natural":"tree"}},"type":"Feature"},
	{"geometry":{"coordinates":[-55.530879,-27.254345],"type":"Point"},"properties":{"osm_id":"6067450310","tag":{"natural":"tree"}},"type":"Feature"},
	{"geometry":{"coordinates":[-55.530523,-27.254275],"type":"Point"},"properties":{"osm_id":"6067450311","tag":{"natural":"tree"}},"type":"Feature"},
	{"geometry":{"coordinates":[-55.530546,-27.254403],"type":"Point"},"properties":{"osm_id":"6067450312","tag":{"natural":"tree"}},"type":"Feature"},
	{"geometry":{"coordinates":[-55.530988,-27.254234],"type":"Point"},"properties":{"osm_id":"6067450313","tag":{"natural":"tree"}},"type":"Feature"},
	{"geometry":{"coordinates":[-55.531471,-27.253701],"type":"Point"},"properties":{"osm_id":"6067450314","tag":{"natural":"tree"}},"type":"Feature"},
	{"geometry":{"coordinates":[-55.531211,-27.253483],"type":"Point"},"properties":{"osm_id":"6067450315","tag":{"natural":"tree"}},"type":"Feature"},
	{"geometry":{"coordinates":[-55.53134,-27.253531],"type":"Point"},"properties":{"osm_id":"6067450316","tag":{"natural":"tree"}},"type":"Feature"},
	{"geometry":{"coordinates":[-55.531475,-27.253489],"type":"Point"},"properties":{"osm_id":"6067450317","tag":{"natural":"tree"}},"type":"Feature"}
]
}
