{
"type": "FeatureCollection",
"features": [
	{"geometry":{"coordinates":[-55.532178,-27.254342],"type":"Point"},"properties":{"osm_id":"1714272874","tag":{"natural":"tree"}},"type":"Feature"},
	{"geometry":{"coordinates":[-55.531052,-27.254836],"type":"Point"},"properties":{"osm_id":"1714272876","tag":{"natural":"tree"}},"type":"Feature"},
	{"geometry":{"coordinates":[-55.532149,-27.25403],"type":"Point"},"properties":{"osm_id":"1714272886","tag":{"natural":"tree"}},"type":"Feature"},
	{"geometry":{"coordinates":[-55.532031,-27.253837],"type":"Point"},"properties":{"osm_id":"1714272900","tag":{"natural":"tree"}},"type":"Feature"},
	{"geometry":{"coordinates":[-55.532476,-27.2545],"type":"Point"},"properties":{"name":"Higuera brava","osm_id":"3286888124","tag":{"natural":"tree","tourism":"attraction"}},"type":"Feature"},
	{"geometry":{"coordinates":[-55.531229,-27.255211],"type":"Point"},"properties":{"osm_id":"3286893029","tag":{"natural":"tree"}},"type":"Feature"},
	{"geometry":{"coordinates":[-55.531403,-27.255345],"type":"Point"},"properties":{"osm_id":"3286893030","tag":{"natural":"tree"}},"type":"Feature"},
	{"geometry":{"coordinates":[-55.531513,-27.255411],"type":"Point"},"properties":{"osm_id":"3286893031","tag":{"natural":"tree"}},"type":"Feature"},
	{"geometry":{"coordinates":[-55.530532,-27.255278],"type":"Point"},"properties":{"osm_id":"3286893032","tag":{"natural":"tree"}},"type":"Feature"},
	{"geometry":{"coordinates":[-55.531021,-27.255774],"type":"Point"},"properties":{"osm_id":"6067450304","tag":{"natural":"tree"}},"type":"Feature"},
	{"geometry":{"coordinates":[-55.530828,-27.255769],"type":"Point"},"properties":{"osm_id":"6067450305","tag":{"natural":"tree"}},"type":"Feature"},
	{"geometry":{"coordinates":[-55.530742,-27.254587],"type":"Point"},"properties":{"osm_id":"6067450306","tag":{"natural":"tree"}},"type":"Feature"},
	{"geometry":{"coordinates":[-55.530743,-27.254666],"type":"Point"},"properties":{"osm_id":"6067450307","tag":{"natural":"tree"}},"type":"Feature"},
	{"geometry":{"coordinates":[-55.530615,-27.254951],"type":"Point"},"properties":{"osm_id":"6067450308","tag":{"natural":"tree"}},"type":"Feature"},
	{"geometry":{"coordinates":[-55.530999,-27.254497],"type":"Point"},"properties":{"osm_id":"6067450309","tag":{"natural":"tree"}},"type":"Feature"},
	{"geometry":{"coordinates":[-55.530878,-27.254345],"type":"Point"},"properties":{"osm_id":"6067450310","tag":{"natural":"tree"}},"type":"Feature"},
	{"geometry":{"coordinates":[-55.530522,-27.254274],"type":"Point"},"properties":{"osm_id":"6067450311","tag":{"natural":"tree"}},"type":"Feature"},
	{"geometry":{"coordinates":[-55.530545,-27.254403],"type":"Point"},"properties":{"osm_id":"6067450312","tag":{"natural":"tree"}},"type":"Feature"},
	{"geometry":{"coordinates":[-55.530988,-27.254233],"type":"Point"},"properties":{"osm_id":"6067450313","tag":{"natural":"tree"}},"type":"Feature"},
	{"geometry":{"coordinates":[-55.53147,-27.2537],"type":"Point"},"properties":{"osm_id":"6067450314","tag":{"natural":"tree"}},"type":"Feature"},
	{"geometry":{"coordinates":[-55.531211,-27.253483],"type":"Point"},"properties":{"osm_id":"6067450315","tag":{"natural":"tree"}},"type":"Feature"},
	{"geometry":{"coordinates":[-55.53134,-27.253531],"type":"Point"},"properties":{"osm_id":"6067450316","tag":{"natural":"tree"}},"type":"Feature"},
	{"geometry":{"coordinates":[-55.531474,-27.253488],"type":"Point"},"properties":{"osm_id":"6067450317","tag":{"natural":"tree"}},"type":"Feature"}
]
}
