{
"type": "FeatureCollection",
"lastupdate": "2020-08-03T00:00:00Z",
"features": [
	{"geometry":{"coordinates":[-90.147701,42.529632],"type":"Point"},"properties":{"name":"Town of Moticello residents recycling","osm_id":"6944334228","tag":{"amenity":"recycling","recycling:aluminium_cans":"yes","recycling:bottles":"yes","recycling:cardboard":"yes","recycling:glass_brown":"yes","recycling:glass_green":"yes","recycling:glass_white":"yes","recycling:jars":"yes","recycling:magazines":"yes","recycling:paper":"yes","recycling:plastic":"yes","recycling:plastics":"yes","recycling:tin_cans":"yes","recycling_type":"container"}},"type":"Feature"}
]
}
