{
"type": "FeatureCollection",
"features": [
	{"geometry":{"coordinates":[-90.147701,42.529632],"type":"Point"},"properties":{"name":"Town of Moticello residents recycling","osm_id":"6944334228","tag":{"amenity":"recycling","recycling:aluminium_cans":"yes","recycling:bottles":"yes","recycling:cardboard":"yes","recycling:glass_brown":"yes","recycling:glass_green":"yes","recycling:glass_white":"yes","recycling:jars":"yes","recycling:magazines":"yes","recycling:paper":"yes","recycling:plastic":"yes","recycling:plastics":"yes","recycling:tin_cans":"yes","recycling_type":"container"}},"type":"Feature"},
	{"geometry":{"coordinates":[-90.14777,42.529644],"type":"Point"},"properties":{"osm_id":"6961293281","tag":{"access":"customers","amenity":"waste_disposal","customers":"Town of Moticello residents","operator":"Town of Moticello residents recycling"}},"type":"Feature"}
]
}
