{
"type": "FeatureCollection",
"features": [
	{"geometry":{"coordinates":[-90.117065,29.941998],"type":"Point"},"properties":{"osm_id":"308769274","tag":{"amenity":"recycling"}},"type":"Feature"},
	{"geometry":{"coordinates":[-90.089613,29.966846],"type":"Point"},"properties":{"name":"Dats Progress Recycling","osm_id":"1252829465","tag":{"amenity":"recycling","opening_hours":"Sa-Su 06:00-17:00","recycling:aluminium":"yes","recycling:scrap_metal":"yes","recycling:sheet_metal":"yes","website":"http://datsprogress.org"}},"type":"Feature"},
	{"geometry":{"coordinates":[-90.095812,29.988234],"type":"Point"},"properties":{"osm_id":"6564124886","tag":{"amenity":"waste_basket"}},"type":"Feature"},
	{"geometry":{"coordinates":[-90.09774,29.99014],"type":"Point"},"properties":{"osm_id":"6564126189","tag":{"amenity":"waste_basket"}},"type":"Feature"}
]
}
