{
"type": "FeatureCollection",
"features": [
	{"geometry":{"coordinates":[13.317858,38.189059],"type":"Point"},"properties":{"osm_id":"1468355921","tag":{"amenity":"recycling","recycling_type":"container"}},"type":"Feature"},
	{"geometry":{"coordinates":[13.314498,38.189102],"type":"Point"},"properties":{"osm_id":"1468355934","tag":{"amenity":"recycling","recycling_type":"container"}},"type":"Feature"},
	{"geometry":{"coordinates":[13.307698,38.189102],"type":"Point"},"properties":{"osm_id":"1468355941","tag":{"amenity":"recycling","recycling_type":"container"}},"type":"Feature"},
	{"geometry":{"coordinates":[13.303322,38.189117],"type":"Point"},"properties":{"osm_id":"1468355943","tag":{"amenity":"recycling","recycling_type":"container"}},"type":"Feature"},
	{"geometry":{"coordinates":[13.30494,38.189118],"type":"Point"},"properties":{"osm_id":"1468355944","tag":{"amenity":"recycling","recycling_type":"container"}},"type":"Feature"},
	{"geometry":{"coordinates":[13.321742,38.190679],"type":"Point"},"properties":{"osm_id":"1468355991","tag":{"amenity":"recycling","recycling_type":"container"}},"type":"Feature"},
	{"geometry":{"coordinates":[13.309189,38.163926],"type":"Point"},"properties":{"name":"Centro raccolta RAP","osm_id":"7981947113","tag":{"amenity":"recycling","opening_hours":"Mo-Sa 07:00-13:00","operator":"RAP","recycling:batteries":"yes","recycling:cardboard":"yes","recycling:clothes":"yes","recycling:cooking_oil":"yes","recycling:electrical_appliances":"yes","recycling:glass":"yes","recycling:glass_bottles":"yes","recycling:green_waste":"yes","recycling:paper":"yes","recycling:plastic":"yes","recycling:plastic_bottles":"yes","recycling:plastic_packaging":"yes","recycling:scrap_metal":"yes","recycling:shoes":"yes","recycling:small_appliances":"yes","recycling:waste":"Ingombranti","recycling_type":"centre","wheelchair":"limited"}},"type":"Feature"},
	{"geometry":{"coordinates":[13.331701,38.151042],"type":"Point"},"properties":{"osm_id":"8314504375","tag":{"amenity":"recycling","operator":"RAP S.p.A.","recycling:glass_bottles":"yes","recycling_type":"container"}},"type":"Feature"},
	{"geometry":{"coordinates":[13.35568,38.142469],"type":"Point"},"properties":{"name":"Raccolta di olio esausto","osm_id":"9111488518","tag":{"amenity":"recycling","fee":"no","recycling_type":"container","waste":"recycling"}},"type":"Feature"}
]
}
