{
"type": "FeatureCollection",
"features": [
	{"geometry":{"coordinates":[-135.072161,60.740372],"type":"Point"},"properties":{"name":"Raven Recycling Society","osm_id":"9173952817","tag":{"addr:housenumber":"100","addr:postcode":"Y1A 2W6","addr:street":"Galena Road","amenity":"recycling","opening_hours":"Monday - Saturday 9am-5pm, and closed on Sunday.","phone":"18676677269","recycling_type":"centre","website":"https://ravenrecycling.org/"}},"type":"Feature"}
]
}
