{
"type": "FeatureCollection",
"lastupdate": "2020-08-05T00:00:00Z",
"features": [
	{"geometry":{"coordinates":[23.799166,62.70451],"type":"Point"},"properties":{"name":"Ekopiste Tohni","osm_id":"2020083301","tag":{"addr:city":"Alavus","addr:housenumber":"481","addr:postcode":"63600","addr:street":"Tohninm\u00e4entie","amenity":"recycling","description":"paperi,lasi- ja metalliker\u00e4ys","operator":"Lakeuden Etappi Oy","recycling:glass":"yes","recycling:glass_bottles":"yes","recycling:magazines":"yes","recycling:newspaper":"yes","recycling:paper":"yes","recycling:paper_packaging":"yes","recycling:scrap_metal":"yes","recycling_type":"container","website":"https://www.etappi.com/index.php?page=vastaanotto&subid=21&jateasema=5&jateasemaid=10"}},"type":"Feature"}
]
}
