{
"type": "FeatureCollection",
"lastupdate": "2020-08-01T00:00:00Z",
"features": [
	{"geometry":{"coordinates":[113.546145,22.124669],"type":"Point"},"properties":{"osm_id":"3343839670","tag":{"amenity":"recycling","location":"overground","recycling:cans":"yes","recycling:paper":"yes","recycling:scrap_metal":"yes","recycling_type":"container"}},"type":"Feature"},
	{"geometry":{"coordinates":[113.546375,22.128028],"type":"Point"},"properties":{"osm_id":"3343839671","tag":{"amenity":"recycling","location":"overground","recycling:cans":"yes","recycling:paper":"yes","recycling:scrap_metal":"yes","recycling_type":"container"}},"type":"Feature"},
	{"geometry":{"coordinates":[113.54632,22.131201],"type":"Point"},"properties":{"osm_id":"3343839672","tag":{"amenity":"recycling","location":"overground","recycling:cans":"yes","recycling:paper":"yes","recycling:scrap_metal":"yes","recycling_type":"container"}},"type":"Feature"},
	{"geometry":{"coordinates":[113.543602,22.134202],"type":"Point"},"properties":{"osm_id":"3343839673","tag":{"amenity":"recycling","recycling:cans":"yes","recycling:paper":"yes","recycling:scrap_metal":"yes"}},"type":"Feature"},
	{"geometry":{"coordinates":[113.552708,22.155978],"type":"Point"},"properties":{"osm_id":"3343839678","tag":{"amenity":"recycling","recycling:cans":"yes","recycling:paper":"yes","recycling:scrap_metal":"yes"}},"type":"Feature"}
]
}
