{
"type": "FeatureCollection",
"features": [
	{"geometry":{"coordinates":[33.774832,-3.182695],"type":"Point"},"properties":{"name":"Buza radio service","osm_id":"5129225321","tag":{"amenity":"recycling","name:en":"Buza radio service"}},"type":"Feature"}
]
}
