{
"type": "FeatureCollection",
"lastupdate": "2020-08-05T00:00:00Z",
"features": [
	{"geometry":{"coordinates":[33.774831,-3.182694],"type":"Point"},"properties":{"name":"Buza radio service","osm_id":"5129225321","tag":{"amenity":"recycling","name:en":"Buza radio service"}},"type":"Feature"}
]
}
