{
"type": "FeatureCollection",
"features": [
	{"geometry":{"coordinates":[-88.891643,39.809008],"type":"Point"},"properties":{"name":"Lynns Tree's","osm_id":"2544223712","tag":{"natural":"tree"}},"type":"Feature"}
]
}
