{
"type": "FeatureCollection",
"features": [
	{"geometry":{"coordinates":[-88.913902,30.406391],"type":"Point"},"properties":{"name":"Tree of Knowledge","osm_id":"6355554300","tag":{"natural":"tree"}},"type":"Feature"}
]
}
