{
"type": "FeatureCollection",
"features": [
	{"geometry":{"coordinates":[-43.595916,-22.907963],"type":"Point"},"properties":{"name":"Lixeira","osm_id":"5651141133","tag":{"amenity":"waste_basket"}},"type":"Feature"},
	{"geometry":{"coordinates":[-43.595043,-22.907946],"type":"Point"},"properties":{"name":"Lixeira","osm_id":"5651141146","tag":{"amenity":"waste_basket","description":"Lixeira"}},"type":"Feature"},
	{"geometry":{"coordinates":[-43.595185,-22.908089],"type":"Point"},"properties":{"name":"Lixeira","osm_id":"5651141149","tag":{"amenity":"waste_basket","description":"Lixeira"}},"type":"Feature"},
	{"geometry":{"coordinates":[-43.594945,-22.908355],"type":"Point"},"properties":{"name":"Lixeira","osm_id":"5651141159","tag":{"amenity":"waste_basket"}},"type":"Feature"},
	{"geometry":{"coordinates":[-43.59542,-22.908276],"type":"Point"},"properties":{"name":"Lixeira","osm_id":"5651141160","tag":{"amenity":"waste_basket","description":"Lixeira"}},"type":"Feature"},
	{"geometry":{"coordinates":[-43.595497,-22.90847],"type":"Point"},"properties":{"name":"Lixeira","osm_id":"5651141162","tag":{"amenity":"waste_basket","description":"Lixeira"}},"type":"Feature"},
	{"geometry":{"coordinates":[-43.596256,-22.907974],"type":"Point"},"properties":{"name":"Lixeira","osm_id":"5651141171","tag":{"amenity":"waste_basket"}},"type":"Feature"},
	{"geometry":{"coordinates":[-43.596539,-22.908042],"type":"Point"},"properties":{"name":"Lixeira","osm_id":"5651141173","tag":{"amenity":"waste_basket"}},"type":"Feature"},
	{"geometry":{"coordinates":[-43.596275,-22.908616],"type":"Point"},"properties":{"name":"Lixeira","osm_id":"5651141174","tag":{"amenity":"waste_basket"}},"type":"Feature"},
	{"geometry":{"coordinates":[-43.596472,-22.90865],"type":"Point"},"properties":{"name":"Lixeira","osm_id":"5651141175","tag":{"amenity":"waste_basket"}},"type":"Feature"}
]
}
