{
"type": "FeatureCollection",
"lastupdate": "2020-08-04T00:00:00Z",
"features": [
	{"geometry":{"coordinates":[-43.595916,-22.907963],"type":"Point"},"properties":{"name":"Lixeira","osm_id":"5651141133","tag":{"amenity":"waste_basket"}},"type":"Feature"},
	{"geometry":{"coordinates":[-43.595043,-22.907946],"type":"Point"},"properties":{"name":"Lixeira","osm_id":"5651141146","tag":{"amenity":"waste_basket","description":"Lixeira"}},"type":"Feature"},
	{"geometry":{"coordinates":[-43.595184,-22.908088],"type":"Point"},"properties":{"name":"Lixeira","osm_id":"5651141149","tag":{"amenity":"waste_basket","description":"Lixeira"}},"type":"Feature"},
	{"geometry":{"coordinates":[-43.594944,-22.908354],"type":"Point"},"properties":{"name":"Lixeira","osm_id":"5651141159","tag":{"amenity":"waste_basket"}},"type":"Feature"},
	{"geometry":{"coordinates":[-43.595419,-22.908275],"type":"Point"},"properties":{"name":"Lixeira","osm_id":"5651141160","tag":{"amenity":"waste_basket","description":"Lixeira"}},"type":"Feature"},
	{"geometry":{"coordinates":[-43.595497,-22.90847],"type":"Point"},"properties":{"name":"Lixeira","osm_id":"5651141162","tag":{"amenity":"waste_basket","description":"Lixeira"}},"type":"Feature"},
	{"geometry":{"coordinates":[-43.596255,-22.907973],"type":"Point"},"properties":{"name":"Lixeira","osm_id":"5651141171","tag":{"amenity":"waste_basket"}},"type":"Feature"},
	{"geometry":{"coordinates":[-43.596538,-22.908041],"type":"Point"},"properties":{"name":"Lixeira","osm_id":"5651141173","tag":{"amenity":"waste_basket"}},"type":"Feature"},
	{"geometry":{"coordinates":[-43.596275,-22.908615],"type":"Point"},"properties":{"name":"Lixeira","osm_id":"5651141174","tag":{"amenity":"waste_basket"}},"type":"Feature"},
	{"geometry":{"coordinates":[-43.596472,-22.90865],"type":"Point"},"properties":{"name":"Lixeira","osm_id":"5651141175","tag":{"amenity":"waste_basket"}},"type":"Feature"}
]
}
