{
"type": "FeatureCollection",
"features": [
	{"geometry":{"coordinates":[9.127455,51.487727],"type":"Point"},"properties":{"osm_id":"687992558","tag":{"amenity":"recycling","recycling:clothes":"yes","recycling:glass":"yes","recycling:shoes":"yes","recycling_type":"container"}},"type":"Feature"},
	{"geometry":{"coordinates":[9.136823,51.489991],"type":"Point"},"properties":{"osm_id":"2274692089","tag":{"amenity":"recycling","recycling:small_appliances":"yes","recycling_type":"container","website":"http://www.kreis-hoexter.de/politik-verwaltung/verwaltung/presse/pressemitteilungen/pressemitteilungen-2013/20130408sammelcontai"}},"type":"Feature"},
	{"geometry":{"coordinates":[9.102218,51.484379],"type":"Point"},"properties":{"osm_id":"2416097123","tag":{"amenity":"recycling","recycling:batteries":"no","recycling:books":"no","recycling:cans":"no","recycling:cardboard":"no","recycling:cartons":"no","recycling:electrical_appliances":"no","recycling:glass":"no","recycling:glass_bottles":"yes","recycling:green_waste":"no","recycling:magazines":"no","recycling:newspaper":"no","recycling:paper":"no","recycling:paper_packaging":"no","recycling:plastic":"no","recycling:plastic_bottles":"no","recycling:plastic_packaging":"no","recycling:scrap_metal":"no","recycling:small_appliances":"no","recycling:waste":"no","recycling:wood":"no","recycling_type":"container"}},"type":"Feature"},
	{"geometry":{"coordinates":[9.137372,51.481752],"type":"Point"},"properties":{"osm_id":"3744784938","tag":{"amenity":"recycling","recycling:glass_bottles":"yes","recycling_type":"container"}},"type":"Feature"},
	{"geometry":{"coordinates":[9.137339,51.481767],"type":"Point"},"properties":{"osm_id":"3744784939","tag":{"amenity":"recycling","recycling:clothes":"yes","recycling:shoes":"yes","recycling_type":"container"}},"type":"Feature"},
	{"geometry":{"coordinates":[9.135196,51.485837],"type":"Point"},"properties":{"osm_id":"3744784948","tag":{"amenity":"waste_basket"}},"type":"Feature"},
	{"geometry":{"coordinates":[9.138573,51.486243],"type":"Point"},"properties":{"osm_id":"3760593507","tag":{"amenity":"recycling","recycling:glass":"yes","recycling_type":"container"}},"type":"Feature"},
	{"geometry":{"coordinates":[9.104208,51.488774],"type":"Point"},"properties":{"osm_id":"6070979555","tag":{"amenity":"waste_basket"}},"type":"Feature"},
	{"geometry":{"coordinates":[9.128611,51.473109],"type":"Point"},"properties":{"osm_id":"7617637079","tag":{"amenity":"recycling","recycling:clothes":"yes","recycling:glass":"yes","recycling_type":"container"}},"type":"Feature"},
	{"geometry":{"coordinates":[9.071118,51.492219],"type":"Point"},"properties":{"osm_id":"7617880859","tag":{"amenity":"recycling","recycling:glass":"yes","recycling_type":"container"}},"type":"Feature"},
	{"geometry":{"coordinates":[9.057555,51.490926],"type":"Point"},"properties":{"osm_id":"7617880865","tag":{"amenity":"waste_basket"}},"type":"Feature"}
]
}
