{
"type": "FeatureCollection",
"features": [
	{"geometry":{"coordinates":[-5.441108,36.16478],"type":"Point"},"properties":{"osm_id":"654571633","tag":{"amenity":"recycling"}},"type":"Feature"},
	{"geometry":{"coordinates":[-5.446954,36.159771],"type":"Point"},"properties":{"osm_id":"655138248","tag":{"amenity":"recycling","location":"overground","recycling_type":"container"}},"type":"Feature"},
	{"geometry":{"coordinates":[-5.447096,36.159112],"type":"Point"},"properties":{"osm_id":"655138249","tag":{"amenity":"recycling","location":"overground","recycling_type":"container"}},"type":"Feature"},
	{"geometry":{"coordinates":[-5.448187,36.157518],"type":"Point"},"properties":{"osm_id":"655138250","tag":{"amenity":"recycling"}},"type":"Feature"},
	{"geometry":{"coordinates":[-5.439146,36.1656],"type":"Point"},"properties":{"osm_id":"655138255","tag":{"amenity":"recycling"}},"type":"Feature"},
	{"geometry":{"coordinates":[-5.443145,36.161733],"type":"Point"},"properties":{"osm_id":"655138256","tag":{"amenity":"recycling"}},"type":"Feature"},
	{"geometry":{"coordinates":[-5.444724,36.129307],"type":"Point"},"properties":{"osm_id":"6575505677","tag":{"amenity":"recycling","recycling:cartons":"yes","recycling:glass_bottles":"yes","recycling:magazines":"yes","recycling:newspaper":"yes","recycling:paper":"yes","recycling:plastic":"yes","recycling:plastic_bottles":"yes","recycling:plastic_packaging":"yes","recycling:waste":"yes","recycling_type":"container"}},"type":"Feature"},
	{"geometry":{"coordinates":[-5.447361,36.12639],"type":"Point"},"properties":{"osm_id":"6575585661","tag":{"amenity":"waste_basket"}},"type":"Feature"},
	{"geometry":{"coordinates":[-5.445064,36.127193],"type":"Point"},"properties":{"osm_id":"6575600937","tag":{"amenity":"waste_basket"}},"type":"Feature"}
]
}
