{
"type": "FeatureCollection",
"features": [
	{"geometry":{"coordinates":[3.399697,50.334448],"type":"Point"},"properties":{"osm_id":"3298326367","tag":{"amenity":"recycling","recycling:glass":"yes","recycling_type":"container"}},"type":"Feature"},
	{"geometry":{"coordinates":[3.396291,50.297775],"type":"Point"},"properties":{"name":"Composteur Jardin des Doux chineurs","osm_id":"7900387400","tag":{"access":"customers","amenity":"recycling","operator":"Ajonc","recycling:compost":"yes","recycling:organic":"yes","recycling_type":"container"}},"type":"Feature"},
	{"geometry":{"coordinates":[3.348264,50.312701],"type":"Point"},"properties":{"name":"Composteur Jardin de Lourches","osm_id":"7943038304","tag":{"access":"customers","amenity":"recycling","operator":"Ajonc","recycling:compost":"yes","recycling:organic":"yes","recycling_type":"container"}},"type":"Feature"},
	{"geometry":{"coordinates":[3.405873,50.320579],"type":"Point"},"properties":{"name":"Composteur Jardin les Grandes Gamelles","osm_id":"7943072319","tag":{"access":"customers","amenity":"recycling","operator":"Ajonc","recycling:compost":"yes","recycling:organic":"yes","recycling_type":"container"}},"type":"Feature"}
]
}
