{
"type": "FeatureCollection",
"features": [
	{"geometry":{"coordinates":[-2.444809,38.363455],"type":"Point"},"properties":{"name":"Carrasca de La Moheda","osm_id":"7417599870","tag":{"denotation":"single","natural":"tree"}},"type":"Feature"},
	{"geometry":{"coordinates":[-2.454905,38.365879],"type":"Point"},"properties":{"name":"Noguera de Collado Tornero","osm_id":"7419924672","tag":{"denotation":"single","natural":"tree"}},"type":"Feature"},
	{"geometry":{"coordinates":[-2.423193,38.387317],"type":"Point"},"properties":{"name":"Encina de Los Tejeros","osm_id":"7419924673","tag":{"denotation":"single","natural":"tree"}},"type":"Feature"},
	{"geometry":{"coordinates":[-2.402324,38.408786],"type":"Point"},"properties":{"name":"Tejo del Collado Verde","osm_id":"7419924674","tag":{"denotation":"single","natural":"tree"}},"type":"Feature"}
]
}
