{
"type": "FeatureCollection",
"features": [
	{"geometry":{"coordinates":[-52.391862,4.529974],"type":"Point"},"properties":{"name":"Arbre creux","osm_id":"1743649022","tag":{"natural":"tree"}},"type":"Feature"}
]
}
