{
"type": "FeatureCollection",
"lastupdate": "2020-08-01T00:00:00Z",
"features": [
	{"geometry":{"coordinates":[-60.76728,2.822677],"type":"Point"},"properties":{"name":"SM Natureza","osm_id":"6365282231","tag":{"amenity":"recycling","operator":"SM Natureza","recycling_type":"centre"}},"type":"Feature"}
]
}
