{
"type": "FeatureCollection",
"features": [
	{"geometry":{"coordinates":[47.052392,39.507624],"type":"Point"},"properties":{"osm_id":"3682491716","tag":{"natural":"tree"}},"type":"Feature"},
	{"geometry":{"coordinates":[47.051895,39.510049],"type":"Point"},"properties":{"osm_id":"3685620294","tag":{"natural":"tree"}},"type":"Feature"},
	{"geometry":{"coordinates":[47.049205,39.51043],"type":"Point"},"properties":{"osm_id":"3685620451","tag":{"natural":"tree"}},"type":"Feature"},
	{"geometry":{"coordinates":[47.049399,39.510214],"type":"Point"},"properties":{"osm_id":"3685620452","tag":{"natural":"tree"}},"type":"Feature"},
	{"geometry":{"coordinates":[47.049984,39.510399],"type":"Point"},"properties":{"osm_id":"3685620453","tag":{"natural":"tree"}},"type":"Feature"},
	{"geometry":{"coordinates":[47.033397,39.514643],"type":"Point"},"properties":{"name":"Platan 800 years old","osm_id":"4655134695","tag":{"natural":"tree"}},"type":"Feature"},
	{"geometry":{"coordinates":[47.032977,39.505133],"type":"Point"},"properties":{"osm_id":"5273211489","tag":{"natural":"tree"}},"type":"Feature"}
]
}
