{
"type": "FeatureCollection",
"features": [
	{"geometry":{"coordinates":[10.202962,52.464078],"type":"Point"},"properties":{"osm_id":"648249291","tag":{"addr:city":"Uetze","addr:country":"DE","natural":"tree"}},"type":"Feature"},
	{"geometry":{"coordinates":[10.282336,52.467042],"type":"Point"},"properties":{"osm_id":"6027209132","tag":{"genus:en":"birch","natural":"tree"}},"type":"Feature"},
	{"geometry":{"coordinates":[10.248036,52.453435],"type":"Point"},"properties":{"osm_id":"6339963177","tag":{"natural":"tree"}},"type":"Feature"},
	{"geometry":{"coordinates":[10.248787,52.453533],"type":"Point"},"properties":{"osm_id":"6339963178","tag":{"natural":"tree"}},"type":"Feature"},
	{"geometry":{"coordinates":[10.249109,52.453601],"type":"Point"},"properties":{"osm_id":"6339963179","tag":{"natural":"tree"}},"type":"Feature"},
	{"geometry":{"coordinates":[10.218419,52.431042],"type":"Point"},"properties":{"osm_id":"6339963477","tag":{"natural":"tree"}},"type":"Feature"},
	{"geometry":{"coordinates":[10.210716,52.429799],"type":"Point"},"properties":{"osm_id":"6339963478","tag":{"natural":"tree"}},"type":"Feature"},
	{"geometry":{"coordinates":[10.210542,52.42982],"type":"Point"},"properties":{"osm_id":"6339963479","tag":{"natural":"tree"}},"type":"Feature"},
	{"geometry":{"coordinates":[10.214586,52.431838],"type":"Point"},"properties":{"osm_id":"6339963480","tag":{"natural":"tree"}},"type":"Feature"},
	{"geometry":{"coordinates":[10.215874,52.430679],"type":"Point"},"properties":{"osm_id":"6339963481","tag":{"natural":"tree"}},"type":"Feature"},
	{"geometry":{"coordinates":[10.215638,52.430666],"type":"Point"},"properties":{"osm_id":"6339963482","tag":{"natural":"tree"}},"type":"Feature"},
	{"geometry":{"coordinates":[10.215533,52.430512],"type":"Point"},"properties":{"osm_id":"6339963483","tag":{"natural":"tree"}},"type":"Feature"},
	{"geometry":{"coordinates":[10.215386,52.43027],"type":"Point"},"properties":{"osm_id":"6339963484","tag":{"natural":"tree"}},"type":"Feature"},
	{"geometry":{"coordinates":[10.21534,52.430079],"type":"Point"},"properties":{"osm_id":"6339963685","tag":{"natural":"tree"}},"type":"Feature"},
	{"geometry":{"coordinates":[10.253108,52.451301],"type":"Point"},"properties":{"osm_id":"6725955165","tag":{"natural":"tree"}},"type":"Feature"},
	{"geometry":{"coordinates":[10.24196,52.465337],"type":"Point"},"properties":{"osm_id":"6727498633","tag":{"natural":"tree"}},"type":"Feature"},
	{"geometry":{"coordinates":[10.255457,52.472146],"type":"Point"},"properties":{"osm_id":"6727520611","tag":{"natural":"tree"}},"type":"Feature"}
]
}
