{
"type": "FeatureCollection",
"features": [
	{"geometry":{"coordinates":[-2.990494,53.817591],"type":"Point"},"properties":{"name":"The Plough","osm_id":"69110621","tag":{"addr:city":"Blackpool","addr:postcode":"FY3 0BX","addr:street":"Chain Lane","addr:suburb":"Staining","amenity":"pub","fhrs:id":"102200"}},"type":"Feature"},
	{"geometry":{"coordinates":[-3.042378,53.825603],"type":"Point"},"properties":{"osm_id":"739655853","tag":{"amenity":"recycling","recycling:cans":"yes","recycling:glass":"yes","recycling:paper":"yes","recycling_type":"container"}},"type":"Feature"},
	{"geometry":{"coordinates":[-3.039547,53.852432],"type":"Point"},"properties":{"osm_id":"3536079383","tag":{"amenity":"waste_basket"}},"type":"Feature"},
	{"geometry":{"coordinates":[-3.02791,53.812525],"type":"Point"},"properties":{"osm_id":"3664723754","tag":{"amenity":"recycling","recycling:cans":"yes","recycling:glass":"no","recycling:glass_bottles":"yes","recycling:plastic_bottles":"yes","recycling_type":"container"}},"type":"Feature"}
]
}
