{
"type": "FeatureCollection",
"features": [
	{"geometry":{"coordinates":[-3.072232,37.162872],"type":"Point"},"properties":{"osm_id":"3709012425","tag":{"amenity":"recycling","recycling:cans":"yes","recycling:glass":"yes","recycling:glass_bottles":"yes","recycling:paper":"yes","recycling:plastic":"yes","recycling_type":"container"}},"type":"Feature"},
	{"geometry":{"coordinates":[-2.992854,37.210511],"type":"Point"},"properties":{"name":"Nivaplast Reciclados, S.L.","osm_id":"6524685240","tag":{"addr:city":"Dolar","addr:postcode":"18512","addr:street":"Camino del Medio","amenity":"recycling","opening_hours":"Mo-Fr 09:00-18:00","phone":"+34 644 96 03 00","recycling_type":"centre","website":"http://nivaplast.es/"}},"type":"Feature"}
]
}
