{
"type": "FeatureCollection",
"lastupdate": "2020-08-04T00:00:00Z",
"features": [
	{"geometry":{"coordinates":[-4.215114,47.797981],"type":"Point"},"properties":{"osm_id":"1413520217","tag":{"amenity":"waste_basket"}},"type":"Feature"},
	{"geometry":{"coordinates":[-4.214889,47.797977],"type":"Point"},"properties":{"osm_id":"1413520221","tag":{"amenity":"waste_basket"}},"type":"Feature"},
	{"geometry":{"coordinates":[-4.183322,47.803273],"type":"Point"},"properties":{"osm_id":"1539370667","tag":{"amenity":"recycling","recycling:glass":"yes","recycling:paper":"yes","recycling_type":"container"}},"type":"Feature"},
	{"geometry":{"coordinates":[-4.183291,47.803277],"type":"Point"},"properties":{"osm_id":"1539370670","tag":{"amenity":"waste_basket"}},"type":"Feature"},
	{"geometry":{"coordinates":[-4.185342,47.799835],"type":"Point"},"properties":{"osm_id":"1707464234","tag":{"amenity":"waste_basket"}},"type":"Feature"},
	{"geometry":{"coordinates":[-4.211939,47.795994],"type":"Point"},"properties":{"osm_id":"2855526738","tag":{"amenity":"waste_basket"}},"type":"Feature"},
	{"geometry":{"coordinates":[-4.211673,47.796131],"type":"Point"},"properties":{"osm_id":"2855526739","tag":{"amenity":"waste_basket"}},"type":"Feature"},
	{"geometry":{"coordinates":[-4.208507,47.801903],"type":"Point"},"properties":{"osm_id":"4018615360","tag":{"amenity":"recycling","recycling:glass":"yes","recycling_type":"container"}},"type":"Feature"},
	{"geometry":{"coordinates":[-4.196459,47.801231],"type":"Point"},"properties":{"osm_id":"4478978036","tag":{"amenity":"recycling","location":"underground","recycling:glass_bottles":"yes","recycling:paper":"yes","recycling:plastic_bottles":"yes","recycling_type":"container"}},"type":"Feature"},
	{"geometry":{"coordinates":[-4.189951,47.798878],"type":"Point"},"properties":{"osm_id":"6660514271","tag":{"amenity":"waste_basket"}},"type":"Feature"}
]
}
