{
"type": "FeatureCollection",
"features": [
	{"geometry":{"coordinates":[9.662915,50.253448],"type":"Point"},"properties":{"name":"Heilsbergeiche","osm_id":"1896451081","tag":{"denotation":"natural_monument","leaf_cycle":"deciduous","leaf_type":"broadleaved","natural":"tree"}},"type":"Feature"}
]
}
