{
"type": "FeatureCollection",
"lastupdate": "2020-08-03T00:00:00Z",
"features": [
	{"geometry":{"coordinates":[2.58026,51.097353],"type":"Point"},"properties":{"osm_id":"2302347212","tag":{"amenity":"recycling","recycling:glass_bottles":"yes","recycling_type":"container"}},"type":"Feature"},
	{"geometry":{"coordinates":[2.584038,51.100422],"type":"Point"},"properties":{"osm_id":"2302347214","tag":{"amenity":"recycling","recycling:glass_bottles":"yes","recycling_type":"container"}},"type":"Feature"},
	{"geometry":{"coordinates":[2.579035,51.096116],"type":"Point"},"properties":{"osm_id":"2302353583","tag":{"amenity":"waste_basket"}},"type":"Feature"},
	{"geometry":{"coordinates":[2.57898,51.095933],"type":"Point"},"properties":{"osm_id":"2302353584","tag":{"amenity":"waste_basket"}},"type":"Feature"},
	{"geometry":{"coordinates":[2.579836,51.09628],"type":"Point"},"properties":{"osm_id":"2302353735","tag":{"amenity":"waste_basket"}},"type":"Feature"},
	{"geometry":{"coordinates":[2.583397,51.099188],"type":"Point"},"properties":{"osm_id":"2914002783","tag":{"amenity":"recycling","recycling:glass_bottles":"yes","recycling_type":"container"}},"type":"Feature"},
	{"geometry":{"coordinates":[2.581135,51.080546],"type":"Point"},"properties":{"osm_id":"2994226582","tag":{"amenity":"recycling","recycling:glass":"yes","recycling_type":"container"}},"type":"Feature"},
	{"geometry":{"coordinates":[2.581166,51.080559],"type":"Point"},"properties":{"osm_id":"2994226584","tag":{"amenity":"recycling","recycling:glass":"yes","recycling_type":"container"}},"type":"Feature"},
	{"geometry":{"coordinates":[2.565805,51.094696],"type":"Point"},"properties":{"osm_id":"3051842913","tag":{"amenity":"waste_basket"}},"type":"Feature"},
	{"geometry":{"coordinates":[2.621496,51.115075],"type":"Point"},"properties":{"osm_id":"3911321371","tag":{"amenity":"recycling","recycling:cans":"no","recycling:clothes":"no","recycling:glass":"no","recycling:glass_bottles":"yes","recycling:paper":"no","recycling:plastic":"no"}},"type":"Feature"},
	{"geometry":{"coordinates":[2.605669,51.109616],"type":"Point"},"properties":{"osm_id":"4335997722","tag":{"amenity":"waste_basket"}},"type":"Feature"},
	{"geometry":{"coordinates":[2.609532,51.11082],"type":"Point"},"properties":{"osm_id":"4336038076","tag":{"amenity":"recycling"}},"type":"Feature"},
	{"geometry":{"coordinates":[2.609109,51.111302],"type":"Point"},"properties":{"osm_id":"4336063439","tag":{"amenity":"waste_basket"}},"type":"Feature"},
	{"geometry":{"coordinates":[2.608644,51.110734],"type":"Point"},"properties":{"osm_id":"4336754004","tag":{"amenity":"waste_basket"}},"type":"Feature"},
	{"geometry":{"coordinates":[2.583541,51.095073],"type":"Point"},"properties":{"barrier":"gate","osm_id":"4760637651"},"type":"Feature"},
	{"geometry":{"coordinates":[2.597735,51.103241],"type":"Point"},"properties":{"osm_id":"4881645979","tag":{"amenity":"recycling","opening_hours":"24/7","recycling:glass_bottles":"yes","recycling:green_waste":"yes","recycling_type":"container"}},"type":"Feature"},
	{"geometry":{"coordinates":[2.617791,51.103735],"type":"Point"},"properties":{"osm_id":"5172717735","tag":{"addr:city":"Koksijde","addr:postcode":"8670","addr:street":"Strandlaan","amenity":"waste_basket","waste":"dog_excrement"}},"type":"Feature"},
	{"geometry":{"coordinates":[2.617565,51.103649],"type":"Point"},"properties":{"osm_id":"5172717736","tag":{"addr:city":"Koksijde","addr:postcode":"8670","addr:street":"Willem Elsschotlaan","amenity":"recycling","recycling:glass":"yes","recycling_type":"container"}},"type":"Feature"},
	{"geometry":{"coordinates":[2.60165,51.105812],"type":"Point"},"properties":{"osm_id":"7612386078","tag":{"amenity":"waste_basket"}},"type":"Feature"},
	{"geometry":{"coordinates":[2.601598,51.105788],"type":"Point"},"properties":{"osm_id":"7612386079","tag":{"amenity":"recycling","recycling:glass_bottles":"yes","recycling_type":"container"}},"type":"Feature"},
	{"geometry":{"coordinates":[2.601582,51.105781],"type":"Point"},"properties":{"osm_id":"7612386080","tag":{"amenity":"recycling","recycling:glass_bottles":"yes","recycling_type":"container"}},"type":"Feature"},
	{"geometry":{"coordinates":[2.601565,51.105775],"type":"Point"},"properties":{"osm_id":"7612386081","tag":{"amenity":"waste_basket","location":"underground"}},"type":"Feature"},
	{"geometry":{"coordinates":[2.627537,51.117201],"type":"Point"},"properties":{"osm_id":"7699634765","tag":{"amenity":"recycling","location":"underground","recycling:waste":"yes","recycling_type":"container"}},"type":"Feature"}
]
}
