{
"type": "FeatureCollection",
"lastupdate": "2020-08-01T00:00:00Z",
"features": [
	{"geometry":{"coordinates":[2.622057,39.709555],"type":"Point"},"properties":{"osm_id":"2081407746","tag":{"amenity":"waste_basket"}},"type":"Feature"},
	{"geometry":{"coordinates":[2.622046,39.709576],"type":"Point"},"properties":{"osm_id":"2081407753","tag":{"amenity":"waste_basket"}},"type":"Feature"},
	{"geometry":{"coordinates":[2.618446,39.711914],"type":"Point"},"properties":{"name":"Punt Verd","osm_id":"2441307642","tag":{"amenity":"recycling","recycling:cooking_oil":"yes","recycling:glass":"yes","recycling:paper":"yes","recycling:plastic":"yes"}},"type":"Feature"},
	{"geometry":{"coordinates":[2.618411,39.712053],"type":"Point"},"properties":{"osm_id":"2441307643","tag":{"amenity":"recycling","recycling:clothes":"yes","recycling:glass":"yes"}},"type":"Feature"},
	{"geometry":{"coordinates":[2.617267,39.712669],"type":"Point"},"properties":{"osm_id":"2663261791","tag":{"amenity":"recycling"}},"type":"Feature"},
	{"geometry":{"coordinates":[2.620909,39.710963],"type":"Point"},"properties":{"osm_id":"2971473373","tag":{"amenity":"recycling","recycling:clothes":"yes","recycling:glass":"yes","recycling:paper":"yes"}},"type":"Feature"}
]
}
