{
"type": "FeatureCollection",
"features": [
	{"geometry":{"coordinates":[2.622057,39.709556],"type":"Point"},"properties":{"osm_id":"2081407746","tag":{"amenity":"waste_basket"}},"type":"Feature"},
	{"geometry":{"coordinates":[2.622047,39.709577],"type":"Point"},"properties":{"osm_id":"2081407753","tag":{"amenity":"waste_basket"}},"type":"Feature"},
	{"geometry":{"coordinates":[2.618447,39.711915],"type":"Point"},"properties":{"name":"Punt Verd","osm_id":"2441307642","tag":{"amenity":"recycling","recycling:cooking_oil":"yes","recycling:glass":"yes","recycling:paper":"yes","recycling:plastic":"yes"}},"type":"Feature"},
	{"geometry":{"coordinates":[2.618411,39.712054],"type":"Point"},"properties":{"osm_id":"2441307643","tag":{"amenity":"recycling","recycling:clothes":"yes","recycling:glass":"yes"}},"type":"Feature"},
	{"geometry":{"coordinates":[2.617267,39.712669],"type":"Point"},"properties":{"osm_id":"2663261791","tag":{"amenity":"recycling"}},"type":"Feature"},
	{"geometry":{"coordinates":[2.620909,39.710964],"type":"Point"},"properties":{"osm_id":"2971473373","tag":{"amenity":"recycling","recycling:clothes":"yes","recycling:glass":"yes","recycling:paper":"yes"}},"type":"Feature"}
]
}
