{
"type": "FeatureCollection",
"lastupdate": "2020-07-31T00:00:00Z",
"features": [
	{"geometry":{"coordinates":[-8.892163,39.861829],"type":"Point"},"properties":{"name":"Ecoponto","osm_id":"2912664422","tag":{"amenity":"recycling"}},"type":"Feature"},
	{"geometry":{"coordinates":[-8.93422,39.868121],"type":"Point"},"properties":{"osm_id":"4399045829","tag":{"amenity":"waste_basket"}},"type":"Feature"},
	{"geometry":{"coordinates":[-8.926365,39.869597],"type":"Point"},"properties":{"osm_id":"4399045878","tag":{"amenity":"recycling","operator":"Valorlis","recycling:glass":"yes","recycling_type":"container"}},"type":"Feature"},
	{"geometry":{"coordinates":[-8.926391,39.869597],"type":"Point"},"properties":{"osm_id":"4399045879","tag":{"amenity":"recycling","operator":"Valorlis","recycling:cardboard":"yes","recycling:paper":"yes","recycling_type":"container"}},"type":"Feature"},
	{"geometry":{"coordinates":[-8.926338,39.869598],"type":"Point"},"properties":{"osm_id":"4399045880","tag":{"amenity":"recycling","operator":"Valorlis","recycling:cans":"yes","recycling:plastic":"yes","recycling:plastic_bottles":"yes","recycling_type":"container"}},"type":"Feature"}
]
}
