{
"type": "FeatureCollection",
"features": [
	{"geometry":{"coordinates":[-24.320262,16.668512],"type":"Point"},"properties":{"osm_id":"6797312758","tag":{"natural":"tree"}},"type":"Feature"},
	{"geometry":{"coordinates":[-24.320322,16.668478],"type":"Point"},"properties":{"osm_id":"6797312759","tag":{"natural":"tree"}},"type":"Feature"},
	{"geometry":{"coordinates":[-24.320247,16.668417],"type":"Point"},"properties":{"osm_id":"6797312760","tag":{"natural":"tree"}},"type":"Feature"},
	{"geometry":{"coordinates":[-24.320284,16.668339],"type":"Point"},"properties":{"osm_id":"6797312761","tag":{"natural":"tree"}},"type":"Feature"},
	{"geometry":{"coordinates":[-24.320421,16.668366],"type":"Point"},"properties":{"osm_id":"6797312762","tag":{"natural":"tree"}},"type":"Feature"},
	{"geometry":{"coordinates":[-24.32225,16.669825],"type":"Point"},"properties":{"osm_id":"6814470400","tag":{"natural":"tree"}},"type":"Feature"},
	{"geometry":{"coordinates":[-24.322602,16.66975],"type":"Point"},"properties":{"osm_id":"6814470416","tag":{"natural":"tree"}},"type":"Feature"},
	{"geometry":{"coordinates":[-24.320971,16.647307],"type":"Point"},"properties":{"name":"palmeira","osm_id":"6828272885","tag":{"natural":"tree"}},"type":"Feature"},
	{"geometry":{"coordinates":[-24.326164,16.647169],"type":"Point"},"properties":{"name":"palmeira","osm_id":"6951040058","tag":{"denotation":"single","natural":"tree"}},"type":"Feature"},
	{"geometry":{"coordinates":[-24.328643,16.646679],"type":"Point"},"properties":{"osm_id":"6955330371","tag":{"natural":"tree"}},"type":"Feature"},
	{"geometry":{"coordinates":[-24.328756,16.646687],"type":"Point"},"properties":{"osm_id":"6955330372","tag":{"natural":"tree"}},"type":"Feature"},
	{"geometry":{"coordinates":[-24.330617,16.646502],"type":"Point"},"properties":{"osm_id":"6955342851","tag":{"natural":"tree"}},"type":"Feature"},
	{"geometry":{"coordinates":[-24.330507,16.646508],"type":"Point"},"properties":{"osm_id":"6955342852","tag":{"natural":"tree"}},"type":"Feature"},
	{"geometry":{"coordinates":[-24.329507,16.644537],"type":"Point"},"properties":{"osm_id":"6955342919","tag":{"natural":"tree"}},"type":"Feature"},
	{"geometry":{"coordinates":[-24.329419,16.64454],"type":"Point"},"properties":{"osm_id":"6955342920","tag":{"natural":"tree"}},"type":"Feature"},
	{"geometry":{"coordinates":[-24.329528,16.644391],"type":"Point"},"properties":{"osm_id":"6955355695","tag":{"natural":"tree"}},"type":"Feature"},
	{"geometry":{"coordinates":[-24.333459,16.647712],"type":"Point"},"properties":{"osm_id":"6955544624","tag":{"natural":"tree"}},"type":"Feature"},
	{"geometry":{"coordinates":[-24.333195,16.647567],"type":"Point"},"properties":{"osm_id":"6955544625","tag":{"natural":"tree"}},"type":"Feature"},
	{"geometry":{"coordinates":[-24.326957,16.647932],"type":"Point"},"properties":{"osm_id":"6955666665","tag":{"natural":"tree"}},"type":"Feature"},
	{"geometry":{"coordinates":[-24.32689,16.647974],"type":"Point"},"properties":{"osm_id":"6955666666","tag":{"natural":"tree"}},"type":"Feature"},
	{"geometry":{"coordinates":[-24.317095,16.658885],"type":"Point"},"properties":{"osm_id":"6957982443","tag":{"natural":"tree"}},"type":"Feature"},
	{"geometry":{"coordinates":[-24.316111,16.658976],"type":"Point"},"properties":{"osm_id":"6958015585","tag":{"natural":"tree"}},"type":"Feature"},
	{"geometry":{"coordinates":[-24.31577,16.659573],"type":"Point"},"properties":{"osm_id":"6958015586","tag":{"natural":"tree"}},"type":"Feature"},
	{"geometry":{"coordinates":[-24.31619,16.65855],"type":"Point"},"properties":{"osm_id":"6958015587","tag":{"natural":"tree"}},"type":"Feature"},
	{"geometry":{"coordinates":[-24.316884,16.655125],"type":"Point"},"properties":{"osm_id":"6958015644","tag":{"natural":"tree"}},"type":"Feature"},
	{"geometry":{"coordinates":[-24.316927,16.654738],"type":"Point"},"properties":{"osm_id":"6958015645","tag":{"natural":"tree"}},"type":"Feature"}
]
}
