{
"type": "FeatureCollection",
"features": [
	{"geometry":{"coordinates":[-74.674089,40.92514],"type":"Point"},"properties":{"barrier":"gate","osm_id":"475238249"},"type":"Feature"},
	{"geometry":{"coordinates":[-74.632474,40.926795],"type":"Point"},"properties":{"name":"Mount Arlington Dump","osm_id":"9124956621","tag":{"amenity":"recycling","recycling_type":"centre"}},"type":"Feature"}
]
}
