{
"type": "FeatureCollection",
"features": [
	{"geometry":{"coordinates":[-117.431664,34.64755],"type":"Point"},"properties":{"name":"Joey's Tree","osm_id":"5904414766","tag":{"denotation":"landmark","leaf_cycle":"evergreen","leaf_type":"needleleaved","natural":"tree"}},"type":"Feature"}
]
}
