{
"type": "FeatureCollection",
"features": [
	{"geometry":{"coordinates":[-117.431663,34.647549],"type":"Point"},"properties":{"name":"Joey's Tree","osm_id":"5904414766","tag":{"denotation":"landmark","leaf_cycle":"evergreen","leaf_type":"needleleaved","natural":"tree"}},"type":"Feature"}
]
}
