{
"type": "FeatureCollection",
"features": [
	{"geometry":{"coordinates":[29.904513,-1.948434],"type":"Point"},"properties":{"name":"Five Trees","osm_id":"8441496545","tag":{"description":"Said to be the center point of Rwanda during colonial times","natural":"tree"}},"type":"Feature"}
]
}
