{
"type": "FeatureCollection",
"lastupdate": "2020-08-05T00:00:00Z",
"features": [
	{"geometry":{"coordinates":[7.227727,62.253295],"type":"Point"},"properties":{"osm_id":"5555190869","tag":{"access":"permissive","amenity":"recycling","description":"Norddal b\u00e5thamn","recycling:glass_bottles":"yes","recycling:paper":"yes","recycling:plastic_packaging":"yes","recycling:waste":"yes","recycling_type":"container","ref:sortere":"19759"}},"type":"Feature"},
	{"geometry":{"coordinates":[7.259839,62.237217],"type":"Point"},"properties":{"osm_id":"5555208857","tag":{"access":"permissive","amenity":"recycling","description":"Engeset","recycling:glass_bottles":"yes","recycling:paper":"yes","recycling:plastic_packaging":"yes","recycling:waste":"yes","recycling_type":"container","ref:sortere":"20684"}},"type":"Feature"},
	{"geometry":{"coordinates":[7.236774,62.253408],"type":"Point"},"properties":{"osm_id":"6195508587","tag":{"amenity":"recycling","description":"Dalsbygda","recycling:batteries":"yes","recycling:clothes":"yes","recycling:electrical_items":"yes","recycling:glass":"yes","recycling:hazardous_waste":"yes","recycling:metal":"yes","recycling:paper":"yes","recycling:plasterboard":"yes","recycling:plastic":"yes","recycling:plastic_packaging":"yes","recycling:polystyrene_foam":"yes","recycling:rubble":"yes","recycling:scrap_metal":"yes","recycling:second_hand":"yes","recycling:waste":"yes","recycling:wood":"yes","recycling_type":"container","ref:sortere":"43","website":"http://arim.no"}},"type":"Feature"}
]
}
