{
"type": "FeatureCollection",
"lastupdate": "2020-08-04T00:00:00Z",
"features": [
	{"geometry":{"coordinates":[7.271504,47.239137],"type":"Point"},"properties":{"osm_id":"1870945918","tag":{"amenity":"recycling","recycling:aluminium_cans":"yes","recycling:aluminium_tins":"yes","recycling:cans":"yes","recycling:clothes":"yes","recycling:glass_bottles":"yes","recycling:small_metal":"yes","recycling_type":"container"}},"type":"Feature"},
	{"geometry":{"coordinates":[7.23334,47.236301],"type":"Point"},"properties":{"name":"Point Rouge Vox Dei Recycling","osm_id":"1981546107","tag":{"amenity":"recycling","recycling_type":"centre"}},"type":"Feature"},
	{"geometry":{"coordinates":[7.224756,47.228998],"type":"Point"},"properties":{"osm_id":"6217572675","tag":{"amenity":"waste_basket","waste":"dog_excrement"}},"type":"Feature"},
	{"geometry":{"coordinates":[7.260952,47.237951],"type":"Point"},"properties":{"osm_id":"7640439611","tag":{"amenity":"waste_basket"}},"type":"Feature"},
	{"geometry":{"coordinates":[7.249906,47.241364],"type":"Point"},"properties":{"osm_id":"7640439616","tag":{"amenity":"waste_basket"}},"type":"Feature"},
	{"geometry":{"coordinates":[7.253719,47.239112],"type":"Point"},"properties":{"osm_id":"7640455469","tag":{"amenity":"waste_basket"}},"type":"Feature"},
	{"geometry":{"coordinates":[7.255141,47.241061],"type":"Point"},"properties":{"osm_id":"7640490435","tag":{"amenity":"waste_basket","waste":"dog_excrement"}},"type":"Feature"},
	{"geometry":{"coordinates":[7.260503,47.243541],"type":"Point"},"properties":{"osm_id":"7640490453","tag":{"amenity":"waste_basket"}},"type":"Feature"},
	{"geometry":{"coordinates":[7.263576,47.244852],"type":"Point"},"properties":{"osm_id":"7640490458","tag":{"amenity":"waste_basket"}},"type":"Feature"},
	{"geometry":{"coordinates":[7.263735,47.244922],"type":"Point"},"properties":{"osm_id":"7640490459","tag":{"amenity":"waste_basket"}},"type":"Feature"},
	{"geometry":{"coordinates":[7.269877,47.243662],"type":"Point"},"properties":{"osm_id":"7640490464","tag":{"amenity":"waste_basket"}},"type":"Feature"},
	{"geometry":{"coordinates":[7.271464,47.243138],"type":"Point"},"properties":{"osm_id":"7640490467","tag":{"amenity":"waste_basket"}},"type":"Feature"}
]
}
