{
"type": "FeatureCollection",
"features": [
	{"geometry":{"coordinates":[11.503778,53.548387],"type":"Point"},"properties":{"osm_id":"312391061","tag":{"natural":"tree"}},"type":"Feature"},
	{"geometry":{"coordinates":[11.446908,53.560866],"type":"Point"},"properties":{"osm_id":"1501635764","tag":{"natural":"tree"}},"type":"Feature"},
	{"geometry":{"coordinates":[11.447169,53.560919],"type":"Point"},"properties":{"osm_id":"1501635768","tag":{"natural":"tree"}},"type":"Feature"},
	{"geometry":{"coordinates":[11.444902,53.561025],"type":"Point"},"properties":{"osm_id":"1501635772","tag":{"natural":"tree"}},"type":"Feature"},
	{"geometry":{"coordinates":[11.447415,53.561034],"type":"Point"},"properties":{"osm_id":"1501635773","tag":{"natural":"tree"}},"type":"Feature"},
	{"geometry":{"coordinates":[11.447214,53.561348],"type":"Point"},"properties":{"osm_id":"1501635801","tag":{"natural":"tree"}},"type":"Feature"},
	{"geometry":{"coordinates":[11.448273,53.561415],"type":"Point"},"properties":{"osm_id":"1501635813","tag":{"natural":"tree"}},"type":"Feature"},
	{"geometry":{"coordinates":[11.446021,53.561725],"type":"Point"},"properties":{"osm_id":"1501635846","tag":{"natural":"tree"}},"type":"Feature"},
	{"geometry":{"coordinates":[11.447274,53.561783],"type":"Point"},"properties":{"osm_id":"1501635847","tag":{"natural":"tree"}},"type":"Feature"},
	{"geometry":{"coordinates":[11.451517,53.561911],"type":"Point"},"properties":{"osm_id":"1501635849","tag":{"natural":"tree"}},"type":"Feature"},
	{"geometry":{"coordinates":[11.44702,53.561933],"type":"Point"},"properties":{"osm_id":"1501635850","tag":{"natural":"tree"}},"type":"Feature"},
	{"geometry":{"coordinates":[11.447102,53.56246],"type":"Point"},"properties":{"osm_id":"1501635910","tag":{"natural":"tree"}},"type":"Feature"},
	{"geometry":{"coordinates":[11.472847,53.588446],"type":"Point"},"properties":{"osm_id":"2274982484","tag":{"denotation":"landmark","natural":"tree","type":"oak"}},"type":"Feature"},
	{"geometry":{"coordinates":[11.510565,53.549357],"type":"Point"},"properties":{"name":"Trompetenbaum","osm_id":"2430354970","tag":{"denotation":"landmark","height":"10","leaf_type":"broadleaved","natural":"tree"}},"type":"Feature"},
	{"geometry":{"coordinates":[11.510838,53.549512],"type":"Point"},"properties":{"name":"Birke","osm_id":"2432118074","tag":{"denotation":"landmark","height":"11","natural":"tree"}},"type":"Feature"},
	{"geometry":{"coordinates":[11.510883,53.549498],"type":"Point"},"properties":{"name":"Birke","osm_id":"2432118076","tag":{"height":"13","natural":"tree"}},"type":"Feature"},
	{"geometry":{"coordinates":[11.510419,53.549397],"type":"Point"},"properties":{"name":"Gingko","osm_id":"2432133825","tag":{"height":"3","natural":"tree"}},"type":"Feature"},
	{"geometry":{"coordinates":[11.510401,53.549315],"type":"Point"},"properties":{"name":"Vogelbeere","osm_id":"2432138540","tag":{"height":"4","natural":"tree"}},"type":"Feature"},
	{"geometry":{"coordinates":[11.503029,53.546158],"type":"Point"},"properties":{"osm_id":"4109996053","tag":{"natural":"tree"}},"type":"Feature"},
	{"geometry":{"coordinates":[11.5029,53.546166],"type":"Point"},"properties":{"osm_id":"4109996054","tag":{"natural":"tree"}},"type":"Feature"},
	{"geometry":{"coordinates":[11.499089,53.552203],"type":"Point"},"properties":{"osm_id":"4109996069","tag":{"natural":"tree"}},"type":"Feature"},
	{"geometry":{"coordinates":[11.499156,53.552279],"type":"Point"},"properties":{"osm_id":"4109996073","tag":{"natural":"tree"}},"type":"Feature"},
	{"geometry":{"coordinates":[11.498995,53.552324],"type":"Point"},"properties":{"osm_id":"4109996075","tag":{"natural":"tree"}},"type":"Feature"},
	{"geometry":{"coordinates":[11.499097,53.552341],"type":"Point"},"properties":{"osm_id":"4109996078","tag":{"natural":"tree"}},"type":"Feature"},
	{"geometry":{"coordinates":[11.471928,53.585077],"type":"Point"},"properties":{"osm_id":"6588085207","tag":{"natural":"tree"}},"type":"Feature"},
	{"geometry":{"coordinates":[11.480646,53.592287],"type":"Point"},"properties":{"osm_id":"6589670206","tag":{"natural":"tree"}},"type":"Feature"},
	{"geometry":{"coordinates":[11.48072,53.592101],"type":"Point"},"properties":{"osm_id":"6589670207","tag":{"natural":"tree"}},"type":"Feature"}
]
}
