{
"type": "FeatureCollection",
"features": [
	{"geometry":{"coordinates":[11.46467,48.678525],"type":"Point"},"properties":{"name":"Dorfeiche","osm_id":"1015559529","tag":{"natural":"tree"}},"type":"Feature"},
	{"geometry":{"coordinates":[11.500684,48.660832],"type":"Point"},"properties":{"osm_id":"2836507269","tag":{"natural":"tree"}},"type":"Feature"},
	{"geometry":{"coordinates":[11.459894,48.640339],"type":"Point"},"properties":{"osm_id":"6592995777","tag":{"natural":"tree"}},"type":"Feature"}
]
}
