{
"type": "FeatureCollection",
"features": [
	{"geometry":{"coordinates":[11.46467,48.678524],"type":"Point"},"properties":{"name":"Dorfeiche","osm_id":"1015559529","tag":{"natural":"tree"}},"type":"Feature"},
	{"geometry":{"coordinates":[11.500684,48.660831],"type":"Point"},"properties":{"osm_id":"2836507269","tag":{"natural":"tree"}},"type":"Feature"},
	{"geometry":{"coordinates":[11.459893,48.640338],"type":"Point"},"properties":{"osm_id":"6592995777","tag":{"natural":"tree"}},"type":"Feature"},
	{"geometry":{"coordinates":[11.502443,48.649776],"type":"Point"},"properties":{"osm_id":"8262496823","tag":{"natural":"tree"}},"type":"Feature"},
	{"geometry":{"coordinates":[11.502982,48.649822],"type":"Point"},"properties":{"osm_id":"8262496829","tag":{"natural":"tree"}},"type":"Feature"},
	{"geometry":{"coordinates":[11.502126,48.649714],"type":"Point"},"properties":{"osm_id":"8262496833","tag":{"natural":"tree"}},"type":"Feature"},
	{"geometry":{"coordinates":[11.503309,48.649831],"type":"Point"},"properties":{"osm_id":"8262496834","tag":{"natural":"tree"}},"type":"Feature"},
	{"geometry":{"coordinates":[11.503451,48.649841],"type":"Point"},"properties":{"osm_id":"8262496836","tag":{"natural":"tree"}},"type":"Feature"},
	{"geometry":{"coordinates":[11.450075,48.633261],"type":"Point"},"properties":{"osm_id":"8932911417","tag":{"natural":"tree"}},"type":"Feature"},
	{"geometry":{"coordinates":[11.46007,48.679423],"type":"Point"},"properties":{"osm_id":"9050778560","tag":{"natural":"tree"}},"type":"Feature"}
]
}
