{
"type": "FeatureCollection",
"features": [
	{"geometry":{"coordinates":[11.46467,48.678524],"type":"Point"},"properties":{"name":"Dorfeiche","osm_id":"1015559529","tag":{"natural":"tree"}},"type":"Feature"},
	{"geometry":{"coordinates":[11.500684,48.660831],"type":"Point"},"properties":{"osm_id":"2836507269","tag":{"natural":"tree"}},"type":"Feature"},
	{"geometry":{"coordinates":[11.459893,48.640338],"type":"Point"},"properties":{"osm_id":"6592995777","tag":{"natural":"tree"}},"type":"Feature"}
]
}
