{
"type": "FeatureCollection",
"features": [
	{"geometry":{"coordinates":[11.451442,3.417949],"type":"Point"},"properties":{"name":"Kossipo","osm_id":"2099675090","tag":{"height":"82","name:botanical":"Entandrophragma candolei","natural":"tree","tourism":"attraction"}},"type":"Feature"}
]
}
