{
"type": "FeatureCollection",
"lastupdate": "2020-08-05T00:00:00Z",
"features": [
	{"geometry":{"coordinates":[2.476055,49.456448],"type":"Point"},"properties":{"name":"Poubelle","osm_id":"3016584708","tag":{"amenity":"waste_basket"}},"type":"Feature"},
	{"geometry":{"coordinates":[2.490098,49.471669],"type":"Point"},"properties":{"osm_id":"5034911968","tag":{"amenity":"recycling","recycling_type":"container"}},"type":"Feature"},
	{"geometry":{"coordinates":[2.496857,49.486131],"type":"Point"},"properties":{"name":"3","osm_id":"5034948570","tag":{"amenity":"recycling","recycling_type":"container"}},"type":"Feature"}
]
}
