{
"type": "FeatureCollection",
"features": [
	{"geometry":{"coordinates":[2.518312,41.814523],"type":"Point"},"properties":{"name":"Mini deixalleria","osm_id":"5831644985","tag":{"amenity":"recycling","recycling_type":"container"}},"type":"Feature"},
	{"geometry":{"coordinates":[2.511472,41.777104],"type":"Point"},"properties":{"osm_id":"6622015085","tag":{"amenity":"recycling","recycling:cans":"yes","recycling:cardboard":"yes","recycling:glass_bottles":"yes","recycling:paper":"yes","recycling:plastic":"yes","recycling:plastic_packaging":"yes","recycling:waste":"yes","recycling_type":"container"}},"type":"Feature"}
]
}
