{
"type": "FeatureCollection",
"features": [
	{"geometry":{"coordinates":[24.618076,60.29692],"type":"Point"},"properties":{"osm_id":"449072228","tag":{"amenity":"waste_basket"}},"type":"Feature"},
	{"geometry":{"coordinates":[24.691489,60.316285],"type":"Point"},"properties":{"osm_id":"1846918230","tag":{"amenity":"waste_basket"}},"type":"Feature"},
	{"geometry":{"coordinates":[24.693087,60.314498],"type":"Point"},"properties":{"osm_id":"2335353219","tag":{"amenity":"waste_basket"}},"type":"Feature"},
	{"geometry":{"coordinates":[24.695064,60.313844],"type":"Point"},"properties":{"osm_id":"2335597824","tag":{"amenity":"waste_basket"}},"type":"Feature"},
	{"geometry":{"coordinates":[24.694855,60.314056],"type":"Point"},"properties":{"osm_id":"2335597904","tag":{"amenity":"waste_basket"}},"type":"Feature"},
	{"geometry":{"coordinates":[24.6949,60.313367],"type":"Point"},"properties":{"osm_id":"2335597915","tag":{"amenity":"waste_basket"}},"type":"Feature"},
	{"geometry":{"coordinates":[24.663892,60.317653],"type":"Point"},"properties":{"name":"Kaitalammensuo","osm_id":"5615177924","tag":{"amenity":"recycling","recycling:organic":"Yes"}},"type":"Feature"}
]
}
