{
"type": "FeatureCollection",
"lastupdate": "2020-08-04T00:00:00Z",
"features": [
	{"geometry":{"coordinates":[24.618075,60.296919],"type":"Point"},"properties":{"osm_id":"449072228","tag":{"amenity":"waste_basket"}},"type":"Feature"},
	{"geometry":{"coordinates":[24.691488,60.316285],"type":"Point"},"properties":{"osm_id":"1846918230","tag":{"amenity":"waste_basket"}},"type":"Feature"},
	{"geometry":{"coordinates":[24.693087,60.314498],"type":"Point"},"properties":{"osm_id":"2335353219","tag":{"amenity":"waste_basket"}},"type":"Feature"},
	{"geometry":{"coordinates":[24.695064,60.313843],"type":"Point"},"properties":{"osm_id":"2335597824","tag":{"amenity":"waste_basket"}},"type":"Feature"},
	{"geometry":{"coordinates":[24.694855,60.314056],"type":"Point"},"properties":{"osm_id":"2335597904","tag":{"amenity":"waste_basket"}},"type":"Feature"},
	{"geometry":{"coordinates":[24.6949,60.313366],"type":"Point"},"properties":{"osm_id":"2335597915","tag":{"amenity":"waste_basket"}},"type":"Feature"},
	{"geometry":{"coordinates":[24.663891,60.317652],"type":"Point"},"properties":{"name":"Kaitalammensuo","osm_id":"5615177924","tag":{"amenity":"recycling","recycling:organic":"Yes"}},"type":"Feature"}
]
}
