{
"type": "FeatureCollection",
"features": [
	{"geometry":{"coordinates":[24.618075,60.296919],"type":"Point"},"properties":{"osm_id":"449072228","tag":{"amenity":"waste_basket"}},"type":"Feature"},
	{"geometry":{"coordinates":[24.691488,60.316285],"type":"Point"},"properties":{"osm_id":"1846918230","tag":{"amenity":"waste_basket","check_date":"2021-07-11"}},"type":"Feature"},
	{"geometry":{"coordinates":[24.6949,60.313366],"type":"Point"},"properties":{"osm_id":"2335597915","tag":{"amenity":"waste_basket","check_date":"2021-07-11"}},"type":"Feature"},
	{"geometry":{"coordinates":[24.663891,60.317652],"type":"Point"},"properties":{"name":"Kaitalammensuo","osm_id":"5615177924","tag":{"amenity":"recycling","recycling:organic":"yes","recycling_type":"container"}},"type":"Feature"}
]
}
