{
"type": "FeatureCollection",
"features": [
	{"geometry":{"coordinates":[24.082706,60.385054],"type":"Point"},"properties":{"osm_id":"8641363930","tag":{"amenity":"recycling","location":"overground","opening_hours":"24/7","recycling:glass_bottles":"yes","recycling:paper":"yes","recycling_type":"container"}},"type":"Feature"}
]
}
