{
"type": "FeatureCollection",
"features": [
	{"geometry":{"coordinates":[16.086133,52.553835],"type":"Point"},"properties":{"name":"Lipa","osm_id":"4571877114","tag":{"leaf_cycle":"deciduous","leaf_type":"broadleaved","natural":"tree"}},"type":"Feature"},
	{"geometry":{"coordinates":[16.086326,52.553861],"type":"Point"},"properties":{"name":"Lipa","osm_id":"4571877115","tag":{"leaf_cycle":"deciduous","leaf_type":"broadleaved","natural":"tree"}},"type":"Feature"},
	{"geometry":{"coordinates":[16.08646,52.553873],"type":"Point"},"properties":{"name":"Lipa","osm_id":"4571877116","tag":{"leaf_cycle":"deciduous","leaf_type":"broadleaved","natural":"tree"}},"type":"Feature"},
	{"geometry":{"coordinates":[16.086791,52.553885],"type":"Point"},"properties":{"name":"Lipa","osm_id":"4571877117","tag":{"leaf_cycle":"deciduous","leaf_type":"broadleaved","natural":"tree"}},"type":"Feature"},
	{"geometry":{"coordinates":[16.086885,52.553874],"type":"Point"},"properties":{"name":"Lipa","osm_id":"4571877118","tag":{"leaf_cycle":"deciduous","leaf_type":"broadleaved","natural":"tree"}},"type":"Feature"},
	{"geometry":{"coordinates":[16.086977,52.553798],"type":"Point"},"properties":{"name":"Lipa","osm_id":"4571877119","tag":{"leaf_cycle":"deciduous","leaf_type":"broadleaved","natural":"tree"}},"type":"Feature"},
	{"geometry":{"coordinates":[16.086692,52.553666],"type":"Point"},"properties":{"name":"Lipa","osm_id":"4571877120","tag":{"leaf_cycle":"deciduous","leaf_type":"broadleaved","natural":"tree"}},"type":"Feature"},
	{"geometry":{"coordinates":[16.086462,52.553633],"type":"Point"},"properties":{"name":"Lipa","osm_id":"4571877121","tag":{"leaf_cycle":"deciduous","leaf_type":"broadleaved","natural":"tree"}},"type":"Feature"},
	{"geometry":{"coordinates":[16.086147,52.55363],"type":"Point"},"properties":{"name":"Lipa","osm_id":"4571877122","tag":{"leaf_cycle":"deciduous","leaf_type":"broadleaved","natural":"tree"}},"type":"Feature"},
	{"geometry":{"coordinates":[16.111338,52.582137],"type":"Point"},"properties":{"osm_id":"5962635132","tag":{"denotation":"natural_monument","leaf_cycle":"deciduous","leaf_type":"broadleaved","natural":"tree"}},"type":"Feature"}
]
}
