{
"type": "FeatureCollection",
"features": [
	{"geometry":{"coordinates":[-86.281416,13.446897],"type":"Point"},"properties":{"name":"Arbol de Balona","osm_id":"8195553280","tag":{"natural":"tree"}},"type":"Feature"},
	{"geometry":{"coordinates":[-86.278427,13.441528],"type":"Point"},"properties":{"name":"Arbol de Matapalo","osm_id":"8195553308","tag":{"natural":"tree"}},"type":"Feature"}
]
}
