{
"type": "FeatureCollection",
"lastupdate": "2020-07-31T00:00:00Z",
"features": [
	{"geometry":{"coordinates":[10.54198,50.00068],"type":"Point"},"properties":{"name":"Wertstoffhof","osm_id":"1847055643","tag":{"amenity":"recycling","recycling_type":"centre"}},"type":"Feature"},
	{"geometry":{"coordinates":[10.49962,49.962577],"type":"Point"},"properties":{"osm_id":"2517048669","tag":{"amenity":"recycling","recycling:glass":"yes","recycling_type":"container"}},"type":"Feature"},
	{"geometry":{"coordinates":[10.545576,49.994525],"type":"Point"},"properties":{"osm_id":"2835253005","tag":{"amenity":"recycling","recycling:glass":"yes","recycling:glass_bottles":"yes","recycling_type":"container"}},"type":"Feature"},
	{"geometry":{"coordinates":[10.473362,49.96769],"type":"Point"},"properties":{"osm_id":"5888195991","tag":{"amenity":"waste_basket"}},"type":"Feature"},
	{"geometry":{"coordinates":[10.477366,49.969775],"type":"Point"},"properties":{"osm_id":"5888250819","tag":{"amenity":"recycling","recycling:cans":"yes","recycling:clothes":"yes","recycling:glass_bottles":"yes","recycling_type":"container"}},"type":"Feature"},
	{"geometry":{"coordinates":[10.464747,49.977924],"type":"Point"},"properties":{"osm_id":"5888250836","tag":{"amenity":"waste_basket"}},"type":"Feature"},
	{"geometry":{"coordinates":[10.469463,50.006244],"type":"Point"},"properties":{"osm_id":"6700772238","tag":{"amenity":"waste_basket"}},"type":"Feature"}
]
}
