{
"type": "FeatureCollection",
"features": [
	{"geometry":{"coordinates":[10.500574,49.230368],"type":"Point"},"properties":{"osm_id":"2950741502","tag":{"amenity":"recycling","location":"overground","recycling:cans":"yes","recycling:glass":"no","recycling:glass_bottles":"yes","recycling_type":"container"}},"type":"Feature"},
	{"geometry":{"coordinates":[10.50558,49.246367],"type":"Point"},"properties":{"osm_id":"6943528681","tag":{"amenity":"waste_basket"}},"type":"Feature"},
	{"geometry":{"coordinates":[10.495287,49.230382],"type":"Point"},"properties":{"osm_id":"7017851219","tag":{"amenity":"waste_basket"}},"type":"Feature"},
	{"geometry":{"coordinates":[10.495173,49.230961],"type":"Point"},"properties":{"osm_id":"7017851227","tag":{"amenity":"waste_basket"}},"type":"Feature"},
	{"geometry":{"coordinates":[10.496673,49.232001],"type":"Point"},"properties":{"osm_id":"7017851236","tag":{"amenity":"waste_basket"}},"type":"Feature"},
	{"geometry":{"coordinates":[10.496923,49.231965],"type":"Point"},"properties":{"osm_id":"7017851254","tag":{"amenity":"waste_basket"}},"type":"Feature"},
	{"geometry":{"coordinates":[10.498536,49.232343],"type":"Point"},"properties":{"osm_id":"7017851363","tag":{"amenity":"waste_basket"}},"type":"Feature"},
	{"geometry":{"coordinates":[10.497882,49.232835],"type":"Point"},"properties":{"osm_id":"7017851384","tag":{"amenity":"waste_basket"}},"type":"Feature"},
	{"geometry":{"coordinates":[10.497817,49.232678],"type":"Point"},"properties":{"osm_id":"7017851386","tag":{"amenity":"waste_basket"}},"type":"Feature"},
	{"geometry":{"coordinates":[10.497615,49.232745],"type":"Point"},"properties":{"osm_id":"7017851389","tag":{"amenity":"waste_basket"}},"type":"Feature"},
	{"geometry":{"coordinates":[10.501394,49.235188],"type":"Point"},"properties":{"osm_id":"7129273825","tag":{"amenity":"recycling","opening_hours":"Mo-Sa 07:00-19:00","recycling:cans":"yes","recycling:glass_bottles":"yes","recycling:paper":"no"}},"type":"Feature"},
	{"geometry":{"coordinates":[10.507289,49.233715],"type":"Point"},"properties":{"osm_id":"7553923436","tag":{"amenity":"recycling","recycling_type":"container"}},"type":"Feature"},
	{"geometry":{"coordinates":[10.490211,49.242425],"type":"Point"},"properties":{"osm_id":"7553923437","tag":{"amenity":"recycling","recycling_type":"container"}},"type":"Feature"}
]
}
