{
"type": "FeatureCollection",
"lastupdate": "2020-08-04T00:00:00Z",
"features": [
	{"geometry":{"coordinates":[10.500573,49.230367],"type":"Point"},"properties":{"osm_id":"2950741502","tag":{"amenity":"recycling","location":"overground","recycling:cans":"yes","recycling:glass":"no","recycling:glass_bottles":"yes","recycling_type":"container"}},"type":"Feature"},
	{"geometry":{"coordinates":[10.505579,49.246366],"type":"Point"},"properties":{"osm_id":"6943528681","tag":{"amenity":"waste_basket"}},"type":"Feature"},
	{"geometry":{"coordinates":[10.495287,49.230381],"type":"Point"},"properties":{"osm_id":"7017851219","tag":{"amenity":"waste_basket"}},"type":"Feature"},
	{"geometry":{"coordinates":[10.495172,49.230961],"type":"Point"},"properties":{"osm_id":"7017851227","tag":{"amenity":"waste_basket"}},"type":"Feature"},
	{"geometry":{"coordinates":[10.496672,49.232001],"type":"Point"},"properties":{"osm_id":"7017851236","tag":{"amenity":"waste_basket"}},"type":"Feature"},
	{"geometry":{"coordinates":[10.496922,49.231965],"type":"Point"},"properties":{"osm_id":"7017851254","tag":{"amenity":"waste_basket"}},"type":"Feature"},
	{"geometry":{"coordinates":[10.498536,49.232343],"type":"Point"},"properties":{"osm_id":"7017851363","tag":{"amenity":"waste_basket"}},"type":"Feature"},
	{"geometry":{"coordinates":[10.497881,49.232834],"type":"Point"},"properties":{"osm_id":"7017851384","tag":{"amenity":"waste_basket"}},"type":"Feature"},
	{"geometry":{"coordinates":[10.497817,49.232677],"type":"Point"},"properties":{"osm_id":"7017851386","tag":{"amenity":"waste_basket"}},"type":"Feature"},
	{"geometry":{"coordinates":[10.497614,49.232745],"type":"Point"},"properties":{"osm_id":"7017851389","tag":{"amenity":"waste_basket"}},"type":"Feature"},
	{"geometry":{"coordinates":[10.501394,49.235188],"type":"Point"},"properties":{"osm_id":"7129273825","tag":{"amenity":"recycling","opening_hours":"Mo-Sa 07:00-19:00","recycling:cans":"yes","recycling:glass_bottles":"yes","recycling:paper":"no"}},"type":"Feature"},
	{"geometry":{"coordinates":[10.507288,49.233714],"type":"Point"},"properties":{"osm_id":"7553923436","tag":{"amenity":"recycling","recycling_type":"container"}},"type":"Feature"},
	{"geometry":{"coordinates":[10.49021,49.242424],"type":"Point"},"properties":{"osm_id":"7553923437","tag":{"amenity":"recycling","recycling_type":"container"}},"type":"Feature"}
]
}
