{
"type": "FeatureCollection",
"lastupdate": "2020-08-01T00:00:00Z",
"features": [
	{"geometry":{"coordinates":[10.468377,48.276909],"type":"Point"},"properties":{"osm_id":"367665541","tag":{"addr:city":"Thannhausen","addr:country":"DE","addr:postcode":"86470","amenity":"recycling","location":"overground","recycling_type":"container"}},"type":"Feature"},
	{"geometry":{"coordinates":[10.468957,48.282106],"type":"Point"},"properties":{"osm_id":"622680799","tag":{"amenity":"waste_basket"}},"type":"Feature"},
	{"geometry":{"coordinates":[10.470297,48.282356],"type":"Point"},"properties":{"osm_id":"2109544026","tag":{"amenity":"waste_basket"}},"type":"Feature"},
	{"geometry":{"coordinates":[10.471675,48.275277],"type":"Point"},"properties":{"osm_id":"3754957463","tag":{"amenity":"waste_basket"}},"type":"Feature"},
	{"geometry":{"coordinates":[10.522116,48.252112],"type":"Point"},"properties":{"barrier":"gate","osm_id":"4442104916"},"type":"Feature"}
]
}
