{
"type": "FeatureCollection",
"features": [
	{"geometry":{"coordinates":[10.468378,48.27691],"type":"Point"},"properties":{"osm_id":"367665541","tag":{"addr:city":"Thannhausen","addr:country":"DE","addr:postcode":"86470","amenity":"recycling","location":"overground","recycling_type":"container"}},"type":"Feature"},
	{"geometry":{"coordinates":[10.468957,48.282107],"type":"Point"},"properties":{"osm_id":"622680799","tag":{"amenity":"waste_basket"}},"type":"Feature"},
	{"geometry":{"coordinates":[10.470297,48.282357],"type":"Point"},"properties":{"osm_id":"2109544026","tag":{"amenity":"waste_basket"}},"type":"Feature"},
	{"geometry":{"coordinates":[10.471676,48.275277],"type":"Point"},"properties":{"osm_id":"3754957463","tag":{"amenity":"waste_basket"}},"type":"Feature"},
	{"geometry":{"coordinates":[10.522117,48.252112],"type":"Point"},"properties":{"barrier":"gate","osm_id":"4442104916"},"type":"Feature"}
]
}
