{
"type": "FeatureCollection",
"lastupdate": "2020-08-05T00:00:00Z",
"features": [
	{"geometry":{"coordinates":[10.479344,44.635982],"type":"Point"},"properties":{"osm_id":"3496890267","tag":{"addr:city":"Quattro Castella","addr:street":"Via Donizone da Canossa","amenity":"recycling","operator":"Iren Ambiente","recycling:cans":"yes","recycling:clothes":"no","recycling:glass":"yes","recycling:paper":"yes","recycling_type":"centre"}},"type":"Feature"}
]
}
