{
"type": "FeatureCollection",
"features": [
	{"geometry":{"coordinates":[-75.516153,2.662254],"type":"Point"},"properties":{"name":"Saman","osm_id":"757222039","tag":{"natural":"tree"}},"type":"Feature"}
]
}
