{
"type": "FeatureCollection",
"lastupdate": "2020-08-05T00:00:00Z",
"features": [
	{"geometry":{"coordinates":[8.877699,54.162509],"type":"Point"},"properties":{"osm_id":"533939812","tag":{"amenity":"waste_basket"}},"type":"Feature"},
	{"geometry":{"coordinates":[8.935654,54.174847],"type":"Point"},"properties":{"osm_id":"540996392","tag":{"amenity":"recycling","operator":"Abfallwirtschaft Dithmarschen","recycling:glass_bottles":"yes","recycling_type":"container"}},"type":"Feature"},
	{"geometry":{"coordinates":[8.881107,54.188654],"type":"Point"},"properties":{"osm_id":"596401686","tag":{"amenity":"waste_basket"}},"type":"Feature"},
	{"geometry":{"coordinates":[8.908705,54.200765],"type":"Point"},"properties":{"osm_id":"596401707","tag":{"amenity":"waste_basket"}},"type":"Feature"},
	{"geometry":{"coordinates":[8.916624,54.207596],"type":"Point"},"properties":{"osm_id":"2424717654","tag":{"amenity":"waste_basket"}},"type":"Feature"},
	{"geometry":{"coordinates":[8.938204,54.206047],"type":"Point"},"properties":{"name":"Recyclinghof Wesselburen","osm_id":"3145201729","tag":{"amenity":"recycling","recycling_type":"centre","website":"https://www.awd-online.de/privatkunden/recyclinghoefe/wesselburen/"}},"type":"Feature"},
	{"geometry":{"coordinates":[8.920552,54.211922],"type":"Point"},"properties":{"osm_id":"6611632233","tag":{"amenity":"waste_basket"}},"type":"Feature"}
]
}
