{
"type": "FeatureCollection",
"features": [
	{"geometry":{"coordinates":[8.906838,53.127114],"type":"Point"},"properties":{"osm_id":"429649470","tag":{"access":"customers","amenity":"recycling","recycling:paper":"yes","recycling:plastic":"yes","recycling_type":"container"}},"type":"Feature"},
	{"geometry":{"coordinates":[8.902448,53.122154],"type":"Point"},"properties":{"osm_id":"528972035","tag":{"amenity":"recycling","recycling:clothes":"yes","recycling:glass":"yes","recycling_type":"container"}},"type":"Feature"},
	{"geometry":{"coordinates":[8.900622,53.120857],"type":"Point"},"properties":{"osm_id":"693353071","tag":{"amenity":"recycling","recycling:clothes":"yes","recycling:glass":"yes","recycling_type":"container"}},"type":"Feature"},
	{"geometry":{"coordinates":[8.911758,53.147241],"type":"Point"},"properties":{"osm_id":"987492671","tag":{"amenity":"recycling","location":"overground","recycling:clothes":"yes","recycling:shoes":"yes","recycling_type":"container"}},"type":"Feature"},
	{"geometry":{"coordinates":[8.89925,53.123844],"type":"Point"},"properties":{"osm_id":"1277298940","tag":{"amenity":"recycling","recycling:glass_bottles":"yes","recycling_type":"container"}},"type":"Feature"},
	{"geometry":{"coordinates":[8.902131,53.121423],"type":"Point"},"properties":{"osm_id":"1581099598","ref":"QUERLANDSTRASSE/VIERRUTENWEG","tag":{"amenity":"waste_basket","ref:tour":"HKB_3","waste_basket:excrement_bags":"yes"}},"type":"Feature"},
	{"geometry":{"coordinates":[8.897742,53.138259],"type":"Point"},"properties":{"is_in":"Scheune","osm_id":"3372077493","tag":{"amenity":"recycling","description":"Papiersammlung der Kirchengemeinde Lilienthal","recycling:paper":"yes","recycling_type":"centre"}},"type":"Feature"},
	{"geometry":{"coordinates":[8.92205,53.148134],"type":"Point"},"properties":{"osm_id":"3977908176","tag":{"amenity":"recycling","recycling:clothes":"yes","recycling:glass_bottles":"yes","recycling_type":"container"}},"type":"Feature"},
	{"geometry":{"coordinates":[8.911067,53.147526],"type":"Point"},"properties":{"osm_id":"4083196654","tag":{"amenity":"recycling","recycling:clothes":"no","recycling:glass_bottles":"yes","recycling:paper":"yes","recycling_type":"container"}},"type":"Feature"},
	{"geometry":{"coordinates":[8.961424,53.172289],"type":"Point"},"properties":{"osm_id":"6222635384","tag":{"amenity":"recycling","recycling:glass_bottles":"yes","recycling_type":"container"}},"type":"Feature"},
	{"geometry":{"coordinates":[8.946392,53.158002],"type":"Point"},"properties":{"osm_id":"9156287961","tag":{"amenity":"recycling","recycling:clothes":"yes","recycling:glass_bottles":"yes","recycling_type":"container"}},"type":"Feature"}
]
}
