{
"type": "FeatureCollection",
"features": [
	{"geometry":{"coordinates":[8.946331,51.756044],"type":"Point"},"properties":{"osm_id":"408476897","tag":{"amenity":"recycling","recycling:clothes":"yes","recycling:glass":"yes","recycling_type":"container"}},"type":"Feature"},
	{"geometry":{"coordinates":[8.944732,51.741131],"type":"Point"},"properties":{"osm_id":"440979822","tag":{"amenity":"recycling","location":"overground","recycling:clothes":"yes","recycling:glass":"yes","recycling_type":"container"}},"type":"Feature"},
	{"geometry":{"coordinates":[8.942062,51.764629],"type":"Point"},"properties":{"osm_id":"662468221","tag":{"amenity":"recycling","operator":"Deutsches Rotes Kreuz","recycling:clothes":"yes","recycling_type":"container"}},"type":"Feature"},
	{"geometry":{"coordinates":[8.954746,51.741523],"type":"Point"},"properties":{"osm_id":"834266572","tag":{"amenity":"recycling","recycling:glass":"yes"}},"type":"Feature"},
	{"geometry":{"coordinates":[8.941921,51.763119],"type":"Point"},"properties":{"osm_id":"1676361038","tag":{"amenity":"recycling","recycling:glass_bottles":"yes","recycling_type":"container"}},"type":"Feature"},
	{"geometry":{"coordinates":[8.943004,51.763517],"type":"Point"},"properties":{"osm_id":"1744780072","tag":{"amenity":"waste_basket"}},"type":"Feature"},
	{"geometry":{"coordinates":[8.942489,51.763558],"type":"Point"},"properties":{"osm_id":"1744780074","tag":{"amenity":"waste_basket"}},"type":"Feature"},
	{"geometry":{"coordinates":[8.949727,51.740292],"type":"Point"},"properties":{"osm_id":"1772749998","tag":{"amenity":"recycling","recycling:clothes":"yes","recycling:glass_bottles":"yes","recycling_type":"container"}},"type":"Feature"},
	{"geometry":{"coordinates":[8.945358,51.762728],"type":"Point"},"properties":{"osm_id":"2122454911","tag":{"amenity":"recycling","recycling:clothes":"yes","recycling:glass":"yes"}},"type":"Feature"},
	{"geometry":{"coordinates":[8.950513,51.760912],"type":"Point"},"properties":{"osm_id":"2953034955","tag":{"amenity":"recycling","recycling:glass_bottles":"yes","recycling_type":"container"}},"type":"Feature"},
	{"geometry":{"coordinates":[8.944892,51.760966],"type":"Point"},"properties":{"osm_id":"2971325447","tag":{"amenity":"recycling","recycling:glass":"yes","recycling_type":"container"}},"type":"Feature"},
	{"geometry":{"coordinates":[8.940647,51.762862],"type":"Point"},"properties":{"osm_id":"3135352593","tag":{"amenity":"waste_basket"}},"type":"Feature"},
	{"geometry":{"coordinates":[8.941834,51.759934],"type":"Point"},"properties":{"osm_id":"3135459447","tag":{"amenity":"recycling","recycling_type":"container"}},"type":"Feature"},
	{"geometry":{"coordinates":[8.931188,51.761716],"type":"Point"},"properties":{"osm_id":"3300121051","tag":{"amenity":"waste_basket"}},"type":"Feature"},
	{"geometry":{"coordinates":[8.942602,51.770406],"type":"Point"},"properties":{"osm_id":"3830828765","tag":{"amenity":"waste_basket"}},"type":"Feature"},
	{"geometry":{"coordinates":[8.944327,51.762739],"type":"Point"},"properties":{"osm_id":"4785957825","tag":{"amenity":"waste_basket"}},"type":"Feature"},
	{"geometry":{"coordinates":[8.91155,51.75968],"type":"Point"},"properties":{"osm_id":"4786888574","tag":{"amenity":"waste_basket"}},"type":"Feature"},
	{"geometry":{"coordinates":[8.944496,51.762906],"type":"Point"},"properties":{"osm_id":"5412031405","tag":{"amenity":"waste_basket"}},"type":"Feature"},
	{"geometry":{"coordinates":[8.942967,51.739982],"type":"Point"},"properties":{"osm_id":"7290858255","tag":{"amenity":"waste_basket"}},"type":"Feature"},
	{"geometry":{"coordinates":[8.945405,51.763057],"type":"Point"},"properties":{"osm_id":"7685509289","tag":{"amenity":"recycling","recycling:clothes":"yes","recycling_type":"container"}},"type":"Feature"},
	{"geometry":{"coordinates":[8.929155,51.765243],"type":"Point"},"properties":{"osm_id":"7710421317","tag":{"amenity":"waste_basket"}},"type":"Feature"},
	{"geometry":{"coordinates":[8.964026,51.728472],"type":"Point"},"properties":{"osm_id":"7710775639","tag":{"amenity":"waste_basket"}},"type":"Feature"},
	{"geometry":{"coordinates":[8.929114,51.768202],"type":"Point"},"properties":{"osm_id":"7713301793","tag":{"amenity":"waste_basket"}},"type":"Feature"},
	{"geometry":{"coordinates":[8.948947,51.741456],"type":"Point"},"properties":{"osm_id":"9108655823","tag":{"amenity":"waste_basket"}},"type":"Feature"}
]
}
