{
"type": "FeatureCollection",
"features": [
	{"geometry":{"coordinates":[8.946331,51.756044],"type":"Point"},"properties":{"osm_id":"408476897","tag":{"amenity":"recycling","recycling:clothes":"yes","recycling:glass":"yes","recycling_type":"container"}},"type":"Feature"},
	{"geometry":{"coordinates":[8.944733,51.741132],"type":"Point"},"properties":{"osm_id":"440979822","tag":{"amenity":"recycling","location":"overground","recycling:clothes":"yes","recycling:glass":"yes","recycling_type":"container"}},"type":"Feature"},
	{"geometry":{"coordinates":[8.942063,51.764629],"type":"Point"},"properties":{"osm_id":"662468221","tag":{"amenity":"recycling","operator":"Deutsches Rotes Kreuz","recycling:clothes":"yes","recycling_type":"container"}},"type":"Feature"},
	{"geometry":{"coordinates":[8.954747,51.741524],"type":"Point"},"properties":{"osm_id":"834266572","tag":{"amenity":"recycling","recycling:glass":"yes"}},"type":"Feature"},
	{"geometry":{"coordinates":[8.941922,51.763119],"type":"Point"},"properties":{"osm_id":"1676361038","tag":{"amenity":"recycling","recycling:glass_bottles":"yes","recycling_type":"container"}},"type":"Feature"},
	{"geometry":{"coordinates":[8.943004,51.763517],"type":"Point"},"properties":{"osm_id":"1744780072","tag":{"amenity":"waste_basket"}},"type":"Feature"},
	{"geometry":{"coordinates":[8.94249,51.763558],"type":"Point"},"properties":{"osm_id":"1744780074","tag":{"amenity":"waste_basket"}},"type":"Feature"},
	{"geometry":{"coordinates":[8.949727,51.740293],"type":"Point"},"properties":{"osm_id":"1772749998","tag":{"amenity":"recycling","recycling:clothes":"yes","recycling:glass_bottles":"yes","recycling_type":"container"}},"type":"Feature"},
	{"geometry":{"coordinates":[8.945358,51.762729],"type":"Point"},"properties":{"osm_id":"2122454911","tag":{"amenity":"recycling","recycling:clothes":"yes","recycling:glass":"yes"}},"type":"Feature"},
	{"geometry":{"coordinates":[8.950514,51.760913],"type":"Point"},"properties":{"osm_id":"2953034955","tag":{"amenity":"recycling","recycling:glass_bottles":"yes","recycling_type":"container"}},"type":"Feature"},
	{"geometry":{"coordinates":[8.944892,51.760967],"type":"Point"},"properties":{"osm_id":"2971325447","tag":{"amenity":"recycling","recycling:glass":"yes","recycling_type":"container"}},"type":"Feature"},
	{"geometry":{"coordinates":[8.940648,51.762863],"type":"Point"},"properties":{"osm_id":"3135352593","tag":{"amenity":"waste_basket"}},"type":"Feature"},
	{"geometry":{"coordinates":[8.941834,51.759935],"type":"Point"},"properties":{"osm_id":"3135459447","tag":{"amenity":"recycling","recycling_type":"container"}},"type":"Feature"},
	{"geometry":{"coordinates":[8.931188,51.761716],"type":"Point"},"properties":{"osm_id":"3300121051","tag":{"amenity":"waste_basket"}},"type":"Feature"},
	{"geometry":{"coordinates":[8.942603,51.770406],"type":"Point"},"properties":{"osm_id":"3830828765","tag":{"amenity":"waste_basket"}},"type":"Feature"},
	{"geometry":{"coordinates":[8.944328,51.762739],"type":"Point"},"properties":{"osm_id":"4785957825","tag":{"amenity":"waste_basket"}},"type":"Feature"},
	{"geometry":{"coordinates":[8.91155,51.75968],"type":"Point"},"properties":{"osm_id":"4786888574","tag":{"amenity":"waste_basket"}},"type":"Feature"},
	{"geometry":{"coordinates":[8.944497,51.762906],"type":"Point"},"properties":{"osm_id":"5412031405","tag":{"amenity":"waste_basket"}},"type":"Feature"},
	{"geometry":{"coordinates":[8.942967,51.739982],"type":"Point"},"properties":{"osm_id":"7290858255","tag":{"amenity":"waste_basket"}},"type":"Feature"},
	{"geometry":{"coordinates":[8.945406,51.763058],"type":"Point"},"properties":{"osm_id":"7685509289","tag":{"amenity":"recycling","recycling:clothes":"yes","recycling_type":"container"}},"type":"Feature"},
	{"geometry":{"coordinates":[8.929156,51.765244],"type":"Point"},"properties":{"osm_id":"7710421317","tag":{"amenity":"waste_basket"}},"type":"Feature"},
	{"geometry":{"coordinates":[8.964026,51.728472],"type":"Point"},"properties":{"osm_id":"7710775639","tag":{"amenity":"waste_basket"}},"type":"Feature"},
	{"geometry":{"coordinates":[8.929115,51.768203],"type":"Point"},"properties":{"osm_id":"7713301793","tag":{"amenity":"waste_basket"}},"type":"Feature"}
]
}
