{
"type": "FeatureCollection",
"features": [
	{"geometry":{"coordinates":[8.941386,50.331333],"type":"Point"},"properties":{"osm_id":"2958419617","tag":{"amenity":"recycling","recycling:cans":"yes","recycling:clothes":"yes"}},"type":"Feature"},
	{"geometry":{"coordinates":[8.941497,50.330572],"type":"Point"},"properties":{"osm_id":"2958419618","tag":{"amenity":"recycling","location":"overground","recycling:cans":"no","recycling:clothes":"yes","recycling:glass":"yes","recycling_type":"container"}},"type":"Feature"},
	{"geometry":{"coordinates":[8.93182,50.329742],"type":"Point"},"properties":{"osm_id":"2958419619","tag":{"amenity":"recycling","location":"overground","recycling:clothes":"yes","recycling:glass":"yes","recycling_type":"container"}},"type":"Feature"},
	{"geometry":{"coordinates":[8.91376,50.330072],"type":"Point"},"properties":{"osm_id":"3700119255","tag":{"amenity":"recycling","recycling:clothes":"yes","recycling:glass_bottles":"yes","recycling:green_waste":"yes","recycling_type":"container"}},"type":"Feature"},
	{"geometry":{"coordinates":[8.944623,50.289544],"type":"Point"},"properties":{"osm_id":"3916709911","tag":{"amenity":"recycling","recycling:clothes":"yes","recycling:glass":"yes","recycling_type":"container"}},"type":"Feature"},
	{"geometry":{"coordinates":[8.945523,50.290517],"type":"Point"},"properties":{"osm_id":"6404293667","tag":{"amenity":"waste_basket","waste":"trash"}},"type":"Feature"},
	{"geometry":{"coordinates":[8.952625,50.30108],"type":"Point"},"properties":{"osm_id":"6455757346","tag":{"amenity":"recycling","recycling:glass_bottles":"yes","recycling_type":"container"}},"type":"Feature"},
	{"geometry":{"coordinates":[8.946736,50.293459],"type":"Point"},"properties":{"osm_id":"7504180742","tag":{"amenity":"waste_basket","waste":"trash"}},"type":"Feature"},
	{"geometry":{"coordinates":[8.915452,50.312399],"type":"Point"},"properties":{"osm_id":"7769508459","tag":{"amenity":"recycling","recycling:clothes":"yes","recycling:glass_bottles":"yes","recycling:shoes":"yes","recycling_type":"container"}},"type":"Feature"}
]
}
