{
"type": "FeatureCollection",
"lastupdate": "2020-08-02T00:00:00Z",
"features": [
	{"geometry":{"coordinates":[8.941385,50.331332],"type":"Point"},"properties":{"osm_id":"2958419617","tag":{"amenity":"recycling","recycling:cans":"yes","recycling:clothes":"yes"}},"type":"Feature"},
	{"geometry":{"coordinates":[8.941496,50.330571],"type":"Point"},"properties":{"osm_id":"2958419618","tag":{"amenity":"recycling","location":"overground","recycling:cans":"no","recycling:clothes":"yes","recycling:glass":"yes","recycling_type":"container"}},"type":"Feature"},
	{"geometry":{"coordinates":[8.93182,50.329742],"type":"Point"},"properties":{"osm_id":"2958419619","tag":{"amenity":"recycling","location":"overground","recycling:clothes":"yes","recycling:glass":"yes","recycling_type":"container"}},"type":"Feature"},
	{"geometry":{"coordinates":[8.913759,50.330072],"type":"Point"},"properties":{"osm_id":"3700119255","tag":{"amenity":"recycling","recycling:clothes":"yes","recycling:glass_bottles":"yes","recycling:green_waste":"yes","recycling_type":"container"}},"type":"Feature"},
	{"geometry":{"coordinates":[8.944623,50.289544],"type":"Point"},"properties":{"osm_id":"3916709911","tag":{"amenity":"recycling","recycling:clothes":"yes","recycling:glass":"yes","recycling_type":"container"}},"type":"Feature"},
	{"geometry":{"coordinates":[8.945522,50.290516],"type":"Point"},"properties":{"osm_id":"6404293667","tag":{"amenity":"waste_basket","waste":"trash"}},"type":"Feature"},
	{"geometry":{"coordinates":[8.952624,50.30108],"type":"Point"},"properties":{"osm_id":"6455757346","tag":{"amenity":"recycling","recycling:glass_bottles":"yes","recycling_type":"container"}},"type":"Feature"},
	{"geometry":{"coordinates":[8.946736,50.293458],"type":"Point"},"properties":{"osm_id":"7504180742","tag":{"amenity":"waste_basket","waste":"trash"}},"type":"Feature"},
	{"geometry":{"coordinates":[8.915452,50.312399],"type":"Point"},"properties":{"osm_id":"7769508459","tag":{"amenity":"recycling","recycling:clothes":"yes","recycling:glass_bottles":"yes","recycling:shoes":"yes","recycling_type":"container"}},"type":"Feature"}
]
}
