{
"type": "FeatureCollection",
"lastupdate": "2020-08-03T00:00:00Z",
"features": [
	{"geometry":{"coordinates":[8.950381,48.382569],"type":"Point"},"properties":{"osm_id":"271939583","tag":{"amenity":"recycling","location":"overground","recycling:clothes":"yes","recycling:glass":"yes","recycling_type":"container"}},"type":"Feature"},
	{"geometry":{"coordinates":[8.951113,48.34329],"type":"Point"},"properties":{"osm_id":"303346717","tag":{"amenity":"recycling","recycling:clothes":"yes","recycling:glass_bottles":"yes"}},"type":"Feature"},
	{"geometry":{"coordinates":[8.957632,48.348199],"type":"Point"},"properties":{"osm_id":"303346966","tag":{"amenity":"recycling","recycling:glass_bottles":"yes"}},"type":"Feature"},
	{"geometry":{"coordinates":[8.958608,48.353542],"type":"Point"},"properties":{"osm_id":"596830471","tag":{"amenity":"recycling","recycling:glass_bottles":"yes","recycling_type":"container"}},"type":"Feature"},
	{"geometry":{"coordinates":[8.949236,48.371101],"type":"Point"},"properties":{"osm_id":"596830486","tag":{"amenity":"recycling","recycling:glass_bottles":"yes"}},"type":"Feature"},
	{"geometry":{"coordinates":[8.898274,48.379972],"type":"Point"},"properties":{"osm_id":"663056959","tag":{"amenity":"recycling","recycling:shoes":"yes"}},"type":"Feature"},
	{"geometry":{"coordinates":[8.893256,48.381233],"type":"Point"},"properties":{"osm_id":"668059240","tag":{"amenity":"recycling","recycling:glass_bottles":"yes"}},"type":"Feature"},
	{"geometry":{"coordinates":[8.877648,48.375065],"type":"Point"},"properties":{"osm_id":"670764797","tag":{"amenity":"recycling","recycling:glass_bottles":"yes"}},"type":"Feature"},
	{"geometry":{"coordinates":[8.88621,48.376197],"type":"Point"},"properties":{"osm_id":"689113699","tag":{"amenity":"recycling","recycling:glass_bottles":"yes"}},"type":"Feature"},
	{"geometry":{"coordinates":[8.884951,48.379553],"type":"Point"},"properties":{"osm_id":"695668329","tag":{"amenity":"recycling","recycling:glass_bottles":"yes"}},"type":"Feature"},
	{"geometry":{"coordinates":[8.884289,48.37646],"type":"Point"},"properties":{"osm_id":"695668342","tag":{"amenity":"recycling","recycling:clothes":"yes"}},"type":"Feature"},
	{"geometry":{"coordinates":[8.893223,48.383448],"type":"Point"},"properties":{"osm_id":"701385975","tag":{"amenity":"recycling","recycling:glass_bottles":"yes"}},"type":"Feature"},
	{"geometry":{"coordinates":[8.880132,48.381897],"type":"Point"},"properties":{"osm_id":"1126700363","tag":{"amenity":"recycling","recycling:glass":"yes"}},"type":"Feature"},
	{"geometry":{"coordinates":[8.880124,48.381896],"type":"Point"},"properties":{"osm_id":"1126700364","tag":{"amenity":"recycling","recycling:glass_bottles":"yes"}},"type":"Feature"},
	{"geometry":{"coordinates":[8.889019,48.384684],"type":"Point"},"properties":{"osm_id":"1470073751","tag":{"amenity":"waste_basket"}},"type":"Feature"},
	{"geometry":{"coordinates":[8.886671,48.385315],"type":"Point"},"properties":{"osm_id":"1470073762","tag":{"amenity":"waste_basket"}},"type":"Feature"}
]
}
