{
"type": "FeatureCollection",
"features": [
	{"geometry":{"coordinates":[8.950382,48.382569],"type":"Point"},"properties":{"osm_id":"271939583","tag":{"amenity":"recycling","location":"overground","recycling:clothes":"yes","recycling:glass":"yes","recycling_type":"container"}},"type":"Feature"},
	{"geometry":{"coordinates":[8.951114,48.34329],"type":"Point"},"properties":{"osm_id":"303346717","tag":{"amenity":"recycling","recycling:clothes":"yes","recycling:glass_bottles":"yes"}},"type":"Feature"},
	{"geometry":{"coordinates":[8.957633,48.348199],"type":"Point"},"properties":{"osm_id":"303346966","tag":{"amenity":"recycling","location":"overground","recycling:clothes":"yes","recycling:glass_bottles":"yes","recycling_type":"container"}},"type":"Feature"},
	{"geometry":{"coordinates":[8.958609,48.353542],"type":"Point"},"properties":{"osm_id":"596830471","tag":{"amenity":"recycling","recycling:glass_bottles":"yes","recycling_type":"container"}},"type":"Feature"},
	{"geometry":{"coordinates":[8.949236,48.371102],"type":"Point"},"properties":{"osm_id":"596830486","tag":{"amenity":"recycling","recycling:clothes":"yes","recycling:glass_bottles":"yes","recycling_type":"container"}},"type":"Feature"},
	{"geometry":{"coordinates":[8.898274,48.379972],"type":"Point"},"properties":{"osm_id":"663056959","tag":{"amenity":"recycling","recycling:shoes":"yes"}},"type":"Feature"},
	{"geometry":{"coordinates":[8.893256,48.381233],"type":"Point"},"properties":{"osm_id":"668059240","tag":{"amenity":"recycling","recycling:glass_bottles":"yes"}},"type":"Feature"},
	{"geometry":{"coordinates":[8.877648,48.375066],"type":"Point"},"properties":{"osm_id":"670764797","tag":{"amenity":"recycling","recycling:glass_bottles":"yes"}},"type":"Feature"},
	{"geometry":{"coordinates":[8.88621,48.376198],"type":"Point"},"properties":{"osm_id":"689113699","tag":{"amenity":"recycling","recycling:glass_bottles":"yes"}},"type":"Feature"},
	{"geometry":{"coordinates":[8.884952,48.379554],"type":"Point"},"properties":{"osm_id":"695668329","tag":{"amenity":"recycling","recycling:glass_bottles":"yes"}},"type":"Feature"},
	{"geometry":{"coordinates":[8.88429,48.376461],"type":"Point"},"properties":{"osm_id":"695668342","tag":{"amenity":"recycling","recycling:clothes":"yes"}},"type":"Feature"},
	{"geometry":{"coordinates":[8.893224,48.383449],"type":"Point"},"properties":{"osm_id":"701385975","tag":{"amenity":"recycling","recycling:glass_bottles":"yes"}},"type":"Feature"},
	{"geometry":{"coordinates":[8.880132,48.381897],"type":"Point"},"properties":{"osm_id":"1126700363","tag":{"amenity":"recycling","recycling:glass":"yes"}},"type":"Feature"},
	{"geometry":{"coordinates":[8.880124,48.381896],"type":"Point"},"properties":{"osm_id":"1126700364","tag":{"amenity":"recycling","recycling:glass_bottles":"yes"}},"type":"Feature"},
	{"geometry":{"coordinates":[8.889019,48.384684],"type":"Point"},"properties":{"osm_id":"1470073751","tag":{"amenity":"waste_basket"}},"type":"Feature"},
	{"geometry":{"coordinates":[8.886671,48.385316],"type":"Point"},"properties":{"osm_id":"1470073762","tag":{"amenity":"waste_basket"}},"type":"Feature"},
	{"geometry":{"coordinates":[8.950653,48.349395],"type":"Point"},"properties":{"osm_id":"7904569758","tag":{"amenity":"recycling","operator":"Deutsches Rotes Kreuz e.V.","recycling:clothes":"yes","recycling:shoes":"yes","recycling_type":"container"}},"type":"Feature"},
	{"geometry":{"coordinates":[8.961278,48.357654],"type":"Point"},"properties":{"osm_id":"7904569759","tag":{"amenity":"recycling","operator":"Deutsches Rotes Kreuz e.V.","recycling:clothes":"yes","recycling:shoes":"yes","recycling_type":"container"}},"type":"Feature"},
	{"geometry":{"coordinates":[8.954425,48.351847],"type":"Point"},"properties":{"osm_id":"7912244566","tag":{"amenity":"recycling","recycling:clothes":"yes","recycling:glass_bottles":"yes","recycling_type":"container"}},"type":"Feature"},
	{"geometry":{"coordinates":[8.958629,48.353649],"type":"Point"},"properties":{"osm_id":"7912244567","tag":{"amenity":"recycling","operator":"Deutsches Rotes Kreuz e.V.","recycling:clothes":"yes","recycling_type":"container"}},"type":"Feature"}
]
}
