{
"type": "FeatureCollection",
"lastupdate": "2020-08-03T00:00:00Z",
"features": [
	{"geometry":{"coordinates":[8.921337,39.423198],"type":"Point"},"properties":{"osm_id":"3344078376","tag":{"addr:street":"Via Roma","amenity":"waste_basket"}},"type":"Feature"}
]
}
