{
"type": "FeatureCollection",
"features": [
	{"geometry":{"coordinates":[-72.555081,-41.577295],"type":"Point"},"properties":{"name":"Alerce Milenario","osm_id":"5446529722","tag":{"natural":"tree"}},"type":"Feature"}
]
}
