{
"type": "FeatureCollection",
"features": [
	{"geometry":{"coordinates":[9.828149,47.8461],"type":"Point"},"properties":{"osm_id":"395808288","tag":{"natural":"tree"}},"type":"Feature"},
	{"geometry":{"coordinates":[9.766506,47.864388],"type":"Point"},"properties":{"osm_id":"2548803412","tag":{"natural":"tree"}},"type":"Feature"},
	{"geometry":{"coordinates":[9.79245,47.838244],"type":"Point"},"properties":{"osm_id":"3514288084","tag":{"natural":"tree"}},"type":"Feature"},
	{"geometry":{"coordinates":[9.76723,47.851979],"type":"Point"},"properties":{"osm_id":"4076478670","tag":{"natural":"tree"}},"type":"Feature"},
	{"geometry":{"coordinates":[9.772261,47.839364],"type":"Point"},"properties":{"osm_id":"4079674813","tag":{"leaf_type":"broadleaved","natural":"tree"}},"type":"Feature"},
	{"geometry":{"coordinates":[9.78207,47.861398],"type":"Point"},"properties":{"osm_id":"4081027048","tag":{"leaf_type":"broadleaved","natural":"tree"}},"type":"Feature"},
	{"geometry":{"coordinates":[9.781438,47.861671],"type":"Point"},"properties":{"osm_id":"4081108336","tag":{"natural":"tree"}},"type":"Feature"},
	{"geometry":{"coordinates":[9.763602,47.871141],"type":"Point"},"properties":{"osm_id":"4081549019","tag":{"natural":"tree"}},"type":"Feature"},
	{"geometry":{"coordinates":[9.782203,47.867529],"type":"Point"},"properties":{"osm_id":"4085247853","tag":{"leaf_type":"broadleaved","natural":"tree"}},"type":"Feature"},
	{"geometry":{"coordinates":[9.781616,47.867567],"type":"Point"},"properties":{"osm_id":"4085247857","tag":{"leaf_type":"broadleaved","natural":"tree"}},"type":"Feature"},
	{"geometry":{"coordinates":[9.781518,47.867755],"type":"Point"},"properties":{"osm_id":"4085247870","tag":{"leaf_type":"broadleaved","natural":"tree"}},"type":"Feature"},
	{"geometry":{"coordinates":[9.772104,47.865783],"type":"Point"},"properties":{"osm_id":"4596119105","tag":{"leaf_type":"broadleaved","natural":"tree"}},"type":"Feature"},
	{"geometry":{"coordinates":[9.776913,47.863613],"type":"Point"},"properties":{"osm_id":"4596250840","tag":{"natural":"tree"}},"type":"Feature"},
	{"geometry":{"coordinates":[9.778185,47.860934],"type":"Point"},"properties":{"osm_id":"4596511171","tag":{"leaf_type":"broadleaved","natural":"tree"}},"type":"Feature"},
	{"geometry":{"coordinates":[9.793016,47.821301],"type":"Point"},"properties":{"name":"Pius-Linde","osm_id":"4734166875","tag":{"genus:de":"Linde","natural":"tree"}},"type":"Feature"},
	{"geometry":{"coordinates":[9.792898,47.821126],"type":"Point"},"properties":{"name":"Leo-Linde","osm_id":"4734166876","tag":{"genus:de":"Linde","natural":"tree"}},"type":"Feature"},
	{"geometry":{"coordinates":[9.793369,47.821917],"type":"Point"},"properties":{"name":"Johannes-Paul-Linde","osm_id":"4734344521","tag":{"genus:de":"Linde","natural":"tree"}},"type":"Feature"},
	{"geometry":{"coordinates":[9.786476,47.835646],"type":"Point"},"properties":{"osm_id":"5625919733","tag":{"bench":"yes","leaf_type":"broadleaved","natural":"tree"}},"type":"Feature"},
	{"geometry":{"coordinates":[9.804057,47.868892],"type":"Point"},"properties":{"osm_id":"7925863066","tag":{"height":"3","leaf_cycle":"deciduous","leaf_type":"broadleaved","natural":"tree"}},"type":"Feature"},
	{"geometry":{"coordinates":[9.804118,47.868832],"type":"Point"},"properties":{"osm_id":"7925863067","tag":{"height":"2","natural":"tree"}},"type":"Feature"},
	{"geometry":{"coordinates":[9.803996,47.868967],"type":"Point"},"properties":{"osm_id":"7925863068","tag":{"height":"4","leaf_type":"broadleaved","natural":"tree"}},"type":"Feature"}
]
}
