{
"type": "FeatureCollection",
"features": [
	{"geometry":{"coordinates":[9.828149,47.8461],"type":"Point"},"properties":{"osm_id":"395808288","tag":{"natural":"tree"}},"type":"Feature"},
	{"geometry":{"coordinates":[9.766505,47.864387],"type":"Point"},"properties":{"osm_id":"2548803412","tag":{"natural":"tree"}},"type":"Feature"},
	{"geometry":{"coordinates":[9.79245,47.838243],"type":"Point"},"properties":{"osm_id":"3514288084","tag":{"natural":"tree"}},"type":"Feature"},
	{"geometry":{"coordinates":[9.767229,47.851979],"type":"Point"},"properties":{"osm_id":"4076478670","tag":{"natural":"tree"}},"type":"Feature"},
	{"geometry":{"coordinates":[9.77226,47.839363],"type":"Point"},"properties":{"osm_id":"4079674813","tag":{"leaf_type":"broadleaved","natural":"tree"}},"type":"Feature"},
	{"geometry":{"coordinates":[9.782069,47.861398],"type":"Point"},"properties":{"osm_id":"4081027048","tag":{"leaf_type":"broadleaved","natural":"tree"}},"type":"Feature"},
	{"geometry":{"coordinates":[9.781437,47.86167],"type":"Point"},"properties":{"osm_id":"4081108336","tag":{"natural":"tree"}},"type":"Feature"},
	{"geometry":{"coordinates":[9.763602,47.87114],"type":"Point"},"properties":{"osm_id":"4081549019","tag":{"natural":"tree"}},"type":"Feature"},
	{"geometry":{"coordinates":[9.782202,47.867528],"type":"Point"},"properties":{"osm_id":"4085247853","tag":{"leaf_type":"broadleaved","natural":"tree"}},"type":"Feature"},
	{"geometry":{"coordinates":[9.781615,47.867567],"type":"Point"},"properties":{"osm_id":"4085247857","tag":{"leaf_type":"broadleaved","natural":"tree"}},"type":"Feature"},
	{"geometry":{"coordinates":[9.781517,47.867754],"type":"Point"},"properties":{"osm_id":"4085247870","tag":{"leaf_type":"broadleaved","natural":"tree"}},"type":"Feature"},
	{"geometry":{"coordinates":[9.772103,47.865783],"type":"Point"},"properties":{"osm_id":"4596119105","tag":{"leaf_type":"broadleaved","natural":"tree"}},"type":"Feature"},
	{"geometry":{"coordinates":[9.776913,47.863613],"type":"Point"},"properties":{"osm_id":"4596250840","tag":{"natural":"tree"}},"type":"Feature"},
	{"geometry":{"coordinates":[9.778184,47.860933],"type":"Point"},"properties":{"osm_id":"4596511171","tag":{"leaf_type":"broadleaved","natural":"tree"}},"type":"Feature"},
	{"geometry":{"coordinates":[9.793016,47.821301],"type":"Point"},"properties":{"name":"Pius-Linde","osm_id":"4734166875","tag":{"genus:de":"Linde","natural":"tree"}},"type":"Feature"},
	{"geometry":{"coordinates":[9.792898,47.821126],"type":"Point"},"properties":{"name":"Leo-Linde","osm_id":"4734166876","tag":{"genus:de":"Linde","natural":"tree"}},"type":"Feature"},
	{"geometry":{"coordinates":[9.793368,47.821916],"type":"Point"},"properties":{"name":"Johannes-Paul-Linde","osm_id":"4734344521","tag":{"genus:de":"Linde","natural":"tree"}},"type":"Feature"},
	{"geometry":{"coordinates":[9.786509,47.835664],"type":"Point"},"properties":{"osm_id":"5625919733","tag":{"bench":"yes","leaf_type":"broadleaved","natural":"tree"}},"type":"Feature"},
	{"geometry":{"coordinates":[9.804056,47.868892],"type":"Point"},"properties":{"osm_id":"7925863066","tag":{"height":"3","leaf_cycle":"deciduous","leaf_type":"broadleaved","natural":"tree"}},"type":"Feature"},
	{"geometry":{"coordinates":[9.804118,47.868831],"type":"Point"},"properties":{"osm_id":"7925863067","tag":{"height":"2","natural":"tree"}},"type":"Feature"},
	{"geometry":{"coordinates":[9.803996,47.868966],"type":"Point"},"properties":{"osm_id":"7925863068","tag":{"height":"4","leaf_type":"broadleaved","natural":"tree"}},"type":"Feature"},
	{"geometry":{"coordinates":[9.777026,47.828717],"type":"Point"},"properties":{"osm_id":"8872981181","tag":{"leaf_cycle":"deciduous","leaf_type":"broadleaved","natural":"tree"}},"type":"Feature"}
]
}
