{
"type": "FeatureCollection",
"lastupdate": "2020-08-03T00:00:00Z",
"features": [
	{"geometry":{"coordinates":[-86.84324,34.991355],"type":"Point"},"properties":{"osm_id":"4430998690","tag":{"amenity":"recycling","operator":"Keep Athens Limestone Beautiful","recycling:books":"yes","recycling:cans":"yes","recycling:cardboard":"yes","recycling:glass_bottles":"yes","recycling:glass_jars":"yes","recycling:newspaper":"yes","recycling:paper":"yes","recycling:plastic":"yes","recycling:plastic_bottles":"yes","recycling_type":"container","website":"http://kalbcares.com/limestone-county-recycling/"}},"type":"Feature"},
	{"geometry":{"coordinates":[-86.848392,34.988218],"type":"Point"},"properties":{"osm_id":"4434407917","tag":{"amenity":"recycling","operator":"Keep Athens Limestone Beautiful","recycling:books":"yes","recycling:cans":"yes","recycling:cardboard":"yes","recycling:glass_bottles":"yes","recycling:glass_jars":"yes","recycling:newspaper":"yes","recycling:paper":"yes","recycling:plastic":"yes","recycling:plastic_bottles":"yes","recycling_type":"container","website":"http://kalbcares.com/limestone-county-recycling/"}},"type":"Feature"}
]
}
