{
"type": "FeatureCollection",
"lastupdate": "2020-08-02T00:00:00Z",
"features": [
	{"geometry":{"coordinates":[-86.874373,21.126414],"type":"Point"},"properties":{"name":"Composto","osm_id":"4902956821","tag":{"amenity":"recycling","name:es":"Composto","operator":"Juan Kintero","phone":"5526642563"}},"type":"Feature"}
]
}
