{
"type": "FeatureCollection",
"features": [
	{"geometry":{"coordinates":[-86.877985,12.418228],"type":"Point"},"properties":{"osm_id":"5182895185","tag":{"amenity":"waste_disposal"}},"type":"Feature"},
	{"geometry":{"coordinates":[-86.877413,12.418436],"type":"Point"},"properties":{"osm_id":"5182925445","tag":{"amenity":"waste_disposal"}},"type":"Feature"},
	{"geometry":{"coordinates":[-86.880495,12.442389],"type":"Point"},"properties":{"osm_id":"5316724193","tag":{"amenity":"waste_disposal"}},"type":"Feature"},
	{"geometry":{"coordinates":[-86.881164,12.442263],"type":"Point"},"properties":{"osm_id":"5316724216","tag":{"amenity":"waste_disposal"}},"type":"Feature"},
	{"geometry":{"coordinates":[-86.876351,12.418228],"type":"Point"},"properties":{"osm_id":"5465133827","tag":{"amenity":"waste_disposal"}},"type":"Feature"},
	{"geometry":{"coordinates":[-86.880316,12.415267],"type":"Point"},"properties":{"name":"Nica Green","osm_id":"6725549661","tag":{"amenity":"recycling","recycling_type":"centre"}},"type":"Feature"}
]
}
