{
"type": "FeatureCollection",
"lastupdate": "2020-07-31T00:00:00Z",
"features": [
	{"geometry":{"coordinates":[-86.880315,12.415267],"type":"Point"},"properties":{"name":"Nica Green","osm_id":"6725549661","tag":{"amenity":"recycling","recycling_type":"centre"}},"type":"Feature"}
]
}
