{
"type": "FeatureCollection",
"lastupdate": "2020-07-31T00:00:00Z",
"features": [
	{"geometry":{"coordinates":[7.652941,51.009877],"type":"Point"},"properties":{"osm_id":"5067475967","tag":{"amenity":"recycling","recycling:clothes":"yes","recycling:glass":"yes","recycling_type":"container"}},"type":"Feature"},
	{"geometry":{"coordinates":[7.65615,50.961117],"type":"Point"},"properties":{"osm_id":"6424198351","tag":{"amenity":"recycling","recycling:glass_bottles":"yes","recycling_type":"container"}},"type":"Feature"},
	{"geometry":{"coordinates":[7.668156,51.009751],"type":"Point"},"properties":{"name":"Lobbe Recyling- und Bringhof","osm_id":"7600119950","tag":{"addr:city":"Bergneustadt","addr:country":"DE","addr:housenumber":"4","addr:postcode":"51702","addr:street":"Hackewiese","amenity":"recycling","contact:email":"bergneustadt@lobbe.de","contact:fax":"+49 2261 48989","contact:phone":"+49 2261 94430","contact:website":"https://www.lobbe.de/lobbe-familienunternehmen/standorte/bergneustadt/","opening_hours":"Mo-Fr 07:00-15:30; PH off","operator":"Lobbe Entsorgung West GmbH & Co. KG","recycling_type":"centre"}},"type":"Feature"}
]
}
