{
"type": "FeatureCollection",
"features": [
	{"geometry":{"coordinates":[7.651626,49.314624],"type":"Point"},"properties":{"osm_id":"820260521","tag":{"amenity":"waste_basket"}},"type":"Feature"},
	{"geometry":{"coordinates":[7.653363,49.31454],"type":"Point"},"properties":{"osm_id":"820261599","tag":{"amenity":"recycling","recycling:clothes":"yes","recycling:glass":"yes","recycling_type":"container"}},"type":"Feature"},
	{"geometry":{"coordinates":[7.654455,49.289509],"type":"Point"},"properties":{"name":"Recyclinghof Waldfischbach-Burgalben","osm_id":"3345664426","tag":{"amenity":"recycling"}},"type":"Feature"},
	{"geometry":{"coordinates":[7.667403,49.289803],"type":"Point"},"properties":{"osm_id":"5961966792","tag":{"amenity":"waste_basket"}},"type":"Feature"},
	{"geometry":{"coordinates":[7.661216,49.282234],"type":"Point"},"properties":{"osm_id":"6847563615","tag":{"amenity":"waste_basket"}},"type":"Feature"}
]
}
