{
"type": "FeatureCollection",
"lastupdate": "2020-08-02T00:00:00Z",
"features": [
	{"geometry":{"coordinates":[7.651625,49.314623],"type":"Point"},"properties":{"osm_id":"820260521","tag":{"amenity":"waste_basket"}},"type":"Feature"},
	{"geometry":{"coordinates":[7.653362,49.314539],"type":"Point"},"properties":{"osm_id":"820261599","tag":{"amenity":"recycling","recycling:clothes":"yes","recycling:glass":"yes","recycling_type":"container"}},"type":"Feature"},
	{"geometry":{"coordinates":[7.654455,49.289508],"type":"Point"},"properties":{"name":"Recyclinghof Waldfischbach-Burgalben","osm_id":"3345664426","tag":{"amenity":"recycling"}},"type":"Feature"},
	{"geometry":{"coordinates":[7.667402,49.289802],"type":"Point"},"properties":{"osm_id":"5961966792","tag":{"amenity":"waste_basket"}},"type":"Feature"},
	{"geometry":{"coordinates":[7.661215,49.282234],"type":"Point"},"properties":{"osm_id":"6847563615","tag":{"amenity":"waste_basket"}},"type":"Feature"}
]
}
