{
"type": "FeatureCollection",
"features": [
	{"geometry":{"coordinates":[7.672791,46.498273],"type":"Point"},"properties":{"name":"Zuckerschopf A","osm_id":"2403628681","tag":{"amenity":"recycling"}},"type":"Feature"},
	{"geometry":{"coordinates":[7.666666,46.482389],"type":"Point"},"properties":{"osm_id":"3425565248","tag":{"amenity":"recycling","recycling_type":"centre"}},"type":"Feature"}
]
}
