{
"type": "FeatureCollection",
"lastupdate": "2020-08-04T00:00:00Z",
"features": [
	{"geometry":{"coordinates":[7.661063,36.787487],"type":"Point"},"properties":{"name":"Environnement protect","osm_id":"4610794889","tag":{"amenity":"recycling","operator":"environnement protect"}},"type":"Feature"}
]
}
