{
"type": "FeatureCollection",
"features": [
	{"geometry":{"coordinates":[7.661064,36.787487],"type":"Point"},"properties":{"name":"Environnement protect","osm_id":"4610794889","tag":{"amenity":"recycling","operator":"environnement protect"}},"type":"Feature"}
]
}
