{
"type": "FeatureCollection",
"features": [
	{"geometry":{"coordinates":[6.487682,52.462828],"type":"Point"},"properties":{"osm_id":"2949960285","tag":{"amenity":"recycling","recycling:clothes":"yes","recycling:shoes":"yes","recycling_type":"container"}},"type":"Feature"},
	{"geometry":{"coordinates":[6.501089,52.467987],"type":"Point"},"properties":{"osm_id":"2951613255","tag":{"amenity":"waste_basket"}},"type":"Feature"},
	{"geometry":{"coordinates":[6.498393,52.470217],"type":"Point"},"properties":{"osm_id":"2951613376","tag":{"amenity":"waste_basket"}},"type":"Feature"},
	{"geometry":{"coordinates":[6.445434,52.437084],"type":"Point"},"properties":{"osm_id":"2953478852","tag":{"amenity":"waste_basket"}},"type":"Feature"},
	{"geometry":{"coordinates":[6.457812,52.435166],"type":"Point"},"properties":{"osm_id":"2961698502","tag":{"amenity":"waste_basket"}},"type":"Feature"},
	{"geometry":{"coordinates":[6.416709,52.454084],"type":"Point"},"properties":{"osm_id":"3950127978","tag":{"amenity":"recycling","location":"underground","recycling_type":"container"}},"type":"Feature"},
	{"geometry":{"coordinates":[6.417176,52.450634],"type":"Point"},"properties":{"osm_id":"3975688598","tag":{"amenity":"recycling","location":"underground","recycling_type":"container"}},"type":"Feature"},
	{"geometry":{"coordinates":[6.478026,52.434088],"type":"Point"},"properties":{"osm_id":"5470988018","tag":{"amenity":"waste_basket","waste":"trash"}},"type":"Feature"},
	{"geometry":{"coordinates":[6.494183,52.464313],"type":"Point"},"properties":{"osm_id":"5687081263","tag":{"amenity":"waste_basket","waste":"trash"}},"type":"Feature"},
	{"geometry":{"coordinates":[6.497337,52.463217],"type":"Point"},"properties":{"osm_id":"5687081312","tag":{"amenity":"waste_basket","waste":"trash"}},"type":"Feature"},
	{"geometry":{"coordinates":[6.4543,52.440648],"type":"Point"},"properties":{"osm_id":"5689793565","tag":{"amenity":"waste_basket","waste":"trash"}},"type":"Feature"},
	{"geometry":{"coordinates":[6.456612,52.450392],"type":"Point"},"properties":{"osm_id":"5689793577","tag":{"amenity":"waste_basket","waste":"trash"}},"type":"Feature"}
]
}
