{
"type": "FeatureCollection",
"lastupdate": "2020-07-31T00:00:00Z",
"features": [
	{"geometry":{"coordinates":[4.044877,51.058559],"type":"Point"},"properties":{"osm_id":"1628956782","tag":{"amenity":"recycling","recycling:glass":"yes"}},"type":"Feature"},
	{"geometry":{"coordinates":[4.129257,51.037536],"type":"Point"},"properties":{"osm_id":"3779087334","tag":{"amenity":"waste_basket"}},"type":"Feature"},
	{"geometry":{"coordinates":[4.045729,51.038036],"type":"Point"},"properties":{"osm_id":"3780930082","tag":{"amenity":"waste_basket"}},"type":"Feature"},
	{"geometry":{"coordinates":[4.051046,51.023225],"type":"Point"},"properties":{"osm_id":"3794154822","tag":{"amenity":"waste_basket"}},"type":"Feature"},
	{"geometry":{"coordinates":[4.050431,51.025146],"type":"Point"},"properties":{"osm_id":"3796801998","tag":{"amenity":"waste_basket"}},"type":"Feature"},
	{"geometry":{"coordinates":[4.088259,51.045372],"type":"Point"},"properties":{"osm_id":"3860698182","tag":{"amenity":"waste_basket"}},"type":"Feature"},
	{"geometry":{"coordinates":[4.105287,51.023287],"type":"Point"},"properties":{"osm_id":"4788616299","tag":{"amenity":"recycling","recycling:glass":"yes","recycling_type":"container"}},"type":"Feature"},
	{"geometry":{"coordinates":[4.1003,51.02529],"type":"Point"},"properties":{"name":"glasbol","osm_id":"4788616300","tag":{"amenity":"recycling","recycling:glass":"yes","recycling_type":"container"}},"type":"Feature"},
	{"geometry":{"coordinates":[4.109338,51.016268],"type":"Point"},"properties":{"osm_id":"4887427028","tag":{"amenity":"recycling","recycling:glass_bottles":"yes","recycling_type":"container"}},"type":"Feature"},
	{"geometry":{"coordinates":[4.09549,51.028641],"type":"Point"},"properties":{"name":"glasbol","osm_id":"4887839570","tag":{"amenity":"recycling","recycling:glass_bottles":"yes","recycling_type":"container"}},"type":"Feature"},
	{"geometry":{"coordinates":[4.115441,51.03266],"type":"Point"},"properties":{"name":"Glasbol","osm_id":"4938358731","tag":{"amenity":"recycling","recycling_type":"container"}},"type":"Feature"},
	{"geometry":{"coordinates":[4.096098,51.015746],"type":"Point"},"properties":{"osm_id":"4961374472","tag":{"amenity":"waste_basket"}},"type":"Feature"},
	{"geometry":{"coordinates":[4.124024,51.026211],"type":"Point"},"properties":{"osm_id":"5132839827","tag":{"amenity":"recycling","description":"Glasbol","recycling:glass_bottles":"yes","recycling_type":"container"}},"type":"Feature"},
	{"geometry":{"coordinates":[4.126998,51.017001],"type":"Point"},"properties":{"osm_id":"5132839828","tag":{"amenity":"recycling","description":"Glasbol","recycling:glass_bottles":"yes","recycling_type":"container"}},"type":"Feature"},
	{"geometry":{"coordinates":[4.091146,51.02011],"type":"Point"},"properties":{"osm_id":"5132839830","tag":{"amenity":"recycling","description":"Glasbol","recycling:glass_bottles":"yes","recycling_type":"container"}},"type":"Feature"},
	{"geometry":{"coordinates":[4.090682,51.020298],"type":"Point"},"properties":{"osm_id":"5132878315","tag":{"amenity":"waste_basket"}},"type":"Feature"},
	{"geometry":{"coordinates":[4.106257,51.052167],"type":"Point"},"properties":{"osm_id":"6174835905","tag":{"amenity":"recycling","recycling_type":"container","waste":"glass"}},"type":"Feature"},
	{"geometry":{"coordinates":[4.093405,51.029797],"type":"Point"},"properties":{"osm_id":"6443201725","tag":{"amenity":"waste_basket"}},"type":"Feature"},
	{"geometry":{"coordinates":[4.092702,51.017986],"type":"Point"},"properties":{"osm_id":"6443201731","tag":{"amenity":"waste_basket"}},"type":"Feature"},
	{"geometry":{"coordinates":[4.092321,51.019168],"type":"Point"},"properties":{"osm_id":"6443201732","tag":{"amenity":"waste_basket"}},"type":"Feature"},
	{"geometry":{"coordinates":[4.090284,51.01943],"type":"Point"},"properties":{"osm_id":"6443201736","tag":{"amenity":"waste_basket"}},"type":"Feature"},
	{"geometry":{"coordinates":[4.089223,51.01931],"type":"Point"},"properties":{"osm_id":"6443201739","tag":{"amenity":"waste_basket"}},"type":"Feature"},
	{"geometry":{"coordinates":[4.09116,51.028142],"type":"Point"},"properties":{"osm_id":"6443201743","tag":{"amenity":"waste_basket"}},"type":"Feature"},
	{"geometry":{"coordinates":[4.09529,51.029489],"type":"Point"},"properties":{"osm_id":"6443201746","tag":{"amenity":"waste_basket"}},"type":"Feature"},
	{"geometry":{"coordinates":[4.09603,51.029298],"type":"Point"},"properties":{"osm_id":"6443201747","tag":{"amenity":"waste_basket"}},"type":"Feature"},
	{"geometry":{"coordinates":[4.096816,51.030172],"type":"Point"},"properties":{"osm_id":"6443201749","tag":{"amenity":"waste_basket"}},"type":"Feature"},
	{"geometry":{"coordinates":[4.096398,51.031655],"type":"Point"},"properties":{"osm_id":"6443201751","tag":{"amenity":"waste_basket"}},"type":"Feature"},
	{"geometry":{"coordinates":[4.096387,51.031546],"type":"Point"},"properties":{"osm_id":"6443201752","tag":{"amenity":"waste_basket"}},"type":"Feature"}
]
}
