{
"type": "FeatureCollection",
"lastupdate": "2020-08-02T00:00:00Z",
"features": [
	{"geometry":{"coordinates":[-122.729962,50.313945],"type":"Point"},"properties":{"name":"Ep-corp","osm_id":"3559302596","tag":{"amenity":"recycling","recycling:batteries":"yes","recycling:books":"no","recycling:cans":"yes","recycling:cardboard":"no","recycling:cartons":"yes","recycling:clothes":"no","recycling:electrical_appliances":"yes","recycling:glass":"yes","recycling:glass_bottles":"yes","recycling:green_waste":"no","recycling:magazines":"no","recycling:newspaper":"no","recycling:paper":"no","recycling:paper_packaging":"no","recycling:plastic":"no","recycling:plastic_bottles":"yes","recycling:plastic_packaging":"no","recycling:scrap_metal":"no","recycling:small_appliances":"yes","recycling_type":"centre"}},"type":"Feature"},
	{"geometry":{"coordinates":[-122.727323,50.312219],"type":"Point"},"properties":{"name":"carnies","osm_id":"3559302807","tag":{"amenity":"recycling","recycling:batteries":"yes","recycling:books":"yes","recycling:cans":"yes","recycling:cardboard":"yes","recycling:cartons":"yes","recycling:clothes":"no","recycling:electrical_appliances":"yes","recycling:glass":"yes","recycling:glass_bottles":"yes","recycling:green_waste":"yes","recycling:magazines":"yes","recycling:newspaper":"yes","recycling:paper":"yes","recycling:paper_packaging":"yes","recycling:plastic":"yes","recycling:plastic_bottles":"yes","recycling:plastic_packaging":"yes","recycling:scrap_metal":"yes","recycling:small_appliances":"yes","recycling_type":"container"}},"type":"Feature"}
]
}
