{
"type": "FeatureCollection",
"features": [
	{"geometry":{"coordinates":[-122.778743,46.624073],"type":"Point"},"properties":{"name":"Lower Dump Station Dumpster","osm_id":"8133807914","tag":{"access":"customers","amenity":"waste_disposal","collection_times":"Mo","operator":"Thousand Trails","waste":"mixed"}},"type":"Feature"},
	{"geometry":{"coordinates":[-122.779862,46.621429],"type":"Point"},"properties":{"name":"Upper Dump Station Dumpster","osm_id":"8133810420","tag":{"access":"customers","amenity":"waste_disposal","collection_times":"Mo","operator":"Thousand Trails","waste":"mixed"}},"type":"Feature"},
	{"geometry":{"coordinates":[-122.781423,46.619499],"type":"Point"},"properties":{"name":"D Section Dumpster","osm_id":"8133810421","tag":{"access":"customers","amenity":"waste_disposal","collection_times":"Mo","operator":"Thousand Trails","waste":"mixed"}},"type":"Feature"},
	{"geometry":{"coordinates":[-122.777234,46.62022],"type":"Point"},"properties":{"osm_id":"8134117037","tag":{"amenity":"waste_basket","waste":"dog_excrement"}},"type":"Feature"}
]
}
