{
"type": "FeatureCollection",
"features": [
	{"geometry":{"coordinates":[4.689221,44.010271],"type":"Point"},"properties":{"osm_id":"3077219524","tag":{"natural":"tree"}},"type":"Feature"},
	{"geometry":{"coordinates":[4.689309,44.0103],"type":"Point"},"properties":{"osm_id":"3077219525","tag":{"natural":"tree"}},"type":"Feature"},
	{"geometry":{"coordinates":[4.689438,44.010325],"type":"Point"},"properties":{"osm_id":"3077219526","tag":{"natural":"tree"}},"type":"Feature"},
	{"geometry":{"coordinates":[4.688711,44.010151],"type":"Point"},"properties":{"osm_id":"3077219527","tag":{"natural":"tree"}},"type":"Feature"},
	{"geometry":{"coordinates":[4.659137,44.013822],"type":"Point"},"properties":{"osm_id":"3077546191","tag":{"natural":"tree"}},"type":"Feature"},
	{"geometry":{"coordinates":[4.660335,44.013911],"type":"Point"},"properties":{"osm_id":"3077546192","tag":{"natural":"tree"}},"type":"Feature"},
	{"geometry":{"coordinates":[4.663296,44.014485],"type":"Point"},"properties":{"osm_id":"3077546236","tag":{"natural":"tree"}},"type":"Feature"},
	{"geometry":{"coordinates":[4.696006,44.011482],"type":"Point"},"properties":{"osm_id":"3091652562","tag":{"natural":"tree","type":"conifer"}},"type":"Feature"},
	{"geometry":{"coordinates":[4.69592,44.011459],"type":"Point"},"properties":{"osm_id":"3091652563","tag":{"natural":"tree"}},"type":"Feature"},
	{"geometry":{"coordinates":[4.695822,44.011437],"type":"Point"},"properties":{"osm_id":"3091652564","tag":{"natural":"tree"}},"type":"Feature"},
	{"geometry":{"coordinates":[4.695746,44.011424],"type":"Point"},"properties":{"osm_id":"3091652565","tag":{"natural":"tree"}},"type":"Feature"},
	{"geometry":{"coordinates":[4.695638,44.011408],"type":"Point"},"properties":{"osm_id":"3091652566","tag":{"natural":"tree"}},"type":"Feature"},
	{"geometry":{"coordinates":[4.69553,44.011383],"type":"Point"},"properties":{"osm_id":"3091652567","tag":{"natural":"tree"}},"type":"Feature"},
	{"geometry":{"coordinates":[4.695444,44.011385],"type":"Point"},"properties":{"osm_id":"3091652568","tag":{"natural":"tree"}},"type":"Feature"},
	{"geometry":{"coordinates":[4.695382,44.011431],"type":"Point"},"properties":{"osm_id":"3091652569","tag":{"natural":"tree"}},"type":"Feature"},
	{"geometry":{"coordinates":[4.696211,44.01158],"type":"Point"},"properties":{"osm_id":"3091652570","tag":{"natural":"tree"}},"type":"Feature"},
	{"geometry":{"coordinates":[4.696265,44.011649],"type":"Point"},"properties":{"osm_id":"3091652571","tag":{"natural":"tree"}},"type":"Feature"},
	{"geometry":{"coordinates":[4.696246,44.011619],"type":"Point"},"properties":{"osm_id":"3091652572","tag":{"natural":"tree"}},"type":"Feature"},
	{"geometry":{"coordinates":[4.665669,44.024127],"type":"Point"},"properties":{"name":"Figuier","osm_id":"6395391905","tag":{"denotation":"agricultural","leaf_cycle":"deciduous","leaf_type":"broadleaved","natural":"tree"}},"type":"Feature"},
	{"geometry":{"coordinates":[4.665662,44.024066],"type":"Point"},"properties":{"name":"Poirier","osm_id":"6395391906","tag":{"denotation":"agricultural","leaf_cycle":"deciduous","leaf_type":"broadleaved","natural":"tree"}},"type":"Feature"},
	{"geometry":{"coordinates":[4.665659,44.024014],"type":"Point"},"properties":{"name":"Pommier","osm_id":"6395391907","tag":{"leaf_type":"broadleaved","natural":"tree"}},"type":"Feature"}
]
}
