{
"type": "FeatureCollection",
"features": [
	{"geometry":{"coordinates":[-49.23418,-18.523627],"type":"Point"},"properties":{"name":"Bambu","osm_id":"4002386332","tag":{"name:botanical":"Bambusa comuna","natural":"tree"}},"type":"Feature"}
]
}
