{
"type": "FeatureCollection",
"features": [
	{"geometry":{"coordinates":[-76.236491,36.741385],"type":"Point"},"properties":{"name":"Fallen Tree Underpass","osm_id":"4938804057","tag":{"natural":"tree"}},"type":"Feature"}
]
}
