{
"type": "FeatureCollection",
"features": [
	{"geometry":{"coordinates":[28.283333,11.983333],"type":"Point"},"properties":{"name":"Umm Derota","osm_id":"7730425205","place":"hamlet","tag":{"GNS:dsg_code":"PPL","GNS:dsg_name":"populated place","GNS:id":"-16168","GNS:modify_date":"2014-12-16","alt_name":"Umm Darota","name:ar":"\u0623\u0645\u0651 \u062f\u0631\u0648\u062a","name:en":"Umm Derota"}},"type":"Feature"}
]
}
