{
"type": "FeatureCollection",
"lastupdate": "2020-08-01T00:00:00Z",
"features": [
	{"geometry":{"coordinates":[28.249808,-26.065687],"type":"Point"},"properties":{"name":"Eco-Park Recycling Bin","osm_id":"1305605619","tag":{"amenity":"recycling","designation":"Eco-Park","recycling:batteries":"yes","recycling:books":"yes","recycling:cans":"yes","recycling:cardboard":"yes","recycling:cartons":"yes","recycling:electrical_appliances":"yes","recycling:glass":"yes","recycling:glass_bottles":"yes","recycling:magazines":"yes","recycling:newspaper":"yes","recycling:paper":"yes","recycling:paper_packaging":"yes","recycling:plastic":"yes","recycling:plastic_bottles":"yes","recycling:plastic_packaging":"yes","recycling:small_appliances":"yes","recycling:waste":"no","recycling_type":"container"}},"type":"Feature"}
]
}
