{
"type": "FeatureCollection",
"features": [
	{"geometry":{"coordinates":[-81.26513,28.706014],"type":"Point"},"properties":{"name":"Pet Waste","osm_id":"3747706259","tag":{"amenity":"waste_basket"}},"type":"Feature"},
	{"geometry":{"coordinates":[-81.264483,28.704993],"type":"Point"},"properties":{"name":"Pet Waste","osm_id":"3747706260","tag":{"amenity":"waste_basket"}},"type":"Feature"},
	{"geometry":{"coordinates":[-81.260873,28.699255],"type":"Point"},"properties":{"osm_id":"3755845755","tag":{"amenity":"waste_basket"}},"type":"Feature"},
	{"geometry":{"coordinates":[-81.260741,28.699453],"type":"Point"},"properties":{"osm_id":"3755845756","tag":{"amenity":"waste_basket"}},"type":"Feature"},
	{"geometry":{"coordinates":[-81.260637,28.69951],"type":"Point"},"properties":{"osm_id":"3755845757","tag":{"amenity":"waste_basket"}},"type":"Feature"},
	{"geometry":{"coordinates":[-81.260881,28.69915],"type":"Point"},"properties":{"osm_id":"3755845758","tag":{"amenity":"waste_basket"}},"type":"Feature"},
	{"geometry":{"coordinates":[-81.264757,28.707036],"type":"Point"},"properties":{"name":"Pet Waste","osm_id":"4083013628","tag":{"amenity":"waste_basket"}},"type":"Feature"},
	{"geometry":{"coordinates":[-81.262759,28.704419],"type":"Point"},"properties":{"name":"Pet Waste","osm_id":"4083013629","tag":{"amenity":"waste_basket"}},"type":"Feature"}
]
}
