{
"type": "FeatureCollection",
"lastupdate": "2020-08-02T00:00:00Z",
"features": [
	{"geometry":{"coordinates":[-81.26513,28.706013],"type":"Point"},"properties":{"name":"Pet Waste","osm_id":"3747706259","tag":{"amenity":"waste_basket"}},"type":"Feature"},
	{"geometry":{"coordinates":[-81.264483,28.704993],"type":"Point"},"properties":{"name":"Pet Waste","osm_id":"3747706260","tag":{"amenity":"waste_basket"}},"type":"Feature"},
	{"geometry":{"coordinates":[-81.260872,28.699254],"type":"Point"},"properties":{"osm_id":"3755845755","tag":{"amenity":"waste_basket"}},"type":"Feature"},
	{"geometry":{"coordinates":[-81.260741,28.699453],"type":"Point"},"properties":{"osm_id":"3755845756","tag":{"amenity":"waste_basket"}},"type":"Feature"},
	{"geometry":{"coordinates":[-81.260636,28.69951],"type":"Point"},"properties":{"osm_id":"3755845757","tag":{"amenity":"waste_basket"}},"type":"Feature"},
	{"geometry":{"coordinates":[-81.26088,28.69915],"type":"Point"},"properties":{"osm_id":"3755845758","tag":{"amenity":"waste_basket"}},"type":"Feature"},
	{"geometry":{"coordinates":[-81.264757,28.707036],"type":"Point"},"properties":{"name":"Pet Waste","osm_id":"4083013628","tag":{"amenity":"waste_basket"}},"type":"Feature"},
	{"geometry":{"coordinates":[-81.262759,28.704418],"type":"Point"},"properties":{"name":"Pet Waste","osm_id":"4083013629","tag":{"amenity":"waste_basket"}},"type":"Feature"}
]
}
