{
"type": "FeatureCollection",
"lastupdate": "2020-08-02T00:00:00Z",
"features": [
	{"geometry":{"coordinates":[-0.102344,39.897136],"type":"Point"},"properties":{"osm_id":"7614042204","tag":{"addr:street":"Cam\u00ed d'Onda","amenity":"recycling","recycling_type":"centre"}},"type":"Feature"}
]
}
