{
"type": "FeatureCollection",
"features": [
	{"geometry":{"coordinates":[-0.116818,39.874467],"type":"Point"},"properties":{"osm_id":"4568526892","tag":{"amenity":"waste_disposal"}},"type":"Feature"},
	{"geometry":{"coordinates":[-0.102344,39.897136],"type":"Point"},"properties":{"osm_id":"7614042204","tag":{"addr:street":"Cam\u00ed d'Onda","amenity":"recycling","recycling_type":"centre"}},"type":"Feature"}
]
}
