{
"type": "FeatureCollection",
"features": [
	{"geometry":{"coordinates":[-122.699892,47.142928],"type":"Point"},"properties":{"name":"Jacobs Family Tree","osm_id":"7256128685","tag":{"leaf_cycle":"deciduous","leaf_type":"broadleaved","natural":"tree"}},"type":"Feature"},
	{"geometry":{"coordinates":[-122.729848,47.147598],"type":"Point"},"properties":{"osm_id":"7256289053","tag":{"leaf_cycle":"deciduous","leaf_type":"broadleaved","natural":"tree"}},"type":"Feature"}
]
}
