{
"type": "FeatureCollection",
"features": [
	{"geometry":{"coordinates":[-119.538755,39.322917],"type":"Point"},"properties":{"name":"The Lone Tree","osm_id":"6887631296","tag":{"natural":"tree"}},"type":"Feature"}
]
}
