{
"type": "FeatureCollection",
"features": [
	{"geometry":{"coordinates":[-119.538755,39.322917],"type":"Point"},"properties":{"is_in":"Molossia","name":"The Lone Tree","osm_id":"6887631296","tag":{"is_in:micronation":"Republic of Molossia","natural":"tree"}},"type":"Feature"}
]
}
