{
"type": "FeatureCollection",
"features": [
	{"geometry":{"coordinates":[-80.080229,32.717166],"type":"Point"},"properties":{"name":"Angel Oak","osm_id":"2218474054","tag":{"natural":"tree","wikidata":"Q4762234"}},"type":"Feature"}
]
}
