{
"type": "FeatureCollection",
"features": [
	{"geometry":{"coordinates":[19.288144,42.093763],"type":"Point"},"properties":{"name":"Kshtenja Runjit","osm_id":"7482611492","tag":{"denotation":"natural_monument","leaf_cycle":"semi_evergreen","leaf_type":"broadleaved","natural":"tree"}},"type":"Feature"}
]
}
