{
"type": "FeatureCollection",
"features": [
	{"geometry":{"coordinates":[-98.624477,30.240775],"type":"Point"},"properties":{"name":"Live Oak","osm_id":"4743193366","tag":{"natural":"tree"}},"type":"Feature"},
	{"geometry":{"coordinates":[-98.62472,30.240885],"type":"Point"},"properties":{"name":"Live Oak","osm_id":"4743193367","tag":{"natural":"tree"}},"type":"Feature"}
]
}
