{
"type": "FeatureCollection",
"features": [
	{"geometry":{"coordinates":[13.830565,51.44482],"type":"Point"},"properties":{"osm_id":"1831847021","tag":{"amenity":"waste_basket"}},"type":"Feature"},
	{"geometry":{"coordinates":[13.84982,51.451347],"type":"Point"},"properties":{"osm_id":"1835220873","tag":{"amenity":"recycling","recycling:glass_bottles":"yes","recycling_type":"container"}},"type":"Feature"},
	{"geometry":{"coordinates":[13.861053,51.452898],"type":"Point"},"properties":{"osm_id":"1838496288","tag":{"amenity":"recycling","recycling:glass_bottles":"yes","recycling_type":"container"}},"type":"Feature"},
	{"geometry":{"coordinates":[13.852944,51.453406],"type":"Point"},"properties":{"name":"Abwasserhebeanlage","osm_id":"1838545363","tag":{"amenity":"recycling"}},"type":"Feature"},
	{"geometry":{"coordinates":[13.864813,51.453078],"type":"Point"},"properties":{"osm_id":"7495171376","tag":{"amenity":"waste_disposal"}},"type":"Feature"},
	{"geometry":{"coordinates":[13.864811,51.453098],"type":"Point"},"properties":{"osm_id":"7495171377","tag":{"amenity":"recycling","recycling:green_waste":"yes","recycling:plastic":"yes","recycling_type":"container"}},"type":"Feature"},
	{"geometry":{"coordinates":[13.873883,51.452305],"type":"Point"},"properties":{"osm_id":"7503591372","tag":{"amenity":"waste_basket"}},"type":"Feature"},
	{"geometry":{"coordinates":[13.873658,51.452434],"type":"Point"},"properties":{"osm_id":"7503591373","tag":{"amenity":"waste_basket"}},"type":"Feature"},
	{"geometry":{"coordinates":[13.873556,51.452581],"type":"Point"},"properties":{"osm_id":"7503591374","tag":{"amenity":"waste_basket"}},"type":"Feature"}
]
}
