{
"type": "FeatureCollection",
"lastupdate": "2020-07-31T00:00:00Z",
"features": [
	{"geometry":{"coordinates":[13.834643,51.192472],"type":"Point"},"properties":{"osm_id":"322615840","tag":{"amenity":"recycling","recycling_type":"container"}},"type":"Feature"},
	{"geometry":{"coordinates":[13.825763,51.19058],"type":"Point"},"properties":{"osm_id":"322644214","tag":{"amenity":"recycling","location":"overground","recycling_type":"container"}},"type":"Feature"},
	{"geometry":{"coordinates":[13.823961,51.183207],"type":"Point"},"properties":{"osm_id":"322644269","tag":{"amenity":"recycling","recycling:clothes":"yes","recycling:glass":"yes","recycling:paper":"yes"}},"type":"Feature"},
	{"geometry":{"coordinates":[13.812554,51.181377],"type":"Point"},"properties":{"osm_id":"670494359","tag":{"amenity":"recycling","recycling:glass_bottles":"yes","recycling:paper":"yes","recycling_type":"container"}},"type":"Feature"},
	{"geometry":{"coordinates":[13.835712,51.189169],"type":"Point"},"properties":{"osm_id":"6754086888","tag":{"amenity":"recycling","recycling:clothes":"yes","recycling:glass":"yes","recycling:paper":"yes","recycling_type":"container"}},"type":"Feature"},
	{"geometry":{"coordinates":[13.820111,51.185449],"type":"Point"},"properties":{"osm_id":"7083743011","tag":{"amenity":"waste_basket","waste":"trash"}},"type":"Feature"},
	{"geometry":{"coordinates":[13.835476,51.185291],"type":"Point"},"properties":{"osm_id":"7658280188","tag":{"amenity":"waste_basket","waste":"trash"}},"type":"Feature"}
]
}
