{
"type": "FeatureCollection",
"features": [
	{"geometry":{"coordinates":[13.812211,44.857011],"type":"Point"},"properties":{"osm_id":"858337026","tag":{"amenity":"recycling"}},"type":"Feature"},
	{"geometry":{"coordinates":[13.864418,44.882446],"type":"Point"},"properties":{"osm_id":"2727491198","tag":{"amenity":"recycling","recycling:cans":"yes","recycling:glass_bottles":"yes","recycling:plastic_bottles":"yes","recycling_type":"centre"}},"type":"Feature"},
	{"geometry":{"coordinates":[13.862865,44.878864],"type":"Point"},"properties":{"osm_id":"2780166183","tag":{"amenity":"recycling","recycling:cans":"yes","recycling:glass_bottles":"yes","recycling:plastic_bottles":"yes"}},"type":"Feature"},
	{"geometry":{"coordinates":[13.844223,44.871341],"type":"Point"},"properties":{"osm_id":"3010170992","tag":{"amenity":"waste_basket"}},"type":"Feature"},
	{"geometry":{"coordinates":[13.847591,44.872009],"type":"Point"},"properties":{"osm_id":"3010171023","tag":{"amenity":"waste_basket"}},"type":"Feature"},
	{"geometry":{"coordinates":[13.86165,44.864891],"type":"Point"},"properties":{"osm_id":"5532163058","tag":{"amenity":"waste_basket"}},"type":"Feature"},
	{"geometry":{"coordinates":[13.861372,44.86384],"type":"Point"},"properties":{"osm_id":"5532163059","tag":{"amenity":"waste_basket"}},"type":"Feature"},
	{"geometry":{"coordinates":[13.861172,44.86385],"type":"Point"},"properties":{"osm_id":"5561415049","tag":{"amenity":"waste_basket"}},"type":"Feature"},
	{"geometry":{"coordinates":[13.814513,44.856065],"type":"Point"},"properties":{"osm_id":"5849060926","tag":{"addr:street":"Stoja","amenity":"waste_disposal","recycling:PET":"yes","recycling:aluminium":"yes","recycling:cardboard":"yes","recycling:glass_bottles":"yes","recycling:plastic":"yes","recycling:waste":"yes","recycling_type":"container"}},"type":"Feature"},
	{"geometry":{"coordinates":[13.813967,44.857846],"type":"Point"},"properties":{"osm_id":"5849706898","tag":{"addr:street":"Stoja","amenity":"waste_disposal","recycling:PET":"yes","recycling:aluminium":"yes","recycling:cardboard":"yes","recycling:glass_bottles":"yes","recycling:plastic":"yes","recycling:waste":"yes","recycling_type":"container"}},"type":"Feature"},
	{"geometry":{"coordinates":[13.849439,44.874757],"type":"Point"},"properties":{"osm_id":"6466160567","tag":{"amenity":"recycling","recycling:aluminium":"yes","recycling:glass":"yes","recycling:paper":"yes","recycling:plastic_bottles":"yes","recycling:waste":"yes","recycling_type":"container"}},"type":"Feature"},
	{"geometry":{"coordinates":[13.856291,44.871939],"type":"Point"},"properties":{"osm_id":"7800334778","tag":{"amenity":"recycling","opening_hours":"24/7","recycling:clothes":"yes","recycling:shoes":"yes","recycling_type":"container"}},"type":"Feature"},
	{"geometry":{"coordinates":[13.850305,44.866635],"type":"Point"},"properties":{"osm_id":"7875877087","tag":{"amenity":"waste_basket"}},"type":"Feature"},
	{"geometry":{"coordinates":[13.845928,44.870068],"type":"Point"},"properties":{"osm_id":"9102897599","tag":{"amenity":"waste_basket"}},"type":"Feature"}
]
}
