{
"type": "FeatureCollection",
"features": [
	{"geometry":{"coordinates":[13.812211,44.857012],"type":"Point"},"properties":{"osm_id":"858337026","tag":{"amenity":"recycling"}},"type":"Feature"},
	{"geometry":{"coordinates":[13.864418,44.882447],"type":"Point"},"properties":{"osm_id":"2727491198","tag":{"amenity":"recycling","recycling:cans":"yes","recycling:glass_bottles":"yes","recycling:plastic_bottles":"yes","recycling_type":"centre"}},"type":"Feature"},
	{"geometry":{"coordinates":[13.862866,44.878864],"type":"Point"},"properties":{"osm_id":"2780166183","tag":{"amenity":"recycling","recycling:cans":"yes","recycling:glass_bottles":"yes","recycling:plastic_bottles":"yes"}},"type":"Feature"},
	{"geometry":{"coordinates":[13.844224,44.871342],"type":"Point"},"properties":{"osm_id":"3010170992","tag":{"amenity":"waste_basket"}},"type":"Feature"},
	{"geometry":{"coordinates":[13.84755,44.872005],"type":"Point"},"properties":{"osm_id":"3010171023","tag":{"amenity":"waste_basket"}},"type":"Feature"},
	{"geometry":{"coordinates":[13.861651,44.864892],"type":"Point"},"properties":{"osm_id":"5532163058","tag":{"amenity":"waste_basket"}},"type":"Feature"},
	{"geometry":{"coordinates":[13.861373,44.863841],"type":"Point"},"properties":{"osm_id":"5532163059","tag":{"amenity":"waste_basket"}},"type":"Feature"},
	{"geometry":{"coordinates":[13.861173,44.863851],"type":"Point"},"properties":{"osm_id":"5561415049","tag":{"amenity":"waste_basket"}},"type":"Feature"},
	{"geometry":{"coordinates":[13.814513,44.856066],"type":"Point"},"properties":{"osm_id":"5849060926","tag":{"addr:street":"Stoja","amenity":"waste_disposal","recycling:PET":"yes","recycling:aluminium":"yes","recycling:cardboard":"yes","recycling:glass_bottles":"yes","recycling:plastic":"yes","recycling:waste":"yes","recycling_type":"container"}},"type":"Feature"},
	{"geometry":{"coordinates":[13.813967,44.857846],"type":"Point"},"properties":{"osm_id":"5849706898","tag":{"addr:street":"Stoja","amenity":"waste_disposal","recycling:PET":"yes","recycling:aluminium":"yes","recycling:cardboard":"yes","recycling:glass_bottles":"yes","recycling:plastic":"yes","recycling:waste":"yes","recycling_type":"container"}},"type":"Feature"},
	{"geometry":{"coordinates":[13.849439,44.874758],"type":"Point"},"properties":{"osm_id":"6466160567","tag":{"amenity":"recycling","recycling:aluminium":"yes","recycling:glass":"yes","recycling:paper":"yes","recycling:plastic_bottles":"yes","recycling:waste":"yes","recycling_type":"container"}},"type":"Feature"},
	{"geometry":{"coordinates":[13.856292,44.871939],"type":"Point"},"properties":{"osm_id":"7800334778","tag":{"amenity":"recycling","opening_hours":"24/7","recycling:clothes":"yes","recycling:shoes":"yes","recycling_type":"container"}},"type":"Feature"},
	{"geometry":{"coordinates":[13.850306,44.866635],"type":"Point"},"properties":{"osm_id":"7875877087","tag":{"amenity":"waste_basket"}},"type":"Feature"}
]
}
