{
"type": "FeatureCollection",
"features": [
	{"geometry":{"coordinates":[-124.030529,41.522019],"type":"Point"},"properties":{"name":"Klamath Tour Thru Tree","osm_id":"4555858964","tag":{"fee":"yes","fee:amount":"$5 per car","natural":"tree","tourism":"attraction","website":"https://www.kampklamath.com/tour_thru_tree_css.html"}},"type":"Feature"}
]
}
