{
"type": "FeatureCollection",
"features": [
	{"geometry":{"coordinates":[-40.151965,-11.706156],"type":"Point"},"properties":{"name":"Algaroba","osm_id":"5310017457","tag":{"natural":"tree"}},"type":"Feature"},
	{"geometry":{"coordinates":[-40.151003,-11.70656],"type":"Point"},"properties":{"osm_id":"5310017458","tag":{"natural":"tree"}},"type":"Feature"},
	{"geometry":{"coordinates":[-40.149018,-11.711681],"type":"Point"},"properties":{"osm_id":"5310115379","tag":{"natural":"tree"}},"type":"Feature"},
	{"geometry":{"coordinates":[-40.149018,-11.71187],"type":"Point"},"properties":{"osm_id":"5310118194","tag":{"natural":"tree"}},"type":"Feature"},
	{"geometry":{"coordinates":[-40.149034,-11.712106],"type":"Point"},"properties":{"osm_id":"5310118968","tag":{"natural":"tree"}},"type":"Feature"},
	{"geometry":{"coordinates":[-40.148591,-11.711699],"type":"Point"},"properties":{"osm_id":"5310119104","tag":{"natural":"tree"}},"type":"Feature"},
	{"geometry":{"coordinates":[-40.148638,-11.711954],"type":"Point"},"properties":{"osm_id":"5310119351","tag":{"natural":"tree"}},"type":"Feature"},
	{"geometry":{"coordinates":[-40.148616,-11.711786],"type":"Point"},"properties":{"osm_id":"5310119352","tag":{"natural":"tree"}},"type":"Feature"},
	{"geometry":{"coordinates":[-40.14914,-11.711977],"type":"Point"},"properties":{"osm_id":"5310119472","tag":{"natural":"tree"}},"type":"Feature"},
	{"geometry":{"coordinates":[-40.151242,-11.706552],"type":"Point"},"properties":{"osm_id":"5310233371","tag":{"natural":"tree"}},"type":"Feature"},
	{"geometry":{"coordinates":[-40.150397,-11.706541],"type":"Point"},"properties":{"osm_id":"5310233398","tag":{"natural":"tree"}},"type":"Feature"},
	{"geometry":{"coordinates":[-40.150713,-11.706579],"type":"Point"},"properties":{"osm_id":"5310235222","tag":{"natural":"tree"}},"type":"Feature"},
	{"geometry":{"coordinates":[-40.147205,-11.707416],"type":"Point"},"properties":{"osm_id":"5310285869","tag":{"natural":"tree"}},"type":"Feature"},
	{"geometry":{"coordinates":[-40.147119,-11.70854],"type":"Point"},"properties":{"osm_id":"5310290415","tag":{"natural":"tree"}},"type":"Feature"},
	{"geometry":{"coordinates":[-40.147216,-11.708571],"type":"Point"},"properties":{"osm_id":"5310291883","tag":{"natural":"tree"}},"type":"Feature"},
	{"geometry":{"coordinates":[-40.147226,-11.707878],"type":"Point"},"properties":{"osm_id":"5310291968","tag":{"natural":"tree"}},"type":"Feature"},
	{"geometry":{"coordinates":[-40.151142,-11.704516],"type":"Point"},"properties":{"osm_id":"5310293259","tag":{"natural":"tree"}},"type":"Feature"},
	{"geometry":{"coordinates":[-40.151133,-11.704816],"type":"Point"},"properties":{"osm_id":"5310295529","tag":{"natural":"tree"}},"type":"Feature"},
	{"geometry":{"coordinates":[-40.150917,-11.704411],"type":"Point"},"properties":{"osm_id":"5310295537","tag":{"natural":"tree"}},"type":"Feature"}
]
}
