{
"type": "FeatureCollection",
"features": [
	{"geometry":{"coordinates":[-40.151965,-11.706157],"type":"Point"},"properties":{"name":"Algaroba","osm_id":"5310017457","tag":{"natural":"tree"}},"type":"Feature"},
	{"geometry":{"coordinates":[-40.151004,-11.70656],"type":"Point"},"properties":{"osm_id":"5310017458","tag":{"natural":"tree"}},"type":"Feature"},
	{"geometry":{"coordinates":[-40.149019,-11.711681],"type":"Point"},"properties":{"osm_id":"5310115379","tag":{"natural":"tree"}},"type":"Feature"},
	{"geometry":{"coordinates":[-40.149019,-11.71187],"type":"Point"},"properties":{"osm_id":"5310118194","tag":{"natural":"tree"}},"type":"Feature"},
	{"geometry":{"coordinates":[-40.149035,-11.712107],"type":"Point"},"properties":{"osm_id":"5310118968","tag":{"natural":"tree"}},"type":"Feature"},
	{"geometry":{"coordinates":[-40.148592,-11.711699],"type":"Point"},"properties":{"osm_id":"5310119104","tag":{"natural":"tree"}},"type":"Feature"},
	{"geometry":{"coordinates":[-40.148638,-11.711955],"type":"Point"},"properties":{"osm_id":"5310119351","tag":{"natural":"tree"}},"type":"Feature"},
	{"geometry":{"coordinates":[-40.148616,-11.711786],"type":"Point"},"properties":{"osm_id":"5310119352","tag":{"natural":"tree"}},"type":"Feature"},
	{"geometry":{"coordinates":[-40.149141,-11.711977],"type":"Point"},"properties":{"osm_id":"5310119472","tag":{"natural":"tree"}},"type":"Feature"},
	{"geometry":{"coordinates":[-40.151242,-11.706552],"type":"Point"},"properties":{"osm_id":"5310233371","tag":{"natural":"tree"}},"type":"Feature"},
	{"geometry":{"coordinates":[-40.150397,-11.706542],"type":"Point"},"properties":{"osm_id":"5310233398","tag":{"natural":"tree"}},"type":"Feature"},
	{"geometry":{"coordinates":[-40.150714,-11.70658],"type":"Point"},"properties":{"osm_id":"5310235222","tag":{"natural":"tree"}},"type":"Feature"},
	{"geometry":{"coordinates":[-40.147205,-11.707416],"type":"Point"},"properties":{"osm_id":"5310285869","tag":{"natural":"tree"}},"type":"Feature"},
	{"geometry":{"coordinates":[-40.14712,-11.70854],"type":"Point"},"properties":{"osm_id":"5310290415","tag":{"natural":"tree"}},"type":"Feature"},
	{"geometry":{"coordinates":[-40.147216,-11.708572],"type":"Point"},"properties":{"osm_id":"5310291883","tag":{"natural":"tree"}},"type":"Feature"},
	{"geometry":{"coordinates":[-40.147227,-11.707878],"type":"Point"},"properties":{"osm_id":"5310291968","tag":{"natural":"tree"}},"type":"Feature"},
	{"geometry":{"coordinates":[-40.151143,-11.704516],"type":"Point"},"properties":{"osm_id":"5310293259","tag":{"natural":"tree"}},"type":"Feature"},
	{"geometry":{"coordinates":[-40.151133,-11.704817],"type":"Point"},"properties":{"osm_id":"5310295529","tag":{"natural":"tree"}},"type":"Feature"},
	{"geometry":{"coordinates":[-40.150917,-11.704412],"type":"Point"},"properties":{"osm_id":"5310295537","tag":{"natural":"tree"}},"type":"Feature"}
]
}
