{
"type": "FeatureCollection",
"features": [
	{"geometry":{"coordinates":[5.072968,43.741811],"type":"Point"},"properties":{"osm_id":"634932748","tag":{"amenity":"recycling","location":"overground","recycling:glass_bottles":"yes","recycling:paper":"yes","recycling:plastic":"no","recycling:plastic_packaging":"yes","recycling_type":"container"}},"type":"Feature"}
]
}
