{
"type": "FeatureCollection",
"features": [
	{"geometry":{"coordinates":[5.072968,43.741811],"type":"Point"},"properties":{"osm_id":"634932748","tag":{"amenity":"recycling","location":"overground","recycling:cans":"yes","recycling:glass":"yes","recycling:paper":"yes","recycling_type":"container"}},"type":"Feature"}
]
}
