{
"type": "FeatureCollection",
"features": [
	{"geometry":{"coordinates":[-47.811364,-23.018125],"type":"Point"},"properties":{"osm_id":"6386997518","tag":{"addr:city":"Laranjal Paulista","addr:postcode":"18500-000","addr:street":"Estrada Municipal do Bairro Entre Rios","addr:suburb":"Entre Rios","amenity":"waste_disposal","fee":"no","opening_hours":"24/7"}},"type":"Feature"}
]
}
