{
"type": "FeatureCollection",
"features": [
	{"geometry":{"coordinates":[8.66679,51.504807],"type":"Point"},"properties":{"osm_id":"1340939338","tag":{"natural":"tree"}},"type":"Feature"},
	{"geometry":{"coordinates":[8.658017,51.467331],"type":"Point"},"properties":{"name":"Naturdenkmal Eiche","osm_id":"1735025918","tag":{"leisure":"nature_reserve","natural":"tree","type":"Eiche"}},"type":"Feature"},
	{"geometry":{"coordinates":[8.655845,51.46545],"type":"Point"},"properties":{"name":"Naturdenkmal Eiche","osm_id":"1735049498","tag":{"leisure":"nature_reserve","natural":"tree","type":"Eiche"}},"type":"Feature"},
	{"geometry":{"coordinates":[8.654415,51.465825],"type":"Point"},"properties":{"name":"Naturdenkmal Eiche","osm_id":"1735049518","tag":{"leisure":"nature_reserve","natural":"tree","type":"Eiche"}},"type":"Feature"},
	{"geometry":{"coordinates":[8.656146,51.465883],"type":"Point"},"properties":{"name":"Naturdenkmal Eiche","osm_id":"1735049552","tag":{"leisure":"nature_reserve","natural":"tree","type":"Eiche"}},"type":"Feature"},
	{"geometry":{"coordinates":[8.613285,51.502884],"type":"Point"},"properties":{"osm_id":"3012121580","tag":{"leisure":"nature_reserve","natural":"tree"}},"type":"Feature"}
]
}
