{
"type": "FeatureCollection",
"features": [
	{"geometry":{"coordinates":[8.673274,48.806714],"type":"Point"},"properties":{"osm_id":"358467907","tag":{"natural":"tree"}},"type":"Feature"},
	{"geometry":{"coordinates":[8.685213,48.769942],"type":"Point"},"properties":{"name":"Luther-Eiche","osm_id":"359191988","tag":{"genus":"Quercus","genus:de":"Eiche","leaf_cycle":"deciduous","leaf_type":"broadleaved","monument":"yes","natural":"tree","wikidata":"Q58013740"}},"type":"Feature"},
	{"geometry":{"coordinates":[8.654536,48.79671],"type":"Point"},"properties":{"osm_id":"2968450135","tag":{"leaf_type":"broadleaved","natural":"tree"}},"type":"Feature"},
	{"geometry":{"coordinates":[8.672482,48.75029],"type":"Point"},"properties":{"osm_id":"3791857918","tag":{"denotation":"landmark","leaf_cycle":"deciduous","leaf_type":"broadleaved","natural":"tree"}},"type":"Feature"}
]
}
