{
"type": "FeatureCollection",
"features": [
	{"geometry":{"coordinates":[8.673274,48.806713],"type":"Point"},"properties":{"osm_id":"358467907","tag":{"natural":"tree"}},"type":"Feature"},
	{"geometry":{"coordinates":[8.685213,48.769941],"type":"Point"},"properties":{"name":"Luther-Eiche","osm_id":"359191988","tag":{"genus":"Quercus","genus:de":"Eiche","leaf_cycle":"deciduous","leaf_type":"broadleaved","monument":"yes","natural":"tree","wikidata":"Q58013740"}},"type":"Feature"},
	{"geometry":{"coordinates":[8.654535,48.796709],"type":"Point"},"properties":{"osm_id":"2968450135","tag":{"leaf_type":"broadleaved","natural":"tree"}},"type":"Feature"},
	{"geometry":{"coordinates":[8.672481,48.75029],"type":"Point"},"properties":{"osm_id":"3791857918","tag":{"denotation":"landmark","leaf_cycle":"deciduous","leaf_type":"broadleaved","natural":"tree"}},"type":"Feature"},
	{"geometry":{"coordinates":[8.699734,48.781587],"type":"Point"},"properties":{"osm_id":"8755810285","tag":{"denotation":"single","height":"20","leaf_cycle":"deciduous","leaf_type":"broadleaved","natural":"tree"}},"type":"Feature"}
]
}
