{
"type": "FeatureCollection",
"features": [
	{"geometry":{"coordinates":[8.696217,44.717832],"type":"Point"},"properties":{"name":"Quercia delle Rapaline","osm_id":"1067843571","tag":{"natural":"tree"}},"type":"Feature"},
	{"geometry":{"coordinates":[8.668073,44.733434],"type":"Point"},"properties":{"osm_id":"1080294049","tag":{"natural":"tree"}},"type":"Feature"},
	{"geometry":{"coordinates":[8.619221,44.755608],"type":"Point"},"properties":{"osm_id":"4002976359","tag":{"leaf_cycle":"deciduous","leaf_type":"broadleaved","natural":"tree"}},"type":"Feature"},
	{"geometry":{"coordinates":[8.619236,44.755667],"type":"Point"},"properties":{"osm_id":"4002976360","tag":{"leaf_cycle":"deciduous","leaf_type":"broadleaved","natural":"tree"}},"type":"Feature"},
	{"geometry":{"coordinates":[8.619575,44.756738],"type":"Point"},"properties":{"osm_id":"4002976361","tag":{"leaf_cycle":"deciduous","leaf_type":"broadleaved","natural":"tree"}},"type":"Feature"},
	{"geometry":{"coordinates":[8.619556,44.756672],"type":"Point"},"properties":{"osm_id":"4002976362","tag":{"leaf_cycle":"deciduous","leaf_type":"broadleaved","natural":"tree"}},"type":"Feature"},
	{"geometry":{"coordinates":[8.619525,44.756597],"type":"Point"},"properties":{"osm_id":"4002976363","tag":{"leaf_cycle":"deciduous","leaf_type":"broadleaved","natural":"tree"}},"type":"Feature"},
	{"geometry":{"coordinates":[8.619501,44.756505],"type":"Point"},"properties":{"osm_id":"4002976364","tag":{"leaf_cycle":"deciduous","leaf_type":"broadleaved","natural":"tree"}},"type":"Feature"},
	{"geometry":{"coordinates":[8.619478,44.756422],"type":"Point"},"properties":{"osm_id":"4002976365","tag":{"leaf_cycle":"deciduous","leaf_type":"broadleaved","natural":"tree"}},"type":"Feature"},
	{"geometry":{"coordinates":[8.619457,44.756349],"type":"Point"},"properties":{"osm_id":"4002976366","tag":{"leaf_cycle":"deciduous","leaf_type":"broadleaved","natural":"tree"}},"type":"Feature"},
	{"geometry":{"coordinates":[8.619407,44.756205],"type":"Point"},"properties":{"osm_id":"4002976367","tag":{"leaf_cycle":"deciduous","leaf_type":"broadleaved","natural":"tree"}},"type":"Feature"},
	{"geometry":{"coordinates":[8.619272,44.755792],"type":"Point"},"properties":{"osm_id":"4002976368","tag":{"leaf_cycle":"deciduous","leaf_type":"broadleaved","natural":"tree"}},"type":"Feature"},
	{"geometry":{"coordinates":[8.619332,44.756003],"type":"Point"},"properties":{"osm_id":"4002976369","tag":{"leaf_cycle":"deciduous","leaf_type":"broadleaved","natural":"tree"}},"type":"Feature"},
	{"geometry":{"coordinates":[8.619245,44.755716],"type":"Point"},"properties":{"osm_id":"4002976370","tag":{"leaf_cycle":"deciduous","leaf_type":"broadleaved","natural":"tree"}},"type":"Feature"},
	{"geometry":{"coordinates":[8.619306,44.7559],"type":"Point"},"properties":{"osm_id":"4002977529","tag":{"leaf_cycle":"deciduous","leaf_type":"broadleaved","natural":"tree"}},"type":"Feature"},
	{"geometry":{"coordinates":[8.619374,44.756116],"type":"Point"},"properties":{"osm_id":"4002977530","tag":{"leaf_cycle":"deciduous","leaf_type":"broadleaved","natural":"tree"}},"type":"Feature"},
	{"geometry":{"coordinates":[8.688251,44.739778],"type":"Point"},"properties":{"osm_id":"7853858541","tag":{"natural":"tree"}},"type":"Feature"},
	{"geometry":{"coordinates":[8.688198,44.739416],"type":"Point"},"properties":{"osm_id":"7853858542","tag":{"natural":"tree"}},"type":"Feature"},
	{"geometry":{"coordinates":[8.688414,44.739335],"type":"Point"},"properties":{"osm_id":"7853858543","tag":{"natural":"tree"}},"type":"Feature"}
]
}
