{
"type": "FeatureCollection",
"features": [
	{"geometry":{"coordinates":[8.427919,48.601497],"type":"Point"},"properties":{"name":"Spechtbaum","osm_id":"1501699072","tag":{"natural":"tree"}},"type":"Feature"},
	{"geometry":{"coordinates":[8.415385,48.599718],"type":"Point"},"properties":{"osm_id":"2609583674","tag":{"natural":"tree"}},"type":"Feature"},
	{"geometry":{"coordinates":[8.418615,48.601117],"type":"Point"},"properties":{"osm_id":"2609583683","tag":{"natural":"tree"}},"type":"Feature"},
	{"geometry":{"coordinates":[8.419034,48.594104],"type":"Point"},"properties":{"osm_id":"2609651846","tag":{"natural":"tree"}},"type":"Feature"},
	{"geometry":{"coordinates":[8.41983,48.594641],"type":"Point"},"properties":{"osm_id":"2609651849","tag":{"natural":"tree"}},"type":"Feature"}
]
}
