{
"type": "FeatureCollection",
"features": [
	{"geometry":{"coordinates":[8.367097,25.111438],"type":"Point"},"properties":{"osm_id":"6949163417","tag":{"natural":"tree"}},"type":"Feature"},
	{"geometry":{"coordinates":[8.3695,25.111356],"type":"Point"},"properties":{"osm_id":"6949163418","tag":{"natural":"tree"}},"type":"Feature"},
	{"geometry":{"coordinates":[8.366711,25.112556],"type":"Point"},"properties":{"osm_id":"6949163420","tag":{"natural":"tree"}},"type":"Feature"},
	{"geometry":{"coordinates":[8.3678,25.110457],"type":"Point"},"properties":{"osm_id":"6949163431","tag":{"natural":"tree"}},"type":"Feature"},
	{"geometry":{"coordinates":[8.365965,25.110477],"type":"Point"},"properties":{"osm_id":"6949163436","tag":{"natural":"tree"}},"type":"Feature"},
	{"geometry":{"coordinates":[8.367934,25.110861],"type":"Point"},"properties":{"osm_id":"6949163451","tag":{"natural":"tree"}},"type":"Feature"},
	{"geometry":{"coordinates":[8.369398,25.111269],"type":"Point"},"properties":{"osm_id":"6949163455","tag":{"natural":"tree"}},"type":"Feature"},
	{"geometry":{"coordinates":[8.367011,25.111511],"type":"Point"},"properties":{"osm_id":"6949174692","tag":{"natural":"tree"}},"type":"Feature"},
	{"geometry":{"coordinates":[8.368095,25.110904],"type":"Point"},"properties":{"osm_id":"6949174702","tag":{"natural":"tree"}},"type":"Feature"},
	{"geometry":{"coordinates":[8.369559,25.111541],"type":"Point"},"properties":{"osm_id":"6949174720","tag":{"natural":"tree"}},"type":"Feature"},
	{"geometry":{"coordinates":[8.369731,25.111735],"type":"Point"},"properties":{"osm_id":"6949174729","tag":{"natural":"tree"}},"type":"Feature"},
	{"geometry":{"coordinates":[8.366743,25.112109],"type":"Point"},"properties":{"osm_id":"6949174732","tag":{"natural":"tree"}},"type":"Feature"},
	{"geometry":{"coordinates":[8.368975,25.110778],"type":"Point"},"properties":{"osm_id":"6949174744","tag":{"natural":"tree"}},"type":"Feature"},
	{"geometry":{"coordinates":[8.373379,25.092318],"type":"Point"},"properties":{"osm_id":"6949211486","tag":{"natural":"tree"}},"type":"Feature"},
	{"geometry":{"coordinates":[8.391197,25.094022],"type":"Point"},"properties":{"osm_id":"7659177915","tag":{"natural":"tree"}},"type":"Feature"},
	{"geometry":{"coordinates":[8.391148,25.095108],"type":"Point"},"properties":{"osm_id":"7659177916","tag":{"natural":"tree"}},"type":"Feature"},
	{"geometry":{"coordinates":[8.392443,25.093477],"type":"Point"},"properties":{"osm_id":"7659177917","tag":{"natural":"tree"}},"type":"Feature"},
	{"geometry":{"coordinates":[8.390592,25.094619],"type":"Point"},"properties":{"osm_id":"7659177918","tag":{"natural":"tree"}},"type":"Feature"},
	{"geometry":{"coordinates":[8.390475,25.094243],"type":"Point"},"properties":{"osm_id":"7659177919","tag":{"natural":"tree"}},"type":"Feature"},
	{"geometry":{"coordinates":[8.390279,25.094975],"type":"Point"},"properties":{"osm_id":"7659177920","tag":{"natural":"tree"}},"type":"Feature"},
	{"geometry":{"coordinates":[8.38977,25.095102],"type":"Point"},"properties":{"osm_id":"7659177921","tag":{"natural":"tree"}},"type":"Feature"},
	{"geometry":{"coordinates":[8.388649,25.094729],"type":"Point"},"properties":{"osm_id":"7659177922","tag":{"natural":"tree"}},"type":"Feature"},
	{"geometry":{"coordinates":[8.3909,25.094831],"type":"Point"},"properties":{"osm_id":"7659177923","tag":{"natural":"tree"}},"type":"Feature"},
	{"geometry":{"coordinates":[8.378971,25.095198],"type":"Point"},"properties":{"osm_id":"7756761440","tag":{"description":"Acacia","natural":"tree"}},"type":"Feature"},
	{"geometry":{"coordinates":[8.378679,25.096479],"type":"Point"},"properties":{"name":"Acacia","osm_id":"7756761441","tag":{"natural":"tree"}},"type":"Feature"},
	{"geometry":{"coordinates":[8.379699,25.096788],"type":"Point"},"properties":{"name":"Acacia","osm_id":"7756761442","tag":{"natural":"tree"}},"type":"Feature"}
]
}
