{
"type": "FeatureCollection",
"features": [
	{"geometry":{"coordinates":[16.441696,43.517383],"type":"Point"},"properties":{"osm_id":"1226972880","tag":{"amenity":"recycling","recycling:paper":"yes"}},"type":"Feature"},
	{"geometry":{"coordinates":[16.449323,43.517653],"type":"Point"},"properties":{"osm_id":"1349427084","tag":{"amenity":"waste_basket"}},"type":"Feature"},
	{"geometry":{"coordinates":[16.477411,43.517474],"type":"Point"},"properties":{"osm_id":"1877420966","tag":{"amenity":"recycling"}},"type":"Feature"},
	{"geometry":{"coordinates":[16.493422,43.54077],"type":"Point"},"properties":{"osm_id":"2496140214","tag":{"amenity":"recycling","location":"overground","recycling:glass":"yes","recycling:paper":"yes","recycling_type":"container","source:amenity":"survey"}},"type":"Feature"},
	{"geometry":{"coordinates":[16.492903,43.540633],"type":"Point"},"properties":{"osm_id":"2499288524","tag":{"amenity":"waste_basket"}},"type":"Feature"},
	{"geometry":{"coordinates":[16.492762,43.540599],"type":"Point"},"properties":{"osm_id":"2499316187","tag":{"amenity":"waste_basket"}},"type":"Feature"},
	{"geometry":{"coordinates":[16.445883,43.520308],"type":"Point"},"properties":{"osm_id":"2525043389","tag":{"amenity":"recycling","recycling:paper":"yes","source:amenity":"survey"}},"type":"Feature"},
	{"geometry":{"coordinates":[16.44599,43.519015],"type":"Point"},"properties":{"osm_id":"2527818876","tag":{"amenity":"recycling","location":"overground","recycling:paper":"yes","recycling:plastic_packaging":"yes","recycling_type":"container"}},"type":"Feature"},
	{"geometry":{"coordinates":[16.493666,43.533009],"type":"Point"},"properties":{"osm_id":"2746549160","tag":{"amenity":"waste_disposal","waste":"trash"}},"type":"Feature"},
	{"geometry":{"coordinates":[16.502569,43.534658],"type":"Point"},"properties":{"osm_id":"2746601298","tag":{"amenity":"waste_disposal"}},"type":"Feature"},
	{"geometry":{"coordinates":[16.442294,43.518225],"type":"Point"},"properties":{"osm_id":"2786351360","tag":{"amenity":"waste_basket"}},"type":"Feature"},
	{"geometry":{"coordinates":[16.446834,43.516714],"type":"Point"},"properties":{"osm_id":"3032257039","tag":{"amenity":"recycling"}},"type":"Feature"},
	{"geometry":{"coordinates":[16.447158,43.542783],"type":"Point"},"properties":{"name":"Cios","osm_id":"3977281433","tag":{"amenity":"recycling","recycling:scrap_metal":"yes","recycling_type":"centre"}},"type":"Feature"},
	{"geometry":{"coordinates":[16.470675,43.518429],"type":"Point"},"properties":{"osm_id":"4111690292","tag":{"amenity":"recycling","recycling:beverage_cartons":"yes","recycling:paper":"yes","recycling:plastic":"yes","recycling_type":"container"}},"type":"Feature"},
	{"geometry":{"coordinates":[16.47074,43.518388],"type":"Point"},"properties":{"osm_id":"4114086057","tag":{"amenity":"waste_disposal"}},"type":"Feature"},
	{"geometry":{"coordinates":[16.451142,43.518573],"type":"Point"},"properties":{"osm_id":"4559241278","tag":{"amenity":"recycling","recycling_type":"container"}},"type":"Feature"},
	{"geometry":{"coordinates":[16.465332,43.543216],"type":"Point"},"properties":{"osm_id":"5078523586","tag":{"amenity":"recycling","location":"overground","recycling_type":"container"}},"type":"Feature"},
	{"geometry":{"coordinates":[16.483315,43.541541],"type":"Point"},"properties":{"osm_id":"5083689990","tag":{"amenity":"waste_basket"}},"type":"Feature"},
	{"geometry":{"coordinates":[16.483255,43.541111],"type":"Point"},"properties":{"osm_id":"5083703439","tag":{"amenity":"waste_basket"}},"type":"Feature"},
	{"geometry":{"coordinates":[16.455334,43.524444],"type":"Point"},"properties":{"name":"Tehnomobil","osm_id":"5892915069","tag":{"amenity":"recycling","opening_hours":"Mo-Fr 08:00-15:00, Sa 08:00-12:00","recycling:batteries":"yes","recycling:electrical_appliances":"yes","recycling:small_appliances":"yes","recycling_type":"centre"}},"type":"Feature"},
	{"geometry":{"coordinates":[16.460017,43.522],"type":"Point"},"properties":{"osm_id":"6870071425","tag":{"amenity":"waste_disposal"}},"type":"Feature"}
]
}
