{
"type": "FeatureCollection",
"lastupdate": "2020-08-02T00:00:00Z",
"features": [
	{"geometry":{"coordinates":[16.441695,43.517383],"type":"Point"},"properties":{"osm_id":"1226972880","tag":{"amenity":"recycling","recycling:paper":"yes"}},"type":"Feature"},
	{"geometry":{"coordinates":[16.449322,43.517653],"type":"Point"},"properties":{"osm_id":"1349427084","tag":{"amenity":"waste_basket"}},"type":"Feature"},
	{"geometry":{"coordinates":[16.477411,43.517474],"type":"Point"},"properties":{"osm_id":"1877420966","tag":{"amenity":"recycling"}},"type":"Feature"},
	{"geometry":{"coordinates":[16.493421,43.540769],"type":"Point"},"properties":{"osm_id":"2496140214","tag":{"amenity":"recycling","location":"overground","recycling:glass":"yes","recycling:paper":"yes","recycling_type":"container","source:amenity":"survey"}},"type":"Feature"},
	{"geometry":{"coordinates":[16.492902,43.540632],"type":"Point"},"properties":{"osm_id":"2499288524","tag":{"amenity":"waste_basket"}},"type":"Feature"},
	{"geometry":{"coordinates":[16.492761,43.540598],"type":"Point"},"properties":{"osm_id":"2499316187","tag":{"amenity":"waste_basket"}},"type":"Feature"},
	{"geometry":{"coordinates":[16.445883,43.520307],"type":"Point"},"properties":{"osm_id":"2525043389","tag":{"amenity":"recycling","recycling:paper":"yes","source:amenity":"survey"}},"type":"Feature"},
	{"geometry":{"coordinates":[16.44599,43.519014],"type":"Point"},"properties":{"osm_id":"2527818876","tag":{"amenity":"recycling","location":"overground","recycling:paper":"yes","recycling:plastic_packaging":"yes","recycling_type":"container"}},"type":"Feature"},
	{"geometry":{"coordinates":[16.442294,43.518224],"type":"Point"},"properties":{"osm_id":"2786351360","tag":{"amenity":"waste_basket"}},"type":"Feature"},
	{"geometry":{"coordinates":[16.446834,43.516714],"type":"Point"},"properties":{"osm_id":"3032257039","tag":{"amenity":"recycling"}},"type":"Feature"},
	{"geometry":{"coordinates":[16.447158,43.542782],"type":"Point"},"properties":{"name":"Cios","osm_id":"3977281433","tag":{"amenity":"recycling","recycling:scrap_metal":"yes","recycling_type":"centre"}},"type":"Feature"},
	{"geometry":{"coordinates":[16.470674,43.518429],"type":"Point"},"properties":{"osm_id":"4111690292","tag":{"amenity":"recycling","recycling:beverage_cartons":"yes","recycling:paper":"yes","recycling:plastic":"yes","recycling_type":"container"}},"type":"Feature"},
	{"geometry":{"coordinates":[16.451141,43.518572],"type":"Point"},"properties":{"osm_id":"4559241278","tag":{"amenity":"recycling","recycling_type":"container"}},"type":"Feature"},
	{"geometry":{"coordinates":[16.465332,43.543216],"type":"Point"},"properties":{"osm_id":"5078523586","tag":{"amenity":"recycling","location":"overground","recycling_type":"container"}},"type":"Feature"},
	{"geometry":{"coordinates":[16.483314,43.54154],"type":"Point"},"properties":{"osm_id":"5083689990","tag":{"amenity":"waste_basket"}},"type":"Feature"},
	{"geometry":{"coordinates":[16.483254,43.541111],"type":"Point"},"properties":{"osm_id":"5083703439","tag":{"amenity":"waste_basket"}},"type":"Feature"},
	{"geometry":{"coordinates":[16.455334,43.524444],"type":"Point"},"properties":{"name":"Tehnomobil","osm_id":"5892915069","tag":{"amenity":"recycling","opening_hours":"Mo-Fr 08:00-15:00, Sa 08:00-12:00","recycling:batteries":"yes","recycling:electrical_appliances":"yes","recycling:small_appliances":"yes","recycling_type":"centre"}},"type":"Feature"}
]
}
