{
"type": "FeatureCollection",
"lastupdate": "2020-08-03T00:00:00Z",
"features": [
	{"geometry":{"coordinates":[-79.527104,43.833117],"type":"Point"},"properties":{"name":"Vaughan Household Hazardous Waste Depot","osm_id":"600243445","tag":{"addr:housenumber":"2840","addr:street":"Rutherford Road","amenity":"recycling","recycling_type":"centre"}},"type":"Feature"},
	{"geometry":{"coordinates":[-79.503419,43.771789],"type":"Point"},"properties":{"osm_id":"1112667750","tag":{"amenity":"waste_basket"}},"type":"Feature"},
	{"geometry":{"coordinates":[-79.503855,43.7717],"type":"Point"},"properties":{"osm_id":"1112671917","tag":{"amenity":"waste_basket"}},"type":"Feature"},
	{"geometry":{"coordinates":[-79.4562,43.783851],"type":"Point"},"properties":{"osm_id":"1415528106","tag":{"amenity":"recycling","recycling_type":"container"}},"type":"Feature"},
	{"geometry":{"coordinates":[-79.456285,43.783932],"type":"Point"},"properties":{"osm_id":"1415528507","tag":{"amenity":"waste_basket"}},"type":"Feature"},
	{"geometry":{"coordinates":[-79.457605,43.785584],"type":"Point"},"properties":{"osm_id":"1415532241","tag":{"amenity":"waste_basket"}},"type":"Feature"},
	{"geometry":{"coordinates":[-79.457578,43.785624],"type":"Point"},"properties":{"osm_id":"1415532468","tag":{"amenity":"recycling","recycling_type":"container"}},"type":"Feature"},
	{"geometry":{"coordinates":[-79.457015,43.786845],"type":"Point"},"properties":{"osm_id":"1415535527","tag":{"amenity":"waste_basket"}},"type":"Feature"},
	{"geometry":{"coordinates":[-79.457042,43.786893],"type":"Point"},"properties":{"osm_id":"1415536160","tag":{"amenity":"recycling","recycling_type":"container"}},"type":"Feature"},
	{"geometry":{"coordinates":[-79.456048,43.802259],"type":"Point"},"properties":{"osm_id":"2798950801","tag":{"amenity":"waste_basket"}},"type":"Feature"},
	{"geometry":{"coordinates":[-79.460839,43.779525],"type":"Point"},"properties":{"osm_id":"4778740559","tag":{"amenity":"waste_basket"}},"type":"Feature"},
	{"geometry":{"coordinates":[-79.458387,43.77995],"type":"Point"},"properties":{"osm_id":"4778740560","tag":{"amenity":"waste_basket"}},"type":"Feature"},
	{"geometry":{"coordinates":[-79.456203,43.816492],"type":"Point"},"properties":{"osm_id":"7754357037","tag":{"amenity":"waste_basket","colour":"black","material":"metal","waste":"trash"}},"type":"Feature"},
	{"geometry":{"coordinates":[-79.456226,43.816485],"type":"Point"},"properties":{"osm_id":"7754357038","tag":{"amenity":"waste_basket","colour":"blue","material":"metal","waste":"recycling"}},"type":"Feature"}
]
}
