{
"type": "FeatureCollection",
"features": [
	{"geometry":{"coordinates":[134.010204,34.094314],"type":"Point"},"properties":{"name":"\u00e4\u00b8\u0089\u00e8\u00a7\u0092\u00e3\u0081\u00ae\u00e3\u0082\u00ab\u00e3\u0083\u0084\u00e3\u0083\u00a9","osm_id":"765707242","tag":{"description":"\u00e9\u00a6\u0099\u00e5\u00b7\u009d\u00e3\u0081\u00ae\u00e4\u00bf\u009d\u00e5\u00ad\u0098\u00e6\u009c\u00a8","leaf_type":"broadleaved","name:botanical":"\u00e3\u0082\u00ab\u00e3\u0083\u0084\u00e3\u0083\u00a9","natural":"tree","type":"broad_leaved"}},"type":"Feature"},
	{"geometry":{"coordinates":[133.993371,34.105404],"type":"Point"},"properties":{"osm_id":"7993829136","tag":{"leaf_cycle":"deciduous","leaf_type":"broadleaved","natural":"tree"}},"type":"Feature"},
	{"geometry":{"coordinates":[133.993631,34.105179],"type":"Point"},"properties":{"osm_id":"7993829137","tag":{"leaf_cycle":"deciduous","leaf_type":"broadleaved","natural":"tree"}},"type":"Feature"},
	{"geometry":{"coordinates":[133.99351,34.105279],"type":"Point"},"properties":{"osm_id":"7993829138","tag":{"leaf_cycle":"deciduous","leaf_type":"broadleaved","natural":"tree"}},"type":"Feature"},
	{"geometry":{"coordinates":[133.993479,34.105308],"type":"Point"},"properties":{"osm_id":"7993829139","tag":{"leaf_cycle":"deciduous","leaf_type":"broadleaved","natural":"tree"}},"type":"Feature"},
	{"geometry":{"coordinates":[133.993402,34.105373],"type":"Point"},"properties":{"osm_id":"7993829140","tag":{"leaf_cycle":"deciduous","leaf_type":"broadleaved","natural":"tree"}},"type":"Feature"},
	{"geometry":{"coordinates":[133.99344,34.105343],"type":"Point"},"properties":{"osm_id":"7993829141","tag":{"leaf_cycle":"deciduous","leaf_type":"broadleaved","natural":"tree"}},"type":"Feature"},
	{"geometry":{"coordinates":[133.993546,34.105246],"type":"Point"},"properties":{"osm_id":"7993829142","tag":{"leaf_cycle":"deciduous","leaf_type":"broadleaved","natural":"tree"}},"type":"Feature"},
	{"geometry":{"coordinates":[133.99358,34.105218],"type":"Point"},"properties":{"osm_id":"7993829143","tag":{"leaf_cycle":"deciduous","leaf_type":"broadleaved","natural":"tree"}},"type":"Feature"}
]
}
