{
"type": "FeatureCollection",
"features": [
	{"geometry":{"coordinates":[134.010204,34.094314],"type":"Point"},"properties":{"name":"\u00e4\u00b8\u0089\u00e8\u00a7\u0092\u00e3\u0081\u00ae\u00e3\u0082\u00ab\u00e3\u0083\u0084\u00e3\u0083\u00a9","osm_id":"765707242","tag":{"description":"\u00e9\u00a6\u0099\u00e5\u00b7\u009d\u00e3\u0081\u00ae\u00e4\u00bf\u009d\u00e5\u00ad\u0098\u00e6\u009c\u00a8","leaf_type":"broadleaved","name:botanical":"\u00e3\u0082\u00ab\u00e3\u0083\u0084\u00e3\u0083\u00a9","natural":"tree","type":"broad_leaved"}},"type":"Feature"}
]
}
