{
"type": "FeatureCollection",
"features": [
	{"geometry":{"coordinates":[119.917628,-3.082548],"type":"Point"},"properties":{"name":"Kambira baby graves","osm_id":"4198124889","tag":{"natural":"tree","tourism":"attraction"}},"type":"Feature"}
]
}
