{
"type": "FeatureCollection",
"features": [
	{"geometry":{"coordinates":[-3.204093,42.25497],"type":"Point"},"properties":{"name":"Haya de Enrique del Rivero","osm_id":"8279898488","tag":{"genus:es":"Haya","natural":"tree"}},"type":"Feature"}
]
}
