{
"type": "FeatureCollection",
"features": [
	{"geometry":{"coordinates":[-3.204392,40.345709],"type":"Point"},"properties":{"name":"Encina de la Pica","osm_id":"4524608693","tag":{"natural":"tree"}},"type":"Feature"},
	{"geometry":{"coordinates":[-3.167021,40.328234],"type":"Point"},"properties":{"osm_id":"8292975548","tag":{"natural":"tree"}},"type":"Feature"},
	{"geometry":{"coordinates":[-3.167269,40.328531],"type":"Point"},"properties":{"osm_id":"8292975549","tag":{"natural":"tree"}},"type":"Feature"},
	{"geometry":{"coordinates":[-3.169269,40.328674],"type":"Point"},"properties":{"osm_id":"8292975550","tag":{"natural":"tree"}},"type":"Feature"},
	{"geometry":{"coordinates":[-3.167403,40.326966],"type":"Point"},"properties":{"osm_id":"8292975551","tag":{"natural":"tree"}},"type":"Feature"},
	{"geometry":{"coordinates":[-3.167521,40.326876],"type":"Point"},"properties":{"osm_id":"8292975552","tag":{"natural":"tree"}},"type":"Feature"},
	{"geometry":{"coordinates":[-3.169139,40.325946],"type":"Point"},"properties":{"osm_id":"8292975553","tag":{"natural":"tree"}},"type":"Feature"},
	{"geometry":{"coordinates":[-3.17088,40.324265],"type":"Point"},"properties":{"osm_id":"8292975604","tag":{"natural":"tree"}},"type":"Feature"},
	{"geometry":{"coordinates":[-3.171566,40.325943],"type":"Point"},"properties":{"osm_id":"8292975605","tag":{"natural":"tree"}},"type":"Feature"},
	{"geometry":{"coordinates":[-3.166419,40.316397],"type":"Point"},"properties":{"osm_id":"8292975625","tag":{"natural":"tree"}},"type":"Feature"},
	{"geometry":{"coordinates":[-3.167245,40.314702],"type":"Point"},"properties":{"osm_id":"8292975626","tag":{"natural":"tree"}},"type":"Feature"}
]
}
