{
"type": "FeatureCollection",
"features": [
	{"geometry":{"coordinates":[-3.204393,40.34571],"type":"Point"},"properties":{"name":"Encina de la Pica","osm_id":"4524608693","tag":{"natural":"tree"}},"type":"Feature"}
]
}
