{
"type": "FeatureCollection",
"features": [
	{"geometry":{"coordinates":[-3.204392,40.345709],"type":"Point"},"properties":{"name":"Encina de la Pica","osm_id":"4524608693","tag":{"natural":"tree"}},"type":"Feature"}
]
}
