{
"type": "FeatureCollection",
"lastupdate": "2020-08-03T00:00:00Z",
"features": [
	{"geometry":{"coordinates":[125.544479,9.738866],"type":"Point"},"properties":{"name":"Materials Recovery Facility","osm_id":"6243725245","tag":{"amenity":"recycling","recycling_type":"centre"}},"type":"Feature"}
]
}
