{
"type": "FeatureCollection",
"features": [
	{"geometry":{"coordinates":[125.544042,9.740654],"type":"Point"},"properties":{"name":"Materials Recovery Facility","osm_id":"6243715994","tag":{"amenity":"waste_disposal"}},"type":"Feature"},
	{"geometry":{"coordinates":[125.544479,9.738866],"type":"Point"},"properties":{"name":"Materials Recovery Facility","osm_id":"6243725245","tag":{"amenity":"recycling","recycling_type":"centre"}},"type":"Feature"},
	{"geometry":{"coordinates":[125.544202,9.737856],"type":"Point"},"properties":{"name":"Materials Recovery Facility","osm_id":"6243749234","tag":{"amenity":"waste_disposal"}},"type":"Feature"},
	{"geometry":{"coordinates":[125.554142,9.740029],"type":"Point"},"properties":{"name":"Materials Recovery Facility","osm_id":"6243784920","tag":{"amenity":"waste_disposal"}},"type":"Feature"},
	{"geometry":{"coordinates":[125.541081,9.748283],"type":"Point"},"properties":{"name":"Materials Recovery Facility","osm_id":"6245793649","tag":{"amenity":"waste_disposal"}},"type":"Feature"}
]
}
