{
"type": "FeatureCollection",
"features": [
	{"geometry":{"coordinates":[125.524024,9.536063],"type":"Point"},"properties":{"name":"Materials Recovery Facility","osm_id":"6240955986","tag":{"amenity":"waste_disposal"}},"type":"Feature"},
	{"geometry":{"coordinates":[125.524053,9.538235],"type":"Point"},"properties":{"name":"Materials Recovery Facility","osm_id":"6241036852","tag":{"amenity":"waste_disposal"}},"type":"Feature"},
	{"geometry":{"coordinates":[125.520987,9.535913],"type":"Point"},"properties":{"name":"P- Rosal MRF","osm_id":"6241110743","tag":{"amenity":"waste_disposal"}},"type":"Feature"},
	{"geometry":{"coordinates":[125.52074,9.536035],"type":"Point"},"properties":{"name":"P- Lesio MRF","osm_id":"6241121458","tag":{"amenity":"waste_disposal"}},"type":"Feature"}
]
}
