{
"type": "FeatureCollection",
"features": [
	{"geometry":{"coordinates":[125.576299,7.037186],"type":"Point"},"properties":{"name":"Balay ni Janrey","osm_id":"5645821585","tag":{"amenity":"waste_basket"}},"type":"Feature"}
]
}
