{
"type": "FeatureCollection",
"lastupdate": "2020-08-04T00:00:00Z",
"features": [
	{"geometry":{"coordinates":[-74.206146,45.82881],"type":"Point"},"properties":{"osm_id":"4197073032","tag":{"amenity":"recycling"}},"type":"Feature"},
	{"geometry":{"coordinates":[-74.181967,45.886834],"type":"Point"},"properties":{"name":"Eco-Centre St-Sauveur","osm_id":"4449743757","tag":{"amenity":"recycling"}},"type":"Feature"}
]
}
