{
"type": "FeatureCollection",
"features": [
	{"geometry":{"coordinates":[-74.206147,45.82881],"type":"Point"},"properties":{"osm_id":"4197073032","tag":{"amenity":"recycling"}},"type":"Feature"},
	{"geometry":{"coordinates":[-74.181968,45.886834],"type":"Point"},"properties":{"name":"Eco-Centre St-Sauveur","osm_id":"4449743757","tag":{"amenity":"recycling"}},"type":"Feature"}
]
}
