{
"type": "FeatureCollection",
"features": [
	{"geometry":{"coordinates":[-5.693939,38.260301],"type":"Point"},"properties":{"name":"Recicar","osm_id":"4866072447","tag":{"amenity":"recycling","recycling_type":"centre"}},"type":"Feature"}
]
}
