{
"type": "FeatureCollection",
"lastupdate": "2020-07-31T00:00:00Z",
"features": [
	{"geometry":{"coordinates":[-5.693938,38.2603],"type":"Point"},"properties":{"name":"Recicar","osm_id":"4866072447","tag":{"amenity":"recycling","recycling_type":"centre"}},"type":"Feature"}
]
}
