{
"type": "FeatureCollection",
"features": [
	{"geometry":{"coordinates":[17.698347,40.398598],"type":"Point"},"properties":{"name":"pino","osm_id":"3070856395","tag":{"natural":"tree"}},"type":"Feature"},
	{"geometry":{"coordinates":[17.742708,40.423003],"type":"Point"},"properties":{"name":"il grande leccio","osm_id":"3260839594","tag":{"natural":"tree"}},"type":"Feature"}
]
}
