{
"type": "FeatureCollection",
"features": [
	{"geometry":{"coordinates":[-122.520684,47.624807],"type":"Point"},"properties":{"osm_id":"4459967394","tag":{"amenity":"waste_basket"}},"type":"Feature"},
	{"geometry":{"coordinates":[-122.520696,47.624807],"type":"Point"},"properties":{"osm_id":"4459967395","tag":{"amenity":"recycling"}},"type":"Feature"},
	{"geometry":{"coordinates":[-122.519565,47.624916],"type":"Point"},"properties":{"osm_id":"4459981231","tag":{"amenity":"waste_basket"}},"type":"Feature"},
	{"geometry":{"coordinates":[-122.519541,47.624919],"type":"Point"},"properties":{"osm_id":"4459981232","tag":{"amenity":"recycling","location":"overground","recycling_type":"container"}},"type":"Feature"},
	{"geometry":{"coordinates":[-122.520123,47.624761],"type":"Point"},"properties":{"osm_id":"4459981233","tag":{"amenity":"waste_basket"}},"type":"Feature"},
	{"geometry":{"coordinates":[-122.519544,47.624765],"type":"Point"},"properties":{"osm_id":"4459983792","tag":{"amenity":"recycling","location":"overground","recycling_type":"container"}},"type":"Feature"},
	{"geometry":{"coordinates":[-122.519706,47.625244],"type":"Point"},"properties":{"osm_id":"4461192791","tag":{"amenity":"waste_basket"}},"type":"Feature"},
	{"geometry":{"coordinates":[-122.51973,47.625384],"type":"Point"},"properties":{"osm_id":"4461192793","tag":{"amenity":"waste_basket"}},"type":"Feature"},
	{"geometry":{"coordinates":[-122.521516,47.624819],"type":"Point"},"properties":{"osm_id":"5470076828","tag":{"amenity":"recycling","recycling:clothes":"yes","recycling_type":"container"}},"type":"Feature"},
	{"geometry":{"coordinates":[-122.521284,47.624975],"type":"Point"},"properties":{"osm_id":"5470076830","tag":{"amenity":"waste_basket"}},"type":"Feature"},
	{"geometry":{"coordinates":[-122.522171,47.624986],"type":"Point"},"properties":{"osm_id":"5470077868","tag":{"amenity":"waste_basket"}},"type":"Feature"},
	{"geometry":{"coordinates":[-122.528638,47.584093],"type":"Point"},"properties":{"osm_id":"7057316445","tag":{"amenity":"waste_basket"}},"type":"Feature"}
]
}
