{
"type": "FeatureCollection",
"features": [
	{"geometry":{"coordinates":[-122.593439,45.378226],"type":"Point"},"properties":{"osm_id":"3572570487","tag":{"amenity":"waste_basket"}},"type":"Feature"},
	{"geometry":{"coordinates":[-122.589931,45.370459],"type":"Point"},"properties":{"name":"Metro South Hazardous Waste Facility","osm_id":"8758932466","tag":{"amenity":"recycling","recycling:hazardous_waste":"yes","recycling_type":"centre"}},"type":"Feature"}
]
}
