{
"type": "FeatureCollection",
"features": [
	{"geometry":{"coordinates":[-3.864046,37.303106],"type":"Point"},"properties":{"name":"Encina del Romero","osm_id":"3078600776","tag":{"denotation":"natural_monument","monument":"yes","natural":"tree"}},"type":"Feature"}
]
}
