{
"type": "FeatureCollection",
"lastupdate": "2020-08-02T00:00:00Z",
"features": [
	{"geometry":{"coordinates":[-88.30875,43.314852],"type":"Point"},"properties":{"name":"RV dump","osm_id":"262527144","tag":{"amenity":"recycling"}},"type":"Feature"}
]
}
