{
"type": "FeatureCollection",
"features": [
	{"geometry":{"coordinates":[-72.791907,-39.853633],"type":"Point"},"properties":{"name":"Contenedor Grande Pancul","osm_id":"4947470934","tag":{"amenity":"waste_disposal"}},"type":"Feature"}
]
}
