{
"type": "FeatureCollection",
"features": [
	{"geometry":{"coordinates":[10.82046,53.421021],"type":"Point"},"properties":{"name":"Hudebuche","osm_id":"3450367455","tag":{"natural":"tree"}},"type":"Feature"}
]
}
