{
"type": "FeatureCollection",
"features": [
	{"geometry":{"coordinates":[10.851175,51.862434],"type":"Point"},"properties":{"osm_id":"863290712","tag":{"natural":"tree"}},"type":"Feature"},
	{"geometry":{"coordinates":[10.826246,51.837328],"type":"Point"},"properties":{"osm_id":"2173831787","tag":{"name:botanical":"Prunus avium","natural":"tree","type":"Kirsche"}},"type":"Feature"}
]
}
