{
"type": "FeatureCollection",
"features": [
	{"geometry":{"coordinates":[18.54231,50.098251],"type":"Point"},"properties":{"osm_id":"2406362742","tag":{"amenity":"waste_basket"}},"type":"Feature"},
	{"geometry":{"coordinates":[18.542184,50.097371],"type":"Point"},"properties":{"osm_id":"2462977542","tag":{"amenity":"waste_basket"}},"type":"Feature"},
	{"geometry":{"coordinates":[18.543918,50.095079],"type":"Point"},"properties":{"osm_id":"2466380061","tag":{"amenity":"waste_basket"}},"type":"Feature"},
	{"geometry":{"coordinates":[18.543956,50.095132],"type":"Point"},"properties":{"osm_id":"2466380091","tag":{"amenity":"waste_basket"}},"type":"Feature"},
	{"geometry":{"coordinates":[18.543928,50.095187],"type":"Point"},"properties":{"osm_id":"2466380112","tag":{"amenity":"waste_basket"}},"type":"Feature"},
	{"geometry":{"coordinates":[18.543967,50.09524],"type":"Point"},"properties":{"osm_id":"2466380133","tag":{"amenity":"waste_basket"}},"type":"Feature"},
	{"geometry":{"coordinates":[18.543938,50.095295],"type":"Point"},"properties":{"osm_id":"2466380152","tag":{"amenity":"waste_basket"}},"type":"Feature"},
	{"geometry":{"coordinates":[18.543976,50.095347],"type":"Point"},"properties":{"osm_id":"2466380187","tag":{"amenity":"waste_basket"}},"type":"Feature"},
	{"geometry":{"coordinates":[18.543949,50.095401],"type":"Point"},"properties":{"osm_id":"2466380201","tag":{"amenity":"waste_basket"}},"type":"Feature"},
	{"geometry":{"coordinates":[18.514194,50.103906],"type":"Point"},"properties":{"osm_id":"2892223207","tag":{"amenity":"waste_basket"}},"type":"Feature"},
	{"geometry":{"coordinates":[18.535084,50.100604],"type":"Point"},"properties":{"osm_id":"3251971616","tag":{"amenity":"waste_basket","source:geometry":"geoportal.gov.pl:ortofoto"}},"type":"Feature"},
	{"geometry":{"coordinates":[18.506685,50.10533],"type":"Point"},"properties":{"osm_id":"4214198564","tag":{"amenity":"waste_basket"}},"type":"Feature"},
	{"geometry":{"coordinates":[18.543104,50.099804],"type":"Point"},"properties":{"osm_id":"4290851477","tag":{"amenity":"waste_basket"}},"type":"Feature"},
	{"geometry":{"coordinates":[18.53432,50.093013],"type":"Point"},"properties":{"name":"Olmet","osm_id":"5565919288","tag":{"amenity":"recycling","fax":"+48 32 472 07 80","opening_hours":"Mo-Fr 07:30-17:00; Sa 07:30-14:00","phone":"+48 32 472 07 77","website":"http://olmet.pl"}},"type":"Feature"},
	{"geometry":{"coordinates":[18.47394,50.105347],"type":"Point"},"properties":{"osm_id":"7806868385","tag":{"amenity":"waste_basket"}},"type":"Feature"},
	{"geometry":{"coordinates":[18.473115,50.105615],"type":"Point"},"properties":{"osm_id":"7806868386","tag":{"amenity":"waste_basket"}},"type":"Feature"},
	{"geometry":{"coordinates":[18.476239,50.104563],"type":"Point"},"properties":{"osm_id":"7806868387","tag":{"amenity":"waste_basket"}},"type":"Feature"},
	{"geometry":{"coordinates":[18.478775,50.104138],"type":"Point"},"properties":{"osm_id":"7806868389","tag":{"amenity":"waste_basket"}},"type":"Feature"},
	{"geometry":{"coordinates":[18.480127,50.103497],"type":"Point"},"properties":{"osm_id":"7806868390","tag":{"amenity":"waste_basket"}},"type":"Feature"}
]
}
