{
"type": "FeatureCollection",
"features": [
	{"geometry":{"coordinates":[18.54231,50.098251],"type":"Point"},"properties":{"osm_id":"2406362742","tag":{"amenity":"waste_basket"}},"type":"Feature"},
	{"geometry":{"coordinates":[18.542184,50.097372],"type":"Point"},"properties":{"osm_id":"2462977542","tag":{"amenity":"waste_basket"}},"type":"Feature"},
	{"geometry":{"coordinates":[18.543919,50.095079],"type":"Point"},"properties":{"osm_id":"2466380061","tag":{"amenity":"waste_basket"}},"type":"Feature"},
	{"geometry":{"coordinates":[18.543957,50.095133],"type":"Point"},"properties":{"osm_id":"2466380091","tag":{"amenity":"waste_basket"}},"type":"Feature"},
	{"geometry":{"coordinates":[18.543928,50.095187],"type":"Point"},"properties":{"osm_id":"2466380112","tag":{"amenity":"waste_basket"}},"type":"Feature"},
	{"geometry":{"coordinates":[18.543967,50.095241],"type":"Point"},"properties":{"osm_id":"2466380133","tag":{"amenity":"waste_basket"}},"type":"Feature"},
	{"geometry":{"coordinates":[18.543939,50.095296],"type":"Point"},"properties":{"osm_id":"2466380152","tag":{"amenity":"waste_basket"}},"type":"Feature"},
	{"geometry":{"coordinates":[18.543977,50.095348],"type":"Point"},"properties":{"osm_id":"2466380187","tag":{"amenity":"waste_basket"}},"type":"Feature"},
	{"geometry":{"coordinates":[18.54395,50.095402],"type":"Point"},"properties":{"osm_id":"2466380201","tag":{"amenity":"waste_basket"}},"type":"Feature"},
	{"geometry":{"coordinates":[18.514194,50.103906],"type":"Point"},"properties":{"osm_id":"2892223207","tag":{"amenity":"waste_basket"}},"type":"Feature"},
	{"geometry":{"coordinates":[18.535084,50.100604],"type":"Point"},"properties":{"osm_id":"3251971616","tag":{"amenity":"waste_basket","source:geometry":"geoportal.gov.pl:ortofoto"}},"type":"Feature"},
	{"geometry":{"coordinates":[18.506685,50.10533],"type":"Point"},"properties":{"osm_id":"4214198564","tag":{"amenity":"waste_basket"}},"type":"Feature"},
	{"geometry":{"coordinates":[18.543105,50.099805],"type":"Point"},"properties":{"osm_id":"4290851477","tag":{"amenity":"waste_basket"}},"type":"Feature"},
	{"geometry":{"coordinates":[18.534321,50.093014],"type":"Point"},"properties":{"name":"Olmet","osm_id":"5565919288","tag":{"amenity":"recycling","fax":"+48 32 472 07 80","opening_hours":"Mo-Fr 07:30-17:00; Sa 07:30-14:00","phone":"+48 32 472 07 77","website":"http://olmet.pl"}},"type":"Feature"},
	{"geometry":{"coordinates":[18.474761,50.106578],"type":"Point"},"properties":{"osm_id":"7806867284","tag":{"amenity":"waste_disposal"}},"type":"Feature"},
	{"geometry":{"coordinates":[18.473939,50.105386],"type":"Point"},"properties":{"osm_id":"7806868385","tag":{"amenity":"waste_basket"}},"type":"Feature"},
	{"geometry":{"coordinates":[18.473115,50.105616],"type":"Point"},"properties":{"osm_id":"7806868386","tag":{"amenity":"waste_basket"}},"type":"Feature"},
	{"geometry":{"coordinates":[18.47624,50.104564],"type":"Point"},"properties":{"osm_id":"7806868387","tag":{"amenity":"waste_basket"}},"type":"Feature"},
	{"geometry":{"coordinates":[18.478776,50.104139],"type":"Point"},"properties":{"osm_id":"7806868389","tag":{"amenity":"waste_basket"}},"type":"Feature"},
	{"geometry":{"coordinates":[18.480128,50.103497],"type":"Point"},"properties":{"osm_id":"7806868390","tag":{"amenity":"waste_basket"}},"type":"Feature"},
	{"geometry":{"coordinates":[18.474958,50.106928],"type":"Point"},"properties":{"osm_id":"7825421829","tag":{"amenity":"waste_disposal"}},"type":"Feature"},
	{"geometry":{"coordinates":[18.47478,50.106605],"type":"Point"},"properties":{"osm_id":"7825421830","tag":{"amenity":"recycling","recycling_type":"container"}},"type":"Feature"},
	{"geometry":{"coordinates":[18.474793,50.106634],"type":"Point"},"properties":{"osm_id":"7825421831","tag":{"amenity":"recycling","recycling_type":"container"}},"type":"Feature"},
	{"geometry":{"coordinates":[18.474801,50.106625],"type":"Point"},"properties":{"osm_id":"7825421832","tag":{"amenity":"recycling","recycling_type":"container"}},"type":"Feature"},
	{"geometry":{"coordinates":[18.474813,50.106663],"type":"Point"},"properties":{"osm_id":"7825421833","tag":{"amenity":"recycling","recycling_type":"container"}},"type":"Feature"}
]
}
