{
"type": "FeatureCollection",
"features": [
	{"geometry":{"coordinates":[22.341948,49.221756],"type":"Point"},"properties":{"osm_id":"4802713627","tag":{"leaf_type":"broadleaved","natural":"tree"}},"type":"Feature"},
	{"geometry":{"coordinates":[22.365854,49.263897],"type":"Point"},"properties":{"name":"Ciekawe drzewo","osm_id":"5249357823","tag":{"natural":"tree"}},"type":"Feature"}
]
}
