{
"type": "FeatureCollection",
"features": [
	{"geometry":{"coordinates":[11.726346,48.263256],"type":"Point"},"properties":{"osm_id":"537161276","tag":{"natural":"tree"}},"type":"Feature"},
	{"geometry":{"coordinates":[11.729049,48.264284],"type":"Point"},"properties":{"osm_id":"537161313","tag":{"natural":"tree"}},"type":"Feature"},
	{"geometry":{"coordinates":[11.710953,48.258518],"type":"Point"},"properties":{"name":"Apfelbaum","osm_id":"6480013151","tag":{"natural":"tree"}},"type":"Feature"}
]
}
