{
"type": "FeatureCollection",
"features": [
	{"geometry":{"coordinates":[11.726346,48.263256],"type":"Point"},"properties":{"osm_id":"537161276","tag":{"natural":"tree"}},"type":"Feature"},
	{"geometry":{"coordinates":[11.729049,48.264284],"type":"Point"},"properties":{"osm_id":"537161313","tag":{"natural":"tree"}},"type":"Feature"},
	{"geometry":{"coordinates":[11.710953,48.258518],"type":"Point"},"properties":{"name":"Apfelbaum","osm_id":"6480013151","tag":{"natural":"tree"}},"type":"Feature"},
	{"geometry":{"coordinates":[11.692308,48.240573],"type":"Point"},"properties":{"name":"Hagebutten","osm_id":"8109796396","tag":{"natural":"tree","wikidata":"Q46740","wikipedia":"en:Rose hip"}},"type":"Feature"},
	{"geometry":{"coordinates":[11.690238,48.240855],"type":"Point"},"properties":{"name":"Hagebutten","osm_id":"8109901954","tag":{"natural":"tree","wikidata":"Q46740","wikipedia":"en:Rose hip"}},"type":"Feature"}
]
}
