{
"type": "FeatureCollection",
"features": [
	{"geometry":{"coordinates":[11.726346,48.263256],"type":"Point"},"properties":{"osm_id":"537161276","tag":{"natural":"tree"}},"type":"Feature"},
	{"geometry":{"coordinates":[11.729049,48.264284],"type":"Point"},"properties":{"osm_id":"537161313","tag":{"natural":"tree"}},"type":"Feature"},
	{"geometry":{"coordinates":[11.710953,48.258518],"type":"Point"},"properties":{"name":"Apfelbaum","osm_id":"6480013151","tag":{"natural":"tree"}},"type":"Feature"},
	{"geometry":{"coordinates":[11.692308,48.240573],"type":"Point"},"properties":{"name":"Hagebutten","osm_id":"8109796396","tag":{"natural":"tree","wikidata":"Q46740","wikipedia":"en:Rose hip"}},"type":"Feature"},
	{"geometry":{"coordinates":[11.690382,48.240837],"type":"Point"},"properties":{"name":"Hagebutten","osm_id":"8109901954","tag":{"natural":"tree","wikidata":"Q46740","wikipedia":"en:Rose hip"}},"type":"Feature"},
	{"geometry":{"coordinates":[11.737604,48.230814],"type":"Point"},"properties":{"osm_id":"8199446034","tag":{"natural":"tree"}},"type":"Feature"},
	{"geometry":{"coordinates":[11.73878,48.231041],"type":"Point"},"properties":{"osm_id":"8199446035","tag":{"natural":"tree"}},"type":"Feature"},
	{"geometry":{"coordinates":[11.692117,48.240575],"type":"Point"},"properties":{"osm_id":"8200057503","tag":{"natural":"tree","wikidata":"Q46740","wikipedia":"en:Rose hip"}},"type":"Feature"},
	{"geometry":{"coordinates":[11.694507,48.2383],"type":"Point"},"properties":{"osm_id":"8200219385","tag":{"natural":"tree"}},"type":"Feature"}
]
}
