{
"type": "FeatureCollection",
"features": [
	{"geometry":{"coordinates":[11.726347,48.263257],"type":"Point"},"properties":{"osm_id":"537161276","tag":{"natural":"tree"}},"type":"Feature"},
	{"geometry":{"coordinates":[11.729049,48.264284],"type":"Point"},"properties":{"osm_id":"537161313","tag":{"natural":"tree"}},"type":"Feature"},
	{"geometry":{"coordinates":[11.710954,48.258519],"type":"Point"},"properties":{"name":"Apfelbaum","osm_id":"6480013151","tag":{"natural":"tree"}},"type":"Feature"}
]
}
