{
"type": "FeatureCollection",
"features": [
	{"geometry":{"coordinates":[11.73499,47.642823],"type":"Point"},"properties":{"osm_id":"2500070462","tag":{"natural":"tree"}},"type":"Feature"},
	{"geometry":{"coordinates":[11.736539,47.643213],"type":"Point"},"properties":{"osm_id":"2500070463","tag":{"natural":"tree"}},"type":"Feature"},
	{"geometry":{"coordinates":[11.727879,47.673324],"type":"Point"},"properties":{"name":"Alte Tann","osm_id":"3922778600","tag":{"natural":"tree"}},"type":"Feature"},
	{"geometry":{"coordinates":[11.742648,47.694952],"type":"Point"},"properties":{"osm_id":"4260629755","tag":{"natural":"tree"}},"type":"Feature"},
	{"geometry":{"coordinates":[11.772709,47.675643],"type":"Point"},"properties":{"osm_id":"4314176813","tag":{"natural":"tree"}},"type":"Feature"},
	{"geometry":{"coordinates":[11.772626,47.675887],"type":"Point"},"properties":{"osm_id":"4314176821","tag":{"natural":"tree"}},"type":"Feature"},
	{"geometry":{"coordinates":[11.770516,47.689093],"type":"Point"},"properties":{"osm_id":"4321762924","tag":{"leaf_type":"broadleaved","natural":"tree"}},"type":"Feature"},
	{"geometry":{"coordinates":[11.774809,47.675543],"type":"Point"},"properties":{"osm_id":"4566719592","tag":{"natural":"tree"}},"type":"Feature"},
	{"geometry":{"coordinates":[11.774933,47.675384],"type":"Point"},"properties":{"osm_id":"4566719593","tag":{"natural":"tree"}},"type":"Feature"},
	{"geometry":{"coordinates":[11.77471,47.675783],"type":"Point"},"properties":{"osm_id":"4566719594","tag":{"natural":"tree"}},"type":"Feature"},
	{"geometry":{"coordinates":[11.773079,47.675675],"type":"Point"},"properties":{"osm_id":"4566719595","tag":{"natural":"tree"}},"type":"Feature"}
]
}
