{
"type": "FeatureCollection",
"features": [
	{"geometry":{"coordinates":[11.73499,47.642823],"type":"Point"},"properties":{"osm_id":"2500070462","tag":{"natural":"tree"}},"type":"Feature"},
	{"geometry":{"coordinates":[11.736539,47.643214],"type":"Point"},"properties":{"osm_id":"2500070463","tag":{"natural":"tree"}},"type":"Feature"},
	{"geometry":{"coordinates":[11.727879,47.673325],"type":"Point"},"properties":{"name":"Alte Tann","osm_id":"3922778600","tag":{"natural":"tree"}},"type":"Feature"},
	{"geometry":{"coordinates":[11.742649,47.694953],"type":"Point"},"properties":{"osm_id":"4260629755","tag":{"natural":"tree"}},"type":"Feature"},
	{"geometry":{"coordinates":[11.77271,47.675644],"type":"Point"},"properties":{"osm_id":"4314176813","tag":{"natural":"tree"}},"type":"Feature"},
	{"geometry":{"coordinates":[11.772626,47.675888],"type":"Point"},"properties":{"osm_id":"4314176821","tag":{"natural":"tree"}},"type":"Feature"},
	{"geometry":{"coordinates":[11.770516,47.689093],"type":"Point"},"properties":{"osm_id":"4321762924","tag":{"leaf_type":"broadleaved","natural":"tree"}},"type":"Feature"},
	{"geometry":{"coordinates":[11.77481,47.675543],"type":"Point"},"properties":{"osm_id":"4566719592","tag":{"natural":"tree"}},"type":"Feature"},
	{"geometry":{"coordinates":[11.774933,47.675384],"type":"Point"},"properties":{"osm_id":"4566719593","tag":{"natural":"tree"}},"type":"Feature"},
	{"geometry":{"coordinates":[11.774711,47.675783],"type":"Point"},"properties":{"osm_id":"4566719594","tag":{"natural":"tree"}},"type":"Feature"},
	{"geometry":{"coordinates":[11.77308,47.675676],"type":"Point"},"properties":{"osm_id":"4566719595","tag":{"natural":"tree"}},"type":"Feature"}
]
}
