{
"type": "FeatureCollection",
"features": [
	{"geometry":{"coordinates":[7.238932,51.698006],"type":"Point"},"properties":{"name":"Eiche","osm_id":"733728252","tag":{"natural":"tree"}},"type":"Feature"},
	{"geometry":{"coordinates":[7.250328,51.684834],"type":"Point"},"properties":{"name":"Alte Buche","osm_id":"1493448371","tag":{"denotation":"natural_monument","leaf_cycle":"deciduous","leaf_type":"broadleaved","natural":"tree"}},"type":"Feature"},
	{"geometry":{"coordinates":[7.227488,51.70764],"type":"Point"},"properties":{"name":"Rotbuche","osm_id":"2416112791","tag":{"denotation":"natural_monument","natural":"tree"}},"type":"Feature"},
	{"geometry":{"coordinates":[7.234032,51.704795],"type":"Point"},"properties":{"name":"Rotbuche","osm_id":"2416115654","tag":{"denotation":"natural_monument","natural":"tree"}},"type":"Feature"},
	{"geometry":{"coordinates":[7.24116,51.718733],"type":"Point"},"properties":{"osm_id":"7712114270","tag":{"leaf_cycle":"deciduous","leaf_type":"broadleaved","natural":"tree"}},"type":"Feature"}
]
}
