{
"type": "FeatureCollection",
"features": [
	{"geometry":{"coordinates":[7.238933,51.698007],"type":"Point"},"properties":{"name":"Eiche","osm_id":"733728252","tag":{"natural":"tree"}},"type":"Feature"},
	{"geometry":{"coordinates":[7.227488,51.707641],"type":"Point"},"properties":{"name":"Rotbuche","osm_id":"2416112791","tag":{"denotation":"natural_monument","natural":"tree"}},"type":"Feature"},
	{"geometry":{"coordinates":[7.234033,51.704795],"type":"Point"},"properties":{"name":"Rotbuche","osm_id":"2416115654","tag":{"denotation":"natural_monument","natural":"tree"}},"type":"Feature"},
	{"geometry":{"coordinates":[7.241161,51.718734],"type":"Point"},"properties":{"osm_id":"7712114270","tag":{"leaf_cycle":"deciduous","leaf_type":"broadleaved","natural":"tree"}},"type":"Feature"}
]
}
