{
"type": "FeatureCollection",
"features": [
	{"geometry":{"coordinates":[7.275289,49.739206],"type":"Point"},"properties":{"name":"Friedenseiche","osm_id":"332722726","tag":{"natural":"tree","start_date":"1871"}},"type":"Feature"}
]
}
