{
"type": "FeatureCollection",
"features": [
	{"geometry":{"coordinates":[-85.05475,31.67848],"type":"Point"},"properties":{"name":"Dumpster","osm_id":"4069945315","tag":{"amenity":"waste_basket"}},"type":"Feature"},
	{"geometry":{"coordinates":[-85.054655,31.678568],"type":"Point"},"properties":{"osm_id":"4069945384","tag":{"amenity":"recycling","recycling:cans":"yes","recycling_type":"container"}},"type":"Feature"},
	{"geometry":{"coordinates":[-85.054687,31.67853],"type":"Point"},"properties":{"name":"Dumpster","osm_id":"4069954793","tag":{"amenity":"waste_basket"}},"type":"Feature"},
	{"geometry":{"coordinates":[-85.054721,31.678503],"type":"Point"},"properties":{"name":"Dumpster","osm_id":"4069954805","tag":{"amenity":"waste_basket"}},"type":"Feature"},
	{"geometry":{"coordinates":[-85.053872,31.678411],"type":"Point"},"properties":{"name":"Poop Basket","osm_id":"4073902109","tag":{"amenity":"waste_basket"}},"type":"Feature"}
]
}
