{
"type": "FeatureCollection",
"lastupdate": "2020-08-02T00:00:00Z",
"features": [
	{"geometry":{"coordinates":[-85.05475,31.67848],"type":"Point"},"properties":{"name":"Dumpster","osm_id":"4069945315","tag":{"amenity":"waste_basket"}},"type":"Feature"},
	{"geometry":{"coordinates":[-85.054655,31.678567],"type":"Point"},"properties":{"osm_id":"4069945384","tag":{"amenity":"recycling","recycling:cans":"yes","recycling_type":"container"}},"type":"Feature"},
	{"geometry":{"coordinates":[-85.054687,31.678529],"type":"Point"},"properties":{"name":"Dumpster","osm_id":"4069954793","tag":{"amenity":"waste_basket"}},"type":"Feature"},
	{"geometry":{"coordinates":[-85.05472,31.678502],"type":"Point"},"properties":{"name":"Dumpster","osm_id":"4069954805","tag":{"amenity":"waste_basket"}},"type":"Feature"},
	{"geometry":{"coordinates":[-85.053871,31.678411],"type":"Point"},"properties":{"name":"Poop Basket","osm_id":"4073902109","tag":{"amenity":"waste_basket"}},"type":"Feature"}
]
}
