{
"type": "FeatureCollection",
"features": [
	{"geometry":{"coordinates":[-82.129718,35.000193],"type":"Point"},"properties":{"name":"Wellford Recylcling Center","osm_id":"6378934746","tag":{"addr:city":"Wellford","addr:housenumber":"595","addr:postcode":"29385","addr:state":"SC","addr:street":"Little Mountain Road","addr:unit":"A","amenity":"recycling","opening_hours":"Mo-Sa 07:00-19:00","operator":"Spartanburg County","operator:type":"government","phone":"864-949-1658","recycling_type":"centre"}},"type":"Feature"}
]
}
