{
"type": "FeatureCollection",
"features": [
	{"geometry":{"coordinates":[-82.139323,34.249311],"type":"Point"},"properties":{"name":"Solid Waste Collection and Recycling Convenience Center","osm_id":"5593506951","tag":{"addr:housenumber":"321","addr:street":"Bucklevel Road","amenity":"recycling","opening_hours":"Mo,Th,Fr 07:00-18:00; Sa 08:00-18:00; Su 13:00-17:00; Tu,We off","operator":"Greenwood County Public Works Department","operator:type":"government","recycling:aluminium":"yes","recycling:cans":"yes","recycling:cardboard":"yes","recycling:electrical_appliances":"yes","recycling:glass":"yes","recycling:green_waste":"yes","recycling:paper":"yes","recycling:plastic":"yes","recycling:scrap_metal":"yes","recycling:waste":"yes","recycling:wood":"yes","recycling_type":"centre"}},"type":"Feature"}
]
}
