{
"type": "FeatureCollection",
"lastupdate": "2020-08-04T00:00:00Z",
"features": [
	{"geometry":{"coordinates":[-82.139089,34.249548],"type":"Point"},"properties":{"name":"Solid Waste and Recycling Convenience Center","osm_id":"5593506951","tag":{"addr:street":"Bucklevel Road","amenity":"recycling","opening_hours":"Mo,Th,Fr 07:00-18:00; Sa 08:00-18:00; Su 13:00-17:00; Tu,We off","operator":"Greenwood County","recycling:cardboard":"yes","recycling:electrical_appliances":"yes","recycling:glass":"yes","recycling:paper":"yes","recycling:plastic":"yes","recycling:waste":"yes","recycling_type":"centre"}},"type":"Feature"}
]
}
