{
"type": "FeatureCollection",
"features": [
	{"geometry":{"coordinates":[-5.172055,57.917494],"type":"Point"},"properties":{"name":"Ullapool Recycling Centre","osm_id":"2155948824","tag":{"amenity":"recycling","owner":"Highland Council","ownership":"municipal","recycling_type":"centre","wikidata":"Q106085791"}},"type":"Feature"},
	{"geometry":{"coordinates":[-5.166017,57.896283],"type":"Point"},"properties":{"osm_id":"5103309336","tag":{"amenity":"waste_basket"}},"type":"Feature"},
	{"geometry":{"coordinates":[-5.1675,57.899204],"type":"Point"},"properties":{"osm_id":"5121424782","tag":{"amenity":"waste_basket"}},"type":"Feature"},
	{"geometry":{"coordinates":[-5.164081,57.896767],"type":"Point"},"properties":{"osm_id":"6720380169","tag":{"amenity":"recycling","recycling:clothes":"yes","recycling:glass_bottles":"yes","recycling_type":"container"}},"type":"Feature"},
	{"geometry":{"coordinates":[-5.161842,57.895934],"type":"Point"},"properties":{"osm_id":"6996962992","tag":{"amenity":"recycling"}},"type":"Feature"}
]
}
