{
"type": "FeatureCollection",
"features": [
	{"geometry":{"coordinates":[-5.128696,55.533246],"type":"Point"},"properties":{"osm_id":"7167191171","tag":{"amenity":"recycling","recycling:clothes":"yes","recycling:shoes":"yes","recycling_type":"container"}},"type":"Feature"},
	{"geometry":{"coordinates":[-5.128731,55.53326],"type":"Point"},"properties":{"osm_id":"8846606979","tag":{"amenity":"recycling","opening_hours":"24/7","recycling:aluminium":"yes","recycling:cans":"yes","recycling:cardboard":"yes","recycling:glass":"yes","recycling:glass_bottles":"yes","recycling:magazines":"yes","recycling:newspaper":"yes","recycling:paper":"yes","recycling:paper_packaging":"yes","recycling:plastic":"yes","recycling:plastic_bottles":"yes","recycling_type":"container"}},"type":"Feature"},
	{"geometry":{"coordinates":[-5.127844,55.575657],"type":"Point"},"properties":{"name":"Brodick Recycling Centre","osm_id":"9146878888","tag":{"amenity":"recycling","owner":"North Ayrshire Council","ownership":"municipal","recycling_type":"centre","wikidata":"Q106085831"}},"type":"Feature"}
]
}
