{
"type": "FeatureCollection",
"features": [
	{"geometry":{"coordinates":[-5.15419,36.41921],"type":"Point"},"properties":{"osm_id":"583267765","tag":{"amenity":"recycling"}},"type":"Feature"},
	{"geometry":{"coordinates":[-5.168886,36.418812],"type":"Point"},"properties":{"osm_id":"623939541","tag":{"amenity":"recycling","recycling:cans":"yes","recycling:glass":"yes","recycling:paper":"yes"}},"type":"Feature"},
	{"geometry":{"coordinates":[-5.148767,36.436994],"type":"Point"},"properties":{"name":"Punto Limpio Estepona","osm_id":"8168209187","tag":{"amenity":"recycling"}},"type":"Feature"}
]
}
