{
"type": "FeatureCollection",
"features": [
	{"geometry":{"coordinates":[101.766446,5.796598],"type":"Point"},"properties":{"name":"Baing tree","osm_id":"6888739143","tag":{"age":"900","denotation":"natural_monument","int_name":"Tetrameles nudiflora R.Br.","natural":"tree"}},"type":"Feature"}
]
}
