{
"type": "FeatureCollection",
"features": [
	{"geometry":{"coordinates":[20.565898,-19.691135],"type":"Point"},"properties":{"osm_id":"5840593373","tag":{"genus":"Adansonia","name:botanical":"Baobab","natural":"tree"}},"type":"Feature"}
]
}
