{
"type": "FeatureCollection",
"features": [
	{"geometry":{"coordinates":[92.035372,21.405641],"type":"Point"},"properties":{"osm_id":"5698796746","tag":{"addr:city":"\u00e0\u00a6\u0095\u00e0\u00a6\u0095\u00e0\u00a7\u008d\u00e0\u00a6\u00b8\u00e0\u00a6\u00ac\u00e0\u00a6\u00be\u00e0\u00a6\u009c\u00e0\u00a6\u00be\u00e0\u00a6\u00b0","addr:postcode":"\u00e0\u00a7\u00aa\u00e0\u00a7\u00ad\u00e0\u00a7\u00a6\u00e0\u00a7\u00a7","addr:street":"\u00e0\u00a6\u00ab\u00e0\u00a6\u00b0\u00e0\u00a6\u00bf\u00e0\u00a6\u00a6\u00e0\u00a7\u0087\u00e0\u00a6\u00b0 \u00e0\u00a6\u0098\u00e0\u00a7\u008b\u00e0\u00a6\u00a8\u00e0\u00a6\u00be","denotation":"single","leaf_cycle":"semi_evergreen","leaf_type":"leafless","natural":"tree"}},"type":"Feature"}
]
}
