{
"type": "FeatureCollection",
"features": [
	{"geometry":{"coordinates":[20.00683,50.0058],"type":"Point"},"properties":{"osm_id":"684711873","tag":{"amenity":"recycling","location":"overground","recycling_type":"container"}},"type":"Feature"},
	{"geometry":{"coordinates":[20.01037,50.006359],"type":"Point"},"properties":{"osm_id":"684711880","tag":{"amenity":"recycling","check_date":"2021-07-03","recycling:clothes":"yes","recycling:glass":"no","recycling:glass_bottles":"yes","recycling:paper":"yes","recycling:plastic":"yes","recycling:scrap_metal":"yes","recycling_type":"container"}},"type":"Feature"},
	{"geometry":{"coordinates":[20.037206,49.987272],"type":"Point"},"properties":{"osm_id":"1906011268","tag":{"amenity":"recycling","recycling_type":"container"}},"type":"Feature"},
	{"geometry":{"coordinates":[19.990573,49.979691],"type":"Point"},"properties":{"osm_id":"1937275658","tag":{"amenity":"recycling","recycling:glass":"yes","recycling:paper":"yes","recycling:plastic":"yes","recycling:scrap_metal":"yes","recycling_type":"container"}},"type":"Feature"},
	{"geometry":{"coordinates":[19.996476,49.993126],"type":"Point"},"properties":{"osm_id":"1937275721","tag":{"amenity":"recycling","recycling:clothes":"yes","recycling:glass":"yes","recycling:paper":"yes","recycling:plastic":"yes","recycling:scrap_metal":"yes","recycling_type":"container"}},"type":"Feature"},
	{"geometry":{"coordinates":[19.98911,49.994132],"type":"Point"},"properties":{"osm_id":"1937275737","tag":{"amenity":"recycling","recycling:glass":"yes","recycling:paper":"yes","recycling:plastic":"yes","recycling:scrap_metal":"yes","recycling_type":"container"}},"type":"Feature"},
	{"geometry":{"coordinates":[19.983155,50.005908],"type":"Point"},"properties":{"osm_id":"1937275788","tag":{"amenity":"recycling","recycling:glass":"yes","recycling:paper":"yes","recycling:plastic":"yes","recycling:scrap_metal":"yes","recycling_type":"container"}},"type":"Feature"},
	{"geometry":{"coordinates":[19.955525,50.006998],"type":"Point"},"properties":{"osm_id":"1937275796","tag":{"amenity":"recycling","recycling:clothes":"yes","recycling:glass":"yes","recycling:paper":"yes","recycling:plastic":"yes","recycling:scrap_metal":"yes","recycling_type":"container"}},"type":"Feature"},
	{"geometry":{"coordinates":[19.960842,50.007454],"type":"Point"},"properties":{"osm_id":"1937275813","tag":{"amenity":"recycling","recycling_type":"container"}},"type":"Feature"},
	{"geometry":{"coordinates":[19.960763,50.007638],"type":"Point"},"properties":{"osm_id":"1937275816","tag":{"amenity":"recycling","recycling_type":"container"}},"type":"Feature"},
	{"geometry":{"coordinates":[20.038156,49.988509],"type":"Point"},"properties":{"osm_id":"2100673070","tag":{"amenity":"recycling","recycling:batteries":"no","recycling:books":"no","recycling:cans":"no","recycling:cardboard":"no","recycling:cartons":"no","recycling:clothes":"yes","recycling:electrical_appliances":"no","recycling:glass":"no","recycling:glass_bottles":"no","recycling:green_waste":"no","recycling:magazines":"no","recycling:newspaper":"no","recycling:paper":"no","recycling:paper_packaging":"no","recycling:plastic":"no","recycling:plastic_bottles":"no","recycling:plastic_packaging":"no","recycling:scrap_metal":"no","recycling:small_appliances":"no","recycling:waste":"no","recycling:wood":"no","recycling_type":"container"}},"type":"Feature"},
	{"geometry":{"coordinates":[20.008867,50.005904],"type":"Point"},"properties":{"osm_id":"5352808044","tag":{"amenity":"recycling","recycling_type":"container"}},"type":"Feature"},
	{"geometry":{"coordinates":[20.007272,50.005751],"type":"Point"},"properties":{"osm_id":"5352808054","tag":{"amenity":"recycling","recycling_type":"container"}},"type":"Feature"},
	{"geometry":{"coordinates":[19.958584,50.004848],"type":"Point"},"properties":{"osm_id":"5433597169","tag":{"amenity":"waste_basket"}},"type":"Feature"},
	{"geometry":{"coordinates":[19.958608,50.005001],"type":"Point"},"properties":{"osm_id":"5433597170","tag":{"amenity":"waste_basket"}},"type":"Feature"},
	{"geometry":{"coordinates":[19.963232,50.004859],"type":"Point"},"properties":{"osm_id":"5433605148","tag":{"amenity":"waste_basket"}},"type":"Feature"},
	{"geometry":{"coordinates":[19.960103,50.004876],"type":"Point"},"properties":{"osm_id":"5433921730","tag":{"amenity":"recycling","recycling:glass":"yes","recycling_type":"container"}},"type":"Feature"},
	{"geometry":{"coordinates":[19.960045,50.00538],"type":"Point"},"properties":{"osm_id":"5433921731","tag":{"amenity":"recycling","recycling:clothes":"yes","recycling_type":"container"}},"type":"Feature"},
	{"geometry":{"coordinates":[19.958978,50.005648],"type":"Point"},"properties":{"osm_id":"5644778683","tag":{"amenity":"waste_basket"}},"type":"Feature"}
]
}
