{
"type": "FeatureCollection",
"features": [
	{"geometry":{"coordinates":[18.631746,53.112151],"type":"Point"},"properties":{"osm_id":"4706668037","tag":{"denotation":"natural_monument","natural":"tree","ref:CRFOP":"PL.ZIPOP.1393.PP.0415062.1162","ref:INSPIRE":"PL.ZIPOP.1393.PP.0415062.1162","website":"http://crfop.gdos.gov.pl/CRFOP/widok/viewfop.jsf?fop=PL.ZIPOP.1393.PP.0415062.1162"}},"type":"Feature"}
]
}
