{
"type": "FeatureCollection",
"features": [
	{"geometry":{"coordinates":[18.574126,52.678624],"type":"Point"},"properties":{"osm_id":"4706675804","tag":{"denotation":"natural_monument","natural":"tree","ref:CRFOP":"PL.ZIPOP.1393.PP.0411032.6062","ref:INSPIRE":"PL.ZIPOP.1393.PP.0411032.6062","website":"http://crfop.gdos.gov.pl/CRFOP/widok/viewfop.jsf?fop=PL.ZIPOP.1393.PP.0411032.6062"}},"type":"Feature"},
	{"geometry":{"coordinates":[18.573644,52.677963],"type":"Point"},"properties":{"osm_id":"4706675805","tag":{"denotation":"natural_monument","natural":"tree","ref:CRFOP":"PL.ZIPOP.1393.PP.0411032.6061","ref:INSPIRE":"PL.ZIPOP.1393.PP.0411032.6061","website":"http://crfop.gdos.gov.pl/CRFOP/widok/viewfop.jsf?fop=PL.ZIPOP.1393.PP.0411032.6061"}},"type":"Feature"},
	{"geometry":{"coordinates":[18.574467,52.678565],"type":"Point"},"properties":{"osm_id":"4706675806","tag":{"denotation":"natural_monument","natural":"tree","ref:CRFOP":"PL.ZIPOP.1393.PP.0411032.6060","ref:INSPIRE":"PL.ZIPOP.1393.PP.0411032.6060","website":"http://crfop.gdos.gov.pl/CRFOP/widok/viewfop.jsf?fop=PL.ZIPOP.1393.PP.0411032.6060"}},"type":"Feature"}
]
}
