{
"type": "FeatureCollection",
"features": [
	{"geometry":{"coordinates":[18.559499,52.544915],"type":"Point"},"properties":{"osm_id":"4706675808","tag":{"denotation":"natural_monument","natural":"tree","ref:CRFOP":"PL.ZIPOP.1393.PP.0411022.274","ref:INSPIRE":"PL.ZIPOP.1393.PP.0411022.274","website":"http://crfop.gdos.gov.pl/CRFOP/widok/viewfop.jsf?fop=PL.ZIPOP.1393.PP.0411022.274"}},"type":"Feature"},
	{"geometry":{"coordinates":[18.558295,52.544716],"type":"Point"},"properties":{"osm_id":"4706675809","tag":{"denotation":"natural_monument","natural":"tree","ref:CRFOP":"PL.ZIPOP.1393.PP.0411022.273","ref:INSPIRE":"PL.ZIPOP.1393.PP.0411022.273","website":"http://crfop.gdos.gov.pl/CRFOP/widok/viewfop.jsf?fop=PL.ZIPOP.1393.PP.0411022.273"}},"type":"Feature"},
	{"geometry":{"coordinates":[18.558346,52.544664],"type":"Point"},"properties":{"osm_id":"4706675810","tag":{"denotation":"natural_monument","natural":"tree","ref:CRFOP":"PL.ZIPOP.1393.PP.0411022.272","ref:INSPIRE":"PL.ZIPOP.1393.PP.0411022.272","website":"http://crfop.gdos.gov.pl/CRFOP/widok/viewfop.jsf?fop=PL.ZIPOP.1393.PP.0411022.272"}},"type":"Feature"},
	{"geometry":{"coordinates":[18.558853,52.545148],"type":"Point"},"properties":{"osm_id":"4706675811","tag":{"denotation":"natural_monument","natural":"tree","ref:CRFOP":"PL.ZIPOP.1393.PP.0411022.271","ref:INSPIRE":"PL.ZIPOP.1393.PP.0411022.271","website":"http://crfop.gdos.gov.pl/CRFOP/widok/viewfop.jsf?fop=PL.ZIPOP.1393.PP.0411022.271"}},"type":"Feature"}
]
}
