{
"type": "FeatureCollection",
"features": [
	{"geometry":{"coordinates":[-120.05587,36.97478],"type":"Point"},"properties":{"name":"Perez Recycling","osm_id":"2951613851","tag":{"amenity":"recycling"}},"type":"Feature"}
]
}
