{
"type": "FeatureCollection",
"lastupdate": "2020-08-03T00:00:00Z",
"features": [
	{"geometry":{"coordinates":[-120.055869,36.97478],"type":"Point"},"properties":{"name":"Perez Recycling","osm_id":"2951613851","tag":{"amenity":"recycling"}},"type":"Feature"}
]
}
