{
"type": "FeatureCollection",
"features": [
	{"geometry":{"coordinates":[19.56722,40.730868],"type":"Point"},"properties":{"osm_id":"6620666600","tag":{"amenity":"waste_disposal","waste":"trash"}},"type":"Feature"},
	{"geometry":{"coordinates":[19.567244,40.730832],"type":"Point"},"properties":{"osm_id":"6620666601","tag":{"amenity":"waste_disposal","waste":"trash"}},"type":"Feature"},
	{"geometry":{"coordinates":[19.566209,40.731175],"type":"Point"},"properties":{"osm_id":"6620731983","tag":{"amenity":"waste_disposal","waste":"trash"}},"type":"Feature"},
	{"geometry":{"coordinates":[19.566171,40.731178],"type":"Point"},"properties":{"osm_id":"6620731984","tag":{"amenity":"waste_disposal","waste":"trash"}},"type":"Feature"},
	{"geometry":{"coordinates":[19.555331,40.721327],"type":"Point"},"properties":{"osm_id":"6621245048","tag":{"amenity":"waste_disposal","waste":"trash"}},"type":"Feature"},
	{"geometry":{"coordinates":[19.555317,40.721308],"type":"Point"},"properties":{"osm_id":"6621245049","tag":{"amenity":"waste_disposal","waste":"trash"}},"type":"Feature"},
	{"geometry":{"coordinates":[19.567673,40.729847],"type":"Point"},"properties":{"osm_id":"6632989485","tag":{"amenity":"waste_disposal","waste":"trash"}},"type":"Feature"},
	{"geometry":{"coordinates":[19.567664,40.729859],"type":"Point"},"properties":{"osm_id":"6632989486","tag":{"amenity":"waste_disposal","waste":"trash"}},"type":"Feature"},
	{"geometry":{"coordinates":[19.557101,40.727773],"type":"Point"},"properties":{"name":"Kosh","osm_id":"6833000818","tag":{"amenity":"waste_basket"}},"type":"Feature"},
	{"geometry":{"coordinates":[19.557112,40.727792],"type":"Point"},"properties":{"name":"Kosh","osm_id":"6833002001","tag":{"amenity":"waste_basket"}},"type":"Feature"}
]
}
