{
"type": "FeatureCollection",
"lastupdate": "2020-08-03T00:00:00Z",
"features": [
	{"geometry":{"coordinates":[19.557101,40.727772],"type":"Point"},"properties":{"name":"Kosh","osm_id":"6833000818","tag":{"amenity":"waste_basket"}},"type":"Feature"},
	{"geometry":{"coordinates":[19.557111,40.727792],"type":"Point"},"properties":{"name":"Kosh","osm_id":"6833002001","tag":{"amenity":"waste_basket"}},"type":"Feature"}
]
}
