{
"type": "FeatureCollection",
"features": [
	{"geometry":{"coordinates":[9.236439,54.198125],"type":"Point"},"properties":{"osm_id":"4924723193","tag":{"amenity":"recycling","operator":"Abfallwirtschaft Dithmarschen","recycling:glass_bottles":"yes","recycling_type":"container"}},"type":"Feature"},
	{"geometry":{"coordinates":[9.246687,54.197264],"type":"Point"},"properties":{"osm_id":"4924723214","tag":{"amenity":"recycling","operator":"Deutsches Rotes Kreuz","recycling:clothes":"yes","recycling:shoes":"yes","recycling_type":"container","website":"https://www.drk.de/"}},"type":"Feature"},
	{"geometry":{"coordinates":[9.236485,54.198142],"type":"Point"},"properties":{"osm_id":"5839517180","tag":{"amenity":"recycling","recycling:clothes":"yes","recycling_type":"container"}},"type":"Feature"}
]
}
