{
"type": "FeatureCollection",
"lastupdate": "2020-08-03T00:00:00Z",
"features": [
	{"geometry":{"coordinates":[9.236438,54.198124],"type":"Point"},"properties":{"osm_id":"4924723193","tag":{"amenity":"recycling","operator":"Abfallwirtschaft Dithmarschen","recycling:glass_bottles":"yes","recycling_type":"container"}},"type":"Feature"},
	{"geometry":{"coordinates":[9.246686,54.197263],"type":"Point"},"properties":{"osm_id":"4924723214","tag":{"amenity":"recycling","operator":"Deutsches Rotes Kreuz","recycling:clothes":"yes","recycling:shoes":"yes","recycling_type":"container","website":"https://www.drk.de/"}},"type":"Feature"},
	{"geometry":{"coordinates":[9.236484,54.198142],"type":"Point"},"properties":{"osm_id":"5839517180","tag":{"amenity":"recycling","recycling:clothes":"yes","recycling_type":"container"}},"type":"Feature"}
]
}
