{
"type": "FeatureCollection",
"features": [
	{"geometry":{"coordinates":[9.234473,47.500556],"type":"Point"},"properties":{"osm_id":"1770741146","tag":{"amenity":"waste_basket"}},"type":"Feature"},
	{"geometry":{"coordinates":[9.251833,47.494275],"type":"Point"},"properties":{"name":"Robidog","osm_id":"2266110757","tag":{"amenity":"waste_basket"}},"type":"Feature"},
	{"geometry":{"coordinates":[9.292765,47.470858],"type":"Point"},"properties":{"osm_id":"4137908184","tag":{"amenity":"recycling"}},"type":"Feature"},
	{"geometry":{"coordinates":[9.228879,47.489028],"type":"Point"},"properties":{"osm_id":"8968532350","tag":{"amenity":"waste_basket","waste":"dog_excrement"}},"type":"Feature"}
]
}
