{
"type": "FeatureCollection",
"features": [
	{"geometry":{"coordinates":[9.234474,47.500557],"type":"Point"},"properties":{"osm_id":"1770741146","tag":{"amenity":"waste_basket"}},"type":"Feature"},
	{"geometry":{"coordinates":[9.251833,47.494275],"type":"Point"},"properties":{"name":"Robidog","osm_id":"2266110757","tag":{"amenity":"waste_basket"}},"type":"Feature"},
	{"geometry":{"coordinates":[9.292765,47.470858],"type":"Point"},"properties":{"osm_id":"4137908184","tag":{"amenity":"recycling"}},"type":"Feature"}
]
}
