{
"type": "FeatureCollection",
"features": [
	{"geometry":{"coordinates":[9.271404,47.389253],"type":"Point"},"properties":{"name":"WinWin-Markt","osm_id":"273141690","tag":{"amenity":"recycling"}},"type":"Feature"},
	{"geometry":{"coordinates":[9.279992,47.37527],"type":"Point"},"properties":{"osm_id":"519720146","tag":{"amenity":"recycling"}},"type":"Feature"},
	{"geometry":{"coordinates":[9.276511,47.389867],"type":"Point"},"properties":{"osm_id":"5315190537","tag":{"amenity":"waste_basket"}},"type":"Feature"},
	{"geometry":{"coordinates":[9.230075,47.38737],"type":"Point"},"properties":{"osm_id":"7683258913","tag":{"amenity":"waste_basket"}},"type":"Feature"},
	{"geometry":{"coordinates":[9.234048,47.389811],"type":"Point"},"properties":{"osm_id":"7683258914","tag":{"amenity":"waste_basket"}},"type":"Feature"},
	{"geometry":{"coordinates":[9.26908,47.3859],"type":"Point"},"properties":{"osm_id":"7881908503","tag":{"amenity":"recycling","opening_hours":"Mo-Fr 07:00-20:00","recycling:clothes":"yes","recycling:glass_bottles":"yes","recycling_type":"container"}},"type":"Feature"},
	{"geometry":{"coordinates":[9.268997,47.385892],"type":"Point"},"properties":{"osm_id":"7881908504","tag":{"amenity":"waste_basket","waste":"dog_excrement"}},"type":"Feature"}
]
}
