{
"type": "FeatureCollection",
"features": [
	{"geometry":{"coordinates":[9.271405,47.389254],"type":"Point"},"properties":{"name":"WinWin-Markt","osm_id":"273141690","tag":{"amenity":"recycling","opening_hours":"Tu-Fr 10:00-17:30; Sa 10:00-16:00","recycling:batteries":"yes","recycling:cans":"yes","recycling:electrical_appliances":"yes","recycling:glass":"yes","recycling:glass_bottles":"yes","recycling:green_waste":"yes","recycling:paper":"yes","recycling:plastic":"yes","recycling:scrap_metal":"yes","recycling:shoes":"yes","recycling:small_appliances":"yes","recycling:waste":"yes","recycling_type":"centre"}},"type":"Feature"},
	{"geometry":{"coordinates":[9.279993,47.37527],"type":"Point"},"properties":{"osm_id":"519720146","tag":{"amenity":"recycling","recycling:clothes":"yes","recycling:glass_bottles":"yes","recycling_type":"container"}},"type":"Feature"},
	{"geometry":{"coordinates":[9.276512,47.389868],"type":"Point"},"properties":{"osm_id":"5315190537","tag":{"amenity":"waste_basket"}},"type":"Feature"},
	{"geometry":{"coordinates":[9.230076,47.387371],"type":"Point"},"properties":{"osm_id":"7683258913","tag":{"amenity":"waste_basket"}},"type":"Feature"},
	{"geometry":{"coordinates":[9.234048,47.389812],"type":"Point"},"properties":{"osm_id":"7683258914","tag":{"amenity":"waste_basket"}},"type":"Feature"},
	{"geometry":{"coordinates":[9.269081,47.3859],"type":"Point"},"properties":{"osm_id":"7881908503","tag":{"amenity":"recycling","opening_hours":"Mo-Fr 07:00-20:00","recycling:clothes":"yes","recycling:glass_bottles":"yes","recycling_type":"container"}},"type":"Feature"},
	{"geometry":{"coordinates":[9.268997,47.385892],"type":"Point"},"properties":{"osm_id":"7881908504","tag":{"amenity":"waste_basket","waste":"dog_excrement"}},"type":"Feature"}
]
}
