{
"type": "FeatureCollection",
"lastupdate": "2020-08-01T00:00:00Z",
"features": [
	{"geometry":{"coordinates":[9.271404,47.389253],"type":"Point"},"properties":{"name":"WinWin-Markt","osm_id":"273141690","tag":{"amenity":"recycling"}},"type":"Feature"},
	{"geometry":{"coordinates":[9.279992,47.37527],"type":"Point"},"properties":{"osm_id":"519720146","tag":{"amenity":"recycling"}},"type":"Feature"},
	{"geometry":{"coordinates":[9.276511,47.389867],"type":"Point"},"properties":{"osm_id":"5315190537","tag":{"amenity":"waste_basket"}},"type":"Feature"},
	{"geometry":{"coordinates":[9.230075,47.38737],"type":"Point"},"properties":{"osm_id":"7683258913","tag":{"amenity":"waste_basket"}},"type":"Feature"},
	{"geometry":{"coordinates":[9.234048,47.389811],"type":"Point"},"properties":{"osm_id":"7683258914","tag":{"amenity":"waste_basket"}},"type":"Feature"}
]
}
