{
"type": "FeatureCollection",
"features": [
	{"geometry":{"coordinates":[-122.198265,47.379977],"type":"Point"},"properties":{"name":"Pear","osm_id":"3725129068","tag":{"natural":"tree"}},"type":"Feature"},
	{"geometry":{"coordinates":[-122.198203,47.379984],"type":"Point"},"properties":{"name":"Pear","osm_id":"3725129069","tag":{"natural":"tree"}},"type":"Feature"},
	{"geometry":{"coordinates":[-122.198108,47.379977],"type":"Point"},"properties":{"name":"Pear","osm_id":"3725129070","tag":{"natural":"tree"}},"type":"Feature"},
	{"geometry":{"coordinates":[-122.198025,47.37998],"type":"Point"},"properties":{"name":"Pear","osm_id":"3725129071","tag":{"natural":"tree"}},"type":"Feature"},
	{"geometry":{"coordinates":[-122.19803,47.380029],"type":"Point"},"properties":{"name":"Pear","osm_id":"3725129072","tag":{"natural":"tree"}},"type":"Feature"},
	{"geometry":{"coordinates":[-122.197948,47.380028],"type":"Point"},"properties":{"name":"Pear","osm_id":"3725129073","tag":{"natural":"tree"}},"type":"Feature"},
	{"geometry":{"coordinates":[-122.197882,47.379976],"type":"Point"},"properties":{"name":"Pear","osm_id":"3725129074","tag":{"natural":"tree"}},"type":"Feature"},
	{"geometry":{"coordinates":[-122.198932,47.380253],"type":"Point"},"properties":{"osm_id":"3725129087","tag":{"natural":"tree"}},"type":"Feature"},
	{"geometry":{"coordinates":[-122.233943,47.339055],"type":"Point"},"properties":{"osm_id":"5083927154","tag":{"natural":"tree"}},"type":"Feature"},
	{"geometry":{"coordinates":[-122.233645,47.339352],"type":"Point"},"properties":{"osm_id":"5083927155","tag":{"natural":"tree"}},"type":"Feature"},
	{"geometry":{"coordinates":[-122.234246,47.339653],"type":"Point"},"properties":{"osm_id":"5083927156","tag":{"natural":"tree"}},"type":"Feature"},
	{"geometry":{"coordinates":[-122.233345,47.339646],"type":"Point"},"properties":{"osm_id":"5083927157","tag":{"natural":"tree"}},"type":"Feature"},
	{"geometry":{"coordinates":[-122.230504,47.385486],"type":"Point"},"properties":{"osm_id":"5136698734","tag":{"natural":"tree"}},"type":"Feature"},
	{"geometry":{"coordinates":[-122.23051,47.385389],"type":"Point"},"properties":{"osm_id":"5136698735","tag":{"natural":"tree"}},"type":"Feature"},
	{"geometry":{"coordinates":[-122.230337,47.385285],"type":"Point"},"properties":{"osm_id":"5136698736","tag":{"natural":"tree"}},"type":"Feature"},
	{"geometry":{"coordinates":[-122.230201,47.385289],"type":"Point"},"properties":{"osm_id":"5136698737","tag":{"natural":"tree"}},"type":"Feature"},
	{"geometry":{"coordinates":[-122.23007,47.385346],"type":"Point"},"properties":{"osm_id":"5136698738","tag":{"natural":"tree"}},"type":"Feature"},
	{"geometry":{"coordinates":[-122.230817,47.385056],"type":"Point"},"properties":{"osm_id":"5136698739","tag":{"natural":"tree"}},"type":"Feature"},
	{"geometry":{"coordinates":[-122.230768,47.385026],"type":"Point"},"properties":{"osm_id":"5136698740","tag":{"natural":"tree"}},"type":"Feature"},
	{"geometry":{"coordinates":[-122.230543,47.38515],"type":"Point"},"properties":{"osm_id":"5136698741","tag":{"natural":"tree"}},"type":"Feature"},
	{"geometry":{"coordinates":[-122.230607,47.385254],"type":"Point"},"properties":{"osm_id":"5136698742","tag":{"natural":"tree"}},"type":"Feature"}
]
}
