{
"type": "FeatureCollection",
"features": [
	{"geometry":{"coordinates":[-122.200328,44.830999],"type":"Point"},"properties":{"name":"Cedar Flat","osm_id":"4333704803","tag":{"natural":"tree"}},"type":"Feature"}
]
}
