{
"type": "FeatureCollection",
"lastupdate": "2020-08-02T00:00:00Z",
"features": [
	{"geometry":{"coordinates":[13.048535,53.147294],"type":"Point"},"properties":{"osm_id":"2269431798","tag":{"amenity":"waste_basket"}},"type":"Feature"},
	{"geometry":{"coordinates":[13.059178,53.148489],"type":"Point"},"properties":{"name":"Altglas","osm_id":"7625050502","tag":{"amenity":"recycling"}},"type":"Feature"}
]
}
