{
"type": "FeatureCollection",
"features": [
	{"geometry":{"coordinates":[13.045472,52.444887],"type":"Point"},"properties":{"osm_id":"252272681","tag":{"amenity":"recycling","operator":"Step","recycling:clothes":"yes","recycling:glass_bottles":"yes","recycling:shoes":"yes","recycling_type":"container"}},"type":"Feature"},
	{"geometry":{"coordinates":[13.014319,52.474833],"type":"Point"},"properties":{"osm_id":"253417119","tag":{"amenity":"recycling","recycling_type":"container"}},"type":"Feature"},
	{"geometry":{"coordinates":[13.012072,52.437671],"type":"Point"},"properties":{"osm_id":"440262962","tag":{"amenity":"recycling","recycling_type":"container"}},"type":"Feature"},
	{"geometry":{"coordinates":[13.058157,52.458006],"type":"Point"},"properties":{"osm_id":"546958228","tag":{"amenity":"recycling","recycling:clothes":"yes","recycling:glass":"yes","recycling_type":"container"}},"type":"Feature"},
	{"geometry":{"coordinates":[13.011898,52.469398],"type":"Point"},"properties":{"osm_id":"1450908860","tag":{"amenity":"recycling","operator":"Step","recycling:clothes":"yes","recycling:glass_bottles":"yes","recycling_type":"container"}},"type":"Feature"},
	{"geometry":{"coordinates":[13.036411,52.452162],"type":"Point"},"properties":{"osm_id":"3389896413","tag":{"amenity":"waste_basket"}},"type":"Feature"},
	{"geometry":{"coordinates":[13.052605,52.44608],"type":"Point"},"properties":{"osm_id":"3752700048","tag":{"amenity":"waste_basket"}},"type":"Feature"},
	{"geometry":{"coordinates":[13.039869,52.441891],"type":"Point"},"properties":{"osm_id":"3810334295","tag":{"amenity":"waste_basket"}},"type":"Feature"},
	{"geometry":{"coordinates":[13.045889,52.442756],"type":"Point"},"properties":{"osm_id":"3912483158","tag":{"amenity":"waste_basket"}},"type":"Feature"},
	{"geometry":{"coordinates":[13.040307,52.445793],"type":"Point"},"properties":{"osm_id":"3912508158","tag":{"amenity":"waste_basket"}},"type":"Feature"},
	{"geometry":{"coordinates":[13.030904,52.445114],"type":"Point"},"properties":{"osm_id":"3995205435","tag":{"amenity":"waste_basket","check_date":"2020-12-31"}},"type":"Feature"},
	{"geometry":{"coordinates":[13.053076,52.434833],"type":"Point"},"properties":{"osm_id":"5275063165","tag":{"amenity":"recycling","location":"overground","recycling:glass_bottles":"yes","recycling_type":"container"}},"type":"Feature"},
	{"geometry":{"coordinates":[13.095517,52.468141],"type":"Point"},"properties":{"osm_id":"5992996130","tag":{"amenity":"recycling","recycling:clothes":"yes","recycling:glass_bottles":"yes","recycling_type":"container"}},"type":"Feature"},
	{"geometry":{"coordinates":[13.059514,52.457589],"type":"Point"},"properties":{"osm_id":"6488172066","tag":{"amenity":"waste_disposal","waste":"trash"}},"type":"Feature"},
	{"geometry":{"coordinates":[13.039534,52.444314],"type":"Point"},"properties":{"osm_id":"9082512207","tag":{"amenity":"waste_basket","waste":"trash"}},"type":"Feature"}
]
}
