{
"type": "FeatureCollection",
"features": [
	{"geometry":{"coordinates":[13.045496,52.444897],"type":"Point"},"properties":{"osm_id":"252272681","tag":{"amenity":"recycling","recycling:cans":"no","recycling:clothes":"yes","recycling:glass":"yes","recycling:glass_bottles":"yes","recycling:plastic":"no","recycling_type":"container"}},"type":"Feature"},
	{"geometry":{"coordinates":[13.014319,52.474834],"type":"Point"},"properties":{"osm_id":"253417119","tag":{"amenity":"recycling","recycling_type":"container"}},"type":"Feature"},
	{"geometry":{"coordinates":[13.012073,52.437671],"type":"Point"},"properties":{"osm_id":"440262962","tag":{"amenity":"recycling","recycling_type":"container"}},"type":"Feature"},
	{"geometry":{"coordinates":[13.058157,52.458007],"type":"Point"},"properties":{"osm_id":"546958228","tag":{"amenity":"recycling","recycling:clothes":"yes","recycling:glass":"yes","recycling_type":"container"}},"type":"Feature"},
	{"geometry":{"coordinates":[13.011898,52.469398],"type":"Point"},"properties":{"osm_id":"1450908860","tag":{"amenity":"recycling","operator":"Step","recycling:clothes":"yes","recycling:glass_bottles":"yes","recycling_type":"container"}},"type":"Feature"},
	{"geometry":{"coordinates":[13.036412,52.452162],"type":"Point"},"properties":{"osm_id":"3389896413","tag":{"amenity":"waste_basket"}},"type":"Feature"},
	{"geometry":{"coordinates":[13.052605,52.446081],"type":"Point"},"properties":{"osm_id":"3752700048","tag":{"amenity":"waste_basket"}},"type":"Feature"},
	{"geometry":{"coordinates":[13.039869,52.441891],"type":"Point"},"properties":{"osm_id":"3810334295","tag":{"amenity":"waste_basket"}},"type":"Feature"},
	{"geometry":{"coordinates":[13.04589,52.442757],"type":"Point"},"properties":{"osm_id":"3912483158","tag":{"amenity":"waste_basket"}},"type":"Feature"},
	{"geometry":{"coordinates":[13.040308,52.445793],"type":"Point"},"properties":{"osm_id":"3912508158","tag":{"amenity":"waste_basket"}},"type":"Feature"},
	{"geometry":{"coordinates":[13.030905,52.445114],"type":"Point"},"properties":{"osm_id":"3995205435","tag":{"amenity":"waste_basket"}},"type":"Feature"},
	{"geometry":{"coordinates":[13.053111,52.434842],"type":"Point"},"properties":{"osm_id":"5275063165","tag":{"amenity":"recycling","location":"overground","recycling:glass_bottles":"yes","recycling_type":"container"}},"type":"Feature"},
	{"geometry":{"coordinates":[13.095518,52.468142],"type":"Point"},"properties":{"osm_id":"5992996130","tag":{"amenity":"recycling","recycling:clothes":"yes","recycling:glass_bottles":"yes","recycling_type":"container"}},"type":"Feature"},
	{"geometry":{"coordinates":[13.059515,52.45759],"type":"Point"},"properties":{"osm_id":"6488172066","tag":{"amenity":"waste_disposal","waste":"trash"}},"type":"Feature"}
]
}
