{
"type": "FeatureCollection",
"lastupdate": "2020-07-31T00:00:00Z",
"features": [
	{"geometry":{"coordinates":[5.732318,46.837036],"type":"Point"},"properties":{"name":"Verre","osm_id":"4687229385","tag":{"amenity":"recycling","recycling:glass":"yes","recycling:glass_bottles":"yes","recycling_type":"container"}},"type":"Feature"},
	{"geometry":{"coordinates":[5.777307,46.815882],"type":"Point"},"properties":{"osm_id":"5639897447","tag":{"amenity":"waste_basket"}},"type":"Feature"}
]
}
