{
"type": "FeatureCollection",
"features": [
	{"geometry":{"coordinates":[10.183797,49.487564],"type":"Point"},"properties":{"name":"Friedenseiche","osm_id":"1782602764","tag":{"natural":"tree","type":"Eiche"}},"type":"Feature"},
	{"geometry":{"coordinates":[10.144571,49.484172],"type":"Point"},"properties":{"osm_id":"5417879649","tag":{"leaf_type":"broadleaved","natural":"tree"}},"type":"Feature"},
	{"geometry":{"coordinates":[10.144574,49.484215],"type":"Point"},"properties":{"osm_id":"5417879650","tag":{"leaf_type":"broadleaved","natural":"tree"}},"type":"Feature"}
]
}
