{
"type": "FeatureCollection",
"features": [
	{"geometry":{"coordinates":[10.183796,49.487563],"type":"Point"},"properties":{"name":"Friedenseiche","osm_id":"1782602764","tag":{"natural":"tree","type":"Eiche"}},"type":"Feature"},
	{"geometry":{"coordinates":[10.144571,49.484171],"type":"Point"},"properties":{"osm_id":"5417879649","tag":{"leaf_type":"broadleaved","natural":"tree"}},"type":"Feature"},
	{"geometry":{"coordinates":[10.144573,49.484215],"type":"Point"},"properties":{"osm_id":"5417879650","tag":{"leaf_type":"broadleaved","natural":"tree"}},"type":"Feature"},
	{"geometry":{"coordinates":[10.195299,49.440265],"type":"Point"},"properties":{"osm_id":"8702103236","tag":{"leaf_cycle":"deciduous","leaf_type":"broadleaved","natural":"tree"}},"type":"Feature"}
]
}
