{
"type": "FeatureCollection",
"features": [
	{"geometry":{"coordinates":[10.183796,49.487563],"type":"Point"},"properties":{"name":"Friedenseiche","osm_id":"1782602764","tag":{"natural":"tree","type":"Eiche"}},"type":"Feature"},
	{"geometry":{"coordinates":[10.144571,49.484171],"type":"Point"},"properties":{"osm_id":"5417879649","tag":{"leaf_type":"broadleaved","natural":"tree"}},"type":"Feature"},
	{"geometry":{"coordinates":[10.144573,49.484215],"type":"Point"},"properties":{"osm_id":"5417879650","tag":{"leaf_type":"broadleaved","natural":"tree"}},"type":"Feature"},
	{"geometry":{"coordinates":[10.195299,49.440265],"type":"Point"},"properties":{"osm_id":"8702103236","tag":{"leaf_cycle":"deciduous","leaf_type":"broadleaved","natural":"tree"}},"type":"Feature"},
	{"geometry":{"coordinates":[10.182546,49.443246],"type":"Point"},"properties":{"osm_id":"8935234651","tag":{"leaf_cycle":"deciduous","leaf_type":"broadleaved","natural":"tree"}},"type":"Feature"},
	{"geometry":{"coordinates":[10.182766,49.443265],"type":"Point"},"properties":{"osm_id":"8935234652","tag":{"leaf_cycle":"deciduous","leaf_type":"broadleaved","natural":"tree"}},"type":"Feature"},
	{"geometry":{"coordinates":[10.180969,49.442337],"type":"Point"},"properties":{"osm_id":"8935234653","tag":{"leaf_cycle":"deciduous","leaf_type":"broadleaved","natural":"tree"}},"type":"Feature"},
	{"geometry":{"coordinates":[10.177061,49.441937],"type":"Point"},"properties":{"osm_id":"8935234697","tag":{"leaf_cycle":"deciduous","leaf_type":"broadleaved","natural":"tree"}},"type":"Feature"},
	{"geometry":{"coordinates":[10.184483,49.445977],"type":"Point"},"properties":{"osm_id":"8935234759","tag":{"leaf_cycle":"deciduous","leaf_type":"broadleaved","natural":"tree"}},"type":"Feature"},
	{"geometry":{"coordinates":[10.184383,49.444146],"type":"Point"},"properties":{"osm_id":"8935234761","tag":{"leaf_cycle":"deciduous","leaf_type":"broadleaved","natural":"tree"}},"type":"Feature"},
	{"geometry":{"coordinates":[10.184682,49.44416],"type":"Point"},"properties":{"osm_id":"8935234762","tag":{"leaf_cycle":"deciduous","leaf_type":"broadleaved","natural":"tree"}},"type":"Feature"}
]
}
