{
"type": "FeatureCollection",
"features": [
	{"geometry":{"coordinates":[22.289262,55.254157],"type":"Point"},"properties":{"osm_id":"1825046788","tag":{"amenity":"recycling","recycling_type":"container"}},"type":"Feature"},
	{"geometry":{"coordinates":[22.264099,55.254585],"type":"Point"},"properties":{"osm_id":"5994037713","tag":{"amenity":"recycling","recycling:glass_bottles":"yes","recycling:paper":"yes","recycling:plastic":"yes","recycling_type":"container"}},"type":"Feature"},
	{"geometry":{"coordinates":[22.29971,55.261512],"type":"Point"},"properties":{"name":"Taromatas","osm_id":"9196008904","tag":{"amenity":"recycling","building":"yes","recycling:aluminium_cans":"yes","recycling:glass_bottles":"yes","recycling:plastic_bottles":"yes","recycling_type":"centre"}},"type":"Feature"}
]
}
