{
"type": "FeatureCollection",
"features": [
	{"geometry":{"coordinates":[86.56096,27.20656],"type":"Point"},"properties":{"name":"bar","osm_id":"3174073326","tag":{"height":"20","natural":"tree","type":"palm"}},"type":"Feature"},
	{"geometry":{"coordinates":[86.560368,27.207565],"type":"Point"},"properties":{"name":"bar","osm_id":"3174073327","tag":{"natural":"tree"}},"type":"Feature"}
]
}
