{
"type": "FeatureCollection",
"features": [
	{"geometry":{"coordinates":[-47.940687,-25.00465],"type":"Point"},"properties":{"name":"RECUCLAGEM","osm_id":"3499090732","tag":{"amenity":"recycling"}},"type":"Feature"}
]
}
