{
"type": "FeatureCollection",
"features": [
	{"geometry":{"coordinates":[18.865739,53.314819],"type":"Point"},"properties":{"osm_id":"4706666412","tag":{"denotation":"natural_monument","natural":"tree","ref:CRFOP":"PL.ZIPOP.1393.PP.0417052.2154","ref:INSPIRE":"PL.ZIPOP.1393.PP.0417052.2154","website":"http://crfop.gdos.gov.pl/CRFOP/widok/viewfop.jsf?fop=PL.ZIPOP.1393.PP.0417052.2154"}},"type":"Feature"},
	{"geometry":{"coordinates":[18.865994,53.31492],"type":"Point"},"properties":{"osm_id":"4706666413","tag":{"denotation":"natural_monument","natural":"tree","ref:CRFOP":"PL.ZIPOP.1393.PP.0417052.2154","ref:INSPIRE":"PL.ZIPOP.1393.PP.0417052.2154","website":"http://crfop.gdos.gov.pl/CRFOP/widok/viewfop.jsf?fop=PL.ZIPOP.1393.PP.0417052.2154"}},"type":"Feature"},
	{"geometry":{"coordinates":[18.866073,53.313567],"type":"Point"},"properties":{"osm_id":"4706666414","tag":{"denotation":"natural_monument","natural":"tree","ref:CRFOP":"PL.ZIPOP.1393.PP.0417052.2154","ref:INSPIRE":"PL.ZIPOP.1393.PP.0417052.2154","website":"http://crfop.gdos.gov.pl/CRFOP/widok/viewfop.jsf?fop=PL.ZIPOP.1393.PP.0417052.2154"}},"type":"Feature"},
	{"geometry":{"coordinates":[18.865602,53.314956],"type":"Point"},"properties":{"osm_id":"4706666415","tag":{"denotation":"natural_monument","natural":"tree","ref:CRFOP":"PL.ZIPOP.1393.PP.0417052.2154","ref:INSPIRE":"PL.ZIPOP.1393.PP.0417052.2154","website":"http://crfop.gdos.gov.pl/CRFOP/widok/viewfop.jsf?fop=PL.ZIPOP.1393.PP.0417052.2154"}},"type":"Feature"},
	{"geometry":{"coordinates":[18.866325,53.314402],"type":"Point"},"properties":{"osm_id":"4706666416","tag":{"denotation":"natural_monument","natural":"tree","ref:CRFOP":"PL.ZIPOP.1393.PP.0417052.2154","ref:INSPIRE":"PL.ZIPOP.1393.PP.0417052.2154","website":"http://crfop.gdos.gov.pl/CRFOP/widok/viewfop.jsf?fop=PL.ZIPOP.1393.PP.0417052.2154"}},"type":"Feature"}
]
}
