{
"type": "FeatureCollection",
"features": [
	{"geometry":{"coordinates":[-1.32005,39.184299],"type":"Point"},"properties":{"name":"Almez de las Casas del Conde","osm_id":"7416941694","tag":{"denotation":"single","natural":"tree"}},"type":"Feature"}
]
}
