{
"type": "FeatureCollection",
"features": [
	{"geometry":{"coordinates":[22.978487,50.111083],"type":"Point"},"properties":{"name":"Nemrod","osm_id":"4033898009","tag":{"denotation":"natural_monument","gid":"93854","kodinspire":"PL.ZIPOP.1393.PP.1809063.748","monument":"yes","natural":"tree","protected":"yes"}},"type":"Feature"}
]
}
