{
"type": "FeatureCollection",
"features": [
	{"geometry":{"coordinates":[12.825276,42.024431],"type":"Point"},"properties":{"osm_id":"3489349290","tag":{"natural":"tree"}},"type":"Feature"},
	{"geometry":{"coordinates":[12.825491,42.024939],"type":"Point"},"properties":{"osm_id":"3489349368","tag":{"natural":"tree"}},"type":"Feature"},
	{"geometry":{"coordinates":[12.825665,42.025902],"type":"Point"},"properties":{"osm_id":"3489349691","tag":{"natural":"tree"}},"type":"Feature"},
	{"geometry":{"coordinates":[12.826783,41.970864],"type":"Point"},"properties":{"name":"Sughera","osm_id":"3702865550","tag":{"natural":"tree"}},"type":"Feature"},
	{"geometry":{"coordinates":[12.762105,41.972002],"type":"Point"},"properties":{"osm_id":"7003769090","tag":{"natural":"tree"}},"type":"Feature"},
	{"geometry":{"coordinates":[12.772156,41.968302],"type":"Point"},"properties":{"osm_id":"7063326540","tag":{"natural":"tree"}},"type":"Feature"},
	{"geometry":{"coordinates":[12.772004,41.968202],"type":"Point"},"properties":{"osm_id":"7063326541","tag":{"natural":"tree"}},"type":"Feature"},
	{"geometry":{"coordinates":[12.772052,41.968081],"type":"Point"},"properties":{"osm_id":"7063326542","tag":{"natural":"tree"}},"type":"Feature"},
	{"geometry":{"coordinates":[12.772223,41.968162],"type":"Point"},"properties":{"osm_id":"7063326543","tag":{"natural":"tree"}},"type":"Feature"},
	{"geometry":{"coordinates":[12.773388,41.969418],"type":"Point"},"properties":{"osm_id":"7063326580","tag":{"natural":"tree"}},"type":"Feature"},
	{"geometry":{"coordinates":[12.773398,41.969562],"type":"Point"},"properties":{"osm_id":"7063326581","tag":{"natural":"tree"}},"type":"Feature"},
	{"geometry":{"coordinates":[12.773344,41.969555],"type":"Point"},"properties":{"osm_id":"7063326582","tag":{"natural":"tree"}},"type":"Feature"},
	{"geometry":{"coordinates":[12.773287,41.969552],"type":"Point"},"properties":{"osm_id":"7063326583","tag":{"natural":"tree"}},"type":"Feature"},
	{"geometry":{"coordinates":[12.77324,41.969541],"type":"Point"},"properties":{"osm_id":"7063326584","tag":{"natural":"tree"}},"type":"Feature"},
	{"geometry":{"coordinates":[12.773172,41.96953],"type":"Point"},"properties":{"osm_id":"7063326585","tag":{"natural":"tree"}},"type":"Feature"}
]
}
