{
"type": "FeatureCollection",
"features": [
	{"geometry":{"coordinates":[21.429948,51.530554],"type":"Point"},"properties":{"name":"Zygmunt August","osm_id":"4770984136","tag":{"denotation":"natural_monument","leaf_cycle":"deciduous","leaf_type":"broadleaved","natural":"tree"}},"type":"Feature"}
]
}
