{
"type": "FeatureCollection",
"features": [
	{"geometry":{"coordinates":[21.434089,49.962487],"type":"Point"},"properties":{"name":"Pomnik przyrody","osm_id":"4029151994","tag":{"denotation":"natural_monument","monument":"yes","natural":"tree","protected":"yes"}},"type":"Feature"},
	{"geometry":{"coordinates":[21.434052,49.962597],"type":"Point"},"properties":{"name":"Pomnik przyrody","osm_id":"4029151995","tag":{"denotation":"natural_monument","monument":"yes","natural":"tree","protected":"yes"}},"type":"Feature"},
	{"geometry":{"coordinates":[21.43672,49.963116],"type":"Point"},"properties":{"name":"Pomnik przyrody","osm_id":"4029151996","tag":{"denotation":"natural_monument","monument":"yes","natural":"tree","protected":"yes"}},"type":"Feature"},
	{"geometry":{"coordinates":[21.436606,49.963142],"type":"Point"},"properties":{"name":"Pomnik przyrody","osm_id":"4029151997","tag":{"denotation":"natural_monument","monument":"yes","natural":"tree","protected":"yes"}},"type":"Feature"},
	{"geometry":{"coordinates":[21.43667,49.963468],"type":"Point"},"properties":{"name":"Pomnik przyrody","osm_id":"4029151998","tag":{"denotation":"natural_monument","monument":"yes","natural":"tree","protected":"yes"}},"type":"Feature"},
	{"geometry":{"coordinates":[21.435823,49.96393],"type":"Point"},"properties":{"name":"Pomnik przyrody","osm_id":"4029151999","tag":{"denotation":"natural_monument","monument":"yes","natural":"tree","protected":"yes"}},"type":"Feature"},
	{"geometry":{"coordinates":[21.435236,49.964387],"type":"Point"},"properties":{"name":"Pomnik przyrody","osm_id":"4029152000","tag":{"denotation":"natural_monument","monument":"yes","natural":"tree","protected":"yes"}},"type":"Feature"},
	{"geometry":{"coordinates":[21.434934,49.964731],"type":"Point"},"properties":{"name":"Pomnik przyrody","osm_id":"4029152001","tag":{"denotation":"natural_monument","monument":"yes","natural":"tree","protected":"yes"}},"type":"Feature"},
	{"geometry":{"coordinates":[21.434181,49.965122],"type":"Point"},"properties":{"name":"Pomnik przyrody","osm_id":"4029152002","tag":{"denotation":"natural_monument","monument":"yes","natural":"tree","protected":"yes"}},"type":"Feature"}
]
}
