{
"type": "FeatureCollection",
"features": [
	{"geometry":{"coordinates":[21.439572,49.937031],"type":"Point"},"properties":{"name":"Stefek","osm_id":"4029151993","tag":{"denotation":"natural_monument","gid":"92454","kodinspire":"PL.ZIPOP.1393.PP.1803023.149","monument":"yes","natural":"tree","protected":"yes"}},"type":"Feature"}
]
}
