{
"type": "FeatureCollection",
"features": [
	{"geometry":{"coordinates":[-4.287105,47.818437],"type":"Point"},"properties":{"osm_id":"383553492","tag":{"amenity":"recycling","location":"overground","recycling:glass":"yes","recycling_type":"container"}},"type":"Feature"},
	{"geometry":{"coordinates":[-4.284048,47.846663],"type":"Point"},"properties":{"osm_id":"473132841","tag":{"amenity":"recycling","recycling:glass":"yes","recycling:scrap_metal":"no"}},"type":"Feature"},
	{"geometry":{"coordinates":[-4.277165,47.84464],"type":"Point"},"properties":{"osm_id":"2103076035","tag":{"amenity":"recycling","recycling:glass":"yes","recycling_type":"container"}},"type":"Feature"},
	{"geometry":{"coordinates":[-4.227569,47.817043],"type":"Point"},"properties":{"osm_id":"4018615373","tag":{"amenity":"recycling","recycling:glass":"yes","recycling_type":"container"}},"type":"Feature"},
	{"geometry":{"coordinates":[-4.226957,47.866672],"type":"Point"},"properties":{"osm_id":"6637980397","tag":{"amenity":"waste_basket"}},"type":"Feature"},
	{"geometry":{"coordinates":[-4.22339,47.867059],"type":"Point"},"properties":{"osm_id":"6637981088","tag":{"amenity":"waste_basket"}},"type":"Feature"}
]
}
