{
"type": "FeatureCollection",
"features": [
	{"geometry":{"coordinates":[9.756603,55.588625],"type":"Point"},"properties":{"name":"Genbrugspladsen Industrivej","osm_id":"895451747","tag":{"amenity":"recycling","recycling_type":"centre"}},"type":"Feature"},
	{"geometry":{"coordinates":[9.794107,55.62537],"type":"Point"},"properties":{"osm_id":"2887194289","tag":{"amenity":"waste_basket"}},"type":"Feature"}
]
}
