{
"type": "FeatureCollection",
"features": [
	{"geometry":{"coordinates":[9.794106,55.62537],"type":"Point"},"properties":{"osm_id":"2887194289","tag":{"amenity":"waste_basket"}},"type":"Feature"},
	{"geometry":{"coordinates":[9.758243,55.594579],"type":"Point"},"properties":{"name":"Fredericia Genbrugsplads og Genbrugscenter","osm_id":"8577142515","tag":{"amenity":"recycling","recycling_type":"centre","start_date":"2021-04-01"}},"type":"Feature"}
]
}
