{
"type": "FeatureCollection",
"lastupdate": "2020-07-31T00:00:00Z",
"features": [
	{"geometry":{"coordinates":[9.756602,55.588625],"type":"Point"},"properties":{"name":"Genbrugspladsen Industrivej","osm_id":"895451747","tag":{"amenity":"recycling","recycling_type":"centre"}},"type":"Feature"},
	{"geometry":{"coordinates":[9.794106,55.62537],"type":"Point"},"properties":{"osm_id":"2887194289","tag":{"amenity":"waste_basket"}},"type":"Feature"}
]
}
