{
"type": "FeatureCollection",
"features": [
	{"geometry":{"coordinates":[-75.721021,42.110078],"type":"Point"},"properties":{"is_in":"Broome,New York,N.Y.,NY,USA","name":"Dunbar","osm_id":"158481659","place":"hamlet","tag":{"gnis:Class":"Populated Place","gnis:County":"Broome","gnis:County_num":"007","gnis:ST_alpha":"NY","gnis:ST_num":"36","gnis:id":"972397","import_uuid":"bb7269ee-502a-5391-8056-e3ce0e66489c"}},"type":"Feature"}
]
}
