{
"type": "FeatureCollection",
"features": [
	{"geometry":{"coordinates":[9.057771,49.463911],"type":"Point"},"properties":{"name":"Waldkatzenbacher Linde","osm_id":"888374677","tag":{"genus":"Tilia","genus:de":"Linde","genus:en":"Lime","leaf_cycle":"deciduous","leaf_type":"broadleaved","natural":"tree"}},"type":"Feature"},
	{"geometry":{"coordinates":[9.056055,49.439563],"type":"Point"},"properties":{"osm_id":"5061726536","tag":{"leaf_type":"broadleaved","natural":"tree"}},"type":"Feature"},
	{"geometry":{"coordinates":[9.056144,49.439571],"type":"Point"},"properties":{"osm_id":"5061726537","tag":{"leaf_type":"broadleaved","natural":"tree"}},"type":"Feature"}
]
}
