{
"type": "FeatureCollection",
"features": [
	{"geometry":{"coordinates":[9.075372,48.116183],"type":"Point"},"properties":{"name":"Linde","osm_id":"489700777","tag":{"natural":"tree"}},"type":"Feature"},
	{"geometry":{"coordinates":[9.095723,48.14058],"type":"Point"},"properties":{"osm_id":"599230357","tag":{"genus":"Tilia","genus:de":"Linde","leaf_type":"broadleaved","natural":"tree"}},"type":"Feature"},
	{"geometry":{"coordinates":[9.080535,48.112784],"type":"Point"},"properties":{"name":"Mogg-Linde","osm_id":"794212852","tag":{"natural":"tree"}},"type":"Feature"},
	{"geometry":{"coordinates":[9.094891,48.120585],"type":"Point"},"properties":{"osm_id":"1243709097","tag":{"natural":"tree"}},"type":"Feature"},
	{"geometry":{"coordinates":[9.122171,48.135044],"type":"Point"},"properties":{"osm_id":"4185027886","tag":{"natural":"tree"}},"type":"Feature"},
	{"geometry":{"coordinates":[9.127122,48.135251],"type":"Point"},"properties":{"osm_id":"4185028003","tag":{"natural":"tree"}},"type":"Feature"},
	{"geometry":{"coordinates":[9.127049,48.134221],"type":"Point"},"properties":{"osm_id":"4185028012","tag":{"natural":"tree"}},"type":"Feature"},
	{"geometry":{"coordinates":[9.123722,48.134353],"type":"Point"},"properties":{"osm_id":"4185165703","tag":{"natural":"tree"}},"type":"Feature"},
	{"geometry":{"coordinates":[9.123919,48.134329],"type":"Point"},"properties":{"osm_id":"4185165704","tag":{"natural":"tree"}},"type":"Feature"},
	{"geometry":{"coordinates":[9.122018,48.133894],"type":"Point"},"properties":{"osm_id":"4185165707","tag":{"natural":"tree"}},"type":"Feature"}
]
}
