{
"type": "FeatureCollection",
"features": [
	{"geometry":{"coordinates":[9.07536,48.116196],"type":"Point"},"properties":{"name":"Linde","osm_id":"489700777","tag":{"natural":"tree"}},"type":"Feature"},
	{"geometry":{"coordinates":[9.095723,48.14058],"type":"Point"},"properties":{"osm_id":"599230357","tag":{"genus":"Tilia","genus:de":"Linde","leaf_type":"broadleaved","natural":"tree"}},"type":"Feature"},
	{"geometry":{"coordinates":[9.080535,48.112783],"type":"Point"},"properties":{"name":"Mogg-Linde","osm_id":"794212852","tag":{"natural":"tree"}},"type":"Feature"},
	{"geometry":{"coordinates":[9.094891,48.120585],"type":"Point"},"properties":{"osm_id":"1243709097","tag":{"natural":"tree"}},"type":"Feature"},
	{"geometry":{"coordinates":[9.122165,48.135058],"type":"Point"},"properties":{"osm_id":"4185027886","tag":{"natural":"tree"}},"type":"Feature"},
	{"geometry":{"coordinates":[9.127121,48.13525],"type":"Point"},"properties":{"osm_id":"4185028003","tag":{"natural":"tree"}},"type":"Feature"},
	{"geometry":{"coordinates":[9.127048,48.134221],"type":"Point"},"properties":{"osm_id":"4185028012","tag":{"natural":"tree"}},"type":"Feature"},
	{"geometry":{"coordinates":[9.123722,48.134352],"type":"Point"},"properties":{"osm_id":"4185165703","tag":{"natural":"tree"}},"type":"Feature"},
	{"geometry":{"coordinates":[9.123919,48.134328],"type":"Point"},"properties":{"osm_id":"4185165704","tag":{"natural":"tree"}},"type":"Feature"},
	{"geometry":{"coordinates":[9.122017,48.133894],"type":"Point"},"properties":{"osm_id":"4185165707","tag":{"natural":"tree"}},"type":"Feature"},
	{"geometry":{"coordinates":[9.077495,48.120356],"type":"Point"},"properties":{"name":"Emil Dreher","osm_id":"8440808434","tag":{"denotation":"natural_monument","genus":"Esche","leaf_cycle":"deciduous","leaf_type":"needleleaved","natural":"tree"}},"type":"Feature"}
]
}
