{
"type": "FeatureCollection",
"features": [
	{"geometry":{"coordinates":[2.635415,46.182004],"type":"Point"},"properties":{"name":"Tilleul creux","osm_id":"3252642861","tag":{"natural":"tree"}},"type":"Feature"}
]
}
