{
"type": "FeatureCollection",
"lastupdate": "2020-07-31T00:00:00Z",
"features": [
	{"geometry":{"coordinates":[10.244884,63.273789],"type":"Point"},"properties":{"osm_id":"440711603","tag":{"amenity":"recycling","description":"Gimse","recycling:glass_bottles":"yes","recycling_type":"container","ref:sortere":"14932"}},"type":"Feature"},
	{"geometry":{"coordinates":[10.260479,63.292844],"type":"Point"},"properties":{"name":"Varmbo gjenvinningsstasjon","osm_id":"892290863","tag":{"amenity":"recycling","recycling:asbestos":"yes","recycling:batteries":"yes","recycling:boats":"yes","recycling:clothes":"yes","recycling:drugs":"yes","recycling:electrical_items":"yes","recycling:garden_waste":"yes","recycling:glass":"yes","recycling:glass_bottles":"yes","recycling:hazardous_waste":"yes","recycling:marine_waste":"yes","recycling:metal":"yes","recycling:paper":"yes","recycling:plasterboard":"yes","recycling:plastic_packaging":"yes","recycling:polystyrene_foam":"yes","recycling:rubble":"yes","recycling:tyres":"yes","recycling:waste":"yes","recycling:wood":"yes","recycling_type":"centre","ref:sortere":"1492"}},"type":"Feature"},
	{"geometry":{"coordinates":[10.267614,63.286468],"type":"Point"},"properties":{"osm_id":"5555204917","tag":{"amenity":"recycling","description":"Gimsevegen","recycling:glass_bottles":"yes","recycling_type":"container","ref:sortere":"14933"}},"type":"Feature"},
	{"geometry":{"coordinates":[10.278607,63.287077],"type":"Point"},"properties":{"osm_id":"5555205422","tag":{"amenity":"recycling","description":"Melhus sentrum, Melhustorget","recycling:glass_bottles":"yes","recycling_type":"container","ref:sortere":"14836"}},"type":"Feature"},
	{"geometry":{"coordinates":[10.275152,63.285828],"type":"Point"},"properties":{"osm_id":"5555205424","tag":{"amenity":"recycling","description":"Melhus sentrum, Mega","recycling:glass_bottles":"yes","recycling_type":"container","ref:sortere":"14835"}},"type":"Feature"},
	{"geometry":{"coordinates":[10.222925,63.277254],"type":"Point"},"properties":{"osm_id":"6195508631","tag":{"access":"permissive","amenity":"recycling","description":"Hytterenovasjon Aundalen (1.3)","recycling:glass_bottles":"yes","recycling:waste":"yes","recycling_type":"container","ref:sortere":"21932"}},"type":"Feature"}
]
}
