{
"type": "FeatureCollection",
"features": [
	{"geometry":{"coordinates":[10.262152,53.907479],"type":"Point"},"properties":{"osm_id":"2156379336","tag":{"amenity":"recycling","recycling:clothes":"yes","recycling:glass_bottles":"yes","recycling_type":"container"}},"type":"Feature"},
	{"geometry":{"coordinates":[10.276922,53.920536],"type":"Point"},"properties":{"osm_id":"4292935658","tag":{"amenity":"recycling","recycling:clothes":"yes","recycling:glass_bottles":"yes","recycling_type":"container"}},"type":"Feature"},
	{"geometry":{"coordinates":[10.213277,53.953086],"type":"Point"},"properties":{"osm_id":"5219904191","tag":{"amenity":"recycling","check_date:recycling":"2020-12-26","recycling:clothes":"yes","recycling_type":"container"}},"type":"Feature"},
	{"geometry":{"coordinates":[10.20896,53.952458],"type":"Point"},"properties":{"osm_id":"6543325202","tag":{"amenity":"recycling","recycling:glass_bottles":"yes","recycling_type":"container"}},"type":"Feature"},
	{"geometry":{"coordinates":[10.213611,53.945868],"type":"Point"},"properties":{"osm_id":"7195055311","tag":{"amenity":"waste_basket"}},"type":"Feature"},
	{"geometry":{"coordinates":[10.195899,53.949065],"type":"Point"},"properties":{"name":"Altglascontainer","osm_id":"8261437393","tag":{"amenity":"recycling","recycling:glass":"yes","recycling_type":"container","waste":"glass"}},"type":"Feature"},
	{"geometry":{"coordinates":[10.195894,53.949097],"type":"Point"},"properties":{"name":"Altkleidercontainer","osm_id":"8261437394","tag":{"amenity":"recycling","recycling:clothes":"yes","recycling_type":"container"}},"type":"Feature"},
	{"geometry":{"coordinates":[10.204162,53.948887],"type":"Point"},"properties":{"osm_id":"8261843619","tag":{"amenity":"waste_basket"}},"type":"Feature"}
]
}
