{
"type": "FeatureCollection",
"features": [
	{"geometry":{"coordinates":[10.214599,53.129339],"type":"Point"},"properties":{"osm_id":"745740882","tag":{"amenity":"recycling","recycling:glass_bottles":"yes","recycling:paper":"yes","recycling_type":"container"}},"type":"Feature"},
	{"geometry":{"coordinates":[10.214222,53.14224],"type":"Point"},"properties":{"name":"Recyclinghof Amelinghausen","osm_id":"894867939","tag":{"amenity":"recycling","recycling:batteries":"yes","recycling:cans":"yes","recycling:clothes":"yes","recycling:glass":"yes","recycling:paper":"yes","recycling:scrap_metal":"yes","recycling_type":"centre"}},"type":"Feature"},
	{"geometry":{"coordinates":[10.234979,53.139489],"type":"Point"},"properties":{"osm_id":"8916137885","tag":{"amenity":"waste_basket","waste":"trash"}},"type":"Feature"},
	{"geometry":{"coordinates":[10.234243,53.139257],"type":"Point"},"properties":{"osm_id":"8916137889","tag":{"amenity":"waste_basket","waste":"trash"}},"type":"Feature"},
	{"geometry":{"coordinates":[10.220127,53.147426],"type":"Point"},"properties":{"osm_id":"8916154776","tag":{"amenity":"waste_basket","waste":"trash"}},"type":"Feature"},
	{"geometry":{"coordinates":[10.221885,53.140809],"type":"Point"},"properties":{"osm_id":"8916155282","tag":{"amenity":"waste_basket","waste":"trash"}},"type":"Feature"},
	{"geometry":{"coordinates":[10.229619,53.134504],"type":"Point"},"properties":{"osm_id":"8916267484","tag":{"amenity":"waste_basket","waste":"trash"}},"type":"Feature"},
	{"geometry":{"coordinates":[10.228048,53.134384],"type":"Point"},"properties":{"osm_id":"8916267486","tag":{"amenity":"waste_basket","waste":"trash"}},"type":"Feature"},
	{"geometry":{"coordinates":[10.227523,53.133667],"type":"Point"},"properties":{"osm_id":"8916267493","tag":{"amenity":"waste_basket","waste":"trash"}},"type":"Feature"},
	{"geometry":{"coordinates":[10.228714,53.132309],"type":"Point"},"properties":{"osm_id":"8916267494","tag":{"amenity":"waste_basket","waste":"trash"}},"type":"Feature"},
	{"geometry":{"coordinates":[10.230288,53.131204],"type":"Point"},"properties":{"osm_id":"8916267496","tag":{"amenity":"waste_basket","waste":"trash"}},"type":"Feature"},
	{"geometry":{"coordinates":[10.230565,53.12824],"type":"Point"},"properties":{"osm_id":"8916267503","tag":{"amenity":"waste_basket","waste":"trash"}},"type":"Feature"},
	{"geometry":{"coordinates":[10.230607,53.127913],"type":"Point"},"properties":{"osm_id":"8916267505","tag":{"amenity":"waste_basket","waste":"trash"}},"type":"Feature"},
	{"geometry":{"coordinates":[10.231145,53.13228],"type":"Point"},"properties":{"osm_id":"8916292119","tag":{"amenity":"waste_basket","waste":"trash"}},"type":"Feature"},
	{"geometry":{"coordinates":[10.230085,53.133406],"type":"Point"},"properties":{"osm_id":"8916292120","tag":{"amenity":"waste_basket","waste":"trash"}},"type":"Feature"},
	{"geometry":{"coordinates":[10.232043,53.135004],"type":"Point"},"properties":{"osm_id":"8916295434","tag":{"amenity":"waste_basket","waste":"trash"}},"type":"Feature"}
]
}
