{
"type": "FeatureCollection",
"features": [
	{"geometry":{"coordinates":[10.267021,49.707472],"type":"Point"},"properties":{"osm_id":"294905422","tag":{"amenity":"recycling","location":"overground","recycling:cans":"yes","recycling:clothes":"yes","recycling:glass_bottles":"yes","recycling:shoes":"yes","recycling_type":"container"}},"type":"Feature"},
	{"geometry":{"coordinates":[10.27215,49.724412],"type":"Point"},"properties":{"osm_id":"748311841","tag":{"amenity":"recycling","recycling:batteries":"yes","recycling:glass_bottles":"yes","recycling_type":"container"}},"type":"Feature"},
	{"geometry":{"coordinates":[10.267629,49.720746],"type":"Point"},"properties":{"osm_id":"5998049348","tag":{"amenity":"waste_basket"}},"type":"Feature"},
	{"geometry":{"coordinates":[10.258659,49.70588],"type":"Point"},"properties":{"osm_id":"9159296901","tag":{"amenity":"waste_basket"}},"type":"Feature"},
	{"geometry":{"coordinates":[10.263507,49.704189],"type":"Point"},"properties":{"osm_id":"9159296916","tag":{"amenity":"waste_basket"}},"type":"Feature"},
	{"geometry":{"coordinates":[10.260035,49.701081],"type":"Point"},"properties":{"osm_id":"9159301625","tag":{"amenity":"waste_basket"}},"type":"Feature"},
	{"geometry":{"coordinates":[10.259029,49.700848],"type":"Point"},"properties":{"osm_id":"9159301626","tag":{"amenity":"waste_basket"}},"type":"Feature"},
	{"geometry":{"coordinates":[10.26811,49.720433],"type":"Point"},"properties":{"osm_id":"9173245899","tag":{"amenity":"waste_basket"}},"type":"Feature"}
]
}
