{
"type": "FeatureCollection",
"lastupdate": "2020-08-05T00:00:00Z",
"features": [
	{"geometry":{"coordinates":[10.267021,49.707472],"type":"Point"},"properties":{"osm_id":"294905422","tag":{"amenity":"recycling","location":"overground","recycling:cans":"yes","recycling:clothes":"yes","recycling:glass_bottles":"yes","recycling:shoes":"yes","recycling_type":"container"}},"type":"Feature"},
	{"geometry":{"coordinates":[10.27215,49.724412],"type":"Point"},"properties":{"osm_id":"748311841","tag":{"amenity":"recycling","recycling_type":"container"}},"type":"Feature"},
	{"geometry":{"coordinates":[10.267629,49.720746],"type":"Point"},"properties":{"osm_id":"5998049348","tag":{"amenity":"waste_basket"}},"type":"Feature"}
]
}
