{
"type": "FeatureCollection",
"lastupdate": "2020-08-01T00:00:00Z",
"features": [
	{"geometry":{"coordinates":[9.647057,39.669554],"type":"Point"},"properties":{"name":"Isola ecologica","osm_id":"1932327349","tag":{"amenity":"recycling","recycling_type":"container"}},"type":"Feature"},
	{"geometry":{"coordinates":[9.582103,39.693584],"type":"Point"},"properties":{"osm_id":"2378820585","tag":{"amenity":"recycling"}},"type":"Feature"}
]
}
