{
"type": "FeatureCollection",
"lastupdate": "2020-08-05T00:00:00Z",
"features": [
	{"geometry":{"coordinates":[-108.9107,45.296475],"type":"Point"},"properties":{"name":"Collective Recyclers Community Drop-off","osm_id":"1445844298","tag":{"addr:housenumber":"406-662-9847","addr:street":"206 N. D St, Bridger, Montana 59014","amenity":"recycling"}},"type":"Feature"},
	{"geometry":{"coordinates":[-108.909691,45.29692],"type":"Point"},"properties":{"name":"Collective Recyclers Main Address/Company Entrance","osm_id":"1445844348","tag":{"addr:housenumber":"406-662-9847","addr:street":"206 N. D St, Bridger, Montana 59014","amenity":"recycling"}},"type":"Feature"}
]
}
