{
"type": "FeatureCollection",
"lastupdate": "2020-08-02T00:00:00Z",
"features": [
	{"geometry":{"coordinates":[-62.951552,44.76721],"type":"Point"},"properties":{"name":"Enviro Depot","osm_id":"465247738","tag":{"addr:housenumber":"11460","addr:postcode":"B0J 1Y0","addr:province":"Nova Scotia","addr:street":"Highway 7","amenity":"recycling","recycling:batteries":"yes","recycling:cans":"yes","recycling:clothes":"yes","recycling:glass":"yes","recycling:paper":"yes","recycling:scrap_metal":"yes","recycling_type":"centre"}},"type":"Feature"}
]
}
