{
"type": "FeatureCollection",
"lastupdate": "2020-08-04T00:00:00Z",
"features": [
	{"geometry":{"coordinates":[8.993107,48.330056],"type":"Point"},"properties":{"osm_id":"300353307","tag":{"amenity":"recycling","location":"overground","recycling:glass_bottles":"yes","recycling_type":"container"}},"type":"Feature"},
	{"geometry":{"coordinates":[8.97577,48.341487],"type":"Point"},"properties":{"osm_id":"303411697","tag":{"amenity":"recycling"}},"type":"Feature"},
	{"geometry":{"coordinates":[8.98592,48.332672],"type":"Point"},"properties":{"osm_id":"4475423866","tag":{"amenity":"recycling","recycling:glass_bottles":"yes","recycling_type":"container"}},"type":"Feature"},
	{"geometry":{"coordinates":[9.048842,48.322862],"type":"Point"},"properties":{"osm_id":"7102270479","tag":{"amenity":"recycling","recycling:glass":"yes","recycling:glass_bottles":"yes","recycling:paper":"yes","recycling_type":"container"}},"type":"Feature"}
]
}
