{
"type": "FeatureCollection",
"lastupdate": "2020-08-01T00:00:00Z",
"features": [
	{"geometry":{"coordinates":[5.473852,60.625641],"type":"Point"},"properties":{"osm_id":"4382050340","tag":{"amenity":"recycling","description":"Ostereidet senter","location":"overground","operator":"UFF","recycling:glass_bottles":"yes","recycling_type":"container","ref:sortere":"14631"}},"type":"Feature"},
	{"geometry":{"coordinates":[5.5255,60.5917],"type":"Point"},"properties":{"osm_id":"5555200964","tag":{"amenity":"recycling","description":"Returpunkt","recycling:glass_bottles":"yes","recycling_type":"container","ref:sortere":"16889"}},"type":"Feature"},
	{"geometry":{"coordinates":[5.5218,60.5899],"type":"Point"},"properties":{"osm_id":"6195514693","tag":{"access":"permissive","amenity":"recycling","description":"Hyttekontainer","recycling_type":"container","ref:sortere":"16977"}},"type":"Feature"}
]
}
