{
"type": "FeatureCollection",
"features": [
	{"geometry":{"coordinates":[13.7629,52.109423],"type":"Point"},"properties":{"name":"Friedenseiche 1870/71","osm_id":"2515599228","tag":{"historic":"yes","natural":"tree"}},"type":"Feature"},
	{"geometry":{"coordinates":[13.743072,52.15335],"type":"Point"},"properties":{"osm_id":"3051876239","tag":{"natural":"tree"}},"type":"Feature"}
]
}
