{
"type": "FeatureCollection",
"features": [
	{"geometry":{"coordinates":[13.776235,47.869805],"type":"Point"},"properties":{"osm_id":"1311747279","tag":{"natural":"tree"}},"type":"Feature"},
	{"geometry":{"coordinates":[13.766809,47.871349],"type":"Point"},"properties":{"osm_id":"3743310704","tag":{"natural":"tree"}},"type":"Feature"},
	{"geometry":{"coordinates":[13.767262,47.87109],"type":"Point"},"properties":{"osm_id":"3743310713","tag":{"natural":"tree"}},"type":"Feature"},
	{"geometry":{"coordinates":[13.711016,47.868651],"type":"Point"},"properties":{"name":"Wunschbaum","osm_id":"7730572970","tag":{"natural":"tree"}},"type":"Feature"},
	{"geometry":{"coordinates":[13.715564,47.870218],"type":"Point"},"properties":{"name":"Mammutbaum","osm_id":"7730572975","tag":{"natural":"tree"}},"type":"Feature"}
]
}
