{
"type": "FeatureCollection",
"features": [
	{"geometry":{"coordinates":[13.776234,47.869805],"type":"Point"},"properties":{"osm_id":"1311747279","tag":{"natural":"tree"}},"type":"Feature"},
	{"geometry":{"coordinates":[13.766808,47.871349],"type":"Point"},"properties":{"osm_id":"3743310704","tag":{"natural":"tree"}},"type":"Feature"},
	{"geometry":{"coordinates":[13.767261,47.87109],"type":"Point"},"properties":{"osm_id":"3743310713","tag":{"natural":"tree"}},"type":"Feature"},
	{"geometry":{"coordinates":[13.711016,47.86865],"type":"Point"},"properties":{"name":"Wunschbaum","osm_id":"7730572970","tag":{"natural":"tree"}},"type":"Feature"},
	{"geometry":{"coordinates":[13.715564,47.870217],"type":"Point"},"properties":{"name":"Mammutbaum","osm_id":"7730572975","tag":{"natural":"tree"}},"type":"Feature"},
	{"geometry":{"coordinates":[13.780273,47.848169],"type":"Point"},"properties":{"osm_id":"8685494789","tag":{"natural":"tree"}},"type":"Feature"},
	{"geometry":{"coordinates":[13.780603,47.848183],"type":"Point"},"properties":{"osm_id":"8685494790","tag":{"natural":"tree"}},"type":"Feature"},
	{"geometry":{"coordinates":[13.78102,47.847832],"type":"Point"},"properties":{"osm_id":"8685494791","tag":{"natural":"tree"}},"type":"Feature"},
	{"geometry":{"coordinates":[13.781003,47.859229],"type":"Point"},"properties":{"osm_id":"8694032224","tag":{"natural":"tree"}},"type":"Feature"},
	{"geometry":{"coordinates":[13.780909,47.859253],"type":"Point"},"properties":{"osm_id":"8694032225","tag":{"natural":"tree"}},"type":"Feature"},
	{"geometry":{"coordinates":[13.78094,47.859321],"type":"Point"},"properties":{"osm_id":"8694032226","tag":{"natural":"tree"}},"type":"Feature"},
	{"geometry":{"coordinates":[13.781006,47.859468],"type":"Point"},"properties":{"osm_id":"8694032227","tag":{"natural":"tree"}},"type":"Feature"},
	{"geometry":{"coordinates":[13.78136,47.858937],"type":"Point"},"properties":{"osm_id":"8694032228","tag":{"natural":"tree"}},"type":"Feature"},
	{"geometry":{"coordinates":[13.781364,47.858671],"type":"Point"},"properties":{"osm_id":"8694032229","tag":{"natural":"tree"}},"type":"Feature"},
	{"geometry":{"coordinates":[13.781366,47.858399],"type":"Point"},"properties":{"osm_id":"8694032230","tag":{"natural":"tree"}},"type":"Feature"},
	{"geometry":{"coordinates":[13.781376,47.858125],"type":"Point"},"properties":{"osm_id":"8694032231","tag":{"natural":"tree"}},"type":"Feature"},
	{"geometry":{"coordinates":[13.781413,47.85783],"type":"Point"},"properties":{"osm_id":"8694032232","tag":{"natural":"tree"}},"type":"Feature"},
	{"geometry":{"coordinates":[13.781412,47.85773],"type":"Point"},"properties":{"osm_id":"8694032233","tag":{"natural":"tree"}},"type":"Feature"},
	{"geometry":{"coordinates":[13.781179,47.857117],"type":"Point"},"properties":{"osm_id":"8694032237","tag":{"natural":"tree"}},"type":"Feature"},
	{"geometry":{"coordinates":[13.778004,47.871988],"type":"Point"},"properties":{"osm_id":"8699267597","tag":{"natural":"tree"}},"type":"Feature"},
	{"geometry":{"coordinates":[13.778173,47.871885],"type":"Point"},"properties":{"osm_id":"8699267598","tag":{"natural":"tree"}},"type":"Feature"},
	{"geometry":{"coordinates":[13.778239,47.871834],"type":"Point"},"properties":{"osm_id":"8699267599","tag":{"natural":"tree"}},"type":"Feature"},
	{"geometry":{"coordinates":[13.778393,47.871697],"type":"Point"},"properties":{"osm_id":"8699267600","tag":{"natural":"tree"}},"type":"Feature"},
	{"geometry":{"coordinates":[13.778604,47.871252],"type":"Point"},"properties":{"osm_id":"8699267601","tag":{"natural":"tree"}},"type":"Feature"},
	{"geometry":{"coordinates":[13.778518,47.871372],"type":"Point"},"properties":{"osm_id":"8699267602","tag":{"natural":"tree"}},"type":"Feature"},
	{"geometry":{"coordinates":[13.77831,47.871596],"type":"Point"},"properties":{"osm_id":"8699267603","tag":{"natural":"tree"}},"type":"Feature"},
	{"geometry":{"coordinates":[13.77818,47.871705],"type":"Point"},"properties":{"osm_id":"8699267604","tag":{"natural":"tree"}},"type":"Feature"},
	{"geometry":{"coordinates":[13.778046,47.871827],"type":"Point"},"properties":{"osm_id":"8699267605","tag":{"natural":"tree"}},"type":"Feature"},
	{"geometry":{"coordinates":[13.777923,47.871923],"type":"Point"},"properties":{"osm_id":"8699267606","tag":{"natural":"tree"}},"type":"Feature"}
]
}
