{
"type": "FeatureCollection",
"features": [
	{"geometry":{"coordinates":[10.515286,53.82693],"type":"Point"},"properties":{"osm_id":"3178733513","tag":{"natural":"tree"}},"type":"Feature"},
	{"geometry":{"coordinates":[10.51544,53.826987],"type":"Point"},"properties":{"osm_id":"3178733514","tag":{"natural":"tree"}},"type":"Feature"},
	{"geometry":{"coordinates":[10.486045,53.830639],"type":"Point"},"properties":{"name":"Friedenseiche 1873","osm_id":"3465046951","tag":{"denomination":"natural_monument","natural":"tree"}},"type":"Feature"},
	{"geometry":{"coordinates":[10.543351,53.822071],"type":"Point"},"properties":{"osm_id":"3838682333","tag":{"natural":"tree"}},"type":"Feature"},
	{"geometry":{"coordinates":[10.474125,53.847692],"type":"Point"},"properties":{"osm_id":"5606954714","tag":{"natural":"tree"}},"type":"Feature"},
	{"geometry":{"coordinates":[10.504239,53.823331],"type":"Point"},"properties":{"osm_id":"7007991259","tag":{"leaf_cycle":"deciduous","leaf_type":"broadleaved","natural":"tree"}},"type":"Feature"},
	{"geometry":{"coordinates":[10.502581,53.852153],"type":"Point"},"properties":{"osm_id":"7323235871","tag":{"natural":"tree"}},"type":"Feature"},
	{"geometry":{"coordinates":[10.502771,53.852066],"type":"Point"},"properties":{"osm_id":"7323235872","tag":{"natural":"tree"}},"type":"Feature"},
	{"geometry":{"coordinates":[10.504518,53.851882],"type":"Point"},"properties":{"osm_id":"7323235873","tag":{"natural":"tree"}},"type":"Feature"},
	{"geometry":{"coordinates":[10.502938,53.851948],"type":"Point"},"properties":{"osm_id":"7323235874","tag":{"natural":"tree"}},"type":"Feature"},
	{"geometry":{"coordinates":[10.503659,53.851821],"type":"Point"},"properties":{"osm_id":"7323235875","tag":{"natural":"tree"}},"type":"Feature"},
	{"geometry":{"coordinates":[10.504098,53.851829],"type":"Point"},"properties":{"osm_id":"7323235876","tag":{"natural":"tree"}},"type":"Feature"},
	{"geometry":{"coordinates":[10.504769,53.851598],"type":"Point"},"properties":{"osm_id":"7323235877","tag":{"natural":"tree"}},"type":"Feature"},
	{"geometry":{"coordinates":[10.504741,53.851619],"type":"Point"},"properties":{"osm_id":"7323235878","tag":{"natural":"tree"}},"type":"Feature"},
	{"geometry":{"coordinates":[10.50471,53.851639],"type":"Point"},"properties":{"osm_id":"7323235879","tag":{"natural":"tree"}},"type":"Feature"},
	{"geometry":{"coordinates":[10.503921,53.852153],"type":"Point"},"properties":{"osm_id":"7323235880","tag":{"natural":"tree"}},"type":"Feature"},
	{"geometry":{"coordinates":[10.504031,53.85207],"type":"Point"},"properties":{"osm_id":"7323235881","tag":{"natural":"tree"}},"type":"Feature"},
	{"geometry":{"coordinates":[10.504677,53.85194],"type":"Point"},"properties":{"osm_id":"7323235882","tag":{"natural":"tree"}},"type":"Feature"}
]
}
