{
"type": "FeatureCollection",
"features": [
	{"geometry":{"coordinates":[10.515286,53.82693],"type":"Point"},"properties":{"osm_id":"3178733513","tag":{"natural":"tree"}},"type":"Feature"},
	{"geometry":{"coordinates":[10.515439,53.826987],"type":"Point"},"properties":{"osm_id":"3178733514","tag":{"natural":"tree"}},"type":"Feature"},
	{"geometry":{"coordinates":[10.486044,53.830638],"type":"Point"},"properties":{"name":"Friedenseiche 1873","osm_id":"3465046951","tag":{"denomination":"natural_monument","natural":"tree"}},"type":"Feature"},
	{"geometry":{"coordinates":[10.543351,53.822071],"type":"Point"},"properties":{"osm_id":"3838682333","tag":{"natural":"tree"}},"type":"Feature"},
	{"geometry":{"coordinates":[10.474125,53.847692],"type":"Point"},"properties":{"osm_id":"5606954714","tag":{"natural":"tree"}},"type":"Feature"},
	{"geometry":{"coordinates":[10.504238,53.823331],"type":"Point"},"properties":{"osm_id":"7007991259","tag":{"leaf_cycle":"deciduous","leaf_type":"broadleaved","natural":"tree"}},"type":"Feature"},
	{"geometry":{"coordinates":[10.502581,53.852153],"type":"Point"},"properties":{"osm_id":"7323235871","tag":{"natural":"tree"}},"type":"Feature"},
	{"geometry":{"coordinates":[10.50277,53.852065],"type":"Point"},"properties":{"osm_id":"7323235872","tag":{"natural":"tree"}},"type":"Feature"},
	{"geometry":{"coordinates":[10.504518,53.851881],"type":"Point"},"properties":{"osm_id":"7323235873","tag":{"natural":"tree"}},"type":"Feature"},
	{"geometry":{"coordinates":[10.502938,53.851948],"type":"Point"},"properties":{"osm_id":"7323235874","tag":{"natural":"tree"}},"type":"Feature"},
	{"geometry":{"coordinates":[10.503658,53.851821],"type":"Point"},"properties":{"osm_id":"7323235875","tag":{"natural":"tree"}},"type":"Feature"},
	{"geometry":{"coordinates":[10.504098,53.851829],"type":"Point"},"properties":{"osm_id":"7323235876","tag":{"natural":"tree"}},"type":"Feature"},
	{"geometry":{"coordinates":[10.504769,53.851597],"type":"Point"},"properties":{"osm_id":"7323235877","tag":{"natural":"tree"}},"type":"Feature"},
	{"geometry":{"coordinates":[10.50474,53.851619],"type":"Point"},"properties":{"osm_id":"7323235878","tag":{"natural":"tree"}},"type":"Feature"},
	{"geometry":{"coordinates":[10.50471,53.851638],"type":"Point"},"properties":{"osm_id":"7323235879","tag":{"natural":"tree"}},"type":"Feature"},
	{"geometry":{"coordinates":[10.50392,53.852152],"type":"Point"},"properties":{"osm_id":"7323235880","tag":{"natural":"tree"}},"type":"Feature"},
	{"geometry":{"coordinates":[10.50403,53.852069],"type":"Point"},"properties":{"osm_id":"7323235881","tag":{"natural":"tree"}},"type":"Feature"},
	{"geometry":{"coordinates":[10.504676,53.851939],"type":"Point"},"properties":{"osm_id":"7323235882","tag":{"natural":"tree"}},"type":"Feature"}
]
}
