{
"type": "FeatureCollection",
"features": [
	{"geometry":{"coordinates":[10.478457,53.274704],"type":"Point"},"properties":{"osm_id":"2920449759","tag":{"genus":"Kastanie","height":"8","leaf_type":"broadleaved","name:botanical":"Castanea","natural":"tree"}},"type":"Feature"},
	{"geometry":{"coordinates":[10.486289,53.241585],"type":"Point"},"properties":{"osm_id":"3225350976","tag":{"leaf_cycle":"evergreen","leaf_type":"needleleaved","natural":"tree"}},"type":"Feature"}
]
}
