{
"type": "FeatureCollection",
"features": [
	{"geometry":{"coordinates":[10.546259,50.119058],"type":"Point"},"properties":{"name":"Alte Linde","osm_id":"951443655","tag":{"natural":"tree"}},"type":"Feature"},
	{"geometry":{"coordinates":[10.50405,50.06682],"type":"Point"},"properties":{"osm_id":"4740960344","tag":{"natural":"tree"}},"type":"Feature"},
	{"geometry":{"coordinates":[10.543387,50.101256],"type":"Point"},"properties":{"name":"Alter Kastanienbaum","osm_id":"4851411583","tag":{"leaf_cycle":"deciduous","leaf_type":"broadleaved","natural":"tree"}},"type":"Feature"},
	{"geometry":{"coordinates":[10.495072,50.110454],"type":"Point"},"properties":{"osm_id":"7597454467","tag":{"natural":"tree"}},"type":"Feature"},
	{"geometry":{"coordinates":[10.482219,50.111077],"type":"Point"},"properties":{"osm_id":"7597454590","tag":{"natural":"tree"}},"type":"Feature"},
	{"geometry":{"coordinates":[10.482775,50.111097],"type":"Point"},"properties":{"osm_id":"7597454591","tag":{"natural":"tree"}},"type":"Feature"},
	{"geometry":{"coordinates":[10.482495,50.111092],"type":"Point"},"properties":{"osm_id":"7597454592","tag":{"natural":"tree"}},"type":"Feature"},
	{"geometry":{"coordinates":[10.481714,50.11106],"type":"Point"},"properties":{"osm_id":"7597454593","tag":{"natural":"tree"}},"type":"Feature"}
]
}
