{
"type": "FeatureCollection",
"features": [
	{"geometry":{"coordinates":[10.54626,50.119059],"type":"Point"},"properties":{"name":"Alte Linde","osm_id":"951443655","tag":{"natural":"tree"}},"type":"Feature"},
	{"geometry":{"coordinates":[10.50405,50.06682],"type":"Point"},"properties":{"osm_id":"4740960344","tag":{"natural":"tree"}},"type":"Feature"},
	{"geometry":{"coordinates":[10.543388,50.101257],"type":"Point"},"properties":{"name":"Alter Kastanienbaum","osm_id":"4851411583","tag":{"leaf_cycle":"deciduous","leaf_type":"broadleaved","natural":"tree"}},"type":"Feature"},
	{"geometry":{"coordinates":[10.495072,50.110455],"type":"Point"},"properties":{"osm_id":"7597454467","tag":{"natural":"tree"}},"type":"Feature"},
	{"geometry":{"coordinates":[10.482219,50.111077],"type":"Point"},"properties":{"osm_id":"7597454590","tag":{"natural":"tree"}},"type":"Feature"},
	{"geometry":{"coordinates":[10.482776,50.111098],"type":"Point"},"properties":{"osm_id":"7597454591","tag":{"natural":"tree"}},"type":"Feature"},
	{"geometry":{"coordinates":[10.482495,50.111093],"type":"Point"},"properties":{"osm_id":"7597454592","tag":{"natural":"tree"}},"type":"Feature"},
	{"geometry":{"coordinates":[10.481715,50.11106],"type":"Point"},"properties":{"osm_id":"7597454593","tag":{"natural":"tree"}},"type":"Feature"}
]
}
