{
"type": "FeatureCollection",
"features": [
	{"geometry":{"coordinates":[10.546746,49.16526],"type":"Point"},"properties":{"osm_id":"1947302447","tag":{"natural":"tree"}},"type":"Feature"},
	{"geometry":{"coordinates":[10.54669,49.165336],"type":"Point"},"properties":{"osm_id":"1947302452","tag":{"natural":"tree"}},"type":"Feature"},
	{"geometry":{"coordinates":[10.54663,49.165417],"type":"Point"},"properties":{"osm_id":"1947302457","tag":{"natural":"tree"}},"type":"Feature"},
	{"geometry":{"coordinates":[10.544564,49.16518],"type":"Point"},"properties":{"osm_id":"1947328578","tag":{"natural":"tree"}},"type":"Feature"},
	{"geometry":{"coordinates":[10.513799,49.177568],"type":"Point"},"properties":{"name":"Kraberbaum","osm_id":"4076555978","tag":{"natural":"tree"}},"type":"Feature"},
	{"geometry":{"coordinates":[10.475975,49.172387],"type":"Point"},"properties":{"osm_id":"4237467716","tag":{"denotation":"landmark","natural":"tree"}},"type":"Feature"}
]
}
