{
"type": "FeatureCollection",
"features": [
	{"geometry":{"coordinates":[10.546745,49.16526],"type":"Point"},"properties":{"osm_id":"1947302447","tag":{"natural":"tree"}},"type":"Feature"},
	{"geometry":{"coordinates":[10.546689,49.165335],"type":"Point"},"properties":{"osm_id":"1947302452","tag":{"natural":"tree"}},"type":"Feature"},
	{"geometry":{"coordinates":[10.54663,49.165416],"type":"Point"},"properties":{"osm_id":"1947302457","tag":{"natural":"tree"}},"type":"Feature"},
	{"geometry":{"coordinates":[10.544563,49.16518],"type":"Point"},"properties":{"osm_id":"1947328578","tag":{"natural":"tree"}},"type":"Feature"},
	{"geometry":{"coordinates":[10.513799,49.177567],"type":"Point"},"properties":{"name":"Kraberbaum","osm_id":"4076555978","tag":{"natural":"tree"}},"type":"Feature"},
	{"geometry":{"coordinates":[10.475975,49.172386],"type":"Point"},"properties":{"osm_id":"4237467716","tag":{"denotation":"landmark","natural":"tree"}},"type":"Feature"}
]
}
