{
"type": "FeatureCollection",
"features": [
	{"geometry":{"coordinates":[10.480328,49.047765],"type":"Point"},"properties":{"osm_id":"1537326534","tag":{"natural":"tree"}},"type":"Feature"},
	{"geometry":{"coordinates":[10.478611,49.046418],"type":"Point"},"properties":{"osm_id":"2317281119","tag":{"natural":"tree"}},"type":"Feature"},
	{"geometry":{"coordinates":[10.5009,49.048986],"type":"Point"},"properties":{"osm_id":"6261925797","tag":{"leaf_cycle":"deciduous","leaf_type":"broadleaved","natural":"tree"}},"type":"Feature"},
	{"geometry":{"coordinates":[10.517289,49.062875],"type":"Point"},"properties":{"name":"Kastanienallee","osm_id":"6584284960","tag":{"denotation":"landmark","natural":"tree"}},"type":"Feature"},
	{"geometry":{"coordinates":[10.517454,49.063034],"type":"Point"},"properties":{"name":"Kastanienallee","osm_id":"6584299022","tag":{"denotation":"landmark","natural":"tree"}},"type":"Feature"},
	{"geometry":{"coordinates":[10.498819,49.069096],"type":"Point"},"properties":{"osm_id":"6694977762","tag":{"leaf_cycle":"deciduous","leaf_type":"broadleaved","natural":"tree"}},"type":"Feature"}
]
}
