{
"type": "FeatureCollection",
"features": [
	{"geometry":{"coordinates":[10.480329,49.047766],"type":"Point"},"properties":{"osm_id":"1537326534","tag":{"natural":"tree"}},"type":"Feature"},
	{"geometry":{"coordinates":[10.478612,49.046418],"type":"Point"},"properties":{"osm_id":"2317281119","tag":{"natural":"tree"}},"type":"Feature"},
	{"geometry":{"coordinates":[10.5009,49.048987],"type":"Point"},"properties":{"osm_id":"6261925797","tag":{"leaf_cycle":"deciduous","leaf_type":"broadleaved","natural":"tree"}},"type":"Feature"},
	{"geometry":{"coordinates":[10.517289,49.062875],"type":"Point"},"properties":{"name":"Kastanienallee","osm_id":"6584284960","tag":{"denotation":"landmark","natural":"tree"}},"type":"Feature"},
	{"geometry":{"coordinates":[10.517454,49.063035],"type":"Point"},"properties":{"name":"Kastanienallee","osm_id":"6584299022","tag":{"denotation":"landmark","natural":"tree"}},"type":"Feature"},
	{"geometry":{"coordinates":[10.49882,49.069097],"type":"Point"},"properties":{"osm_id":"6694977762","tag":{"leaf_cycle":"deciduous","leaf_type":"broadleaved","natural":"tree"}},"type":"Feature"}
]
}
