{
"type": "FeatureCollection",
"features": [
	{"geometry":{"coordinates":[10.533876,45.844407],"type":"Point"},"properties":{"name":"Castagno del singol","osm_id":"2023809452","tag":{"name:botanical":"Castanea sativa","natural":"tree","type":"chestnut"}},"type":"Feature"}
]
}
