{
"type": "FeatureCollection",
"features": [
	{"geometry":{"coordinates":[10.496957,42.988548],"type":"Point"},"properties":{"osm_id":"1651069302","tag":{"circumference":"3.7","name:botanical":"Quercus pubescens","natural":"tree","type":"Roverella"}},"type":"Feature"},
	{"geometry":{"coordinates":[10.493978,42.985883],"type":"Point"},"properties":{"osm_id":"2081333728","tag":{"circumference":"1.2","name:botanical":"Laurus nobilis","natural":"tree","type":"Alloro"}},"type":"Feature"},
	{"geometry":{"coordinates":[10.495656,42.987951],"type":"Point"},"properties":{"osm_id":"2081333729","tag":{"circumference":"3.5","name:botanical":"Pinus pinea","natural":"tree","type":"Pino domestico"}},"type":"Feature"},
	{"geometry":{"coordinates":[10.491254,42.989645],"type":"Point"},"properties":{"osm_id":"2820760441","tag":{"natural":"tree"}},"type":"Feature"},
	{"geometry":{"coordinates":[10.49107,42.98966],"type":"Point"},"properties":{"osm_id":"2820760446","tag":{"natural":"tree"}},"type":"Feature"}
]
}
