{
"type": "FeatureCollection",
"lastupdate": "2020-07-31T00:00:00Z",
"features": [
	{"geometry":{"coordinates":[1.147719,52.320604],"type":"Point"},"properties":{"osm_id":"284992279","tag":{"amenity":"recycling","layer":"3","location":"overground","recycling:glass":"yes","recycling_type":"container"}},"type":"Feature"},
	{"geometry":{"coordinates":[1.154975,52.319848],"type":"Point"},"properties":{"osm_id":"4888261269","tag":{"amenity":"waste_basket"}},"type":"Feature"},
	{"geometry":{"coordinates":[1.145835,52.320237],"type":"Point"},"properties":{"osm_id":"7040539618","tag":{"amenity":"waste_basket"}},"type":"Feature"}
]
}
