{
"type": "FeatureCollection",
"lastupdate": "2020-08-06T00:00:00Z",
"features": [
	{"geometry":{"coordinates":[11.471991,49.750521],"type":"Point"},"properties":{"osm_id":"946954325","tag":{"amenity":"recycling"}},"type":"Feature"},
	{"geometry":{"coordinates":[11.506022,49.739441],"type":"Point"},"properties":{"osm_id":"1315495722","tag":{"amenity":"recycling","location":"overground","recycling:glass":"yes","recycling_type":"container"}},"type":"Feature"},
	{"geometry":{"coordinates":[11.465483,49.727254],"type":"Point"},"properties":{"osm_id":"1413928621","tag":{"amenity":"waste_basket"}},"type":"Feature"},
	{"geometry":{"coordinates":[11.471407,49.727474],"type":"Point"},"properties":{"osm_id":"1438386272","tag":{"amenity":"recycling","recycling:cans":"yes","recycling:clothes":"yes","recycling:glass":"yes","recycling:shoes":"yes","recycling_type":"container"}},"type":"Feature"},
	{"geometry":{"coordinates":[11.510307,49.74825],"type":"Point"},"properties":{"osm_id":"7774190045","tag":{"amenity":"waste_basket"}},"type":"Feature"},
	{"geometry":{"coordinates":[11.51063,49.748289],"type":"Point"},"properties":{"osm_id":"7774190046","tag":{"amenity":"waste_basket"}},"type":"Feature"},
	{"geometry":{"coordinates":[11.511091,49.74846],"type":"Point"},"properties":{"osm_id":"7774190047","tag":{"amenity":"waste_basket"}},"type":"Feature"}
]
}
