{
"type": "FeatureCollection",
"lastupdate": "2020-07-31T00:00:00Z",
"features": [
	{"geometry":{"coordinates":[11.440496,49.272967],"type":"Point"},"properties":{"osm_id":"190125839","tag":{"amenity":"recycling"}},"type":"Feature"},
	{"geometry":{"coordinates":[11.438023,49.27909],"type":"Point"},"properties":{"osm_id":"190138367","tag":{"amenity":"recycling","recycling_type":"container"}},"type":"Feature"},
	{"geometry":{"coordinates":[11.431824,49.282493],"type":"Point"},"properties":{"osm_id":"190138375","tag":{"amenity":"recycling"}},"type":"Feature"},
	{"geometry":{"coordinates":[11.45197,49.275622],"type":"Point"},"properties":{"osm_id":"192296295","tag":{"amenity":"recycling","location":"overground","recycling_type":"container"}},"type":"Feature"},
	{"geometry":{"coordinates":[11.464286,49.300742],"type":"Point"},"properties":{"osm_id":"201670570","tag":{"amenity":"recycling"}},"type":"Feature"},
	{"geometry":{"coordinates":[11.455736,49.311868],"type":"Point"},"properties":{"osm_id":"281253856","tag":{"amenity":"recycling","recycling:batteries":"no","recycling:clothes":"no"}},"type":"Feature"},
	{"geometry":{"coordinates":[11.457595,49.315272],"type":"Point"},"properties":{"osm_id":"281253875","tag":{"amenity":"recycling","recycling:batteries":"no","recycling:clothes":"no"}},"type":"Feature"},
	{"geometry":{"coordinates":[11.469069,49.286394],"type":"Point"},"properties":{"osm_id":"289901025","tag":{"amenity":"recycling","location":"overground","recycling:clothes":"yes","recycling:glass":"yes","recycling:glass_bottles":"yes","recycling_type":"container"}},"type":"Feature"},
	{"geometry":{"coordinates":[11.456234,49.287993],"type":"Point"},"properties":{"osm_id":"289901026","tag":{"amenity":"recycling","recycling:clothes":"yes","recycling:glass":"yes"}},"type":"Feature"},
	{"geometry":{"coordinates":[11.466699,49.281718],"type":"Point"},"properties":{"osm_id":"294935130","tag":{"amenity":"recycling","recycling:clothes":"yes","recycling:glass":"yes"}},"type":"Feature"},
	{"geometry":{"coordinates":[11.49041,49.286231],"type":"Point"},"properties":{"osm_id":"295472252","tag":{"amenity":"recycling","location":"overground","recycling:clothes":"yes","recycling_type":"container"}},"type":"Feature"},
	{"geometry":{"coordinates":[11.501551,49.318046],"type":"Point"},"properties":{"osm_id":"305472263","tag":{"amenity":"recycling","recycling:clothes":"yes","recycling:glass":"yes","recycling_type":"container"}},"type":"Feature"},
	{"geometry":{"coordinates":[11.454055,49.280176],"type":"Point"},"properties":{"osm_id":"345303460","tag":{"amenity":"recycling","recycling:clothes":"yes","recycling:glass":"yes","recycling:paper":"no","recycling:scrap_metal":"yes","recycling_type":"container"}},"type":"Feature"},
	{"geometry":{"coordinates":[11.477768,49.294179],"type":"Point"},"properties":{"osm_id":"1768037445","tag":{"amenity":"waste_basket"}},"type":"Feature"},
	{"geometry":{"coordinates":[11.474846,49.289992],"type":"Point"},"properties":{"osm_id":"1768056510","tag":{"amenity":"waste_basket"}},"type":"Feature"},
	{"geometry":{"coordinates":[11.450336,49.285326],"type":"Point"},"properties":{"osm_id":"1971242681","tag":{"amenity":"recycling","recycling:batteries":"no","recycling:books":"no","recycling:cans":"yes","recycling:cardboard":"no","recycling:cartons":"no","recycling:clothes":"no","recycling:electrical_appliances":"no","recycling:glass":"no","recycling:glass_bottles":"yes","recycling:green_waste":"no","recycling:magazines":"no","recycling:newspaper":"no","recycling:paper_packaging":"no","recycling:plastic":"no","recycling:plastic_bottles":"no","recycling:plastic_packaging":"no","recycling:scrap_metal":"no","recycling:small_appliances":"no","recycling:waste":"no","recycling:wood":"no","recycling_type":"container"}},"type":"Feature"},
	{"geometry":{"coordinates":[11.483387,49.27992],"type":"Point"},"properties":{"osm_id":"4965515448","tag":{"amenity":"recycling","recycling:glass_bottles":"yes","recycling_type":"container"}},"type":"Feature"},
	{"geometry":{"coordinates":[11.502314,49.270872],"type":"Point"},"properties":{"osm_id":"5189344753","tag":{"amenity":"waste_basket"}},"type":"Feature"},
	{"geometry":{"coordinates":[11.464347,49.295103],"type":"Point"},"properties":{"osm_id":"5236380824","tag":{"amenity":"waste_basket"}},"type":"Feature"},
	{"geometry":{"coordinates":[11.463705,49.294765],"type":"Point"},"properties":{"osm_id":"5236387926","tag":{"amenity":"waste_basket"}},"type":"Feature"}
]
}
