{
"type": "FeatureCollection",
"features": [
	{"geometry":{"coordinates":[11.438774,43.774727],"type":"Point"},"properties":{"name":"Italia Spurghi","osm_id":"7873785975","tag":{"amenity":"recycling","recycling_type":"centre"}},"type":"Feature"},
	{"geometry":{"coordinates":[11.43703,43.771126],"type":"Point"},"properties":{"osm_id":"7938624293","tag":{"amenity":"recycling","recycling_type":"container"}},"type":"Feature"},
	{"geometry":{"coordinates":[11.437046,43.771211],"type":"Point"},"properties":{"osm_id":"7938624294","tag":{"amenity":"recycling","recycling_type":"container"}},"type":"Feature"},
	{"geometry":{"coordinates":[11.436511,43.772134],"type":"Point"},"properties":{"osm_id":"7959669182","tag":{"amenity":"recycling","recycling_type":"container"}},"type":"Feature"},
	{"geometry":{"coordinates":[11.436119,43.774916],"type":"Point"},"properties":{"osm_id":"8075741876","tag":{"amenity":"recycling","recycling_type":"container"}},"type":"Feature"},
	{"geometry":{"coordinates":[11.442458,43.774991],"type":"Point"},"properties":{"osm_id":"8075741877","tag":{"amenity":"recycling","recycling_type":"container"}},"type":"Feature"},
	{"geometry":{"coordinates":[11.443795,43.775491],"type":"Point"},"properties":{"osm_id":"8075741878","tag":{"amenity":"recycling","recycling_type":"container"}},"type":"Feature"},
	{"geometry":{"coordinates":[11.438892,43.772471],"type":"Point"},"properties":{"osm_id":"8075741879","tag":{"amenity":"recycling","recycling_type":"container"}},"type":"Feature"},
	{"geometry":{"coordinates":[11.436266,43.776053],"type":"Point"},"properties":{"osm_id":"8075741881","tag":{"amenity":"recycling","recycling_type":"container"}},"type":"Feature"},
	{"geometry":{"coordinates":[11.440518,43.774431],"type":"Point"},"properties":{"osm_id":"8075741882","tag":{"amenity":"recycling","recycling_type":"container"}},"type":"Feature"},
	{"geometry":{"coordinates":[11.445867,43.775644],"type":"Point"},"properties":{"osm_id":"8075741883","tag":{"amenity":"recycling","recycling_type":"container"}},"type":"Feature"},
	{"geometry":{"coordinates":[11.440572,43.773051],"type":"Point"},"properties":{"osm_id":"8075741884","tag":{"amenity":"recycling","recycling_type":"container"}},"type":"Feature"},
	{"geometry":{"coordinates":[11.433936,43.771597],"type":"Point"},"properties":{"osm_id":"8075741885","tag":{"amenity":"recycling","recycling_type":"container"}},"type":"Feature"},
	{"geometry":{"coordinates":[11.435989,43.773463],"type":"Point"},"properties":{"osm_id":"8075741886","tag":{"amenity":"recycling","recycling_type":"container"}},"type":"Feature"},
	{"geometry":{"coordinates":[11.437962,43.774452],"type":"Point"},"properties":{"osm_id":"8075741887","tag":{"amenity":"recycling","recycling_type":"container"}},"type":"Feature"},
	{"geometry":{"coordinates":[11.444586,43.777766],"type":"Point"},"properties":{"osm_id":"8075741888","tag":{"amenity":"recycling","recycling_type":"container"}},"type":"Feature"},
	{"geometry":{"coordinates":[11.44026,43.775813],"type":"Point"},"properties":{"osm_id":"8075741889","tag":{"amenity":"recycling","recycling_type":"container"}},"type":"Feature"},
	{"geometry":{"coordinates":[11.431388,43.773134],"type":"Point"},"properties":{"osm_id":"8075741890","tag":{"amenity":"recycling","recycling_type":"container"}},"type":"Feature"},
	{"geometry":{"coordinates":[11.441905,43.777759],"type":"Point"},"properties":{"osm_id":"8075973879","tag":{"amenity":"recycling","recycling_type":"container"}},"type":"Feature"},
	{"geometry":{"coordinates":[11.441664,43.775254],"type":"Point"},"properties":{"osm_id":"8076064443","tag":{"amenity":"recycling","recycling_type":"container"}},"type":"Feature"},
	{"geometry":{"coordinates":[11.43114,43.776664],"type":"Point"},"properties":{"osm_id":"8076064455","tag":{"amenity":"recycling","recycling_type":"container"}},"type":"Feature"},
	{"geometry":{"coordinates":[11.438308,43.771829],"type":"Point"},"properties":{"osm_id":"8313289374","tag":{"amenity":"recycling","recycling_type":"container"}},"type":"Feature"}
]
}
