{
"type": "FeatureCollection",
"features": [
	{"geometry":{"coordinates":[11.438774,43.774727],"type":"Point"},"properties":{"name":"Italia Spurghi","osm_id":"7873785975"},"type":"Feature"},
	{"geometry":{"coordinates":[11.438774,43.774727],"type":"Point"},"properties":{"name":"Italia Spurghi","osm_id":"7873785975","tag":{"amenity":"recycling","recycling_type":"centre"}},"type":"Feature"}
]
}
