{
"type": "FeatureCollection",
"features": [
	{"geometry":{"coordinates":[11.438774,43.774727],"type":"Point"},"properties":{"name":"Italia Spurghi","osm_id":"7873785975","tag":{"amenity":"recycling","recycling_type":"centre"}},"type":"Feature"},
	{"geometry":{"coordinates":[11.43703,43.771126],"type":"Point"},"properties":{"osm_id":"7938624293","tag":{"amenity":"recycling","recycling_type":"container"}},"type":"Feature"},
	{"geometry":{"coordinates":[11.437046,43.771211],"type":"Point"},"properties":{"osm_id":"7938624294","tag":{"amenity":"recycling","recycling_type":"container"}},"type":"Feature"},
	{"geometry":{"coordinates":[11.436511,43.772134],"type":"Point"},"properties":{"osm_id":"7959669182","tag":{"amenity":"recycling","recycling_type":"container"}},"type":"Feature"}
]
}
