{
"type": "FeatureCollection",
"features": [
	{"geometry":{"coordinates":[-7.241446,53.188945],"type":"Point"},"properties":{"name":"Billa Tree","osm_id":"8616013442","tag":{"natural":"tree"}},"type":"Feature"}
]
}
