{
"type": "FeatureCollection",
"features": [
	{"geometry":{"coordinates":[-7.241446,53.188945],"type":"Point"},"properties":{"name":"Billa Tree","osm_id":"8616013442","tag":{"natural":"tree"}},"type":"Feature"},
	{"geometry":{"coordinates":[-7.23227,53.211369],"type":"Point"},"properties":{"osm_id":"9124346219","tag":{"natural":"tree"}},"type":"Feature"},
	{"geometry":{"coordinates":[-7.231975,53.211423],"type":"Point"},"properties":{"osm_id":"9124346220","tag":{"natural":"tree"}},"type":"Feature"},
	{"geometry":{"coordinates":[-7.230607,53.211028],"type":"Point"},"properties":{"osm_id":"9124346221","tag":{"natural":"tree"}},"type":"Feature"},
	{"geometry":{"coordinates":[-7.215941,53.208834],"type":"Point"},"properties":{"osm_id":"9124432291","tag":{"natural":"tree"}},"type":"Feature"},
	{"geometry":{"coordinates":[-7.216102,53.208863],"type":"Point"},"properties":{"osm_id":"9124432292","tag":{"natural":"tree"}},"type":"Feature"},
	{"geometry":{"coordinates":[-7.217607,53.209149],"type":"Point"},"properties":{"osm_id":"9124432293","tag":{"natural":"tree"}},"type":"Feature"}
]
}
