{
"type": "FeatureCollection",
"features": [
	{"geometry":{"coordinates":[11.371261,50.826258],"type":"Point"},"properties":{"osm_id":"276080359","tag":{"natural":"tree","tourism":"attraction"}},"type":"Feature"},
	{"geometry":{"coordinates":[11.362222,50.825438],"type":"Point"},"properties":{"osm_id":"281799540","tag":{"genus":"Tilia","genus:de":"Linde","leaf_cycle":"deciduous","leaf_type":"broadleaved","natural":"tree"}},"type":"Feature"},
	{"geometry":{"coordinates":[11.397279,50.793388],"type":"Point"},"properties":{"name":"Spaal-Linde","osm_id":"4502506773","tag":{"genus":"Tilia","genus:de":"Linde","leaf_type":"broadleaved","natural":"tree"}},"type":"Feature"},
	{"geometry":{"coordinates":[11.418169,50.839135],"type":"Point"},"properties":{"osm_id":"4831026796","tag":{"leaf_cycle":"deciduous","leaf_type":"broadleaved","natural":"tree"}},"type":"Feature"},
	{"geometry":{"coordinates":[11.340036,50.808526],"type":"Point"},"properties":{"osm_id":"6515423623","tag":{"denotation":"landmark","diameter_crown":"10","genus":"Tilia","height":"12","leaf_cycle":"deciduous","leaf_type":"broadleaved","natural":"tree"}},"type":"Feature"}
]
}
