{
"type": "FeatureCollection",
"features": [
	{"geometry":{"coordinates":[11.38936,50.714553],"type":"Point"},"properties":{"osm_id":"1075098601","tag":{"denotation":"landmark","leaf_cycle":"deciduous","leaf_type":"broadleaved","natural":"tree"}},"type":"Feature"},
	{"geometry":{"coordinates":[11.347257,50.696066],"type":"Point"},"properties":{"osm_id":"1630123584","tag":{"description":"Linde","leaf_type":"broadleaved","natural":"tree"}},"type":"Feature"},
	{"geometry":{"coordinates":[11.34724,50.696071],"type":"Point"},"properties":{"osm_id":"1630123585","tag":{"description":"Linde","leaf_type":"broadleaved","natural":"tree"}},"type":"Feature"},
	{"geometry":{"coordinates":[11.347221,50.696077],"type":"Point"},"properties":{"osm_id":"1630123586","tag":{"description":"Linde","leaf_type":"broadleaved","natural":"tree"}},"type":"Feature"},
	{"geometry":{"coordinates":[11.358296,50.68994],"type":"Point"},"properties":{"name":"Biedernlinde","osm_id":"1713400351","tag":{"natural":"tree"}},"type":"Feature"},
	{"geometry":{"coordinates":[11.374236,50.68926],"type":"Point"},"properties":{"osm_id":"2130869970","tag":{"natural":"tree"}},"type":"Feature"},
	{"geometry":{"coordinates":[11.39246,50.730791],"type":"Point"},"properties":{"osm_id":"3567667982","tag":{"denotation":"landmark","leaf_type":"broadleaved","natural":"tree"}},"type":"Feature"},
	{"geometry":{"coordinates":[11.350156,50.725767],"type":"Point"},"properties":{"osm_id":"4303406167","tag":{"natural":"tree"}},"type":"Feature"},
	{"geometry":{"coordinates":[11.341273,50.696539],"type":"Point"},"properties":{"name":"Wurzeleiche","osm_id":"4510265514","tag":{"natural":"tree"}},"type":"Feature"},
	{"geometry":{"coordinates":[11.339798,50.722308],"type":"Point"},"properties":{"osm_id":"4971304175","tag":{"natural":"tree"}},"type":"Feature"},
	{"geometry":{"coordinates":[11.339737,50.722315],"type":"Point"},"properties":{"osm_id":"4971304176","tag":{"natural":"tree"}},"type":"Feature"},
	{"geometry":{"coordinates":[11.339676,50.722322],"type":"Point"},"properties":{"osm_id":"4971304177","tag":{"natural":"tree"}},"type":"Feature"},
	{"geometry":{"coordinates":[11.33992,50.722294],"type":"Point"},"properties":{"osm_id":"4971304178","tag":{"natural":"tree"}},"type":"Feature"},
	{"geometry":{"coordinates":[11.339859,50.722301],"type":"Point"},"properties":{"osm_id":"4971304179","tag":{"natural":"tree"}},"type":"Feature"},
	{"geometry":{"coordinates":[11.339782,50.72226],"type":"Point"},"properties":{"osm_id":"4971304180","tag":{"natural":"tree"}},"type":"Feature"},
	{"geometry":{"coordinates":[11.339721,50.722267],"type":"Point"},"properties":{"osm_id":"4971304181","tag":{"natural":"tree"}},"type":"Feature"},
	{"geometry":{"coordinates":[11.33966,50.722274],"type":"Point"},"properties":{"osm_id":"4971304182","tag":{"natural":"tree"}},"type":"Feature"},
	{"geometry":{"coordinates":[11.339904,50.722246],"type":"Point"},"properties":{"osm_id":"4971304183","tag":{"natural":"tree"}},"type":"Feature"},
	{"geometry":{"coordinates":[11.339843,50.722253],"type":"Point"},"properties":{"osm_id":"4971304184","tag":{"natural":"tree"}},"type":"Feature"},
	{"geometry":{"coordinates":[11.339892,50.722199],"type":"Point"},"properties":{"osm_id":"4971304185","tag":{"natural":"tree"}},"type":"Feature"},
	{"geometry":{"coordinates":[11.339831,50.722206],"type":"Point"},"properties":{"osm_id":"4971304186","tag":{"natural":"tree"}},"type":"Feature"},
	{"geometry":{"coordinates":[11.33977,50.722213],"type":"Point"},"properties":{"osm_id":"4971304187","tag":{"natural":"tree"}},"type":"Feature"},
	{"geometry":{"coordinates":[11.339709,50.72222],"type":"Point"},"properties":{"osm_id":"4971304188","tag":{"natural":"tree"}},"type":"Feature"},
	{"geometry":{"coordinates":[11.339648,50.722227],"type":"Point"},"properties":{"osm_id":"4971304189","tag":{"natural":"tree"}},"type":"Feature"},
	{"geometry":{"coordinates":[11.339643,50.722559],"type":"Point"},"properties":{"osm_id":"4971304190","tag":{"natural":"tree"}},"type":"Feature"},
	{"geometry":{"coordinates":[11.338582,50.722666],"type":"Point"},"properties":{"osm_id":"5940237513","tag":{"genus:de":"Birke","genus:en":"birch","natural":"tree"}},"type":"Feature"},
	{"geometry":{"coordinates":[11.340063,50.722018],"type":"Point"},"properties":{"osm_id":"5940237514","tag":{"genus:de":"Buche","genus:en":"beech","natural":"tree"}},"type":"Feature"},
	{"geometry":{"coordinates":[11.338086,50.72346],"type":"Point"},"properties":{"osm_id":"5940244737","tag":{"natural":"tree"}},"type":"Feature"},
	{"geometry":{"coordinates":[11.41751,50.722015],"type":"Point"},"properties":{"osm_id":"7594490126","tag":{"denotation":"urban","leaf_cycle":"deciduous","leaf_type":"broadleaved","natural":"tree"}},"type":"Feature"}
]
}
