{
"type": "FeatureCollection",
"features": [
	{"geometry":{"coordinates":[11.360549,43.12546],"type":"Point"},"properties":{"osm_id":"3905344869","tag":{"circumference":"3.2","leaf_cycle":"deciduous","leaf_type":"broadleaved","name:botanical":"Fraxinus oxyphylla","natural":"tree"}},"type":"Feature"}
]
}
