{
"type": "FeatureCollection",
"features": [
	{"geometry":{"coordinates":[17.7769,53.344764],"type":"Point"},"properties":{"osm_id":"4706692573","tag":{"denotation":"natural_monument","natural":"tree","ref:CRFOP":"PL.ZIPOP.1393.PP.0403043.976","ref:INSPIRE":"PL.ZIPOP.1393.PP.0403043.976","website":"http://crfop.gdos.gov.pl/CRFOP/widok/viewfop.jsf?fop=PL.ZIPOP.1393.PP.0403043.976"}},"type":"Feature"}
]
}
