{
"type": "FeatureCollection",
"features": [
	{"geometry":{"coordinates":[17.818391,53.112094],"type":"Point"},"properties":{"osm_id":"4706694891","tag":{"denotation":"natural_monument","natural":"tree","ref:CRFOP":"PL.ZIPOP.1393.PP.0403012.51","ref:INSPIRE":"PL.ZIPOP.1393.PP.0403012.51","start_date":"1991-08-14","website":"http://crfop.gdos.gov.pl/CRFOP/widok/viewfop.jsf?fop=PL.ZIPOP.1393.PP.0403012.51"}},"type":"Feature"}
]
}
