{
"type": "FeatureCollection",
"features": [
	{"geometry":{"coordinates":[17.785405,52.873563],"type":"Point"},"properties":{"osm_id":"4706665403","tag":{"denotation":"natural_monument","natural":"tree","ref:CRFOP":"PL.ZIPOP.1393.PP.0419063.2286","ref:INSPIRE":"PL.ZIPOP.1393.PP.0419063.2286","website":"http://crfop.gdos.gov.pl/CRFOP/widok/viewfop.jsf?fop=PL.ZIPOP.1393.PP.0419063.2286"}},"type":"Feature"},
	{"geometry":{"coordinates":[17.764828,52.88521],"type":"Point"},"properties":{"osm_id":"4706665404","tag":{"denotation":"natural_monument","natural":"tree","ref:CRFOP":"PL.ZIPOP.1393.PP.0419063.2285","ref:INSPIRE":"PL.ZIPOP.1393.PP.0419063.2285","website":"http://crfop.gdos.gov.pl/CRFOP/widok/viewfop.jsf?fop=PL.ZIPOP.1393.PP.0419063.2285"}},"type":"Feature"},
	{"geometry":{"coordinates":[17.765097,52.88508],"type":"Point"},"properties":{"osm_id":"4706665405","tag":{"denotation":"natural_monument","natural":"tree","ref:CRFOP":"PL.ZIPOP.1393.PP.0419063.2285","ref:INSPIRE":"PL.ZIPOP.1393.PP.0419063.2285","website":"http://crfop.gdos.gov.pl/CRFOP/widok/viewfop.jsf?fop=PL.ZIPOP.1393.PP.0419063.2285"}},"type":"Feature"}
]
}
