{
"type": "FeatureCollection",
"features": [
	{"geometry":{"coordinates":[16.426642,49.11418],"type":"Point"},"properties":{"osm_id":"347315809","tag":{"amenity":"recycling"}},"type":"Feature"},
	{"geometry":{"coordinates":[16.426506,49.114313],"type":"Point"},"properties":{"osm_id":"347315816","tag":{"amenity":"recycling","location":"overground","recycling_type":"container"}},"type":"Feature"},
	{"geometry":{"coordinates":[16.428881,49.113328],"type":"Point"},"properties":{"osm_id":"347315822","tag":{"amenity":"recycling","location":"overground","recycling_type":"container"}},"type":"Feature"},
	{"geometry":{"coordinates":[16.360707,49.102059],"type":"Point"},"properties":{"osm_id":"5306707824","tag":{"amenity":"waste_basket"}},"type":"Feature"},
	{"geometry":{"coordinates":[16.355216,49.104661],"type":"Point"},"properties":{"osm_id":"5306707826","tag":{"amenity":"waste_basket"}},"type":"Feature"},
	{"geometry":{"coordinates":[16.350952,49.108157],"type":"Point"},"properties":{"osm_id":"5306707828","tag":{"amenity":"waste_basket"}},"type":"Feature"},
	{"geometry":{"coordinates":[16.350077,49.107912],"type":"Point"},"properties":{"osm_id":"5306707830","tag":{"amenity":"waste_basket"}},"type":"Feature"},
	{"geometry":{"coordinates":[16.364765,49.098955],"type":"Point"},"properties":{"osm_id":"5875790285","tag":{"amenity":"waste_basket"}},"type":"Feature"},
	{"geometry":{"coordinates":[16.361624,49.100219],"type":"Point"},"properties":{"osm_id":"5875957138","tag":{"amenity":"waste_basket"}},"type":"Feature"},
	{"geometry":{"coordinates":[16.374637,49.0964],"type":"Point"},"properties":{"osm_id":"6359296492","tag":{"amenity":"recycling","recycling:clothes":"yes","recycling:electrical_appliances":"yes","recycling:glass":"yes","recycling:glass_bottles":"yes","recycling:paper":"yes","recycling:plastic":"yes","recycling:plastic_bottles":"yes","recycling:plastic_packaging":"yes","recycling:shoes":"yes","recycling:small_appliances":"yes","recycling_type":"container"}},"type":"Feature"},
	{"geometry":{"coordinates":[16.385763,49.096988],"type":"Point"},"properties":{"osm_id":"7473534185","tag":{"amenity":"waste_basket"}},"type":"Feature"},
	{"geometry":{"coordinates":[16.378772,49.097268],"type":"Point"},"properties":{"osm_id":"7657412094","tag":{"amenity":"recycling","recycling_type":"container"}},"type":"Feature"}
]
}
