{
"type": "FeatureCollection",
"features": [
	{"geometry":{"coordinates":[-15.061542,11.244504],"type":"Point"},"properties":{"name":"Poilau Grande","osm_id":"4739937622","tag":{"natural":"tree"}},"type":"Feature"}
]
}
