{
"type": "FeatureCollection",
"features": [
	{"geometry":{"coordinates":[-120.104003,38.126766],"type":"Point"},"properties":{"name":"Red Pine Tree","osm_id":"2794092611","tag":{"natural":"tree","type":"conifer"}},"type":"Feature"},
	{"geometry":{"coordinates":[-120.124241,38.097207],"type":"Point"},"properties":{"osm_id":"2794104468","tag":{"denotation":"landmark","natural":"tree","type":"conifer"}},"type":"Feature"},
	{"geometry":{"coordinates":[-120.123336,38.097011],"type":"Point"},"properties":{"osm_id":"2794104469","tag":{"denotation":"landmark","natural":"tree","type":"conifer"}},"type":"Feature"},
	{"geometry":{"coordinates":[-120.124345,38.097923],"type":"Point"},"properties":{"osm_id":"2794104470","tag":{"denotation":"landmark","natural":"tree","type":"conifer"}},"type":"Feature"},
	{"geometry":{"coordinates":[-120.123315,38.097785],"type":"Point"},"properties":{"osm_id":"2794104471","tag":{"denotation":"landmark","natural":"tree","type":"conifer"}},"type":"Feature"}
]
}
