{
"type": "FeatureCollection",
"features": [
	{"geometry":{"coordinates":[21.523606,49.604402],"type":"Point"},"properties":{"osm_id":"3158588471","tag":{"natural":"tree"}},"type":"Feature"},
	{"geometry":{"coordinates":[21.523699,49.604424],"type":"Point"},"properties":{"osm_id":"3158588473","tag":{"natural":"tree"}},"type":"Feature"},
	{"geometry":{"coordinates":[21.523996,49.604499],"type":"Point"},"properties":{"osm_id":"3158588479","tag":{"natural":"tree"}},"type":"Feature"},
	{"geometry":{"coordinates":[21.524019,49.604572],"type":"Point"},"properties":{"osm_id":"3158588485","tag":{"natural":"tree"}},"type":"Feature"},
	{"geometry":{"coordinates":[21.523867,49.6047],"type":"Point"},"properties":{"osm_id":"3158588493","tag":{"natural":"tree"}},"type":"Feature"},
	{"geometry":{"coordinates":[21.524072,49.604704],"type":"Point"},"properties":{"osm_id":"3158588494","tag":{"natural":"tree"}},"type":"Feature"},
	{"geometry":{"coordinates":[21.523785,49.604743],"type":"Point"},"properties":{"osm_id":"3158588496","tag":{"natural":"tree"}},"type":"Feature"},
	{"geometry":{"coordinates":[21.523696,49.604764],"type":"Point"},"properties":{"osm_id":"3158588497","tag":{"natural":"tree"}},"type":"Feature"},
	{"geometry":{"coordinates":[21.523986,49.604775],"type":"Point"},"properties":{"osm_id":"3158588500","tag":{"natural":"tree"}},"type":"Feature"},
	{"geometry":{"coordinates":[21.523828,49.604796],"type":"Point"},"properties":{"osm_id":"3158588503","tag":{"natural":"tree"}},"type":"Feature"},
	{"geometry":{"coordinates":[21.524122,49.604835],"type":"Point"},"properties":{"osm_id":"3158588507","tag":{"natural":"tree"}},"type":"Feature"},
	{"geometry":{"coordinates":[21.523957,49.604876],"type":"Point"},"properties":{"osm_id":"3158588509","tag":{"natural":"tree"}},"type":"Feature"},
	{"geometry":{"coordinates":[21.523076,49.605257],"type":"Point"},"properties":{"name":"Pomnik przyrody","osm_id":"4026515110","tag":{"denotation":"natural_monument","monument":"yes","natural":"tree","protected":"yes"}},"type":"Feature"},
	{"geometry":{"coordinates":[21.523146,49.6055],"type":"Point"},"properties":{"name":"Pomnik przyrody","osm_id":"4026515111","tag":{"denotation":"natural_monument","monument":"yes","natural":"tree","protected":"yes"}},"type":"Feature"}
]
}
