{
"type": "FeatureCollection",
"features": [
	{"geometry":{"coordinates":[14.058674,45.483251],"type":"Point"},"properties":{"osm_id":"2487904256","tag":{"natural":"tree"}},"type":"Feature"},
	{"geometry":{"coordinates":[14.055886,45.480847],"type":"Point"},"properties":{"osm_id":"2487905832","tag":{"natural":"tree"}},"type":"Feature"},
	{"geometry":{"coordinates":[14.006403,45.482329],"type":"Point"},"properties":{"name":"Stara bukva","osm_id":"5199633965","tag":{"name:botanical":"tilia","natural":"tree","type":"broad_leaved"}},"type":"Feature"}
]
}
