{
"type": "FeatureCollection",
"features": [
	{"geometry":{"coordinates":[-88.33632,44.290477],"type":"Point"},"properties":{"name":"Construcation Waste","osm_id":"5776227663","tag":{"amenity":"waste_disposal"}},"type":"Feature"},
	{"geometry":{"coordinates":[-88.335414,44.290338],"type":"Point"},"properties":{"name":"General Garbage","osm_id":"5776227664","tag":{"amenity":"waste_disposal"}},"type":"Feature"},
	{"geometry":{"coordinates":[-88.335524,44.29063],"type":"Point"},"properties":{"name":"General Recycleables","osm_id":"5776227665","tag":{"amenity":"recycling","recycling_type":"container"}},"type":"Feature"},
	{"geometry":{"coordinates":[-88.381436,44.322519],"type":"Point"},"properties":{"osm_id":"7176640570","tag":{"amenity":"waste_basket"}},"type":"Feature"},
	{"geometry":{"coordinates":[-88.381554,44.323555],"type":"Point"},"properties":{"osm_id":"7176640571","tag":{"amenity":"waste_basket"}},"type":"Feature"},
	{"geometry":{"coordinates":[-88.387285,44.324942],"type":"Point"},"properties":{"osm_id":"7176640616","tag":{"amenity":"waste_basket"}},"type":"Feature"},
	{"geometry":{"coordinates":[-88.388103,44.324658],"type":"Point"},"properties":{"osm_id":"7176640617","tag":{"amenity":"waste_basket"}},"type":"Feature"},
	{"geometry":{"coordinates":[-88.387927,44.324819],"type":"Point"},"properties":{"osm_id":"7176640618","tag":{"amenity":"waste_basket"}},"type":"Feature"}
]
}
