{
"type": "FeatureCollection",
"features": [
	{"geometry":{"coordinates":[-88.33632,44.290476],"type":"Point"},"properties":{"name":"Construcation Waste","osm_id":"5776227663","tag":{"amenity":"waste_disposal"}},"type":"Feature"},
	{"geometry":{"coordinates":[-88.335414,44.290338],"type":"Point"},"properties":{"name":"General Garbage","osm_id":"5776227664","tag":{"amenity":"waste_disposal"}},"type":"Feature"},
	{"geometry":{"coordinates":[-88.335523,44.290629],"type":"Point"},"properties":{"name":"General Recycleables","osm_id":"5776227665","tag":{"amenity":"recycling","recycling_type":"container"}},"type":"Feature"},
	{"geometry":{"coordinates":[-88.381435,44.322519],"type":"Point"},"properties":{"osm_id":"7176640570","tag":{"amenity":"waste_basket"}},"type":"Feature"},
	{"geometry":{"coordinates":[-88.381554,44.323554],"type":"Point"},"properties":{"osm_id":"7176640571","tag":{"amenity":"waste_basket"}},"type":"Feature"},
	{"geometry":{"coordinates":[-88.387284,44.324941],"type":"Point"},"properties":{"osm_id":"7176640616","tag":{"amenity":"waste_basket"}},"type":"Feature"},
	{"geometry":{"coordinates":[-88.388102,44.324657],"type":"Point"},"properties":{"osm_id":"7176640617","tag":{"amenity":"waste_basket"}},"type":"Feature"},
	{"geometry":{"coordinates":[-88.387926,44.324818],"type":"Point"},"properties":{"osm_id":"7176640618","tag":{"amenity":"waste_basket"}},"type":"Feature"},
	{"geometry":{"coordinates":[-88.358036,44.308377],"type":"Point"},"properties":{"osm_id":"9122416421","tag":{"amenity":"waste_basket","waste":"trash"}},"type":"Feature"}
]
}
