{
"type": "FeatureCollection",
"lastupdate": "2020-08-03T00:00:00Z",
"features": [
	{"geometry":{"coordinates":[8.168186,53.398216],"type":"Point"},"properties":{"name":"Recyclinghof","osm_id":"2313683191","tag":{"amenity":"recycling","recycling_type":"centre"}},"type":"Feature"},
	{"geometry":{"coordinates":[8.152035,53.390134],"type":"Point"},"properties":{"osm_id":"2934641111","tag":{"amenity":"recycling","recycling:clothes":"yes","recycling:glass":"yes","recycling_type":"container"}},"type":"Feature"},
	{"geometry":{"coordinates":[8.154397,53.38905],"type":"Point"},"properties":{"osm_id":"2934642810","tag":{"amenity":"recycling","recycling:clothes":"yes","recycling_type":"container"}},"type":"Feature"}
]
}
