{
"type": "FeatureCollection",
"features": [
	{"geometry":{"coordinates":[8.123159,47.763887],"type":"Point"},"properties":{"osm_id":"100090496","tag":{"amenity":"recycling","location":"overground","recycling_type":"container"}},"type":"Feature"},
	{"geometry":{"coordinates":[8.122637,47.76902],"type":"Point"},"properties":{"osm_id":"4922629349","tag":{"amenity":"waste_basket"}},"type":"Feature"}
]
}
