{
"type": "FeatureCollection",
"features": [
	{"geometry":{"coordinates":[8.123158,47.763887],"type":"Point"},"properties":{"osm_id":"100090496","tag":{"amenity":"recycling","location":"overground","recycling:glass_bottles":"yes","recycling_type":"container"}},"type":"Feature"},
	{"geometry":{"coordinates":[8.122636,47.769019],"type":"Point"},"properties":{"osm_id":"4922629349","tag":{"amenity":"waste_basket"}},"type":"Feature"},
	{"geometry":{"coordinates":[8.125048,47.761759],"type":"Point"},"properties":{"osm_id":"8702073407","tag":{"amenity":"waste_basket"}},"type":"Feature"},
	{"geometry":{"coordinates":[8.131148,47.762699],"type":"Point"},"properties":{"osm_id":"8702092774","tag":{"amenity":"waste_basket"}},"type":"Feature"},
	{"geometry":{"coordinates":[8.127904,47.75979],"type":"Point"},"properties":{"osm_id":"9160242020","tag":{"amenity":"waste_basket"}},"type":"Feature"}
]
}
