{
"type": "FeatureCollection",
"lastupdate": "2020-07-31T00:00:00Z",
"features": [
	{"geometry":{"coordinates":[8.123158,47.763887],"type":"Point"},"properties":{"osm_id":"100090496","tag":{"amenity":"recycling","location":"overground","recycling_type":"container"}},"type":"Feature"},
	{"geometry":{"coordinates":[8.122636,47.769019],"type":"Point"},"properties":{"osm_id":"4922629349","tag":{"amenity":"waste_basket"}},"type":"Feature"}
]
}
