{
"type": "FeatureCollection",
"lastupdate": "2020-08-03T00:00:00Z",
"features": [
	{"geometry":{"coordinates":[8.153948,47.679767],"type":"Point"},"properties":{"osm_id":"316324693","tag":{"amenity":"recycling","recycling_type":"container"}},"type":"Feature"},
	{"geometry":{"coordinates":[8.135483,47.645398],"type":"Point"},"properties":{"osm_id":"1440565163","tag":{"amenity":"waste_basket"}},"type":"Feature"},
	{"geometry":{"coordinates":[8.130129,47.648149],"type":"Point"},"properties":{"osm_id":"1440565222","tag":{"amenity":"waste_basket"}},"type":"Feature"},
	{"geometry":{"coordinates":[8.091204,47.643661],"type":"Point"},"properties":{"osm_id":"1786637030","tag":{"amenity":"waste_basket"}},"type":"Feature"},
	{"geometry":{"coordinates":[8.169032,47.64671],"type":"Point"},"properties":{"name":"Wertstoffstation","osm_id":"2031812393","tag":{"amenity":"recycling","opening_hours":"Mo-Sa 08:00-13:00,15:00-20:00","operator":"Freiwillige Feuerwehr Gai\u00df","recycling:cans":"yes","recycling:glass":"yes"}},"type":"Feature"}
]
}
