{
"type": "FeatureCollection",
"features": [
	{"geometry":{"coordinates":[8.129738,45.608886],"type":"Point"},"properties":{"osm_id":"2721152232","tag":{"amenity":"recycling","recycling:glass":"yes"}},"type":"Feature"},
	{"geometry":{"coordinates":[8.143118,45.609017],"type":"Point"},"properties":{"osm_id":"3586327919","tag":{"amenity":"waste_disposal"}},"type":"Feature"},
	{"geometry":{"coordinates":[8.147913,45.609272],"type":"Point"},"properties":{"osm_id":"3586448012","tag":{"amenity":"waste_disposal"}},"type":"Feature"},
	{"geometry":{"coordinates":[8.148693,45.602911],"type":"Point"},"properties":{"osm_id":"3586483307","tag":{"amenity":"waste_disposal"}},"type":"Feature"},
	{"geometry":{"coordinates":[8.149104,45.604134],"type":"Point"},"properties":{"osm_id":"3586484537","tag":{"amenity":"waste_disposal"}},"type":"Feature"},
	{"geometry":{"coordinates":[8.141717,45.604191],"type":"Point"},"properties":{"osm_id":"3586630207","tag":{"amenity":"waste_disposal"}},"type":"Feature"},
	{"geometry":{"coordinates":[8.146201,45.632837],"type":"Point"},"properties":{"name":"Ecocompattatore bottiglie di plastica","osm_id":"5969582370","tag":{"amenity":"recycling","operator":"Riciclia","recycling:plastic":"yes","recycling_type":"container"}},"type":"Feature"}
]
}
