{
"type": "FeatureCollection",
"lastupdate": "2020-08-03T00:00:00Z",
"features": [
	{"geometry":{"coordinates":[8.129738,45.608886],"type":"Point"},"properties":{"osm_id":"2721152232","tag":{"amenity":"recycling","recycling:glass":"yes"}},"type":"Feature"},
	{"geometry":{"coordinates":[8.146201,45.632837],"type":"Point"},"properties":{"name":"Ecocompattatore bottiglie di plastica","osm_id":"5969582370","tag":{"amenity":"recycling","operator":"Riciclia","recycling:plastic":"yes","recycling_type":"container"}},"type":"Feature"}
]
}
