{
"type": "FeatureCollection",
"features": [
	{"geometry":{"coordinates":[-3.339162,56.591404],"type":"Point"},"properties":{"osm_id":"619466394","tag":{"amenity":"recycling","recycling:cans":"yes","recycling:glass":"yes"}},"type":"Feature"},
	{"geometry":{"coordinates":[-3.335075,56.588062],"type":"Point"},"properties":{"name":"Blairgowrie recycling centre","osm_id":"9148482159","tag":{"amenity":"recycling","owner":"Perth & Kinross Council","ownership":"municipal","recycling_type":"centre","wikidata":"Q106085847"}},"type":"Feature"}
]
}
