{
"type": "FeatureCollection",
"features": [
	{"geometry":{"coordinates":[-3.330077,56.120678],"type":"Point"},"properties":{"name":"Rober Smith Court","osm_id":"60944672","tag":{"amenity":"recycling"}},"type":"Feature"},
	{"geometry":{"coordinates":[-3.257983,56.102402],"type":"Point"},"properties":{"osm_id":"7126932926","tag":{"amenity":"recycling","recycling_type":"container"}},"type":"Feature"}
]
}
