{
"type": "FeatureCollection",
"lastupdate": "2020-07-31T00:00:00Z",
"features": [
	{"geometry":{"coordinates":[-3.330077,56.120678],"type":"Point"},"properties":{"name":"Rober Smith Court","osm_id":"60944672","tag":{"amenity":"recycling"}},"type":"Feature"},
	{"geometry":{"coordinates":[-3.257982,56.102402],"type":"Point"},"properties":{"osm_id":"7126932926","tag":{"amenity":"recycling","recycling_type":"container"}},"type":"Feature"}
]
}
