{
"type": "FeatureCollection",
"features": [
	{"geometry":{"coordinates":[7.71331,50.933481],"type":"Point"},"properties":{"osm_id":"3539029905","tag":{"natural":"tree"}},"type":"Feature"},
	{"geometry":{"coordinates":[7.710878,50.931013],"type":"Point"},"properties":{"osm_id":"3539191285","tag":{"natural":"tree"}},"type":"Feature"},
	{"geometry":{"coordinates":[7.688689,50.9292],"type":"Point"},"properties":{"name":"Biotopbaum","osm_id":"7368403087","tag":{"natural":"tree"}},"type":"Feature"}
]
}
