{
"type": "FeatureCollection",
"features": [
	{"geometry":{"coordinates":[83.739244,28.408063],"type":"Point"},"properties":{"name":"Chautari","osm_id":"6905171097","tag":{"natural":"tree"}},"type":"Feature"},
	{"geometry":{"coordinates":[83.701996,28.401931],"type":"Point"},"properties":{"name":"Chautari","osm_id":"6907937186","tag":{"natural":"tree"}},"type":"Feature"},
	{"geometry":{"coordinates":[83.705913,28.399933],"type":"Point"},"properties":{"name":"Chautari","osm_id":"6907937188","tag":{"natural":"tree"}},"type":"Feature"},
	{"geometry":{"coordinates":[83.705898,28.398655],"type":"Point"},"properties":{"name":"Chautari","osm_id":"6907937190","tag":{"natural":"tree"}},"type":"Feature"},
	{"geometry":{"coordinates":[83.70855,28.397159],"type":"Point"},"properties":{"name":"Chautari","osm_id":"6907937192","tag":{"natural":"tree"}},"type":"Feature"},
	{"geometry":{"coordinates":[83.712728,28.395498],"type":"Point"},"properties":{"name":"Chautari","osm_id":"6907937193","tag":{"natural":"tree"}},"type":"Feature"},
	{"geometry":{"coordinates":[83.691892,28.399655],"type":"Point"},"properties":{"name":"Chautari","osm_id":"6907961964","tag":{"natural":"tree"}},"type":"Feature"},
	{"geometry":{"coordinates":[83.697213,28.400999],"type":"Point"},"properties":{"name":"Chautari","osm_id":"6907961967","tag":{"natural":"tree"}},"type":"Feature"},
	{"geometry":{"coordinates":[83.700665,28.399104],"type":"Point"},"properties":{"name":"Chautari","osm_id":"6908282944","tag":{"natural":"tree"}},"type":"Feature"},
	{"geometry":{"coordinates":[83.702003,28.396675],"type":"Point"},"properties":{"name":"Chautari","osm_id":"6908282955","tag":{"natural":"tree"}},"type":"Feature"},
	{"geometry":{"coordinates":[83.702628,28.394874],"type":"Point"},"properties":{"name":"Chautari","osm_id":"6908282957","tag":{"natural":"tree"}},"type":"Feature"},
	{"geometry":{"coordinates":[83.706023,28.38912],"type":"Point"},"properties":{"name":"Chautari","osm_id":"6908282966","tag":{"natural":"tree"}},"type":"Feature"},
	{"geometry":{"coordinates":[83.706373,28.387813],"type":"Point"},"properties":{"name":"Chautari","osm_id":"6908282967","tag":{"natural":"tree"}},"type":"Feature"},
	{"geometry":{"coordinates":[83.699795,28.40128],"type":"Point"},"properties":{"name":"Chautari","osm_id":"6908487497","tag":{"natural":"tree"}},"type":"Feature"}
]
}
