{
"type": "FeatureCollection",
"features": [
	{"geometry":{"coordinates":[83.739244,28.408062],"type":"Point"},"properties":{"name":"Chautari","osm_id":"6905171097","tag":{"natural":"tree"}},"type":"Feature"},
	{"geometry":{"coordinates":[83.701995,28.401931],"type":"Point"},"properties":{"name":"Chautari","osm_id":"6907937186","tag":{"natural":"tree"}},"type":"Feature"},
	{"geometry":{"coordinates":[83.705912,28.399932],"type":"Point"},"properties":{"name":"Chautari","osm_id":"6907937188","tag":{"natural":"tree"}},"type":"Feature"},
	{"geometry":{"coordinates":[83.705898,28.398655],"type":"Point"},"properties":{"name":"Chautari","osm_id":"6907937190","tag":{"natural":"tree"}},"type":"Feature"},
	{"geometry":{"coordinates":[83.708549,28.397159],"type":"Point"},"properties":{"name":"Chautari","osm_id":"6907937192","tag":{"natural":"tree"}},"type":"Feature"},
	{"geometry":{"coordinates":[83.712728,28.395497],"type":"Point"},"properties":{"name":"Chautari","osm_id":"6907937193","tag":{"natural":"tree"}},"type":"Feature"},
	{"geometry":{"coordinates":[83.691892,28.399655],"type":"Point"},"properties":{"name":"Chautari","osm_id":"6907961964","tag":{"natural":"tree"}},"type":"Feature"},
	{"geometry":{"coordinates":[83.697212,28.400998],"type":"Point"},"properties":{"name":"Chautari","osm_id":"6907961967","tag":{"natural":"tree"}},"type":"Feature"},
	{"geometry":{"coordinates":[83.700664,28.399103],"type":"Point"},"properties":{"name":"Chautari","osm_id":"6908282944","tag":{"natural":"tree"}},"type":"Feature"},
	{"geometry":{"coordinates":[83.702002,28.396674],"type":"Point"},"properties":{"name":"Chautari","osm_id":"6908282955","tag":{"natural":"tree"}},"type":"Feature"},
	{"geometry":{"coordinates":[83.702627,28.394873],"type":"Point"},"properties":{"name":"Chautari","osm_id":"6908282957","tag":{"natural":"tree"}},"type":"Feature"},
	{"geometry":{"coordinates":[83.706022,28.38912],"type":"Point"},"properties":{"name":"Chautari","osm_id":"6908282966","tag":{"natural":"tree"}},"type":"Feature"},
	{"geometry":{"coordinates":[83.706372,28.387813],"type":"Point"},"properties":{"name":"Chautari","osm_id":"6908282967","tag":{"natural":"tree"}},"type":"Feature"},
	{"geometry":{"coordinates":[83.699794,28.401279],"type":"Point"},"properties":{"name":"Chautari","osm_id":"6908487497","tag":{"natural":"tree"}},"type":"Feature"}
]
}
