{
"type": "FeatureCollection",
"lastupdate": "2020-07-31T00:00:00Z",
"features": [
	{"geometry":{"coordinates":[-0.361273,42.775216],"type":"Point"},"properties":{"osm_id":"454535551","tag":{"amenity":"recycling","recycling:cans":"yes","recycling:glass_bottles":"yes","recycling:paper":"yes","recycling_type":"container"}},"type":"Feature"},
	{"geometry":{"coordinates":[-0.359183,42.775248],"type":"Point"},"properties":{"osm_id":"454535581","tag":{"amenity":"recycling","recycling:cans":"yes","recycling:glass_bottles":"yes","recycling:paper":"yes","recycling_type":"container"}},"type":"Feature"},
	{"geometry":{"coordinates":[-0.356687,42.778882],"type":"Point"},"properties":{"osm_id":"454535607","tag":{"amenity":"recycling","recycling:glass_bottles":"yes","recycling_type":"container"}},"type":"Feature"},
	{"geometry":{"coordinates":[-0.363197,42.774201],"type":"Point"},"properties":{"osm_id":"3842311048","tag":{"addr:city":"Formigal","addr:street":"Avenida de Huesca","amenity":"recycling","recycling:cans":"yes","recycling:glass_bottles":"yes","recycling:paper":"yes","recycling:plastic":"yes","recycling_type":"container"}},"type":"Feature"},
	{"geometry":{"coordinates":[-0.359552,42.773082],"type":"Point"},"properties":{"osm_id":"3842311049","tag":{"amenity":"recycling","recycling:cans":"yes","recycling:glass_bottles":"yes","recycling:paper":"yes","recycling:plastic":"yes","recycling_type":"container"}},"type":"Feature"},
	{"geometry":{"coordinates":[-0.36093,42.77351],"type":"Point"},"properties":{"osm_id":"3842317857","tag":{"amenity":"recycling","recycling:cans":"yes","recycling:glass_bottles":"yes","recycling:paper":"yes","recycling:plastic":"yes","recycling_type":"container"}},"type":"Feature"},
	{"geometry":{"coordinates":[-0.360598,42.774189],"type":"Point"},"properties":{"osm_id":"6614881972","tag":{"amenity":"recycling","recycling:organic_waste":"yes","recycling_type":"container"}},"type":"Feature"}
]
}
