{
"type": "FeatureCollection",
"features": [
	{"geometry":{"coordinates":[-0.361274,42.775217],"type":"Point"},"properties":{"osm_id":"454535551","tag":{"amenity":"recycling","recycling:cans":"yes","recycling:glass_bottles":"yes","recycling:paper":"yes","recycling_type":"container"}},"type":"Feature"},
	{"geometry":{"coordinates":[-0.359184,42.775249],"type":"Point"},"properties":{"osm_id":"454535581","tag":{"amenity":"recycling","recycling:cans":"yes","recycling:glass_bottles":"yes","recycling:paper":"yes","recycling_type":"container"}},"type":"Feature"},
	{"geometry":{"coordinates":[-0.356688,42.778882],"type":"Point"},"properties":{"osm_id":"454535607","tag":{"amenity":"recycling","recycling:glass_bottles":"yes","recycling_type":"container"}},"type":"Feature"},
	{"geometry":{"coordinates":[-0.363197,42.774201],"type":"Point"},"properties":{"osm_id":"3842311048","tag":{"addr:city":"Formigal","addr:street":"Avenida de Huesca","amenity":"recycling","recycling:cans":"yes","recycling:glass_bottles":"yes","recycling:paper":"yes","recycling:plastic":"yes","recycling_type":"container"}},"type":"Feature"},
	{"geometry":{"coordinates":[-0.359553,42.773083],"type":"Point"},"properties":{"osm_id":"3842311049","tag":{"amenity":"recycling","recycling:cans":"yes","recycling:glass_bottles":"yes","recycling:paper":"yes","recycling:plastic":"yes","recycling_type":"container"}},"type":"Feature"},
	{"geometry":{"coordinates":[-0.360931,42.773511],"type":"Point"},"properties":{"osm_id":"3842317857","tag":{"amenity":"recycling","recycling:cans":"yes","recycling:glass_bottles":"yes","recycling:paper":"yes","recycling:plastic":"yes","recycling_type":"container"}},"type":"Feature"},
	{"geometry":{"coordinates":[-0.360599,42.774189],"type":"Point"},"properties":{"osm_id":"6614881972","tag":{"amenity":"recycling","recycling:organic_waste":"yes","recycling_type":"container"}},"type":"Feature"}
]
}
