{
"type": "FeatureCollection",
"features": [
	{"geometry":{"coordinates":[101.444291,1.672597],"type":"Point"},"properties":{"name":"akasia","osm_id":"5938808826","tag":{"leaf_type":"akasia","natural":"tree"}},"type":"Feature"},
	{"geometry":{"coordinates":[101.44448,1.672249],"type":"Point"},"properties":{"name":"pohon akasia","osm_id":"5938808831","tag":{"height":"6","leaf_type":"pohon akasia","natural":"tree"}},"type":"Feature"},
	{"geometry":{"coordinates":[101.44881,1.674337],"type":"Point"},"properties":{"osm_id":"5972688123","tag":{"leaf_type":"pohon","natural":"tree"}},"type":"Feature"},
	{"geometry":{"coordinates":[101.448703,1.674323],"type":"Point"},"properties":{"osm_id":"5972688124","tag":{"leaf_type":"pohon","natural":"tree"}},"type":"Feature"},
	{"geometry":{"coordinates":[101.448773,1.674296],"type":"Point"},"properties":{"osm_id":"5972688125","tag":{"leaf_type":"pohon","natural":"tree"}},"type":"Feature"},
	{"geometry":{"coordinates":[101.44869,1.673945],"type":"Point"},"properties":{"osm_id":"5972688150","tag":{"leaf_type":"pohon taman","natural":"tree"}},"type":"Feature"},
	{"geometry":{"coordinates":[101.448848,1.673948],"type":"Point"},"properties":{"osm_id":"5972688151","tag":{"leaf_type":"pohon taman","natural":"tree"}},"type":"Feature"},
	{"geometry":{"coordinates":[101.449038,1.673943],"type":"Point"},"properties":{"osm_id":"5972688152","tag":{"leaf_type":"pohon taman","natural":"tree"}},"type":"Feature"},
	{"geometry":{"coordinates":[101.448952,1.673943],"type":"Point"},"properties":{"osm_id":"5972688153","tag":{"leaf_type":"pohon taman","natural":"tree"}},"type":"Feature"}
]
}
