{
"type": "FeatureCollection",
"features": [
	{"geometry":{"coordinates":[0.148005,51.766301],"type":"Point"},"properties":{"osm_id":"320752994","tag":{"amenity":"waste_basket","waste":"dog_excrement"}},"type":"Feature"},
	{"geometry":{"coordinates":[0.114258,51.776497],"type":"Point"},"properties":{"name":"The Stow Recycling Centre","osm_id":"1298325523","tag":{"amenity":"recycling","opening_hours":"24/7","recycling:cans":"yes","recycling:cardboard":"no","recycling:glass_bottles":"yes","recycling:magazines":"yes","recycling:newspaper":"yes"}},"type":"Feature"},
	{"geometry":{"coordinates":[0.132427,51.758285],"type":"Point"},"properties":{"osm_id":"4975386625","tag":{"amenity":"waste_basket"}},"type":"Feature"},
	{"geometry":{"coordinates":[0.13225,51.758605],"type":"Point"},"properties":{"osm_id":"4975386627","tag":{"amenity":"waste_basket"}},"type":"Feature"},
	{"geometry":{"coordinates":[0.130639,51.758045],"type":"Point"},"properties":{"osm_id":"4977402664","tag":{"amenity":"waste_basket"}},"type":"Feature"},
	{"geometry":{"coordinates":[0.132321,51.758301],"type":"Point"},"properties":{"osm_id":"4977402666","tag":{"amenity":"waste_basket"}},"type":"Feature"},
	{"geometry":{"coordinates":[0.092937,51.776836],"type":"Point"},"properties":{"osm_id":"8356140979","tag":{"amenity":"waste_basket"}},"type":"Feature"},
	{"geometry":{"coordinates":[0.093044,51.776862],"type":"Point"},"properties":{"osm_id":"8356140980","tag":{"amenity":"waste_basket"}},"type":"Feature"},
	{"geometry":{"coordinates":[0.093096,51.776933],"type":"Point"},"properties":{"osm_id":"8356140981","tag":{"amenity":"waste_basket"}},"type":"Feature"},
	{"geometry":{"coordinates":[0.093031,51.777005],"type":"Point"},"properties":{"osm_id":"8356140982","tag":{"amenity":"waste_basket"}},"type":"Feature"},
	{"geometry":{"coordinates":[0.092831,51.776879],"type":"Point"},"properties":{"osm_id":"8356140983","tag":{"amenity":"waste_basket"}},"type":"Feature"},
	{"geometry":{"coordinates":[0.092815,51.776949],"type":"Point"},"properties":{"osm_id":"8356140984","tag":{"amenity":"waste_basket"}},"type":"Feature"},
	{"geometry":{"coordinates":[0.092898,51.777006],"type":"Point"},"properties":{"osm_id":"8356140985","tag":{"amenity":"waste_basket"}},"type":"Feature"},
	{"geometry":{"coordinates":[0.094463,51.780604],"type":"Point"},"properties":{"osm_id":"8372616252","tag":{"amenity":"waste_basket"}},"type":"Feature"},
	{"geometry":{"coordinates":[0.100789,51.774793],"type":"Point"},"properties":{"osm_id":"8419500412","tag":{"amenity":"waste_basket","waste":"dog_excrement"}},"type":"Feature"},
	{"geometry":{"coordinates":[0.094336,51.775325],"type":"Point"},"properties":{"osm_id":"8619110569","tag":{"amenity":"waste_basket"}},"type":"Feature"},
	{"geometry":{"coordinates":[0.094186,51.775023],"type":"Point"},"properties":{"osm_id":"8619110570","tag":{"amenity":"waste_basket","waste":"dog_excrement"}},"type":"Feature"},
	{"geometry":{"coordinates":[0.131236,51.76717],"type":"Point"},"properties":{"osm_id":"8857594863","tag":{"amenity":"recycling","recycling_type":"centre"}},"type":"Feature"},
	{"geometry":{"coordinates":[0.152363,51.766811],"type":"Point"},"properties":{"osm_id":"8883981928","tag":{"amenity":"waste_basket","waste":"dog_excrement"}},"type":"Feature"},
	{"geometry":{"coordinates":[0.124002,51.753996],"type":"Point"},"properties":{"osm_id":"8927408122","tag":{"amenity":"waste_basket"}},"type":"Feature"}
]
}
