{
"type": "FeatureCollection",
"lastupdate": "2020-08-03T00:00:00Z",
"features": [
	{"geometry":{"coordinates":[0.148005,51.766301],"type":"Point"},"properties":{"osm_id":"320752994","tag":{"amenity":"waste_basket","waste":"dog_excrement"}},"type":"Feature"},
	{"geometry":{"coordinates":[0.114258,51.776497],"type":"Point"},"properties":{"name":"The Stow Recycling Centre","osm_id":"1298325523","tag":{"amenity":"recycling","opening_hours":"24/7","recycling:cans":"yes","recycling:cardboard":"no","recycling:glass_bottles":"yes","recycling:magazines":"yes","recycling:newspaper":"yes"}},"type":"Feature"},
	{"geometry":{"coordinates":[0.132427,51.758285],"type":"Point"},"properties":{"osm_id":"4975386625","tag":{"amenity":"waste_basket"}},"type":"Feature"},
	{"geometry":{"coordinates":[0.13225,51.758605],"type":"Point"},"properties":{"osm_id":"4975386627","tag":{"amenity":"waste_basket"}},"type":"Feature"},
	{"geometry":{"coordinates":[0.130639,51.758045],"type":"Point"},"properties":{"osm_id":"4977402664","tag":{"amenity":"waste_basket"}},"type":"Feature"},
	{"geometry":{"coordinates":[0.132321,51.758301],"type":"Point"},"properties":{"osm_id":"4977402666","tag":{"amenity":"waste_basket"}},"type":"Feature"}
]
}
