{
"type": "FeatureCollection",
"features": [
	{"geometry":{"coordinates":[-151.422387,59.602604],"type":"Point"},"properties":{"name":"Port of Homer Waste Oil Collection Facility","osm_id":"5659692332","tag":{"amenity":"recycling","fee":"no","operator":"City of Homer","recycling:oil":"yes","recycling_type":"container"}},"type":"Feature"},
	{"geometry":{"coordinates":[-151.422534,59.602702],"type":"Point"},"properties":{"osm_id":"5659692335","tag":{"amenity":"waste_disposal","operator":"City of Homer"}},"type":"Feature"},
	{"geometry":{"coordinates":[-151.424465,59.603257],"type":"Point"},"properties":{"osm_id":"5659692340","tag":{"amenity":"waste_disposal","operator":"City of Homer"}},"type":"Feature"}
]
}
