{
"type": "FeatureCollection",
"lastupdate": "2020-08-04T00:00:00Z",
"features": [
	{"geometry":{"coordinates":[-151.422386,59.602604],"type":"Point"},"properties":{"name":"Port of Homer Waste Oil Collection Facility","osm_id":"5659692332","tag":{"amenity":"recycling","fee":"no","operator":"City of Homer","recycling:oil":"yes","recycling_type":"container"}},"type":"Feature"}
]
}
