{
"type": "FeatureCollection",
"features": [
	{"geometry":{"coordinates":[29.896135,-0.211365],"type":"Point"},"properties":{"name":"Kazinga Dustbin","osm_id":"6735356106","tag":{"addr:county":"Bunyaruguru","addr:district":"Rubirizi","addr:parish":"Kazinga","addr:subcounty":"Katunguru","addr:village":"Kanombe","amenity":"waste_disposal","fee":"no","lit":"no","operator":"community","start_date":"2019-06-01","waste":"Domestic"}},"type":"Feature"},
	{"geometry":{"coordinates":[29.897207,-0.210172],"type":"Point"},"properties":{"name":"School Dustin","osm_id":"6735356111","tag":{"addr:county":"Bunyaruguru","addr:district":"Rubirizi","addr:parish":"Kazinga","addr:subcounty":"Katunguru","addr:village":"Kanombe","amenity":"waste_disposal","fee":"no","lit":"no","operator":"government","start_date":"2004-01-01","waste":"Domestic"}},"type":"Feature"}
]
}
