{
"type": "FeatureCollection",
"features": [
	{"geometry":{"coordinates":[-48.871589,-25.260491],"type":"Point"},"properties":{"name":"Arvore Grande","osm_id":"860698546","tag":{"amenity":"drinking_water","natural":"tree"}},"type":"Feature"}
]
}
