{
"type": "FeatureCollection",
"lastupdate": "2020-07-31T00:00:00Z",
"features": [
	{"geometry":{"coordinates":[11.971481,51.53136],"type":"Point"},"properties":{"osm_id":"355571096","tag":{"amenity":"recycling","recycling:clothes":"yes","recycling:glass_bottles":"yes","recycling_type":"container"}},"type":"Feature"},
	{"geometry":{"coordinates":[11.954022,51.560121],"type":"Point"},"properties":{"osm_id":"475016081","tag":{"amenity":"recycling","recycling_type":"container"}},"type":"Feature"},
	{"geometry":{"coordinates":[11.955532,51.553868],"type":"Point"},"properties":{"osm_id":"475016939","tag":{"amenity":"recycling","recycling_type":"container"}},"type":"Feature"},
	{"geometry":{"coordinates":[12.002135,51.555275],"type":"Point"},"properties":{"osm_id":"1710841105","tag":{"amenity":"recycling"}},"type":"Feature"},
	{"geometry":{"coordinates":[11.954122,51.559147],"type":"Point"},"properties":{"osm_id":"2896526676","tag":{"amenity":"recycling","recycling:cans":"no","recycling:clothes":"yes","recycling:glass_bottles":"yes","recycling:paper":"no","recycling_type":"container"}},"type":"Feature"},
	{"geometry":{"coordinates":[11.954119,51.559122],"type":"Point"},"properties":{"osm_id":"2896526677","tag":{"amenity":"waste_basket"}},"type":"Feature"},
	{"geometry":{"coordinates":[11.955971,51.559339],"type":"Point"},"properties":{"osm_id":"2896526679","tag":{"amenity":"waste_basket"}},"type":"Feature"},
	{"geometry":{"coordinates":[11.994719,51.510898],"type":"Point"},"properties":{"osm_id":"2949180916","tag":{"amenity":"recycling","recycling:clothes":"yes","recycling:glass_bottles":"yes","recycling_type":"container"}},"type":"Feature"},
	{"geometry":{"coordinates":[12.035931,51.549865],"type":"Point"},"properties":{"osm_id":"2949183271","tag":{"amenity":"recycling","recycling:clothes":"yes","recycling:glass_bottles":"yes","recycling_type":"container"}},"type":"Feature"},
	{"geometry":{"coordinates":[11.956719,51.521828],"type":"Point"},"properties":{"osm_id":"3460971404","tag":{"amenity":"recycling","recycling:clothes":"yes"}},"type":"Feature"},
	{"geometry":{"coordinates":[11.957679,51.522375],"type":"Point"},"properties":{"osm_id":"3460971405","tag":{"amenity":"recycling","recycling:clothes":"yes"}},"type":"Feature"},
	{"geometry":{"coordinates":[11.994133,51.509439],"type":"Point"},"properties":{"osm_id":"3959870850","tag":{"amenity":"waste_basket"}},"type":"Feature"},
	{"geometry":{"coordinates":[11.973506,51.53113],"type":"Point"},"properties":{"osm_id":"4774550676","tag":{"amenity":"waste_basket"}},"type":"Feature"},
	{"geometry":{"coordinates":[11.967622,51.531124],"type":"Point"},"properties":{"osm_id":"4774550677","tag":{"amenity":"recycling","recycling:glass_bottles":"yes","recycling_type":"container"}},"type":"Feature"},
	{"geometry":{"coordinates":[12.025128,51.534278],"type":"Point"},"properties":{"osm_id":"6224202930","tag":{"amenity":"recycling","recycling:clothes":"yes","recycling:glass_bottles":"yes","recycling:shoes":"yes","recycling_type":"container"}},"type":"Feature"},
	{"geometry":{"coordinates":[11.990739,51.511422],"type":"Point"},"properties":{"osm_id":"6328603585","tag":{"amenity":"recycling","location":"overground","recycling_type":"container"}},"type":"Feature"},
	{"geometry":{"coordinates":[12.026947,51.551859],"type":"Point"},"properties":{"osm_id":"6375025369","tag":{"amenity":"waste_basket","waste":"trash"}},"type":"Feature"},
	{"geometry":{"coordinates":[12.027969,51.551358],"type":"Point"},"properties":{"osm_id":"6375025592","tag":{"amenity":"waste_basket","waste":"dog_excrement"}},"type":"Feature"},
	{"geometry":{"coordinates":[11.960851,51.521872],"type":"Point"},"properties":{"osm_id":"7102173540","tag":{"amenity":"waste_basket"}},"type":"Feature"},
	{"geometry":{"coordinates":[11.96086,51.521677],"type":"Point"},"properties":{"osm_id":"7102173541","tag":{"amenity":"waste_basket"}},"type":"Feature"},
	{"geometry":{"coordinates":[11.961434,51.521975],"type":"Point"},"properties":{"osm_id":"7102173542","tag":{"amenity":"waste_basket"}},"type":"Feature"},
	{"geometry":{"coordinates":[11.961545,51.521849],"type":"Point"},"properties":{"osm_id":"7102173543","tag":{"amenity":"waste_basket"}},"type":"Feature"},
	{"geometry":{"coordinates":[11.960255,51.521832],"type":"Point"},"properties":{"osm_id":"7102173545","tag":{"amenity":"waste_basket"}},"type":"Feature"}
]
}
