{
"type": "FeatureCollection",
"features": [
	{"geometry":{"coordinates":[11.971481,51.531361],"type":"Point"},"properties":{"osm_id":"355571096","tag":{"amenity":"recycling","recycling:clothes":"yes","recycling:glass_bottles":"yes","recycling_type":"container"}},"type":"Feature"},
	{"geometry":{"coordinates":[11.954022,51.560121],"type":"Point"},"properties":{"osm_id":"475016081","tag":{"amenity":"recycling","recycling_type":"container"}},"type":"Feature"},
	{"geometry":{"coordinates":[11.955532,51.553869],"type":"Point"},"properties":{"osm_id":"475016939","tag":{"amenity":"recycling","recycling_type":"container"}},"type":"Feature"},
	{"geometry":{"coordinates":[12.002135,51.555275],"type":"Point"},"properties":{"osm_id":"1710841105","tag":{"amenity":"recycling"}},"type":"Feature"},
	{"geometry":{"coordinates":[11.954122,51.559148],"type":"Point"},"properties":{"osm_id":"2896526676","tag":{"amenity":"recycling","recycling:cans":"no","recycling:clothes":"yes","recycling:glass_bottles":"yes","recycling:paper":"no","recycling_type":"container"}},"type":"Feature"},
	{"geometry":{"coordinates":[11.95412,51.559123],"type":"Point"},"properties":{"osm_id":"2896526677","tag":{"amenity":"waste_basket"}},"type":"Feature"},
	{"geometry":{"coordinates":[11.955972,51.55934],"type":"Point"},"properties":{"osm_id":"2896526679","tag":{"amenity":"waste_basket"}},"type":"Feature"},
	{"geometry":{"coordinates":[11.994719,51.510898],"type":"Point"},"properties":{"osm_id":"2949180916","tag":{"amenity":"recycling","recycling:clothes":"yes","recycling:glass_bottles":"yes","recycling_type":"container"}},"type":"Feature"},
	{"geometry":{"coordinates":[12.035932,51.549865],"type":"Point"},"properties":{"osm_id":"2949183271","tag":{"amenity":"recycling","recycling:clothes":"yes","recycling:glass_bottles":"yes","recycling_type":"container"}},"type":"Feature"},
	{"geometry":{"coordinates":[11.95672,51.521829],"type":"Point"},"properties":{"osm_id":"3460971404","tag":{"amenity":"recycling","recycling:clothes":"yes"}},"type":"Feature"},
	{"geometry":{"coordinates":[11.95768,51.522375],"type":"Point"},"properties":{"osm_id":"3460971405","tag":{"amenity":"recycling","recycling:clothes":"yes"}},"type":"Feature"},
	{"geometry":{"coordinates":[11.994133,51.509439],"type":"Point"},"properties":{"osm_id":"3959870850","tag":{"amenity":"waste_basket"}},"type":"Feature"},
	{"geometry":{"coordinates":[11.973506,51.531131],"type":"Point"},"properties":{"osm_id":"4774550676","tag":{"amenity":"waste_basket"}},"type":"Feature"},
	{"geometry":{"coordinates":[11.967623,51.531125],"type":"Point"},"properties":{"osm_id":"4774550677","tag":{"amenity":"recycling","recycling:glass_bottles":"yes","recycling_type":"container"}},"type":"Feature"},
	{"geometry":{"coordinates":[12.025129,51.534279],"type":"Point"},"properties":{"osm_id":"6224202930","tag":{"amenity":"recycling","recycling:clothes":"yes","recycling:glass_bottles":"yes","recycling:shoes":"yes","recycling_type":"container"}},"type":"Feature"},
	{"geometry":{"coordinates":[11.99074,51.511423],"type":"Point"},"properties":{"osm_id":"6328603585","tag":{"amenity":"recycling","location":"overground","recycling_type":"container"}},"type":"Feature"},
	{"geometry":{"coordinates":[12.026947,51.551859],"type":"Point"},"properties":{"osm_id":"6375025369","tag":{"amenity":"waste_basket","waste":"trash"}},"type":"Feature"},
	{"geometry":{"coordinates":[12.027969,51.551359],"type":"Point"},"properties":{"osm_id":"6375025592","tag":{"amenity":"waste_basket","waste":"dog_excrement"}},"type":"Feature"},
	{"geometry":{"coordinates":[11.960852,51.521872],"type":"Point"},"properties":{"osm_id":"7102173540","tag":{"amenity":"waste_basket"}},"type":"Feature"},
	{"geometry":{"coordinates":[11.96086,51.521677],"type":"Point"},"properties":{"osm_id":"7102173541","tag":{"amenity":"waste_basket"}},"type":"Feature"},
	{"geometry":{"coordinates":[11.961435,51.521976],"type":"Point"},"properties":{"osm_id":"7102173542","tag":{"amenity":"waste_basket"}},"type":"Feature"},
	{"geometry":{"coordinates":[11.961545,51.52185],"type":"Point"},"properties":{"osm_id":"7102173543","tag":{"amenity":"waste_basket"}},"type":"Feature"},
	{"geometry":{"coordinates":[11.960451,51.52193],"type":"Point"},"properties":{"osm_id":"7102173544","tag":{"amenity":"waste_disposal"}},"type":"Feature"},
	{"geometry":{"coordinates":[11.960255,51.521832],"type":"Point"},"properties":{"osm_id":"7102173545","tag":{"amenity":"waste_basket"}},"type":"Feature"}
]
}
