{
"type": "FeatureCollection",
"features": [
	{"geometry":{"coordinates":[11.983738,46.793643],"type":"Point"},"properties":{"osm_id":"3228574623","tag":{"amenity":"recycling","location":"overground","recycling:cans":"yes","recycling:glass":"yes","recycling:paper":"yes","recycling_type":"container"}},"type":"Feature"},
	{"geometry":{"coordinates":[11.980215,46.794792],"type":"Point"},"properties":{"osm_id":"3228574624","tag":{"amenity":"recycling","location":"overground","recycling:cans":"yes","recycling:glass":"yes","recycling:paper":"yes","recycling_type":"container"}},"type":"Feature"},
	{"geometry":{"coordinates":[11.98209,46.795412],"type":"Point"},"properties":{"osm_id":"3901137852","tag":{"amenity":"recycling","location":"overground","recycling_type":"container"}},"type":"Feature"},
	{"geometry":{"coordinates":[11.961347,46.777882],"type":"Point"},"properties":{"osm_id":"4426202763","tag":{"amenity":"waste_basket"}},"type":"Feature"},
	{"geometry":{"coordinates":[11.961664,46.779724],"type":"Point"},"properties":{"osm_id":"4426202784","tag":{"amenity":"waste_basket"}},"type":"Feature"},
	{"geometry":{"coordinates":[11.980761,46.792538],"type":"Point"},"properties":{"osm_id":"5339428107","tag":{"amenity":"recycling","recycling_type":"container"}},"type":"Feature"},
	{"geometry":{"coordinates":[11.954767,46.784205],"type":"Point"},"properties":{"osm_id":"7780549225","tag":{"amenity":"waste_basket"}},"type":"Feature"},
	{"geometry":{"coordinates":[11.960268,46.782637],"type":"Point"},"properties":{"osm_id":"7781001626","tag":{"amenity":"waste_basket"}},"type":"Feature"},
	{"geometry":{"coordinates":[11.957991,46.783334],"type":"Point"},"properties":{"osm_id":"7781001631","tag":{"amenity":"waste_basket"}},"type":"Feature"}
]
}
