{
"type": "FeatureCollection",
"lastupdate": "2020-08-01T00:00:00Z",
"features": [
	{"geometry":{"coordinates":[11.983738,46.793643],"type":"Point"},"properties":{"osm_id":"3228574623","tag":{"amenity":"recycling","location":"overground","recycling:cans":"yes","recycling:glass":"yes","recycling:paper":"yes","recycling_type":"container"}},"type":"Feature"},
	{"geometry":{"coordinates":[11.980214,46.794792],"type":"Point"},"properties":{"osm_id":"3228574624","tag":{"amenity":"recycling","location":"overground","recycling:cans":"yes","recycling:glass":"yes","recycling:paper":"yes","recycling_type":"container"}},"type":"Feature"},
	{"geometry":{"coordinates":[11.98209,46.795412],"type":"Point"},"properties":{"osm_id":"3901137852","tag":{"amenity":"recycling","location":"overground","recycling_type":"container"}},"type":"Feature"},
	{"geometry":{"coordinates":[11.961346,46.777881],"type":"Point"},"properties":{"osm_id":"4426202763","tag":{"amenity":"waste_basket"}},"type":"Feature"},
	{"geometry":{"coordinates":[11.961663,46.779723],"type":"Point"},"properties":{"osm_id":"4426202784","tag":{"amenity":"waste_basket"}},"type":"Feature"},
	{"geometry":{"coordinates":[11.98076,46.792537],"type":"Point"},"properties":{"osm_id":"5339428107","tag":{"amenity":"recycling","recycling_type":"container"}},"type":"Feature"}
]
}
