{
"type": "FeatureCollection",
"features": [
	{"geometry":{"coordinates":[12.036006,46.451392],"type":"Point"},"properties":{"osm_id":"3625276011","tag":{"amenity":"waste_basket"}},"type":"Feature"},
	{"geometry":{"coordinates":[11.956077,46.480937],"type":"Point"},"properties":{"osm_id":"3988103156","tag":{"amenity":"recycling","recycling:cans":"yes","recycling:clothes":"no","recycling:glass":"yes","recycling:glass_bottles":"yes","recycling:paper":"yes","recycling:plastic":"yes","recycling_type":"container"}},"type":"Feature"},
	{"geometry":{"coordinates":[12.036308,46.451356],"type":"Point"},"properties":{"osm_id":"6690877099","tag":{"amenity":"recycling","recycling:drugs":"yes","recycling_type":"container"}},"type":"Feature"},
	{"geometry":{"coordinates":[11.995331,46.452849],"type":"Point"},"properties":{"name":"Ecocentro","osm_id":"6712042584","tag":{"amenity":"recycling","recycling_type":"centre"}},"type":"Feature"}
]
}
