{
"type": "FeatureCollection",
"lastupdate": "2020-08-03T00:00:00Z",
"features": [
	{"geometry":{"coordinates":[12.015156,46.045742],"type":"Point"},"properties":{"name":"Ecocentro","osm_id":"2493688308","tag":{"amenity":"recycling"}},"type":"Feature"},
	{"geometry":{"coordinates":[12.021427,46.044936],"type":"Point"},"properties":{"osm_id":"2493867999","tag":{"amenity":"waste_basket"}},"type":"Feature"}
]
}
