{
"type": "FeatureCollection",
"features": [
	{"geometry":{"coordinates":[12.015156,46.045742],"type":"Point"},"properties":{"name":"Ecocentro","osm_id":"2493688308","tag":{"amenity":"recycling"}},"type":"Feature"},
	{"geometry":{"coordinates":[12.021428,46.044937],"type":"Point"},"properties":{"osm_id":"2493867999","tag":{"amenity":"waste_basket"}},"type":"Feature"}
]
}
