{
"type": "FeatureCollection",
"features": [
	{"geometry":{"coordinates":[16.360517,47.612461],"type":"Point"},"properties":{"name":"Mammutbaum","osm_id":"1442096921","tag":{"natural":"tree"}},"type":"Feature"},
	{"geometry":{"coordinates":[16.427036,47.578777],"type":"Point"},"properties":{"osm_id":"6402490226","tag":{"denotation":"urban","leaf_cycle":"deciduous","leaf_type":"broadleaved","natural":"tree"}},"type":"Feature"},
	{"geometry":{"coordinates":[16.427179,47.578731],"type":"Point"},"properties":{"osm_id":"6402490227","tag":{"denotation":"urban","leaf_cycle":"deciduous","leaf_type":"broadleaved","natural":"tree"}},"type":"Feature"},
	{"geometry":{"coordinates":[16.427256,47.57882],"type":"Point"},"properties":{"osm_id":"6402490228","tag":{"denotation":"urban","leaf_cycle":"deciduous","leaf_type":"broadleaved","natural":"tree"}},"type":"Feature"},
	{"geometry":{"coordinates":[16.427116,47.578869],"type":"Point"},"properties":{"osm_id":"6402490229","tag":{"denotation":"urban","leaf_cycle":"deciduous","leaf_type":"broadleaved","natural":"tree"}},"type":"Feature"},
	{"geometry":{"coordinates":[16.42759,47.578352],"type":"Point"},"properties":{"osm_id":"6403592251","tag":{"natural":"tree"}},"type":"Feature"},
	{"geometry":{"coordinates":[16.422601,47.58608],"type":"Point"},"properties":{"osm_id":"6704013800","tag":{"natural":"tree"}},"type":"Feature"}
]
}
