{
"type": "FeatureCollection",
"features": [
	{"geometry":{"coordinates":[16.360516,47.612461],"type":"Point"},"properties":{"name":"Mammutbaum","osm_id":"1442096921","tag":{"natural":"tree"}},"type":"Feature"},
	{"geometry":{"coordinates":[16.427035,47.578776],"type":"Point"},"properties":{"osm_id":"6402490226","tag":{"denotation":"urban","leaf_cycle":"deciduous","leaf_type":"broadleaved","natural":"tree"}},"type":"Feature"},
	{"geometry":{"coordinates":[16.427179,47.57873],"type":"Point"},"properties":{"osm_id":"6402490227","tag":{"denotation":"urban","leaf_cycle":"deciduous","leaf_type":"broadleaved","natural":"tree"}},"type":"Feature"},
	{"geometry":{"coordinates":[16.427255,47.578819],"type":"Point"},"properties":{"osm_id":"6402490228","tag":{"denotation":"urban","leaf_cycle":"deciduous","leaf_type":"broadleaved","natural":"tree"}},"type":"Feature"},
	{"geometry":{"coordinates":[16.427116,47.578868],"type":"Point"},"properties":{"osm_id":"6402490229","tag":{"denotation":"urban","leaf_cycle":"deciduous","leaf_type":"broadleaved","natural":"tree"}},"type":"Feature"},
	{"geometry":{"coordinates":[16.42759,47.578351],"type":"Point"},"properties":{"osm_id":"6403592251","tag":{"natural":"tree"}},"type":"Feature"},
	{"geometry":{"coordinates":[16.422601,47.586079],"type":"Point"},"properties":{"osm_id":"6704013800","tag":{"natural":"tree"}},"type":"Feature"}
]
}
