{
"type": "FeatureCollection",
"lastupdate": "2020-08-01T00:00:00Z",
"features": [
	{"geometry":{"coordinates":[-70.747283,-33.262684],"type":"Point"},"properties":{"name":"Sca Chile","osm_id":"4776056321","tag":{"amenity":"recycling","website":"www sacchile.com"}},"type":"Feature"},
	{"geometry":{"coordinates":[-70.702812,-33.275345],"type":"Point"},"properties":{"osm_id":"6786932772","tag":{"amenity":"waste_basket"}},"type":"Feature"},
	{"geometry":{"coordinates":[-70.703025,-33.275209],"type":"Point"},"properties":{"osm_id":"6786932781","tag":{"amenity":"waste_basket"}},"type":"Feature"},
	{"geometry":{"coordinates":[-70.702699,-33.275215],"type":"Point"},"properties":{"osm_id":"6878440164","tag":{"amenity":"recycling","recycling_type":"container"}},"type":"Feature"},
	{"geometry":{"coordinates":[-70.703912,-33.274849],"type":"Point"},"properties":{"osm_id":"7005236110","tag":{"amenity":"waste_basket"}},"type":"Feature"},
	{"geometry":{"coordinates":[-70.703843,-33.27392],"type":"Point"},"properties":{"osm_id":"7005236111","tag":{"amenity":"waste_basket"}},"type":"Feature"},
	{"geometry":{"coordinates":[-70.703992,-33.274065],"type":"Point"},"properties":{"osm_id":"7005256041","tag":{"amenity":"waste_basket"}},"type":"Feature"},
	{"geometry":{"coordinates":[-70.703955,-33.274337],"type":"Point"},"properties":{"osm_id":"7005434567","tag":{"amenity":"waste_basket"}},"type":"Feature"},
	{"geometry":{"coordinates":[-70.703947,-33.274433],"type":"Point"},"properties":{"osm_id":"7005434568","tag":{"amenity":"waste_basket"}},"type":"Feature"},
	{"geometry":{"coordinates":[-70.703929,-33.274603],"type":"Point"},"properties":{"osm_id":"7005469332","tag":{"amenity":"waste_basket"}},"type":"Feature"},
	{"geometry":{"coordinates":[-70.703148,-33.274911],"type":"Point"},"properties":{"osm_id":"7641660276","tag":{"amenity":"waste_basket"}},"type":"Feature"},
	{"geometry":{"coordinates":[-70.703276,-33.275015],"type":"Point"},"properties":{"osm_id":"7641660280","tag":{"amenity":"waste_basket"}},"type":"Feature"},
	{"geometry":{"coordinates":[-70.703372,-33.275071],"type":"Point"},"properties":{"osm_id":"7641660284","tag":{"amenity":"waste_basket"}},"type":"Feature"}
]
}
