{
"type": "FeatureCollection",
"features": [
	{"geometry":{"coordinates":[-70.747283,-33.262685],"type":"Point"},"properties":{"name":"Sca Chile","osm_id":"4776056321","tag":{"amenity":"recycling","website":"www sacchile.com"}},"type":"Feature"},
	{"geometry":{"coordinates":[-70.702813,-33.275346],"type":"Point"},"properties":{"osm_id":"6786932772","tag":{"amenity":"waste_basket"}},"type":"Feature"},
	{"geometry":{"coordinates":[-70.703026,-33.275209],"type":"Point"},"properties":{"osm_id":"6786932781","tag":{"amenity":"waste_basket"}},"type":"Feature"},
	{"geometry":{"coordinates":[-70.702699,-33.275216],"type":"Point"},"properties":{"osm_id":"6878440164","tag":{"amenity":"recycling","recycling_type":"container"}},"type":"Feature"},
	{"geometry":{"coordinates":[-70.703913,-33.274849],"type":"Point"},"properties":{"osm_id":"7005236110","tag":{"amenity":"waste_basket"}},"type":"Feature"},
	{"geometry":{"coordinates":[-70.703843,-33.273921],"type":"Point"},"properties":{"osm_id":"7005236111","tag":{"amenity":"waste_basket"}},"type":"Feature"},
	{"geometry":{"coordinates":[-70.703992,-33.274065],"type":"Point"},"properties":{"osm_id":"7005256041","tag":{"amenity":"waste_basket"}},"type":"Feature"},
	{"geometry":{"coordinates":[-70.703956,-33.274337],"type":"Point"},"properties":{"osm_id":"7005434567","tag":{"amenity":"waste_basket"}},"type":"Feature"},
	{"geometry":{"coordinates":[-70.703947,-33.274434],"type":"Point"},"properties":{"osm_id":"7005434568","tag":{"amenity":"waste_basket"}},"type":"Feature"},
	{"geometry":{"coordinates":[-70.70393,-33.274603],"type":"Point"},"properties":{"osm_id":"7005469332","tag":{"amenity":"waste_basket"}},"type":"Feature"},
	{"geometry":{"coordinates":[-70.703149,-33.274912],"type":"Point"},"properties":{"osm_id":"7641660276","tag":{"amenity":"waste_basket"}},"type":"Feature"},
	{"geometry":{"coordinates":[-70.703277,-33.275016],"type":"Point"},"properties":{"osm_id":"7641660280","tag":{"amenity":"waste_basket"}},"type":"Feature"},
	{"geometry":{"coordinates":[-70.703373,-33.275072],"type":"Point"},"properties":{"osm_id":"7641660284","tag":{"amenity":"waste_basket"}},"type":"Feature"}
]
}
