{
"type": "FeatureCollection",
"features": [
	{"geometry":{"coordinates":[-5.932823,54.57426],"type":"Point"},"properties":{"osm_id":"288516408","tag":{"amenity":"recycling","description":"bottle bank","location":"overground","recycling:glass_bottles":"yes","recycling_type":"container"}},"type":"Feature"},
	{"geometry":{"coordinates":[-5.95519,54.576425],"type":"Point"},"properties":{"osm_id":"1945415157","tag":{"amenity":"recycling"}},"type":"Feature"},
	{"geometry":{"coordinates":[-5.88902,54.584743],"type":"Point"},"properties":{"osm_id":"2395711421","tag":{"amenity":"waste_basket"}},"type":"Feature"},
	{"geometry":{"coordinates":[-5.891678,54.585934],"type":"Point"},"properties":{"osm_id":"2395711423","tag":{"amenity":"waste_basket"}},"type":"Feature"},
	{"geometry":{"coordinates":[-5.967137,54.578831],"type":"Point"},"properties":{"osm_id":"2612909696","tag":{"amenity":"waste_basket"}},"type":"Feature"},
	{"geometry":{"coordinates":[-5.966183,54.580065],"type":"Point"},"properties":{"osm_id":"2612909758","tag":{"amenity":"waste_basket"}},"type":"Feature"},
	{"geometry":{"coordinates":[-5.896472,54.6014],"type":"Point"},"properties":{"osm_id":"3007181072","tag":{"amenity":"waste_basket"}},"type":"Feature"},
	{"geometry":{"coordinates":[-5.932668,54.619647],"type":"Point"},"properties":{"barrier":"gate","osm_id":"4080201571"},"type":"Feature"},
	{"geometry":{"coordinates":[-5.918618,54.580008],"type":"Point"},"properties":{"barrier":"gate","osm_id":"6111390685"},"type":"Feature"},
	{"geometry":{"coordinates":[-5.918555,54.580006],"type":"Point"},"properties":{"barrier":"gate","osm_id":"6208993891"},"type":"Feature"},
	{"geometry":{"coordinates":[-5.9303,54.599054],"type":"Point"},"properties":{"osm_id":"6906995462","tag":{"amenity":"waste_basket","colour":"black"}},"type":"Feature"},
	{"geometry":{"coordinates":[-5.929451,54.599386],"type":"Point"},"properties":{"osm_id":"6906995463","tag":{"amenity":"waste_basket","colour":"black"}},"type":"Feature"},
	{"geometry":{"coordinates":[-5.929743,54.599395],"type":"Point"},"properties":{"osm_id":"6906995464","tag":{"amenity":"waste_basket"}},"type":"Feature"},
	{"geometry":{"coordinates":[-5.929258,54.599254],"type":"Point"},"properties":{"osm_id":"6906995465","tag":{"amenity":"waste_basket"}},"type":"Feature"},
	{"geometry":{"coordinates":[-5.929056,54.599439],"type":"Point"},"properties":{"osm_id":"6906995466","tag":{"amenity":"waste_basket"}},"type":"Feature"},
	{"geometry":{"coordinates":[-5.927502,54.599703],"type":"Point"},"properties":{"osm_id":"6906995467","tag":{"amenity":"waste_basket"}},"type":"Feature"},
	{"geometry":{"coordinates":[-5.926084,54.608793],"type":"Point"},"properties":{"osm_id":"6907020828","tag":{"amenity":"waste_basket"}},"type":"Feature"},
	{"geometry":{"coordinates":[-5.925987,54.608627],"type":"Point"},"properties":{"osm_id":"6907020831","tag":{"amenity":"waste_basket"}},"type":"Feature"}
]
}
