{
"type": "FeatureCollection",
"features": [
	{"geometry":{"coordinates":[10.316774,52.853453],"type":"Point"},"properties":{"osm_id":"365582161","tag":{"natural":"tree"}},"type":"Feature"},
	{"geometry":{"coordinates":[10.301297,52.807193],"type":"Point"},"properties":{"name":"Tilemannseiche","osm_id":"691243904","tag":{"denotation":"natural_monument","genus":"Quercus","genus:de":"Eiche","genus:en":"Oak","leaf_type":"broadleaved","monument":"yes","natural":"tree"}},"type":"Feature"},
	{"geometry":{"coordinates":[10.306989,52.852319],"type":"Point"},"properties":{"osm_id":"4690815186","tag":{"natural":"tree"}},"type":"Feature"},
	{"geometry":{"coordinates":[10.30746,52.8524],"type":"Point"},"properties":{"osm_id":"4690815187","tag":{"natural":"tree"}},"type":"Feature"}
]
}
