{
"type": "FeatureCollection",
"features": [
	{"geometry":{"coordinates":[10.353965,49.738469],"type":"Point"},"properties":{"name":"Gerichtslinde","osm_id":"404573769","tag":{"genus":"Tilia","leaf_cycle":"deciduous","leaf_type":"broadleaved","natural":"tree"}},"type":"Feature"},
	{"geometry":{"coordinates":[10.356145,49.767455],"type":"Point"},"properties":{"osm_id":"3257879909","tag":{"natural":"tree"}},"type":"Feature"},
	{"geometry":{"coordinates":[10.368517,49.751707],"type":"Point"},"properties":{"osm_id":"8025256065","tag":{"leaf_type":"broadleaved","natural":"tree"}},"type":"Feature"},
	{"geometry":{"coordinates":[10.366421,49.778319],"type":"Point"},"properties":{"osm_id":"8126634984","tag":{"natural":"tree"}},"type":"Feature"},
	{"geometry":{"coordinates":[10.366365,49.778373],"type":"Point"},"properties":{"osm_id":"8126634985","tag":{"natural":"tree"}},"type":"Feature"},
	{"geometry":{"coordinates":[10.366316,49.778491],"type":"Point"},"properties":{"osm_id":"8126634986","tag":{"natural":"tree"}},"type":"Feature"},
	{"geometry":{"coordinates":[10.366276,49.77857],"type":"Point"},"properties":{"osm_id":"8126634987","tag":{"natural":"tree"}},"type":"Feature"},
	{"geometry":{"coordinates":[10.366452,49.778256],"type":"Point"},"properties":{"osm_id":"8126634988","tag":{"natural":"tree"}},"type":"Feature"},
	{"geometry":{"coordinates":[10.366028,49.778126],"type":"Point"},"properties":{"osm_id":"8126634989","tag":{"natural":"tree"}},"type":"Feature"},
	{"geometry":{"coordinates":[10.365903,49.778091],"type":"Point"},"properties":{"osm_id":"8126634990","tag":{"natural":"tree"}},"type":"Feature"},
	{"geometry":{"coordinates":[10.365455,49.778026],"type":"Point"},"properties":{"osm_id":"8126634991","tag":{"natural":"tree"}},"type":"Feature"}
]
}
