{
"type": "FeatureCollection",
"features": [
	{"geometry":{"coordinates":[10.353965,49.738469],"type":"Point"},"properties":{"name":"Gerichtslinde","osm_id":"404573769","tag":{"genus":"Tilia","leaf_cycle":"deciduous","leaf_type":"broadleaved","natural":"tree"}},"type":"Feature"},
	{"geometry":{"coordinates":[10.356145,49.767455],"type":"Point"},"properties":{"osm_id":"3257879909","tag":{"natural":"tree"}},"type":"Feature"},
	{"geometry":{"coordinates":[10.368517,49.751707],"type":"Point"},"properties":{"osm_id":"8025256065","tag":{"leaf_type":"broadleaved","natural":"tree"}},"type":"Feature"},
	{"geometry":{"coordinates":[10.366421,49.778319],"type":"Point"},"properties":{"osm_id":"8126634984","tag":{"natural":"tree"}},"type":"Feature"},
	{"geometry":{"coordinates":[10.366365,49.778373],"type":"Point"},"properties":{"osm_id":"8126634985","tag":{"natural":"tree"}},"type":"Feature"},
	{"geometry":{"coordinates":[10.366316,49.778491],"type":"Point"},"properties":{"osm_id":"8126634986","tag":{"natural":"tree"}},"type":"Feature"},
	{"geometry":{"coordinates":[10.366276,49.77857],"type":"Point"},"properties":{"osm_id":"8126634987","tag":{"natural":"tree"}},"type":"Feature"},
	{"geometry":{"coordinates":[10.366452,49.778256],"type":"Point"},"properties":{"osm_id":"8126634988","tag":{"natural":"tree"}},"type":"Feature"},
	{"geometry":{"coordinates":[10.366028,49.778126],"type":"Point"},"properties":{"osm_id":"8126634989","tag":{"natural":"tree"}},"type":"Feature"},
	{"geometry":{"coordinates":[10.365903,49.778091],"type":"Point"},"properties":{"osm_id":"8126634990","tag":{"natural":"tree"}},"type":"Feature"},
	{"geometry":{"coordinates":[10.365455,49.778026],"type":"Point"},"properties":{"osm_id":"8126634991","tag":{"natural":"tree"}},"type":"Feature"},
	{"geometry":{"coordinates":[10.284557,49.759781],"type":"Point"},"properties":{"osm_id":"8220651140","tag":{"natural":"tree"}},"type":"Feature"},
	{"geometry":{"coordinates":[10.284522,49.759651],"type":"Point"},"properties":{"osm_id":"8220651141","tag":{"natural":"tree"}},"type":"Feature"},
	{"geometry":{"coordinates":[10.284546,49.759352],"type":"Point"},"properties":{"osm_id":"8220651142","tag":{"natural":"tree"}},"type":"Feature"},
	{"geometry":{"coordinates":[10.284677,49.758928],"type":"Point"},"properties":{"osm_id":"8220651143","tag":{"natural":"tree"}},"type":"Feature"},
	{"geometry":{"coordinates":[10.284588,49.758726],"type":"Point"},"properties":{"osm_id":"8220651144","tag":{"natural":"tree"}},"type":"Feature"},
	{"geometry":{"coordinates":[10.284504,49.758544],"type":"Point"},"properties":{"osm_id":"8220651145","tag":{"natural":"tree"}},"type":"Feature"},
	{"geometry":{"coordinates":[10.284317,49.758342],"type":"Point"},"properties":{"osm_id":"8220651146","tag":{"natural":"tree"}},"type":"Feature"},
	{"geometry":{"coordinates":[10.284186,49.758146],"type":"Point"},"properties":{"osm_id":"8220651147","tag":{"natural":"tree"}},"type":"Feature"},
	{"geometry":{"coordinates":[10.28403,49.757953],"type":"Point"},"properties":{"osm_id":"8220651148","tag":{"natural":"tree"}},"type":"Feature"},
	{"geometry":{"coordinates":[10.283781,49.757676],"type":"Point"},"properties":{"osm_id":"8220651149","tag":{"natural":"tree"}},"type":"Feature"},
	{"geometry":{"coordinates":[10.283639,49.757482],"type":"Point"},"properties":{"osm_id":"8220651150","tag":{"natural":"tree"}},"type":"Feature"},
	{"geometry":{"coordinates":[10.283484,49.757308],"type":"Point"},"properties":{"osm_id":"8220651151","tag":{"natural":"tree"}},"type":"Feature"},
	{"geometry":{"coordinates":[10.283329,49.757127],"type":"Point"},"properties":{"osm_id":"8220651152","tag":{"natural":"tree"}},"type":"Feature"},
	{"geometry":{"coordinates":[10.283781,49.753606],"type":"Point"},"properties":{"osm_id":"8220651200","tag":{"natural":"tree"}},"type":"Feature"},
	{"geometry":{"coordinates":[10.283671,49.753635],"type":"Point"},"properties":{"osm_id":"8220651201","tag":{"natural":"tree"}},"type":"Feature"},
	{"geometry":{"coordinates":[10.283305,49.75374],"type":"Point"},"properties":{"osm_id":"8220651202","tag":{"natural":"tree"}},"type":"Feature"}
]
}
