{
"type": "FeatureCollection",
"features": [
	{"geometry":{"coordinates":[10.353965,49.738469],"type":"Point"},"properties":{"name":"Gerichtslinde","osm_id":"404573769","tag":{"genus":"Tilia","leaf_cycle":"deciduous","leaf_type":"broadleaved","natural":"tree"}},"type":"Feature"},
	{"geometry":{"coordinates":[10.356145,49.767455],"type":"Point"},"properties":{"osm_id":"3257879909","tag":{"natural":"tree"}},"type":"Feature"}
]
}
