{
"type": "FeatureCollection",
"features": [
	{"geometry":{"coordinates":[10.310638,43.88538],"type":"Point"},"properties":{"name":"Olivo dei 30 zoccoli","osm_id":"5781759825","tag":{"denotation":"natural_monument","leaf_cycle":"evergreen","leaf_type":"broadleaved","natural":"tree","tree":"olive_tree","wikidata":"Q27868535","wikipedia":"it:Olivo dei 30 zoccoli"}},"type":"Feature"},
	{"geometry":{"coordinates":[10.363275,43.853759],"type":"Point"},"properties":{"osm_id":"9170440466","tag":{"natural":"tree"}},"type":"Feature"},
	{"geometry":{"coordinates":[10.363315,43.853829],"type":"Point"},"properties":{"osm_id":"9170440467","tag":{"natural":"tree"}},"type":"Feature"},
	{"geometry":{"coordinates":[10.363344,43.853902],"type":"Point"},"properties":{"osm_id":"9170440468","tag":{"natural":"tree"}},"type":"Feature"},
	{"geometry":{"coordinates":[10.363374,43.853971],"type":"Point"},"properties":{"osm_id":"9170440469","tag":{"natural":"tree"}},"type":"Feature"}
]
}
