{
"type": "FeatureCollection",
"features": [
	{"geometry":{"coordinates":[10.310639,43.885381],"type":"Point"},"properties":{"name":"Olivo dei 30 zoccoli","osm_id":"5781759825","tag":{"denotation":"natural_monument","leaf_cycle":"evergreen","leaf_type":"broadleaved","natural":"tree","tree":"olive_tree","wikidata":"Q27868535","wikipedia":"it:Olivo dei 30 zoccoli"}},"type":"Feature"}
]
}
