{
"type": "FeatureCollection",
"lastupdate": "2020-08-01T00:00:00Z",
"features": [
	{"geometry":{"coordinates":[-101.393581,26.908265],"type":"Point"},"properties":{"name":"La Guera","osm_id":"5338974085","tag":{"amenity":"recycling","recycling_type":"centre"}},"type":"Feature"}
]
}
