{
"type": "FeatureCollection",
"features": [
	{"geometry":{"coordinates":[-77.239807,38.773219],"type":"Point"},"properties":{"osm_id":"1379537397","tag":{"natural":"tree"}},"type":"Feature"},
	{"geometry":{"coordinates":[-77.239682,38.77326],"type":"Point"},"properties":{"osm_id":"1379537398","tag":{"natural":"tree"}},"type":"Feature"},
	{"geometry":{"coordinates":[-77.213438,38.762124],"type":"Point"},"properties":{"name":"Daventry Playground","osm_id":"4313136200","tag":{"amenity_1":"waste_basket","leisure":"park","natural":"tree","surface":"woodchips"}},"type":"Feature"},
	{"geometry":{"coordinates":[-77.229914,38.815789],"type":"Point"},"properties":{"osm_id":"6949161339","tag":{"natural":"tree"}},"type":"Feature"}
]
}
