{
"type": "FeatureCollection",
"features": [
	{"geometry":{"coordinates":[11.544743,45.284165],"type":"Point"},"properties":{"name":"Ecocentro","osm_id":"3584152893","tag":{"addr:city":"Noventa Vicentina","addr:postcode":"36025","addr:street":"Via Collegio Armeno","amenity":"recycling"}},"type":"Feature"},
	{"geometry":{"coordinates":[11.539485,45.291614],"type":"Point"},"properties":{"osm_id":"3595129616","tag":{"amenity":"waste_basket"}},"type":"Feature"},
	{"geometry":{"coordinates":[11.539078,45.336327],"type":"Point"},"properties":{"osm_id":"4294602819","tag":{"amenity":"waste_basket"}},"type":"Feature"},
	{"geometry":{"coordinates":[11.536932,45.33651],"type":"Point"},"properties":{"name":"Raccolta Abiti Usati","osm_id":"4294617695","tag":{"amenity":"waste_basket"}},"type":"Feature"}
]
}
