{
"type": "FeatureCollection",
"features": [
	{"geometry":{"coordinates":[11.539485,45.291614],"type":"Point"},"properties":{"osm_id":"3595129616","tag":{"amenity":"waste_basket"}},"type":"Feature"},
	{"geometry":{"coordinates":[11.539077,45.336326],"type":"Point"},"properties":{"osm_id":"4294602819","tag":{"amenity":"waste_basket"}},"type":"Feature"},
	{"geometry":{"coordinates":[11.536931,45.336509],"type":"Point"},"properties":{"name":"Raccolta Abiti Usati","osm_id":"4294617695","tag":{"amenity":"waste_basket"}},"type":"Feature"}
]
}
