{
"type": "FeatureCollection",
"features": [
	{"geometry":{"coordinates":[-80.350149,22.607847],"type":"Point"},"properties":{"osm_id":"5010111266","tag":{"natural":"tree"}},"type":"Feature"},
	{"geometry":{"coordinates":[-80.350234,22.608219],"type":"Point"},"properties":{"osm_id":"5010111267","tag":{"natural":"tree"}},"type":"Feature"},
	{"geometry":{"coordinates":[-80.350119,22.608098],"type":"Point"},"properties":{"osm_id":"5010111268","tag":{"natural":"tree"}},"type":"Feature"},
	{"geometry":{"coordinates":[-80.349938,22.608142],"type":"Point"},"properties":{"osm_id":"5010111269","tag":{"natural":"tree"}},"type":"Feature"},
	{"geometry":{"coordinates":[-80.350299,22.607718],"type":"Point"},"properties":{"osm_id":"5010111270","tag":{"natural":"tree"}},"type":"Feature"},
	{"geometry":{"coordinates":[-80.350416,22.607745],"type":"Point"},"properties":{"osm_id":"5010111271","tag":{"natural":"tree"}},"type":"Feature"},
	{"geometry":{"coordinates":[-80.350569,22.607665],"type":"Point"},"properties":{"osm_id":"5010111272","tag":{"natural":"tree"}},"type":"Feature"},
	{"geometry":{"coordinates":[-80.337837,22.604142],"type":"Point"},"properties":{"osm_id":"8980704051","tag":{"access":"yes","hoops":"2","leaf_type":"broadleaved","lit":"no","natural":"tree","surface":"concrete"}},"type":"Feature"},
	{"geometry":{"coordinates":[-80.337045,22.600782],"type":"Point"},"properties":{"osm_id":"8980704060","tag":{"denomination":"catholic","leaf_type":"broadleaved","natural":"tree","object:city":"Manaca"}},"type":"Feature"},
	{"geometry":{"coordinates":[-80.337194,22.599865],"type":"Point"},"properties":{"osm_id":"8990658448","tag":{"denotation":"street","leaf_type":"broadleaved","natural":"tree","object:city":"Manacas"}},"type":"Feature"},
	{"geometry":{"coordinates":[-80.337132,22.599162],"type":"Point"},"properties":{"osm_id":"8990658449","tag":{"denotation":"street","leaf_type":"broadleaved","natural":"tree","object:city":"Manacas"}},"type":"Feature"},
	{"geometry":{"coordinates":[-80.337826,22.604234],"type":"Point"},"properties":{"osm_id":"8990883386","tag":{"access":"yes","hoops":"2","leaf_type":"broadleaved","lit":"no","natural":"tree","surface":"concrete"}},"type":"Feature"}
]
}
