{
"type": "FeatureCollection",
"features": [
	{"geometry":{"coordinates":[4.973416,51.031355],"type":"Point"},"properties":{"osm_id":"1476500341","tag":{"amenity":"waste_basket"}},"type":"Feature"},
	{"geometry":{"coordinates":[4.985349,51.022639],"type":"Point"},"properties":{"osm_id":"1489462060","tag":{"amenity":"recycling","recycling:bottles":"yes","recycling_type":"container"}},"type":"Feature"},
	{"geometry":{"coordinates":[4.968645,51.043519],"type":"Point"},"properties":{"osm_id":"2682293877","tag":{"amenity":"waste_basket"}},"type":"Feature"},
	{"geometry":{"coordinates":[4.975984,51.051123],"type":"Point"},"properties":{"osm_id":"4012754862","tag":{"amenity":"waste_basket"}},"type":"Feature"},
	{"geometry":{"coordinates":[5.00872,51.056465],"type":"Point"},"properties":{"name":"Glas","osm_id":"5369883401","tag":{"amenity":"recycling","recycling:glass":"yes","recycling_type":"container"}},"type":"Feature"},
	{"geometry":{"coordinates":[4.934062,51.041194],"type":"Point"},"properties":{"osm_id":"5456608052","tag":{"amenity":"waste_basket"}},"type":"Feature"},
	{"geometry":{"coordinates":[4.9289,51.044063],"type":"Point"},"properties":{"osm_id":"5461974465","tag":{"amenity":"waste_basket"}},"type":"Feature"},
	{"geometry":{"coordinates":[4.929952,51.044048],"type":"Point"},"properties":{"osm_id":"5461979129","tag":{"amenity":"waste_basket"}},"type":"Feature"},
	{"geometry":{"coordinates":[4.981457,51.03177],"type":"Point"},"properties":{"osm_id":"5470869743","tag":{"amenity":"waste_basket"}},"type":"Feature"},
	{"geometry":{"coordinates":[4.980949,51.031981],"type":"Point"},"properties":{"osm_id":"5470869744","tag":{"amenity":"waste_basket"}},"type":"Feature"},
	{"geometry":{"coordinates":[4.968003,51.043147],"type":"Point"},"properties":{"osm_id":"6357914307","tag":{"amenity":"waste_basket"}},"type":"Feature"},
	{"geometry":{"coordinates":[4.928963,51.044326],"type":"Point"},"properties":{"osm_id":"7302120432","tag":{"amenity":"waste_basket","colour":"green","material":"plastic","waste":"trash"}},"type":"Feature"}
]
}
