{
"type": "FeatureCollection",
"features": [
	{"geometry":{"coordinates":[-52.301127,4.939752],"type":"Point"},"properties":{"name":"Egon","osm_id":"1158361962","tag":{"height":"20 m","natural":"tree"}},"type":"Feature"},
	{"geometry":{"coordinates":[-52.310414,4.942939],"type":"Point"},"properties":{"osm_id":"1935519013","tag":{"natural":"tree"}},"type":"Feature"},
	{"geometry":{"coordinates":[-52.336896,4.936508],"type":"Point"},"properties":{"osm_id":"5947639228","tag":{"natural":"tree"}},"type":"Feature"},
	{"geometry":{"coordinates":[-52.330809,4.943123],"type":"Point"},"properties":{"osm_id":"6409568381","tag":{"leaf_cycle":"evergreen","leaf_type":"broadleaved","natural":"tree"}},"type":"Feature"},
	{"geometry":{"coordinates":[-52.331638,4.943399],"type":"Point"},"properties":{"osm_id":"6455925311","tag":{"natural":"tree"}},"type":"Feature"},
	{"geometry":{"coordinates":[-52.330801,4.943314],"type":"Point"},"properties":{"osm_id":"6455925312","tag":{"natural":"tree"}},"type":"Feature"},
	{"geometry":{"coordinates":[-52.331795,4.943472],"type":"Point"},"properties":{"osm_id":"6455925313","tag":{"natural":"tree"}},"type":"Feature"},
	{"geometry":{"coordinates":[-52.331678,4.943614],"type":"Point"},"properties":{"osm_id":"6455925314","tag":{"natural":"tree"}},"type":"Feature"},
	{"geometry":{"coordinates":[-52.331196,4.943358],"type":"Point"},"properties":{"osm_id":"6455925315","tag":{"natural":"tree"}},"type":"Feature"},
	{"geometry":{"coordinates":[-52.331356,4.943333],"type":"Point"},"properties":{"osm_id":"6455925316","tag":{"natural":"tree"}},"type":"Feature"},
	{"geometry":{"coordinates":[-52.331278,4.943346],"type":"Point"},"properties":{"osm_id":"6455925317","tag":{"natural":"tree"}},"type":"Feature"},
	{"geometry":{"coordinates":[-52.29554,4.935906],"type":"Point"},"properties":{"osm_id":"6591575703","tag":{"leaf_cycle":"evergreen","leaf_type":"broadleaved","natural":"tree"}},"type":"Feature"},
	{"geometry":{"coordinates":[-52.313924,4.94507],"type":"Point"},"properties":{"osm_id":"6695585696","tag":{"natural":"tree"}},"type":"Feature"},
	{"geometry":{"coordinates":[-52.313832,4.945381],"type":"Point"},"properties":{"osm_id":"6695585697","tag":{"natural":"tree"}},"type":"Feature"},
	{"geometry":{"coordinates":[-52.313777,4.945392],"type":"Point"},"properties":{"osm_id":"6695585698","tag":{"natural":"tree"}},"type":"Feature"},
	{"geometry":{"coordinates":[-52.314018,4.945128],"type":"Point"},"properties":{"osm_id":"6695585699","tag":{"natural":"tree"}},"type":"Feature"},
	{"geometry":{"coordinates":[-52.314014,4.945295],"type":"Point"},"properties":{"osm_id":"6695585700","tag":{"natural":"tree"}},"type":"Feature"},
	{"geometry":{"coordinates":[-52.322279,4.933414],"type":"Point"},"properties":{"osm_id":"7347215548","tag":{"leaf_type":"broadleaved","natural":"tree","source:position":"BDOrtho IGN"}},"type":"Feature"},
	{"geometry":{"coordinates":[-52.322182,4.933432],"type":"Point"},"properties":{"osm_id":"7347215549","tag":{"leaf_type":"broadleaved","natural":"tree","source:position":"BDOrtho IGN"}},"type":"Feature"}
]
}
