{
"type": "FeatureCollection",
"features": [
	{"geometry":{"coordinates":[-4.727256,58.566667],"type":"Point"},"properties":{"name":"Durness Recycling Centre","osm_id":"9151220044","tag":{"amenity":"recycling","owner":"Highland Council","ownership":"municipal","recycling_type":"centre","wikidata":"Q106085786"}},"type":"Feature"}
]
}
