{
"type": "FeatureCollection",
"lastupdate": "2020-08-06T00:00:00Z",
"features": [
	{"geometry":{"coordinates":[-4.697568,40.650095],"type":"Point"},"properties":{"osm_id":"652725319","tag":{"amenity":"recycling","recycling:cans":"yes","recycling:clothes":"yes","recycling:glass_bottles":"yes","recycling:paper":"yes","recycling_type":"container"}},"type":"Feature"},
	{"geometry":{"coordinates":[-4.698676,40.65369],"type":"Point"},"properties":{"osm_id":"652755193","tag":{"amenity":"recycling","recycling:cans":"yes","recycling_type":"container"}},"type":"Feature"},
	{"geometry":{"coordinates":[-4.674418,40.665876],"type":"Point"},"properties":{"osm_id":"657893715","tag":{"amenity":"recycling","recycling:cans":"yes","recycling:glass_bottles":"yes","recycling:paper":"yes","recycling_type":"container"}},"type":"Feature"},
	{"geometry":{"coordinates":[-4.672485,40.666224],"type":"Point"},"properties":{"osm_id":"657893873","tag":{"amenity":"recycling","recycling:cans":"yes","recycling:glass_bottles":"yes","recycling:paper":"yes","recycling_type":"container"}},"type":"Feature"},
	{"geometry":{"coordinates":[-4.689328,40.655693],"type":"Point"},"properties":{"osm_id":"845910082","tag":{"amenity":"recycling","recycling:batteries":"yes","recycling:books":"no","recycling:cans":"no","recycling:cardboard":"no","recycling:cartons":"no","recycling:clothes":"no","recycling:electrical_appliances":"no","recycling:glass":"no","recycling:glass_bottles":"no","recycling:green_waste":"no","recycling:magazines":"no","recycling:newspaper":"no","recycling:paper":"no","recycling:paper_packaging":"no","recycling:plastic":"no","recycling:plastic_bottles":"no","recycling:plastic_packaging":"no","recycling:scrap_metal":"no","recycling:small_appliances":"no","recycling:waste":"no","recycling:wood":"no","recycling_type":"container"}},"type":"Feature"},
	{"geometry":{"coordinates":[-4.671086,40.663165],"type":"Point"},"properties":{"osm_id":"904599767","tag":{"amenity":"recycling","recycling_type":"container"}},"type":"Feature"},
	{"geometry":{"coordinates":[-4.671021,40.665338],"type":"Point"},"properties":{"osm_id":"904599770","tag":{"amenity":"recycling","recycling_type":"container"}},"type":"Feature"},
	{"geometry":{"coordinates":[-4.674152,40.660005],"type":"Point"},"properties":{"osm_id":"3168599318","tag":{"amenity":"recycling","recycling_type":"container"}},"type":"Feature"},
	{"geometry":{"coordinates":[-4.683812,40.647892],"type":"Point"},"properties":{"name":"Paplera","osm_id":"3561307662","tag":{"amenity":"waste_basket"}},"type":"Feature"},
	{"geometry":{"coordinates":[-4.682653,40.648053],"type":"Point"},"properties":{"osm_id":"3561314083","tag":{"amenity":"waste_basket"}},"type":"Feature"}
]
}
