{
"type": "FeatureCollection",
"features": [
	{"geometry":{"coordinates":[12.871379,53.551958],"type":"Point"},"properties":{"name":"Tinkoeiche","osm_id":"3096292141","tag":{"denotation":"natural_monument","leaf_cycle":"deciduous","leaf_type":"broadleaved","natural":"tree"}},"type":"Feature"},
	{"geometry":{"coordinates":[12.842237,53.543368],"type":"Point"},"properties":{"osm_id":"5580149584","tag":{"natural":"tree"}},"type":"Feature"},
	{"geometry":{"coordinates":[12.86313,53.556904],"type":"Point"},"properties":{"osm_id":"5582179191","tag":{"natural":"tree"}},"type":"Feature"},
	{"geometry":{"coordinates":[12.834459,53.540741],"type":"Point"},"properties":{"osm_id":"5585916140","tag":{"natural":"tree"}},"type":"Feature"},
	{"geometry":{"coordinates":[12.854924,53.543985],"type":"Point"},"properties":{"osm_id":"5586685685","tag":{"natural":"tree"}},"type":"Feature"},
	{"geometry":{"coordinates":[12.861415,53.541444],"type":"Point"},"properties":{"osm_id":"5586685778","tag":{"natural":"tree"}},"type":"Feature"},
	{"geometry":{"coordinates":[12.864521,53.540459],"type":"Point"},"properties":{"osm_id":"5586685805","tag":{"natural":"tree"}},"type":"Feature"},
	{"geometry":{"coordinates":[12.863759,53.540348],"type":"Point"},"properties":{"osm_id":"5586685806","tag":{"natural":"tree"}},"type":"Feature"},
	{"geometry":{"coordinates":[12.864081,53.540667],"type":"Point"},"properties":{"osm_id":"5586685807","tag":{"natural":"tree"}},"type":"Feature"},
	{"geometry":{"coordinates":[12.863942,53.540482],"type":"Point"},"properties":{"osm_id":"5586685808","tag":{"natural":"tree"}},"type":"Feature"},
	{"geometry":{"coordinates":[12.862634,53.543797],"type":"Point"},"properties":{"osm_id":"5586685862","tag":{"natural":"tree"}},"type":"Feature"},
	{"geometry":{"coordinates":[12.847053,53.546447],"type":"Point"},"properties":{"osm_id":"6945011799","tag":{"natural":"tree"}},"type":"Feature"},
	{"geometry":{"coordinates":[12.846973,53.546449],"type":"Point"},"properties":{"osm_id":"6945011800","tag":{"natural":"tree"}},"type":"Feature"}
]
}
