{
"type": "FeatureCollection",
"features": [
	{"geometry":{"coordinates":[12.871379,53.551959],"type":"Point"},"properties":{"name":"Tinkoeiche","osm_id":"3096292141","tag":{"denotation":"natural_monument","leaf_cycle":"deciduous","leaf_type":"broadleaved","natural":"tree"}},"type":"Feature"},
	{"geometry":{"coordinates":[12.842238,53.543368],"type":"Point"},"properties":{"osm_id":"5580149584","tag":{"natural":"tree"}},"type":"Feature"},
	{"geometry":{"coordinates":[12.86313,53.556904],"type":"Point"},"properties":{"osm_id":"5582179191","tag":{"natural":"tree"}},"type":"Feature"},
	{"geometry":{"coordinates":[12.83446,53.540742],"type":"Point"},"properties":{"osm_id":"5585916140","tag":{"natural":"tree"}},"type":"Feature"},
	{"geometry":{"coordinates":[12.854925,53.543986],"type":"Point"},"properties":{"osm_id":"5586685685","tag":{"natural":"tree"}},"type":"Feature"},
	{"geometry":{"coordinates":[12.861415,53.541445],"type":"Point"},"properties":{"osm_id":"5586685778","tag":{"natural":"tree"}},"type":"Feature"},
	{"geometry":{"coordinates":[12.864521,53.54046],"type":"Point"},"properties":{"osm_id":"5586685805","tag":{"natural":"tree"}},"type":"Feature"},
	{"geometry":{"coordinates":[12.86376,53.540348],"type":"Point"},"properties":{"osm_id":"5586685806","tag":{"natural":"tree"}},"type":"Feature"},
	{"geometry":{"coordinates":[12.864082,53.540667],"type":"Point"},"properties":{"osm_id":"5586685807","tag":{"natural":"tree"}},"type":"Feature"},
	{"geometry":{"coordinates":[12.863942,53.540482],"type":"Point"},"properties":{"osm_id":"5586685808","tag":{"natural":"tree"}},"type":"Feature"},
	{"geometry":{"coordinates":[12.862635,53.543797],"type":"Point"},"properties":{"osm_id":"5586685862","tag":{"natural":"tree"}},"type":"Feature"},
	{"geometry":{"coordinates":[12.847054,53.546448],"type":"Point"},"properties":{"osm_id":"6945011799","tag":{"natural":"tree"}},"type":"Feature"},
	{"geometry":{"coordinates":[12.846974,53.546449],"type":"Point"},"properties":{"osm_id":"6945011800","tag":{"natural":"tree"}},"type":"Feature"}
]
}
