{
"type": "FeatureCollection",
"features": [
	{"geometry":{"coordinates":[12.8386,53.438044],"type":"Point"},"properties":{"name":"Naturdenkmal Sommerlinde","osm_id":"446688672","tag":{"circumference":"4","denotation":"natural_monument","genus":"Tilia","height":"15","leaf_cycle":"deciduous","leaf_type":"broadleaved","name:botanical":"Tilia platyphyllus","natural":"tree","opening_hours":"24/7","start_date":"~C13","tourism":"attraction"}},"type":"Feature"},
	{"geometry":{"coordinates":[12.886523,53.460597],"type":"Point"},"properties":{"osm_id":"4961776772","tag":{"natural":"tree"}},"type":"Feature"},
	{"geometry":{"coordinates":[12.888838,53.46181],"type":"Point"},"properties":{"osm_id":"4961776773","tag":{"natural":"tree"}},"type":"Feature"},
	{"geometry":{"coordinates":[12.871717,53.475976],"type":"Point"},"properties":{"osm_id":"8679417958","tag":{"denotation":"natural_monument","description":"alte hohle Eiche","leaf_type":"broadleaved","natural":"tree"}},"type":"Feature"}
]
}
