{
"type": "FeatureCollection",
"features": [
	{"geometry":{"coordinates":[12.881584,52.757918],"type":"Point"},"properties":{"name":"Kaiser- und Gedenkeiche von 1897","osm_id":"4547724884","tag":{"denotation":"natural_monument","description":"Gedenkeiche zum 100. Geburtstag von Kaiser Wilhelm I.","leaf_cycle":"deciduous","leaf_type":"broadleaved","natural":"tree"}},"type":"Feature"},
	{"geometry":{"coordinates":[12.879571,52.800113],"type":"Point"},"properties":{"osm_id":"4871737976","tag":{"natural":"tree"}},"type":"Feature"},
	{"geometry":{"coordinates":[12.881633,52.800165],"type":"Point"},"properties":{"osm_id":"4871737977","tag":{"natural":"tree"}},"type":"Feature"},
	{"geometry":{"coordinates":[12.881408,52.800172],"type":"Point"},"properties":{"osm_id":"4871737978","tag":{"natural":"tree"}},"type":"Feature"},
	{"geometry":{"coordinates":[12.88372,52.800134],"type":"Point"},"properties":{"osm_id":"4871737979","tag":{"natural":"tree"}},"type":"Feature"},
	{"geometry":{"coordinates":[12.883337,52.80019],"type":"Point"},"properties":{"osm_id":"4871737980","tag":{"natural":"tree"}},"type":"Feature"},
	{"geometry":{"coordinates":[12.882937,52.800259],"type":"Point"},"properties":{"osm_id":"4871737981","tag":{"natural":"tree"}},"type":"Feature"},
	{"geometry":{"coordinates":[12.882771,52.800133],"type":"Point"},"properties":{"osm_id":"4871737982","tag":{"natural":"tree"}},"type":"Feature"},
	{"geometry":{"coordinates":[12.882773,52.799912],"type":"Point"},"properties":{"osm_id":"4871737983","tag":{"natural":"tree"}},"type":"Feature"}
]
}
