{
"type": "FeatureCollection",
"features": [
	{"geometry":{"coordinates":[-78.889628,43.002896],"type":"Point"},"properties":{"name":"Tin Can Alley","osm_id":"8095119248","tag":{"addr:city":"Tonawanda","addr:housenumber":"386","addr:postcode":"14150","addr:state":"NY","addr:street":"Hinds Street","amenity":"recycling","recycling:cans":"yes","recycling:glass_bottles":"yes","recycling:plastic_bottles":"yes","recycling_type":"centre"}},"type":"Feature"},
	{"geometry":{"coordinates":[-78.889475,43.003066],"type":"Point"},"properties":{"osm_id":"8672753175","tag":{"amenity":"recycling","opening_hours":"24/7","recycling:clothes":"yes","recycling_type":"container"}},"type":"Feature"}
]
}
