{
"type": "FeatureCollection",
"features": [
	{"geometry":{"coordinates":[-78.878945,36.171216],"type":"Point"},"properties":{"name":"Durham County Solid Waste","osm_id":"8907448653","tag":{"addr:city":"Bahama","addr:housenumber":"9008","addr:postcode":"27503","addr:state":"NC","addr:street":"Quail Roost Road","amenity":"recycling","building":"commercial","recycling:cans":"yes","recycling:oils":"yes","recycling:paper":"yes","recycling:plastic":"yes","recycling:yard_waste":"yes","recycling_type":"centre"}},"type":"Feature"}
]
}
