{
"type": "FeatureCollection",
"lastupdate": "2020-08-02T00:00:00Z",
"features": [
	{"geometry":{"coordinates":[-78.844674,35.682948],"type":"Point"},"properties":{"osm_id":"7181758003","tag":{"addr:city":"Apex","addr:housenumber":"6120","addr:state":"NC","addr:street":"Old Smithfield Road","amenity":"recycling","recycling_type":"centre"}},"type":"Feature"}
]
}
