{
"type": "FeatureCollection",
"features": [
	{"geometry":{"coordinates":[-78.839641,35.711593],"type":"Point"},"properties":{"osm_id":"6717743859","tag":{"amenity":"waste_disposal"}},"type":"Feature"},
	{"geometry":{"coordinates":[-78.844674,35.682948],"type":"Point"},"properties":{"osm_id":"7181758003","tag":{"addr:city":"Apex","addr:housenumber":"6120","addr:state":"NC","addr:street":"Old Smithfield Road","amenity":"recycling","recycling_type":"centre"}},"type":"Feature"}
]
}
