{
"type": "FeatureCollection",
"features": [
	{"geometry":{"coordinates":[-0.630825,52.809057],"type":"Point"},"properties":{"name":"Newton's Apple Tree","osm_id":"3402214833","tag":{"genus:en":"apple","natural":"tree"}},"type":"Feature"}
]
}
