{
"type": "FeatureCollection",
"features": [
	{"geometry":{"coordinates":[-87.920039,44.525175],"type":"Point"},"properties":{"name":"Apple Tree","osm_id":"3701868378","tag":{"natural":"tree"}},"type":"Feature"},
	{"geometry":{"coordinates":[-87.91996,44.525371],"type":"Point"},"properties":{"name":"Crab Apple","osm_id":"3714546014","tag":{"natural":"tree"}},"type":"Feature"},
	{"geometry":{"coordinates":[-87.90308,44.52465],"type":"Point"},"properties":{"osm_id":"5534922830","tag":{"natural":"tree"}},"type":"Feature"}
]
}
