{
"type": "FeatureCollection",
"features": [
	{"geometry":{"coordinates":[8.526589,53.233585],"type":"Point"},"properties":{"osm_id":"290465471","tag":{"amenity":"recycling","location":"overground","recycling:glass":"yes","recycling_type":"container"}},"type":"Feature"},
	{"geometry":{"coordinates":[8.585512,53.249158],"type":"Point"},"properties":{"osm_id":"389674570","tag":{"amenity":"recycling","recycling:glass":"yes"}},"type":"Feature"},
	{"geometry":{"coordinates":[8.563077,53.25329],"type":"Point"},"properties":{"osm_id":"466105398","tag":{"amenity":"recycling"}},"type":"Feature"},
	{"geometry":{"coordinates":[8.568373,53.255],"type":"Point"},"properties":{"osm_id":"466105406","tag":{"amenity":"recycling"}},"type":"Feature"},
	{"geometry":{"coordinates":[8.59414,53.231731],"type":"Point"},"properties":{"osm_id":"2295107846","tag":{"amenity":"recycling","recycling:glass_bottles":"yes","recycling_type":"container"}},"type":"Feature"},
	{"geometry":{"coordinates":[8.59668,53.252183],"type":"Point"},"properties":{"osm_id":"4208674058","tag":{"amenity":"recycling","recycling:glass":"yes","recycling_type":"container"}},"type":"Feature"},
	{"geometry":{"coordinates":[8.605438,53.278028],"type":"Point"},"properties":{"osm_id":"4427896598","tag":{"amenity":"waste_basket"}},"type":"Feature"},
	{"geometry":{"coordinates":[8.605377,53.278033],"type":"Point"},"properties":{"osm_id":"4431681289","tag":{"amenity":"recycling","recycling:glass":"yes","recycling_type":"container"}},"type":"Feature"},
	{"geometry":{"coordinates":[8.537612,53.228399],"type":"Point"},"properties":{"osm_id":"6123909453","tag":{"amenity":"recycling","recycling:glass":"yes"}},"type":"Feature"}
]
}
