{
"type": "FeatureCollection",
"features": [
	{"geometry":{"coordinates":[-92.347596,47.336281],"type":"Point"},"properties":{"name":"St Louis County Transfer Site","osm_id":"4812213621","tag":{"addr:city":"Makinen","addr:housenumber":"6327","addr:state":"MN","addr:street":"Long Lake Road","amenity":"waste_disposal"}},"type":"Feature"}
]
}
