{
"type": "FeatureCollection",
"features": [
	{"geometry":{"coordinates":[-72.832348,42.014776],"type":"Point"},"properties":{"name":"big white oak","osm_id":"6384327114","tag":{"natural":"tree"}},"type":"Feature"},
	{"geometry":{"coordinates":[-72.832165,42.014779],"type":"Point"},"properties":{"name":"big white oak","osm_id":"6384327115","tag":{"natural":"tree"}},"type":"Feature"}
]
}
