{
"type": "FeatureCollection",
"features": [
	{"geometry":{"coordinates":[145.371505,-41.041403],"type":"Point"},"properties":{"name":"Big Tree","osm_id":"5352577987","tag":{"natural":"tree"}},"type":"Feature"}
]
}
