{
"type": "FeatureCollection",
"features": [
	{"geometry":{"coordinates":[-47.938463,-18.097222],"type":"Point"},"properties":{"name":"Caryocar brasiliense","osm_id":"8837360233","tag":{"natural":"tree"}},"type":"Feature"}
]
}
