{
"type": "FeatureCollection",
"features": [
	{"geometry":{"coordinates":[15.330046,57.160961],"type":"Point"},"properties":{"name":"Kristina Nilsson tallen","osm_id":"4266846955","tag":{"genus":"pinus","historic":"yes","leaf_cycle":"evergreen","leaf_type":"needleleaved","name:en":"Kristina Nilsson pine","natural":"tree"}},"type":"Feature"}
]
}
