{
"type": "FeatureCollection",
"features": [
	{"geometry":{"coordinates":[15.371433,40.278167],"type":"Point"},"properties":{"name":"Albero riparo di Alfonso","osm_id":"8934549642","tag":{"natural":"tree"}},"type":"Feature"}
]
}
