{
"type": "FeatureCollection",
"features": [
	{"geometry":{"coordinates":[-123.114592,38.479796],"type":"Point"},"properties":{"name":"2020 VISION","osm_id":"8510718969","tag":{"natural":"tree"}},"type":"Feature"}
]
}
