{
"type": "FeatureCollection",
"features": [
	{"geometry":{"coordinates":[39.381659,-6.871412],"type":"Point"},"properties":{"osm_id":"5160544265","tag":{"natural":"tree"}},"type":"Feature"},
	{"geometry":{"coordinates":[39.381225,-6.871237],"type":"Point"},"properties":{"osm_id":"5160544266","tag":{"natural":"tree"}},"type":"Feature"},
	{"geometry":{"coordinates":[39.409568,-6.872585],"type":"Point"},"properties":{"name":"muembe","osm_id":"8326902607","tag":{"natural":"tree"}},"type":"Feature"}
]
}
