{
"type": "FeatureCollection",
"features": [
	{"geometry":{"coordinates":[12.631975,51.740866],"type":"Point"},"properties":{"name":"Wildbirne","osm_id":"2990514729","tag":{"denotation":"natural_monument","natural":"tree"}},"type":"Feature"},
	{"geometry":{"coordinates":[12.632206,51.758456],"type":"Point"},"properties":{"osm_id":"3123453728","tag":{"natural":"tree"}},"type":"Feature"},
	{"geometry":{"coordinates":[12.60702,51.760891],"type":"Point"},"properties":{"osm_id":"4972414995","tag":{"natural":"tree"}},"type":"Feature"},
	{"geometry":{"coordinates":[12.618481,51.770548],"type":"Point"},"properties":{"osm_id":"4972417248","tag":{"natural":"tree"}},"type":"Feature"},
	{"geometry":{"coordinates":[12.618677,51.771025],"type":"Point"},"properties":{"osm_id":"4972417249","tag":{"natural":"tree"}},"type":"Feature"},
	{"geometry":{"coordinates":[12.617607,51.771078],"type":"Point"},"properties":{"osm_id":"4972417250","tag":{"natural":"tree"}},"type":"Feature"},
	{"geometry":{"coordinates":[12.6174,51.770943],"type":"Point"},"properties":{"osm_id":"4972417251","tag":{"natural":"tree"}},"type":"Feature"},
	{"geometry":{"coordinates":[12.627456,51.770069],"type":"Point"},"properties":{"osm_id":"4972417309","tag":{"natural":"tree"}},"type":"Feature"},
	{"geometry":{"coordinates":[12.627308,51.770052],"type":"Point"},"properties":{"osm_id":"4972417310","tag":{"natural":"tree"}},"type":"Feature"},
	{"geometry":{"coordinates":[12.628504,51.769592],"type":"Point"},"properties":{"osm_id":"4972417311","tag":{"natural":"tree"}},"type":"Feature"},
	{"geometry":{"coordinates":[12.628709,51.769566],"type":"Point"},"properties":{"osm_id":"4972417312","tag":{"natural":"tree"}},"type":"Feature"},
	{"geometry":{"coordinates":[12.628943,51.769544],"type":"Point"},"properties":{"osm_id":"4972417313","tag":{"natural":"tree"}},"type":"Feature"},
	{"geometry":{"coordinates":[12.629339,51.769283],"type":"Point"},"properties":{"osm_id":"4972417314","tag":{"natural":"tree"}},"type":"Feature"},
	{"geometry":{"coordinates":[12.637012,51.769703],"type":"Point"},"properties":{"osm_id":"4972417346","tag":{"natural":"tree"}},"type":"Feature"},
	{"geometry":{"coordinates":[12.640004,51.769079],"type":"Point"},"properties":{"osm_id":"4972417347","tag":{"natural":"tree"}},"type":"Feature"},
	{"geometry":{"coordinates":[12.641077,51.770437],"type":"Point"},"properties":{"osm_id":"4972417348","tag":{"natural":"tree"}},"type":"Feature"},
	{"geometry":{"coordinates":[12.639987,51.770523],"type":"Point"},"properties":{"osm_id":"4972417349","tag":{"natural":"tree"}},"type":"Feature"},
	{"geometry":{"coordinates":[12.64633,51.774629],"type":"Point"},"properties":{"osm_id":"4972417354","tag":{"natural":"tree"}},"type":"Feature"},
	{"geometry":{"coordinates":[12.645647,51.774875],"type":"Point"},"properties":{"osm_id":"4972417355","tag":{"natural":"tree"}},"type":"Feature"},
	{"geometry":{"coordinates":[12.645061,51.773492],"type":"Point"},"properties":{"osm_id":"4972417356","tag":{"natural":"tree"}},"type":"Feature"}
]
}
