{
"type": "FeatureCollection",
"features": [
	{"geometry":{"coordinates":[-1.42425,53.441792],"type":"Point"},"properties":{"osm_id":"6898295962","tag":{"leaf_cycle":"evergreen","leaf_type":"needleleaved","natural":"tree"}},"type":"Feature"},
	{"geometry":{"coordinates":[-1.424281,53.441871],"type":"Point"},"properties":{"osm_id":"6898295966","tag":{"leaf_cycle":"evergreen","leaf_type":"needleleaved","natural":"tree"}},"type":"Feature"},
	{"geometry":{"coordinates":[-1.46715,53.481179],"type":"Point"},"properties":{"name":"Silver Birch","osm_id":"7063660744","tag":{"natural":"tree"}},"type":"Feature"}
]
}
