{
"type": "FeatureCollection",
"features": [
	{"geometry":{"coordinates":[-1.424249,53.441791],"type":"Point"},"properties":{"osm_id":"6898295962","tag":{"leaf_cycle":"evergreen","leaf_type":"needleleaved","natural":"tree"}},"type":"Feature"},
	{"geometry":{"coordinates":[-1.42428,53.44187],"type":"Point"},"properties":{"osm_id":"6898295966","tag":{"leaf_cycle":"evergreen","leaf_type":"needleleaved","natural":"tree"}},"type":"Feature"},
	{"geometry":{"coordinates":[-1.46715,53.481178],"type":"Point"},"properties":{"name":"Silver Birch","osm_id":"7063660744","tag":{"natural":"tree"}},"type":"Feature"}
]
}
