{
"type": "FeatureCollection",
"features": [
	{"geometry":{"coordinates":[34.893057,32.342365],"type":"Point"},"properties":{"osm_id":"545804291","tag":{"amenity":"recycling","location":"overground","recycling_type":"container"}},"type":"Feature"}
]
}
