{
"type": "FeatureCollection",
"features": [
	{"geometry":{"coordinates":[23.672915,56.936552],"type":"Point"},"properties":{"osm_id":"2469810978","tag":{"amenity":"recycling","location":"overground","recycling:cans":"yes","recycling:glass_bottles":"yes","recycling:paper":"yes","recycling:plastic":"no","recycling:plastic_packaging":"yes","recycling_type":"container"}},"type":"Feature"},
	{"geometry":{"coordinates":[23.687067,56.93904],"type":"Point"},"properties":{"osm_id":"2469810983","tag":{"amenity":"recycling"}},"type":"Feature"},
	{"geometry":{"coordinates":[23.6928,56.9418],"type":"Point"},"properties":{"osm_id":"2469810988","tag":{"amenity":"recycling","location":"overground","recycling:cans":"yes","recycling:glass_bottles":"yes","recycling:paper":"yes","recycling:plastic":"no","recycling:plastic_packaging":"yes","recycling_type":"container"}},"type":"Feature"}
]
}
