{
"type": "FeatureCollection",
"features": [
	{"geometry":{"coordinates":[2.77785,42.850303],"type":"Point"},"properties":{"osm_id":"2107108425","tag":{"natural":"tree"}},"type":"Feature"},
	{"geometry":{"coordinates":[2.778575,42.849019],"type":"Point"},"properties":{"osm_id":"2336852371","tag":{"natural":"tree"}},"type":"Feature"},
	{"geometry":{"coordinates":[2.778577,42.849065],"type":"Point"},"properties":{"osm_id":"2336852374","tag":{"natural":"tree"}},"type":"Feature"},
	{"geometry":{"coordinates":[2.778047,42.849216],"type":"Point"},"properties":{"osm_id":"2336852390","tag":{"name:botanical":"Platanus","natural":"tree"}},"type":"Feature"},
	{"geometry":{"coordinates":[2.775175,42.844748],"type":"Point"},"properties":{"osm_id":"2336872285","tag":{"natural":"tree"}},"type":"Feature"},
	{"geometry":{"coordinates":[2.775269,42.844786],"type":"Point"},"properties":{"osm_id":"2336872288","tag":{"natural":"tree"}},"type":"Feature"},
	{"geometry":{"coordinates":[2.775506,42.844893],"type":"Point"},"properties":{"osm_id":"2336872301","tag":{"natural":"tree"}},"type":"Feature"}
]
}
