{
"type": "FeatureCollection",
"features": [
	{"geometry":{"coordinates":[2.777849,42.850303],"type":"Point"},"properties":{"osm_id":"2107108425","tag":{"natural":"tree"}},"type":"Feature"},
	{"geometry":{"coordinates":[2.778574,42.849018],"type":"Point"},"properties":{"osm_id":"2336852371","tag":{"natural":"tree"}},"type":"Feature"},
	{"geometry":{"coordinates":[2.778577,42.849065],"type":"Point"},"properties":{"osm_id":"2336852374","tag":{"natural":"tree"}},"type":"Feature"},
	{"geometry":{"coordinates":[2.778047,42.849215],"type":"Point"},"properties":{"osm_id":"2336852390","tag":{"name:botanical":"Platanus","natural":"tree"}},"type":"Feature"},
	{"geometry":{"coordinates":[2.775174,42.844748],"type":"Point"},"properties":{"osm_id":"2336872285","tag":{"natural":"tree"}},"type":"Feature"},
	{"geometry":{"coordinates":[2.775268,42.844786],"type":"Point"},"properties":{"osm_id":"2336872288","tag":{"natural":"tree"}},"type":"Feature"},
	{"geometry":{"coordinates":[2.775505,42.844892],"type":"Point"},"properties":{"osm_id":"2336872301","tag":{"natural":"tree"}},"type":"Feature"}
]
}
