{
"type": "FeatureCollection",
"features": [
	{"geometry":{"coordinates":[19.494159,49.008908],"type":"Point"},"properties":{"name":"Buk","osm_id":"4680802337","tag":{"height":"15","leaf_cycle":"deciduous","leaf_type":"broadleaved","natural":"tree"}},"type":"Feature"}
]
}
