{
"type": "FeatureCollection",
"features": [
	{"geometry":{"coordinates":[19.493597,46.276702],"type":"Point"},"properties":{"name":"Gyermekfa","osm_id":"3487611701","tag":{"natural":"tree","source:date":"2011-06-24","url":"http://turistautak.hu/poi.php?id=15859"}},"type":"Feature"}
]
}
