{
"type": "FeatureCollection",
"lastupdate": "2020-08-03T00:00:00Z",
"features": [
	{"geometry":{"coordinates":[1.47753,52.535045],"type":"Point"},"properties":{"osm_id":"682383593","tag":{"amenity":"recycling","location":"overground","recycling_type":"container"}},"type":"Feature"},
	{"geometry":{"coordinates":[1.473153,52.533824],"type":"Point"},"properties":{"osm_id":"682383594","tag":{"amenity":"recycling","recycling_type":"container"}},"type":"Feature"}
]
}
