{
"type": "FeatureCollection",
"features": [
	{"geometry":{"coordinates":[1.431272,49.73657],"type":"Point"},"properties":{"osm_id":"2151099659","tag":{"amenity":"recycling","recycling_type":"container"}},"type":"Feature"},
	{"geometry":{"coordinates":[1.433728,49.733863],"type":"Point"},"properties":{"name":"The name","osm_id":"2151099705","tag":{"amenity":"recycling","recycling:clothes":"yes","recycling:glass":"no","recycling:glass_bottles":"yes","recycling_type":"container"}},"type":"Feature"},
	{"geometry":{"coordinates":[1.433302,49.729131],"type":"Point"},"properties":{"osm_id":"2152037690","tag":{"amenity":"waste_basket","waste":"trash"}},"type":"Feature"},
	{"geometry":{"coordinates":[1.433189,49.730197],"type":"Point"},"properties":{"osm_id":"8946392200","tag":{"amenity":"waste_basket","waste":"trash"}},"type":"Feature"},
	{"geometry":{"coordinates":[1.432732,49.729564],"type":"Point"},"properties":{"osm_id":"8956715817","tag":{"amenity":"waste_basket","waste":"trash"}},"type":"Feature"},
	{"geometry":{"coordinates":[1.430128,49.727991],"type":"Point"},"properties":{"osm_id":"8956716046","tag":{"amenity":"waste_basket","waste":"trash"}},"type":"Feature"}
]
}
