{
"type": "FeatureCollection",
"lastupdate": "2020-08-05T00:00:00Z",
"features": [
	{"geometry":{"coordinates":[1.431272,49.73657],"type":"Point"},"properties":{"osm_id":"2151099659","tag":{"amenity":"recycling","recycling_type":"container"}},"type":"Feature"},
	{"geometry":{"coordinates":[1.433728,49.733863],"type":"Point"},"properties":{"name":"The name","osm_id":"2151099705","tag":{"amenity":"recycling","recycling:clothes":"yes","recycling:glass":"no","recycling:glass_bottles":"yes","recycling_type":"container"}},"type":"Feature"},
	{"geometry":{"coordinates":[1.433108,49.729285],"type":"Point"},"properties":{"osm_id":"2152037690","tag":{"amenity":"waste_basket"}},"type":"Feature"}
]
}
