{
"type": "FeatureCollection",
"features": [
	{"geometry":{"coordinates":[-116.995043,32.64033],"type":"Point"},"properties":{"name":"Strawberry Tree","osm_id":"5869712885","tag":{"natural":"tree"}},"type":"Feature"},
	{"geometry":{"coordinates":[-117.060563,32.630032],"type":"Point"},"properties":{"osm_id":"6780184038","tag":{"natural":"tree"}},"type":"Feature"},
	{"geometry":{"coordinates":[-117.060388,32.630062],"type":"Point"},"properties":{"osm_id":"6780184039","tag":{"natural":"tree"}},"type":"Feature"},
	{"geometry":{"coordinates":[-116.998101,32.639857],"type":"Point"},"properties":{"osm_id":"6780184072","tag":{"natural":"tree"}},"type":"Feature"},
	{"geometry":{"coordinates":[-117.032716,32.631905],"type":"Point"},"properties":{"osm_id":"7118284280","tag":{"natural":"tree"}},"type":"Feature"},
	{"geometry":{"coordinates":[-117.032647,32.631939],"type":"Point"},"properties":{"osm_id":"7118284281","tag":{"natural":"tree"}},"type":"Feature"},
	{"geometry":{"coordinates":[-117.03252,32.632033],"type":"Point"},"properties":{"osm_id":"7118284282","tag":{"natural":"tree"}},"type":"Feature"},
	{"geometry":{"coordinates":[-117.000646,32.679409],"type":"Point"},"properties":{"osm_id":"7557732109","tag":{"natural":"tree"}},"type":"Feature"},
	{"geometry":{"coordinates":[-117.000581,32.679127],"type":"Point"},"properties":{"osm_id":"7557732144","tag":{"natural":"tree"}},"type":"Feature"}
]
}
