{
"type": "FeatureCollection",
"features": [
	{"geometry":{"coordinates":[-116.995043,32.64033],"type":"Point"},"properties":{"name":"Strawberry Tree","osm_id":"5869712885","tag":{"natural":"tree"}},"type":"Feature"},
	{"geometry":{"coordinates":[-117.060563,32.630032],"type":"Point"},"properties":{"osm_id":"6780184038","tag":{"natural":"tree"}},"type":"Feature"},
	{"geometry":{"coordinates":[-117.060388,32.630063],"type":"Point"},"properties":{"osm_id":"6780184039","tag":{"natural":"tree"}},"type":"Feature"},
	{"geometry":{"coordinates":[-116.998101,32.639858],"type":"Point"},"properties":{"osm_id":"6780184072","tag":{"natural":"tree"}},"type":"Feature"},
	{"geometry":{"coordinates":[-117.032717,32.631906],"type":"Point"},"properties":{"osm_id":"7118284280","tag":{"natural":"tree"}},"type":"Feature"},
	{"geometry":{"coordinates":[-117.032648,32.63194],"type":"Point"},"properties":{"osm_id":"7118284281","tag":{"natural":"tree"}},"type":"Feature"},
	{"geometry":{"coordinates":[-117.032521,32.632033],"type":"Point"},"properties":{"osm_id":"7118284282","tag":{"natural":"tree"}},"type":"Feature"},
	{"geometry":{"coordinates":[-117.000647,32.67941],"type":"Point"},"properties":{"osm_id":"7557732109","tag":{"natural":"tree"}},"type":"Feature"},
	{"geometry":{"coordinates":[-117.000581,32.679127],"type":"Point"},"properties":{"osm_id":"7557732144","tag":{"natural":"tree"}},"type":"Feature"}
]
}
