{
"type": "FeatureCollection",
"lastupdate": "2020-08-05T00:00:00Z",
"features": [
	{"geometry":{"coordinates":[0.373067,43.321504],"type":"Point"},"properties":{"name":"Bouteilles/Verre","osm_id":"1889326350","tag":{"amenity":"recycling","location":"overground","recycling_type":"container"}},"type":"Feature"},
	{"geometry":{"coordinates":[0.361429,43.309655],"type":"Point"},"properties":{"barrier":"gate","osm_id":"2902264283","tag":{"bicycle":"no","foot":"no"}},"type":"Feature"}
]
}
