{
"type": "FeatureCollection",
"features": [
	{"geometry":{"coordinates":[12.216048,53.588559],"type":"Point"},"properties":{"name":"Lebensbaum","osm_id":"5029512021","tag":{"denotation":"natural_monument","leaf_cycle":"evergreen","leaf_type":"needleleaved","natural":"tree"}},"type":"Feature"}
]
}
