{
"type": "FeatureCollection",
"features": [
	{"geometry":{"coordinates":[12.198793,51.893491],"type":"Point"},"properties":{"name":"Friedenseiche","osm_id":"2688938242","tag":{"denotation":"natural_monument","genus:de":"Eiche","height":"10","image":"https://commons.wikimedia.org/wiki/File:Rodleben,_Friedenseiche.JPG","leaf_type":"broadleaved","natural":"tree"}},"type":"Feature"}
]
}
