{
"type": "FeatureCollection",
"features": [
	{"geometry":{"coordinates":[12.16159,50.752044],"type":"Point"},"properties":{"osm_id":"427827555","tag":{"genus":"Tilia","genus:de":"Linde","natural":"tree"}},"type":"Feature"},
	{"geometry":{"coordinates":[12.199768,50.74489],"type":"Point"},"properties":{"osm_id":"1777477184","tag":{"natural":"tree"}},"type":"Feature"},
	{"geometry":{"coordinates":[12.160326,50.760231],"type":"Point"},"properties":{"osm_id":"3575458307","tag":{"natural":"tree"}},"type":"Feature"},
	{"geometry":{"coordinates":[12.195527,50.790564],"type":"Point"},"properties":{"name":"Naturdenkmal Stieleiche am Ehrendenkmal","osm_id":"7680575848","tag":{"denotation":"natural_monument","leaf_cycle":"deciduous","leaf_type":"broadleaved","natural":"tree"}},"type":"Feature"},
	{"geometry":{"coordinates":[12.169711,50.744144],"type":"Point"},"properties":{"osm_id":"7776498211","tag":{"natural":"tree"}},"type":"Feature"}
]
}
