{
"type": "FeatureCollection",
"features": [
	{"geometry":{"coordinates":[12.171367,50.601175],"type":"Point"},"properties":{"name":"Baumreihe Bauernpflaumen","osm_id":"1900829149","tag":{"natural":"tree"}},"type":"Feature"},
	{"geometry":{"coordinates":[12.170869,50.609603],"type":"Point"},"properties":{"osm_id":"2412830901","tag":{"natural":"tree"}},"type":"Feature"},
	{"geometry":{"coordinates":[12.133957,50.613418],"type":"Point"},"properties":{"osm_id":"2662969423","tag":{"natural":"tree"}},"type":"Feature"},
	{"geometry":{"coordinates":[12.179032,50.61259],"type":"Point"},"properties":{"name":"Wildapfel in Schlehenhecke","osm_id":"5021592706","tag":{"natural":"tree"}},"type":"Feature"},
	{"geometry":{"coordinates":[12.168809,50.60601],"type":"Point"},"properties":{"osm_id":"5581503716","tag":{"leaf_type":"broadleaved","natural":"tree"}},"type":"Feature"},
	{"geometry":{"coordinates":[12.158453,50.605123],"type":"Point"},"properties":{"osm_id":"7394185603","tag":{"description":"Deutsche Eiche, passend zur Bismarck-Gedenktafel","leaf_cycle":"deciduous","leaf_type":"broadleaved","natural":"tree"}},"type":"Feature"},
	{"geometry":{"coordinates":[12.193,50.623305],"type":"Point"},"properties":{"osm_id":"7631681219","tag":{"natural":"tree"}},"type":"Feature"}
]
}
