{
"type": "FeatureCollection",
"features": [
	{"geometry":{"coordinates":[12.171368,50.601175],"type":"Point"},"properties":{"name":"Baumreihe Bauernpflaumen","osm_id":"1900829149","tag":{"natural":"tree"}},"type":"Feature"},
	{"geometry":{"coordinates":[12.170869,50.609603],"type":"Point"},"properties":{"osm_id":"2412830901","tag":{"natural":"tree"}},"type":"Feature"},
	{"geometry":{"coordinates":[12.133958,50.613418],"type":"Point"},"properties":{"osm_id":"2662969423","tag":{"natural":"tree"}},"type":"Feature"},
	{"geometry":{"coordinates":[12.179033,50.612591],"type":"Point"},"properties":{"name":"Wildapfel in Schlehenhecke","osm_id":"5021592706","tag":{"natural":"tree"}},"type":"Feature"},
	{"geometry":{"coordinates":[12.16881,50.60601],"type":"Point"},"properties":{"osm_id":"5581503716","tag":{"leaf_type":"broadleaved","natural":"tree"}},"type":"Feature"},
	{"geometry":{"coordinates":[12.158454,50.605123],"type":"Point"},"properties":{"osm_id":"7394185603","tag":{"description":"Deutsche Eiche, passend zur Bismarck-Gedenktafel","leaf_cycle":"deciduous","leaf_type":"broadleaved","natural":"tree"}},"type":"Feature"},
	{"geometry":{"coordinates":[12.193001,50.623306],"type":"Point"},"properties":{"osm_id":"7631681219","tag":{"natural":"tree"}},"type":"Feature"}
]
}
