{
"type": "FeatureCollection",
"lastupdate": "2020-08-04T00:00:00Z",
"features": [
	{"geometry":{"coordinates":[171.65245,-43.6353],"type":"Point"},"properties":{"name":"Methven Recyle Center","osm_id":"489328193","tag":{"amenity":"recycling"}},"type":"Feature"}
]
}
