{
"type": "FeatureCollection",
"features": [
	{"geometry":{"coordinates":[171.652451,-43.6353],"type":"Point"},"properties":{"name":"Methven Recyle Center","osm_id":"489328193","tag":{"amenity":"recycling"}},"type":"Feature"}
]
}
