{
"type": "FeatureCollection",
"features": [
	{"geometry":{"coordinates":[-78.593317,35.978882],"type":"Point"},"properties":{"name":"Wake County Convenience Center 8","osm_id":"6219562001","tag":{"amenity":"recycling","recycling_type":"centre"}},"type":"Feature"},
	{"geometry":{"coordinates":[-78.599374,35.960586],"type":"Point"},"properties":{"osm_id":"9054365515","tag":{"amenity":"waste_basket"}},"type":"Feature"}
]
}
