{
"type": "FeatureCollection",
"lastupdate": "2020-07-31T00:00:00Z",
"features": [
	{"geometry":{"coordinates":[-78.593317,35.978882],"type":"Point"},"properties":{"name":"Wake County Convenience Center 8","osm_id":"6219562001","tag":{"amenity":"recycling","recycling_type":"centre"}},"type":"Feature"}
]
}
