{
"type": "FeatureCollection",
"features": [
	{"geometry":{"coordinates":[-123.220908,39.006072],"type":"Point"},"properties":{"name":"Madrone","osm_id":"7766291151","tag":{"natural":"tree"}},"type":"Feature"}
]
}
