{
"type": "FeatureCollection",
"lastupdate": "2020-08-01T00:00:00Z",
"features": [
	{"geometry":{"coordinates":[20.774133,46.9274],"type":"Point"},"properties":{"osm_id":"3459957992","tag":{"amenity":"recycling","source:date":"2012-08-01","url":"http://turistautak.hu/poi.php?id=121469"}},"type":"Feature"},
	{"geometry":{"coordinates":[20.8231,46.92941],"type":"Point"},"properties":{"osm_id":"3459958203","tag":{"addr:street":"Kossuth Lajos utca","amenity":"recycling","recycling_type":"container","source:date":"2012-08-01","url":"http://turistautak.hu/poi.php?id=76912"}},"type":"Feature"},
	{"geometry":{"coordinates":[20.821681,46.930668],"type":"Point"},"properties":{"osm_id":"3459958212","tag":{"amenity":"recycling","recycling_type":"container","source:date":"2012-08-14","url":"http://turistautak.hu/poi.php?id=143168"}},"type":"Feature"},
	{"geometry":{"coordinates":[20.819798,46.93237],"type":"Point"},"properties":{"osm_id":"3459958226","tag":{"amenity":"recycling","source:date":"2013-10-31","url":"http://turistautak.hu/poi.php?id=161334"}},"type":"Feature"},
	{"geometry":{"coordinates":[20.78923,46.933285],"type":"Point"},"properties":{"osm_id":"3459958232","tag":{"amenity":"recycling","source:date":"2012-03-28","url":"http://turistautak.hu/poi.php?id=136328"}},"type":"Feature"},
	{"geometry":{"coordinates":[20.779967,46.93585],"type":"Point"},"properties":{"osm_id":"3459958255","tag":{"amenity":"recycling","source:date":"2012-08-01","url":"http://turistautak.hu/poi.php?id=137901"}},"type":"Feature"}
]
}
