{
"type": "FeatureCollection",
"features": [
	{"geometry":{"coordinates":[-2.941723,55.897989],"type":"Point"},"properties":{"name":"The Great Yew of Ormiston","osm_id":"1888319972","tag":{"denotation":"natural_monument","leaf_cycle":"evergreen","leaf_type":"needleleaved","natural":"tree","tourism":"attraction","website":"http://www.ancienttreeforum.co.uk/ancient-trees/ancient-tree-sites-to-visit/scotland/great-yew-of-ormiston/"}},"type":"Feature"},
	{"geometry":{"coordinates":[-2.978485,55.909691],"type":"Point"},"properties":{"osm_id":"5329999691","tag":{"natural":"tree"}},"type":"Feature"},
	{"geometry":{"coordinates":[-2.960773,55.909638],"type":"Point"},"properties":{"osm_id":"5723391537","tag":{"natural":"tree"}},"type":"Feature"},
	{"geometry":{"coordinates":[-2.962129,55.910696],"type":"Point"},"properties":{"osm_id":"5723391538","tag":{"natural":"tree"}},"type":"Feature"},
	{"geometry":{"coordinates":[-2.940415,55.897838],"type":"Point"},"properties":{"osm_id":"7966791956","tag":{"natural":"tree"}},"type":"Feature"}
]
}
