{
"type": "FeatureCollection",
"features": [
	{"geometry":{"coordinates":[-2.914527,48.427596],"type":"Point"},"properties":{"name":"Quercus","osm_id":"7220633586","tag":{"denotation":"remarquable","natural":"tree"}},"type":"Feature"}
]
}
