{
"type": "FeatureCollection",
"features": [
	{"geometry":{"coordinates":[-2.939494,37.477655],"type":"Point"},"properties":{"name":"Pino Grande","osm_id":"3078600796","tag":{"denotation":"natural_monument","monument":"yes","natural":"tree"}},"type":"Feature"}
]
}
