{
"type": "FeatureCollection",
"lastupdate": "2020-08-01T00:00:00Z",
"features": [
	{"geometry":{"coordinates":[-112.810623,31.939763],"type":"Point"},"properties":{"osm_id":"4705776567","tag":{"amenity":"waste_basket"}},"type":"Feature"},
	{"geometry":{"coordinates":[-112.809572,31.941469],"type":"Point"},"properties":{"name":"dog waste station","osm_id":"4705776699","tag":{"amenity":"waste_basket"}},"type":"Feature"},
	{"geometry":{"coordinates":[-112.811233,31.939232],"type":"Point"},"properties":{"osm_id":"4705776710","tag":{"amenity":"waste_basket"}},"type":"Feature"},
	{"geometry":{"coordinates":[-112.810983,31.938714],"type":"Point"},"properties":{"name":"dog waste station","osm_id":"4706956617","tag":{"amenity":"waste_basket"}},"type":"Feature"},
	{"geometry":{"coordinates":[-112.811845,31.939751],"type":"Point"},"properties":{"osm_id":"4706956619","tag":{"amenity":"waste_basket"}},"type":"Feature"}
]
}
