{
"type": "FeatureCollection",
"features": [
	{"geometry":{"coordinates":[-112.810624,31.939763],"type":"Point"},"properties":{"osm_id":"4705776567","tag":{"amenity":"waste_basket"}},"type":"Feature"},
	{"geometry":{"coordinates":[-112.809573,31.941469],"type":"Point"},"properties":{"name":"dog waste station","osm_id":"4705776699","tag":{"amenity":"waste_basket"}},"type":"Feature"},
	{"geometry":{"coordinates":[-112.811234,31.939232],"type":"Point"},"properties":{"osm_id":"4705776710","tag":{"amenity":"waste_basket"}},"type":"Feature"},
	{"geometry":{"coordinates":[-112.810984,31.938715],"type":"Point"},"properties":{"name":"dog waste station","osm_id":"4706956617","tag":{"amenity":"waste_basket"}},"type":"Feature"},
	{"geometry":{"coordinates":[-112.811845,31.939752],"type":"Point"},"properties":{"osm_id":"4706956619","tag":{"amenity":"waste_basket"}},"type":"Feature"}
]
}
