{
"type": "FeatureCollection",
"features": [
	{"geometry":{"coordinates":[13.614995,54.572938],"type":"Point"},"properties":{"name":"Wildkirschen Und Hollunder","osm_id":"1257961084","tag":{"natural":"tree"}},"type":"Feature"}
]
}
