{
"type": "FeatureCollection",
"features": [
	{"geometry":{"coordinates":[13.542904,54.389096],"type":"Point"},"properties":{"osm_id":"2284972492","tag":{"natural":"tree"}},"type":"Feature"},
	{"geometry":{"coordinates":[13.598436,54.391215],"type":"Point"},"properties":{"name":"Max-Dreyer-Buche","osm_id":"2804018568","tag":{"natural":"tree"}},"type":"Feature"},
	{"geometry":{"coordinates":[13.609526,54.399224],"type":"Point"},"properties":{"osm_id":"8878231126","tag":{"leaf_cycle":"deciduous","leaf_type":"broadleaved","natural":"tree"}},"type":"Feature"},
	{"geometry":{"coordinates":[13.609574,54.399406],"type":"Point"},"properties":{"osm_id":"8878231127","tag":{"leaf_cycle":"deciduous","leaf_type":"broadleaved","natural":"tree"}},"type":"Feature"}
]
}
