{
"type": "FeatureCollection",
"features": [
	{"geometry":{"coordinates":[13.542905,54.389097],"type":"Point"},"properties":{"osm_id":"2284972492","tag":{"natural":"tree"}},"type":"Feature"},
	{"geometry":{"coordinates":[13.598437,54.391215],"type":"Point"},"properties":{"name":"Max-Dreyer-Buche","osm_id":"2804018568","tag":{"natural":"tree"}},"type":"Feature"}
]
}
