{
"type": "FeatureCollection",
"features": [
	{"geometry":{"coordinates":[13.619397,41.648376],"type":"Point"},"properties":{"name":"Ulivo con scorcio sulla Torre Medievale","osm_id":"4393460691","tag":{"natural":"tree"}},"type":"Feature"}
]
}
