{
"type": "FeatureCollection",
"lastupdate": "2020-08-02T00:00:00Z",
"features": [
	{"geometry":{"coordinates":[-81.3261,48.476419],"type":"Point"},"properties":{"name":"Outdoor Sharps Disposal Bin","osm_id":"6921632508","tag":{"amenity":"waste_basket","waste":"trash"}},"type":"Feature"}
]
}
