{
"type": "FeatureCollection",
"features": [
	{"geometry":{"coordinates":[-81.326101,48.476419],"type":"Point"},"properties":{"name":"Outdoor Sharps Disposal Bin","osm_id":"6921632508","tag":{"amenity":"waste_basket","waste":"trash"}},"type":"Feature"}
]
}
