{
"type": "FeatureCollection",
"features": [
	{"geometry":{"coordinates":[88.287192,22.560935],"type":"Point"},"properties":{"name":"The Great Banyan Tree","osm_id":"663942601","tag":{"natural":"tree"}},"type":"Feature"}
]
}
