{
"type": "FeatureCollection",
"features": [
	{"geometry":{"coordinates":[88.287193,22.560936],"type":"Point"},"properties":{"name":"The Great Banyan Tree","osm_id":"663942601","tag":{"natural":"tree"}},"type":"Feature"}
]
}
