{
"type": "FeatureCollection",
"features": [
	{"geometry":{"coordinates":[18.975094,53.142971],"type":"Point"},"properties":{"osm_id":"4706662837","tag":{"denotation":"natural_monument","natural":"tree","ref:CRFOP":"PL.ZIPOP.1393.PP.0405032.612","ref:INSPIRE":"PL.ZIPOP.1393.PP.0405032.612","website":"http://crfop.gdos.gov.pl/CRFOP/widok/viewfop.jsf?fop=PL.ZIPOP.1393.PP.0405032.612"}},"type":"Feature"},
	{"geometry":{"coordinates":[18.981032,53.164351],"type":"Point"},"properties":{"osm_id":"4706691037","tag":{"denotation":"natural_monument","natural":"tree","ref:CRFOP":"PL.ZIPOP.1393.PP.0405043.997","ref:INSPIRE":"PL.ZIPOP.1393.PP.0405043.997","website":"http://crfop.gdos.gov.pl/CRFOP/widok/viewfop.jsf?fop=PL.ZIPOP.1393.PP.0405043.997"}},"type":"Feature"},
	{"geometry":{"coordinates":[18.981207,53.16458],"type":"Point"},"properties":{"osm_id":"4706691038","tag":{"denotation":"natural_monument","natural":"tree","ref:CRFOP":"PL.ZIPOP.1393.PP.0405043.997","ref:INSPIRE":"PL.ZIPOP.1393.PP.0405043.997","website":"http://crfop.gdos.gov.pl/CRFOP/widok/viewfop.jsf?fop=PL.ZIPOP.1393.PP.0405043.997"}},"type":"Feature"},
	{"geometry":{"coordinates":[18.981401,53.164517],"type":"Point"},"properties":{"osm_id":"4706691039","tag":{"denotation":"natural_monument","natural":"tree","ref:CRFOP":"PL.ZIPOP.1393.PP.0405043.997","ref:INSPIRE":"PL.ZIPOP.1393.PP.0405043.997","website":"http://crfop.gdos.gov.pl/CRFOP/widok/viewfop.jsf?fop=PL.ZIPOP.1393.PP.0405043.997"}},"type":"Feature"},
	{"geometry":{"coordinates":[18.981263,53.164441],"type":"Point"},"properties":{"osm_id":"4706691040","tag":{"denotation":"natural_monument","natural":"tree","ref:CRFOP":"PL.ZIPOP.1393.PP.0405043.997","ref:INSPIRE":"PL.ZIPOP.1393.PP.0405043.997","website":"http://crfop.gdos.gov.pl/CRFOP/widok/viewfop.jsf?fop=PL.ZIPOP.1393.PP.0405043.997"}},"type":"Feature"},
	{"geometry":{"coordinates":[18.981419,53.16443],"type":"Point"},"properties":{"osm_id":"4706691041","tag":{"denotation":"natural_monument","natural":"tree","ref:CRFOP":"PL.ZIPOP.1393.PP.0405043.997","ref:INSPIRE":"PL.ZIPOP.1393.PP.0405043.997","website":"http://crfop.gdos.gov.pl/CRFOP/widok/viewfop.jsf?fop=PL.ZIPOP.1393.PP.0405043.997"}},"type":"Feature"},
	{"geometry":{"coordinates":[18.98131,53.164334],"type":"Point"},"properties":{"osm_id":"4706691042","tag":{"denotation":"natural_monument","natural":"tree","ref:CRFOP":"PL.ZIPOP.1393.PP.0405043.997","ref:INSPIRE":"PL.ZIPOP.1393.PP.0405043.997","website":"http://crfop.gdos.gov.pl/CRFOP/widok/viewfop.jsf?fop=PL.ZIPOP.1393.PP.0405043.997"}},"type":"Feature"},
	{"geometry":{"coordinates":[18.981315,53.164206],"type":"Point"},"properties":{"osm_id":"4706691043","tag":{"denotation":"natural_monument","natural":"tree","ref:CRFOP":"PL.ZIPOP.1393.PP.0405043.997","ref:INSPIRE":"PL.ZIPOP.1393.PP.0405043.997","website":"http://crfop.gdos.gov.pl/CRFOP/widok/viewfop.jsf?fop=PL.ZIPOP.1393.PP.0405043.997"}},"type":"Feature"},
	{"geometry":{"coordinates":[18.950224,53.170663],"type":"Point"},"properties":{"osm_id":"4706691053","tag":{"denotation":"natural_monument","natural":"tree","ref:CRFOP":"PL.ZIPOP.1393.PP.0405043.1000","ref:INSPIRE":"PL.ZIPOP.1393.PP.0405043.1000","website":"http://crfop.gdos.gov.pl/CRFOP/widok/viewfop.jsf?fop=PL.ZIPOP.1393.PP.0405043.1000"}},"type":"Feature"},
	{"geometry":{"coordinates":[18.96261,53.130663],"type":"Point"},"properties":{"osm_id":"4706691073","tag":{"denotation":"natural_monument","natural":"tree","ref:CRFOP":"PL.ZIPOP.1393.PP.0405032.593","ref:INSPIRE":"PL.ZIPOP.1393.PP.0405032.593","website":"http://crfop.gdos.gov.pl/CRFOP/widok/viewfop.jsf?fop=PL.ZIPOP.1393.PP.0405032.593"}},"type":"Feature"}
]
}
