{
"type": "FeatureCollection",
"features": [
	{"geometry":{"coordinates":[34.361137,-1.579423],"type":"Point"},"properties":{"name":"Dispensary Dustbin","osm_id":"4983693633","tag":{"amenity":"waste_basket","name:en":"Dispensary Dustbin","name:sw":"Sehemu ya Kutupa Uchafu"}},"type":"Feature"}
]
}
