{
"type": "FeatureCollection",
"lastupdate": "2020-07-31T00:00:00Z",
"features": [
	{"geometry":{"coordinates":[34.361136,-1.579422],"type":"Point"},"properties":{"name":"Dispensary Dustbin","osm_id":"4983693633","tag":{"amenity":"waste_basket","name:en":"Dispensary Dustbin","name:sw":"Sehemu ya Kutupa Uchafu"}},"type":"Feature"}
]
}
