{
"type": "FeatureCollection",
"lastupdate": "2020-07-31T00:00:00Z",
"features": [
	{"geometry":{"coordinates":[-119.299777,34.426347],"type":"Point"},"properties":{"name":"Ojai Valley Organics \"Recycling Center\" (composting)","osm_id":"5735515815","tag":{"amenity":"recycling","recycling_type":"centre"}},"type":"Feature"}
]
}
