{
"type": "FeatureCollection",
"features": [
	{"geometry":{"coordinates":[14.497217,53.422648],"type":"Point"},"properties":{"osm_id":"297681469","tag":{"amenity":"recycling"}},"type":"Feature"},
	{"geometry":{"coordinates":[14.439527,53.431732],"type":"Point"},"properties":{"osm_id":"494590635","tag":{"amenity":"recycling"}},"type":"Feature"},
	{"geometry":{"coordinates":[14.459279,53.434728],"type":"Point"},"properties":{"osm_id":"497121838","tag":{"amenity":"recycling"}},"type":"Feature"},
	{"geometry":{"coordinates":[14.501621,53.430703],"type":"Point"},"properties":{"osm_id":"538094251","tag":{"amenity":"recycling"}},"type":"Feature"},
	{"geometry":{"coordinates":[14.482603,53.425585],"type":"Point"},"properties":{"osm_id":"1296996978","tag":{"amenity":"recycling"}},"type":"Feature"},
	{"geometry":{"coordinates":[14.483664,53.425481],"type":"Point"},"properties":{"osm_id":"1296996993","tag":{"amenity":"recycling"}},"type":"Feature"},
	{"geometry":{"coordinates":[14.464691,53.384714],"type":"Point"},"properties":{"osm_id":"1622824939","tag":{"amenity":"recycling"}},"type":"Feature"},
	{"geometry":{"coordinates":[14.430314,53.413523],"type":"Point"},"properties":{"osm_id":"1875634505","tag":{"amenity":"recycling"}},"type":"Feature"},
	{"geometry":{"coordinates":[14.499047,53.435054],"type":"Point"},"properties":{"osm_id":"2027749509","tag":{"amenity":"recycling","recycling:clothes":"yes","recycling:paper":"yes","recycling:plastic":"yes","recycling_type":"container"}},"type":"Feature"},
	{"geometry":{"coordinates":[14.477135,53.389442],"type":"Point"},"properties":{"osm_id":"2675876140","tag":{"amenity":"waste_basket"}},"type":"Feature"},
	{"geometry":{"coordinates":[14.477966,53.389257],"type":"Point"},"properties":{"osm_id":"2675876150","tag":{"amenity":"waste_basket"}},"type":"Feature"},
	{"geometry":{"coordinates":[14.477557,53.38913],"type":"Point"},"properties":{"osm_id":"2675876153","tag":{"amenity":"waste_basket"}},"type":"Feature"},
	{"geometry":{"coordinates":[14.476467,53.389564],"type":"Point"},"properties":{"osm_id":"2675876155","tag":{"amenity":"waste_basket"}},"type":"Feature"},
	{"geometry":{"coordinates":[14.478158,53.389696],"type":"Point"},"properties":{"osm_id":"2675876156","tag":{"amenity":"waste_basket"}},"type":"Feature"},
	{"geometry":{"coordinates":[14.479486,53.388244],"type":"Point"},"properties":{"osm_id":"2675876157","tag":{"amenity":"waste_basket"}},"type":"Feature"},
	{"geometry":{"coordinates":[14.479207,53.38854],"type":"Point"},"properties":{"osm_id":"2675876158","tag":{"amenity":"waste_basket"}},"type":"Feature"},
	{"geometry":{"coordinates":[14.477654,53.389826],"type":"Point"},"properties":{"osm_id":"2773894373","tag":{"amenity":"waste_basket"}},"type":"Feature"},
	{"geometry":{"coordinates":[14.497058,53.400386],"type":"Point"},"properties":{"osm_id":"2856789537","tag":{"amenity":"recycling","recycling:glass":"yes","recycling:paper":"yes","recycling:plastic":"yes","recycling_type":"container"}},"type":"Feature"},
	{"geometry":{"coordinates":[14.497875,53.40109],"type":"Point"},"properties":{"osm_id":"2856789538","tag":{"amenity":"recycling","recycling:glass":"yes","recycling:paper":"yes","recycling:plastic":"yes","recycling_type":"container"}},"type":"Feature"},
	{"geometry":{"coordinates":[14.498608,53.401741],"type":"Point"},"properties":{"osm_id":"2856789539","tag":{"amenity":"recycling","recycling:glass":"yes","recycling:paper":"yes","recycling:plastic":"yes","recycling_type":"container"}},"type":"Feature"},
	{"geometry":{"coordinates":[14.494438,53.394161],"type":"Point"},"properties":{"osm_id":"5330168424","tag":{"amenity":"waste_disposal"}},"type":"Feature"},
	{"geometry":{"coordinates":[14.492576,53.394009],"type":"Point"},"properties":{"osm_id":"5330168435","tag":{"amenity":"waste_disposal"}},"type":"Feature"},
	{"geometry":{"coordinates":[14.493525,53.396186],"type":"Point"},"properties":{"osm_id":"6257560757","tag":{"amenity":"recycling","recycling:glass":"yes","recycling:paper":"yes","recycling:plastic":"yes","recycling_type":"container"}},"type":"Feature"},
	{"geometry":{"coordinates":[14.457686,53.433257],"type":"Point"},"properties":{"name":"Recykling","osm_id":"6696410499","tag":{"amenity":"recycling"}},"type":"Feature"},
	{"geometry":{"coordinates":[14.498534,53.414902],"type":"Point"},"properties":{"barrier":"gate","osm_id":"6799811040"},"type":"Feature"}
]
}
