{
"type": "FeatureCollection",
"features": [
	{"geometry":{"coordinates":[14.497218,53.422648],"type":"Point"},"properties":{"osm_id":"297681469","tag":{"amenity":"recycling"}},"type":"Feature"},
	{"geometry":{"coordinates":[14.439527,53.431732],"type":"Point"},"properties":{"osm_id":"494590635","tag":{"amenity":"recycling"}},"type":"Feature"},
	{"geometry":{"coordinates":[14.459279,53.434729],"type":"Point"},"properties":{"osm_id":"497121838","tag":{"amenity":"recycling"}},"type":"Feature"},
	{"geometry":{"coordinates":[14.501622,53.430703],"type":"Point"},"properties":{"osm_id":"538094251","tag":{"amenity":"recycling"}},"type":"Feature"},
	{"geometry":{"coordinates":[14.482604,53.425586],"type":"Point"},"properties":{"osm_id":"1296996978","tag":{"amenity":"recycling"}},"type":"Feature"},
	{"geometry":{"coordinates":[14.483665,53.425481],"type":"Point"},"properties":{"osm_id":"1296996993","tag":{"amenity":"recycling"}},"type":"Feature"},
	{"geometry":{"coordinates":[14.464691,53.384715],"type":"Point"},"properties":{"osm_id":"1622824939","tag":{"amenity":"recycling"}},"type":"Feature"},
	{"geometry":{"coordinates":[14.430314,53.413524],"type":"Point"},"properties":{"osm_id":"1875634505","tag":{"amenity":"recycling"}},"type":"Feature"},
	{"geometry":{"coordinates":[14.499047,53.435054],"type":"Point"},"properties":{"osm_id":"2027749509","tag":{"amenity":"recycling","recycling:clothes":"yes","recycling:paper":"yes","recycling:plastic":"yes","recycling_type":"container"}},"type":"Feature"},
	{"geometry":{"coordinates":[14.477136,53.389442],"type":"Point"},"properties":{"osm_id":"2675876140","tag":{"amenity":"waste_basket"}},"type":"Feature"},
	{"geometry":{"coordinates":[14.477966,53.389258],"type":"Point"},"properties":{"osm_id":"2675876150","tag":{"amenity":"waste_basket"}},"type":"Feature"},
	{"geometry":{"coordinates":[14.477558,53.389131],"type":"Point"},"properties":{"osm_id":"2675876153","tag":{"amenity":"waste_basket"}},"type":"Feature"},
	{"geometry":{"coordinates":[14.476468,53.389564],"type":"Point"},"properties":{"osm_id":"2675876155","tag":{"amenity":"waste_basket"}},"type":"Feature"},
	{"geometry":{"coordinates":[14.478158,53.389697],"type":"Point"},"properties":{"osm_id":"2675876156","tag":{"amenity":"waste_basket"}},"type":"Feature"},
	{"geometry":{"coordinates":[14.479487,53.388244],"type":"Point"},"properties":{"osm_id":"2675876157","tag":{"amenity":"waste_basket"}},"type":"Feature"},
	{"geometry":{"coordinates":[14.479208,53.388541],"type":"Point"},"properties":{"osm_id":"2675876158","tag":{"amenity":"waste_basket"}},"type":"Feature"},
	{"geometry":{"coordinates":[14.477654,53.389827],"type":"Point"},"properties":{"osm_id":"2773894373","tag":{"amenity":"waste_basket"}},"type":"Feature"},
	{"geometry":{"coordinates":[14.497058,53.400386],"type":"Point"},"properties":{"osm_id":"2856789537","tag":{"amenity":"recycling","recycling:glass":"yes","recycling:paper":"yes","recycling:plastic":"yes","recycling_type":"container"}},"type":"Feature"},
	{"geometry":{"coordinates":[14.497876,53.401091],"type":"Point"},"properties":{"osm_id":"2856789538","tag":{"amenity":"recycling","recycling:glass":"yes","recycling:paper":"yes","recycling:plastic":"yes","recycling_type":"container"}},"type":"Feature"},
	{"geometry":{"coordinates":[14.498608,53.401742],"type":"Point"},"properties":{"osm_id":"2856789539","tag":{"amenity":"recycling","recycling:glass":"yes","recycling:paper":"yes","recycling:plastic":"yes","recycling_type":"container"}},"type":"Feature"},
	{"geometry":{"coordinates":[14.494439,53.394161],"type":"Point"},"properties":{"osm_id":"5330168424","tag":{"amenity":"waste_disposal"}},"type":"Feature"},
	{"geometry":{"coordinates":[14.492576,53.394009],"type":"Point"},"properties":{"osm_id":"5330168435","tag":{"amenity":"waste_disposal"}},"type":"Feature"},
	{"geometry":{"coordinates":[14.493526,53.396186],"type":"Point"},"properties":{"osm_id":"6257560757","tag":{"amenity":"recycling","recycling:glass":"yes","recycling:paper":"yes","recycling:plastic":"yes","recycling_type":"container"}},"type":"Feature"},
	{"geometry":{"coordinates":[14.457687,53.433258],"type":"Point"},"properties":{"name":"Recykling","osm_id":"6696410499","tag":{"amenity":"recycling"}},"type":"Feature"},
	{"geometry":{"coordinates":[14.498535,53.414902],"type":"Point"},"properties":{"barrier":"gate","osm_id":"6799811040"},"type":"Feature"}
]
}
