{
"type": "FeatureCollection",
"lastupdate": "2020-08-02T00:00:00Z",
"features": [
	{"geometry":{"coordinates":[14.438165,53.371726],"type":"Point"},"properties":{"osm_id":"1891390244","tag":{"amenity":"recycling"}},"type":"Feature"},
	{"geometry":{"coordinates":[14.44031,53.356957],"type":"Point"},"properties":{"osm_id":"2274359436","tag":{"amenity":"recycling"}},"type":"Feature"},
	{"geometry":{"coordinates":[14.439478,53.338095],"type":"Point"},"properties":{"osm_id":"2309795476","tag":{"amenity":"recycling","recycling:glass":"yes","recycling:paper":"yes","recycling:plastic":"yes"}},"type":"Feature"},
	{"geometry":{"coordinates":[14.477244,53.374945],"type":"Point"},"properties":{"name":"Stena","osm_id":"4286296896","tag":{"amenity":"recycling"}},"type":"Feature"}
]
}
