{
"type": "FeatureCollection",
"features": [
	{"geometry":{"coordinates":[14.416352,51.189688],"type":"Point"},"properties":{"osm_id":"296926656","tag":{"amenity":"recycling","recycling:glass":"yes"}},"type":"Feature"},
	{"geometry":{"coordinates":[14.452459,51.19521],"type":"Point"},"properties":{"osm_id":"296948729","tag":{"amenity":"recycling","recycling:glass_bottles":"yes","recycling_type":"container"}},"type":"Feature"},
	{"geometry":{"coordinates":[14.428993,51.186867],"type":"Point"},"properties":{"osm_id":"327175998","tag":{"amenity":"recycling","recycling_type":"container"}},"type":"Feature"},
	{"geometry":{"coordinates":[14.437011,51.190129],"type":"Point"},"properties":{"osm_id":"327176288","tag":{"amenity":"recycling","location":"overground","recycling_type":"container"}},"type":"Feature"},
	{"geometry":{"coordinates":[14.439581,51.186533],"type":"Point"},"properties":{"osm_id":"327215535","tag":{"amenity":"recycling","recycling_type":"container"}},"type":"Feature"},
	{"geometry":{"coordinates":[14.439543,51.189115],"type":"Point"},"properties":{"osm_id":"327215666","tag":{"amenity":"recycling","recycling_type":"container"}},"type":"Feature"},
	{"geometry":{"coordinates":[14.4413,51.191044],"type":"Point"},"properties":{"osm_id":"327215782","tag":{"amenity":"recycling","recycling:glass_bottles":"yes","recycling:paper":"yes","recycling_type":"container"}},"type":"Feature"},
	{"geometry":{"coordinates":[14.441117,51.194521],"type":"Point"},"properties":{"osm_id":"327222076","tag":{"amenity":"recycling","recycling_type":"container"}},"type":"Feature"},
	{"geometry":{"coordinates":[14.4388,51.19329],"type":"Point"},"properties":{"osm_id":"327235503","tag":{"amenity":"recycling","recycling_type":"container"}},"type":"Feature"},
	{"geometry":{"coordinates":[14.434813,51.188136],"type":"Point"},"properties":{"osm_id":"493929486","tag":{"amenity":"recycling","recycling:clothes":"yes","recycling:glass_bottles":"yes","recycling:paper":"yes","recycling_type":"container"}},"type":"Feature"},
	{"geometry":{"coordinates":[14.423459,51.180076],"type":"Point"},"properties":{"osm_id":"493929536","tag":{"amenity":"recycling","location":"overground","recycling:clothes":"yes","recycling:glass_bottles":"yes","recycling:paper":"yes","recycling_type":"container"}},"type":"Feature"},
	{"geometry":{"coordinates":[14.475481,51.194215],"type":"Point"},"properties":{"osm_id":"1323800640","tag":{"amenity":"recycling","recycling_type":"container"}},"type":"Feature"},
	{"geometry":{"coordinates":[14.426772,51.183128],"type":"Point"},"properties":{"osm_id":"1765177921","tag":{"amenity":"recycling","location":"overground","recycling:glass_bottles":"yes","recycling:paper":"yes","recycling_type":"container"}},"type":"Feature"},
	{"geometry":{"coordinates":[14.433383,51.181497],"type":"Point"},"properties":{"osm_id":"2727069340","tag":{"amenity":"recycling","recycling:clothes":"yes","recycling:glass_bottles":"yes","recycling:paper":"yes","recycling_type":"container"}},"type":"Feature"},
	{"geometry":{"coordinates":[14.419074,51.194624],"type":"Point"},"properties":{"osm_id":"4308352079","tag":{"amenity":"recycling","recycling_type":"container"}},"type":"Feature"},
	{"geometry":{"coordinates":[14.479739,51.224907],"type":"Point"},"properties":{"osm_id":"5341681325","tag":{"amenity":"waste_basket","waste":"trash"}},"type":"Feature"}
]
}
