{
"type": "FeatureCollection",
"lastupdate": "2020-08-01T00:00:00Z",
"features": [
	{"geometry":{"coordinates":[14.464134,48.152602],"type":"Point"},"properties":{"name":"Alstoffsammelzentrum","osm_id":"1397641544","tag":{"amenity":"recycling","recycling:wood":"yes","recycling_type":"centre"}},"type":"Feature"},
	{"geometry":{"coordinates":[14.467292,48.14199],"type":"Point"},"properties":{"osm_id":"2638818712","tag":{"amenity":"recycling","recycling:clothes":"yes","recycling:glass":"yes","recycling:paper":"yes"}},"type":"Feature"},
	{"geometry":{"coordinates":[14.464836,48.152512],"type":"Point"},"properties":{"osm_id":"2638819229","tag":{"amenity":"recycling","recycling:clothes":"yes"}},"type":"Feature"}
]
}
