{
"type": "FeatureCollection",
"features": [
	{"geometry":{"coordinates":[14.413419,46.14042],"type":"Point"},"properties":{"osm_id":"8818876808","tag":{"amenity":"waste_basket"}},"type":"Feature"},
	{"geometry":{"coordinates":[14.413614,46.140478],"type":"Point"},"properties":{"osm_id":"8818920204","tag":{"amenity":"waste_basket"}},"type":"Feature"},
	{"geometry":{"coordinates":[14.413771,46.140145],"type":"Point"},"properties":{"osm_id":"8818939137","tag":{"amenity":"waste_basket"}},"type":"Feature"},
	{"geometry":{"coordinates":[14.361291,46.150065],"type":"Point"},"properties":{"name":"Zbirni center Draga","osm_id":"8978147068","tag":{"amenity":"recycling"}},"type":"Feature"}
]
}
