{
"type": "FeatureCollection",
"lastupdate": "2020-08-05T00:00:00Z",
"features": [
	{"geometry":{"coordinates":[-1.764057,51.338729],"type":"Point"},"properties":{"name":"Co-op bring bank","osm_id":"845343207","tag":{"amenity":"recycling","recycling:cans":"yes","recycling:clothes":"yes","recycling:foil":"yes","recycling:glass_bottles":"yes","recycling:newspaper":"yes","recycling:paper":"yes","recycling:shoes":"yes"}},"type":"Feature"}
]
}
