{
"type": "FeatureCollection",
"lastupdate": "2020-07-31T00:00:00Z",
"features": [
	{"geometry":{"coordinates":[-1.819038,50.72671],"type":"Point"},"properties":{"osm_id":"825716389","tag":{"amenity":"recycling"}},"type":"Feature"},
	{"geometry":{"coordinates":[-1.780039,50.736039],"type":"Point"},"properties":{"name":"Pitsite car park","osm_id":"2017018188","tag":{"amenity":"recycling","recycling:cans":"yes","recycling:cardboard":"yes","recycling:cartons":"yes","recycling:clothes":"yes","recycling:foil":"yes","recycling:glass_bottles":"yes","recycling:newspaper":"yes","recycling:paper":"yes","recycling:plastic_bottles":"yes","recycling:shoes":"yes"}},"type":"Feature"}
]
}
