{
"type": "FeatureCollection",
"features": [
	{"geometry":{"coordinates":[-1.819038,50.72671],"type":"Point"},"properties":{"osm_id":"825716389","tag":{"amenity":"recycling","location":"overground","recycling_type":"container"}},"type":"Feature"},
	{"geometry":{"coordinates":[-1.780039,50.736039],"type":"Point"},"properties":{"name":"Pitsite car park","osm_id":"2017018188","tag":{"amenity":"recycling","recycling:cans":"yes","recycling:cardboard":"yes","recycling:cartons":"yes","recycling:clothes":"yes","recycling:foil":"yes","recycling:glass_bottles":"yes","recycling:newspaper":"yes","recycling:paper":"yes","recycling:plastic_bottles":"yes","recycling:shoes":"yes"}},"type":"Feature"},
	{"geometry":{"coordinates":[-1.837762,50.728059],"type":"Point"},"properties":{"osm_id":"8710482718","tag":{"amenity":"waste_basket","waste":"cigarettes;trash"}},"type":"Feature"},
	{"geometry":{"coordinates":[-1.838135,50.728078],"type":"Point"},"properties":{"osm_id":"8710482723","tag":{"amenity":"waste_basket","waste":"cigarettes;trash"}},"type":"Feature"}
]
}
