{
"type": "FeatureCollection",
"features": [
	{"geometry":{"coordinates":[-1.763496,47.473812],"type":"Point"},"properties":{"osm_id":"596455677","tag":{"amenity":"waste_basket"}},"type":"Feature"},
	{"geometry":{"coordinates":[-1.763199,47.473717],"type":"Point"},"properties":{"osm_id":"596455681","tag":{"amenity":"waste_basket"}},"type":"Feature"},
	{"geometry":{"coordinates":[-1.763968,47.475648],"type":"Point"},"properties":{"osm_id":"597704467","tag":{"amenity":"waste_basket","check_date":"2021-09-29"}},"type":"Feature"},
	{"geometry":{"coordinates":[-1.765975,47.476499],"type":"Point"},"properties":{"osm_id":"598098018","tag":{"amenity":"recycling","recycling:glass_bottles":"yes","recycling_type":"container"}},"type":"Feature"},
	{"geometry":{"coordinates":[-1.762124,47.473944],"type":"Point"},"properties":{"osm_id":"1693266038","tag":{"amenity":"waste_basket"}},"type":"Feature"},
	{"geometry":{"coordinates":[-1.760802,47.474527],"type":"Point"},"properties":{"name":"PAV jollan de clerville","osm_id":"1694291579","tag":{"amenity":"recycling","recycling:cartons":"no","recycling:magazines":"yes","recycling:newspaper":"yes","recycling:paper":"yes","recycling:paper_packaging":"yes","recycling:plastic":"yes","recycling:plastic_bottles":"yes","recycling_type":"container"}},"type":"Feature"},
	{"geometry":{"coordinates":[-1.760522,47.472043],"type":"Point"},"properties":{"osm_id":"1711533433","tag":{"amenity":"recycling","recycling:glass_bottles":"yes","recycling:paper":"yes","recycling_type":"container"}},"type":"Feature"},
	{"geometry":{"coordinates":[-1.7667,47.481478],"type":"Point"},"properties":{"osm_id":"1731730149","tag":{"amenity":"recycling","recycling:glass_bottles":"yes","recycling:paper":"yes","recycling_type":"container"}},"type":"Feature"},
	{"geometry":{"coordinates":[-1.768853,47.478013],"type":"Point"},"properties":{"osm_id":"1733047587","tag":{"amenity":"recycling","recycling:clothes":"yes","recycling:glass_bottles":"yes","recycling_type":"container"}},"type":"Feature"},
	{"geometry":{"coordinates":[-1.772548,47.478829],"type":"Point"},"properties":{"osm_id":"1733047593","tag":{"amenity":"recycling","recycling:glass_bottles":"yes","recycling:paper":"yes","recycling_type":"container"}},"type":"Feature"},
	{"geometry":{"coordinates":[-1.765912,47.483639],"type":"Point"},"properties":{"osm_id":"1733048185","tag":{"amenity":"recycling","recycling:cans":"yes","recycling:glass_bottles":"yes","recycling:paper":"yes","recycling_type":"container"}},"type":"Feature"},
	{"geometry":{"coordinates":[-1.769056,47.471511],"type":"Point"},"properties":{"osm_id":"6848274569","tag":{"amenity":"waste_basket"}},"type":"Feature"},
	{"geometry":{"coordinates":[-1.78158,47.471234],"type":"Point"},"properties":{"osm_id":"8780585270","tag":{"amenity":"waste_basket","material":"steel"}},"type":"Feature"},
	{"geometry":{"coordinates":[-1.763909,47.468995],"type":"Point"},"properties":{"osm_id":"8892435186","tag":{"amenity":"waste_basket"}},"type":"Feature"},
	{"geometry":{"coordinates":[-1.762527,47.48123],"type":"Point"},"properties":{"osm_id":"8892693978","tag":{"amenity":"waste_basket"}},"type":"Feature"},
	{"geometry":{"coordinates":[-1.762666,47.481121],"type":"Point"},"properties":{"osm_id":"8892693979","tag":{"amenity":"waste_basket"}},"type":"Feature"},
	{"geometry":{"coordinates":[-1.762564,47.481156],"type":"Point"},"properties":{"osm_id":"8892693980","tag":{"amenity":"waste_basket"}},"type":"Feature"}
]
}
