{
"type": "FeatureCollection",
"features": [
	{"geometry":{"coordinates":[22.707274,49.388964],"type":"Point"},"properties":{"name":"Pomnik przyrody","osm_id":"4024572234","tag":{"denotation":"natural_monument","monument":"yes","natural":"tree","protected":"yes"}},"type":"Feature"},
	{"geometry":{"coordinates":[22.707591,49.38924],"type":"Point"},"properties":{"name":"Pomnik przyrody","osm_id":"4024572235","tag":{"denotation":"natural_monument","monument":"yes","natural":"tree","protected":"yes"}},"type":"Feature"}
]
}
