{
"type": "FeatureCollection",
"lastupdate": "2020-07-31T00:00:00Z",
"features": [
	{"geometry":{"coordinates":[-8.401016,40.302027],"type":"Point"},"properties":{"name":"Ecoponto","osm_id":"7643333236","tag":{"amenity":"recycling","opening_hours":"24/7","recycling:glass":"yes","recycling:paper":"yes","recycling:plastic":"yes","recycling_type":"container"}},"type":"Feature"}
]
}
