{
"type": "FeatureCollection",
"features": [
	{"geometry":{"coordinates":[-122.090524,37.335189],"type":"Point"},"properties":{"name":"California bay tree","osm_id":"3203995218","tag":{"natural":"tree"}},"type":"Feature"},
	{"geometry":{"coordinates":[-122.109835,37.333993],"type":"Point"},"properties":{"osm_id":"3489958820","tag":{"natural":"tree"}},"type":"Feature"},
	{"geometry":{"coordinates":[-122.107334,37.334088],"type":"Point"},"properties":{"osm_id":"3489958827","tag":{"natural":"tree"}},"type":"Feature"},
	{"geometry":{"coordinates":[-122.109417,37.334351],"type":"Point"},"properties":{"osm_id":"3489958845","tag":{"natural":"tree"}},"type":"Feature"},
	{"geometry":{"coordinates":[-122.107316,37.334374],"type":"Point"},"properties":{"osm_id":"3611337306","tag":{"natural":"tree"}},"type":"Feature"},
	{"geometry":{"coordinates":[-122.155356,37.358201],"type":"Point"},"properties":{"osm_id":"6439987382","tag":{"natural":"tree"}},"type":"Feature"},
	{"geometry":{"coordinates":[-122.155628,37.362476],"type":"Point"},"properties":{"osm_id":"6444315963","tag":{"natural":"tree"}},"type":"Feature"},
	{"geometry":{"coordinates":[-122.155561,37.361599],"type":"Point"},"properties":{"osm_id":"6444315964","tag":{"natural":"tree"}},"type":"Feature"},
	{"geometry":{"coordinates":[-122.156541,37.361617],"type":"Point"},"properties":{"osm_id":"6444315965","tag":{"natural":"tree"}},"type":"Feature"},
	{"geometry":{"coordinates":[-122.158432,37.364137],"type":"Point"},"properties":{"osm_id":"6444315966","tag":{"natural":"tree"}},"type":"Feature"},
	{"geometry":{"coordinates":[-122.090996,37.351895],"type":"Point"},"properties":{"osm_id":"6446667320","tag":{"natural":"tree"}},"type":"Feature"}
]
}
