{
"type": "FeatureCollection",
"features": [
	{"geometry":{"coordinates":[-122.090523,37.335189],"type":"Point"},"properties":{"name":"California bay tree","osm_id":"3203995218","tag":{"natural":"tree"}},"type":"Feature"},
	{"geometry":{"coordinates":[-122.109834,37.333993],"type":"Point"},"properties":{"osm_id":"3489958820","tag":{"natural":"tree"}},"type":"Feature"},
	{"geometry":{"coordinates":[-122.107334,37.334088],"type":"Point"},"properties":{"osm_id":"3489958827","tag":{"natural":"tree"}},"type":"Feature"},
	{"geometry":{"coordinates":[-122.109417,37.334351],"type":"Point"},"properties":{"osm_id":"3489958845","tag":{"natural":"tree"}},"type":"Feature"},
	{"geometry":{"coordinates":[-122.107316,37.334373],"type":"Point"},"properties":{"osm_id":"3611337306","tag":{"natural":"tree"}},"type":"Feature"},
	{"geometry":{"coordinates":[-122.155355,37.3582],"type":"Point"},"properties":{"osm_id":"6439987382","tag":{"natural":"tree"}},"type":"Feature"},
	{"geometry":{"coordinates":[-122.155627,37.362476],"type":"Point"},"properties":{"osm_id":"6444315963","tag":{"natural":"tree"}},"type":"Feature"},
	{"geometry":{"coordinates":[-122.15556,37.361599],"type":"Point"},"properties":{"osm_id":"6444315964","tag":{"natural":"tree"}},"type":"Feature"},
	{"geometry":{"coordinates":[-122.15654,37.361617],"type":"Point"},"properties":{"osm_id":"6444315965","tag":{"natural":"tree"}},"type":"Feature"},
	{"geometry":{"coordinates":[-122.158431,37.364137],"type":"Point"},"properties":{"osm_id":"6444315966","tag":{"natural":"tree"}},"type":"Feature"},
	{"geometry":{"coordinates":[-122.090995,37.351894],"type":"Point"},"properties":{"osm_id":"6446667320","tag":{"natural":"tree"}},"type":"Feature"},
	{"geometry":{"coordinates":[-122.108584,37.358418],"type":"Point"},"properties":{"osm_id":"8178556733","tag":{"natural":"tree"}},"type":"Feature"}
]
}
