{
"type": "FeatureCollection",
"features": [
	{"geometry":{"coordinates":[13.758303,48.791063],"type":"Point"},"properties":{"osm_id":"2496406556","tag":{"amenity":"recycling","location":"overground","recycling_type":"container"}},"type":"Feature"}
]
}
