{
"type": "FeatureCollection",
"features": [
	{"geometry":{"coordinates":[13.758304,48.791064],"type":"Point"},"properties":{"osm_id":"2496406556","tag":{"amenity":"recycling","location":"overground","recycling:cans":"yes","recycling:clothes":"yes","recycling:glass_bottles":"yes","recycling:shoes":"yes","recycling_type":"container"}},"type":"Feature"}
]
}
