{
"type": "FeatureCollection",
"lastupdate": "2020-08-04T00:00:00Z",
"features": [
	{"geometry":{"coordinates":[34.365703,61.794211],"type":"Point"},"properties":{"osm_id":"1744195296","tag":{"amenity":"waste_basket"}},"type":"Feature"},
	{"geometry":{"coordinates":[34.367469,61.79337],"type":"Point"},"properties":{"osm_id":"1744450688","tag":{"amenity":"waste_basket"}},"type":"Feature"},
	{"geometry":{"coordinates":[34.371113,61.798316],"type":"Point"},"properties":{"osm_id":"2813223570","tag":{"amenity":"waste_basket"}},"type":"Feature"},
	{"geometry":{"coordinates":[34.371112,61.798317],"type":"Point"},"properties":{"osm_id":"2813232350","tag":{"amenity":"waste_basket"}},"type":"Feature"},
	{"geometry":{"coordinates":[34.393392,61.7737],"type":"Point"},"properties":{"osm_id":"4214380894","tag":{"amenity":"recycling","recycling:cardboard":"yes","recycling:paper":"yes","recycling_type":"container"}},"type":"Feature"},
	{"geometry":{"coordinates":[34.373112,61.793651],"type":"Point"},"properties":{"osm_id":"4225417490","tag":{"amenity":"waste_basket"}},"type":"Feature"},
	{"geometry":{"coordinates":[34.373356,61.793544],"type":"Point"},"properties":{"osm_id":"4225420891","tag":{"amenity":"waste_basket"}},"type":"Feature"},
	{"geometry":{"coordinates":[34.366935,61.7919],"type":"Point"},"properties":{"osm_id":"4230224201","tag":{"amenity":"recycling","location":"overground","recycling:cartons":"yes","recycling:paper_packaging":"yes","recycling_type":"container"}},"type":"Feature"},
	{"geometry":{"coordinates":[34.399472,61.780172],"type":"Point"},"properties":{"osm_id":"4337623734","tag":{"amenity":"recycling","recycling:cans":"yes","recycling:cardboard":"yes","recycling:glass_bottles":"yes","recycling:paper":"yes","recycling:plastic_bottles":"yes","recycling_type":"container"}},"type":"Feature"},
	{"geometry":{"coordinates":[34.382409,61.786285],"type":"Point"},"properties":{"osm_id":"4346039691","tag":{"amenity":"waste_basket"}},"type":"Feature"},
	{"geometry":{"coordinates":[34.381744,61.786211],"type":"Point"},"properties":{"osm_id":"4346042691","tag":{"amenity":"waste_basket"}},"type":"Feature"},
	{"geometry":{"coordinates":[34.390435,61.775086],"type":"Point"},"properties":{"osm_id":"4357999397","tag":{"amenity":"waste_basket"}},"type":"Feature"},
	{"geometry":{"coordinates":[34.390442,61.775105],"type":"Point"},"properties":{"osm_id":"4357999399","tag":{"amenity":"waste_basket"}},"type":"Feature"},
	{"geometry":{"coordinates":[34.385832,61.785944],"type":"Point"},"properties":{"osm_id":"4359007589","tag":{"amenity":"waste_basket"}},"type":"Feature"},
	{"geometry":{"coordinates":[34.382253,61.786697],"type":"Point"},"properties":{"osm_id":"4359007609","tag":{"amenity":"waste_basket"}},"type":"Feature"}
]
}
