{
"type": "FeatureCollection",
"features": [
	{"geometry":{"coordinates":[9.926177,48.268751],"type":"Point"},"properties":{"osm_id":"2460080745","tag":{"genus:de":"Apfelbaum","natural":"tree"}},"type":"Feature"},
	{"geometry":{"coordinates":[9.906105,48.246272],"type":"Point"},"properties":{"osm_id":"2917646932","tag":{"natural":"tree"}},"type":"Feature"},
	{"geometry":{"coordinates":[9.905992,48.246213],"type":"Point"},"properties":{"osm_id":"2917646934","tag":{"natural":"tree"}},"type":"Feature"},
	{"geometry":{"coordinates":[9.906062,48.246161],"type":"Point"},"properties":{"osm_id":"2917646938","tag":{"natural":"tree"}},"type":"Feature"},
	{"geometry":{"coordinates":[9.907553,48.247436],"type":"Point"},"properties":{"osm_id":"2918332166","tag":{"natural":"tree"}},"type":"Feature"},
	{"geometry":{"coordinates":[9.926623,48.250567],"type":"Point"},"properties":{"osm_id":"2920611389","tag":{"natural":"tree"}},"type":"Feature"},
	{"geometry":{"coordinates":[9.925385,48.244109],"type":"Point"},"properties":{"osm_id":"2920655034","tag":{"natural":"tree"}},"type":"Feature"},
	{"geometry":{"coordinates":[9.924472,48.244639],"type":"Point"},"properties":{"osm_id":"2920655038","tag":{"natural":"tree"}},"type":"Feature"},
	{"geometry":{"coordinates":[9.897631,48.282816],"type":"Point"},"properties":{"osm_id":"2924934033","tag":{"natural":"tree"}},"type":"Feature"},
	{"geometry":{"coordinates":[9.881561,48.235186],"type":"Point"},"properties":{"name":"Naturdenkmal Jahneiche","osm_id":"3308401105","tag":{"natural":"tree"}},"type":"Feature"},
	{"geometry":{"coordinates":[9.850911,48.236844],"type":"Point"},"properties":{"osm_id":"4326751622","tag":{"natural":"tree"}},"type":"Feature"},
	{"geometry":{"coordinates":[9.850874,48.236769],"type":"Point"},"properties":{"osm_id":"4326751636","tag":{"natural":"tree"}},"type":"Feature"},
	{"geometry":{"coordinates":[9.850807,48.236626],"type":"Point"},"properties":{"osm_id":"4326751641","tag":{"natural":"tree"}},"type":"Feature"},
	{"geometry":{"coordinates":[9.884878,48.231628],"type":"Point"},"properties":{"osm_id":"4680378828","tag":{"denotation":"natural_monument","natural":"tree"}},"type":"Feature"},
	{"geometry":{"coordinates":[9.896576,48.261575],"type":"Point"},"properties":{"osm_id":"5242367386","tag":{"natural":"tree"}},"type":"Feature"},
	{"geometry":{"coordinates":[9.876183,48.274343],"type":"Point"},"properties":{"osm_id":"6046120082","tag":{"leaf_cycle":"deciduous","leaf_type":"broadleaved","natural":"tree"}},"type":"Feature"},
	{"geometry":{"coordinates":[9.873134,48.276314],"type":"Point"},"properties":{"osm_id":"6046120083","tag":{"leaf_cycle":"deciduous","leaf_type":"broadleaved","natural":"tree"}},"type":"Feature"},
	{"geometry":{"coordinates":[9.862555,48.251084],"type":"Point"},"properties":{"osm_id":"6046306361","tag":{"leaf_cycle":"deciduous","leaf_type":"broadleaved","natural":"tree"}},"type":"Feature"},
	{"geometry":{"coordinates":[9.856183,48.264013],"type":"Point"},"properties":{"osm_id":"6048995326","tag":{"leaf_cycle":"deciduous","leaf_type":"broadleaved","natural":"tree"}},"type":"Feature"},
	{"geometry":{"coordinates":[9.858883,48.261573],"type":"Point"},"properties":{"osm_id":"6048995327","tag":{"leaf_cycle":"deciduous","leaf_type":"broadleaved","natural":"tree"}},"type":"Feature"},
	{"geometry":{"coordinates":[9.854946,48.261272],"type":"Point"},"properties":{"osm_id":"6048995328","tag":{"leaf_cycle":"deciduous","leaf_type":"broadleaved","natural":"tree"}},"type":"Feature"},
	{"geometry":{"coordinates":[9.853083,48.248344],"type":"Point"},"properties":{"osm_id":"6048995355","tag":{"leaf_cycle":"deciduous","leaf_type":"broadleaved","natural":"tree"}},"type":"Feature"},
	{"geometry":{"coordinates":[9.850807,48.248363],"type":"Point"},"properties":{"osm_id":"6048995356","tag":{"leaf_cycle":"deciduous","leaf_type":"broadleaved","natural":"tree"}},"type":"Feature"},
	{"geometry":{"coordinates":[9.853501,48.250037],"type":"Point"},"properties":{"osm_id":"6048995357","tag":{"leaf_cycle":"deciduous","leaf_type":"broadleaved","natural":"tree"}},"type":"Feature"},
	{"geometry":{"coordinates":[9.90098,48.279273],"type":"Point"},"properties":{"osm_id":"6054619582","tag":{"leaf_cycle":"evergreen","leaf_type":"needleleaved","natural":"tree"}},"type":"Feature"},
	{"geometry":{"coordinates":[9.904368,48.278502],"type":"Point"},"properties":{"osm_id":"6466128705","tag":{"natural":"tree"}},"type":"Feature"},
	{"geometry":{"coordinates":[9.85308,48.248294],"type":"Point"},"properties":{"osm_id":"6555819115","tag":{"leaf_cycle":"deciduous","leaf_type":"broadleaved","natural":"tree"}},"type":"Feature"}
]
}
