{
"type": "FeatureCollection",
"features": [
	{"geometry":{"coordinates":[9.847563,24.535846],"type":"Point"},"properties":{"name":"Acacia","osm_id":"9004481271","tag":{"natural":"tree"}},"type":"Feature"},
	{"geometry":{"coordinates":[9.84796,24.535744],"type":"Point"},"properties":{"name":"Acacia","osm_id":"9004481272","tag":{"natural":"tree"}},"type":"Feature"},
	{"geometry":{"coordinates":[9.84675,24.534114],"type":"Point"},"properties":{"name":"Acacia","osm_id":"9004481273","tag":{"natural":"tree"}},"type":"Feature"},
	{"geometry":{"coordinates":[9.847134,24.534114],"type":"Point"},"properties":{"name":"Acacia","osm_id":"9004481274","tag":{"natural":"tree"}},"type":"Feature"},
	{"geometry":{"coordinates":[9.846868,24.534304],"type":"Point"},"properties":{"name":"Acacia","osm_id":"9004481275","tag":{"natural":"tree"}},"type":"Feature"},
	{"geometry":{"coordinates":[9.846611,24.534624],"type":"Point"},"properties":{"name":"Acacia","osm_id":"9004481276","tag":{"natural":"tree"}},"type":"Feature"},
	{"geometry":{"coordinates":[9.847123,24.534321],"type":"Point"},"properties":{"name":"Acacia","osm_id":"9004481277","tag":{"natural":"tree"}},"type":"Feature"}
]
}
