{
"type": "FeatureCollection",
"features": [
	{"geometry":{"coordinates":[6.402515,51.047314],"type":"Point"},"properties":{"osm_id":"7629671309","tag":{"amenity":"recycling","clothes":"yes","contact:website":"https://www.drk-heinsberg.de/","operator":"DRK Kreisverband Heinsberg","recycling_type":"container"}},"type":"Feature"},
	{"geometry":{"coordinates":[6.337056,51.058661],"type":"Point"},"properties":{"osm_id":"7931849302","tag":{"amenity":"waste_basket"}},"type":"Feature"},
	{"geometry":{"coordinates":[6.335035,51.058983],"type":"Point"},"properties":{"osm_id":"7945403453","tag":{"amenity":"recycling","recycling:clothes":"yes","recycling_type":"container"}},"type":"Feature"},
	{"geometry":{"coordinates":[6.331686,51.059394],"type":"Point"},"properties":{"osm_id":"7945403454","tag":{"amenity":"waste_basket"}},"type":"Feature"}
]
}
