{
"type": "FeatureCollection",
"lastupdate": "2020-08-05T00:00:00Z",
"features": [
	{"geometry":{"coordinates":[6.402515,51.047314],"type":"Point"},"properties":{"osm_id":"7629671309","tag":{"amenity":"recycling","clothes":"yes","contact:website":"https://www.drk-heinsberg.de/","operator":"DRK Kreisverband Heinsberg","recycling_type":"container"}},"type":"Feature"}
]
}
