{
"type": "FeatureCollection",
"features": [
	{"geometry":{"coordinates":[6.402516,51.047315],"type":"Point"},"properties":{"osm_id":"7629671309","tag":{"amenity":"recycling","clothes":"yes","contact:website":"https://www.drk-heinsberg.de/","operator":"DRK Kreisverband Heinsberg","recycling_type":"container"}},"type":"Feature"},
	{"geometry":{"coordinates":[6.337057,51.058662],"type":"Point"},"properties":{"osm_id":"7931849302","tag":{"amenity":"waste_basket"}},"type":"Feature"},
	{"geometry":{"coordinates":[6.335036,51.058984],"type":"Point"},"properties":{"osm_id":"7945403453","tag":{"amenity":"recycling","recycling:clothes":"yes","recycling_type":"container"}},"type":"Feature"},
	{"geometry":{"coordinates":[6.331686,51.059394],"type":"Point"},"properties":{"osm_id":"7945403454","tag":{"amenity":"waste_basket"}},"type":"Feature"}
]
}
