{
"type": "FeatureCollection",
"lastupdate": "2020-08-02T00:00:00Z",
"features": [
	{"geometry":{"coordinates":[6.371633,46.096345],"type":"Point"},"properties":{"osm_id":"472333122","tag":{"amenity":"recycling","recycling:glass":"yes","recycling:paper":"yes","recycling:plastic_bottles":"yes","recycling_type":"container"}},"type":"Feature"},
	{"geometry":{"coordinates":[6.348159,46.115872],"type":"Point"},"properties":{"osm_id":"472448410","tag":{"amenity":"recycling","recycling:glass":"yes","recycling:paper":"yes","recycling:plastic_bottles":"yes","recycling_type":"container"}},"type":"Feature"},
	{"geometry":{"coordinates":[6.337041,46.133565],"type":"Point"},"properties":{"osm_id":"472465690","tag":{"amenity":"recycling","location":"underground","recycling:glass":"yes","recycling:paper":"yes","recycling:plastic_bottles":"yes","recycling_type":"container"}},"type":"Feature"},
	{"geometry":{"coordinates":[6.399128,46.08478],"type":"Point"},"properties":{"osm_id":"1137699530","tag":{"amenity":"recycling","recycling:glass":"yes","recycling:paper":"yes","recycling_type":"container"}},"type":"Feature"},
	{"geometry":{"coordinates":[6.407248,46.106938],"type":"Point"},"properties":{"osm_id":"1268246962","tag":{"amenity":"recycling","recycling:glass":"yes","recycling:paper":"yes","recycling_type":"container"}},"type":"Feature"},
	{"geometry":{"coordinates":[6.33894,46.100029],"type":"Point"},"properties":{"osm_id":"6343410005","tag":{"amenity":"recycling","recycling_type":"container"}},"type":"Feature"}
]
}
