{
"type": "FeatureCollection",
"features": [
	{"geometry":{"coordinates":[6.371634,46.096346],"type":"Point"},"properties":{"osm_id":"472333122","tag":{"amenity":"recycling","recycling:glass":"yes","recycling:paper":"yes","recycling:plastic_bottles":"yes","recycling_type":"container"}},"type":"Feature"},
	{"geometry":{"coordinates":[6.34816,46.115873],"type":"Point"},"properties":{"osm_id":"472448410","tag":{"amenity":"recycling","recycling:glass":"yes","recycling:paper":"yes","recycling:plastic_bottles":"yes","recycling_type":"container"}},"type":"Feature"},
	{"geometry":{"coordinates":[6.337042,46.133566],"type":"Point"},"properties":{"osm_id":"472465690","tag":{"amenity":"recycling","location":"underground","recycling:glass":"yes","recycling:paper":"yes","recycling:plastic_bottles":"yes","recycling_type":"container"}},"type":"Feature"},
	{"geometry":{"coordinates":[6.399128,46.08478],"type":"Point"},"properties":{"osm_id":"1137699530","tag":{"amenity":"recycling","recycling:glass":"yes","recycling:paper":"yes","recycling_type":"container"}},"type":"Feature"},
	{"geometry":{"coordinates":[6.407249,46.106939],"type":"Point"},"properties":{"osm_id":"1268246962","tag":{"amenity":"recycling","recycling:glass":"yes","recycling:paper":"yes","recycling_type":"container"}},"type":"Feature"},
	{"geometry":{"coordinates":[6.33894,46.10003],"type":"Point"},"properties":{"osm_id":"6343410005","tag":{"amenity":"recycling","recycling_type":"container"}},"type":"Feature"},
	{"geometry":{"coordinates":[6.374594,46.079456],"type":"Point"},"properties":{"osm_id":"7580063803","tag":{"amenity":"waste_disposal"}},"type":"Feature"}
]
}
