{
"type": "FeatureCollection",
"lastupdate": "2020-08-02T00:00:00Z",
"features": [
	{"geometry":{"coordinates":[6.330328,45.195974],"type":"Point"},"properties":{"osm_id":"606044447","tag":{"amenity":"recycling","location":"underground","recycling:glass_bottles":"yes","recycling_type":"container"}},"type":"Feature"}
]
}
