{
"type": "FeatureCollection",
"features": [
	{"geometry":{"coordinates":[-73.731978,42.865201],"type":"Point"},"properties":{"name":"Town of Halfmoon Solid Waste and Recycling Center","osm_id":"1618397709","tag":{"amenity":"recycling","recycling_type":"centre"}},"type":"Feature"}
]
}
