{
"type": "FeatureCollection",
"features": [
	{"geometry":{"coordinates":[10.611403,53.436582],"type":"Point"},"properties":{"osm_id":"278714167","tag":{"amenity":"recycling","recycling:clothes":"yes","recycling:glass_bottles":"yes","recycling:paper":"yes","recycling_type":"container"}},"type":"Feature"},
	{"geometry":{"coordinates":[10.614337,53.480665],"type":"Point"},"properties":{"osm_id":"413488076","tag":{"amenity":"recycling","recycling:clothes":"yes","recycling:glass_bottles":"yes","recycling:paper":"yes","recycling_type":"container"}},"type":"Feature"},
	{"geometry":{"coordinates":[10.613621,53.453417],"type":"Point"},"properties":{"osm_id":"957119874","tag":{"amenity":"recycling","recycling:clothes":"yes","recycling:glass_bottles":"yes","recycling:paper":"yes","recycling_type":"container"}},"type":"Feature"},
	{"geometry":{"coordinates":[10.628552,53.461341],"type":"Point"},"properties":{"osm_id":"1014712185","tag":{"amenity":"recycling","mapillary":"Juujp2PGiHg7mFhEPyNfwA","recycling:glass":"yes","recycling:paper":"yes","recycling_type":"container","survey:date":"2019-02-03"}},"type":"Feature"},
	{"geometry":{"coordinates":[10.615357,53.479456],"type":"Point"},"properties":{"osm_id":"3752162951","tag":{"amenity":"waste_basket"}},"type":"Feature"},
	{"geometry":{"coordinates":[10.566177,53.472661],"type":"Point"},"properties":{"osm_id":"3929663326","tag":{"amenity":"recycling","recycling:clothes":"yes","recycling:glass_bottles":"yes","recycling:paper":"yes","recycling_type":"container"}},"type":"Feature"},
	{"geometry":{"coordinates":[10.60546,53.484379],"type":"Point"},"properties":{"osm_id":"3935739112","tag":{"amenity":"recycling","recycling:clothes":"yes","recycling:glass_bottles":"yes","recycling:paper":"yes","recycling_type":"container"}},"type":"Feature"},
	{"geometry":{"coordinates":[10.624102,53.47471],"type":"Point"},"properties":{"osm_id":"5161913133","tag":{"amenity":"waste_basket"}},"type":"Feature"},
	{"geometry":{"coordinates":[10.626217,53.473514],"type":"Point"},"properties":{"osm_id":"5161917927","tag":{"amenity":"waste_basket"}},"type":"Feature"},
	{"geometry":{"coordinates":[10.623136,53.475219],"type":"Point"},"properties":{"osm_id":"5161927423","tag":{"amenity":"waste_basket"}},"type":"Feature"},
	{"geometry":{"coordinates":[10.623114,53.475233],"type":"Point"},"properties":{"osm_id":"5161927424","tag":{"amenity":"waste_basket"}},"type":"Feature"},
	{"geometry":{"coordinates":[10.624443,53.474476],"type":"Point"},"properties":{"osm_id":"5161939311","tag":{"amenity":"waste_basket"}},"type":"Feature"},
	{"geometry":{"coordinates":[10.625119,53.474135],"type":"Point"},"properties":{"osm_id":"5161940433","tag":{"amenity":"waste_basket"}},"type":"Feature"},
	{"geometry":{"coordinates":[10.621961,53.475596],"type":"Point"},"properties":{"osm_id":"5225459823","tag":{"amenity":"waste_basket"}},"type":"Feature"},
	{"geometry":{"coordinates":[10.622591,53.474425],"type":"Point"},"properties":{"osm_id":"5243493548","tag":{"amenity":"recycling","location":"underground","recycling:glass_bottles":"yes","recycling:paper":"yes","recycling_type":"container"}},"type":"Feature"},
	{"geometry":{"coordinates":[10.622958,53.475041],"type":"Point"},"properties":{"osm_id":"7238545271","tag":{"amenity":"waste_basket"}},"type":"Feature"},
	{"geometry":{"coordinates":[10.623522,53.474003],"type":"Point"},"properties":{"osm_id":"7238545272","tag":{"amenity":"waste_basket"}},"type":"Feature"},
	{"geometry":{"coordinates":[10.623202,53.474475],"type":"Point"},"properties":{"osm_id":"7238545273","tag":{"amenity":"waste_basket"}},"type":"Feature"},
	{"geometry":{"coordinates":[10.627462,53.445991],"type":"Point"},"properties":{"osm_id":"8309784893","tag":{"amenity":"waste_basket","waste":"trash"}},"type":"Feature"},
	{"geometry":{"coordinates":[10.606825,53.488021],"type":"Point"},"properties":{"osm_id":"8826253443","tag":{"amenity":"recycling","recycling:clothes":"yes","recycling:glass_bottles":"yes","recycling:paper":"yes","recycling:shoes":"yes","recycling_type":"container"}},"type":"Feature"},
	{"geometry":{"coordinates":[10.605486,53.487807],"type":"Point"},"properties":{"osm_id":"8826253445","tag":{"amenity":"waste_basket"}},"type":"Feature"},
	{"geometry":{"coordinates":[10.623087,53.477926],"type":"Point"},"properties":{"osm_id":"9137072838","tag":{"amenity":"waste_basket"}},"type":"Feature"}
]
}
