{
"type": "FeatureCollection",
"features": [
	{"geometry":{"coordinates":[10.623752,52.193767],"type":"Point"},"properties":{"osm_id":"264182059","tag":{"amenity":"recycling","recycling_type":"container"}},"type":"Feature"},
	{"geometry":{"coordinates":[10.598656,52.170409],"type":"Point"},"properties":{"osm_id":"271166933","tag":{"amenity":"recycling","recycling:clothes":"yes","recycling:glass_bottles":"yes","recycling:paper":"yes","recycling:shoes":"yes","recycling_type":"container"}},"type":"Feature"},
	{"geometry":{"coordinates":[10.58777,52.192696],"type":"Point"},"properties":{"osm_id":"275298341","tag":{"amenity":"recycling","recycling:clothes":"yes","recycling:glass":"yes","recycling:paper":"yes","recycling:shoes":"yes","recycling_type":"container"}},"type":"Feature"},
	{"geometry":{"coordinates":[10.569188,52.173784],"type":"Point"},"properties":{"osm_id":"278774144","tag":{"amenity":"recycling","recycling:clothes":"yes","recycling:shoes":"yes","recycling_type":"container"}},"type":"Feature"},
	{"geometry":{"coordinates":[10.565186,52.169543],"type":"Point"},"properties":{"osm_id":"287607218","tag":{"amenity":"recycling","recycling:clothes":"yes","recycling:shoes":"yes","recycling_type":"container"}},"type":"Feature"},
	{"geometry":{"coordinates":[10.633044,52.211504],"type":"Point"},"properties":{"osm_id":"300054637","tag":{"amenity":"recycling","location":"overground","recycling:glass":"yes","recycling:paper":"yes","recycling_type":"container"}},"type":"Feature"},
	{"geometry":{"coordinates":[10.556861,52.17218],"type":"Point"},"properties":{"osm_id":"312161005","tag":{"amenity":"recycling","recycling_type":"container"}},"type":"Feature"},
	{"geometry":{"coordinates":[10.579556,52.182164],"type":"Point"},"properties":{"osm_id":"401791322","tag":{"amenity":"recycling","recycling:clothes":"yes","recycling:glass":"yes","recycling:paper":"yes"}},"type":"Feature"},
	{"geometry":{"coordinates":[10.564049,52.171175],"type":"Point"},"properties":{"osm_id":"569096081","tag":{"amenity":"recycling","recycling:glass":"yes","recycling:paper":"yes","recycling:shoes":"yes","recycling_type":"container"}},"type":"Feature"},
	{"geometry":{"coordinates":[10.54959,52.164449],"type":"Point"},"properties":{"osm_id":"600053708","tag":{"amenity":"recycling","recycling:clothes":"yes","recycling:shoes":"yes","recycling_type":"container"}},"type":"Feature"},
	{"geometry":{"coordinates":[10.572553,52.168292],"type":"Point"},"properties":{"osm_id":"713373519","tag":{"amenity":"recycling","recycling:clothes":"yes","recycling:glass":"yes","recycling:paper":"yes","recycling:shoes":"yes","recycling_type":"container"}},"type":"Feature"},
	{"geometry":{"coordinates":[10.573223,52.168465],"type":"Point"},"properties":{"osm_id":"713373523","tag":{"amenity":"recycling","recycling:electrical_appliances":"yes","recycling_type":"container"}},"type":"Feature"},
	{"geometry":{"coordinates":[10.547099,52.176945],"type":"Point"},"properties":{"osm_id":"1086994442","tag":{"amenity":"recycling","recycling:clothes":"yes","recycling:glass_bottles":"yes","recycling:paper":"yes","recycling_type":"container"}},"type":"Feature"},
	{"geometry":{"coordinates":[10.560623,52.179688],"type":"Point"},"properties":{"osm_id":"1368553460","tag":{"access":"no","amenity":"recycling","recycling:paper":"yes","recycling_type":"container"}},"type":"Feature"},
	{"geometry":{"coordinates":[10.558999,52.166508],"type":"Point"},"properties":{"osm_id":"2267452518","tag":{"amenity":"recycling","recycling:glass":"yes","recycling_type":"container"}},"type":"Feature"},
	{"geometry":{"coordinates":[10.554538,52.167773],"type":"Point"},"properties":{"osm_id":"6433560657","tag":{"amenity":"recycling","recycling:clothes":"yes","recycling:shoes":"yes","recycling_type":"container"}},"type":"Feature"}
]
}
