{
"type": "FeatureCollection",
"lastupdate": "2020-08-05T00:00:00Z",
"features": [
	{"geometry":{"coordinates":[10.556531,49.88777],"type":"Point"},"properties":{"name":"Wertsotffhof","osm_id":"1703493595","tag":{"amenity":"recycling","recycling_type":"centre"}},"type":"Feature"}
]
}
