{
"type": "FeatureCollection",
"features": [
	{"geometry":{"coordinates":[10.585758,47.421232],"type":"Point"},"properties":{"name":"Recyclinghof Forchach","osm_id":"4476928310","tag":{"amenity":"recycling","recycling_type":"centre"}},"type":"Feature"}
]
}
