{
"type": "FeatureCollection",
"lastupdate": "2020-08-05T00:00:00Z",
"features": [
	{"geometry":{"coordinates":[18.193397,40.355685],"type":"Point"},"properties":{"osm_id":"4209722795","ref":"11","tag":{"amenity":"recycling","location":"underground","recycling:SAP":"yes","recycling_type":"container"}},"type":"Feature"},
	{"geometry":{"coordinates":[18.204714,40.359125],"type":"Point"},"properties":{"name":"Isola Ecologica Interrata Informatizzata","osm_id":"4209722796","ref":"12","tag":{"amenity":"recycling","collection_times":"24/7","location":"underground","recycling:SAP":"yes","recycling_type":"container"}},"type":"Feature"},
	{"geometry":{"coordinates":[18.204881,40.365818],"type":"Point"},"properties":{"barrier":"gate","osm_id":"7294806123"},"type":"Feature"}
]
}
