{
"type": "FeatureCollection",
"features": [
	{"geometry":{"coordinates":[8.569987,48.274862],"type":"Point"},"properties":{"name":"Eiche","osm_id":"3213158936","tag":{"natural":"tree"}},"type":"Feature"},
	{"geometry":{"coordinates":[8.569907,48.274915],"type":"Point"},"properties":{"name":"Eiche","osm_id":"3213159861","tag":{"natural":"tree"}},"type":"Feature"},
	{"geometry":{"coordinates":[8.569691,48.273065],"type":"Point"},"properties":{"name":"Walnussbaum","osm_id":"3213207059","tag":{"natural":"tree"}},"type":"Feature"},
	{"geometry":{"coordinates":[8.55326,48.236204],"type":"Point"},"properties":{"osm_id":"4246396985","tag":{"natural":"tree"}},"type":"Feature"},
	{"geometry":{"coordinates":[8.55338,48.236341],"type":"Point"},"properties":{"osm_id":"4246396986","tag":{"natural":"tree"}},"type":"Feature"},
	{"geometry":{"coordinates":[8.556239,48.239021],"type":"Point"},"properties":{"osm_id":"4288252445","tag":{"natural":"tree"}},"type":"Feature"},
	{"geometry":{"coordinates":[8.590525,48.281373],"type":"Point"},"properties":{"osm_id":"7806082116","tag":{"leaf_type":"broadleaved","natural":"tree"}},"type":"Feature"}
]
}
