{
"type": "FeatureCollection",
"features": [
	{"geometry":{"coordinates":[8.605622,39.225443],"type":"Point"},"properties":{"name":"Grande Quercia","osm_id":"3319079979","tag":{"natural":"tree"}},"type":"Feature"}
]
}
