{
"type": "FeatureCollection",
"features": [
	{"geometry":{"coordinates":[103.703331,1.342752],"type":"Point"},"properties":{"osm_id":"1107580373","tag":{"amenity":"recycling","location":"overground","recycling_type":"container"}},"type":"Feature"},
	{"geometry":{"coordinates":[103.689104,1.351835],"type":"Point"},"properties":{"osm_id":"4275263706","tag":{"amenity":"waste_disposal"}},"type":"Feature"},
	{"geometry":{"coordinates":[103.684599,1.346989],"type":"Point"},"properties":{"osm_id":"4275263743","tag":{"amenity":"waste_disposal"}},"type":"Feature"},
	{"geometry":{"coordinates":[103.688117,1.349374],"type":"Point"},"properties":{"osm_id":"4287920494","tag":{"amenity":"waste_basket"}},"type":"Feature"},
	{"geometry":{"coordinates":[103.702578,1.343977],"type":"Point"},"properties":{"osm_id":"5770475427","tag":{"amenity":"recycling","recycling:cans":"yes","recycling:paper":"yes","recycling:plastic":"yes","recycling_type":"container"}},"type":"Feature"},
	{"geometry":{"coordinates":[103.701216,1.343788],"type":"Point"},"properties":{"osm_id":"5770475428","tag":{"amenity":"recycling","recycling:cans":"yes","recycling:paper":"yes","recycling:plastic":"yes","recycling_type":"container"}},"type":"Feature"},
	{"geometry":{"coordinates":[103.701621,1.344773],"type":"Point"},"properties":{"osm_id":"5773139453","tag":{"amenity":"recycling","recycling:cans":"yes","recycling:paper":"yes","recycling:plastic":"yes","recycling_type":"container"}},"type":"Feature"}
]
}
