{
"type": "FeatureCollection",
"features": [
	{"geometry":{"coordinates":[103.70333,1.342751],"type":"Point"},"properties":{"osm_id":"1107580373","tag":{"amenity":"recycling","location":"overground","recycling_type":"container"}},"type":"Feature"},
	{"geometry":{"coordinates":[103.689103,1.351834],"type":"Point"},"properties":{"osm_id":"4275263706","tag":{"amenity":"waste_disposal"}},"type":"Feature"},
	{"geometry":{"coordinates":[103.684599,1.346989],"type":"Point"},"properties":{"osm_id":"4275263743","tag":{"amenity":"waste_disposal"}},"type":"Feature"},
	{"geometry":{"coordinates":[103.688116,1.349373],"type":"Point"},"properties":{"osm_id":"4287920494","tag":{"amenity":"waste_basket"}},"type":"Feature"},
	{"geometry":{"coordinates":[103.702577,1.343976],"type":"Point"},"properties":{"osm_id":"5770475427","tag":{"amenity":"recycling","recycling:cans":"yes","recycling:paper":"yes","recycling:plastic":"yes","recycling_type":"container"}},"type":"Feature"},
	{"geometry":{"coordinates":[103.701216,1.343787],"type":"Point"},"properties":{"osm_id":"5770475428","tag":{"amenity":"recycling","recycling:cans":"yes","recycling:paper":"yes","recycling:plastic":"yes","recycling_type":"container"}},"type":"Feature"},
	{"geometry":{"coordinates":[103.701621,1.344772],"type":"Point"},"properties":{"osm_id":"5773139453","tag":{"amenity":"recycling","recycling:cans":"yes","recycling:paper":"yes","recycling:plastic":"yes","recycling_type":"container"}},"type":"Feature"},
	{"geometry":{"coordinates":[103.696905,1.337404],"type":"Point"},"properties":{"osm_id":"8427250744","tag":{"amenity":"waste_basket"}},"type":"Feature"},
	{"geometry":{"coordinates":[103.695959,1.336045],"type":"Point"},"properties":{"osm_id":"8568755368","tag":{"amenity":"recycling","location":"overground","recycling_type":"container"}},"type":"Feature"}
]
}
