{
"type": "FeatureCollection",
"features": [
	{"geometry":{"coordinates":[0.190357,50.817704],"type":"Point"},"properties":{"name":"Ancient Yew Tree, Wilmington Church.","osm_id":"4042454693","tag":{"denotation":"religious","leaf_cycle":"deciduous","leaf_type":"needleleaved","natural":"tree","type":"yew"}},"type":"Feature"},
	{"geometry":{"coordinates":[0.237567,50.81583],"type":"Point"},"properties":{"name":"Old Crooked tree","osm_id":"4794997403","tag":{"leaf_cycle":"semi_evergreen","leaf_type":"broadleaved","natural":"tree"}},"type":"Feature"},
	{"geometry":{"coordinates":[0.252776,50.806718],"type":"Point"},"properties":{"osm_id":"4941275234","tag":{"leaf_type":"broadleaved","natural":"tree"}},"type":"Feature"},
	{"geometry":{"coordinates":[0.252939,50.806744],"type":"Point"},"properties":{"osm_id":"4941275235","tag":{"leaf_type":"broadleaved","natural":"tree"}},"type":"Feature"},
	{"geometry":{"coordinates":[0.24881,50.807003],"type":"Point"},"properties":{"osm_id":"4947588895","tag":{"natural":"tree"}},"type":"Feature"}
]
}
