{
"type": "FeatureCollection",
"features": [
	{"geometry":{"coordinates":[28.342617,37.055003],"type":"Point"},"properties":{"name":"Old tree","osm_id":"3164963012","tag":{"natural":"tree"}},"type":"Feature"},
	{"geometry":{"coordinates":[28.357662,37.08882],"type":"Point"},"properties":{"osm_id":"8777818275","tag":{"natural":"tree"}},"type":"Feature"},
	{"geometry":{"coordinates":[28.357762,37.089036],"type":"Point"},"properties":{"osm_id":"8777859241","tag":{"natural":"tree"}},"type":"Feature"},
	{"geometry":{"coordinates":[28.357771,37.088977],"type":"Point"},"properties":{"osm_id":"8777859242","tag":{"natural":"tree"}},"type":"Feature"},
	{"geometry":{"coordinates":[28.357779,37.088925],"type":"Point"},"properties":{"osm_id":"8777859243","tag":{"natural":"tree"}},"type":"Feature"},
	{"geometry":{"coordinates":[28.357784,37.088878],"type":"Point"},"properties":{"osm_id":"8777859244","tag":{"natural":"tree"}},"type":"Feature"},
	{"geometry":{"coordinates":[28.357793,37.088828],"type":"Point"},"properties":{"osm_id":"8777859245","tag":{"natural":"tree"}},"type":"Feature"},
	{"geometry":{"coordinates":[28.357805,37.088774],"type":"Point"},"properties":{"osm_id":"8777859246","tag":{"natural":"tree"}},"type":"Feature"},
	{"geometry":{"coordinates":[28.357799,37.088737],"type":"Point"},"properties":{"osm_id":"8777859247","tag":{"natural":"tree"}},"type":"Feature"},
	{"geometry":{"coordinates":[28.357805,37.088678],"type":"Point"},"properties":{"osm_id":"8777859248","tag":{"natural":"tree"}},"type":"Feature"},
	{"geometry":{"coordinates":[28.357818,37.088626],"type":"Point"},"properties":{"osm_id":"8777859249","tag":{"natural":"tree"}},"type":"Feature"},
	{"geometry":{"coordinates":[28.357823,37.088583],"type":"Point"},"properties":{"osm_id":"8777859250","tag":{"natural":"tree"}},"type":"Feature"},
	{"geometry":{"coordinates":[28.357689,37.089033],"type":"Point"},"properties":{"osm_id":"8777859251","tag":{"natural":"tree"}},"type":"Feature"},
	{"geometry":{"coordinates":[28.357702,37.088975],"type":"Point"},"properties":{"osm_id":"8777859252","tag":{"natural":"tree"}},"type":"Feature"},
	{"geometry":{"coordinates":[28.357708,37.088921],"type":"Point"},"properties":{"osm_id":"8777859253","tag":{"natural":"tree"}},"type":"Feature"},
	{"geometry":{"coordinates":[28.357712,37.088881],"type":"Point"},"properties":{"osm_id":"8777859254","tag":{"natural":"tree"}},"type":"Feature"},
	{"geometry":{"coordinates":[28.357728,37.088831],"type":"Point"},"properties":{"osm_id":"8777859255","tag":{"natural":"tree"}},"type":"Feature"},
	{"geometry":{"coordinates":[28.35773,37.088769],"type":"Point"},"properties":{"osm_id":"8777859256","tag":{"natural":"tree"}},"type":"Feature"},
	{"geometry":{"coordinates":[28.357827,37.089039],"type":"Point"},"properties":{"osm_id":"8777859310","tag":{"natural":"tree"}},"type":"Feature"},
	{"geometry":{"coordinates":[28.357838,37.088931],"type":"Point"},"properties":{"osm_id":"8777859311","tag":{"natural":"tree"}},"type":"Feature"},
	{"geometry":{"coordinates":[28.357846,37.088881],"type":"Point"},"properties":{"osm_id":"8777859312","tag":{"natural":"tree"}},"type":"Feature"},
	{"geometry":{"coordinates":[28.357856,37.088829],"type":"Point"},"properties":{"osm_id":"8777859313","tag":{"natural":"tree"}},"type":"Feature"},
	{"geometry":{"coordinates":[28.357628,37.089021],"type":"Point"},"properties":{"osm_id":"8777859314","tag":{"natural":"tree"}},"type":"Feature"},
	{"geometry":{"coordinates":[28.357644,37.088977],"type":"Point"},"properties":{"osm_id":"8777859315","tag":{"natural":"tree"}},"type":"Feature"},
	{"geometry":{"coordinates":[28.357645,37.088933],"type":"Point"},"properties":{"osm_id":"8777859316","tag":{"natural":"tree"}},"type":"Feature"},
	{"geometry":{"coordinates":[28.357654,37.088877],"type":"Point"},"properties":{"osm_id":"8777859317","tag":{"natural":"tree"}},"type":"Feature"},
	{"geometry":{"coordinates":[28.357736,37.088723],"type":"Point"},"properties":{"osm_id":"8777859334","tag":{"natural":"tree"}},"type":"Feature"},
	{"geometry":{"coordinates":[28.357738,37.088675],"type":"Point"},"properties":{"osm_id":"8777859335","tag":{"natural":"tree"}},"type":"Feature"}
]
}
