{
"type": "FeatureCollection",
"features": [
	{"geometry":{"coordinates":[28.342617,37.055003],"type":"Point"},"properties":{"name":"Old tree","osm_id":"3164963012","tag":{"natural":"tree"}},"type":"Feature"}
]
}
