{
"type": "FeatureCollection",
"features": [
	{"geometry":{"coordinates":[3.799738,51.085665],"type":"Point"},"properties":{"osm_id":"6186313286","tag":{"amenity":"recycling","location":"overground","recycling_type":"container"}},"type":"Feature"},
	{"geometry":{"coordinates":[3.800014,51.085742],"type":"Point"},"properties":{"osm_id":"6186313387","tag":{"amenity":"waste_basket"}},"type":"Feature"},
	{"geometry":{"coordinates":[3.792542,51.082864],"type":"Point"},"properties":{"osm_id":"6186313398","tag":{"amenity":"waste_basket"}},"type":"Feature"},
	{"geometry":{"coordinates":[3.800167,51.08557],"type":"Point"},"properties":{"osm_id":"6186313586","tag":{"amenity":"waste_basket"}},"type":"Feature"},
	{"geometry":{"coordinates":[3.792876,51.069022],"type":"Point"},"properties":{"osm_id":"7318074487","tag":{"amenity":"waste_basket"}},"type":"Feature"},
	{"geometry":{"coordinates":[3.83766,51.096806],"type":"Point"},"properties":{"osm_id":"7797183389","tag":{"amenity":"recycling"}},"type":"Feature"},
	{"geometry":{"coordinates":[3.822508,51.098116],"type":"Point"},"properties":{"osm_id":"7911846740","tag":{"amenity":"waste_basket"}},"type":"Feature"},
	{"geometry":{"coordinates":[3.822221,51.098393],"type":"Point"},"properties":{"osm_id":"7911846752","tag":{"amenity":"waste_basket"}},"type":"Feature"}
]
}
