{
"type": "FeatureCollection",
"lastupdate": "2020-08-06T00:00:00Z",
"features": [
	{"geometry":{"coordinates":[3.799738,51.085664],"type":"Point"},"properties":{"osm_id":"6186313286","tag":{"amenity":"recycling","location":"overground","recycling_type":"container"}},"type":"Feature"},
	{"geometry":{"coordinates":[3.800014,51.085741],"type":"Point"},"properties":{"osm_id":"6186313387","tag":{"amenity":"waste_basket"}},"type":"Feature"},
	{"geometry":{"coordinates":[3.792541,51.082864],"type":"Point"},"properties":{"osm_id":"6186313398","tag":{"amenity":"waste_basket"}},"type":"Feature"},
	{"geometry":{"coordinates":[3.800167,51.085569],"type":"Point"},"properties":{"osm_id":"6186313586","tag":{"amenity":"waste_basket"}},"type":"Feature"},
	{"geometry":{"coordinates":[3.792876,51.069021],"type":"Point"},"properties":{"osm_id":"7318074487","tag":{"amenity":"waste_basket"}},"type":"Feature"}
]
}
