{
"type": "FeatureCollection",
"features": [
	{"geometry":{"coordinates":[3.799738,51.085664],"type":"Point"},"properties":{"osm_id":"6186313286","tag":{"amenity":"recycling","location":"overground","recycling_type":"container"}},"type":"Feature"},
	{"geometry":{"coordinates":[3.800014,51.085741],"type":"Point"},"properties":{"osm_id":"6186313387","tag":{"amenity":"waste_basket"}},"type":"Feature"},
	{"geometry":{"coordinates":[3.792541,51.082864],"type":"Point"},"properties":{"osm_id":"6186313398","tag":{"amenity":"waste_basket"}},"type":"Feature"},
	{"geometry":{"coordinates":[3.800167,51.085569],"type":"Point"},"properties":{"osm_id":"6186313586","tag":{"amenity":"waste_basket"}},"type":"Feature"},
	{"geometry":{"coordinates":[3.792876,51.069021],"type":"Point"},"properties":{"osm_id":"7318074487","tag":{"amenity":"waste_basket"}},"type":"Feature"},
	{"geometry":{"coordinates":[3.837659,51.096805],"type":"Point"},"properties":{"osm_id":"7797183389","tag":{"amenity":"recycling"}},"type":"Feature"},
	{"geometry":{"coordinates":[3.822507,51.098116],"type":"Point"},"properties":{"osm_id":"7911846740","tag":{"amenity":"waste_basket"}},"type":"Feature"},
	{"geometry":{"coordinates":[3.822221,51.098393],"type":"Point"},"properties":{"osm_id":"7911846752","tag":{"amenity":"waste_basket"}},"type":"Feature"},
	{"geometry":{"coordinates":[3.811603,51.089622],"type":"Point"},"properties":{"osm_id":"8953902018","tag":{"amenity":"recycling","recycling_type":"container"}},"type":"Feature"},
	{"geometry":{"coordinates":[3.830929,51.070849],"type":"Point"},"properties":{"osm_id":"8972237218","tag":{"amenity":"recycling","recycling_type":"container"}},"type":"Feature"}
]
}
