{
"type": "FeatureCollection",
"features": [
	{"geometry":{"coordinates":[8.503473,51.574254],"type":"Point"},"properties":{"name":"Mutter Eiche","osm_id":"2087790918","tag":{"genus":"Quercus","genus:de":"Eiche","leaf_cycle":"deciduous","leaf_type":"broadleaved","natural":"tree"}},"type":"Feature"},
	{"geometry":{"coordinates":[8.515859,51.593122],"type":"Point"},"properties":{"osm_id":"3239247394","tag":{"leaf_cycle":"deciduous","leaf_type":"broadleaved","natural":"tree"}},"type":"Feature"},
	{"geometry":{"coordinates":[8.516003,51.59376],"type":"Point"},"properties":{"osm_id":"3239247408","tag":{"leaf_cycle":"deciduous","leaf_type":"broadleaved","natural":"tree"}},"type":"Feature"},
	{"geometry":{"coordinates":[8.520681,51.594259],"type":"Point"},"properties":{"osm_id":"3239247418","tag":{"leaf_cycle":"deciduous","leaf_type":"broadleaved","natural":"tree"}},"type":"Feature"},
	{"geometry":{"coordinates":[8.521006,51.59577],"type":"Point"},"properties":{"osm_id":"3239247565","tag":{"leaf_cycle":"deciduous","leaf_type":"broadleaved","natural":"tree"}},"type":"Feature"},
	{"geometry":{"coordinates":[8.524362,51.608515],"type":"Point"},"properties":{"osm_id":"7553585259","tag":{"leaf_cycle":"deciduous","leaf_type":"broadleaved","natural":"tree"}},"type":"Feature"}
]
}
