{
"type": "FeatureCollection",
"features": [
	{"geometry":{"coordinates":[8.464561,50.910251],"type":"Point"},"properties":{"name":"Leipziglinde","osm_id":"2407088231","tag":{"leaf_type":"broadleaved","natural":"tree","start_date":"1913"}},"type":"Feature"},
	{"geometry":{"coordinates":[8.475962,50.955919],"type":"Point"},"properties":{"osm_id":"4423230241","tag":{"natural":"tree"}},"type":"Feature"},
	{"geometry":{"coordinates":[8.460393,50.912084],"type":"Point"},"properties":{"osm_id":"6488247865","tag":{"natural":"tree"}},"type":"Feature"},
	{"geometry":{"coordinates":[8.460336,50.912013],"type":"Point"},"properties":{"osm_id":"6488247866","tag":{"natural":"tree"}},"type":"Feature"},
	{"geometry":{"coordinates":[8.460575,50.912245],"type":"Point"},"properties":{"osm_id":"6488247867","tag":{"natural":"tree"}},"type":"Feature"},
	{"geometry":{"coordinates":[8.460543,50.912278],"type":"Point"},"properties":{"osm_id":"6488247868","tag":{"natural":"tree"}},"type":"Feature"},
	{"geometry":{"coordinates":[8.460716,50.912315],"type":"Point"},"properties":{"osm_id":"6488247869","tag":{"natural":"tree"}},"type":"Feature"},
	{"geometry":{"coordinates":[8.460948,50.912195],"type":"Point"},"properties":{"osm_id":"6488247870","tag":{"natural":"tree"}},"type":"Feature"},
	{"geometry":{"coordinates":[8.460692,50.912411],"type":"Point"},"properties":{"osm_id":"6488247871","tag":{"natural":"tree"}},"type":"Feature"},
	{"geometry":{"coordinates":[8.459967,50.912314],"type":"Point"},"properties":{"osm_id":"6488247872","tag":{"natural":"tree"}},"type":"Feature"},
	{"geometry":{"coordinates":[8.465443,50.915136],"type":"Point"},"properties":{"osm_id":"6488247879","tag":{"natural":"tree"}},"type":"Feature"},
	{"geometry":{"coordinates":[8.465616,50.914599],"type":"Point"},"properties":{"osm_id":"6488247880","tag":{"natural":"tree"}},"type":"Feature"},
	{"geometry":{"coordinates":[8.465681,50.914601],"type":"Point"},"properties":{"osm_id":"6488247881","tag":{"natural":"tree"}},"type":"Feature"},
	{"geometry":{"coordinates":[8.471662,50.912913],"type":"Point"},"properties":{"osm_id":"6488247908","tag":{"natural":"tree"}},"type":"Feature"},
	{"geometry":{"coordinates":[8.47154,50.912832],"type":"Point"},"properties":{"osm_id":"6488247909","tag":{"natural":"tree"}},"type":"Feature"},
	{"geometry":{"coordinates":[8.470906,50.912668],"type":"Point"},"properties":{"osm_id":"6488247910","tag":{"natural":"tree"}},"type":"Feature"},
	{"geometry":{"coordinates":[8.470555,50.912763],"type":"Point"},"properties":{"osm_id":"6488247929","tag":{"natural":"tree"}},"type":"Feature"},
	{"geometry":{"coordinates":[8.470579,50.912681],"type":"Point"},"properties":{"osm_id":"6488247930","tag":{"natural":"tree"}},"type":"Feature"}
]
}
