{
"type": "FeatureCollection",
"features": [
	{"geometry":{"coordinates":[8.46456,50.91025],"type":"Point"},"properties":{"name":"Leipziglinde","osm_id":"2407088231","tag":{"leaf_type":"broadleaved","natural":"tree","start_date":"1913"}},"type":"Feature"},
	{"geometry":{"coordinates":[8.475962,50.955919],"type":"Point"},"properties":{"osm_id":"4423230241","tag":{"natural":"tree"}},"type":"Feature"},
	{"geometry":{"coordinates":[8.460393,50.912084],"type":"Point"},"properties":{"osm_id":"6488247865","tag":{"natural":"tree"}},"type":"Feature"},
	{"geometry":{"coordinates":[8.460335,50.912012],"type":"Point"},"properties":{"osm_id":"6488247866","tag":{"natural":"tree"}},"type":"Feature"},
	{"geometry":{"coordinates":[8.460575,50.912244],"type":"Point"},"properties":{"osm_id":"6488247867","tag":{"natural":"tree"}},"type":"Feature"},
	{"geometry":{"coordinates":[8.460542,50.912277],"type":"Point"},"properties":{"osm_id":"6488247868","tag":{"natural":"tree"}},"type":"Feature"},
	{"geometry":{"coordinates":[8.460716,50.912314],"type":"Point"},"properties":{"osm_id":"6488247869","tag":{"natural":"tree"}},"type":"Feature"},
	{"geometry":{"coordinates":[8.460947,50.912195],"type":"Point"},"properties":{"osm_id":"6488247870","tag":{"natural":"tree"}},"type":"Feature"},
	{"geometry":{"coordinates":[8.460691,50.912411],"type":"Point"},"properties":{"osm_id":"6488247871","tag":{"natural":"tree"}},"type":"Feature"},
	{"geometry":{"coordinates":[8.459966,50.912313],"type":"Point"},"properties":{"osm_id":"6488247872","tag":{"natural":"tree"}},"type":"Feature"},
	{"geometry":{"coordinates":[8.465443,50.915136],"type":"Point"},"properties":{"osm_id":"6488247879","tag":{"natural":"tree"}},"type":"Feature"},
	{"geometry":{"coordinates":[8.465615,50.914599],"type":"Point"},"properties":{"osm_id":"6488247880","tag":{"natural":"tree"}},"type":"Feature"},
	{"geometry":{"coordinates":[8.46568,50.9146],"type":"Point"},"properties":{"osm_id":"6488247881","tag":{"natural":"tree"}},"type":"Feature"},
	{"geometry":{"coordinates":[8.471662,50.912913],"type":"Point"},"properties":{"osm_id":"6488247908","tag":{"natural":"tree"}},"type":"Feature"},
	{"geometry":{"coordinates":[8.47154,50.912831],"type":"Point"},"properties":{"osm_id":"6488247909","tag":{"natural":"tree"}},"type":"Feature"},
	{"geometry":{"coordinates":[8.470905,50.912667],"type":"Point"},"properties":{"osm_id":"6488247910","tag":{"natural":"tree"}},"type":"Feature"},
	{"geometry":{"coordinates":[8.470554,50.912762],"type":"Point"},"properties":{"osm_id":"6488247929","tag":{"natural":"tree"}},"type":"Feature"},
	{"geometry":{"coordinates":[8.470578,50.912681],"type":"Point"},"properties":{"osm_id":"6488247930","tag":{"natural":"tree"}},"type":"Feature"},
	{"geometry":{"coordinates":[8.459813,50.912136],"type":"Point"},"properties":{"osm_id":"8808205022","tag":{"natural":"tree"}},"type":"Feature"},
	{"geometry":{"coordinates":[8.459606,50.9121],"type":"Point"},"properties":{"osm_id":"8808205114","tag":{"natural":"tree"}},"type":"Feature"},
	{"geometry":{"coordinates":[8.458991,50.912013],"type":"Point"},"properties":{"osm_id":"8808205124","tag":{"natural":"tree"}},"type":"Feature"},
	{"geometry":{"coordinates":[8.463797,50.919805],"type":"Point"},"properties":{"osm_id":"8833867005","tag":{"natural":"tree"}},"type":"Feature"},
	{"geometry":{"coordinates":[8.442888,50.925463],"type":"Point"},"properties":{"osm_id":"8866117631","tag":{"denotation":"natural_monument","leaf_cycle":"deciduous","leaf_type":"broadleaved","natural":"tree"}},"type":"Feature"},
	{"geometry":{"coordinates":[8.441514,50.926256],"type":"Point"},"properties":{"osm_id":"8866139103","tag":{"denotation":"urban","leaf_cycle":"deciduous","leaf_type":"broadleaved","natural":"tree"}},"type":"Feature"},
	{"geometry":{"coordinates":[8.441628,50.926288],"type":"Point"},"properties":{"osm_id":"8866139104","tag":{"denotation":"urban","leaf_cycle":"deciduous","leaf_type":"broadleaved","natural":"tree"}},"type":"Feature"},
	{"geometry":{"coordinates":[8.441749,50.926316],"type":"Point"},"properties":{"osm_id":"8866139105","tag":{"denotation":"urban","leaf_cycle":"deciduous","leaf_type":"broadleaved","natural":"tree"}},"type":"Feature"},
	{"geometry":{"coordinates":[8.441862,50.926347],"type":"Point"},"properties":{"osm_id":"8866139106","tag":{"denotation":"urban","leaf_cycle":"deciduous","leaf_type":"broadleaved","natural":"tree"}},"type":"Feature"},
	{"geometry":{"coordinates":[8.461743,50.912737],"type":"Point"},"properties":{"osm_id":"8941011936","tag":{"natural":"tree"}},"type":"Feature"}
]
}
