{
"type": "FeatureCollection",
"features": [
	{"geometry":{"coordinates":[8.515245,50.724768],"type":"Point"},"properties":{"name":"Kaiser Wilhelm Linde","osm_id":"600572716","tag":{"genus":"Tilia","genus:de":"Linde","leaf_cycle":"deciduous","leaf_type":"broadleaved","natural":"tree"}},"type":"Feature"},
	{"geometry":{"coordinates":[8.510135,50.727128],"type":"Point"},"properties":{"osm_id":"763956302","tag":{"natural":"tree"}},"type":"Feature"},
	{"geometry":{"coordinates":[8.496324,50.725924],"type":"Point"},"properties":{"osm_id":"763956418","tag":{"natural":"tree"}},"type":"Feature"},
	{"geometry":{"coordinates":[8.513779,50.735111],"type":"Point"},"properties":{"name":"Zollbuche","osm_id":"773404164","tag":{"genus":"Fagus","genus:de":"Buche","leaf_cycle":"deciduous","leaf_type":"broadleaved","natural":"tree","opening_hours":"24/7","tourism":"attraction","wheelchair":"limited"}},"type":"Feature"},
	{"geometry":{"coordinates":[8.509557,50.707382],"type":"Point"},"properties":{"name":"Dicke Eiche","osm_id":"840628012","tag":{"natural":"tree"}},"type":"Feature"},
	{"geometry":{"coordinates":[8.50241,50.707039],"type":"Point"},"properties":{"osm_id":"862885233","tag":{"natural":"tree"}},"type":"Feature"},
	{"geometry":{"coordinates":[8.480542,50.706985],"type":"Point"},"properties":{"osm_id":"864678360","tag":{"natural":"tree"}},"type":"Feature"},
	{"geometry":{"coordinates":[8.511934,50.725222],"type":"Point"},"properties":{"osm_id":"1340234425","tag":{"natural":"tree"}},"type":"Feature"},
	{"geometry":{"coordinates":[8.512301,50.725525],"type":"Point"},"properties":{"osm_id":"1340234514","tag":{"natural":"tree"}},"type":"Feature"},
	{"geometry":{"coordinates":[8.511811,50.725298],"type":"Point"},"properties":{"osm_id":"1340234718","tag":{"natural":"tree"}},"type":"Feature"},
	{"geometry":{"coordinates":[8.512105,50.725585],"type":"Point"},"properties":{"osm_id":"1340234816","tag":{"natural":"tree"}},"type":"Feature"},
	{"geometry":{"coordinates":[8.502904,50.725876],"type":"Point"},"properties":{"osm_id":"1501778449","tag":{"natural":"tree"}},"type":"Feature"},
	{"geometry":{"coordinates":[8.5049,50.726166],"type":"Point"},"properties":{"osm_id":"1501778459","tag":{"natural":"tree"}},"type":"Feature"},
	{"geometry":{"coordinates":[8.522147,50.729742],"type":"Point"},"properties":{"osm_id":"1707445316","tag":{"natural":"tree"}},"type":"Feature"},
	{"geometry":{"coordinates":[8.482643,50.686196],"type":"Point"},"properties":{"osm_id":"2904089038","tag":{"leaf_type":"broadleaved","natural":"tree"}},"type":"Feature"},
	{"geometry":{"coordinates":[8.513842,50.733532],"type":"Point"},"properties":{"osm_id":"3561095338","tag":{"leaf_cycle":"deciduous","leaf_type":"broadleaved","natural":"tree"}},"type":"Feature"},
	{"geometry":{"coordinates":[8.513858,50.733536],"type":"Point"},"properties":{"osm_id":"3561095339","tag":{"leaf_cycle":"deciduous","leaf_type":"broadleaved","natural":"tree"}},"type":"Feature"},
	{"geometry":{"coordinates":[8.513813,50.733546],"type":"Point"},"properties":{"osm_id":"3561095340","tag":{"leaf_cycle":"deciduous","leaf_type":"broadleaved","natural":"tree"}},"type":"Feature"},
	{"geometry":{"coordinates":[8.513804,50.733555],"type":"Point"},"properties":{"osm_id":"3561095342","tag":{"leaf_cycle":"deciduous","leaf_type":"broadleaved","natural":"tree"}},"type":"Feature"},
	{"geometry":{"coordinates":[8.460276,50.680875],"type":"Point"},"properties":{"osm_id":"6493421816","tag":{"natural":"tree"}},"type":"Feature"},
	{"geometry":{"coordinates":[8.472012,50.708884],"type":"Point"},"properties":{"name":"Adlereiche","osm_id":"7656603123","tag":{"natural":"tree"}},"type":"Feature"},
	{"geometry":{"coordinates":[8.510458,50.708106],"type":"Point"},"properties":{"name":"Alte Eiche","osm_id":"7656622070","tag":{"natural":"tree"}},"type":"Feature"}
]
}
