{
"type": "FeatureCollection",
"features": [
	{"geometry":{"coordinates":[8.498364,50.445437],"type":"Point"},"properties":{"name":"Wasserbuche","osm_id":"809816105","tag":{"natural":"tree"}},"type":"Feature"},
	{"geometry":{"coordinates":[8.523572,50.449346],"type":"Point"},"properties":{"osm_id":"828812463","tag":{"natural":"tree"}},"type":"Feature"},
	{"geometry":{"coordinates":[8.469716,50.411903],"type":"Point"},"properties":{"name":"Forstmeister-Siegfried-Eiche","osm_id":"912078858","tag":{"leaf_cycle":"deciduous","leaf_type":"broadleaved","natural":"tree","tourism":"attraction"}},"type":"Feature"},
	{"geometry":{"coordinates":[8.481676,50.449284],"type":"Point"},"properties":{"osm_id":"7785460950","tag":{"denotation":"landmark","leaf_cycle":"deciduous","leaf_type":"broadleaved","natural":"tree"}},"type":"Feature"},
	{"geometry":{"coordinates":[8.480997,50.449175],"type":"Point"},"properties":{"osm_id":"7785460951","tag":{"denotation":"landmark","leaf_cycle":"deciduous","leaf_type":"broadleaved","natural":"tree"}},"type":"Feature"},
	{"geometry":{"coordinates":[8.475498,50.446662],"type":"Point"},"properties":{"osm_id":"7785460952","tag":{"denotation":"landmark","leaf_cycle":"deciduous","leaf_type":"broadleaved","natural":"tree"}},"type":"Feature"},
	{"geometry":{"coordinates":[8.478248,50.443519],"type":"Point"},"properties":{"osm_id":"7785460953","tag":{"denotation":"landmark","leaf_cycle":"deciduous","leaf_type":"broadleaved","natural":"tree"}},"type":"Feature"},
	{"geometry":{"coordinates":[8.517193,50.447918],"type":"Point"},"properties":{"osm_id":"8911316961","tag":{"circumference":"4.2","denotation":"natural_monument","genus":"Linde","height":"10","leaf_cycle":"deciduous","leaf_type":"broadleaved","natural":"tree","start_date":"1500-1600","url":"www.lahn-dill-kreis.de/fileadmin/user_upload/ldk/LDK/Buergerservice/Bauen___Naturschutz/Naturdenkmale/134_ND_28_Linde_Waldsolms_Griedelbach.pdf"}},"type":"Feature"}
]
}
