{
"type": "FeatureCollection",
"features": [
	{"geometry":{"coordinates":[8.498365,50.445437],"type":"Point"},"properties":{"name":"Wasserbuche","osm_id":"809816105","tag":{"natural":"tree"}},"type":"Feature"},
	{"geometry":{"coordinates":[8.523572,50.449347],"type":"Point"},"properties":{"osm_id":"828812463","tag":{"natural":"tree"}},"type":"Feature"},
	{"geometry":{"coordinates":[8.469716,50.411903],"type":"Point"},"properties":{"name":"Forstmeister-Siegfried-Eiche","osm_id":"912078858","tag":{"leaf_cycle":"deciduous","leaf_type":"broadleaved","natural":"tree","tourism":"attraction"}},"type":"Feature"},
	{"geometry":{"coordinates":[8.481676,50.449285],"type":"Point"},"properties":{"osm_id":"7785460950","tag":{"denotation":"landmark","leaf_cycle":"deciduous","leaf_type":"broadleaved","natural":"tree"}},"type":"Feature"},
	{"geometry":{"coordinates":[8.480997,50.449175],"type":"Point"},"properties":{"osm_id":"7785460951","tag":{"denotation":"landmark","leaf_cycle":"deciduous","leaf_type":"broadleaved","natural":"tree"}},"type":"Feature"},
	{"geometry":{"coordinates":[8.475499,50.446663],"type":"Point"},"properties":{"osm_id":"7785460952","tag":{"denotation":"landmark","leaf_cycle":"deciduous","leaf_type":"broadleaved","natural":"tree"}},"type":"Feature"},
	{"geometry":{"coordinates":[8.478248,50.44352],"type":"Point"},"properties":{"osm_id":"7785460953","tag":{"denotation":"landmark","leaf_cycle":"deciduous","leaf_type":"broadleaved","natural":"tree"}},"type":"Feature"}
]
}
