{
"type": "FeatureCollection",
"features": [
	{"geometry":{"coordinates":[8.459924,50.360706],"type":"Point"},"properties":{"name":"Dicke Eiche","osm_id":"360605261","tag":{"leaf_type":"broadleaved","natural":"tree"}},"type":"Feature"},
	{"geometry":{"coordinates":[8.498825,50.370102],"type":"Point"},"properties":{"osm_id":"2367674345","tag":{"denotation":"landmark","natural":"tree"}},"type":"Feature"},
	{"geometry":{"coordinates":[8.501492,50.395408],"type":"Point"},"properties":{"name":"Meineidsbuche","osm_id":"2387057094","tag":{"natural":"tree","tourism":"attraction"}},"type":"Feature"}
]
}
