{
"type": "FeatureCollection",
"features": [
	{"geometry":{"coordinates":[8.438341,48.150867],"type":"Point"},"properties":{"name":"Eiche","osm_id":"293258482","tag":{"natural":"tree"}},"type":"Feature"},
	{"geometry":{"coordinates":[8.480463,48.135553],"type":"Point"},"properties":{"osm_id":"4102413282","tag":{"natural":"tree"}},"type":"Feature"},
	{"geometry":{"coordinates":[8.502191,48.132116],"type":"Point"},"properties":{"osm_id":"4102466684","tag":{"denotation":"urban","leaf_cycle":"deciduous","leaf_type":"broadleaved","natural":"tree"}},"type":"Feature"},
	{"geometry":{"coordinates":[8.480152,48.133695],"type":"Point"},"properties":{"osm_id":"4102469219","tag":{"leaf_cycle":"deciduous","leaf_type":"broadleaved","natural":"tree"}},"type":"Feature"}
]
}
