{
"type": "FeatureCollection",
"features": [
	{"geometry":{"coordinates":[8.438341,48.150866],"type":"Point"},"properties":{"name":"Eiche","osm_id":"293258482","tag":{"natural":"tree"}},"type":"Feature"},
	{"geometry":{"coordinates":[8.480463,48.135552],"type":"Point"},"properties":{"osm_id":"4102413282","tag":{"natural":"tree"}},"type":"Feature"},
	{"geometry":{"coordinates":[8.502191,48.132115],"type":"Point"},"properties":{"osm_id":"4102466684","tag":{"denotation":"urban","leaf_cycle":"deciduous","leaf_type":"broadleaved","natural":"tree"}},"type":"Feature"},
	{"geometry":{"coordinates":[8.480151,48.133694],"type":"Point"},"properties":{"osm_id":"4102469219","tag":{"leaf_cycle":"deciduous","leaf_type":"broadleaved","natural":"tree"}},"type":"Feature"},
	{"geometry":{"coordinates":[8.451632,48.128719],"type":"Point"},"properties":{"name":"Wetterfichte","osm_id":"8235833378","tag":{"natural":"tree"}},"type":"Feature"}
]
}
