{
"type": "FeatureCollection",
"features": [
	{"geometry":{"coordinates":[8.457996,39.69463],"type":"Point"},"properties":{"name":"Ginepro","osm_id":"2458077517","tag":{"name:botanical":"Juniperus communis","natural":"tree"}},"type":"Feature"}
]
}
