{
"type": "FeatureCollection",
"features": [
	{"geometry":{"coordinates":[9.149518,49.345164],"type":"Point"},"properties":{"name":"Geistereiche","osm_id":"708125510","tag":{"genus":"Quercus","genus:de":"Eiche","leaf_cycle":"deciduous","leaf_type":"broadleaved","natural":"tree"}},"type":"Feature"},
	{"geometry":{"coordinates":[9.147145,49.353675],"type":"Point"},"properties":{"osm_id":"2020649871","tag":{"natural":"tree"}},"type":"Feature"},
	{"geometry":{"coordinates":[9.16834,49.335984],"type":"Point"},"properties":{"osm_id":"6932818881","tag":{"natural":"tree"}},"type":"Feature"},
	{"geometry":{"coordinates":[9.171239,49.33285],"type":"Point"},"properties":{"osm_id":"6932835411","tag":{"natural":"tree"}},"type":"Feature"},
	{"geometry":{"coordinates":[9.169102,49.332402],"type":"Point"},"properties":{"osm_id":"6932835412","tag":{"natural":"tree"}},"type":"Feature"},
	{"geometry":{"coordinates":[9.165703,49.332557],"type":"Point"},"properties":{"osm_id":"6932835462","tag":{"natural":"tree"}},"type":"Feature"},
	{"geometry":{"coordinates":[9.166122,49.332605],"type":"Point"},"properties":{"osm_id":"6932835463","tag":{"natural":"tree"}},"type":"Feature"},
	{"geometry":{"coordinates":[9.166708,49.332766],"type":"Point"},"properties":{"osm_id":"6932835464","tag":{"natural":"tree"}},"type":"Feature"},
	{"geometry":{"coordinates":[9.167084,49.332642],"type":"Point"},"properties":{"osm_id":"6932835465","tag":{"natural":"tree"}},"type":"Feature"},
	{"geometry":{"coordinates":[9.167336,49.332551],"type":"Point"},"properties":{"osm_id":"6932835466","tag":{"natural":"tree"}},"type":"Feature"},
	{"geometry":{"coordinates":[9.14738,49.325312],"type":"Point"},"properties":{"osm_id":"6935626993","tag":{"natural":"tree"}},"type":"Feature"},
	{"geometry":{"coordinates":[9.147254,49.325442],"type":"Point"},"properties":{"osm_id":"6935626994","tag":{"natural":"tree"}},"type":"Feature"},
	{"geometry":{"coordinates":[9.173299,49.341972],"type":"Point"},"properties":{"osm_id":"6936795201","tag":{"natural":"tree"}},"type":"Feature"},
	{"geometry":{"coordinates":[9.175119,49.341789],"type":"Point"},"properties":{"osm_id":"6936795225","tag":{"natural":"tree"}},"type":"Feature"},
	{"geometry":{"coordinates":[9.170088,49.343054],"type":"Point"},"properties":{"osm_id":"6937514140","tag":{"natural":"tree"}},"type":"Feature"},
	{"geometry":{"coordinates":[9.178676,49.340836],"type":"Point"},"properties":{"osm_id":"6937522100","tag":{"natural":"tree"}},"type":"Feature"},
	{"geometry":{"coordinates":[9.178516,49.34066],"type":"Point"},"properties":{"osm_id":"6937522101","tag":{"natural":"tree"}},"type":"Feature"},
	{"geometry":{"coordinates":[9.174494,49.345646],"type":"Point"},"properties":{"osm_id":"6937901582","tag":{"natural":"tree"}},"type":"Feature"}
]
}
