{
"type": "FeatureCollection",
"features": [
	{"geometry":{"coordinates":[9.149519,49.345165],"type":"Point"},"properties":{"name":"Geistereiche","osm_id":"708125510","tag":{"genus":"Quercus","genus:de":"Eiche","leaf_cycle":"deciduous","leaf_type":"broadleaved","natural":"tree"}},"type":"Feature"},
	{"geometry":{"coordinates":[9.147146,49.353676],"type":"Point"},"properties":{"osm_id":"2020649871","tag":{"natural":"tree"}},"type":"Feature"},
	{"geometry":{"coordinates":[9.168341,49.335985],"type":"Point"},"properties":{"osm_id":"6932818881","tag":{"natural":"tree"}},"type":"Feature"},
	{"geometry":{"coordinates":[9.171239,49.332851],"type":"Point"},"properties":{"osm_id":"6932835411","tag":{"natural":"tree"}},"type":"Feature"},
	{"geometry":{"coordinates":[9.169103,49.332403],"type":"Point"},"properties":{"osm_id":"6932835412","tag":{"natural":"tree"}},"type":"Feature"},
	{"geometry":{"coordinates":[9.165704,49.332558],"type":"Point"},"properties":{"osm_id":"6932835462","tag":{"natural":"tree"}},"type":"Feature"},
	{"geometry":{"coordinates":[9.166123,49.332606],"type":"Point"},"properties":{"osm_id":"6932835463","tag":{"natural":"tree"}},"type":"Feature"},
	{"geometry":{"coordinates":[9.166708,49.332767],"type":"Point"},"properties":{"osm_id":"6932835464","tag":{"natural":"tree"}},"type":"Feature"},
	{"geometry":{"coordinates":[9.167084,49.332642],"type":"Point"},"properties":{"osm_id":"6932835465","tag":{"natural":"tree"}},"type":"Feature"},
	{"geometry":{"coordinates":[9.167337,49.332552],"type":"Point"},"properties":{"osm_id":"6932835466","tag":{"natural":"tree"}},"type":"Feature"},
	{"geometry":{"coordinates":[9.147381,49.325313],"type":"Point"},"properties":{"osm_id":"6935626993","tag":{"natural":"tree"}},"type":"Feature"},
	{"geometry":{"coordinates":[9.147255,49.325442],"type":"Point"},"properties":{"osm_id":"6935626994","tag":{"natural":"tree"}},"type":"Feature"},
	{"geometry":{"coordinates":[9.173299,49.341972],"type":"Point"},"properties":{"osm_id":"6936795201","tag":{"natural":"tree"}},"type":"Feature"},
	{"geometry":{"coordinates":[9.175119,49.341789],"type":"Point"},"properties":{"osm_id":"6936795225","tag":{"natural":"tree"}},"type":"Feature"},
	{"geometry":{"coordinates":[9.170088,49.343055],"type":"Point"},"properties":{"osm_id":"6937514140","tag":{"natural":"tree"}},"type":"Feature"},
	{"geometry":{"coordinates":[9.178676,49.340837],"type":"Point"},"properties":{"osm_id":"6937522100","tag":{"natural":"tree"}},"type":"Feature"},
	{"geometry":{"coordinates":[9.178517,49.34066],"type":"Point"},"properties":{"osm_id":"6937522101","tag":{"natural":"tree"}},"type":"Feature"},
	{"geometry":{"coordinates":[9.174494,49.345647],"type":"Point"},"properties":{"osm_id":"6937901582","tag":{"natural":"tree"}},"type":"Feature"}
]
}
