{
"type": "FeatureCollection",
"features": [
	{"geometry":{"coordinates":[9.195181,45.023671],"type":"Point"},"properties":{"name":"Cedro secolare","osm_id":"1806337662","tag":{"natural":"tree"}},"type":"Feature"},
	{"geometry":{"coordinates":[9.155362,45.012483],"type":"Point"},"properties":{"osm_id":"5954065115","tag":{"natural":"tree"}},"type":"Feature"}
]
}
