{
"type": "FeatureCollection",
"features": [
	{"geometry":{"coordinates":[-108.159827,32.854442],"type":"Point"},"properties":{"name":"Big Tree","osm_id":"2510956968","tag":{"natural":"tree"}},"type":"Feature"}
]
}
