{
"type": "FeatureCollection",
"features": [
	{"geometry":{"coordinates":[-108.159828,32.854443],"type":"Point"},"properties":{"name":"Big Tree","osm_id":"2510956968","tag":{"natural":"tree"}},"type":"Feature"}
]
}
