{
"type": "FeatureCollection",
"features": [
	{"geometry":{"coordinates":[7.475606,51.334638],"type":"Point"},"properties":{"osm_id":"676094031","tag":{"amenity":"recycling","location":"overground","recycling:glass":"yes","recycling:paper":"yes","recycling_type":"container"}},"type":"Feature"},
	{"geometry":{"coordinates":[7.496925,51.332868],"type":"Point"},"properties":{"osm_id":"1268999263","tag":{"amenity":"waste_basket"}},"type":"Feature"},
	{"geometry":{"coordinates":[7.492751,51.328123],"type":"Point"},"properties":{"osm_id":"1268999264","tag":{"amenity":"waste_basket"}},"type":"Feature"},
	{"geometry":{"coordinates":[7.488649,51.330033],"type":"Point"},"properties":{"osm_id":"1268999265","tag":{"amenity":"waste_basket"}},"type":"Feature"},
	{"geometry":{"coordinates":[7.504337,51.334129],"type":"Point"},"properties":{"osm_id":"1268999280","tag":{"amenity":"waste_basket"}},"type":"Feature"},
	{"geometry":{"coordinates":[7.500578,51.334256],"type":"Point"},"properties":{"osm_id":"1268999296","tag":{"amenity":"waste_basket"}},"type":"Feature"},
	{"geometry":{"coordinates":[7.521871,51.291747],"type":"Point"},"properties":{"osm_id":"1756949052","tag":{"amenity":"recycling","recycling:glass":"yes","recycling:paper":"yes"}},"type":"Feature"},
	{"geometry":{"coordinates":[7.481429,51.330591],"type":"Point"},"properties":{"osm_id":"2354151415","tag":{"amenity":"waste_basket"}},"type":"Feature"},
	{"geometry":{"coordinates":[7.481044,51.331065],"type":"Point"},"properties":{"osm_id":"2354151419","tag":{"amenity":"waste_basket"}},"type":"Feature"},
	{"geometry":{"coordinates":[7.48042,51.332109],"type":"Point"},"properties":{"osm_id":"2354151423","tag":{"amenity":"waste_basket"}},"type":"Feature"},
	{"geometry":{"coordinates":[7.490021,51.324783],"type":"Point"},"properties":{"osm_id":"2374722403","tag":{"amenity":"waste_basket"}},"type":"Feature"},
	{"geometry":{"coordinates":[7.49863,51.340416],"type":"Point"},"properties":{"osm_id":"2374722558","tag":{"amenity":"recycling","recycling:clothes":"yes","recycling:glass":"yes","recycling:paper":"yes","recycling_type":"container"}},"type":"Feature"},
	{"geometry":{"coordinates":[7.482668,51.329383],"type":"Point"},"properties":{"osm_id":"3695166624","tag":{"access":"private","amenity":"recycling","recycling_type":"container"}},"type":"Feature"},
	{"geometry":{"coordinates":[7.483393,51.325115],"type":"Point"},"properties":{"osm_id":"4428024083","tag":{"amenity":"waste_basket"}},"type":"Feature"},
	{"geometry":{"coordinates":[7.483126,51.328021],"type":"Point"},"properties":{"osm_id":"4988374283","tag":{"amenity":"waste_basket"}},"type":"Feature"},
	{"geometry":{"coordinates":[7.482853,51.322885],"type":"Point"},"properties":{"osm_id":"4988374284","tag":{"amenity":"waste_basket"}},"type":"Feature"}
]
}
