{
"type": "FeatureCollection",
"lastupdate": "2020-08-02T00:00:00Z",
"features": [
	{"geometry":{"coordinates":[7.475606,51.334638],"type":"Point"},"properties":{"osm_id":"676094031","tag":{"amenity":"recycling","location":"overground","recycling:glass":"yes","recycling:paper":"yes","recycling_type":"container"}},"type":"Feature"},
	{"geometry":{"coordinates":[7.496925,51.332868],"type":"Point"},"properties":{"osm_id":"1268999263","tag":{"amenity":"waste_basket"}},"type":"Feature"},
	{"geometry":{"coordinates":[7.492751,51.328122],"type":"Point"},"properties":{"osm_id":"1268999264","tag":{"amenity":"waste_basket"}},"type":"Feature"},
	{"geometry":{"coordinates":[7.488649,51.330033],"type":"Point"},"properties":{"osm_id":"1268999265","tag":{"amenity":"waste_basket"}},"type":"Feature"},
	{"geometry":{"coordinates":[7.504337,51.334128],"type":"Point"},"properties":{"osm_id":"1268999280","tag":{"amenity":"waste_basket"}},"type":"Feature"},
	{"geometry":{"coordinates":[7.500578,51.334256],"type":"Point"},"properties":{"osm_id":"1268999296","tag":{"amenity":"waste_basket"}},"type":"Feature"},
	{"geometry":{"coordinates":[7.521871,51.291747],"type":"Point"},"properties":{"osm_id":"1756949052","tag":{"amenity":"recycling","recycling:glass":"yes","recycling:paper":"yes"}},"type":"Feature"},
	{"geometry":{"coordinates":[7.481429,51.33059],"type":"Point"},"properties":{"osm_id":"2354151415","tag":{"amenity":"waste_basket"}},"type":"Feature"},
	{"geometry":{"coordinates":[7.481044,51.331065],"type":"Point"},"properties":{"osm_id":"2354151419","tag":{"amenity":"waste_basket"}},"type":"Feature"},
	{"geometry":{"coordinates":[7.480419,51.332109],"type":"Point"},"properties":{"osm_id":"2354151423","tag":{"amenity":"waste_basket"}},"type":"Feature"},
	{"geometry":{"coordinates":[7.490021,51.324782],"type":"Point"},"properties":{"osm_id":"2374722403","tag":{"amenity":"waste_basket"}},"type":"Feature"},
	{"geometry":{"coordinates":[7.49863,51.340416],"type":"Point"},"properties":{"osm_id":"2374722558","tag":{"amenity":"recycling","recycling:clothes":"yes","recycling:glass":"yes","recycling:paper":"yes","recycling_type":"container"}},"type":"Feature"},
	{"geometry":{"coordinates":[7.482667,51.329382],"type":"Point"},"properties":{"osm_id":"3695166624","tag":{"access":"private","amenity":"recycling","recycling_type":"container"}},"type":"Feature"},
	{"geometry":{"coordinates":[7.483393,51.325114],"type":"Point"},"properties":{"osm_id":"4428024083","tag":{"amenity":"waste_basket"}},"type":"Feature"},
	{"geometry":{"coordinates":[7.483126,51.32802],"type":"Point"},"properties":{"osm_id":"4988374283","tag":{"amenity":"waste_basket"}},"type":"Feature"},
	{"geometry":{"coordinates":[7.482852,51.322884],"type":"Point"},"properties":{"osm_id":"4988374284","tag":{"amenity":"waste_basket"}},"type":"Feature"}
]
}
