{
"type": "FeatureCollection",
"lastupdate": "2020-08-01T00:00:00Z",
"features": [
	{"geometry":{"coordinates":[7.536521,50.01252],"type":"Point"},"properties":{"osm_id":"302907596","tag":{"amenity":"recycling","recycling:glass":"yes","recycling_type":"container"}},"type":"Feature"},
	{"geometry":{"coordinates":[7.54547,50.04438],"type":"Point"},"properties":{"osm_id":"322521441","tag":{"amenity":"recycling","location":"overground","recycling:clothes":"yes","recycling:glass_bottles":"yes","recycling_type":"container"}},"type":"Feature"},
	{"geometry":{"coordinates":[7.502614,50.039012],"type":"Point"},"properties":{"osm_id":"5842144229","tag":{"amenity":"waste_basket"}},"type":"Feature"}
]
}
