{
"type": "FeatureCollection",
"features": [
	{"geometry":{"coordinates":[7.47447,48.742334],"type":"Point"},"properties":{"osm_id":"3321536998","tag":{"addr:city":"Lupstein","addr:postcode":"67490","addr:street":"Rue Principale","amenity":"recycling","recycling:cans":"no","recycling:clothes":"yes","recycling:glass_bottles":"yes","recycling:paper":"yes","recycling_type":"container"}},"type":"Feature"},
	{"geometry":{"coordinates":[7.526024,48.748643],"type":"Point"},"properties":{"osm_id":"3339553169","tag":{"addr:city":"Melsheim","addr:postcode":"67270","addr:street":"Rue du Stade","amenity":"recycling"}},"type":"Feature"},
	{"geometry":{"coordinates":[7.515056,48.732261],"type":"Point"},"properties":{"osm_id":"3465161041","tag":{"amenity":"recycling","recycling_type":"container"}},"type":"Feature"},
	{"geometry":{"coordinates":[7.507326,48.745905],"type":"Point"},"properties":{"osm_id":"3767104461","tag":{"amenity":"waste_basket"}},"type":"Feature"},
	{"geometry":{"coordinates":[7.507692,48.745893],"type":"Point"},"properties":{"osm_id":"3767105084","tag":{"amenity":"waste_basket"}},"type":"Feature"},
	{"geometry":{"coordinates":[7.507088,48.746025],"type":"Point"},"properties":{"osm_id":"3767105398","tag":{"amenity":"waste_basket"}},"type":"Feature"},
	{"geometry":{"coordinates":[7.485359,48.736392],"type":"Point"},"properties":{"osm_id":"3919983039","tag":{"amenity":"waste_basket"}},"type":"Feature"},
	{"geometry":{"coordinates":[7.488302,48.736898],"type":"Point"},"properties":{"osm_id":"3931676486","tag":{"amenity":"waste_basket","operator":"Commune"}},"type":"Feature"},
	{"geometry":{"coordinates":[7.515986,48.71093],"type":"Point"},"properties":{"osm_id":"6300907545","tag":{"amenity":"waste_basket"}},"type":"Feature"},
	{"geometry":{"coordinates":[7.520456,48.738078],"type":"Point"},"properties":{"osm_id":"6341828866","tag":{"amenity":"waste_basket"}},"type":"Feature"},
	{"geometry":{"coordinates":[7.520635,48.738073],"type":"Point"},"properties":{"osm_id":"6344536362","tag":{"amenity":"waste_basket"}},"type":"Feature"},
	{"geometry":{"coordinates":[7.511392,48.702969],"type":"Point"},"properties":{"osm_id":"6727149330","tag":{"amenity":"recycling","recycling_type":"container"}},"type":"Feature"},
	{"geometry":{"coordinates":[7.513947,48.707703],"type":"Point"},"properties":{"osm_id":"6776798267","tag":{"amenity":"waste_basket"}},"type":"Feature"}
]
}
