{
"type": "FeatureCollection",
"lastupdate": "2020-08-01T00:00:00Z",
"features": [
	{"geometry":{"coordinates":[7.474469,48.742333],"type":"Point"},"properties":{"osm_id":"3321536998","tag":{"addr:city":"Lupstein","addr:postcode":"67490","addr:street":"Rue Principale","amenity":"recycling","recycling:cans":"no","recycling:clothes":"yes","recycling:glass_bottles":"yes","recycling:paper":"yes","recycling_type":"container"}},"type":"Feature"},
	{"geometry":{"coordinates":[7.526023,48.748642],"type":"Point"},"properties":{"osm_id":"3339553169","tag":{"addr:city":"Melsheim","addr:postcode":"67270","addr:street":"Rue du Stade","amenity":"recycling"}},"type":"Feature"},
	{"geometry":{"coordinates":[7.515056,48.732261],"type":"Point"},"properties":{"osm_id":"3465161041","tag":{"amenity":"recycling","recycling_type":"container"}},"type":"Feature"},
	{"geometry":{"coordinates":[7.507325,48.745905],"type":"Point"},"properties":{"osm_id":"3767104461","tag":{"amenity":"waste_basket"}},"type":"Feature"},
	{"geometry":{"coordinates":[7.507691,48.745892],"type":"Point"},"properties":{"osm_id":"3767105084","tag":{"amenity":"waste_basket"}},"type":"Feature"},
	{"geometry":{"coordinates":[7.507087,48.746025],"type":"Point"},"properties":{"osm_id":"3767105398","tag":{"amenity":"waste_basket"}},"type":"Feature"},
	{"geometry":{"coordinates":[7.485359,48.736392],"type":"Point"},"properties":{"osm_id":"3919983039","tag":{"amenity":"waste_basket"}},"type":"Feature"},
	{"geometry":{"coordinates":[7.488301,48.736898],"type":"Point"},"properties":{"osm_id":"3931676486","tag":{"amenity":"waste_basket","operator":"Commune"}},"type":"Feature"},
	{"geometry":{"coordinates":[7.515985,48.710929],"type":"Point"},"properties":{"osm_id":"6300907545","tag":{"amenity":"waste_basket"}},"type":"Feature"},
	{"geometry":{"coordinates":[7.520455,48.738078],"type":"Point"},"properties":{"osm_id":"6341828866","tag":{"amenity":"waste_basket"}},"type":"Feature"},
	{"geometry":{"coordinates":[7.520635,48.738073],"type":"Point"},"properties":{"osm_id":"6344536362","tag":{"amenity":"waste_basket"}},"type":"Feature"},
	{"geometry":{"coordinates":[7.511392,48.702968],"type":"Point"},"properties":{"osm_id":"6727149330","tag":{"amenity":"recycling","recycling_type":"container"}},"type":"Feature"},
	{"geometry":{"coordinates":[7.513947,48.707702],"type":"Point"},"properties":{"osm_id":"6776798267","tag":{"amenity":"waste_basket"}},"type":"Feature"}
]
}
