{
"type": "FeatureCollection",
"features": [
	{"geometry":{"coordinates":[7.535015,47.614203],"type":"Point"},"properties":{"osm_id":"1281988478","tag":{"amenity":"recycling"}},"type":"Feature"},
	{"geometry":{"coordinates":[7.54315,47.605868],"type":"Point"},"properties":{"osm_id":"1282045554","tag":{"amenity":"recycling","location":"overground","recycling_type":"container"}},"type":"Feature"},
	{"geometry":{"coordinates":[7.533847,47.597451],"type":"Point"},"properties":{"osm_id":"4393158877","tag":{"amenity":"waste_basket"}},"type":"Feature"},
	{"geometry":{"coordinates":[7.534973,47.596185],"type":"Point"},"properties":{"osm_id":"4393159211","tag":{"amenity":"waste_basket"}},"type":"Feature"},
	{"geometry":{"coordinates":[7.558256,47.578948],"type":"Point"},"properties":{"osm_id":"4425021395","tag":{"amenity":"recycling","location":"overground","recycling_type":"container"}},"type":"Feature"},
	{"geometry":{"coordinates":[7.531415,47.579415],"type":"Point"},"properties":{"osm_id":"4509165982","tag":{"amenity":"recycling","recycling_type":"centre"}},"type":"Feature"},
	{"geometry":{"coordinates":[7.520594,47.579371],"type":"Point"},"properties":{"osm_id":"4515977700","tag":{"amenity":"recycling","recycling_type":"container"}},"type":"Feature"},
	{"geometry":{"coordinates":[7.554797,47.589646],"type":"Point"},"properties":{"osm_id":"5580635391","tag":{"amenity":"waste_basket"}},"type":"Feature"},
	{"geometry":{"coordinates":[7.552671,47.577294],"type":"Point"},"properties":{"osm_id":"5596105941","tag":{"amenity":"waste_basket"}},"type":"Feature"},
	{"geometry":{"coordinates":[7.552714,47.577211],"type":"Point"},"properties":{"osm_id":"5596105942","tag":{"amenity":"waste_basket"}},"type":"Feature"},
	{"geometry":{"coordinates":[7.550046,47.597355],"type":"Point"},"properties":{"osm_id":"5616640527","tag":{"amenity":"recycling"}},"type":"Feature"},
	{"geometry":{"coordinates":[7.556791,47.577591],"type":"Point"},"properties":{"osm_id":"5618281468","tag":{"amenity":"waste_basket"}},"type":"Feature"},
	{"geometry":{"coordinates":[7.556424,47.577747],"type":"Point"},"properties":{"osm_id":"5618281470","tag":{"amenity":"waste_basket"}},"type":"Feature"},
	{"geometry":{"coordinates":[7.55343,47.580377],"type":"Point"},"properties":{"osm_id":"5624168179","tag":{"amenity":"waste_basket"}},"type":"Feature"},
	{"geometry":{"coordinates":[7.557771,47.596516],"type":"Point"},"properties":{"osm_id":"5626173668","tag":{"amenity":"recycling"}},"type":"Feature"},
	{"geometry":{"coordinates":[7.554319,47.580549],"type":"Point"},"properties":{"osm_id":"5641377409","tag":{"amenity":"waste_basket"}},"type":"Feature"},
	{"geometry":{"coordinates":[7.552686,47.578669],"type":"Point"},"properties":{"osm_id":"5641784505","tag":{"amenity":"waste_basket"}},"type":"Feature"},
	{"geometry":{"coordinates":[7.552846,47.57848],"type":"Point"},"properties":{"osm_id":"5641784608","tag":{"amenity":"waste_basket"}},"type":"Feature"},
	{"geometry":{"coordinates":[7.556761,47.580714],"type":"Point"},"properties":{"osm_id":"5647394412","tag":{"amenity":"waste_basket"}},"type":"Feature"},
	{"geometry":{"coordinates":[7.555896,47.607435],"type":"Point"},"properties":{"osm_id":"5678429595","tag":{"amenity":"waste_basket"}},"type":"Feature"},
	{"geometry":{"coordinates":[7.555189,47.6078],"type":"Point"},"properties":{"osm_id":"5678430324","tag":{"amenity":"waste_basket"}},"type":"Feature"},
	{"geometry":{"coordinates":[7.556622,47.607335],"type":"Point"},"properties":{"osm_id":"5678430325","tag":{"amenity":"waste_basket"}},"type":"Feature"},
	{"geometry":{"coordinates":[7.524324,47.613958],"type":"Point"},"properties":{"osm_id":"5692127277","tag":{"amenity":"recycling","recycling_type":"container"}},"type":"Feature"},
	{"geometry":{"coordinates":[7.506172,47.593351],"type":"Point"},"properties":{"osm_id":"5785083265","tag":{"amenity":"recycling","recycling_type":"container"}},"type":"Feature"},
	{"geometry":{"coordinates":[7.506735,47.607046],"type":"Point"},"properties":{"osm_id":"5785083266","tag":{"amenity":"recycling","recycling_type":"container"}},"type":"Feature"},
	{"geometry":{"coordinates":[7.557561,47.59082],"type":"Point"},"properties":{"osm_id":"5887582044","tag":{"amenity":"waste_basket"}},"type":"Feature"},
	{"geometry":{"coordinates":[7.556557,47.581728],"type":"Point"},"properties":{"osm_id":"5956940485","tag":{"amenity":"waste_basket"}},"type":"Feature"},
	{"geometry":{"coordinates":[7.556023,47.582002],"type":"Point"},"properties":{"osm_id":"5956944885","tag":{"amenity":"waste_basket"}},"type":"Feature"}
]
}
