{
"type": "FeatureCollection",
"features": [
	{"geometry":{"coordinates":[7.482964,47.013584],"type":"Point"},"properties":{"osm_id":"943312098","tag":{"amenity":"recycling","location":"overground","recycling:cans":"yes","recycling:clothes":"yes","recycling:glass_bottles":"yes","recycling:scrap_metal":"yes","recycling_type":"container"}},"type":"Feature"},
	{"geometry":{"coordinates":[7.525514,47.018636],"type":"Point"},"properties":{"osm_id":"1946000841","tag":{"amenity":"recycling","recycling:cans":"yes","recycling:clothes":"yes","recycling:glass_bottles":"yes","recycling:plastic_bottles":"yes","recycling_type":"centre"}},"type":"Feature"},
	{"geometry":{"coordinates":[7.477986,46.982823],"type":"Point"},"properties":{"osm_id":"5349558512","tag":{"amenity":"recycling","recycling:cans":"yes","recycling:clothes":"yes","recycling:glass_bottles":"yes","recycling:shoes":"yes","recycling_type":"container"}},"type":"Feature"},
	{"geometry":{"coordinates":[7.492667,47.017827],"type":"Point"},"properties":{"osm_id":"5837193370","tag":{"amenity":"recycling","recycling:cans":"yes","recycling:glass_bottles":"yes","recycling_type":"container"}},"type":"Feature"},
	{"geometry":{"coordinates":[7.493126,47.016344],"type":"Point"},"properties":{"osm_id":"6328915205","tag":{"amenity":"recycling","recycling:pet":"yes","recycling_type":"container"}},"type":"Feature"},
	{"geometry":{"coordinates":[7.493137,47.016351],"type":"Point"},"properties":{"osm_id":"6328915206","tag":{"amenity":"recycling","recycling:glass":"yes","recycling_type":"container"}},"type":"Feature"},
	{"geometry":{"coordinates":[7.534519,47.019547],"type":"Point"},"properties":{"osm_id":"6516602045","tag":{"amenity":"waste_basket"}},"type":"Feature"},
	{"geometry":{"coordinates":[7.519787,46.987546],"type":"Point"},"properties":{"osm_id":"7098635730","tag":{"amenity":"waste_basket"}},"type":"Feature"},
	{"geometry":{"coordinates":[7.519204,46.990461],"type":"Point"},"properties":{"osm_id":"7098635732","tag":{"amenity":"waste_basket"}},"type":"Feature"},
	{"geometry":{"coordinates":[7.484796,47.023331],"type":"Point"},"properties":{"osm_id":"7110452157","tag":{"amenity":"waste_basket"}},"type":"Feature"},
	{"geometry":{"coordinates":[7.484977,47.018499],"type":"Point"},"properties":{"osm_id":"7110452175","tag":{"amenity":"waste_basket"}},"type":"Feature"},
	{"geometry":{"coordinates":[7.475821,47.025738],"type":"Point"},"properties":{"osm_id":"7110461214","tag":{"amenity":"waste_basket"}},"type":"Feature"},
	{"geometry":{"coordinates":[7.484963,47.018588],"type":"Point"},"properties":{"osm_id":"7389779368","tag":{"amenity":"waste_basket"}},"type":"Feature"},
	{"geometry":{"coordinates":[7.485007,47.018673],"type":"Point"},"properties":{"osm_id":"7389779377","tag":{"amenity":"waste_basket"}},"type":"Feature"},
	{"geometry":{"coordinates":[7.554734,47.016681],"type":"Point"},"properties":{"osm_id":"7394766883","tag":{"amenity":"waste_basket"}},"type":"Feature"},
	{"geometry":{"coordinates":[7.482885,47.01638],"type":"Point"},"properties":{"osm_id":"8644676349","tag":{"amenity":"recycling","opening_hours":"Mo-Sa 07:00-20:00","recycling:cans":"yes","recycling:clothes":"yes","recycling:glass_bottles":"yes","recycling:shoes":"yes","recycling_type":"container"}},"type":"Feature"},
	{"geometry":{"coordinates":[7.483592,47.015487],"type":"Point"},"properties":{"osm_id":"8644676350","tag":{"amenity":"waste_basket","waste":"trash;cigarettes"}},"type":"Feature"},
	{"geometry":{"coordinates":[7.483769,47.015665],"type":"Point"},"properties":{"osm_id":"8669171582","tag":{"amenity":"waste_basket","waste":"cigarettes;trash"}},"type":"Feature"},
	{"geometry":{"coordinates":[7.48359,47.015589],"type":"Point"},"properties":{"osm_id":"8669171584","tag":{"amenity":"waste_basket","waste":"cigarettes;trash"}},"type":"Feature"},
	{"geometry":{"coordinates":[7.479011,47.020756],"type":"Point"},"properties":{"osm_id":"9010987925","tag":{"amenity":"waste_basket"}},"type":"Feature"}
]
}
