{
"type": "FeatureCollection",
"features": [
	{"geometry":{"coordinates":[7.482965,47.013584],"type":"Point"},"properties":{"osm_id":"943312098","tag":{"amenity":"recycling","location":"overground","recycling:cans":"yes","recycling:clothes":"yes","recycling:glass_bottles":"yes","recycling:scrap_metal":"yes","recycling_type":"container"}},"type":"Feature"},
	{"geometry":{"coordinates":[7.525514,47.018636],"type":"Point"},"properties":{"osm_id":"1946000841","tag":{"amenity":"recycling","recycling:cans":"yes","recycling:clothes":"yes","recycling:glass_bottles":"yes","recycling:plastic_bottles":"yes","recycling_type":"centre"}},"type":"Feature"},
	{"geometry":{"coordinates":[7.477987,46.982824],"type":"Point"},"properties":{"osm_id":"5349558512","tag":{"amenity":"recycling","recycling:cans":"yes","recycling:clothes":"yes","recycling:glass_bottles":"yes","recycling_type":"container"}},"type":"Feature"},
	{"geometry":{"coordinates":[7.492668,47.017827],"type":"Point"},"properties":{"osm_id":"5837193370","tag":{"amenity":"recycling","recycling:glass":"yes","recycling:scrap_metal":"yes","recycling_type":"container"}},"type":"Feature"},
	{"geometry":{"coordinates":[7.493127,47.016345],"type":"Point"},"properties":{"osm_id":"6328915205","tag":{"amenity":"recycling","recycling:pet":"yes","recycling_type":"container"}},"type":"Feature"},
	{"geometry":{"coordinates":[7.493138,47.016352],"type":"Point"},"properties":{"osm_id":"6328915206","tag":{"amenity":"recycling","recycling:glass":"yes","recycling_type":"container"}},"type":"Feature"},
	{"geometry":{"coordinates":[7.53452,47.019548],"type":"Point"},"properties":{"osm_id":"6516602045","tag":{"amenity":"waste_basket"}},"type":"Feature"},
	{"geometry":{"coordinates":[7.519788,46.987546],"type":"Point"},"properties":{"osm_id":"7098635730","tag":{"amenity":"waste_basket"}},"type":"Feature"},
	{"geometry":{"coordinates":[7.519204,46.990461],"type":"Point"},"properties":{"osm_id":"7098635732","tag":{"amenity":"waste_basket"}},"type":"Feature"},
	{"geometry":{"coordinates":[7.484796,47.023332],"type":"Point"},"properties":{"osm_id":"7110452157","tag":{"amenity":"waste_basket"}},"type":"Feature"},
	{"geometry":{"coordinates":[7.484978,47.018499],"type":"Point"},"properties":{"osm_id":"7110452175","tag":{"amenity":"waste_basket"}},"type":"Feature"},
	{"geometry":{"coordinates":[7.475821,47.025738],"type":"Point"},"properties":{"osm_id":"7110461214","tag":{"amenity":"waste_basket"}},"type":"Feature"},
	{"geometry":{"coordinates":[7.484964,47.018589],"type":"Point"},"properties":{"osm_id":"7389779368","tag":{"amenity":"waste_basket"}},"type":"Feature"},
	{"geometry":{"coordinates":[7.485007,47.018674],"type":"Point"},"properties":{"osm_id":"7389779377","tag":{"amenity":"waste_basket"}},"type":"Feature"},
	{"geometry":{"coordinates":[7.554735,47.016681],"type":"Point"},"properties":{"osm_id":"7394766883","tag":{"amenity":"waste_basket"}},"type":"Feature"}
]
}
