{
"type": "FeatureCollection",
"features": [
	{"geometry":{"coordinates":[110.827125,-7.563743],"type":"Point"},"properties":{"name":"Bank Sampah Mugi Rejeki","osm_id":"6130031292","tag":{"amenity":"recycling","recycling_type":"centre"}},"type":"Feature"}
]
}
