{
"type": "FeatureCollection",
"features": [
	{"geometry":{"coordinates":[7.972172,51.943595],"type":"Point"},"properties":{"osm_id":"281039224","tag":{"amenity":"recycling","recycling:clothes":"yes","recycling:glass":"yes","recycling:glass_bottles":"yes","recycling:paper":"yes"}},"type":"Feature"},
	{"geometry":{"coordinates":[7.967489,51.917624],"type":"Point"},"properties":{"osm_id":"281558669","tag":{"amenity":"recycling","location":"overground","recycling:clothes":"yes","recycling:glass":"yes","recycling:paper":"yes","recycling_type":"container"}},"type":"Feature"},
	{"geometry":{"coordinates":[7.988787,51.941801],"type":"Point"},"properties":{"osm_id":"282047623","tag":{"amenity":"recycling","recycling:glass":"yes"}},"type":"Feature"},
	{"geometry":{"coordinates":[7.963609,51.921327],"type":"Point"},"properties":{"osm_id":"358147580","tag":{"amenity":"recycling","building":"yes","recycling:clothes":"yes","recycling:glass":"yes","recycling:paper":"yes","recycling_type":"container"}},"type":"Feature"},
	{"geometry":{"coordinates":[7.949783,51.92222],"type":"Point"},"properties":{"osm_id":"441805004","tag":{"amenity":"recycling","recycling:clothes":"yes","recycling:glass":"yes","recycling:paper":"yes","recycling_type":"container"}},"type":"Feature"},
	{"geometry":{"coordinates":[7.971553,51.929605],"type":"Point"},"properties":{"osm_id":"441805006","tag":{"amenity":"recycling","recycling:clothes":"yes","recycling:glass":"yes","recycling:paper":"yes","recycling_type":"container"}},"type":"Feature"},
	{"geometry":{"coordinates":[7.969362,51.915559],"type":"Point"},"properties":{"osm_id":"497292750","tag":{"amenity":"recycling","location":"overground","recycling_type":"container"}},"type":"Feature"},
	{"geometry":{"coordinates":[7.961021,51.923308],"type":"Point"},"properties":{"osm_id":"577794598","tag":{"amenity":"recycling","location":"overground","recycling:clothes":"yes","recycling:glass":"yes","recycling:paper":"yes","recycling_type":"container"}},"type":"Feature"},
	{"geometry":{"coordinates":[7.971046,51.921663],"type":"Point"},"properties":{"osm_id":"1039949096","tag":{"amenity":"recycling","location":"overground","recycling:clothes":"yes","recycling:glass":"yes","recycling_type":"container"}},"type":"Feature"},
	{"geometry":{"coordinates":[7.964753,51.929044],"type":"Point"},"properties":{"osm_id":"8154346426","tag":{"amenity":"recycling","recycling:glass_bottles":"yes","recycling_type":"container"}},"type":"Feature"},
	{"geometry":{"coordinates":[7.985439,51.941799],"type":"Point"},"properties":{"osm_id":"9079178972","tag":{"amenity":"waste_basket","colour":"grau","material":"metal","waste":"trash;cigarettes"}},"type":"Feature"},
	{"geometry":{"coordinates":[7.9855,51.94177],"type":"Point"},"properties":{"osm_id":"9079178973","tag":{"amenity":"waste_basket","material":"metal","waste":"trash;cigarettes"}},"type":"Feature"}
]
}
