{
"type": "FeatureCollection",
"lastupdate": "2020-07-31T00:00:00Z",
"features": [
	{"geometry":{"coordinates":[7.972172,51.943595],"type":"Point"},"properties":{"osm_id":"281039224","tag":{"amenity":"recycling","recycling:clothes":"yes","recycling:glass":"yes","recycling:glass_bottles":"yes","recycling:paper":"yes"}},"type":"Feature"},
	{"geometry":{"coordinates":[7.967489,51.917624],"type":"Point"},"properties":{"osm_id":"281558669","tag":{"amenity":"recycling","location":"overground","recycling:clothes":"yes","recycling:glass":"yes","recycling:paper":"yes","recycling_type":"container"}},"type":"Feature"},
	{"geometry":{"coordinates":[7.988787,51.941801],"type":"Point"},"properties":{"osm_id":"282047623","tag":{"amenity":"recycling","recycling:glass":"yes"}},"type":"Feature"},
	{"geometry":{"coordinates":[7.963609,51.921327],"type":"Point"},"properties":{"osm_id":"358147580","tag":{"amenity":"recycling","building":"yes","recycling:clothes":"yes","recycling:glass":"yes","recycling:paper":"yes","recycling_type":"container"}},"type":"Feature"},
	{"geometry":{"coordinates":[7.949798,51.922198],"type":"Point"},"properties":{"osm_id":"441805004","tag":{"amenity":"recycling","recycling:clothes":"yes","recycling:glass":"yes","recycling:paper":"yes","recycling_type":"container"}},"type":"Feature"},
	{"geometry":{"coordinates":[7.971494,51.929559],"type":"Point"},"properties":{"osm_id":"441805006","tag":{"amenity":"recycling","recycling:clothes":"yes","recycling:glass":"yes","recycling:paper":"yes","recycling_type":"container"}},"type":"Feature"},
	{"geometry":{"coordinates":[7.965343,51.929011],"type":"Point"},"properties":{"osm_id":"441805007","tag":{"amenity":"recycling"}},"type":"Feature"},
	{"geometry":{"coordinates":[7.969344,51.915559],"type":"Point"},"properties":{"osm_id":"497292750","tag":{"amenity":"recycling","location":"overground","recycling_type":"container"}},"type":"Feature"},
	{"geometry":{"coordinates":[7.961021,51.923308],"type":"Point"},"properties":{"osm_id":"577794598","tag":{"amenity":"recycling","location":"overground","recycling:clothes":"yes","recycling:glass":"yes","recycling:paper":"yes","recycling_type":"container"}},"type":"Feature"},
	{"geometry":{"coordinates":[7.971046,51.921663],"type":"Point"},"properties":{"osm_id":"1039949096","tag":{"amenity":"recycling","location":"overground","recycling:clothes":"yes","recycling:glass":"yes","recycling_type":"container"}},"type":"Feature"}
]
}
