{
"type": "FeatureCollection",
"features": [
	{"geometry":{"coordinates":[7.933758,51.804573],"type":"Point"},"properties":{"osm_id":"4721063849","tag":{"amenity":"recycling","location":"overground","recycling:glass_bottles":"yes","recycling_type":"container"}},"type":"Feature"},
	{"geometry":{"coordinates":[7.918862,51.820057],"type":"Point"},"properties":{"osm_id":"8458702491","tag":{"amenity":"recycling","location":"overground","recycling:clothes":"yes","recycling:glass_bottles":"yes","recycling_type":"container"}},"type":"Feature"},
	{"geometry":{"coordinates":[7.96292,51.789772],"type":"Point"},"properties":{"osm_id":"8458702492","tag":{"amenity":"recycling","location":"overground","recycling:glass_bottles":"yes","recycling_type":"container"}},"type":"Feature"}
]
}
