{
"type": "FeatureCollection",
"lastupdate": "2020-08-03T00:00:00Z",
"features": [
	{"geometry":{"coordinates":[8.64971,51.376426],"type":"Point"},"properties":{"osm_id":"832858387","tag":{"amenity":"recycling","location":"overground","recycling:glass_bottles":"yes","recycling_type":"container"}},"type":"Feature"},
	{"geometry":{"coordinates":[8.641988,51.375064],"type":"Point"},"properties":{"osm_id":"832964548","tag":{"amenity":"recycling","recycling:glass":"yes"}},"type":"Feature"},
	{"geometry":{"coordinates":[8.660611,51.35422],"type":"Point"},"properties":{"osm_id":"7417653463","tag":{"amenity":"recycling","recycling:glass_bottles":"yes","recycling_type":"container"}},"type":"Feature"},
	{"geometry":{"coordinates":[8.660628,51.354228],"type":"Point"},"properties":{"osm_id":"7417653464","tag":{"amenity":"recycling","recycling:clothes":"yes","recycling_type":"container"}},"type":"Feature"},
	{"geometry":{"coordinates":[8.661124,51.354393],"type":"Point"},"properties":{"osm_id":"7417653465","tag":{"amenity":"waste_basket"}},"type":"Feature"},
	{"geometry":{"coordinates":[8.649744,51.376384],"type":"Point"},"properties":{"osm_id":"7418800121","tag":{"amenity":"recycling","location":"overground","recycling:clothes":"yes","recycling_type":"container"}},"type":"Feature"}
]
}
