{
"type": "FeatureCollection",
"features": [
	{"geometry":{"coordinates":[8.646446,46.880846],"type":"Point"},"properties":{"osm_id":"306663030","tag":{"amenity":"recycling","location":"overground","recycling:cans":"yes","recycling:glass_bottles":"yes","recycling:glass_bottles:colour":"green/brown/white","recycling:paper":"no","recycling_type":"container"}},"type":"Feature"},
	{"geometry":{"coordinates":[8.631397,46.876347],"type":"Point"},"properties":{"osm_id":"306663496","tag":{"amenity":"recycling","location":"overground","recycling:clothes":"yes","recycling_type":"container"}},"type":"Feature"},
	{"geometry":{"coordinates":[8.641623,46.882442],"type":"Point"},"properties":{"osm_id":"306664057","tag":{"amenity":"recycling","location":"overground","recycling:glass_bottles":"yes","recycling:glass_bottles:colour":"green/brown/white","recycling_type":"container"}},"type":"Feature"},
	{"geometry":{"coordinates":[8.663567,46.877312],"type":"Point"},"properties":{"osm_id":"668973586","tag":{"amenity":"recycling"}},"type":"Feature"},
	{"geometry":{"coordinates":[8.626149,46.90637],"type":"Point"},"properties":{"osm_id":"2622686342","tag":{"amenity":"recycling"}},"type":"Feature"},
	{"geometry":{"coordinates":[8.625409,46.915804],"type":"Point"},"properties":{"osm_id":"3835754253","tag":{"amenity":"recycling"}},"type":"Feature"},
	{"geometry":{"coordinates":[8.6276,46.866539],"type":"Point"},"properties":{"osm_id":"4579739411","tag":{"amenity":"recycling","recycling:aluminium":"yes","recycling:cans":"yes","recycling:glass_bottles":"yes","recycling_type":"container"}},"type":"Feature"},
	{"geometry":{"coordinates":[8.627669,46.866532],"type":"Point"},"properties":{"osm_id":"4580984150","tag":{"amenity":"waste_disposal"}},"type":"Feature"},
	{"geometry":{"coordinates":[8.631474,46.875892],"type":"Point"},"properties":{"osm_id":"4642325885","tag":{"amenity":"waste_basket"}},"type":"Feature"},
	{"geometry":{"coordinates":[8.623512,46.901026],"type":"Point"},"properties":{"osm_id":"5371168673","tag":{"amenity":"waste_basket"}},"type":"Feature"},
	{"geometry":{"coordinates":[8.623868,46.901397],"type":"Point"},"properties":{"osm_id":"5371168674","tag":{"amenity":"waste_basket"}},"type":"Feature"},
	{"geometry":{"coordinates":[8.623385,46.901956],"type":"Point"},"properties":{"osm_id":"5371168675","tag":{"amenity":"waste_basket"}},"type":"Feature"},
	{"geometry":{"coordinates":[8.624762,46.897897],"type":"Point"},"properties":{"osm_id":"5371168676","tag":{"amenity":"recycling"}},"type":"Feature"},
	{"geometry":{"coordinates":[8.624283,46.902646],"type":"Point"},"properties":{"osm_id":"5371168679","tag":{"amenity":"waste_basket"}},"type":"Feature"},
	{"geometry":{"coordinates":[8.624029,46.902634],"type":"Point"},"properties":{"osm_id":"5371168682","tag":{"amenity":"waste_basket"}},"type":"Feature"},
	{"geometry":{"coordinates":[8.623885,46.90187],"type":"Point"},"properties":{"osm_id":"5371168684","tag":{"amenity":"waste_basket"}},"type":"Feature"},
	{"geometry":{"coordinates":[8.687469,46.903484],"type":"Point"},"properties":{"osm_id":"8041195249","tag":{"amenity":"waste_basket","waste":"trash"}},"type":"Feature"},
	{"geometry":{"coordinates":[8.681784,46.876671],"type":"Point"},"properties":{"osm_id":"8041195250","tag":{"amenity":"recycling","recycling:cans":"yes","recycling:glass_bottles":"yes","recycling_type":"container"}},"type":"Feature"},
	{"geometry":{"coordinates":[8.623341,46.916565],"type":"Point"},"properties":{"osm_id":"8868849083","tag":{"amenity":"waste_basket"}},"type":"Feature"},
	{"geometry":{"coordinates":[8.63106,46.878118],"type":"Point"},"properties":{"osm_id":"8870062210","tag":{"amenity":"recycling","opening_hours":"24/7","recycling:cans":"yes","recycling:clothes":"yes","recycling:glass_bottles":"yes","recycling:glass_bottles:colour":"green/brown/white","recycling_type":"container"}},"type":"Feature"},
	{"geometry":{"coordinates":[8.634079,46.887276],"type":"Point"},"properties":{"osm_id":"9021096753","tag":{"amenity":"recycling","recycling:cans":"yes","recycling:clothes":"yes","recycling:cooking_oil":"yes","recycling:glass_bottles":"yes","recycling:glass_bottles:colour":"green/brown/white","recycling_type":"container"}},"type":"Feature"},
	{"geometry":{"coordinates":[8.630057,46.86695],"type":"Point"},"properties":{"osm_id":"9124940313","tag":{"amenity":"waste_basket","waste":"trash"}},"type":"Feature"}
]
}
