{
"type": "FeatureCollection",
"features": [
	{"geometry":{"coordinates":[8.626478,46.354925],"type":"Point"},"properties":{"osm_id":"687952560","tag":{"amenity":"recycling","location":"overground","recycling_type":"container"}},"type":"Feature"}
]
}
