{
"type": "FeatureCollection",
"lastupdate": "2020-08-06T00:00:00Z",
"features": [
	{"geometry":{"coordinates":[-122.223124,47.453338],"type":"Point"},"properties":{"osm_id":"3641760604","tag":{"amenity":"recycling","recycling:clothes":"yes"}},"type":"Feature"},
	{"geometry":{"coordinates":[-122.196824,47.41632],"type":"Point"},"properties":{"osm_id":"3649757550","tag":{"amenity":"recycling","recycling:clothes":"yes","recycling_type":"container"}},"type":"Feature"},
	{"geometry":{"coordinates":[-122.172068,47.417294],"type":"Point"},"properties":{"osm_id":"3721667149","tag":{"amenity":"waste_basket"}},"type":"Feature"},
	{"geometry":{"coordinates":[-122.223608,47.440479],"type":"Point"},"properties":{"osm_id":"3786512588","tag":{"amenity":"recycling","location":"overground","recycling:clothes":"yes","recycling_type":"container"}},"type":"Feature"},
	{"geometry":{"coordinates":[-122.248681,47.441496],"type":"Point"},"properties":{"osm_id":"4438244790","tag":{"amenity":"recycling","recycling:newspaper":"yes","recycling_type":"container"}},"type":"Feature"},
	{"geometry":{"coordinates":[-122.253663,47.4565],"type":"Point"},"properties":{"osm_id":"4915881844","tag":{"amenity":"waste_basket"}},"type":"Feature"},
	{"geometry":{"coordinates":[-122.253664,47.456464],"type":"Point"},"properties":{"osm_id":"4915881845","tag":{"amenity":"waste_basket"}},"type":"Feature"},
	{"geometry":{"coordinates":[-122.253665,47.456707],"type":"Point"},"properties":{"osm_id":"4915881846","tag":{"amenity":"waste_basket"}},"type":"Feature"},
	{"geometry":{"coordinates":[-122.253664,47.456671],"type":"Point"},"properties":{"osm_id":"4915881848","tag":{"amenity":"waste_basket"}},"type":"Feature"},
	{"geometry":{"coordinates":[-122.247182,47.456658],"type":"Point"},"properties":{"osm_id":"6733736487","tag":{"amenity":"waste_basket"}},"type":"Feature"},
	{"geometry":{"coordinates":[-122.247421,47.456531],"type":"Point"},"properties":{"osm_id":"6733736488","tag":{"amenity":"waste_basket"}},"type":"Feature"},
	{"geometry":{"coordinates":[-122.245504,47.45325],"type":"Point"},"properties":{"osm_id":"6733736497","tag":{"amenity":"waste_basket"}},"type":"Feature"},
	{"geometry":{"coordinates":[-122.245811,47.452825],"type":"Point"},"properties":{"osm_id":"6733843887","tag":{"amenity":"waste_basket"}},"type":"Feature"},
	{"geometry":{"coordinates":[-122.246843,47.456183],"type":"Point"},"properties":{"osm_id":"6733844485","tag":{"amenity":"waste_basket"}},"type":"Feature"},
	{"geometry":{"coordinates":[-122.244561,47.447379],"type":"Point"},"properties":{"osm_id":"6733994486","tag":{"amenity":"waste_basket"}},"type":"Feature"},
	{"geometry":{"coordinates":[-122.244734,47.4472],"type":"Point"},"properties":{"osm_id":"6733994985","tag":{"amenity":"waste_basket"}},"type":"Feature"},
	{"geometry":{"coordinates":[-122.245746,47.446543],"type":"Point"},"properties":{"osm_id":"6733995187","tag":{"amenity":"waste_basket"}},"type":"Feature"}
]
}
