{
"type": "FeatureCollection",
"features": [
	{"geometry":{"coordinates":[2.443425,44.441537],"type":"Point"},"properties":{"osm_id":"2967199026","tag":{"natural":"tree"}},"type":"Feature"},
	{"geometry":{"coordinates":[2.442583,44.443898],"type":"Point"},"properties":{"osm_id":"2967231849","tag":{"natural":"tree"}},"type":"Feature"},
	{"geometry":{"coordinates":[2.442153,44.443332],"type":"Point"},"properties":{"osm_id":"2967239803","tag":{"natural":"tree"}},"type":"Feature"},
	{"geometry":{"coordinates":[2.41164,44.427787],"type":"Point"},"properties":{"osm_id":"3220046627","tag":{"natural":"tree"}},"type":"Feature"},
	{"geometry":{"coordinates":[2.41135,44.427798],"type":"Point"},"properties":{"osm_id":"3220046628","tag":{"natural":"tree"}},"type":"Feature"},
	{"geometry":{"coordinates":[2.457814,44.439803],"type":"Point"},"properties":{"osm_id":"3598863523","tag":{"leaf_type":"broadleaved","natural":"tree"}},"type":"Feature"},
	{"geometry":{"coordinates":[2.457754,44.439819],"type":"Point"},"properties":{"osm_id":"3598863525","tag":{"leaf_type":"broadleaved","natural":"tree"}},"type":"Feature"},
	{"geometry":{"coordinates":[2.457698,44.439833],"type":"Point"},"properties":{"osm_id":"3598863526","tag":{"leaf_type":"broadleaved","natural":"tree"}},"type":"Feature"},
	{"geometry":{"coordinates":[2.457647,44.439851],"type":"Point"},"properties":{"osm_id":"3598863529","tag":{"leaf_type":"broadleaved","natural":"tree"}},"type":"Feature"},
	{"geometry":{"coordinates":[2.457428,44.440018],"type":"Point"},"properties":{"osm_id":"3598863533","tag":{"leaf_type":"broadleaved","natural":"tree"}},"type":"Feature"},
	{"geometry":{"coordinates":[2.45737,44.440046],"type":"Point"},"properties":{"osm_id":"3598863536","tag":{"leaf_type":"broadleaved","natural":"tree"}},"type":"Feature"},
	{"geometry":{"coordinates":[2.419592,44.411467],"type":"Point"},"properties":{"osm_id":"6695130690","tag":{"natural":"tree"}},"type":"Feature"},
	{"geometry":{"coordinates":[2.442317,44.441697],"type":"Point"},"properties":{"osm_id":"6702791810","tag":{"leaf_cycle":"deciduous","leaf_type":"broadleaved","natural":"tree"}},"type":"Feature"},
	{"geometry":{"coordinates":[2.442337,44.441599],"type":"Point"},"properties":{"osm_id":"6702791811","tag":{"leaf_cycle":"deciduous","leaf_type":"broadleaved","natural":"tree"}},"type":"Feature"},
	{"geometry":{"coordinates":[2.442713,44.44157],"type":"Point"},"properties":{"osm_id":"6702791814","tag":{"leaf_cycle":"deciduous","leaf_type":"broadleaved","natural":"tree"}},"type":"Feature"},
	{"geometry":{"coordinates":[2.442823,44.441565],"type":"Point"},"properties":{"osm_id":"6702791816","tag":{"leaf_cycle":"deciduous","leaf_type":"broadleaved","natural":"tree"}},"type":"Feature"},
	{"geometry":{"coordinates":[2.442927,44.44156],"type":"Point"},"properties":{"osm_id":"6702791817","tag":{"leaf_cycle":"deciduous","leaf_type":"broadleaved","natural":"tree"}},"type":"Feature"},
	{"geometry":{"coordinates":[2.400664,44.445043],"type":"Point"},"properties":{"osm_id":"6703146674","tag":{"leaf_cycle":"deciduous","leaf_type":"broadleaved","natural":"tree"}},"type":"Feature"},
	{"geometry":{"coordinates":[2.373852,44.443304],"type":"Point"},"properties":{"osm_id":"6707653679","tag":{"leaf_cycle":"deciduous","leaf_type":"broadleaved","natural":"tree"}},"type":"Feature"},
	{"geometry":{"coordinates":[2.387175,44.448111],"type":"Point"},"properties":{"osm_id":"6715885445","tag":{"natural":"tree"}},"type":"Feature"},
	{"geometry":{"coordinates":[2.387297,44.448113],"type":"Point"},"properties":{"osm_id":"6715885446","tag":{"natural":"tree"}},"type":"Feature"},
	{"geometry":{"coordinates":[2.387418,44.448112],"type":"Point"},"properties":{"osm_id":"6715885447","tag":{"natural":"tree"}},"type":"Feature"},
	{"geometry":{"coordinates":[2.448672,44.412106],"type":"Point"},"properties":{"osm_id":"8750399738","tag":{"natural":"tree"}},"type":"Feature"},
	{"geometry":{"coordinates":[2.44363,44.402878],"type":"Point"},"properties":{"osm_id":"8960221150","tag":{"natural":"tree"}},"type":"Feature"},
	{"geometry":{"coordinates":[2.446765,44.408268],"type":"Point"},"properties":{"osm_id":"8960222190","tag":{"natural":"tree"}},"type":"Feature"},
	{"geometry":{"coordinates":[2.415671,44.453614],"type":"Point"},"properties":{"name":"Saule Pleureur","osm_id":"8974078218","tag":{"denotation":"park","leaf_cycle":"deciduous","leaf_type":"broadleaved","natural":"tree"}},"type":"Feature"},
	{"geometry":{"coordinates":[2.427222,44.414882],"type":"Point"},"properties":{"osm_id":"9064746098","tag":{"natural":"tree"}},"type":"Feature"},
	{"geometry":{"coordinates":[2.418868,44.463503],"type":"Point"},"properties":{"osm_id":"9085631710","tag":{"natural":"tree"}},"type":"Feature"}
]
}
