{
"type": "FeatureCollection",
"features": [
	{"geometry":{"coordinates":[-47.540986,-22.312115],"type":"Point"},"properties":{"name":"Flecha Dourada","osm_id":"6482929733","tag":{"amenity":"recycling","recycling_type":"centre"}},"type":"Feature"}
]
}
