{
"type": "FeatureCollection",
"lastupdate": "2020-08-02T00:00:00Z",
"features": [
	{"geometry":{"coordinates":[-47.540986,-22.312114],"type":"Point"},"properties":{"name":"Flecha Dourada","osm_id":"6482929733","tag":{"amenity":"recycling","recycling_type":"centre"}},"type":"Feature"}
]
}
