{
"type": "FeatureCollection",
"features": [
	{"geometry":{"coordinates":[14.826914,47.214972],"type":"Point"},"properties":{"osm_id":"2046025929","tag":{"natural":"tree"}},"type":"Feature"},
	{"geometry":{"coordinates":[14.826983,47.215076],"type":"Point"},"properties":{"osm_id":"2046025931","tag":{"natural":"tree"}},"type":"Feature"},
	{"geometry":{"coordinates":[14.827053,47.215154],"type":"Point"},"properties":{"osm_id":"2046025940","tag":{"natural":"tree"}},"type":"Feature"},
	{"geometry":{"coordinates":[14.827107,47.215213],"type":"Point"},"properties":{"osm_id":"2046025947","tag":{"natural":"tree"}},"type":"Feature"},
	{"geometry":{"coordinates":[14.784738,47.198895],"type":"Point"},"properties":{"osm_id":"3532933738","tag":{"natural":"tree"}},"type":"Feature"},
	{"geometry":{"coordinates":[14.784777,47.198782],"type":"Point"},"properties":{"osm_id":"3532933739","tag":{"natural":"tree"}},"type":"Feature"},
	{"geometry":{"coordinates":[14.784842,47.19868],"type":"Point"},"properties":{"osm_id":"3532933740","tag":{"natural":"tree"}},"type":"Feature"},
	{"geometry":{"coordinates":[14.784898,47.198582],"type":"Point"},"properties":{"osm_id":"3532933741","tag":{"natural":"tree"}},"type":"Feature"},
	{"geometry":{"coordinates":[14.785386,47.19937],"type":"Point"},"properties":{"osm_id":"3532933742","tag":{"natural":"tree"}},"type":"Feature"},
	{"geometry":{"coordinates":[14.785178,47.199325],"type":"Point"},"properties":{"osm_id":"3532933743","tag":{"natural":"tree"}},"type":"Feature"},
	{"geometry":{"coordinates":[14.784932,47.199275],"type":"Point"},"properties":{"osm_id":"3532933744","tag":{"natural":"tree"}},"type":"Feature"},
	{"geometry":{"coordinates":[14.783652,47.217826],"type":"Point"},"properties":{"name":"Naturdenkmal","osm_id":"3913281669","tag":{"natural":"tree"}},"type":"Feature"},
	{"geometry":{"coordinates":[14.796432,47.184299],"type":"Point"},"properties":{"osm_id":"5609637129","tag":{"natural":"tree"}},"type":"Feature"},
	{"geometry":{"coordinates":[14.829256,47.213875],"type":"Point"},"properties":{"osm_id":"6296122236","tag":{"height":"4","natural":"tree"}},"type":"Feature"},
	{"geometry":{"coordinates":[14.829682,47.214527],"type":"Point"},"properties":{"osm_id":"6296122239","tag":{"height":"14","natural":"tree"}},"type":"Feature"},
	{"geometry":{"coordinates":[14.829577,47.21455],"type":"Point"},"properties":{"osm_id":"6296122240","tag":{"height":"14","natural":"tree"}},"type":"Feature"},
	{"geometry":{"coordinates":[14.829778,47.215024],"type":"Point"},"properties":{"osm_id":"6296122243","tag":{"height":"4","natural":"tree"}},"type":"Feature"},
	{"geometry":{"coordinates":[14.829983,47.215046],"type":"Point"},"properties":{"osm_id":"6296122244","tag":{"height":"4","natural":"tree"}},"type":"Feature"},
	{"geometry":{"coordinates":[14.829812,47.215078],"type":"Point"},"properties":{"osm_id":"6296122245","tag":{"height":"4","natural":"tree"}},"type":"Feature"},
	{"geometry":{"coordinates":[14.829683,47.214875],"type":"Point"},"properties":{"osm_id":"6296122246","tag":{"height":"4","natural":"tree"}},"type":"Feature"},
	{"geometry":{"coordinates":[14.829608,47.214757],"type":"Point"},"properties":{"osm_id":"6296122247","tag":{"height":"4","natural":"tree"}},"type":"Feature"},
	{"geometry":{"coordinates":[14.829514,47.2146],"type":"Point"},"properties":{"osm_id":"6296122248","tag":{"height":"4","natural":"tree"}},"type":"Feature"},
	{"geometry":{"coordinates":[14.829422,47.21446],"type":"Point"},"properties":{"osm_id":"6296122249","tag":{"height":"4","natural":"tree"}},"type":"Feature"},
	{"geometry":{"coordinates":[14.829343,47.214339],"type":"Point"},"properties":{"osm_id":"6296122250","tag":{"height":"4","natural":"tree"}},"type":"Feature"},
	{"geometry":{"coordinates":[14.82927,47.214219],"type":"Point"},"properties":{"osm_id":"6296122251","tag":{"height":"4","natural":"tree"}},"type":"Feature"},
	{"geometry":{"coordinates":[14.829193,47.214096],"type":"Point"},"properties":{"osm_id":"6296122267","tag":{"height":"4","natural":"tree"}},"type":"Feature"},
	{"geometry":{"coordinates":[14.829289,47.214058],"type":"Point"},"properties":{"osm_id":"6296122268","tag":{"height":"4","natural":"tree"}},"type":"Feature"},
	{"geometry":{"coordinates":[14.82935,47.214006],"type":"Point"},"properties":{"osm_id":"6296122269","tag":{"height":"4","natural":"tree"}},"type":"Feature"},
	{"geometry":{"coordinates":[14.829269,47.214033],"type":"Point"},"properties":{"osm_id":"6296122270","tag":{"height":"4","natural":"tree"}},"type":"Feature"},
	{"geometry":{"coordinates":[14.829173,47.214068],"type":"Point"},"properties":{"osm_id":"6296122271","tag":{"height":"4","natural":"tree"}},"type":"Feature"}
]
}
