{
"type": "FeatureCollection",
"features": [
	{"geometry":{"coordinates":[14.841492,37.001743],"type":"Point"},"properties":{"name":"Pero","osm_id":"6655813822","tag":{"natural":"tree"}},"type":"Feature"}
]
}
