{
"type": "FeatureCollection",
"features": [
	{"geometry":{"coordinates":[-80.33151,32.483084],"type":"Point"},"properties":{"osm_id":"813280274","tag":{"amenity":"recycling","recycling_type":"container"}},"type":"Feature"},
	{"geometry":{"coordinates":[-80.294717,32.506326],"type":"Point"},"properties":{"osm_id":"4095974866","tag":{"amenity":"recycling","recycling:cans":"yes","recycling:plastic":"yes","recycling_type":"container"}},"type":"Feature"},
	{"geometry":{"coordinates":[-80.294773,32.506343],"type":"Point"},"properties":{"osm_id":"4095974867","tag":{"amenity":"waste_basket"}},"type":"Feature"},
	{"geometry":{"coordinates":[-80.300698,32.510888],"type":"Point"},"properties":{"osm_id":"4096272333","tag":{"amenity":"waste_basket"}},"type":"Feature"},
	{"geometry":{"coordinates":[-80.300754,32.510862],"type":"Point"},"properties":{"osm_id":"4096272336","tag":{"amenity":"recycling","recycling:cans":"yes","recycling:plastic":"yes","recycling_type":"container"}},"type":"Feature"},
	{"geometry":{"coordinates":[-80.323175,32.50231],"type":"Point"},"properties":{"osm_id":"4097417994","tag":{"amenity":"waste_basket"}},"type":"Feature"},
	{"geometry":{"coordinates":[-80.323139,32.502291],"type":"Point"},"properties":{"osm_id":"4097417999","tag":{"amenity":"recycling","recycling:cans":"yes","recycling:glass":"yes","recycling_type":"container"}},"type":"Feature"},
	{"geometry":{"coordinates":[-80.299379,32.513548],"type":"Point"},"properties":{"name":"Oyster Shell Drop Off","osm_id":"4100439139","tag":{"amenity":"recycling","recycling:oyster_shell":"yes","recycling_type":"container"}},"type":"Feature"}
]
}
