{
"type": "FeatureCollection",
"lastupdate": "2020-08-06T00:00:00Z",
"features": [
	{"geometry":{"coordinates":[-80.331509,32.483083],"type":"Point"},"properties":{"osm_id":"813280274","tag":{"amenity":"recycling","recycling_type":"container"}},"type":"Feature"},
	{"geometry":{"coordinates":[-80.294717,32.506326],"type":"Point"},"properties":{"osm_id":"4095974866","tag":{"amenity":"recycling","recycling:cans":"yes","recycling:plastic":"yes","recycling_type":"container"}},"type":"Feature"},
	{"geometry":{"coordinates":[-80.294772,32.506342],"type":"Point"},"properties":{"osm_id":"4095974867","tag":{"amenity":"waste_basket"}},"type":"Feature"},
	{"geometry":{"coordinates":[-80.300697,32.510887],"type":"Point"},"properties":{"osm_id":"4096272333","tag":{"amenity":"waste_basket"}},"type":"Feature"},
	{"geometry":{"coordinates":[-80.300754,32.510861],"type":"Point"},"properties":{"osm_id":"4096272336","tag":{"amenity":"recycling","recycling:cans":"yes","recycling:plastic":"yes","recycling_type":"container"}},"type":"Feature"},
	{"geometry":{"coordinates":[-80.323174,32.502309],"type":"Point"},"properties":{"osm_id":"4097417994","tag":{"amenity":"waste_basket"}},"type":"Feature"},
	{"geometry":{"coordinates":[-80.323139,32.502291],"type":"Point"},"properties":{"osm_id":"4097417999","tag":{"amenity":"recycling","recycling:cans":"yes","recycling:glass":"yes","recycling_type":"container"}},"type":"Feature"},
	{"geometry":{"coordinates":[-80.299378,32.513548],"type":"Point"},"properties":{"name":"Oyster Shell Drop Off","osm_id":"4100439139","tag":{"amenity":"recycling","recycling:oyster_shell":"yes","recycling_type":"container"}},"type":"Feature"}
]
}
