{
"type": "FeatureCollection",
"features": [
	{"geometry":{"coordinates":[-1.915275,54.54086],"type":"Point"},"properties":{"osm_id":"1716292034","tag":{"amenity":"waste_basket"}},"type":"Feature"},
	{"geometry":{"coordinates":[-1.915793,54.542815],"type":"Point"},"properties":{"osm_id":"1716292126","tag":{"amenity":"waste_basket"}},"type":"Feature"},
	{"geometry":{"coordinates":[-1.924906,54.544432],"type":"Point"},"properties":{"osm_id":"1716292211","tag":{"amenity":"waste_basket"}},"type":"Feature"},
	{"geometry":{"coordinates":[-1.889009,54.557396],"type":"Point"},"properties":{"name":"Stainton Grove HWRC","osm_id":"2514398842","tag":{"addr:city":"Barnard Castle","addr:housename":"Stainton Grove HWRC","addr:postcode":"DL12 8UH","addr:street":"Stainton Grove","amenity":"recycling","opening_hours":"Mo-Su 09:00-18:00; Dec 25 off; Jan 01 off","operator":"Durham County Council","operator:type":"government","owner":"Durham County Council","ownership":"municipal","recycling:batteries":"yes","recycling:cans":"yes","recycling:car_batteries":"yes","recycling:cardboard":"yes","recycling:carpets":"yes","recycling:cartons":"yes","recycling:cooking_oil":"yes","recycling:fluorescent_tubes":"yes","recycling:fridges_and_freezers":"yes","recycling:garden_waste":"yes","recycling:gas_bottles":"yes","recycling:general_waste":"yes","recycling:glass":"yes","recycling:oil":"yes","recycling:paper":"yes","recycling:plasterboard":"yes","recycling:plastics":"yes","recycling:rubble":"yes","recycling:scrap_metal":"yes","recycling:shoes":"yes","recycling:soil":"yes","recycling:textiles":"yes","recycling:tv_monitor":"yes","recycling:tyres":"yes","recycling:wood":"yes","recycling_type":"centre","website":"http://www.durham.gov.uk/article/21849/Stainton-Grove-HWRC-tip-","wikidata":"Q106093450"}},"type":"Feature"},
	{"geometry":{"coordinates":[-1.927621,54.542762],"type":"Point"},"properties":{"osm_id":"3834220452","tag":{"amenity":"waste_basket","check_date":"2021-10-25"}},"type":"Feature"},
	{"geometry":{"coordinates":[-1.923914,54.542793],"type":"Point"},"properties":{"osm_id":"3834353579","tag":{"amenity":"waste_basket"}},"type":"Feature"},
	{"geometry":{"coordinates":[-1.932077,54.542093],"type":"Point"},"properties":{"osm_id":"3838678073","tag":{"amenity":"waste_basket"}},"type":"Feature"},
	{"geometry":{"coordinates":[-1.924419,54.540767],"type":"Point"},"properties":{"osm_id":"3838714829","tag":{"amenity":"waste_basket"}},"type":"Feature"},
	{"geometry":{"coordinates":[-1.923992,54.541451],"type":"Point"},"properties":{"osm_id":"3838714834","tag":{"amenity":"waste_basket"}},"type":"Feature"},
	{"geometry":{"coordinates":[-1.923482,54.542047],"type":"Point"},"properties":{"osm_id":"3838714839","tag":{"amenity":"waste_basket"}},"type":"Feature"},
	{"geometry":{"coordinates":[-1.9222,54.541987],"type":"Point"},"properties":{"osm_id":"3838729694","tag":{"amenity":"waste_basket"}},"type":"Feature"},
	{"geometry":{"coordinates":[-1.923633,54.542677],"type":"Point"},"properties":{"osm_id":"3838777997","tag":{"amenity":"waste_basket"}},"type":"Feature"},
	{"geometry":{"coordinates":[-1.919443,54.547061],"type":"Point"},"properties":{"osm_id":"3839066686","tag":{"amenity":"waste_basket"}},"type":"Feature"},
	{"geometry":{"coordinates":[-1.924072,54.544907],"type":"Point"},"properties":{"osm_id":"3839234719","tag":{"amenity":"waste_basket"}},"type":"Feature"},
	{"geometry":{"coordinates":[-1.924194,54.54498],"type":"Point"},"properties":{"osm_id":"3839238975","tag":{"amenity":"waste_basket"}},"type":"Feature"},
	{"geometry":{"coordinates":[-1.927427,54.544805],"type":"Point"},"properties":{"osm_id":"8808502350","tag":{"amenity":"waste_basket"}},"type":"Feature"}
]
}
