{
"type": "FeatureCollection",
"lastupdate": "2020-08-05T00:00:00Z",
"features": [
	{"geometry":{"coordinates":[-1.908373,52.416484],"type":"Point"},"properties":{"osm_id":"257549667","tag":{"amenity":"recycling"}},"type":"Feature"},
	{"geometry":{"coordinates":[-1.91854,52.416467],"type":"Point"},"properties":{"name":"Lifford Lane Household Recycling Centre","osm_id":"287879975","tag":{"amenity":"recycling","recycling_type":"centre"}},"type":"Feature"},
	{"geometry":{"coordinates":[-1.92691,52.410481],"type":"Point"},"properties":{"osm_id":"417727570","tag":{"amenity":"waste_basket"}},"type":"Feature"},
	{"geometry":{"coordinates":[-1.915656,52.40879],"type":"Point"},"properties":{"osm_id":"621512486","tag":{"amenity":"recycling"}},"type":"Feature"},
	{"geometry":{"coordinates":[-1.917086,52.423956],"type":"Point"},"properties":{"osm_id":"760735733","tag":{"amenity":"waste_basket"}},"type":"Feature"},
	{"geometry":{"coordinates":[-1.918892,52.427749],"type":"Point"},"properties":{"osm_id":"760735807","tag":{"amenity":"waste_basket"}},"type":"Feature"},
	{"geometry":{"coordinates":[-1.877212,52.417352],"type":"Point"},"properties":{"osm_id":"7677190036","tag":{"amenity":"waste_basket","colour":"black","material":"plastic"}},"type":"Feature"}
]
}
