{
"type": "FeatureCollection",
"features": [
	{"geometry":{"coordinates":[-1.908374,52.416485],"type":"Point"},"properties":{"osm_id":"257549667","tag":{"amenity":"recycling"}},"type":"Feature"},
	{"geometry":{"coordinates":[-1.918541,52.416467],"type":"Point"},"properties":{"name":"Lifford Lane Household Recycling Centre","osm_id":"287879975","tag":{"amenity":"recycling","recycling_type":"centre"}},"type":"Feature"},
	{"geometry":{"coordinates":[-1.9174,52.428431],"type":"Point"},"properties":{"osm_id":"417727556","tag":{"amenity":"waste_disposal"}},"type":"Feature"},
	{"geometry":{"coordinates":[-1.917711,52.42804],"type":"Point"},"properties":{"osm_id":"417727558","tag":{"amenity":"waste_disposal"}},"type":"Feature"},
	{"geometry":{"coordinates":[-1.926911,52.410481],"type":"Point"},"properties":{"osm_id":"417727570","tag":{"amenity":"waste_basket"}},"type":"Feature"},
	{"geometry":{"coordinates":[-1.915656,52.40879],"type":"Point"},"properties":{"osm_id":"621512486","tag":{"amenity":"recycling"}},"type":"Feature"},
	{"geometry":{"coordinates":[-1.917086,52.423956],"type":"Point"},"properties":{"osm_id":"760735733","tag":{"amenity":"waste_basket"}},"type":"Feature"},
	{"geometry":{"coordinates":[-1.918892,52.42775],"type":"Point"},"properties":{"osm_id":"760735807","tag":{"amenity":"waste_basket"}},"type":"Feature"},
	{"geometry":{"coordinates":[-1.877213,52.417353],"type":"Point"},"properties":{"osm_id":"7677190036","tag":{"amenity":"waste_basket","colour":"black","material":"plastic"}},"type":"Feature"},
	{"geometry":{"coordinates":[-1.869822,52.38895],"type":"Point"},"properties":{"osm_id":"7824419880","tag":{"amenity":"waste_basket","waste":"dog_excrement"}},"type":"Feature"},
	{"geometry":{"coordinates":[-1.880658,52.397201],"type":"Point"},"properties":{"osm_id":"7837576893","tag":{"amenity":"waste_basket"}},"type":"Feature"},
	{"geometry":{"coordinates":[-1.880882,52.397128],"type":"Point"},"properties":{"osm_id":"7837576894","tag":{"amenity":"waste_basket","waste":"dog_excrement"}},"type":"Feature"},
	{"geometry":{"coordinates":[-1.883576,52.393829],"type":"Point"},"properties":{"osm_id":"7837576903","tag":{"amenity":"waste_basket"}},"type":"Feature"},
	{"geometry":{"coordinates":[-1.884693,52.386376],"type":"Point"},"properties":{"osm_id":"7837576917","tag":{"amenity":"waste_basket"}},"type":"Feature"}
]
}
