{
"type": "FeatureCollection",
"features": [
	{"geometry":{"coordinates":[-1.876748,46.731076],"type":"Point"},"properties":{"osm_id":"1875924230","tag":{"amenity":"recycling"}},"type":"Feature"},
	{"geometry":{"coordinates":[-1.930743,46.692064],"type":"Point"},"properties":{"osm_id":"4293497604","tag":{"amenity":"recycling"}},"type":"Feature"},
	{"geometry":{"coordinates":[-1.932893,46.695945],"type":"Point"},"properties":{"osm_id":"5772233521","tag":{"amenity":"recycling","recycling:cardboard":"yes","recycling:glass":"yes","recycling_type":"container"}},"type":"Feature"},
	{"geometry":{"coordinates":[-1.90028,46.720251],"type":"Point"},"properties":{"osm_id":"8094647773","tag":{"amenity":"recycling","recycling_type":"container"}},"type":"Feature"},
	{"geometry":{"coordinates":[-1.903742,46.716344],"type":"Point"},"properties":{"osm_id":"8094647774","tag":{"amenity":"recycling","recycling:clothes":"yes","recycling_type":"container"}},"type":"Feature"},
	{"geometry":{"coordinates":[-1.906981,46.715819],"type":"Point"},"properties":{"osm_id":"8094647775","tag":{"amenity":"recycling","recycling:paper":"yes","recycling_type":"container"}},"type":"Feature"},
	{"geometry":{"coordinates":[-1.932245,46.691054],"type":"Point"},"properties":{"osm_id":"8261811791","tag":{"amenity":"waste_basket"}},"type":"Feature"},
	{"geometry":{"coordinates":[-1.927119,46.681193],"type":"Point"},"properties":{"osm_id":"8261812947","tag":{"amenity":"recycling","recycling_type":"container"}},"type":"Feature"},
	{"geometry":{"coordinates":[-1.911337,46.717223],"type":"Point"},"properties":{"osm_id":"8264400188","tag":{"amenity":"waste_basket"}},"type":"Feature"},
	{"geometry":{"coordinates":[-1.906962,46.715842],"type":"Point"},"properties":{"osm_id":"8269544267","tag":{"amenity":"recycling","recycling:glass_bottles":"yes","recycling_type":"container"}},"type":"Feature"},
	{"geometry":{"coordinates":[-1.918722,46.707374],"type":"Point"},"properties":{"osm_id":"8269544346","tag":{"amenity":"recycling","recycling:waste":"yes","recycling_type":"container"}},"type":"Feature"},
	{"geometry":{"coordinates":[-1.918695,46.707364],"type":"Point"},"properties":{"osm_id":"8269544347","tag":{"amenity":"recycling","recycling:paper":"yes","recycling_type":"container"}},"type":"Feature"},
	{"geometry":{"coordinates":[-1.918671,46.707354],"type":"Point"},"properties":{"osm_id":"8269544348","tag":{"amenity":"recycling","recycling:glass_bottles":"yes","recycling_type":"container"}},"type":"Feature"},
	{"geometry":{"coordinates":[-1.918749,46.707381],"type":"Point"},"properties":{"osm_id":"8269544349","tag":{"amenity":"recycling","recycling_type":"container"}},"type":"Feature"},
	{"geometry":{"coordinates":[-1.901975,46.724258],"type":"Point"},"properties":{"osm_id":"8273091812","tag":{"amenity":"waste_basket"}},"type":"Feature"},
	{"geometry":{"coordinates":[-1.903093,46.719753],"type":"Point"},"properties":{"osm_id":"8273113266","tag":{"amenity":"waste_basket"}},"type":"Feature"},
	{"geometry":{"coordinates":[-1.903737,46.716195],"type":"Point"},"properties":{"osm_id":"8273116168","tag":{"amenity":"recycling","location":"underground","recycling:waste":"yes","recycling_type":"container"}},"type":"Feature"},
	{"geometry":{"coordinates":[-1.902973,46.715778],"type":"Point"},"properties":{"osm_id":"8273120779","tag":{"amenity":"waste_basket"}},"type":"Feature"},
	{"geometry":{"coordinates":[-1.903932,46.719264],"type":"Point"},"properties":{"osm_id":"8273122502","tag":{"amenity":"waste_basket"}},"type":"Feature"},
	{"geometry":{"coordinates":[-1.902311,46.724424],"type":"Point"},"properties":{"osm_id":"8273130825","tag":{"amenity":"waste_basket"}},"type":"Feature"},
	{"geometry":{"coordinates":[-1.903417,46.715698],"type":"Point"},"properties":{"osm_id":"8273131820","tag":{"amenity":"waste_basket"}},"type":"Feature"},
	{"geometry":{"coordinates":[-1.901401,46.716043],"type":"Point"},"properties":{"osm_id":"8273131821","tag":{"amenity":"waste_basket"}},"type":"Feature"},
	{"geometry":{"coordinates":[-1.912445,46.731173],"type":"Point"},"properties":{"osm_id":"8275005945","tag":{"amenity":"recycling","recycling:waste":"yes","recycling_type":"container"}},"type":"Feature"},
	{"geometry":{"coordinates":[-1.912433,46.731198],"type":"Point"},"properties":{"osm_id":"8275005946","tag":{"amenity":"recycling","recycling:packaging":"yes","recycling_type":"container"}},"type":"Feature"},
	{"geometry":{"coordinates":[-1.912418,46.731222],"type":"Point"},"properties":{"osm_id":"8275005947","tag":{"amenity":"recycling","recycling:glass_bottles":"yes","recycling_type":"container"}},"type":"Feature"},
	{"geometry":{"coordinates":[-1.912412,46.73125],"type":"Point"},"properties":{"osm_id":"8275005948","tag":{"amenity":"recycling","recycling:paper":"yes","recycling_type":"container"}},"type":"Feature"}
]
}
