{
"type": "FeatureCollection",
"features": [
	{"geometry":{"coordinates":[11.257646,52.646297],"type":"Point"},"properties":{"name":"Jemmeritzer Eiche","osm_id":"518897607","tag":{"diameter":"240 cm","height":"29","natural":"tree","type":"Eiche"}},"type":"Feature"},
	{"geometry":{"coordinates":[11.289662,52.65983],"type":"Point"},"properties":{"osm_id":"5237635917","tag":{"natural":"tree"}},"type":"Feature"}
]
}
