{
"type": "FeatureCollection",
"features": [
	{"geometry":{"coordinates":[11.257539,52.646324],"type":"Point"},"properties":{"name":"Jemmeritzer Eiche","osm_id":"518897607","tag":{"height":"29","leisure":"nature_reserve","natural":"tree","type":"Eiche"}},"type":"Feature"},
	{"geometry":{"coordinates":[11.289662,52.65983],"type":"Point"},"properties":{"osm_id":"5237635917","tag":{"natural":"tree"}},"type":"Feature"}
]
}
