{
"type": "FeatureCollection",
"features": [
	{"geometry":{"coordinates":[11.312179,52.597349],"type":"Point"},"properties":{"name":"Ferchel-Eiche","osm_id":"392731934","tag":{"genus":"Quercus","genus:de":"Eiche","genus:en":"Oak","leaf_type":"broadleaved","natural":"tree","wikidata":"Q1405005","wikipedia":"de:Ferchel"}},"type":"Feature"},
	{"geometry":{"coordinates":[11.289752,52.610194],"type":"Point"},"properties":{"name":"Zichtauer Eiche","osm_id":"500718684","tag":{"genus":"Quercus","genus:de":"Eiche","genus:en":"Oak","leaf_type":"broadleaved","natural":"tree"}},"type":"Feature"},
	{"geometry":{"coordinates":[11.29721,52.60766],"type":"Point"},"properties":{"osm_id":"2321862005","tag":{"circumference":"6","denotation":"natural_monument","genus":"Platanus","genus:de":"Platane","leaf_type":"broadleaved","natural":"tree"}},"type":"Feature"},
	{"geometry":{"coordinates":[11.296547,52.608216],"type":"Point"},"properties":{"name":"Lindendom","osm_id":"2321862034","tag":{"denotation":"natural_monument","genus":"Tilia","genus:de":"Linde","leaf_type":"broadleaved","natural":"tree"}},"type":"Feature"}
]
}
