{
"type": "FeatureCollection",
"features": [
	{"geometry":{"coordinates":[11.311499,50.324279],"type":"Point"},"properties":{"osm_id":"4346191810","tag":{"natural":"tree"}},"type":"Feature"},
	{"geometry":{"coordinates":[11.312848,50.32623],"type":"Point"},"properties":{"osm_id":"4346191811","tag":{"natural":"tree"}},"type":"Feature"},
	{"geometry":{"coordinates":[11.312683,50.326152],"type":"Point"},"properties":{"osm_id":"4346191812","tag":{"natural":"tree"}},"type":"Feature"},
	{"geometry":{"coordinates":[11.292243,50.31197],"type":"Point"},"properties":{"osm_id":"4346192424","tag":{"natural":"tree"}},"type":"Feature"},
	{"geometry":{"coordinates":[11.325462,50.322673],"type":"Point"},"properties":{"name":"Linde","osm_id":"4702457646","tag":{"leaf_cycle":"deciduous","leaf_type":"broadleaved","natural":"tree"}},"type":"Feature"},
	{"geometry":{"coordinates":[11.311316,50.324028],"type":"Point"},"properties":{"osm_id":"4702457652","tag":{"natural":"tree"}},"type":"Feature"}
]
}
