{
"type": "FeatureCollection",
"features": [
	{"geometry":{"coordinates":[11.293718,49.74752],"type":"Point"},"properties":{"osm_id":"2385353128","tag":{"natural":"tree"}},"type":"Feature"},
	{"geometry":{"coordinates":[11.309469,49.773829],"type":"Point"},"properties":{"osm_id":"4936276176","tag":{"natural":"tree"}},"type":"Feature"},
	{"geometry":{"coordinates":[11.310075,49.773661],"type":"Point"},"properties":{"osm_id":"4936276177","tag":{"natural":"tree"}},"type":"Feature"},
	{"geometry":{"coordinates":[11.310043,49.773599],"type":"Point"},"properties":{"osm_id":"4936276178","tag":{"natural":"tree"}},"type":"Feature"},
	{"geometry":{"coordinates":[11.310135,49.773614],"type":"Point"},"properties":{"osm_id":"4936276179","tag":{"natural":"tree"}},"type":"Feature"},
	{"geometry":{"coordinates":[11.26878,49.73775],"type":"Point"},"properties":{"name":"Dorflinde","osm_id":"5818946083","tag":{"denotation":"natural_monument","leaf_cycle":"deciduous","leaf_type":"broadleaved","natural":"tree"}},"type":"Feature"},
	{"geometry":{"coordinates":[11.299084,49.764701],"type":"Point"},"properties":{"name":"Linde","osm_id":"7093308977","tag":{"denotation":"landmark","leaf_cycle":"deciduous","leaf_type":"broadleaved","natural":"tree"}},"type":"Feature"},
	{"geometry":{"coordinates":[11.32964,49.766035],"type":"Point"},"properties":{"name":"Linde","osm_id":"7093366295","tag":{"denotation":"landmark","leaf_cycle":"deciduous","leaf_type":"broadleaved","natural":"tree"}},"type":"Feature"},
	{"geometry":{"coordinates":[11.308703,49.764375],"type":"Point"},"properties":{"name":"Linde","osm_id":"7093727179","tag":{"natural":"tree"}},"type":"Feature"}
]
}
