{
"type": "FeatureCollection",
"features": [
	{"geometry":{"coordinates":[11.293717,49.747519],"type":"Point"},"properties":{"osm_id":"2385353128","tag":{"natural":"tree"}},"type":"Feature"},
	{"geometry":{"coordinates":[11.309468,49.773829],"type":"Point"},"properties":{"osm_id":"4936276176","tag":{"natural":"tree"}},"type":"Feature"},
	{"geometry":{"coordinates":[11.310075,49.773661],"type":"Point"},"properties":{"osm_id":"4936276177","tag":{"natural":"tree"}},"type":"Feature"},
	{"geometry":{"coordinates":[11.310043,49.773598],"type":"Point"},"properties":{"osm_id":"4936276178","tag":{"natural":"tree"}},"type":"Feature"},
	{"geometry":{"coordinates":[11.310134,49.773614],"type":"Point"},"properties":{"osm_id":"4936276179","tag":{"natural":"tree"}},"type":"Feature"},
	{"geometry":{"coordinates":[11.268779,49.737749],"type":"Point"},"properties":{"name":"Dorflinde","osm_id":"5818946083","tag":{"denotation":"natural_monument","genus":"Tilia","genus:de":"Linde","leaf_cycle":"deciduous","leaf_type":"broadleaved","natural":"tree"}},"type":"Feature"},
	{"geometry":{"coordinates":[11.299084,49.7647],"type":"Point"},"properties":{"osm_id":"7093308977","tag":{"denotation":"landmark","genus":"Tilia","genus:de":"Linde","leaf_cycle":"deciduous","leaf_type":"broadleaved","natural":"tree"}},"type":"Feature"},
	{"geometry":{"coordinates":[11.32964,49.766034],"type":"Point"},"properties":{"osm_id":"7093366295","tag":{"denotation":"landmark","genus":"Tilia","genus:de":"Linde","leaf_cycle":"deciduous","leaf_type":"broadleaved","natural":"tree"}},"type":"Feature"},
	{"geometry":{"coordinates":[11.308702,49.764374],"type":"Point"},"properties":{"osm_id":"7093727179","tag":{"genus":"Tilia","genus:de":"Linde","natural":"tree"}},"type":"Feature"},
	{"geometry":{"coordinates":[11.319449,49.773905],"type":"Point"},"properties":{"osm_id":"8371566209","tag":{"natural":"tree"}},"type":"Feature"}
]
}
