{
"type": "FeatureCollection",
"features": [
	{"geometry":{"coordinates":[-74.562361,-8.37709],"type":"Point"},"properties":{"name":"Lupuna","osm_id":"1482039771","tag":{"natural":"tree"}},"type":"Feature"},
	{"geometry":{"coordinates":[-74.532282,-8.382705],"type":"Point"},"properties":{"osm_id":"2835079992","tag":{"natural":"tree"}},"type":"Feature"},
	{"geometry":{"coordinates":[-74.562205,-8.377289],"type":"Point"},"properties":{"osm_id":"2843316615","tag":{"natural":"tree"}},"type":"Feature"},
	{"geometry":{"coordinates":[-74.550246,-8.397335],"type":"Point"},"properties":{"osm_id":"2867845577","tag":{"natural":"tree"}},"type":"Feature"},
	{"geometry":{"coordinates":[-74.550361,-8.397488],"type":"Point"},"properties":{"osm_id":"2867845578","tag":{"natural":"tree"}},"type":"Feature"},
	{"geometry":{"coordinates":[-74.550226,-8.397452],"type":"Point"},"properties":{"osm_id":"2867845579","tag":{"natural":"tree"}},"type":"Feature"},
	{"geometry":{"coordinates":[-74.550028,-8.398067],"type":"Point"},"properties":{"osm_id":"2867845580","tag":{"natural":"tree"}},"type":"Feature"},
	{"geometry":{"coordinates":[-74.550135,-8.397758],"type":"Point"},"properties":{"osm_id":"2867845581","tag":{"natural":"tree"}},"type":"Feature"},
	{"geometry":{"coordinates":[-74.562869,-8.398344],"type":"Point"},"properties":{"osm_id":"2869612068","tag":{"natural":"tree"}},"type":"Feature"},
	{"geometry":{"coordinates":[-74.562754,-8.398311],"type":"Point"},"properties":{"osm_id":"2869612069","tag":{"natural":"tree"}},"type":"Feature"},
	{"geometry":{"coordinates":[-74.53691,-8.380981],"type":"Point"},"properties":{"osm_id":"2903179104","tag":{"natural":"tree"}},"type":"Feature"},
	{"geometry":{"coordinates":[-74.536828,-8.381024],"type":"Point"},"properties":{"osm_id":"2903179105","tag":{"natural":"tree"}},"type":"Feature"},
	{"geometry":{"coordinates":[-74.537135,-8.381082],"type":"Point"},"properties":{"osm_id":"2903179106","tag":{"natural":"tree"}},"type":"Feature"},
	{"geometry":{"coordinates":[-74.575683,-8.355577],"type":"Point"},"properties":{"osm_id":"2903664193","tag":{"natural":"tree"}},"type":"Feature"},
	{"geometry":{"coordinates":[-74.575632,-8.355628],"type":"Point"},"properties":{"osm_id":"2903664194","tag":{"natural":"tree"}},"type":"Feature"},
	{"geometry":{"coordinates":[-74.575592,-8.355672],"type":"Point"},"properties":{"osm_id":"2903664195","tag":{"natural":"tree"}},"type":"Feature"},
	{"geometry":{"coordinates":[-74.575538,-8.35572],"type":"Point"},"properties":{"osm_id":"2903664196","tag":{"natural":"tree"}},"type":"Feature"},
	{"geometry":{"coordinates":[-74.57617,-8.354617],"type":"Point"},"properties":{"osm_id":"2903670138","tag":{"natural":"tree"}},"type":"Feature"},
	{"geometry":{"coordinates":[-74.575896,-8.35439],"type":"Point"},"properties":{"osm_id":"2903670139","tag":{"natural":"tree"}},"type":"Feature"},
	{"geometry":{"coordinates":[-74.575414,-8.35473],"type":"Point"},"properties":{"osm_id":"2903670140","tag":{"natural":"tree"}},"type":"Feature"},
	{"geometry":{"coordinates":[-74.575484,-8.354812],"type":"Point"},"properties":{"osm_id":"2903670141","tag":{"natural":"tree"}},"type":"Feature"},
	{"geometry":{"coordinates":[-74.575626,-8.354921],"type":"Point"},"properties":{"osm_id":"2903670142","tag":{"natural":"tree"}},"type":"Feature"},
	{"geometry":{"coordinates":[-74.575911,-8.35522],"type":"Point"},"properties":{"osm_id":"2903670157","tag":{"natural":"tree"}},"type":"Feature"},
	{"geometry":{"coordinates":[-74.531849,-8.37844],"type":"Point"},"properties":{"osm_id":"5590542589","tag":{"natural":"tree"}},"type":"Feature"},
	{"geometry":{"coordinates":[-74.533425,-8.378244],"type":"Point"},"properties":{"osm_id":"5590542590","tag":{"natural":"tree"}},"type":"Feature"},
	{"geometry":{"coordinates":[-74.533529,-8.378226],"type":"Point"},"properties":{"osm_id":"5590542591","tag":{"natural":"tree"}},"type":"Feature"},
	{"geometry":{"coordinates":[-74.533588,-8.378381],"type":"Point"},"properties":{"osm_id":"5590542592","tag":{"natural":"tree"}},"type":"Feature"},
	{"geometry":{"coordinates":[-74.533647,-8.378298],"type":"Point"},"properties":{"osm_id":"5590542593","tag":{"natural":"tree"}},"type":"Feature"},
	{"geometry":{"coordinates":[-74.532752,-8.378417],"type":"Point"},"properties":{"osm_id":"5590542594","tag":{"natural":"tree"}},"type":"Feature"},
	{"geometry":{"coordinates":[-74.533552,-8.378599],"type":"Point"},"properties":{"osm_id":"5590542595","tag":{"natural":"tree"}},"type":"Feature"},
	{"geometry":{"coordinates":[-74.533638,-8.378756],"type":"Point"},"properties":{"osm_id":"5590542596","tag":{"natural":"tree"}},"type":"Feature"},
	{"geometry":{"coordinates":[-74.533668,-8.378792],"type":"Point"},"properties":{"osm_id":"5590542597","tag":{"natural":"tree"}},"type":"Feature"}
]
}
