{
"type": "FeatureCollection",
"features": [
	{"geometry":{"coordinates":[-74.562362,-8.377091],"type":"Point"},"properties":{"name":"Lupuna","osm_id":"1482039771","tag":{"natural":"tree"}},"type":"Feature"},
	{"geometry":{"coordinates":[-74.532283,-8.382705],"type":"Point"},"properties":{"osm_id":"2835079992","tag":{"natural":"tree"}},"type":"Feature"},
	{"geometry":{"coordinates":[-74.562206,-8.377289],"type":"Point"},"properties":{"osm_id":"2843316615","tag":{"natural":"tree"}},"type":"Feature"},
	{"geometry":{"coordinates":[-74.550246,-8.397336],"type":"Point"},"properties":{"osm_id":"2867845577","tag":{"natural":"tree"}},"type":"Feature"},
	{"geometry":{"coordinates":[-74.550361,-8.397488],"type":"Point"},"properties":{"osm_id":"2867845578","tag":{"natural":"tree"}},"type":"Feature"},
	{"geometry":{"coordinates":[-74.550227,-8.397453],"type":"Point"},"properties":{"osm_id":"2867845579","tag":{"natural":"tree"}},"type":"Feature"},
	{"geometry":{"coordinates":[-74.550029,-8.398067],"type":"Point"},"properties":{"osm_id":"2867845580","tag":{"natural":"tree"}},"type":"Feature"},
	{"geometry":{"coordinates":[-74.550136,-8.397758],"type":"Point"},"properties":{"osm_id":"2867845581","tag":{"natural":"tree"}},"type":"Feature"},
	{"geometry":{"coordinates":[-74.562869,-8.398345],"type":"Point"},"properties":{"osm_id":"2869612068","tag":{"natural":"tree"}},"type":"Feature"},
	{"geometry":{"coordinates":[-74.562754,-8.398311],"type":"Point"},"properties":{"osm_id":"2869612069","tag":{"natural":"tree"}},"type":"Feature"},
	{"geometry":{"coordinates":[-74.53691,-8.380982],"type":"Point"},"properties":{"osm_id":"2903179104","tag":{"natural":"tree"}},"type":"Feature"},
	{"geometry":{"coordinates":[-74.536829,-8.381025],"type":"Point"},"properties":{"osm_id":"2903179105","tag":{"natural":"tree"}},"type":"Feature"},
	{"geometry":{"coordinates":[-74.537135,-8.381083],"type":"Point"},"properties":{"osm_id":"2903179106","tag":{"natural":"tree"}},"type":"Feature"},
	{"geometry":{"coordinates":[-74.575683,-8.355577],"type":"Point"},"properties":{"osm_id":"2903664193","tag":{"natural":"tree"}},"type":"Feature"},
	{"geometry":{"coordinates":[-74.575632,-8.355628],"type":"Point"},"properties":{"osm_id":"2903664194","tag":{"natural":"tree"}},"type":"Feature"},
	{"geometry":{"coordinates":[-74.575593,-8.355673],"type":"Point"},"properties":{"osm_id":"2903664195","tag":{"natural":"tree"}},"type":"Feature"},
	{"geometry":{"coordinates":[-74.575538,-8.355721],"type":"Point"},"properties":{"osm_id":"2903664196","tag":{"natural":"tree"}},"type":"Feature"},
	{"geometry":{"coordinates":[-74.57617,-8.354618],"type":"Point"},"properties":{"osm_id":"2903670138","tag":{"natural":"tree"}},"type":"Feature"},
	{"geometry":{"coordinates":[-74.575897,-8.354391],"type":"Point"},"properties":{"osm_id":"2903670139","tag":{"natural":"tree"}},"type":"Feature"},
	{"geometry":{"coordinates":[-74.575414,-8.35473],"type":"Point"},"properties":{"osm_id":"2903670140","tag":{"natural":"tree"}},"type":"Feature"},
	{"geometry":{"coordinates":[-74.575484,-8.354813],"type":"Point"},"properties":{"osm_id":"2903670141","tag":{"natural":"tree"}},"type":"Feature"},
	{"geometry":{"coordinates":[-74.575626,-8.354921],"type":"Point"},"properties":{"osm_id":"2903670142","tag":{"natural":"tree"}},"type":"Feature"},
	{"geometry":{"coordinates":[-74.575912,-8.355221],"type":"Point"},"properties":{"osm_id":"2903670157","tag":{"natural":"tree"}},"type":"Feature"},
	{"geometry":{"coordinates":[-74.531849,-8.37844],"type":"Point"},"properties":{"osm_id":"5590542589","tag":{"natural":"tree"}},"type":"Feature"},
	{"geometry":{"coordinates":[-74.533425,-8.378245],"type":"Point"},"properties":{"osm_id":"5590542590","tag":{"natural":"tree"}},"type":"Feature"},
	{"geometry":{"coordinates":[-74.53353,-8.378227],"type":"Point"},"properties":{"osm_id":"5590542591","tag":{"natural":"tree"}},"type":"Feature"},
	{"geometry":{"coordinates":[-74.533589,-8.378382],"type":"Point"},"properties":{"osm_id":"5590542592","tag":{"natural":"tree"}},"type":"Feature"},
	{"geometry":{"coordinates":[-74.533648,-8.378298],"type":"Point"},"properties":{"osm_id":"5590542593","tag":{"natural":"tree"}},"type":"Feature"},
	{"geometry":{"coordinates":[-74.532753,-8.378418],"type":"Point"},"properties":{"osm_id":"5590542594","tag":{"natural":"tree"}},"type":"Feature"},
	{"geometry":{"coordinates":[-74.533552,-8.3786],"type":"Point"},"properties":{"osm_id":"5590542595","tag":{"natural":"tree"}},"type":"Feature"},
	{"geometry":{"coordinates":[-74.533639,-8.378757],"type":"Point"},"properties":{"osm_id":"5590542596","tag":{"natural":"tree"}},"type":"Feature"},
	{"geometry":{"coordinates":[-74.533668,-8.378793],"type":"Point"},"properties":{"osm_id":"5590542597","tag":{"natural":"tree"}},"type":"Feature"}
]
}
