{
"type": "FeatureCollection",
"lastupdate": "2020-07-31T00:00:00Z",
"features": [
	{"geometry":{"coordinates":[-66.689109,45.944208],"type":"Point"},"properties":{"name":"Bishop Dr Irving Recycling Depot","osm_id":"1820633412","tag":{"amenity":"recycling"}},"type":"Feature"},
	{"geometry":{"coordinates":[-66.680932,45.949052],"type":"Point"},"properties":{"osm_id":"2290910073","tag":{"amenity":"waste_basket"}},"type":"Feature"},
	{"geometry":{"coordinates":[-66.680554,45.949513],"type":"Point"},"properties":{"osm_id":"2290913097","tag":{"amenity":"waste_basket"}},"type":"Feature"},
	{"geometry":{"coordinates":[-66.623224,45.918127],"type":"Point"},"properties":{"name":"Computers for Schools (CFS)","osm_id":"3418901093","tag":{"addr:city":"Fredericton","addr:housenumber":"125","addr:postcode":"E3B 5H1","addr:street":"Hilton Road","amenity":"recycling","recycling:computers":"yes","website":"http://cfsopenb.nbed.nb.ca/"}},"type":"Feature"}
]
}
