{
"type": "FeatureCollection",
"features": [
	{"geometry":{"coordinates":[-44.888312,-20.095511],"type":"Point"},"properties":{"name":"Bambu","osm_id":"7312232088","tag":{"leaf_cycle":"evergreen","leaf_type":"mixed","natural":"tree"}},"type":"Feature"},
	{"geometry":{"coordinates":[-44.88837,-20.095468],"type":"Point"},"properties":{"name":"Bambu","osm_id":"7312232089","tag":{"leaf_cycle":"evergreen","leaf_type":"mixed","natural":"tree"}},"type":"Feature"},
	{"geometry":{"coordinates":[-44.888127,-20.095752],"type":"Point"},"properties":{"name":"Bambu","osm_id":"7312232090","tag":{"leaf_cycle":"evergreen","leaf_type":"mixed","natural":"tree"}},"type":"Feature"},
	{"geometry":{"coordinates":[-44.887978,-20.095668],"type":"Point"},"properties":{"name":"Bambu","osm_id":"7312232091","tag":{"leaf_cycle":"evergreen","leaf_type":"mixed","natural":"tree"}},"type":"Feature"}
]
}
