{
"type": "FeatureCollection",
"features": [
	{"geometry":{"coordinates":[23.730517,50.413813],"type":"Point"},"properties":{"name":"Sosna Grottgera","osm_id":"3005708415","tag":{"natural":"tree"}},"type":"Feature"},
	{"geometry":{"coordinates":[23.734637,50.414574],"type":"Point"},"properties":{"osm_id":"8912189404","tag":{"natural":"tree"}},"type":"Feature"},
	{"geometry":{"coordinates":[23.734725,50.414575],"type":"Point"},"properties":{"osm_id":"8912189405","tag":{"natural":"tree"}},"type":"Feature"},
	{"geometry":{"coordinates":[23.734826,50.414447],"type":"Point"},"properties":{"osm_id":"8912189406","tag":{"natural":"tree"}},"type":"Feature"},
	{"geometry":{"coordinates":[23.734648,50.414477],"type":"Point"},"properties":{"osm_id":"8912189407","tag":{"natural":"tree"}},"type":"Feature"},
	{"geometry":{"coordinates":[23.734992,50.414553],"type":"Point"},"properties":{"osm_id":"8912189408","tag":{"natural":"tree"}},"type":"Feature"}
]
}
