{
"type": "FeatureCollection",
"features": [
	{"geometry":{"coordinates":[23.730481,50.413836],"type":"Point"},"properties":{"name":"Sosna Grottgera","osm_id":"3005708415","tag":{"natural":"tree"}},"type":"Feature"}
]
}
