{
"type": "FeatureCollection",
"features": [
	{"geometry":{"coordinates":[-0.529026,52.169352],"type":"Point"},"properties":{"name":"Glass recycling ","osm_id":"7640840163","tag":{"amenity":"recycling"}},"type":"Feature"}
]
}
