{
"type": "FeatureCollection",
"features": [
	{"geometry":{"coordinates":[-0.529026,52.169352],"type":"Point"},"properties":{"name":"Glass recycling ","osm_id":"7640840163","tag":{"amenity":"recycling"}},"type":"Feature"},
	{"geometry":{"coordinates":[-0.602418,52.202694],"type":"Point"},"properties":{"osm_id":"7947806366","tag":{"amenity":"waste_basket","waste":"dog_excrement"}},"type":"Feature"},
	{"geometry":{"coordinates":[-0.591419,52.20635],"type":"Point"},"properties":{"osm_id":"7947868989","tag":{"amenity":"waste_basket","waste":"dog_excrement"}},"type":"Feature"}
]
}
