{
"type": "FeatureCollection",
"features": [
	{"geometry":{"coordinates":[-0.529027,52.169353],"type":"Point"},"properties":{"name":"Glass recycling ","osm_id":"7640840163","tag":{"amenity":"recycling"}},"type":"Feature"},
	{"geometry":{"coordinates":[-0.602419,52.202695],"type":"Point"},"properties":{"osm_id":"7947806366","tag":{"amenity":"waste_basket","waste":"dog_excrement"}},"type":"Feature"},
	{"geometry":{"coordinates":[-0.591419,52.206351],"type":"Point"},"properties":{"osm_id":"7947868989","tag":{"amenity":"waste_basket","waste":"dog_excrement"}},"type":"Feature"}
]
}
