{
"type": "FeatureCollection",
"features": [
	{"geometry":{"coordinates":[-0.587031,38.965893],"type":"Point"},"properties":{"osm_id":"3894001931","tag":{"addr:city":"Canals","addr:postcode":"46650","addr:street":"Carrer Innovadora","amenity":"recycling","recycling:cans":"yes","recycling:glass_bottles":"yes","recycling_type":"container"}},"type":"Feature"},
	{"geometry":{"coordinates":[-0.535692,38.985129],"type":"Point"},"properties":{"osm_id":"7312014426","tag":{"amenity":"waste_disposal"}},"type":"Feature"}
]
}
