{
"type": "FeatureCollection",
"lastupdate": "2020-07-31T00:00:00Z",
"features": [
	{"geometry":{"coordinates":[-0.58703,38.965892],"type":"Point"},"properties":{"osm_id":"3894001931","tag":{"addr:city":"Canals","addr:postcode":"46650","addr:street":"Carrer Innovadora","amenity":"recycling","recycling:cans":"yes","recycling:glass_bottles":"yes","recycling_type":"container"}},"type":"Feature"}
]
}
