{
"type": "FeatureCollection",
"features": [
	{"geometry":{"coordinates":[-0.58703,38.965892],"type":"Point"},"properties":{"osm_id":"3894001931","tag":{"addr:city":"Canals","addr:postcode":"46650","addr:street":"Carrer Innovadora","amenity":"recycling","recycling:cans":"yes","recycling:glass_bottles":"yes","recycling_type":"container"}},"type":"Feature"},
	{"geometry":{"coordinates":[-0.535691,38.985129],"type":"Point"},"properties":{"osm_id":"7312014426","tag":{"amenity":"waste_disposal"}},"type":"Feature"},
	{"geometry":{"coordinates":[-0.545158,38.981533],"type":"Point"},"properties":{"osm_id":"8689954758","tag":{"amenity":"recycling","recycling_type":"container"}},"type":"Feature"},
	{"geometry":{"coordinates":[-0.547447,38.979056],"type":"Point"},"properties":{"osm_id":"8710184435","tag":{"amenity":"recycling","recycling_type":"container"}},"type":"Feature"}
]
}
