{
"type": "FeatureCollection",
"features": [
	{"geometry":{"coordinates":[31.786782,3.19565],"type":"Point"},"properties":{"name":"Waste basket for mungula I market in Block C","osm_id":"5772349440","tag":{"addr:block":"Mungula I Market in Block C","addr:district":"Adjumani","addr:settlement":"Mungula","amenity":"waste_basket","fee":"no","lit":"no","operator:type":"community","source:version":"Sanitation;v3.0.2","start_date":"2016-05-01","waste":"Polythene bag, plastic bottle ,etc"}},"type":"Feature"},
	{"geometry":{"coordinates":[31.786557,3.195658],"type":"Point"},"properties":{"name":"Metal waste basket for mungula I market","osm_id":"5772349441","tag":{"addr:block":"Mungula I market in block C","addr:district":"Adjumani","addr:settlement":"Mungula","amenity":"waste_basket","fee":"no","lit":"no","operator:type":"community","source:version":"Sanitation;v3.0.2","start_date":"2016-07-01","waste":"Polythene bags, fruits waste"}},"type":"Feature"},
	{"geometry":{"coordinates":[31.786715,3.195302],"type":"Point"},"properties":{"name":"Waste basket for mungula I market","osm_id":"5772349442","tag":{"addr:block":"Mungula I market in block C","addr:district":"Adjumani","addr:settlement":"Mungula","amenity":"waste_basket","fee":"no","lit":"no","operator":"LWF","operator:type":"ngo","source:version":"Sanitation;v3.0.2","start_date":"2016-06-01","waste":"Plastic bottle, polythene bags , waste from fruits, etc"}},"type":"Feature"},
	{"geometry":{"coordinates":[31.78685,3.195088],"type":"Point"},"properties":{"name":"Waste disposal for mungula I market","osm_id":"5772349445","tag":{"addr:block":"Mungula I market Block C","addr:district":"Adjumani","addr:settlement":"Mungula","amenity":"waste_disposal","fee":"no","lit":"no","operator":"FH","operator:type":"ngo","source:version":"Sanitation;v3.0.2","start_date":"2014-05-01","waste":"Market waste , waste from shop and etc"}},"type":"Feature"}
]
}
