{
"type": "FeatureCollection",
"features": [
	{"geometry":{"coordinates":[-74.57261,40.556607],"type":"Point"},"properties":{"name":"Somerset County Recycling","osm_id":"1959861883","tag":{"amenity":"recycling","recycling_type":"centre"}},"type":"Feature"},
	{"geometry":{"coordinates":[-74.592743,40.536379],"type":"Point"},"properties":{"highway":"crossing","osm_id":"7126238891","tag":{"crossing":"marked"}},"type":"Feature"},
	{"geometry":{"coordinates":[-74.5932,40.535934],"type":"Point"},"properties":{"highway":"crossing","osm_id":"7126238949","tag":{"crossing":"marked"}},"type":"Feature"}
]
}
