{
"type": "FeatureCollection",
"features": [
	{"geometry":{"coordinates":[-74.57261,40.556607],"type":"Point"},"properties":{"name":"Somerset County Recycling","osm_id":"1959861883","tag":{"amenity":"recycling","recycling_type":"centre"}},"type":"Feature"}
]
}
