{
"type": "FeatureCollection",
"lastupdate": "2020-08-06T00:00:00Z",
"features": [
	{"geometry":{"coordinates":[15.945511,48.511658],"type":"Point"},"properties":{"name":"Gemeindesammelzentrum","osm_id":"1375625233","tag":{"amenity":"recycling","recycling_type":"centre"}},"type":"Feature"},
	{"geometry":{"coordinates":[15.99134,48.465379],"type":"Point"},"properties":{"name":"Bauhof","osm_id":"1502697047","tag":{"amenity":"recycling","recycling:batteries":"yes","recycling:cartons":"yes","recycling:electrical_appliances":"yes","recycling:glass":"yes","recycling:glass_bottles":"yes","recycling:green_waste":"yes","recycling:paper":"yes","recycling_type":"centre"}},"type":"Feature"},
	{"geometry":{"coordinates":[15.952267,48.466707],"type":"Point"},"properties":{"osm_id":"6168979395","tag":{"amenity":"waste_basket"}},"type":"Feature"},
	{"geometry":{"coordinates":[15.967196,48.470744],"type":"Point"},"properties":{"osm_id":"6434649188","tag":{"amenity":"waste_basket"}},"type":"Feature"},
	{"geometry":{"coordinates":[15.95459,48.469501],"type":"Point"},"properties":{"osm_id":"6434681429","tag":{"amenity":"waste_basket"}},"type":"Feature"},
	{"geometry":{"coordinates":[15.967108,48.475592],"type":"Point"},"properties":{"osm_id":"6434749688","tag":{"amenity":"recycling","recycling:green_waste":"yes","recycling_type":"container"}},"type":"Feature"},
	{"geometry":{"coordinates":[15.944267,48.496294],"type":"Point"},"properties":{"osm_id":"6435249575","tag":{"amenity":"waste_basket"}},"type":"Feature"},
	{"geometry":{"coordinates":[15.924305,48.490707],"type":"Point"},"properties":{"osm_id":"7061847312","tag":{"amenity":"waste_basket"}},"type":"Feature"},
	{"geometry":{"coordinates":[15.929662,48.478752],"type":"Point"},"properties":{"osm_id":"7061847348","tag":{"amenity":"waste_basket"}},"type":"Feature"},
	{"geometry":{"coordinates":[15.946772,48.499804],"type":"Point"},"properties":{"osm_id":"7069374307","tag":{"amenity":"waste_basket"}},"type":"Feature"},
	{"geometry":{"coordinates":[15.964086,48.463468],"type":"Point"},"properties":{"osm_id":"7298033231","tag":{"amenity":"waste_basket"}},"type":"Feature"},
	{"geometry":{"coordinates":[15.967438,48.462939],"type":"Point"},"properties":{"osm_id":"7528757536","tag":{"amenity":"waste_basket"}},"type":"Feature"}
]
}
