{
"type": "FeatureCollection",
"lastupdate": "2020-08-05T00:00:00Z",
"features": [
	{"geometry":{"coordinates":[-122.108111,37.652455],"type":"Point"},"properties":{"name":"Nexcycle","osm_id":"1238955067","tag":{"amenity":"recycling","recycling:cans":"yes","recycling:glass_bottles":"yes","recycling:plastic_bottles":"yes"}},"type":"Feature"},
	{"geometry":{"coordinates":[-122.091928,37.660165],"type":"Point"},"properties":{"osm_id":"4650266139","tag":{"amenity":"waste_basket"}},"type":"Feature"},
	{"geometry":{"coordinates":[-122.091408,37.660335],"type":"Point"},"properties":{"osm_id":"4650266146","tag":{"amenity":"waste_basket"}},"type":"Feature"},
	{"geometry":{"coordinates":[-122.093365,37.662486],"type":"Point"},"properties":{"osm_id":"4650278744","tag":{"amenity":"waste_basket"}},"type":"Feature"}
]
}
