{
"type": "FeatureCollection",
"features": [
	{"geometry":{"coordinates":[-83.975448,34.784063],"type":"Point"},"properties":{"name":"Whiteoak Stomp","osm_id":"5101100677","tag":{"natural":"tree"}},"type":"Feature"}
]
}
