{
"type": "FeatureCollection",
"features": [
	{"geometry":{"coordinates":[-57.394899,-35.132126],"type":"Point"},"properties":{"name":"Senderos Reserva El Destino","osm_id":"3792174423","tag":{"natural":"tree"}},"type":"Feature"}
]
}
