{
"type": "FeatureCollection",
"features": [
	{"geometry":{"coordinates":[19.836263,45.281196],"type":"Point"},"properties":{"name":"Otpad Skoric","osm_id":"4810423122","tag":{"amenity":"recycling","name:sr":"Otpad Skoric","operator":"Otkup i prodaja metala i elektronike"}},"type":"Feature"}
]
}
