{
"type": "FeatureCollection",
"features": [
	{"geometry":{"coordinates":[-76.50845,44.286927],"type":"Point"},"properties":{"name":"Bee Tree","osm_id":"454732038","tag":{"natural":"tree"}},"type":"Feature"}
]
}
