{
"type": "FeatureCollection",
"features": [
	{"geometry":{"coordinates":[114.025812,22.532975],"type":"Point"},"properties":{"name":"\u00e5\u00a4\u00a9\u00e5\u00ae\u0089\u00e5\u009e\u0083\u00e5\u009c\u00be\u00e8\u00bd\u00ac\u00e8\u00bf\u0090\u00e7\u00ab\u0099","osm_id":"4823463474","tag":{"amenity":"waste_disposal","name:zh":"\u5929\u5b89\u5783\u573e\u8f6c\u8fd0\u7ad9","name:zh-Hans":"\u5929\u5b89\u5783\u573e\u8f6c\u8fd0\u7ad9","name:zh-Hant":"\u5929\u5b89\u5783\u573e\u8f49\u904b\u7ad9"}},"type":"Feature"}
]
}
