{
"type": "FeatureCollection",
"features": [
	{"geometry":{"coordinates":[114.025812,22.532975],"type":"Point"},"properties":{"name":"\u00e5\u00a4\u00a9\u00e5\u00ae\u0089\u00e5\u009e\u0083\u00e5\u009c\u00be\u00e8\u00bd\u00ac\u00e8\u00bf\u0090\u00e7\u00ab\u0099","osm_id":"4823463474","tag":{"amenity":"waste_disposal","name:zh":"\u00e5\u00a4\u00a9\u00e5\u00ae\u0089\u00e5\u009e\u0083\u00e5\u009c\u00be\u00e8\u00bd\u00ac\u00e8\u00bf\u0090\u00e7\u00ab\u0099","name:zh-Hans":"\u00e5\u00a4\u00a9\u00e5\u00ae\u0089\u00e5\u009e\u0083\u00e5\u009c\u00be\u00e8\u00bd\u00ac\u00e8\u00bf\u0090\u00e7\u00ab\u0099","name:zh-Hant":"\u00e5\u00a4\u00a9\u00e5\u00ae\u0089\u00e5\u009e\u0083\u00e5\u009c\u00be\u00e8\u00bd\u0089\u00e9\u0081\u008b\u00e7\u00ab\u0099"}},"type":"Feature"}
]
}
