{
"type": "FeatureCollection",
"lastupdate": "2020-08-06T00:00:00Z",
"features": [
	{"geometry":{"coordinates":[114.02453,22.44528],"type":"Point"},"properties":{"osm_id":"2406459611","tag":{"amenity":"recycling","recycling:cans":"yes","recycling:paper":"yes","recycling:plastic":"yes","recycling_type":"container"}},"type":"Feature"},
	{"geometry":{"coordinates":[114.023325,22.444717],"type":"Point"},"properties":{"osm_id":"2406459675","tag":{"amenity":"waste_basket"}},"type":"Feature"},
	{"geometry":{"coordinates":[114.023647,22.444715],"type":"Point"},"properties":{"osm_id":"2406459877","tag":{"amenity":"waste_basket"}},"type":"Feature"},
	{"geometry":{"coordinates":[114.024481,22.44477],"type":"Point"},"properties":{"osm_id":"2406468086","tag":{"amenity":"waste_basket"}},"type":"Feature"},
	{"geometry":{"coordinates":[114.024484,22.444656],"type":"Point"},"properties":{"osm_id":"2406468087","tag":{"amenity":"waste_basket"}},"type":"Feature"},
	{"geometry":{"coordinates":[114.034053,22.443745],"type":"Point"},"properties":{"name":"\u00e4\u00b8\u008d\u00e6\u0098\u00af\u00e5\u009e\u0083\u00e5\u009c\u00be\u00e7\u00ab\u0099 Waste-no-mall","osm_id":"5655134867","tag":{"amenity":"recycling","facebook":"https://www.facebook.com/WasteNoMall/","name:en":"Waste-no-mall","name:zh":"\u4e0d\u662f\u5783\u573e\u7ad9","opening_hours":"Sa 16:00-18:00","recycling_type":"centre"}},"type":"Feature"}
]
}
