{
"type": "FeatureCollection",
"features": [
	{"geometry":{"coordinates":[-1.405907,52.273411],"type":"Point"},"properties":{"name":"Bascote Rubbish Disposal","osm_id":"2498333630","tag":{"access":"permissive","amenity":"waste_disposal","operator":"Canal and River Trust","waste":"trash","waterway":"waste_disposal"}},"type":"Feature"}
]
}
