{
"type": "FeatureCollection",
"features": [
	{"geometry":{"coordinates":[-1.337098,51.073938],"type":"Point"},"properties":{"name":"Recycling Bank - Waitrose Winchester","osm_id":"1847503736","tag":{"amenity":"recycling","designation":"Recycling Bank","recycling:batteries":"no","recycling:books":"no","recycling:cans":"yes","recycling:cardboard":"yes","recycling:cartons":"no","recycling:clothes":"yes","recycling:electrical_appliances":"no","recycling:glass":"yes","recycling:glass_bottles":"yes","recycling:green_waste":"no","recycling:magazines":"yes","recycling:newspaper":"yes","recycling:paper":"yes","recycling:paper_packaging":"no","recycling:plastic":"no","recycling:plastic_bottles":"yes","recycling:plastic_packaging":"no","recycling:scrap_metal":"no","recycling:small_appliances":"no","recycling:waste":"no","recycling:wood":"no","recycling_type":"container"}},"type":"Feature"},
	{"geometry":{"coordinates":[-1.391169,51.084431],"type":"Point"},"properties":{"osm_id":"9101376874","tag":{"amenity":"waste_basket"}},"type":"Feature"},
	{"geometry":{"coordinates":[-1.390494,51.084681],"type":"Point"},"properties":{"osm_id":"9111797347","tag":{"amenity":"waste_basket"}},"type":"Feature"}
]
}
