{
"type": "FeatureCollection",
"features": [
	{"geometry":{"coordinates":[-1.332109,46.150374],"type":"Point"},"properties":{"osm_id":"1883503057","tag":{"amenity":"recycling","recycling:glass_bottles":"yes","recycling:paper":"yes","recycling_type":"container"}},"type":"Feature"},
	{"geometry":{"coordinates":[-1.323868,46.146525],"type":"Point"},"properties":{"osm_id":"2431986688","tag":{"amenity":"waste_basket"}},"type":"Feature"},
	{"geometry":{"coordinates":[-1.324475,46.15474],"type":"Point"},"properties":{"osm_id":"2437306292","tag":{"amenity":"recycling","location":"underground","recycling:glass_bottles":"yes","recycling:paper":"yes","recycling_type":"container"}},"type":"Feature"},
	{"geometry":{"coordinates":[-1.385772,46.17928],"type":"Point"},"properties":{"osm_id":"2800777501","tag":{"amenity":"recycling","recycling:glass_bottles":"yes","recycling:paper":"yes","source:recycling:paper":"survey"}},"type":"Feature"},
	{"geometry":{"coordinates":[-1.360092,46.189254],"type":"Point"},"properties":{"barrier":"gate","osm_id":"3655538813","tag":{"access":"destination"}},"type":"Feature"},
	{"geometry":{"coordinates":[-1.325686,46.187165],"type":"Point"},"properties":{"osm_id":"7909269785","tag":{"amenity":"waste_basket","survey:date":"2020-09-15","waste":"trash"}},"type":"Feature"},
	{"geometry":{"coordinates":[-1.394074,46.178792],"type":"Point"},"properties":{"osm_id":"7913617385","tag":{"amenity":"recycling","recycling:clothes":"no","recycling:glass_bottles":"yes","recycling:paper":"yes","recycling:plastic":"no","recycling_type":"container","survey:date":"2020-09-16"}},"type":"Feature"},
	{"geometry":{"coordinates":[-1.391947,46.184253],"type":"Point"},"properties":{"osm_id":"7927533485","tag":{"amenity":"waste_basket","survey:date":"2020-09-21","waste":"trash"}},"type":"Feature"},
	{"geometry":{"coordinates":[-1.392262,46.184587],"type":"Point"},"properties":{"osm_id":"7927533487","tag":{"amenity":"waste_basket","survey:date":"2020-09-21","waste":"trash"}},"type":"Feature"},
	{"geometry":{"coordinates":[-1.391888,46.184064],"type":"Point"},"properties":{"osm_id":"7927546186","tag":{"amenity":"waste_basket","survey:date":"2020-09-21","waste":"trash"}},"type":"Feature"},
	{"geometry":{"coordinates":[-1.392259,46.184062],"type":"Point"},"properties":{"osm_id":"7927943985","tag":{"amenity":"waste_basket","survey:date":"2020-09-21","waste":"trash"}},"type":"Feature"},
	{"geometry":{"coordinates":[-1.392238,46.184803],"type":"Point"},"properties":{"osm_id":"7927944585","tag":{"amenity":"waste_basket","survey:date":"2020-09-21","waste":"trash"}},"type":"Feature"},
	{"geometry":{"coordinates":[-1.392536,46.186513],"type":"Point"},"properties":{"osm_id":"7928877786","tag":{"amenity":"waste_basket","survey:date":"2020-09-21","waste":"trash"}},"type":"Feature"},
	{"geometry":{"coordinates":[-1.392428,46.18391],"type":"Point"},"properties":{"osm_id":"7931008885","tag":{"amenity":"waste_basket","survey:date":"2020-09-22","waste":"trash"}},"type":"Feature"},
	{"geometry":{"coordinates":[-1.395226,46.188129],"type":"Point"},"properties":{"osm_id":"8450517323","tag":{"amenity":"waste_disposal"}},"type":"Feature"},
	{"geometry":{"coordinates":[-1.362507,46.162579],"type":"Point"},"properties":{"osm_id":"9010777572","tag":{"amenity":"waste_basket"}},"type":"Feature"},
	{"geometry":{"coordinates":[-1.355992,46.194632],"type":"Point"},"properties":{"osm_id":"9012098108","tag":{"amenity":"waste_disposal"}},"type":"Feature"}
]
}
