{
"type": "FeatureCollection",
"lastupdate": "2020-08-05T00:00:00Z",
"features": [
	{"geometry":{"coordinates":[-1.332109,46.150374],"type":"Point"},"properties":{"osm_id":"1883503057","tag":{"amenity":"recycling","recycling:glass_bottles":"yes","recycling:paper":"yes","recycling_type":"container"}},"type":"Feature"},
	{"geometry":{"coordinates":[-1.323868,46.146525],"type":"Point"},"properties":{"osm_id":"2431986688","tag":{"amenity":"waste_basket"}},"type":"Feature"},
	{"geometry":{"coordinates":[-1.324475,46.15474],"type":"Point"},"properties":{"osm_id":"2437306292","tag":{"amenity":"recycling","location":"underground","recycling:glass_bottles":"yes","recycling:paper":"yes","recycling_type":"container"}},"type":"Feature"},
	{"geometry":{"coordinates":[-1.385772,46.17928],"type":"Point"},"properties":{"osm_id":"2800777501","tag":{"amenity":"recycling","recycling:glass_bottles":"yes","recycling:paper":"yes","source:recycling:paper":"survey"}},"type":"Feature"},
	{"geometry":{"coordinates":[-1.360092,46.189254],"type":"Point"},"properties":{"barrier":"gate","osm_id":"3655538813","tag":{"access":"destination"}},"type":"Feature"}
]
}
