{
"type": "FeatureCollection",
"features": [
	{"geometry":{"coordinates":[-1.33211,46.150375],"type":"Point"},"properties":{"osm_id":"1883503057","tag":{"amenity":"recycling","recycling:glass_bottles":"yes","recycling:paper":"yes","recycling_type":"container"}},"type":"Feature"},
	{"geometry":{"coordinates":[-1.323868,46.146526],"type":"Point"},"properties":{"osm_id":"2431986688","tag":{"amenity":"waste_basket"}},"type":"Feature"},
	{"geometry":{"coordinates":[-1.324476,46.154741],"type":"Point"},"properties":{"osm_id":"2437306292","tag":{"amenity":"recycling","location":"underground","recycling:glass_bottles":"yes","recycling:paper":"yes","recycling_type":"container"}},"type":"Feature"},
	{"geometry":{"coordinates":[-1.385772,46.179281],"type":"Point"},"properties":{"osm_id":"2800777501","tag":{"amenity":"recycling","recycling:glass_bottles":"yes","recycling:paper":"yes","source:recycling:paper":"survey"}},"type":"Feature"},
	{"geometry":{"coordinates":[-1.360092,46.189254],"type":"Point"},"properties":{"barrier":"gate","osm_id":"3655538813","tag":{"access":"destination"}},"type":"Feature"},
	{"geometry":{"coordinates":[-1.325687,46.187165],"type":"Point"},"properties":{"osm_id":"7909269785","tag":{"amenity":"waste_basket","survey:date":"2020-09-15","waste":"trash"}},"type":"Feature"},
	{"geometry":{"coordinates":[-1.394074,46.178793],"type":"Point"},"properties":{"osm_id":"7913617385","tag":{"amenity":"recycling","recycling:clothes":"no","recycling:glass_bottles":"yes","recycling:paper":"yes","recycling:plastic":"no","recycling_type":"container","survey:date":"2020-09-16"}},"type":"Feature"},
	{"geometry":{"coordinates":[-1.391948,46.184253],"type":"Point"},"properties":{"osm_id":"7927533485","tag":{"amenity":"waste_basket","survey:date":"2020-09-21","waste":"trash"}},"type":"Feature"},
	{"geometry":{"coordinates":[-1.392262,46.184588],"type":"Point"},"properties":{"osm_id":"7927533487","tag":{"amenity":"waste_basket","survey:date":"2020-09-21","waste":"trash"}},"type":"Feature"},
	{"geometry":{"coordinates":[-1.391888,46.184064],"type":"Point"},"properties":{"osm_id":"7927546186","tag":{"amenity":"waste_basket","survey:date":"2020-09-21","waste":"trash"}},"type":"Feature"},
	{"geometry":{"coordinates":[-1.39226,46.184063],"type":"Point"},"properties":{"osm_id":"7927943985","tag":{"amenity":"waste_basket","survey:date":"2020-09-21","waste":"trash"}},"type":"Feature"},
	{"geometry":{"coordinates":[-1.392239,46.184803],"type":"Point"},"properties":{"osm_id":"7927944585","tag":{"amenity":"waste_basket","survey:date":"2020-09-21","waste":"trash"}},"type":"Feature"},
	{"geometry":{"coordinates":[-1.392537,46.186513],"type":"Point"},"properties":{"osm_id":"7928877786","tag":{"amenity":"waste_basket","survey:date":"2020-09-21","waste":"trash"}},"type":"Feature"},
	{"geometry":{"coordinates":[-1.392428,46.18391],"type":"Point"},"properties":{"osm_id":"7931008885","tag":{"amenity":"waste_basket","survey:date":"2020-09-22","waste":"trash"}},"type":"Feature"}
]
}
