{
"type": "FeatureCollection",
"features": [
	{"geometry":{"coordinates":[-1.34555,45.976481],"type":"Point"},"properties":{"osm_id":"830367155","tag":{"amenity":"recycling","recycling_type":"container"}},"type":"Feature"},
	{"geometry":{"coordinates":[-1.325858,45.980347],"type":"Point"},"properties":{"osm_id":"834641911","tag":{"amenity":"recycling"}},"type":"Feature"},
	{"geometry":{"coordinates":[-1.337523,45.977185],"type":"Point"},"properties":{"osm_id":"834641955","tag":{"amenity":"recycling"}},"type":"Feature"},
	{"geometry":{"coordinates":[-1.343667,46.010089],"type":"Point"},"properties":{"osm_id":"836511903","tag":{"amenity":"recycling","recycling_type":"container"}},"type":"Feature"},
	{"geometry":{"coordinates":[-1.336271,46.008022],"type":"Point"},"properties":{"osm_id":"836511984","tag":{"amenity":"recycling","recycling_type":"container"}},"type":"Feature"},
	{"geometry":{"coordinates":[-1.320889,45.962641],"type":"Point"},"properties":{"osm_id":"843106510","tag":{"amenity":"recycling"}},"type":"Feature"},
	{"geometry":{"coordinates":[-1.343402,45.989432],"type":"Point"},"properties":{"osm_id":"843106519","tag":{"amenity":"recycling"}},"type":"Feature"},
	{"geometry":{"coordinates":[-1.329784,45.955746],"type":"Point"},"properties":{"osm_id":"843106850","tag":{"amenity":"recycling"}},"type":"Feature"},
	{"geometry":{"coordinates":[-1.379499,45.953872],"type":"Point"},"properties":{"osm_id":"1395196918","tag":{"amenity":"recycling","recycling_type":"container"}},"type":"Feature"},
	{"geometry":{"coordinates":[-1.376407,45.97128],"type":"Point"},"properties":{"osm_id":"3041145111","tag":{"amenity":"recycling","recycling:glass":"yes"}},"type":"Feature"},
	{"geometry":{"coordinates":[-1.36947,45.987648],"type":"Point"},"properties":{"osm_id":"4988335514","tag":{"amenity":"recycling","recycling_type":"container"}},"type":"Feature"},
	{"geometry":{"coordinates":[-1.352326,45.972683],"type":"Point"},"properties":{"osm_id":"5006795632","tag":{"amenity":"recycling","recycling:glass_bottles":"yes","recycling_type":"container"}},"type":"Feature"},
	{"geometry":{"coordinates":[-1.391159,45.982329],"type":"Point"},"properties":{"osm_id":"5050746221","tag":{"amenity":"recycling","location":"overground","recycling:glass_bottles":"yes","recycling:paper":"yes","recycling:waste":"yes","recycling_type":"container"}},"type":"Feature"},
	{"geometry":{"coordinates":[-1.329721,46.00523],"type":"Point"},"properties":{"osm_id":"5679255418","tag":{"amenity":"waste_disposal"}},"type":"Feature"},
	{"geometry":{"coordinates":[-1.329718,46.005209],"type":"Point"},"properties":{"osm_id":"5679256329","tag":{"amenity":"recycling","recycling:glass":"yes","recycling:plastic_packaging":"yes","recycling_type":"container"}},"type":"Feature"},
	{"geometry":{"coordinates":[-1.335077,45.99575],"type":"Point"},"properties":{"osm_id":"5776980129","tag":{"amenity":"waste_basket"}},"type":"Feature"},
	{"geometry":{"coordinates":[-1.350455,45.952375],"type":"Point"},"properties":{"osm_id":"5843511816","tag":{"amenity":"recycling","recycling:glass":"yes","recycling:glass_bottles":"yes","recycling_type":"container"}},"type":"Feature"},
	{"geometry":{"coordinates":[-1.366075,45.955191],"type":"Point"},"properties":{"osm_id":"5843555372","tag":{"amenity":"recycling","recycling:glass":"yes","recycling:glass_bottles":"yes","recycling_type":"container"}},"type":"Feature"},
	{"geometry":{"coordinates":[-1.366323,45.955498],"type":"Point"},"properties":{"osm_id":"5843565628","tag":{"amenity":"waste_basket"}},"type":"Feature"},
	{"geometry":{"coordinates":[-1.345392,45.976611],"type":"Point"},"properties":{"osm_id":"7795139886","tag":{"amenity":"recycling","recycling_type":"container"}},"type":"Feature"},
	{"geometry":{"coordinates":[-1.326254,45.970986],"type":"Point"},"properties":{"osm_id":"7798469015","tag":{"amenity":"recycling","recycling_type":"container"}},"type":"Feature"},
	{"geometry":{"coordinates":[-1.347458,45.972527],"type":"Point"},"properties":{"osm_id":"8036609180","tag":{"amenity":"recycling","opening_hours":"24/7","recycling:glass":"yes","recycling:glass_bottles":"yes","recycling_type":"container","wheelchair":"no"}},"type":"Feature"}
]
}
