{
"type": "FeatureCollection",
"features": [
	{"geometry":{"coordinates":[-1.335431,44.037798],"type":"Point"},"properties":{"name":"C.CapD LHomy","osm_id":"4325222461","tag":{"amenity":"recycling","operator":"SITCOM - C\u00f4te sud des Landes","operator:wikidata":"Q90819597","recycling:batteries":"yes","recycling:beverage_cartons":"yes","recycling:cans":"yes","recycling:glass_bottles":"yes","recycling:paper":"yes","recycling:paper_packaging":"yes","recycling:plastic_bottles":"yes","recycling_type":"container","ref:FR:SITCOM":"PAV-374354"}},"type":"Feature"},
	{"geometry":{"coordinates":[-1.337936,44.037437],"type":"Point"},"properties":{"name":"CAP D L HOMY R D la Foret","osm_id":"4325264008","tag":{"amenity":"recycling","operator":"SITCOM - C\u00f4te sud des Landes","operator:wikidata":"Q90819597","recycling:cans":"yes","recycling:glass_bottles":"yes","recycling:paper":"yes","recycling:paper_packaging":"yes","recycling:plastic_bottles":"yes","recycling_type":"container","ref:FR:SITCOM":"PAV-480241"}},"type":"Feature"},
	{"geometry":{"coordinates":[-1.335026,44.036872],"type":"Point"},"properties":{"osm_id":"5039863447","tag":{"amenity":"waste_basket"}},"type":"Feature"},
	{"geometry":{"coordinates":[-1.337688,44.03858],"type":"Point"},"properties":{"osm_id":"6720793001","tag":{"amenity":"waste_basket","waste":"trash"}},"type":"Feature"},
	{"geometry":{"coordinates":[-1.337314,44.038477],"type":"Point"},"properties":{"name":"Cap De L Homy","osm_id":"7440802335","tag":{"amenity":"recycling","operator":"SITCOM - C\u00f4te sud des Landes","operator:wikidata":"Q90819597","recycling:batteries":"yes","recycling_type":"container","ref:FR:SITCOM":"PAV-374355"}},"type":"Feature"}
]
}
