{
"type": "FeatureCollection",
"features": [
	{"geometry":{"coordinates":[-64.110265,-30.769848],"type":"Point"},"properties":{"name":"Algarrobo Historico","osm_id":"4020584459","tag":{"natural":"tree"}},"type":"Feature"}
]
}
