{
"type": "FeatureCollection",
"features": [
	{"geometry":{"coordinates":[7.131876,52.302725],"type":"Point"},"properties":{"osm_id":"954028583","tag":{"amenity":"recycling","recycling_type":"container"}},"type":"Feature"},
	{"geometry":{"coordinates":[7.135383,52.300959],"type":"Point"},"properties":{"osm_id":"1966232036","tag":{"amenity":"recycling","recycling_type":"container"}},"type":"Feature"},
	{"geometry":{"coordinates":[7.133481,52.304311],"type":"Point"},"properties":{"osm_id":"1966232037","tag":{"amenity":"recycling","recycling_type":"container"}},"type":"Feature"},
	{"geometry":{"coordinates":[7.136463,52.302378],"type":"Point"},"properties":{"osm_id":"1966797424","tag":{"amenity":"waste_basket"}},"type":"Feature"},
	{"geometry":{"coordinates":[7.136823,52.302398],"type":"Point"},"properties":{"osm_id":"1966797430","tag":{"amenity":"waste_basket"}},"type":"Feature"},
	{"geometry":{"coordinates":[7.149607,52.291895],"type":"Point"},"properties":{"osm_id":"3202436709","tag":{"amenity":"waste_basket"}},"type":"Feature"},
	{"geometry":{"coordinates":[7.158399,52.301783],"type":"Point"},"properties":{"osm_id":"3526260621","tag":{"amenity":"waste_basket"}},"type":"Feature"},
	{"geometry":{"coordinates":[7.153007,52.308033],"type":"Point"},"properties":{"osm_id":"3623345218","tag":{"amenity":"recycling","recycling:clothes":"yes","recycling:shoes":"yes","recycling_type":"container"}},"type":"Feature"},
	{"geometry":{"coordinates":[7.154296,52.309046],"type":"Point"},"properties":{"osm_id":"3623345219","tag":{"amenity":"recycling","recycling:clothes":"yes","recycling:shoes":"yes","recycling_type":"container"}},"type":"Feature"},
	{"geometry":{"coordinates":[7.161669,52.286222],"type":"Point"},"properties":{"osm_id":"5104252396","tag":{"amenity":"waste_basket"}},"type":"Feature"},
	{"geometry":{"coordinates":[7.157579,52.312295],"type":"Point"},"properties":{"name":"Wertstoffhof Schnitker","osm_id":"6087127868","tag":{"amenity":"recycling","recycling_type":"centre"}},"type":"Feature"},
	{"geometry":{"coordinates":[7.15994,52.302356],"type":"Point"},"properties":{"osm_id":"6681738491","tag":{"amenity":"waste_basket","waste":"trash"}},"type":"Feature"},
	{"geometry":{"coordinates":[7.133468,52.291195],"type":"Point"},"properties":{"osm_id":"7563528927","tag":{"amenity":"waste_basket"}},"type":"Feature"}
]
}
