{
"type": "FeatureCollection",
"features": [
	{"geometry":{"coordinates":[7.131875,52.302724],"type":"Point"},"properties":{"osm_id":"954028583","tag":{"amenity":"recycling","recycling_type":"container"}},"type":"Feature"},
	{"geometry":{"coordinates":[7.135382,52.300959],"type":"Point"},"properties":{"osm_id":"1966232036","tag":{"amenity":"recycling","recycling_type":"container"}},"type":"Feature"},
	{"geometry":{"coordinates":[7.13348,52.304311],"type":"Point"},"properties":{"osm_id":"1966232037","tag":{"amenity":"recycling","recycling_type":"container"}},"type":"Feature"},
	{"geometry":{"coordinates":[7.136462,52.302377],"type":"Point"},"properties":{"osm_id":"1966797424","tag":{"amenity":"waste_basket"}},"type":"Feature"},
	{"geometry":{"coordinates":[7.136822,52.302398],"type":"Point"},"properties":{"osm_id":"1966797430","tag":{"amenity":"waste_basket"}},"type":"Feature"},
	{"geometry":{"coordinates":[7.149606,52.291894],"type":"Point"},"properties":{"osm_id":"3202436709","tag":{"amenity":"waste_basket"}},"type":"Feature"},
	{"geometry":{"coordinates":[7.158398,52.301783],"type":"Point"},"properties":{"osm_id":"3526260621","tag":{"amenity":"waste_basket"}},"type":"Feature"},
	{"geometry":{"coordinates":[7.153007,52.308033],"type":"Point"},"properties":{"osm_id":"3623345218","tag":{"amenity":"recycling","recycling:clothes":"yes","recycling:shoes":"yes","recycling_type":"container"}},"type":"Feature"},
	{"geometry":{"coordinates":[7.154295,52.309045],"type":"Point"},"properties":{"osm_id":"3623345219","tag":{"amenity":"recycling","recycling:clothes":"yes","recycling:shoes":"yes","recycling_type":"container"}},"type":"Feature"},
	{"geometry":{"coordinates":[7.161668,52.286221],"type":"Point"},"properties":{"osm_id":"5104252396","tag":{"amenity":"waste_basket"}},"type":"Feature"},
	{"geometry":{"coordinates":[7.157579,52.312294],"type":"Point"},"properties":{"name":"Wertstoffhof Schnitker","osm_id":"6087127868","tag":{"amenity":"recycling","recycling_type":"centre"}},"type":"Feature"},
	{"geometry":{"coordinates":[7.15994,52.302356],"type":"Point"},"properties":{"osm_id":"6681738491","tag":{"amenity":"waste_basket","waste":"trash"}},"type":"Feature"},
	{"geometry":{"coordinates":[7.133467,52.291194],"type":"Point"},"properties":{"osm_id":"7563528927","tag":{"amenity":"waste_basket"}},"type":"Feature"}
]
}
