{
"type": "FeatureCollection",
"features": [
	{"geometry":{"coordinates":[7.159196,51.94859],"type":"Point"},"properties":{"osm_id":"307183373","tag":{"amenity":"recycling","location":"overground","recycling_type":"container"}},"type":"Feature"},
	{"geometry":{"coordinates":[7.169063,51.948645],"type":"Point"},"properties":{"osm_id":"307410282","tag":{"amenity":"recycling"}},"type":"Feature"},
	{"geometry":{"coordinates":[7.160489,51.95296],"type":"Point"},"properties":{"osm_id":"364753711","tag":{"amenity":"recycling","recycling:clothes":"yes","recycling:glass":"yes"}},"type":"Feature"},
	{"geometry":{"coordinates":[7.14723,51.947648],"type":"Point"},"properties":{"osm_id":"403196457","tag":{"amenity":"recycling","recycling:clothes":"yes","recycling:glass":"yes"}},"type":"Feature"},
	{"geometry":{"coordinates":[7.162442,51.960915],"type":"Point"},"properties":{"osm_id":"656028110","tag":{"amenity":"recycling","recycling:batteries":"yes","recycling:clothes":"yes","recycling:glass":"yes"}},"type":"Feature"},
	{"geometry":{"coordinates":[7.166667,51.95167],"type":"Point"},"properties":{"osm_id":"6551134413","tag":{"amenity":"waste_basket"}},"type":"Feature"},
	{"geometry":{"coordinates":[7.166729,51.951702],"type":"Point"},"properties":{"osm_id":"6551134414","tag":{"amenity":"waste_basket"}},"type":"Feature"},
	{"geometry":{"coordinates":[7.165948,51.951292],"type":"Point"},"properties":{"osm_id":"6551134417","tag":{"amenity":"waste_basket"}},"type":"Feature"},
	{"geometry":{"coordinates":[7.127051,51.959617],"type":"Point"},"properties":{"osm_id":"6819437951","tag":{"amenity":"waste_basket"}},"type":"Feature"},
	{"geometry":{"coordinates":[7.126488,51.959254],"type":"Point"},"properties":{"osm_id":"6819437952","tag":{"amenity":"waste_basket"}},"type":"Feature"}
]
}
