{
"type": "FeatureCollection",
"features": [
	{"geometry":{"coordinates":[7.159197,51.94859],"type":"Point"},"properties":{"osm_id":"307183373","tag":{"amenity":"recycling","location":"overground","recycling_type":"container"}},"type":"Feature"},
	{"geometry":{"coordinates":[7.169063,51.948646],"type":"Point"},"properties":{"osm_id":"307410282","tag":{"amenity":"recycling"}},"type":"Feature"},
	{"geometry":{"coordinates":[7.16049,51.952961],"type":"Point"},"properties":{"osm_id":"364753711","tag":{"amenity":"recycling","recycling:clothes":"yes","recycling:glass":"yes"}},"type":"Feature"},
	{"geometry":{"coordinates":[7.14723,51.947648],"type":"Point"},"properties":{"osm_id":"403196457","tag":{"amenity":"recycling","recycling:clothes":"yes","recycling:glass":"yes"}},"type":"Feature"},
	{"geometry":{"coordinates":[7.162443,51.960916],"type":"Point"},"properties":{"osm_id":"656028110","tag":{"amenity":"recycling","recycling:batteries":"yes","recycling:clothes":"yes","recycling:glass":"yes"}},"type":"Feature"},
	{"geometry":{"coordinates":[7.166668,51.951671],"type":"Point"},"properties":{"osm_id":"6551134413","tag":{"amenity":"waste_basket"}},"type":"Feature"},
	{"geometry":{"coordinates":[7.166729,51.951703],"type":"Point"},"properties":{"osm_id":"6551134414","tag":{"amenity":"waste_basket"}},"type":"Feature"},
	{"geometry":{"coordinates":[7.165949,51.951293],"type":"Point"},"properties":{"osm_id":"6551134417","tag":{"amenity":"waste_basket"}},"type":"Feature"},
	{"geometry":{"coordinates":[7.127052,51.959618],"type":"Point"},"properties":{"osm_id":"6819437951","tag":{"amenity":"waste_basket"}},"type":"Feature"},
	{"geometry":{"coordinates":[7.126489,51.959254],"type":"Point"},"properties":{"osm_id":"6819437952","tag":{"amenity":"waste_basket"}},"type":"Feature"},
	{"geometry":{"coordinates":[7.200118,51.944266],"type":"Point"},"properties":{"osm_id":"7948598853","tag":{"amenity":"waste_basket","material":"steel","operator":"Stadt Coesfeld","waste":"mixed"}},"type":"Feature"},
	{"geometry":{"coordinates":[7.189346,51.946006],"type":"Point"},"properties":{"osm_id":"7948625097","tag":{"amenity":"waste_basket","material":"steel","operator":"Stadt Coesfeld","waste":"mixed"}},"type":"Feature"}
]
}
