{
"type": "FeatureCollection",
"features": [
	{"geometry":{"coordinates":[7.159196,51.94859],"type":"Point"},"properties":{"osm_id":"307183373","tag":{"amenity":"recycling","location":"overground","recycling_type":"container"}},"type":"Feature"},
	{"geometry":{"coordinates":[7.168678,51.948619],"type":"Point"},"properties":{"osm_id":"307410282","tag":{"amenity":"recycling","recycling:glass_bottles":"yes","recycling_type":"container"}},"type":"Feature"},
	{"geometry":{"coordinates":[7.160756,51.952883],"type":"Point"},"properties":{"osm_id":"364753711","tag":{"amenity":"recycling","recycling:clothes":"yes","recycling:glass":"yes"}},"type":"Feature"},
	{"geometry":{"coordinates":[7.14723,51.947648],"type":"Point"},"properties":{"osm_id":"403196457","tag":{"amenity":"recycling","recycling:clothes":"yes","recycling:glass":"yes"}},"type":"Feature"},
	{"geometry":{"coordinates":[7.162442,51.960915],"type":"Point"},"properties":{"osm_id":"656028110","tag":{"amenity":"recycling","recycling:batteries":"yes","recycling:clothes":"yes","recycling:glass":"yes"}},"type":"Feature"},
	{"geometry":{"coordinates":[7.166659,51.951672],"type":"Point"},"properties":{"osm_id":"6551134413","tag":{"amenity":"waste_basket"}},"type":"Feature"},
	{"geometry":{"coordinates":[7.166722,51.951706],"type":"Point"},"properties":{"osm_id":"6551134414","tag":{"amenity":"waste_basket"}},"type":"Feature"},
	{"geometry":{"coordinates":[7.165944,51.951298],"type":"Point"},"properties":{"osm_id":"6551134417","tag":{"amenity":"waste_basket"}},"type":"Feature"},
	{"geometry":{"coordinates":[7.127051,51.959617],"type":"Point"},"properties":{"osm_id":"6819437951","tag":{"amenity":"waste_basket"}},"type":"Feature"},
	{"geometry":{"coordinates":[7.126488,51.959254],"type":"Point"},"properties":{"osm_id":"6819437952","tag":{"amenity":"waste_basket"}},"type":"Feature"},
	{"geometry":{"coordinates":[7.200118,51.944265],"type":"Point"},"properties":{"osm_id":"7948598853","tag":{"amenity":"waste_basket","material":"steel","operator":"Stadt Coesfeld","waste":"mixed"}},"type":"Feature"},
	{"geometry":{"coordinates":[7.189345,51.946006],"type":"Point"},"properties":{"osm_id":"7948625097","tag":{"amenity":"waste_basket","material":"steel","operator":"Stadt Coesfeld","waste":"mixed"}},"type":"Feature"},
	{"geometry":{"coordinates":[7.195029,51.951184],"type":"Point"},"properties":{"osm_id":"7964472132","tag":{"amenity":"waste_basket","colour":"grey","material":"metal","operator":"Stadt Coesfeld","waste":"mixed"}},"type":"Feature"},
	{"geometry":{"coordinates":[7.166953,51.951842],"type":"Point"},"properties":{"osm_id":"8761747136","tag":{"amenity":"waste_basket"}},"type":"Feature"},
	{"geometry":{"coordinates":[7.122696,51.998306],"type":"Point"},"properties":{"osm_id":"8796758798","tag":{"amenity":"waste_basket","waste":"trash"}},"type":"Feature"}
]
}
