{
"type": "FeatureCollection",
"lastupdate": "2020-08-01T00:00:00Z",
"features": [
	{"geometry":{"coordinates":[7.156632,48.044396],"type":"Point"},"properties":{"name":"Centre de TRI et de Valorisation","osm_id":"880817043","tag":{"amenity":"recycling","recycling_type":"centre"}},"type":"Feature"},
	{"geometry":{"coordinates":[7.13781,48.040699],"type":"Point"},"properties":{"osm_id":"1671208243","tag":{"amenity":"waste_basket"}},"type":"Feature"},
	{"geometry":{"coordinates":[7.137072,48.040701],"type":"Point"},"properties":{"osm_id":"1671208249","tag":{"amenity":"waste_basket"}},"type":"Feature"},
	{"geometry":{"coordinates":[7.131264,48.041911],"type":"Point"},"properties":{"osm_id":"1751759319","tag":{"amenity":"waste_basket"}},"type":"Feature"},
	{"geometry":{"coordinates":[7.160596,48.003005],"type":"Point"},"properties":{"osm_id":"2304849339","tag":{"amenity":"recycling"}},"type":"Feature"},
	{"geometry":{"coordinates":[7.152305,48.043628],"type":"Point"},"properties":{"osm_id":"3455891306","tag":{"amenity":"recycling","recycling:glass_bottles":"yes","recycling:paper":"yes","recycling_type":"container"}},"type":"Feature"},
	{"geometry":{"coordinates":[7.135817,48.042267],"type":"Point"},"properties":{"osm_id":"6273794073","tag":{"amenity":"recycling","opening_hours":"24/7","recycling:glass_bottles":"yes","recycling_type":"container"}},"type":"Feature"}
]
}
