{
"type": "FeatureCollection",
"features": [
	{"geometry":{"coordinates":[7.188428,43.821522],"type":"Point"},"properties":{"name":"Poubelle","osm_id":"4009031698","tag":{"amenity":"waste_basket"}},"type":"Feature"},
	{"geometry":{"coordinates":[7.188231,43.820963],"type":"Point"},"properties":{"name":"Poubelle","osm_id":"4009071235","tag":{"amenity":"waste_basket"}},"type":"Feature"}
]
}
