{
"type": "FeatureCollection",
"lastupdate": "2020-08-02T00:00:00Z",
"features": [
	{"geometry":{"coordinates":[7.188427,43.821522],"type":"Point"},"properties":{"name":"Poubelle","osm_id":"4009031698","tag":{"amenity":"waste_basket"}},"type":"Feature"},
	{"geometry":{"coordinates":[7.18823,43.820962],"type":"Point"},"properties":{"name":"Poubelle","osm_id":"4009071235","tag":{"amenity":"waste_basket"}},"type":"Feature"}
]
}
