{
"type": "FeatureCollection",
"lastupdate": "2020-08-06T00:00:00Z",
"features": [
	{"geometry":{"coordinates":[12.831641,61.888577],"type":"Point"},"properties":{"osm_id":"775202382","tag":{"amenity":"recycling","location":"overground","recycling:batteries":"yes","recycling:glass":"yes","recycling:scrap_metal":"yes","recycling_type":"container"}},"type":"Feature"}
]
}
