{
"type": "FeatureCollection",
"features": [
	{"geometry":{"coordinates":[12.772441,52.361671],"type":"Point"},"properties":{"osm_id":"417283670","tag":{"amenity":"recycling","location":"overground","recycling:glass":"yes","recycling_type":"container"}},"type":"Feature"},
	{"geometry":{"coordinates":[12.745153,52.361824],"type":"Point"},"properties":{"osm_id":"428135755","tag":{"amenity":"recycling","mapillary":"xRo-c5-Ay_7TBzqN4PRdBw","recycling:glass_bottles":"yes","recycling_type":"container","survey:date":"2018-05-20"}},"type":"Feature"},
	{"geometry":{"coordinates":[12.755597,52.361808],"type":"Point"},"properties":{"osm_id":"428135769","tag":{"amenity":"recycling","recycling:glass_bottles":"yes","recycling_type":"container"}},"type":"Feature"},
	{"geometry":{"coordinates":[12.773846,52.364596],"type":"Point"},"properties":{"barrier":"gate","osm_id":"2125533512"},"type":"Feature"},
	{"geometry":{"coordinates":[12.80593,52.36027],"type":"Point"},"properties":{"osm_id":"7549546920","tag":{"amenity":"recycling","recycling:glass_bottles":"yes","recycling_type":"container"}},"type":"Feature"},
	{"geometry":{"coordinates":[12.80019,52.359923],"type":"Point"},"properties":{"osm_id":"7549546923","tag":{"amenity":"recycling","recycling:glass_bottles":"yes","recycling_type":"container"}},"type":"Feature"},
	{"geometry":{"coordinates":[12.799877,52.359639],"type":"Point"},"properties":{"osm_id":"7552052720","tag":{"amenity":"recycling","recycling:clothes":"yes","recycling_type":"container"}},"type":"Feature"}
]
}
