{
"type": "FeatureCollection",
"features": [
	{"geometry":{"coordinates":[12.757311,52.176451],"type":"Point"},"properties":{"osm_id":"721371995","tag":{"amenity":"recycling","recycling:glass":"yes","recycling_type":"container"}},"type":"Feature"},
	{"geometry":{"coordinates":[12.767264,52.179215],"type":"Point"},"properties":{"osm_id":"1846439621","tag":{"amenity":"recycling","location":"overground","recycling:clothes":"yes","recycling:glass_bottles":"yes","recycling:shoes":"yes","recycling_type":"container"}},"type":"Feature"},
	{"geometry":{"coordinates":[12.758448,52.18663],"type":"Point"},"properties":{"osm_id":"3410710301","tag":{"amenity":"waste_basket"}},"type":"Feature"},
	{"geometry":{"coordinates":[12.759378,52.187253],"type":"Point"},"properties":{"osm_id":"3410710314","tag":{"amenity":"waste_basket"}},"type":"Feature"}
]
}
