{
"type": "FeatureCollection",
"lastupdate": "2020-08-05T00:00:00Z",
"features": [
	{"geometry":{"coordinates":[12.829501,48.317766],"type":"Point"},"properties":{"osm_id":"863266588","tag":{"amenity":"waste_basket"}},"type":"Feature"},
	{"geometry":{"coordinates":[12.831368,48.306979],"type":"Point"},"properties":{"name":"Wertstoffhof","osm_id":"4715251889","tag":{"amenity":"recycling","name:de":"Wertstoffhof","operator":"Gemeinde Zeilarn"}},"type":"Feature"}
]
}
