{
"type": "FeatureCollection",
"lastupdate": "2020-07-31T00:00:00Z",
"features": [
	{"geometry":{"coordinates":[12.819081,48.16756],"type":"Point"},"properties":{"osm_id":"186019938","tag":{"amenity":"recycling"}},"type":"Feature"},
	{"geometry":{"coordinates":[12.785066,48.194522],"type":"Point"},"properties":{"osm_id":"944812907","tag":{"amenity":"recycling","recycling:glass":"yes"}},"type":"Feature"},
	{"geometry":{"coordinates":[12.783239,48.191771],"type":"Point"},"properties":{"osm_id":"1243948518","tag":{"amenity":"recycling","location":"overground","recycling:glass":"yes","recycling_type":"container"}},"type":"Feature"},
	{"geometry":{"coordinates":[12.82632,48.167434],"type":"Point"},"properties":{"osm_id":"6434427096","tag":{"amenity":"recycling"}},"type":"Feature"},
	{"geometry":{"coordinates":[12.826121,48.167214],"type":"Point"},"properties":{"osm_id":"6434427102","tag":{"amenity":"recycling"}},"type":"Feature"},
	{"geometry":{"coordinates":[12.831572,48.172111],"type":"Point"},"properties":{"osm_id":"6657300460","tag":{"amenity":"waste_basket"}},"type":"Feature"},
	{"geometry":{"coordinates":[12.83125,48.172088],"type":"Point"},"properties":{"osm_id":"6657300461","tag":{"amenity":"waste_basket"}},"type":"Feature"},
	{"geometry":{"coordinates":[12.791749,48.191273],"type":"Point"},"properties":{"osm_id":"7306673661","tag":{"amenity":"waste_basket"}},"type":"Feature"},
	{"geometry":{"coordinates":[12.826682,48.167769],"type":"Point"},"properties":{"osm_id":"7575800534","tag":{"amenity":"recycling","recycling:glass":"yes","recycling:glass_1":"yes","recycling:glass_bottles":"yes","recycling:glass_bottom":"yes","recycling:glass_brown":"yes","recycling:glass_clear":"yes","recycling:glass_green":"yes","recycling:glass_jars":"yes","recycling:glass_white":"yes","recycling:glasses":"yes","recycling_type":"container"}},"type":"Feature"}
]
}
