{
"type": "FeatureCollection",
"lastupdate": "2020-08-04T00:00:00Z",
"features": [
	{"geometry":{"coordinates":[12.787719,47.438368],"type":"Point"},"properties":{"name":"Recyclinghof Leogang","osm_id":"1753173023","tag":{"amenity":"recycling","recycling:batteries":"yes","recycling:books":"yes","recycling:cans":"yes","recycling:cartons":"yes","recycling:clothes":"yes","recycling:electrical_appliances":"yes","recycling:glass":"yes","recycling:glass_bottles":"yes","recycling:green_waste":"yes","recycling:newspaper":"yes","recycling:paper":"yes","recycling:paper_packaging":"yes","recycling:plastic":"yes","recycling:plastic_bottles":"yes","recycling:plastic_packaging":"yes","recycling:scrap_metal":"yes","recycling:waste":"yes","recycling:wood":"yes","recycling_type":"centre"}},"type":"Feature"},
	{"geometry":{"coordinates":[12.815599,47.447434],"type":"Point"},"properties":{"osm_id":"6436668855","tag":{"amenity":"waste_basket"}},"type":"Feature"},
	{"geometry":{"coordinates":[12.815121,47.447291],"type":"Point"},"properties":{"osm_id":"6436668861","tag":{"amenity":"waste_basket"}},"type":"Feature"},
	{"geometry":{"coordinates":[12.830283,47.426734],"type":"Point"},"properties":{"osm_id":"6498634512","tag":{"amenity":"waste_basket"}},"type":"Feature"}
]
}
