{
"type": "FeatureCollection",
"lastupdate": "2020-08-06T00:00:00Z",
"features": [
	{"geometry":{"coordinates":[12.787432,46.865185],"type":"Point"},"properties":{"name":"Recyclinghof Zettersfeld","osm_id":"1640369475","tag":{"addr:city":"Thurn","addr:country":"AT","addr:housenumber":"18","addr:place":"Zettersfeld","addr:postcode":"9904","amenity":"recycling","recycling_centre":"yes"}},"type":"Feature"}
]
}
