{
"type": "FeatureCollection",
"features": [
	{"geometry":{"coordinates":[75.103383,42.719338],"type":"Point"},"properties":{"name":"Ahorn","osm_id":"3491216287","tag":{"natural":"tree"}},"type":"Feature"}
]
}
