{
"type": "FeatureCollection",
"features": [
	{"geometry":{"coordinates":[12.480862,50.571394],"type":"Point"},"properties":{"osm_id":"4353772909","tag":{"leaf_cycle":"deciduous","leaf_type":"broadleaved","natural":"tree"}},"type":"Feature"},
	{"geometry":{"coordinates":[12.48117,50.571459],"type":"Point"},"properties":{"osm_id":"4353772910","tag":{"leaf_cycle":"deciduous","leaf_type":"broadleaved","natural":"tree"}},"type":"Feature"},
	{"geometry":{"coordinates":[12.481486,50.571505],"type":"Point"},"properties":{"osm_id":"4353772911","tag":{"leaf_cycle":"deciduous","leaf_type":"broadleaved","natural":"tree"}},"type":"Feature"},
	{"geometry":{"coordinates":[12.555654,50.620048],"type":"Point"},"properties":{"name":"Gerichtseiche","osm_id":"4599948305","tag":{"natural":"tree"}},"type":"Feature"},
	{"geometry":{"coordinates":[12.549435,50.604436],"type":"Point"},"properties":{"osm_id":"6252670188","tag":{"natural":"tree"}},"type":"Feature"},
	{"geometry":{"coordinates":[12.545155,50.624216],"type":"Point"},"properties":{"osm_id":"6252670227","tag":{"natural":"tree"}},"type":"Feature"},
	{"geometry":{"coordinates":[12.543202,50.62309],"type":"Point"},"properties":{"osm_id":"6252670251","tag":{"natural":"tree"}},"type":"Feature"},
	{"geometry":{"coordinates":[12.547472,50.622494],"type":"Point"},"properties":{"osm_id":"6252670269","tag":{"natural":"tree"}},"type":"Feature"},
	{"geometry":{"coordinates":[12.545519,50.622658],"type":"Point"},"properties":{"osm_id":"6252670310","tag":{"natural":"tree"}},"type":"Feature"},
	{"geometry":{"coordinates":[12.547048,50.624764],"type":"Point"},"properties":{"osm_id":"6252670326","tag":{"natural":"tree"}},"type":"Feature"},
	{"geometry":{"coordinates":[12.549693,50.604531],"type":"Point"},"properties":{"osm_id":"6252670342","tag":{"natural":"tree"}},"type":"Feature"},
	{"geometry":{"coordinates":[12.553983,50.617463],"type":"Point"},"properties":{"osm_id":"6252670353","tag":{"natural":"tree"}},"type":"Feature"},
	{"geometry":{"coordinates":[12.542698,50.623342],"type":"Point"},"properties":{"osm_id":"6252670364","tag":{"natural":"tree"}},"type":"Feature"},
	{"geometry":{"coordinates":[12.545653,50.622463],"type":"Point"},"properties":{"osm_id":"6252670408","tag":{"natural":"tree"}},"type":"Feature"},
	{"geometry":{"coordinates":[12.549407,50.614137],"type":"Point"},"properties":{"osm_id":"6252670455","tag":{"natural":"tree"}},"type":"Feature"},
	{"geometry":{"coordinates":[12.549611,50.608484],"type":"Point"},"properties":{"osm_id":"6252670480","tag":{"natural":"tree"}},"type":"Feature"},
	{"geometry":{"coordinates":[12.547574,50.622436],"type":"Point"},"properties":{"osm_id":"6252670527","tag":{"natural":"tree"}},"type":"Feature"},
	{"geometry":{"coordinates":[12.550313,50.620155],"type":"Point"},"properties":{"osm_id":"6252685512","tag":{"natural":"tree"}},"type":"Feature"},
	{"geometry":{"coordinates":[12.549781,50.59571],"type":"Point"},"properties":{"osm_id":"6432484102","tag":{"natural":"tree"}},"type":"Feature"},
	{"geometry":{"coordinates":[12.549596,50.59576],"type":"Point"},"properties":{"osm_id":"6432484103","tag":{"natural":"tree"}},"type":"Feature"}
]
}
