{
"type": "FeatureCollection",
"features": [
	{"geometry":{"coordinates":[12.480861,50.571394],"type":"Point"},"properties":{"osm_id":"4353772909","tag":{"leaf_cycle":"deciduous","leaf_type":"broadleaved","natural":"tree"}},"type":"Feature"},
	{"geometry":{"coordinates":[12.481169,50.571459],"type":"Point"},"properties":{"osm_id":"4353772910","tag":{"leaf_cycle":"deciduous","leaf_type":"broadleaved","natural":"tree"}},"type":"Feature"},
	{"geometry":{"coordinates":[12.481485,50.571504],"type":"Point"},"properties":{"osm_id":"4353772911","tag":{"leaf_cycle":"deciduous","leaf_type":"broadleaved","natural":"tree"}},"type":"Feature"},
	{"geometry":{"coordinates":[12.555653,50.620048],"type":"Point"},"properties":{"name":"Gerichtseiche","osm_id":"4599948305","tag":{"natural":"tree"}},"type":"Feature"},
	{"geometry":{"coordinates":[12.549435,50.604435],"type":"Point"},"properties":{"osm_id":"6252670188","tag":{"natural":"tree"}},"type":"Feature"},
	{"geometry":{"coordinates":[12.545154,50.624215],"type":"Point"},"properties":{"osm_id":"6252670227","tag":{"natural":"tree"}},"type":"Feature"},
	{"geometry":{"coordinates":[12.543201,50.623089],"type":"Point"},"properties":{"osm_id":"6252670251","tag":{"natural":"tree"}},"type":"Feature"},
	{"geometry":{"coordinates":[12.547472,50.622494],"type":"Point"},"properties":{"osm_id":"6252670269","tag":{"natural":"tree"}},"type":"Feature"},
	{"geometry":{"coordinates":[12.545519,50.622657],"type":"Point"},"properties":{"osm_id":"6252670310","tag":{"natural":"tree"}},"type":"Feature"},
	{"geometry":{"coordinates":[12.547048,50.624763],"type":"Point"},"properties":{"osm_id":"6252670326","tag":{"natural":"tree"}},"type":"Feature"},
	{"geometry":{"coordinates":[12.549692,50.604531],"type":"Point"},"properties":{"osm_id":"6252670342","tag":{"natural":"tree"}},"type":"Feature"},
	{"geometry":{"coordinates":[12.553982,50.617463],"type":"Point"},"properties":{"osm_id":"6252670353","tag":{"natural":"tree"}},"type":"Feature"},
	{"geometry":{"coordinates":[12.542697,50.623341],"type":"Point"},"properties":{"osm_id":"6252670364","tag":{"natural":"tree"}},"type":"Feature"},
	{"geometry":{"coordinates":[12.545653,50.622463],"type":"Point"},"properties":{"osm_id":"6252670408","tag":{"natural":"tree"}},"type":"Feature"},
	{"geometry":{"coordinates":[12.549406,50.614137],"type":"Point"},"properties":{"osm_id":"6252670455","tag":{"natural":"tree"}},"type":"Feature"},
	{"geometry":{"coordinates":[12.549611,50.608483],"type":"Point"},"properties":{"osm_id":"6252670480","tag":{"natural":"tree"}},"type":"Feature"},
	{"geometry":{"coordinates":[12.547573,50.622436],"type":"Point"},"properties":{"osm_id":"6252670527","tag":{"natural":"tree"}},"type":"Feature"},
	{"geometry":{"coordinates":[12.550313,50.620155],"type":"Point"},"properties":{"osm_id":"6252685512","tag":{"natural":"tree"}},"type":"Feature"},
	{"geometry":{"coordinates":[12.549781,50.595709],"type":"Point"},"properties":{"osm_id":"6432484102","tag":{"natural":"tree"}},"type":"Feature"},
	{"geometry":{"coordinates":[12.549596,50.595759],"type":"Point"},"properties":{"osm_id":"6432484103","tag":{"natural":"tree"}},"type":"Feature"},
	{"geometry":{"coordinates":[12.53244,50.619216],"type":"Point"},"properties":{"osm_id":"8632927969","tag":{"natural":"tree"}},"type":"Feature"}
]
}
