{
"type": "FeatureCollection",
"features": [
	{"geometry":{"coordinates":[12.492504,42.983864],"type":"Point"},"properties":{"name":"Tiglio di Monte Cinque Querce","osm_id":"5178511630","tag":{"denotation":"natural_monument","genus":"Tilia cordata Mill.","leaf_cycle":"deciduous","leaf_type":"broadleaved","natural":"tree"}},"type":"Feature"}
]
}
