{
"type": "FeatureCollection",
"features": [
	{"geometry":{"coordinates":[17.502452,58.947479],"type":"Point"},"properties":{"osm_id":"4562289420","tag":{"leaf_cycle":"evergreen","leaf_type":"needleleaved","natural":"tree"}},"type":"Feature"},
	{"geometry":{"coordinates":[17.569008,58.948491],"type":"Point"},"properties":{"name":"Eken vid Tullgarn","osm_id":"8938665517","tag":{"denotation":"single","leaf_type":"broadleaved","natural":"tree","survey:date":"2021-07-20"}},"type":"Feature"}
]
}
