{
"type": "FeatureCollection",
"features": [
	{"geometry":{"coordinates":[17.493696,53.345909],"type":"Point"},"properties":{"osm_id":"4706671771","tag":{"denotation":"natural_monument","natural":"tree","ref:CRFOP":"PL.ZIPOP.1393.PP.0413043.2190","ref:INSPIRE":"PL.ZIPOP.1393.PP.0413043.2190","website":"http://crfop.gdos.gov.pl/CRFOP/widok/viewfop.jsf?fop=PL.ZIPOP.1393.PP.0413043.2190"}},"type":"Feature"},
	{"geometry":{"coordinates":[17.493721,53.346387],"type":"Point"},"properties":{"osm_id":"4706671772","tag":{"denotation":"natural_monument","natural":"tree","ref:CRFOP":"PL.ZIPOP.1393.PP.0413043.2189","ref:INSPIRE":"PL.ZIPOP.1393.PP.0413043.2189","website":"http://crfop.gdos.gov.pl/CRFOP/widok/viewfop.jsf?fop=PL.ZIPOP.1393.PP.0413043.2189"}},"type":"Feature"},
	{"geometry":{"coordinates":[17.493044,53.346033],"type":"Point"},"properties":{"osm_id":"4706671773","tag":{"denotation":"natural_monument","natural":"tree","ref:CRFOP":"PL.ZIPOP.1393.PP.0413043.2188","ref:INSPIRE":"PL.ZIPOP.1393.PP.0413043.2188","website":"http://crfop.gdos.gov.pl/CRFOP/widok/viewfop.jsf?fop=PL.ZIPOP.1393.PP.0413043.2188"}},"type":"Feature"},
	{"geometry":{"coordinates":[17.49367,53.346309],"type":"Point"},"properties":{"osm_id":"4706671774","tag":{"denotation":"natural_monument","natural":"tree","ref:CRFOP":"PL.ZIPOP.1393.PP.0413043.2187","ref:INSPIRE":"PL.ZIPOP.1393.PP.0413043.2187","website":"http://crfop.gdos.gov.pl/CRFOP/widok/viewfop.jsf?fop=PL.ZIPOP.1393.PP.0413043.2187"}},"type":"Feature"},
	{"geometry":{"coordinates":[17.49342,53.346181],"type":"Point"},"properties":{"osm_id":"4706671775","tag":{"denotation":"natural_monument","natural":"tree","ref:CRFOP":"PL.ZIPOP.1393.PP.0413043.2186","ref:INSPIRE":"PL.ZIPOP.1393.PP.0413043.2186","website":"http://crfop.gdos.gov.pl/CRFOP/widok/viewfop.jsf?fop=PL.ZIPOP.1393.PP.0413043.2186"}},"type":"Feature"},
	{"geometry":{"coordinates":[17.493241,53.346054],"type":"Point"},"properties":{"osm_id":"4706671777","tag":{"denotation":"natural_monument","natural":"tree","ref:CRFOP":"PL.ZIPOP.1393.PP.0413043.2184","ref:INSPIRE":"PL.ZIPOP.1393.PP.0413043.2184","website":"http://crfop.gdos.gov.pl/CRFOP/widok/viewfop.jsf?fop=PL.ZIPOP.1393.PP.0413043.2184"}},"type":"Feature"},
	{"geometry":{"coordinates":[17.492407,53.346668],"type":"Point"},"properties":{"osm_id":"4706673139","tag":{"denotation":"natural_monument","natural":"tree","ref:CRFOP":"PL.ZIPOP.1393.PP.0413043.2203","ref:INSPIRE":"PL.ZIPOP.1393.PP.0413043.2203","website":"http://crfop.gdos.gov.pl/CRFOP/widok/viewfop.jsf?fop=PL.ZIPOP.1393.PP.0413043.2203"}},"type":"Feature"},
	{"geometry":{"coordinates":[17.492906,53.346602],"type":"Point"},"properties":{"osm_id":"4706673140","tag":{"denotation":"natural_monument","natural":"tree","ref:CRFOP":"PL.ZIPOP.1393.PP.0413043.2203","ref:INSPIRE":"PL.ZIPOP.1393.PP.0413043.2203","website":"http://crfop.gdos.gov.pl/CRFOP/widok/viewfop.jsf?fop=PL.ZIPOP.1393.PP.0413043.2203"}},"type":"Feature"},
	{"geometry":{"coordinates":[17.495178,53.346731],"type":"Point"},"properties":{"osm_id":"4706673141","tag":{"denotation":"natural_monument","natural":"tree","ref:CRFOP":"PL.ZIPOP.1393.PP.0413043.2202","ref:INSPIRE":"PL.ZIPOP.1393.PP.0413043.2202","website":"http://crfop.gdos.gov.pl/CRFOP/widok/viewfop.jsf?fop=PL.ZIPOP.1393.PP.0413043.2202"}},"type":"Feature"}
]
}
