{
"type": "FeatureCollection",
"features": [
	{"geometry":{"coordinates":[17.572624,52.703129],"type":"Point"},"properties":{"name":"Chrobry","osm_id":"4706665413","tag":{"denotation":"natural_monument","natural":"tree","ref:CRFOP":"PL.ZIPOP.1393.PP.0419052.1498","ref:INSPIRE":"PL.ZIPOP.1393.PP.0419052.1498","website":"http://crfop.gdos.gov.pl/CRFOP/widok/viewfop.jsf?fop=PL.ZIPOP.1393.PP.0419052.1498"}},"type":"Feature"},
	{"geometry":{"coordinates":[17.490734,52.699783],"type":"Point"},"properties":{"osm_id":"4706665974","tag":{"denotation":"natural_monument","natural":"tree","ref:CRFOP":"PL.ZIPOP.1393.PP.0419033.828","ref:INSPIRE":"PL.ZIPOP.1393.PP.0419033.828","website":"http://crfop.gdos.gov.pl/CRFOP/widok/viewfop.jsf?fop=PL.ZIPOP.1393.PP.0419033.828"}},"type":"Feature"},
	{"geometry":{"coordinates":[17.490984,52.700088],"type":"Point"},"properties":{"osm_id":"4706665975","tag":{"denotation":"natural_monument","natural":"tree","ref:CRFOP":"PL.ZIPOP.1393.PP.0419033.828","ref:INSPIRE":"PL.ZIPOP.1393.PP.0419033.828","website":"http://crfop.gdos.gov.pl/CRFOP/widok/viewfop.jsf?fop=PL.ZIPOP.1393.PP.0419033.828"}},"type":"Feature"},
	{"geometry":{"coordinates":[17.491108,52.701126],"type":"Point"},"properties":{"osm_id":"4706665976","tag":{"denotation":"natural_monument","natural":"tree","ref:CRFOP":"PL.ZIPOP.1393.PP.0419033.828","ref:INSPIRE":"PL.ZIPOP.1393.PP.0419033.828","website":"http://crfop.gdos.gov.pl/CRFOP/widok/viewfop.jsf?fop=PL.ZIPOP.1393.PP.0419033.828"}},"type":"Feature"},
	{"geometry":{"coordinates":[17.491169,52.700839],"type":"Point"},"properties":{"osm_id":"4706665977","tag":{"denotation":"natural_monument","natural":"tree","ref:CRFOP":"PL.ZIPOP.1393.PP.0419033.828","ref:INSPIRE":"PL.ZIPOP.1393.PP.0419033.828","website":"http://crfop.gdos.gov.pl/CRFOP/widok/viewfop.jsf?fop=PL.ZIPOP.1393.PP.0419033.828"}},"type":"Feature"},
	{"geometry":{"coordinates":[17.490514,52.70042],"type":"Point"},"properties":{"osm_id":"4706665978","tag":{"denotation":"natural_monument","natural":"tree","ref:CRFOP":"PL.ZIPOP.1393.PP.0419033.828","ref:INSPIRE":"PL.ZIPOP.1393.PP.0419033.828","website":"http://crfop.gdos.gov.pl/CRFOP/widok/viewfop.jsf?fop=PL.ZIPOP.1393.PP.0419033.828"}},"type":"Feature"},
	{"geometry":{"coordinates":[17.521584,52.71805],"type":"Point"},"properties":{"osm_id":"6767545408","tag":{"natural":"tree"}},"type":"Feature"}
]
}
