{
"type": "FeatureCollection",
"features": [
	{"geometry":{"coordinates":[22.589593,-14.681158],"type":"Point"},"properties":{"name":"Palmtree","osm_id":"3851393828","tag":{"denotation":"landmark","leaf_cycle":"evergreen","natural":"tree"}},"type":"Feature"}
]
}
