{
"type": "FeatureCollection",
"features": [
	{"geometry":{"coordinates":[112.405729,37.956466],"type":"Point"},"properties":{"name":"\u00e9\u00a9\u00ac\u00e5\u00a4\u00b4\u00e6\u00b0\u00b4\u00e8\u0080\u0081\u00e6\u009d\u00be","osm_id":"4504794676","tag":{"name:botanical":"Pinus","name:zh":"\u00e9\u00a9\u00ac\u00e5\u00a4\u00b4\u00e6\u00b0\u00b4\u00e8\u0080\u0081\u00e6\u009d\u00be","natural":"tree"}},"type":"Feature"}
]
}
