{
"type": "FeatureCollection",
"lastupdate": "2020-08-03T00:00:00Z",
"features": [
	{"geometry":{"coordinates":[8.339187,51.989981],"type":"Point"},"properties":{"osm_id":"305908575","tag":{"amenity":"recycling"}},"type":"Feature"},
	{"geometry":{"coordinates":[8.278143,51.950101],"type":"Point"},"properties":{"osm_id":"497167926","tag":{"amenity":"recycling","location":"overground","recycling:glass_bottles":"yes","recycling_type":"container"}},"type":"Feature"},
	{"geometry":{"coordinates":[8.34688,51.951157],"type":"Point"},"properties":{"osm_id":"619517323","tag":{"amenity":"recycling","recycling:glass_bottles":"yes","recycling:paper":"yes","recycling_type":"container"}},"type":"Feature"},
	{"geometry":{"coordinates":[8.280635,51.946828],"type":"Point"},"properties":{"osm_id":"2120912018","tag":{"amenity":"waste_basket"}},"type":"Feature"},
	{"geometry":{"coordinates":[8.282513,51.94598],"type":"Point"},"properties":{"osm_id":"2120912020","tag":{"amenity":"waste_basket"}},"type":"Feature"},
	{"geometry":{"coordinates":[8.280583,51.94732],"type":"Point"},"properties":{"osm_id":"2120912021","tag":{"amenity":"waste_basket"}},"type":"Feature"},
	{"geometry":{"coordinates":[8.281478,51.946278],"type":"Point"},"properties":{"osm_id":"2120912023","tag":{"amenity":"waste_basket"}},"type":"Feature"},
	{"geometry":{"coordinates":[8.280659,51.946203],"type":"Point"},"properties":{"osm_id":"2120912027","tag":{"amenity":"waste_basket"}},"type":"Feature"},
	{"geometry":{"coordinates":[8.287442,51.949196],"type":"Point"},"properties":{"osm_id":"3826567141","tag":{"amenity":"recycling","recycling:electrical_appliances":"yes","recycling:glass":"yes","recycling_type":"container"}},"type":"Feature"},
	{"geometry":{"coordinates":[8.287308,51.949292],"type":"Point"},"properties":{"osm_id":"3826567143","tag":{"amenity":"recycling","recycling:clothes":"yes","recycling_type":"container"}},"type":"Feature"},
	{"geometry":{"coordinates":[8.278158,51.950087],"type":"Point"},"properties":{"osm_id":"5667460884","tag":{"amenity":"recycling","recycling:clothes":"yes","recycling:shoes":"yes","recycling_type":"container"}},"type":"Feature"},
	{"geometry":{"coordinates":[8.277138,51.951907],"type":"Point"},"properties":{"osm_id":"5667460885","tag":{"amenity":"recycling","recycling:clothes":"yes","recycling:shoes":"yes","recycling_type":"container"}},"type":"Feature"}
]
}
