{
"type": "FeatureCollection",
"features": [
	{"geometry":{"coordinates":[8.31351,50.252439],"type":"Point"},"properties":{"osm_id":"255874867","tag":{"amenity":"recycling","recycling_type":"container"}},"type":"Feature"},
	{"geometry":{"coordinates":[8.3145,50.253016],"type":"Point"},"properties":{"osm_id":"266745700","tag":{"amenity":"recycling","recycling:batteries":"no","recycling:books":"no","recycling:cans":"no","recycling:cardboard":"no","recycling:cartons":"no","recycling:clothes":"no","recycling:electrical_items":"no","recycling:glass":"no","recycling:glass_bottles":"no","recycling:green_waste":"yes","recycling:magazines":"no","recycling:newspaper":"no","recycling:paper":"no","recycling:paper_packaging":"no","recycling:plastic":"no","recycling:plastic_bottles":"no","recycling:plastic_packaging":"no","recycling:scrap_metal":"no","recycling:small_appliances":"no","recycling:waste":"no","recycling:wood":"no","recycling_type":"container"}},"type":"Feature"},
	{"geometry":{"coordinates":[8.274966,50.285141],"type":"Point"},"properties":{"osm_id":"287100115","tag":{"amenity":"recycling","recycling:glass":"yes","recycling_type":"container"}},"type":"Feature"},
	{"geometry":{"coordinates":[8.280814,50.283777],"type":"Point"},"properties":{"osm_id":"287466278","tag":{"amenity":"recycling","recycling:clothes":"yes","recycling:glass":"yes","recycling_type":"container"}},"type":"Feature"},
	{"geometry":{"coordinates":[8.314415,50.248191],"type":"Point"},"properties":{"osm_id":"330162821","tag":{"amenity":"recycling","recycling_type":"container"}},"type":"Feature"},
	{"geometry":{"coordinates":[8.280919,50.269806],"type":"Point"},"properties":{"osm_id":"3587682850","tag":{"amenity":"recycling","recycling:clothes":"yes","recycling:glass_bottles":"yes","recycling_type":"container"}},"type":"Feature"},
	{"geometry":{"coordinates":[8.274002,50.240021],"type":"Point"},"properties":{"osm_id":"4583029980","tag":{"amenity":"waste_basket"}},"type":"Feature"},
	{"geometry":{"coordinates":[8.31075,50.248396],"type":"Point"},"properties":{"osm_id":"4729334568","tag":{"amenity":"waste_basket"}},"type":"Feature"},
	{"geometry":{"coordinates":[8.31044,50.248762],"type":"Point"},"properties":{"name":"CityGreenPoint","osm_id":"4729334569","tag":{"amenity":"recycling","recycling:batteries":"yes","recycling:clothes":"yes","recycling:electrical_appliances":"yes","recycling:shoes":"yes","recycling_type":"container"}},"type":"Feature"},
	{"geometry":{"coordinates":[8.311985,50.250638],"type":"Point"},"properties":{"osm_id":"4729334570","tag":{"amenity":"waste_basket"}},"type":"Feature"},
	{"geometry":{"coordinates":[8.349106,50.274436],"type":"Point"},"properties":{"osm_id":"5646364212","tag":{"amenity":"recycling","recycling:clothes":"yes","recycling:glass":"yes","recycling_type":"container"}},"type":"Feature"},
	{"geometry":{"coordinates":[8.290076,50.235978],"type":"Point"},"properties":{"osm_id":"7214417423","tag":{"amenity":"waste_basket"}},"type":"Feature"},
	{"geometry":{"coordinates":[8.316367,50.23619],"type":"Point"},"properties":{"osm_id":"7676692097","tag":{"amenity":"recycling","recycling:clothes":"yes","recycling:shoes":"yes","recycling_type":"container"}},"type":"Feature"}
]
}
