{
"type": "FeatureCollection",
"features": [
	{"geometry":{"coordinates":[-5.817846,43.440251],"type":"Point"},"properties":{"osm_id":"1424241956","tag":{"amenity":"waste_basket"}},"type":"Feature"},
	{"geometry":{"coordinates":[-5.817936,43.440615],"type":"Point"},"properties":{"osm_id":"1424241960","tag":{"amenity":"waste_basket"}},"type":"Feature"},
	{"geometry":{"coordinates":[-5.818199,43.44087],"type":"Point"},"properties":{"osm_id":"1424241961","tag":{"amenity":"waste_basket"}},"type":"Feature"},
	{"geometry":{"coordinates":[-5.818348,43.441135],"type":"Point"},"properties":{"osm_id":"1424241962","tag":{"amenity":"waste_basket"}},"type":"Feature"},
	{"geometry":{"coordinates":[-5.817276,43.440523],"type":"Point"},"properties":{"osm_id":"1424250469","tag":{"amenity":"waste_basket"}},"type":"Feature"},
	{"geometry":{"coordinates":[-5.81703,43.440716],"type":"Point"},"properties":{"osm_id":"1424250471","tag":{"amenity":"waste_basket"}},"type":"Feature"},
	{"geometry":{"coordinates":[-5.817945,43.441154],"type":"Point"},"properties":{"osm_id":"3578883718","tag":{"amenity":"waste_basket"}},"type":"Feature"},
	{"geometry":{"coordinates":[-5.844342,43.437006],"type":"Point"},"properties":{"osm_id":"3579405349","tag":{"amenity":"waste_basket"}},"type":"Feature"},
	{"geometry":{"coordinates":[-5.842385,43.437564],"type":"Point"},"properties":{"osm_id":"3579405352","tag":{"amenity":"waste_basket"}},"type":"Feature"},
	{"geometry":{"coordinates":[-5.809253,43.399567],"type":"Point"},"properties":{"osm_id":"4741588364","tag":{"amenity":"recycling","recycling_type":"container"}},"type":"Feature"},
	{"geometry":{"coordinates":[-5.805696,43.40467],"type":"Point"},"properties":{"name":"Contenedores de reciclaje (3)","osm_id":"5927230234","tag":{"amenity":"recycling"}},"type":"Feature"}
]
}
