{
"type": "FeatureCollection",
"features": [
	{"geometry":{"coordinates":[-5.817846,43.44025],"type":"Point"},"properties":{"osm_id":"1424241956","tag":{"amenity":"waste_basket"}},"type":"Feature"},
	{"geometry":{"coordinates":[-5.817936,43.440615],"type":"Point"},"properties":{"osm_id":"1424241960","tag":{"amenity":"waste_basket"}},"type":"Feature"},
	{"geometry":{"coordinates":[-5.818199,43.440869],"type":"Point"},"properties":{"osm_id":"1424241961","tag":{"amenity":"waste_basket"}},"type":"Feature"},
	{"geometry":{"coordinates":[-5.818347,43.441135],"type":"Point"},"properties":{"osm_id":"1424241962","tag":{"amenity":"waste_basket"}},"type":"Feature"},
	{"geometry":{"coordinates":[-5.817275,43.440522],"type":"Point"},"properties":{"osm_id":"1424250469","tag":{"amenity":"waste_basket"}},"type":"Feature"},
	{"geometry":{"coordinates":[-5.81703,43.440716],"type":"Point"},"properties":{"osm_id":"1424250471","tag":{"amenity":"waste_basket"}},"type":"Feature"},
	{"geometry":{"coordinates":[-5.817945,43.441153],"type":"Point"},"properties":{"osm_id":"3578883718","tag":{"amenity":"waste_basket"}},"type":"Feature"},
	{"geometry":{"coordinates":[-5.844342,43.437006],"type":"Point"},"properties":{"osm_id":"3579405349","tag":{"amenity":"waste_basket"}},"type":"Feature"},
	{"geometry":{"coordinates":[-5.842384,43.437563],"type":"Point"},"properties":{"osm_id":"3579405352","tag":{"amenity":"waste_basket"}},"type":"Feature"},
	{"geometry":{"coordinates":[-5.809253,43.399567],"type":"Point"},"properties":{"osm_id":"4741588364","tag":{"amenity":"recycling","recycling_type":"container"}},"type":"Feature"},
	{"geometry":{"coordinates":[-5.805695,43.404669],"type":"Point"},"properties":{"name":"Contenedores de reciclaje (3)","osm_id":"5927230234","tag":{"amenity":"recycling"}},"type":"Feature"}
]
}
