{
"type": "FeatureCollection",
"features": [
	{"geometry":{"coordinates":[14.976149,48.292952],"type":"Point"},"properties":{"osm_id":"904047070","tag":{"amenity":"waste_basket"}},"type":"Feature"},
	{"geometry":{"coordinates":[14.959325,48.284406],"type":"Point"},"properties":{"name":"Wohnmobil  Ver-Entsorgung","osm_id":"958315362","tag":{"amenity":"waste_disposal"}},"type":"Feature"},
	{"geometry":{"coordinates":[14.957837,48.284555],"type":"Point"},"properties":{"osm_id":"958581582","tag":{"amenity":"waste_basket"}},"type":"Feature"},
	{"geometry":{"coordinates":[14.9577,48.283548],"type":"Point"},"properties":{"osm_id":"958581717","tag":{"amenity":"waste_basket"}},"type":"Feature"},
	{"geometry":{"coordinates":[14.958262,48.28428],"type":"Point"},"properties":{"osm_id":"958581744","tag":{"amenity":"waste_basket"}},"type":"Feature"},
	{"geometry":{"coordinates":[14.956741,48.283756],"type":"Point"},"properties":{"osm_id":"958581803","tag":{"amenity":"waste_basket"}},"type":"Feature"},
	{"geometry":{"coordinates":[14.957282,48.283312],"type":"Point"},"properties":{"osm_id":"958581949","tag":{"amenity":"waste_basket"}},"type":"Feature"},
	{"geometry":{"coordinates":[14.958079,48.283779],"type":"Point"},"properties":{"osm_id":"958582062","tag":{"amenity":"waste_basket"}},"type":"Feature"},
	{"geometry":{"coordinates":[14.981436,48.326379],"type":"Point"},"properties":{"osm_id":"3505407294","tag":{"amenity":"recycling","description":"ASI Dorfstetten 1: Friedhof","recycling_type":"container"}},"type":"Feature"}
]
}
