{
"type": "FeatureCollection",
"features": [
	{"geometry":{"coordinates":[-2.041753,57.367943],"type":"Point"},"properties":{"osm_id":"355507596","tag":{"amenity":"recycling","recycling_type":"container"}},"type":"Feature"},
	{"geometry":{"coordinates":[-2.06481,57.369294],"type":"Point"},"properties":{"osm_id":"356190029","tag":{"amenity":"recycling"}},"type":"Feature"},
	{"geometry":{"coordinates":[-2.076397,57.362608],"type":"Point"},"properties":{"osm_id":"356193414","tag":{"amenity":"recycling"}},"type":"Feature"},
	{"geometry":{"coordinates":[-2.073073,57.364238],"type":"Point"},"properties":{"osm_id":"610903732","tag":{"amenity":"recycling"}},"type":"Feature"},
	{"geometry":{"coordinates":[-2.053693,57.369874],"type":"Point"},"properties":{"name":"Ellon Household Waste & Recycling Centre","osm_id":"1453597969","tag":{"amenity":"recycling","recycling_type":"centre"}},"type":"Feature"},
	{"geometry":{"coordinates":[-2.07501,57.364988],"type":"Point"},"properties":{"osm_id":"7880773290","tag":{"amenity":"waste_basket","waste":"trash"}},"type":"Feature"},
	{"geometry":{"coordinates":[-2.072246,57.365423],"type":"Point"},"properties":{"osm_id":"7881816253","tag":{"amenity":"waste_basket","waste":"trash"}},"type":"Feature"},
	{"geometry":{"coordinates":[-2.071935,57.366362],"type":"Point"},"properties":{"osm_id":"7882243604","tag":{"amenity":"waste_basket","waste":"trash"}},"type":"Feature"},
	{"geometry":{"coordinates":[-2.072389,57.366097],"type":"Point"},"properties":{"osm_id":"7882243618","tag":{"amenity":"waste_basket","waste":"trash"}},"type":"Feature"},
	{"geometry":{"coordinates":[-2.071589,57.366109],"type":"Point"},"properties":{"osm_id":"7888113233","tag":{"amenity":"waste_basket","waste":"trash"}},"type":"Feature"}
]
}
