{
"type": "FeatureCollection",
"features": [
	{"geometry":{"coordinates":[21.205959,50.271669],"type":"Point"},"properties":{"name":"Pomnik przyrody","osm_id":"4037296703","tag":{"denotation":"natural_monument","monument":"yes","natural":"tree","protected":"yes"}},"type":"Feature"},
	{"geometry":{"coordinates":[21.191533,50.288648],"type":"Point"},"properties":{"name":"Pomnik przyrody","osm_id":"4037296704","tag":{"denotation":"natural_monument","monument":"yes","natural":"tree","protected":"yes"}},"type":"Feature"}
]
}
