{
"type": "FeatureCollection",
"features": [
	{"geometry":{"coordinates":[21.233423,45.772335],"type":"Point"},"properties":{"name":"Pomul gros","osm_id":"7580391589","tag":{"circumference":"4.47","denotation":"landmark","genus":"Platanus","height":"21","leaf_cycle":"deciduous","leaf_type":"broadleaved","natural":"tree","start_date":"1681"}},"type":"Feature"}
]
}
