{
"type": "FeatureCollection",
"features": [
	{"geometry":{"coordinates":[13.81436,47.861666],"type":"Point"},"properties":{"name":"Eibe","osm_id":"3748676446","tag":{"leaf_cycle":"evergreen","leaf_type":"needleleaved","natural":"tree"}},"type":"Feature"},
	{"geometry":{"coordinates":[13.81547,47.866394],"type":"Point"},"properties":{"name":"Eibe","osm_id":"3748681635","tag":{"leaf_cycle":"evergreen","leaf_type":"needleleaved","natural":"tree"}},"type":"Feature"},
	{"geometry":{"coordinates":[13.814995,47.866303],"type":"Point"},"properties":{"name":"Eibe","osm_id":"3748681636","tag":{"leaf_cycle":"evergreen","leaf_type":"needleleaved","natural":"tree"}},"type":"Feature"},
	{"geometry":{"coordinates":[13.815714,47.867424],"type":"Point"},"properties":{"name":"Eibe","osm_id":"3748683929","tag":{"leaf_cycle":"evergreen","leaf_type":"needleleaved","natural":"tree"}},"type":"Feature"},
	{"geometry":{"coordinates":[13.816145,47.87061],"type":"Point"},"properties":{"name":"Eibe","osm_id":"3748687131","tag":{"leaf_cycle":"evergreen","leaf_type":"needleleaved","natural":"tree"}},"type":"Feature"}
]
}
