{
"type": "FeatureCollection",
"features": [
	{"geometry":{"coordinates":[13.81436,47.861667],"type":"Point"},"properties":{"name":"Eibe","osm_id":"3748676446","tag":{"leaf_cycle":"evergreen","leaf_type":"needleleaved","natural":"tree"}},"type":"Feature"},
	{"geometry":{"coordinates":[13.81547,47.866394],"type":"Point"},"properties":{"name":"Eibe","osm_id":"3748681635","tag":{"leaf_cycle":"evergreen","leaf_type":"needleleaved","natural":"tree"}},"type":"Feature"},
	{"geometry":{"coordinates":[13.814995,47.866304],"type":"Point"},"properties":{"name":"Eibe","osm_id":"3748681636","tag":{"leaf_cycle":"evergreen","leaf_type":"needleleaved","natural":"tree"}},"type":"Feature"},
	{"geometry":{"coordinates":[13.815715,47.867425],"type":"Point"},"properties":{"name":"Eibe","osm_id":"3748683929","tag":{"leaf_cycle":"evergreen","leaf_type":"needleleaved","natural":"tree"}},"type":"Feature"},
	{"geometry":{"coordinates":[13.816146,47.87061],"type":"Point"},"properties":{"name":"Eibe","osm_id":"3748687131","tag":{"leaf_cycle":"evergreen","leaf_type":"needleleaved","natural":"tree"}},"type":"Feature"}
]
}
