{
"type": "FeatureCollection",
"lastupdate": "2020-08-05T00:00:00Z",
"features": [
	{"geometry":{"coordinates":[6.228451,53.270142],"type":"Point"},"properties":{"osm_id":"3987727230","tag":{"amenity":"waste_basket"}},"type":"Feature"},
	{"geometry":{"coordinates":[6.230401,53.274537],"type":"Point"},"properties":{"osm_id":"4052463120","tag":{"amenity":"recycling","recycling:cans":"no","recycling:clothes":"yes","recycling:glass":"no","recycling:glass_bottles":"yes","recycling:paper":"no","recycling:plastic":"no","recycling_type":"container"}},"type":"Feature"},
	{"geometry":{"coordinates":[6.156147,53.277462],"type":"Point"},"properties":{"osm_id":"4231855904","tag":{"amenity":"recycling","location":"underground","recycling:glass_bottles":"yes","recycling_type":"container"}},"type":"Feature"},
	{"geometry":{"coordinates":[6.154753,53.27436],"type":"Point"},"properties":{"osm_id":"4231855905","tag":{"amenity":"recycling","location":"underground","recycling:glass_bottles":"yes","recycling_type":"container"}},"type":"Feature"},
	{"geometry":{"coordinates":[6.173845,53.228651],"type":"Point"},"properties":{"osm_id":"4762682422","tag":{"amenity":"waste_basket","waste":"trash"}},"type":"Feature"},
	{"geometry":{"coordinates":[6.157603,53.270725],"type":"Point"},"properties":{"osm_id":"5037855599","tag":{"amenity":"waste_basket","description":"blikvanger","waste":"trash"}},"type":"Feature"},
	{"geometry":{"coordinates":[6.158189,53.277475],"type":"Point"},"properties":{"osm_id":"5080318335","tag":{"amenity":"waste_basket","waste":"trash"}},"type":"Feature"},
	{"geometry":{"coordinates":[6.154343,53.278115],"type":"Point"},"properties":{"osm_id":"5082465067","tag":{"amenity":"waste_basket","waste":"trash"}},"type":"Feature"},
	{"geometry":{"coordinates":[6.23213,53.274524],"type":"Point"},"properties":{"osm_id":"6346246942","tag":{"amenity":"waste_basket","material":"metal","waste":"trash"}},"type":"Feature"},
	{"geometry":{"coordinates":[6.226476,53.273181],"type":"Point"},"properties":{"osm_id":"6346246965","tag":{"amenity":"waste_basket","material":"metal","waste":"trash"}},"type":"Feature"},
	{"geometry":{"coordinates":[6.179159,53.272042],"type":"Point"},"properties":{"osm_id":"6486623206","tag":{"amenity":"waste_basket","waste":"trash"}},"type":"Feature"},
	{"geometry":{"coordinates":[6.229314,53.250021],"type":"Point"},"properties":{"osm_id":"7350696762","tag":{"amenity":"waste_basket","waste":"trash"}},"type":"Feature"}
]
}
