{
"type": "FeatureCollection",
"lastupdate": "2020-08-02T00:00:00Z",
"features": [
	{"geometry":{"coordinates":[16.284536,47.107152],"type":"Point"},"properties":{"name":"Altstoffsammelstelle","osm_id":"3989458620","tag":{"amenity":"recycling","operator":"Gemeinde Tobaj","recycling_type":"centre"}},"type":"Feature"},
	{"geometry":{"coordinates":[16.284339,47.106865],"type":"Point"},"properties":{"osm_id":"3989458621","tag":{"amenity":"recycling","recycling:cans":"yes","recycling:clothes":"yes","recycling:glass":"no","recycling:glass_bottles":"yes","recycling:paper":"no","recycling:plastic":"no","recycling_type":"container"}},"type":"Feature"}
]
}
