{
"type": "FeatureCollection",
"features": [
	{"geometry":{"coordinates":[136.886536,-4.520353],"type":"Point"},"properties":{"name":"Room-07","osm_id":"7796514960"},"type":"Feature"},
	{"geometry":{"coordinates":[136.886465,-4.520379],"type":"Point"},"properties":{"name":"Room-08","osm_id":"7796514961"},"type":"Feature"}
]
}
