{
"type": "FeatureCollection",
"features": [
	{"geometry":{"coordinates":[3.926062,51.537408],"type":"Point"},"properties":{"osm_id":"3641612299","tag":{"amenity":"waste_basket"}},"type":"Feature"},
	{"geometry":{"coordinates":[3.87752,51.512716],"type":"Point"},"properties":{"osm_id":"4848349653","tag":{"amenity":"waste_basket"}},"type":"Feature"},
	{"geometry":{"coordinates":[3.877994,51.515369],"type":"Point"},"properties":{"osm_id":"4848351463","tag":{"amenity":"waste_basket"}},"type":"Feature"},
	{"geometry":{"coordinates":[3.874994,51.517064],"type":"Point"},"properties":{"osm_id":"4849561099","tag":{"amenity":"waste_basket"}},"type":"Feature"},
	{"geometry":{"coordinates":[3.879236,51.513426],"type":"Point"},"properties":{"osm_id":"5518799276","tag":{"amenity":"waste_basket"}},"type":"Feature"},
	{"geometry":{"coordinates":[3.879188,51.513561],"type":"Point"},"properties":{"osm_id":"5518799278","tag":{"amenity":"waste_basket"}},"type":"Feature"},
	{"geometry":{"coordinates":[3.89037,51.510879],"type":"Point"},"properties":{"osm_id":"7006257210","tag":{"amenity":"recycling","operator":"Gemeente Goes","recycling:waste":"yes","recycling_type":"container"}},"type":"Feature"},
	{"geometry":{"coordinates":[3.890421,51.510877],"type":"Point"},"properties":{"osm_id":"7006257211","tag":{"amenity":"recycling","operator":"Gemeente Goes","recycling:waste":"yes","recycling_type":"container"}},"type":"Feature"},
	{"geometry":{"coordinates":[3.890471,51.510877],"type":"Point"},"properties":{"osm_id":"7006257212","tag":{"amenity":"recycling","operator":"Gemeente Goes","recycling:waste":"yes","recycling_type":"container"}},"type":"Feature"},
	{"geometry":{"coordinates":[3.890384,51.510984],"type":"Point"},"properties":{"osm_id":"7101478334","tag":{"amenity":"recycling","operator":"Gemeente Goes","recycling:waste":"yes","recycling_type":"container"}},"type":"Feature"},
	{"geometry":{"coordinates":[3.890435,51.510982],"type":"Point"},"properties":{"osm_id":"7101478335","tag":{"amenity":"recycling","operator":"Gemeente Goes","recycling:waste":"yes","recycling_type":"container"}},"type":"Feature"},
	{"geometry":{"coordinates":[3.890484,51.510982],"type":"Point"},"properties":{"osm_id":"7101478336","tag":{"amenity":"recycling","operator":"Gemeente Goes","recycling:waste":"yes","recycling_type":"container"}},"type":"Feature"},
	{"geometry":{"coordinates":[3.889969,51.512893],"type":"Point"},"properties":{"name":"Milieustraat","osm_id":"7815307448","tag":{"amenity":"recycling","opening_hours":"Mo-Fr 10:00-12:30,13:00-17:00, Sa 09:00-15:00; PH off","operator":"Zeeuwse ReinigingsDienst B.V.","recycling:batteries":"yes","recycling:clothes":"yes","recycling:electrical_appliances":"yes","recycling:fluorescent_tubes":"yes","recycling:garden_waste":"yes","recycling:glass":"yes","recycling:glass_bottles":"yes","recycling:green_waste":"yes","recycling:hazardous_waste":"yes","recycling:low_energy_bulbs":"yes","recycling:organic":"yes","recycling:paint":"yes","recycling:paper":"yes","recycling:plastic":"yes","recycling:rubble":"yes","recycling:scrap_metal":"yes","recycling:small_appliances":"yes","recycling:tyres":"no","recycling:waste":"yes","recycling:white_goods":"yes","recycling:wood":"yes","recycling_type":"centre","website":"https://www.zrd.nl/milieustraten/locaties/locatie:goes.htm","wheelchair":"yes"}},"type":"Feature"}
]
}
