{
"type": "FeatureCollection",
"lastupdate": "2020-08-02T00:00:00Z",
"features": [
	{"geometry":{"coordinates":[10.849759,51.018429],"type":"Point"},"properties":{"osm_id":"837389538","tag":{"amenity":"recycling","location":"overground","recycling:clothes":"yes","recycling:glass_bottles":"yes","recycling:paper":"yes","recycling_type":"container"}},"type":"Feature"},
	{"geometry":{"coordinates":[10.846416,51.017054],"type":"Point"},"properties":{"osm_id":"837389597","tag":{"amenity":"recycling"}},"type":"Feature"}
]
}
