{
"type": "FeatureCollection",
"features": [
	{"geometry":{"coordinates":[10.834923,50.713602],"type":"Point"},"properties":{"osm_id":"277956035","tag":{"amenity":"recycling","recycling:cartons":"yes","recycling:glass":"yes","recycling_type":"container"}},"type":"Feature"},
	{"geometry":{"coordinates":[10.864997,50.681562],"type":"Point"},"properties":{"osm_id":"281575368","tag":{"amenity":"recycling","location":"overground","recycling:clothes":"yes","recycling:glass":"yes","recycling:glass_bottles":"yes","recycling:paper":"yes","recycling:plastic_packaging":"yes","recycling:shoes":"yes","recycling_type":"container"}},"type":"Feature"},
	{"geometry":{"coordinates":[10.856986,50.715983],"type":"Point"},"properties":{"osm_id":"390042375","tag":{"amenity":"recycling","recycling:cans":"yes","recycling:cartons":"yes","recycling:glass":"yes","recycling_type":"container"}},"type":"Feature"},
	{"geometry":{"coordinates":[10.856489,50.68114],"type":"Point"},"properties":{"osm_id":"747559364","tag":{"amenity":"waste_basket"}},"type":"Feature"},
	{"geometry":{"coordinates":[10.866089,50.683169],"type":"Point"},"properties":{"osm_id":"747559489","tag":{"amenity":"waste_basket"}},"type":"Feature"},
	{"geometry":{"coordinates":[10.891476,50.698342],"type":"Point"},"properties":{"osm_id":"1514837364","tag":{"amenity":"recycling","recycling:glass":"yes","recycling_type":"container"}},"type":"Feature"},
	{"geometry":{"coordinates":[10.883936,50.680814],"type":"Point"},"properties":{"osm_id":"2377435299","tag":{"amenity":"waste_basket"}},"type":"Feature"},
	{"geometry":{"coordinates":[10.835291,50.715663],"type":"Point"},"properties":{"osm_id":"2962394637","tag":{"amenity":"waste_basket"}},"type":"Feature"},
	{"geometry":{"coordinates":[10.820108,50.716657],"type":"Point"},"properties":{"osm_id":"4542779445","tag":{"amenity":"waste_disposal"}},"type":"Feature"},
	{"geometry":{"coordinates":[10.829038,50.733031],"type":"Point"},"properties":{"osm_id":"5773644213","tag":{"amenity":"recycling","recycling:glass":"yes"}},"type":"Feature"},
	{"geometry":{"coordinates":[10.853389,50.700244],"type":"Point"},"properties":{"osm_id":"8598853441","tag":{"amenity":"waste_basket"}},"type":"Feature"},
	{"geometry":{"coordinates":[10.846821,50.686332],"type":"Point"},"properties":{"osm_id":"9143765787","tag":{"amenity":"waste_basket"}},"type":"Feature"}
]
}
