{
"type": "FeatureCollection",
"features": [
	{"geometry":{"coordinates":[10.894161,48.621354],"type":"Point"},"properties":{"osm_id":"552387764","tag":{"amenity":"waste_basket"}},"type":"Feature"},
	{"geometry":{"coordinates":[10.893991,48.621762],"type":"Point"},"properties":{"osm_id":"552387812","tag":{"amenity":"waste_basket"}},"type":"Feature"},
	{"geometry":{"coordinates":[10.893277,48.622177],"type":"Point"},"properties":{"osm_id":"552387826","tag":{"amenity":"waste_basket"}},"type":"Feature"},
	{"geometry":{"coordinates":[10.896828,48.622563],"type":"Point"},"properties":{"osm_id":"552429180","tag":{"amenity":"waste_basket"}},"type":"Feature"},
	{"geometry":{"coordinates":[10.867844,48.599005],"type":"Point"},"properties":{"osm_id":"756644088","tag":{"amenity":"waste_basket"}},"type":"Feature"},
	{"geometry":{"coordinates":[10.868204,48.59877],"type":"Point"},"properties":{"osm_id":"756644131","tag":{"amenity":"recycling","recycling:cans":"yes","recycling:glass":"yes"}},"type":"Feature"},
	{"geometry":{"coordinates":[10.863312,48.604286],"type":"Point"},"properties":{"name":"Wertstoffhof Ellgau","osm_id":"756644195","tag":{"amenity":"recycling","recycling:batteries":"yes","recycling:cans":"yes","recycling:glass":"yes","recycling:paper":"yes","recycling:scrap_metal":"yes","recycling_type":"centre"}},"type":"Feature"},
	{"geometry":{"coordinates":[10.828164,48.601842],"type":"Point"},"properties":{"name":"Recyclinghof","osm_id":"842165524","tag":{"amenity":"recycling","opening_hours":"Sa 09:30-12:30","recycling:batteries":"yes","recycling:cans":"yes","recycling:clothes":"yes","recycling:glass":"yes","recycling:paper":"yes","recycling:scrap_metal":"yes","recycling_type":"centre"}},"type":"Feature"},
	{"geometry":{"coordinates":[10.817278,48.632034],"type":"Point"},"properties":{"osm_id":"879281675","tag":{"amenity":"recycling","recycling:glass":"yes"}},"type":"Feature"},
	{"geometry":{"coordinates":[10.841739,48.57943],"type":"Point"},"properties":{"osm_id":"3695974483","tag":{"amenity":"recycling","description:de":"Recycling, Glas, Blech, Altkleider","recycling:cans":"yes","recycling:clothes":"yes","recycling:glass":"yes","recycling:shoes":"yes","recycling_type":"container"}},"type":"Feature"}
]
}
