{
"type": "FeatureCollection",
"lastupdate": "2020-08-06T00:00:00Z",
"features": [
	{"geometry":{"coordinates":[-99.142856,29.351368],"type":"Point"},"properties":{"name":"Hondo Paper Recycle","osm_id":"1494236745","tag":{"amenity":"recycling","opening_hours":"24/7","recycling:beverage_cartons":"yes","recycling:cardboard":"yes","recycling:newspaper":"yes","recycling:paper":"yes","recycling:paper_packaging":"yes","recycling_type":"centre"}},"type":"Feature"}
]
}
