{
"type": "FeatureCollection",
"lastupdate": "2020-08-04T00:00:00Z",
"features": [
	{"geometry":{"coordinates":[-99.182739,18.878109],"type":"Point"},"properties":{"osm_id":"1663342137","tag":{"addr:city":"Jiutepec","addr:country":"MX","addr:state":"Morelos","addr:street":"Paseo del Pozo","amenity":"recycling","recycling:cans":"yes","recycling:glass":"yes","recycling:paper":"yes","recycling_type":"centre"}},"type":"Feature"},
	{"geometry":{"coordinates":[-99.200539,18.849106],"type":"Point"},"properties":{"osm_id":"7423864335","tag":{"amenity":"recycling","recycling_type":"centre"}},"type":"Feature"}
]
}
