{
"type": "FeatureCollection",
"lastupdate": "2020-07-31T00:00:00Z",
"features": [
	{"geometry":{"coordinates":[116.106296,5.991202],"type":"Point"},"properties":{"name":"Recycle Bins","osm_id":"2457050991","tag":{"amenity":"recycling"}},"type":"Feature"},
	{"geometry":{"coordinates":[116.106233,5.990591],"type":"Point"},"properties":{"name":"Recycle Bins","osm_id":"2462497208","tag":{"amenity":"recycling"}},"type":"Feature"}
]
}
