{
"type": "FeatureCollection",
"features": [
	{"geometry":{"coordinates":[-124.518714,49.834645],"type":"Point"},"properties":{"osm_id":"9081204488","tag":{"amenity":"waste_basket","waste":"dog_excrement"}},"type":"Feature"},
	{"geometry":{"coordinates":[-124.5276,49.831551],"type":"Point"},"properties":{"osm_id":"9083211197","tag":{"amenity":"waste_basket","waste":"dog_excrement;trash"}},"type":"Feature"},
	{"geometry":{"coordinates":[-124.525443,49.819811],"type":"Point"},"properties":{"osm_id":"9083211199","tag":{"amenity":"waste_basket","waste":"dog_excrement;trash"}},"type":"Feature"},
	{"geometry":{"coordinates":[-124.526785,49.828083],"type":"Point"},"properties":{"osm_id":"9083211200","tag":{"amenity":"waste_basket","waste":"dog_excrement;trash"}},"type":"Feature"},
	{"geometry":{"coordinates":[-124.525468,49.822109],"type":"Point"},"properties":{"osm_id":"9083282723","tag":{"amenity":"waste_basket","waste":"dog_excrement;trash"}},"type":"Feature"},
	{"geometry":{"coordinates":[-124.515372,49.836661],"type":"Point"},"properties":{"name":"Sunset Coast Bottle Depot","osm_id":"9089846183","tag":{"addr:housenumber":"7127","addr:street":"Duncan Street","amenity":"recycling","phone":"+1-604-489-0011","recycling:cans":"yes","recycling:electrical_appliances":"yes","recycling:electronics":"yes","recycling:glass_bottles":"yes","recycling:plastic_bottles":"yes","recycling_type":"centre","website":"https://www.return-it.ca/locations/sunset-coast-bottle-depot/"}},"type":"Feature"}
]
}
