{
"type": "FeatureCollection",
"features": [
	{"geometry":{"coordinates":[-17.906725,28.607583],"type":"Point"},"properties":{"osm_id":"1086069016","tag":{"amenity":"recycling","recycling:glass_bottles":"yes","recycling:paper":"yes","recycling_type":"container"}},"type":"Feature"},
	{"geometry":{"coordinates":[-17.908038,28.582036],"type":"Point"},"properties":{"osm_id":"1195770212","tag":{"amenity":"recycling"}},"type":"Feature"},
	{"geometry":{"coordinates":[-17.888177,28.595261],"type":"Point"},"properties":{"osm_id":"1200877739","tag":{"amenity":"recycling","location":"overground","recycling_type":"container"}},"type":"Feature"},
	{"geometry":{"coordinates":[-17.922575,28.606493],"type":"Point"},"properties":{"osm_id":"1201021548","tag":{"amenity":"waste_basket"}},"type":"Feature"},
	{"geometry":{"coordinates":[-17.908909,28.586209],"type":"Point"},"properties":{"osm_id":"2495507055","tag":{"amenity":"recycling","location":"overground","recycling:glass":"yes","recycling:paper":"yes","recycling:plastic":"yes","recycling_type":"container"}},"type":"Feature"},
	{"geometry":{"coordinates":[-17.909133,28.586597],"type":"Point"},"properties":{"osm_id":"2495507076","tag":{"amenity":"recycling","location":"overground","recycling:paper":"yes","recycling:plastic":"yes","recycling_type":"container"}},"type":"Feature"},
	{"geometry":{"coordinates":[-17.910062,28.587286],"type":"Point"},"properties":{"osm_id":"2495507080","tag":{"amenity":"recycling","location":"overground","recycling:glass":"yes","recycling:paper":"yes","recycling:plastic":"yes","recycling_type":"container"}},"type":"Feature"},
	{"geometry":{"coordinates":[-17.909842,28.587711],"type":"Point"},"properties":{"osm_id":"2495507083","tag":{"amenity":"recycling","location":"overground","recycling:glass":"yes","recycling:paper":"yes","recycling:plastic":"yes","recycling_type":"container"}},"type":"Feature"},
	{"geometry":{"coordinates":[-17.888493,28.552411],"type":"Point"},"properties":{"osm_id":"2558476752","tag":{"amenity":"recycling","recycling:glass_bottles":"yes","recycling_type":"container"}},"type":"Feature"},
	{"geometry":{"coordinates":[-17.889088,28.553306],"type":"Point"},"properties":{"osm_id":"2558476753","tag":{"amenity":"recycling","recycling:glass_bottles":"yes","recycling_type":"container"}},"type":"Feature"},
	{"geometry":{"coordinates":[-17.906783,28.611685],"type":"Point"},"properties":{"osm_id":"2560369961","tag":{"amenity":"recycling","recycling:glass_bottles":"yes","recycling_type":"container"}},"type":"Feature"},
	{"geometry":{"coordinates":[-17.879099,28.596109],"type":"Point"},"properties":{"osm_id":"4569411294","tag":{"amenity":"recycling","recycling:cans":"yes","recycling:cardboard":"yes","recycling:glass":"yes","recycling:glass_bottles":"yes","recycling:paper":"yes","recycling:plastic":"yes","recycling:plastic_bottles":"yes","recycling:plastic_packaging":"yes","recycling:waste":"yes","recycling_type":"container"}},"type":"Feature"},
	{"geometry":{"coordinates":[-17.90232,28.573062],"type":"Point"},"properties":{"osm_id":"4695990864","tag":{"amenity":"recycling","recycling_type":"container"}},"type":"Feature"},
	{"geometry":{"coordinates":[-17.909347,28.598034],"type":"Point"},"properties":{"osm_id":"4876661467","tag":{"amenity":"recycling","recycling:glass_bottles":"yes"}},"type":"Feature"},
	{"geometry":{"coordinates":[-17.900029,28.612323],"type":"Point"},"properties":{"osm_id":"5314138576","tag":{"amenity":"recycling","recycling_type":"container"}},"type":"Feature"},
	{"geometry":{"coordinates":[-17.917406,28.592189],"type":"Point"},"properties":{"osm_id":"5320884083","tag":{"amenity":"recycling","location":"overground","recycling_type":"container"}},"type":"Feature"}
]
}
