{
"type": "FeatureCollection",
"features": [
	{"geometry":{"coordinates":[175.790188,-38.058944],"type":"Point"},"properties":{"name":"Putaruru Transfer Station","osm_id":"5267648745","tag":{"amenity":"recycling"}},"type":"Feature"}
]
}
