{
"type": "FeatureCollection",
"lastupdate": "2020-08-06T00:00:00Z",
"features": [
	{"geometry":{"coordinates":[175.790188,-38.058943],"type":"Point"},"properties":{"name":"Putaruru Transfer Station","osm_id":"5267648745","tag":{"amenity":"recycling"}},"type":"Feature"}
]
}
