{
"type": "FeatureCollection",
"features": [
	{"geometry":{"coordinates":[120.550243,16.424652],"type":"Point"},"properties":{"name":"Irisan Dumpsite Workers Cooperative","osm_id":"4688332570","tag":{"amenity":"waste_disposal"}},"type":"Feature"},
	{"geometry":{"coordinates":[120.576092,16.449004],"type":"Point"},"properties":{"osm_id":"4930907831","tag":{"amenity":"waste_disposal","collection_times":"Mo-Su 06:00-08:00"}},"type":"Feature"},
	{"geometry":{"coordinates":[120.576258,16.447898],"type":"Point"},"properties":{"osm_id":"4930907832","tag":{"amenity":"waste_disposal","collection_times":"Mo-Su 06:00-08:00"}},"type":"Feature"},
	{"geometry":{"coordinates":[120.548694,16.412354],"type":"Point"},"properties":{"name":"Materials Recovery Facility","osm_id":"5928408463","tag":{"amenity":"recycling","recycling_type":"centre"}},"type":"Feature"},
	{"geometry":{"coordinates":[120.568988,16.455001],"type":"Point"},"properties":{"osm_id":"6550527885","tag":{"amenity":"waste_disposal"}},"type":"Feature"},
	{"geometry":{"coordinates":[120.569118,16.453927],"type":"Point"},"properties":{"osm_id":"6550533285","tag":{"amenity":"waste_disposal"}},"type":"Feature"},
	{"geometry":{"coordinates":[120.557971,16.417998],"type":"Point"},"properties":{"osm_id":"9201273251","tag":{"amenity":"waste_basket"}},"type":"Feature"}
]
}
