{
"type": "FeatureCollection",
"lastupdate": "2020-08-03T00:00:00Z",
"features": [
	{"geometry":{"coordinates":[120.548694,16.412354],"type":"Point"},"properties":{"name":"Materials Recovery Facility","osm_id":"5928408463","tag":{"amenity":"recycling","recycling_type":"centre"}},"type":"Feature"}
]
}
