{
"type": "FeatureCollection",
"features": [
	{"geometry":{"coordinates":[-1.104308,38.841804],"type":"Point"},"properties":{"name":"Pino Jabonero","osm_id":"7417269108","tag":{"denotation":"single","natural":"tree"}},"type":"Feature"},
	{"geometry":{"coordinates":[-1.09309,38.866716],"type":"Point"},"properties":{"name":"Olmos","osm_id":"7417269109","tag":{"denotation":"park","natural":"tree"}},"type":"Feature"}
]
}
