{
"type": "FeatureCollection",
"features": [
	{"geometry":{"coordinates":[-80.196994,41.021884],"type":"Point"},"properties":{"name":"Scott Twp Recycling drop off","osm_id":"482805593","tag":{"amenity":"recycling"}},"type":"Feature"}
]
}
