{
"type": "FeatureCollection",
"lastupdate": "2020-08-02T00:00:00Z",
"features": [
	{"geometry":{"coordinates":[-80.196993,41.021884],"type":"Point"},"properties":{"name":"Scott Twp Recycling drop off","osm_id":"482805593","tag":{"amenity":"recycling"}},"type":"Feature"}
]
}
