{
"type": "FeatureCollection",
"features": [
	{"geometry":{"coordinates":[0.602676,51.645224],"type":"Point"},"properties":{"name":"South Woodham Ferrers Recycling Centre","osm_id":"1026358561","tag":{"addr:city":"South Woodham Ferrers","addr:housename":"South Woodham Ferrers Civic Amenity Site","addr:postcode":"CM3 5XH","addr:street":"Ferrers Road","amenity":"recycling","operator":"Veolia Environmental Services ( U K ) Plc","operator:type":"private","owner":"Essex County Council","ownership":"municipal","recycling:batteries":"yes","recycling:books":"yes","recycling:cans":"yes","recycling:cardboard":"yes","recycling:clothes":"yes","recycling:electrical_items":"yes","recycling:engine_oil":"yes","recycling:garden_waste":"yes","recycling:glass":"yes","recycling:glass_bottles":"yes","recycling:hardcore":"yes","recycling:paper":"yes","recycling:scrap_metal":"yes","recycling:sheet_metal":"yes","recycling:small_appliances":"yes","recycling:white_goods":"yes","recycling:wood":"yes","recycling_type":"centre","website":"https://www.loveessex.org/find-your-nearest-recycling-centre/south-woodham-ferrers-recycling-centre/","wikidata":"Q106093790"}},"type":"Feature"},
	{"geometry":{"coordinates":[0.614433,51.629069],"type":"Point"},"properties":{"osm_id":"1194241362","tag":{"amenity":"recycling","recycling:cans":"yes","recycling:clothes":"yes","recycling:glass":"yes","recycling:paper":"yes"}},"type":"Feature"}
]
}
