{
"type": "FeatureCollection",
"features": [
	{"geometry":{"coordinates":[-2.440686,48.651589],"type":"Point"},"properties":{"osm_id":"2268056630","tag":{"amenity":"recycling","recycling:clothes":"no","recycling:glass_bottles":"yes","recycling:paper":"yes","recycling_type":"container"}},"type":"Feature"},
	{"geometry":{"coordinates":[-2.404338,48.639464],"type":"Point"},"properties":{"osm_id":"5868997190","tag":{"amenity":"waste_basket"}},"type":"Feature"},
	{"geometry":{"coordinates":[-2.389702,48.638636],"type":"Point"},"properties":{"osm_id":"6651916143","tag":{"amenity":"recycling","location":"overground","recycling:glass":"yes","recycling_type":"container"}},"type":"Feature"},
	{"geometry":{"coordinates":[-2.437402,48.63636],"type":"Point"},"properties":{"osm_id":"9162041394","tag":{"amenity":"waste_disposal"}},"type":"Feature"},
	{"geometry":{"coordinates":[-2.43746,48.63635],"type":"Point"},"properties":{"osm_id":"9162041395","tag":{"amenity":"recycling","recycling_type":"container"}},"type":"Feature"}
]
}
