{
"type": "FeatureCollection",
"features": [
	{"geometry":{"coordinates":[-2.422893,47.880247],"type":"Point"},"properties":{"osm_id":"2264860939","tag":{"amenity":"waste_basket"}},"type":"Feature"},
	{"geometry":{"coordinates":[-2.385875,47.919702],"type":"Point"},"properties":{"osm_id":"3834562890","tag":{"amenity":"waste_basket"}},"type":"Feature"},
	{"geometry":{"coordinates":[-2.385879,47.919518],"type":"Point"},"properties":{"osm_id":"3834562891","tag":{"amenity":"waste_basket"}},"type":"Feature"},
	{"geometry":{"coordinates":[-2.388143,47.921335],"type":"Point"},"properties":{"name":"Emballages et papier","osm_id":"5915589988","tag":{"amenity":"waste_disposal"}},"type":"Feature"},
	{"geometry":{"coordinates":[-2.423697,47.881286],"type":"Point"},"properties":{"osm_id":"6786089302","tag":{"amenity":"waste_basket"}},"type":"Feature"},
	{"geometry":{"coordinates":[-2.423236,47.880725],"type":"Point"},"properties":{"osm_id":"6786089304","tag":{"amenity":"waste_basket"}},"type":"Feature"},
	{"geometry":{"coordinates":[-2.385923,47.928865],"type":"Point"},"properties":{"osm_id":"8954248865","tag":{"amenity":"waste_disposal"}},"type":"Feature"},
	{"geometry":{"coordinates":[-2.38629,47.929905],"type":"Point"},"properties":{"osm_id":"8955454867","tag":{"amenity":"waste_disposal"}},"type":"Feature"}
]
}
