{
"type": "FeatureCollection",
"features": [
	{"geometry":{"coordinates":[-2.422894,47.880247],"type":"Point"},"properties":{"osm_id":"2264860939","tag":{"amenity":"waste_basket"}},"type":"Feature"},
	{"geometry":{"coordinates":[-2.385876,47.919703],"type":"Point"},"properties":{"osm_id":"3834562890","tag":{"amenity":"waste_basket"}},"type":"Feature"},
	{"geometry":{"coordinates":[-2.38588,47.919519],"type":"Point"},"properties":{"osm_id":"3834562891","tag":{"amenity":"waste_basket"}},"type":"Feature"},
	{"geometry":{"coordinates":[-2.388143,47.921335],"type":"Point"},"properties":{"name":"Emballages et papier","osm_id":"5915589988","tag":{"amenity":"waste_disposal"}},"type":"Feature"},
	{"geometry":{"coordinates":[-2.423698,47.881287],"type":"Point"},"properties":{"osm_id":"6786089302","tag":{"amenity":"waste_basket"}},"type":"Feature"},
	{"geometry":{"coordinates":[-2.423236,47.880725],"type":"Point"},"properties":{"osm_id":"6786089304","tag":{"amenity":"waste_basket"}},"type":"Feature"}
]
}
