{
"type": "FeatureCollection",
"features": [
	{"geometry":{"coordinates":[-2.422893,47.880247],"type":"Point"},"properties":{"osm_id":"2264860939","tag":{"amenity":"waste_basket"}},"type":"Feature"},
	{"geometry":{"coordinates":[-2.385875,47.919702],"type":"Point"},"properties":{"osm_id":"3834562890","tag":{"amenity":"waste_basket"}},"type":"Feature"},
	{"geometry":{"coordinates":[-2.385879,47.919518],"type":"Point"},"properties":{"osm_id":"3834562891","tag":{"amenity":"waste_basket"}},"type":"Feature"},
	{"geometry":{"coordinates":[-2.388143,47.921335],"type":"Point"},"properties":{"name":"Emballages et papier","osm_id":"5915589988","tag":{"amenity":"waste_disposal"}},"type":"Feature"},
	{"geometry":{"coordinates":[-2.423697,47.881286],"type":"Point"},"properties":{"osm_id":"6786089302","tag":{"amenity":"waste_basket"}},"type":"Feature"},
	{"geometry":{"coordinates":[-2.423236,47.880725],"type":"Point"},"properties":{"osm_id":"6786089304","tag":{"amenity":"waste_basket"}},"type":"Feature"},
	{"geometry":{"coordinates":[-2.385923,47.928865],"type":"Point"},"properties":{"osm_id":"8954248865","tag":{"amenity":"waste_disposal"}},"type":"Feature"},
	{"geometry":{"coordinates":[-2.38629,47.929905],"type":"Point"},"properties":{"osm_id":"8955454867","tag":{"amenity":"waste_disposal"}},"type":"Feature"},
	{"geometry":{"coordinates":[-2.387285,47.924325],"type":"Point"},"properties":{"osm_id":"8959594992","tag":{"amenity":"waste_disposal"}},"type":"Feature"},
	{"geometry":{"coordinates":[-2.38734,47.922776],"type":"Point"},"properties":{"osm_id":"8959603838","tag":{"amenity":"waste_disposal"}},"type":"Feature"},
	{"geometry":{"coordinates":[-2.388605,47.922694],"type":"Point"},"properties":{"osm_id":"8959656381","tag":{"amenity":"waste_disposal"}},"type":"Feature"},
	{"geometry":{"coordinates":[-2.387986,47.923525],"type":"Point"},"properties":{"osm_id":"8959656393","tag":{"amenity":"waste_disposal"}},"type":"Feature"},
	{"geometry":{"coordinates":[-2.455802,47.901786],"type":"Point"},"properties":{"osm_id":"9029065056","tag":{"amenity":"waste_disposal","image":"https://westnordost.de/p/56180.jpg","waste":"household"}},"type":"Feature"},
	{"geometry":{"coordinates":[-2.455815,47.901784],"type":"Point"},"properties":{"osm_id":"9029065057","tag":{"amenity":"waste_disposal","image":"https://westnordost.de/p/56180.jpg","waste":"household"}},"type":"Feature"},
	{"geometry":{"coordinates":[-2.455829,47.901782],"type":"Point"},"properties":{"osm_id":"9029065058","tag":{"amenity":"waste_disposal","image":"https://westnordost.de/p/56180.jpg","waste":"recycling"}},"type":"Feature"},
	{"geometry":{"coordinates":[-2.44803,47.906904],"type":"Point"},"properties":{"osm_id":"9029142852","tag":{"amenity":"waste_disposal"}},"type":"Feature"},
	{"geometry":{"coordinates":[-2.44804,47.906924],"type":"Point"},"properties":{"osm_id":"9029142853","tag":{"amenity":"waste_disposal"}},"type":"Feature"},
	{"geometry":{"coordinates":[-2.448073,47.906925],"type":"Point"},"properties":{"osm_id":"9029142854","tag":{"amenity":"waste_disposal"}},"type":"Feature"},
	{"geometry":{"coordinates":[-2.448091,47.906917],"type":"Point"},"properties":{"osm_id":"9029142855","tag":{"amenity":"waste_disposal"}},"type":"Feature"},
	{"geometry":{"coordinates":[-2.448097,47.906905],"type":"Point"},"properties":{"osm_id":"9029142856","tag":{"amenity":"waste_disposal"}},"type":"Feature"},
	{"geometry":{"coordinates":[-2.448097,47.906891],"type":"Point"},"properties":{"osm_id":"9029142857","tag":{"amenity":"waste_disposal"}},"type":"Feature"},
	{"geometry":{"coordinates":[-2.448085,47.906882],"type":"Point"},"properties":{"osm_id":"9029142858","tag":{"amenity":"waste_disposal"}},"type":"Feature"},
	{"geometry":{"coordinates":[-2.448072,47.906875],"type":"Point"},"properties":{"osm_id":"9029142859","tag":{"amenity":"waste_disposal"}},"type":"Feature"}
]
}
