{
"type": "FeatureCollection",
"lastupdate": "2020-08-06T00:00:00Z",
"features": [
	{"geometry":{"coordinates":[-2.39265,40.075478],"type":"Point"},"properties":{"name":"Punto verde","osm_id":"3797560141","tag":{"amenity":"recycling","recycling_type":"container"}},"type":"Feature"}
]
}
