{
"type": "FeatureCollection",
"features": [
	{"geometry":{"coordinates":[-2.399535,40.023382],"type":"Point"},"properties":{"name":"Punto limpio","osm_id":"3814580478","tag":{"amenity":"recycling","recycling_type":"container"}},"type":"Feature"}
]
}
