{
"type": "FeatureCollection",
"features": [
	{"geometry":{"coordinates":[13.368927,47.48704],"type":"Point"},"properties":{"name":"St. Martiner Tannenstrauch","osm_id":"3067183378","tag":{"denotation":"landmark","natural":"tree","wikidata":"Q16857092"}},"type":"Feature"}
]
}
