{
"type": "FeatureCollection",
"features": [
	{"geometry":{"coordinates":[13.402289,42.209246],"type":"Point"},"properties":{"name":"Faggio","osm_id":"4683229395","tag":{"leaf_cycle":"deciduous","leaf_type":"broadleaved","natural":"tree"}},"type":"Feature"},
	{"geometry":{"coordinates":[13.402289,42.209329],"type":"Point"},"properties":{"name":"Faggio","osm_id":"4683229396","tag":{"leaf_cycle":"deciduous","leaf_type":"broadleaved","natural":"tree"}},"type":"Feature"},
	{"geometry":{"coordinates":[13.401278,42.209409],"type":"Point"},"properties":{"name":"Faggio","osm_id":"4683229397","tag":{"leaf_cycle":"deciduous","leaf_type":"broadleaved","natural":"tree"}},"type":"Feature"}
]
}
