{
"type": "FeatureCollection",
"features": [
	{"geometry":{"coordinates":[13.402289,42.209245],"type":"Point"},"properties":{"name":"Faggio","osm_id":"4683229395","tag":{"leaf_cycle":"deciduous","leaf_type":"broadleaved","natural":"tree"}},"type":"Feature"},
	{"geometry":{"coordinates":[13.402289,42.209328],"type":"Point"},"properties":{"name":"Faggio","osm_id":"4683229396","tag":{"leaf_cycle":"deciduous","leaf_type":"broadleaved","natural":"tree"}},"type":"Feature"},
	{"geometry":{"coordinates":[13.401277,42.209408],"type":"Point"},"properties":{"name":"Faggio","osm_id":"4683229397","tag":{"leaf_cycle":"deciduous","leaf_type":"broadleaved","natural":"tree"}},"type":"Feature"}
]
}
