{
"type": "FeatureCollection",
"features": [
	{"geometry":{"coordinates":[2.277532,49.166282],"type":"Point"},"properties":{"osm_id":"6579843387","tag":{"amenity":"recycling","opening_hours":"Mo 14:00-18:00; Th-Sa 09:00-12:00,14:00-18:00","phone":"0 800 60 20 02","recycling_type":"centre","website":"https://www.smdoise.fr/dechetteries/dechetterie-de-mesnil-en-thelle/"}},"type":"Feature"},
	{"geometry":{"coordinates":[2.283084,49.176898],"type":"Point"},"properties":{"osm_id":"7532907941","tag":{"amenity":"recycling","recycling:glass_bottles":"yes","recycling_type":"container"}},"type":"Feature"}
]
}
