{
"type": "FeatureCollection",
"lastupdate": "2020-07-31T00:00:00Z",
"features": [
	{"geometry":{"coordinates":[2.229466,41.934461],"type":"Point"},"properties":{"osm_id":"1886046476","tag":{"amenity":"recycling"}},"type":"Feature"},
	{"geometry":{"coordinates":[2.281256,41.931097],"type":"Point"},"properties":{"name":"deixalleria de Calldetenes","osm_id":"1886499325","tag":{"amenity":"recycling","area":"yes","recycling:glass_bottles":"yes","recycling:paper":"yes","recycling:scrap_metal":"yes","recycling_type":"centre"}},"type":"Feature"},
	{"geometry":{"coordinates":[2.235925,41.952446],"type":"Point"},"properties":{"osm_id":"1907668682","tag":{"amenity":"recycling"}},"type":"Feature"},
	{"geometry":{"coordinates":[2.249768,41.960113],"type":"Point"},"properties":{"osm_id":"1926995419","tag":{"amenity":"recycling","recycling:glass_bottles":"yes","recycling:paper":"yes","recycling_type":"container"}},"type":"Feature"},
	{"geometry":{"coordinates":[2.24059,41.93041],"type":"Point"},"properties":{"osm_id":"2706679953","tag":{"amenity":"recycling","recycling:cans":"yes","recycling:clothes":"no","recycling:glass_bottles":"yes","recycling:paper":"yes","recycling_type":"container"}},"type":"Feature"},
	{"geometry":{"coordinates":[2.241057,41.930452],"type":"Point"},"properties":{"osm_id":"2706679954","tag":{"amenity":"recycling","recycling:cans":"yes","recycling:clothes":"no","recycling:glass_bottles":"yes","recycling:paper":"yes","recycling_type":"container"}},"type":"Feature"},
	{"geometry":{"coordinates":[2.240376,41.93179],"type":"Point"},"properties":{"osm_id":"2706679955","tag":{"amenity":"recycling","recycling:cans":"yes","recycling:clothes":"no","recycling:glass_bottles":"yes","recycling:paper":"yes","recycling_type":"container"}},"type":"Feature"},
	{"geometry":{"coordinates":[2.240995,41.931951],"type":"Point"},"properties":{"osm_id":"2708948936","tag":{"amenity":"recycling","recycling:cans":"no","recycling:clothes":"no","recycling:glass_bottles":"yes","recycling:paper":"yes","recycling_type":"container"}},"type":"Feature"},
	{"geometry":{"coordinates":[2.243389,41.943185],"type":"Point"},"properties":{"osm_id":"3126589665","tag":{"amenity":"recycling","recycling_type":"container"}},"type":"Feature"},
	{"geometry":{"coordinates":[2.239888,41.934379],"type":"Point"},"properties":{"osm_id":"4569029083","tag":{"amenity":"recycling","recycling:cans":"yes","recycling:glass_bottles":"yes","recycling:green_waste":"yes","recycling:paper":"yes","recycling:plastic":"yes","recycling:plastic_bottles":"yes","recycling:plastic_packaging":"yes","recycling_type":"container"}},"type":"Feature"},
	{"geometry":{"coordinates":[2.255272,41.928657],"type":"Point"},"properties":{"osm_id":"6192645488","tag":{"amenity":"recycling"}},"type":"Feature"}
]
}
