{
"type": "FeatureCollection",
"lastupdate": "2020-07-31T00:00:00Z",
"features": [
	{"geometry":{"coordinates":[-16.840979,28.230979],"type":"Point"},"properties":{"osm_id":"3710749208","tag":{"amenity":"recycling","recycling_type":"container"}},"type":"Feature"},
	{"geometry":{"coordinates":[-16.814538,28.296852],"type":"Point"},"properties":{"osm_id":"3711827134","tag":{"amenity":"recycling","location":"overground","recycling:cans":"yes","recycling:paper":"yes","recycling_type":"container"}},"type":"Feature"},
	{"geometry":{"coordinates":[-16.815487,28.297109],"type":"Point"},"properties":{"osm_id":"3711827147","tag":{"amenity":"recycling","recycling:cans":"yes","recycling:cardboard":"yes","recycling:clothes":"yes","recycling:paper":"yes","recycling:shoes":"yes","recycling_type":"container"}},"type":"Feature"},
	{"geometry":{"coordinates":[-16.83985,28.2386],"type":"Point"},"properties":{"osm_id":"3978439197","tag":{"amenity":"recycling","recycling:cans":"yes","recycling:cardboard":"yes","recycling:glass":"no","recycling:glass_bottles":"yes","recycling:paper":"yes","recycling:plastic_bottles":"yes","recycling:plastic_packaging":"yes","recycling_type":"container"}},"type":"Feature"},
	{"geometry":{"coordinates":[-16.793203,28.242429],"type":"Point"},"properties":{"osm_id":"5233144705","tag":{"amenity":"recycling","recycling:glass":"yes","recycling_type":"container"}},"type":"Feature"},
	{"geometry":{"coordinates":[-16.793319,28.242736],"type":"Point"},"properties":{"osm_id":"5233144706","tag":{"amenity":"waste_basket"}},"type":"Feature"},
	{"geometry":{"coordinates":[-16.814503,28.296935],"type":"Point"},"properties":{"osm_id":"5411782002","tag":{"amenity":"recycling","recycling:cans":"yes","recycling:cardboard":"yes","recycling:clothes":"yes","recycling:paper":"yes","recycling:shoes":"yes","recycling:waste":"yes","recycling_type":"container"}},"type":"Feature"},
	{"geometry":{"coordinates":[-16.834571,28.238693],"type":"Point"},"properties":{"osm_id":"5415450747","tag":{"amenity":"recycling","recycling_type":"container"}},"type":"Feature"},
	{"geometry":{"coordinates":[-16.838092,28.244764],"type":"Point"},"properties":{"osm_id":"5469265958","tag":{"amenity":"recycling","recycling:glass_bottles":"yes","recycling_type":"container"}},"type":"Feature"},
	{"geometry":{"coordinates":[-16.83732,28.24148],"type":"Point"},"properties":{"osm_id":"5469265959","tag":{"amenity":"recycling","recycling:cans":"yes","recycling:cardboard":"yes","recycling:glass":"no","recycling:glass_bottles":"yes","recycling:paper":"yes","recycling:plastic":"yes","recycling:plastic_bottles":"yes","recycling:plastic_packaging":"yes","recycling:waste":"yes","recycling_type":"container"}},"type":"Feature"},
	{"geometry":{"coordinates":[-16.838572,28.239601],"type":"Point"},"properties":{"osm_id":"5469265960","tag":{"amenity":"recycling","recycling:cardboard":"yes","recycling:plastic":"yes","recycling:plastic_bottles":"no","recycling:plastic_packaging":"no","recycling_type":"container"}},"type":"Feature"},
	{"geometry":{"coordinates":[-16.814668,28.296955],"type":"Point"},"properties":{"osm_id":"6382024699","tag":{"amenity":"waste_basket"}},"type":"Feature"},
	{"geometry":{"coordinates":[-16.819005,28.269922],"type":"Point"},"properties":{"osm_id":"6383868474","tag":{"amenity":"recycling"}},"type":"Feature"},
	{"geometry":{"coordinates":[-16.818949,28.268762],"type":"Point"},"properties":{"osm_id":"6383869009","tag":{"amenity":"waste_basket"}},"type":"Feature"},
	{"geometry":{"coordinates":[-16.818122,28.266393],"type":"Point"},"properties":{"osm_id":"6383869010","tag":{"amenity":"recycling"}},"type":"Feature"},
	{"geometry":{"coordinates":[-16.807695,28.266058],"type":"Point"},"properties":{"osm_id":"6383869011","tag":{"amenity":"waste_basket"}},"type":"Feature"},
	{"geometry":{"coordinates":[-16.819192,28.269805],"type":"Point"},"properties":{"osm_id":"6383869109","tag":{"amenity":"waste_basket"}},"type":"Feature"},
	{"geometry":{"coordinates":[-16.816331,28.297917],"type":"Point"},"properties":{"osm_id":"6383869200","tag":{"amenity":"recycling","mapillary":"A0ETZFKyU56K3ygXrnhlDg","recycling_type":"container","survey:date":"2020-02-02"}},"type":"Feature"},
	{"geometry":{"coordinates":[-16.842198,28.240935],"type":"Point"},"properties":{"osm_id":"6387477720","tag":{"amenity":"waste_basket"}},"type":"Feature"},
	{"geometry":{"coordinates":[-16.84034,28.244928],"type":"Point"},"properties":{"osm_id":"6387478310","tag":{"amenity":"recycling"}},"type":"Feature"}
]
}
