{
"type": "FeatureCollection",
"features": [
	{"geometry":{"coordinates":[5.487745,52.005596],"type":"Point"},"properties":{"name":"Eenzame Eik","osm_id":"771165249","tag":{"natural":"tree"}},"type":"Feature"},
	{"geometry":{"coordinates":[5.532737,52.022754],"type":"Point"},"properties":{"osm_id":"6185409672","tag":{"natural":"tree"}},"type":"Feature"},
	{"geometry":{"coordinates":[5.530765,52.027095],"type":"Point"},"properties":{"osm_id":"6361879348","tag":{"natural":"tree"}},"type":"Feature"},
	{"geometry":{"coordinates":[5.531228,52.027383],"type":"Point"},"properties":{"osm_id":"6361879349","tag":{"natural":"tree"}},"type":"Feature"},
	{"geometry":{"coordinates":[5.531328,52.02736],"type":"Point"},"properties":{"osm_id":"6361879350","tag":{"natural":"tree"}},"type":"Feature"},
	{"geometry":{"coordinates":[5.530926,52.027297],"type":"Point"},"properties":{"osm_id":"6361879351","tag":{"natural":"tree"}},"type":"Feature"},
	{"geometry":{"coordinates":[5.531728,52.026472],"type":"Point"},"properties":{"osm_id":"6511977380","tag":{"natural":"tree"}},"type":"Feature"},
	{"geometry":{"coordinates":[5.530452,52.02671],"type":"Point"},"properties":{"osm_id":"6511977381","tag":{"natural":"tree"}},"type":"Feature"},
	{"geometry":{"coordinates":[5.530399,52.026657],"type":"Point"},"properties":{"osm_id":"6511977382","tag":{"natural":"tree"}},"type":"Feature"},
	{"geometry":{"coordinates":[5.530354,52.026595],"type":"Point"},"properties":{"osm_id":"6511977383","tag":{"natural":"tree"}},"type":"Feature"},
	{"geometry":{"coordinates":[5.530307,52.02654],"type":"Point"},"properties":{"osm_id":"6511977384","tag":{"natural":"tree"}},"type":"Feature"},
	{"geometry":{"coordinates":[5.531946,52.02655],"type":"Point"},"properties":{"osm_id":"6511980185","tag":{"natural":"tree"}},"type":"Feature"},
	{"geometry":{"coordinates":[5.531622,52.026147],"type":"Point"},"properties":{"osm_id":"6511980186","tag":{"natural":"tree"}},"type":"Feature"},
	{"geometry":{"coordinates":[5.531446,52.026227],"type":"Point"},"properties":{"osm_id":"6511980187","tag":{"natural":"tree"}},"type":"Feature"},
	{"geometry":{"coordinates":[5.531328,52.026259],"type":"Point"},"properties":{"osm_id":"6511980188","tag":{"natural":"tree"}},"type":"Feature"},
	{"geometry":{"coordinates":[5.53577,52.01996],"type":"Point"},"properties":{"osm_id":"6513885352","tag":{"natural":"tree"}},"type":"Feature"}
]
}
