{
"type": "FeatureCollection",
"features": [
	{"geometry":{"coordinates":[5.487745,52.005596],"type":"Point"},"properties":{"name":"Eenzame Eik","osm_id":"771165249","tag":{"natural":"tree"}},"type":"Feature"},
	{"geometry":{"coordinates":[5.532736,52.022753],"type":"Point"},"properties":{"osm_id":"6185409672","tag":{"natural":"tree"}},"type":"Feature"},
	{"geometry":{"coordinates":[5.530765,52.027095],"type":"Point"},"properties":{"osm_id":"6361879348","tag":{"natural":"tree"}},"type":"Feature"},
	{"geometry":{"coordinates":[5.531227,52.027382],"type":"Point"},"properties":{"osm_id":"6361879349","tag":{"natural":"tree"}},"type":"Feature"},
	{"geometry":{"coordinates":[5.531327,52.027359],"type":"Point"},"properties":{"osm_id":"6361879350","tag":{"natural":"tree"}},"type":"Feature"},
	{"geometry":{"coordinates":[5.530925,52.027297],"type":"Point"},"properties":{"osm_id":"6361879351","tag":{"natural":"tree"}},"type":"Feature"},
	{"geometry":{"coordinates":[5.531727,52.026471],"type":"Point"},"properties":{"osm_id":"6511977380","tag":{"natural":"tree"}},"type":"Feature"},
	{"geometry":{"coordinates":[5.530452,52.026709],"type":"Point"},"properties":{"osm_id":"6511977381","tag":{"natural":"tree"}},"type":"Feature"},
	{"geometry":{"coordinates":[5.530399,52.026657],"type":"Point"},"properties":{"osm_id":"6511977382","tag":{"natural":"tree"}},"type":"Feature"},
	{"geometry":{"coordinates":[5.530354,52.026594],"type":"Point"},"properties":{"osm_id":"6511977383","tag":{"natural":"tree"}},"type":"Feature"},
	{"geometry":{"coordinates":[5.530307,52.02654],"type":"Point"},"properties":{"osm_id":"6511977384","tag":{"natural":"tree"}},"type":"Feature"},
	{"geometry":{"coordinates":[5.531946,52.026549],"type":"Point"},"properties":{"osm_id":"6511980185","tag":{"natural":"tree"}},"type":"Feature"},
	{"geometry":{"coordinates":[5.531621,52.026146],"type":"Point"},"properties":{"osm_id":"6511980186","tag":{"natural":"tree"}},"type":"Feature"},
	{"geometry":{"coordinates":[5.531446,52.026226],"type":"Point"},"properties":{"osm_id":"6511980187","tag":{"natural":"tree"}},"type":"Feature"},
	{"geometry":{"coordinates":[5.531327,52.026259],"type":"Point"},"properties":{"osm_id":"6511980188","tag":{"natural":"tree"}},"type":"Feature"},
	{"geometry":{"coordinates":[5.535769,52.01996],"type":"Point"},"properties":{"osm_id":"6513885352","tag":{"natural":"tree"}},"type":"Feature"}
]
}
