{
"type": "FeatureCollection",
"lastupdate": "2020-08-04T00:00:00Z",
"features": [
	{"geometry":{"coordinates":[-80.090191,37.288818],"type":"Point"},"properties":{"name":"Salem Recycling","osm_id":"2688768157","tag":{"amenity":"recycling","recycling_type":"container"}},"type":"Feature"}
]
}
