{
"type": "FeatureCollection",
"features": [
	{"geometry":{"coordinates":[145.531941,-41.787274],"type":"Point"},"properties":{"name":"Rosebery Waste Transfer Station","osm_id":"469649129","tag":{"amenity":"waste_disposal","landuse":"landfill"}},"type":"Feature"}
]
}
