{
"type": "FeatureCollection",
"features": [
	{"geometry":{"coordinates":[9.146999,53.966719],"type":"Point"},"properties":{"osm_id":"33116912","tag":{"amenity":"recycling","check_date":"2021-05-22","operator":"Abfallwirtschaft Dithmarschen","recycling:glass_bottles":"yes","recycling_type":"container"}},"type":"Feature"},
	{"geometry":{"coordinates":[9.200709,53.966069],"type":"Point"},"properties":{"osm_id":"1402278626","tag":{"amenity":"recycling","check_date":"2021-06-29","operator":"Abfallwirtschaft Dithmarschen","recycling:glass_bottles":"yes","recycling_type":"container"}},"type":"Feature"},
	{"geometry":{"coordinates":[9.225335,53.983429],"type":"Point"},"properties":{"osm_id":"2460597916","tag":{"amenity":"recycling","check_date":"2021-05-13","operator":"Abfallwirtschaft Dithmarschen","recycling:glass_bottles":"yes","recycling_type":"container"}},"type":"Feature"},
	{"geometry":{"coordinates":[9.146954,53.966682],"type":"Point"},"properties":{"osm_id":"3488104883","tag":{"amenity":"recycling","check_date":"2021-05-22","operator":"Humana","recycling:clothes":"yes","recycling_type":"container","website":"https://www.humana-kleidersammlung.de/"}},"type":"Feature"},
	{"geometry":{"coordinates":[9.225381,53.983403],"type":"Point"},"properties":{"osm_id":"3532349942","tag":{"amenity":"recycling","check_date":"2021-05-13","operator":"Deutsches Rotes Kreuz","recycling:clothes":"yes","recycling_type":"container"}},"type":"Feature"},
	{"geometry":{"coordinates":[9.200773,53.966064],"type":"Point"},"properties":{"osm_id":"3604392766","tag":{"amenity":"recycling","check_date":"2021-06-29","operator":"Deutsches Rotes Kreuz","recycling:clothes":"yes","recycling_type":"container"}},"type":"Feature"}
]
}
