{
"type": "FeatureCollection",
"features": [
	{"geometry":{"coordinates":[9.228471,48.586304],"type":"Point"},"properties":{"osm_id":"339918400","tag":{"amenity":"recycling","recycling:clothes":"yes","recycling:glass":"yes","recycling_type":"container"}},"type":"Feature"},
	{"geometry":{"coordinates":[9.224843,48.607241],"type":"Point"},"properties":{"osm_id":"418083112","tag":{"amenity":"recycling","recycling:batteries":"no","recycling:books":"no","recycling:cans":"no","recycling:cardboard":"no","recycling:cartons":"no","recycling:clothes":"yes","recycling:electrical_appliances":"no","recycling:glass":"yes","recycling:glass_bottles":"yes","recycling:green_waste":"no","recycling:magazines":"no","recycling:newspaper":"no","recycling:paper":"no","recycling:paper_packaging":"no","recycling:plastic":"no","recycling:plastic_bottles":"no","recycling:plastic_packaging":"no","recycling:scrap_metal":"no","recycling:small_appliances":"no","recycling:waste":"no","recycling:wood":"no","recycling_type":"container"}},"type":"Feature"},
	{"geometry":{"coordinates":[9.224776,48.603547],"type":"Point"},"properties":{"osm_id":"418083139","tag":{"amenity":"recycling","recycling:clothes":"yes","recycling:glass":"yes"}},"type":"Feature"},
	{"geometry":{"coordinates":[9.224958,48.60596],"type":"Point"},"properties":{"name":"Bauhof","osm_id":"649232325","tag":{"amenity":"recycling","recycling_type":"centre"}},"type":"Feature"},
	{"geometry":{"coordinates":[9.196196,48.577067],"type":"Point"},"properties":{"osm_id":"794381697","tag":{"amenity":"recycling","recycling:glass":"yes","recycling_type":"container"}},"type":"Feature"},
	{"geometry":{"coordinates":[9.187102,48.578102],"type":"Point"},"properties":{"osm_id":"830437898","tag":{"amenity":"recycling","recycling:glass":"yes","recycling_type":"container"}},"type":"Feature"},
	{"geometry":{"coordinates":[9.194488,48.577933],"type":"Point"},"properties":{"osm_id":"1282715054","tag":{"amenity":"waste_basket"}},"type":"Feature"},
	{"geometry":{"coordinates":[9.196288,48.578236],"type":"Point"},"properties":{"osm_id":"1282715057","tag":{"amenity":"waste_basket"}},"type":"Feature"},
	{"geometry":{"coordinates":[9.175306,48.590158],"type":"Point"},"properties":{"osm_id":"2166945052","tag":{"amenity":"waste_basket"}},"type":"Feature"},
	{"geometry":{"coordinates":[9.207845,48.623969],"type":"Point"},"properties":{"osm_id":"2914934416","tag":{"amenity":"recycling","recycling:clothes":"yes","recycling:glass":"yes","recycling:glass_bottles":"yes","recycling_type":"container"}},"type":"Feature"},
	{"geometry":{"coordinates":[9.221532,48.62187],"type":"Point"},"properties":{"osm_id":"3258427474","tag":{"amenity":"waste_basket"}},"type":"Feature"},
	{"geometry":{"coordinates":[9.188657,48.590216],"type":"Point"},"properties":{"osm_id":"3403854455","tag":{"amenity":"waste_basket"}},"type":"Feature"},
	{"geometry":{"coordinates":[9.205311,48.622605],"type":"Point"},"properties":{"osm_id":"4849031731","tag":{"amenity":"waste_basket"}},"type":"Feature"},
	{"geometry":{"coordinates":[9.216702,48.623731],"type":"Point"},"properties":{"osm_id":"7573212232","tag":{"amenity":"waste_basket","waste":"dog_excrement"}},"type":"Feature"}
]
}
