{
"type": "FeatureCollection",
"features": [
	{"geometry":{"coordinates":[9.148923,47.117466],"type":"Point"},"properties":{"osm_id":"32097486","tag":{"amenity":"recycling","recycling:cans":"yes","recycling:glass_bottles":"yes","recycling_type":"container"}},"type":"Feature"},
	{"geometry":{"coordinates":[9.141317,47.147962],"type":"Point"},"properties":{"name":"Entsorgungspark Amden","osm_id":"3459780993","tag":{"amenity":"recycling","recycling:batteries":"yes","recycling:books":"yes","recycling:cans":"yes","recycling:cardboard":"yes","recycling:cartons":"yes","recycling:clothes":"no","recycling:electrical_appliances":"no","recycling:glass":"yes","recycling:glass_bottles":"yes","recycling:green_waste":"yes","recycling:magazines":"yes","recycling:newspaper":"yes","recycling:paper":"yes","recycling:paper_packaging":"yes","recycling:plastic":"no","recycling:plastic_bottles":"no","recycling:plastic_packaging":"no","recycling:scrap_metal":"yes","recycling:small_appliances":"no","recycling:waste":"yes","recycling:wood":"yes","recycling_type":"centre"}},"type":"Feature"},
	{"geometry":{"coordinates":[9.148318,47.148937],"type":"Point"},"properties":{"osm_id":"5975961979","tag":{"amenity":"recycling","recycling:clothes":"yes","recycling_type":"container"}},"type":"Feature"},
	{"geometry":{"coordinates":[9.161442,47.142585],"type":"Point"},"properties":{"osm_id":"6358846824","tag":{"amenity":"waste_basket","fee":"yes","vending":"excrement_bags","waste":"dog_excrement"}},"type":"Feature"},
	{"geometry":{"coordinates":[9.174655,47.147128],"type":"Point"},"properties":{"name":"belloo","osm_id":"6391645010","tag":{"amenity":"waste_basket","waste":"dog_excrement"}},"type":"Feature"},
	{"geometry":{"coordinates":[9.17698,47.149837],"type":"Point"},"properties":{"osm_id":"6419346075","tag":{"amenity":"waste_basket","waste":"dog_excrement"}},"type":"Feature"},
	{"geometry":{"coordinates":[9.176935,47.147789],"type":"Point"},"properties":{"name":"robidog","osm_id":"6502280260","tag":{"amenity":"waste_basket","waste":"dog_excrement"}},"type":"Feature"},
	{"geometry":{"coordinates":[9.153526,47.142461],"type":"Point"},"properties":{"osm_id":"6516342993","tag":{"amenity":"waste_basket"}},"type":"Feature"},
	{"geometry":{"coordinates":[9.148429,47.145574],"type":"Point"},"properties":{"osm_id":"6516343018","tag":{"amenity":"waste_basket","waste":"dog_excrement"}},"type":"Feature"},
	{"geometry":{"coordinates":[9.150065,47.144503],"type":"Point"},"properties":{"osm_id":"6516343028","tag":{"amenity":"waste_basket"}},"type":"Feature"},
	{"geometry":{"coordinates":[9.144528,47.14771],"type":"Point"},"properties":{"name":"belloo","osm_id":"6516343030","tag":{"amenity":"waste_basket","waste":"dog_excrement"}},"type":"Feature"},
	{"geometry":{"coordinates":[9.147217,47.146915],"type":"Point"},"properties":{"osm_id":"6516343036","tag":{"amenity":"waste_basket"}},"type":"Feature"},
	{"geometry":{"coordinates":[9.149883,47.144274],"type":"Point"},"properties":{"osm_id":"6516343040","tag":{"amenity":"waste_basket"}},"type":"Feature"},
	{"geometry":{"coordinates":[9.178829,47.145297],"type":"Point"},"properties":{"osm_id":"6516587625","tag":{"amenity":"waste_basket","waste":"dog_excrement"}},"type":"Feature"},
	{"geometry":{"coordinates":[9.163022,47.1427],"type":"Point"},"properties":{"osm_id":"6516587645","tag":{"amenity":"waste_basket","waste":"dog_excrement"}},"type":"Feature"},
	{"geometry":{"coordinates":[9.173885,47.147138],"type":"Point"},"properties":{"osm_id":"6535645936","tag":{"amenity":"waste_basket"}},"type":"Feature"},
	{"geometry":{"coordinates":[9.170528,47.145152],"type":"Point"},"properties":{"osm_id":"6681698218","tag":{"amenity":"waste_basket","waste":"dog_excrement"}},"type":"Feature"},
	{"geometry":{"coordinates":[9.148373,47.14892],"type":"Point"},"properties":{"osm_id":"7640617855","tag":{"amenity":"recycling","recycling:waste":"yes","recycling_type":"container"}},"type":"Feature"},
	{"geometry":{"coordinates":[9.164869,47.1512],"type":"Point"},"properties":{"osm_id":"7686013805","tag":{"amenity":"waste_basket","waste":"dog_excrement"}},"type":"Feature"}
]
}
