{
"type": "FeatureCollection",
"lastupdate": "2020-08-01T00:00:00Z",
"features": [
	{"geometry":{"coordinates":[9.155206,46.9202],"type":"Point"},"properties":{"osm_id":"3571675393","tag":{"amenity":"waste_basket"}},"type":"Feature"},
	{"geometry":{"coordinates":[9.173245,46.916598],"type":"Point"},"properties":{"osm_id":"4413009892","tag":{"amenity":"waste_basket","waste":"dog_excrement"}},"type":"Feature"},
	{"geometry":{"coordinates":[9.183176,46.917176],"type":"Point"},"properties":{"osm_id":"4413505291","tag":{"amenity":"waste_basket"}},"type":"Feature"},
	{"geometry":{"coordinates":[9.183153,46.917269],"type":"Point"},"properties":{"osm_id":"4413505292","tag":{"amenity":"waste_basket"}},"type":"Feature"},
	{"geometry":{"coordinates":[9.169666,46.918268],"type":"Point"},"properties":{"osm_id":"6893834011","tag":{"addr:city":"Elm","addr:postcode":"8767","addr:street":"Segnes","amenity":"recycling","recycling:aluminium":"yes","recycling:batteries":"yes","recycling:electronic_scrap":"yes","recycling:glass":"yes","recycling:green_waste":"yes","recycling:oils":"yes","recycling:textiles":"yes","recycling_type":"container"}},"type":"Feature"}
]
}
