{
"type": "FeatureCollection",
"features": [
	{"geometry":{"coordinates":[7.111849,51.119522],"type":"Point"},"properties":{"osm_id":"85465536","tag":{"amenity":"recycling"}},"type":"Feature"},
	{"geometry":{"coordinates":[7.107909,51.120614],"type":"Point"},"properties":{"osm_id":"85652329","tag":{"amenity":"recycling","location":"overground","recycling_type":"container"}},"type":"Feature"},
	{"geometry":{"coordinates":[7.109857,51.098462],"type":"Point"},"properties":{"osm_id":"266756582","tag":{"amenity":"recycling","recycling_type":"container"}},"type":"Feature"},
	{"geometry":{"coordinates":[7.072428,51.091341],"type":"Point"},"properties":{"osm_id":"391205485","tag":{"amenity":"recycling","recycling:glass":"yes","recycling_type":"container"}},"type":"Feature"},
	{"geometry":{"coordinates":[7.057076,51.071293],"type":"Point"},"properties":{"osm_id":"622878757","tag":{"amenity":"recycling"}},"type":"Feature"},
	{"geometry":{"coordinates":[7.061797,51.072534],"type":"Point"},"properties":{"osm_id":"622887463","tag":{"amenity":"recycling","location":"overground","recycling_type":"container"}},"type":"Feature"},
	{"geometry":{"coordinates":[7.087243,51.108747],"type":"Point"},"properties":{"osm_id":"827743522","tag":{"amenity":"recycling","location":"overground","recycling:glass":"yes","recycling_type":"container"}},"type":"Feature"},
	{"geometry":{"coordinates":[7.113539,51.091725],"type":"Point"},"properties":{"osm_id":"1720138783","tag":{"amenity":"recycling","recycling:glass_bottles":"yes","recycling_type":"container"}},"type":"Feature"},
	{"geometry":{"coordinates":[7.118136,51.083389],"type":"Point"},"properties":{"osm_id":"4315511590","tag":{"amenity":"waste_basket"}},"type":"Feature"},
	{"geometry":{"coordinates":[7.11828,51.083281],"type":"Point"},"properties":{"osm_id":"4315522296","tag":{"amenity":"waste_basket"}},"type":"Feature"},
	{"geometry":{"coordinates":[7.117757,51.083235],"type":"Point"},"properties":{"osm_id":"4315522390","tag":{"amenity":"waste_basket"}},"type":"Feature"},
	{"geometry":{"coordinates":[7.112429,51.104601],"type":"Point"},"properties":{"osm_id":"4564699210","tag":{"amenity":"recycling"}},"type":"Feature"},
	{"geometry":{"coordinates":[7.054021,51.090784],"type":"Point"},"properties":{"osm_id":"5143404221","tag":{"amenity":"waste_basket"}},"type":"Feature"},
	{"geometry":{"coordinates":[7.056841,51.091434],"type":"Point"},"properties":{"osm_id":"5143597521","tag":{"amenity":"waste_basket"}},"type":"Feature"},
	{"geometry":{"coordinates":[7.060805,51.072005],"type":"Point"},"properties":{"osm_id":"7422237666","tag":{"amenity":"waste_basket"}},"type":"Feature"},
	{"geometry":{"coordinates":[7.074206,51.070066],"type":"Point"},"properties":{"osm_id":"7488826885","tag":{"amenity":"waste_basket"}},"type":"Feature"}
]
}
