{
"type": "FeatureCollection",
"lastupdate": "2020-08-03T00:00:00Z",
"features": [
	{"geometry":{"coordinates":[7.111849,51.119521],"type":"Point"},"properties":{"osm_id":"85465536","tag":{"amenity":"recycling"}},"type":"Feature"},
	{"geometry":{"coordinates":[7.107909,51.120613],"type":"Point"},"properties":{"osm_id":"85652329","tag":{"amenity":"recycling","location":"overground","recycling_type":"container"}},"type":"Feature"},
	{"geometry":{"coordinates":[7.109856,51.098462],"type":"Point"},"properties":{"osm_id":"266756582","tag":{"amenity":"recycling","recycling_type":"container"}},"type":"Feature"},
	{"geometry":{"coordinates":[7.072427,51.09134],"type":"Point"},"properties":{"osm_id":"391205485","tag":{"amenity":"recycling","recycling:glass":"yes","recycling_type":"container"}},"type":"Feature"},
	{"geometry":{"coordinates":[7.057076,51.071293],"type":"Point"},"properties":{"osm_id":"622878757","tag":{"amenity":"recycling"}},"type":"Feature"},
	{"geometry":{"coordinates":[7.061796,51.072533],"type":"Point"},"properties":{"osm_id":"622887463","tag":{"amenity":"recycling","location":"overground","recycling_type":"container"}},"type":"Feature"},
	{"geometry":{"coordinates":[7.087242,51.108746],"type":"Point"},"properties":{"osm_id":"827743522","tag":{"amenity":"recycling","location":"overground","recycling:glass":"yes","recycling_type":"container"}},"type":"Feature"},
	{"geometry":{"coordinates":[7.113539,51.091724],"type":"Point"},"properties":{"osm_id":"1720138783","tag":{"amenity":"recycling","recycling:glass_bottles":"yes","recycling_type":"container"}},"type":"Feature"},
	{"geometry":{"coordinates":[7.118136,51.083388],"type":"Point"},"properties":{"osm_id":"4315511590","tag":{"amenity":"waste_basket"}},"type":"Feature"},
	{"geometry":{"coordinates":[7.118279,51.083281],"type":"Point"},"properties":{"osm_id":"4315522296","tag":{"amenity":"waste_basket"}},"type":"Feature"},
	{"geometry":{"coordinates":[7.117757,51.083234],"type":"Point"},"properties":{"osm_id":"4315522390","tag":{"amenity":"waste_basket"}},"type":"Feature"},
	{"geometry":{"coordinates":[7.112428,51.1046],"type":"Point"},"properties":{"osm_id":"4564699210","tag":{"amenity":"recycling"}},"type":"Feature"},
	{"geometry":{"coordinates":[7.05402,51.090783],"type":"Point"},"properties":{"osm_id":"5143404221","tag":{"amenity":"waste_basket"}},"type":"Feature"},
	{"geometry":{"coordinates":[7.056841,51.091434],"type":"Point"},"properties":{"osm_id":"5143597521","tag":{"amenity":"waste_basket"}},"type":"Feature"},
	{"geometry":{"coordinates":[7.060805,51.072005],"type":"Point"},"properties":{"osm_id":"7422237666","tag":{"amenity":"waste_basket"}},"type":"Feature"},
	{"geometry":{"coordinates":[7.074205,51.070065],"type":"Point"},"properties":{"osm_id":"7488826885","tag":{"amenity":"waste_basket"}},"type":"Feature"}
]
}
