{
"type": "FeatureCollection",
"features": [
	{"geometry":{"coordinates":[-123.990247,49.223417],"type":"Point"},"properties":{"name":"Large Fallen tree","osm_id":"8070666174","tag":{"natural":"tree"}},"type":"Feature"}
]
}
