{
"type": "FeatureCollection",
"features": [
	{"geometry":{"coordinates":[1.572844,41.442787],"type":"Point"},"properties":{"name":"Pi de la Planxa (Monumental)","osm_id":"4896863759","tag":{"natural":"tree"}},"type":"Feature"}
]
}
