{
"type": "FeatureCollection",
"lastupdate": "2020-08-02T00:00:00Z",
"features": [
	{"geometry":{"coordinates":[-77.428831,38.394602],"type":"Point"},"properties":{"name":"Northern Virginia Metals","osm_id":"5898582299","tag":{"addr:city":"Stafford","addr:housenumber":"32","addr:postcode":"22554","addr:state":"VA","addr:street":"Eskimo Hill Road","amenity":"recycling","fax":"+1-540-602-7310","phone":"+1-540-659-3043","recycling:metal":"yes","recycling_type":"centre","start_date":"1987","website":"http://novametalsrecycling.com"}},"type":"Feature"}
]
}
