{
"type": "FeatureCollection",
"features": [
	{"geometry":{"coordinates":[9.328345,53.57464],"type":"Point"},"properties":{"name":"Luthereiche","osm_id":"7313280053","tag":{"leaf_cycle":"deciduous","leaf_type":"broadleaved","natural":"tree"}},"type":"Feature"}
]
}
