{
"type": "FeatureCollection",
"features": [
	{"geometry":{"coordinates":[-0.942192,41.916019],"type":"Point"},"properties":{"name":"Pino Valdenavarro","osm_id":"7312605830","tag":{"natural":"tree"}},"type":"Feature"}
]
}
