{
"type": "FeatureCollection",
"features": [
	{"geometry":{"coordinates":[9.26212,53.996669],"type":"Point"},"properties":{"name":"Friedenseiche","osm_id":"1664049125","tag":{"natural":"tree"}},"type":"Feature"}
]
}
