{
"type": "FeatureCollection",
"features": [
	{"geometry":{"coordinates":[9.262119,53.996668],"type":"Point"},"properties":{"name":"Friedenseiche","osm_id":"1664049125","tag":{"natural":"tree"}},"type":"Feature"}
]
}
