{
"type": "FeatureCollection",
"features": [
	{"geometry":{"coordinates":[9.311048,39.357024],"type":"Point"},"properties":{"name":"Su Suergiu Mannu de su Troccu Nieddu","osm_id":"7098039732","tag":{"leaf_cycle":"evergreen","leaf_type":"broadleaved","natural":"tree"}},"type":"Feature"}
]
}
