{
"type": "FeatureCollection",
"features": [
	{"geometry":{"coordinates":[2.188569,42.907066],"type":"Point"},"properties":{"osm_id":"306165832","tag":{"amenity":"recycling","recycling:glass_bottles":"yes","recycling:paper":"yes","recycling:plastic":"yes","recycling_type":"container"}},"type":"Feature"},
	{"geometry":{"coordinates":[2.165944,42.896466],"type":"Point"},"properties":{"osm_id":"736708192","tag":{"amenity":"recycling","recycling:glass_bottles":"yes","recycling_type":"container"}},"type":"Feature"},
	{"geometry":{"coordinates":[2.172426,42.905005],"type":"Point"},"properties":{"osm_id":"915872802","tag":{"amenity":"recycling","recycling:glass_bottles":"yes","recycling:paper":"yes","recycling:plastic":"yes","recycling:waste":"yes","recycling_type":"container"}},"type":"Feature"},
	{"geometry":{"coordinates":[2.172223,42.912002],"type":"Point"},"properties":{"osm_id":"915872901","tag":{"amenity":"recycling","recycling:glass_bottles":"yes","recycling_type":"container"}},"type":"Feature"},
	{"geometry":{"coordinates":[2.148069,42.938496],"type":"Point"},"properties":{"osm_id":"1860092329","tag":{"amenity":"recycling"}},"type":"Feature"},
	{"geometry":{"coordinates":[2.113903,42.935409],"type":"Point"},"properties":{"osm_id":"1894658143","tag":{"amenity":"recycling"}},"type":"Feature"},
	{"geometry":{"coordinates":[2.113495,42.895258],"type":"Point"},"properties":{"osm_id":"3695042383","tag":{"amenity":"recycling","recycling_type":"container"}},"type":"Feature"},
	{"geometry":{"coordinates":[2.190009,42.880774],"type":"Point"},"properties":{"osm_id":"6161634792","tag":{"amenity":"recycling","recycling:glass_bottles":"yes","recycling_type":"container"}},"type":"Feature"},
	{"geometry":{"coordinates":[2.19307,42.893908],"type":"Point"},"properties":{"osm_id":"6161634795","tag":{"amenity":"recycling","recycling:glass_bottles":"yes","recycling_type":"container"}},"type":"Feature"},
	{"geometry":{"coordinates":[2.192783,42.893623],"type":"Point"},"properties":{"osm_id":"6161634796","tag":{"amenity":"recycling","recycling:clothes":"yes","recycling_type":"container"}},"type":"Feature"},
	{"geometry":{"coordinates":[2.183772,42.877358],"type":"Point"},"properties":{"osm_id":"7813248113","tag":{"amenity":"waste_basket"}},"type":"Feature"},
	{"geometry":{"coordinates":[2.192861,42.893671],"type":"Point"},"properties":{"osm_id":"7813267511","tag":{"amenity":"waste_basket"}},"type":"Feature"},
	{"geometry":{"coordinates":[2.183481,42.876004],"type":"Point"},"properties":{"osm_id":"7832544930","tag":{"amenity":"recycling","location":"underground","recycling:cardboard":"yes","recycling:glass_bottles":"yes","recycling:paper":"yes","recycling:plastic":"yes","recycling_type":"container"}},"type":"Feature"},
	{"geometry":{"coordinates":[2.183471,42.876016],"type":"Point"},"properties":{"osm_id":"7832544931","tag":{"access":"yes","amenity":"waste_disposal","location":"underground","waste":"trash"}},"type":"Feature"},
	{"geometry":{"coordinates":[2.176685,42.876338],"type":"Point"},"properties":{"osm_id":"7846557383","tag":{"amenity":"recycling","recycling:glass_bottles":"yes","recycling_type":"container"}},"type":"Feature"},
	{"geometry":{"coordinates":[2.176457,42.875969],"type":"Point"},"properties":{"osm_id":"7846557384","tag":{"amenity":"waste_basket"}},"type":"Feature"},
	{"geometry":{"coordinates":[2.176804,42.876991],"type":"Point"},"properties":{"osm_id":"7846562192","tag":{"amenity":"waste_basket"}},"type":"Feature"},
	{"geometry":{"coordinates":[2.184529,42.876515],"type":"Point"},"properties":{"osm_id":"7862945562","tag":{"amenity":"waste_basket","waste":"dog_excrement"}},"type":"Feature"},
	{"geometry":{"coordinates":[2.188004,42.878168],"type":"Point"},"properties":{"osm_id":"7913213108","tag":{"amenity":"waste_basket"}},"type":"Feature"},
	{"geometry":{"coordinates":[2.189204,42.881533],"type":"Point"},"properties":{"osm_id":"7931349733","tag":{"amenity":"waste_basket"}},"type":"Feature"},
	{"geometry":{"coordinates":[2.192695,42.937589],"type":"Point"},"properties":{"osm_id":"7995300811","tag":{"amenity":"waste_disposal"}},"type":"Feature"},
	{"geometry":{"coordinates":[2.192101,42.897253],"type":"Point"},"properties":{"osm_id":"9053549818","tag":{"amenity":"waste_disposal"}},"type":"Feature"},
	{"geometry":{"coordinates":[2.192192,42.897257],"type":"Point"},"properties":{"osm_id":"9053549823","tag":{"amenity":"waste_disposal"}},"type":"Feature"},
	{"geometry":{"coordinates":[2.154068,42.892109],"type":"Point"},"properties":{"osm_id":"9118461335","tag":{"amenity":"recycling","recycling_type":"container"}},"type":"Feature"}
]
}
