{
"type": "FeatureCollection",
"lastupdate": "2020-08-02T00:00:00Z",
"features": [
	{"geometry":{"coordinates":[-7.400893,52.84217],"type":"Point"},"properties":{"name":"Bring Bank","osm_id":"567453826","tag":{"amenity":"recycling"}},"type":"Feature"}
]
}
