{
"type": "FeatureCollection",
"features": [
	{"geometry":{"coordinates":[-2.309701,40.462072],"type":"Point"},"properties":{"name":"catalpa","osm_id":"8890464749","tag":{"denotation":"garden","leaf_cycle":"deciduous","leaf_type":"broadleaved","natural":"tree"}},"type":"Feature"},
	{"geometry":{"coordinates":[-2.308727,40.46096],"type":"Point"},"properties":{"osm_id":"8890464750","tag":{"natural":"tree"}},"type":"Feature"}
]
}
