{
"type": "FeatureCollection",
"features": [
	{"geometry":{"coordinates":[-2.339954,39.108992],"type":"Point"},"properties":{"name":"Carrasca de Monteagudo","osm_id":"7416741306","tag":{"denotation":"single","natural":"tree"}},"type":"Feature"}
]
}
