{
"type": "FeatureCollection",
"features": [
	{"geometry":{"coordinates":[-2.32012,38.234799],"type":"Point"},"properties":{"name":"Carrasca de Yetas","osm_id":"7423854315","tag":{"denotation":"single","natural":"tree"}},"type":"Feature"}
]
}
