{
"type": "FeatureCollection",
"features": [
	{"geometry":{"coordinates":[105.858589,15.021812],"type":"Point"},"properties":{"name":"Irvingia Gabonensis (Dika Nut Tree)","osm_id":"6194130009","tag":{"natural":"tree"}},"type":"Feature"},
	{"geometry":{"coordinates":[105.866165,15.005605],"type":"Point"},"properties":{"name":"Albizia Saman Tree","osm_id":"6194130396","tag":{"natural":"tree"}},"type":"Feature"}
]
}
