{
"type": "FeatureCollection",
"features": [
	{"geometry":{"coordinates":[-8.021447,41.462088],"type":"Point"},"properties":{"name":"Ecoponto","osm_id":"2979080327","tag":{"amenity":"recycling"}},"type":"Feature"},
	{"geometry":{"coordinates":[-8.007083,41.459163],"type":"Point"},"properties":{"osm_id":"6508583322","tag":{"amenity":"waste_basket","colour":"green"}},"type":"Feature"},
	{"geometry":{"coordinates":[-8.006946,41.457888],"type":"Point"},"properties":{"osm_id":"6508583323","tag":{"amenity":"waste_basket","colour":"green"}},"type":"Feature"},
	{"geometry":{"coordinates":[-8.011372,41.459786],"type":"Point"},"properties":{"osm_id":"6508583340","tag":{"amenity":"waste_basket","colour":"green"}},"type":"Feature"},
	{"geometry":{"coordinates":[-8.017913,41.457574],"type":"Point"},"properties":{"osm_id":"6508583397","tag":{"amenity":"recycling","recycling:glass_bottles":"yes","recycling:paper":"yes","recycling:plastic_bottles":"yes","recycling_type":"container"}},"type":"Feature"}
]
}
