{
"type": "FeatureCollection",
"lastupdate": "2020-08-04T00:00:00Z",
"features": [
	{"geometry":{"coordinates":[-8.021447,41.462088],"type":"Point"},"properties":{"name":"Ecoponto","osm_id":"2979080327","tag":{"amenity":"recycling"}},"type":"Feature"},
	{"geometry":{"coordinates":[-8.007131,41.459165],"type":"Point"},"properties":{"osm_id":"6508583322","tag":{"amenity":"waste_basket","colour":"green"}},"type":"Feature"},
	{"geometry":{"coordinates":[-8.00694,41.457909],"type":"Point"},"properties":{"osm_id":"6508583323","tag":{"amenity":"waste_basket","colour":"green"}},"type":"Feature"},
	{"geometry":{"coordinates":[-8.01131,41.459786],"type":"Point"},"properties":{"osm_id":"6508583340","tag":{"amenity":"waste_basket","colour":"green"}},"type":"Feature"},
	{"geometry":{"coordinates":[-8.017913,41.457574],"type":"Point"},"properties":{"osm_id":"6508583397","tag":{"amenity":"recycling","recycling:glass_bottles":"yes","recycling:paper":"yes","recycling:plastic_bottles":"yes","recycling_type":"container"}},"type":"Feature"}
]
}
