{
"type": "FeatureCollection",
"lastupdate": "2020-08-06T00:00:00Z",
"features": [
	{"geometry":{"coordinates":[-17.275875,14.71246],"type":"Point"},"properties":{"osm_id":"2437060725","tag":{"amenity":"recycling","recycling_type":"container"}},"type":"Feature"},
	{"geometry":{"coordinates":[-17.270772,14.714201],"type":"Point"},"properties":{"osm_id":"2492229111","tag":{"amenity":"recycling","recycling_type":"container"}},"type":"Feature"},
	{"geometry":{"coordinates":[-17.274193,14.715761],"type":"Point"},"properties":{"osm_id":"2898928816","tag":{"amenity":"recycling","recycling_type":"container"}},"type":"Feature"},
	{"geometry":{"coordinates":[-17.27471,14.716071],"type":"Point"},"properties":{"osm_id":"2898931486","tag":{"amenity":"recycling","recycling_type":"container"}},"type":"Feature"},
	{"geometry":{"coordinates":[-17.275236,14.731065],"type":"Point"},"properties":{"name":"Point collecte dechets","osm_id":"5613522121","tag":{"amenity":"recycling"}},"type":"Feature"}
]
}
