{
"type": "FeatureCollection",
"features": [
	{"geometry":{"coordinates":[91.822281,22.254473],"type":"Point"},"properties":{"name":"EBL Sky Lounge","osm_id":"5660147340","tag":{"amenity":"recycling"}},"type":"Feature"}
]
}
