{
"type": "FeatureCollection",
"features": [
	{"geometry":{"coordinates":[77.525233,12.88132],"type":"Point"},"properties":{"osm_id":"5810244685","tag":{"natural":"tree"}},"type":"Feature"},
	{"geometry":{"coordinates":[77.591254,12.893107],"type":"Point"},"properties":{"name":"Eucalyptus","osm_id":"6566429008","tag":{"natural":"tree"}},"type":"Feature"},
	{"geometry":{"coordinates":[77.591264,12.893693],"type":"Point"},"properties":{"name":"Acacia","osm_id":"6566429009","tag":{"natural":"tree"}},"type":"Feature"},
	{"geometry":{"coordinates":[77.591967,12.894211],"type":"Point"},"properties":{"name":"Black Plum","osm_id":"6566429010","tag":{"natural":"tree"}},"type":"Feature"},
	{"geometry":{"coordinates":[77.591216,12.894169],"type":"Point"},"properties":{"name":"Bhadrachalam Eucalyptus","osm_id":"6566429011","tag":{"natural":"tree"}},"type":"Feature"},
	{"geometry":{"coordinates":[77.580616,12.896026],"type":"Point"},"properties":{"osm_id":"7633038568","tag":{"natural":"tree"}},"type":"Feature"},
	{"geometry":{"coordinates":[77.5807,12.896028],"type":"Point"},"properties":{"osm_id":"7633038569","tag":{"natural":"tree"}},"type":"Feature"},
	{"geometry":{"coordinates":[77.580666,12.896079],"type":"Point"},"properties":{"osm_id":"7633038570","tag":{"natural":"tree"}},"type":"Feature"},
	{"geometry":{"coordinates":[77.580616,12.896009],"type":"Point"},"properties":{"osm_id":"7633099189","tag":{"natural":"tree"}},"type":"Feature"},
	{"geometry":{"coordinates":[77.580521,12.896007],"type":"Point"},"properties":{"osm_id":"7633099193","tag":{"natural":"tree"}},"type":"Feature"},
	{"geometry":{"coordinates":[77.579495,12.896444],"type":"Point"},"properties":{"osm_id":"7633875760","tag":{"natural":"tree"}},"type":"Feature"},
	{"geometry":{"coordinates":[77.579456,12.896838],"type":"Point"},"properties":{"osm_id":"7633875761","tag":{"natural":"tree","noname":"Tamrind Tree"}},"type":"Feature"},
	{"geometry":{"coordinates":[77.579421,12.896742],"type":"Point"},"properties":{"osm_id":"7633875764","tag":{"natural":"tree"}},"type":"Feature"},
	{"geometry":{"coordinates":[77.57962,12.896834],"type":"Point"},"properties":{"osm_id":"7633875765","tag":{"natural":"tree"}},"type":"Feature"},
	{"geometry":{"coordinates":[77.57963,12.896801],"type":"Point"},"properties":{"osm_id":"7633941543","tag":{"natural":"tree"}},"type":"Feature"},
	{"geometry":{"coordinates":[77.579743,12.897202],"type":"Point"},"properties":{"osm_id":"7634014713","tag":{"natural":"tree","noname":"Tamrind Tree"}},"type":"Feature"},
	{"geometry":{"coordinates":[77.579441,12.897229],"type":"Point"},"properties":{"osm_id":"7634014714","tag":{"natural":"tree","noname":"Tamrind Tree"}},"type":"Feature"},
	{"geometry":{"coordinates":[77.579578,12.897122],"type":"Point"},"properties":{"osm_id":"7634014716","tag":{"natural":"tree","noname":"Tamrind Tree"}},"type":"Feature"},
	{"geometry":{"coordinates":[77.579598,12.897305],"type":"Point"},"properties":{"osm_id":"7634014717","tag":{"natural":"tree","noname":"Tamrind Tree"}},"type":"Feature"},
	{"geometry":{"coordinates":[77.580138,12.897457],"type":"Point"},"properties":{"osm_id":"7634014719","tag":{"natural":"tree","noname":"Tamrind Tree"}},"type":"Feature"},
	{"geometry":{"coordinates":[77.57941,12.897051],"type":"Point"},"properties":{"osm_id":"7634014720","tag":{"natural":"tree","noname":"Tamrind Tree"}},"type":"Feature"},
	{"geometry":{"coordinates":[77.579933,12.897329],"type":"Point"},"properties":{"osm_id":"7634014721","tag":{"natural":"tree","noname":"Tamrind Tree"}},"type":"Feature"},
	{"geometry":{"coordinates":[77.579774,12.897408],"type":"Point"},"properties":{"osm_id":"7634014722","tag":{"natural":"tree","noname":"Tamrind Tree"}},"type":"Feature"},
	{"geometry":{"coordinates":[77.579754,12.896891],"type":"Point"},"properties":{"osm_id":"7634031487","tag":{"natural":"tree"}},"type":"Feature"},
	{"geometry":{"coordinates":[77.579782,12.896798],"type":"Point"},"properties":{"osm_id":"7634031501","tag":{"natural":"tree"}},"type":"Feature"}
]
}
