{
"type": "FeatureCollection",
"features": [
	{"geometry":{"coordinates":[77.525233,12.881319],"type":"Point"},"properties":{"osm_id":"5810244685","tag":{"natural":"tree"}},"type":"Feature"},
	{"geometry":{"coordinates":[77.591253,12.893107],"type":"Point"},"properties":{"name":"Eucalyptus","osm_id":"6566429008","tag":{"natural":"tree"}},"type":"Feature"},
	{"geometry":{"coordinates":[77.591264,12.893692],"type":"Point"},"properties":{"name":"Acacia","osm_id":"6566429009","tag":{"natural":"tree"}},"type":"Feature"},
	{"geometry":{"coordinates":[77.591967,12.89421],"type":"Point"},"properties":{"name":"Black Plum","osm_id":"6566429010","tag":{"natural":"tree"}},"type":"Feature"},
	{"geometry":{"coordinates":[77.591216,12.894168],"type":"Point"},"properties":{"name":"Bhadrachalam Eucalyptus","osm_id":"6566429011","tag":{"natural":"tree"}},"type":"Feature"},
	{"geometry":{"coordinates":[77.580615,12.896026],"type":"Point"},"properties":{"osm_id":"7633038568","tag":{"natural":"tree"}},"type":"Feature"},
	{"geometry":{"coordinates":[77.580699,12.896028],"type":"Point"},"properties":{"osm_id":"7633038569","tag":{"natural":"tree"}},"type":"Feature"},
	{"geometry":{"coordinates":[77.580665,12.896079],"type":"Point"},"properties":{"osm_id":"7633038570","tag":{"natural":"tree"}},"type":"Feature"},
	{"geometry":{"coordinates":[77.580615,12.896008],"type":"Point"},"properties":{"osm_id":"7633099189","tag":{"natural":"tree"}},"type":"Feature"},
	{"geometry":{"coordinates":[77.580521,12.896006],"type":"Point"},"properties":{"osm_id":"7633099193","tag":{"natural":"tree"}},"type":"Feature"},
	{"geometry":{"coordinates":[77.579494,12.896443],"type":"Point"},"properties":{"osm_id":"7633875760","tag":{"natural":"tree"}},"type":"Feature"},
	{"geometry":{"coordinates":[77.579456,12.896837],"type":"Point"},"properties":{"osm_id":"7633875761","tag":{"natural":"tree","noname":"Tamrind Tree"}},"type":"Feature"},
	{"geometry":{"coordinates":[77.579421,12.896741],"type":"Point"},"properties":{"osm_id":"7633875764","tag":{"natural":"tree"}},"type":"Feature"},
	{"geometry":{"coordinates":[77.579619,12.896834],"type":"Point"},"properties":{"osm_id":"7633875765","tag":{"natural":"tree"}},"type":"Feature"},
	{"geometry":{"coordinates":[77.579629,12.8968],"type":"Point"},"properties":{"osm_id":"7633941543","tag":{"natural":"tree"}},"type":"Feature"},
	{"geometry":{"coordinates":[77.579743,12.897202],"type":"Point"},"properties":{"osm_id":"7634014713","tag":{"natural":"tree","noname":"Tamrind Tree"}},"type":"Feature"},
	{"geometry":{"coordinates":[77.579441,12.897228],"type":"Point"},"properties":{"osm_id":"7634014714","tag":{"natural":"tree","noname":"Tamrind Tree"}},"type":"Feature"},
	{"geometry":{"coordinates":[77.579578,12.897122],"type":"Point"},"properties":{"osm_id":"7634014716","tag":{"natural":"tree","noname":"Tamrind Tree"}},"type":"Feature"},
	{"geometry":{"coordinates":[77.579598,12.897305],"type":"Point"},"properties":{"osm_id":"7634014717","tag":{"natural":"tree","noname":"Tamrind Tree"}},"type":"Feature"},
	{"geometry":{"coordinates":[77.580137,12.897456],"type":"Point"},"properties":{"osm_id":"7634014719","tag":{"natural":"tree","noname":"Tamrind Tree"}},"type":"Feature"},
	{"geometry":{"coordinates":[77.579409,12.89705],"type":"Point"},"properties":{"osm_id":"7634014720","tag":{"natural":"tree","noname":"Tamrind Tree"}},"type":"Feature"},
	{"geometry":{"coordinates":[77.579932,12.897328],"type":"Point"},"properties":{"osm_id":"7634014721","tag":{"natural":"tree","noname":"Tamrind Tree"}},"type":"Feature"},
	{"geometry":{"coordinates":[77.579774,12.897408],"type":"Point"},"properties":{"osm_id":"7634014722","tag":{"natural":"tree","noname":"Tamrind Tree"}},"type":"Feature"},
	{"geometry":{"coordinates":[77.579754,12.896891],"type":"Point"},"properties":{"osm_id":"7634031487","tag":{"natural":"tree"}},"type":"Feature"},
	{"geometry":{"coordinates":[77.579782,12.896798],"type":"Point"},"properties":{"osm_id":"7634031501","tag":{"natural":"tree"}},"type":"Feature"}
]
}
