{
"type": "FeatureCollection",
"features": [
	{"geometry":{"coordinates":[15.720925,46.155252],"type":"Point"},"properties":{"osm_id":"5266878552","tag":{"natural":"tree"}},"type":"Feature"},
	{"geometry":{"coordinates":[15.721043,46.155187],"type":"Point"},"properties":{"osm_id":"5266878553","tag":{"natural":"tree"}},"type":"Feature"},
	{"geometry":{"coordinates":[15.721097,46.155163],"type":"Point"},"properties":{"osm_id":"5266878554","tag":{"natural":"tree"}},"type":"Feature"},
	{"geometry":{"coordinates":[15.720862,46.155019],"type":"Point"},"properties":{"osm_id":"5266878555","tag":{"natural":"tree"}},"type":"Feature"},
	{"geometry":{"coordinates":[15.720581,46.154995],"type":"Point"},"properties":{"osm_id":"5266878556","tag":{"natural":"tree"}},"type":"Feature"},
	{"geometry":{"coordinates":[15.720494,46.155014],"type":"Point"},"properties":{"osm_id":"5266878557","tag":{"natural":"tree"}},"type":"Feature"},
	{"geometry":{"coordinates":[15.721067,46.155109],"type":"Point"},"properties":{"osm_id":"5266878558","tag":{"natural":"tree"}},"type":"Feature"},
	{"geometry":{"coordinates":[15.72101,46.155057],"type":"Point"},"properties":{"osm_id":"5266878559","tag":{"natural":"tree"}},"type":"Feature"},
	{"geometry":{"coordinates":[15.721026,46.154936],"type":"Point"},"properties":{"osm_id":"5266878560","tag":{"natural":"tree"}},"type":"Feature"},
	{"geometry":{"coordinates":[15.720372,46.155259],"type":"Point"},"properties":{"osm_id":"5266878827","tag":{"natural":"tree"}},"type":"Feature"},
	{"geometry":{"coordinates":[15.72034,46.155216],"type":"Point"},"properties":{"osm_id":"5266878828","tag":{"natural":"tree"}},"type":"Feature"},
	{"geometry":{"coordinates":[15.720267,46.155201],"type":"Point"},"properties":{"osm_id":"5266878829","tag":{"natural":"tree"}},"type":"Feature"},
	{"geometry":{"coordinates":[15.720232,46.155268],"type":"Point"},"properties":{"osm_id":"5266878830","tag":{"natural":"tree"}},"type":"Feature"},
	{"geometry":{"coordinates":[15.720309,46.155311],"type":"Point"},"properties":{"osm_id":"5266878831","tag":{"natural":"tree"}},"type":"Feature"},
	{"geometry":{"coordinates":[15.664648,46.156032],"type":"Point"},"properties":{"name":"stoljetna lipa","osm_id":"9126476034","tag":{"denotation":"landmark","height":"10","leaf_cycle":"deciduous","leaf_type":"broadleaved","natural":"tree"}},"type":"Feature"}
]
}
