{
"type": "FeatureCollection",
"features": [
	{"geometry":{"coordinates":[-77.919081,43.292247],"type":"Point"},"properties":{"name":"Upstate Bottle Return","osm_id":"7154712089","tag":{"amenity":"recycling","recycling_type":"centre"}},"type":"Feature"}
]
}
