{
"type": "FeatureCollection",
"lastupdate": "2020-08-06T00:00:00Z",
"features": [
	{"geometry":{"coordinates":[-77.91908,43.292246],"type":"Point"},"properties":{"name":"Upstate Bottle Return","osm_id":"7154712089","tag":{"amenity":"recycling","recycling_type":"centre"}},"type":"Feature"}
]
}
