{
"type": "FeatureCollection",
"features": [
	{"geometry":{"coordinates":[-77.897208,34.495722],"type":"Point"},"properties":{"is_in":"Pender,North Carolina,N.C.,NC,USA","name":"Twin Oak","osm_id":"158481415","place":"hamlet","tag":{"gnis:Class":"Populated Place","gnis:County":"Pender","gnis:County_num":"141","gnis:ST_alpha":"NC","gnis:ST_num":"37","gnis:id":"1023026","import_uuid":"bb7269ee-502a-5391-8056-e3ce0e66489c"}},"type":"Feature"}
]
}
