{
"type": "FeatureCollection",
"features": [
	{"geometry":{"coordinates":[-0.602419,40.0289],"type":"Point"},"properties":{"name":"Pino Rey","osm_id":"1713053470","tag":{"natural":"tree","type":"pine"}},"type":"Feature"}
]
}
