{
"type": "FeatureCollection",
"lastupdate": "2020-07-31T00:00:00Z",
"features": [
	{"geometry":{"coordinates":[1.094435,43.616287],"type":"Point"},"properties":{"osm_id":"1390302650","tag":{"amenity":"recycling","recycling_type":"container"}},"type":"Feature"},
	{"geometry":{"coordinates":[1.079319,43.615558],"type":"Point"},"properties":{"osm_id":"1391582642","tag":{"amenity":"recycling","recycling:clothes":"yes","recycling:glass_bottles":"yes","recycling_type":"container","wheelchair":"no"}},"type":"Feature"},
	{"geometry":{"coordinates":[1.131968,43.632202],"type":"Point"},"properties":{"osm_id":"2356876048","tag":{"amenity":"recycling"}},"type":"Feature"},
	{"geometry":{"coordinates":[1.085535,43.610146],"type":"Point"},"properties":{"osm_id":"4075777799","tag":{"amenity":"recycling","recycling:glass_bottles":"yes","recycling_type":"container","wheelchair":"no"}},"type":"Feature"},
	{"geometry":{"coordinates":[1.087311,43.609264],"type":"Point"},"properties":{"osm_id":"4114344091","tag":{"amenity":"recycling","recycling:glass_bottles":"yes","recycling_type":"container","wheelchair":"no"}},"type":"Feature"},
	{"geometry":{"coordinates":[1.071175,43.602757],"type":"Point"},"properties":{"osm_id":"4171974292","tag":{"amenity":"recycling","recycling:glass_bottles":"yes","recycling_type":"container","wheelchair":"no"}},"type":"Feature"},
	{"geometry":{"coordinates":[1.071695,43.603127],"type":"Point"},"properties":{"barrier":"gate","osm_id":"4171974295"},"type":"Feature"},
	{"geometry":{"coordinates":[1.071255,43.602723],"type":"Point"},"properties":{"barrier":"gate","osm_id":"4710346858","tag":{"addr:housenumber":"3","entrance":"main"}},"type":"Feature"},
	{"geometry":{"coordinates":[1.070732,43.602999],"type":"Point"},"properties":{"barrier":"gate","osm_id":"4710349104"},"type":"Feature"},
	{"geometry":{"coordinates":[1.073954,43.61523],"type":"Point"},"properties":{"osm_id":"6203495303","tag":{"amenity":"waste_basket"}},"type":"Feature"},
	{"geometry":{"coordinates":[1.079312,43.610282],"type":"Point"},"properties":{"osm_id":"6528644326","tag":{"amenity":"waste_basket","waste":"trash"}},"type":"Feature"},
	{"geometry":{"coordinates":[1.079556,43.610431],"type":"Point"},"properties":{"osm_id":"6528644329","tag":{"amenity":"waste_basket","waste":"trash"}},"type":"Feature"}
]
}
