{
"type": "FeatureCollection",
"features": [
	{"geometry":{"coordinates":[1.094436,43.616288],"type":"Point"},"properties":{"osm_id":"1390302650","tag":{"amenity":"recycling","recycling_type":"container"}},"type":"Feature"},
	{"geometry":{"coordinates":[1.07932,43.615559],"type":"Point"},"properties":{"osm_id":"1391582642","tag":{"amenity":"recycling","recycling:clothes":"yes","recycling:glass_bottles":"yes","recycling_type":"container","wheelchair":"no"}},"type":"Feature"},
	{"geometry":{"coordinates":[1.131968,43.632203],"type":"Point"},"properties":{"osm_id":"2356876048","tag":{"amenity":"recycling"}},"type":"Feature"},
	{"geometry":{"coordinates":[1.085535,43.610146],"type":"Point"},"properties":{"osm_id":"4075777799","tag":{"amenity":"recycling","recycling:glass_bottles":"yes","recycling_type":"container","wheelchair":"no"}},"type":"Feature"},
	{"geometry":{"coordinates":[1.087311,43.609264],"type":"Point"},"properties":{"osm_id":"4114344091","tag":{"amenity":"recycling","recycling:glass_bottles":"yes","recycling_type":"container","wheelchair":"no"}},"type":"Feature"},
	{"geometry":{"coordinates":[1.071175,43.602758],"type":"Point"},"properties":{"osm_id":"4171974292","tag":{"amenity":"recycling","recycling:glass_bottles":"yes","recycling_type":"container","wheelchair":"no"}},"type":"Feature"},
	{"geometry":{"coordinates":[1.071696,43.603127],"type":"Point"},"properties":{"barrier":"gate","osm_id":"4171974295"},"type":"Feature"},
	{"geometry":{"coordinates":[1.071255,43.602724],"type":"Point"},"properties":{"barrier":"gate","osm_id":"4710346858","tag":{"addr:housenumber":"3","entrance":"main"}},"type":"Feature"},
	{"geometry":{"coordinates":[1.070733,43.603],"type":"Point"},"properties":{"barrier":"gate","osm_id":"4710349104"},"type":"Feature"},
	{"geometry":{"coordinates":[1.073955,43.61523],"type":"Point"},"properties":{"osm_id":"6203495303","tag":{"amenity":"waste_basket"}},"type":"Feature"},
	{"geometry":{"coordinates":[1.079312,43.610283],"type":"Point"},"properties":{"osm_id":"6528644326","tag":{"amenity":"waste_basket","waste":"trash"}},"type":"Feature"},
	{"geometry":{"coordinates":[1.079557,43.610431],"type":"Point"},"properties":{"osm_id":"6528644329","tag":{"amenity":"waste_basket","waste":"trash"}},"type":"Feature"}
]
}
