{
"type": "FeatureCollection",
"lastupdate": "2020-08-06T00:00:00Z",
"features": [
	{"geometry":{"coordinates":[17.667162,40.700366],"type":"Point"},"properties":{"name":"Ebea sud Iaia ecologica","osm_id":"4795141082","tag":{"amenity":"recycling","phone":"+39 0831 991906","recycling_type":"centre"}},"type":"Feature"}
]
}
