{
"type": "FeatureCollection",
"features": [
	{"geometry":{"coordinates":[-110.671012,50.060247],"type":"Point"},"properties":{"name":"Maple Tree","osm_id":"5680772085","tag":{"natural":"tree"}},"type":"Feature"},
	{"geometry":{"coordinates":[-110.671045,50.060196],"type":"Point"},"properties":{"name":"Maple Tree","osm_id":"5680772088","tag":{"natural":"tree"}},"type":"Feature"},
	{"geometry":{"coordinates":[-110.671353,50.060694],"type":"Point"},"properties":{"name":"Bush","osm_id":"5680772655","tag":{"natural":"tree"}},"type":"Feature"},
	{"geometry":{"coordinates":[-110.671172,50.060223],"type":"Point"},"properties":{"name":"Maple Tree","osm_id":"5680772656","tag":{"natural":"tree"}},"type":"Feature"},
	{"geometry":{"coordinates":[-110.671518,50.060773],"type":"Point"},"properties":{"name":"Pine Tree","osm_id":"5680772659","tag":{"natural":"tree"}},"type":"Feature"},
	{"geometry":{"coordinates":[-110.671348,50.060274],"type":"Point"},"properties":{"name":"Maple Tree","osm_id":"5680772733","tag":{"natural":"tree"}},"type":"Feature"},
	{"geometry":{"coordinates":[-110.670945,50.060346],"type":"Point"},"properties":{"name":"Maple Tree","osm_id":"5680772735","tag":{"natural":"tree"}},"type":"Feature"},
	{"geometry":{"coordinates":[-110.670892,50.060434],"type":"Point"},"properties":{"name":"Maple Tree","osm_id":"5680772736","tag":{"natural":"tree"}},"type":"Feature"},
	{"geometry":{"coordinates":[-110.670362,50.059122],"type":"Point"},"properties":{"osm_id":"6410697515","tag":{"natural":"tree"}},"type":"Feature"},
	{"geometry":{"coordinates":[-110.662534,50.020758],"type":"Point"},"properties":{"name":"Pine Tree","osm_id":"6419382654","tag":{"natural":"tree"}},"type":"Feature"}
]
}
