{
"type": "FeatureCollection",
"features": [
	{"geometry":{"coordinates":[-76.7392,40.20947],"type":"Point"},"properties":{"name":"Middletown Woody Waste","osm_id":"3812779501","tag":{"amenity":"recycling","recycling:batteries":"no","recycling:books":"no","recycling:cans":"no","recycling:cardboard":"no","recycling:cartons":"no","recycling:clothes":"no","recycling:electrical_appliances":"no","recycling:glass":"no","recycling:glass_bottles":"no","recycling:green_waste":"yes","recycling:magazines":"no","recycling:newspaper":"no","recycling:paper":"no","recycling:paper_packaging":"no","recycling:plastic":"no","recycling:plastic_bottles":"no","recycling:plastic_packaging":"no","recycling:scrap_metal":"no","recycling:small_appliances":"no","recycling:waste":"no","recycling:wood":"yes"}},"type":"Feature"},
	{"geometry":{"coordinates":[-76.799972,40.20861],"type":"Point"},"properties":{"osm_id":"6504994201","tag":{"amenity":"waste_basket"}},"type":"Feature"},
	{"geometry":{"coordinates":[-76.799617,40.208544],"type":"Point"},"properties":{"osm_id":"6504994202","tag":{"amenity":"waste_basket"}},"type":"Feature"},
	{"geometry":{"coordinates":[-76.799446,40.208236],"type":"Point"},"properties":{"osm_id":"6504994203","tag":{"amenity":"waste_basket"}},"type":"Feature"}
]
}
