{
"type": "FeatureCollection",
"features": [
	{"geometry":{"coordinates":[-76.739201,40.209471],"type":"Point"},"properties":{"name":"Middletown Woody Waste","osm_id":"3812779501","tag":{"amenity":"recycling","recycling:batteries":"no","recycling:books":"no","recycling:cans":"no","recycling:cardboard":"no","recycling:cartons":"no","recycling:clothes":"no","recycling:electrical_appliances":"no","recycling:glass":"no","recycling:glass_bottles":"no","recycling:green_waste":"yes","recycling:magazines":"no","recycling:newspaper":"no","recycling:paper":"no","recycling:paper_packaging":"no","recycling:plastic":"no","recycling:plastic_bottles":"no","recycling:plastic_packaging":"no","recycling:scrap_metal":"no","recycling:small_appliances":"no","recycling:waste":"no","recycling:wood":"yes"}},"type":"Feature"},
	{"geometry":{"coordinates":[-76.763482,40.197933],"type":"Point"},"properties":{"osm_id":"6501232503","tag":{"amenity":"waste_disposal"}},"type":"Feature"},
	{"geometry":{"coordinates":[-76.767648,40.198407],"type":"Point"},"properties":{"osm_id":"6501252365","tag":{"amenity":"waste_disposal"}},"type":"Feature"},
	{"geometry":{"coordinates":[-76.76762,40.198398],"type":"Point"},"properties":{"osm_id":"6501252366","tag":{"amenity":"waste_disposal"}},"type":"Feature"},
	{"geometry":{"coordinates":[-76.799973,40.208611],"type":"Point"},"properties":{"osm_id":"6504994201","tag":{"amenity":"waste_basket"}},"type":"Feature"},
	{"geometry":{"coordinates":[-76.799618,40.208544],"type":"Point"},"properties":{"osm_id":"6504994202","tag":{"amenity":"waste_basket"}},"type":"Feature"},
	{"geometry":{"coordinates":[-76.799447,40.208237],"type":"Point"},"properties":{"osm_id":"6504994203","tag":{"amenity":"waste_basket"}},"type":"Feature"}
]
}
