{
"type": "FeatureCollection",
"features": [
	{"geometry":{"coordinates":[-85.427063,42.775987],"type":"Point"},"properties":{"name":"Downed Trees","osm_id":"3445696099","tag":{"natural":"tree"}},"type":"Feature"},
	{"geometry":{"coordinates":[-85.40023,42.781789],"type":"Point"},"properties":{"name":"Downed Tree","osm_id":"3466173678","tag":{"natural":"tree"}},"type":"Feature"}
]
}
