{
"type": "FeatureCollection",
"features": [
	{"geometry":{"coordinates":[-2.255172,43.291786],"type":"Point"},"properties":{"osm_id":"561149943","tag":{"amenity":"recycling","location":"overground","recycling:cans":"yes","recycling:clothes":"yes","recycling:glass_bottles":"yes","recycling:paper":"yes","recycling_type":"container"}},"type":"Feature"},
	{"geometry":{"coordinates":[-2.255732,43.294645],"type":"Point"},"properties":{"osm_id":"561176322","tag":{"amenity":"recycling","recycling:cans":"yes","recycling:glass":"yes","recycling:paper":"yes"}},"type":"Feature"},
	{"geometry":{"coordinates":[-2.258767,43.296286],"type":"Point"},"properties":{"osm_id":"561197266","tag":{"amenity":"recycling","location":"overground","recycling:cans":"yes","recycling:glass_bottles":"yes","recycling:paper":"yes","recycling_type":"container"}},"type":"Feature"},
	{"geometry":{"coordinates":[-2.255969,43.297016],"type":"Point"},"properties":{"osm_id":"2441953975","tag":{"amenity":"waste_disposal"}},"type":"Feature"},
	{"geometry":{"coordinates":[-2.204891,43.304099],"type":"Point"},"properties":{"osm_id":"5655792431","tag":{"amenity":"waste_basket"}},"type":"Feature"},
	{"geometry":{"coordinates":[-2.250967,43.295794],"type":"Point"},"properties":{"osm_id":"5655792527","tag":{"amenity":"waste_disposal"}},"type":"Feature"},
	{"geometry":{"coordinates":[-2.266083,43.284598],"type":"Point"},"properties":{"osm_id":"5655792826","tag":{"amenity":"waste_disposal"}},"type":"Feature"},
	{"geometry":{"coordinates":[-2.248963,43.296764],"type":"Point"},"properties":{"osm_id":"5655792828","tag":{"amenity":"waste_disposal"}},"type":"Feature"},
	{"geometry":{"coordinates":[-2.205873,43.303455],"type":"Point"},"properties":{"osm_id":"5655792830","tag":{"amenity":"waste_basket"}},"type":"Feature"},
	{"geometry":{"coordinates":[-2.25308,43.293696],"type":"Point"},"properties":{"osm_id":"5655817721","tag":{"amenity":"waste_disposal"}},"type":"Feature"},
	{"geometry":{"coordinates":[-2.201543,43.310316],"type":"Point"},"properties":{"osm_id":"6041372072","tag":{"amenity":"waste_basket"}},"type":"Feature"}
]
}
