{
"type": "FeatureCollection",
"lastupdate": "2020-07-31T00:00:00Z",
"features": [
	{"geometry":{"coordinates":[-2.255172,43.291786],"type":"Point"},"properties":{"osm_id":"561149943","tag":{"amenity":"recycling","location":"overground","recycling:cans":"yes","recycling:clothes":"yes","recycling:glass_bottles":"yes","recycling:paper":"yes","recycling_type":"container"}},"type":"Feature"},
	{"geometry":{"coordinates":[-2.255731,43.294644],"type":"Point"},"properties":{"osm_id":"561176322","tag":{"amenity":"recycling","recycling:cans":"yes","recycling:glass":"yes","recycling:paper":"yes"}},"type":"Feature"},
	{"geometry":{"coordinates":[-2.258767,43.296286],"type":"Point"},"properties":{"osm_id":"561197266","tag":{"amenity":"recycling","location":"overground","recycling:cans":"yes","recycling:glass_bottles":"yes","recycling:paper":"yes","recycling_type":"container"}},"type":"Feature"},
	{"geometry":{"coordinates":[-2.204891,43.304098],"type":"Point"},"properties":{"osm_id":"5655792431","tag":{"amenity":"waste_basket"}},"type":"Feature"},
	{"geometry":{"coordinates":[-2.205872,43.303455],"type":"Point"},"properties":{"osm_id":"5655792830","tag":{"amenity":"waste_basket"}},"type":"Feature"},
	{"geometry":{"coordinates":[-2.201542,43.310316],"type":"Point"},"properties":{"osm_id":"6041372072","tag":{"amenity":"waste_basket"}},"type":"Feature"}
]
}
