{
"type": "FeatureCollection",
"features": [
	{"geometry":{"coordinates":[-86.927707,40.436124],"type":"Point"},"properties":{"osm_id":"5984244203","tag":{"natural":"tree"}},"type":"Feature"},
	{"geometry":{"coordinates":[-86.934717,40.426453],"type":"Point"},"properties":{"name":"hazelnut","osm_id":"9178797758","tag":{"natural":"tree"}},"type":"Feature"}
]
}
