{
"type": "FeatureCollection",
"lastupdate": "2020-07-31T00:00:00Z",
"features": [
	{"geometry":{"coordinates":[-111.084413,50.193888],"type":"Point"},"properties":{"name":"Roadside Turnout","osm_id":"5680702117","tag":{"amenity":"waste_basket"}},"type":"Feature"}
]
}
