{
"type": "FeatureCollection",
"features": [
	{"geometry":{"coordinates":[-5.387822,39.378802],"type":"Point"},"properties":{"name":"palmera","osm_id":"7886732417","tag":{"denotation":"garden","leaf_cycle":"evergreen","natural":"tree"}},"type":"Feature"},
	{"geometry":{"coordinates":[-5.387923,39.378941],"type":"Point"},"properties":{"name":"palmera","osm_id":"7886732418","tag":{"denotation":"garden","leaf_cycle":"evergreen","natural":"tree"}},"type":"Feature"},
	{"geometry":{"coordinates":[-5.387929,39.378998],"type":"Point"},"properties":{"name":"palmera","osm_id":"7886732419","tag":{"denotation":"garden","leaf_cycle":"evergreen","natural":"tree"}},"type":"Feature"}
]
}
