{
"type": "FeatureCollection",
"features": [
	{"geometry":{"coordinates":[-5.387822,39.378801],"type":"Point"},"properties":{"name":"palmera","osm_id":"7886732417","tag":{"denotation":"garden","leaf_cycle":"evergreen","natural":"tree"}},"type":"Feature"},
	{"geometry":{"coordinates":[-5.387922,39.37894],"type":"Point"},"properties":{"name":"palmera","osm_id":"7886732418","tag":{"denotation":"garden","leaf_cycle":"evergreen","natural":"tree"}},"type":"Feature"},
	{"geometry":{"coordinates":[-5.387929,39.378997],"type":"Point"},"properties":{"name":"palmera","osm_id":"7886732419","tag":{"denotation":"garden","leaf_cycle":"evergreen","natural":"tree"}},"type":"Feature"}
]
}
