{
"type": "FeatureCollection",
"features": [
	{"geometry":{"coordinates":[-5.426704,36.957708],"type":"Point"},"properties":{"name":"Chaparro de la Vega","osm_id":"2029478729","tag":{"natural":"tree","wikidata":"Q5764654"}},"type":"Feature"},
	{"geometry":{"coordinates":[-5.439899,36.969575],"type":"Point"},"properties":{"osm_id":"4663729024","tag":{"natural":"tree"}},"type":"Feature"},
	{"geometry":{"coordinates":[-5.439836,36.969535],"type":"Point"},"properties":{"osm_id":"4663729025","tag":{"natural":"tree"}},"type":"Feature"},
	{"geometry":{"coordinates":[-5.439896,36.969487],"type":"Point"},"properties":{"osm_id":"4663729026","tag":{"natural":"tree"}},"type":"Feature"},
	{"geometry":{"coordinates":[-5.439844,36.969488],"type":"Point"},"properties":{"osm_id":"4663729027","tag":{"natural":"tree"}},"type":"Feature"},
	{"geometry":{"coordinates":[-5.442997,36.970394],"type":"Point"},"properties":{"osm_id":"4663743484","tag":{"natural":"tree"}},"type":"Feature"},
	{"geometry":{"coordinates":[-5.442896,36.970424],"type":"Point"},"properties":{"osm_id":"4663743485","tag":{"natural":"tree"}},"type":"Feature"},
	{"geometry":{"coordinates":[-5.442788,36.970508],"type":"Point"},"properties":{"osm_id":"4663743486","tag":{"natural":"tree"}},"type":"Feature"},
	{"geometry":{"coordinates":[-5.442839,36.97045],"type":"Point"},"properties":{"osm_id":"4663743487","tag":{"natural":"tree"}},"type":"Feature"},
	{"geometry":{"coordinates":[-5.442737,36.970825],"type":"Point"},"properties":{"osm_id":"4663743488","tag":{"natural":"tree"}},"type":"Feature"},
	{"geometry":{"coordinates":[-5.44281,36.970752],"type":"Point"},"properties":{"osm_id":"4663744389","tag":{"natural":"tree"}},"type":"Feature"},
	{"geometry":{"coordinates":[-5.442745,36.970655],"type":"Point"},"properties":{"osm_id":"4663744390","tag":{"natural":"tree"}},"type":"Feature"},
	{"geometry":{"coordinates":[-5.442689,36.970739],"type":"Point"},"properties":{"osm_id":"4663744391","tag":{"natural":"tree"}},"type":"Feature"},
	{"geometry":{"coordinates":[-5.442609,36.970713],"type":"Point"},"properties":{"osm_id":"4663744392","tag":{"natural":"tree"}},"type":"Feature"},
	{"geometry":{"coordinates":[-5.442638,36.970653],"type":"Point"},"properties":{"osm_id":"4663744393","tag":{"natural":"tree"}},"type":"Feature"},
	{"geometry":{"coordinates":[-5.442705,36.970568],"type":"Point"},"properties":{"osm_id":"4663744394","tag":{"natural":"tree"}},"type":"Feature"},
	{"geometry":{"coordinates":[-5.442718,36.97046],"type":"Point"},"properties":{"osm_id":"4663744395","tag":{"natural":"tree"}},"type":"Feature"},
	{"geometry":{"coordinates":[-5.442592,36.970362],"type":"Point"},"properties":{"osm_id":"4663744396","tag":{"natural":"tree"}},"type":"Feature"},
	{"geometry":{"coordinates":[-5.442713,36.970336],"type":"Point"},"properties":{"osm_id":"4663744397","tag":{"natural":"tree"}},"type":"Feature"},
	{"geometry":{"coordinates":[-5.442643,36.970424],"type":"Point"},"properties":{"osm_id":"4663744398","tag":{"natural":"tree"}},"type":"Feature"},
	{"geometry":{"coordinates":[-5.442592,36.970531],"type":"Point"},"properties":{"osm_id":"4663744399","tag":{"natural":"tree"}},"type":"Feature"},
	{"geometry":{"coordinates":[-5.442568,36.970604],"type":"Point"},"properties":{"osm_id":"4663744400","tag":{"natural":"tree"}},"type":"Feature"},
	{"geometry":{"coordinates":[-5.44252,36.970664],"type":"Point"},"properties":{"osm_id":"4663744401","tag":{"natural":"tree"}},"type":"Feature"},
	{"geometry":{"coordinates":[-5.442638,36.970917],"type":"Point"},"properties":{"osm_id":"4663744402","tag":{"natural":"tree"}},"type":"Feature"},
	{"geometry":{"coordinates":[-5.443078,36.970336],"type":"Point"},"properties":{"osm_id":"4663744403","tag":{"natural":"tree"}},"type":"Feature"}
]
}
