{
"type": "FeatureCollection",
"features": [
	{"geometry":{"coordinates":[-5.426705,36.957708],"type":"Point"},"properties":{"name":"Chaparro de la Vega","osm_id":"2029478729","tag":{"natural":"tree","wikidata":"Q5764654"}},"type":"Feature"},
	{"geometry":{"coordinates":[-5.4399,36.969576],"type":"Point"},"properties":{"osm_id":"4663729024","tag":{"natural":"tree"}},"type":"Feature"},
	{"geometry":{"coordinates":[-5.439837,36.969535],"type":"Point"},"properties":{"osm_id":"4663729025","tag":{"natural":"tree"}},"type":"Feature"},
	{"geometry":{"coordinates":[-5.439897,36.969487],"type":"Point"},"properties":{"osm_id":"4663729026","tag":{"natural":"tree"}},"type":"Feature"},
	{"geometry":{"coordinates":[-5.439844,36.969489],"type":"Point"},"properties":{"osm_id":"4663729027","tag":{"natural":"tree"}},"type":"Feature"},
	{"geometry":{"coordinates":[-5.442998,36.970395],"type":"Point"},"properties":{"osm_id":"4663743484","tag":{"natural":"tree"}},"type":"Feature"},
	{"geometry":{"coordinates":[-5.442896,36.970425],"type":"Point"},"properties":{"osm_id":"4663743485","tag":{"natural":"tree"}},"type":"Feature"},
	{"geometry":{"coordinates":[-5.442789,36.970508],"type":"Point"},"properties":{"osm_id":"4663743486","tag":{"natural":"tree"}},"type":"Feature"},
	{"geometry":{"coordinates":[-5.44284,36.97045],"type":"Point"},"properties":{"osm_id":"4663743487","tag":{"natural":"tree"}},"type":"Feature"},
	{"geometry":{"coordinates":[-5.442738,36.970825],"type":"Point"},"properties":{"osm_id":"4663743488","tag":{"natural":"tree"}},"type":"Feature"},
	{"geometry":{"coordinates":[-5.44281,36.970752],"type":"Point"},"properties":{"osm_id":"4663744389","tag":{"natural":"tree"}},"type":"Feature"},
	{"geometry":{"coordinates":[-5.442746,36.970656],"type":"Point"},"properties":{"osm_id":"4663744390","tag":{"natural":"tree"}},"type":"Feature"},
	{"geometry":{"coordinates":[-5.442689,36.97074],"type":"Point"},"properties":{"osm_id":"4663744391","tag":{"natural":"tree"}},"type":"Feature"},
	{"geometry":{"coordinates":[-5.442609,36.970714],"type":"Point"},"properties":{"osm_id":"4663744392","tag":{"natural":"tree"}},"type":"Feature"},
	{"geometry":{"coordinates":[-5.442639,36.970654],"type":"Point"},"properties":{"osm_id":"4663744393","tag":{"natural":"tree"}},"type":"Feature"},
	{"geometry":{"coordinates":[-5.442706,36.970568],"type":"Point"},"properties":{"osm_id":"4663744394","tag":{"natural":"tree"}},"type":"Feature"},
	{"geometry":{"coordinates":[-5.442719,36.970461],"type":"Point"},"properties":{"osm_id":"4663744395","tag":{"natural":"tree"}},"type":"Feature"},
	{"geometry":{"coordinates":[-5.442593,36.970362],"type":"Point"},"properties":{"osm_id":"4663744396","tag":{"natural":"tree"}},"type":"Feature"},
	{"geometry":{"coordinates":[-5.442714,36.970337],"type":"Point"},"properties":{"osm_id":"4663744397","tag":{"natural":"tree"}},"type":"Feature"},
	{"geometry":{"coordinates":[-5.442644,36.970425],"type":"Point"},"properties":{"osm_id":"4663744398","tag":{"natural":"tree"}},"type":"Feature"},
	{"geometry":{"coordinates":[-5.442593,36.970532],"type":"Point"},"properties":{"osm_id":"4663744399","tag":{"natural":"tree"}},"type":"Feature"},
	{"geometry":{"coordinates":[-5.442569,36.970605],"type":"Point"},"properties":{"osm_id":"4663744400","tag":{"natural":"tree"}},"type":"Feature"},
	{"geometry":{"coordinates":[-5.442521,36.970665],"type":"Point"},"properties":{"osm_id":"4663744401","tag":{"natural":"tree"}},"type":"Feature"},
	{"geometry":{"coordinates":[-5.442639,36.970917],"type":"Point"},"properties":{"osm_id":"4663744402","tag":{"natural":"tree"}},"type":"Feature"},
	{"geometry":{"coordinates":[-5.443078,36.970337],"type":"Point"},"properties":{"osm_id":"4663744403","tag":{"natural":"tree"}},"type":"Feature"}
]
}
