{
"type": "FeatureCollection",
"features": [
	{"geometry":{"coordinates":[22.183997,50.056996],"type":"Point"},"properties":{"osm_id":"2579678566","tag":{"natural":"tree"}},"type":"Feature"},
	{"geometry":{"coordinates":[22.197,50.047419],"type":"Point"},"properties":{"osm_id":"2839869026","tag":{"natural":"tree"}},"type":"Feature"},
	{"geometry":{"coordinates":[22.234859,50.043264],"type":"Point"},"properties":{"osm_id":"2968531579","tag":{"natural":"tree"}},"type":"Feature"},
	{"geometry":{"coordinates":[22.233636,50.043021],"type":"Point"},"properties":{"osm_id":"3362550537","tag":{"natural":"tree"}},"type":"Feature"},
	{"geometry":{"coordinates":[22.233982,50.043095],"type":"Point"},"properties":{"osm_id":"3362550538","tag":{"natural":"tree"}},"type":"Feature"},
	{"geometry":{"coordinates":[22.224889,50.027951],"type":"Point"},"properties":{"osm_id":"3510093897","tag":{"natural":"tree"}},"type":"Feature"},
	{"geometry":{"coordinates":[22.224691,50.027961],"type":"Point"},"properties":{"osm_id":"3510093898","tag":{"natural":"tree"}},"type":"Feature"},
	{"geometry":{"coordinates":[22.224746,50.027962],"type":"Point"},"properties":{"osm_id":"3510093899","tag":{"natural":"tree"}},"type":"Feature"},
	{"geometry":{"coordinates":[22.224543,50.02798],"type":"Point"},"properties":{"osm_id":"3510093900","tag":{"natural":"tree"}},"type":"Feature"},
	{"geometry":{"coordinates":[22.224349,50.027991],"type":"Point"},"properties":{"osm_id":"3510093901","tag":{"natural":"tree"}},"type":"Feature"},
	{"geometry":{"coordinates":[22.224207,50.028004],"type":"Point"},"properties":{"osm_id":"3510093903","tag":{"natural":"tree"}},"type":"Feature"},
	{"geometry":{"coordinates":[22.224066,50.028017],"type":"Point"},"properties":{"osm_id":"3510093904","tag":{"natural":"tree"}},"type":"Feature"},
	{"geometry":{"coordinates":[22.223726,50.02804],"type":"Point"},"properties":{"osm_id":"3510093906","tag":{"natural":"tree"}},"type":"Feature"},
	{"geometry":{"coordinates":[22.223521,50.028051],"type":"Point"},"properties":{"osm_id":"3510093908","tag":{"natural":"tree"}},"type":"Feature"},
	{"geometry":{"coordinates":[22.223377,50.028064],"type":"Point"},"properties":{"osm_id":"3510093909","tag":{"natural":"tree"}},"type":"Feature"},
	{"geometry":{"coordinates":[22.223238,50.028075],"type":"Point"},"properties":{"osm_id":"3510093910","tag":{"natural":"tree"}},"type":"Feature"},
	{"geometry":{"coordinates":[22.223041,50.028087],"type":"Point"},"properties":{"osm_id":"3510093911","tag":{"natural":"tree"}},"type":"Feature"},
	{"geometry":{"coordinates":[22.222695,50.028108],"type":"Point"},"properties":{"osm_id":"3510093912","tag":{"natural":"tree"}},"type":"Feature"},
	{"geometry":{"coordinates":[22.222564,50.028121],"type":"Point"},"properties":{"osm_id":"3510093913","tag":{"natural":"tree"}},"type":"Feature"},
	{"geometry":{"coordinates":[22.222416,50.028131],"type":"Point"},"properties":{"osm_id":"3510093914","tag":{"natural":"tree"}},"type":"Feature"},
	{"geometry":{"coordinates":[22.181645,50.019682],"type":"Point"},"properties":{"name":"Pomnik przyrody","osm_id":"4005802328","tag":{"denotation":"natural_monument","monument":"yes","natural":"tree","protected":"yes"}},"type":"Feature"},
	{"geometry":{"coordinates":[22.15823,50.036099],"type":"Point"},"properties":{"name":"Pomnik przyrody","osm_id":"4005802329","tag":{"denotation":"natural_monument","monument":"yes","natural":"tree","protected":"yes"}},"type":"Feature"},
	{"geometry":{"coordinates":[22.180727,50.037621],"type":"Point"},"properties":{"name":"Pomnik przyrody","osm_id":"4005802330","tag":{"denotation":"natural_monument","monument":"yes","natural":"tree","protected":"yes"}},"type":"Feature"}
]
}
