{
"type": "FeatureCollection",
"features": [
	{"geometry":{"coordinates":[22.194876,49.910581],"type":"Point"},"properties":{"name":"Pomnik Przyrody","osm_id":"4001622019","tag":{"denotation":"natural_monument","monument":"yes","natural":"tree"}},"type":"Feature"},
	{"geometry":{"coordinates":[22.160132,49.923958],"type":"Point"},"properties":{"name":"Pomnik Przyrody","osm_id":"4001622021","tag":{"denotation":"natural_monument","monument":"yes","natural":"tree"}},"type":"Feature"},
	{"geometry":{"coordinates":[22.160592,49.924019],"type":"Point"},"properties":{"name":"Pomnik Przyrody","osm_id":"4001622022","tag":{"denotation":"natural_monument","monument":"yes","natural":"tree"}},"type":"Feature"},
	{"geometry":{"coordinates":[22.160257,49.924092],"type":"Point"},"properties":{"name":"Pomnik Przyrody","osm_id":"4001622023","tag":{"denotation":"natural_monument","monument":"yes","natural":"tree"}},"type":"Feature"},
	{"geometry":{"coordinates":[22.160706,49.924204],"type":"Point"},"properties":{"name":"Pomnik Przyrody","osm_id":"4001622024","tag":{"denotation":"natural_monument","monument":"yes","natural":"tree"}},"type":"Feature"},
	{"geometry":{"coordinates":[22.160852,49.924223],"type":"Point"},"properties":{"name":"Pomnik Przyrody","osm_id":"4001622025","tag":{"denotation":"natural_monument","monument":"yes","natural":"tree"}},"type":"Feature"},
	{"geometry":{"coordinates":[22.158853,49.924485],"type":"Point"},"properties":{"name":"Pomnik Przyrody","osm_id":"4001622026","tag":{"denotation":"natural_monument","monument":"yes","natural":"tree"}},"type":"Feature"},
	{"geometry":{"coordinates":[22.158793,49.92457],"type":"Point"},"properties":{"name":"Pomnik Przyrody","osm_id":"4001622027","tag":{"denotation":"natural_monument","monument":"yes","natural":"tree"}},"type":"Feature"}
]
}
