{
"type": "FeatureCollection",
"features": [
	{"geometry":{"coordinates":[22.204583,49.358431],"type":"Point"},"properties":{"name":"Szumny","osm_id":"4024572228","tag":{"denotation":"natural_monument","gid":"95414","kodinspire":"PL.ZIPOP.1393.PP.1817073.1533","monument":"yes","natural":"tree","protected":"yes"}},"type":"Feature"},
	{"geometry":{"coordinates":[22.203185,49.36256],"type":"Point"},"properties":{"name":"Ignacy","osm_id":"4024572229","tag":{"denotation":"natural_monument","gid":"95417","kodinspire":"PL.ZIPOP.1393.PP.1817073.1536","monument":"yes","natural":"tree","protected":"yes"}},"type":"Feature"},
	{"geometry":{"coordinates":[22.202557,49.36261],"type":"Point"},"properties":{"name":"Aleksander","osm_id":"4024572230","tag":{"denotation":"natural_monument","gid":"95415","kodinspire":"PL.ZIPOP.1393.PP.1817073.1534","monument":"yes","natural":"tree","protected":"yes"}},"type":"Feature"},
	{"geometry":{"coordinates":[22.203,49.362683],"type":"Point"},"properties":{"name":"Ksawery","osm_id":"4024572231","tag":{"denotation":"natural_monument","gid":"95416","kodinspire":"PL.ZIPOP.1393.PP.1817073.1535","monument":"yes","natural":"tree","protected":"yes"}},"type":"Feature"}
]
}
