{
"type": "FeatureCollection",
"features": [
	{"geometry":{"coordinates":[13.093277,47.32173],"type":"Point"},"properties":{"name":"Naturdenkmal","osm_id":"1800973281","tag":{"historic":"memorial","natural":"tree"}},"type":"Feature"},
	{"geometry":{"coordinates":[13.034581,47.334383],"type":"Point"},"properties":{"osm_id":"1860489517","tag":{"natural":"tree"}},"type":"Feature"},
	{"geometry":{"coordinates":[13.044549,47.314126],"type":"Point"},"properties":{"osm_id":"3979593221","tag":{"natural":"tree"}},"type":"Feature"},
	{"geometry":{"coordinates":[13.044489,47.313754],"type":"Point"},"properties":{"osm_id":"5316404579","tag":{"natural":"tree"}},"type":"Feature"},
	{"geometry":{"coordinates":[13.044557,47.3138],"type":"Point"},"properties":{"osm_id":"5316404580","tag":{"natural":"tree"}},"type":"Feature"},
	{"geometry":{"coordinates":[13.044618,47.313841],"type":"Point"},"properties":{"osm_id":"5316404581","tag":{"natural":"tree"}},"type":"Feature"},
	{"geometry":{"coordinates":[13.044683,47.313885],"type":"Point"},"properties":{"osm_id":"5316404582","tag":{"natural":"tree"}},"type":"Feature"},
	{"geometry":{"coordinates":[13.043382,47.313489],"type":"Point"},"properties":{"osm_id":"5316404583","tag":{"natural":"tree"}},"type":"Feature"},
	{"geometry":{"coordinates":[13.044964,47.314086],"type":"Point"},"properties":{"osm_id":"5316404585","tag":{"natural":"tree"}},"type":"Feature"},
	{"geometry":{"coordinates":[13.045168,47.314222],"type":"Point"},"properties":{"osm_id":"5316404586","tag":{"natural":"tree"}},"type":"Feature"},
	{"geometry":{"coordinates":[13.045296,47.314307],"type":"Point"},"properties":{"osm_id":"5316404587","tag":{"natural":"tree"}},"type":"Feature"},
	{"geometry":{"coordinates":[13.045543,47.31444],"type":"Point"},"properties":{"osm_id":"5316404588","tag":{"natural":"tree"}},"type":"Feature"},
	{"geometry":{"coordinates":[13.045394,47.314371],"type":"Point"},"properties":{"osm_id":"5316404589","tag":{"natural":"tree"}},"type":"Feature"},
	{"geometry":{"coordinates":[13.039572,47.309197],"type":"Point"},"properties":{"osm_id":"5700055090","tag":{"natural":"tree"}},"type":"Feature"},
	{"geometry":{"coordinates":[13.039697,47.310796],"type":"Point"},"properties":{"osm_id":"5700055092","tag":{"natural":"tree"}},"type":"Feature"},
	{"geometry":{"coordinates":[13.043938,47.313821],"type":"Point"},"properties":{"osm_id":"7321381271","tag":{"natural":"tree"}},"type":"Feature"},
	{"geometry":{"coordinates":[13.0439,47.313872],"type":"Point"},"properties":{"osm_id":"7321381272","tag":{"natural":"tree"}},"type":"Feature"},
	{"geometry":{"coordinates":[13.043852,47.313915],"type":"Point"},"properties":{"osm_id":"7321381273","tag":{"natural":"tree"}},"type":"Feature"},
	{"geometry":{"coordinates":[13.043809,47.313917],"type":"Point"},"properties":{"osm_id":"7321381274","tag":{"natural":"tree"}},"type":"Feature"},
	{"geometry":{"coordinates":[13.043838,47.313965],"type":"Point"},"properties":{"osm_id":"7321381275","tag":{"natural":"tree"}},"type":"Feature"},
	{"geometry":{"coordinates":[13.044275,47.313538],"type":"Point"},"properties":{"osm_id":"7321411227","tag":{"natural":"tree"}},"type":"Feature"},
	{"geometry":{"coordinates":[13.043842,47.313953],"type":"Point"},"properties":{"osm_id":"7321446023","tag":{"natural":"tree"}},"type":"Feature"},
	{"geometry":{"coordinates":[13.043845,47.313943],"type":"Point"},"properties":{"osm_id":"7321446024","tag":{"natural":"tree"}},"type":"Feature"},
	{"geometry":{"coordinates":[13.043069,47.313364],"type":"Point"},"properties":{"osm_id":"7321446032","tag":{"natural":"tree"}},"type":"Feature"},
	{"geometry":{"coordinates":[13.043138,47.313403],"type":"Point"},"properties":{"osm_id":"7321446033","tag":{"natural":"tree"}},"type":"Feature"},
	{"geometry":{"coordinates":[13.04322,47.313451],"type":"Point"},"properties":{"osm_id":"7321446034","tag":{"natural":"tree"}},"type":"Feature"},
	{"geometry":{"coordinates":[13.043581,47.313545],"type":"Point"},"properties":{"osm_id":"7321446035","tag":{"natural":"tree"}},"type":"Feature"},
	{"geometry":{"coordinates":[13.043676,47.313576],"type":"Point"},"properties":{"osm_id":"7321446036","tag":{"natural":"tree"}},"type":"Feature"},
	{"geometry":{"coordinates":[13.043789,47.313604],"type":"Point"},"properties":{"osm_id":"7321446037","tag":{"natural":"tree"}},"type":"Feature"},
	{"geometry":{"coordinates":[13.043902,47.313627],"type":"Point"},"properties":{"osm_id":"7321446038","tag":{"natural":"tree"}},"type":"Feature"}
]
}
