{
"type": "FeatureCollection",
"features": [
	{"geometry":{"coordinates":[44.943471,34.517586],"type":"Point"},"properties":{"name":"BaranQitar","osm_id":"7730943884","ref":"BaranQitar","tag":{"natural":"tree"}},"type":"Feature"},
	{"geometry":{"coordinates":[44.936878,34.522374],"type":"Point"},"properties":{"name":"BaranQitar","osm_id":"7730964101","ref":"BaranQitar","tag":{"natural":"tree"}},"type":"Feature"}
]
}
