{
"type": "FeatureCollection",
"lastupdate": "2020-08-02T00:00:00Z",
"features": [
	{"geometry":{"coordinates":[-0.790224,38.478904],"type":"Point"},"properties":{"name":"RSU","osm_id":"367634878","ref":"22","tag":{"amenity":"recycling"}},"type":"Feature"},
	{"geometry":{"coordinates":[-0.789727,38.479054],"type":"Point"},"properties":{"name":"RSU","osm_id":"367634890","ref":"23","tag":{"amenity":"recycling"}},"type":"Feature"},
	{"geometry":{"coordinates":[-0.78921,38.479224],"type":"Point"},"properties":{"name":"RSU","osm_id":"367634903","ref":"24","tag":{"amenity":"recycling"}},"type":"Feature"},
	{"geometry":{"coordinates":[-0.790858,38.47877],"type":"Point"},"properties":{"name":"RSU","osm_id":"367634915","ref":"21","tag":{"amenity":"recycling"}},"type":"Feature"},
	{"geometry":{"coordinates":[-0.79085,38.478757],"type":"Point"},"properties":{"name":"Vidrio","osm_id":"367634929","ref":"2","tag":{"amenity":"recycling","recycling:glass":"yes"}},"type":"Feature"},
	{"geometry":{"coordinates":[-0.78867,38.479385],"type":"Point"},"properties":{"name":"RSU","osm_id":"367634942","ref":"25","tag":{"amenity":"recycling"}},"type":"Feature"},
	{"geometry":{"coordinates":[-0.762065,38.477902],"type":"Point"},"properties":{"osm_id":"4184490072","tag":{"amenity":"recycling","recycling:waste":"yes","recycling_type":"container"}},"type":"Feature"},
	{"geometry":{"coordinates":[-0.789591,38.473162],"type":"Point"},"properties":{"osm_id":"4692517326","tag":{"amenity":"recycling","recycling_type":"container"}},"type":"Feature"},
	{"geometry":{"coordinates":[-0.790472,38.476792],"type":"Point"},"properties":{"osm_id":"4692530942","tag":{"amenity":"recycling","operator":"Vidrio, Carton y Plastico","recycling:cardboard":"yes","recycling:glass_bottles":"yes","recycling:plastic":"yes","recycling_type":"container"}},"type":"Feature"},
	{"geometry":{"coordinates":[-0.788518,38.477538],"type":"Point"},"properties":{"osm_id":"4692530944","tag":{"amenity":"recycling","operator":"Vidrio, Carton y Plastico","recycling:cardboard":"yes","recycling:glass_bottles":"yes","recycling:plastic":"yes","recycling_type":"container"}},"type":"Feature"},
	{"geometry":{"coordinates":[-0.787285,38.477892],"type":"Point"},"properties":{"osm_id":"4692530945","tag":{"amenity":"recycling","operator":"Pl\u00e1stico y Cart\u00f3n","recycling:cardboard":"yes","recycling:plastic":"yes","recycling_type":"container"}},"type":"Feature"},
	{"geometry":{"coordinates":[-0.789013,38.478488],"type":"Point"},"properties":{"osm_id":"4692530947","tag":{"amenity":"recycling","operator":"Vidrio, Carton y Plastico","recycling:cardboard":"yes","recycling:glass_bottles":"yes","recycling:plastic":"yes","recycling_type":"container"}},"type":"Feature"},
	{"geometry":{"coordinates":[-0.789864,38.4782],"type":"Point"},"properties":{"osm_id":"4692530949","tag":{"amenity":"recycling","operator":"Ropas","recycling:clothes":"yes","recycling_type":"container"}},"type":"Feature"},
	{"geometry":{"coordinates":[-0.789684,38.479128],"type":"Point"},"properties":{"osm_id":"4692530968","tag":{"amenity":"recycling","operator":"Vidrio","recycling:glass_bottles":"yes","recycling_type":"container"}},"type":"Feature"},
	{"geometry":{"coordinates":[-0.786401,38.478331],"type":"Point"},"properties":{"osm_id":"4692530970","tag":{"amenity":"recycling","operator":"Vidrio, Cart\u00f3n y Pl\u00e1stico","recycling:cardboard":"yes","recycling:glass_bottles":"yes","recycling:plastic":"yes","recycling_type":"container"}},"type":"Feature"},
	{"geometry":{"coordinates":[-0.785886,38.478094],"type":"Point"},"properties":{"osm_id":"4692530971","tag":{"amenity":"recycling","operator":"Vidrio","recycling:glass_bottles":"yes","recycling_type":"container"}},"type":"Feature"},
	{"geometry":{"coordinates":[-0.786169,38.479339],"type":"Point"},"properties":{"osm_id":"4692530977","tag":{"amenity":"recycling","operator":"Vidrio, Carton y Plastico","recycling:cardboard":"yes","recycling:glass_bottles":"yes","recycling:plastic":"yes","recycling_type":"container"}},"type":"Feature"},
	{"geometry":{"coordinates":[-0.787526,38.47716],"type":"Point"},"properties":{"osm_id":"4692530988","tag":{"amenity":"recycling","operator":"Vidrio","recycling:glass_bottles":"yes","recycling_type":"container"}},"type":"Feature"},
	{"geometry":{"coordinates":[-0.788522,38.476828],"type":"Point"},"properties":{"osm_id":"4692531494","tag":{"amenity":"recycling","operator":"Vidrio","recycling:glass_bottles":"yes","recycling_type":"container"}},"type":"Feature"},
	{"geometry":{"coordinates":[-0.788801,38.478615],"type":"Point"},"properties":{"osm_id":"4708301255","tag":{"amenity":"waste_basket"}},"type":"Feature"},
	{"geometry":{"coordinates":[-0.788278,38.478688],"type":"Point"},"properties":{"osm_id":"4708301256","tag":{"amenity":"waste_basket"}},"type":"Feature"},
	{"geometry":{"coordinates":[-0.787901,38.478802],"type":"Point"},"properties":{"osm_id":"4708309892","tag":{"amenity":"waste_basket"}},"type":"Feature"}
]
}
