{
"type": "FeatureCollection",
"features": [
	{"geometry":{"coordinates":[30.84951,-0.833352],"type":"Point"},"properties":{"name":"waste pit","osm_id":"6285467250","tag":{"addr:block":"Kahirimbi C","addr:district":"Isingiro","addr:settlement":"Nakivale","addr:subcamp":"Juru","addr:village":"Village C","addr:zone":"Kahirimbi","amenity":"waste_disposal","fee":"no","lit":"unlit","operator:type":"community","source:form":"v_4.0.5","waste":"Rubbish"}},"type":"Feature"},
	{"geometry":{"coordinates":[30.84951,-0.833352],"type":"Point"},"properties":{"name":"Waste pit","osm_id":"6288605113","tag":{"addr:block":"Kahirimbi C","addr:district":"Isingiro","addr:settlement":"Nakivale","addr:subcamp":"Juru","addr:village":"Village C","addr:zone":"Kahirimbi","amenity":"waste_disposal","fee":"no","lit":"lit","monitored":"yes","monitored_by":"Kahirimbi Primary School","operator:type":"community","start_date":"2006-02-01","waste":"Rubbish"}},"type":"Feature"}
]
}
