{
"type": "FeatureCollection",
"lastupdate": "2020-08-03T00:00:00Z",
"features": [
	{"geometry":{"coordinates":[-3.963545,57.773971],"type":"Point"},"properties":{"name":"Fearn Hall","osm_id":"1416255612","tag":{"amenity":"recycling"}},"type":"Feature"}
]
}
