{
"type": "FeatureCollection",
"features": [
	{"geometry":{"coordinates":[-3.963546,57.773971],"type":"Point"},"properties":{"name":"Fearn Hall","osm_id":"1416255612","tag":{"amenity":"recycling"}},"type":"Feature"}
]
}
