{
"type": "FeatureCollection",
"features": [
	{"geometry":{"coordinates":[-3.997292,48.103003],"type":"Point"},"properties":{"osm_id":"346983490","tag":{"amenity":"recycling","recycling:cardboard":"yes","recycling:glass_bottles":"yes","recycling:paper":"yes","recycling:plastic_bottles":"yes","recycling_type":"container"}},"type":"Feature"},
	{"geometry":{"coordinates":[-4.00739,48.105761],"type":"Point"},"properties":{"osm_id":"346983496","tag":{"amenity":"recycling","recycling_type":"container"}},"type":"Feature"},
	{"geometry":{"coordinates":[-3.990904,48.103628],"type":"Point"},"properties":{"osm_id":"479098949","tag":{"amenity":"recycling","recycling_type":"container"}},"type":"Feature"},
	{"geometry":{"coordinates":[-3.99715,48.096865],"type":"Point"},"properties":{"osm_id":"496505073","tag":{"amenity":"recycling","recycling:plastic_bottles":"yes","recycling_type":"container"}},"type":"Feature"},
	{"geometry":{"coordinates":[-3.997037,48.096873],"type":"Point"},"properties":{"osm_id":"496505074","tag":{"amenity":"recycling","recycling:glass_bottles":"yes","recycling_type":"container"}},"type":"Feature"},
	{"geometry":{"coordinates":[-3.996896,48.09688],"type":"Point"},"properties":{"osm_id":"496505075","tag":{"amenity":"recycling","operator":"Abi29","recycling:clothes":"yes","recycling_type":"container"}},"type":"Feature"},
	{"geometry":{"coordinates":[-3.996975,48.096878],"type":"Point"},"properties":{"osm_id":"496505076","tag":{"amenity":"recycling","recycling:cardboard":"yes","recycling:paper":"yes","recycling_type":"container"}},"type":"Feature"},
	{"geometry":{"coordinates":[-3.974672,48.104165],"type":"Point"},"properties":{"osm_id":"1097094309","tag":{"amenity":"recycling","recycling:glass":"yes","recycling_type":"container"}},"type":"Feature"},
	{"geometry":{"coordinates":[-3.976463,48.062789],"type":"Point"},"properties":{"osm_id":"1428376238","tag":{"amenity":"recycling"}},"type":"Feature"},
	{"geometry":{"coordinates":[-4.008415,48.099733],"type":"Point"},"properties":{"name":"Clos de Lannec'huen","osm_id":"3150771923","tag":{"amenity":"recycling","recycling:beverage_cartons":"yes","recycling:cans":"yes","recycling:paper":"yes","recycling:plastic_bottles":"yes","recycling_type":"container"}},"type":"Feature"},
	{"geometry":{"coordinates":[-4.00843,48.099751],"type":"Point"},"properties":{"name":"Clos de Lannec'huen","osm_id":"3150771924","tag":{"amenity":"recycling","recycling:glass":"yes","recycling_type":"container"}},"type":"Feature"},
	{"geometry":{"coordinates":[-4.002186,48.106481],"type":"Point"},"properties":{"name":"Rue Haute","osm_id":"3150771926","tag":{"amenity":"recycling","recycling:glass":"yes","recycling_type":"container"}},"type":"Feature"},
	{"geometry":{"coordinates":[-4.002138,48.106495],"type":"Point"},"properties":{"name":"Rue Haute","osm_id":"3150771927","tag":{"amenity":"recycling","recycling:beverage_cartons":"yes","recycling:cans":"yes","recycling:paper":"yes","recycling:plastic_bottles":"yes","recycling_type":"container"}},"type":"Feature"},
	{"geometry":{"coordinates":[-4.007402,48.103131],"type":"Point"},"properties":{"osm_id":"3179364290","tag":{"amenity":"recycling","recycling:glass":"yes","recycling_type":"container"}},"type":"Feature"},
	{"geometry":{"coordinates":[-4.007399,48.103153],"type":"Point"},"properties":{"osm_id":"3179364291","tag":{"amenity":"recycling","recycling:beverage_cartons":"yes","recycling:cans":"yes","recycling:paper":"yes","recycling:plastic_bottles":"yes","recycling_type":"container"}},"type":"Feature"},
	{"geometry":{"coordinates":[-4.006051,48.104851],"type":"Point"},"properties":{"osm_id":"7343165220","tag":{"amenity":"waste_basket","waste":"trash"}},"type":"Feature"},
	{"geometry":{"coordinates":[-4.005448,48.099747],"type":"Point"},"properties":{"osm_id":"7343165284","tag":{"amenity":"recycling","recycling:beverage_cartons":"yes","recycling:cans":"yes","recycling:paper":"yes","recycling:plastic_bottles":"yes","recycling_type":"container"}},"type":"Feature"},
	{"geometry":{"coordinates":[-4.005483,48.099748],"type":"Point"},"properties":{"osm_id":"7343165285","tag":{"amenity":"recycling","recycling:glass":"yes","recycling_type":"container"}},"type":"Feature"},
	{"geometry":{"coordinates":[-3.997025,48.099246],"type":"Point"},"properties":{"osm_id":"7487303649","tag":{"amenity":"waste_basket","waste":"trash"}},"type":"Feature"}
]
}
