{
"type": "FeatureCollection",
"features": [
	{"geometry":{"coordinates":[-98.437259,19.276061],"type":"Point"},"properties":{"name":"El Chamizal","osm_id":"5277852976","tag":{"natural":"tree"}},"type":"Feature"}
]
}
