{
"type": "FeatureCollection",
"features": [
	{"geometry":{"coordinates":[-98.43726,19.276062],"type":"Point"},"properties":{"name":"El Chamizal","osm_id":"5277852976","tag":{"natural":"tree"}},"type":"Feature"}
]
}
