{
"type": "FeatureCollection",
"lastupdate": "2020-07-31T00:00:00Z",
"features": [
	{"geometry":{"coordinates":[7.621343,52.25718],"type":"Point"},"properties":{"osm_id":"360887154","tag":{"amenity":"recycling","location":"overground","recycling:glass":"yes","recycling_type":"container"}},"type":"Feature"},
	{"geometry":{"coordinates":[7.644559,52.266721],"type":"Point"},"properties":{"osm_id":"6653253601","tag":{"amenity":"waste_basket"}},"type":"Feature"}
]
}
