{
"type": "FeatureCollection",
"features": [
	{"geometry":{"coordinates":[7.641041,51.020065],"type":"Point"},"properties":{"osm_id":"277747115","tag":{"amenity":"recycling","location":"overground","recycling:clothes":"yes","recycling:glass":"yes","recycling_type":"container"}},"type":"Feature"},
	{"geometry":{"coordinates":[7.640273,51.033583],"type":"Point"},"properties":{"osm_id":"593875287","tag":{"amenity":"recycling"}},"type":"Feature"},
	{"geometry":{"coordinates":[7.644572,51.016877],"type":"Point"},"properties":{"osm_id":"662294924","tag":{"amenity":"recycling","recycling:glass":"yes","recycling_type":"container"}},"type":"Feature"},
	{"geometry":{"coordinates":[7.642128,51.037996],"type":"Point"},"properties":{"osm_id":"2915651334","tag":{"amenity":"recycling","location":"overground","recycling:clothes":"yes","recycling:glass":"yes","recycling_type":"container"}},"type":"Feature"},
	{"geometry":{"coordinates":[7.608938,51.017802],"type":"Point"},"properties":{"osm_id":"2986152417","tag":{"amenity":"waste_basket"}},"type":"Feature"},
	{"geometry":{"coordinates":[7.628754,51.055211],"type":"Point"},"properties":{"osm_id":"4002962979","tag":{"amenity":"recycling","recycling:cans":"no","recycling:clothes":"yes","recycling:glass":"no","recycling:glass_bottles":"yes","recycling:paper":"no","recycling:plastic":"no","recycling_type":"container"}},"type":"Feature"},
	{"geometry":{"coordinates":[7.605019,51.024626],"type":"Point"},"properties":{"osm_id":"4397480959","tag":{"amenity":"recycling","recycling:clothes":"yes","recycling_type":"container"}},"type":"Feature"},
	{"geometry":{"coordinates":[7.60089,51.02793],"type":"Point"},"properties":{"osm_id":"4397480961","tag":{"amenity":"recycling","recycling:clothes":"yes","recycling:glass":"yes","recycling_type":"container"}},"type":"Feature"},
	{"geometry":{"coordinates":[7.599775,51.027288],"type":"Point"},"properties":{"osm_id":"4546661151","tag":{"amenity":"waste_basket"}},"type":"Feature"},
	{"geometry":{"coordinates":[7.614348,51.024519],"type":"Point"},"properties":{"osm_id":"4589575378","tag":{"amenity":"recycling","recycling:clothes":"yes","recycling_type":"container"}},"type":"Feature"},
	{"geometry":{"coordinates":[7.613862,51.023947],"type":"Point"},"properties":{"osm_id":"4589845533","tag":{"amenity":"waste_basket"}},"type":"Feature"},
	{"geometry":{"coordinates":[7.561269,51.020731],"type":"Point"},"properties":{"osm_id":"4758387183","tag":{"amenity":"recycling","operator":"Deutsches Rotes Kreuz","recycling:clothes":"yes","recycling_type":"container"}},"type":"Feature"},
	{"geometry":{"coordinates":[7.580955,51.035296],"type":"Point"},"properties":{"osm_id":"5294082172","tag":{"amenity":"waste_disposal"}},"type":"Feature"},
	{"geometry":{"coordinates":[7.624622,51.06778],"type":"Point"},"properties":{"osm_id":"5571454125","tag":{"amenity":"waste_basket","waste":"trash"}},"type":"Feature"},
	{"geometry":{"coordinates":[7.629106,51.055555],"type":"Point"},"properties":{"osm_id":"5571454133","tag":{"amenity":"waste_basket","waste":"trash"}},"type":"Feature"},
	{"geometry":{"coordinates":[7.629061,51.055491],"type":"Point"},"properties":{"osm_id":"5571454134","tag":{"amenity":"waste_basket","waste":"trash"}},"type":"Feature"},
	{"geometry":{"coordinates":[7.635863,51.038191],"type":"Point"},"properties":{"osm_id":"5599074986","tag":{"amenity":"waste_basket","waste":"trash"}},"type":"Feature"},
	{"geometry":{"coordinates":[7.642727,51.041859],"type":"Point"},"properties":{"osm_id":"5599074988","tag":{"amenity":"waste_basket","waste":"trash"}},"type":"Feature"},
	{"geometry":{"coordinates":[7.63416,51.036209],"type":"Point"},"properties":{"osm_id":"5599131424","tag":{"amenity":"waste_basket","waste":"trash"}},"type":"Feature"},
	{"geometry":{"coordinates":[7.580426,51.049328],"type":"Point"},"properties":{"osm_id":"5716489284","tag":{"amenity":"waste_basket"}},"type":"Feature"},
	{"geometry":{"coordinates":[7.580159,51.049176],"type":"Point"},"properties":{"osm_id":"5716489285","tag":{"amenity":"waste_basket"}},"type":"Feature"}
]
}
