{
"type": "FeatureCollection",
"features": [
	{"geometry":{"coordinates":[7.64104,51.020065],"type":"Point"},"properties":{"osm_id":"277747115","tag":{"amenity":"recycling","location":"overground","recycling:clothes":"yes","recycling:glass":"yes","recycling_type":"container"}},"type":"Feature"},
	{"geometry":{"coordinates":[7.640272,51.033582],"type":"Point"},"properties":{"osm_id":"593875287","tag":{"amenity":"recycling"}},"type":"Feature"},
	{"geometry":{"coordinates":[7.644571,51.016877],"type":"Point"},"properties":{"osm_id":"662294924","tag":{"amenity":"recycling","recycling:glass":"yes","recycling_type":"container"}},"type":"Feature"},
	{"geometry":{"coordinates":[7.642127,51.037995],"type":"Point"},"properties":{"osm_id":"2915651334","tag":{"amenity":"recycling","location":"overground","recycling:clothes":"yes","recycling:glass":"yes","recycling_type":"container"}},"type":"Feature"},
	{"geometry":{"coordinates":[7.608937,51.017801],"type":"Point"},"properties":{"osm_id":"2986152417","tag":{"amenity":"waste_basket","check_date":"2021-06-16"}},"type":"Feature"},
	{"geometry":{"coordinates":[7.628753,51.05521],"type":"Point"},"properties":{"osm_id":"4002962979","tag":{"amenity":"recycling","recycling:cans":"no","recycling:clothes":"yes","recycling:glass":"no","recycling:glass_bottles":"yes","recycling:paper":"no","recycling:plastic":"no","recycling_type":"container"}},"type":"Feature"},
	{"geometry":{"coordinates":[7.605019,51.024625],"type":"Point"},"properties":{"osm_id":"4397480959","tag":{"amenity":"recycling","recycling:clothes":"yes","recycling_type":"container"}},"type":"Feature"},
	{"geometry":{"coordinates":[7.600889,51.02793],"type":"Point"},"properties":{"osm_id":"4397480961","tag":{"amenity":"recycling","recycling:clothes":"yes","recycling:glass":"yes","recycling_type":"container"}},"type":"Feature"},
	{"geometry":{"coordinates":[7.599775,51.027288],"type":"Point"},"properties":{"osm_id":"4546661151","tag":{"amenity":"waste_basket"}},"type":"Feature"},
	{"geometry":{"coordinates":[7.614348,51.024519],"type":"Point"},"properties":{"osm_id":"4589575378","tag":{"amenity":"recycling","recycling:clothes":"yes","recycling_type":"container"}},"type":"Feature"},
	{"geometry":{"coordinates":[7.613861,51.023946],"type":"Point"},"properties":{"osm_id":"4589845533","tag":{"amenity":"waste_basket"}},"type":"Feature"},
	{"geometry":{"coordinates":[7.560983,51.020213],"type":"Point"},"properties":{"osm_id":"4758387183","tag":{"amenity":"recycling","operator":"Deutsches Rotes Kreuz","recycling:clothes":"yes","recycling_type":"container"}},"type":"Feature"},
	{"geometry":{"coordinates":[7.580955,51.035295],"type":"Point"},"properties":{"osm_id":"5294082172","tag":{"amenity":"waste_disposal"}},"type":"Feature"},
	{"geometry":{"coordinates":[7.624621,51.067779],"type":"Point"},"properties":{"osm_id":"5571454125","tag":{"amenity":"waste_basket","waste":"trash"}},"type":"Feature"},
	{"geometry":{"coordinates":[7.629105,51.055554],"type":"Point"},"properties":{"osm_id":"5571454133","tag":{"amenity":"waste_basket","waste":"trash"}},"type":"Feature"},
	{"geometry":{"coordinates":[7.629061,51.055491],"type":"Point"},"properties":{"osm_id":"5571454134","tag":{"amenity":"waste_basket","waste":"trash"}},"type":"Feature"},
	{"geometry":{"coordinates":[7.635862,51.038191],"type":"Point"},"properties":{"osm_id":"5599074986","tag":{"amenity":"waste_basket","waste":"trash"}},"type":"Feature"},
	{"geometry":{"coordinates":[7.642726,51.041859],"type":"Point"},"properties":{"osm_id":"5599074988","tag":{"amenity":"waste_basket","waste":"trash"}},"type":"Feature"},
	{"geometry":{"coordinates":[7.634159,51.036209],"type":"Point"},"properties":{"osm_id":"5599131424","tag":{"amenity":"waste_basket","waste":"trash"}},"type":"Feature"},
	{"geometry":{"coordinates":[7.580426,51.049328],"type":"Point"},"properties":{"osm_id":"5716489284","tag":{"amenity":"waste_basket"}},"type":"Feature"},
	{"geometry":{"coordinates":[7.580158,51.049176],"type":"Point"},"properties":{"osm_id":"5716489285","tag":{"amenity":"waste_basket"}},"type":"Feature"},
	{"geometry":{"coordinates":[7.625328,51.062231],"type":"Point"},"properties":{"osm_id":"8042302452","tag":{"amenity":"waste_basket"}},"type":"Feature"},
	{"geometry":{"coordinates":[7.635694,51.037834],"type":"Point"},"properties":{"osm_id":"8311826007","tag":{"amenity":"waste_basket"}},"type":"Feature"},
	{"geometry":{"coordinates":[7.562045,51.024349],"type":"Point"},"properties":{"osm_id":"8318537384","tag":{"amenity":"waste_basket","colour":"grey","material":"metal","operator":"Stadt Gumnmersbach","waste":"trash;cigarettes"}},"type":"Feature"},
	{"geometry":{"coordinates":[7.612694,51.015652],"type":"Point"},"properties":{"osm_id":"8842879562","tag":{"amenity":"waste_basket","waste":"trash"}},"type":"Feature"},
	{"geometry":{"coordinates":[7.613939,51.016488],"type":"Point"},"properties":{"osm_id":"8842879564","tag":{"amenity":"waste_basket"}},"type":"Feature"}
]
}
