{
"type": "FeatureCollection",
"lastupdate": "2020-08-06T00:00:00Z",
"features": [
	{"geometry":{"coordinates":[7.60197,48.14815],"type":"Point"},"properties":{"osm_id":"1758984474","tag":{"amenity":"waste_basket"}},"type":"Feature"},
	{"geometry":{"coordinates":[7.628383,48.123136],"type":"Point"},"properties":{"osm_id":"2679053336","tag":{"amenity":"waste_basket"}},"type":"Feature"},
	{"geometry":{"coordinates":[7.618526,48.143358],"type":"Point"},"properties":{"osm_id":"4996326765","tag":{"amenity":"recycling","location":"overground","recycling:batteries":"yes","recycling:clothes":"yes","recycling:shoes":"yes","recycling:small_electrical_appliances":"yes","recycling_type":"container"}},"type":"Feature"}
]
}
