{
"type": "FeatureCollection",
"features": [
	{"geometry":{"coordinates":[7.60197,48.14815],"type":"Point"},"properties":{"osm_id":"1758984474","tag":{"amenity":"waste_basket"}},"type":"Feature"},
	{"geometry":{"coordinates":[7.628383,48.123136],"type":"Point"},"properties":{"osm_id":"2679053336","tag":{"amenity":"waste_basket"}},"type":"Feature"},
	{"geometry":{"coordinates":[7.618526,48.143358],"type":"Point"},"properties":{"osm_id":"4996326765","tag":{"amenity":"recycling","location":"overground","recycling:batteries":"yes","recycling:clothes":"yes","recycling:shoes":"yes","recycling:small_electrical_appliances":"yes","recycling_type":"container"}},"type":"Feature"},
	{"geometry":{"coordinates":[7.607401,48.141157],"type":"Point"},"properties":{"osm_id":"8491917087","tag":{"amenity":"waste_basket"}},"type":"Feature"},
	{"geometry":{"coordinates":[7.611113,48.146681],"type":"Point"},"properties":{"osm_id":"8493121667","tag":{"amenity":"waste_basket","waste":"trash"}},"type":"Feature"}
]
}
