{
"type": "FeatureCollection",
"features": [
	{"geometry":{"coordinates":[7.612131,47.390017],"type":"Point"},"properties":{"name":"Robidog","osm_id":"732092491","tag":{"amenity":"waste_basket","waste":"dog_excrement"}},"type":"Feature"},
	{"geometry":{"coordinates":[7.620692,47.396338],"type":"Point"},"properties":{"name":"Robidog","osm_id":"2557301491","tag":{"amenity":"waste_basket","waste":"dog_excrement"}},"type":"Feature"},
	{"geometry":{"coordinates":[7.618874,47.397608],"type":"Point"},"properties":{"name":"Robidog","osm_id":"2557301493","tag":{"amenity":"waste_basket","waste":"dog_excrement"}},"type":"Feature"},
	{"geometry":{"coordinates":[7.61262,47.397898],"type":"Point"},"properties":{"name":"Robidog","osm_id":"2557301495","tag":{"amenity":"waste_basket","waste":"dog_excrement"}},"type":"Feature"},
	{"geometry":{"coordinates":[7.614185,47.395876],"type":"Point"},"properties":{"name":"Robidog","osm_id":"2557301497","tag":{"amenity":"waste_basket","waste":"dog_excrement"}},"type":"Feature"},
	{"geometry":{"coordinates":[7.616104,47.393624],"type":"Point"},"properties":{"name":"Robidog","osm_id":"2557301499","tag":{"amenity":"waste_basket","waste":"dog_excrement"}},"type":"Feature"},
	{"geometry":{"coordinates":[7.609795,47.394215],"type":"Point"},"properties":{"name":"Robidog","osm_id":"2557301501","tag":{"amenity":"waste_basket","waste":"dog_excrement"}},"type":"Feature"},
	{"geometry":{"coordinates":[7.614173,47.389995],"type":"Point"},"properties":{"name":"Robidog","osm_id":"2557301505","tag":{"amenity":"waste_basket","waste":"dog_excrement"}},"type":"Feature"},
	{"geometry":{"coordinates":[7.619857,47.388124],"type":"Point"},"properties":{"name":"Robidog","osm_id":"2557301506","tag":{"amenity":"waste_basket","waste":"dog_excrement"}},"type":"Feature"},
	{"geometry":{"coordinates":[7.630415,47.394095],"type":"Point"},"properties":{"name":"Robidog","osm_id":"2557301508","tag":{"amenity":"waste_basket","waste":"dog_excrement"}},"type":"Feature"},
	{"geometry":{"coordinates":[7.629026,47.395293],"type":"Point"},"properties":{"name":"Robidog","osm_id":"2558184533","tag":{"amenity":"waste_basket","waste":"dog_excrement"}},"type":"Feature"},
	{"geometry":{"coordinates":[7.629514,47.396397],"type":"Point"},"properties":{"name":"Robidog","osm_id":"2558184594","tag":{"amenity":"waste_basket","waste":"dog_excrement"}},"type":"Feature"},
	{"geometry":{"coordinates":[7.623365,47.394401],"type":"Point"},"properties":{"name":"Robidog","osm_id":"2558184643","tag":{"amenity":"waste_basket","waste":"dog_excrement"}},"type":"Feature"}
]
}
