{
"type": "FeatureCollection",
"lastupdate": "2020-08-02T00:00:00Z",
"features": [
	{"geometry":{"coordinates":[7.61213,47.390016],"type":"Point"},"properties":{"name":"Robidog","osm_id":"732092491","tag":{"amenity":"waste_basket","waste":"dog_excrement"}},"type":"Feature"},
	{"geometry":{"coordinates":[7.620691,47.396338],"type":"Point"},"properties":{"name":"Robidog","osm_id":"2557301491","tag":{"amenity":"waste_basket","waste":"dog_excrement"}},"type":"Feature"},
	{"geometry":{"coordinates":[7.618873,47.397607],"type":"Point"},"properties":{"name":"Robidog","osm_id":"2557301493","tag":{"amenity":"waste_basket","waste":"dog_excrement"}},"type":"Feature"},
	{"geometry":{"coordinates":[7.61262,47.397898],"type":"Point"},"properties":{"name":"Robidog","osm_id":"2557301495","tag":{"amenity":"waste_basket","waste":"dog_excrement"}},"type":"Feature"},
	{"geometry":{"coordinates":[7.614184,47.395876],"type":"Point"},"properties":{"name":"Robidog","osm_id":"2557301497","tag":{"amenity":"waste_basket","waste":"dog_excrement"}},"type":"Feature"},
	{"geometry":{"coordinates":[7.616103,47.393623],"type":"Point"},"properties":{"name":"Robidog","osm_id":"2557301499","tag":{"amenity":"waste_basket","waste":"dog_excrement"}},"type":"Feature"},
	{"geometry":{"coordinates":[7.609795,47.394215],"type":"Point"},"properties":{"name":"Robidog","osm_id":"2557301501","tag":{"amenity":"waste_basket","waste":"dog_excrement"}},"type":"Feature"},
	{"geometry":{"coordinates":[7.614173,47.389994],"type":"Point"},"properties":{"name":"Robidog","osm_id":"2557301505","tag":{"amenity":"waste_basket","waste":"dog_excrement"}},"type":"Feature"},
	{"geometry":{"coordinates":[7.619856,47.388124],"type":"Point"},"properties":{"name":"Robidog","osm_id":"2557301506","tag":{"amenity":"waste_basket","waste":"dog_excrement"}},"type":"Feature"},
	{"geometry":{"coordinates":[7.630415,47.394094],"type":"Point"},"properties":{"name":"Robidog","osm_id":"2557301508","tag":{"amenity":"waste_basket","waste":"dog_excrement"}},"type":"Feature"},
	{"geometry":{"coordinates":[7.629025,47.395292],"type":"Point"},"properties":{"name":"Robidog","osm_id":"2558184533","tag":{"amenity":"waste_basket","waste":"dog_excrement"}},"type":"Feature"},
	{"geometry":{"coordinates":[7.629514,47.396396],"type":"Point"},"properties":{"name":"Robidog","osm_id":"2558184594","tag":{"amenity":"waste_basket","waste":"dog_excrement"}},"type":"Feature"},
	{"geometry":{"coordinates":[7.623364,47.3944],"type":"Point"},"properties":{"name":"Robidog","osm_id":"2558184643","tag":{"amenity":"waste_basket","waste":"dog_excrement"}},"type":"Feature"}
]
}
