{
"type": "FeatureCollection",
"features": [
	{"geometry":{"coordinates":[145.278833,-37.725743],"type":"Point"},"properties":{"name":"Golden Oak","osm_id":"9093375452","tag":{"description":"Low branching, wide specimen, lower lateral limbs are disproportionately large to central trunk. Another example at Ballarat.","diameter":"1m","height":"17","leaf_cycle":"deciduous","leaf_type":"broadleaved","natural":"tree"}},"type":"Feature"}
]
}
