{
"type": "FeatureCollection",
"features": [
	{"geometry":{"coordinates":[19.131744,53.148692],"type":"Point"},"properties":{"osm_id":"4706691057","tag":{"denotation":"natural_monument","natural":"tree","ref:CRFOP":"PL.ZIPOP.1393.PP.0405032.608","ref:INSPIRE":"PL.ZIPOP.1393.PP.0405032.608","website":"http://crfop.gdos.gov.pl/CRFOP/widok/viewfop.jsf?fop=PL.ZIPOP.1393.PP.0405032.608"}},"type":"Feature"},
	{"geometry":{"coordinates":[19.137814,53.157301],"type":"Point"},"properties":{"osm_id":"4706691061","tag":{"denotation":"natural_monument","natural":"tree","ref:CRFOP":"PL.ZIPOP.1393.PP.0405032.604","ref:INSPIRE":"PL.ZIPOP.1393.PP.0405032.604","website":"http://crfop.gdos.gov.pl/CRFOP/widok/viewfop.jsf?fop=PL.ZIPOP.1393.PP.0405032.604"}},"type":"Feature"},
	{"geometry":{"coordinates":[19.137553,53.156977],"type":"Point"},"properties":{"osm_id":"4706691062","tag":{"denotation":"natural_monument","natural":"tree","ref:CRFOP":"PL.ZIPOP.1393.PP.0405032.604","ref:INSPIRE":"PL.ZIPOP.1393.PP.0405032.604","website":"http://crfop.gdos.gov.pl/CRFOP/widok/viewfop.jsf?fop=PL.ZIPOP.1393.PP.0405032.604"}},"type":"Feature"},
	{"geometry":{"coordinates":[19.137332,53.157371],"type":"Point"},"properties":{"osm_id":"4706691063","tag":{"denotation":"natural_monument","natural":"tree","ref:CRFOP":"PL.ZIPOP.1393.PP.0405032.604","ref:INSPIRE":"PL.ZIPOP.1393.PP.0405032.604","website":"http://crfop.gdos.gov.pl/CRFOP/widok/viewfop.jsf?fop=PL.ZIPOP.1393.PP.0405032.604"}},"type":"Feature"},
	{"geometry":{"coordinates":[19.159435,53.130525],"type":"Point"},"properties":{"osm_id":"4706691467","tag":{"denotation":"natural_monument","natural":"tree","ref:CRFOP":"PL.ZIPOP.1393.PP.0405052.1475","ref:INSPIRE":"PL.ZIPOP.1393.PP.0405052.1475","website":"http://crfop.gdos.gov.pl/CRFOP/widok/viewfop.jsf?fop=PL.ZIPOP.1393.PP.0405052.1475"}},"type":"Feature"}
]
}
