{
"type": "FeatureCollection",
"features": [
	{"geometry":{"coordinates":[19.114366,53.061077],"type":"Point"},"properties":{"osm_id":"4706691387","tag":{"denotation":"natural_monument","natural":"tree","ref:CRFOP":"PL.ZIPOP.1393.PP.0405052.1481","ref:INSPIRE":"PL.ZIPOP.1393.PP.0405052.1481","website":"http://crfop.gdos.gov.pl/CRFOP/widok/viewfop.jsf?fop=PL.ZIPOP.1393.PP.0405052.1481"}},"type":"Feature"},
	{"geometry":{"coordinates":[19.114498,53.061231],"type":"Point"},"properties":{"osm_id":"4706691388","tag":{"denotation":"natural_monument","natural":"tree","ref:CRFOP":"PL.ZIPOP.1393.PP.0405052.1481","ref:INSPIRE":"PL.ZIPOP.1393.PP.0405052.1481","website":"http://crfop.gdos.gov.pl/CRFOP/widok/viewfop.jsf?fop=PL.ZIPOP.1393.PP.0405052.1481"}},"type":"Feature"},
	{"geometry":{"coordinates":[19.115017,53.061128],"type":"Point"},"properties":{"osm_id":"4706691389","tag":{"denotation":"natural_monument","natural":"tree","ref:CRFOP":"PL.ZIPOP.1393.PP.0405052.1481","ref:INSPIRE":"PL.ZIPOP.1393.PP.0405052.1481","website":"http://crfop.gdos.gov.pl/CRFOP/widok/viewfop.jsf?fop=PL.ZIPOP.1393.PP.0405052.1481"}},"type":"Feature"}
]
}
