{
"type": "FeatureCollection",
"features": [
	{"geometry":{"coordinates":[31.952103,3.467205],"type":"Point"},"properties":{"name":"Waste disposal","osm_id":"5772350769","tag":{"addr:block":"Nyumanzi market","addr:district":"Adjumani","addr:settlement":"Nyumanzi","amenity":"waste_disposal","fee":"no","lit":"no","operator":"LWF","operator:type":"ngo","source:version":"Sanitation;v3.0.2","start_date":"2015-04-01","waste":"Market waste"}},"type":"Feature"},
	{"geometry":{"coordinates":[31.952721,3.465836],"type":"Point"},"properties":{"name":"Waste disposal","osm_id":"5772350770","tag":{"addr:block":"Nyumanzi market","addr:district":"Adjumani","addr:settlement":"Nyumanzi","amenity":"waste_disposal","fee":"no","lit":"no","operator":"LWF","operator:type":"ngo","source:version":"Sanitation;v3.0.2","start_date":"2014-09-01","waste":"Market waste and polythene bag"}},"type":"Feature"},
	{"geometry":{"coordinates":[31.94081,3.457681],"type":"Point"},"properties":{"name":"Waste basket","osm_id":"5772350775","tag":{"addr:block":"Nyumanzi Community centre","addr:district":"Adjumani","addr:settlement":"Nyumanzi","amenity":"waste_basket","fee":"no","lit":"no","operator":"UNHCR","operator:type":"ngo","source:version":"Sanitation;v3.0.2","start_date":"2015-07-01","waste":"Plastic bottle, polythene bag"}},"type":"Feature"}
]
}
