{
"type": "FeatureCollection",
"lastupdate": "2020-07-31T00:00:00Z",
"features": [
	{"geometry":{"coordinates":[31.94081,3.457681],"type":"Point"},"properties":{"name":"Waste basket","osm_id":"5772350775","tag":{"addr:block":"Nyumanzi Community centre","addr:district":"Adjumani","addr:settlement":"Nyumanzi","amenity":"waste_basket","fee":"no","lit":"no","operator":"UNHCR","operator:type":"ngo","source:version":"Sanitation;v3.0.2","start_date":"2015-07-01","waste":"Plastic bottle, polythene bag"}},"type":"Feature"}
]
}
