{
"type": "FeatureCollection",
"features": [
	{"geometry":{"coordinates":[-105.346803,41.133614],"type":"Point"},"properties":{"name":"Tree Rock","osm_id":"998389244","tag":{"natural":"tree","tourism":"attraction"}},"type":"Feature"}
]
}
