{
"type": "FeatureCollection",
"features": [
	{"geometry":{"coordinates":[10.115638,56.885764],"type":"Point"},"properties":{"name":"Metal- og Glas container","osm_id":"8427045319","tag":{"amenity":"recycling","opening_hours":"24/7","recycling:glass":"yes","recycling:scrap_metal":"yes","recycling_type":"centre"}},"type":"Feature"}
]
}
