{
"type": "FeatureCollection",
"features": [
	{"geometry":{"coordinates":[10.108512,55.271876],"type":"Point"},"properties":{"highway":"bus_stop","name":"Vestfyns Udd. Center","osm_id":"2559095328","ref":"2244","tag":{"amenity":"waste_basket","bench":"yes","bus":"yes","departures_board":"timetable","lit":"sunset-sunrise","network":"FynBus","network:wikidata":"Q12313224","network:wikipedia":"da:FynBus","operator":"Fynbus","public_transport":"platform","shelter":"yes","shelter_type":"public_transport","waste_basket":"yes"}},"type":"Feature"},
	{"geometry":{"coordinates":[10.108262,55.271709],"type":"Point"},"properties":{"highway":"bus_stop","name":"Glamsbjerg Uddannelsescenter","osm_id":"2559095361","tag":{"amenity":"waste_basket","bench":"yes","bus":"yes","departures_board":"timetable","public_transport":"platform","shelter":"yes","shelter_type":"public_transport"}},"type":"Feature"},
	{"geometry":{"coordinates":[10.108244,55.271712],"type":"Point"},"properties":{"highway":"bus_stop","name":"Vestfyns Udd. Center","osm_id":"9035653482","ref":"1869","tag":{"amenity":"waste_basket","bench":"yes","bus":"yes","departures_board":"timetable","lit":"sunset-sunrise","network":"FynBus","network:wikidata":"Q12313224","network:wikipedia":"da:FynBus","operator":"Fynbus","public_transport":"platform","shelter":"yes","shelter_type":"public_transport","waste_basket":"yes"}},"type":"Feature"}
]
}
