{
"type": "FeatureCollection",
"lastupdate": "2020-07-31T00:00:00Z",
"features": [
	{"geometry":{"coordinates":[10.108512,55.271876],"type":"Point"},"properties":{"highway":"bus_stop","name":"Glamsbjerg Uddannelsescenter","osm_id":"2559095328","tag":{"amenity":"waste_basket","bench":"yes","bus":"yes","departures_board":"timetable","public_transport":"platform","shelter":"yes","shelter_type":"public_transport"}},"type":"Feature"},
	{"geometry":{"coordinates":[10.108262,55.271709],"type":"Point"},"properties":{"highway":"bus_stop","name":"Glamsbjerg Uddannelsescenter","osm_id":"2559095361","tag":{"amenity":"waste_basket","bench":"yes","bus":"yes","departures_board":"timetable","public_transport":"platform","shelter":"yes","shelter_type":"public_transport"}},"type":"Feature"}
]
}
