{
"type": "FeatureCollection",
"features": [
	{"geometry":{"coordinates":[10.126157,52.007816],"type":"Point"},"properties":{"osm_id":"303587854","tag":{"amenity":"recycling","recycling:glass":"yes","recycling:paper":"yes"}},"type":"Feature"},
	{"geometry":{"coordinates":[10.13214,52.006565],"type":"Point"},"properties":{"osm_id":"469234673","tag":{"amenity":"recycling","location":"overground","recycling:clothes":"yes","recycling:glass":"yes","recycling:paper":"yes","recycling_type":"container"}},"type":"Feature"},
	{"geometry":{"coordinates":[10.134896,52.004368],"type":"Point"},"properties":{"osm_id":"538974928","tag":{"amenity":"recycling","recycling:glass":"yes","recycling:paper":"yes","recycling_type":"container"}},"type":"Feature"},
	{"geometry":{"coordinates":[10.135703,52.008832],"type":"Point"},"properties":{"osm_id":"851133189","tag":{"amenity":"recycling","recycling:glass":"yes","recycling:paper":"yes","recycling_type":"container"}},"type":"Feature"},
	{"geometry":{"coordinates":[10.114121,52.036934],"type":"Point"},"properties":{"osm_id":"858958994","tag":{"amenity":"recycling","recycling:glass":"yes"}},"type":"Feature"},
	{"geometry":{"coordinates":[10.126225,52.005269],"type":"Point"},"properties":{"osm_id":"6260782710","tag":{"amenity":"waste_basket"}},"type":"Feature"},
	{"geometry":{"coordinates":[10.132294,52.010617],"type":"Point"},"properties":{"osm_id":"7124114214","tag":{"amenity":"recycling","recycling:clothes":"yes","recycling_type":"container"}},"type":"Feature"},
	{"geometry":{"coordinates":[10.132611,52.010609],"type":"Point"},"properties":{"osm_id":"7124114233","tag":{"amenity":"recycling","recycling:clothes":"yes","recycling_type":"container"}},"type":"Feature"}
]
}
