{
"type": "FeatureCollection",
"lastupdate": "2020-08-02T00:00:00Z",
"features": [
	{"geometry":{"coordinates":[10.178145,50.297697],"type":"Point"},"properties":{"osm_id":"393362698","tag":{"amenity":"recycling"}},"type":"Feature"},
	{"geometry":{"coordinates":[10.119758,50.291554],"type":"Point"},"properties":{"osm_id":"531969788","tag":{"amenity":"recycling","recycling:glass":"yes","recycling:paper":"yes"}},"type":"Feature"},
	{"geometry":{"coordinates":[10.191932,50.328383],"type":"Point"},"properties":{"osm_id":"1239493501","tag":{"amenity":"recycling","recycling:batteries":"yes","recycling:cans":"yes","recycling:glass":"yes","recycling:paper":"yes","recycling:scrap_metal":"yes"}},"type":"Feature"},
	{"geometry":{"coordinates":[10.158103,50.329986],"type":"Point"},"properties":{"osm_id":"1676192552","tag":{"amenity":"waste_basket"}},"type":"Feature"},
	{"geometry":{"coordinates":[10.137874,50.337064],"type":"Point"},"properties":{"osm_id":"1679868190","tag":{"addr:street":"Obere Gasse","amenity":"recycling","recycling:batteries":"yes","recycling:cans":"yes","recycling:glass":"yes","recycling:paper":"yes","recycling_type":"container"}},"type":"Feature"},
	{"geometry":{"coordinates":[10.165192,50.331563],"type":"Point"},"properties":{"osm_id":"7256100085","tag":{"amenity":"recycling","recycling:cans":"yes","recycling:glass":"yes","recycling:paper":"yes","recycling_type":"container"}},"type":"Feature"},
	{"geometry":{"coordinates":[10.165142,50.331571],"type":"Point"},"properties":{"osm_id":"7256100086","tag":{"amenity":"recycling","recycling:clothes":"yes","recycling_type":"container"}},"type":"Feature"}
]
}
