{
"type": "FeatureCollection",
"features": [
	{"geometry":{"coordinates":[10.178146,50.297698],"type":"Point"},"properties":{"osm_id":"393362698","tag":{"amenity":"recycling"}},"type":"Feature"},
	{"geometry":{"coordinates":[10.119758,50.291554],"type":"Point"},"properties":{"osm_id":"531969788","tag":{"amenity":"recycling","recycling:glass":"yes","recycling:paper":"yes"}},"type":"Feature"},
	{"geometry":{"coordinates":[10.191932,50.328384],"type":"Point"},"properties":{"osm_id":"1239493501","tag":{"amenity":"recycling","recycling:batteries":"yes","recycling:cans":"yes","recycling:glass":"yes","recycling:paper":"yes","recycling:scrap_metal":"yes"}},"type":"Feature"},
	{"geometry":{"coordinates":[10.158104,50.329986],"type":"Point"},"properties":{"osm_id":"1676192552","tag":{"amenity":"waste_basket"}},"type":"Feature"},
	{"geometry":{"coordinates":[10.137875,50.337065],"type":"Point"},"properties":{"osm_id":"1679868190","tag":{"addr:street":"Obere Gasse","amenity":"recycling","recycling:batteries":"yes","recycling:cans":"yes","recycling:glass":"yes","recycling:paper":"yes","recycling_type":"container"}},"type":"Feature"},
	{"geometry":{"coordinates":[10.165193,50.331564],"type":"Point"},"properties":{"osm_id":"7256100085","tag":{"amenity":"recycling","recycling:cans":"yes","recycling:glass":"yes","recycling:paper":"yes","recycling_type":"container"}},"type":"Feature"},
	{"geometry":{"coordinates":[10.165142,50.331572],"type":"Point"},"properties":{"osm_id":"7256100086","tag":{"amenity":"recycling","recycling:clothes":"yes","recycling_type":"container"}},"type":"Feature"}
]
}
