{
"type": "FeatureCollection",
"features": [
	{"geometry":{"coordinates":[10.178145,50.297697],"type":"Point"},"properties":{"osm_id":"393362698","tag":{"amenity":"recycling","recycling_type":"container"}},"type":"Feature"},
	{"geometry":{"coordinates":[10.119758,50.291554],"type":"Point"},"properties":{"osm_id":"531969788","tag":{"amenity":"recycling","recycling:glass":"yes","recycling:paper":"yes"}},"type":"Feature"},
	{"geometry":{"coordinates":[10.192175,50.328422],"type":"Point"},"properties":{"osm_id":"1239493501","tag":{"amenity":"recycling","recycling:batteries":"yes","recycling:cans":"yes","recycling:glass":"no","recycling:glass_bottles":"yes","recycling:paper":"yes","recycling:scrap_metal":"yes","recycling_type":"container"}},"type":"Feature"},
	{"geometry":{"coordinates":[10.158103,50.329986],"type":"Point"},"properties":{"osm_id":"1676192552","tag":{"amenity":"waste_basket"}},"type":"Feature"},
	{"geometry":{"coordinates":[10.137874,50.337064],"type":"Point"},"properties":{"osm_id":"1679868190","tag":{"addr:street":"Obere Gasse","amenity":"recycling","recycling:batteries":"yes","recycling:cans":"yes","recycling:glass":"yes","recycling:paper":"yes","recycling_type":"container"}},"type":"Feature"},
	{"geometry":{"coordinates":[10.165192,50.331563],"type":"Point"},"properties":{"osm_id":"7256100085","tag":{"amenity":"recycling","recycling:cans":"yes","recycling:glass":"yes","recycling:paper":"yes","recycling_type":"container"}},"type":"Feature"},
	{"geometry":{"coordinates":[10.165142,50.331571],"type":"Point"},"properties":{"osm_id":"7256100086","tag":{"amenity":"recycling","recycling:clothes":"yes","recycling_type":"container"}},"type":"Feature"},
	{"geometry":{"coordinates":[10.195268,50.327533],"type":"Point"},"properties":{"osm_id":"8828285959","tag":{"amenity":"waste_basket"}},"type":"Feature"},
	{"geometry":{"coordinates":[10.194996,50.327628],"type":"Point"},"properties":{"osm_id":"8828285962","tag":{"amenity":"waste_basket"}},"type":"Feature"},
	{"geometry":{"coordinates":[10.171887,50.31271],"type":"Point"},"properties":{"osm_id":"8936573521","tag":{"amenity":"recycling","recycling:cardboard":"yes","recycling:clothes":"yes","recycling:glass_bottles":"yes","recycling:paper":"yes","recycling:shoes":"yes","recycling_type":"container"}},"type":"Feature"},
	{"geometry":{"coordinates":[10.170038,50.313132],"type":"Point"},"properties":{"osm_id":"8936573530","tag":{"amenity":"waste_basket"}},"type":"Feature"}
]
}
