{
"type": "FeatureCollection",
"lastupdate": "2020-08-03T00:00:00Z",
"features": [
	{"geometry":{"coordinates":[10.17106,48.223286],"type":"Point"},"properties":{"name":"Recyclinghof","osm_id":"333130137","tag":{"amenity":"recycling","recycling:glass":"yes","recycling:paper":"yes","recycling:scrap_metal":"yes","recycling_type":"centre"}},"type":"Feature"},
	{"geometry":{"coordinates":[10.169739,48.194761],"type":"Point"},"properties":{"name":"Wertstoffhof Unterroth","osm_id":"434467596","tag":{"amenity":"recycling","opening_hours":"Sa 09:30-11:30","recycling:cans":"yes","recycling:clothes":"yes","recycling:glass":"yes","recycling:paper":"yes","recycling:scrap_metal":"yes","recycling_type":"centre"}},"type":"Feature"},
	{"geometry":{"coordinates":[10.185839,48.174638],"type":"Point"},"properties":{"name":"Wertstoffhof Oberroth","osm_id":"441904856","tag":{"amenity":"recycling","opening_hours":"Sa 09:00-10:00","recycling:cans":"yes","recycling:glass":"yes","recycling:paper":"yes","recycling:scrap_metal":"yes","recycling_type":"centre"}},"type":"Feature"},
	{"geometry":{"coordinates":[10.112071,48.219842],"type":"Point"},"properties":{"osm_id":"885659644","tag":{"amenity":"recycling","recycling:cans":"yes","recycling:clothes":"yes","recycling:glass":"yes","recycling:paper":"yes","recycling_type":"container"}},"type":"Feature"},
	{"geometry":{"coordinates":[10.109392,48.200827],"type":"Point"},"properties":{"osm_id":"885659682","tag":{"amenity":"recycling","recycling:cans":"yes","recycling:clothes":"yes","recycling:glass":"yes","recycling:paper":"yes","recycling_type":"container"}},"type":"Feature"},
	{"geometry":{"coordinates":[10.114,48.215853],"type":"Point"},"properties":{"osm_id":"885659804","tag":{"amenity":"recycling","recycling:cans":"yes","recycling:glass":"yes","recycling:paper":"yes","recycling_type":"container"}},"type":"Feature"},
	{"geometry":{"coordinates":[10.108705,48.22346],"type":"Point"},"properties":{"osm_id":"937175491","tag":{"amenity":"recycling","recycling:cans":"yes","recycling:glass":"yes","recycling:paper":"yes","recycling_type":"container"}},"type":"Feature"},
	{"geometry":{"coordinates":[10.143589,48.182774],"type":"Point"},"properties":{"osm_id":"1229999928","tag":{"amenity":"recycling","recycling:glass":"yes","recycling:paper":"yes"}},"type":"Feature"},
	{"geometry":{"coordinates":[10.117607,48.186786],"type":"Point"},"properties":{"osm_id":"1276332329","tag":{"amenity":"recycling","recycling:glass":"yes","recycling:paper":"yes","recycling_type":"container"}},"type":"Feature"},
	{"geometry":{"coordinates":[10.121078,48.216719],"type":"Point"},"properties":{"osm_id":"1736046390","tag":{"amenity":"waste_basket"}},"type":"Feature"},
	{"geometry":{"coordinates":[10.109331,48.175702],"type":"Point"},"properties":{"osm_id":"1768672352","tag":{"amenity":"recycling","recycling:cans":"yes","recycling:clothes":"yes","recycling:glass":"yes","recycling:paper":"yes","recycling_type":"container"}},"type":"Feature"},
	{"geometry":{"coordinates":[10.145662,48.174999],"type":"Point"},"properties":{"osm_id":"1792838084","tag":{"amenity":"recycling","recycling:glass":"yes","recycling:paper":"yes","recycling_type":"container"}},"type":"Feature"},
	{"geometry":{"coordinates":[10.166195,48.187503],"type":"Point"},"properties":{"osm_id":"2441199312","tag":{"amenity":"waste_basket"}},"type":"Feature"},
	{"geometry":{"coordinates":[10.177626,48.219993],"type":"Point"},"properties":{"osm_id":"2482172098","tag":{"amenity":"recycling","location":"overground","recycling:clothes":"yes","recycling_type":"container"}},"type":"Feature"},
	{"geometry":{"coordinates":[10.169876,48.194703],"type":"Point"},"properties":{"osm_id":"4172174705","tag":{"amenity":"recycling","recycling:glass":"yes","recycling_type":"container"}},"type":"Feature"},
	{"geometry":{"coordinates":[10.169892,48.19481],"type":"Point"},"properties":{"osm_id":"4172174709","tag":{"amenity":"recycling","recycling:clothes":"yes","recycling_type":"container"}},"type":"Feature"},
	{"geometry":{"coordinates":[10.11089,48.216512],"type":"Point"},"properties":{"osm_id":"4606063001","tag":{"amenity":"recycling","recycling:cans":"yes","recycling:clothes":"yes","recycling:glass":"yes","recycling:paper":"yes","recycling_type":"container"}},"type":"Feature"}
]
}
