{
"type": "FeatureCollection",
"lastupdate": "2020-08-01T00:00:00Z",
"features": [
	{"geometry":{"coordinates":[10.174503,47.998807],"type":"Point"},"properties":{"osm_id":"392243079","tag":{"amenity":"recycling","location":"overground","recycling:cans":"yes","recycling:glass":"yes","recycling:paper":"yes","recycling:scrap_metal":"yes","recycling_type":"container"}},"type":"Feature"},
	{"geometry":{"coordinates":[10.155564,48.042451],"type":"Point"},"properties":{"osm_id":"990044598","tag":{"amenity":"recycling","recycling:clothes":"yes","recycling:shoes":"yes"}},"type":"Feature"},
	{"geometry":{"coordinates":[10.185181,48.003861],"type":"Point"},"properties":{"osm_id":"1185125526","tag":{"amenity":"recycling","recycling:cans":"yes","recycling:glass":"yes","recycling:paper":"yes","recycling_type":"container"}},"type":"Feature"},
	{"geometry":{"coordinates":[10.189993,47.996367],"type":"Point"},"properties":{"osm_id":"1207112453","tag":{"amenity":"recycling"}},"type":"Feature"},
	{"geometry":{"coordinates":[10.169401,48.004614],"type":"Point"},"properties":{"osm_id":"2522683006","tag":{"amenity":"recycling","recycling:cans":"yes","recycling:glass":"yes","recycling:paper":"yes","recycling_type":"container"}},"type":"Feature"},
	{"geometry":{"coordinates":[10.184882,47.991142],"type":"Point"},"properties":{"osm_id":"2786617764","tag":{"amenity":"recycling","recycling_type":"container"}},"type":"Feature"},
	{"geometry":{"coordinates":[10.162611,48.010835],"type":"Point"},"properties":{"osm_id":"4363891474","tag":{"amenity":"recycling","location":"overground","recycling:cans":"yes","recycling:glass":"yes","recycling:paper":"yes","recycling:plastic":"yes","recycling_type":"container"}},"type":"Feature"},
	{"geometry":{"coordinates":[10.14995,48.030802],"type":"Point"},"properties":{"osm_id":"4783665761","tag":{"amenity":"recycling","recycling:clothes":"yes","recycling:shoes":"yes","recycling_type":"container"}},"type":"Feature"},
	{"geometry":{"coordinates":[10.172893,48.019106],"type":"Point"},"properties":{"osm_id":"6653231366","tag":{"amenity":"waste_basket","waste":"trash"}},"type":"Feature"}
]
}
