{
"type": "FeatureCollection",
"features": [
	{"geometry":{"coordinates":[-10.743609,7.805268],"type":"Point"},"properties":{"osm_id":"2936888675","tag":{"natural":"tree"}},"type":"Feature"},
	{"geometry":{"coordinates":[-10.743443,7.805347],"type":"Point"},"properties":{"osm_id":"2936888691","tag":{"natural":"tree"}},"type":"Feature"},
	{"geometry":{"coordinates":[-10.743374,7.805537],"type":"Point"},"properties":{"osm_id":"2936889231","tag":{"natural":"tree"}},"type":"Feature"},
	{"geometry":{"coordinates":[-10.790283,7.879216],"type":"Point"},"properties":{"osm_id":"2937574016","tag":{"addr:city":"Jojoima","natural":"tree"}},"type":"Feature"}
]
}
