{
"type": "FeatureCollection",
"lastupdate": "2020-07-31T00:00:00Z",
"features": [
	{"geometry":{"coordinates":[-76.140702,42.983689],"type":"Point"},"properties":{"name":"Mission Returns","osm_id":"2685638741","tag":{"amenity":"recycling","collection_times":"Mo-Sa 10:00-18:00; Su 11:00-16:00","description":"Bottle and Can Redemption Center","recycling:cans":"yes","recycling:glass_bottles":"yes","recycling_type":"centre","website":"http://www.rmlifechanging.org/mission-returns/"}},"type":"Feature"},
	{"geometry":{"coordinates":[-76.154568,43.002798],"type":"Point"},"properties":{"name":"Bottle & Can Retrieval Center","osm_id":"6814066472","tag":{"addr:housenumber":"438","addr:postcode":"13207","addr:street":"West Seneca Turnpike","amenity":"recycling","branch":"West Seneca Turnpike","opening_hours":"Mo-Fr 10:00-18:00; Sa 09:00-16:00; Su 11:00-15:00","phone":"+1-315-913-3851","recycling:cans":"yes","recycling:glass_bottles":"yes","recycling:plastic_bottles":"yes","recycling_type":"centre","website":"https://bottleandcanrc.com/our-locations/central-new-york/syracuse-ny-438-w-seneca-tpke/"}},"type":"Feature"}
]
}
