{
"type": "FeatureCollection",
"lastupdate": "2020-07-31T00:00:00Z",
"features": [
	{"geometry":{"coordinates":[-76.167646,42.593282],"type":"Point"},"properties":{"name":"Cortland Count Recycling Center","osm_id":"4004579454","tag":{"addr:city":"Cortland","addr:housenumber":"137","addr:postcode":"13045","addr:state":"NY","addr:street":"Pendleton Street","amenity":"recycling","operator":"County of Cortland"}},"type":"Feature"}
]
}
