{
"type": "FeatureCollection",
"lastupdate": "2020-07-31T00:00:00Z",
"features": [
	{"geometry":{"coordinates":[-123.049325,46.847225],"type":"Point"},"properties":{"osm_id":"2393510846","tag":{"amenity":"recycling"}},"type":"Feature"},
	{"geometry":{"coordinates":[-123.048355,46.847558],"type":"Point"},"properties":{"osm_id":"2393510885","tag":{"amenity":"waste_basket"}},"type":"Feature"},
	{"geometry":{"coordinates":[-123.080395,46.821864],"type":"Point"},"properties":{"name":"Book Recycle Bin","osm_id":"4666485056","tag":{"amenity":"recycling","recycling_type":"container"}},"type":"Feature"}
]
}
