{
"type": "FeatureCollection",
"features": [
	{"geometry":{"coordinates":[-123.049326,46.847226],"type":"Point"},"properties":{"osm_id":"2393510846","tag":{"amenity":"recycling"}},"type":"Feature"},
	{"geometry":{"coordinates":[-123.048355,46.847558],"type":"Point"},"properties":{"osm_id":"2393510885","tag":{"amenity":"waste_basket"}},"type":"Feature"},
	{"geometry":{"coordinates":[-123.080396,46.821865],"type":"Point"},"properties":{"name":"Book Recycle Bin","osm_id":"4666485056","tag":{"amenity":"recycling","recycling_type":"container"}},"type":"Feature"}
]
}
