{
"type": "FeatureCollection",
"features": [
	{"geometry":{"coordinates":[10.044483,52.276175],"type":"Point"},"properties":{"name":"Alte Esche","osm_id":"855359887","tag":{"natural":"tree","type":"Esche"}},"type":"Feature"},
	{"geometry":{"coordinates":[10.023915,52.296346],"type":"Point"},"properties":{"osm_id":"3489197776","tag":{"natural":"tree"}},"type":"Feature"},
	{"geometry":{"coordinates":[10.084169,52.303837],"type":"Point"},"properties":{"osm_id":"3609835049","tag":{"denotation":"landmark","leaf_cycle":"deciduous","leaf_type":"broadleaved","natural":"tree"}},"type":"Feature"},
	{"geometry":{"coordinates":[10.06782,52.289084],"type":"Point"},"properties":{"osm_id":"3621423615","tag":{"natural":"tree"}},"type":"Feature"},
	{"geometry":{"coordinates":[10.06757,52.288993],"type":"Point"},"properties":{"osm_id":"3621423616","tag":{"natural":"tree"}},"type":"Feature"},
	{"geometry":{"coordinates":[10.068274,52.288215],"type":"Point"},"properties":{"osm_id":"3621423617","tag":{"natural":"tree"}},"type":"Feature"},
	{"geometry":{"coordinates":[10.069767,52.288325],"type":"Point"},"properties":{"osm_id":"3621423618","tag":{"natural":"tree"}},"type":"Feature"},
	{"geometry":{"coordinates":[10.071179,52.288263],"type":"Point"},"properties":{"osm_id":"3621423619","tag":{"natural":"tree"}},"type":"Feature"},
	{"geometry":{"coordinates":[10.070786,52.28821],"type":"Point"},"properties":{"osm_id":"3621423620","tag":{"natural":"tree"}},"type":"Feature"},
	{"geometry":{"coordinates":[10.071772,52.288342],"type":"Point"},"properties":{"osm_id":"3621423621","tag":{"natural":"tree"}},"type":"Feature"},
	{"geometry":{"coordinates":[10.072087,52.288385],"type":"Point"},"properties":{"osm_id":"3621423622","tag":{"natural":"tree"}},"type":"Feature"},
	{"geometry":{"coordinates":[10.070318,52.288378],"type":"Point"},"properties":{"osm_id":"3621423623","tag":{"natural":"tree"}},"type":"Feature"},
	{"geometry":{"coordinates":[10.069652,52.288084],"type":"Point"},"properties":{"osm_id":"3621423624","tag":{"natural":"tree"}},"type":"Feature"},
	{"geometry":{"coordinates":[10.069967,52.288108],"type":"Point"},"properties":{"osm_id":"3621423625","tag":{"natural":"tree"}},"type":"Feature"},
	{"geometry":{"coordinates":[10.069547,52.288112],"type":"Point"},"properties":{"osm_id":"3621423630","tag":{"natural":"tree"}},"type":"Feature"}
]
}
