{
"type": "FeatureCollection",
"features": [
	{"geometry":{"coordinates":[10.074108,49.898284],"type":"Point"},"properties":{"osm_id":"2861787450","tag":{"leaf_type":"broadleaved","natural":"tree"}},"type":"Feature"},
	{"geometry":{"coordinates":[10.074166,49.89808],"type":"Point"},"properties":{"osm_id":"2861787451","tag":{"leaf_type":"broadleaved","natural":"tree"}},"type":"Feature"},
	{"geometry":{"coordinates":[10.073573,49.89847],"type":"Point"},"properties":{"osm_id":"2861787452","tag":{"leaf_type":"broadleaved","natural":"tree"}},"type":"Feature"},
	{"geometry":{"coordinates":[10.07361,49.898328],"type":"Point"},"properties":{"osm_id":"2861787454","tag":{"leaf_type":"broadleaved","natural":"tree"}},"type":"Feature"},
	{"geometry":{"coordinates":[10.073618,49.898259],"type":"Point"},"properties":{"osm_id":"2861787455","tag":{"leaf_type":"broadleaved","natural":"tree"}},"type":"Feature"},
	{"geometry":{"coordinates":[10.073739,49.898253],"type":"Point"},"properties":{"osm_id":"2861787456","tag":{"leaf_type":"broadleaved","natural":"tree"}},"type":"Feature"},
	{"geometry":{"coordinates":[10.070686,49.897329],"type":"Point"},"properties":{"osm_id":"2862604233","tag":{"leaf_type":"broadleaved","natural":"tree"}},"type":"Feature"},
	{"geometry":{"coordinates":[10.073747,49.898361],"type":"Point"},"properties":{"osm_id":"2881289842","tag":{"natural":"tree"}},"type":"Feature"},
	{"geometry":{"coordinates":[10.073597,49.898397],"type":"Point"},"properties":{"osm_id":"2881289843","tag":{"leaf_type":"broadleaved","natural":"tree"}},"type":"Feature"},
	{"geometry":{"coordinates":[10.07858,49.900304],"type":"Point"},"properties":{"osm_id":"3911165792","tag":{"natural":"tree"}},"type":"Feature"},
	{"geometry":{"coordinates":[10.079669,49.900327],"type":"Point"},"properties":{"osm_id":"3911165793","tag":{"natural":"tree"}},"type":"Feature"},
	{"geometry":{"coordinates":[10.079774,49.900327],"type":"Point"},"properties":{"osm_id":"3911165794","tag":{"natural":"tree"}},"type":"Feature"},
	{"geometry":{"coordinates":[10.079782,49.900226],"type":"Point"},"properties":{"osm_id":"3911165795","tag":{"natural":"tree"}},"type":"Feature"},
	{"geometry":{"coordinates":[10.079297,49.900208],"type":"Point"},"properties":{"osm_id":"3911165796","tag":{"natural":"tree"}},"type":"Feature"},
	{"geometry":{"coordinates":[10.078997,49.900205],"type":"Point"},"properties":{"osm_id":"3911165797","tag":{"natural":"tree"}},"type":"Feature"},
	{"geometry":{"coordinates":[10.077316,49.900153],"type":"Point"},"properties":{"osm_id":"3911165798","tag":{"natural":"tree"}},"type":"Feature"},
	{"geometry":{"coordinates":[10.077456,49.900191],"type":"Point"},"properties":{"osm_id":"3911165799","tag":{"natural":"tree"}},"type":"Feature"},
	{"geometry":{"coordinates":[10.077102,49.900144],"type":"Point"},"properties":{"osm_id":"3911165800","tag":{"natural":"tree"}},"type":"Feature"},
	{"geometry":{"coordinates":[10.06081,49.921223],"type":"Point"},"properties":{"osm_id":"3914112370","tag":{"leaf_cycle":"deciduous","leaf_type":"broadleaved","natural":"tree"}},"type":"Feature"},
	{"geometry":{"coordinates":[10.060499,49.920896],"type":"Point"},"properties":{"osm_id":"3914112371","tag":{"leaf_cycle":"deciduous","leaf_type":"broadleaved","natural":"tree"}},"type":"Feature"},
	{"geometry":{"coordinates":[10.060951,49.920762],"type":"Point"},"properties":{"osm_id":"3914112372","tag":{"leaf_cycle":"deciduous","leaf_type":"broadleaved","natural":"tree"}},"type":"Feature"},
	{"geometry":{"coordinates":[10.060429,49.922087],"type":"Point"},"properties":{"osm_id":"3914112374","tag":{"leaf_cycle":"deciduous","leaf_type":"broadleaved","natural":"tree"}},"type":"Feature"},
	{"geometry":{"coordinates":[10.023427,49.897638],"type":"Point"},"properties":{"osm_id":"3918088577","tag":{"leaf_cycle":"deciduous","leaf_type":"broadleaved","natural":"tree"}},"type":"Feature"},
	{"geometry":{"coordinates":[10.02356,49.897821],"type":"Point"},"properties":{"osm_id":"3918088578","tag":{"leaf_cycle":"deciduous","leaf_type":"broadleaved","natural":"tree"}},"type":"Feature"},
	{"geometry":{"coordinates":[10.023496,49.897736],"type":"Point"},"properties":{"osm_id":"3918088579","tag":{"leaf_cycle":"deciduous","leaf_type":"broadleaved","natural":"tree"}},"type":"Feature"},
	{"geometry":{"coordinates":[10.080923,49.925373],"type":"Point"},"properties":{"osm_id":"4298666795","tag":{"natural":"tree"}},"type":"Feature"},
	{"geometry":{"coordinates":[10.077801,49.944811],"type":"Point"},"properties":{"name":"Linde","osm_id":"5025714141","tag":{"natural":"tree"}},"type":"Feature"}
]
}
