{
"type": "FeatureCollection",
"features": [
	{"geometry":{"coordinates":[10.074108,49.898285],"type":"Point"},"properties":{"osm_id":"2861787450","tag":{"leaf_type":"broadleaved","natural":"tree"}},"type":"Feature"},
	{"geometry":{"coordinates":[10.074167,49.89808],"type":"Point"},"properties":{"osm_id":"2861787451","tag":{"leaf_type":"broadleaved","natural":"tree"}},"type":"Feature"},
	{"geometry":{"coordinates":[10.073574,49.89847],"type":"Point"},"properties":{"osm_id":"2861787452","tag":{"leaf_type":"broadleaved","natural":"tree"}},"type":"Feature"},
	{"geometry":{"coordinates":[10.07361,49.898328],"type":"Point"},"properties":{"osm_id":"2861787454","tag":{"leaf_type":"broadleaved","natural":"tree"}},"type":"Feature"},
	{"geometry":{"coordinates":[10.073618,49.89826],"type":"Point"},"properties":{"osm_id":"2861787455","tag":{"leaf_type":"broadleaved","natural":"tree"}},"type":"Feature"},
	{"geometry":{"coordinates":[10.07374,49.898254],"type":"Point"},"properties":{"osm_id":"2861787456","tag":{"leaf_type":"broadleaved","natural":"tree"}},"type":"Feature"},
	{"geometry":{"coordinates":[10.070686,49.897329],"type":"Point"},"properties":{"osm_id":"2862604233","tag":{"leaf_type":"broadleaved","natural":"tree"}},"type":"Feature"},
	{"geometry":{"coordinates":[10.073748,49.898362],"type":"Point"},"properties":{"osm_id":"2881289842","tag":{"natural":"tree"}},"type":"Feature"},
	{"geometry":{"coordinates":[10.073597,49.898397],"type":"Point"},"properties":{"osm_id":"2881289843","tag":{"leaf_type":"broadleaved","natural":"tree"}},"type":"Feature"},
	{"geometry":{"coordinates":[10.078581,49.900305],"type":"Point"},"properties":{"osm_id":"3911165792","tag":{"natural":"tree"}},"type":"Feature"},
	{"geometry":{"coordinates":[10.07967,49.900328],"type":"Point"},"properties":{"osm_id":"3911165793","tag":{"natural":"tree"}},"type":"Feature"},
	{"geometry":{"coordinates":[10.079775,49.900328],"type":"Point"},"properties":{"osm_id":"3911165794","tag":{"natural":"tree"}},"type":"Feature"},
	{"geometry":{"coordinates":[10.079783,49.900227],"type":"Point"},"properties":{"osm_id":"3911165795","tag":{"natural":"tree"}},"type":"Feature"},
	{"geometry":{"coordinates":[10.079298,49.900209],"type":"Point"},"properties":{"osm_id":"3911165796","tag":{"natural":"tree"}},"type":"Feature"},
	{"geometry":{"coordinates":[10.078997,49.900205],"type":"Point"},"properties":{"osm_id":"3911165797","tag":{"natural":"tree"}},"type":"Feature"},
	{"geometry":{"coordinates":[10.077316,49.900153],"type":"Point"},"properties":{"osm_id":"3911165798","tag":{"natural":"tree"}},"type":"Feature"},
	{"geometry":{"coordinates":[10.077457,49.900191],"type":"Point"},"properties":{"osm_id":"3911165799","tag":{"natural":"tree"}},"type":"Feature"},
	{"geometry":{"coordinates":[10.077103,49.900144],"type":"Point"},"properties":{"osm_id":"3911165800","tag":{"natural":"tree"}},"type":"Feature"},
	{"geometry":{"coordinates":[10.060811,49.921223],"type":"Point"},"properties":{"osm_id":"3914112370","tag":{"leaf_cycle":"deciduous","leaf_type":"broadleaved","natural":"tree"}},"type":"Feature"},
	{"geometry":{"coordinates":[10.060499,49.920897],"type":"Point"},"properties":{"osm_id":"3914112371","tag":{"leaf_cycle":"deciduous","leaf_type":"broadleaved","natural":"tree"}},"type":"Feature"},
	{"geometry":{"coordinates":[10.060951,49.920762],"type":"Point"},"properties":{"osm_id":"3914112372","tag":{"leaf_cycle":"deciduous","leaf_type":"broadleaved","natural":"tree"}},"type":"Feature"},
	{"geometry":{"coordinates":[10.06043,49.922088],"type":"Point"},"properties":{"osm_id":"3914112374","tag":{"leaf_cycle":"deciduous","leaf_type":"broadleaved","natural":"tree"}},"type":"Feature"},
	{"geometry":{"coordinates":[10.023428,49.897638],"type":"Point"},"properties":{"osm_id":"3918088577","tag":{"leaf_cycle":"deciduous","leaf_type":"broadleaved","natural":"tree"}},"type":"Feature"},
	{"geometry":{"coordinates":[10.02356,49.897821],"type":"Point"},"properties":{"osm_id":"3918088578","tag":{"leaf_cycle":"deciduous","leaf_type":"broadleaved","natural":"tree"}},"type":"Feature"},
	{"geometry":{"coordinates":[10.023497,49.897736],"type":"Point"},"properties":{"osm_id":"3918088579","tag":{"leaf_cycle":"deciduous","leaf_type":"broadleaved","natural":"tree"}},"type":"Feature"},
	{"geometry":{"coordinates":[10.080924,49.925373],"type":"Point"},"properties":{"osm_id":"4298666795","tag":{"natural":"tree"}},"type":"Feature"},
	{"geometry":{"coordinates":[10.077802,49.944812],"type":"Point"},"properties":{"name":"Linde","osm_id":"5025714141","tag":{"natural":"tree"}},"type":"Feature"}
]
}
