{
"type": "FeatureCollection",
"features": [
	{"geometry":{"coordinates":[12.712655,52.676556],"type":"Point"},"properties":{"osm_id":"2894504377","tag":{"amenity":"recycling","location":"overground","recycling_type":"container"}},"type":"Feature"}
]
}
