{
"type": "FeatureCollection",
"features": [
	{"geometry":{"coordinates":[12.731575,51.030435],"type":"Point"},"properties":{"osm_id":"512075334","tag":{"amenity":"recycling","recycling:glass_bottles":"yes","recycling_type":"container"}},"type":"Feature"},
	{"geometry":{"coordinates":[12.692186,51.018869],"type":"Point"},"properties":{"osm_id":"512082184","tag":{"amenity":"recycling","recycling:cans":"yes","recycling:paper":"yes"}},"type":"Feature"},
	{"geometry":{"coordinates":[12.700005,51.019022],"type":"Point"},"properties":{"osm_id":"512082202","tag":{"amenity":"recycling","recycling:glass_bottles":"yes","recycling_type":"container"}},"type":"Feature"},
	{"geometry":{"coordinates":[12.688046,51.054668],"type":"Point"},"properties":{"osm_id":"749057194","tag":{"amenity":"waste_basket"}},"type":"Feature"},
	{"geometry":{"coordinates":[12.695178,51.050459],"type":"Point"},"properties":{"osm_id":"1116943791","tag":{"amenity":"recycling","recycling:glass_bottles":"yes","recycling_type":"container"}},"type":"Feature"},
	{"geometry":{"coordinates":[12.69836,51.053468],"type":"Point"},"properties":{"osm_id":"1224432672","tag":{"amenity":"waste_basket"}},"type":"Feature"},
	{"geometry":{"coordinates":[12.683968,51.057769],"type":"Point"},"properties":{"osm_id":"1304798612","tag":{"amenity":"recycling","location":"overground","recycling:cans":"yes","recycling:clothes":"yes","recycling:glass":"no","recycling:glass_bottles":"yes","recycling:paper":"yes","recycling_type":"container"}},"type":"Feature"},
	{"geometry":{"coordinates":[12.696315,51.058519],"type":"Point"},"properties":{"osm_id":"2506347155","tag":{"amenity":"waste_basket"}},"type":"Feature"},
	{"geometry":{"coordinates":[12.702464,51.051828],"type":"Point"},"properties":{"osm_id":"2784876270","tag":{"amenity":"waste_basket"}},"type":"Feature"},
	{"geometry":{"coordinates":[12.702568,51.051903],"type":"Point"},"properties":{"osm_id":"2784876273","tag":{"amenity":"waste_basket"}},"type":"Feature"},
	{"geometry":{"coordinates":[12.704719,51.050808],"type":"Point"},"properties":{"osm_id":"3434770944","tag":{"amenity":"recycling","recycling:glass_bottles":"yes","recycling_type":"container","wheelchair":"yes"}},"type":"Feature"},
	{"geometry":{"coordinates":[12.707524,51.046341],"type":"Point"},"properties":{"osm_id":"6244869847","tag":{"amenity":"recycling","recycling:glass_bottles":"yes","recycling_type":"container","wheelchair":"yes"}},"type":"Feature"}
]
}
