{
"type": "FeatureCollection",
"features": [
	{"geometry":{"coordinates":[12.731575,51.030435],"type":"Point"},"properties":{"osm_id":"512075334","tag":{"amenity":"recycling","recycling:glass_bottles":"yes","recycling_type":"container"}},"type":"Feature"},
	{"geometry":{"coordinates":[12.692187,51.018869],"type":"Point"},"properties":{"osm_id":"512082184","tag":{"amenity":"recycling","recycling:cans":"yes","recycling:paper":"yes"}},"type":"Feature"},
	{"geometry":{"coordinates":[12.700006,51.019023],"type":"Point"},"properties":{"osm_id":"512082202","tag":{"amenity":"recycling","recycling:glass_bottles":"yes","recycling_type":"container"}},"type":"Feature"},
	{"geometry":{"coordinates":[12.688047,51.054669],"type":"Point"},"properties":{"osm_id":"749057194","tag":{"amenity":"waste_basket"}},"type":"Feature"},
	{"geometry":{"coordinates":[12.695178,51.05046],"type":"Point"},"properties":{"osm_id":"1116943791","tag":{"amenity":"recycling","check_date:recycling":"2020-09-13","recycling:glass_bottles":"yes","recycling_type":"container"}},"type":"Feature"},
	{"geometry":{"coordinates":[12.698361,51.053468],"type":"Point"},"properties":{"osm_id":"1224432672","tag":{"amenity":"waste_basket"}},"type":"Feature"},
	{"geometry":{"coordinates":[12.683969,51.05777],"type":"Point"},"properties":{"osm_id":"1304798612","tag":{"amenity":"recycling","location":"overground","recycling:cans":"yes","recycling:clothes":"yes","recycling:glass":"no","recycling:glass_bottles":"yes","recycling:paper":"yes","recycling_type":"container"}},"type":"Feature"},
	{"geometry":{"coordinates":[12.696316,51.05852],"type":"Point"},"properties":{"osm_id":"2506347155","tag":{"amenity":"waste_basket"}},"type":"Feature"},
	{"geometry":{"coordinates":[12.702465,51.051828],"type":"Point"},"properties":{"osm_id":"2784876270","tag":{"amenity":"waste_basket"}},"type":"Feature"},
	{"geometry":{"coordinates":[12.702568,51.051904],"type":"Point"},"properties":{"osm_id":"2784876273","tag":{"amenity":"waste_basket"}},"type":"Feature"},
	{"geometry":{"coordinates":[12.704719,51.050808],"type":"Point"},"properties":{"osm_id":"3434770944","tag":{"amenity":"recycling","recycling:glass_bottles":"yes","recycling_type":"container","wheelchair":"yes"}},"type":"Feature"},
	{"geometry":{"coordinates":[12.707524,51.046342],"type":"Point"},"properties":{"osm_id":"6244869847","tag":{"amenity":"recycling","recycling:glass_bottles":"yes","recycling_type":"container","wheelchair":"yes"}},"type":"Feature"}
]
}
