{
"type": "FeatureCollection",
"features": [
	{"geometry":{"coordinates":[12.73262,46.84028],"type":"Point"},"properties":{"name":"Bau- und Recyclinghof","osm_id":"1749621459","tag":{"amenity":"recycling","recycling_type":"centre"}},"type":"Feature"}
]
}
