{
"type": "FeatureCollection",
"features": [
	{"geometry":{"coordinates":[-7.574299,54.874771],"type":"Point"},"properties":{"name":"Faerie Tree","osm_id":"7832527951","tag":{"natural":"tree"}},"type":"Feature"}
]
}
