{
"type": "FeatureCollection",
"lastupdate": "2020-08-04T00:00:00Z",
"features": [
	{"geometry":{"coordinates":[6.265987,51.930828],"type":"Point"},"properties":{"osm_id":"6343097642","tag":{"amenity":"recycling","location":"overground","recycling:glass_bottles":"yes","recycling:paper":"yes","recycling_type":"container"}},"type":"Feature"},
	{"geometry":{"coordinates":[6.262558,51.93061],"type":"Point"},"properties":{"osm_id":"6349633273","tag":{"amenity":"recycling","location":"overground","recycling:glass_bottles":"yes","recycling:paper":"yes","recycling_type":"container"}},"type":"Feature"},
	{"geometry":{"coordinates":[6.263679,51.92619],"type":"Point"},"properties":{"osm_id":"6350605621","tag":{"amenity":"waste_basket"}},"type":"Feature"},
	{"geometry":{"coordinates":[6.265007,51.932538],"type":"Point"},"properties":{"osm_id":"6356705230","tag":{"amenity":"waste_basket","waste":"trash"}},"type":"Feature"},
	{"geometry":{"coordinates":[6.265796,51.932568],"type":"Point"},"properties":{"osm_id":"6356705231","tag":{"amenity":"waste_basket","waste":"trash"}},"type":"Feature"},
	{"geometry":{"coordinates":[6.267603,51.931563],"type":"Point"},"properties":{"osm_id":"6356738368","tag":{"amenity":"waste_basket","waste":"trash"}},"type":"Feature"},
	{"geometry":{"coordinates":[6.269438,51.930959],"type":"Point"},"properties":{"osm_id":"6356738369","tag":{"amenity":"waste_basket","waste":"dog_excrement"}},"type":"Feature"},
	{"geometry":{"coordinates":[6.269456,51.930968],"type":"Point"},"properties":{"osm_id":"6356738370","tag":{"amenity":"waste_basket","waste":"trash"}},"type":"Feature"},
	{"geometry":{"coordinates":[6.268632,51.931185],"type":"Point"},"properties":{"osm_id":"6356738372","tag":{"amenity":"recycling","location":"overground","recycling:glass_bottles":"yes","recycling:paper":"yes","recycling_type":"container"}},"type":"Feature"},
	{"geometry":{"coordinates":[6.263945,51.932655],"type":"Point"},"properties":{"osm_id":"6356738661","tag":{"amenity":"waste_basket","waste":"trash"}},"type":"Feature"},
	{"geometry":{"coordinates":[6.261686,51.93037],"type":"Point"},"properties":{"osm_id":"6358934255","tag":{"amenity":"waste_basket","waste":"trash"}},"type":"Feature"},
	{"geometry":{"coordinates":[6.264477,51.930942],"type":"Point"},"properties":{"osm_id":"6358934259","tag":{"amenity":"waste_basket","waste":"trash"}},"type":"Feature"},
	{"geometry":{"coordinates":[6.256624,51.897518],"type":"Point"},"properties":{"osm_id":"6654601850","tag":{"amenity":"waste_basket"}},"type":"Feature"}
]
}
