{
"type": "FeatureCollection",
"features": [
	{"geometry":{"coordinates":[6.27538,50.963608],"type":"Point"},"properties":{"osm_id":"41740304","tag":{"amenity":"recycling"}},"type":"Feature"},
	{"geometry":{"coordinates":[6.272694,50.979702],"type":"Point"},"properties":{"osm_id":"41740315","tag":{"amenity":"recycling","recycling_type":"container"}},"type":"Feature"},
	{"geometry":{"coordinates":[6.258316,50.961212],"type":"Point"},"properties":{"osm_id":"41752067","tag":{"amenity":"recycling"}},"type":"Feature"},
	{"geometry":{"coordinates":[6.270323,50.971649],"type":"Point"},"properties":{"osm_id":"519258875","tag":{"amenity":"recycling","recycling:glass":"yes","recycling_type":"container"}},"type":"Feature"},
	{"geometry":{"coordinates":[6.292588,50.99336],"type":"Point"},"properties":{"osm_id":"726721954","tag":{"amenity":"recycling","recycling:clothes":"yes","recycling:glass":"yes"}},"type":"Feature"},
	{"geometry":{"coordinates":[6.315921,50.999771],"type":"Point"},"properties":{"osm_id":"726721965","tag":{"amenity":"recycling","recycling:clothes":"yes","recycling:glass":"yes"}},"type":"Feature"},
	{"geometry":{"coordinates":[6.313353,50.95995],"type":"Point"},"properties":{"osm_id":"842023417","tag":{"amenity":"recycling","recycling:clothes":"yes","recycling:glass":"yes"}},"type":"Feature"},
	{"geometry":{"coordinates":[6.317276,50.965359],"type":"Point"},"properties":{"osm_id":"855221055","tag":{"amenity":"recycling","recycling_type":"container"}},"type":"Feature"},
	{"geometry":{"coordinates":[6.240972,51.007252],"type":"Point"},"properties":{"osm_id":"1933933431","tag":{"addr:street":"Fochsensteg","amenity":"recycling","recycling:clothes":"yes","recycling:glass":"yes","recycling:glass_bottles":"yes","recycling_type":"container"}},"type":"Feature"},
	{"geometry":{"coordinates":[6.322868,50.964144],"type":"Point"},"properties":{"osm_id":"4365137581","tag":{"amenity":"waste_basket"}},"type":"Feature"},
	{"geometry":{"coordinates":[6.282032,50.979894],"type":"Point"},"properties":{"name":"Glascontainer","osm_id":"4854107303","tag":{"amenity":"recycling","recycling_type":"container"}},"type":"Feature"},
	{"geometry":{"coordinates":[6.271077,50.98225],"type":"Point"},"properties":{"osm_id":"4854112694","tag":{"amenity":"recycling","recycling:glass_bottles":"yes","recycling_type":"container"}},"type":"Feature"},
	{"geometry":{"coordinates":[6.317291,50.965391],"type":"Point"},"properties":{"osm_id":"5260042190","tag":{"amenity":"recycling","recycling_type":"container"}},"type":"Feature"}
]
}
