{
"type": "FeatureCollection",
"lastupdate": "2020-08-02T00:00:00Z",
"features": [
	{"geometry":{"coordinates":[6.275379,50.963607],"type":"Point"},"properties":{"osm_id":"41740304","tag":{"amenity":"recycling"}},"type":"Feature"},
	{"geometry":{"coordinates":[6.272694,50.979702],"type":"Point"},"properties":{"osm_id":"41740315","tag":{"amenity":"recycling","recycling_type":"container"}},"type":"Feature"},
	{"geometry":{"coordinates":[6.258316,50.961211],"type":"Point"},"properties":{"osm_id":"41752067","tag":{"amenity":"recycling"}},"type":"Feature"},
	{"geometry":{"coordinates":[6.270322,50.971648],"type":"Point"},"properties":{"osm_id":"519258875","tag":{"amenity":"recycling","recycling:glass":"yes","recycling_type":"container"}},"type":"Feature"},
	{"geometry":{"coordinates":[6.292587,50.99336],"type":"Point"},"properties":{"osm_id":"726721954","tag":{"amenity":"recycling","recycling:clothes":"yes","recycling:glass":"yes"}},"type":"Feature"},
	{"geometry":{"coordinates":[6.31592,50.99977],"type":"Point"},"properties":{"osm_id":"726721965","tag":{"amenity":"recycling","recycling:clothes":"yes","recycling:glass":"yes"}},"type":"Feature"},
	{"geometry":{"coordinates":[6.313353,50.95995],"type":"Point"},"properties":{"osm_id":"842023417","tag":{"amenity":"recycling","recycling:clothes":"yes","recycling:glass":"yes"}},"type":"Feature"},
	{"geometry":{"coordinates":[6.317275,50.965359],"type":"Point"},"properties":{"osm_id":"855221055","tag":{"amenity":"recycling","recycling_type":"container"}},"type":"Feature"},
	{"geometry":{"coordinates":[6.240971,51.007251],"type":"Point"},"properties":{"osm_id":"1933933431","tag":{"addr:street":"Fochsensteg","amenity":"recycling","recycling:clothes":"yes","recycling:glass":"yes","recycling:glass_bottles":"yes","recycling_type":"container"}},"type":"Feature"},
	{"geometry":{"coordinates":[6.322867,50.964144],"type":"Point"},"properties":{"osm_id":"4365137581","tag":{"amenity":"waste_basket"}},"type":"Feature"},
	{"geometry":{"coordinates":[6.282031,50.979893],"type":"Point"},"properties":{"name":"Glascontainer","osm_id":"4854107303","tag":{"amenity":"recycling","recycling_type":"container"}},"type":"Feature"},
	{"geometry":{"coordinates":[6.271077,50.98225],"type":"Point"},"properties":{"osm_id":"4854112694","tag":{"amenity":"recycling","recycling:glass_bottles":"yes","recycling_type":"container"}},"type":"Feature"},
	{"geometry":{"coordinates":[6.31729,50.96539],"type":"Point"},"properties":{"osm_id":"5260042190","tag":{"amenity":"recycling","recycling_type":"container"}},"type":"Feature"}
]
}
