{
"type": "FeatureCollection",
"lastupdate": "2020-08-01T00:00:00Z",
"features": [
	{"geometry":{"coordinates":[6.287333,49.659149],"type":"Point"},"properties":{"osm_id":"1518131846","tag":{"amenity":"waste_basket"}},"type":"Feature"},
	{"geometry":{"coordinates":[6.287201,49.659306],"type":"Point"},"properties":{"osm_id":"1518131855","tag":{"amenity":"waste_basket"}},"type":"Feature"},
	{"geometry":{"coordinates":[6.298188,49.663475],"type":"Point"},"properties":{"osm_id":"1518131874","tag":{"amenity":"waste_basket"}},"type":"Feature"},
	{"geometry":{"coordinates":[6.304022,49.666194],"type":"Point"},"properties":{"osm_id":"1518148888","tag":{"amenity":"waste_basket"}},"type":"Feature"},
	{"geometry":{"coordinates":[6.30394,49.666317],"type":"Point"},"properties":{"osm_id":"1518148891","tag":{"amenity":"waste_basket"}},"type":"Feature"},
	{"geometry":{"coordinates":[6.264625,49.620099],"type":"Point"},"properties":{"osm_id":"2167660034","tag":{"amenity":"waste_basket"}},"type":"Feature"},
	{"geometry":{"coordinates":[6.266303,49.621101],"type":"Point"},"properties":{"osm_id":"2167660036","tag":{"amenity":"waste_basket"}},"type":"Feature"},
	{"geometry":{"coordinates":[6.303035,49.666691],"type":"Point"},"properties":{"osm_id":"3725229460","tag":{"amenity":"waste_basket"}},"type":"Feature"},
	{"geometry":{"coordinates":[6.302956,49.666279],"type":"Point"},"properties":{"osm_id":"3725242156","tag":{"amenity":"waste_basket"}},"type":"Feature"},
	{"geometry":{"coordinates":[6.303135,49.666326],"type":"Point"},"properties":{"osm_id":"3725242157","tag":{"amenity":"waste_basket"}},"type":"Feature"},
	{"geometry":{"coordinates":[6.303283,49.66697],"type":"Point"},"properties":{"osm_id":"3725242468","tag":{"amenity":"waste_basket"}},"type":"Feature"},
	{"geometry":{"coordinates":[6.26873,49.630769],"type":"Point"},"properties":{"osm_id":"3729130763","tag":{"amenity":"waste_basket"}},"type":"Feature"},
	{"geometry":{"coordinates":[6.268498,49.630474],"type":"Point"},"properties":{"osm_id":"3729133038","tag":{"amenity":"waste_basket"}},"type":"Feature"},
	{"geometry":{"coordinates":[6.284611,49.645768],"type":"Point"},"properties":{"osm_id":"4570543283","tag":{"amenity":"waste_basket"}},"type":"Feature"},
	{"geometry":{"coordinates":[6.290369,49.649351],"type":"Point"},"properties":{"osm_id":"4570543288","tag":{"amenity":"waste_basket"}},"type":"Feature"},
	{"geometry":{"coordinates":[6.296712,49.652254],"type":"Point"},"properties":{"osm_id":"4570546290","tag":{"amenity":"waste_basket"}},"type":"Feature"},
	{"geometry":{"coordinates":[6.300056,49.654272],"type":"Point"},"properties":{"osm_id":"4570546292","tag":{"amenity":"waste_basket"}},"type":"Feature"},
	{"geometry":{"coordinates":[6.268448,49.630719],"type":"Point"},"properties":{"name":"Texaid","osm_id":"5001364127","tag":{"amenity":"recycling","recycling:clothes":"yes","recycling_type":"container"}},"type":"Feature"},
	{"geometry":{"coordinates":[6.303158,49.667333],"type":"Point"},"properties":{"osm_id":"5632879009","tag":{"amenity":"waste_basket"}},"type":"Feature"},
	{"geometry":{"coordinates":[6.295488,49.666492],"type":"Point"},"properties":{"osm_id":"5632879010","tag":{"amenity":"waste_basket"}},"type":"Feature"},
	{"geometry":{"coordinates":[6.29455,49.667145],"type":"Point"},"properties":{"osm_id":"5632879013","tag":{"amenity":"waste_basket"}},"type":"Feature"},
	{"geometry":{"coordinates":[6.327948,49.616305],"type":"Point"},"properties":{"osm_id":"5651496600","tag":{"amenity":"waste_basket"}},"type":"Feature"},
	{"geometry":{"coordinates":[6.269522,49.631124],"type":"Point"},"properties":{"osm_id":"5774797553","tag":{"amenity":"waste_basket"}},"type":"Feature"},
	{"geometry":{"coordinates":[6.268309,49.631066],"type":"Point"},"properties":{"osm_id":"5774802155","tag":{"amenity":"waste_basket"}},"type":"Feature"}
]
}
