{
"type": "FeatureCollection",
"lastupdate": "2020-08-05T00:00:00Z",
"features": [
	{"geometry":{"coordinates":[149.232722,-35.34671],"type":"Point"},"properties":{"osm_id":"249996226","tag":{"amenity":"waste_basket"}},"type":"Feature"},
	{"geometry":{"coordinates":[149.207211,-35.360527],"type":"Point"},"properties":{"osm_id":"5235925871","tag":{"amenity":"waste_basket"}},"type":"Feature"},
	{"geometry":{"coordinates":[149.183411,-35.324744],"type":"Point"},"properties":{"name":"Return-It Fyshwick Bulk Depot","osm_id":"6536136926","tag":{"addr:housenumber":"151","addr:street":"Gladstone Street","amenity":"recycling","recycling:cans":"yes","recycling:glass_bottles":"yes","recycling:plastic_bottles":"yes","recycling_type":"centre","website":"https://actcds.com.au/return_point/fyshwick-bulk-depot/"}},"type":"Feature"},
	{"geometry":{"coordinates":[149.230105,-35.354687],"type":"Point"},"properties":{"osm_id":"7141987344","tag":{"amenity":"waste_basket"}},"type":"Feature"},
	{"geometry":{"coordinates":[149.218154,-35.367302],"type":"Point"},"properties":{"osm_id":"7179793627","tag":{"amenity":"waste_basket","waste":"dog_excrement"}},"type":"Feature"},
	{"geometry":{"coordinates":[149.217351,-35.366942],"type":"Point"},"properties":{"osm_id":"7179793628","tag":{"amenity":"waste_basket","waste":"dog_excrement"}},"type":"Feature"},
	{"geometry":{"coordinates":[149.218662,-35.367789],"type":"Point"},"properties":{"osm_id":"7215430337","tag":{"amenity":"waste_basket"}},"type":"Feature"},
	{"geometry":{"coordinates":[149.217301,-35.366776],"type":"Point"},"properties":{"osm_id":"7215430338","tag":{"amenity":"waste_basket"}},"type":"Feature"}
]
}
