{
"type": "FeatureCollection",
"features": [
	{"geometry":{"coordinates":[-122.395512,37.604701],"type":"Point"},"properties":{"name":"Nexcycle","osm_id":"263050781","tag":{"amenity":"recycling","description":"Open Fri-Sat 9:30am-4:30pm"}},"type":"Feature"},
	{"geometry":{"coordinates":[-122.425252,37.608039],"type":"Point"},"properties":{"osm_id":"1249416435","tag":{"amenity":"recycling"}},"type":"Feature"}
]
}
