{
"type": "FeatureCollection",
"features": [
	{"geometry":{"coordinates":[-63.851753,46.397291],"type":"Point"},"properties":{"name":"White Spruce","osm_id":"3667057178","tag":{"leaf_cycle":"evergreen","leaf_type":"needleleaved","name:botanical":"picea glauca","natural":"tree"}},"type":"Feature"}
]
}
