{
"type": "FeatureCollection",
"lastupdate": "2020-08-06T00:00:00Z",
"features": [
	{"geometry":{"coordinates":[-1.699436,37.635967],"type":"Point"},"properties":{"name":"Punto Limpio","osm_id":"2421115793","tag":{"amenity":"recycling","recycling:batteries":"yes","recycling:cartons":"yes","recycling:clothes":"yes","recycling:cooking_oil":"yes","recycling:fluorescent_tubes":"yes","recycling:glass":"yes","recycling:glass_bottles":"yes","recycling:magazines":"yes","recycling:newspaper":"yes","recycling:paper":"yes","recycling:paper_packaging":"yes","recycling:plastic":"yes","recycling:plastic_bottles":"yes","recycling:plastic_packaging":"yes","recycling_type":"container"}},"type":"Feature"}
]
}
