{
"type": "FeatureCollection",
"features": [
	{"geometry":{"coordinates":[147.326117,-42.893143],"type":"Point"},"properties":{"osm_id":"944987402","tag":{"amenity":"waste_basket"}},"type":"Feature"},
	{"geometry":{"coordinates":[147.328167,-42.895805],"type":"Point"},"properties":{"osm_id":"953663486","tag":{"amenity":"waste_basket"}},"type":"Feature"},
	{"geometry":{"coordinates":[147.328453,-42.896011],"type":"Point"},"properties":{"osm_id":"953663487","tag":{"amenity":"waste_basket"}},"type":"Feature"},
	{"geometry":{"coordinates":[147.329073,-42.895706],"type":"Point"},"properties":{"osm_id":"953663488","tag":{"amenity":"waste_basket"}},"type":"Feature"},
	{"geometry":{"coordinates":[147.329961,-42.882541],"type":"Point"},"properties":{"osm_id":"2152682068","tag":{"amenity":"waste_basket"}},"type":"Feature"},
	{"geometry":{"coordinates":[147.329862,-42.882666],"type":"Point"},"properties":{"osm_id":"2152682093","tag":{"amenity":"waste_basket"}},"type":"Feature"},
	{"geometry":{"coordinates":[147.329536,-42.882486],"type":"Point"},"properties":{"osm_id":"2152682096","tag":{"amenity":"waste_basket"}},"type":"Feature"},
	{"geometry":{"coordinates":[147.329623,-42.882373],"type":"Point"},"properties":{"osm_id":"2152682203","tag":{"amenity":"waste_basket"}},"type":"Feature"},
	{"geometry":{"coordinates":[147.328329,-42.881809],"type":"Point"},"properties":{"osm_id":"2152682219","tag":{"amenity":"waste_basket"}},"type":"Feature"},
	{"geometry":{"coordinates":[147.328982,-42.882212],"type":"Point"},"properties":{"osm_id":"2152682257","tag":{"amenity":"waste_basket"}},"type":"Feature"},
	{"geometry":{"coordinates":[147.327331,-42.895283],"type":"Point"},"properties":{"osm_id":"2323039529","tag":{"amenity":"waste_basket"}},"type":"Feature"},
	{"geometry":{"coordinates":[147.327538,-42.895161],"type":"Point"},"properties":{"osm_id":"2323039531","tag":{"amenity":"waste_basket"}},"type":"Feature"},
	{"geometry":{"coordinates":[147.327329,-42.895013],"type":"Point"},"properties":{"osm_id":"2323039533","tag":{"amenity":"waste_basket"}},"type":"Feature"},
	{"geometry":{"coordinates":[147.327859,-42.895365],"type":"Point"},"properties":{"osm_id":"2323999175","tag":{"amenity":"waste_basket"}},"type":"Feature"},
	{"geometry":{"coordinates":[147.346795,-42.909279],"type":"Point"},"properties":{"osm_id":"3806703800","tag":{"amenity":"waste_basket"}},"type":"Feature"},
	{"geometry":{"coordinates":[147.331137,-42.885773],"type":"Point"},"properties":{"osm_id":"3956193661","tag":{"amenity":"waste_basket"}},"type":"Feature"},
	{"geometry":{"coordinates":[147.331193,-42.88562],"type":"Point"},"properties":{"osm_id":"3956193662","tag":{"amenity":"waste_basket"}},"type":"Feature"},
	{"geometry":{"coordinates":[147.331241,-42.883027],"type":"Point"},"properties":{"osm_id":"3956243157","tag":{"amenity":"waste_basket"}},"type":"Feature"},
	{"geometry":{"coordinates":[147.327721,-42.895005],"type":"Point"},"properties":{"name":"Lifeline Charity Donation Bin","osm_id":"4691682190","tag":{"amenity":"recycling","recycling:clothes":"yes","recycling_type":"container"}},"type":"Feature"},
	{"geometry":{"coordinates":[147.346875,-42.90904],"type":"Point"},"properties":{"osm_id":"5335960333","tag":{"amenity":"waste_basket"}},"type":"Feature"},
	{"geometry":{"coordinates":[147.331848,-42.884747],"type":"Point"},"properties":{"osm_id":"6821618086","tag":{"amenity":"waste_basket"}},"type":"Feature"},
	{"geometry":{"coordinates":[147.328777,-42.885306],"type":"Point"},"properties":{"osm_id":"6821618087","tag":{"amenity":"waste_basket"}},"type":"Feature"},
	{"geometry":{"coordinates":[147.327882,-42.886115],"type":"Point"},"properties":{"osm_id":"6821618185","tag":{"amenity":"waste_basket"}},"type":"Feature"},
	{"geometry":{"coordinates":[147.33105,-42.886292],"type":"Point"},"properties":{"osm_id":"6829244385","tag":{"amenity":"waste_basket"}},"type":"Feature"},
	{"geometry":{"coordinates":[147.332431,-42.886539],"type":"Point"},"properties":{"osm_id":"6986034587","tag":{"amenity":"waste_basket","material":"metal"}},"type":"Feature"}
]
}
