{
"type": "FeatureCollection",
"features": [
	{"geometry":{"coordinates":[-64.79,18.33119],"type":"Point"},"properties":{"name":"Love City dumpster","osm_id":"4786841666","tag":{"amenity":"waste_disposal"}},"type":"Feature"}
]
}
