{
"type": "FeatureCollection",
"lastupdate": "2020-07-31T00:00:00Z",
"features": [
	{"geometry":{"coordinates":[-122.861446,49.089708],"type":"Point"},"properties":{"osm_id":"3612036771","tag":{"amenity":"waste_basket"}},"type":"Feature"},
	{"geometry":{"coordinates":[-122.804255,49.045838],"type":"Point"},"properties":{"osm_id":"4162408150","tag":{"amenity":"waste_basket"}},"type":"Feature"},
	{"geometry":{"coordinates":[-122.812077,49.065245],"type":"Point"},"properties":{"osm_id":"4162408268","tag":{"amenity":"waste_basket"}},"type":"Feature"},
	{"geometry":{"coordinates":[-122.805204,49.06229],"type":"Point"},"properties":{"osm_id":"4173940293","tag":{"amenity":"waste_basket"}},"type":"Feature"},
	{"geometry":{"coordinates":[-122.804141,49.062351],"type":"Point"},"properties":{"osm_id":"4173940295","tag":{"amenity":"waste_basket"}},"type":"Feature"},
	{"geometry":{"coordinates":[-122.814516,49.074811],"type":"Point"},"properties":{"osm_id":"4577059151","tag":{"amenity":"recycling","recycling_type":"container"}},"type":"Feature"},
	{"geometry":{"coordinates":[-122.865964,49.09005],"type":"Point"},"properties":{"osm_id":"4835703773","tag":{"amenity":"waste_basket"}},"type":"Feature"},
	{"geometry":{"coordinates":[-122.842264,49.064886],"type":"Point"},"properties":{"osm_id":"5035489987","tag":{"amenity":"waste_basket"}},"type":"Feature"},
	{"geometry":{"coordinates":[-122.834986,49.060677],"type":"Point"},"properties":{"name":"White Rock Return-It Depot","osm_id":"6211138616","tag":{"addr:housenumber":"3221","addr:street":"140 Street","amenity":"recycling","opening_hours":"Mo-Sa 09:00-18:00; Su 10:00-17:00; PH off","phone":"+1-778-294-9919","recycling_type":"centre","website":"https://www.return-it.ca/locations/white-rock-return-it-depot"}},"type":"Feature"},
	{"geometry":{"coordinates":[-122.857288,49.049564],"type":"Point"},"properties":{"osm_id":"7542396157","tag":{"amenity":"waste_basket"}},"type":"Feature"}
]
}
