{
"type": "FeatureCollection",
"lastupdate": "2020-08-06T00:00:00Z",
"features": [
	{"geometry":{"coordinates":[-122.855113,45.12546],"type":"Point"},"properties":{"name":"M & M Towing","osm_id":"3614227626","tag":{"amenity":"recycling"}},"type":"Feature"}
]
}
