{
"type": "FeatureCollection",
"features": [
	{"geometry":{"coordinates":[-122.855113,45.125461],"type":"Point"},"properties":{"name":"M & M Towing","osm_id":"3614227626","tag":{"amenity":"recycling"}},"type":"Feature"}
]
}
