{
"type": "FeatureCollection",
"features": [
	{"geometry":{"coordinates":[-3.13929,11.138454],"type":"Point"},"properties":{"name":"Baobab","osm_id":"813533401","tag":{"natural":"tree"}},"type":"Feature"}
]
}
