{
"type": "FeatureCollection",
"lastupdate": "2020-08-05T00:00:00Z",
"features": [
	{"geometry":{"coordinates":[-2.613049,56.60175],"type":"Point"},"properties":{"name":"Letham Grange Hotel","osm_id":"540940208","tag":{"amenity":"recycling","tourism":"hotel"}},"type":"Feature"}
]
}
