{
"type": "FeatureCollection",
"features": [
	{"geometry":{"coordinates":[-2.613049,56.601751],"type":"Point"},"properties":{"name":"Letham Grange Hotel","osm_id":"540940208","tag":{"amenity":"recycling","tourism":"hotel"}},"type":"Feature"}
]
}
