{
"type": "FeatureCollection",
"features": [
	{"geometry":{"coordinates":[-2.616313,51.193391],"type":"Point"},"properties":{"name":"Hill Quarry Recycling","osm_id":"1449108953","tag":{"amenity":"recycling","recycling:batteries":"yes","recycling:cans":"yes","recycling:cardboard":"yes","recycling:electrical_appliances":"yes","recycling:glass":"yes","recycling:glass_bottles":"yes","recycling:green_waste":"yes","recycling:magazines":"yes","recycling:newspaper":"yes","recycling:paper":"yes","recycling:paper_packaging":"yes","recycling:plastic":"yes","recycling:plastic_bottles":"yes","recycling:small_appliances":"yes","recycling:waste":"yes","recycling_type":"centre"}},"type":"Feature"}
]
}
