{
"type": "FeatureCollection",
"features": [
	{"geometry":{"coordinates":[-2.595604,47.794317],"type":"Point"},"properties":{"osm_id":"3659357846","tag":{"addr:city":"Tr\u00e9dion","addr:postcode":"56250","amenity":"recycling","recycling:cans":"yes","recycling:glass":"yes","recycling:paper":"yes"}},"type":"Feature"}
]
}
