{
"type": "FeatureCollection",
"features": [
	{"geometry":{"coordinates":[-2.59425,47.604758],"type":"Point"},"properties":{"osm_id":"2640194447","tag":{"amenity":"recycling","recycling_type":"container"}},"type":"Feature"},
	{"geometry":{"coordinates":[-2.630496,47.580037],"type":"Point"},"properties":{"osm_id":"2844275641","tag":{"amenity":"waste_disposal"}},"type":"Feature"},
	{"geometry":{"coordinates":[-2.635445,47.630294],"type":"Point"},"properties":{"osm_id":"2952594364","tag":{"amenity":"recycling","recycling:glass":"yes","recycling_type":"container"}},"type":"Feature"},
	{"geometry":{"coordinates":[-2.614272,47.610513],"type":"Point"},"properties":{"osm_id":"3544962336","tag":{"amenity":"waste_basket"}},"type":"Feature"},
	{"geometry":{"coordinates":[-2.614505,47.610804],"type":"Point"},"properties":{"osm_id":"3544962343","tag":{"amenity":"waste_basket"}},"type":"Feature"},
	{"geometry":{"coordinates":[-2.593216,47.604205],"type":"Point"},"properties":{"osm_id":"3838470855","tag":{"amenity":"recycling","operator":"SYSEM","recycling:cans":"yes","recycling:clothes":"no","recycling:glass":"no","recycling:glass_bottles":"no","recycling:paper":"yes","recycling:plastic":"yes","recycling_type":"container","wheelchair":"yes"}},"type":"Feature"},
	{"geometry":{"coordinates":[-2.601321,47.606339],"type":"Point"},"properties":{"osm_id":"3838470860","tag":{"amenity":"recycling","operator":"SYSEM","recycling:cans":"yes","recycling:clothes":"no","recycling:glass":"no","recycling:glass_bottles":"no","recycling:paper":"yes","recycling:plastic":"yes","recycling_type":"container","wheelchair":"yes"}},"type":"Feature"},
	{"geometry":{"coordinates":[-2.58548,47.605503],"type":"Point"},"properties":{"name":"Poubelles","osm_id":"4426768478","tag":{"amenity":"waste_basket"}},"type":"Feature"},
	{"geometry":{"coordinates":[-2.585579,47.607],"type":"Point"},"properties":{"name":"Poubelles de la residence","osm_id":"4426768479","tag":{"amenity":"waste_basket"}},"type":"Feature"},
	{"geometry":{"coordinates":[-2.587347,47.607196],"type":"Point"},"properties":{"osm_id":"6674299680","tag":{"amenity":"recycling","operator":"Vannes Agglo","recycling_type":"container"}},"type":"Feature"}
]
}
