{
"type": "FeatureCollection",
"features": [
	{"geometry":{"coordinates":[-1.708264,50.803488],"type":"Point"},"properties":{"name":"Navigation Tree","osm_id":"400010334","tag":{"natural":"tree"}},"type":"Feature"},
	{"geometry":{"coordinates":[-1.755359,50.844812],"type":"Point"},"properties":{"osm_id":"5667664394","tag":{"natural":"tree"}},"type":"Feature"}
]
}
