{
"type": "FeatureCollection",
"features": [
	{"geometry":{"coordinates":[-1.676851,43.134239],"type":"Point"},"properties":{"osm_id":"3104563564","tag":{"natural":"tree"}},"type":"Feature"},
	{"geometry":{"coordinates":[-1.676752,43.134169],"type":"Point"},"properties":{"osm_id":"3104563589","tag":{"natural":"tree"}},"type":"Feature"},
	{"geometry":{"coordinates":[-1.741497,43.165451],"type":"Point"},"properties":{"name":"Tejo","osm_id":"4836306636","tag":{"natural":"tree"}},"type":"Feature"},
	{"geometry":{"coordinates":[-1.74127,43.165448],"type":"Point"},"properties":{"name":"Tejo","osm_id":"4836307015","tag":{"natural":"tree"}},"type":"Feature"},
	{"geometry":{"coordinates":[-1.740145,43.165144],"type":"Point"},"properties":{"name":"Tejo","osm_id":"4836308191","tag":{"natural":"tree"}},"type":"Feature"},
	{"geometry":{"coordinates":[-1.740523,43.165154],"type":"Point"},"properties":{"name":"Tejo","osm_id":"4841373146","tag":{"natural":"tree"}},"type":"Feature"},
	{"geometry":{"coordinates":[-1.740878,43.166047],"type":"Point"},"properties":{"name":"Roble","osm_id":"4841375825","tag":{"natural":"tree"}},"type":"Feature"},
	{"geometry":{"coordinates":[-1.710836,43.133327],"type":"Point"},"properties":{"osm_id":"5355231234","tag":{"natural":"tree"}},"type":"Feature"},
	{"geometry":{"coordinates":[-1.679556,43.135062],"type":"Point"},"properties":{"osm_id":"7603216341","tag":{"natural":"tree"}},"type":"Feature"},
	{"geometry":{"coordinates":[-1.671879,43.133249],"type":"Point"},"properties":{"osm_id":"7620665452","tag":{"natural":"tree"}},"type":"Feature"},
	{"geometry":{"coordinates":[-1.673105,43.133454],"type":"Point"},"properties":{"osm_id":"7620704713","tag":{"natural":"tree"}},"type":"Feature"},
	{"geometry":{"coordinates":[-1.673101,43.133409],"type":"Point"},"properties":{"osm_id":"7620704714","tag":{"natural":"tree"}},"type":"Feature"},
	{"geometry":{"coordinates":[-1.673097,43.13338],"type":"Point"},"properties":{"osm_id":"7620704715","tag":{"natural":"tree"}},"type":"Feature"},
	{"geometry":{"coordinates":[-1.673093,43.133338],"type":"Point"},"properties":{"osm_id":"7620704716","tag":{"natural":"tree"}},"type":"Feature"},
	{"geometry":{"coordinates":[-1.673078,43.133306],"type":"Point"},"properties":{"osm_id":"7620704717","tag":{"natural":"tree"}},"type":"Feature"},
	{"geometry":{"coordinates":[-1.67307,43.133278],"type":"Point"},"properties":{"osm_id":"7620704718","tag":{"natural":"tree"}},"type":"Feature"},
	{"geometry":{"coordinates":[-1.680978,43.136682],"type":"Point"},"properties":{"osm_id":"7726566089","tag":{"natural":"tree"}},"type":"Feature"}
]
}
