{
"type": "FeatureCollection",
"features": [
	{"geometry":{"coordinates":[-1.693337,38.621343],"type":"Point"},"properties":{"name":"Pino de El Raso","osm_id":"7417599827","tag":{"denotation":"single","natural":"tree"}},"type":"Feature"}
]
}
