{
"type": "FeatureCollection",
"lastupdate": "2020-08-01T00:00:00Z",
"features": [
	{"geometry":{"coordinates":[-0.486866,51.140111],"type":"Point"},"properties":{"name":"Recycling containers","osm_id":"3512659393","tag":{"addr:city":"Cranleigh","addr:postcode":"GU6 8AF","addr:street":"Village Way","amenity":"recycling","recycling:cans":"yes","recycling:cardboard":"yes","recycling:cartons":"yes","recycling:clothes":"yes","recycling:foil":"yes","recycling:glass":"yes","recycling:paper":"yes","recycling:plastic_bottles":"yes","recycling:plastic_packaging":"yes","recycling:small_appliances":"yes","recycling_type":"container"}},"type":"Feature"}
]
}
