{
"type": "FeatureCollection",
"features": [
	{"geometry":{"coordinates":[-0.487477,45.766017],"type":"Point"},"properties":{"osm_id":"7869499125","tag":{"amenity":"recycling","brand":"Le Relais","charity":"yes","recycling:clothes":"yes","recycling:shoes":"yes","recycling_type":"container","website":"https://www.lerelais.org/"}},"type":"Feature"}
]
}
