{
"type": "FeatureCollection",
"features": [
	{"geometry":{"coordinates":[9.432924,52.337157],"type":"Point"},"properties":{"osm_id":"690146529","tag":{"amenity":"recycling","recycling_type":"container"}},"type":"Feature"},
	{"geometry":{"coordinates":[9.430692,52.324652],"type":"Point"},"properties":{"osm_id":"743224719","tag":{"amenity":"waste_basket"}},"type":"Feature"},
	{"geometry":{"coordinates":[9.431823,52.323671],"type":"Point"},"properties":{"osm_id":"743224743","tag":{"amenity":"waste_basket"}},"type":"Feature"},
	{"geometry":{"coordinates":[9.440437,52.324423],"type":"Point"},"properties":{"osm_id":"2213172970","tag":{"amenity":"waste_basket"}},"type":"Feature"},
	{"geometry":{"coordinates":[9.414019,52.333816],"type":"Point"},"properties":{"osm_id":"4341052237","tag":{"amenity":"recycling"}},"type":"Feature"},
	{"geometry":{"coordinates":[9.414552,52.33375],"type":"Point"},"properties":{"osm_id":"7966729569","tag":{"amenity":"recycling","recycling:glass_bottles":"yes","recycling_type":"container"}},"type":"Feature"},
	{"geometry":{"coordinates":[9.407009,52.353666],"type":"Point"},"properties":{"osm_id":"9103422777","tag":{"amenity":"recycling","recycling:glass_bottles":"yes","recycling_type":"container","wheelchair":"yes"}},"type":"Feature"},
	{"geometry":{"coordinates":[9.407026,52.353619],"type":"Point"},"properties":{"osm_id":"9105204937","tag":{"amenity":"recycling","operator":"Deutsches Rotes Kreuz","recycling:clothes":"yes","recycling:shoes":"yes","recycling_type":"container","wheelchair":"yes"}},"type":"Feature"},
	{"geometry":{"coordinates":[9.439705,52.368411],"type":"Point"},"properties":{"name":"Wertstoffhof Kolenfeld","osm_id":"9152465537","tag":{"amenity":"recycling","building":"industrial","operator":"aha","recycling:cans":"yes","recycling:cardboard":"yes","recycling:clothes":"yes","recycling:glass":"yes","recycling:glass_bottles":"yes","recycling:paper":"yes","recycling:plastic":"yes","recycling:plastic_packaging":"yes","recycling:waste":"yes","recycling_type":"centre","website":"https://www.aha-region.de/"}},"type":"Feature"}
]
}
