{
"type": "FeatureCollection",
"features": [
	{"geometry":{"coordinates":[9.413403,49.092703],"type":"Point"},"properties":{"osm_id":"927310014","tag":{"amenity":"recycling","recycling:batteries":"no","recycling:glass":"yes","recycling:paper":"yes","recycling_type":"container"}},"type":"Feature"},
	{"geometry":{"coordinates":[9.478037,49.092358],"type":"Point"},"properties":{"name":"Recyclinghof","osm_id":"1577936168","tag":{"amenity":"recycling","recycling_type":"centre"}},"type":"Feature"},
	{"geometry":{"coordinates":[9.445671,49.040903],"type":"Point"},"properties":{"osm_id":"1591161384","tag":{"amenity":"recycling","recycling:glass_bottles":"yes","recycling:paper":"yes","recycling_type":"container"}},"type":"Feature"},
	{"geometry":{"coordinates":[9.469833,49.04978],"type":"Point"},"properties":{"osm_id":"1591162100","tag":{"amenity":"recycling","recycling:glass":"yes","recycling:paper":"yes","recycling_type":"container"}},"type":"Feature"},
	{"geometry":{"coordinates":[9.45497,49.065487],"type":"Point"},"properties":{"osm_id":"1591162346","tag":{"amenity":"recycling","recycling:glass":"yes","recycling:paper":"yes","recycling_type":"container"}},"type":"Feature"},
	{"geometry":{"coordinates":[9.463463,49.077727],"type":"Point"},"properties":{"osm_id":"3274943068","tag":{"amenity":"recycling","location":"overground","material":"metal","opening_hours":"Mo-Sa 08:00-18:00","operator":"Landkreis Heilbronn","recycling:cans":"yes","recycling:glass":"yes","recycling:paper":"yes","recycling_type":"container"}},"type":"Feature"},
	{"geometry":{"coordinates":[9.410468,49.061311],"type":"Point"},"properties":{"osm_id":"6354140143","tag":{"amenity":"waste_basket"}},"type":"Feature"},
	{"geometry":{"coordinates":[9.410662,49.091324],"type":"Point"},"properties":{"osm_id":"8387463523","tag":{"amenity":"recycling","recycling:batteries":"no","recycling:clothes":"yes","recycling:glass":"yes","recycling:paper":"yes","recycling_type":"container"}},"type":"Feature"},
	{"geometry":{"coordinates":[9.477648,49.092582],"type":"Point"},"properties":{"osm_id":"8605115268","tag":{"amenity":"recycling","recycling:clothes":"yes","recycling_type":"container"}},"type":"Feature"}
]
}
