{
"type": "FeatureCollection",
"lastupdate": "2020-08-02T00:00:00Z",
"features": [
	{"geometry":{"coordinates":[9.413403,49.092703],"type":"Point"},"properties":{"osm_id":"927310014","tag":{"amenity":"recycling","recycling:batteries":"no","recycling:glass":"yes","recycling:paper":"yes","recycling_type":"container"}},"type":"Feature"},
	{"geometry":{"coordinates":[9.478037,49.092358],"type":"Point"},"properties":{"name":"Recyclinghof","osm_id":"1577936168","tag":{"amenity":"recycling","recycling_type":"centre"}},"type":"Feature"},
	{"geometry":{"coordinates":[9.445671,49.040903],"type":"Point"},"properties":{"osm_id":"1591161384","tag":{"amenity":"recycling","recycling:glass":"yes","recycling:paper":"yes","recycling_type":"container"}},"type":"Feature"},
	{"geometry":{"coordinates":[9.469833,49.04978],"type":"Point"},"properties":{"osm_id":"1591162100","tag":{"amenity":"recycling","recycling:glass":"yes","recycling:paper":"yes","recycling_type":"container"}},"type":"Feature"},
	{"geometry":{"coordinates":[9.45497,49.065487],"type":"Point"},"properties":{"osm_id":"1591162346","tag":{"amenity":"recycling","recycling:glass":"yes","recycling:paper":"yes","recycling_type":"container"}},"type":"Feature"},
	{"geometry":{"coordinates":[9.463463,49.077727],"type":"Point"},"properties":{"osm_id":"3274943068","tag":{"amenity":"recycling","location":"overground","material":"metal","operator":"Gemeinde W\u00fcstenrot","recycling:cans":"yes","recycling:clothes":"yes","recycling:glass":"yes","recycling:paper":"yes","recycling_type":"container"}},"type":"Feature"},
	{"geometry":{"coordinates":[9.410468,49.061311],"type":"Point"},"properties":{"osm_id":"6354140143","tag":{"amenity":"waste_basket"}},"type":"Feature"}
]
}
