{
"type": "FeatureCollection",
"lastupdate": "2020-08-04T00:00:00Z",
"features": [
	{"geometry":{"coordinates":[9.485182,45.744583],"type":"Point"},"properties":{"name":"Piattaforma Ecologica","osm_id":"491292489","tag":{"amenity":"recycling"}},"type":"Feature"},
	{"geometry":{"coordinates":[9.406483,45.722681],"type":"Point"},"properties":{"osm_id":"527391227","tag":{"amenity":"recycling"}},"type":"Feature"},
	{"geometry":{"coordinates":[9.459563,45.710888],"type":"Point"},"properties":{"osm_id":"2451966974","tag":{"amenity":"recycling","recycling:batteries":"yes","recycling:books":"yes","recycling:cartons":"yes","recycling:clothes":"yes","recycling:electrical_appliances":"yes","recycling:glass":"yes","recycling:glass_bottles":"yes","recycling:green_waste":"yes","recycling:magazines":"yes","recycling:newspaper":"yes","recycling:paper":"yes","recycling:paper_packaging":"yes","recycling:plastic":"yes","recycling:plastic_bottles":"yes","recycling:small_appliances":"yes","recycling:waste":"yes","recycling:wood":"yes","recycling_type":"centre"}},"type":"Feature"},
	{"geometry":{"coordinates":[9.450661,45.743518],"type":"Point"},"properties":{"osm_id":"5748770932","tag":{"amenity":"waste_basket"}},"type":"Feature"},
	{"geometry":{"coordinates":[9.461624,45.732696],"type":"Point"},"properties":{"osm_id":"5950685693","tag":{"amenity":"waste_basket","description":"Bidone per la raccolta dei medicinali scaduti","waste":"medicines"}},"type":"Feature"},
	{"geometry":{"coordinates":[9.461618,45.732725],"type":"Point"},"properties":{"osm_id":"5950685694","tag":{"amenity":"waste_basket","description":"Bidone per la raccolta pile usate","waste":"battery"}},"type":"Feature"},
	{"geometry":{"coordinates":[9.443059,45.71407],"type":"Point"},"properties":{"osm_id":"6448299294","tag":{"amenity":"waste_basket"}},"type":"Feature"},
	{"geometry":{"coordinates":[9.44311,45.714061],"type":"Point"},"properties":{"osm_id":"6448299295","tag":{"amenity":"waste_basket"}},"type":"Feature"},
	{"geometry":{"coordinates":[9.44315,45.714025],"type":"Point"},"properties":{"osm_id":"6448299296","tag":{"amenity":"waste_basket"}},"type":"Feature"},
	{"geometry":{"coordinates":[9.443203,45.713976],"type":"Point"},"properties":{"osm_id":"6448299297","tag":{"amenity":"waste_basket"}},"type":"Feature"},
	{"geometry":{"coordinates":[9.443282,45.713922],"type":"Point"},"properties":{"osm_id":"6448299298","tag":{"amenity":"waste_basket"}},"type":"Feature"},
	{"geometry":{"coordinates":[9.443361,45.71387],"type":"Point"},"properties":{"osm_id":"6448299299","tag":{"amenity":"waste_basket"}},"type":"Feature"}
]
}
