{
"type": "FeatureCollection",
"lastupdate": "2020-08-02T00:00:00Z",
"features": [
	{"geometry":{"coordinates":[16.62258,48.377678],"type":"Point"},"properties":{"name":"Wertstoffsammelstelle","osm_id":"2921581853","tag":{"amenity":"recycling","recycling:clothes":"yes","recycling:glass":"yes"}},"type":"Feature"},
	{"geometry":{"coordinates":[16.642407,48.36812],"type":"Point"},"properties":{"osm_id":"3547297418","tag":{"amenity":"waste_basket"}},"type":"Feature"}
]
}
