{
"type": "FeatureCollection",
"features": [
	{"geometry":{"coordinates":[7.968666,49.869958],"type":"Point"},"properties":{"osm_id":"3079801786","tag":{"natural":"tree"}},"type":"Feature"},
	{"geometry":{"coordinates":[7.967118,49.870934],"type":"Point"},"properties":{"osm_id":"3079801792","tag":{"natural":"tree"}},"type":"Feature"},
	{"geometry":{"coordinates":[7.966594,49.871414],"type":"Point"},"properties":{"osm_id":"3079801801","tag":{"natural":"tree"}},"type":"Feature"},
	{"geometry":{"coordinates":[7.966095,49.871901],"type":"Point"},"properties":{"osm_id":"3079801806","tag":{"natural":"tree"}},"type":"Feature"},
	{"geometry":{"coordinates":[7.966446,49.854836],"type":"Point"},"properties":{"osm_id":"3659456152","tag":{"natural":"tree"}},"type":"Feature"},
	{"geometry":{"coordinates":[7.976331,49.871699],"type":"Point"},"properties":{"osm_id":"3798714215","tag":{"natural":"tree"}},"type":"Feature"},
	{"geometry":{"coordinates":[7.99667,49.885752],"type":"Point"},"properties":{"osm_id":"3798718369","tag":{"natural":"tree"}},"type":"Feature"},
	{"geometry":{"coordinates":[7.986643,49.862525],"type":"Point"},"properties":{"name":"Freiheitsbaum","osm_id":"5782201802","tag":{"natural":"tree"}},"type":"Feature"},
	{"geometry":{"coordinates":[7.984504,49.860596],"type":"Point"},"properties":{"osm_id":"6205242233","tag":{"natural":"tree"}},"type":"Feature"},
	{"geometry":{"coordinates":[7.98393,49.860758],"type":"Point"},"properties":{"osm_id":"6205242234","tag":{"natural":"tree"}},"type":"Feature"},
	{"geometry":{"coordinates":[7.984034,49.860663],"type":"Point"},"properties":{"osm_id":"6205242235","tag":{"natural":"tree"}},"type":"Feature"},
	{"geometry":{"coordinates":[7.98416,49.860634],"type":"Point"},"properties":{"osm_id":"6205242236","tag":{"natural":"tree"}},"type":"Feature"},
	{"geometry":{"coordinates":[7.984246,49.860703],"type":"Point"},"properties":{"osm_id":"6205242237","tag":{"natural":"tree"}},"type":"Feature"},
	{"geometry":{"coordinates":[7.992564,49.859971],"type":"Point"},"properties":{"osm_id":"7710474953","tag":{"natural":"tree"}},"type":"Feature"},
	{"geometry":{"coordinates":[7.98246,49.867585],"type":"Point"},"properties":{"osm_id":"7712113243","tag":{"natural":"tree"}},"type":"Feature"},
	{"geometry":{"coordinates":[7.982172,49.867058],"type":"Point"},"properties":{"osm_id":"7712113244","tag":{"natural":"tree"}},"type":"Feature"},
	{"geometry":{"coordinates":[7.981443,49.8674],"type":"Point"},"properties":{"osm_id":"7712113245","tag":{"natural":"tree"}},"type":"Feature"},
	{"geometry":{"coordinates":[7.979648,49.867022],"type":"Point"},"properties":{"osm_id":"7712113246","tag":{"natural":"tree"}},"type":"Feature"},
	{"geometry":{"coordinates":[7.980936,49.866089],"type":"Point"},"properties":{"osm_id":"7712119511","tag":{"natural":"tree"}},"type":"Feature"},
	{"geometry":{"coordinates":[7.98199,49.865764],"type":"Point"},"properties":{"osm_id":"7712119528","tag":{"natural":"tree"}},"type":"Feature"},
	{"geometry":{"coordinates":[7.98414,49.865682],"type":"Point"},"properties":{"osm_id":"7712119543","tag":{"natural":"tree"}},"type":"Feature"},
	{"geometry":{"coordinates":[7.983112,49.865811],"type":"Point"},"properties":{"osm_id":"7712119561","tag":{"natural":"tree"}},"type":"Feature"}
]
}
