{
"type": "FeatureCollection",
"features": [
	{"geometry":{"coordinates":[7.968666,49.869958],"type":"Point"},"properties":{"osm_id":"3079801786","tag":{"natural":"tree"}},"type":"Feature"},
	{"geometry":{"coordinates":[7.967117,49.870934],"type":"Point"},"properties":{"osm_id":"3079801792","tag":{"natural":"tree"}},"type":"Feature"},
	{"geometry":{"coordinates":[7.966593,49.871413],"type":"Point"},"properties":{"osm_id":"3079801801","tag":{"natural":"tree"}},"type":"Feature"},
	{"geometry":{"coordinates":[7.966095,49.871901],"type":"Point"},"properties":{"osm_id":"3079801806","tag":{"natural":"tree"}},"type":"Feature"},
	{"geometry":{"coordinates":[7.966445,49.854836],"type":"Point"},"properties":{"osm_id":"3659456152","tag":{"natural":"tree"}},"type":"Feature"},
	{"geometry":{"coordinates":[7.976331,49.871699],"type":"Point"},"properties":{"osm_id":"3798714215","tag":{"natural":"tree"}},"type":"Feature"},
	{"geometry":{"coordinates":[7.99667,49.885751],"type":"Point"},"properties":{"osm_id":"3798718369","tag":{"natural":"tree"}},"type":"Feature"},
	{"geometry":{"coordinates":[7.986643,49.862524],"type":"Point"},"properties":{"name":"Freiheitsbaum","osm_id":"5782201802","tag":{"natural":"tree"}},"type":"Feature"},
	{"geometry":{"coordinates":[7.984503,49.860595],"type":"Point"},"properties":{"osm_id":"6205242233","tag":{"natural":"tree"}},"type":"Feature"},
	{"geometry":{"coordinates":[7.983929,49.860758],"type":"Point"},"properties":{"osm_id":"6205242234","tag":{"natural":"tree"}},"type":"Feature"},
	{"geometry":{"coordinates":[7.984034,49.860663],"type":"Point"},"properties":{"osm_id":"6205242235","tag":{"natural":"tree"}},"type":"Feature"},
	{"geometry":{"coordinates":[7.98416,49.860633],"type":"Point"},"properties":{"osm_id":"6205242236","tag":{"natural":"tree"}},"type":"Feature"},
	{"geometry":{"coordinates":[7.984246,49.860703],"type":"Point"},"properties":{"osm_id":"6205242237","tag":{"natural":"tree"}},"type":"Feature"},
	{"geometry":{"coordinates":[7.992563,49.85997],"type":"Point"},"properties":{"osm_id":"7710474953","tag":{"natural":"tree"}},"type":"Feature"},
	{"geometry":{"coordinates":[7.982459,49.867584],"type":"Point"},"properties":{"osm_id":"7712113243","tag":{"natural":"tree"}},"type":"Feature"},
	{"geometry":{"coordinates":[7.982172,49.867057],"type":"Point"},"properties":{"osm_id":"7712113244","tag":{"natural":"tree"}},"type":"Feature"},
	{"geometry":{"coordinates":[7.981443,49.8674],"type":"Point"},"properties":{"osm_id":"7712113245","tag":{"natural":"tree"}},"type":"Feature"},
	{"geometry":{"coordinates":[7.979648,49.867022],"type":"Point"},"properties":{"osm_id":"7712113246","tag":{"natural":"tree"}},"type":"Feature"},
	{"geometry":{"coordinates":[7.980936,49.866089],"type":"Point"},"properties":{"osm_id":"7712119511","tag":{"natural":"tree"}},"type":"Feature"},
	{"geometry":{"coordinates":[7.981989,49.865763],"type":"Point"},"properties":{"osm_id":"7712119528","tag":{"natural":"tree"}},"type":"Feature"},
	{"geometry":{"coordinates":[7.984139,49.865682],"type":"Point"},"properties":{"osm_id":"7712119543","tag":{"natural":"tree"}},"type":"Feature"},
	{"geometry":{"coordinates":[7.983111,49.865811],"type":"Point"},"properties":{"osm_id":"7712119561","tag":{"natural":"tree"}},"type":"Feature"}
]
}
