{
"type": "FeatureCollection",
"features": [
	{"geometry":{"coordinates":[7.980136,25.576995],"type":"Point"},"properties":{"name":"Acacia","osm_id":"7644312690","tag":{"natural":"tree"}},"type":"Feature"}
]
}
