{
"type": "FeatureCollection",
"features": [
	{"geometry":{"coordinates":[7.918861,25.156454],"type":"Point"},"properties":{"name":"Acacia","osm_id":"7695198044","tag":{"natural":"tree"}},"type":"Feature"}
]
}
