{
"type": "FeatureCollection",
"features": [
	{"geometry":{"coordinates":[7.991462,24.920263],"type":"Point"},"properties":{"name":"Acacia","osm_id":"7171365972","tag":{"leaf_cycle":"semi_evergreen","leaf_type":"needleleaved","natural":"tree"}},"type":"Feature"},
	{"geometry":{"coordinates":[7.918929,24.890645],"type":"Point"},"properties":{"name":"Acacia","osm_id":"7803625629","tag":{"natural":"tree"}},"type":"Feature"},
	{"geometry":{"coordinates":[7.986137,24.870273],"type":"Point"},"properties":{"name":"Acacia","osm_id":"7804700606","tag":{"natural":"tree"}},"type":"Feature"}
]
}
