{
"type": "FeatureCollection",
"features": [
	{"geometry":{"coordinates":[7.989799,13.753661],"type":"Point"},"properties":{"osm_id":"5483014849","tag":{"natural":"tree"}},"type":"Feature"},
	{"geometry":{"coordinates":[7.98973,13.75365],"type":"Point"},"properties":{"osm_id":"5483014850","tag":{"natural":"tree"}},"type":"Feature"},
	{"geometry":{"coordinates":[7.989823,13.753619],"type":"Point"},"properties":{"osm_id":"5483014851","tag":{"natural":"tree"}},"type":"Feature"},
	{"geometry":{"coordinates":[7.989883,13.753467],"type":"Point"},"properties":{"osm_id":"5483014852","tag":{"natural":"tree"}},"type":"Feature"},
	{"geometry":{"coordinates":[7.990249,13.753346],"type":"Point"},"properties":{"osm_id":"5483014853","tag":{"natural":"tree"}},"type":"Feature"},
	{"geometry":{"coordinates":[7.99009,13.753404],"type":"Point"},"properties":{"osm_id":"5483014854","tag":{"natural":"tree"}},"type":"Feature"},
	{"geometry":{"coordinates":[7.989856,13.75337],"type":"Point"},"properties":{"osm_id":"5483014855","tag":{"natural":"tree"}},"type":"Feature"},
	{"geometry":{"coordinates":[7.989838,13.753481],"type":"Point"},"properties":{"osm_id":"5483014856","tag":{"natural":"tree"}},"type":"Feature"},
	{"geometry":{"coordinates":[7.989769,13.753396],"type":"Point"},"properties":{"osm_id":"5483014857","tag":{"natural":"tree"}},"type":"Feature"},
	{"geometry":{"coordinates":[7.990175,13.753151],"type":"Point"},"properties":{"osm_id":"5483014858","tag":{"natural":"tree"}},"type":"Feature"},
	{"geometry":{"coordinates":[7.990134,13.753215],"type":"Point"},"properties":{"osm_id":"5483014859","tag":{"natural":"tree"}},"type":"Feature"},
	{"geometry":{"coordinates":[7.989941,13.753288],"type":"Point"},"properties":{"osm_id":"5483014860","tag":{"natural":"tree"}},"type":"Feature"},
	{"geometry":{"coordinates":[7.989965,13.753222],"type":"Point"},"properties":{"osm_id":"5483014861","tag":{"natural":"tree"}},"type":"Feature"},
	{"geometry":{"coordinates":[7.989854,13.75308],"type":"Point"},"properties":{"osm_id":"5483014862","tag":{"natural":"tree"}},"type":"Feature"},
	{"geometry":{"coordinates":[7.989829,13.753119],"type":"Point"},"properties":{"osm_id":"5483014863","tag":{"natural":"tree"}},"type":"Feature"},
	{"geometry":{"coordinates":[7.989847,13.753576],"type":"Point"},"properties":{"osm_id":"5483014864","tag":{"natural":"tree"}},"type":"Feature"},
	{"geometry":{"coordinates":[7.990184,13.753532],"type":"Point"},"properties":{"osm_id":"5483014865","tag":{"natural":"tree"}},"type":"Feature"},
	{"geometry":{"coordinates":[7.990306,13.753502],"type":"Point"},"properties":{"osm_id":"5483014866","tag":{"natural":"tree"}},"type":"Feature"},
	{"geometry":{"coordinates":[7.990353,13.7534],"type":"Point"},"properties":{"osm_id":"5483014867","tag":{"natural":"tree"}},"type":"Feature"},
	{"geometry":{"coordinates":[7.99034,13.753307],"type":"Point"},"properties":{"osm_id":"5483014868","tag":{"natural":"tree"}},"type":"Feature"},
	{"geometry":{"coordinates":[7.990237,13.753305],"type":"Point"},"properties":{"osm_id":"5483014869","tag":{"natural":"tree"}},"type":"Feature"},
	{"geometry":{"coordinates":[7.990104,13.753301],"type":"Point"},"properties":{"osm_id":"5483014870","tag":{"natural":"tree"}},"type":"Feature"},
	{"geometry":{"coordinates":[7.990072,13.753448],"type":"Point"},"properties":{"osm_id":"5483014871","tag":{"natural":"tree"}},"type":"Feature"},
	{"geometry":{"coordinates":[7.989981,13.753447],"type":"Point"},"properties":{"osm_id":"5483014872","tag":{"natural":"tree"}},"type":"Feature"},
	{"geometry":{"coordinates":[7.990011,13.753178],"type":"Point"},"properties":{"osm_id":"5483014873","tag":{"natural":"tree"}},"type":"Feature"},
	{"geometry":{"coordinates":[7.98993,13.753231],"type":"Point"},"properties":{"osm_id":"5483014874","tag":{"natural":"tree"}},"type":"Feature"},
	{"geometry":{"coordinates":[7.990149,13.753178],"type":"Point"},"properties":{"osm_id":"5483014875","tag":{"natural":"tree"}},"type":"Feature"},
	{"geometry":{"coordinates":[7.990114,13.753361],"type":"Point"},"properties":{"osm_id":"5483014876","tag":{"natural":"tree"}},"type":"Feature"},
	{"geometry":{"coordinates":[7.989867,13.753422],"type":"Point"},"properties":{"osm_id":"5483014877","tag":{"natural":"tree"}},"type":"Feature"},
	{"geometry":{"coordinates":[7.990914,13.765908],"type":"Point"},"properties":{"name":"Arbre neem","osm_id":"8011147641","tag":{"natural":"tree"}},"type":"Feature"},
	{"geometry":{"coordinates":[7.984938,13.761408],"type":"Point"},"properties":{"name":"Neem Arbre","osm_id":"8013060997","tag":{"natural":"tree"}},"type":"Feature"}
]
}
