{
"type": "FeatureCollection",
"features": [
	{"geometry":{"coordinates":[-85.386361,31.253081],"type":"Point"},"properties":{"name":"Long Excavation and Recycling","osm_id":"7686661033","tag":{"addr:city":"Dothan","addr:housenumber":"119","addr:postcode":"36303","addr:state":"AL","addr:street":"Ross Clark Circle","amenity":"recycling","phone":"+1-334-596-9270","recycling_type":"centre"}},"type":"Feature"},
	{"geometry":{"coordinates":[-85.359384,31.223417],"type":"Point"},"properties":{"name":"Schnitzer Scrap Metal","osm_id":"7686661055","tag":{"addr:city":"Dothan","addr:housenumber":"2101","addr:postcode":"36303","addr:state":"AL","addr:street":"Columbia Highway","amenity":"recycling","fax":"+1-334-671-3945","opening_hours":"Mo-Fr 08:00-16:00; Sa 08:00-12:00; Su closed","phone":"+1-334-671-3680","recycling:scrap_metal":"yes","recycling_type":"centre","website":"https://www.schnitzersteel.com/company_locations.aspx?View=Detail&ID=8"}},"type":"Feature"}
]
}
