{
"type": "FeatureCollection",
"features": [
	{"geometry":{"coordinates":[28.442507,-14.443805],"type":"Point"},"properties":{"name":"The Big Tree","osm_id":"6511916312","tag":{"denotation":"landmark","heritage":"yes","leaf_cycle":"semi_deciduous","leaf_type":"broadleaved","natural":"tree"}},"type":"Feature"}
]
}
