{
"type": "FeatureCollection",
"features": [
	{"geometry":{"coordinates":[22.795606,47.231961],"type":"Point"},"properties":{"name":"Parcul Central","osm_id":"4364507637","tag":{"natural":"tree"}},"type":"Feature"}
]
}
