{
"type": "FeatureCollection",
"features": [
	{"geometry":{"coordinates":[22.795605,47.23196],"type":"Point"},"properties":{"name":"Parcul Central","osm_id":"4364507637","tag":{"natural":"tree"}},"type":"Feature"},
	{"geometry":{"coordinates":[22.7944,47.227607],"type":"Point"},"properties":{"osm_id":"9154323607","tag":{"natural":"tree"}},"type":"Feature"}
]
}
