{
"type": "FeatureCollection",
"features": [
	{"geometry":{"coordinates":[0.423138,42.137831],"type":"Point"},"properties":{"name":"Carrasca","osm_id":"2497967388","tag":{"natural":"tree"}},"type":"Feature"}
]
}
