{
"type": "FeatureCollection",
"features": [
	{"geometry":{"coordinates":[-72.077442,42.117532],"type":"Point"},"properties":{"name":"Stately White Pine Grove","osm_id":"5231179924","tag":{"natural":"tree"}},"type":"Feature"}
]
}
