{
"type": "FeatureCollection",
"lastupdate": "2020-07-31T00:00:00Z",
"features": [
	{"geometry":{"coordinates":[11.603002,63.04838],"type":"Point"},"properties":{"osm_id":"5555188517","tag":{"access":"permissive","amenity":"recycling","description":"Brekka","recycling:waste":"yes","recycling_type":"container","ref:sortere":"20324"}},"type":"Feature"},
	{"geometry":{"coordinates":[11.623873,63.04492],"type":"Point"},"properties":{"osm_id":"5555188518","tag":{"access":"permissive","amenity":"recycling","description":"Langmyr\u00e5sen","recycling:waste":"yes","recycling_type":"container","ref:sortere":"20323"}},"type":"Feature"},
	{"geometry":{"coordinates":[11.653147,63.044886],"type":"Point"},"properties":{"osm_id":"5555188519","tag":{"access":"permissive","amenity":"recycling","description":"Tydal helsehus","recycling:glass_bottles":"yes","recycling:paper":"yes","recycling:waste":"yes","recycling_type":"container","ref:sortere":"20320;20322"}},"type":"Feature"},
	{"geometry":{"coordinates":[11.679411,63.040856],"type":"Point"},"properties":{"name":"Tydal gjenbrukstorg","osm_id":"5555201809","tag":{"amenity":"recycling","recycling:asbestos":"yes","recycling:batteries":"yes","recycling:boats":"yes","recycling:clothes":"yes","recycling:electrical_items":"yes","recycling:garden_waste":"yes","recycling:glass":"yes","recycling:glass_bottles":"yes","recycling:hazardous_waste":"yes","recycling:marine_waste":"yes","recycling:metal":"yes","recycling:paper":"yes","recycling:plasterboard":"yes","recycling:plastic":"yes","recycling:plastic_packaging":"yes","recycling:polystyrene_foam":"yes","recycling:rubble":"yes","recycling:tyres":"yes","recycling:waste":"yes","recycling:wood":"yes","recycling_type":"centre","ref:sortere":"5197"}},"type":"Feature"},
	{"geometry":{"coordinates":[11.679867,63.040107],"type":"Point"},"properties":{"osm_id":"6195511343","tag":{"access":"permissive","amenity":"recycling","description":"Bergg\u00e5rdsmyra","recycling:glass_bottles":"yes","recycling:organic":"yes","recycling:paper":"yes","recycling:plastic_packaging":"yes","recycling:waste":"yes","recycling_type":"container","ref:sortere":"20319"}},"type":"Feature"},
	{"geometry":{"coordinates":[11.678706,63.041338],"type":"Point"},"properties":{"osm_id":"6195511344","tag":{"amenity":"recycling","description":"Langdalsvegen","recycling_type":"container","ref:sortere":"20318"}},"type":"Feature"}
]
}
