{
"type": "FeatureCollection",
"lastupdate": "2020-07-31T00:00:00Z",
"features": [
	{"geometry":{"coordinates":[11.63768,60.893924],"type":"Point"},"properties":{"name":"Hornmoen gjenvinningsstasjon, Elverum","osm_id":"859292044","tag":{"amenity":"recycling","recycling:batteries":"yes","recycling:electrical_items":"yes","recycling:garden_waste":"yes","recycling:glass":"yes","recycling:glass_bottles":"yes","recycling:hazardous_waste":"yes","recycling:metal":"yes","recycling:paper":"yes","recycling:rubble":"yes","recycling:tyres":"yes","recycling:waste":"yes","recycling:wood":"yes","recycling_type":"centre","ref:sortere":"1173"}},"type":"Feature"},
	{"geometry":{"coordinates":[11.685512,60.88912],"type":"Point"},"properties":{"osm_id":"6195509948","tag":{"access":"permissive","amenity":"recycling","description":"Hytterestcontainer Hornmoen ved Europaveien","recycling:waste":"yes","recycling_type":"container","ref:sortere":"21800"}},"type":"Feature"}
]
}
