{
"type": "FeatureCollection",
"features": [
	{"geometry":{"coordinates":[11.656235,47.973496],"type":"Point"},"properties":{"osm_id":"392726715","tag":{"amenity":"recycling","recycling:clothes":"yes","recycling:glass_bottles":"yes","recycling:shoes":"yes","recycling_type":"container"}},"type":"Feature"},
	{"geometry":{"coordinates":[11.657888,47.969394],"type":"Point"},"properties":{"osm_id":"411856760","tag":{"amenity":"recycling","recycling:clothes":"yes","recycling:glass_bottles":"yes","recycling:shoes":"yes","recycling_type":"container"}},"type":"Feature"},
	{"geometry":{"coordinates":[11.662277,47.966758],"type":"Point"},"properties":{"name":"Wertstoffhof Sauerlach","osm_id":"755804487","tag":{"amenity":"recycling","recycling_type":"centre"}},"type":"Feature"},
	{"geometry":{"coordinates":[11.648715,47.974707],"type":"Point"},"properties":{"osm_id":"1675975163","tag":{"amenity":"recycling","operator":"Gemeinde Sauerlach","recycling:clothes":"yes","recycling:glass_bottles":"yes","recycling:shoes":"yes","recycling_type":"container"}},"type":"Feature"},
	{"geometry":{"coordinates":[11.625193,47.935488],"type":"Point"},"properties":{"osm_id":"1676763584","tag":{"amenity":"waste_basket"}},"type":"Feature"},
	{"geometry":{"coordinates":[11.637688,47.946112],"type":"Point"},"properties":{"osm_id":"6426332228","tag":{"amenity":"waste_basket","waste":"dog_excrement"}},"type":"Feature"},
	{"geometry":{"coordinates":[11.633894,47.941029],"type":"Point"},"properties":{"osm_id":"7589601392","tag":{"amenity":"waste_basket","waste":"trash"}},"type":"Feature"}
]
}
