{
"type": "FeatureCollection",
"features": [
	{"geometry":{"coordinates":[11.656236,47.973497],"type":"Point"},"properties":{"osm_id":"392726715","tag":{"amenity":"recycling","recycling:glass":"yes","recycling_type":"container"}},"type":"Feature"},
	{"geometry":{"coordinates":[11.657889,47.969394],"type":"Point"},"properties":{"osm_id":"411856760","tag":{"amenity":"recycling","recycling:glass":"yes","recycling_type":"container"}},"type":"Feature"},
	{"geometry":{"coordinates":[11.662277,47.966758],"type":"Point"},"properties":{"name":"Wertstoffhof Sauerlach","osm_id":"755804487","tag":{"amenity":"recycling","recycling_type":"centre"}},"type":"Feature"},
	{"geometry":{"coordinates":[11.648716,47.974707],"type":"Point"},"properties":{"osm_id":"1675975163","tag":{"amenity":"recycling","operator":"Gemeinde Sauerlach","recycling_type":"container"}},"type":"Feature"},
	{"geometry":{"coordinates":[11.625193,47.935488],"type":"Point"},"properties":{"osm_id":"1676763584","tag":{"amenity":"waste_basket"}},"type":"Feature"},
	{"geometry":{"coordinates":[11.637689,47.946112],"type":"Point"},"properties":{"osm_id":"6426332228","tag":{"amenity":"waste_basket","waste":"dog_excrement"}},"type":"Feature"},
	{"geometry":{"coordinates":[11.633895,47.941029],"type":"Point"},"properties":{"osm_id":"7589601392","tag":{"amenity":"waste_basket","waste":"trash"}},"type":"Feature"}
]
}
