{
"type": "FeatureCollection",
"features": [
	{"geometry":{"coordinates":[-3.356008,57.360926],"type":"Point"},"properties":{"osm_id":"7700274603","tag":{"height":"4","leaf_cycle":"deciduous","leaf_type":"broadleaved","natural":"tree"}},"type":"Feature"},
	{"geometry":{"coordinates":[-3.355268,57.36403],"type":"Point"},"properties":{"osm_id":"7900473911","tag":{"diameter_crown":"7","height":"7","leaf_cycle":"deciduous","leaf_type":"broadleaved","natural":"tree"}},"type":"Feature"},
	{"geometry":{"coordinates":[-3.35761,57.356418],"type":"Point"},"properties":{"name":"Gallow Tree (site of)","osm_id":"7902668157","tag":{"description":"as marked on 1862 Ordnance Survey 6\"map","natural":"tree"}},"type":"Feature"}
]
}
