{
"type": "FeatureCollection",
"features": [
	{"geometry":{"coordinates":[8.876075,52.323595],"type":"Point"},"properties":{"osm_id":"2209778480","tag":{"natural":"tree"}},"type":"Feature"},
	{"geometry":{"coordinates":[8.842851,52.338095],"type":"Point"},"properties":{"osm_id":"4543000319","tag":{"natural":"tree"}},"type":"Feature"},
	{"geometry":{"coordinates":[8.842959,52.338089],"type":"Point"},"properties":{"osm_id":"4543000320","tag":{"natural":"tree"}},"type":"Feature"},
	{"geometry":{"coordinates":[8.843052,52.338118],"type":"Point"},"properties":{"osm_id":"4543000321","tag":{"natural":"tree"}},"type":"Feature"},
	{"geometry":{"coordinates":[8.843172,52.338221],"type":"Point"},"properties":{"osm_id":"4543000323","tag":{"natural":"tree"}},"type":"Feature"},
	{"geometry":{"coordinates":[8.843239,52.338319],"type":"Point"},"properties":{"osm_id":"4543000324","tag":{"natural":"tree"}},"type":"Feature"},
	{"geometry":{"coordinates":[8.843342,52.338417],"type":"Point"},"properties":{"osm_id":"4543000325","tag":{"natural":"tree"}},"type":"Feature"},
	{"geometry":{"coordinates":[8.842581,52.338479],"type":"Point"},"properties":{"osm_id":"4543000326","tag":{"natural":"tree"}},"type":"Feature"},
	{"geometry":{"coordinates":[8.842438,52.338528],"type":"Point"},"properties":{"osm_id":"4543005151","tag":{"natural":"tree"}},"type":"Feature"},
	{"geometry":{"coordinates":[8.842285,52.33829],"type":"Point"},"properties":{"osm_id":"4543005152","tag":{"natural":"tree"}},"type":"Feature"},
	{"geometry":{"coordinates":[8.842092,52.338251],"type":"Point"},"properties":{"osm_id":"4543005153","tag":{"natural":"tree"}},"type":"Feature"},
	{"geometry":{"coordinates":[8.842258,52.33819],"type":"Point"},"properties":{"osm_id":"4543005154","tag":{"natural":"tree"}},"type":"Feature"},
	{"geometry":{"coordinates":[8.842387,52.338254],"type":"Point"},"properties":{"osm_id":"4543005155","tag":{"natural":"tree"}},"type":"Feature"},
	{"geometry":{"coordinates":[8.790812,52.350112],"type":"Point"},"properties":{"name":"schwarzer Pohl","osm_id":"7417896052","tag":{"denotation":"landmark","natural":"tree"}},"type":"Feature"}
]
}
