{
"type": "FeatureCollection",
"features": [
	{"geometry":{"coordinates":[8.801473,51.060048],"type":"Point"},"properties":{"osm_id":"937883665","tag":{"natural":"tree"}},"type":"Feature"},
	{"geometry":{"coordinates":[8.792779,51.057213],"type":"Point"},"properties":{"osm_id":"1269835273","tag":{"natural":"tree"}},"type":"Feature"},
	{"geometry":{"coordinates":[8.862191,51.06878],"type":"Point"},"properties":{"name":"Friedenseiche","osm_id":"2540003297","tag":{"natural":"tree"}},"type":"Feature"}
]
}
