{
"type": "FeatureCollection",
"features": [
	{"geometry":{"coordinates":[8.801473,51.060048],"type":"Point"},"properties":{"osm_id":"937883665","tag":{"natural":"tree"}},"type":"Feature"},
	{"geometry":{"coordinates":[8.792779,51.057213],"type":"Point"},"properties":{"osm_id":"1269835273","tag":{"natural":"tree"}},"type":"Feature"},
	{"geometry":{"coordinates":[8.862191,51.06878],"type":"Point"},"properties":{"name":"Friedenseiche","osm_id":"2540003297","tag":{"natural":"tree"}},"type":"Feature"},
	{"geometry":{"coordinates":[8.79981,51.015104],"type":"Point"},"properties":{"osm_id":"8394873215","tag":{"natural":"tree"}},"type":"Feature"},
	{"geometry":{"coordinates":[8.799635,51.014973],"type":"Point"},"properties":{"osm_id":"8394873216","tag":{"natural":"tree"}},"type":"Feature"},
	{"geometry":{"coordinates":[8.798699,51.014901],"type":"Point"},"properties":{"osm_id":"8394911133","tag":{"natural":"tree"}},"type":"Feature"},
	{"geometry":{"coordinates":[8.798569,51.014812],"type":"Point"},"properties":{"osm_id":"8394911134","tag":{"natural":"tree"}},"type":"Feature"},
	{"geometry":{"coordinates":[8.797087,51.039193],"type":"Point"},"properties":{"osm_id":"8397251803","tag":{"natural":"tree"}},"type":"Feature"},
	{"geometry":{"coordinates":[8.830876,51.052031],"type":"Point"},"properties":{"osm_id":"8407746175","tag":{"natural":"tree"}},"type":"Feature"},
	{"geometry":{"coordinates":[8.830808,51.052374],"type":"Point"},"properties":{"osm_id":"8407746176","tag":{"natural":"tree"}},"type":"Feature"},
	{"geometry":{"coordinates":[8.830276,51.052337],"type":"Point"},"properties":{"osm_id":"8407746177","tag":{"natural":"tree"}},"type":"Feature"}
]
}
