{
"type": "FeatureCollection",
"features": [
	{"geometry":{"coordinates":[8.828162,39.847729],"type":"Point"},"properties":{"name":"Bagolaro, Celtis australis","osm_id":"8328272834","tag":{"circumference":"320","denotation":"natural_monument","description":"AlberoMonumentale della Sardegna, riferimento legislativo Allegato A - Sezione 1 Decreto Dipartimentale N. 5450 del 19/12/2017","height":"9","natural":"tree"}},"type":"Feature"}
]
}
