{
"type": "FeatureCollection",
"lastupdate": "2020-08-01T00:00:00Z",
"features": [
	{"geometry":{"coordinates":[-72.691137,41.492714],"type":"Point"},"properties":{"name":"Middlefield & Durham Recycling Center","osm_id":"6717376078","tag":{"amenity":"recycling","recycling_type":"centre"}},"type":"Feature"}
]
}
