{
"type": "FeatureCollection",
"lastupdate": "2020-08-02T00:00:00Z",
"features": [
	{"geometry":{"coordinates":[55.414335,25.317457],"type":"Point"},"properties":{"name":"2nd Hand Depot","osm_id":"4639342792","tag":{"amenity":"recycling","name:en":"2nd Hand Depot"}},"type":"Feature"}
]
}
