{
"type": "FeatureCollection",
"features": [
	{"geometry":{"coordinates":[17.425793,48.150905],"type":"Point"},"properties":{"name":"Pachov strom","osm_id":"8923606848","tag":{"alt_name":"U Pacha","natural":"tree"}},"type":"Feature"}
]
}
