{
"type": "FeatureCollection",
"features": [
	{"geometry":{"coordinates":[12.894535,51.15893],"type":"Point"},"properties":{"osm_id":"1867554545","tag":{"amenity":"recycling","recycling:cartons":"yes","recycling:glass":"yes","recycling:glass_bottles":"yes","recycling:paper":"yes","recycling_type":"container"}},"type":"Feature"},
	{"geometry":{"coordinates":[12.881606,51.17048],"type":"Point"},"properties":{"osm_id":"2523143297","tag":{"amenity":"recycling","recycling:glass":"yes","recycling:paper":"yes"}},"type":"Feature"},
	{"geometry":{"coordinates":[12.913389,51.162016],"type":"Point"},"properties":{"name":"Wertstoffhof Leisnig","osm_id":"3144897060","tag":{"addr:city":"Leisnig","addr:country":"DE","addr:housenumber":"20","addr:postcode":"04703","addr:street":"Am Donnerberg","amenity":"recycling","contact:website":"https://www.ekm-mittelsachsen.de","opening_hours":"We,Fr 14:00-18:00; Sa 08:00-12:00","recycling:batteries":"yes","recycling:cds":"yes","recycling:clothes":"yes","recycling:computers":"yes","recycling:electrical_appliances":"yes","recycling:electrical_items":"yes","recycling:glass":"yes","recycling:paper":"yes","recycling:paper_packaging":"yes","recycling:plastic":"yes","recycling:scrap_metal":"yes","recycling_type":"centre"}},"type":"Feature"}
]
}
