{
"type": "FeatureCollection",
"lastupdate": "2020-07-31T00:00:00Z",
"features": [
	{"geometry":{"coordinates":[12.840309,48.168992],"type":"Point"},"properties":{"osm_id":"157001773","tag":{"amenity":"recycling","location":"overground","recycling:glass":"yes","recycling_type":"container"}},"type":"Feature"},
	{"geometry":{"coordinates":[12.86078,48.197289],"type":"Point"},"properties":{"osm_id":"298631970","tag":{"amenity":"recycling","recycling:glass":"yes"}},"type":"Feature"},
	{"geometry":{"coordinates":[12.835699,48.166593],"type":"Point"},"properties":{"osm_id":"6373603470","tag":{"amenity":"waste_basket"}},"type":"Feature"},
	{"geometry":{"coordinates":[12.839278,48.168782],"type":"Point"},"properties":{"osm_id":"6657281808","tag":{"amenity":"waste_basket"}},"type":"Feature"}
]
}
