{
"type": "FeatureCollection",
"features": [
	{"geometry":{"coordinates":[12.840309,48.168992],"type":"Point"},"properties":{"osm_id":"157001773","tag":{"amenity":"recycling","location":"overground","recycling:glass":"yes","recycling_type":"container"}},"type":"Feature"},
	{"geometry":{"coordinates":[12.86078,48.197289],"type":"Point"},"properties":{"osm_id":"298631970","tag":{"amenity":"recycling","recycling:glass":"yes"}},"type":"Feature"},
	{"geometry":{"coordinates":[12.835699,48.166593],"type":"Point"},"properties":{"osm_id":"6373603470","tag":{"amenity":"waste_basket"}},"type":"Feature"},
	{"geometry":{"coordinates":[12.839278,48.168782],"type":"Point"},"properties":{"osm_id":"6657281808","tag":{"amenity":"waste_basket"}},"type":"Feature"},
	{"geometry":{"coordinates":[12.836865,48.167082],"type":"Point"},"properties":{"osm_id":"8958001851","tag":{"amenity":"waste_basket"}},"type":"Feature"},
	{"geometry":{"coordinates":[12.832418,48.166817],"type":"Point"},"properties":{"osm_id":"8960502598","tag":{"amenity":"waste_basket","waste":"trash"}},"type":"Feature"},
	{"geometry":{"coordinates":[12.842359,48.17159],"type":"Point"},"properties":{"osm_id":"9023333579","tag":{"amenity":"waste_basket","waste":"trash"}},"type":"Feature"},
	{"geometry":{"coordinates":[12.840104,48.167505],"type":"Point"},"properties":{"osm_id":"9023333582","tag":{"amenity":"waste_basket","waste":"trash"}},"type":"Feature"},
	{"geometry":{"coordinates":[12.839527,48.167597],"type":"Point"},"properties":{"osm_id":"9023333585","tag":{"amenity":"waste_basket","waste":"trash"}},"type":"Feature"},
	{"geometry":{"coordinates":[12.838004,48.167792],"type":"Point"},"properties":{"osm_id":"9023333587","tag":{"amenity":"waste_basket","waste":"trash"}},"type":"Feature"},
	{"geometry":{"coordinates":[12.844505,48.167614],"type":"Point"},"properties":{"osm_id":"9023333589","tag":{"amenity":"waste_basket","waste":"dog_excrement"}},"type":"Feature"},
	{"geometry":{"coordinates":[12.843151,48.166894],"type":"Point"},"properties":{"osm_id":"9023333593","tag":{"amenity":"waste_basket","waste":"trash"}},"type":"Feature"}
]
}
