{
"type": "FeatureCollection",
"lastupdate": "2020-08-06T00:00:00Z",
"features": [
	{"geometry":{"coordinates":[12.846782,47.437849],"type":"Point"},"properties":{"osm_id":"835622096","tag":{"amenity":"waste_basket"}},"type":"Feature"},
	{"geometry":{"coordinates":[12.897706,47.406535],"type":"Point"},"properties":{"name":"Recyclinghof Maria Alm","osm_id":"4607720613","tag":{"amenity":"recycling","operator":"Gemeinde Maria Alm","recycling_type":"centre"}},"type":"Feature"},
	{"geometry":{"coordinates":[12.860638,47.424109],"type":"Point"},"properties":{"name":"Recyclinghof Saalfelden","osm_id":"4946733392","tag":{"amenity":"recycling","recycling:batteries":"yes","recycling:cans":"yes","recycling:cardboard":"yes","recycling:clothes":"yes","recycling:electrical_appliances":"yes","recycling:glass":"yes","recycling:glass_bottles":"yes","recycling:green_waste":"yes","recycling:paper":"yes","recycling:plastic":"yes","recycling:plastic_bottles":"yes","recycling:plastic_packaging":"yes","recycling:scrap_metal":"yes","recycling:shoes":"yes","recycling:small_appliances":"yes","recycling:waste":"yes","recycling_type":"centre","wheelchair":"yes"}},"type":"Feature"},
	{"geometry":{"coordinates":[12.901959,47.408907],"type":"Point"},"properties":{"osm_id":"5876978442","tag":{"amenity":"waste_basket"}},"type":"Feature"},
	{"geometry":{"coordinates":[12.875167,47.412139],"type":"Point"},"properties":{"osm_id":"6441589706","tag":{"amenity":"waste_basket"}},"type":"Feature"},
	{"geometry":{"coordinates":[12.846831,47.420991],"type":"Point"},"properties":{"osm_id":"6459156112","tag":{"amenity":"waste_basket"}},"type":"Feature"},
	{"geometry":{"coordinates":[12.843136,47.417192],"type":"Point"},"properties":{"osm_id":"6459156128","tag":{"amenity":"waste_basket"}},"type":"Feature"},
	{"geometry":{"coordinates":[12.844078,47.418987],"type":"Point"},"properties":{"osm_id":"6459156184","tag":{"amenity":"waste_basket"}},"type":"Feature"},
	{"geometry":{"coordinates":[12.844036,47.418798],"type":"Point"},"properties":{"osm_id":"6459156388","tag":{"amenity":"waste_basket"}},"type":"Feature"},
	{"geometry":{"coordinates":[12.84449,47.420935],"type":"Point"},"properties":{"osm_id":"6459156398","tag":{"amenity":"waste_basket"}},"type":"Feature"},
	{"geometry":{"coordinates":[12.846624,47.421061],"type":"Point"},"properties":{"osm_id":"6459882250","tag":{"amenity":"waste_basket"}},"type":"Feature"},
	{"geometry":{"coordinates":[12.846216,47.420707],"type":"Point"},"properties":{"osm_id":"6459882261","tag":{"amenity":"waste_basket"}},"type":"Feature"},
	{"geometry":{"coordinates":[12.848457,47.416773],"type":"Point"},"properties":{"osm_id":"6459882602","tag":{"amenity":"waste_basket"}},"type":"Feature"},
	{"geometry":{"coordinates":[12.847971,47.416745],"type":"Point"},"properties":{"osm_id":"6459882603","tag":{"amenity":"waste_basket"}},"type":"Feature"},
	{"geometry":{"coordinates":[12.846409,47.416079],"type":"Point"},"properties":{"osm_id":"6459882606","tag":{"amenity":"waste_basket"}},"type":"Feature"},
	{"geometry":{"coordinates":[12.844508,47.416605],"type":"Point"},"properties":{"osm_id":"6459882617","tag":{"amenity":"waste_basket"}},"type":"Feature"},
	{"geometry":{"coordinates":[12.843371,47.417141],"type":"Point"},"properties":{"osm_id":"6459882622","tag":{"amenity":"waste_basket"}},"type":"Feature"},
	{"geometry":{"coordinates":[12.843492,47.41704],"type":"Point"},"properties":{"osm_id":"6459882623","tag":{"amenity":"waste_basket"}},"type":"Feature"},
	{"geometry":{"coordinates":[12.84547,47.41978],"type":"Point"},"properties":{"osm_id":"6459882643","tag":{"amenity":"waste_basket"}},"type":"Feature"},
	{"geometry":{"coordinates":[12.845363,47.420375],"type":"Point"},"properties":{"osm_id":"6459882652","tag":{"amenity":"waste_basket"}},"type":"Feature"},
	{"geometry":{"coordinates":[12.849051,47.426945],"type":"Point"},"properties":{"osm_id":"6498606822","tag":{"amenity":"waste_basket"}},"type":"Feature"},
	{"geometry":{"coordinates":[12.849096,47.413138],"type":"Point"},"properties":{"osm_id":"6783333829","tag":{"amenity":"waste_basket"}},"type":"Feature"}
]
}
