{
"type": "FeatureCollection",
"features": [
	{"geometry":{"coordinates":[12.846782,47.437849],"type":"Point"},"properties":{"osm_id":"835622096","tag":{"amenity":"waste_basket"}},"type":"Feature"},
	{"geometry":{"coordinates":[12.897706,47.406535],"type":"Point"},"properties":{"name":"Recyclinghof Maria Alm","osm_id":"4607720613","tag":{"amenity":"recycling","operator":"Gemeinde Maria Alm","recycling_type":"centre"}},"type":"Feature"},
	{"geometry":{"coordinates":[12.860638,47.42411],"type":"Point"},"properties":{"name":"Recyclinghof Saalfelden","osm_id":"4946733392","tag":{"amenity":"recycling","recycling:batteries":"yes","recycling:cans":"yes","recycling:cardboard":"yes","recycling:clothes":"yes","recycling:electrical_appliances":"yes","recycling:glass":"yes","recycling:glass_bottles":"yes","recycling:green_waste":"yes","recycling:paper":"yes","recycling:plastic":"yes","recycling:plastic_bottles":"yes","recycling:plastic_packaging":"yes","recycling:scrap_metal":"yes","recycling:shoes":"yes","recycling:small_appliances":"yes","recycling:waste":"yes","recycling_type":"centre","wheelchair":"yes"}},"type":"Feature"},
	{"geometry":{"coordinates":[12.901959,47.408907],"type":"Point"},"properties":{"osm_id":"5876978442","tag":{"amenity":"waste_basket"}},"type":"Feature"},
	{"geometry":{"coordinates":[12.875167,47.41214],"type":"Point"},"properties":{"osm_id":"6441589706","tag":{"amenity":"waste_basket"}},"type":"Feature"},
	{"geometry":{"coordinates":[12.846832,47.420991],"type":"Point"},"properties":{"osm_id":"6459156112","tag":{"amenity":"waste_basket"}},"type":"Feature"},
	{"geometry":{"coordinates":[12.843137,47.417193],"type":"Point"},"properties":{"osm_id":"6459156128","tag":{"amenity":"waste_basket"}},"type":"Feature"},
	{"geometry":{"coordinates":[12.844078,47.418987],"type":"Point"},"properties":{"osm_id":"6459156184","tag":{"amenity":"waste_basket"}},"type":"Feature"},
	{"geometry":{"coordinates":[12.844036,47.418799],"type":"Point"},"properties":{"osm_id":"6459156388","tag":{"amenity":"waste_basket"}},"type":"Feature"},
	{"geometry":{"coordinates":[12.844491,47.420936],"type":"Point"},"properties":{"osm_id":"6459156398","tag":{"amenity":"waste_basket"}},"type":"Feature"},
	{"geometry":{"coordinates":[12.846625,47.421062],"type":"Point"},"properties":{"osm_id":"6459882250","tag":{"amenity":"waste_basket"}},"type":"Feature"},
	{"geometry":{"coordinates":[12.846216,47.420707],"type":"Point"},"properties":{"osm_id":"6459882261","tag":{"amenity":"waste_basket"}},"type":"Feature"},
	{"geometry":{"coordinates":[12.848457,47.416773],"type":"Point"},"properties":{"osm_id":"6459882602","tag":{"amenity":"waste_basket"}},"type":"Feature"},
	{"geometry":{"coordinates":[12.847972,47.416745],"type":"Point"},"properties":{"osm_id":"6459882603","tag":{"amenity":"waste_basket"}},"type":"Feature"},
	{"geometry":{"coordinates":[12.846409,47.41608],"type":"Point"},"properties":{"osm_id":"6459882606","tag":{"amenity":"waste_basket"}},"type":"Feature"},
	{"geometry":{"coordinates":[12.844509,47.416605],"type":"Point"},"properties":{"osm_id":"6459882617","tag":{"amenity":"waste_basket"}},"type":"Feature"},
	{"geometry":{"coordinates":[12.843372,47.417142],"type":"Point"},"properties":{"osm_id":"6459882622","tag":{"amenity":"waste_basket"}},"type":"Feature"},
	{"geometry":{"coordinates":[12.843492,47.417041],"type":"Point"},"properties":{"osm_id":"6459882623","tag":{"amenity":"waste_basket"}},"type":"Feature"},
	{"geometry":{"coordinates":[12.845471,47.419781],"type":"Point"},"properties":{"osm_id":"6459882643","tag":{"amenity":"waste_basket"}},"type":"Feature"},
	{"geometry":{"coordinates":[12.845363,47.420376],"type":"Point"},"properties":{"osm_id":"6459882652","tag":{"amenity":"waste_basket"}},"type":"Feature"},
	{"geometry":{"coordinates":[12.849052,47.426945],"type":"Point"},"properties":{"osm_id":"6498606822","tag":{"amenity":"waste_basket"}},"type":"Feature"},
	{"geometry":{"coordinates":[12.849097,47.413139],"type":"Point"},"properties":{"osm_id":"6783333829","tag":{"amenity":"waste_basket"}},"type":"Feature"}
]
}
