{
"type": "FeatureCollection",
"lastupdate": "2020-08-05T00:00:00Z",
"features": [
	{"geometry":{"coordinates":[12.878929,45.602072],"type":"Point"},"properties":{"osm_id":"2904778701","tag":{"amenity":"recycling"}},"type":"Feature"},
	{"geometry":{"coordinates":[12.88087,45.602506],"type":"Point"},"properties":{"osm_id":"2904780854","tag":{"amenity":"recycling"}},"type":"Feature"},
	{"geometry":{"coordinates":[12.883236,45.601032],"type":"Point"},"properties":{"osm_id":"2904807201","tag":{"amenity":"recycling"}},"type":"Feature"},
	{"geometry":{"coordinates":[12.885192,45.600398],"type":"Point"},"properties":{"osm_id":"2905330801","tag":{"amenity":"recycling"}},"type":"Feature"},
	{"geometry":{"coordinates":[12.918787,45.619999],"type":"Point"},"properties":{"osm_id":"3271254037","tag":{"amenity":"waste_basket"}},"type":"Feature"},
	{"geometry":{"coordinates":[12.918026,45.62255],"type":"Point"},"properties":{"osm_id":"3271254852","tag":{"amenity":"waste_basket"}},"type":"Feature"},
	{"geometry":{"coordinates":[12.876801,45.59739],"type":"Point"},"properties":{"osm_id":"3604593614","tag":{"amenity":"recycling","recycling_type":"container"}},"type":"Feature"},
	{"geometry":{"coordinates":[12.880601,45.607865],"type":"Point"},"properties":{"name":"Ecocentro","osm_id":"3861552017","tag":{"amenity":"recycling","recycling_type":"centre"}},"type":"Feature"},
	{"geometry":{"coordinates":[12.874155,45.595851],"type":"Point"},"properties":{"osm_id":"3861552034","tag":{"amenity":"recycling","recycling_type":"container"}},"type":"Feature"},
	{"geometry":{"coordinates":[12.875563,45.597566],"type":"Point"},"properties":{"osm_id":"3861552037","tag":{"amenity":"waste_basket"}},"type":"Feature"},
	{"geometry":{"coordinates":[12.875344,45.597658],"type":"Point"},"properties":{"osm_id":"3861552039","tag":{"amenity":"recycling","recycling_type":"container"}},"type":"Feature"},
	{"geometry":{"coordinates":[12.885558,45.59867],"type":"Point"},"properties":{"osm_id":"3861552042","tag":{"amenity":"recycling","recycling_type":"container"}},"type":"Feature"},
	{"geometry":{"coordinates":[12.891224,45.600229],"type":"Point"},"properties":{"osm_id":"6314164891","tag":{"amenity":"waste_basket"}},"type":"Feature"},
	{"geometry":{"coordinates":[12.889922,45.604408],"type":"Point"},"properties":{"osm_id":"6314299211","tag":{"amenity":"waste_basket"}},"type":"Feature"},
	{"geometry":{"coordinates":[12.84647,45.588626],"type":"Point"},"properties":{"osm_id":"6499583548","tag":{"amenity":"waste_basket"}},"type":"Feature"},
	{"geometry":{"coordinates":[12.850417,45.588399],"type":"Point"},"properties":{"osm_id":"6799755485","tag":{"amenity":"waste_basket","waste":"trash"}},"type":"Feature"},
	{"geometry":{"coordinates":[12.850415,45.588389],"type":"Point"},"properties":{"osm_id":"6799755486","tag":{"amenity":"recycling","recycling:glass":"yes","recycling:paper":"yes","recycling:plastic":"yes","recycling_type":"container"}},"type":"Feature"}
]
}
