{
"type": "FeatureCollection",
"features": [
	{"geometry":{"coordinates":[12.878929,45.602072],"type":"Point"},"properties":{"osm_id":"2904778701","tag":{"amenity":"recycling"}},"type":"Feature"},
	{"geometry":{"coordinates":[12.88087,45.602506],"type":"Point"},"properties":{"osm_id":"2904780854","tag":{"amenity":"recycling"}},"type":"Feature"},
	{"geometry":{"coordinates":[12.883237,45.601032],"type":"Point"},"properties":{"osm_id":"2904807201","tag":{"amenity":"recycling"}},"type":"Feature"},
	{"geometry":{"coordinates":[12.885192,45.600398],"type":"Point"},"properties":{"osm_id":"2905330801","tag":{"amenity":"recycling"}},"type":"Feature"},
	{"geometry":{"coordinates":[12.918787,45.62],"type":"Point"},"properties":{"osm_id":"3271254037","tag":{"amenity":"waste_basket"}},"type":"Feature"},
	{"geometry":{"coordinates":[12.918026,45.622551],"type":"Point"},"properties":{"osm_id":"3271254852","tag":{"amenity":"waste_basket"}},"type":"Feature"},
	{"geometry":{"coordinates":[12.876802,45.59739],"type":"Point"},"properties":{"osm_id":"3604593614","tag":{"amenity":"recycling","recycling_type":"container"}},"type":"Feature"},
	{"geometry":{"coordinates":[12.880601,45.607865],"type":"Point"},"properties":{"name":"Ecocentro","osm_id":"3861552017","tag":{"amenity":"recycling","recycling_type":"centre"}},"type":"Feature"},
	{"geometry":{"coordinates":[12.874155,45.595852],"type":"Point"},"properties":{"osm_id":"3861552034","tag":{"amenity":"recycling","recycling_type":"container"}},"type":"Feature"},
	{"geometry":{"coordinates":[12.875563,45.597567],"type":"Point"},"properties":{"osm_id":"3861552037","tag":{"amenity":"waste_basket"}},"type":"Feature"},
	{"geometry":{"coordinates":[12.875345,45.597659],"type":"Point"},"properties":{"osm_id":"3861552039","tag":{"amenity":"recycling","recycling_type":"container"}},"type":"Feature"},
	{"geometry":{"coordinates":[12.885558,45.598671],"type":"Point"},"properties":{"osm_id":"3861552042","tag":{"amenity":"recycling","recycling_type":"container"}},"type":"Feature"},
	{"geometry":{"coordinates":[12.891225,45.600229],"type":"Point"},"properties":{"osm_id":"6314164891","tag":{"amenity":"waste_basket"}},"type":"Feature"},
	{"geometry":{"coordinates":[12.889922,45.604408],"type":"Point"},"properties":{"osm_id":"6314299211","tag":{"amenity":"waste_basket"}},"type":"Feature"},
	{"geometry":{"coordinates":[12.870745,45.601007],"type":"Point"},"properties":{"osm_id":"6399445651","tag":{"amenity":"waste_disposal"}},"type":"Feature"},
	{"geometry":{"coordinates":[12.86725,45.599485],"type":"Point"},"properties":{"osm_id":"6399559307","tag":{"amenity":"waste_disposal"}},"type":"Feature"},
	{"geometry":{"coordinates":[12.869454,45.600063],"type":"Point"},"properties":{"osm_id":"6399559342","tag":{"amenity":"waste_disposal"}},"type":"Feature"},
	{"geometry":{"coordinates":[12.846471,45.588626],"type":"Point"},"properties":{"osm_id":"6499583548","tag":{"amenity":"waste_basket"}},"type":"Feature"},
	{"geometry":{"coordinates":[12.848938,45.588859],"type":"Point"},"properties":{"osm_id":"6499583590","tag":{"amenity":"waste_disposal"}},"type":"Feature"},
	{"geometry":{"coordinates":[12.849246,45.588972],"type":"Point"},"properties":{"osm_id":"6499583591","tag":{"amenity":"waste_disposal"}},"type":"Feature"},
	{"geometry":{"coordinates":[12.850778,45.589586],"type":"Point"},"properties":{"osm_id":"6499771222","tag":{"amenity":"waste_disposal"}},"type":"Feature"},
	{"geometry":{"coordinates":[12.852869,45.590314],"type":"Point"},"properties":{"osm_id":"6499973632","tag":{"amenity":"waste_disposal"}},"type":"Feature"},
	{"geometry":{"coordinates":[12.8481,45.588296],"type":"Point"},"properties":{"osm_id":"6499973944","tag":{"amenity":"waste_disposal"}},"type":"Feature"},
	{"geometry":{"coordinates":[12.847681,45.588275],"type":"Point"},"properties":{"osm_id":"6499973945","tag":{"amenity":"waste_disposal"}},"type":"Feature"},
	{"geometry":{"coordinates":[12.847301,45.586566],"type":"Point"},"properties":{"osm_id":"6501065753","tag":{"amenity":"waste_disposal"}},"type":"Feature"},
	{"geometry":{"coordinates":[12.852712,45.589037],"type":"Point"},"properties":{"osm_id":"6501233364","tag":{"amenity":"waste_disposal"}},"type":"Feature"},
	{"geometry":{"coordinates":[12.853619,45.590272],"type":"Point"},"properties":{"osm_id":"6501233365","tag":{"amenity":"waste_disposal"}},"type":"Feature"},
	{"geometry":{"coordinates":[12.850418,45.588399],"type":"Point"},"properties":{"osm_id":"6799755485","tag":{"amenity":"waste_basket","waste":"trash"}},"type":"Feature"},
	{"geometry":{"coordinates":[12.850415,45.58839],"type":"Point"},"properties":{"osm_id":"6799755486","tag":{"amenity":"recycling","recycling:glass":"yes","recycling:paper":"yes","recycling:plastic":"yes","recycling_type":"container"}},"type":"Feature"},
	{"geometry":{"coordinates":[12.841732,45.584809],"type":"Point"},"properties":{"osm_id":"7913767590","tag":{"amenity":"waste_disposal"}},"type":"Feature"}
]
}
