{
"type": "FeatureCollection",
"features": [
	{"geometry":{"coordinates":[-116.713656,33.745024],"type":"Point"},"properties":{"name":"Idyllwild Christmas Tree","osm_id":"3740881867","tag":{"leaf_cycle":"evergreen","leaf_type":"needleleaved","natural":"tree"}},"type":"Feature"},
	{"geometry":{"coordinates":[-116.713801,33.744403],"type":"Point"},"properties":{"osm_id":"3740883867","tag":{"natural":"tree"}},"type":"Feature"},
	{"geometry":{"coordinates":[-116.715574,33.7445],"type":"Point"},"properties":{"osm_id":"3740883868","tag":{"natural":"tree"}},"type":"Feature"},
	{"geometry":{"coordinates":[-116.713523,33.744767],"type":"Point"},"properties":{"osm_id":"3752211695","tag":{"natural":"tree"}},"type":"Feature"},
	{"geometry":{"coordinates":[-116.713745,33.744657],"type":"Point"},"properties":{"osm_id":"3752211696","tag":{"natural":"tree"}},"type":"Feature"},
	{"geometry":{"coordinates":[-116.713639,33.744605],"type":"Point"},"properties":{"osm_id":"3752211697","tag":{"natural":"tree"}},"type":"Feature"},
	{"geometry":{"coordinates":[-116.712952,33.745486],"type":"Point"},"properties":{"osm_id":"3752211698","tag":{"natural":"tree"}},"type":"Feature"},
	{"geometry":{"coordinates":[-116.713354,33.745221],"type":"Point"},"properties":{"osm_id":"3752211699","tag":{"natural":"tree"}},"type":"Feature"},
	{"geometry":{"coordinates":[-116.713285,33.745127],"type":"Point"},"properties":{"osm_id":"3752211700","tag":{"natural":"tree"}},"type":"Feature"}
]
}
