{
"type": "FeatureCollection",
"features": [
	{"geometry":{"coordinates":[-116.713655,33.745023],"type":"Point"},"properties":{"name":"Idyllwild Christmas Tree","osm_id":"3740881867","tag":{"leaf_cycle":"evergreen","leaf_type":"needleleaved","natural":"tree"}},"type":"Feature"},
	{"geometry":{"coordinates":[-116.7138,33.744402],"type":"Point"},"properties":{"osm_id":"3740883867","tag":{"natural":"tree"}},"type":"Feature"},
	{"geometry":{"coordinates":[-116.715573,33.744499],"type":"Point"},"properties":{"osm_id":"3740883868","tag":{"natural":"tree"}},"type":"Feature"},
	{"geometry":{"coordinates":[-116.713523,33.744766],"type":"Point"},"properties":{"osm_id":"3752211695","tag":{"natural":"tree"}},"type":"Feature"},
	{"geometry":{"coordinates":[-116.713744,33.744657],"type":"Point"},"properties":{"osm_id":"3752211696","tag":{"natural":"tree"}},"type":"Feature"},
	{"geometry":{"coordinates":[-116.713638,33.744604],"type":"Point"},"properties":{"osm_id":"3752211697","tag":{"natural":"tree"}},"type":"Feature"},
	{"geometry":{"coordinates":[-116.712951,33.745485],"type":"Point"},"properties":{"osm_id":"3752211698","tag":{"natural":"tree"}},"type":"Feature"},
	{"geometry":{"coordinates":[-116.713354,33.745221],"type":"Point"},"properties":{"osm_id":"3752211699","tag":{"natural":"tree"}},"type":"Feature"},
	{"geometry":{"coordinates":[-116.713284,33.745126],"type":"Point"},"properties":{"osm_id":"3752211700","tag":{"natural":"tree"}},"type":"Feature"}
]
}
