{
"type": "FeatureCollection",
"features": [
	{"geometry":{"coordinates":[-42.796741,-5.003312],"type":"Point"},"properties":{"name":"PRR - 36","osm_id":"8285041498","tag":{"amenity":"waste_disposal","waste":"rubble"}},"type":"Feature"}
]
}
