{
"type": "FeatureCollection",
"features": [
	{"geometry":{"coordinates":[-42.789813,-5.056291],"type":"Point"},"properties":{"osm_id":"7272027874","tag":{"amenity":"waste_basket"}},"type":"Feature"},
	{"geometry":{"coordinates":[-42.78994,-5.056135],"type":"Point"},"properties":{"osm_id":"7272029698","tag":{"amenity":"waste_basket"}},"type":"Feature"},
	{"geometry":{"coordinates":[-42.789743,-5.05569],"type":"Point"},"properties":{"osm_id":"7272050924","tag":{"amenity":"waste_basket"}},"type":"Feature"},
	{"geometry":{"coordinates":[-42.790639,-5.056548],"type":"Point"},"properties":{"osm_id":"7272526668","tag":{"amenity":"waste_basket"}},"type":"Feature"},
	{"geometry":{"coordinates":[-42.791553,-5.056971],"type":"Point"},"properties":{"osm_id":"7272551635","tag":{"amenity":"waste_basket"}},"type":"Feature"},
	{"geometry":{"coordinates":[-42.791926,-5.071609],"type":"Point"},"properties":{"osm_id":"8259815074","tag":{"amenity":"recycling","recycling:glass":"yes","recycling:glass_bottles":"yes","recycling:paper":"yes","recycling_type":"container"}},"type":"Feature"},
	{"geometry":{"coordinates":[-42.761341,-5.071821],"type":"Point"},"properties":{"osm_id":"8259815075","tag":{"amenity":"recycling","recycling_type":"container"}},"type":"Feature"},
	{"geometry":{"coordinates":[-42.801499,-5.069809],"type":"Point"},"properties":{"osm_id":"8259815076","tag":{"amenity":"recycling","recycling_type":"container"}},"type":"Feature"},
	{"geometry":{"coordinates":[-42.799937,-5.076899],"type":"Point"},"properties":{"osm_id":"8259827123","tag":{"amenity":"recycling","recycling_type":"container"}},"type":"Feature"},
	{"geometry":{"coordinates":[-42.799348,-5.082725],"type":"Point"},"properties":{"osm_id":"8259827124","tag":{"amenity":"recycling","recycling_type":"container"}},"type":"Feature"},
	{"geometry":{"coordinates":[-42.777631,-5.09053],"type":"Point"},"properties":{"name":"PRR - 07","osm_id":"8285041443","tag":{"amenity":"waste_disposal","waste":"rubble"}},"type":"Feature"},
	{"geometry":{"coordinates":[-42.796115,-5.075576],"type":"Point"},"properties":{"name":"PRR - 08-","osm_id":"8285041444","tag":{"amenity":"waste_disposal","waste":"rubble"}},"type":"Feature"},
	{"geometry":{"coordinates":[-42.7892,-5.054444],"type":"Point"},"properties":{"name":"PPR - 09","osm_id":"8285041445","tag":{"amenity":"waste_disposal","waste":"rubble"}},"type":"Feature"},
	{"geometry":{"coordinates":[-42.757956,-5.061338],"type":"Point"},"properties":{"name":"PRR - 10","osm_id":"8285041446","tag":{"amenity":"waste_disposal","waste":"rubble"}},"type":"Feature"},
	{"geometry":{"coordinates":[-42.747266,-5.050598],"type":"Point"},"properties":{"name":"PRR - 11","osm_id":"8285041448","tag":{"amenity":"waste_disposal","waste":"rubble"}},"type":"Feature"},
	{"geometry":{"coordinates":[-42.781075,-5.014817],"type":"Point"},"properties":{"name":"PRR - 23","osm_id":"8285041485","tag":{"amenity":"waste_disposal","waste":"rubble"}},"type":"Feature"},
	{"geometry":{"coordinates":[-42.772909,-5.058345],"type":"Point"},"properties":{"name":"PRR - 24","osm_id":"8285041486","tag":{"amenity":"waste_disposal","waste":"rubble"}},"type":"Feature"},
	{"geometry":{"coordinates":[-42.735992,-5.057718],"type":"Point"},"properties":{"name":"PRR - 25","osm_id":"8285041487","tag":{"amenity":"waste_disposal","waste":"rubble"}},"type":"Feature"},
	{"geometry":{"coordinates":[-42.759704,-5.076137],"type":"Point"},"properties":{"name":"PRR - 26","osm_id":"8285041488","tag":{"amenity":"waste_disposal","waste":"rubble"}},"type":"Feature"},
	{"geometry":{"coordinates":[-42.765119,-5.090276],"type":"Point"},"properties":{"name":"PRR - 27","osm_id":"8285041489","tag":{"amenity":"waste_disposal","waste":"rubble"}},"type":"Feature"},
	{"geometry":{"coordinates":[-42.74154,-5.083309],"type":"Point"},"properties":{"name":"PRR - 34","osm_id":"8285041496","tag":{"amenity":"waste_disposal","waste":"rubble"}},"type":"Feature"},
	{"geometry":{"coordinates":[-42.768512,-5.087851],"type":"Point"},"properties":{"name":"PRR - 40","osm_id":"8285041502","tag":{"amenity":"waste_disposal","waste":"rubble"}},"type":"Feature"},
	{"geometry":{"coordinates":[-42.765466,-5.060075],"type":"Point"},"properties":{"name":"PRR - 41","osm_id":"8285041503","tag":{"amenity":"waste_disposal","waste":"rubble"}},"type":"Feature"},
	{"geometry":{"coordinates":[-42.733756,-5.089212],"type":"Point"},"properties":{"name":"PRR - 47","osm_id":"8285041509","tag":{"amenity":"waste_disposal","waste":"rubble"}},"type":"Feature"},
	{"geometry":{"coordinates":[-42.760905,-5.072087],"type":"Point"},"properties":{"osm_id":"8339234241","tag":{"amenity":"recycling","recycling_type":"container"}},"type":"Feature"}
]
}
