{
"type": "FeatureCollection",
"features": [
	{"geometry":{"coordinates":[7.378083,52.228184],"type":"Point"},"properties":{"osm_id":"669764720","tag":{"amenity":"recycling","location":"overground","recycling:glass":"yes","recycling_type":"container"}},"type":"Feature"},
	{"geometry":{"coordinates":[7.351801,52.224601],"type":"Point"},"properties":{"osm_id":"7589666742","tag":{"amenity":"waste_basket","waste":"trash"}},"type":"Feature"},
	{"geometry":{"coordinates":[7.373959,52.216823],"type":"Point"},"properties":{"osm_id":"7589666796","tag":{"amenity":"waste_basket","waste":"trash"}},"type":"Feature"},
	{"geometry":{"coordinates":[7.355387,52.258271],"type":"Point"},"properties":{"osm_id":"8653268453","tag":{"amenity":"waste_basket"}},"type":"Feature"}
]
}
