{
"type": "FeatureCollection",
"features": [
	{"geometry":{"coordinates":[7.319253,50.524738],"type":"Point"},"properties":{"osm_id":"624188440","tag":{"amenity":"recycling","recycling:clothes":"yes","recycling:glass":"yes"}},"type":"Feature"},
	{"geometry":{"coordinates":[7.312015,50.517749],"type":"Point"},"properties":{"osm_id":"660375824","tag":{"amenity":"recycling","location":"overground","recycling:glass":"yes","recycling:glass_bottles":"yes","recycling_type":"container"}},"type":"Feature"},
	{"geometry":{"coordinates":[7.310562,50.514578],"type":"Point"},"properties":{"osm_id":"939474448","tag":{"amenity":"recycling","location":"overground","recycling:glass":"yes","recycling:glass_bottles":"yes","recycling_type":"container"}},"type":"Feature"},
	{"geometry":{"coordinates":[7.36497,50.545174],"type":"Point"},"properties":{"osm_id":"2642823505","tag":{"amenity":"recycling"}},"type":"Feature"},
	{"geometry":{"coordinates":[7.304443,50.520751],"type":"Point"},"properties":{"osm_id":"3598660844","tag":{"amenity":"recycling","layer":"0","recycling:clothes":"yes"}},"type":"Feature"},
	{"geometry":{"coordinates":[7.368051,50.567829],"type":"Point"},"properties":{"osm_id":"4868031922","tag":{"amenity":"recycling","recycling:glass":"yes","recycling_type":"container"}},"type":"Feature"},
	{"geometry":{"coordinates":[7.297495,50.556428],"type":"Point"},"properties":{"osm_id":"4971927586","tag":{"amenity":"recycling","recycling":"glass","recycling:clothes":"yes","recycling:glass":"no","recycling:glass_bottles":"yes","recycling_type":"container"}},"type":"Feature"},
	{"geometry":{"coordinates":[7.307335,50.515241],"type":"Point"},"properties":{"osm_id":"6687428731","tag":{"amenity":"waste_basket"}},"type":"Feature"},
	{"geometry":{"coordinates":[7.34794,50.559938],"type":"Point"},"properties":{"osm_id":"8364197492","tag":{"amenity":"recycling","recycling:glass_bottles":"yes"}},"type":"Feature"},
	{"geometry":{"coordinates":[7.347934,50.559912],"type":"Point"},"properties":{"osm_id":"8364197493","tag":{"amenity":"recycling","recycling:clothes":"yes","recycling:shoes":"yes","recycling_type":"container"}},"type":"Feature"}
]
}
