{
"type": "FeatureCollection",
"features": [
	{"geometry":{"coordinates":[-4.756499,54.086372],"type":"Point"},"properties":{"osm_id":"414899375","tag":{"amenity":"recycling"}},"type":"Feature"},
	{"geometry":{"coordinates":[-4.755991,54.086703],"type":"Point"},"properties":{"name":"Hospice Shop","osm_id":"1666047899","tag":{"amenity":"recycling","recycling:batteries":"no","recycling:books":"yes","recycling:clothes":"yes","recycling:electrical_appliances":"yes","recycling:furniture":"yes","recycling:glass":"yes","recycling:magazines":"yes","recycling:small_appliances":"yes","recycling_type":"centre"}},"type":"Feature"},
	{"geometry":{"coordinates":[-4.75941,54.085333],"type":"Point"},"properties":{"osm_id":"8355908521","tag":{"amenity":"waste_basket"}},"type":"Feature"},
	{"geometry":{"coordinates":[-4.759311,54.085664],"type":"Point"},"properties":{"osm_id":"8355908545","tag":{"amenity":"waste_basket"}},"type":"Feature"},
	{"geometry":{"coordinates":[-4.759278,54.085768],"type":"Point"},"properties":{"osm_id":"8355908546","tag":{"amenity":"waste_basket"}},"type":"Feature"},
	{"geometry":{"coordinates":[-4.759182,54.086055],"type":"Point"},"properties":{"osm_id":"8355908552","tag":{"amenity":"waste_basket"}},"type":"Feature"}
]
}
