{
"type": "FeatureCollection",
"features": [
	{"geometry":{"coordinates":[-4.7565,54.086372],"type":"Point"},"properties":{"osm_id":"414899375","tag":{"amenity":"recycling"}},"type":"Feature"},
	{"geometry":{"coordinates":[-4.755992,54.086703],"type":"Point"},"properties":{"name":"Hospice Shop","osm_id":"1666047899","tag":{"amenity":"recycling","recycling:batteries":"no","recycling:books":"yes","recycling:clothes":"yes","recycling:electrical_appliances":"yes","recycling:furniture":"yes","recycling:glass":"yes","recycling:magazines":"yes","recycling:small_appliances":"yes","recycling_type":"centre"}},"type":"Feature"}
]
}
