{
"type": "FeatureCollection",
"name": "points",
"crs": { "type": "name", "properties": { "name": "urn:ogc:def:crs:OGC:1.3:CRS84" } },
"features": [
{ "type": "Feature", "properties": { "osm_id": "1339118253", "other_tags": "\"natural\"=>\"tree\"" }, "geometry": { "type": "Point", "coordinates": [ -2.4511529, 52.6363968 ] } },
{ "type": "Feature", "properties": { "osm_id": "1340586607", "other_tags": "\"natural\"=>\"tree\"" }, "geometry": { "type": "Point", "coordinates": [ -2.4830468, 52.6277445 ] } },
{ "type": "Feature", "properties": { "osm_id": "1340661792", "other_tags": "\"natural\"=>\"tree\"" }, "geometry": { "type": "Point", "coordinates": [ -2.4555619, 52.6389905 ] } },
{ "type": "Feature", "properties": { "osm_id": "1367917637", "other_tags": "\"natural\"=>\"tree\"" }, "geometry": { "type": "Point", "coordinates": [ -2.4439109, 52.6373901 ] } },
{ "type": "Feature", "properties": { "osm_id": "1367917641", "other_tags": "\"natural\"=>\"tree\"" }, "geometry": { "type": "Point", "coordinates": [ -2.4437432, 52.6373095 ] } },
{ "type": "Feature", "properties": { "osm_id": "3203167505", "name": "Memorial Tree", "other_tags": "\"natural\"=>\"tree\"" }, "geometry": { "type": "Point", "coordinates": [ -2.4540122, 52.6195201 ] } },
{ "type": "Feature", "properties": { "osm_id": "5245784515", "other_tags": "\"natural\"=>\"tree\"" }, "geometry": { "type": "Point", "coordinates": [ -2.3872324, 52.7486193 ] } },
{ "type": "Feature", "properties": { "osm_id": "6400465084", "other_tags": "\"natural\"=>\"tree\"" }, "geometry": { "type": "Point", "coordinates": [ -2.6020004, 52.7479568 ] } },
{ "type": "Feature", "properties": { "osm_id": "6400465385", "other_tags": "\"natural\"=>\"tree\"" }, "geometry": { "type": "Point", "coordinates": [ -2.6093598, 52.7463364 ] } },
{ "type": "Feature", "properties": { "osm_id": "6400465386", "other_tags": "\"natural\"=>\"tree\"" }, "geometry": { "type": "Point", "coordinates": [ -2.6075655, 52.7456059 ] } },
{ "type": "Feature", "properties": { "osm_id": "6400465416", "other_tags": "\"natural\"=>\"tree\"" }, "geometry": { "type": "Point", "coordinates": [ -2.6015036, 52.7484331 ] } },
{ "type": "Feature", "properties": { "osm_id": "6400465417", "other_tags": "\"natural\"=>\"tree\"" }, "geometry": { "type": "Point", "coordinates": [ -2.6013695, 52.7494397 ] } },
{ "type": "Feature", "properties": { "osm_id": "7399370325", "other_tags": "\"natural\"=>\"tree\"" }, "geometry": { "type": "Point", "coordinates": [ -2.3799814, 52.7404226 ] } },
{ "type": "Feature", "properties": { "osm_id": "7399370326", "other_tags": "\"natural\"=>\"tree\"" }, "geometry": { "type": "Point", "coordinates": [ -2.3808346, 52.7396271 ] } }
]
}
