{
"type": "FeatureCollection",
"name": "points",
"crs": { "type": "name", "properties": { "name": "urn:ogc:def:crs:OGC:1.3:CRS84" } },
"features": [
{ "type": "Feature", "properties": { "osm_id": "1147434771", "other_tags": "\"natural\"=>\"tree\"" }, "geometry": { "type": "Point", "coordinates": [ -2.2296074, 52.1879492 ] } },
{ "type": "Feature", "properties": { "osm_id": "1147435075", "other_tags": "\"natural\"=>\"tree\"" }, "geometry": { "type": "Point", "coordinates": [ -2.2296026, 52.1880317 ] } },
{ "type": "Feature", "properties": { "osm_id": "1313522050", "name": "Babnardo Centenary", "other_tags": "\"natural\"=>\"tree\"" }, "geometry": { "type": "Point", "coordinates": [ -2.2301443, 52.1893456 ] } },
{ "type": "Feature", "properties": { "osm_id": "2338067708", "other_tags": "\"natural\"=>\"tree\"" }, "geometry": { "type": "Point", "coordinates": [ -2.2211613, 52.1884498 ] } },
{ "type": "Feature", "properties": { "osm_id": "2361965522", "other_tags": "\"natural\"=>\"tree\"" }, "geometry": { "type": "Point", "coordinates": [ -2.2292697, 52.2073634 ] } },
{ "type": "Feature", "properties": { "osm_id": "2361967537", "name": "Sweet Gum tree", "other_tags": "\"natural\"=>\"tree\"" }, "geometry": { "type": "Point", "coordinates": [ -2.2288728, 52.2072714 ] } },
{ "type": "Feature", "properties": { "osm_id": "2723971884", "other_tags": "\"natural\"=>\"tree\"" }, "geometry": { "type": "Point", "coordinates": [ -2.2224601, 52.1867803 ] } },
{ "type": "Feature", "properties": { "osm_id": "2723971887", "other_tags": "\"natural\"=>\"tree\"" }, "geometry": { "type": "Point", "coordinates": [ -2.2224782, 52.1869341 ] } },
{ "type": "Feature", "properties": { "osm_id": "2723971892", "other_tags": "\"natural\"=>\"tree\"" }, "geometry": { "type": "Point", "coordinates": [ -2.2224782, 52.1870202 ] } },
{ "type": "Feature", "properties": { "osm_id": "2723971898", "other_tags": "\"natural\"=>\"tree\"" }, "geometry": { "type": "Point", "coordinates": [ -2.2224767, 52.1870953 ] } },
{ "type": "Feature", "properties": { "osm_id": "2723971915", "other_tags": "\"natural\"=>\"tree\"" }, "geometry": { "type": "Point", "coordinates": [ -2.2224722, 52.1871907 ] } },
{ "type": "Feature", "properties": { "osm_id": "2723971921", "other_tags": "\"natural\"=>\"tree\"" }, "geometry": { "type": "Point", "coordinates": [ -2.2224691, 52.1872657 ] } },
{ "type": "Feature", "properties": { "osm_id": "2723971943", "other_tags": "\"natural\"=>\"tree\"" }, "geometry": { "type": "Point", "coordinates": [ -2.2224601, 52.187413 ] } },
{ "type": "Feature", "properties": { "osm_id": "2723971955", "other_tags": "\"natural\"=>\"tree\"" }, "geometry": { "type": "Point", "coordinates": [ -2.222451, 52.1875213 ] } },
{ "type": "Feature", "properties": { "osm_id": "2723971964", "other_tags": "\"natural\"=>\"tree\"" }, "geometry": { "type": "Point", "coordinates": [ -2.222448, 52.1876723 ] } },
{ "type": "Feature", "properties": { "osm_id": "2769075872", "other_tags": "\"natural\"=>\"tree\"" }, "geometry": { "type": "Point", "coordinates": [ -2.2182241, 52.1930931 ] } },
{ "type": "Feature", "properties": { "osm_id": "3964179913", "other_tags": "\"natural\"=>\"tree\"" }, "geometry": { "type": "Point", "coordinates": [ -2.232444, 52.2144454 ] } },
{ "type": "Feature", "properties": { "osm_id": "3964179939", "other_tags": "\"natural\"=>\"tree\"" }, "geometry": { "type": "Point", "coordinates": [ -2.2323957, 52.214332 ] } },
{ "type": "Feature", "properties": { "osm_id": "3964179946", "other_tags": "\"natural\"=>\"tree\"" }, "geometry": { "type": "Point", "coordinates": [ -2.2324976, 52.2147445 ] } },
{ "type": "Feature", "properties": { "osm_id": "3964181358", "other_tags": "\"natural\"=>\"tree\"" }, "geometry": { "type": "Point", "coordinates": [ -2.2324842, 52.214544 ] } }
]
}
