{
"type": "FeatureCollection",
"name": "points",
"crs": { "type": "name", "properties": { "name": "urn:ogc:def:crs:OGC:1.3:CRS84" } },
"features": [
{ "type": "Feature", "properties": { "osm_id": "6499653304", "other_tags": "\"natural\"=>\"tree\"" }, "geometry": { "type": "Point", "coordinates": [ -4.8154796, 55.9587293 ] } },
{ "type": "Feature", "properties": { "osm_id": "6499653305", "other_tags": "\"natural\"=>\"tree\"" }, "geometry": { "type": "Point", "coordinates": [ -4.8159114, 55.9586076 ] } },
{ "type": "Feature", "properties": { "osm_id": "6499653306", "other_tags": "\"natural\"=>\"tree\"" }, "geometry": { "type": "Point", "coordinates": [ -4.8156647, 55.9585881 ] } },
{ "type": "Feature", "properties": { "osm_id": "6499653307", "other_tags": "\"natural\"=>\"tree\"" }, "geometry": { "type": "Point", "coordinates": [ -4.8158551, 55.9585341 ] } },
{ "type": "Feature", "properties": { "osm_id": "6499653308", "other_tags": "\"natural\"=>\"tree\"" }, "geometry": { "type": "Point", "coordinates": [ -4.8154229, 55.9586555 ] } },
{ "type": "Feature", "properties": { "osm_id": "6499653309", "other_tags": "\"natural\"=>\"tree\"" }, "geometry": { "type": "Point", "coordinates": [ -4.8156486, 55.9586843 ] } },
{ "type": "Feature", "properties": { "osm_id": "6500583898", "other_tags": "\"natural\"=>\"tree\"" }, "geometry": { "type": "Point", "coordinates": [ -4.8157365, 55.9570849 ] } },
{ "type": "Feature", "properties": { "osm_id": "6500583923", "other_tags": "\"natural\"=>\"tree\"" }, "geometry": { "type": "Point", "coordinates": [ -4.8159363, 55.9569573 ] } }
]
}
