{
"type": "FeatureCollection",
"features": [
	{"geometry":{"coordinates":[-8.035958,38.292184],"type":"Point"},"properties":{"osm_id":"3840005363","tag":{"height":"2","leaf_cycle":"mixed","leaf_type":"broadleaved","natural":"tree"}},"type":"Feature"},
	{"geometry":{"coordinates":[-8.035841,38.292349],"type":"Point"},"properties":{"osm_id":"3840005364","tag":{"height":"2","leaf_cycle":"mixed","leaf_type":"broadleaved","natural":"tree"}},"type":"Feature"},
	{"geometry":{"coordinates":[-8.03578,38.292423],"type":"Point"},"properties":{"osm_id":"3840005365","tag":{"height":"2","leaf_cycle":"mixed","leaf_type":"broadleaved","natural":"tree"}},"type":"Feature"},
	{"geometry":{"coordinates":[-8.035667,38.292907],"type":"Point"},"properties":{"osm_id":"3840014688","tag":{"height":"1","name:botanical":"Oliveira","natural":"tree"}},"type":"Feature"},
	{"geometry":{"coordinates":[-8.036763,38.288209],"type":"Point"},"properties":{"osm_id":"3859804763","tag":{"height":"3","leaf_cycle":"evergreen","leaf_type":"broadleaved","natural":"tree"}},"type":"Feature"},
	{"geometry":{"coordinates":[-8.036793,38.288211],"type":"Point"},"properties":{"osm_id":"3859804764","tag":{"height":"3","leaf_cycle":"evergreen","leaf_type":"broadleaved","natural":"tree"}},"type":"Feature"},
	{"geometry":{"coordinates":[-8.036821,38.288211],"type":"Point"},"properties":{"osm_id":"3859804765","tag":{"height":"3","leaf_cycle":"evergreen","leaf_type":"broadleaved","natural":"tree"}},"type":"Feature"},
	{"geometry":{"coordinates":[-8.036756,38.28826],"type":"Point"},"properties":{"osm_id":"3859804766","tag":{"height":"3","leaf_cycle":"evergreen","leaf_type":"broadleaved","natural":"tree"}},"type":"Feature"},
	{"geometry":{"coordinates":[-8.036813,38.288262],"type":"Point"},"properties":{"osm_id":"3859804767","tag":{"height":"3","leaf_cycle":"evergreen","leaf_type":"broadleaved","natural":"tree"}},"type":"Feature"},
	{"geometry":{"coordinates":[-8.036748,38.288306],"type":"Point"},"properties":{"osm_id":"3859804768","tag":{"height":"3","leaf_cycle":"evergreen","leaf_type":"broadleaved","natural":"tree"}},"type":"Feature"},
	{"geometry":{"coordinates":[-8.036775,38.288307],"type":"Point"},"properties":{"osm_id":"3859804769","tag":{"height":"3","leaf_cycle":"evergreen","leaf_type":"broadleaved","natural":"tree"}},"type":"Feature"},
	{"geometry":{"coordinates":[-8.036809,38.288308],"type":"Point"},"properties":{"osm_id":"3859804770","tag":{"height":"3","leaf_cycle":"evergreen","leaf_type":"broadleaved","natural":"tree"}},"type":"Feature"},
	{"geometry":{"coordinates":[-8.034428,38.287496],"type":"Point"},"properties":{"osm_id":"3908800680","tag":{"height":"4","leaf_type":"broadleaved","natural":"tree"}},"type":"Feature"},
	{"geometry":{"coordinates":[-8.037474,38.28883],"type":"Point"},"properties":{"osm_id":"4608506820","tag":{"leaf_type":"broadleaved","natural":"tree"}},"type":"Feature"}
]
}
