{
"type": "FeatureCollection",
"features": [
	{"geometry":{"coordinates":[-8.035958,38.292183],"type":"Point"},"properties":{"osm_id":"3840005363","tag":{"height":"2","leaf_cycle":"mixed","leaf_type":"broadleaved","natural":"tree"}},"type":"Feature"},
	{"geometry":{"coordinates":[-8.035841,38.292349],"type":"Point"},"properties":{"osm_id":"3840005364","tag":{"height":"2","leaf_cycle":"mixed","leaf_type":"broadleaved","natural":"tree"}},"type":"Feature"},
	{"geometry":{"coordinates":[-8.03578,38.292422],"type":"Point"},"properties":{"osm_id":"3840005365","tag":{"height":"2","leaf_cycle":"mixed","leaf_type":"broadleaved","natural":"tree"}},"type":"Feature"},
	{"geometry":{"coordinates":[-8.035666,38.292906],"type":"Point"},"properties":{"osm_id":"3840014688","tag":{"height":"1","name:botanical":"Oliveira","natural":"tree"}},"type":"Feature"},
	{"geometry":{"coordinates":[-8.036762,38.288209],"type":"Point"},"properties":{"osm_id":"3859804763","tag":{"height":"3","leaf_cycle":"evergreen","leaf_type":"broadleaved","natural":"tree"}},"type":"Feature"},
	{"geometry":{"coordinates":[-8.036793,38.28821],"type":"Point"},"properties":{"osm_id":"3859804764","tag":{"height":"3","leaf_cycle":"evergreen","leaf_type":"broadleaved","natural":"tree"}},"type":"Feature"},
	{"geometry":{"coordinates":[-8.03682,38.28821],"type":"Point"},"properties":{"osm_id":"3859804765","tag":{"height":"3","leaf_cycle":"evergreen","leaf_type":"broadleaved","natural":"tree"}},"type":"Feature"},
	{"geometry":{"coordinates":[-8.036756,38.288259],"type":"Point"},"properties":{"osm_id":"3859804766","tag":{"height":"3","leaf_cycle":"evergreen","leaf_type":"broadleaved","natural":"tree"}},"type":"Feature"},
	{"geometry":{"coordinates":[-8.036813,38.288261],"type":"Point"},"properties":{"osm_id":"3859804767","tag":{"height":"3","leaf_cycle":"evergreen","leaf_type":"broadleaved","natural":"tree"}},"type":"Feature"},
	{"geometry":{"coordinates":[-8.036747,38.288305],"type":"Point"},"properties":{"osm_id":"3859804768","tag":{"height":"3","leaf_cycle":"evergreen","leaf_type":"broadleaved","natural":"tree"}},"type":"Feature"},
	{"geometry":{"coordinates":[-8.036774,38.288307],"type":"Point"},"properties":{"osm_id":"3859804769","tag":{"height":"3","leaf_cycle":"evergreen","leaf_type":"broadleaved","natural":"tree"}},"type":"Feature"},
	{"geometry":{"coordinates":[-8.036808,38.288308],"type":"Point"},"properties":{"osm_id":"3859804770","tag":{"height":"3","leaf_cycle":"evergreen","leaf_type":"broadleaved","natural":"tree"}},"type":"Feature"},
	{"geometry":{"coordinates":[-8.034428,38.287495],"type":"Point"},"properties":{"osm_id":"3908800680","tag":{"height":"4","leaf_type":"broadleaved","natural":"tree"}},"type":"Feature"},
	{"geometry":{"coordinates":[-8.037473,38.28883],"type":"Point"},"properties":{"osm_id":"4608506820","tag":{"leaf_type":"broadleaved","natural":"tree"}},"type":"Feature"}
]
}
