{
"type": "FeatureCollection",
"lastupdate": "2020-08-05T00:00:00Z",
"features": [
	{"geometry":{"coordinates":[20.741689,47.9722],"type":"Point"},"properties":{"osm_id":"3437755217","tag":{"addr:street":"Hars\u00e1ny R\u00e1k\u00f3czi Ferenc utca","amenity":"recycling","source:date":"2012-05-18","url":"http://turistautak.hu/poi.php?id=57227"}},"type":"Feature"}
]
}
