{
"type": "FeatureCollection",
"features": [
	{"geometry":{"coordinates":[97.656196,3.690954],"type":"Point"},"properties":{"name":"Remarquable tree","osm_id":"5985155630","tag":{"natural":"tree"}},"type":"Feature"}
]
}
