{
"type": "FeatureCollection",
"lastupdate": "2020-08-06T00:00:00Z",
"features": [
	{"geometry":{"coordinates":[-76.327764,40.056207],"type":"Point"},"properties":{"name":"Lancaster County Solid Waste","osm_id":"4753113822","tag":{"amenity":"recycling","phone":"+1 (717) 397-9968","recycling_type":"centre","website":"https://www.lcswma.org/"}},"type":"Feature"}
]
}
